{
  "type": "Feature",
  "properties": {
    "gn:admin1_code":"WR",
    "gn:admin2_code":"8",
    "gn:admin3_code":"49",
    "gn:admin4_code":"490027",
    "gn:asciiname":"Gonaha",
    "gn:country_code":"NP",
    "gn:dem":104,
    "gn:feature_class":"P",
    "gn:feature_code":"PPLL",
    "gn:name":"Gonaha",
    "gn:population":0,
    "gn:timezone":"Asia/Kathmandu",
    "iso:country":"NP",
    "name:ceb_x_preferred":[
        "Gonaha"
    ],
    "name:fra_x_preferred":[
        "Gonaha"
    ],
    "name:msa_x_preferred":[
        "Gonaha"
    ],
    "name:nep_x_preferred":[
        "\u0917\u094b\u0928\u093e\u0939\u093e"
    ],
    "name:new_x_preferred":[
        "\u0917\u094b\u0928\u093e\u0939\u093e"
    ],
    "name:pol_x_preferred":[
        "Gonaha"
    ],
    "wof:name":"Gonaha",
    "wof:placetype":"locality"
},
  "geometry": {"coordinates":[83.37419,27.47752],"type":"Point"}
}