{
  "type": "Feature",
  "properties": {
    "gn:admin1_code":"CR",
    "gn:admin2_code":"1",
    "gn:admin3_code":"30.0",
    "gn:admin4_code":"300011.0",
    "gn:asciiname":"Ysrbang",
    "gn:country_code":"NP",
    "gn:dem":1003,
    "gn:feature_class":"P",
    "gn:feature_code":"PPLL",
    "gn:name":"Ysrbang",
    "gn:population":0,
    "gn:timezone":"Asia/Kathmandu",
    "iso:country":"NP",
    "wof:name":"Ysrbang",
    "wof:placetype":"locality"
},
  "geometry": {"coordinates":[84.72891,27.73757],"type":"Point"}
}