{
  "type": "Feature",
  "properties": {
    "gn:admin1_code":"FR",
    "gn:admin2_code":"9",
    "gn:admin3_code":"74",
    "gn:admin4_code":"740054",
    "gn:asciiname":"Anarikholi Goth",
    "gn:country_code":"NP",
    "gn:dem":1084,
    "gn:feature_class":"P",
    "gn:feature_code":"PPLL",
    "gn:name":"Anarikholi Goth",
    "gn:population":0,
    "gn:timezone":"Asia/Kathmandu",
    "iso:country":"NP",
    "wof:name":"Anarikholi Goth",
    "wof:placetype":"locality"
},
  "geometry": {"coordinates":[80.89910999999999,29.44024000000001],"type":"Point"}
}