{
  "type": "Feature",
  "properties": {
    "gn:admin1_code":"FR",
    "gn:admin2_code":"9",
    "gn:admin3_code":"73.0",
    "gn:admin4_code":"730003.0",
    "gn:asciiname":"Serakhuti",
    "gn:country_code":"NP",
    "gn:dem":1664,
    "gn:feature_class":"P",
    "gn:feature_code":"PPLL",
    "gn:name":"Serakhuti",
    "gn:population":0,
    "gn:timezone":"Asia/Kathmandu",
    "iso:country":"NP",
    "wof:name":"Serakhuti",
    "wof:placetype":"locality"
},
  "geometry": {"coordinates":[80.6096,29.28219],"type":"Point"}
}