{
  "type": "Feature",
  "properties": {
    "gn:admin1_code":"CR",
    "gn:admin2_code":"1",
    "gn:admin3_code":"24.0",
    "gn:admin4_code":"240014.0",
    "gn:asciiname":"Haldebesi",
    "gn:country_code":"NP",
    "gn:dem":694,
    "gn:feature_class":"P",
    "gn:feature_code":"PPLL",
    "gn:name":"Haldebesi",
    "gn:population":0,
    "gn:timezone":"Asia/Kathmandu",
    "iso:country":"NP",
    "wof:name":"Haldebesi",
    "wof:placetype":"locality"
},
  "geometry": {"coordinates":[85.67585,27.70069],"type":"Point"}
}