{
  "type": "Feature",
  "properties": {
    "gn:admin1_code":"MR",
    "gn:admin2_code":"2",
    "gn:admin3_code":"60.0",
    "gn:admin4_code":"600021.0",
    "gn:asciiname":"Narepani",
    "gn:country_code":"NP",
    "gn:dem":986,
    "gn:feature_class":"P",
    "gn:feature_code":"PPLL",
    "gn:name":"Narepani",
    "gn:population":0,
    "gn:timezone":"Asia/Kathmandu",
    "iso:country":"NP",
    "wof:name":"Narepani",
    "wof:placetype":"locality"
},
  "geometry": {"coordinates":[81.65779000000001,28.82363],"type":"Point"}
}