{
  "type": "Feature",
  "properties": {
    "gn:admin1_code":"ER",
    "gn:admin2_code":"7.0",
    "gn:admin3_code":"6.0",
    "gn:admin4_code":"60013.0",
    "gn:asciiname":"Katahare",
    "gn:country_code":"NP",
    "gn:dem":687,
    "gn:feature_class":"P",
    "gn:feature_code":"PPLL",
    "gn:name":"Katahare",
    "gn:population":0,
    "gn:timezone":"Asia/Kathmandu",
    "iso:country":"NP",
    "wof:name":"Katahare",
    "wof:placetype":"locality"
},
  "geometry": {"coordinates":[87.25584000000001,26.84541],"type":"Point"}
}