{
  "type": "Feature",
  "properties": {
    "gn:admin1_code":"MR",
    "gn:admin2_code":"12",
    "gn:admin3_code":"54",
    "gn:admin4_code":"540027",
    "gn:asciiname":"Rawalbara",
    "gn:country_code":"NP",
    "gn:dem":1802,
    "gn:feature_class":"P",
    "gn:feature_code":"PPLL",
    "gn:name":"Rawalbara",
    "gn:population":0,
    "gn:timezone":"Asia/Kathmandu",
    "iso:country":"NP",
    "wof:name":"Rawalbara",
    "wof:placetype":"locality"
},
  "geometry": {"coordinates":[82.46525,28.62935],"type":"Point"}
}