{
  "type": "Feature",
  "properties": {
    "gn:admin1_code":"MR",
    "gn:admin2_code":"6",
    "gn:admin3_code":"64.0",
    "gn:admin4_code":"640024.0",
    "gn:asciiname":"Ghankhaya",
    "gn:country_code":"NP",
    "gn:dem":2354,
    "gn:feature_class":"P",
    "gn:feature_code":"PPLL",
    "gn:name":"Ghankhaya",
    "gn:population":0,
    "gn:timezone":"Asia/Kathmandu",
    "iso:country":"NP",
    "wof:name":"Ghankhaya",
    "wof:placetype":"locality"
},
  "geometry": {"coordinates":[81.83825999999998,29.15261],"type":"Point"}
}