{
  "type": "Feature",
  "properties": {
    "gn:admin1_code":"WR",
    "gn:admin2_code":"8",
    "gn:admin3_code":"48",
    "gn:admin4_code":"480015",
    "gn:asciiname":"Sitabas",
    "gn:country_code":"NP",
    "gn:dem":288,
    "gn:feature_class":"P",
    "gn:feature_code":"PPLL",
    "gn:name":"Sitabas",
    "gn:population":0,
    "gn:timezone":"Asia/Kathmandu",
    "iso:country":"NP",
    "wof:name":"Sitabas",
    "wof:placetype":"locality"
},
  "geometry": {"coordinates":[84.18648,27.70373],"type":"Point"}
}