{
  "type": "Feature",
  "properties": {
    "gn:admin1_code":"ER",
    "gn:admin2_code":"7.0",
    "gn:admin3_code":"6.0",
    "gn:admin4_code":"60025.0",
    "gn:asciiname":"Haripur",
    "gn:country_code":"NP",
    "gn:dem":79,
    "gn:feature_class":"P",
    "gn:feature_code":"PPLL",
    "gn:name":"Haripur",
    "gn:population":0,
    "gn:timezone":"Asia/Kathmandu",
    "iso:country":"NP",
    "name:cat_x_preferred":[
        "Haripur"
    ],
    "name:ceb_x_preferred":[
        "Haripur"
    ],
    "name:fra_x_preferred":[
        "Haripur"
    ],
    "name:new_x_preferred":[
        "\u0939\u0930\u093f\u092a\u0941\u0930 \u0917\u093e\u0935\u093f\u0938"
    ],
    "name:pol_x_preferred":[
        "Haripur"
    ],
    "name:rus_x_preferred":[
        "\u0425\u0430\u0440\u0438\u043f\u0443\u0440"
    ],
    "name:swe_x_preferred":[
        "Haripur"
    ],
    "name:tur_x_preferred":[
        "Haripur"
    ],
    "wof:name":"Haripur",
    "wof:placetype":"locality"
},
  "geometry": {"coordinates":[86.99165000000001,26.54555],"type":"Point"}
}