{
  "type": "Feature",
  "properties": {
    "gn:admin1_code":"ER",
    "gn:admin2_code":"10.0",
    "gn:admin3_code":"1.0",
    "gn:admin4_code":"10010.0",
    "gn:asciiname":"Kuwapani",
    "gn:country_code":"NP",
    "gn:dem":1674,
    "gn:feature_class":"P",
    "gn:feature_code":"PPLL",
    "gn:name":"Kuwapani",
    "gn:population":0,
    "gn:timezone":"Asia/Kathmandu",
    "iso:country":"NP",
    "wof:name":"Kuwapani",
    "wof:placetype":"locality"
},
  "geometry": {"coordinates":[87.62124,27.31284],"type":"Point"}
}