{
  "type": "Feature",
  "properties": {
    "gn:admin1_code":"MR",
    "gn:admin2_code":"12",
    "gn:admin3_code":"55",
    "gn:admin4_code":"550031",
    "gn:asciiname":"Jairu",
    "gn:country_code":"NP",
    "gn:dem":971,
    "gn:feature_class":"P",
    "gn:feature_code":"PPLL",
    "gn:name":"Jairu",
    "gn:population":0,
    "gn:timezone":"Asia/Kathmandu",
    "iso:country":"NP",
    "wof:name":"Jairu",
    "wof:placetype":"locality"
},
  "geometry": {"coordinates":[82.00109,28.44434],"type":"Point"}
}