{
  "type": "Feature",
  "properties": {
    "gn:admin1_code":"MR",
    "gn:admin2_code":"12",
    "gn:admin3_code":"56.0",
    "gn:admin4_code":"560004.0",
    "gn:asciiname":"Kasiyapur",
    "gn:country_code":"NP",
    "gn:dem":242,
    "gn:feature_class":"P",
    "gn:feature_code":"PPLL",
    "gn:name":"Kasiyapur",
    "gn:population":0,
    "gn:timezone":"Asia/Kathmandu",
    "iso:country":"NP",
    "wof:name":"Kasiyapur",
    "wof:placetype":"locality"
},
  "geometry": {"coordinates":[82.50051000000001,27.8474],"type":"Point"}
}