{
  "type": "Feature",
  "properties": {
    "gn:admin1_code":"WR",
    "gn:admin2_code":"4.0",
    "gn:admin3_code":"39.0",
    "gn:admin4_code":"390053.0",
    "gn:asciiname":"Dumrechhapa",
    "gn:country_code":"NP",
    "gn:dem":1579,
    "gn:feature_class":"P",
    "gn:feature_code":"PPLL",
    "gn:name":"Dumrechhapa",
    "gn:population":0,
    "gn:timezone":"Asia/Kathmandu",
    "iso:country":"NP",
    "wof:name":"Dumrechhapa",
    "wof:placetype":"locality"
},
  "geometry": {"coordinates":[83.68482,28.0135],"type":"Point"}
}