{
  "type": "Feature",
  "properties": {
    "gn:admin1_code":"ER",
    "gn:admin2_code":"13",
    "gn:admin3_code":"15",
    "gn:admin4_code":"150104",
    "gn:asciiname":"Kachandaha",
    "gn:country_code":"NP",
    "gn:dem":115,
    "gn:feature_class":"P",
    "gn:feature_code":"PPLL",
    "gn:name":"Kachandaha",
    "gn:population":0,
    "gn:timezone":"Asia/Kathmandu",
    "iso:country":"NP",
    "wof:name":"Kachandaha",
    "wof:placetype":"locality"
},
  "geometry": {"coordinates":[86.68392,26.61244000000001],"type":"Point"}
}