{
  "type": "Feature",
  "properties": {
    "gn:admin1_code":"MR",
    "gn:admin2_code":"2.0",
    "gn:admin3_code":"59.0",
    "gn:admin4_code":"590010.0",
    "gn:asciiname":"Madanechaur",
    "gn:country_code":"NP",
    "gn:dem":593,
    "gn:feature_class":"P",
    "gn:feature_code":"PPLL",
    "gn:name":"Madanechaur",
    "gn:population":0,
    "gn:timezone":"Asia/Kathmandu",
    "iso:country":"NP",
    "wof:name":"Madanechaur",
    "wof:placetype":"locality"
},
  "geometry": {"coordinates":[81.73596999999999,28.46001],"type":"Point"}
}