{
  "type": "Feature",
  "properties": {
    "gn:admin1_code":"ER",
    "gn:admin2_code":"10",
    "gn:admin3_code":"2",
    "gn:admin4_code":"20038",
    "gn:asciiname":"Nigale",
    "gn:country_code":"NP",
    "gn:dem":1426,
    "gn:feature_class":"P",
    "gn:feature_code":"PPLL",
    "gn:name":"Nigale",
    "gn:population":0,
    "gn:timezone":"Asia/Kathmandu",
    "iso:country":"NP",
    "wof:name":"Nigale",
    "wof:placetype":"locality"
},
  "geometry": {"coordinates":[87.61851999999998,27.06792],"type":"Point"}
}