{
  "type": "Feature",
  "properties": {
    "gn:admin1_code":"FR",
    "gn:admin2_code":"14",
    "gn:admin3_code":"68",
    "gn:admin4_code":"680038",
    "gn:asciiname":"Simali",
    "gn:country_code":"NP",
    "gn:dem":1815,
    "gn:feature_class":"P",
    "gn:feature_code":"PPLL",
    "gn:name":"Simali",
    "gn:population":0,
    "gn:timezone":"Asia/Kathmandu",
    "iso:country":"NP",
    "wof:name":"Simali",
    "wof:placetype":"locality"
},
  "geometry": {"coordinates":[80.84583000000001,29.6346],"type":"Point"}
}