{
  "type": "Feature",
  "properties": {
    "gn:admin1_code":"CR",
    "gn:admin2_code":"11",
    "gn:admin3_code":"31",
    "gn:admin4_code":"310040.0",
    "gn:asciiname":"Thakaljor",
    "gn:country_code":"NP",
    "gn:dem":648,
    "gn:feature_class":"P",
    "gn:feature_code":"PPLL",
    "gn:name":"Thakaljor",
    "gn:population":0,
    "gn:timezone":"Asia/Kathmandu",
    "iso:country":"NP",
    "wof:name":"Thakaljor",
    "wof:placetype":"locality"
},
  "geometry": {"coordinates":[85.22740999999998,27.26473],"type":"Point"}
}