{
  "type": "Feature",
  "properties": {
    "gn:admin1_code":"ER",
    "gn:admin2_code":"13",
    "gn:admin3_code":"12",
    "gn:admin4_code":"120049",
    "gn:asciiname":"Binase",
    "gn:country_code":"NP",
    "gn:dem":1246,
    "gn:feature_class":"P",
    "gn:feature_code":"PPLL",
    "gn:name":"Binase",
    "gn:population":0,
    "gn:timezone":"Asia/Kathmandu",
    "iso:country":"NP",
    "wof:name":"Binase",
    "wof:placetype":"locality"
},
  "geometry": {"coordinates":[86.38101,27.23656],"type":"Point"}
}