{
  "type": "Feature",
  "properties": {
    "gn:admin1_code":"FR",
    "gn:admin2_code":"14",
    "gn:admin3_code":"71.0",
    "gn:admin4_code":"710028.0",
    "gn:asciiname":"Bunga",
    "gn:country_code":"NP",
    "gn:dem":1641,
    "gn:feature_class":"P",
    "gn:feature_code":"PPLL",
    "gn:name":"Bunga",
    "gn:population":0,
    "gn:timezone":"Asia/Kathmandu",
    "iso:country":"NP",
    "name:ceb_x_preferred":[
        "Bunga"
    ],
    "name:ind_x_preferred":[
        "Bunga"
    ],
    "name:swe_x_preferred":[
        "Bunga"
    ],
    "name:tgl_x_preferred":[
        "Bunga"
    ],
    "wof:name":"Bunga",
    "wof:placetype":"locality"
},
  "geometry": {"coordinates":[80.70253000000002,28.98144000000001],"type":"Point"}
}