{
  "type": "Feature",
  "properties": {
    "gn:admin1_code":"MR",
    "gn:admin2_code":"2",
    "gn:admin3_code":"61.0",
    "gn:admin4_code":"610029.0",
    "gn:asciiname":"Syakri",
    "gn:country_code":"NP",
    "gn:dem":1830,
    "gn:feature_class":"P",
    "gn:feature_code":"PPLL",
    "gn:name":"Syakri",
    "gn:population":0,
    "gn:timezone":"Asia/Kathmandu",
    "iso:country":"NP",
    "wof:name":"Syakri",
    "wof:placetype":"locality"
},
  "geometry": {"coordinates":[82.11219,28.81403],"type":"Point"}
}