{
  "type": "Feature",
  "properties": {
    "gn:admin1_code":"ER",
    "gn:admin2_code":"13.0",
    "gn:admin3_code":"14.0",
    "gn:admin4_code":"140027.0",
    "gn:asciiname":"Dhungre",
    "gn:country_code":"NP",
    "gn:dem":300,
    "gn:feature_class":"P",
    "gn:feature_code":"PPLL",
    "gn:name":"Dhungre",
    "gn:population":0,
    "gn:timezone":"Asia/Kathmandu",
    "iso:country":"NP",
    "wof:name":"Dhungre",
    "wof:placetype":"locality"
},
  "geometry": {"coordinates":[86.52558000000001,26.85579],"type":"Point"}
}