{
  "type": "Feature",
  "properties": {
    "gn:admin1_code":"CR",
    "gn:admin2_code":"5",
    "gn:admin3_code":"22.0",
    "gn:admin4_code":"220052.0",
    "gn:asciiname":"Jhisepu",
    "gn:country_code":"NP",
    "gn:dem":1646,
    "gn:feature_class":"P",
    "gn:feature_code":"PPLL",
    "gn:name":"Jhisepu",
    "gn:population":0,
    "gn:timezone":"Asia/Kathmandu",
    "iso:country":"NP",
    "wof:name":"Jhisepu",
    "wof:placetype":"locality"
},
  "geometry": {"coordinates":[86.18689999999999,27.57203],"type":"Point"}
}