{
  "type": "Feature",
  "properties": {
    "gn:admin1_code":"CR",
    "gn:admin2_code":"5",
    "gn:admin3_code":"19",
    "gn:admin4_code":"190096",
    "gn:asciiname":"Belhi",
    "gn:country_code":"NP",
    "gn:dem":92,
    "gn:feature_class":"P",
    "gn:feature_code":"PPLL",
    "gn:name":"Belhi",
    "gn:population":0,
    "gn:timezone":"Asia/Kathmandu",
    "iso:country":"NP",
    "name:fra_x_preferred":[
        "Belhi"
    ],
    "name:pol_x_preferred":[
        "Belhi"
    ],
    "wof:name":"Belhi",
    "wof:placetype":"locality"
},
  "geometry": {"coordinates":[85.49176,26.91913],"type":"Point"}
}