{
  "type": "Feature",
  "properties": {
    "gn:admin1_code":"FR",
    "gn:admin2_code":"9",
    "gn:admin3_code":"74",
    "gn:admin4_code":"740053",
    "gn:asciiname":"Kulakoban",
    "gn:country_code":"NP",
    "gn:dem":2456,
    "gn:feature_class":"P",
    "gn:feature_code":"PPLL",
    "gn:name":"Kulakoban",
    "gn:population":0,
    "gn:timezone":"Asia/Kathmandu",
    "iso:country":"NP",
    "wof:name":"Kulakoban",
    "wof:placetype":"locality"
},
  "geometry": {"coordinates":[80.71214000000001,29.49167000000001],"type":"Point"}
}