{
  "type": "Feature",
  "properties": {
    "gn:admin1_code":"MR",
    "gn:admin2_code":"12",
    "gn:admin3_code":"52",
    "gn:admin4_code":"520003.0",
    "gn:asciiname":"Aduwabari",
    "gn:country_code":"NP",
    "gn:dem":476,
    "gn:feature_class":"P",
    "gn:feature_code":"PPLL",
    "gn:name":"Aduwabari",
    "gn:population":0,
    "gn:timezone":"Asia/Kathmandu",
    "iso:country":"NP",
    "wof:name":"Aduwabari",
    "wof:placetype":"locality"
},
  "geometry": {"coordinates":[82.78491,27.91776],"type":"Point"}
}