{
  "type": "Feature",
  "properties": {
    "gn:admin1_code":"MR",
    "gn:admin2_code":"12",
    "gn:admin3_code":"54",
    "gn:admin4_code":"540010",
    "gn:asciiname":"Kuriban",
    "gn:country_code":"NP",
    "gn:dem":2087,
    "gn:feature_class":"P",
    "gn:feature_code":"PPLL",
    "gn:name":"Kuriban",
    "gn:population":0,
    "gn:timezone":"Asia/Kathmandu",
    "iso:country":"NP",
    "wof:name":"Kuriban",
    "wof:placetype":"locality"
},
  "geometry": {"coordinates":[82.41798,28.7079],"type":"Point"}
}