{
  "type": "Feature",
  "properties": {
    "gn:admin1_code":"ER",
    "gn:admin2_code":"10",
    "gn:admin3_code":"4.0",
    "gn:admin4_code":"40023.0",
    "gn:asciiname":"Basnetgaun",
    "gn:country_code":"NP",
    "gn:dem":97,
    "gn:feature_class":"P",
    "gn:feature_code":"PPLL",
    "gn:name":"Basnetgaun",
    "gn:population":0,
    "gn:timezone":"Asia/Kathmandu",
    "iso:country":"NP",
    "wof:name":"Basnetgaun",
    "wof:placetype":"locality"
},
  "geometry": {"coordinates":[88.02585999999999,26.55296],"type":"Point"}
}