{
  "type": "Feature",
  "properties": {
    "gn:admin1_code":"ER",
    "gn:admin2_code":"13.0",
    "gn:admin3_code":"14.0",
    "gn:admin4_code":"140029.0",
    "gn:asciiname":"Kolbote",
    "gn:country_code":"NP",
    "gn:dem":810,
    "gn:feature_class":"P",
    "gn:feature_code":"PPLL",
    "gn:name":"Kolbote",
    "gn:population":0,
    "gn:timezone":"Asia/Kathmandu",
    "iso:country":"NP",
    "wof:name":"Kolbote",
    "wof:placetype":"locality"
},
  "geometry": {"coordinates":[86.61978000000001,26.91971],"type":"Point"}
}