{
  "type": "Feature",
  "properties": {
    "gn:admin1_code":"CR",
    "gn:admin2_code":"1",
    "gn:admin3_code":"23",
    "gn:admin4_code":"230074",
    "gn:asciiname":"Laharetol",
    "gn:country_code":"NP",
    "gn:dem":1580,
    "gn:feature_class":"P",
    "gn:feature_code":"PPLL",
    "gn:name":"Laharetol",
    "gn:population":0,
    "gn:timezone":"Asia/Kathmandu",
    "iso:country":"NP",
    "wof:name":"Laharetol",
    "wof:placetype":"locality"
},
  "geometry": {"coordinates":[85.80334000000001,27.6735],"type":"Point"}
}