{
  "type": "Feature",
  "properties": {
    "gn:admin1_code":"WR",
    "gn:admin2_code":"8",
    "gn:admin3_code":"46.0",
    "gn:admin4_code":"460006.0",
    "gn:asciiname":"Pauwagaun",
    "gn:country_code":"NP",
    "gn:dem":1153,
    "gn:feature_class":"P",
    "gn:feature_code":"PPLL",
    "gn:name":"Pauwagaun",
    "gn:population":0,
    "gn:timezone":"Asia/Kathmandu",
    "iso:country":"NP",
    "wof:name":"Pauwagaun",
    "wof:placetype":"locality"
},
  "geometry": {"coordinates":[83.16989000000002,28.16963],"type":"Point"}
}