{
  "type": "Feature",
  "properties": {
    "gn:admin1_code":"FR",
    "gn:admin2_code":"9",
    "gn:admin3_code":"73.0",
    "gn:admin4_code":"730015.0",
    "gn:asciiname":"Palethar",
    "gn:country_code":"NP",
    "gn:dem":1943,
    "gn:feature_class":"P",
    "gn:feature_code":"PPLL",
    "gn:name":"Palethar",
    "gn:population":0,
    "gn:timezone":"Asia/Kathmandu",
    "iso:country":"NP",
    "wof:name":"Palethar",
    "wof:placetype":"locality"
},
  "geometry": {"coordinates":[80.63448000000002,29.37152],"type":"Point"}
}