{
  "type": "Feature",
  "properties": {
    "gn:admin1_code":"FR",
    "gn:admin2_code":"14",
    "gn:admin3_code":"69.0",
    "gn:admin4_code":"690011.0",
    "gn:asciiname":"Basnegada",
    "gn:country_code":"NP",
    "gn:dem":1457,
    "gn:feature_class":"P",
    "gn:feature_code":"PPLL",
    "gn:name":"Basnegada",
    "gn:population":0,
    "gn:timezone":"Asia/Kathmandu",
    "iso:country":"NP",
    "wof:name":"Basnegada",
    "wof:placetype":"locality"
},
  "geometry": {"coordinates":[81.36476999999999,29.0456],"type":"Point"}
}