{
  "type": "Feature",
  "properties": {
    "gn:admin1_code":"CR",
    "gn:admin2_code":"11",
    "gn:admin3_code":"31",
    "gn:admin4_code":"310043.0",
    "gn:asciiname":"Simaltwak",
    "gn:country_code":"NP",
    "gn:dem":906,
    "gn:feature_class":"P",
    "gn:feature_code":"PPLL",
    "gn:name":"Simaltwak",
    "gn:population":0,
    "gn:timezone":"Asia/Kathmandu",
    "iso:country":"NP",
    "wof:name":"Simaltwak",
    "wof:placetype":"locality"
},
  "geometry": {"coordinates":[85.25736999999999,27.41918],"type":"Point"}
}