{
  "type": "Feature",
  "properties": {
    "gn:admin1_code":"ER",
    "gn:admin2_code":"10.0",
    "gn:admin3_code":"1.0",
    "gn:admin4_code":"10043.0",
    "gn:asciiname":"Tamewa",
    "gn:country_code":"NP",
    "gn:dem":1661,
    "gn:feature_class":"P",
    "gn:feature_code":"PPLL",
    "gn:name":"Tamewa",
    "gn:population":0,
    "gn:timezone":"Asia/Kathmandu",
    "iso:country":"NP",
    "wof:name":"Tamewa",
    "wof:placetype":"locality"
},
  "geometry": {"coordinates":[87.80131,27.51318],"type":"Point"}
}