{
  "type": "Feature",
  "properties": {
    "gn:admin1_code":"FR",
    "gn:admin2_code":"14",
    "gn:admin3_code":"69.0",
    "gn:admin4_code":"690002.0",
    "gn:asciiname":"Boharabada",
    "gn:country_code":"NP",
    "gn:dem":591,
    "gn:feature_class":"P",
    "gn:feature_code":"PPLL",
    "gn:name":"Boharabada",
    "gn:population":0,
    "gn:timezone":"Asia/Kathmandu",
    "iso:country":"NP",
    "wof:name":"Boharabada",
    "wof:placetype":"locality"
},
  "geometry": {"coordinates":[81.20078000000002,29.21173],"type":"Point"}
}