{
  "type": "Feature",
  "properties": {
    "gn:admin1_code":"WR",
    "gn:admin2_code":"8",
    "gn:admin3_code":"46.0",
    "gn:admin4_code":"460053.0",
    "gn:asciiname":"Khamipatagaun",
    "gn:country_code":"NP",
    "gn:dem":997,
    "gn:feature_class":"P",
    "gn:feature_code":"PPLL",
    "gn:name":"Khamipatagaun",
    "gn:population":0,
    "gn:timezone":"Asia/Kathmandu",
    "iso:country":"NP",
    "wof:name":"Khamipatagaun",
    "wof:placetype":"locality"
},
  "geometry": {"coordinates":[83.5544,28.07133],"type":"Point"}
}