{
  "type": "Feature",
  "properties": {
    "gn:admin1_code":"MR",
    "gn:admin2_code":"12",
    "gn:admin3_code":"55",
    "gn:admin4_code":"550004",
    "gn:asciiname":"Patke",
    "gn:country_code":"NP",
    "gn:dem":954,
    "gn:feature_class":"P",
    "gn:feature_code":"PPLL",
    "gn:name":"Patke",
    "gn:population":0,
    "gn:timezone":"Asia/Kathmandu",
    "iso:country":"NP",
    "wof:name":"Patke",
    "wof:placetype":"locality"
},
  "geometry": {"coordinates":[82.07731,28.58525],"type":"Point"}
}