{
  "type": "Feature",
  "properties": {
    "gn:admin1_code":"FR",
    "gn:admin2_code":"9",
    "gn:admin3_code":"74",
    "gn:admin4_code":"740004",
    "gn:asciiname":"Karakot",
    "gn:country_code":"NP",
    "gn:dem":1797,
    "gn:feature_class":"P",
    "gn:feature_code":"PPLL",
    "gn:name":"Karakot",
    "gn:population":0,
    "gn:timezone":"Asia/Kathmandu",
    "iso:country":"NP",
    "wof:name":"Karakot",
    "wof:placetype":"locality"
},
  "geometry": {"coordinates":[80.74736999999998,29.6181],"type":"Point"}
}