{
  "type": "Feature",
  "properties": {
    "gn:admin1_code":"CR",
    "gn:admin2_code":"1.0",
    "gn:admin3_code":"26.0",
    "gn:admin4_code":"260017.0",
    "gn:asciiname":"Sudal",
    "gn:country_code":"NP",
    "gn:dem":1480,
    "gn:feature_class":"P",
    "gn:feature_code":"PPLL",
    "gn:name":"Sudal",
    "gn:population":0,
    "gn:timezone":"Asia/Kathmandu",
    "iso:country":"NP",
    "name:bih_x_preferred":[
        "\u0938\u0941\u0921\u093e\u0932"
    ],
    "name:ceb_x_preferred":[
        "Sudal"
    ],
    "name:msa_x_preferred":[
        "Sudal"
    ],
    "name:nep_x_preferred":[
        "\u0938\u0941\u0921\u093e\u0932"
    ],
    "name:new_x_preferred":[
        "\u0938\u0941\u0926\u093e\u0932"
    ],
    "name:pol_x_preferred":[
        "Sudal"
    ],
    "wof:name":"Sudal",
    "wof:placetype":"locality"
},
  "geometry": {"coordinates":[85.48751,27.68029000000001],"type":"Point"}
}