{
  "type": "Feature",
  "properties": {
    "gn:admin1_code":"CR",
    "gn:admin2_code":"1",
    "gn:admin3_code":"24.0",
    "gn:admin4_code":"240039.0",
    "gn:asciiname":"Hartan",
    "gn:country_code":"NP",
    "gn:dem":702,
    "gn:feature_class":"P",
    "gn:feature_code":"PPLL",
    "gn:name":"Hartan",
    "gn:population":0,
    "gn:timezone":"Asia/Kathmandu",
    "iso:country":"NP",
    "wof:name":"Hartan",
    "wof:placetype":"locality"
},
  "geometry": {"coordinates":[85.82496,27.53887000000001],"type":"Point"}
}