{
  "type": "Feature",
  "properties": {
    "gn:admin1_code":"FR",
    "gn:admin2_code":"9",
    "gn:admin3_code":"74",
    "gn:admin4_code":"740063",
    "gn:asciiname":"Baru",
    "gn:country_code":"NP",
    "gn:dem":1498,
    "gn:feature_class":"P",
    "gn:feature_code":"PPLL",
    "gn:name":"Baru",
    "gn:population":0,
    "gn:timezone":"Asia/Kathmandu",
    "iso:country":"NP",
    "name:ces_x_preferred":[
        "Baru"
    ],
    "name:nld_x_preferred":[
        "Baru"
    ],
    "name:spa_x_preferred":[
        "Baru"
    ],
    "wof:name":"Baru",
    "wof:placetype":"locality"
},
  "geometry": {"coordinates":[80.35754,29.38828],"type":"Point"}
}