{
  "type": "Feature",
  "properties": {
    "gn:admin1_code":"CR",
    "gn:admin2_code":"5",
    "gn:admin3_code":"20",
    "gn:admin4_code":"200012",
    "gn:asciiname":"Thakle",
    "gn:country_code":"NP",
    "gn:dem":768,
    "gn:feature_class":"P",
    "gn:feature_code":"PPLL",
    "gn:name":"Thakle",
    "gn:population":0,
    "gn:timezone":"Asia/Kathmandu",
    "iso:country":"NP",
    "name:bih_x_preferred":[
        "\u0925\u093e\u0915\u094d\u0932\u0947"
    ],
    "name:ceb_x_preferred":[
        "Thakle"
    ],
    "name:fra_x_preferred":[
        "Thakle"
    ],
    "name:msa_x_preferred":[
        "Thakle"
    ],
    "name:nep_x_preferred":[
        "\u0925\u093e\u0915\u094d\u0932\u0947"
    ],
    "name:new_x_preferred":[
        "\u0925\u093e\u0915\u094d\u0932\u0947"
    ],
    "name:pol_x_preferred":[
        "Thakle"
    ],
    "wof:name":"Thakle",
    "wof:placetype":"locality"
},
  "geometry": {"coordinates":[86.10982,27.24256],"type":"Point"}
}