{
  "type": "Feature",
  "properties": {
    "gn:admin1_code":"MR",
    "gn:admin2_code":"12",
    "gn:admin3_code":"53",
    "gn:admin4_code":"530047",
    "gn:asciiname":"Puchir",
    "gn:country_code":"NP",
    "gn:dem":1859,
    "gn:feature_class":"P",
    "gn:feature_code":"PPLL",
    "gn:name":"Puchir",
    "gn:population":0,
    "gn:timezone":"Asia/Kathmandu",
    "iso:country":"NP",
    "wof:name":"Puchir",
    "wof:placetype":"locality"
},
  "geometry": {"coordinates":[82.68395,28.51512],"type":"Point"}
}