{
  "type": "Feature",
  "properties": {
    "gn:admin1_code":"ER",
    "gn:admin2_code":"13",
    "gn:admin3_code":"16",
    "gn:admin4_code":"160038",
    "gn:asciiname":"Asawan",
    "gn:country_code":"NP",
    "gn:dem":107,
    "gn:feature_class":"P",
    "gn:feature_code":"PPLL",
    "gn:name":"Asawan",
    "gn:population":0,
    "gn:timezone":"Asia/Kathmandu",
    "iso:country":"NP",
    "wof:name":"Asawan",
    "wof:placetype":"locality"
},
  "geometry": {"coordinates":[86.18964,26.8428],"type":"Point"}
}