{
  "type": "Feature",
  "properties": {
    "gn:admin1_code":"CR",
    "gn:admin2_code":"1",
    "gn:admin3_code":"25",
    "gn:admin4_code":"250040",
    "gn:asciiname":"Jhyalpati",
    "gn:country_code":"NP",
    "gn:dem":1454,
    "gn:feature_class":"P",
    "gn:feature_code":"PPLL",
    "gn:name":"Jhyalpati",
    "gn:population":0,
    "gn:timezone":"Asia/Kathmandu",
    "iso:country":"NP",
    "wof:name":"Jhyalpati",
    "wof:placetype":"locality"
},
  "geometry": {"coordinates":[85.32624,27.6119],"type":"Point"}
}