{
  "type": "Feature",
  "properties": {
    "gn:admin1_code":"WR",
    "gn:admin2_code":"8",
    "gn:admin3_code":"47",
    "gn:admin4_code":"470047",
    "gn:asciiname":"Mujhun",
    "gn:country_code":"NP",
    "gn:dem":1225,
    "gn:feature_class":"P",
    "gn:feature_code":"PPLL",
    "gn:name":"Mujhun",
    "gn:population":0,
    "gn:timezone":"Asia/Kathmandu",
    "iso:country":"NP",
    "wof:name":"Mujhun",
    "wof:placetype":"locality"
},
  "geometry": {"coordinates":[83.39922,27.87952],"type":"Point"}
}