{
  "type": "Feature",
  "properties": {
    "gn:admin1_code":"MR",
    "gn:admin2_code":"12",
    "gn:admin3_code":"53",
    "gn:admin4_code":"530033",
    "gn:asciiname":"Harobang",
    "gn:country_code":"NP",
    "gn:dem":1629,
    "gn:feature_class":"P",
    "gn:feature_code":"PPLL",
    "gn:name":"Harobang",
    "gn:population":0,
    "gn:timezone":"Asia/Kathmandu",
    "iso:country":"NP",
    "wof:name":"Harobang",
    "wof:placetype":"locality"
},
  "geometry": {"coordinates":[82.70001999999999,28.25777],"type":"Point"}
}