{
  "type": "Feature",
  "properties": {
    "gn:admin1_code":"FR",
    "gn:admin2_code":"14",
    "gn:admin3_code":"71.0",
    "gn:admin4_code":"710010.0",
    "gn:asciiname":"Saraswatinagar",
    "gn:country_code":"NP",
    "gn:dem":177,
    "gn:feature_class":"P",
    "gn:feature_code":"PPLL",
    "gn:name":"Saraswatinagar",
    "gn:population":0,
    "gn:timezone":"Asia/Kathmandu",
    "iso:country":"NP",
    "name:ceb_x_preferred":[
        "Saraswotinagar"
    ],
    "name:mai_x_preferred":[
        "\u0938\u0930\u0938\u094d\u0935\u0924\u0940\u0928\u0917\u0930"
    ],
    "name:msa_x_preferred":[
        "Saraswotinagar"
    ],
    "name:nep_x_preferred":[
        "\u0938\u0930\u0938\u094d\u0935\u0924\u0940\u0928\u0917\u0930"
    ],
    "name:new_x_preferred":[
        "\u0938\u0930\u0938\u094d\u0935\u0924\u0940\u0928\u0917\u0930"
    ],
    "name:pol_x_preferred":[
        "Saraswotinagar"
    ],
    "wof:name":"Saraswatinagar",
    "wof:placetype":"locality"
},
  "geometry": {"coordinates":[80.57979,28.69531],"type":"Point"}
}