{
  "type": "Feature",
  "properties": {
    "gn:admin1_code":"FR",
    "gn:admin2_code":"9",
    "gn:admin3_code":"75.0",
    "gn:admin4_code":"750002.0",
    "gn:asciiname":"Jharkanda",
    "gn:country_code":"NP",
    "gn:dem":1407,
    "gn:feature_class":"P",
    "gn:feature_code":"PPLL",
    "gn:name":"Jharkanda",
    "gn:population":0,
    "gn:timezone":"Asia/Kathmandu",
    "iso:country":"NP",
    "wof:name":"Jharkanda",
    "wof:placetype":"locality"
},
  "geometry": {"coordinates":[80.52774000000002,29.68961],"type":"Point"}
}