{
  "type": "Feature",
  "properties": {
    "gn:admin1_code":"WR",
    "gn:admin2_code":"8",
    "gn:admin3_code":"46.0",
    "gn:admin4_code":"460045.0",
    "gn:asciiname":"Mahabhir",
    "gn:country_code":"NP",
    "gn:dem":1760,
    "gn:feature_class":"P",
    "gn:feature_code":"PPLL",
    "gn:name":"Mahabhir",
    "gn:population":0,
    "gn:timezone":"Asia/Kathmandu",
    "iso:country":"NP",
    "wof:name":"Mahabhir",
    "wof:placetype":"locality"
},
  "geometry": {"coordinates":[83.10739000000002,28.24153],"type":"Point"}
}