{
  "type": "Feature",
  "properties": {
    "gn:admin1_code":"WR",
    "gn:admin2_code":"4",
    "gn:admin3_code":"40.0",
    "gn:admin4_code":"400003.0",
    "gn:asciiname":"Fair(Haribodhani Ekadashi",
    "gn:country_code":"NP",
    "gn:dem":650,
    "gn:feature_class":"P",
    "gn:feature_code":"PPLL",
    "gn:name":"Fair(Haribodhani Ekadashi",
    "gn:population":0,
    "gn:timezone":"Asia/Kathmandu",
    "iso:country":"NP",
    "wof:name":"Fair(Haribodhani Ekadashi",
    "wof:placetype":"locality"
},
  "geometry": {"coordinates":[84.1541,28.21309],"type":"Point"}
}