{
  "type": "Feature",
  "properties": {
    "gn:admin1_code":"WR",
    "gn:admin2_code":"8",
    "gn:admin3_code":"49",
    "gn:admin4_code":"490036",
    "gn:asciiname":"Kaluwa",
    "gn:country_code":"NP",
    "gn:dem":120,
    "gn:feature_class":"P",
    "gn:feature_code":"PPLL",
    "gn:name":"Kaluwa",
    "gn:population":0,
    "gn:timezone":"Asia/Kathmandu",
    "iso:country":"NP",
    "wof:name":"Kaluwa",
    "wof:placetype":"locality"
},
  "geometry": {"coordinates":[83.35715,27.64369000000001],"type":"Point"}
}