{
  "type": "Feature",
  "properties": {
    "gn:admin1_code":"MR",
    "gn:admin2_code":"2",
    "gn:admin3_code":"61.0",
    "gn:admin4_code":"610011.0",
    "gn:asciiname":"Odalpata Tusare",
    "gn:country_code":"NP",
    "gn:dem":1542,
    "gn:feature_class":"P",
    "gn:feature_code":"PPLL",
    "gn:name":"Odalpata Tusare",
    "gn:population":0,
    "gn:timezone":"Asia/Kathmandu",
    "iso:country":"NP",
    "wof:name":"Odalpata Tusare",
    "wof:placetype":"locality"
},
  "geometry": {"coordinates":[81.96064,28.70644],"type":"Point"}
}