{
  "type": "Feature",
  "properties": {
    "gn:admin1_code":"MR",
    "gn:admin2_code":"12",
    "gn:admin3_code":"55",
    "gn:admin4_code":"550031",
    "gn:asciiname":"Panchare",
    "gn:country_code":"NP",
    "gn:dem":1496,
    "gn:feature_class":"P",
    "gn:feature_code":"PPLL",
    "gn:name":"Panchare",
    "gn:population":0,
    "gn:timezone":"Asia/Kathmandu",
    "iso:country":"NP",
    "wof:name":"Panchare",
    "wof:placetype":"locality"
},
  "geometry": {"coordinates":[81.98668000000001,28.41678],"type":"Point"}
}