{
  "type": "Feature",
  "properties": {
    "gn:admin1_code":"CR",
    "gn:admin2_code":"5",
    "gn:admin3_code":"18",
    "gn:admin4_code":"180036",
    "gn:asciiname":"Kalkatetol",
    "gn:country_code":"NP",
    "gn:dem":264,
    "gn:feature_class":"P",
    "gn:feature_code":"PPLL",
    "gn:name":"Kalkatetol",
    "gn:population":0,
    "gn:timezone":"Asia/Kathmandu",
    "iso:country":"NP",
    "wof:name":"Kalkatetol",
    "wof:placetype":"locality"
},
  "geometry": {"coordinates":[85.78971,27.0557],"type":"Point"}
}