{
  "type": "Feature",
  "properties": {
    "gn:admin1_code":"CR",
    "gn:admin2_code":"5",
    "gn:admin3_code":"19",
    "gn:admin4_code":"190076",
    "gn:asciiname":"Guidung",
    "gn:country_code":"NP",
    "gn:dem":536,
    "gn:feature_class":"P",
    "gn:feature_code":"PPLL",
    "gn:name":"Guidung",
    "gn:population":0,
    "gn:timezone":"Asia/Kathmandu",
    "iso:country":"NP",
    "wof:name":"Guidung",
    "wof:placetype":"locality"
},
  "geometry": {"coordinates":[85.77885999999999,27.09724000000001],"type":"Point"}
}