{
  "type": "Feature",
  "properties": {
    "gn:admin1_code":"MR",
    "gn:admin2_code":"12",
    "gn:admin3_code":"55",
    "gn:admin4_code":"550031",
    "gn:asciiname":"Daraban",
    "gn:country_code":"NP",
    "gn:dem":1300,
    "gn:feature_class":"P",
    "gn:feature_code":"PPLL",
    "gn:name":"Daraban",
    "gn:population":0,
    "gn:timezone":"Asia/Kathmandu",
    "iso:country":"NP",
    "name:fas_x_preferred":[
        "\u062f\u0627\u0631\u0627\u0628\u0627\u0646"
    ],
    "name:urd_x_preferred":[
        "\u062f\u0627\u0631\u0627\u0628\u0627\u0646"
    ],
    "wof:name":"Daraban",
    "wof:placetype":"locality"
},
  "geometry": {"coordinates":[82.00825999999998,28.43809000000001],"type":"Point"}
}