{
  "type": "Feature",
  "properties": {
    "gn:admin1_code":"MR",
    "gn:admin2_code":"2.0",
    "gn:admin3_code":"59.0",
    "gn:admin4_code":"590036.0",
    "gn:asciiname":"Badachaur",
    "gn:country_code":"NP",
    "gn:dem":1495,
    "gn:feature_class":"P",
    "gn:feature_code":"PPLL",
    "gn:name":"Badachaur",
    "gn:population":0,
    "gn:timezone":"Asia/Kathmandu",
    "iso:country":"NP",
    "wof:name":"Badachaur",
    "wof:placetype":"locality"
},
  "geometry": {"coordinates":[81.84598000000003,28.65286],"type":"Point"}
}