{
  "type": "Feature",
  "properties": {
    "gn:admin1_code":"ER",
    "gn:admin2_code":"10",
    "gn:admin3_code":"2",
    "gn:admin4_code":"20033",
    "gn:asciiname":"Ithung",
    "gn:country_code":"NP",
    "gn:dem":2341,
    "gn:feature_class":"P",
    "gn:feature_code":"PPLL",
    "gn:name":"Ithung",
    "gn:population":0,
    "gn:timezone":"Asia/Kathmandu",
    "iso:country":"NP",
    "wof:name":"Ithung",
    "wof:placetype":"locality"
},
  "geometry": {"coordinates":[87.81809,27.07137],"type":"Point"}
}