{
  "type": "Feature",
  "properties": {
    "gn:admin1_code":"CR",
    "gn:admin2_code":"11",
    "gn:admin3_code":"35.0",
    "gn:admin4_code":"350009.0",
    "gn:asciiname":"Targaun",
    "gn:country_code":"NP",
    "gn:dem":729,
    "gn:feature_class":"P",
    "gn:feature_code":"PPLL",
    "gn:name":"Targaun",
    "gn:population":0,
    "gn:timezone":"Asia/Kathmandu",
    "iso:country":"NP",
    "wof:name":"Targaun",
    "wof:placetype":"locality"
},
  "geometry": {"coordinates":[84.55192,27.79775],"type":"Point"}
}