{
  "type": "Feature",
  "properties": {
    "gn:admin1_code":"CR",
    "gn:admin2_code":"5",
    "gn:admin3_code":"19",
    "gn:admin4_code":"190071",
    "gn:asciiname":"Hattisude",
    "gn:country_code":"NP",
    "gn:dem":356,
    "gn:feature_class":"P",
    "gn:feature_code":"PPLL",
    "gn:name":"Hattisude",
    "gn:population":0,
    "gn:timezone":"Asia/Kathmandu",
    "iso:country":"NP",
    "wof:name":"Hattisude",
    "wof:placetype":"locality"
},
  "geometry": {"coordinates":[85.71335999999999,27.15005],"type":"Point"}
}