{
  "type": "Feature",
  "properties": {
    "gn:admin1_code":"MR",
    "gn:admin2_code":"2.0",
    "gn:admin3_code":"58.0",
    "gn:admin4_code":"580011.0",
    "gn:asciiname":"Terha Nambar Basti",
    "gn:country_code":"NP",
    "gn:dem":147,
    "gn:feature_class":"P",
    "gn:feature_code":"PPLL",
    "gn:name":"Terha Nambar Basti",
    "gn:population":0,
    "gn:timezone":"Asia/Kathmandu",
    "iso:country":"NP",
    "wof:name":"Terha Nambar Basti",
    "wof:placetype":"locality"
},
  "geometry": {"coordinates":[81.29309000000001,28.23486],"type":"Point"}
}