{
  "type": "Feature",
  "properties": {
    "gn:admin1_code":"ER",
    "gn:admin2_code":"13.0",
    "gn:admin3_code":"14.0",
    "gn:admin4_code":"140006.0",
    "gn:asciiname":"Barpani",
    "gn:country_code":"NP",
    "gn:dem":153,
    "gn:feature_class":"P",
    "gn:feature_code":"PPLL",
    "gn:name":"Barpani",
    "gn:population":0,
    "gn:timezone":"Asia/Kathmandu",
    "iso:country":"NP",
    "wof:name":"Barpani",
    "wof:placetype":"locality"
},
  "geometry": {"coordinates":[86.92071999999997,26.81635],"type":"Point"}
}