{
  "type": "Feature",
  "properties": {
    "gn:admin1_code":"CR",
    "gn:admin2_code":"5",
    "gn:admin3_code":"22.0",
    "gn:admin4_code":"220040.0",
    "gn:asciiname":"Diyale",
    "gn:country_code":"NP",
    "gn:dem":1421,
    "gn:feature_class":"P",
    "gn:feature_code":"PPLL",
    "gn:name":"Diyale",
    "gn:population":0,
    "gn:timezone":"Asia/Kathmandu",
    "iso:country":"NP",
    "wof:name":"Diyale",
    "wof:placetype":"locality"
},
  "geometry": {"coordinates":[86.05812,27.51021],"type":"Point"}
}