{
  "type": "Feature",
  "properties": {
    "gn:admin1_code":"MR",
    "gn:admin2_code":"12",
    "gn:admin3_code":"56.0",
    "gn:admin4_code":"560001.0",
    "gn:asciiname":"Bagiya",
    "gn:country_code":"NP",
    "gn:dem":805,
    "gn:feature_class":"P",
    "gn:feature_code":"PPLL",
    "gn:name":"Bagiya",
    "gn:population":0,
    "gn:timezone":"Asia/Kathmandu",
    "iso:country":"NP",
    "wof:name":"Bagiya",
    "wof:placetype":"locality"
},
  "geometry": {"coordinates":[82.15803000000002,28.20765],"type":"Point"}
}