{
  "type": "Feature",
  "properties": {
    "gn:admin1_code":"WR",
    "gn:admin2_code":"4.0",
    "gn:admin3_code":"39.0",
    "gn:admin4_code":"390018.0",
    "gn:asciiname":"Lindiswanra",
    "gn:country_code":"NP",
    "gn:dem":851,
    "gn:feature_class":"P",
    "gn:feature_code":"PPLL",
    "gn:name":"Lindiswanra",
    "gn:population":0,
    "gn:timezone":"Asia/Kathmandu",
    "iso:country":"NP",
    "wof:name":"Lindiswanra",
    "wof:placetype":"locality"
},
  "geometry": {"coordinates":[83.96115,27.96669],"type":"Point"}
}