{
  "type": "Feature",
  "properties": {
    "gn:admin1_code":"FR",
    "gn:admin2_code":"14",
    "gn:admin3_code":"71.0",
    "gn:admin4_code":"710040.0",
    "gn:asciiname":"Baka",
    "gn:country_code":"NP",
    "gn:dem":264,
    "gn:feature_class":"P",
    "gn:feature_code":"PPLL",
    "gn:name":"Baka",
    "gn:population":0,
    "gn:timezone":"Asia/Kathmandu",
    "iso:country":"NP",
    "name:bel_x_preferred":[
        "\u0411\u0430\u043a\u0430"
    ],
    "name:cat_x_preferred":[
        "Baka"
    ],
    "name:ceb_x_preferred":[
        "Baka"
    ],
    "name:deu_x_preferred":[
        "Baka"
    ],
    "name:fra_x_preferred":[
        "Baka"
    ],
    "name:hun_x_preferred":[
        "Baka"
    ],
    "name:ita_x_preferred":[
        "Baka"
    ],
    "name:lav_x_preferred":[
        "Baka"
    ],
    "name:nld_x_preferred":[
        "Baka"
    ],
    "name:pol_x_preferred":[
        "Baka"
    ],
    "name:rus_x_preferred":[
        "\u0411\u0430\u043a\u0430"
    ],
    "name:spa_x_preferred":[
        "Baka"
    ],
    "name:srp_x_preferred":[
        "\u0411\u0430\u043a\u0430"
    ],
    "name:swe_x_preferred":[
        "Baka"
    ],
    "name:tgl_x_preferred":[
        "Baka"
    ],
    "name:ukr_x_preferred":[
        "\u0411\u0430\u043a\u0430"
    ],
    "wof:name":"Baka",
    "wof:placetype":"locality"
},
  "geometry": {"coordinates":[81.28438,28.68434],"type":"Point"}
}