{
  "type": "Feature",
  "properties": {
    "gn:admin1_code":"ER",
    "gn:admin2_code":"13",
    "gn:admin3_code":"15",
    "gn:admin4_code":"150065",
    "gn:asciiname":"Bhaluwahi",
    "gn:country_code":"NP",
    "gn:dem":143,
    "gn:feature_class":"P",
    "gn:feature_code":"PPLL",
    "gn:name":"Bhaluwahi",
    "gn:population":0,
    "gn:timezone":"Asia/Kathmandu",
    "iso:country":"NP",
    "wof:name":"Bhaluwahi",
    "wof:placetype":"locality"
},
  "geometry": {"coordinates":[86.7313,26.64419],"type":"Point"}
}