{
  "type": "Feature",
  "properties": {
    "gn:admin1_code":"FR",
    "gn:admin2_code":"14",
    "gn:admin3_code":"69",
    "gn:admin4_code":"690038",
    "gn:asciiname":"Todkesal",
    "gn:country_code":"NP",
    "gn:dem":744,
    "gn:feature_class":"P",
    "gn:feature_code":"PPLL",
    "gn:name":"Todkesal",
    "gn:population":0,
    "gn:timezone":"Asia/Kathmandu",
    "iso:country":"NP",
    "wof:name":"Todkesal",
    "wof:placetype":"locality"
},
  "geometry": {"coordinates":[81.42546999999998,29.03283],"type":"Point"}
}