{
  "type": "Feature",
  "properties": {
    "gn:admin1_code":"FR",
    "gn:admin2_code":"14.0",
    "gn:admin3_code":"67.0",
    "gn:admin4_code":"670015.0",
    "gn:asciiname":"Raran Goth",
    "gn:country_code":"NP",
    "gn:dem":2048,
    "gn:feature_class":"P",
    "gn:feature_code":"PPLL",
    "gn:name":"Raran Goth",
    "gn:population":0,
    "gn:timezone":"Asia/Kathmandu",
    "iso:country":"NP",
    "wof:name":"Raran Goth",
    "wof:placetype":"locality"
},
  "geometry": {"coordinates":[81.46210000000001,29.51114],"type":"Point"}
}