{
  "type": "Feature",
  "properties": {
    "gn:admin1_code":"WR",
    "gn:admin2_code":"4",
    "gn:admin3_code":"40.0",
    "gn:admin4_code":"400007.0",
    "gn:asciiname":"Sabet",
    "gn:country_code":"NP",
    "gn:dem":1728,
    "gn:feature_class":"P",
    "gn:feature_code":"PPLL",
    "gn:name":"Sabet",
    "gn:population":0,
    "gn:timezone":"Asia/Kathmandu",
    "iso:country":"NP",
    "wof:name":"Sabet",
    "wof:placetype":"locality"
},
  "geometry": {"coordinates":[83.74641,28.34057],"type":"Point"}
}