{
  "type": "Feature",
  "properties": {
    "gn:admin1_code":"FR",
    "gn:admin2_code":"14.0",
    "gn:admin3_code":"67.0",
    "gn:admin4_code":"670022.0",
    "gn:asciiname":"Naudakot",
    "gn:country_code":"NP",
    "gn:dem":2046,
    "gn:feature_class":"P",
    "gn:feature_code":"PPLL",
    "gn:name":"Naudakot",
    "gn:population":0,
    "gn:timezone":"Asia/Kathmandu",
    "iso:country":"NP",
    "wof:name":"Naudakot",
    "wof:placetype":"locality"
},
  "geometry": {"coordinates":[81.40857,29.48499],"type":"Point"}
}