{
  "type": "Feature",
  "properties": {
    "gn:admin1_code":"CR",
    "gn:admin2_code":"5",
    "gn:admin3_code":"21",
    "gn:admin4_code":"210021",
    "gn:asciiname":"Chari",
    "gn:country_code":"NP",
    "gn:dem":1781,
    "gn:feature_class":"P",
    "gn:feature_code":"PPLL",
    "gn:name":"Chari",
    "gn:population":0,
    "gn:timezone":"Asia/Kathmandu",
    "iso:country":"NP",
    "name:ceb_x_preferred":[
        "Chari"
    ],
    "name:fin_x_preferred":[
        "Chari"
    ],
    "name:hin_x_preferred":[
        "\u091a\u0930\u0940"
    ],
    "name:ita_x_preferred":[
        "Chari"
    ],
    "wof:name":"Chari",
    "wof:placetype":"locality"
},
  "geometry": {"coordinates":[86.39636999999998,27.59006],"type":"Point"}
}