{
  "type": "Feature",
  "properties": {
    "gn:admin1_code":"FR",
    "gn:admin2_code":"14",
    "gn:admin3_code":"68",
    "gn:admin4_code":"680024",
    "gn:asciiname":"Bhatgaun",
    "gn:country_code":"NP",
    "gn:dem":1472,
    "gn:feature_class":"P",
    "gn:feature_code":"PPLL",
    "gn:name":"Bhatgaun",
    "gn:population":0,
    "gn:timezone":"Asia/Kathmandu",
    "iso:country":"NP",
    "wof:name":"Bhatgaun",
    "wof:placetype":"locality"
},
  "geometry": {"coordinates":[81.03846,29.46735],"type":"Point"}
}