{
  "type": "Feature",
  "properties": {
    "gn:admin1_code":"CR",
    "gn:admin2_code":"5",
    "gn:admin3_code":"19",
    "gn:admin4_code":"190056",
    "gn:asciiname":"Lalbandi",
    "gn:country_code":"NP",
    "gn:dem":154,
    "gn:feature_class":"P",
    "gn:feature_code":"PPLL",
    "gn:name":"Lalbandi",
    "gn:population":0,
    "gn:timezone":"Asia/Kathmandu",
    "iso:country":"NP",
    "name:bih_x_preferred":[
        "\u0932\u093e\u0932\u092c\u0902\u0926\u0940"
    ],
    "name:ceb_x_preferred":[
        "Lalbandi"
    ],
    "name:deu_x_preferred":[
        "Lalbandi"
    ],
    "name:mai_x_preferred":[
        "\u0932\u093e\u0932\u092c\u0928\u094d\u0926\u0940"
    ],
    "name:nep_x_preferred":[
        "\u0932\u093e\u0932\u092c\u0928\u094d\u0926\u0940 \u0928\u0917\u0930\u092a\u093e\u0932\u093f\u0915\u093e"
    ],
    "name:new_x_preferred":[
        "\u0932\u093e\u0932\u092c\u0928\u094d\u0926\u0940"
    ],
    "name:pol_x_preferred":[
        "Lalbandi"
    ],
    "name:urd_x_preferred":[
        "\u0644\u0627\u0644\u0628\u0627\u0646\u0688\u06cc"
    ],
    "wof:name":"Lalbandi",
    "wof:placetype":"locality"
},
  "geometry": {"coordinates":[85.63913000000002,27.05541],"type":"Point"}
}