{
  "type": "Feature",
  "properties": {
    "gn:admin1_code":"ER",
    "gn:admin2_code":"7",
    "gn:admin3_code":"5",
    "gn:admin4_code":"50024.0",
    "gn:asciiname":"Pothiya",
    "gn:country_code":"NP",
    "gn:dem":91,
    "gn:feature_class":"P",
    "gn:feature_code":"PPLL",
    "gn:name":"Pothiya",
    "gn:population":0,
    "gn:timezone":"Asia/Kathmandu",
    "iso:country":"NP",
    "wof:name":"Pothiya",
    "wof:placetype":"locality"
},
  "geometry": {"coordinates":[87.30629,26.56867],"type":"Point"}
}