{
  "type": "Feature",
  "properties": {
    "gn:admin1_code":"WR",
    "gn:admin2_code":"4",
    "gn:admin3_code":"36.0",
    "gn:admin4_code":"360053.0",
    "gn:asciiname":"Tukrang",
    "gn:country_code":"NP",
    "gn:dem":1159,
    "gn:feature_class":"P",
    "gn:feature_code":"PPLL",
    "gn:name":"Tukrang",
    "gn:population":0,
    "gn:timezone":"Asia/Kathmandu",
    "iso:country":"NP",
    "wof:name":"Tukrang",
    "wof:placetype":"locality"
},
  "geometry": {"coordinates":[84.71854,28.15522],"type":"Point"}
}