{
  "type": "Feature",
  "properties": {
    "gn:admin1_code":"CR",
    "gn:admin2_code":"1",
    "gn:admin3_code":"30.0",
    "gn:admin4_code":"300029.0",
    "gn:asciiname":"Jaire",
    "gn:country_code":"NP",
    "gn:dem":773,
    "gn:feature_class":"P",
    "gn:feature_code":"PPLL",
    "gn:name":"Jaire",
    "gn:population":0,
    "gn:timezone":"Asia/Kathmandu",
    "iso:country":"NP",
    "wof:name":"Jaire",
    "wof:placetype":"locality"
},
  "geometry": {"coordinates":[84.78372,27.87519],"type":"Point"}
}