{
  "type": "Feature",
  "properties": {
    "gn:admin1_code":"FR",
    "gn:admin2_code":"14.0",
    "gn:admin3_code":"67.0",
    "gn:admin4_code":"670002.0",
    "gn:asciiname":"Ghattya",
    "gn:country_code":"NP",
    "gn:dem":2411,
    "gn:feature_class":"P",
    "gn:feature_code":"PPLL",
    "gn:name":"Ghattya",
    "gn:population":0,
    "gn:timezone":"Asia/Kathmandu",
    "iso:country":"NP",
    "wof:name":"Ghattya",
    "wof:placetype":"locality"
},
  "geometry": {"coordinates":[81.69365000000001,29.54801],"type":"Point"}
}