{
  "type": "Feature",
  "properties": {
    "gn:admin1_code":"FR",
    "gn:admin2_code":"14",
    "gn:admin3_code":"71.0",
    "gn:admin4_code":"710001.0",
    "gn:asciiname":"Lamki",
    "gn:country_code":"NP",
    "gn:dem":188,
    "gn:feature_class":"P",
    "gn:feature_code":"PPLL",
    "gn:name":"Lamki",
    "gn:population":0,
    "gn:timezone":"Asia/Kathmandu",
    "iso:country":"NP",
    "name:urd_x_preferred":[
        "\u0644\u0627\u0645\u06a9\u06cc"
    ],
    "wof:name":"Lamki",
    "wof:placetype":"locality"
},
  "geometry": {"coordinates":[81.16431999999998,28.62788],"type":"Point"}
}