{
  "type": "Feature",
  "properties": {
    "gn:admin1_code":"MR",
    "gn:admin2_code":"6",
    "gn:admin3_code":"62.0",
    "gn:admin4_code":"620007.0",
    "gn:asciiname":"Bhata Aul",
    "gn:country_code":"NP",
    "gn:dem":1808,
    "gn:feature_class":"P",
    "gn:feature_code":"PPLL",
    "gn:name":"Bhata Aul",
    "gn:population":0,
    "gn:timezone":"Asia/Kathmandu",
    "iso:country":"NP",
    "wof:name":"Bhata Aul",
    "wof:placetype":"locality"
},
  "geometry": {"coordinates":[82.56209,29.02569],"type":"Point"}
}