{
  "type": "Feature",
  "properties": {
    "gn:admin1_code":"FR",
    "gn:admin2_code":"14",
    "gn:admin3_code":"68",
    "gn:admin4_code":"680015",
    "gn:asciiname":"Gauka Chhana",
    "gn:country_code":"NP",
    "gn:dem":2117,
    "gn:feature_class":"P",
    "gn:feature_code":"PPLL",
    "gn:name":"Gauka Chhana",
    "gn:population":0,
    "gn:timezone":"Asia/Kathmandu",
    "iso:country":"NP",
    "wof:name":"Gauka Chhana",
    "wof:placetype":"locality"
},
  "geometry": {"coordinates":[81.2163,29.44917],"type":"Point"}
}