{
  "type": "Feature",
  "properties": {
    "gn:admin1_code":"ER",
    "gn:admin2_code":"13",
    "gn:admin3_code":"13",
    "gn:admin4_code":"130048",
    "gn:asciiname":"Desare",
    "gn:country_code":"NP",
    "gn:dem":1745,
    "gn:feature_class":"P",
    "gn:feature_code":"PPLL",
    "gn:name":"Desare",
    "gn:population":0,
    "gn:timezone":"Asia/Kathmandu",
    "iso:country":"NP",
    "wof:name":"Desare",
    "wof:placetype":"locality"
},
  "geometry": {"coordinates":[86.73265000000001,27.3534],"type":"Point"}
}