{
  "type": "Feature",
  "properties": {
    "gn:admin1_code":"WR",
    "gn:admin2_code":"4.0",
    "gn:admin3_code":"38.0",
    "gn:admin4_code":"380036.0",
    "gn:asciiname":"Gahate",
    "gn:country_code":"NP",
    "gn:dem":683,
    "gn:feature_class":"P",
    "gn:feature_code":"PPLL",
    "gn:name":"Gahate",
    "gn:population":0,
    "gn:timezone":"Asia/Kathmandu",
    "iso:country":"NP",
    "wof:name":"Gahate",
    "wof:placetype":"locality"
},
  "geometry": {"coordinates":[83.97414999999999,28.06606],"type":"Point"}
}