{
  "type": "Feature",
  "properties": {
    "gn:admin1_code":"WR",
    "gn:admin2_code":"3",
    "gn:admin3_code":"45",
    "gn:admin4_code":"450058",
    "gn:asciiname":"Remi",
    "gn:country_code":"NP",
    "gn:dem":1242,
    "gn:feature_class":"P",
    "gn:feature_code":"PPLL",
    "gn:name":"Remi",
    "gn:population":0,
    "gn:timezone":"Asia/Kathmandu",
    "iso:country":"NP",
    "wof:name":"Remi",
    "wof:placetype":"locality"
},
  "geometry": {"coordinates":[83.24836999999999,28.22734],"type":"Point"}
}