{
  "type": "Feature",
  "properties": {
    "gn:admin1_code":"WR",
    "gn:admin2_code":"3",
    "gn:admin3_code":"45",
    "gn:admin4_code":"450058",
    "gn:asciiname":"Remi",
    "gn:country_code":"NP",
    "gn:dem":1242,
    "gn:feature_class":"P",
    "gn:feature_code":"PPLL",
    "gn:name":"Remi",
    "gn:population":0,
    "gn:timezone":"Asia/Kathmandu",
    "iso:country":"NP",
    "name:bre_x_preferred":[
        "Remi"
    ],
    "name:bul_x_preferred":[
        "\u0420\u0435\u043c\u0438"
    ],
    "name:cat_x_preferred":[
        "Rems"
    ],
    "name:cym_x_preferred":[
        "Remi"
    ],
    "name:deu_x_preferred":[
        "Remer"
    ],
    "name:fra_x_preferred":[
        "R\u00e8mes"
    ],
    "name:heb_x_preferred":[
        "\u05e8\u05de\u05d9\u05dd"
    ],
    "name:ind_x_preferred":[
        "Remi"
    ],
    "name:ita_x_preferred":[
        "Remi"
    ],
    "name:kor_x_preferred":[
        "\ub808\ubbf8\uc871"
    ],
    "name:nld_x_preferred":[
        "Remi"
    ],
    "name:pol_x_preferred":[
        "Remowie"
    ],
    "name:por_x_preferred":[
        "Remos"
    ],
    "name:rus_x_preferred":[
        "\u0420\u0435\u043c\u044b"
    ],
    "name:spa_x_preferred":[
        "Remos"
    ],
    "name:zho_x_preferred":[
        "\u96f7\u7c73\u4eba"
    ],
    "wof:name":"Remi",
    "wof:placetype":"locality"
},
  "geometry": {"coordinates":[83.24836999999999,28.22734],"type":"Point"}
}