{
  "type": "Feature",
  "properties": {
    "gn:admin1_code":"CR",
    "gn:admin2_code":"5",
    "gn:admin3_code":"22.0",
    "gn:admin4_code":"220021.0",
    "gn:asciiname":"Dhungeswanra",
    "gn:country_code":"NP",
    "gn:dem":2009,
    "gn:feature_class":"P",
    "gn:feature_code":"PPLL",
    "gn:name":"Dhungeswanra",
    "gn:population":0,
    "gn:timezone":"Asia/Kathmandu",
    "iso:country":"NP",
    "wof:name":"Dhungeswanra",
    "wof:placetype":"locality"
},
  "geometry": {"coordinates":[86.12201999999998,27.55045],"type":"Point"}
}