{
  "type": "Feature",
  "properties": {
    "gn:admin1_code":"WR",
    "gn:admin2_code":"4.0",
    "gn:admin3_code":"38.0",
    "gn:admin4_code":"380037.0",
    "gn:asciiname":"Jhatare",
    "gn:country_code":"NP",
    "gn:dem":433,
    "gn:feature_class":"P",
    "gn:feature_code":"PPLL",
    "gn:name":"Jhatare",
    "gn:population":0,
    "gn:timezone":"Asia/Kathmandu",
    "iso:country":"NP",
    "wof:name":"Jhatare",
    "wof:placetype":"locality"
},
  "geometry": {"coordinates":[84.18037,27.87508],"type":"Point"}
}