{
  "type": "Feature",
  "properties": {
    "gn:admin1_code":"ER",
    "gn:admin2_code":"7",
    "gn:admin3_code":"5",
    "gn:admin4_code":"50021",
    "gn:asciiname":"Mandali Tappu",
    "gn:country_code":"NP",
    "gn:dem":83,
    "gn:feature_class":"P",
    "gn:feature_code":"PPLL",
    "gn:name":"Mandali Tappu",
    "gn:population":0,
    "gn:timezone":"Asia/Kathmandu",
    "iso:country":"NP",
    "wof:name":"Mandali Tappu",
    "wof:placetype":"locality"
},
  "geometry": {"coordinates":[87.57845,26.50926],"type":"Point"}
}