{
  "type": "Feature",
  "properties": {
    "gn:admin1_code":"MR",
    "gn:admin2_code":"2",
    "gn:admin3_code":"60.0",
    "gn:admin4_code":"600035.0",
    "gn:asciiname":"Salleri",
    "gn:country_code":"NP",
    "gn:dem":911,
    "gn:feature_class":"P",
    "gn:feature_code":"PPLL",
    "gn:name":"Salleri",
    "gn:population":0,
    "gn:timezone":"Asia/Kathmandu",
    "iso:country":"NP",
    "name:ceb_x_preferred":[
        "Salleri"
    ],
    "name:deu_x_preferred":[
        "Salleri"
    ],
    "name:pol_x_preferred":[
        "Salleri"
    ],
    "wof:name":"Salleri",
    "wof:placetype":"locality"
},
  "geometry": {"coordinates":[81.70578,28.86348],"type":"Point"}
}