{
  "type": "Feature",
  "properties": {
    "gn:admin1_code":"CR",
    "gn:admin2_code":"5",
    "gn:admin3_code":"22.0",
    "gn:admin4_code":"220032.0",
    "gn:asciiname":"Chisopani",
    "gn:country_code":"NP",
    "gn:dem":2280,
    "gn:feature_class":"P",
    "gn:feature_code":"PPLL",
    "gn:name":"Chisopani",
    "gn:population":0,
    "gn:timezone":"Asia/Kathmandu",
    "iso:country":"NP",
    "wof:name":"Chisopani",
    "wof:placetype":"locality"
},
  "geometry": {"coordinates":[85.94985,27.69743],"type":"Point"}
}