{
  "type": "Feature",
  "properties": {
    "gn:admin1_code":"CR",
    "gn:admin2_code":"11.0",
    "gn:admin3_code":"33.0",
    "gn:admin4_code":"330028.0",
    "gn:asciiname":"Goth",
    "gn:country_code":"NP",
    "gn:dem":101,
    "gn:feature_class":"P",
    "gn:feature_code":"PPLL",
    "gn:name":"Goth",
    "gn:population":0,
    "gn:timezone":"Asia/Kathmandu",
    "iso:country":"NP",
    "wof:name":"Goth",
    "wof:placetype":"locality"
},
  "geometry": {"coordinates":[84.94895,27.08645],"type":"Point"}
}