{
  "type": "Feature",
  "properties": {
    "gn:admin1_code":"CR",
    "gn:admin2_code":"11",
    "gn:admin3_code":"31",
    "gn:admin4_code":"310020",
    "gn:asciiname":"Nyureni",
    "gn:country_code":"NP",
    "gn:dem":456,
    "gn:feature_class":"P",
    "gn:feature_code":"PPLL",
    "gn:name":"Nyureni",
    "gn:population":0,
    "gn:timezone":"Asia/Kathmandu",
    "iso:country":"NP",
    "wof:name":"Nyureni",
    "wof:placetype":"locality"
},
  "geometry": {"coordinates":[85.06744999999999,27.40778],"type":"Point"}
}