{
  "type": "Feature",
  "properties": {
    "gn:admin1_code":"MR",
    "gn:admin2_code":"12",
    "gn:admin3_code":"54",
    "gn:admin4_code":"540004",
    "gn:asciiname":"Chhinkhet",
    "gn:country_code":"NP",
    "gn:dem":1089,
    "gn:feature_class":"P",
    "gn:feature_code":"PPLL",
    "gn:name":"Chhinkhet",
    "gn:population":0,
    "gn:timezone":"Asia/Kathmandu",
    "iso:country":"NP",
    "wof:name":"Chhinkhet",
    "wof:placetype":"locality"
},
  "geometry": {"coordinates":[82.46347,28.6761],"type":"Point"}
}