{
  "type": "Feature",
  "properties": {
    "gn:admin1_code":"ER",
    "gn:admin2_code":"7.0",
    "gn:admin3_code":"10.0",
    "gn:admin4_code":"100001.0",
    "gn:asciiname":"Mukchimala",
    "gn:country_code":"NP",
    "gn:dem":1545,
    "gn:feature_class":"P",
    "gn:feature_code":"PPLL",
    "gn:name":"Mukchimala",
    "gn:population":0,
    "gn:timezone":"Asia/Kathmandu",
    "iso:country":"NP",
    "wof:name":"Mukchimala",
    "wof:placetype":"locality"
},
  "geometry": {"coordinates":[87.07835,27.15899000000001],"type":"Point"}
}