{
  "type": "Feature",
  "properties": {
    "gn:admin1_code":"FR",
    "gn:admin2_code":"14",
    "gn:admin3_code":"70.0",
    "gn:admin4_code":"700028.0",
    "gn:asciiname":"Katelgaun",
    "gn:country_code":"NP",
    "gn:dem":1737,
    "gn:feature_class":"P",
    "gn:feature_code":"PPLL",
    "gn:name":"Katelgaun",
    "gn:population":0,
    "gn:timezone":"Asia/Kathmandu",
    "iso:country":"NP",
    "wof:name":"Katelgaun",
    "wof:placetype":"locality"
},
  "geometry": {"coordinates":[80.94048000000002,29.34265],"type":"Point"}
}