{
  "type": "Feature",
  "properties": {
    "gn:admin1_code":"FR",
    "gn:admin2_code":"9",
    "gn:admin3_code":"73.0",
    "gn:admin4_code":"730013.0",
    "gn:asciiname":"Pipalkot",
    "gn:country_code":"NP",
    "gn:dem":1135,
    "gn:feature_class":"P",
    "gn:feature_code":"PPLL",
    "gn:name":"Pipalkot",
    "gn:population":0,
    "gn:timezone":"Asia/Kathmandu",
    "iso:country":"NP",
    "name:nep_x_preferred":[
        "\u092a\u093f\u092a\u0932\u0915\u094b\u091f"
    ],
    "name:pol_x_preferred":[
        "Pipalkot"
    ],
    "wof:name":"Pipalkot",
    "wof:placetype":"locality"
},
  "geometry": {"coordinates":[80.22372,29.05764000000001],"type":"Point"}
}