{
  "type": "Feature",
  "properties": {
    "gn:admin1_code":"FR",
    "gn:admin2_code":"9",
    "gn:admin3_code":"73.0",
    "gn:admin4_code":"730006.0",
    "gn:asciiname":"Bhakuda",
    "gn:country_code":"NP",
    "gn:dem":1625,
    "gn:feature_class":"P",
    "gn:feature_code":"PPLL",
    "gn:name":"Bhakuda",
    "gn:population":0,
    "gn:timezone":"Asia/Kathmandu",
    "iso:country":"NP",
    "wof:name":"Bhakuda",
    "wof:placetype":"locality"
},
  "geometry": {"coordinates":[80.68970999999998,29.41928],"type":"Point"}
}