{
  "type": "Feature",
  "properties": {
    "gn:country":"NP",
    "gn:fcode":"PPL",
    "gn:population":20284,
    "iso:country":"NP",
    "name:ara_x_preferred":[
        "\u0645\u0627\u0644\u0627\u0646\u063a\u0627\u0648\u0627"
    ],
    "name:bho_x_preferred":[
        "\u092e\u0932\u0902\u0917\u0935\u093e"
    ],
    "name:deu_x_preferred":[
        "Malangwa"
    ],
    "name:eng_x_preferred":[
        "Malangawa"
    ],
    "name:fra_x_preferred":[
        "Malangwa"
    ],
    "name:jpn_x_preferred":[
        "\u30de\u30e9\u30f3\u30ac\u30ef"
    ],
    "name:mai_x_preferred":[
        "\u092e\u0932\u0919\u094d\u0935\u093e \u0928\u0917\u0930\u092a\u093e\u0932\u093f\u0915\u093e"
    ],
    "name:nep_x_preferred":[
        "Mala\u1e45gaw\u0101"
    ],
    "name:nep_x_variant":[
        "\u092e\u0932\u0902\u0917\u0935\u093e \u0928\u0917\u0930\u092a\u093e\u0932\u093f\u0915\u093e"
    ],
    "name:new_x_preferred":[
        "\u092e\u0932\u0919\u0935\u093e \u0928\u0917\u0930\u092a\u093e\u0932\u093f\u0915\u093e"
    ],
    "name:nld_x_preferred":[
        "Malangwa"
    ],
    "name:pol_x_preferred":[
        "Malangawa"
    ],
    "name:por_x_preferred":[
        "Malangwa"
    ],
    "name:rus_x_preferred":[
        "\u041c\u0430\u043b\u0430\u043d\u0433\u0432\u0430"
    ],
    "name:ukr_x_preferred":[
        "\u041c\u0430\u043b\u0430\u043d\u0433\u0432\u0430"
    ],
    "name:und_x_variant":[
        "Malankwa"
    ],
    "name:urd_x_preferred":[
        "\u0645\u0644\u0646\u06af\u0648\u0627"
    ],
    "name:zho_x_preferred":[
        "\u9ed8\u502b\u74dc"
    ],
    "qs:name":"Malangwa",
    "qs:photos_9r":0,
    "qs:photos_sr":0,
    "qs:pop_sr":"7",
    "wd:wordcount":1001,
    "wof:name":"Malangwa",
    "wof:placetype":"locality",
    "wof:population":20284
},
  "geometry": {"coordinates":[85.55811,26.85679],"type":"Point"}
}