{
  "type": "Feature",
  "properties": {
    "gn:admin1_code":"MR",
    "gn:admin2_code":"2.0",
    "gn:admin3_code":"57.0",
    "gn:admin4_code":"570010.0",
    "gn:asciiname":"Patharaiya",
    "gn:country_code":"NP",
    "gn:dem":157,
    "gn:feature_class":"P",
    "gn:feature_code":"PPLL",
    "gn:name":"Patharaiya",
    "gn:population":0,
    "gn:timezone":"Asia/Kathmandu",
    "iso:country":"NP",
    "wof:name":"Patharaiya",
    "wof:placetype":"locality"
},
  "geometry": {"coordinates":[81.8507,28.05131],"type":"Point"}
}