{
  "type": "Feature",
  "properties": {
    "gn:admin1_code":"MR",
    "gn:admin2_code":"2",
    "gn:admin3_code":"60.0",
    "gn:admin4_code":"600034.0",
    "gn:asciiname":"Paduka",
    "gn:country_code":"NP",
    "gn:dem":1814,
    "gn:feature_class":"P",
    "gn:feature_code":"PPLL",
    "gn:name":"Paduka",
    "gn:population":0,
    "gn:timezone":"Asia/Kathmandu",
    "iso:country":"NP",
    "name:ben_x_preferred":[
        "\u0996\u09a1\u09bc\u09ae"
    ],
    "name:fra_x_preferred":[
        "Paduka"
    ],
    "name:ita_x_preferred":[
        "Paduka"
    ],
    "name:mal_x_preferred":[
        "\u0d2e\u0d46\u0d24\u0d3f\u0d2f\u0d1f\u0d3f"
    ],
    "name:rus_x_preferred":[
        "\u041f\u0430\u0434\u0443\u043a\u0430"
    ],
    "wof:name":"Paduka",
    "wof:placetype":"locality"
},
  "geometry": {"coordinates":[81.86532,28.83201],"type":"Point"}
}