{
  "type": "Feature",
  "properties": {
    "gn:admin1_code":"ER",
    "gn:admin2_code":"10",
    "gn:admin3_code":"2",
    "gn:admin4_code":"20010",
    "gn:asciiname":"Jaringe",
    "gn:country_code":"NP",
    "gn:dem":2041,
    "gn:feature_class":"P",
    "gn:feature_code":"PPLL",
    "gn:name":"Jaringe",
    "gn:population":0,
    "gn:timezone":"Asia/Kathmandu",
    "iso:country":"NP",
    "wof:name":"Jaringe",
    "wof:placetype":"locality"
},
  "geometry": {"coordinates":[87.89346,27.21902],"type":"Point"}
}