{
  "type": "Feature",
  "properties": {
    "gn:admin1_code":"WR",
    "gn:admin2_code":"8",
    "gn:admin3_code":"48",
    "gn:admin4_code":"480010",
    "gn:asciiname":"Dandathok",
    "gn:country_code":"NP",
    "gn:dem":777,
    "gn:feature_class":"P",
    "gn:feature_code":"PPLL",
    "gn:name":"Dandathok",
    "gn:population":0,
    "gn:timezone":"Asia/Kathmandu",
    "iso:country":"NP",
    "wof:name":"Dandathok",
    "wof:placetype":"locality"
},
  "geometry": {"coordinates":[84.19535999999999,27.8149],"type":"Point"}
}