{
  "type": "Feature",
  "properties": {
    "gn:admin1_code":"MR",
    "gn:admin2_code":"12",
    "gn:admin3_code":"53",
    "gn:admin4_code":"530008",
    "gn:asciiname":"Tallo Kewari",
    "gn:country_code":"NP",
    "gn:dem":1556,
    "gn:feature_class":"P",
    "gn:feature_code":"PPLL",
    "gn:name":"Tallo Kewari",
    "gn:population":0,
    "gn:timezone":"Asia/Kathmandu",
    "iso:country":"NP",
    "wof:name":"Tallo Kewari",
    "wof:placetype":"locality"
},
  "geometry": {"coordinates":[82.51846999999999,28.48423],"type":"Point"}
}