{
  "type": "Feature",
  "properties": {
    "gn:admin1_code":"CR",
    "gn:admin2_code":"5",
    "gn:admin3_code":"18",
    "gn:admin4_code":"180043",
    "gn:asciiname":"Laksmipur",
    "gn:country_code":"NP",
    "gn:dem":85,
    "gn:feature_class":"P",
    "gn:feature_code":"PPLL",
    "gn:name":"Laksmipur",
    "gn:population":0,
    "gn:timezone":"Asia/Kathmandu",
    "iso:country":"NP",
    "wof:name":"Laksmipur",
    "wof:placetype":"locality"
},
  "geometry": {"coordinates":[85.89126999999998,26.77907],"type":"Point"}
}