{
  "type": "Feature",
  "properties": {
    "gn:admin1_code":"WR",
    "gn:admin2_code":"4",
    "gn:admin3_code":"37",
    "gn:admin4_code":"370055",
    "gn:asciiname":"Suryapal",
    "gn:country_code":"NP",
    "gn:dem":840,
    "gn:feature_class":"P",
    "gn:feature_code":"PPLL",
    "gn:name":"Suryapal",
    "gn:population":0,
    "gn:timezone":"Asia/Kathmandu",
    "iso:country":"NP",
    "name:fra_x_preferred":[
        "Suryapal"
    ],
    "name:msa_x_preferred":[
        "Suryapal"
    ],
    "name:nep_x_preferred":[
        "\u0938\u0942\u0930\u094d\u092f\u092a\u093e\u0932"
    ],
    "name:new_x_preferred":[
        "\u0938\u0941\u0930\u094d\u092f\u092a\u093e\u0932"
    ],
    "name:pol_x_preferred":[
        "Suryapal"
    ],
    "wof:name":"Suryapal",
    "wof:placetype":"locality"
},
  "geometry": {"coordinates":[84.25958,28.12101],"type":"Point"}
}