{
  "type": "Feature",
  "properties": {
    "gn:admin1_code":"CR",
    "gn:admin2_code":"1",
    "gn:admin3_code":"25",
    "gn:admin4_code":"250002",
    "gn:asciiname":"Majhgaun",
    "gn:country_code":"NP",
    "gn:dem":1767,
    "gn:feature_class":"P",
    "gn:feature_code":"PPLL",
    "gn:name":"Majhgaun",
    "gn:population":0,
    "gn:timezone":"Asia/Kathmandu",
    "iso:country":"NP",
    "wof:name":"Majhgaun",
    "wof:placetype":"locality"
},
  "geometry": {"coordinates":[85.36396999999999,27.58536],"type":"Point"}
}