{
  "type": "Feature",
  "properties": {
    "gn:admin1_code":"00",
    "gn:asciiname":"Pachtale",
    "gn:country_code":"NP",
    "gn:dem":202,
    "gn:feature_class":"P",
    "gn:feature_code":"PPL",
    "gn:name":"P\u0101\u0303chtale",
    "gn:population":0,
    "gn:timezone":"Asia/Kathmandu",
    "iso:country":"NP",
    "name:nep_x_preferred":[
        "P\u0101\u0303chtale"
    ],
    "wof:name":"Pachtale",
    "wof:placetype":"locality"
},
  "geometry": {"coordinates":[86.53622,26.81349],"type":"Point"}
}