{
  "type": "Feature",
  "properties": {
    "gn:admin1_code":"CR",
    "gn:admin2_code":"11",
    "gn:admin3_code":"35.0",
    "gn:admin4_code":"350020.0",
    "gn:asciiname":"Jyandala",
    "gn:country_code":"NP",
    "gn:dem":1527,
    "gn:feature_class":"P",
    "gn:feature_code":"PPLL",
    "gn:name":"Jyandala",
    "gn:population":0,
    "gn:timezone":"Asia/Kathmandu",
    "iso:country":"NP",
    "wof:name":"Jyandala",
    "wof:placetype":"locality"
},
  "geometry": {"coordinates":[84.63405,27.75783],"type":"Point"}
}