{
  "type": "Feature",
  "properties": {
    "gn:admin1_code":"ER",
    "gn:admin2_code":"13",
    "gn:admin3_code":"12",
    "gn:admin4_code":"120049",
    "gn:asciiname":"Devitar",
    "gn:country_code":"NP",
    "gn:dem":1444,
    "gn:feature_class":"P",
    "gn:feature_code":"PPLL",
    "gn:name":"Devitar",
    "gn:population":0,
    "gn:timezone":"Asia/Kathmandu",
    "iso:country":"NP",
    "name:bih_x_preferred":[
        "\u0926\u0947\u0935\u0940\u091f\u093e\u0930"
    ],
    "name:ceb_x_preferred":[
        "Devitar"
    ],
    "name:fra_x_preferred":[
        "Devitar"
    ],
    "name:mai_x_preferred":[
        "\u0926\u0947\u0935\u0940\u091f\u093e\u0930"
    ],
    "name:msa_x_preferred":[
        "Devitar"
    ],
    "name:nep_x_preferred":[
        "\u0926\u0947\u0935\u0940\u091f\u093e\u0930"
    ],
    "name:new_x_preferred":[
        "\u0926\u0947\u0935\u0940\u091f\u093e\u0930"
    ],
    "name:pol_x_preferred":[
        "Devitar"
    ],
    "wof:name":"Devitar",
    "wof:placetype":"locality"
},
  "geometry": {"coordinates":[86.37233000000001,27.2603],"type":"Point"}
}