{
  "type": "Feature",
  "properties": {
    "gn:admin1_code":"FR",
    "gn:admin2_code":"9",
    "gn:admin3_code":"75.0",
    "gn:admin4_code":"750026.0",
    "gn:asciiname":"Kimtad",
    "gn:country_code":"NP",
    "gn:dem":842,
    "gn:feature_class":"P",
    "gn:feature_code":"PPLL",
    "gn:name":"Kimtad",
    "gn:population":0,
    "gn:timezone":"Asia/Kathmandu",
    "iso:country":"NP",
    "wof:name":"Kimtad",
    "wof:placetype":"locality"
},
  "geometry": {"coordinates":[80.39655999999999,29.67598],"type":"Point"}
}