{
  "type": "Feature",
  "properties": {
    "gn:admin1_code":"FR",
    "gn:admin2_code":"14",
    "gn:admin3_code":"71.0",
    "gn:admin4_code":"710014.0",
    "gn:asciiname":"Margaht",
    "gn:country_code":"NP",
    "gn:dem":188,
    "gn:feature_class":"P",
    "gn:feature_code":"PPLL",
    "gn:name":"Margaht",
    "gn:population":0,
    "gn:timezone":"Asia/Kathmandu",
    "iso:country":"NP",
    "wof:name":"Margaht",
    "wof:placetype":"locality"
},
  "geometry": {"coordinates":[80.55344000000002,28.76789],"type":"Point"}
}