{
  "type": "Feature",
  "properties": {
    "gn:admin1_code":"MR",
    "gn:admin2_code":"2.0",
    "gn:admin3_code":"57.0",
    "gn:admin4_code":"570027.0",
    "gn:asciiname":"Obhari (Baikunthapur)",
    "gn:country_code":"NP",
    "gn:dem":176,
    "gn:feature_class":"P",
    "gn:feature_code":"PPLL",
    "gn:name":"Obhari (Baikunthapur)",
    "gn:population":0,
    "gn:timezone":"Asia/Kathmandu",
    "iso:country":"NP",
    "wof:name":"Obhari (Baikunthapur)",
    "wof:placetype":"locality"
},
  "geometry": {"coordinates":[81.8128,28.12914],"type":"Point"}
}