{
  "type": "Feature",
  "properties": {
    "gn:admin1_code":"00",
    "gn:asciiname":"Pasandhara",
    "gn:country_code":"NP",
    "gn:dem":2610,
    "gn:feature_class":"P",
    "gn:feature_code":"PPL",
    "gn:name":"P\u0101s\u0101ndh\u0101ra",
    "gn:population":0,
    "gn:timezone":"Asia/Kathmandu",
    "iso:country":"NP",
    "wof:name":"Pasandhara",
    "wof:placetype":"locality"
},
  "geometry": {"coordinates":[82.66918000000003,28.76993],"type":"Point"}
}