{
  "type": "Feature",
  "properties": {
    "gn:admin1_code":"ER",
    "gn:admin2_code":"7",
    "gn:admin3_code":"9",
    "gn:admin4_code":"90025",
    "gn:asciiname":"Talkharka",
    "gn:country_code":"NP",
    "gn:dem":1982,
    "gn:feature_class":"P",
    "gn:feature_code":"PPLL",
    "gn:name":"Talkharka",
    "gn:population":0,
    "gn:timezone":"Asia/Kathmandu",
    "iso:country":"NP",
    "wof:name":"Talkharka",
    "wof:placetype":"locality"
},
  "geometry": {"coordinates":[87.37891,27.6603],"type":"Point"}
}