{
  "type": "Feature",
  "properties": {
    "gn:admin1_code":"WR",
    "gn:admin2_code":"8",
    "gn:admin3_code":"46.0",
    "gn:admin4_code":"460072.0",
    "gn:asciiname":"Phalamedanda",
    "gn:country_code":"NP",
    "gn:dem":1341,
    "gn:feature_class":"P",
    "gn:feature_code":"PPLL",
    "gn:name":"Phalamedanda",
    "gn:population":0,
    "gn:timezone":"Asia/Kathmandu",
    "iso:country":"NP",
    "wof:name":"Phalamedanda",
    "wof:placetype":"locality"
},
  "geometry": {"coordinates":[83.24243,28.02827000000001],"type":"Point"}
}