{
  "type": "Feature",
  "properties": {
    "gn:admin1_code":"ER",
    "gn:admin2_code":"10",
    "gn:admin3_code":"3.0",
    "gn:admin4_code":"30036.0",
    "gn:asciiname":"Musedanda",
    "gn:country_code":"NP",
    "gn:dem":1945,
    "gn:feature_class":"P",
    "gn:feature_code":"PPLL",
    "gn:name":"Musedanda",
    "gn:population":0,
    "gn:timezone":"Asia/Kathmandu",
    "iso:country":"NP",
    "wof:name":"Musedanda",
    "wof:placetype":"locality"
},
  "geometry": {"coordinates":[87.88484,27.02366],"type":"Point"}
}