{
  "type": "Feature",
  "properties": {
    "gn:admin1_code":"MR",
    "gn:admin2_code":"2",
    "gn:admin3_code":"61.0",
    "gn:admin4_code":"610004.0",
    "gn:asciiname":"Guarna",
    "gn:country_code":"NP",
    "gn:dem":2244,
    "gn:feature_class":"P",
    "gn:feature_code":"PPLL",
    "gn:name":"Guarna",
    "gn:population":0,
    "gn:timezone":"Asia/Kathmandu",
    "iso:country":"NP",
    "wof:name":"Guarna",
    "wof:placetype":"locality"
},
  "geometry": {"coordinates":[81.91678,28.85025],"type":"Point"}
}