{
  "type": "Feature",
  "properties": {
    "gn:admin1_code":"WR",
    "gn:admin2_code":"3",
    "gn:admin3_code":"45.0",
    "gn:admin4_code":"450013.0",
    "gn:asciiname":"Bagdur",
    "gn:country_code":"NP",
    "gn:dem":2334,
    "gn:feature_class":"P",
    "gn:feature_code":"PPLL",
    "gn:name":"Bagdur",
    "gn:population":0,
    "gn:timezone":"Asia/Kathmandu",
    "iso:country":"NP",
    "wof:name":"Bagdur",
    "wof:placetype":"locality"
},
  "geometry": {"coordinates":[83.08884999999999,28.41903],"type":"Point"}
}