{
  "type": "Feature",
  "properties": {
    "gn:admin1_code":"FR",
    "gn:admin2_code":"14",
    "gn:admin3_code":"70.0",
    "gn:admin4_code":"700013.0",
    "gn:asciiname":"Mathillo Sirkholi",
    "gn:country_code":"NP",
    "gn:dem":865,
    "gn:feature_class":"P",
    "gn:feature_code":"PPLL",
    "gn:name":"Mathillo Sirkholi",
    "gn:population":0,
    "gn:timezone":"Asia/Kathmandu",
    "iso:country":"NP",
    "wof:name":"Mathillo Sirkholi",
    "wof:placetype":"locality"
},
  "geometry": {"coordinates":[80.90589,29.27373],"type":"Point"}
}