{
  "type": "Feature",
  "properties": {
    "gn:admin1_code":"WR",
    "gn:admin2_code":"4",
    "gn:admin3_code":"40.0",
    "gn:admin4_code":"400004.0",
    "gn:asciiname":"Thulakhet",
    "gn:country_code":"NP",
    "gn:dem":884,
    "gn:feature_class":"P",
    "gn:feature_code":"PPLL",
    "gn:name":"Thulakhet",
    "gn:population":0,
    "gn:timezone":"Asia/Kathmandu",
    "iso:country":"NP",
    "wof:name":"Thulakhet",
    "wof:placetype":"locality"
},
  "geometry": {"coordinates":[83.87111,28.24827],"type":"Point"}
}