{
  "type": "Feature",
  "properties": {
    "gn:admin1_code":"MR",
    "gn:admin2_code":"6",
    "gn:admin3_code":"62.0",
    "gn:admin4_code":"620018.0",
    "gn:asciiname":"Rupa",
    "gn:country_code":"NP",
    "gn:dem":2700,
    "gn:feature_class":"P",
    "gn:feature_code":"PPLL",
    "gn:name":"Rupa",
    "gn:population":0,
    "gn:timezone":"Asia/Kathmandu",
    "iso:country":"NP",
    "wof:name":"Rupa",
    "wof:placetype":"locality"
},
  "geometry": {"coordinates":[83.00058,28.86597],"type":"Point"}
}