{
  "type": "Feature",
  "properties": {
    "gn:admin1_code":"CR",
    "gn:admin2_code":"1",
    "gn:admin3_code":"24.0",
    "gn:admin4_code":"240002.0",
    "gn:asciiname":"Majhtol",
    "gn:country_code":"NP",
    "gn:dem":1452,
    "gn:feature_class":"P",
    "gn:feature_code":"PPLL",
    "gn:name":"Majhtol",
    "gn:population":0,
    "gn:timezone":"Asia/Kathmandu",
    "iso:country":"NP",
    "wof:name":"Majhtol",
    "wof:placetype":"locality"
},
  "geometry": {"coordinates":[85.54789,27.55744],"type":"Point"}
}