{
  "type": "Feature",
  "properties": {
    "gn:admin1_code":"MR",
    "gn:admin2_code":"2",
    "gn:admin3_code":"61.0",
    "gn:admin4_code":"610011.0",
    "gn:asciiname":"Badikati",
    "gn:country_code":"NP",
    "gn:dem":1738,
    "gn:feature_class":"P",
    "gn:feature_code":"PPLL",
    "gn:name":"Badikati",
    "gn:population":0,
    "gn:timezone":"Asia/Kathmandu",
    "iso:country":"NP",
    "wof:name":"Badikati",
    "wof:placetype":"locality"
},
  "geometry": {"coordinates":[81.90642,28.71694],"type":"Point"}
}