{
  "type": "Feature",
  "properties": {
    "gn:admin1_code":"CR",
    "gn:admin2_code":"1",
    "gn:admin3_code":"25",
    "gn:admin4_code":"250029.0",
    "gn:asciiname":"Bhaise",
    "gn:country_code":"NP",
    "gn:dem":1595,
    "gn:feature_class":"P",
    "gn:feature_code":"PPLL",
    "gn:name":"Bhaise",
    "gn:population":0,
    "gn:timezone":"Asia/Kathmandu",
    "iso:country":"NP",
    "wof:name":"Bhaise",
    "wof:placetype":"locality"
},
  "geometry": {"coordinates":[85.31033000000002,27.56366],"type":"Point"}
}