{
  "type": "Feature",
  "properties": {
    "gn:admin1_code":"CR",
    "gn:admin2_code":"5",
    "gn:admin3_code":"19",
    "gn:admin4_code":"190053",
    "gn:asciiname":"Khutauna",
    "gn:country_code":"NP",
    "gn:dem":80,
    "gn:feature_class":"P",
    "gn:feature_code":"PPLL",
    "gn:name":"Khutauna",
    "gn:population":0,
    "gn:timezone":"Asia/Kathmandu",
    "iso:country":"NP",
    "name:bih_x_preferred":[
        "\u0916\u0941\u091f\u094c\u0928\u093e"
    ],
    "name:nep_x_preferred":[
        "\u0916\u0941\u091f\u094c\u0928\u093e"
    ],
    "name:new_x_preferred":[
        "\u0916\u0941\u091f\u094c\u0928\u093e"
    ],
    "name:pol_x_preferred":[
        "Khutauna"
    ],
    "wof:name":"Khutauna",
    "wof:placetype":"locality"
},
  "geometry": {"coordinates":[85.53336999999998,26.8308],"type":"Point"}
}