{
  "type": "Feature",
  "properties": {
    "gn:admin1_code":"WR",
    "gn:admin2_code":"8",
    "gn:admin3_code":"47",
    "gn:admin4_code":"470040",
    "gn:asciiname":"Jaluke",
    "gn:country_code":"NP",
    "gn:dem":1227,
    "gn:feature_class":"P",
    "gn:feature_code":"PPLL",
    "gn:name":"Jaluke",
    "gn:population":0,
    "gn:timezone":"Asia/Kathmandu",
    "iso:country":"NP",
    "wof:name":"Jaluke",
    "wof:placetype":"locality"
},
  "geometry": {"coordinates":[83.48439999999999,27.88993],"type":"Point"}
}