{
  "type": "Feature",
  "properties": {
    "gn:admin1_code":"CR",
    "gn:admin2_code":"5",
    "gn:admin3_code":"22.0",
    "gn:admin4_code":"220049.0",
    "gn:asciiname":"Puchharkharka",
    "gn:country_code":"NP",
    "gn:dem":2152,
    "gn:feature_class":"P",
    "gn:feature_code":"PPLL",
    "gn:name":"Puchharkharka",
    "gn:population":0,
    "gn:timezone":"Asia/Kathmandu",
    "iso:country":"NP",
    "wof:name":"Puchharkharka",
    "wof:placetype":"locality"
},
  "geometry": {"coordinates":[86.22103,27.71692],"type":"Point"}
}