{
  "type": "Feature",
  "properties": {
    "gn:admin1_code":"CR",
    "gn:admin2_code":"5",
    "gn:admin3_code":"20",
    "gn:admin4_code":"200004",
    "gn:asciiname":"Bhangredhik",
    "gn:country_code":"NP",
    "gn:dem":782,
    "gn:feature_class":"P",
    "gn:feature_code":"PPLL",
    "gn:name":"Bhangredhik",
    "gn:population":0,
    "gn:timezone":"Asia/Kathmandu",
    "iso:country":"NP",
    "wof:name":"Bhangredhik",
    "wof:placetype":"locality"
},
  "geometry": {"coordinates":[86.13412,27.16191],"type":"Point"}
}