{
  "type": "Feature",
  "properties": {
    "gn:admin1_code":"CR",
    "gn:admin2_code":"5",
    "gn:admin3_code":"22.0",
    "gn:admin4_code":"220013.0",
    "gn:asciiname":"Kabreswanra",
    "gn:country_code":"NP",
    "gn:dem":1598,
    "gn:feature_class":"P",
    "gn:feature_code":"PPLL",
    "gn:name":"Kabreswanra",
    "gn:population":0,
    "gn:timezone":"Asia/Kathmandu",
    "iso:country":"NP",
    "wof:name":"Kabreswanra",
    "wof:placetype":"locality"
},
  "geometry": {"coordinates":[86.14048000000003,27.52969],"type":"Point"}
}