{
  "type": "Feature",
  "properties": {
    "iso:country":"NP",
    "name:unk_x_variant":[
        "Char Pargana"
    ],
    "qs:gn_country":"NP",
    "qs:gn_fcode":"ADM3",
    "qs:gn_pop":613253,
    "qs:name":"Sirha",
    "qs:name_adm0":"Nepal",
    "qs:name_adm1":"Purwanchal",
    "qs:photos":0,
    "qs:photos_1k":0,
    "qs:photos_9k":0,
    "qs:photos_9r":0,
    "qs:photos_all":0,
    "qs:photos_sr":0,
    "qs:placetype":"Town",
    "qs:pop_sr":"11",
    "qs:woe_adm0":23424911,
    "wof:name":"Sirha",
    "wof:placetype":"locality",
    "wof:population":613253
},
  "geometry": {"coordinates":[86.33333,26.75],"type":"Point"}
}