{
  "type": "Feature",
  "properties": {
    "gn:admin1_code":"WR",
    "gn:admin2_code":"4",
    "gn:admin3_code":"37",
    "gn:admin4_code":"370051",
    "gn:asciiname":"Kamrakhu",
    "gn:country_code":"NP",
    "gn:dem":861,
    "gn:feature_class":"P",
    "gn:feature_code":"PPLL",
    "gn:name":"Kamrakhu",
    "gn:population":0,
    "gn:timezone":"Asia/Kathmandu",
    "iso:country":"NP",
    "wof:name":"Kamrakhu",
    "wof:placetype":"locality"
},
  "geometry": {"coordinates":[84.4631,28.18593],"type":"Point"}
}