{
  "type": "Feature",
  "properties": {
    "gn:admin1_code":"WR",
    "gn:admin2_code":"4.0",
    "gn:admin3_code":"38.0",
    "gn:admin4_code":"380019.0",
    "gn:asciiname":"Mandre Bajar",
    "gn:country_code":"NP",
    "gn:dem":549,
    "gn:feature_class":"P",
    "gn:feature_code":"PPLL",
    "gn:name":"Mandre Bajar",
    "gn:population":0,
    "gn:timezone":"Asia/Kathmandu",
    "iso:country":"NP",
    "wof:name":"Mandre Bajar",
    "wof:placetype":"locality"
},
  "geometry": {"coordinates":[84.03335,28.03871],"type":"Point"}
}