{
  "type": "Feature",
  "properties": {
    "gn:admin1_code":"MR",
    "gn:admin2_code":"2.0",
    "gn:admin3_code":"59.0",
    "gn:admin4_code":"590018.0",
    "gn:asciiname":"Tata",
    "gn:country_code":"NP",
    "gn:dem":944,
    "gn:feature_class":"P",
    "gn:feature_code":"PPLL",
    "gn:name":"Tata",
    "gn:population":0,
    "gn:timezone":"Asia/Kathmandu",
    "iso:country":"NP",
    "name:ara_x_preferred":[
        "\u062a\u0627\u062a\u0627"
    ],
    "name:cat_x_preferred":[
        "Tata"
    ],
    "name:ceb_x_preferred":[
        "Tata"
    ],
    "name:deu_x_preferred":[
        "Tata"
    ],
    "name:epo_x_preferred":[
        "Tata"
    ],
    "name:fas_x_preferred":[
        "\u062a\u0627\u062a\u0627"
    ],
    "name:fra_x_preferred":[
        "Tata"
    ],
    "name:heb_x_preferred":[
        "\u05d8\u05d8\u05d4"
    ],
    "name:ita_x_preferred":[
        "Tata"
    ],
    "name:lit_x_preferred":[
        "Tata"
    ],
    "name:nld_x_preferred":[
        "Tata"
    ],
    "name:nor_x_preferred":[
        "Tata"
    ],
    "name:pol_x_preferred":[
        "Tata"
    ],
    "name:por_x_preferred":[
        "Tata"
    ],
    "name:ron_x_preferred":[
        "Tata"
    ],
    "name:rus_x_preferred":[
        "\u0422\u0430\u0442\u0430"
    ],
    "name:slk_x_preferred":[
        "Tata"
    ],
    "name:spa_x_preferred":[
        "Tata"
    ],
    "name:swe_x_preferred":[
        "Tata"
    ],
    "name:tam_x_preferred":[
        "\u0b9f\u0bbe\u0b9f\u0bcd\u0b9f\u0bbe"
    ],
    "name:tha_x_preferred":[
        "\u0e17\u0e32\u0e17\u0e32"
    ],
    "name:tur_x_preferred":[
        "Tata"
    ],
    "name:ukr_x_preferred":[
        "Tata"
    ],
    "name:uzb_x_preferred":[
        "Tata"
    ],
    "wof:name":"Tata",
    "wof:placetype":"locality"
},
  "geometry": {"coordinates":[81.9246,28.61439],"type":"Point"}
}