{
  "type": "Feature",
  "properties": {
    "gn:admin1_code":"MR",
    "gn:admin2_code":"2.0",
    "gn:admin3_code":"58.0",
    "gn:admin4_code":"580001.0",
    "gn:asciiname":"Jogipur",
    "gn:country_code":"NP",
    "gn:dem":151,
    "gn:feature_class":"P",
    "gn:feature_code":"PPLL",
    "gn:name":"Jogipur",
    "gn:population":0,
    "gn:timezone":"Asia/Kathmandu",
    "iso:country":"NP",
    "wof:name":"Jogipur",
    "wof:placetype":"locality"
},
  "geometry": {"coordinates":[81.15343,28.43892],"type":"Point"}
}