{
  "type": "Feature",
  "properties": {
    "gn:admin1_code":"ER",
    "gn:admin2_code":"13",
    "gn:admin3_code":"13",
    "gn:admin4_code":"130045",
    "gn:asciiname":"Lamidanda Bhanjyang",
    "gn:country_code":"NP",
    "gn:dem":1217,
    "gn:feature_class":"P",
    "gn:feature_code":"PPLL",
    "gn:name":"Lamidanda Bhanjyang",
    "gn:population":0,
    "gn:timezone":"Asia/Kathmandu",
    "iso:country":"NP",
    "wof:name":"Lamidanda Bhanjyang",
    "wof:placetype":"locality"
},
  "geometry": {"coordinates":[86.69230999999998,27.25005],"type":"Point"}
}