{
  "type": "Feature",
  "properties": {
    "gn:admin1_code":"CR",
    "gn:admin2_code":"1",
    "gn:admin3_code":"25",
    "gn:admin4_code":"250023",
    "gn:asciiname":"Bistagaun",
    "gn:country_code":"NP",
    "gn:dem":1299,
    "gn:feature_class":"P",
    "gn:feature_code":"PPLL",
    "gn:name":"Bistagaun",
    "gn:population":0,
    "gn:timezone":"Asia/Kathmandu",
    "iso:country":"NP",
    "wof:name":"Bistagaun",
    "wof:placetype":"locality"
},
  "geometry": {"coordinates":[85.35434000000002,27.66398],"type":"Point"}
}