{
  "type": "Feature",
  "properties": {
    "gn:admin1_code":"CR",
    "gn:admin2_code":"5",
    "gn:admin3_code":"17.0",
    "gn:admin4_code":"170012.0",
    "gn:asciiname":"Dumariya",
    "gn:country_code":"NP",
    "gn:dem":111,
    "gn:feature_class":"P",
    "gn:feature_code":"PPLL",
    "gn:name":"Dumariya",
    "gn:population":0,
    "gn:timezone":"Asia/Kathmandu",
    "iso:country":"NP",
    "name:ceb_x_preferred":[
        "Dumariya"
    ],
    "name:fra_x_preferred":[
        "Dumariya"
    ],
    "name:mai_x_preferred":[
        "\u0921\u0941\u092e\u092e\u0940\u092f\u093e"
    ],
    "name:nep_x_preferred":[
        "\u0926\u0941\u092e\u0930\u093f\u092f\u093e"
    ],
    "name:new_x_preferred":[
        "\u0926\u0941\u092e\u0930\u093f\u092f\u093e"
    ],
    "name:pol_x_preferred":[
        "Dumariya"
    ],
    "wof:name":"Dumariya",
    "wof:placetype":"locality"
},
  "geometry": {"coordinates":[86.11751,26.85385],"type":"Point"}
}