{
  "type": "Feature",
  "properties": {
    "gn:admin1_code":"MR",
    "gn:admin2_code":"12",
    "gn:admin3_code":"55",
    "gn:admin4_code":"550012",
    "gn:asciiname":"Birai Khoriya",
    "gn:country_code":"NP",
    "gn:dem":1511,
    "gn:feature_class":"P",
    "gn:feature_code":"PPLL",
    "gn:name":"Birai Khoriya",
    "gn:population":0,
    "gn:timezone":"Asia/Kathmandu",
    "iso:country":"NP",
    "wof:name":"Birai Khoriya",
    "wof:placetype":"locality"
},
  "geometry": {"coordinates":[82.35256,28.54208],"type":"Point"}
}