{
  "type": "Feature",
  "properties": {
    "gn:admin1_code":"FR",
    "gn:admin2_code":"9",
    "gn:admin3_code":"74",
    "gn:admin4_code":"740027",
    "gn:asciiname":"Tham",
    "gn:country_code":"NP",
    "gn:dem":1736,
    "gn:feature_class":"P",
    "gn:feature_code":"PPLL",
    "gn:name":"Tham",
    "gn:population":0,
    "gn:timezone":"Asia/Kathmandu",
    "iso:country":"NP",
    "wof:name":"Tham",
    "wof:placetype":"locality"
},
  "geometry": {"coordinates":[80.52435,29.39977],"type":"Point"}
}