{
  "type": "Feature",
  "properties": {
    "gn:admin1_code":"MR",
    "gn:admin2_code":"2.0",
    "gn:admin3_code":"59.0",
    "gn:admin4_code":"590009.0",
    "gn:asciiname":"Lekkhet",
    "gn:country_code":"NP",
    "gn:dem":1091,
    "gn:feature_class":"P",
    "gn:feature_code":"PPLL",
    "gn:name":"Lekkhet",
    "gn:population":0,
    "gn:timezone":"Asia/Kathmandu",
    "iso:country":"NP",
    "wof:name":"Lekkhet",
    "wof:placetype":"locality"
},
  "geometry": {"coordinates":[81.43831999999998,28.85906],"type":"Point"}
}