{
  "type": "Feature",
  "properties": {
    "gn:admin1_code":"CR",
    "gn:admin2_code":"1",
    "gn:admin3_code":"25",
    "gn:admin4_code":"250033",
    "gn:asciiname":"Okharbot",
    "gn:country_code":"NP",
    "gn:dem":1857,
    "gn:feature_class":"P",
    "gn:feature_code":"PPLL",
    "gn:name":"Okharbot",
    "gn:population":0,
    "gn:timezone":"Asia/Kathmandu",
    "iso:country":"NP",
    "wof:name":"Okharbot",
    "wof:placetype":"locality"
},
  "geometry": {"coordinates":[85.34291,27.54621],"type":"Point"}
}