{
  "type": "Feature",
  "properties": {
    "gn:admin1_code":"CR",
    "gn:admin2_code":"1",
    "gn:admin3_code":"25",
    "gn:admin4_code":"250033",
    "gn:asciiname":"Okharbot",
    "gn:country_code":"NP",
    "gn:dem":1857,
    "gn:feature_class":"P",
    "gn:feature_code":"PPLL",
    "gn:name":"Okharbot",
    "gn:population":0,
    "gn:timezone":"Asia/Kathmandu",
    "iso:country":"NP",
    "name:ceb_x_preferred":[
        "Okharbot"
    ],
    "name:fra_x_preferred":[
        "Okharbot"
    ],
    "name:mai_x_preferred":[
        "\u0913\u0916\u0930\u092c\u094b\u091f"
    ],
    "name:msa_x_preferred":[
        "Okharbot"
    ],
    "name:nep_x_preferred":[
        "\u0913\u0916\u0930\u092c\u094b\u091f"
    ],
    "name:new_x_preferred":[
        "\u0913\u0916\u0930\u092c\u094b\u091f"
    ],
    "name:pol_x_preferred":[
        "Okharbot"
    ],
    "wof:name":"Okharbot",
    "wof:placetype":"locality"
},
  "geometry": {"coordinates":[85.34291,27.54621],"type":"Point"}
}