{
  "type": "Feature",
  "properties": {
    "gn:admin1_code":"FR",
    "gn:admin2_code":"9",
    "gn:admin3_code":"75.0",
    "gn:admin4_code":"750039.0",
    "gn:asciiname":"Magrum",
    "gn:country_code":"NP",
    "gn:dem":2702,
    "gn:feature_class":"P",
    "gn:feature_code":"PPLL",
    "gn:name":"Magrum",
    "gn:population":0,
    "gn:timezone":"Asia/Kathmandu",
    "iso:country":"NP",
    "wof:name":"Magrum",
    "wof:placetype":"locality"
},
  "geometry": {"coordinates":[80.64131,29.92737],"type":"Point"}
}