{
  "type": "Feature",
  "properties": {
    "gn:admin1_code":"WR",
    "gn:admin2_code":"4.0",
    "gn:admin3_code":"39.0",
    "gn:admin4_code":"390002.0",
    "gn:asciiname":"Keware",
    "gn:country_code":"NP",
    "gn:dem":1053,
    "gn:feature_class":"P",
    "gn:feature_code":"PPLL",
    "gn:name":"Keware",
    "gn:population":0,
    "gn:timezone":"Asia/Kathmandu",
    "iso:country":"NP",
    "wof:name":"Keware",
    "wof:placetype":"locality"
},
  "geometry": {"coordinates":[83.75761999999997,28.07982],"type":"Point"}
}