{
  "type": "Feature",
  "properties": {
    "gn:admin1_code":"WR",
    "gn:admin2_code":"3",
    "gn:admin3_code":"43",
    "gn:admin4_code":"430021",
    "gn:asciiname":"Nayaban",
    "gn:country_code":"NP",
    "gn:dem":2321,
    "gn:feature_class":"P",
    "gn:feature_code":"PPLL",
    "gn:name":"Nayaban",
    "gn:population":0,
    "gn:timezone":"Asia/Kathmandu",
    "iso:country":"NP",
    "wof:name":"Nayaban",
    "wof:placetype":"locality"
},
  "geometry": {"coordinates":[83.27249999999999,28.51895],"type":"Point"}
}