{
  "type": "Feature",
  "properties": {
    "gn:admin1_code":"MR",
    "gn:admin2_code":"12",
    "gn:admin3_code":"55",
    "gn:admin4_code":"550015",
    "gn:asciiname":"Mathillo Syanla",
    "gn:country_code":"NP",
    "gn:dem":1482,
    "gn:feature_class":"P",
    "gn:feature_code":"PPLL",
    "gn:name":"Mathillo Syanla",
    "gn:population":0,
    "gn:timezone":"Asia/Kathmandu",
    "iso:country":"NP",
    "wof:name":"Mathillo Syanla",
    "wof:placetype":"locality"
},
  "geometry": {"coordinates":[82.12745,28.35375],"type":"Point"}
}