{
  "type": "Feature",
  "properties": {
    "gn:admin1_code":"00",
    "gn:asciiname":"Tarapgaon",
    "gn:country_code":"NP",
    "gn:dem":4118,
    "gn:feature_class":"P",
    "gn:feature_code":"PPL",
    "gn:name":"Tar\u0101pgaon",
    "gn:population":0,
    "gn:timezone":"Asia/Kathmandu",
    "iso:country":"NP",
    "wof:name":"Tarapgaon",
    "wof:placetype":"locality"
},
  "geometry": {"coordinates":[83.18814,29.13175],"type":"Point"}
}