{
  "type": "Feature",
  "properties": {
    "gn:admin1_code":"FR",
    "gn:admin2_code":"14",
    "gn:admin3_code":"68",
    "gn:admin4_code":"680014",
    "gn:asciiname":"Burdhaula Nagna Bhanjyang",
    "gn:country_code":"NP",
    "gn:dem":3614,
    "gn:feature_class":"P",
    "gn:feature_code":"PPLL",
    "gn:name":"Burdhaula Nagna Bhanjyang",
    "gn:population":0,
    "gn:timezone":"Asia/Kathmandu",
    "iso:country":"NP",
    "wof:name":"Burdhaula Nagna Bhanjyang",
    "wof:placetype":"locality"
},
  "geometry": {"coordinates":[81.25949,29.67942],"type":"Point"}
}