{
  "type": "Feature",
  "properties": {
    "gn:admin1_code":"WR",
    "gn:admin2_code":"4.0",
    "gn:admin3_code":"38.0",
    "gn:admin4_code":"380045.0",
    "gn:asciiname":"Beltari",
    "gn:country_code":"NP",
    "gn:dem":364,
    "gn:feature_class":"P",
    "gn:feature_code":"PPLL",
    "gn:name":"Beltari",
    "gn:population":0,
    "gn:timezone":"Asia/Kathmandu",
    "iso:country":"NP",
    "wof:name":"Beltari",
    "wof:placetype":"locality"
},
  "geometry": {"coordinates":[84.25194999999999,28.00404],"type":"Point"}
}