{
  "type": "Feature",
  "properties": {
    "gn:admin1_code":"ER",
    "gn:admin2_code":"7",
    "gn:admin3_code":"7.0",
    "gn:admin4_code":"70011.0",
    "gn:asciiname":"Panchakanya",
    "gn:country_code":"NP",
    "gn:dem":951,
    "gn:feature_class":"P",
    "gn:feature_code":"PPLL",
    "gn:name":"Panchakanya",
    "gn:population":0,
    "gn:timezone":"Asia/Kathmandu",
    "iso:country":"NP",
    "name:bcl_x_preferred":[
        "Panchakanya"
    ],
    "name:ben_x_preferred":[
        "\u09aa\u099e\u09cd\u099a\u0995\u09a8\u09cd\u09af\u09be"
    ],
    "name:hin_x_preferred":[
        "\u092a\u0902\u091a\u0915\u0928\u094d\u092f\u093e"
    ],
    "name:mai_x_preferred":[
        "\u092a\u091e\u094d\u091a\u0915\u0928\u094d\u092f\u093e"
    ],
    "name:mal_x_preferred":[
        "\u0d2a\u0d1e\u0d4d\u0d1a\u0d15\u0d28\u0d4d\u0d2f\u0d15\u0d2e\u0d3e\u0d7c"
    ],
    "name:nep_x_preferred":[
        "\u092a\u091e\u094d\u091a\u0915\u0928\u094d\u092f\u093e"
    ],
    "name:new_x_preferred":[
        "\u092a\u091e\u094d\u091a\u0915\u0928\u094d\u092f\u093e"
    ],
    "name:tam_x_preferred":[
        "\u0baa\u0b9e\u0bcd\u0b9a\u0b95\u0ba9\u0bcd\u0ba9\u0bbf\u0b95\u0bc8"
    ],
    "name:urd_x_preferred":[
        "\u067e\u0646\u0686 \u06a9\u0646\u06cc\u0627"
    ],
    "wof:name":"Panchakanya",
    "wof:placetype":"locality"
},
  "geometry": {"coordinates":[87.22445,26.9531],"type":"Point"}
}