{
  "type": "Feature",
  "properties": {
    "gn:admin1_code":"ER",
    "gn:admin2_code":"7",
    "gn:admin3_code":"7.0",
    "gn:admin4_code":"70011.0",
    "gn:asciiname":"Panchakanya",
    "gn:country_code":"NP",
    "gn:dem":951,
    "gn:feature_class":"P",
    "gn:feature_code":"PPLL",
    "gn:name":"Panchakanya",
    "gn:population":0,
    "gn:timezone":"Asia/Kathmandu",
    "iso:country":"NP",
    "wof:name":"Panchakanya",
    "wof:placetype":"locality"
},
  "geometry": {"coordinates":[87.22445,26.9531],"type":"Point"}
}