{
  "type": "Feature",
  "properties": {
    "gn:admin1_code":"FR",
    "gn:admin2_code":"14",
    "gn:admin3_code":"71.0",
    "gn:admin4_code":"710024.0",
    "gn:asciiname":"Purba Matkauna",
    "gn:country_code":"NP",
    "gn:dem":188,
    "gn:feature_class":"P",
    "gn:feature_code":"PPLL",
    "gn:name":"Purba Matkauna",
    "gn:population":0,
    "gn:timezone":"Asia/Kathmandu",
    "iso:country":"NP",
    "wof:name":"Purba Matkauna",
    "wof:placetype":"locality"
},
  "geometry": {"coordinates":[80.83499,28.75261],"type":"Point"}
}