{
  "type": "Feature",
  "properties": {
    "gn:admin1_code":"WR",
    "gn:admin2_code":"8",
    "gn:admin3_code":"49",
    "gn:admin4_code":"490019",
    "gn:asciiname":"Pipal Danda",
    "gn:country_code":"NP",
    "gn:dem":145,
    "gn:feature_class":"P",
    "gn:feature_code":"PPLL",
    "gn:name":"Pipal Danda",
    "gn:population":0,
    "gn:timezone":"Asia/Kathmandu",
    "iso:country":"NP",
    "wof:name":"Pipal Danda",
    "wof:placetype":"locality"
},
  "geometry": {"coordinates":[83.59206999999998,27.64857],"type":"Point"}
}