{
  "type": "Feature",
  "properties": {
    "gn:admin1_code":"MR",
    "gn:admin2_code":"6",
    "gn:admin3_code":"66.0",
    "gn:admin4_code":"660021.0",
    "gn:asciiname":"Tallo Jilu",
    "gn:country_code":"NP",
    "gn:dem":3035,
    "gn:feature_class":"P",
    "gn:feature_code":"PPLL",
    "gn:name":"Tallo Jilu",
    "gn:population":0,
    "gn:timezone":"Asia/Kathmandu",
    "iso:country":"NP",
    "wof:name":"Tallo Jilu",
    "wof:placetype":"locality"
},
  "geometry": {"coordinates":[81.84645,29.78515],"type":"Point"}
}