{
  "type": "Feature",
  "properties": {
    "gn:admin1_code":"ER",
    "gn:admin2_code":"7",
    "gn:admin3_code":"5",
    "gn:admin4_code":"50034",
    "gn:asciiname":"Sano Turke",
    "gn:country_code":"NP",
    "gn:dem":248,
    "gn:feature_class":"P",
    "gn:feature_code":"PPLL",
    "gn:name":"Sano Turke",
    "gn:population":0,
    "gn:timezone":"Asia/Kathmandu",
    "iso:country":"NP",
    "wof:name":"Sano Turke",
    "wof:placetype":"locality"
},
  "geometry": {"coordinates":[87.45833,26.74137],"type":"Point"}
}