{
  "type": "Feature",
  "properties": {
    "gn:admin1_code":"FR",
    "gn:admin2_code":"14",
    "gn:admin3_code":"71.0",
    "gn:admin4_code":"710038.0",
    "gn:asciiname":"Bhedikhor",
    "gn:country_code":"NP",
    "gn:dem":1118,
    "gn:feature_class":"P",
    "gn:feature_code":"PPLL",
    "gn:name":"Bhedikhor",
    "gn:population":0,
    "gn:timezone":"Asia/Kathmandu",
    "iso:country":"NP",
    "wof:name":"Bhedikhor",
    "wof:placetype":"locality"
},
  "geometry": {"coordinates":[80.55468,29.05183],"type":"Point"}
}