{
  "type": "Feature",
  "properties": {
    "gn:admin1_code":"WR",
    "gn:admin2_code":"8",
    "gn:admin3_code":"49",
    "gn:admin4_code":"490060",
    "gn:asciiname":"Sonbarsa",
    "gn:country_code":"NP",
    "gn:dem":93,
    "gn:feature_class":"P",
    "gn:feature_code":"PPLL",
    "gn:name":"Sonbarsa",
    "gn:population":0,
    "gn:timezone":"Asia/Kathmandu",
    "iso:country":"NP",
    "name:ceb_x_preferred":[
        "Sonbarsa"
    ],
    "name:mai_x_preferred":[
        "\u0938\u094b\u0928\u092c\u0930\u094d\u0937\u093e"
    ],
    "name:msa_x_preferred":[
        "Sonbarsa"
    ],
    "name:nep_x_preferred":[
        "\u0938\u094b\u0928\u092c\u0930\u094d\u0937\u093e"
    ],
    "name:new_x_preferred":[
        "\u0938\u094b\u0928\u0935\u0930\u094d\u0937"
    ],
    "name:pol_x_preferred":[
        "Sonbarsa"
    ],
    "wof:name":"Sonbarsa",
    "wof:placetype":"locality"
},
  "geometry": {"coordinates":[83.31369000000002,27.34286],"type":"Point"}
}