{
  "type": "Feature",
  "properties": {
    "gn:admin1_code":"CR",
    "gn:admin2_code":"1",
    "gn:admin3_code":"30.0",
    "gn:admin4_code":"300013.0",
    "gn:asciiname":"Kotegaun",
    "gn:country_code":"NP",
    "gn:dem":967,
    "gn:feature_class":"P",
    "gn:feature_code":"PPLL",
    "gn:name":"Kotegaun",
    "gn:population":0,
    "gn:timezone":"Asia/Kathmandu",
    "iso:country":"NP",
    "wof:name":"Kotegaun",
    "wof:placetype":"locality"
},
  "geometry": {"coordinates":[84.86363,27.78052000000001],"type":"Point"}
}