{
  "type": "Feature",
  "properties": {
    "gn:admin1_code":"ER",
    "gn:admin2_code":"10",
    "gn:admin3_code":"4.0",
    "gn:admin4_code":"40014.0",
    "gn:asciiname":"Khalgaun",
    "gn:country_code":"NP",
    "gn:dem":141,
    "gn:feature_class":"P",
    "gn:feature_code":"PPLL",
    "gn:name":"Khalgaun",
    "gn:population":0,
    "gn:timezone":"Asia/Kathmandu",
    "iso:country":"NP",
    "wof:name":"Khalgaun",
    "wof:placetype":"locality"
},
  "geometry": {"coordinates":[88.08386,26.67509],"type":"Point"}
}