{
  "type": "Feature",
  "properties": {
    "gn:admin1_code":"WR",
    "gn:admin2_code":"3",
    "gn:admin3_code":"45.0",
    "gn:admin4_code":"450003.0",
    "gn:asciiname":"Rananam",
    "gn:country_code":"NP",
    "gn:dem":1993,
    "gn:feature_class":"P",
    "gn:feature_code":"PPLL",
    "gn:name":"Rananam",
    "gn:population":0,
    "gn:timezone":"Asia/Kathmandu",
    "iso:country":"NP",
    "wof:name":"Rananam",
    "wof:placetype":"locality"
},
  "geometry": {"coordinates":[83.40392,28.30084],"type":"Point"}
}