{
  "type": "Feature",
  "properties": {
    "gn:admin1_code":"MR",
    "gn:admin2_code":"2",
    "gn:admin3_code":"60.0",
    "gn:admin4_code":"600028.0",
    "gn:asciiname":"Jauchaur",
    "gn:country_code":"NP",
    "gn:dem":1415,
    "gn:feature_class":"P",
    "gn:feature_code":"PPLL",
    "gn:name":"Jauchaur",
    "gn:population":0,
    "gn:timezone":"Asia/Kathmandu",
    "iso:country":"NP",
    "wof:name":"Jauchaur",
    "wof:placetype":"locality"
},
  "geometry": {"coordinates":[81.54749,29.01934],"type":"Point"}
}