{
  "type": "Feature",
  "properties": {
    "gn:admin1_code":"CR",
    "gn:admin2_code":"11",
    "gn:admin3_code":"31",
    "gn:admin4_code":"310004",
    "gn:asciiname":"Dhumari",
    "gn:country_code":"NP",
    "gn:dem":885,
    "gn:feature_class":"P",
    "gn:feature_code":"PPLL",
    "gn:name":"Dhumari",
    "gn:population":0,
    "gn:timezone":"Asia/Kathmandu",
    "iso:country":"NP",
    "wof:name":"Dhumari",
    "wof:placetype":"locality"
},
  "geometry": {"coordinates":[85.01496,27.45797],"type":"Point"}
}