{
  "type": "Feature",
  "properties": {
    "gn:admin1_code":"00",
    "gn:asciiname":"Gijintar",
    "gn:country_code":"NP",
    "gn:dem":970,
    "gn:feature_class":"P",
    "gn:feature_code":"PPL",
    "gn:name":"Giji\u1e45\u1e6d\u0101r",
    "gn:population":0,
    "gn:timezone":"Asia/Kathmandu",
    "iso:country":"NP",
    "wof:name":"Gijintar",
    "wof:placetype":"locality"
},
  "geometry": {"coordinates":[86.40127,27.09669],"type":"Point"}
}