{
  "type": "Feature",
  "properties": {
    "gn:admin1_code":"ER",
    "gn:admin2_code":"13",
    "gn:admin3_code":"15",
    "gn:admin4_code":"150102",
    "gn:asciiname":"Rupani",
    "gn:country_code":"NP",
    "gn:dem":125,
    "gn:feature_class":"P",
    "gn:feature_code":"PPLL",
    "gn:name":"Rupani",
    "gn:population":0,
    "gn:timezone":"Asia/Kathmandu",
    "iso:country":"NP",
    "wof:name":"Rupani",
    "wof:placetype":"locality"
},
  "geometry": {"coordinates":[86.71678,26.63055],"type":"Point"}
}