{
  "type": "Feature",
  "properties": {
    "gn:admin1_code":"MR",
    "gn:admin2_code":"12",
    "gn:admin3_code":"54",
    "gn:admin4_code":"540007",
    "gn:asciiname":"Trisule",
    "gn:country_code":"NP",
    "gn:dem":1479,
    "gn:feature_class":"P",
    "gn:feature_code":"PPLL",
    "gn:name":"Trisule",
    "gn:population":0,
    "gn:timezone":"Asia/Kathmandu",
    "iso:country":"NP",
    "wof:name":"Trisule",
    "wof:placetype":"locality"
},
  "geometry": {"coordinates":[82.38558,28.61653],"type":"Point"}
}