{
  "type": "Feature",
  "properties": {
    "gn:admin1_code":"ER",
    "gn:admin2_code":"7.0",
    "gn:admin3_code":"8.0",
    "gn:admin4_code":"80006.0",
    "gn:asciiname":"Mulkharka",
    "gn:country_code":"NP",
    "gn:dem":1802,
    "gn:feature_class":"P",
    "gn:feature_code":"PPLL",
    "gn:name":"Mulkharka",
    "gn:population":0,
    "gn:timezone":"Asia/Kathmandu",
    "iso:country":"NP",
    "wof:name":"Mulkharka",
    "wof:placetype":"locality"
},
  "geometry": {"coordinates":[87.43796999999998,27.08625],"type":"Point"}
}