{
  "type": "Feature",
  "properties": {
    "gn:admin1_code":"ER",
    "gn:admin2_code":"7.0",
    "gn:admin3_code":"8.0",
    "gn:admin4_code":"80006.0",
    "gn:asciiname":"Mulkharka",
    "gn:country_code":"NP",
    "gn:dem":1802,
    "gn:feature_class":"P",
    "gn:feature_code":"PPLL",
    "gn:name":"Mulkharka",
    "gn:population":0,
    "gn:timezone":"Asia/Kathmandu",
    "iso:country":"NP",
    "name:bih_x_preferred":[
        "\u092e\u0942\u0932\u0916\u0930\u094d\u0915"
    ],
    "name:ceb_x_preferred":[
        "Mulkharka"
    ],
    "name:fra_x_preferred":[
        "Mulkharka"
    ],
    "name:hin_x_preferred":[
        "\u092e\u0942\u0932\u0916\u0930\u094d\u0915"
    ],
    "name:mai_x_preferred":[
        "\u092e\u0942\u0932\u0916\u0930\u094d\u0915"
    ],
    "name:msa_x_preferred":[
        "Mulkharka"
    ],
    "name:nep_x_preferred":[
        "\u092e\u0942\u0932\u0916\u0930\u094d\u0915"
    ],
    "name:new_x_preferred":[
        "\u092e\u0941\u0932\u0916\u0930\u094d\u0915"
    ],
    "name:pol_x_preferred":[
        "Mulkharka"
    ],
    "wof:name":"Mulkharka",
    "wof:placetype":"locality"
},
  "geometry": {"coordinates":[87.43796999999998,27.08625],"type":"Point"}
}