{
  "type": "Feature",
  "properties": {
    "gn:admin1_code":"ER",
    "gn:admin2_code":"13",
    "gn:admin3_code":"15",
    "gn:admin4_code":"150064.0",
    "gn:asciiname":"Khesraha",
    "gn:country_code":"NP",
    "gn:dem":115,
    "gn:feature_class":"P",
    "gn:feature_code":"PPLL",
    "gn:name":"Khesraha",
    "gn:population":0,
    "gn:timezone":"Asia/Kathmandu",
    "iso:country":"NP",
    "wof:name":"Khesraha",
    "wof:placetype":"locality"
},
  "geometry": {"coordinates":[86.59990999999999,26.63],"type":"Point"}
}