{
  "type": "Feature",
  "properties": {
    "gn:admin1_code":"FR",
    "gn:admin2_code":"14",
    "gn:admin3_code":"69",
    "gn:admin4_code":"690035.0",
    "gn:asciiname":"Simalkatne",
    "gn:country_code":"NP",
    "gn:dem":1109,
    "gn:feature_class":"P",
    "gn:feature_code":"PPLL",
    "gn:name":"Simalkatne",
    "gn:population":0,
    "gn:timezone":"Asia/Kathmandu",
    "iso:country":"NP",
    "wof:name":"Simalkatne",
    "wof:placetype":"locality"
},
  "geometry": {"coordinates":[81.34373000000002,29.16395],"type":"Point"}
}