{
  "type": "Feature",
  "properties": {
    "gn:admin1_code":"00",
    "gn:asciiname":"Nayachhap",
    "gn:country_code":"NP",
    "gn:dem":923,
    "gn:feature_class":"P",
    "gn:feature_code":"PPL",
    "gn:name":"Nay\u0101\u0303chh\u0101p",
    "gn:population":0,
    "gn:timezone":"Asia/Kathmandu",
    "iso:country":"NP",
    "name:nep_x_preferred":[
        "Nay\u0101nchh\u0101p"
    ],
    "name:und_x_variant":[
        "Nay\u0101\u0303chh\u0101p"
    ],
    "wof:name":"Nayachhap",
    "wof:placetype":"locality"
},
  "geometry": {"coordinates":[85.90295999999999,27.38989],"type":"Point"}
}