{
  "type": "Feature",
  "properties": {
    "gn:admin1_code":"WR",
    "gn:admin2_code":"4.0",
    "gn:admin3_code":"39.0",
    "gn:admin4_code":"390004.0",
    "gn:asciiname":"Rauteko Pairho",
    "gn:country_code":"NP",
    "gn:dem":1256,
    "gn:feature_class":"P",
    "gn:feature_code":"PPLL",
    "gn:name":"Rauteko Pairho",
    "gn:population":0,
    "gn:timezone":"Asia/Kathmandu",
    "iso:country":"NP",
    "wof:name":"Rauteko Pairho",
    "wof:placetype":"locality"
},
  "geometry": {"coordinates":[83.87859,28.167],"type":"Point"}
}