{
  "type": "Feature",
  "properties": {
    "gn:admin1_code":"MR",
    "gn:admin2_code":"6",
    "gn:admin3_code":"66.0",
    "gn:admin4_code":"660018.0",
    "gn:asciiname":"Bike Lamjong",
    "gn:country_code":"NP",
    "gn:dem":3487,
    "gn:feature_class":"P",
    "gn:feature_code":"PPLL",
    "gn:name":"Bike Lamjong",
    "gn:population":0,
    "gn:timezone":"Asia/Kathmandu",
    "iso:country":"NP",
    "wof:name":"Bike Lamjong",
    "wof:placetype":"locality"
},
  "geometry": {"coordinates":[81.47945,30.09841],"type":"Point"}
}