{
  "type": "Feature",
  "properties": {
    "gn:admin1_code":"WR",
    "gn:admin2_code":"4.0",
    "gn:admin3_code":"38.0",
    "gn:admin4_code":"380019.0",
    "gn:asciiname":"Banrang",
    "gn:country_code":"NP",
    "gn:dem":795,
    "gn:feature_class":"P",
    "gn:feature_code":"PPLL",
    "gn:name":"Banrang",
    "gn:population":0,
    "gn:timezone":"Asia/Kathmandu",
    "iso:country":"NP",
    "wof:name":"Banrang",
    "wof:placetype":"locality"
},
  "geometry": {"coordinates":[84.00776,28.05593],"type":"Point"}
}