{
  "type": "Feature",
  "properties": {
    "gn:admin1_code":"WR",
    "gn:admin2_code":"8",
    "gn:admin3_code":"51.0",
    "gn:admin4_code":"510039.0",
    "gn:asciiname":"Nipane",
    "gn:country_code":"NP",
    "gn:dem":1516,
    "gn:feature_class":"P",
    "gn:feature_code":"PPLL",
    "gn:name":"Nipane",
    "gn:population":0,
    "gn:timezone":"Asia/Kathmandu",
    "iso:country":"NP",
    "name:ceb_x_preferred":[
        "Nipane"
    ],
    "name:deu_x_preferred":[
        "Nipane"
    ],
    "wof:name":"Nipane",
    "wof:placetype":"locality"
},
  "geometry": {"coordinates":[83.1407,27.88774],"type":"Point"}
}