{
  "type": "Feature",
  "properties": {
    "gn:admin1_code":"MR",
    "gn:admin2_code":"6",
    "gn:admin3_code":"64.0",
    "gn:admin4_code":"640004.0",
    "gn:asciiname":"Baldhare",
    "gn:country_code":"NP",
    "gn:dem":2326,
    "gn:feature_class":"P",
    "gn:feature_code":"PPLL",
    "gn:name":"Baldhare",
    "gn:population":0,
    "gn:timezone":"Asia/Kathmandu",
    "iso:country":"NP",
    "wof:name":"Baldhare",
    "wof:placetype":"locality"
},
  "geometry": {"coordinates":[81.69719000000001,29.14355],"type":"Point"}
}