{
  "type": "Feature",
  "properties": {
    "gn:admin1_code":"WR",
    "gn:admin2_code":"4",
    "gn:admin3_code":"37",
    "gn:admin4_code":"370036",
    "gn:asciiname":"Thakan",
    "gn:country_code":"NP",
    "gn:dem":1071,
    "gn:feature_class":"P",
    "gn:feature_code":"PPLL",
    "gn:name":"Thakan",
    "gn:population":0,
    "gn:timezone":"Asia/Kathmandu",
    "iso:country":"NP",
    "wof:name":"Thakan",
    "wof:placetype":"locality"
},
  "geometry": {"coordinates":[84.39793,28.31847],"type":"Point"}
}