{
  "type": "Feature",
  "properties": {
    "gn:admin1_code":"WR",
    "gn:admin2_code":"4.0",
    "gn:admin3_code":"39.0",
    "gn:admin4_code":"390058.0",
    "gn:asciiname":"Bajakot",
    "gn:country_code":"NP",
    "gn:dem":1188,
    "gn:feature_class":"P",
    "gn:feature_code":"PPLL",
    "gn:name":"Bajakot",
    "gn:population":0,
    "gn:timezone":"Asia/Kathmandu",
    "iso:country":"NP",
    "wof:name":"Bajakot",
    "wof:placetype":"locality"
},
  "geometry": {"coordinates":[83.73700000000002,27.95626],"type":"Point"}
}