{
  "type": "Feature",
  "properties": {
    "gn:admin1_code":"MR",
    "gn:admin2_code":"12",
    "gn:admin3_code":"53",
    "gn:admin4_code":"530040",
    "gn:asciiname":"Uapllo Jany",
    "gn:country_code":"NP",
    "gn:dem":1939,
    "gn:feature_class":"P",
    "gn:feature_code":"PPLL",
    "gn:name":"Uapllo Jany",
    "gn:population":0,
    "gn:timezone":"Asia/Kathmandu",
    "iso:country":"NP",
    "wof:name":"Uapllo Jany",
    "wof:placetype":"locality"
},
  "geometry": {"coordinates":[82.44384000000002,28.46606],"type":"Point"}
}