{
  "type": "Feature",
  "properties": {
    "gn:admin1_code":"MR",
    "gn:admin2_code":"6",
    "gn:admin3_code":"66.0",
    "gn:admin4_code":"660018.0",
    "gn:asciiname":"Shiv Shiv",
    "gn:country_code":"NP",
    "gn:dem":4428,
    "gn:feature_class":"P",
    "gn:feature_code":"PPLL",
    "gn:name":"Shiv Shiv",
    "gn:population":0,
    "gn:timezone":"Asia/Kathmandu",
    "iso:country":"NP",
    "wof:name":"Shiv Shiv",
    "wof:placetype":"locality"
},
  "geometry": {"coordinates":[81.38781,30.13554],"type":"Point"}
}