{
  "type": "Feature",
  "properties": {
    "gn:admin1_code":"CR",
    "gn:admin2_code":"1",
    "gn:admin3_code":"30.0",
    "gn:admin4_code":"300030.0",
    "gn:asciiname":"Khanigaun",
    "gn:country_code":"NP",
    "gn:dem":1194,
    "gn:feature_class":"P",
    "gn:feature_code":"PPLL",
    "gn:name":"Khanigaun",
    "gn:population":0,
    "gn:timezone":"Asia/Kathmandu",
    "iso:country":"NP",
    "wof:name":"Khanigaun",
    "wof:placetype":"locality"
},
  "geometry": {"coordinates":[84.94999,28.01225],"type":"Point"}
}