{
  "type": "Feature",
  "properties": {
    "gn:admin1_code":"MR",
    "gn:admin2_code":"12",
    "gn:admin3_code":"53",
    "gn:admin4_code":"530025",
    "gn:asciiname":"Siurichaur",
    "gn:country_code":"NP",
    "gn:dem":1008,
    "gn:feature_class":"P",
    "gn:feature_code":"PPLL",
    "gn:name":"Siurichaur",
    "gn:population":0,
    "gn:timezone":"Asia/Kathmandu",
    "iso:country":"NP",
    "wof:name":"Siurichaur",
    "wof:placetype":"locality"
},
  "geometry": {"coordinates":[82.57999000000002,28.27681],"type":"Point"}
}