{
  "type": "Feature",
  "properties": {
    "gn:admin1_code":"ER",
    "gn:admin2_code":"10",
    "gn:admin3_code":"3.0",
    "gn:admin4_code":"30016.0",
    "gn:asciiname":"Nigure",
    "gn:country_code":"NP",
    "gn:dem":1802,
    "gn:feature_class":"P",
    "gn:feature_code":"PPLL",
    "gn:name":"Nigure",
    "gn:population":0,
    "gn:timezone":"Asia/Kathmandu",
    "iso:country":"NP",
    "wof:name":"Nigure",
    "wof:placetype":"locality"
},
  "geometry": {"coordinates":[87.99664,27.03284],"type":"Point"}
}