{
  "type": "Feature",
  "properties": {
    "gn:admin1_code":"WR",
    "gn:admin2_code":"4.0",
    "gn:admin3_code":"39.0",
    "gn:admin4_code":"390055.0",
    "gn:asciiname":"Tilhar",
    "gn:country_code":"NP",
    "gn:dem":1058,
    "gn:feature_class":"P",
    "gn:feature_code":"PPLL",
    "gn:name":"Tilhar",
    "gn:population":0,
    "gn:timezone":"Asia/Kathmandu",
    "iso:country":"NP",
    "wof:name":"Tilhar",
    "wof:placetype":"locality"
},
  "geometry": {"coordinates":[83.95891999999998,28.13097],"type":"Point"}
}