{
  "type": "Feature",
  "properties": {
    "gn:admin1_code":"ER",
    "gn:admin2_code":"13",
    "gn:admin3_code":"15",
    "gn:admin4_code":"150027",
    "gn:asciiname":"Sakhada",
    "gn:country_code":"NP",
    "gn:dem":70,
    "gn:feature_class":"P",
    "gn:feature_code":"PPLL",
    "gn:name":"Sakhada",
    "gn:population":0,
    "gn:timezone":"Asia/Kathmandu",
    "iso:country":"NP",
    "wof:name":"Sakhada",
    "wof:placetype":"locality"
},
  "geometry": {"coordinates":[86.73689,26.45236],"type":"Point"}
}