{
  "type": "Feature",
  "properties": {
    "gn:admin1_code":"ER",
    "gn:admin2_code":"10",
    "gn:admin3_code":"3.0",
    "gn:admin4_code":"30013.0",
    "gn:asciiname":"Rajduwali",
    "gn:country_code":"NP",
    "gn:dem":539,
    "gn:feature_class":"P",
    "gn:feature_code":"PPLL",
    "gn:name":"Rajduwali",
    "gn:population":0,
    "gn:timezone":"Asia/Kathmandu",
    "iso:country":"NP",
    "wof:name":"Rajduwali",
    "wof:placetype":"locality"
},
  "geometry": {"coordinates":[87.93677,26.88556],"type":"Point"}
}