{
  "type": "Feature",
  "properties": {
    "gn:admin1_code":"CR",
    "gn:admin2_code":"5",
    "gn:admin3_code":"20",
    "gn:admin4_code":"200045",
    "gn:asciiname":"Gorke",
    "gn:country_code":"NP",
    "gn:dem":1206,
    "gn:feature_class":"P",
    "gn:feature_code":"PPLL",
    "gn:name":"Gorke",
    "gn:population":0,
    "gn:timezone":"Asia/Kathmandu",
    "iso:country":"NP",
    "wof:name":"Gorke",
    "wof:placetype":"locality"
},
  "geometry": {"coordinates":[85.74144,27.395],"type":"Point"}
}