{
  "type": "Feature",
  "properties": {
    "gn:admin1_code":"CR",
    "gn:admin2_code":"5",
    "gn:admin3_code":"18",
    "gn:admin4_code":"180030",
    "gn:asciiname":"Bhanhiya",
    "gn:country_code":"NP",
    "gn:dem":70,
    "gn:feature_class":"P",
    "gn:feature_code":"PPLL",
    "gn:name":"Bhanhiya",
    "gn:population":0,
    "gn:timezone":"Asia/Kathmandu",
    "iso:country":"NP",
    "wof:name":"Bhanhiya",
    "wof:placetype":"locality"
},
  "geometry": {"coordinates":[85.75012,26.68594],"type":"Point"}
}