{
  "type": "Feature",
  "properties": {
    "gn:admin1_code":"ER",
    "gn:admin2_code":"10",
    "gn:admin3_code":"2",
    "gn:admin4_code":"20010",
    "gn:asciiname":"Khunga",
    "gn:country_code":"NP",
    "gn:dem":1579,
    "gn:feature_class":"P",
    "gn:feature_code":"PPLL",
    "gn:name":"Khunga",
    "gn:population":0,
    "gn:timezone":"Asia/Kathmandu",
    "iso:country":"NP",
    "wof:name":"Khunga",
    "wof:placetype":"locality"
},
  "geometry": {"coordinates":[87.87521,27.21482],"type":"Point"}
}