{
  "type": "Feature",
  "properties": {
    "gn:admin1_code":"CR",
    "gn:admin2_code":"11",
    "gn:admin3_code":"31",
    "gn:admin4_code":"310008",
    "gn:asciiname":"Chanpghari",
    "gn:country_code":"NP",
    "gn:dem":1185,
    "gn:feature_class":"P",
    "gn:feature_code":"PPLL",
    "gn:name":"Chanpghari",
    "gn:population":0,
    "gn:timezone":"Asia/Kathmandu",
    "iso:country":"NP",
    "wof:name":"Chanpghari",
    "wof:placetype":"locality"
},
  "geometry": {"coordinates":[85.1074,27.55411],"type":"Point"}
}