{
  "type": "Feature",
  "properties": {
    "gn:admin1_code":"WR",
    "gn:admin2_code":"4",
    "gn:admin3_code":"36.0",
    "gn:admin4_code":"360050.0",
    "gn:asciiname":"Dhuseni",
    "gn:country_code":"NP",
    "gn:dem":542,
    "gn:feature_class":"P",
    "gn:feature_code":"PPLL",
    "gn:name":"Dhuseni",
    "gn:population":0,
    "gn:timezone":"Asia/Kathmandu",
    "iso:country":"NP",
    "name:fra_x_preferred":[
        "Dhuseni"
    ],
    "name:pol_x_preferred":[
        "Dhuseni"
    ],
    "wof:name":"Dhuseni",
    "wof:placetype":"locality"
},
  "geometry": {"coordinates":[84.60011999999998,27.98762],"type":"Point"}
}