{
  "type": "Feature",
  "properties": {
    "gn:admin1_code":"CR",
    "gn:admin2_code":"11",
    "gn:admin3_code":"31",
    "gn:admin4_code":"310034",
    "gn:asciiname":"Ratematetol",
    "gn:country_code":"NP",
    "gn:dem":519,
    "gn:feature_class":"P",
    "gn:feature_code":"PPLL",
    "gn:name":"Ratematetol",
    "gn:population":0,
    "gn:timezone":"Asia/Kathmandu",
    "iso:country":"NP",
    "wof:name":"Ratematetol",
    "wof:placetype":"locality"
},
  "geometry": {"coordinates":[84.99051,27.40104],"type":"Point"}
}