{
  "type": "Feature",
  "properties": {
    "gn:admin1_code":"MR",
    "gn:admin2_code":"12",
    "gn:admin3_code":"56.0",
    "gn:admin4_code":"560014.0",
    "gn:asciiname":"Tikuli Damar",
    "gn:country_code":"NP",
    "gn:dem":563,
    "gn:feature_class":"P",
    "gn:feature_code":"PPLL",
    "gn:name":"Tikuli Damar",
    "gn:population":0,
    "gn:timezone":"Asia/Kathmandu",
    "iso:country":"NP",
    "wof:name":"Tikuli Damar",
    "wof:placetype":"locality"
},
  "geometry": {"coordinates":[82.64028,27.95588],"type":"Point"}
}