{
  "type": "Feature",
  "properties": {
    "gn:admin1_code":"FR",
    "gn:admin2_code":"9",
    "gn:admin3_code":"75.0",
    "gn:admin4_code":"750002.0",
    "gn:asciiname":"Matyul",
    "gn:country_code":"NP",
    "gn:dem":1026,
    "gn:feature_class":"P",
    "gn:feature_code":"PPLL",
    "gn:name":"Matyul",
    "gn:population":0,
    "gn:timezone":"Asia/Kathmandu",
    "iso:country":"NP",
    "wof:name":"Matyul",
    "wof:placetype":"locality"
},
  "geometry": {"coordinates":[80.51313,29.67948],"type":"Point"}
}