{
  "type": "Feature",
  "properties": {
    "gn:admin1_code":"MR",
    "gn:admin2_code":"12",
    "gn:admin3_code":"54",
    "gn:admin4_code":"540016",
    "gn:asciiname":"Igna",
    "gn:country_code":"NP",
    "gn:dem":1742,
    "gn:feature_class":"P",
    "gn:feature_code":"PPLL",
    "gn:name":"Igna",
    "gn:population":0,
    "gn:timezone":"Asia/Kathmandu",
    "iso:country":"NP",
    "wof:name":"Igna",
    "wof:placetype":"locality"
},
  "geometry": {"coordinates":[82.43671999999999,28.68963],"type":"Point"}
}