{
  "type": "Feature",
  "properties": {
    "gn:admin1_code":"MR",
    "gn:admin2_code":"12",
    "gn:admin3_code":"55",
    "gn:admin4_code":"550003",
    "gn:asciiname":"Melbote",
    "gn:country_code":"NP",
    "gn:dem":1266,
    "gn:feature_class":"P",
    "gn:feature_code":"PPLL",
    "gn:name":"Melbote",
    "gn:population":0,
    "gn:timezone":"Asia/Kathmandu",
    "iso:country":"NP",
    "wof:name":"Melbote",
    "wof:placetype":"locality"
},
  "geometry": {"coordinates":[82.23579000000002,28.43643],"type":"Point"}
}