{
  "type": "Feature",
  "properties": {
    "gn:admin1_code":"MR",
    "gn:admin2_code":"12",
    "gn:admin3_code":"56.0",
    "gn:admin4_code":"560014.0",
    "gn:asciiname":"Mahabhir",
    "gn:country_code":"NP",
    "gn:dem":451,
    "gn:feature_class":"P",
    "gn:feature_code":"PPLL",
    "gn:name":"Mahabhir",
    "gn:population":0,
    "gn:timezone":"Asia/Kathmandu",
    "iso:country":"NP",
    "wof:name":"Mahabhir",
    "wof:placetype":"locality"
},
  "geometry": {"coordinates":[82.75575000000001,27.91005],"type":"Point"}
}