{
  "type": "Feature",
  "properties": {
    "gn:admin1_code":"FR",
    "gn:admin2_code":"9",
    "gn:admin3_code":"74",
    "gn:admin4_code":"740043",
    "gn:asciiname":"Dharmaghat",
    "gn:country_code":"NP",
    "gn:dem":619,
    "gn:feature_class":"P",
    "gn:feature_code":"PPLL",
    "gn:name":"Dharmaghat",
    "gn:population":0,
    "gn:timezone":"Asia/Kathmandu",
    "iso:country":"NP",
    "wof:name":"Dharmaghat",
    "wof:placetype":"locality"
},
  "geometry": {"coordinates":[80.26098,29.40301],"type":"Point"}
}