{
  "type": "Feature",
  "properties": {
    "gn:admin1_code":"MR",
    "gn:admin2_code":"12",
    "gn:admin3_code":"54",
    "gn:admin4_code":"540024",
    "gn:asciiname":"Pokharapata",
    "gn:country_code":"NP",
    "gn:dem":1866,
    "gn:feature_class":"P",
    "gn:feature_code":"PPLL",
    "gn:name":"Pokharapata",
    "gn:population":0,
    "gn:timezone":"Asia/Kathmandu",
    "iso:country":"NP",
    "wof:name":"Pokharapata",
    "wof:placetype":"locality"
},
  "geometry": {"coordinates":[82.64043000000002,28.56339],"type":"Point"}
}