{
  "type": "Feature",
  "properties": {
    "gn:admin1_code":"MR",
    "gn:admin2_code":"2",
    "gn:admin3_code":"60.0",
    "gn:admin4_code":"600056.0",
    "gn:asciiname":"Kathatgaun",
    "gn:country_code":"NP",
    "gn:dem":1373,
    "gn:feature_class":"P",
    "gn:feature_code":"PPLL",
    "gn:name":"Kathatgaun",
    "gn:population":0,
    "gn:timezone":"Asia/Kathmandu",
    "iso:country":"NP",
    "wof:name":"Kathatgaun",
    "wof:placetype":"locality"
},
  "geometry": {"coordinates":[81.50530000000001,28.99236],"type":"Point"}
}