{
  "type": "Feature",
  "properties": {
    "gn:admin1_code":"MR",
    "gn:admin2_code":"12",
    "gn:admin3_code":"53",
    "gn:admin4_code":"530013",
    "gn:asciiname":"Masinapakha",
    "gn:country_code":"NP",
    "gn:dem":1910,
    "gn:feature_class":"P",
    "gn:feature_code":"PPLL",
    "gn:name":"Masinapakha",
    "gn:population":0,
    "gn:timezone":"Asia/Kathmandu",
    "iso:country":"NP",
    "wof:name":"Masinapakha",
    "wof:placetype":"locality"
},
  "geometry": {"coordinates":[82.51309999999999,28.35623],"type":"Point"}
}