{
  "type": "Feature",
  "properties": {
    "gn:admin1_code":"CR",
    "gn:admin2_code":"1",
    "gn:admin3_code":"23",
    "gn:admin4_code":"230056",
    "gn:asciiname":"Kurathali",
    "gn:country_code":"NP",
    "gn:dem":1917,
    "gn:feature_class":"P",
    "gn:feature_code":"PPLL",
    "gn:name":"Kurathali",
    "gn:population":0,
    "gn:timezone":"Asia/Kathmandu",
    "iso:country":"NP",
    "wof:name":"Kurathali",
    "wof:placetype":"locality"
},
  "geometry": {"coordinates":[85.91991,27.74654],"type":"Point"}
}