{
  "type": "Feature",
  "properties": {
    "gn:admin1_code":"CR",
    "gn:admin2_code":"5",
    "gn:admin3_code":"22.0",
    "gn:admin4_code":"220004.0",
    "gn:asciiname":"Dokthali",
    "gn:country_code":"NP",
    "gn:dem":1137,
    "gn:feature_class":"P",
    "gn:feature_code":"PPLL",
    "gn:name":"Dokthali",
    "gn:population":0,
    "gn:timezone":"Asia/Kathmandu",
    "iso:country":"NP",
    "wof:name":"Dokthali",
    "wof:placetype":"locality"
},
  "geometry": {"coordinates":[86.08211999999997,27.68809000000001],"type":"Point"}
}