{
  "type": "Feature",
  "properties": {
    "gn:admin1_code":"MR",
    "gn:admin2_code":"12",
    "gn:admin3_code":"56.0",
    "gn:admin4_code":"560036.0",
    "gn:asciiname":"Baruwagaun",
    "gn:country_code":"NP",
    "gn:dem":264,
    "gn:feature_class":"P",
    "gn:feature_code":"PPLL",
    "gn:name":"Baruwagaun",
    "gn:population":0,
    "gn:timezone":"Asia/Kathmandu",
    "iso:country":"NP",
    "wof:name":"Baruwagaun",
    "wof:placetype":"locality"
},
  "geometry": {"coordinates":[82.60774000000001,27.84149],"type":"Point"}
}