{
  "type": "Feature",
  "properties": {
    "gn:admin1_code":"WR",
    "gn:admin2_code":"3",
    "gn:admin3_code":"44",
    "gn:admin4_code":"440025",
    "gn:asciiname":"Bastala",
    "gn:country_code":"NP",
    "gn:dem":1259,
    "gn:feature_class":"P",
    "gn:feature_code":"PPLL",
    "gn:name":"Bastala",
    "gn:population":0,
    "gn:timezone":"Asia/Kathmandu",
    "iso:country":"NP",
    "wof:name":"Bastala",
    "wof:placetype":"locality"
},
  "geometry": {"coordinates":[83.64877,28.06269],"type":"Point"}
}