{
  "type": "Feature",
  "properties": {
    "gn:admin1_code":"00",
    "gn:asciiname":"Kandrangadhi",
    "gn:country_code":"NP",
    "gn:dem":1338,
    "gn:feature_class":"P",
    "gn:feature_code":"PPL",
    "gn:name":"Kandr\u0101\u1e45ga\u1e0dhi\u0307\u0304",
    "gn:population":0,
    "gn:timezone":"Asia/Kathmandu",
    "iso:country":"NP",
    "name:nep_x_preferred":[
        "Kandr\u0101\u1e45ga\u1e0dhi\u0307\u0304"
    ],
    "name:und_x_variant":[
        "K\u0101ndr\u0101ng Garhi"
    ],
    "wof:name":"Kandrangadhi",
    "wof:placetype":"locality"
},
  "geometry": {"coordinates":[84.79119,27.70876],"type":"Point"}
}