{
  "type": "Feature",
  "properties": {
    "gn:admin1_code":"CR",
    "gn:admin2_code":"5",
    "gn:admin3_code":"21",
    "gn:admin4_code":"210047.0",
    "gn:asciiname":"Rasanalu Patle",
    "gn:country_code":"NP",
    "gn:dem":1966,
    "gn:feature_class":"P",
    "gn:feature_code":"PPLL",
    "gn:name":"Rasanalu Patle",
    "gn:population":0,
    "gn:timezone":"Asia/Kathmandu",
    "iso:country":"NP",
    "wof:name":"Rasanalu Patle",
    "wof:placetype":"locality"
},
  "geometry": {"coordinates":[86.20525000000001,27.56713],"type":"Point"}
}