{
  "type": "Feature",
  "properties": {
    "gn:admin1_code":"CR",
    "gn:admin2_code":"1",
    "gn:admin3_code":"30.0",
    "gn:admin4_code":"300002.0",
    "gn:asciiname":"Bhaltar",
    "gn:country_code":"NP",
    "gn:dem":467,
    "gn:feature_class":"P",
    "gn:feature_code":"PPLL",
    "gn:name":"Bhaltar",
    "gn:population":0,
    "gn:timezone":"Asia/Kathmandu",
    "iso:country":"NP",
    "wof:name":"Bhaltar",
    "wof:placetype":"locality"
},
  "geometry": {"coordinates":[85.01235,27.78858],"type":"Point"}
}