{
  "type": "Feature",
  "properties": {
    "gn:admin1_code":"ER",
    "gn:admin2_code":"13",
    "gn:admin3_code":"15",
    "gn:admin4_code":"150100",
    "gn:asciiname":"Rajpur Khatawetol",
    "gn:country_code":"NP",
    "gn:dem":99,
    "gn:feature_class":"P",
    "gn:feature_code":"PPLL",
    "gn:name":"Rajpur Khatawetol",
    "gn:population":0,
    "gn:timezone":"Asia/Kathmandu",
    "iso:country":"NP",
    "wof:name":"Rajpur Khatawetol",
    "wof:placetype":"locality"
},
  "geometry": {"coordinates":[86.65261,26.58333],"type":"Point"}
}