{
  "type": "Feature",
  "properties": {
    "gn:admin1_code":"WR",
    "gn:admin2_code":"8",
    "gn:admin3_code":"48",
    "gn:admin4_code":"480064.0",
    "gn:asciiname":"Janakpur",
    "gn:country_code":"NP",
    "gn:dem":113,
    "gn:feature_class":"P",
    "gn:feature_code":"PPLL",
    "gn:name":"Janakpur",
    "gn:population":0,
    "gn:timezone":"Asia/Kathmandu",
    "iso:country":"NP",
    "wof:name":"Janakpur",
    "wof:placetype":"locality"
},
  "geometry": {"coordinates":[83.74065,27.51208],"type":"Point"}
}