{
  "type": "Feature",
  "properties": {
    "gn:admin1_code":"WR",
    "gn:admin2_code":"4",
    "gn:admin3_code":"36.0",
    "gn:admin4_code":"360008.0",
    "gn:asciiname":"Amraitar",
    "gn:country_code":"NP",
    "gn:dem":545,
    "gn:feature_class":"P",
    "gn:feature_code":"PPLL",
    "gn:name":"Amraitar",
    "gn:population":0,
    "gn:timezone":"Asia/Kathmandu",
    "iso:country":"NP",
    "wof:name":"Amraitar",
    "wof:placetype":"locality"
},
  "geometry": {"coordinates":[84.50848000000001,27.98965],"type":"Point"}
}