{
  "type": "Feature",
  "properties": {
    "gn:admin1_code":"MR",
    "gn:admin2_code":"6",
    "gn:admin3_code":"66.0",
    "gn:admin4_code":"660013.0",
    "gn:asciiname":"Simchaur",
    "gn:country_code":"NP",
    "gn:dem":3899,
    "gn:feature_class":"P",
    "gn:feature_code":"PPLL",
    "gn:name":"Simchaur",
    "gn:population":0,
    "gn:timezone":"Asia/Kathmandu",
    "iso:country":"NP",
    "name:ceb_x_preferred":[
        "Simchaur"
    ],
    "name:fra_x_preferred":[
        "Simchaur"
    ],
    "name:mai_x_preferred":[
        "\u0938\u093f\u092e\u091a\u094c\u0930"
    ],
    "name:msa_x_preferred":[
        "Simchaur"
    ],
    "name:nep_x_preferred":[
        "\u0938\u093f\u092e\u091a\u094c\u0930"
    ],
    "name:new_x_preferred":[
        "\u0938\u093f\u092e\u094d\u091a\u094c\u0930"
    ],
    "name:pol_x_preferred":[
        "Simchaur"
    ],
    "wof:name":"Simchaur",
    "wof:placetype":"locality"
},
  "geometry": {"coordinates":[81.50578,30.2195],"type":"Point"}
}