{
  "type": "Feature",
  "properties": {
    "gn:admin1_code":"WR",
    "gn:admin2_code":"8",
    "gn:admin3_code":"46.0",
    "gn:admin4_code":"460066.0",
    "gn:asciiname":"Bhujunge",
    "gn:country_code":"NP",
    "gn:dem":1464,
    "gn:feature_class":"P",
    "gn:feature_code":"PPLL",
    "gn:name":"Bhujunge",
    "gn:population":0,
    "gn:timezone":"Asia/Kathmandu",
    "iso:country":"NP",
    "wof:name":"Bhujunge",
    "wof:placetype":"locality"
},
  "geometry": {"coordinates":[83.09169,28.15216],"type":"Point"}
}