{
  "type": "Feature",
  "properties": {
    "gn:admin1_code":"MR",
    "gn:admin2_code":"2",
    "gn:admin3_code":"61.0",
    "gn:admin4_code":"610030.0",
    "gn:asciiname":"Pathar Chalna",
    "gn:country_code":"NP",
    "gn:dem":2104,
    "gn:feature_class":"P",
    "gn:feature_code":"PPLL",
    "gn:name":"Pathar Chalna",
    "gn:population":0,
    "gn:timezone":"Asia/Kathmandu",
    "iso:country":"NP",
    "wof:name":"Pathar Chalna",
    "wof:placetype":"locality"
},
  "geometry": {"coordinates":[81.86995,28.67261],"type":"Point"}
}