{
  "type": "Feature",
  "properties": {
    "gn:admin1_code":"MR",
    "gn:admin2_code":"2.0",
    "gn:admin3_code":"59.0",
    "gn:admin4_code":"590023.0",
    "gn:asciiname":"Dharap Thape",
    "gn:country_code":"NP",
    "gn:dem":1092,
    "gn:feature_class":"P",
    "gn:feature_code":"PPLL",
    "gn:name":"Dharap Thape",
    "gn:population":0,
    "gn:timezone":"Asia/Kathmandu",
    "iso:country":"NP",
    "wof:name":"Dharap Thape",
    "wof:placetype":"locality"
},
  "geometry": {"coordinates":[81.66721,28.64299],"type":"Point"}
}