{
  "type": "Feature",
  "properties": {
    "gn:admin1_code":"MR",
    "gn:admin2_code":"6",
    "gn:admin3_code":"63.0",
    "gn:admin4_code":"630016.0",
    "gn:asciiname":"Lumshera",
    "gn:country_code":"NP",
    "gn:dem":2446,
    "gn:feature_class":"P",
    "gn:feature_code":"PPLL",
    "gn:name":"Lumshera",
    "gn:population":0,
    "gn:timezone":"Asia/Kathmandu",
    "iso:country":"NP",
    "wof:name":"Lumshera",
    "wof:placetype":"locality"
},
  "geometry": {"coordinates":[82.01855999999999,29.2324],"type":"Point"}
}