{
  "type": "Feature",
  "properties": {
    "gn:admin1_code":"WR",
    "gn:admin2_code":"4",
    "gn:admin3_code":"40.0",
    "gn:admin4_code":"400009.0",
    "gn:asciiname":"Lekkuna",
    "gn:country_code":"NP",
    "gn:dem":1641,
    "gn:feature_class":"P",
    "gn:feature_code":"PPLL",
    "gn:name":"Lekkuna",
    "gn:population":0,
    "gn:timezone":"Asia/Kathmandu",
    "iso:country":"NP",
    "wof:name":"Lekkuna",
    "wof:placetype":"locality"
},
  "geometry": {"coordinates":[83.83882,28.32403],"type":"Point"}
}