{
  "type": "Feature",
  "properties": {
    "gn:admin1_code":"ER",
    "gn:admin2_code":"13.0",
    "gn:admin3_code":"14.0",
    "gn:admin4_code":"140018.0",
    "gn:asciiname":"Sallabote",
    "gn:country_code":"NP",
    "gn:dem":726,
    "gn:feature_class":"P",
    "gn:feature_code":"PPLL",
    "gn:name":"Sallabote",
    "gn:population":0,
    "gn:timezone":"Asia/Kathmandu",
    "iso:country":"NP",
    "wof:name":"Sallabote",
    "wof:placetype":"locality"
},
  "geometry": {"coordinates":[87.04718000000003,26.85339],"type":"Point"}
}