{
  "type": "Feature",
  "properties": {
    "gn:admin1_code":"MR",
    "gn:admin2_code":"12",
    "gn:admin3_code":"52",
    "gn:admin4_code":"520043",
    "gn:asciiname":"Takura",
    "gn:country_code":"NP",
    "gn:dem":871,
    "gn:feature_class":"P",
    "gn:feature_code":"PPLL",
    "gn:name":"Takura",
    "gn:population":0,
    "gn:timezone":"Asia/Kathmandu",
    "iso:country":"NP",
    "name:por_x_preferred":[
        "Takura Tendayi"
    ],
    "name:slk_x_preferred":[
        "Takura"
    ],
    "wof:name":"Takura",
    "wof:placetype":"locality"
},
  "geometry": {"coordinates":[82.71101999999998,28.17287],"type":"Point"}
}