{
  "type": "Feature",
  "properties": {
    "gn:admin1_code":"WR",
    "gn:admin2_code":"8",
    "gn:admin3_code":"48",
    "gn:admin4_code":"480021",
    "gn:asciiname":"Beltari",
    "gn:country_code":"NP",
    "gn:dem":192,
    "gn:feature_class":"P",
    "gn:feature_code":"PPLL",
    "gn:name":"Beltari",
    "gn:population":0,
    "gn:timezone":"Asia/Kathmandu",
    "iso:country":"NP",
    "wof:name":"Beltari",
    "wof:placetype":"locality"
},
  "geometry": {"coordinates":[84.39061,27.70866],"type":"Point"}
}