{
  "type": "Feature",
  "properties": {
    "gn:admin1_code":"MR",
    "gn:admin2_code":"12",
    "gn:admin3_code":"52",
    "gn:admin4_code":"520021",
    "gn:asciiname":"Ghorlate",
    "gn:country_code":"NP",
    "gn:dem":628,
    "gn:feature_class":"P",
    "gn:feature_code":"PPLL",
    "gn:name":"Ghorlate",
    "gn:population":0,
    "gn:timezone":"Asia/Kathmandu",
    "iso:country":"NP",
    "wof:name":"Ghorlate",
    "wof:placetype":"locality"
},
  "geometry": {"coordinates":[82.8965,27.9512],"type":"Point"}
}