{
  "type": "Feature",
  "properties": {
    "gn:admin1_code":"MR",
    "gn:admin2_code":"2",
    "gn:admin3_code":"61.0",
    "gn:admin4_code":"610017.0",
    "gn:asciiname":"Khut",
    "gn:country_code":"NP",
    "gn:dem":1469,
    "gn:feature_class":"P",
    "gn:feature_code":"PPLL",
    "gn:name":"Khut",
    "gn:population":0,
    "gn:timezone":"Asia/Kathmandu",
    "iso:country":"NP",
    "wof:name":"Khut",
    "wof:placetype":"locality"
},
  "geometry": {"coordinates":[81.97929999999999,28.80434],"type":"Point"}
}