{
  "type": "Feature",
  "properties": {
    "gn:admin1_code":"FR",
    "gn:admin2_code":"14",
    "gn:admin3_code":"70.0",
    "gn:admin4_code":"700040.0",
    "gn:asciiname":"Surkal",
    "gn:country_code":"NP",
    "gn:dem":978,
    "gn:feature_class":"P",
    "gn:feature_code":"PPLL",
    "gn:name":"Surkal",
    "gn:population":0,
    "gn:timezone":"Asia/Kathmandu",
    "iso:country":"NP",
    "wof:name":"Surkal",
    "wof:placetype":"locality"
},
  "geometry": {"coordinates":[80.88351,29.2599],"type":"Point"}
}