{
  "type": "Feature",
  "properties": {
    "gn:admin1_code":"FR",
    "gn:admin2_code":"14.0",
    "gn:admin3_code":"69.0",
    "gn:admin4_code":"690044.0",
    "gn:asciiname":"Matemadu",
    "gn:country_code":"NP",
    "gn:dem":897,
    "gn:feature_class":"P",
    "gn:feature_code":"PPLL",
    "gn:name":"Matemadu",
    "gn:population":0,
    "gn:timezone":"Asia/Kathmandu",
    "iso:country":"NP",
    "wof:name":"Matemadu",
    "wof:placetype":"locality"
},
  "geometry": {"coordinates":[81.43608,29.08239],"type":"Point"}
}