{
  "type": "Feature",
  "properties": {
    "gn:admin1_code":"00",
    "gn:asciiname":"Sire",
    "gn:country_code":"NP",
    "gn:dem":1936,
    "gn:feature_class":"P",
    "gn:feature_code":"PPL",
    "gn:name":"Sire",
    "gn:population":0,
    "gn:timezone":"Asia/Kathmandu",
    "iso:country":"NP",
    "wof:name":"Sire",
    "wof:placetype":"locality"
},
  "geometry": {"coordinates":[85.38639999999999,27.54988],"type":"Point"}
}