{
  "type": "Feature",
  "properties": {
    "gn:admin1_code":"FR",
    "gn:admin2_code":"14",
    "gn:admin3_code":"71.0",
    "gn:admin4_code":"710033.0",
    "gn:asciiname":"Shivatalbasti",
    "gn:country_code":"NP",
    "gn:dem":170,
    "gn:feature_class":"P",
    "gn:feature_code":"PPLL",
    "gn:name":"Shivatalbasti",
    "gn:population":0,
    "gn:timezone":"Asia/Kathmandu",
    "iso:country":"NP",
    "wof:name":"Shivatalbasti",
    "wof:placetype":"locality"
},
  "geometry": {"coordinates":[80.66931,28.64461],"type":"Point"}
}