{
  "type": "Feature",
  "properties": {
    "gn:admin1_code":"MR",
    "gn:admin2_code":"12",
    "gn:admin3_code":"53",
    "gn:admin4_code":"530050",
    "gn:asciiname":"Bhirkholagaun",
    "gn:country_code":"NP",
    "gn:dem":2459,
    "gn:feature_class":"P",
    "gn:feature_code":"PPLL",
    "gn:name":"Bhirkholagaun",
    "gn:population":0,
    "gn:timezone":"Asia/Kathmandu",
    "iso:country":"NP",
    "wof:name":"Bhirkholagaun",
    "wof:placetype":"locality"
},
  "geometry": {"coordinates":[82.60349000000002,28.42738],"type":"Point"}
}