{
  "type": "Feature",
  "properties": {
    "gn:admin1_code":"ER",
    "gn:admin2_code":"7",
    "gn:admin3_code":"5",
    "gn:admin4_code":"50062",
    "gn:asciiname":"Shantipur",
    "gn:country_code":"NP",
    "gn:dem":95,
    "gn:feature_class":"P",
    "gn:feature_code":"PPLL",
    "gn:name":"Shantipur",
    "gn:population":0,
    "gn:timezone":"Asia/Kathmandu",
    "iso:country":"NP",
    "name:ben_x_preferred":[
        "\u09b6\u09be\u09a8\u09cd\u09a4\u09bf\u09aa\u09c1\u09b0"
    ],
    "name:bih_x_preferred":[
        "\u0936\u093e\u0902\u0924\u093f\u092a\u0941\u0930"
    ],
    "name:bpy_x_preferred":[
        "\u09b6\u09be\u09a8\u09cd\u09a4\u09bf\u09aa\u09c1\u09b0"
    ],
    "name:ceb_x_preferred":[
        "Sh\u0101ntipur"
    ],
    "name:hif_x_preferred":[
        "Santipur"
    ],
    "name:ita_x_preferred":[
        "Santipur"
    ],
    "name:msa_x_preferred":[
        "Santipur"
    ],
    "name:new_x_preferred":[
        "\u0936\u093e\u0928\u094d\u0924\u093f\u092a\u0941\u0930"
    ],
    "name:ori_x_preferred":[
        "\u0b36\u0b3e\u0b28\u0b4d\u0b24\u0b3f\u0b2a\u0b41\u0b30"
    ],
    "name:pol_x_preferred":[
        "Shantipur"
    ],
    "name:por_x_preferred":[
        "Santipur"
    ],
    "name:rus_x_preferred":[
        "\u0428\u0430\u043d\u0442\u0438\u043f\u0443\u0440"
    ],
    "name:spa_x_preferred":[
        "Santipur"
    ],
    "name:swe_x_preferred":[
        "Santipur"
    ],
    "name:tam_x_preferred":[
        "\u0b9a\u0bbe\u0ba8\u0bcd\u0ba4\u0bbf\u0baa\u0bcd\u0baa\u0bc2\u0bb0\u0bcd"
    ],
    "name:vie_x_preferred":[
        "Santipur"
    ],
    "name:war_x_preferred":[
        "Shantipur"
    ],
    "name:zho_x_preferred":[
        "\u6851\u8482\u666e\u5c14"
    ],
    "wof:name":"Shantipur",
    "wof:placetype":"locality"
},
  "geometry": {"coordinates":[87.35200999999998,26.56646],"type":"Point"}
}