{
  "type": "Feature",
  "properties": {
    "gn:admin1_code":"WR",
    "gn:admin2_code":"8",
    "gn:admin3_code":"46.0",
    "gn:admin4_code":"460076.0",
    "gn:asciiname":"Harsinglot",
    "gn:country_code":"NP",
    "gn:dem":1534,
    "gn:feature_class":"P",
    "gn:feature_code":"PPLL",
    "gn:name":"Harsinglot",
    "gn:population":0,
    "gn:timezone":"Asia/Kathmandu",
    "iso:country":"NP",
    "wof:name":"Harsinglot",
    "wof:placetype":"locality"
},
  "geometry": {"coordinates":[83.50964999999999,28.00024],"type":"Point"}
}