{
  "type": "Feature",
  "properties": {
    "gn:admin1_code":"CR",
    "gn:admin2_code":"1",
    "gn:admin3_code":"23",
    "gn:admin4_code":"230002",
    "gn:asciiname":"Gairigau",
    "gn:country_code":"NP",
    "gn:dem":1361,
    "gn:feature_class":"P",
    "gn:feature_code":"PPLL",
    "gn:name":"Gairigau",
    "gn:population":0,
    "gn:timezone":"Asia/Kathmandu",
    "iso:country":"NP",
    "wof:name":"Gairigau",
    "wof:placetype":"locality"
},
  "geometry": {"coordinates":[85.60604000000002,27.78918],"type":"Point"}
}