{
  "type": "Feature",
  "properties": {
    "gn:admin1_code":"MR",
    "gn:admin2_code":"12",
    "gn:admin3_code":"53",
    "gn:admin4_code":"530021",
    "gn:asciiname":"Bathachaur",
    "gn:country_code":"NP",
    "gn:dem":1501,
    "gn:feature_class":"P",
    "gn:feature_code":"PPLL",
    "gn:name":"Bathachaur",
    "gn:population":0,
    "gn:timezone":"Asia/Kathmandu",
    "iso:country":"NP",
    "wof:name":"Bathachaur",
    "wof:placetype":"locality"
},
  "geometry": {"coordinates":[82.56808000000002,28.25787],"type":"Point"}
}