{
  "type": "Feature",
  "properties": {
    "gn:admin1_code":"ER",
    "gn:admin2_code":"10",
    "gn:admin3_code":"3.0",
    "gn:admin4_code":"30025.0",
    "gn:asciiname":"Kalkate",
    "gn:country_code":"NP",
    "gn:dem":182,
    "gn:feature_class":"P",
    "gn:feature_code":"PPLL",
    "gn:name":"Kalkate",
    "gn:population":0,
    "gn:timezone":"Asia/Kathmandu",
    "iso:country":"NP",
    "wof:name":"Kalkate",
    "wof:placetype":"locality"
},
  "geometry": {"coordinates":[87.87013,26.7427],"type":"Point"}
}