{
  "type": "Feature",
  "properties": {
    "gn:admin1_code":"MR",
    "gn:admin2_code":"2",
    "gn:admin3_code":"60.0",
    "gn:admin4_code":"600015.0",
    "gn:asciiname":"Shanti Bajar",
    "gn:country_code":"NP",
    "gn:dem":1440,
    "gn:feature_class":"P",
    "gn:feature_code":"PPLL",
    "gn:name":"Shanti Bajar",
    "gn:population":0,
    "gn:timezone":"Asia/Kathmandu",
    "iso:country":"NP",
    "wof:name":"Shanti Bajar",
    "wof:placetype":"locality"
},
  "geometry": {"coordinates":[81.59071,28.85239],"type":"Point"}
}