{
  "type": "Feature",
  "properties": {
    "gn:admin1_code":"ER",
    "gn:admin2_code":"7",
    "gn:admin3_code":"9",
    "gn:admin4_code":"90029",
    "gn:asciiname":"Tenchhung",
    "gn:country_code":"NP",
    "gn:dem":1530,
    "gn:feature_class":"P",
    "gn:feature_code":"PPLL",
    "gn:name":"Tenchhung",
    "gn:population":0,
    "gn:timezone":"Asia/Kathmandu",
    "iso:country":"NP",
    "wof:name":"Tenchhung",
    "wof:placetype":"locality"
},
  "geometry": {"coordinates":[87.02585999999999,27.47704],"type":"Point"}
}