{
  "type": "Feature",
  "properties": {
    "gn:admin1_code":"00",
    "gn:asciiname":"Ghanbar",
    "gn:country_code":"NP",
    "gn:dem":1975,
    "gn:feature_class":"P",
    "gn:feature_code":"PPL",
    "gn:name":"Gh\u0101\u1e45bar",
    "gn:population":0,
    "gn:timezone":"Asia/Kathmandu",
    "iso:country":"NP",
    "wof:name":"Ghanbar",
    "wof:placetype":"locality"
},
  "geometry": {"coordinates":[85.31264,28.00867],"type":"Point"}
}