{
  "type": "Feature",
  "properties": {
    "gn:admin1_code":"ER",
    "gn:admin2_code":"13",
    "gn:admin3_code":"12",
    "gn:admin4_code":"120049",
    "gn:asciiname":"Pakhe",
    "gn:country_code":"NP",
    "gn:dem":2065,
    "gn:feature_class":"P",
    "gn:feature_code":"PPLL",
    "gn:name":"Pakhe",
    "gn:population":0,
    "gn:timezone":"Asia/Kathmandu",
    "iso:country":"NP",
    "wof:name":"Pakhe",
    "wof:placetype":"locality"
},
  "geometry": {"coordinates":[86.35902,27.26944],"type":"Point"}
}