{
  "type": "Feature",
  "properties": {
    "gn:admin1_code":"MR",
    "gn:admin2_code":"6",
    "gn:admin3_code":"65",
    "gn:admin4_code":"650006",
    "gn:asciiname":"Bumcha",
    "gn:country_code":"NP",
    "gn:dem":2097,
    "gn:feature_class":"P",
    "gn:feature_code":"PPLL",
    "gn:name":"Bumcha",
    "gn:population":0,
    "gn:timezone":"Asia/Kathmandu",
    "iso:country":"NP",
    "wof:name":"Bumcha",
    "wof:placetype":"locality"
},
  "geometry": {"coordinates":[82.02508,29.61153],"type":"Point"}
}