{
  "type": "Feature",
  "properties": {
    "gn:admin1_code":"WR",
    "gn:admin2_code":"8",
    "gn:admin3_code":"47",
    "gn:admin4_code":"470020",
    "gn:asciiname":"Hattikot",
    "gn:country_code":"NP",
    "gn:dem":790,
    "gn:feature_class":"P",
    "gn:feature_code":"PPLL",
    "gn:name":"Hattikot",
    "gn:population":0,
    "gn:timezone":"Asia/Kathmandu",
    "iso:country":"NP",
    "wof:name":"Hattikot",
    "wof:placetype":"locality"
},
  "geometry": {"coordinates":[83.52866999999998,27.72805],"type":"Point"}
}