{
  "type": "Feature",
  "properties": {
    "gn:admin1_code":"FR",
    "gn:admin2_code":"9",
    "gn:admin3_code":"74",
    "gn:admin4_code":"740056",
    "gn:asciiname":"Jhaulek",
    "gn:country_code":"NP",
    "gn:dem":1963,
    "gn:feature_class":"P",
    "gn:feature_code":"PPLL",
    "gn:name":"Jhaulek",
    "gn:population":0,
    "gn:timezone":"Asia/Kathmandu",
    "iso:country":"NP",
    "wof:name":"Jhaulek",
    "wof:placetype":"locality"
},
  "geometry": {"coordinates":[80.66134,29.46674],"type":"Point"}
}