{
  "type": "Feature",
  "properties": {
    "gn:admin1_code":"CR",
    "gn:admin2_code":"1",
    "gn:admin3_code":"24.0",
    "gn:admin4_code":"240083.0",
    "gn:asciiname":"Phetar",
    "gn:country_code":"NP",
    "gn:dem":1296,
    "gn:feature_class":"P",
    "gn:feature_code":"PPLL",
    "gn:name":"Phetar",
    "gn:population":0,
    "gn:timezone":"Asia/Kathmandu",
    "iso:country":"NP",
    "wof:name":"Phetar",
    "wof:placetype":"locality"
},
  "geometry": {"coordinates":[85.62315,27.50562],"type":"Point"}
}