{
  "type": "Feature",
  "properties": {
    "gn:admin1_code":"WR",
    "gn:admin2_code":"4",
    "gn:admin3_code":"37",
    "gn:admin4_code":"370059",
    "gn:asciiname":"Naubise",
    "gn:country_code":"NP",
    "gn:dem":566,
    "gn:feature_class":"P",
    "gn:feature_code":"PPLL",
    "gn:name":"Naubise",
    "gn:population":0,
    "gn:timezone":"Asia/Kathmandu",
    "iso:country":"NP",
    "name:deu_x_preferred":[
        "Naubise"
    ],
    "name:mai_x_preferred":[
        "\u0928\u094c\u092c\u093f\u0938\u0947"
    ],
    "name:msa_x_preferred":[
        "Naubise"
    ],
    "name:nep_x_preferred":[
        "\u0928\u094c\u092c\u093f\u0938\u0947"
    ],
    "name:new_x_preferred":[
        "\u0928\u094c\u092c\u093f\u0938\u0947"
    ],
    "name:pol_x_preferred":[
        "Naubise"
    ],
    "wof:name":"Naubise",
    "wof:placetype":"locality"
},
  "geometry": {"coordinates":[84.43661999999998,28.11197],"type":"Point"}
}