{
  "type": "Feature",
  "properties": {
    "gn:admin1_code":"FR",
    "gn:admin2_code":"9",
    "gn:admin3_code":"73.0",
    "gn:admin4_code":"730021.0",
    "gn:asciiname":"Goja",
    "gn:country_code":"NP",
    "gn:dem":501,
    "gn:feature_class":"P",
    "gn:feature_code":"PPLL",
    "gn:name":"Goja",
    "gn:population":0,
    "gn:timezone":"Asia/Kathmandu",
    "iso:country":"NP",
    "wof:name":"Goja",
    "wof:placetype":"locality"
},
  "geometry": {"coordinates":[80.36442,29.14031],"type":"Point"}
}