{
  "type": "Feature",
  "properties": {
    "gn:admin1_code":"MR",
    "gn:admin2_code":"6",
    "gn:admin3_code":"65",
    "gn:admin4_code":"650018",
    "gn:asciiname":"Gadapani",
    "gn:country_code":"NP",
    "gn:dem":2185,
    "gn:feature_class":"P",
    "gn:feature_code":"PPLL",
    "gn:name":"Gadapani",
    "gn:population":0,
    "gn:timezone":"Asia/Kathmandu",
    "iso:country":"NP",
    "wof:name":"Gadapani",
    "wof:placetype":"locality"
},
  "geometry": {"coordinates":[82.19305,29.53646],"type":"Point"}
}