{
  "type": "Feature",
  "properties": {
    "gn:admin1_code":"ER",
    "gn:admin2_code":"10",
    "gn:admin3_code":"4.0",
    "gn:admin4_code":"40017.0",
    "gn:asciiname":"Tangabari",
    "gn:country_code":"NP",
    "gn:dem":111,
    "gn:feature_class":"P",
    "gn:feature_code":"PPLL",
    "gn:name":"Tangabari",
    "gn:population":0,
    "gn:timezone":"Asia/Kathmandu",
    "iso:country":"NP",
    "wof:name":"Tangabari",
    "wof:placetype":"locality"
},
  "geometry": {"coordinates":[88.00189,26.59986],"type":"Point"}
}