{
  "type": "Feature",
  "properties": {
    "gn:admin1_code":"00",
    "gn:asciiname":"Gothgau",
    "gn:country_code":"NP",
    "gn:dem":131,
    "gn:feature_class":"P",
    "gn:feature_code":"PPL",
    "gn:name":"Go\u1e6dhg\u0101\u0169",
    "gn:population":0,
    "gn:timezone":"Asia/Kathmandu",
    "iso:country":"NP",
    "name:nep_x_preferred":[
        "Go\u1e6dhg\u0101\u0169"
    ],
    "wof:name":"Gothgau",
    "wof:placetype":"locality"
},
  "geometry": {"coordinates":[87.34634,26.66078],"type":"Point"}
}