{
  "type": "Feature",
  "properties": {
    "gn:admin1_code":"WR",
    "gn:admin2_code":"3",
    "gn:admin3_code":"44",
    "gn:admin4_code":"440020",
    "gn:asciiname":"Saslyan",
    "gn:country_code":"NP",
    "gn:dem":1289,
    "gn:feature_class":"P",
    "gn:feature_code":"PPLL",
    "gn:name":"Saslyan",
    "gn:population":0,
    "gn:timezone":"Asia/Kathmandu",
    "iso:country":"NP",
    "wof:name":"Saslyan",
    "wof:placetype":"locality"
},
  "geometry": {"coordinates":[83.60292,28.32245],"type":"Point"}
}