{
  "type": "Feature",
  "properties": {
    "gn:admin1_code":"CR",
    "gn:admin2_code":"1",
    "gn:admin3_code":"30.0",
    "gn:admin4_code":"300020.0",
    "gn:asciiname":"Ghartigaun",
    "gn:country_code":"NP",
    "gn:dem":1057,
    "gn:feature_class":"P",
    "gn:feature_code":"PPLL",
    "gn:name":"Ghartigaun",
    "gn:population":0,
    "gn:timezone":"Asia/Kathmandu",
    "iso:country":"NP",
    "wof:name":"Ghartigaun",
    "wof:placetype":"locality"
},
  "geometry": {"coordinates":[84.93285999999998,27.84082],"type":"Point"}
}