{
  "type": "Feature",
  "properties": {
    "gn:admin1_code":"WR",
    "gn:admin2_code":"8",
    "gn:admin3_code":"46.0",
    "gn:admin4_code":"460066.0",
    "gn:asciiname":"Sano pokhara",
    "gn:country_code":"NP",
    "gn:dem":1699,
    "gn:feature_class":"P",
    "gn:feature_code":"PPLL",
    "gn:name":"Sano pokhara",
    "gn:population":0,
    "gn:timezone":"Asia/Kathmandu",
    "iso:country":"NP",
    "wof:name":"Sano pokhara",
    "wof:placetype":"locality"
},
  "geometry": {"coordinates":[83.06156,28.11422],"type":"Point"}
}