{
  "type": "Feature",
  "properties": {
    "gn:admin1_code":"WR",
    "gn:admin2_code":"4",
    "gn:admin3_code":"36.0",
    "gn:admin4_code":"360039.0",
    "gn:asciiname":"Ningaun",
    "gn:country_code":"NP",
    "gn:dem":3210,
    "gn:feature_class":"P",
    "gn:feature_code":"PPLL",
    "gn:name":"Ningaun",
    "gn:population":0,
    "gn:timezone":"Asia/Kathmandu",
    "iso:country":"NP",
    "wof:name":"Ningaun",
    "wof:placetype":"locality"
},
  "geometry": {"coordinates":[84.71562,28.57511],"type":"Point"}
}