{
  "type": "Feature",
  "properties": {
    "gn:admin1_code":"MR",
    "gn:admin2_code":"2",
    "gn:admin3_code":"60.0",
    "gn:admin4_code":"600052.0",
    "gn:asciiname":"Nauli",
    "gn:country_code":"NP",
    "gn:dem":1156,
    "gn:feature_class":"P",
    "gn:feature_code":"PPLL",
    "gn:name":"Nauli",
    "gn:population":0,
    "gn:timezone":"Asia/Kathmandu",
    "iso:country":"NP",
    "name:deu_x_preferred":[
        "Nauli"
    ],
    "name:fra_x_preferred":[
        "Nauli"
    ],
    "name:nld_x_preferred":[
        "Nauli"
    ],
    "wof:name":"Nauli",
    "wof:placetype":"locality"
},
  "geometry": {"coordinates":[81.46138000000001,28.98761],"type":"Point"}
}