{
  "type": "Feature",
  "properties": {
    "gn:admin1_code":"ER",
    "gn:admin2_code":"7",
    "gn:admin3_code":"10.0",
    "gn:admin4_code":"100036.0",
    "gn:asciiname":"Jagirgaun",
    "gn:country_code":"NP",
    "gn:dem":1326,
    "gn:feature_class":"P",
    "gn:feature_code":"PPLL",
    "gn:name":"Jagirgaun",
    "gn:population":0,
    "gn:timezone":"Asia/Kathmandu",
    "iso:country":"NP",
    "wof:name":"Jagirgaun",
    "wof:placetype":"locality"
},
  "geometry": {"coordinates":[86.99023000000003,27.15517],"type":"Point"}
}