{
  "type": "Feature",
  "properties": {
    "gn:admin1_code":"WR",
    "gn:admin2_code":"4",
    "gn:admin3_code":"36.0",
    "gn:admin4_code":"360027.0",
    "gn:asciiname":"Shahichhap",
    "gn:country_code":"NP",
    "gn:dem":779,
    "gn:feature_class":"P",
    "gn:feature_code":"PPLL",
    "gn:name":"Shahichhap",
    "gn:population":0,
    "gn:timezone":"Asia/Kathmandu",
    "iso:country":"NP",
    "wof:name":"Shahichhap",
    "wof:placetype":"locality"
},
  "geometry": {"coordinates":[84.8052,27.7799],"type":"Point"}
}