{
  "type": "Feature",
  "properties": {
    "gn:admin1_code":"MR",
    "gn:admin2_code":"12",
    "gn:admin3_code":"56.0",
    "gn:admin4_code":"560016.0",
    "gn:asciiname":"Padampur",
    "gn:country_code":"NP",
    "gn:dem":567,
    "gn:feature_class":"P",
    "gn:feature_code":"PPLL",
    "gn:name":"Padampur",
    "gn:population":0,
    "gn:timezone":"Asia/Kathmandu",
    "iso:country":"NP",
    "name:ceb_x_preferred":[
        "Padampur"
    ],
    "name:swe_x_preferred":[
        "Padampur"
    ],
    "wof:name":"Padampur",
    "wof:placetype":"locality"
},
  "geometry": {"coordinates":[82.18069,28.09379],"type":"Point"}
}