{
  "type": "Feature",
  "properties": {
    "gn:admin1_code":"ER",
    "gn:admin2_code":"13",
    "gn:admin3_code":"15",
    "gn:admin4_code":"150096",
    "gn:asciiname":"Prasbani",
    "gn:country_code":"NP",
    "gn:dem":110,
    "gn:feature_class":"P",
    "gn:feature_code":"PPLL",
    "gn:name":"Prasbani",
    "gn:population":0,
    "gn:timezone":"Asia/Kathmandu",
    "iso:country":"NP",
    "wof:name":"Prasbani",
    "wof:placetype":"locality"
},
  "geometry": {"coordinates":[86.79299999999998,26.61457],"type":"Point"}
}