{
  "type": "Feature",
  "properties": {
    "gn:admin1_code":"CR",
    "gn:admin2_code":"11",
    "gn:admin3_code":"35.0",
    "gn:admin4_code":"350022.0",
    "gn:asciiname":"Muling",
    "gn:country_code":"NP",
    "gn:dem":881,
    "gn:feature_class":"P",
    "gn:feature_code":"PPLL",
    "gn:name":"Muling",
    "gn:population":0,
    "gn:timezone":"Asia/Kathmandu",
    "iso:country":"NP",
    "name:ara_x_preferred":[
        "\u0645\u0648\u0644\u0646\u062c"
    ],
    "name:dan_x_preferred":[
        "Muling"
    ],
    "name:deu_x_preferred":[
        "Muling"
    ],
    "name:fra_x_preferred":[
        "Muling"
    ],
    "name:ita_x_preferred":[
        "Muling"
    ],
    "name:jpn_x_preferred":[
        "\u7a46\u30ea\u30e7\u30a6\u5e02"
    ],
    "name:kik_x_preferred":[
        "Muling"
    ],
    "name:kor_x_preferred":[
        "\ubb34\ub9c1\uc2dc"
    ],
    "name:mlg_x_preferred":[
        "Muling"
    ],
    "name:nor_x_preferred":[
        "Muling"
    ],
    "name:pam_x_preferred":[
        "Muling"
    ],
    "name:rus_x_preferred":[
        "\u041c\u0443\u043b\u0438\u043d"
    ],
    "name:swe_x_preferred":[
        "Muling"
    ],
    "name:urd_x_preferred":[
        "\u0645\u0648\u0644\u0646\u06af"
    ],
    "name:vie_x_preferred":[
        "S\u00f4ng M\u1ee5c L\u0103ng"
    ],
    "name:vie_x_variant":[
        "M\u1ee5c L\u0103ng"
    ],
    "name:zho_x_preferred":[
        "\u7a46\u68f1\u5e02"
    ],
    "wof:name":"Muling",
    "wof:placetype":"locality"
},
  "geometry": {"coordinates":[84.69746000000001,27.68505],"type":"Point"}
}