{
  "type": "Feature",
  "properties": {
    "gn:admin1_code":"00",
    "gn:asciiname":"Guruntol",
    "gn:country_code":"NP",
    "gn:dem":370,
    "gn:feature_class":"P",
    "gn:feature_code":"PPL",
    "gn:name":"Guru\u1e45\u1e6dol",
    "gn:population":0,
    "gn:timezone":"Asia/Kathmandu",
    "iso:country":"NP",
    "name:nep_x_preferred":[
        "Guru\u1e45\u1e6dol"
    ],
    "wof:name":"Guruntol",
    "wof:placetype":"locality"
},
  "geometry": {"coordinates":[85.99308000000001,27.09419],"type":"Point"}
}