{
  "type": "Feature",
  "properties": {
    "gn:admin1_code":"WR",
    "gn:admin2_code":"8",
    "gn:admin3_code":"47",
    "gn:admin4_code":"470016",
    "gn:asciiname":"Baitighatgaun",
    "gn:country_code":"NP",
    "gn:dem":611,
    "gn:feature_class":"P",
    "gn:feature_code":"PPLL",
    "gn:name":"Baitighatgaun",
    "gn:population":0,
    "gn:timezone":"Asia/Kathmandu",
    "iso:country":"NP",
    "wof:name":"Baitighatgaun",
    "wof:placetype":"locality"
},
  "geometry": {"coordinates":[83.94199,27.81829],"type":"Point"}
}