{
  "type": "Feature",
  "properties": {
    "gn:admin1_code":"FR",
    "gn:admin2_code":"14",
    "gn:admin3_code":"70.0",
    "gn:admin4_code":"700008.0",
    "gn:asciiname":"TalloIkda",
    "gn:country_code":"NP",
    "gn:dem":1134,
    "gn:feature_class":"P",
    "gn:feature_code":"PPLL",
    "gn:name":"TalloIkda",
    "gn:population":0,
    "gn:timezone":"Asia/Kathmandu",
    "iso:country":"NP",
    "wof:name":"TalloIkda",
    "wof:placetype":"locality"
},
  "geometry": {"coordinates":[80.55601,29.11258],"type":"Point"}
}