{
  "type": "Feature",
  "properties": {
    "gn:admin1_code":"ER",
    "gn:admin2_code":"7",
    "gn:admin3_code":"7.0",
    "gn:admin4_code":"70033.0",
    "gn:asciiname":"Ramite Malbase",
    "gn:country_code":"NP",
    "gn:dem":1201,
    "gn:feature_class":"P",
    "gn:feature_code":"PPLL",
    "gn:name":"Ramite Malbase",
    "gn:population":0,
    "gn:timezone":"Asia/Kathmandu",
    "iso:country":"NP",
    "wof:name":"Ramite Malbase",
    "wof:placetype":"locality"
},
  "geometry": {"coordinates":[87.29581,27.07808],"type":"Point"}
}