{
  "type": "Feature",
  "properties": {
    "gn:admin1_code":"00",
    "gn:asciiname":"Mauwadada",
    "gn:country_code":"NP",
    "gn:dem":157,
    "gn:feature_class":"P",
    "gn:feature_code":"PPL",
    "gn:name":"Mauw\u0101\u1e0d\u0101\u0303\u1e0d\u0101",
    "gn:population":0,
    "gn:timezone":"Asia/Kathmandu",
    "iso:country":"NP",
    "name:nep_x_preferred":[
        "Mauw\u0101\u1e0d\u0101\u0303\u1e0d\u0101"
    ],
    "wof:name":"Mauwadada",
    "wof:placetype":"locality"
},
  "geometry": {"coordinates":[86.37657,26.78408],"type":"Point"}
}