{
  "type": "Feature",
  "properties": {
    "gn:admin1_code":"MR",
    "gn:admin2_code":"12",
    "gn:admin3_code":"56.0",
    "gn:admin4_code":"560020.0",
    "gn:asciiname":"Pauwakot",
    "gn:country_code":"NP",
    "gn:dem":1103,
    "gn:feature_class":"P",
    "gn:feature_code":"PPLL",
    "gn:name":"Pauwakot",
    "gn:population":0,
    "gn:timezone":"Asia/Kathmandu",
    "iso:country":"NP",
    "wof:name":"Pauwakot",
    "wof:placetype":"locality"
},
  "geometry": {"coordinates":[82.54106,28.01955],"type":"Point"}
}