{
  "type": "Feature",
  "properties": {
    "gn:admin1_code":"00",
    "gn:asciiname":"Thotundada",
    "gn:country_code":"NP",
    "gn:dem":2267,
    "gn:feature_class":"P",
    "gn:feature_code":"PPL",
    "gn:name":"Thotu\u1e45\u1e0d\u0101\u0303\u1e0d\u0101",
    "gn:population":0,
    "gn:timezone":"Asia/Kathmandu",
    "iso:country":"NP",
    "name:und_x_variant":[
        "Thotu\u1e45\u1e0d\u0101\u0303\u1e0d\u0101",
        "Thotu\u1e45\u1e0d\u0101n\u1e0d\u0101"
    ],
    "wof:name":"Thotundada",
    "wof:placetype":"locality"
},
  "geometry": {"coordinates":[85.47648000000002,27.89399],"type":"Point"}
}