{
  "type": "Feature",
  "properties": {
    "gn:admin1_code":"WR",
    "gn:admin2_code":"8",
    "gn:admin3_code":"50.0",
    "gn:admin4_code":"500074.0",
    "gn:asciiname":"Bankatti",
    "gn:country_code":"NP",
    "gn:dem":122,
    "gn:feature_class":"P",
    "gn:feature_code":"PPLL",
    "gn:name":"Bankatti",
    "gn:population":0,
    "gn:timezone":"Asia/Kathmandu",
    "iso:country":"NP",
    "wof:name":"Bankatti",
    "wof:placetype":"locality"
},
  "geometry": {"coordinates":[82.9105,27.63863],"type":"Point"}
}