{
  "type": "Feature",
  "properties": {
    "gn:admin1_code":"MR",
    "gn:admin2_code":"6",
    "gn:admin3_code":"64.0",
    "gn:admin4_code":"640010.0",
    "gn:asciiname":"Madagaun",
    "gn:country_code":"NP",
    "gn:dem":1624,
    "gn:feature_class":"P",
    "gn:feature_code":"PPLL",
    "gn:name":"Madagaun",
    "gn:population":0,
    "gn:timezone":"Asia/Kathmandu",
    "iso:country":"NP",
    "wof:name":"Madagaun",
    "wof:placetype":"locality"
},
  "geometry": {"coordinates":[81.55741,29.18613],"type":"Point"}
}