{
  "type": "Feature",
  "properties": {
    "gn:admin1_code":"FR",
    "gn:admin2_code":"14.0",
    "gn:admin3_code":"69.0",
    "gn:admin4_code":"690051.0",
    "gn:asciiname":"Nardev",
    "gn:country_code":"NP",
    "gn:dem":1206,
    "gn:feature_class":"P",
    "gn:feature_code":"PPLL",
    "gn:name":"Nardev",
    "gn:population":0,
    "gn:timezone":"Asia/Kathmandu",
    "iso:country":"NP",
    "wof:name":"Nardev",
    "wof:placetype":"locality"
},
  "geometry": {"coordinates":[81.33466,28.94882],"type":"Point"}
}