{
  "type": "Feature",
  "properties": {
    "gn:admin1_code":"CR",
    "gn:admin2_code":"5",
    "gn:admin3_code":"22.0",
    "gn:admin4_code":"220022.0",
    "gn:asciiname":"Panchghare",
    "gn:country_code":"NP",
    "gn:dem":1818,
    "gn:feature_class":"P",
    "gn:feature_code":"PPLL",
    "gn:name":"Panchghare",
    "gn:population":0,
    "gn:timezone":"Asia/Kathmandu",
    "iso:country":"NP",
    "wof:name":"Panchghare",
    "wof:placetype":"locality"
},
  "geometry": {"coordinates":[86.11759000000001,27.56725],"type":"Point"}
}