{
  "type": "Feature",
  "properties": {
    "gn:admin1_code":"FR",
    "gn:admin2_code":"14",
    "gn:admin3_code":"68",
    "gn:admin4_code":"680010",
    "gn:asciiname":"Kadapani Goth",
    "gn:country_code":"NP",
    "gn:dem":2127,
    "gn:feature_class":"P",
    "gn:feature_code":"PPLL",
    "gn:name":"Kadapani Goth",
    "gn:population":0,
    "gn:timezone":"Asia/Kathmandu",
    "iso:country":"NP",
    "wof:name":"Kadapani Goth",
    "wof:placetype":"locality"
},
  "geometry": {"coordinates":[81.32637,29.58634],"type":"Point"}
}