{
  "type": "Feature",
  "properties": {
    "gn:admin1_code":"ER",
    "gn:admin2_code":"7.0",
    "gn:admin3_code":"8.0",
    "gn:admin4_code":"80005.0",
    "gn:asciiname":"Bokhim",
    "gn:country_code":"NP",
    "gn:dem":1154,
    "gn:feature_class":"P",
    "gn:feature_code":"PPLL",
    "gn:name":"Bokhim",
    "gn:population":0,
    "gn:timezone":"Asia/Kathmandu",
    "iso:country":"NP",
    "name:ceb_x_preferred":[
        "Bokhim"
    ],
    "name:msa_x_preferred":[
        "Bokhim"
    ],
    "name:nep_x_preferred":[
        "\u092c\u094b\u0916\u093f\u092e"
    ],
    "name:new_x_preferred":[
        "\u092c\u094b\u0916\u093f\u092e"
    ],
    "name:pol_x_preferred":[
        "Bokhim"
    ],
    "wof:name":"Bokhim",
    "wof:placetype":"locality"
},
  "geometry": {"coordinates":[87.70016,27.19076],"type":"Point"}
}