{
  "type": "Feature",
  "properties": {
    "gn:admin1_code":"MR",
    "gn:admin2_code":"12",
    "gn:admin3_code":"52",
    "gn:admin4_code":"520012",
    "gn:asciiname":"Salghari",
    "gn:country_code":"NP",
    "gn:dem":659,
    "gn:feature_class":"P",
    "gn:feature_code":"PPLL",
    "gn:name":"Salghari",
    "gn:population":0,
    "gn:timezone":"Asia/Kathmandu",
    "iso:country":"NP",
    "wof:name":"Salghari",
    "wof:placetype":"locality"
},
  "geometry": {"coordinates":[82.80325999999999,28.08879],"type":"Point"}
}