{
  "type": "Feature",
  "properties": {
    "gn:admin1_code":"FR",
    "gn:admin2_code":"14",
    "gn:admin3_code":"68",
    "gn:admin4_code":"680014",
    "gn:asciiname":"Jharigaun",
    "gn:country_code":"NP",
    "gn:dem":2113,
    "gn:feature_class":"P",
    "gn:feature_code":"PPLL",
    "gn:name":"Jharigaun",
    "gn:population":0,
    "gn:timezone":"Asia/Kathmandu",
    "iso:country":"NP",
    "wof:name":"Jharigaun",
    "wof:placetype":"locality"
},
  "geometry": {"coordinates":[81.29001,29.63598],"type":"Point"}
}