{
  "type": "Feature",
  "properties": {
    "gn:admin1_code":"CR",
    "gn:admin2_code":"5.0",
    "gn:asciiname":"Siundibadada",
    "gn:country_code":"NP",
    "gn:dem":1386,
    "gn:feature_class":"P",
    "gn:feature_code":"PPL",
    "gn:name":"Siundi\u0307\u0304b\u0101\u1e0d\u0101\u0303\u1e0d\u0101",
    "gn:population":0,
    "gn:timezone":"Asia/Kathmandu",
    "iso:country":"NP",
    "name:und_x_variant":[
        "Siundi\u0307\u0304b\u0101\u1e0d\u0101\u0303\u1e0d\u0101",
        "Siund\u012bb\u0101\u1e0d\u0101n\u1e0d\u0101"
    ],
    "wof:name":"Siundibadada",
    "wof:placetype":"locality"
},
  "geometry": {"coordinates":[85.84738,27.37874],"type":"Point"}
}