{
  "type": "Feature",
  "properties": {
    "gn:admin1_code":"CR",
    "gn:admin2_code":"11",
    "gn:admin3_code":"31",
    "gn:admin4_code":"310009.0",
    "gn:asciiname":"Targo",
    "gn:country_code":"NP",
    "gn:dem":1686,
    "gn:feature_class":"P",
    "gn:feature_code":"PPLL",
    "gn:name":"Targo",
    "gn:population":0,
    "gn:timezone":"Asia/Kathmandu",
    "iso:country":"NP",
    "wof:name":"Targo",
    "wof:placetype":"locality"
},
  "geometry": {"coordinates":[85.17731999999999,27.49688],"type":"Point"}
}