{
  "type": "Feature",
  "properties": {
    "gn:admin1_code":"ER",
    "gn:admin2_code":"10.0",
    "gn:admin3_code":"1.0",
    "gn:admin4_code":"10021.0",
    "gn:asciiname":"Pauwa",
    "gn:country_code":"NP",
    "gn:dem":1762,
    "gn:feature_class":"P",
    "gn:feature_code":"PPLL",
    "gn:name":"Pauwa",
    "gn:population":0,
    "gn:timezone":"Asia/Kathmandu",
    "iso:country":"NP",
    "wof:name":"Pauwa",
    "wof:placetype":"locality"
},
  "geometry": {"coordinates":[87.86104,27.4192],"type":"Point"}
}