{
  "type": "Feature",
  "properties": {
    "gn:admin1_code":"ER",
    "gn:admin2_code":"10",
    "gn:admin3_code":"4.0",
    "gn:admin4_code":"40037.0",
    "gn:asciiname":"Suryatol",
    "gn:country_code":"NP",
    "gn:dem":146,
    "gn:feature_class":"P",
    "gn:feature_code":"PPLL",
    "gn:name":"Suryatol",
    "gn:population":0,
    "gn:timezone":"Asia/Kathmandu",
    "iso:country":"NP",
    "wof:name":"Suryatol",
    "wof:placetype":"locality"
},
  "geometry": {"coordinates":[88.15879,26.68183],"type":"Point"}
}