{
  "type": "Feature",
  "properties": {
    "gn:admin1_code":"FR",
    "gn:admin2_code":"9",
    "gn:admin3_code":"73.0",
    "gn:admin4_code":"730019.0",
    "gn:asciiname":"Khetigaun",
    "gn:country_code":"NP",
    "gn:dem":1205,
    "gn:feature_class":"P",
    "gn:feature_code":"PPLL",
    "gn:name":"Khetigaun",
    "gn:population":0,
    "gn:timezone":"Asia/Kathmandu",
    "iso:country":"NP",
    "wof:name":"Khetigaun",
    "wof:placetype":"locality"
},
  "geometry": {"coordinates":[80.33436999999998,29.25248],"type":"Point"}
}