{
  "type": "Feature",
  "properties": {
    "gn:admin1_code":"MR",
    "gn:admin2_code":"6",
    "gn:admin3_code":"64.0",
    "gn:admin4_code":"640019.0",
    "gn:asciiname":"Unichaur",
    "gn:country_code":"NP",
    "gn:dem":1860,
    "gn:feature_class":"P",
    "gn:feature_code":"PPLL",
    "gn:name":"Unichaur",
    "gn:population":0,
    "gn:timezone":"Asia/Kathmandu",
    "iso:country":"NP",
    "wof:name":"Unichaur",
    "wof:placetype":"locality"
},
  "geometry": {"coordinates":[81.76725,29.08251],"type":"Point"}
}