{
  "type": "Feature",
  "properties": {
    "gn:admin1_code":"MR",
    "gn:admin2_code":"2",
    "gn:admin3_code":"61.0",
    "gn:admin4_code":"610017.0",
    "gn:asciiname":"Batkule",
    "gn:country_code":"NP",
    "gn:dem":1340,
    "gn:feature_class":"P",
    "gn:feature_code":"PPLL",
    "gn:name":"Batkule",
    "gn:population":0,
    "gn:timezone":"Asia/Kathmandu",
    "iso:country":"NP",
    "wof:name":"Batkule",
    "wof:placetype":"locality"
},
  "geometry": {"coordinates":[81.93876,28.80951],"type":"Point"}
}