{
  "type": "Feature",
  "properties": {
    "gn:admin1_code":"CR",
    "gn:admin2_code":"1",
    "gn:admin3_code":"28",
    "gn:admin4_code":"280056",
    "gn:asciiname":"Dinggaun",
    "gn:country_code":"NP",
    "gn:dem":1971,
    "gn:feature_class":"P",
    "gn:feature_code":"PPLL",
    "gn:name":"Dinggaun",
    "gn:population":0,
    "gn:timezone":"Asia/Kathmandu",
    "iso:country":"NP",
    "wof:name":"Dinggaun",
    "wof:placetype":"locality"
},
  "geometry": {"coordinates":[85.46145,27.86976],"type":"Point"}
}