{
  "type": "Feature",
  "properties": {
    "gn:admin1_code":"WR",
    "gn:admin2_code":"3",
    "gn:admin3_code":"45.0",
    "gn:admin4_code":"450052.0",
    "gn:asciiname":"Gawa",
    "gn:country_code":"NP",
    "gn:dem":1527,
    "gn:feature_class":"P",
    "gn:feature_code":"PPLL",
    "gn:name":"Gawa",
    "gn:population":0,
    "gn:timezone":"Asia/Kathmandu",
    "iso:country":"NP",
    "name:bar_x_preferred":[
        "Gawa"
    ],
    "name:ceb_x_preferred":[
        "Gawa"
    ],
    "name:swe_x_preferred":[
        "Gawa"
    ],
    "wof:name":"Gawa",
    "wof:placetype":"locality"
},
  "geometry": {"coordinates":[83.60214000000001,28.15378],"type":"Point"}
}