{
  "type": "Feature",
  "properties": {
    "gn:admin1_code":"FR",
    "gn:admin2_code":"14",
    "gn:admin3_code":"69",
    "gn:admin4_code":"690026",
    "gn:asciiname":"Kopchekhet",
    "gn:country_code":"NP",
    "gn:dem":1099,
    "gn:feature_class":"P",
    "gn:feature_code":"PPLL",
    "gn:name":"Kopchekhet",
    "gn:population":0,
    "gn:timezone":"Asia/Kathmandu",
    "iso:country":"NP",
    "wof:name":"Kopchekhet",
    "wof:placetype":"locality"
},
  "geometry": {"coordinates":[81.23698,28.94489],"type":"Point"}
}