{
  "type": "Feature",
  "properties": {
    "gn:admin1_code":"00",
    "gn:asciiname":"Sukhkhad",
    "gn:country_code":"NP",
    "gn:dem":162,
    "gn:feature_class":"P",
    "gn:feature_code":"PPL",
    "gn:name":"Sukhkha\u1e0d",
    "gn:population":0,
    "gn:timezone":"Asia/Kathmandu",
    "iso:country":"NP",
    "name:nep_x_preferred":[
        "Sukhkha\u1e0d"
    ],
    "name:und_x_variant":[
        "Sukhar"
    ],
    "wof:name":"Sukhkhad",
    "wof:placetype":"locality"
},
  "geometry": {"coordinates":[80.95640999999998,28.6745],"type":"Point"}
}