{
  "type": "Feature",
  "properties": {
    "gn:admin1_code":"WR",
    "gn:admin2_code":"8",
    "gn:admin3_code":"47",
    "gn:admin4_code":"470015",
    "gn:asciiname":"Khorbari",
    "gn:country_code":"NP",
    "gn:dem":1338,
    "gn:feature_class":"P",
    "gn:feature_code":"PPLL",
    "gn:name":"Khorbari",
    "gn:population":0,
    "gn:timezone":"Asia/Kathmandu",
    "iso:country":"NP",
    "wof:name":"Khorbari",
    "wof:placetype":"locality"
},
  "geometry": {"coordinates":[83.60723,27.86141],"type":"Point"}
}