{
  "type": "Feature",
  "properties": {
    "gn:admin1_code":"CR",
    "gn:admin2_code":"11",
    "gn:admin3_code":"35.0",
    "gn:admin4_code":"350029.0",
    "gn:asciiname":"Kanchabasti",
    "gn:country_code":"NP",
    "gn:dem":184,
    "gn:feature_class":"P",
    "gn:feature_code":"PPLL",
    "gn:name":"Kanchabasti",
    "gn:population":0,
    "gn:timezone":"Asia/Kathmandu",
    "iso:country":"NP",
    "wof:name":"Kanchabasti",
    "wof:placetype":"locality"
},
  "geometry": {"coordinates":[84.34161999999998,27.59883],"type":"Point"}
}