{
  "type": "Feature",
  "properties": {
    "gn:admin1_code":"ER",
    "gn:admin2_code":"10.0",
    "gn:admin3_code":"1.0",
    "gn:admin4_code":"10042.0",
    "gn:asciiname":"Maghu Thumka",
    "gn:country_code":"NP",
    "gn:dem":4277,
    "gn:feature_class":"P",
    "gn:feature_code":"PPLL",
    "gn:name":"Maghu Thumka",
    "gn:population":0,
    "gn:timezone":"Asia/Kathmandu",
    "iso:country":"NP",
    "wof:name":"Maghu Thumka",
    "wof:placetype":"locality"
},
  "geometry": {"coordinates":[88.02261999999997,27.41942],"type":"Point"}
}