{
  "type": "Feature",
  "properties": {
    "gn:admin1_code":"MR",
    "gn:admin2_code":"6",
    "gn:admin3_code":"62.0",
    "gn:admin4_code":"620008.0",
    "gn:asciiname":"Baijibara",
    "gn:country_code":"NP",
    "gn:dem":3880,
    "gn:feature_class":"P",
    "gn:feature_code":"PPLL",
    "gn:name":"Baijibara",
    "gn:population":0,
    "gn:timezone":"Asia/Kathmandu",
    "iso:country":"NP",
    "wof:name":"Baijibara",
    "wof:placetype":"locality"
},
  "geometry": {"coordinates":[83.00213000000002,28.91394],"type":"Point"}
}