{
  "type": "Feature",
  "properties": {
    "gn:admin1_code":"CR",
    "gn:admin2_code":"1",
    "gn:admin3_code":"25",
    "gn:admin4_code":"250022",
    "gn:asciiname":"Bhisdanda",
    "gn:country_code":"NP",
    "gn:dem":1524,
    "gn:feature_class":"P",
    "gn:feature_code":"PPLL",
    "gn:name":"Bhisdanda",
    "gn:population":0,
    "gn:timezone":"Asia/Kathmandu",
    "iso:country":"NP",
    "wof:name":"Bhisdanda",
    "wof:placetype":"locality"
},
  "geometry": {"coordinates":[85.31614999999999,27.48931],"type":"Point"}
}