{
  "type": "Feature",
  "properties": {
    "gn:admin1_code":"MR",
    "gn:admin2_code":"2",
    "gn:admin3_code":"61.0",
    "gn:admin4_code":"610026.0",
    "gn:asciiname":"Pipaltada",
    "gn:country_code":"NP",
    "gn:dem":1218,
    "gn:feature_class":"P",
    "gn:feature_code":"PPLL",
    "gn:name":"Pipaltada",
    "gn:population":0,
    "gn:timezone":"Asia/Kathmandu",
    "iso:country":"NP",
    "wof:name":"Pipaltada",
    "wof:placetype":"locality"
},
  "geometry": {"coordinates":[81.94225,28.74317000000001],"type":"Point"}
}