{
  "type": "Feature",
  "properties": {
    "gn:admin1_code":"MR",
    "gn:admin2_code":"12",
    "gn:admin3_code":"54",
    "gn:admin4_code":"540029",
    "gn:asciiname":"Dobato Pakho",
    "gn:country_code":"NP",
    "gn:dem":1297,
    "gn:feature_class":"P",
    "gn:feature_code":"PPLL",
    "gn:name":"Dobato Pakho",
    "gn:population":0,
    "gn:timezone":"Asia/Kathmandu",
    "iso:country":"NP",
    "wof:name":"Dobato Pakho",
    "wof:placetype":"locality"
},
  "geometry": {"coordinates":[82.53006999999999,28.66104],"type":"Point"}
}