{
  "type": "Feature",
  "properties": {
    "gn:admin1_code":"CR",
    "gn:admin2_code":"5",
    "gn:admin3_code":"17.0",
    "gn:admin4_code":"170084.0",
    "gn:asciiname":"Mahendranagar",
    "gn:country_code":"NP",
    "gn:dem":122,
    "gn:feature_class":"P",
    "gn:feature_code":"PPLL",
    "gn:name":"Mahendranagar",
    "gn:population":0,
    "gn:timezone":"Asia/Kathmandu",
    "iso:country":"NP",
    "name:hin_x_preferred":[
        "\u092e\u0939\u0947\u0928\u094d\u0926\u094d\u0930\u0928\u0917\u0930 \u0928\u0917\u0930\u092a\u093e\u0932\u093f\u0915\u093e"
    ],
    "name:jpn_x_preferred":[
        "\u30de\u30d8\u30f3\u30c9\u30e9\u30ca\u30ac\u30eb"
    ],
    "wof:name":"Mahendranagar",
    "wof:placetype":"locality"
},
  "geometry": {"coordinates":[85.97246,26.86306],"type":"Point"}
}