{
  "type": "Feature",
  "properties": {
    "gn:admin1_code":"MR",
    "gn:admin2_code":"2.0",
    "gn:admin3_code":"59.0",
    "gn:admin4_code":"590014.0",
    "gn:asciiname":"Timure",
    "gn:country_code":"NP",
    "gn:dem":1740,
    "gn:feature_class":"P",
    "gn:feature_code":"PPLL",
    "gn:name":"Timure",
    "gn:population":0,
    "gn:timezone":"Asia/Kathmandu",
    "iso:country":"NP",
    "name:deu_x_preferred":[
        "Timure"
    ],
    "name:fra_x_preferred":[
        "Timure"
    ],
    "name:mai_x_preferred":[
        "\u091f\u093f\u092e\u0941\u0930\u0947"
    ],
    "name:msa_x_preferred":[
        "Timure"
    ],
    "name:nep_x_preferred":[
        "\u091f\u093f\u092e\u0941\u0930\u0947"
    ],
    "name:new_x_preferred":[
        "\u091f\u093f\u092e\u0941\u0930\u0947"
    ],
    "name:pol_x_preferred":[
        "Timure"
    ],
    "wof:name":"Timure",
    "wof:placetype":"locality"
},
  "geometry": {"coordinates":[81.97309,28.39695],"type":"Point"}
}