{
  "type": "Feature",
  "properties": {
    "gn:admin1_code":"WR",
    "gn:admin2_code":"8",
    "gn:admin3_code":"51.0",
    "gn:admin4_code":"510026.0",
    "gn:asciiname":"Dhab",
    "gn:country_code":"NP",
    "gn:dem":873,
    "gn:feature_class":"P",
    "gn:feature_code":"PPLL",
    "gn:name":"Dhab",
    "gn:population":0,
    "gn:timezone":"Asia/Kathmandu",
    "iso:country":"NP",
    "wof:name":"Dhab",
    "wof:placetype":"locality"
},
  "geometry": {"coordinates":[83.26477,27.92003],"type":"Point"}
}