{
  "type": "Feature",
  "properties": {
    "gn:admin1_code":"MR",
    "gn:admin2_code":"12",
    "gn:admin3_code":"53",
    "gn:admin4_code":"530006",
    "gn:asciiname":"Munaghare",
    "gn:country_code":"NP",
    "gn:dem":1190,
    "gn:feature_class":"P",
    "gn:feature_code":"PPLL",
    "gn:name":"Munaghare",
    "gn:population":0,
    "gn:timezone":"Asia/Kathmandu",
    "iso:country":"NP",
    "wof:name":"Munaghare",
    "wof:placetype":"locality"
},
  "geometry": {"coordinates":[82.41785,28.16209000000001],"type":"Point"}
}