{
  "type": "Feature",
  "properties": {
    "gn:admin1_code":"MR",
    "gn:admin2_code":"6",
    "gn:admin3_code":"65",
    "gn:admin4_code":"650009",
    "gn:asciiname":"Birat Temple",
    "gn:country_code":"NP",
    "gn:dem":3539,
    "gn:feature_class":"P",
    "gn:feature_code":"PPLL",
    "gn:name":"Birat Temple",
    "gn:population":0,
    "gn:timezone":"Asia/Kathmandu",
    "iso:country":"NP",
    "wof:name":"Birat Temple",
    "wof:placetype":"locality"
},
  "geometry": {"coordinates":[81.95676,29.44644000000001],"type":"Point"}
}