{
  "type": "Feature",
  "properties": {
    "gn:admin1_code":"MR",
    "gn:admin2_code":"6",
    "gn:admin3_code":"65",
    "gn:admin4_code":"650021",
    "gn:asciiname":"Rinrakya",
    "gn:country_code":"NP",
    "gn:dem":2673,
    "gn:feature_class":"P",
    "gn:feature_code":"PPLL",
    "gn:name":"Rinrakya",
    "gn:population":0,
    "gn:timezone":"Asia/Kathmandu",
    "iso:country":"NP",
    "wof:name":"Rinrakya",
    "wof:placetype":"locality"
},
  "geometry": {"coordinates":[81.93021,29.54506],"type":"Point"}
}