{
  "type": "Feature",
  "properties": {
    "gn:admin1_code":"ER",
    "gn:admin2_code":"13.0",
    "gn:admin3_code":"14.0",
    "gn:admin4_code":"140024.0",
    "gn:asciiname":"Khecha",
    "gn:country_code":"NP",
    "gn:dem":619,
    "gn:feature_class":"P",
    "gn:feature_code":"PPLL",
    "gn:name":"Khecha",
    "gn:population":0,
    "gn:timezone":"Asia/Kathmandu",
    "iso:country":"NP",
    "wof:name":"Khecha",
    "wof:placetype":"locality"
},
  "geometry": {"coordinates":[87.11243,26.90203],"type":"Point"}
}