{
  "type": "Feature",
  "properties": {
    "gn:admin1_code":"MR",
    "gn:admin2_code":"2",
    "gn:admin3_code":"60.0",
    "gn:admin4_code":"600010.0",
    "gn:asciiname":"Kami Tol",
    "gn:country_code":"NP",
    "gn:dem":1400,
    "gn:feature_class":"P",
    "gn:feature_code":"PPLL",
    "gn:name":"Kami Tol",
    "gn:population":0,
    "gn:timezone":"Asia/Kathmandu",
    "iso:country":"NP",
    "wof:name":"Kami Tol",
    "wof:placetype":"locality"
},
  "geometry": {"coordinates":[81.78676999999998,28.84034],"type":"Point"}
}