{
  "type": "Feature",
  "properties": {
    "gn:admin1_code":"WR",
    "gn:admin2_code":"4",
    "gn:admin3_code":"37",
    "gn:admin4_code":"370009",
    "gn:asciiname":"Lamiswanra",
    "gn:country_code":"NP",
    "gn:dem":1164,
    "gn:feature_class":"P",
    "gn:feature_code":"PPLL",
    "gn:name":"Lamiswanra",
    "gn:population":0,
    "gn:timezone":"Asia/Kathmandu",
    "iso:country":"NP",
    "wof:name":"Lamiswanra",
    "wof:placetype":"locality"
},
  "geometry": {"coordinates":[84.4808,28.14639],"type":"Point"}
}