{
  "type": "Feature",
  "properties": {
    "gn:admin1_code":"ER",
    "gn:admin2_code":"13",
    "gn:admin3_code":"12",
    "gn:admin4_code":"120021",
    "gn:asciiname":"Buldanda",
    "gn:country_code":"NP",
    "gn:dem":2078,
    "gn:feature_class":"P",
    "gn:feature_code":"PPLL",
    "gn:name":"Buldanda",
    "gn:population":0,
    "gn:timezone":"Asia/Kathmandu",
    "iso:country":"NP",
    "wof:name":"Buldanda",
    "wof:placetype":"locality"
},
  "geometry": {"coordinates":[86.36408,27.32576],"type":"Point"}
}