{
  "type": "Feature",
  "properties": {
    "gn:admin1_code":"CR",
    "gn:admin2_code":"5",
    "gn:admin3_code":"19",
    "gn:admin4_code":"190043.0",
    "gn:asciiname":"Kaltol",
    "gn:country_code":"NP",
    "gn:dem":139,
    "gn:feature_class":"P",
    "gn:feature_code":"PPLL",
    "gn:name":"Kaltol",
    "gn:population":0,
    "gn:timezone":"Asia/Kathmandu",
    "iso:country":"NP",
    "wof:name":"Kaltol",
    "wof:placetype":"locality"
},
  "geometry": {"coordinates":[85.65451999999998,27.01025],"type":"Point"}
}