{
  "type": "Feature",
  "properties": {
    "gn:admin1_code":"CR",
    "gn:admin2_code":"5",
    "gn:admin3_code":"20",
    "gn:admin4_code":"200014",
    "gn:asciiname":"Sarutar",
    "gn:country_code":"NP",
    "gn:dem":739,
    "gn:feature_class":"P",
    "gn:feature_code":"PPLL",
    "gn:name":"Sarutar",
    "gn:population":0,
    "gn:timezone":"Asia/Kathmandu",
    "iso:country":"NP",
    "wof:name":"Sarutar",
    "wof:placetype":"locality"
},
  "geometry": {"coordinates":[86.15563,27.22712000000001],"type":"Point"}
}