{
  "type": "Feature",
  "properties": {
    "gn:admin1_code":"CR",
    "gn:admin2_code":"5",
    "gn:admin3_code":"20",
    "gn:admin4_code":"200007",
    "gn:asciiname":"Kalapani",
    "gn:country_code":"NP",
    "gn:dem":657,
    "gn:feature_class":"P",
    "gn:feature_code":"PPLL",
    "gn:name":"Kalapani",
    "gn:population":0,
    "gn:timezone":"Asia/Kathmandu",
    "iso:country":"NP",
    "wof:name":"Kalapani",
    "wof:placetype":"locality"
},
  "geometry": {"coordinates":[86.06126,27.08183],"type":"Point"}
}