{
  "type": "Feature",
  "properties": {
    "gn:admin1_code":"00",
    "gn:asciiname":"Jaidun",
    "gn:country_code":"NP",
    "gn:dem":2594,
    "gn:feature_class":"P",
    "gn:feature_code":"PPL",
    "gn:name":"Jaidu\u1e45",
    "gn:population":0,
    "gn:timezone":"Asia/Kathmandu",
    "iso:country":"NP",
    "wof:name":"Jaidun",
    "wof:placetype":"locality"
},
  "geometry": {"coordinates":[86.51485,27.46105],"type":"Point"}
}