{
  "type": "Feature",
  "properties": {
    "gn:admin1_code":"CR",
    "gn:admin2_code":"5",
    "gn:admin3_code":"22.0",
    "gn:admin4_code":"220007.0",
    "gn:asciiname":"Masing",
    "gn:country_code":"NP",
    "gn:dem":2688,
    "gn:feature_class":"P",
    "gn:feature_code":"PPLL",
    "gn:name":"Masing",
    "gn:population":0,
    "gn:timezone":"Asia/Kathmandu",
    "iso:country":"NP",
    "name:est_x_preferred":[
        "Masing"
    ],
    "name:rus_x_preferred":[
        "\u041c\u0430\u0437\u0438\u043d\u0433"
    ],
    "wof:name":"Masing",
    "wof:placetype":"locality"
},
  "geometry": {"coordinates":[86.05096999999998,27.85475],"type":"Point"}
}