{
  "type": "Feature",
  "properties": {
    "gn:admin1_code":"CR",
    "gn:admin2_code":"11",
    "gn:admin3_code":"31",
    "gn:admin4_code":"310006",
    "gn:asciiname":"Purano Kisedi",
    "gn:country_code":"NP",
    "gn:dem":910,
    "gn:feature_class":"P",
    "gn:feature_code":"PPLL",
    "gn:name":"Purano Kisedi",
    "gn:population":0,
    "gn:timezone":"Asia/Kathmandu",
    "iso:country":"NP",
    "wof:name":"Purano Kisedi",
    "wof:placetype":"locality"
},
  "geometry": {"coordinates":[85.01775000000001,27.4922],"type":"Point"}
}