{
  "type": "Feature",
  "properties": {
    "gn:admin1_code":"FR",
    "gn:admin2_code":"9",
    "gn:admin3_code":"74",
    "gn:admin4_code":"740029",
    "gn:asciiname":"Asurketi",
    "gn:country_code":"NP",
    "gn:dem":1684,
    "gn:feature_class":"P",
    "gn:feature_code":"PPLL",
    "gn:name":"Asurketi",
    "gn:population":0,
    "gn:timezone":"Asia/Kathmandu",
    "iso:country":"NP",
    "wof:name":"Asurketi",
    "wof:placetype":"locality"
},
  "geometry": {"coordinates":[80.70423000000002,29.56487000000001],"type":"Point"}
}