{
  "type": "Feature",
  "properties": {
    "gn:admin1_code":"CR",
    "gn:admin2_code":"5",
    "gn:admin3_code":"22.0",
    "gn:admin4_code":"220028.0",
    "gn:asciiname":"Kade",
    "gn:country_code":"NP",
    "gn:dem":2496,
    "gn:feature_class":"P",
    "gn:feature_code":"PPLL",
    "gn:name":"Kade",
    "gn:population":0,
    "gn:timezone":"Asia/Kathmandu",
    "iso:country":"NP",
    "wof:name":"Kade",
    "wof:placetype":"locality"
},
  "geometry": {"coordinates":[85.96311999999998,27.60703],"type":"Point"}
}