{
  "type": "Feature",
  "properties": {
    "gn:admin1_code":"CR",
    "gn:admin2_code":"5",
    "gn:admin3_code":"22.0",
    "gn:admin4_code":"220028.0",
    "gn:asciiname":"Kade",
    "gn:country_code":"NP",
    "gn:dem":2496,
    "gn:feature_class":"P",
    "gn:feature_code":"PPLL",
    "gn:name":"Kade",
    "gn:population":0,
    "gn:timezone":"Asia/Kathmandu",
    "iso:country":"NP",
    "name:ceb_x_preferred":[
        "Kade"
    ],
    "name:deu_x_preferred":[
        "Kade"
    ],
    "name:epo_x_preferred":[
        "Kade"
    ],
    "name:fas_x_preferred":[
        "\u06a9\u0627\u062f\u0647"
    ],
    "name:ita_x_preferred":[
        "Kade"
    ],
    "name:kaz_x_preferred":[
        "\u041a\u0430\u0434\u0435"
    ],
    "name:mkd_x_preferred":[
        "\u041a\u0430\u0434\u0435"
    ],
    "name:nld_x_preferred":[
        "Kade"
    ],
    "name:ron_x_preferred":[
        "Kade"
    ],
    "name:rus_x_preferred":[
        "\u041a\u0430\u0434\u0435"
    ],
    "name:uzb_x_preferred":[
        "Kade"
    ],
    "name:vol_x_preferred":[
        "Kade"
    ],
    "wof:name":"Kade",
    "wof:placetype":"locality"
},
  "geometry": {"coordinates":[85.96311999999998,27.60703],"type":"Point"}
}