{
  "type": "Feature",
  "properties": {
    "gn:admin1_code":"WR",
    "gn:admin2_code":"8",
    "gn:admin3_code":"50.0",
    "gn:admin4_code":"500073.0",
    "gn:asciiname":"Semari",
    "gn:country_code":"NP",
    "gn:dem":93,
    "gn:feature_class":"P",
    "gn:feature_code":"PPLL",
    "gn:name":"Semari",
    "gn:population":0,
    "gn:timezone":"Asia/Kathmandu",
    "iso:country":"NP",
    "wof:name":"Semari",
    "wof:placetype":"locality"
},
  "geometry": {"coordinates":[82.97627,27.46748],"type":"Point"}
}