{
  "type": "Feature",
  "properties": {
    "gn:admin1_code":"CR",
    "gn:admin2_code":"11",
    "gn:admin3_code":"34",
    "gn:admin4_code":"340007",
    "gn:asciiname":"Barwa",
    "gn:country_code":"NP",
    "gn:dem":93,
    "gn:feature_class":"P",
    "gn:feature_code":"PPLL",
    "gn:name":"Barwa",
    "gn:population":0,
    "gn:timezone":"Asia/Kathmandu",
    "iso:country":"NP",
    "name:deu_x_preferred":[
        "Barwa"
    ],
    "name:slv_x_preferred":[
        "Barwa"
    ],
    "wof:name":"Barwa",
    "wof:placetype":"locality"
},
  "geometry": {"coordinates":[84.83532,27.10172],"type":"Point"}
}