{
  "type": "Feature",
  "properties": {
    "gn:admin1_code":"WR",
    "gn:admin2_code":"3",
    "gn:admin3_code":"44",
    "gn:admin4_code":"440046",
    "gn:asciiname":"Sadhane",
    "gn:country_code":"NP",
    "gn:dem":906,
    "gn:feature_class":"P",
    "gn:feature_code":"PPLL",
    "gn:name":"Sadhane",
    "gn:population":0,
    "gn:timezone":"Asia/Kathmandu",
    "iso:country":"NP",
    "wof:name":"Sadhane",
    "wof:placetype":"locality"
},
  "geometry": {"coordinates":[83.67079,28.06575],"type":"Point"}
}