{
  "type": "Feature",
  "properties": {
    "gn:admin1_code":"WR",
    "gn:admin2_code":"4",
    "gn:admin3_code":"36.0",
    "gn:admin4_code":"360038.0",
    "gn:asciiname":"Lapu",
    "gn:country_code":"NP",
    "gn:dem":1686,
    "gn:feature_class":"P",
    "gn:feature_code":"PPLL",
    "gn:name":"Lapu",
    "gn:population":0,
    "gn:timezone":"Asia/Kathmandu",
    "iso:country":"NP",
    "name:ceb_x_preferred":[
        "Lapu"
    ],
    "name:mai_x_preferred":[
        "\u0932\u092a\u0941"
    ],
    "name:msa_x_preferred":[
        "Lapu"
    ],
    "name:new_x_preferred":[
        "\u0932\u093e\u092a\u0941"
    ],
    "name:pol_x_preferred":[
        "Lapu"
    ],
    "name:urd_x_preferred":[
        "\u0644\u0627\u067e\u0648"
    ],
    "wof:name":"Lapu",
    "wof:placetype":"locality"
},
  "geometry": {"coordinates":[84.86046999999998,28.18235],"type":"Point"}
}