{
  "type": "Feature",
  "properties": {
    "gn:admin1_code":"WR",
    "gn:admin2_code":"4",
    "gn:admin3_code":"36.0",
    "gn:admin4_code":"360026.0",
    "gn:asciiname":"Torkekharka",
    "gn:country_code":"NP",
    "gn:dem":2667,
    "gn:feature_class":"P",
    "gn:feature_code":"PPLL",
    "gn:name":"Torkekharka",
    "gn:population":0,
    "gn:timezone":"Asia/Kathmandu",
    "iso:country":"NP",
    "wof:name":"Torkekharka",
    "wof:placetype":"locality"
},
  "geometry": {"coordinates":[84.69541,28.25002000000001],"type":"Point"}
}