{
  "type": "Feature",
  "properties": {
    "gn:admin1_code":"00",
    "gn:asciiname":"Dadabari",
    "gn:country_code":"NP",
    "gn:dem":153,
    "gn:feature_class":"P",
    "gn:feature_code":"PPL",
    "gn:name":"\u1e0c\u0101\u0303\u1e0d\u0101b\u0101ri\u0307\u0304",
    "gn:population":0,
    "gn:timezone":"Asia/Kathmandu",
    "iso:country":"NP",
    "name:nep_x_preferred":[
        "\u1e0c\u0101\u0303\u1e0d\u0101b\u0101ri\u0307\u0304"
    ],
    "wof:name":"Dadabari",
    "wof:placetype":"locality"
},
  "geometry": {"coordinates":[86.97538,26.8134],"type":"Point"}
}