{
  "type": "Feature",
  "properties": {
    "gn:admin1_code":"CR",
    "gn:admin2_code":"11",
    "gn:admin3_code":"31",
    "gn:admin4_code":"310019",
    "gn:asciiname":"Puyale",
    "gn:country_code":"NP",
    "gn:dem":509,
    "gn:feature_class":"P",
    "gn:feature_code":"PPLL",
    "gn:name":"Puyale",
    "gn:population":0,
    "gn:timezone":"Asia/Kathmandu",
    "iso:country":"NP",
    "wof:name":"Puyale",
    "wof:placetype":"locality"
},
  "geometry": {"coordinates":[85.12349,27.37119],"type":"Point"}
}