{
  "type": "Feature",
  "properties": {
    "gn:admin1_code":"WR",
    "gn:admin2_code":"8",
    "gn:admin3_code":"47",
    "gn:admin4_code":"470031.0",
    "gn:asciiname":"Dewaglri Chull",
    "gn:country_code":"NP",
    "gn:dem":1259,
    "gn:feature_class":"P",
    "gn:feature_code":"PPLL",
    "gn:name":"Dewaglri Chull",
    "gn:population":0,
    "gn:timezone":"Asia/Kathmandu",
    "iso:country":"NP",
    "wof:name":"Dewaglri Chull",
    "wof:placetype":"locality"
},
  "geometry": {"coordinates":[83.65015,27.79581],"type":"Point"}
}