{
  "type": "Feature",
  "properties": {
    "gn:admin1_code":"WR",
    "gn:admin2_code":"3",
    "gn:admin3_code":"44",
    "gn:admin4_code":"440040",
    "gn:asciiname":"Raniswara",
    "gn:country_code":"NP",
    "gn:dem":1177,
    "gn:feature_class":"P",
    "gn:feature_code":"PPLL",
    "gn:name":"Raniswara",
    "gn:population":0,
    "gn:timezone":"Asia/Kathmandu",
    "iso:country":"NP",
    "wof:name":"Raniswara",
    "wof:placetype":"locality"
},
  "geometry": {"coordinates":[83.73681999999999,28.21768],"type":"Point"}
}