{
  "type": "Feature",
  "properties": {
    "gn:admin1_code":"WR",
    "gn:admin2_code":"8",
    "gn:admin3_code":"48",
    "gn:admin4_code":"480013",
    "gn:asciiname":"Keramtar",
    "gn:country_code":"NP",
    "gn:dem":369,
    "gn:feature_class":"P",
    "gn:feature_code":"PPLL",
    "gn:name":"Keramtar",
    "gn:population":0,
    "gn:timezone":"Asia/Kathmandu",
    "iso:country":"NP",
    "wof:name":"Keramtar",
    "wof:placetype":"locality"
},
  "geometry": {"coordinates":[84.08189,27.85186],"type":"Point"}
}