{
  "type": "Feature",
  "properties": {
    "gn:admin1_code":"ER",
    "gn:admin2_code":"10",
    "gn:admin3_code":"4.0",
    "gn:admin4_code":"40034.0",
    "gn:asciiname":"Kadogaun",
    "gn:country_code":"NP",
    "gn:dem":84,
    "gn:feature_class":"P",
    "gn:feature_code":"PPLL",
    "gn:name":"Kadogaun",
    "gn:population":0,
    "gn:timezone":"Asia/Kathmandu",
    "iso:country":"NP",
    "wof:name":"Kadogaun",
    "wof:placetype":"locality"
},
  "geometry": {"coordinates":[87.79621999999998,26.50496],"type":"Point"}
}