{
  "type": "Feature",
  "properties": {
    "gn:admin1_code":"MR",
    "gn:admin2_code":"12",
    "gn:admin3_code":"53",
    "gn:admin4_code":"530032",
    "gn:asciiname":"Masinabang",
    "gn:country_code":"NP",
    "gn:dem":1420,
    "gn:feature_class":"P",
    "gn:feature_code":"PPLL",
    "gn:name":"Masinabang",
    "gn:population":0,
    "gn:timezone":"Asia/Kathmandu",
    "iso:country":"NP",
    "wof:name":"Masinabang",
    "wof:placetype":"locality"
},
  "geometry": {"coordinates":[82.56820999999999,28.17113],"type":"Point"}
}