{
  "type": "Feature",
  "properties": {
    "gn:admin1_code":"ER",
    "gn:admin2_code":"13",
    "gn:admin3_code":"12",
    "gn:admin4_code":"120031",
    "gn:asciiname":"Bhulkegaun",
    "gn:country_code":"NP",
    "gn:dem":575,
    "gn:feature_class":"P",
    "gn:feature_code":"PPLL",
    "gn:name":"Bhulkegaun",
    "gn:population":0,
    "gn:timezone":"Asia/Kathmandu",
    "iso:country":"NP",
    "wof:name":"Bhulkegaun",
    "wof:placetype":"locality"
},
  "geometry": {"coordinates":[86.41476,27.2438],"type":"Point"}
}