{
  "type": "Feature",
  "properties": {
    "gn:admin1_code":"MR",
    "gn:admin2_code":"6",
    "gn:admin3_code":"65",
    "gn:admin4_code":"650019",
    "gn:asciiname":"Tharpa",
    "gn:country_code":"NP",
    "gn:dem":2217,
    "gn:feature_class":"P",
    "gn:feature_code":"PPLL",
    "gn:name":"Tharpa",
    "gn:population":0,
    "gn:timezone":"Asia/Kathmandu",
    "iso:country":"NP",
    "wof:name":"Tharpa",
    "wof:placetype":"locality"
},
  "geometry": {"coordinates":[82.18468,29.55982],"type":"Point"}
}