{
  "type": "Feature",
  "properties": {
    "gn:admin1_code":"MR",
    "gn:admin2_code":"2.0",
    "gn:admin3_code":"57.0",
    "gn:admin4_code":"570003.0",
    "gn:asciiname":"Halkarapurwa",
    "gn:country_code":"NP",
    "gn:dem":140,
    "gn:feature_class":"P",
    "gn:feature_code":"PPLL",
    "gn:name":"Halkarapurwa",
    "gn:population":0,
    "gn:timezone":"Asia/Kathmandu",
    "iso:country":"NP",
    "wof:name":"Halkarapurwa",
    "wof:placetype":"locality"
},
  "geometry": {"coordinates":[81.71263,28.06129],"type":"Point"}
}