{
  "type": "Feature",
  "properties": {
    "gn:admin1_code":"CR",
    "gn:admin2_code":"1",
    "gn:admin3_code":"24.0",
    "gn:admin4_code":"240071.0",
    "gn:asciiname":"Khawa",
    "gn:country_code":"NP",
    "gn:dem":1317,
    "gn:feature_class":"P",
    "gn:feature_code":"PPLL",
    "gn:name":"Khawa",
    "gn:population":0,
    "gn:timezone":"Asia/Kathmandu",
    "iso:country":"NP",
    "name:bih_x_preferred":[
        "\u0916\u093e\u0935\u093e"
    ],
    "name:ceb_x_preferred":[
        "Khawa"
    ],
    "name:mai_x_preferred":[
        "\u0916\u093e\u0935\u093e"
    ],
    "name:msa_x_preferred":[
        "Khawa"
    ],
    "name:nep_x_preferred":[
        "\u0916\u093e\u0935\u093e"
    ],
    "name:new_x_preferred":[
        "\u0916\u0935\u093e"
    ],
    "name:pol_x_preferred":[
        "Khawa"
    ],
    "wof:name":"Khawa",
    "wof:placetype":"locality"
},
  "geometry": {"coordinates":[85.58904,27.63116],"type":"Point"}
}