{
  "type": "Feature",
  "properties": {
    "gn:admin1_code":"MR",
    "gn:admin2_code":"6.0",
    "gn:asciiname":"Phoi Mahadev",
    "gn:country_code":"NP",
    "gn:dem":3141,
    "gn:feature_class":"P",
    "gn:feature_code":"PPLL",
    "gn:name":"Phoi Mahadev",
    "gn:population":0,
    "gn:timezone":"Asia/Kathmandu",
    "iso:country":"NP",
    "name:dty_x_preferred":[
        "\u092b\u094b\u0908\u092e\u0939\u093e\u0926\u0947\u0935"
    ],
    "name:mai_x_preferred":[
        "\u092b\u094b\u0908\u092e\u0939\u093e\u0926\u0947\u0935"
    ],
    "name:msa_x_preferred":[
        "Phoi Mahadev"
    ],
    "name:nep_x_preferred":[
        "\u092b\u094b\u0908\u092e\u0939\u093e\u0926\u0947\u0935"
    ],
    "name:pol_x_preferred":[
        "Phoi Mahadev"
    ],
    "wof:name":"Phoi Mahadev",
    "wof:placetype":"locality"
},
  "geometry": {"coordinates":[81.86099,29.20327],"type":"Point"}
}