{
  "type": "Feature",
  "properties": {
    "gn:admin1_code":"WR",
    "gn:admin2_code":"4",
    "gn:admin3_code":"40.0",
    "gn:admin4_code":"400045.0",
    "gn:asciiname":"Bhalam",
    "gn:country_code":"NP",
    "gn:dem":946,
    "gn:feature_class":"P",
    "gn:feature_code":"PPLL",
    "gn:name":"Bhalam",
    "gn:population":0,
    "gn:timezone":"Asia/Kathmandu",
    "iso:country":"NP",
    "name:ceb_x_preferred":[
        "Valam"
    ],
    "name:fra_x_preferred":[
        "Valam"
    ],
    "name:mai_x_preferred":[
        "\u092d\u0932\u093e\u092e"
    ],
    "name:msa_x_preferred":[
        "Valam"
    ],
    "name:nep_x_preferred":[
        "\u092d\u0932\u093e\u092e"
    ],
    "name:new_x_preferred":[
        "\u092d\u093e\u0932\u092e"
    ],
    "name:pol_x_preferred":[
        "Valam"
    ],
    "wof:name":"Bhalam",
    "wof:placetype":"locality"
},
  "geometry": {"coordinates":[83.99719,28.24942],"type":"Point"}
}