{
  "type": "Feature",
  "properties": {
    "gn:admin1_code":"ER",
    "gn:admin2_code":"10",
    "gn:admin3_code":"3.0",
    "gn:admin4_code":"30002.0",
    "gn:asciiname":"Bhalukhop",
    "gn:country_code":"NP",
    "gn:dem":440,
    "gn:feature_class":"P",
    "gn:feature_code":"PPLL",
    "gn:name":"Bhalukhop",
    "gn:population":0,
    "gn:timezone":"Asia/Kathmandu",
    "iso:country":"NP",
    "wof:name":"Bhalukhop",
    "wof:placetype":"locality"
},
  "geometry": {"coordinates":[87.74165000000001,26.73762],"type":"Point"}
}