{
  "type": "Feature",
  "properties": {
    "gn:admin1_code":"ER",
    "gn:admin2_code":"13",
    "gn:admin3_code":"11",
    "gn:admin4_code":"110027",
    "gn:asciiname":"Bhalukhop",
    "gn:country_code":"NP",
    "gn:dem":2167,
    "gn:feature_class":"P",
    "gn:feature_code":"PPLL",
    "gn:name":"Bhalukhop",
    "gn:population":0,
    "gn:timezone":"Asia/Kathmandu",
    "iso:country":"NP",
    "wof:name":"Bhalukhop",
    "wof:placetype":"locality"
},
  "geometry": {"coordinates":[86.63285999999999,27.42924],"type":"Point"}
}