{
  "type": "Feature",
  "properties": {
    "gn:admin1_code":"FR",
    "gn:admin2_code":"9",
    "gn:admin3_code":"74",
    "gn:admin4_code":"740052",
    "gn:asciiname":"Mad",
    "gn:country_code":"NP",
    "gn:dem":1831,
    "gn:feature_class":"P",
    "gn:feature_code":"PPLL",
    "gn:name":"Mad",
    "gn:population":0,
    "gn:timezone":"Asia/Kathmandu",
    "iso:country":"NP",
    "name:dan_x_preferred":[
        "Mad"
    ],
    "name:deu_x_preferred":[
        "Mad"
    ],
    "name:fin_x_preferred":[
        "Mad"
    ],
    "name:hun_x_preferred":[
        "MAD"
    ],
    "name:nor_x_preferred":[
        "MAD"
    ],
    "name:por_x_preferred":[
        "Mad"
    ],
    "name:tur_x_preferred":[
        "Mad"
    ],
    "name:yid_x_preferred":[
        "\u05de\u05d0\u05d3\u05e2"
    ],
    "wof:name":"Mad",
    "wof:placetype":"locality"
},
  "geometry": {"coordinates":[80.34057,29.411],"type":"Point"}
}