{
  "type": "Feature",
  "properties": {
    "gn:admin1_code":"FR",
    "gn:admin2_code":"14",
    "gn:admin3_code":"69.0",
    "gn:admin4_code":"690010.0",
    "gn:asciiname":"Santada",
    "gn:country_code":"NP",
    "gn:dem":1133,
    "gn:feature_class":"P",
    "gn:feature_code":"PPLL",
    "gn:name":"Santada",
    "gn:population":0,
    "gn:timezone":"Asia/Kathmandu",
    "iso:country":"NP",
    "wof:name":"Santada",
    "wof:placetype":"locality"
},
  "geometry": {"coordinates":[81.40573000000001,29.18132],"type":"Point"}
}