{
  "type": "Feature",
  "properties": {
    "gn:admin1_code":"CR",
    "gn:admin2_code":"11",
    "gn:admin3_code":"31",
    "gn:admin4_code":"310006",
    "gn:asciiname":"Ranikolek",
    "gn:country_code":"NP",
    "gn:dem":1334,
    "gn:feature_class":"P",
    "gn:feature_code":"PPLL",
    "gn:name":"Ranikolek",
    "gn:population":0,
    "gn:timezone":"Asia/Kathmandu",
    "iso:country":"NP",
    "wof:name":"Ranikolek",
    "wof:placetype":"locality"
},
  "geometry": {"coordinates":[85.06775999999998,27.53592],"type":"Point"}
}