{
  "type": "Feature",
  "properties": {
    "gn:admin1_code":"WR",
    "gn:admin2_code":"4",
    "gn:admin3_code":"40.0",
    "gn:admin4_code":"400005.0",
    "gn:asciiname":"Surtane",
    "gn:country_code":"NP",
    "gn:dem":948,
    "gn:feature_class":"P",
    "gn:feature_code":"PPLL",
    "gn:name":"Surtane",
    "gn:population":0,
    "gn:timezone":"Asia/Kathmandu",
    "iso:country":"NP",
    "wof:name":"Surtane",
    "wof:placetype":"locality"
},
  "geometry": {"coordinates":[84.02705999999998,28.12986],"type":"Point"}
}