{
  "type": "Feature",
  "properties": {
    "gn:admin1_code":"WR",
    "gn:admin2_code":"8",
    "gn:admin3_code":"50.0",
    "gn:admin4_code":"500068.0",
    "gn:asciiname":"Bhagawanpur",
    "gn:country_code":"NP",
    "gn:dem":152,
    "gn:feature_class":"P",
    "gn:feature_code":"PPLL",
    "gn:name":"Bhagawanpur",
    "gn:population":0,
    "gn:timezone":"Asia/Kathmandu",
    "iso:country":"NP",
    "wof:name":"Bhagawanpur",
    "wof:placetype":"locality"
},
  "geometry": {"coordinates":[82.79954000000002,27.68225],"type":"Point"}
}