{
  "type": "Feature",
  "properties": {
    "gn:admin1_code":"WR",
    "gn:admin2_code":"4",
    "gn:admin3_code":"37",
    "gn:admin4_code":"370044",
    "gn:asciiname":"Wakswanra",
    "gn:country_code":"NP",
    "gn:dem":1430,
    "gn:feature_class":"P",
    "gn:feature_code":"PPLL",
    "gn:name":"Wakswanra",
    "gn:population":0,
    "gn:timezone":"Asia/Kathmandu",
    "iso:country":"NP",
    "wof:name":"Wakswanra",
    "wof:placetype":"locality"
},
  "geometry": {"coordinates":[84.50149999999999,28.20767],"type":"Point"}
}