{
  "type": "Feature",
  "properties": {
    "gn:admin1_code":"FR",
    "gn:admin2_code":"9",
    "gn:admin3_code":"75.0",
    "gn:admin4_code":"750034.0",
    "gn:asciiname":"Timaladera",
    "gn:country_code":"NP",
    "gn:dem":1441,
    "gn:feature_class":"P",
    "gn:feature_code":"PPLL",
    "gn:name":"Timaladera",
    "gn:population":0,
    "gn:timezone":"Asia/Kathmandu",
    "iso:country":"NP",
    "wof:name":"Timaladera",
    "wof:placetype":"locality"
},
  "geometry": {"coordinates":[80.69525,29.72518],"type":"Point"}
}