{
  "type": "Feature",
  "properties": {
    "gn:admin1_code":"CR",
    "gn:admin2_code":"1",
    "gn:admin3_code":"27.0",
    "gn:admin4_code":"270046.0",
    "gn:asciiname":"Ramkot",
    "gn:country_code":"NP",
    "gn:dem":1394,
    "gn:feature_class":"P",
    "gn:feature_code":"PPLL",
    "gn:name":"Ramkot",
    "gn:population":0,
    "gn:timezone":"Asia/Kathmandu",
    "iso:country":"NP",
    "name:ceb_x_preferred":[
        "Ramkot"
    ],
    "name:msa_x_preferred":[
        "Ramkot"
    ],
    "name:pol_x_preferred":[
        "Ramkot"
    ],
    "wof:name":"Ramkot",
    "wof:placetype":"locality"
},
  "geometry": {"coordinates":[85.25596999999998,27.72299000000001],"type":"Point"}
}