{
  "type": "Feature",
  "properties": {
    "gn:admin1_code":"WR",
    "gn:admin2_code":"3",
    "gn:admin3_code":"45.0",
    "gn:admin4_code":"450014.0",
    "gn:asciiname":"Puchharagaun",
    "gn:country_code":"NP",
    "gn:dem":2234,
    "gn:feature_class":"P",
    "gn:feature_code":"PPLL",
    "gn:name":"Puchharagaun",
    "gn:population":0,
    "gn:timezone":"Asia/Kathmandu",
    "iso:country":"NP",
    "wof:name":"Puchharagaun",
    "wof:placetype":"locality"
},
  "geometry": {"coordinates":[83.00819,28.37815],"type":"Point"}
}