{
  "type": "Feature",
  "properties": {
    "gn:admin1_code":"MR",
    "gn:admin2_code":"2",
    "gn:admin3_code":"60.0",
    "gn:admin4_code":"600053.0",
    "gn:asciiname":"Singasain",
    "gn:country_code":"NP",
    "gn:dem":1744,
    "gn:feature_class":"P",
    "gn:feature_code":"PPLL",
    "gn:name":"Singasain",
    "gn:population":0,
    "gn:timezone":"Asia/Kathmandu",
    "iso:country":"NP",
    "name:ceb_x_preferred":[
        "Singasain"
    ],
    "name:mai_x_preferred":[
        "\u0938\u093f\u0902\u0939\u093e\u0938\u0948\u0928 \u0917\u093e.\u0935\u093f.\u0938."
    ],
    "name:msa_x_preferred":[
        "Singasain"
    ],
    "name:nep_x_preferred":[
        "\u0938\u093f\u0902\u0939\u093e\u0938\u0948\u0928 \u0917\u093e.\u0935\u093f.\u0938."
    ],
    "name:new_x_preferred":[
        "\u0938\u093f\u0902\u0939\u093e\u0938\u0948\u0928"
    ],
    "name:pol_x_preferred":[
        "Sinhasain"
    ],
    "wof:name":"Singasain",
    "wof:placetype":"locality"
},
  "geometry": {"coordinates":[81.49556,29.05619],"type":"Point"}
}