{
  "type": "Feature",
  "properties": {
    "gn:admin1_code":"WR",
    "gn:admin2_code":"4",
    "gn:admin3_code":"36.0",
    "gn:admin4_code":"360056.0",
    "gn:asciiname":"Sarsim",
    "gn:country_code":"NP",
    "gn:dem":2396,
    "gn:feature_class":"P",
    "gn:feature_code":"PPLL",
    "gn:name":"Sarsim",
    "gn:population":0,
    "gn:timezone":"Asia/Kathmandu",
    "iso:country":"NP",
    "wof:name":"Sarsim",
    "wof:placetype":"locality"
},
  "geometry": {"coordinates":[84.90904,28.40739],"type":"Point"}
}