{
  "type": "Feature",
  "properties": {
    "gn:admin1_code":"MR",
    "gn:admin2_code":"2.0",
    "gn:admin3_code":"57.0",
    "gn:admin4_code":"570042.0",
    "gn:asciiname":"Udharpur",
    "gn:country_code":"NP",
    "gn:dem":159,
    "gn:feature_class":"P",
    "gn:feature_code":"PPLL",
    "gn:name":"Udharpur",
    "gn:population":0,
    "gn:timezone":"Asia/Kathmandu",
    "iso:country":"NP",
    "wof:name":"Udharpur",
    "wof:placetype":"locality"
},
  "geometry": {"coordinates":[81.67015000000001,28.15111],"type":"Point"}
}