{
  "type": "Feature",
  "properties": {
    "gn:admin1_code":"FR",
    "gn:admin2_code":"9",
    "gn:admin3_code":"75.0",
    "gn:admin4_code":"750041.0",
    "gn:asciiname":"Khetar",
    "gn:country_code":"NP",
    "gn:dem":903,
    "gn:feature_class":"P",
    "gn:feature_code":"PPLL",
    "gn:name":"Khetar",
    "gn:population":0,
    "gn:timezone":"Asia/Kathmandu",
    "iso:country":"NP",
    "wof:name":"Khetar",
    "wof:placetype":"locality"
},
  "geometry": {"coordinates":[80.39779,29.75513],"type":"Point"}
}