{
  "type": "Feature",
  "properties": {
    "gn:admin1_code":"WR",
    "gn:admin2_code":"4",
    "gn:admin3_code":"37",
    "gn:admin4_code":"370019",
    "gn:asciiname":"Ramchokbesi",
    "gn:country_code":"NP",
    "gn:dem":638,
    "gn:feature_class":"P",
    "gn:feature_code":"PPLL",
    "gn:name":"Ramchokbesi",
    "gn:population":0,
    "gn:timezone":"Asia/Kathmandu",
    "iso:country":"NP",
    "wof:name":"Ramchokbesi",
    "wof:placetype":"locality"
},
  "geometry": {"coordinates":[84.44965000000001,28.17504000000001],"type":"Point"}
}