{
  "type": "Feature",
  "properties": {
    "gn:admin1_code":"FR",
    "gn:admin2_code":"14",
    "gn:admin3_code":"70.0",
    "gn:admin4_code":"700018.0",
    "gn:asciiname":"Thapagaun",
    "gn:country_code":"NP",
    "gn:dem":1064,
    "gn:feature_class":"P",
    "gn:feature_code":"PPLL",
    "gn:name":"Thapagaun",
    "gn:population":0,
    "gn:timezone":"Asia/Kathmandu",
    "iso:country":"NP",
    "wof:name":"Thapagaun",
    "wof:placetype":"locality"
},
  "geometry": {"coordinates":[81.06334,29.24658],"type":"Point"}
}