{
  "type": "Feature",
  "properties": {
    "gn:admin1_code":"CR",
    "gn:admin2_code":"1",
    "gn:admin3_code":"28",
    "gn:admin4_code":"280024",
    "gn:asciiname":"Kalleri",
    "gn:country_code":"NP",
    "gn:dem":1195,
    "gn:feature_class":"P",
    "gn:feature_code":"PPLL",
    "gn:name":"Kalleri",
    "gn:population":0,
    "gn:timezone":"Asia/Kathmandu",
    "iso:country":"NP",
    "wof:name":"Kalleri",
    "wof:placetype":"locality"
},
  "geometry": {"coordinates":[85.06251,27.90212],"type":"Point"}
}