{
  "type": "Feature",
  "properties": {
    "gn:admin1_code":"WR",
    "gn:admin2_code":"4",
    "gn:admin3_code":"36.0",
    "gn:admin4_code":"360047.0",
    "gn:asciiname":"Chhapthok",
    "gn:country_code":"NP",
    "gn:dem":628,
    "gn:feature_class":"P",
    "gn:feature_code":"PPLL",
    "gn:name":"Chhapthok",
    "gn:population":0,
    "gn:timezone":"Asia/Kathmandu",
    "iso:country":"NP",
    "wof:name":"Chhapthok",
    "wof:placetype":"locality"
},
  "geometry": {"coordinates":[84.50204000000002,28.04168],"type":"Point"}
}