{
  "type": "Feature",
  "properties": {
    "gn:admin1_code":"WR",
    "gn:admin2_code":"8",
    "gn:admin3_code":"48",
    "gn:admin4_code":"480070",
    "gn:asciiname":"Basantapur",
    "gn:country_code":"NP",
    "gn:dem":209,
    "gn:feature_class":"P",
    "gn:feature_code":"PPLL",
    "gn:name":"Basantapur",
    "gn:population":0,
    "gn:timezone":"Asia/Kathmandu",
    "iso:country":"NP",
    "name:fra_x_preferred":[
        "Basantapur"
    ],
    "name:pol_x_preferred":[
        "Basantapur"
    ],
    "wof:name":"Basantapur",
    "wof:placetype":"locality"
},
  "geometry": {"coordinates":[84.02733000000001,27.65809],"type":"Point"}
}