{
  "type": "Feature",
  "properties": {
    "gn:admin1_code":"MR",
    "gn:admin2_code":"12",
    "gn:admin3_code":"53",
    "gn:admin4_code":"530026",
    "gn:asciiname":"Ghopte",
    "gn:country_code":"NP",
    "gn:dem":1542,
    "gn:feature_class":"P",
    "gn:feature_code":"PPLL",
    "gn:name":"Ghopte",
    "gn:population":0,
    "gn:timezone":"Asia/Kathmandu",
    "iso:country":"NP",
    "wof:name":"Ghopte",
    "wof:placetype":"locality"
},
  "geometry": {"coordinates":[82.65586999999999,28.26007],"type":"Point"}
}