{
  "type": "Feature",
  "properties": {
    "gn:admin1_code":"MR",
    "gn:admin2_code":"6",
    "gn:admin3_code":"64.0",
    "gn:admin4_code":"640028.0",
    "gn:asciiname":"Khatedi Bada",
    "gn:country_code":"NP",
    "gn:dem":1712,
    "gn:feature_class":"P",
    "gn:feature_code":"PPLL",
    "gn:name":"Khatedi Bada",
    "gn:population":0,
    "gn:timezone":"Asia/Kathmandu",
    "iso:country":"NP",
    "wof:name":"Khatedi Bada",
    "wof:placetype":"locality"
},
  "geometry": {"coordinates":[81.64746,29.10421],"type":"Point"}
}