{
  "type": "Feature",
  "properties": {
    "gn:admin1_code":"CR",
    "gn:admin2_code":"11",
    "gn:admin3_code":"31",
    "gn:admin4_code":"310040",
    "gn:asciiname":"Dahidamar",
    "gn:country_code":"NP",
    "gn:dem":331,
    "gn:feature_class":"P",
    "gn:feature_code":"PPLL",
    "gn:name":"Dahidamar",
    "gn:population":0,
    "gn:timezone":"Asia/Kathmandu",
    "iso:country":"NP",
    "wof:name":"Dahidamar",
    "wof:placetype":"locality"
},
  "geometry": {"coordinates":[85.17935,27.34459],"type":"Point"}
}