{
  "type": "Feature",
  "properties": {
    "gn:admin1_code":"CR",
    "gn:admin2_code":"5",
    "gn:admin3_code":"21",
    "gn:admin4_code":"210049",
    "gn:asciiname":"Salupati",
    "gn:country_code":"NP",
    "gn:dem":1334,
    "gn:feature_class":"P",
    "gn:feature_code":"PPLL",
    "gn:name":"Salupati",
    "gn:population":0,
    "gn:timezone":"Asia/Kathmandu",
    "iso:country":"NP",
    "name:ceb_x_preferred":[
        "Salupati"
    ],
    "name:msa_x_preferred":[
        "Salupati"
    ],
    "name:new_x_preferred":[
        "\u0938\u093e\u0932\u0941\u092a\u093e\u091f\u0940"
    ],
    "name:pol_x_preferred":[
        "Salupati"
    ],
    "wof:name":"Salupati",
    "wof:placetype":"locality"
},
  "geometry": {"coordinates":[86.14303000000002,27.36385],"type":"Point"}
}