{
  "type": "Feature",
  "properties": {
    "gn:admin1_code":"WR",
    "gn:admin2_code":"3",
    "gn:admin3_code":"44",
    "gn:admin4_code":"440033",
    "gn:asciiname":"Panchamull",
    "gn:country_code":"NP",
    "gn:dem":2016,
    "gn:feature_class":"P",
    "gn:feature_code":"PPLL",
    "gn:name":"Panchamull",
    "gn:population":0,
    "gn:timezone":"Asia/Kathmandu",
    "iso:country":"NP",
    "wof:name":"Panchamull",
    "wof:placetype":"locality"
},
  "geometry": {"coordinates":[83.61018,28.35182],"type":"Point"}
}