{
  "type": "Feature",
  "properties": {
    "gn:admin1_code":"WR",
    "gn:admin2_code":"8",
    "gn:admin3_code":"49",
    "gn:admin4_code":"490060",
    "gn:asciiname":"Islampur",
    "gn:country_code":"NP",
    "gn:dem":94,
    "gn:feature_class":"P",
    "gn:feature_code":"PPLL",
    "gn:name":"Islampur",
    "gn:population":0,
    "gn:timezone":"Asia/Kathmandu",
    "iso:country":"NP",
    "name:ben_x_preferred":[
        "\u0987\u09b8\u09b2\u09be\u09ae\u09aa\u09c1\u09b0"
    ],
    "name:ceb_x_preferred":[
        "Islampur"
    ],
    "name:deu_x_preferred":[
        "Islampur"
    ],
    "name:new_x_preferred":[
        "\u0907\u0938\u094d\u0932\u093e\u092e\u092a\u0941\u0930"
    ],
    "name:ori_x_preferred":[
        "\u0b07\u0b38\u0b32\u0b3e\u0b2e\u0b2a\u0b41\u0b30"
    ],
    "name:swe_x_preferred":[
        "Islampur"
    ],
    "name:vie_x_preferred":[
        "Islampur"
    ],
    "wof:name":"Islampur",
    "wof:placetype":"locality"
},
  "geometry": {"coordinates":[83.31869,27.36167],"type":"Point"}
}