{
  "type": "Feature",
  "properties": {
    "gn:admin1_code":"ER",
    "gn:admin2_code":"7",
    "gn:admin3_code":"5",
    "gn:admin4_code":"50017",
    "gn:asciiname":"Laksmimarg",
    "gn:country_code":"NP",
    "gn:dem":140,
    "gn:feature_class":"P",
    "gn:feature_code":"PPLL",
    "gn:name":"Laksmimarg",
    "gn:population":0,
    "gn:timezone":"Asia/Kathmandu",
    "iso:country":"NP",
    "wof:name":"Laksmimarg",
    "wof:placetype":"locality"
},
  "geometry": {"coordinates":[87.45305999999999,26.65458],"type":"Point"}
}