{
  "type": "Feature",
  "properties": {
    "gn:admin1_code":"MR",
    "gn:admin2_code":"12",
    "gn:admin3_code":"52",
    "gn:admin4_code":"520034",
    "gn:asciiname":"Darimchaur",
    "gn:country_code":"NP",
    "gn:dem":652,
    "gn:feature_class":"P",
    "gn:feature_code":"PPLL",
    "gn:name":"Darimchaur",
    "gn:population":0,
    "gn:timezone":"Asia/Kathmandu",
    "iso:country":"NP",
    "wof:name":"Darimchaur",
    "wof:placetype":"locality"
},
  "geometry": {"coordinates":[82.7966,28.07201],"type":"Point"}
}