{
  "type": "Feature",
  "properties": {
    "gn:admin1_code":"ER",
    "gn:admin2_code":"7",
    "gn:admin3_code":"7.0",
    "gn:admin4_code":"70034.0",
    "gn:asciiname":"Imektol",
    "gn:country_code":"NP",
    "gn:dem":1751,
    "gn:feature_class":"P",
    "gn:feature_code":"PPLL",
    "gn:name":"Imektol",
    "gn:population":0,
    "gn:timezone":"Asia/Kathmandu",
    "iso:country":"NP",
    "wof:name":"Imektol",
    "wof:placetype":"locality"
},
  "geometry": {"coordinates":[87.39519,27.02896],"type":"Point"}
}