{
  "type": "Feature",
  "properties": {
    "gn:admin1_code":"MR",
    "gn:admin2_code":"12",
    "gn:admin3_code":"53",
    "gn:admin4_code":"530010",
    "gn:asciiname":"Koibang",
    "gn:country_code":"NP",
    "gn:dem":1960,
    "gn:feature_class":"P",
    "gn:feature_code":"PPLL",
    "gn:name":"Koibang",
    "gn:population":0,
    "gn:timezone":"Asia/Kathmandu",
    "iso:country":"NP",
    "wof:name":"Koibang",
    "wof:placetype":"locality"
},
  "geometry": {"coordinates":[82.84985999999998,28.38071],"type":"Point"}
}