{
  "type": "Feature",
  "properties": {
    "gn:admin1_code":"CR",
    "gn:admin2_code":"5",
    "gn:admin3_code":"19",
    "gn:admin4_code":"190001",
    "gn:asciiname":"Narharganj",
    "gn:country_code":"NP",
    "gn:dem":78,
    "gn:feature_class":"P",
    "gn:feature_code":"PPLL",
    "gn:name":"Narharganj",
    "gn:population":0,
    "gn:timezone":"Asia/Kathmandu",
    "iso:country":"NP",
    "wof:name":"Narharganj",
    "wof:placetype":"locality"
},
  "geometry": {"coordinates":[85.35911999999998,26.79732000000001],"type":"Point"}
}