{
  "type": "Feature",
  "properties": {
    "gn:admin1_code":"WR",
    "gn:admin2_code":"4.0",
    "gn:admin3_code":"39.0",
    "gn:admin4_code":"390059.0",
    "gn:asciiname":"Belauti Chhap",
    "gn:country_code":"NP",
    "gn:dem":830,
    "gn:feature_class":"P",
    "gn:feature_code":"PPLL",
    "gn:name":"Belauti Chhap",
    "gn:population":0,
    "gn:timezone":"Asia/Kathmandu",
    "iso:country":"NP",
    "wof:name":"Belauti Chhap",
    "wof:placetype":"locality"
},
  "geometry": {"coordinates":[83.70314999999999,27.95009000000001],"type":"Point"}
}