{
  "type": "Feature",
  "properties": {
    "gn:admin1_code":"WR",
    "gn:admin2_code":"4.0",
    "gn:admin3_code":"38.0",
    "gn:admin4_code":"380023.0",
    "gn:asciiname":"Khanaeghari",
    "gn:country_code":"NP",
    "gn:dem":593,
    "gn:feature_class":"P",
    "gn:feature_code":"PPLL",
    "gn:name":"Khanaeghari",
    "gn:population":0,
    "gn:timezone":"Asia/Kathmandu",
    "iso:country":"NP",
    "wof:name":"Khanaeghari",
    "wof:placetype":"locality"
},
  "geometry": {"coordinates":[84.32914,27.99921],"type":"Point"}
}