{
  "type": "Feature",
  "properties": {
    "gn:admin1_code":"CR",
    "gn:admin2_code":"1",
    "gn:admin3_code":"27.0",
    "gn:admin4_code":"270048.0",
    "gn:asciiname":"Naikhandi",
    "gn:country_code":"NP",
    "gn:dem":1254,
    "gn:feature_class":"P",
    "gn:feature_code":"PPLL",
    "gn:name":"Naikhandi",
    "gn:population":0,
    "gn:timezone":"Asia/Kathmandu",
    "iso:country":"NP",
    "wof:name":"Naikhandi",
    "wof:placetype":"locality"
},
  "geometry": {"coordinates":[85.29491,27.60573],"type":"Point"}
}