{
  "type": "Feature",
  "properties": {
    "gn:admin1_code":"CR",
    "gn:admin2_code":"5",
    "gn:admin3_code":"20",
    "gn:admin4_code":"200034",
    "gn:asciiname":"Dahaldanda",
    "gn:country_code":"NP",
    "gn:dem":864,
    "gn:feature_class":"P",
    "gn:feature_code":"PPLL",
    "gn:name":"Dahaldanda",
    "gn:population":0,
    "gn:timezone":"Asia/Kathmandu",
    "iso:country":"NP",
    "wof:name":"Dahaldanda",
    "wof:placetype":"locality"
},
  "geometry": {"coordinates":[85.78204000000002,27.28248],"type":"Point"}
}