{
  "type": "Feature",
  "properties": {
    "gn:admin1_code":"WR",
    "gn:admin2_code":"8",
    "gn:admin3_code":"51.0",
    "gn:admin4_code":"510014.0",
    "gn:asciiname":"Lamdanda",
    "gn:country_code":"NP",
    "gn:dem":1136,
    "gn:feature_class":"P",
    "gn:feature_code":"PPLL",
    "gn:name":"Lamdanda",
    "gn:population":0,
    "gn:timezone":"Asia/Kathmandu",
    "iso:country":"NP",
    "wof:name":"Lamdanda",
    "wof:placetype":"locality"
},
  "geometry": {"coordinates":[83.22349,27.89693],"type":"Point"}
}