{
  "type": "Feature",
  "properties": {
    "gn:admin1_code":"MR",
    "gn:admin2_code":"12",
    "gn:admin3_code":"53",
    "gn:admin4_code":"530030",
    "gn:asciiname":"Sarsubari",
    "gn:country_code":"NP",
    "gn:dem":2459,
    "gn:feature_class":"P",
    "gn:feature_code":"PPLL",
    "gn:name":"Sarsubari",
    "gn:population":0,
    "gn:timezone":"Asia/Kathmandu",
    "iso:country":"NP",
    "wof:name":"Sarsubari",
    "wof:placetype":"locality"
},
  "geometry": {"coordinates":[82.60720999999999,28.50325],"type":"Point"}
}