{
  "type": "Feature",
  "properties": {
    "gn:admin1_code":"CR",
    "gn:admin2_code":"1",
    "gn:admin3_code":"23",
    "gn:admin4_code":"230027.0",
    "gn:asciiname":"Damsing",
    "gn:country_code":"NP",
    "gn:dem":1475,
    "gn:feature_class":"P",
    "gn:feature_code":"PPLL",
    "gn:name":"Damsing",
    "gn:population":0,
    "gn:timezone":"Asia/Kathmandu",
    "iso:country":"NP",
    "wof:name":"Damsing",
    "wof:placetype":"locality"
},
  "geometry": {"coordinates":[85.79512,27.815],"type":"Point"}
}