{
  "type": "Feature",
  "properties": {
    "gn:admin1_code":"MR",
    "gn:admin2_code":"12",
    "gn:admin3_code":"54",
    "gn:admin4_code":"540007",
    "gn:asciiname":"Chhibang",
    "gn:country_code":"NP",
    "gn:dem":1106,
    "gn:feature_class":"P",
    "gn:feature_code":"PPLL",
    "gn:name":"Chhibang",
    "gn:population":0,
    "gn:timezone":"Asia/Kathmandu",
    "iso:country":"NP",
    "wof:name":"Chhibang",
    "wof:placetype":"locality"
},
  "geometry": {"coordinates":[82.41727,28.63169000000001],"type":"Point"}
}