{
  "type": "Feature",
  "properties": {
    "gn:admin1_code":"MR",
    "gn:admin2_code":"2.0",
    "gn:admin3_code":"59.0",
    "gn:admin4_code":"590043.0",
    "gn:asciiname":"Galeligaun",
    "gn:country_code":"NP",
    "gn:dem":517,
    "gn:feature_class":"P",
    "gn:feature_code":"PPLL",
    "gn:name":"Galeligaun",
    "gn:population":0,
    "gn:timezone":"Asia/Kathmandu",
    "iso:country":"NP",
    "wof:name":"Galeligaun",
    "wof:placetype":"locality"
},
  "geometry": {"coordinates":[81.75964,28.46659],"type":"Point"}
}