{
  "type": "Feature",
  "properties": {
    "gn:admin1_code":"MR",
    "gn:admin2_code":"2",
    "gn:admin3_code":"60.0",
    "gn:admin4_code":"600054.0",
    "gn:asciiname":"Tilepata",
    "gn:country_code":"NP",
    "gn:dem":1582,
    "gn:feature_class":"P",
    "gn:feature_code":"PPLL",
    "gn:name":"Tilepata",
    "gn:population":0,
    "gn:timezone":"Asia/Kathmandu",
    "iso:country":"NP",
    "name:ceb_x_preferred":[
        "Tilepata"
    ],
    "name:dty_x_preferred":[
        "\u0924\u093f\u0932\u0947\u092a\u093e\u091f\u093e"
    ],
    "name:mai_x_preferred":[
        "\u0924\u093f\u0932\u0947\u092a\u093e\u091f\u093e"
    ],
    "name:msa_x_preferred":[
        "Tilepata"
    ],
    "name:nep_x_preferred":[
        "\u0924\u093f\u092a\u093e\u0932\u0947\u091f\u093e \u0917\u093e.\u0935\u093f.\u0938."
    ],
    "name:new_x_preferred":[
        "\u0924\u093f\u0932\u0947\u092a\u093e\u091f\u093e"
    ],
    "name:pol_x_preferred":[
        "Tilepata"
    ],
    "wof:name":"Tilepata",
    "wof:placetype":"locality"
},
  "geometry": {"coordinates":[81.48841,29.01568],"type":"Point"}
}