{
  "type": "Feature",
  "properties": {
    "gn:admin1_code":"FR",
    "gn:admin2_code":"14",
    "gn:admin3_code":"68",
    "gn:admin4_code":"680035",
    "gn:asciiname":"Dhamigaun",
    "gn:country_code":"NP",
    "gn:dem":1547,
    "gn:feature_class":"P",
    "gn:feature_code":"PPLL",
    "gn:name":"Dhamigaun",
    "gn:population":0,
    "gn:timezone":"Asia/Kathmandu",
    "iso:country":"NP",
    "wof:name":"Dhamigaun",
    "wof:placetype":"locality"
},
  "geometry": {"coordinates":[81.00610999999998,29.46],"type":"Point"}
}