{
  "type": "Feature",
  "properties": {
    "gn:admin1_code":"WR",
    "gn:admin2_code":"8",
    "gn:admin3_code":"47",
    "gn:admin4_code":"470042",
    "gn:asciiname":"Gauntul",
    "gn:country_code":"NP",
    "gn:dem":927,
    "gn:feature_class":"P",
    "gn:feature_code":"PPLL",
    "gn:name":"Gauntul",
    "gn:population":0,
    "gn:timezone":"Asia/Kathmandu",
    "iso:country":"NP",
    "wof:name":"Gauntul",
    "wof:placetype":"locality"
},
  "geometry": {"coordinates":[83.57151,27.7948],"type":"Point"}
}