{
  "type": "Feature",
  "properties": {
    "gn:admin1_code":"FR",
    "gn:admin2_code":"14",
    "gn:admin3_code":"68",
    "gn:admin4_code":"680020",
    "gn:asciiname":"Ram Ramdi",
    "gn:country_code":"NP",
    "gn:dem":2556,
    "gn:feature_class":"P",
    "gn:feature_code":"PPLL",
    "gn:name":"Ram Ramdi",
    "gn:population":0,
    "gn:timezone":"Asia/Kathmandu",
    "iso:country":"NP",
    "wof:name":"Ram Ramdi",
    "wof:placetype":"locality"
},
  "geometry": {"coordinates":[81.26082,29.79107],"type":"Point"}
}