{
  "type": "Feature",
  "properties": {
    "gn:admin1_code":"MR",
    "gn:admin2_code":"6",
    "gn:admin3_code":"64.0",
    "gn:admin4_code":"640003.0",
    "gn:asciiname":"Dugra",
    "gn:country_code":"NP",
    "gn:dem":2749,
    "gn:feature_class":"P",
    "gn:feature_code":"PPLL",
    "gn:name":"Dugra",
    "gn:population":0,
    "gn:timezone":"Asia/Kathmandu",
    "iso:country":"NP",
    "wof:name":"Dugra",
    "wof:placetype":"locality"
},
  "geometry": {"coordinates":[81.84678000000002,29.11968],"type":"Point"}
}