{
  "type": "Feature",
  "properties": {
    "gn:admin1_code":"MR",
    "gn:admin2_code":"12",
    "gn:admin3_code":"56.0",
    "gn:admin4_code":"560010.0",
    "gn:asciiname":"Khajarauta",
    "gn:country_code":"NP",
    "gn:dem":268,
    "gn:feature_class":"P",
    "gn:feature_code":"PPLL",
    "gn:name":"Khajarauta",
    "gn:population":0,
    "gn:timezone":"Asia/Kathmandu",
    "iso:country":"NP",
    "wof:name":"Khajarauta",
    "wof:placetype":"locality"
},
  "geometry": {"coordinates":[82.57531999999998,27.80594],"type":"Point"}
}