{
  "type": "Feature",
  "properties": {
    "gn:admin1_code":"ER",
    "gn:admin2_code":"10",
    "gn:admin3_code":"3.0",
    "gn:admin4_code":"30006.0",
    "gn:asciiname":"Bisaune",
    "gn:country_code":"NP",
    "gn:dem":361,
    "gn:feature_class":"P",
    "gn:feature_code":"PPLL",
    "gn:name":"Bisaune",
    "gn:population":0,
    "gn:timezone":"Asia/Kathmandu",
    "iso:country":"NP",
    "wof:name":"Bisaune",
    "wof:placetype":"locality"
},
  "geometry": {"coordinates":[87.75494,26.72523],"type":"Point"}
}