{
  "type": "Feature",
  "properties": {
    "gn:admin1_code":"WR",
    "gn:admin2_code":"4.0",
    "gn:admin3_code":"39.0",
    "gn:admin4_code":"390041.0",
    "gn:asciiname":"Alkedhunga",
    "gn:country_code":"NP",
    "gn:dem":976,
    "gn:feature_class":"P",
    "gn:feature_code":"PPLL",
    "gn:name":"Alkedhunga",
    "gn:population":0,
    "gn:timezone":"Asia/Kathmandu",
    "iso:country":"NP",
    "wof:name":"Alkedhunga",
    "wof:placetype":"locality"
},
  "geometry": {"coordinates":[83.69074999999999,27.96624000000001],"type":"Point"}
}