{
  "type": "Feature",
  "properties": {
    "gn:admin1_code":"MR",
    "gn:admin2_code":"12",
    "gn:admin3_code":"54",
    "gn:admin4_code":"540010",
    "gn:asciiname":"Golenchaur",
    "gn:country_code":"NP",
    "gn:dem":2277,
    "gn:feature_class":"P",
    "gn:feature_code":"PPLL",
    "gn:name":"Golenchaur",
    "gn:population":0,
    "gn:timezone":"Asia/Kathmandu",
    "iso:country":"NP",
    "wof:name":"Golenchaur",
    "wof:placetype":"locality"
},
  "geometry": {"coordinates":[82.39291999999998,28.72526],"type":"Point"}
}