{
  "type": "Feature",
  "properties": {
    "gn:admin1_code":"MR",
    "gn:admin2_code":"12",
    "gn:admin3_code":"55",
    "gn:admin4_code":"550025",
    "gn:asciiname":"Baghmare",
    "gn:country_code":"NP",
    "gn:dem":1331,
    "gn:feature_class":"P",
    "gn:feature_code":"PPLL",
    "gn:name":"Baghmare",
    "gn:population":0,
    "gn:timezone":"Asia/Kathmandu",
    "iso:country":"NP",
    "name:ceb_x_preferred":[
        "Baghmare"
    ],
    "name:mai_x_preferred":[
        "\u092c\u093e\u0918\u092e\u093e\u0930\u0947 \u0917\u093e.\u0935\u093f.\u0938."
    ],
    "name:msa_x_preferred":[
        "Baghmare"
    ],
    "name:nep_x_preferred":[
        "\u092c\u093e\u0918\u092e\u093e\u0930\u0947"
    ],
    "name:new_x_preferred":[
        "\u092c\u093e\u0918\u092e\u093e\u0930\u0947"
    ],
    "name:pol_x_preferred":[
        "Baghmare"
    ],
    "wof:name":"Baghmare",
    "wof:placetype":"locality"
},
  "geometry": {"coordinates":[82.22821,28.30262],"type":"Point"}
}