{
  "type": "Feature",
  "properties": {
    "gn:admin1_code":"MR",
    "gn:admin2_code":"12",
    "gn:admin3_code":"52",
    "gn:admin4_code":"520033",
    "gn:asciiname":"Dandagaun",
    "gn:country_code":"NP",
    "gn:dem":1320,
    "gn:feature_class":"P",
    "gn:feature_code":"PPLL",
    "gn:name":"Dandagaun",
    "gn:population":0,
    "gn:timezone":"Asia/Kathmandu",
    "iso:country":"NP",
    "wof:name":"Dandagaun",
    "wof:placetype":"locality"
},
  "geometry": {"coordinates":[82.99366999999999,28.1787],"type":"Point"}
}