{
  "type": "Feature",
  "properties": {
    "gn:admin1_code":"MR",
    "gn:admin2_code":"12",
    "gn:admin3_code":"54",
    "gn:admin4_code":"540043",
    "gn:asciiname":"Nopokharka",
    "gn:country_code":"NP",
    "gn:dem":2679,
    "gn:feature_class":"P",
    "gn:feature_code":"PPLL",
    "gn:name":"Nopokharka",
    "gn:population":0,
    "gn:timezone":"Asia/Kathmandu",
    "iso:country":"NP",
    "wof:name":"Nopokharka",
    "wof:placetype":"locality"
},
  "geometry": {"coordinates":[82.84953,28.56707],"type":"Point"}
}