{
  "type": "Feature",
  "properties": {
    "gn:admin1_code":"ER",
    "gn:admin2_code":"13.0",
    "gn:admin3_code":"14.0",
    "gn:admin4_code":"140031.0",
    "gn:asciiname":"Madale",
    "gn:country_code":"NP",
    "gn:dem":367,
    "gn:feature_class":"P",
    "gn:feature_code":"PPLL",
    "gn:name":"Madale",
    "gn:population":0,
    "gn:timezone":"Asia/Kathmandu",
    "iso:country":"NP",
    "wof:name":"Madale",
    "wof:placetype":"locality"
},
  "geometry": {"coordinates":[86.52153,27.09854],"type":"Point"}
}