{
  "type": "Feature",
  "properties": {
    "gn:admin1_code":"00",
    "gn:asciiname":"Ratagau",
    "gn:country_code":"NP",
    "gn:dem":1031,
    "gn:feature_class":"P",
    "gn:feature_code":"PPL",
    "gn:name":"R\u0101t\u0101g\u0101\u0169",
    "gn:population":0,
    "gn:timezone":"Asia/Kathmandu",
    "iso:country":"NP",
    "wof:name":"Ratagau",
    "wof:placetype":"locality"
},
  "geometry": {"coordinates":[86.65493000000002,27.37734],"type":"Point"}
}