{
  "type": "Feature",
  "properties": {
    "gn:admin1_code":"FR",
    "gn:admin2_code":"9",
    "gn:admin3_code":"72.0",
    "gn:admin4_code":"720003.0",
    "gn:asciiname":"Latthaghat",
    "gn:country_code":"NP",
    "gn:dem":202,
    "gn:feature_class":"P",
    "gn:feature_code":"PPLL",
    "gn:name":"Latthaghat",
    "gn:population":0,
    "gn:timezone":"Asia/Kathmandu",
    "iso:country":"NP",
    "wof:name":"Latthaghat",
    "wof:placetype":"locality"
},
  "geometry": {"coordinates":[80.10048,28.91454],"type":"Point"}
}