{
  "type": "Feature",
  "properties": {
    "gn:admin1_code":"CR",
    "gn:admin2_code":"1",
    "gn:admin3_code":"24.0",
    "gn:admin4_code":"240073.0",
    "gn:asciiname":"Luiche",
    "gn:country_code":"NP",
    "gn:dem":591,
    "gn:feature_class":"P",
    "gn:feature_code":"PPLL",
    "gn:name":"Luiche",
    "gn:population":0,
    "gn:timezone":"Asia/Kathmandu",
    "iso:country":"NP",
    "wof:name":"Luiche",
    "wof:placetype":"locality"
},
  "geometry": {"coordinates":[85.46441,27.40001],"type":"Point"}
}