{
  "type": "Feature",
  "properties": {
    "gn:admin1_code":"ER",
    "gn:admin2_code":"7",
    "gn:admin3_code":"9",
    "gn:admin4_code":"90013",
    "gn:asciiname":"Sekaha Bhangkharka",
    "gn:country_code":"NP",
    "gn:dem":1704,
    "gn:feature_class":"P",
    "gn:feature_code":"PPLL",
    "gn:name":"Sekaha Bhangkharka",
    "gn:population":0,
    "gn:timezone":"Asia/Kathmandu",
    "iso:country":"NP",
    "wof:name":"Sekaha Bhangkharka",
    "wof:placetype":"locality"
},
  "geometry": {"coordinates":[87.18115,27.43938],"type":"Point"}
}