{
  "type": "Feature",
  "properties": {
    "gn:admin1_code":"CR",
    "gn:admin2_code":"1",
    "gn:admin3_code":"24.0",
    "gn:admin4_code":"240038.0",
    "gn:asciiname":"Paudelthok",
    "gn:country_code":"NP",
    "gn:dem":1499,
    "gn:feature_class":"P",
    "gn:feature_code":"PPLL",
    "gn:name":"Paudelthok",
    "gn:population":0,
    "gn:timezone":"Asia/Kathmandu",
    "iso:country":"NP",
    "wof:name":"Paudelthok",
    "wof:placetype":"locality"
},
  "geometry": {"coordinates":[85.68370999999998,27.54072],"type":"Point"}
}