{
  "type": "Feature",
  "properties": {
    "gn:admin1_code":"CR",
    "gn:admin2_code":"11",
    "gn:admin3_code":"35.0",
    "gn:admin4_code":"350016.0",
    "gn:asciiname":"Khadrauli",
    "gn:country_code":"NP",
    "gn:dem":171,
    "gn:feature_class":"P",
    "gn:feature_code":"PPLL",
    "gn:name":"Khadrauli",
    "gn:population":0,
    "gn:timezone":"Asia/Kathmandu",
    "iso:country":"NP",
    "wof:name":"Khadrauli",
    "wof:placetype":"locality"
},
  "geometry": {"coordinates":[84.31433,27.56968],"type":"Point"}
}