{
  "type": "Feature",
  "properties": {
    "gn:admin1_code":"FR",
    "gn:admin2_code":"14",
    "gn:admin3_code":"71.0",
    "gn:admin4_code":"710013.0",
    "gn:asciiname":"Surmi",
    "gn:country_code":"NP",
    "gn:dem":167,
    "gn:feature_class":"P",
    "gn:feature_code":"PPLL",
    "gn:name":"Surmi",
    "gn:population":0,
    "gn:timezone":"Asia/Kathmandu",
    "iso:country":"NP",
    "wof:name":"Surmi",
    "wof:placetype":"locality"
},
  "geometry": {"coordinates":[80.78386,28.62575],"type":"Point"}
}