{
  "type": "Feature",
  "properties": {
    "gn:admin1_code":"FR",
    "gn:admin2_code":"9",
    "gn:admin3_code":"73.0",
    "gn:admin4_code":"730014.0",
    "gn:asciiname":"Moigaun",
    "gn:country_code":"NP",
    "gn:dem":1220,
    "gn:feature_class":"P",
    "gn:feature_code":"PPLL",
    "gn:name":"Moigaun",
    "gn:population":0,
    "gn:timezone":"Asia/Kathmandu",
    "iso:country":"NP",
    "wof:name":"Moigaun",
    "wof:placetype":"locality"
},
  "geometry": {"coordinates":[80.74384000000001,29.28682],"type":"Point"}
}