{
  "type": "Feature",
  "properties": {
    "gn:admin1_code":"WR",
    "gn:admin2_code":"4.0",
    "gn:admin3_code":"39.0",
    "gn:admin4_code":"390006.0",
    "gn:asciiname":"Kaule",
    "gn:country_code":"NP",
    "gn:dem":1386,
    "gn:feature_class":"P",
    "gn:feature_code":"PPLL",
    "gn:name":"Kaule",
    "gn:population":0,
    "gn:timezone":"Asia/Kathmandu",
    "iso:country":"NP",
    "name:ceb_x_preferred":[
        "Kaule"
    ],
    "name:deu_x_preferred":[
        "Kaule"
    ],
    "name:pol_x_preferred":[
        "Kaule"
    ],
    "name:swe_x_preferred":[
        "Kaule"
    ],
    "wof:name":"Kaule",
    "wof:placetype":"locality"
},
  "geometry": {"coordinates":[83.91391,28.07984],"type":"Point"}
}