{
  "type": "Feature",
  "properties": {
    "gn:admin1_code":"MR",
    "gn:admin2_code":"12",
    "gn:admin3_code":"55",
    "gn:admin4_code":"550013",
    "gn:asciiname":"Jyamirekholagaun",
    "gn:country_code":"NP",
    "gn:dem":910,
    "gn:feature_class":"P",
    "gn:feature_code":"PPLL",
    "gn:name":"Jyamirekholagaun",
    "gn:population":0,
    "gn:timezone":"Asia/Kathmandu",
    "iso:country":"NP",
    "wof:name":"Jyamirekholagaun",
    "wof:placetype":"locality"
},
  "geometry": {"coordinates":[82.07313000000001,28.44852],"type":"Point"}
}