{
  "type": "Feature",
  "properties": {
    "gn:admin1_code":"WR",
    "gn:admin2_code":"8",
    "gn:admin3_code":"46.0",
    "gn:admin4_code":"460061.0",
    "gn:asciiname":"Khanikholagaun",
    "gn:country_code":"NP",
    "gn:dem":946,
    "gn:feature_class":"P",
    "gn:feature_code":"PPLL",
    "gn:name":"Khanikholagaun",
    "gn:population":0,
    "gn:timezone":"Asia/Kathmandu",
    "iso:country":"NP",
    "wof:name":"Khanikholagaun",
    "wof:placetype":"locality"
},
  "geometry": {"coordinates":[83.19013000000002,28.26327],"type":"Point"}
}