{
  "type": "Feature",
  "properties": {
    "gn:admin1_code":"CR",
    "gn:admin2_code":"5",
    "gn:admin3_code":"21",
    "gn:admin4_code":"210055",
    "gn:asciiname":"Nigure",
    "gn:country_code":"NP",
    "gn:dem":2685,
    "gn:feature_class":"P",
    "gn:feature_code":"PPLL",
    "gn:name":"Nigure",
    "gn:population":0,
    "gn:timezone":"Asia/Kathmandu",
    "iso:country":"NP",
    "wof:name":"Nigure",
    "wof:placetype":"locality"
},
  "geometry": {"coordinates":[85.92063,27.55959],"type":"Point"}
}