{
  "type": "Feature",
  "properties": {
    "gn:admin1_code":"WR",
    "gn:admin2_code":"3",
    "gn:admin3_code":"44",
    "gn:admin4_code":"440009",
    "gn:asciiname":"Baumara",
    "gn:country_code":"NP",
    "gn:dem":1620,
    "gn:feature_class":"P",
    "gn:feature_code":"PPLL",
    "gn:name":"Baumara",
    "gn:population":0,
    "gn:timezone":"Asia/Kathmandu",
    "iso:country":"NP",
    "wof:name":"Baumara",
    "wof:placetype":"locality"
},
  "geometry": {"coordinates":[83.72619,28.15852000000001],"type":"Point"}
}