{
  "type": "Feature",
  "properties": {
    "gn:admin1_code":"WR",
    "gn:admin2_code":"4.0",
    "gn:admin3_code":"39.0",
    "gn:admin4_code":"390052.0",
    "gn:asciiname":"Jaruwa",
    "gn:country_code":"NP",
    "gn:dem":668,
    "gn:feature_class":"P",
    "gn:feature_code":"PPLL",
    "gn:name":"Jaruwa",
    "gn:population":0,
    "gn:timezone":"Asia/Kathmandu",
    "iso:country":"NP",
    "wof:name":"Jaruwa",
    "wof:placetype":"locality"
},
  "geometry": {"coordinates":[83.59998,27.93494],"type":"Point"}
}