{
  "type": "Feature",
  "properties": {
    "gn:admin1_code":"00",
    "gn:asciiname":"Merun",
    "gn:country_code":"NP",
    "gn:dem":2825,
    "gn:feature_class":"P",
    "gn:feature_code":"PPL",
    "gn:name":"Meru\u1e45",
    "gn:population":0,
    "gn:timezone":"Asia/Kathmandu",
    "iso:country":"NP",
    "wof:name":"Merun",
    "wof:placetype":"locality"
},
  "geometry": {"coordinates":[86.90286,27.25263],"type":"Point"}
}