{
  "type": "Feature",
  "properties": {
    "gn:admin1_code":"FR",
    "gn:admin2_code":"14",
    "gn:admin3_code":"68",
    "gn:admin4_code":"680007",
    "gn:asciiname":"Bhandelgauj",
    "gn:country_code":"NP",
    "gn:dem":1560,
    "gn:feature_class":"P",
    "gn:feature_code":"PPLL",
    "gn:name":"Bhandelgauj",
    "gn:population":0,
    "gn:timezone":"Asia/Kathmandu",
    "iso:country":"NP",
    "wof:name":"Bhandelgauj",
    "wof:placetype":"locality"
},
  "geometry": {"coordinates":[81.02405999999998,29.49766],"type":"Point"}
}