{
  "type": "Feature",
  "properties": {
    "gn:admin1_code":"WR",
    "gn:admin2_code":"4",
    "gn:admin3_code":"40.0",
    "gn:admin4_code":"400019.0",
    "gn:asciiname":"Chhapswara",
    "gn:country_code":"NP",
    "gn:dem":885,
    "gn:feature_class":"P",
    "gn:feature_code":"PPLL",
    "gn:name":"Chhapswara",
    "gn:population":0,
    "gn:timezone":"Asia/Kathmandu",
    "iso:country":"NP",
    "wof:name":"Chhapswara",
    "wof:placetype":"locality"
},
  "geometry": {"coordinates":[83.95059000000001,28.16729],"type":"Point"}
}