{
  "type": "Feature",
  "properties": {
    "gn:admin1_code":"FR",
    "gn:admin2_code":"14",
    "gn:admin3_code":"71.0",
    "gn:admin4_code":"710038.0",
    "gn:asciiname":"Siradi",
    "gn:country_code":"NP",
    "gn:dem":775,
    "gn:feature_class":"P",
    "gn:feature_code":"PPLL",
    "gn:name":"Siradi",
    "gn:population":0,
    "gn:timezone":"Asia/Kathmandu",
    "iso:country":"NP",
    "wof:name":"Siradi",
    "wof:placetype":"locality"
},
  "geometry": {"coordinates":[80.59028000000001,29.0114],"type":"Point"}
}