{
  "type": "Feature",
  "properties": {
    "gn:admin1_code":"CR",
    "gn:admin2_code":"11",
    "gn:admin3_code":"31",
    "gn:admin4_code":"310010",
    "gn:asciiname":"Taudar Thapagaun",
    "gn:country_code":"NP",
    "gn:dem":1920,
    "gn:feature_class":"P",
    "gn:feature_code":"PPLL",
    "gn:name":"Taudar Thapagaun",
    "gn:population":0,
    "gn:timezone":"Asia/Kathmandu",
    "iso:country":"NP",
    "wof:name":"Taudar Thapagaun",
    "wof:placetype":"locality"
},
  "geometry": {"coordinates":[85.15473,27.66656],"type":"Point"}
}