{
  "type": "Feature",
  "properties": {
    "gn:admin1_code":"ER",
    "gn:admin2_code":"13",
    "gn:admin3_code":"13.0",
    "gn:admin4_code":"130038.0",
    "gn:asciiname":"Piple",
    "gn:country_code":"NP",
    "gn:dem":1498,
    "gn:feature_class":"P",
    "gn:feature_code":"PPLL",
    "gn:name":"Piple",
    "gn:population":0,
    "gn:timezone":"Asia/Kathmandu",
    "iso:country":"NP",
    "name:new_x_preferred":[
        "\u092a\u093f\u092a\u094d\u0932\u0947"
    ],
    "name:pol_x_preferred":[
        "Piple"
    ],
    "wof:name":"Piple",
    "wof:placetype":"locality"
},
  "geometry": {"coordinates":[86.82068000000002,27.30078],"type":"Point"}
}