{
  "type": "Feature",
  "properties": {
    "gn:admin1_code":"FR",
    "gn:admin2_code":"9",
    "gn:admin3_code":"74",
    "gn:admin4_code":"740008",
    "gn:asciiname":"Manakot",
    "gn:country_code":"NP",
    "gn:dem":1612,
    "gn:feature_class":"P",
    "gn:feature_code":"PPLL",
    "gn:name":"Manakot",
    "gn:population":0,
    "gn:timezone":"Asia/Kathmandu",
    "iso:country":"NP",
    "name:fra_x_preferred":[
        "Manakot"
    ],
    "name:mai_x_preferred":[
        "\u092e\u093e\u0928\u093e\u0915\u094b\u091f"
    ],
    "name:msa_x_preferred":[
        "Manakot"
    ],
    "name:nep_x_preferred":[
        "\u092e\u093e\u0928\u093e\u0915\u094b\u091f"
    ],
    "name:new_x_preferred":[
        "\u092e\u0928\u0915\u094b\u0924"
    ],
    "name:pol_x_preferred":[
        "Manakot"
    ],
    "wof:name":"Manakot",
    "wof:placetype":"locality"
},
  "geometry": {"coordinates":[80.73145,29.56568],"type":"Point"}
}