{
  "type": "Feature",
  "properties": {
    "gn:admin1_code":"ER",
    "gn:admin2_code":"10",
    "gn:admin3_code":"2",
    "gn:admin4_code":"20023",
    "gn:asciiname":"Narkate",
    "gn:country_code":"NP",
    "gn:dem":1652,
    "gn:feature_class":"P",
    "gn:feature_code":"PPLL",
    "gn:name":"Narkate",
    "gn:population":0,
    "gn:timezone":"Asia/Kathmandu",
    "iso:country":"NP",
    "wof:name":"Narkate",
    "wof:placetype":"locality"
},
  "geometry": {"coordinates":[87.73331,27.07402],"type":"Point"}
}