{
  "type": "Feature",
  "properties": {
    "gn:admin1_code":"FR",
    "gn:admin2_code":"14",
    "gn:admin3_code":"70.0",
    "gn:admin4_code":"700009.0",
    "gn:asciiname":"Aili",
    "gn:country_code":"NP",
    "gn:dem":1718,
    "gn:feature_class":"P",
    "gn:feature_code":"PPLL",
    "gn:name":"Aili",
    "gn:population":0,
    "gn:timezone":"Asia/Kathmandu",
    "iso:country":"NP",
    "name:deu_x_preferred":[
        "Aili"
    ],
    "name:est_x_preferred":[
        "Aili"
    ],
    "name:fin_x_preferred":[
        "Aili"
    ],
    "wof:name":"Aili",
    "wof:placetype":"locality"
},
  "geometry": {"coordinates":[80.89530999999999,29.35145],"type":"Point"}
}