{
  "type": "Feature",
  "properties": {
    "gn:admin1_code":"MR",
    "gn:admin2_code":"2",
    "gn:admin3_code":"60.0",
    "gn:admin4_code":"600035.0",
    "gn:asciiname":"Sirubari",
    "gn:country_code":"NP",
    "gn:dem":807,
    "gn:feature_class":"P",
    "gn:feature_code":"PPLL",
    "gn:name":"Sirubari",
    "gn:population":0,
    "gn:timezone":"Asia/Kathmandu",
    "iso:country":"NP",
    "wof:name":"Sirubari",
    "wof:placetype":"locality"
},
  "geometry": {"coordinates":[81.74426,28.83579000000001],"type":"Point"}
}