{
  "type": "Feature",
  "properties": {
    "gn:admin1_code":"MR",
    "gn:admin2_code":"6",
    "gn:admin3_code":"63.0",
    "gn:admin4_code":"630025.0",
    "gn:asciiname":"Bijora Hiu Chuli",
    "gn:country_code":"NP",
    "gn:dem":5716,
    "gn:feature_class":"P",
    "gn:feature_code":"PPLL",
    "gn:name":"Bijora Hiu Chuli",
    "gn:population":0,
    "gn:timezone":"Asia/Kathmandu",
    "iso:country":"NP",
    "wof:name":"Bijora Hiu Chuli",
    "wof:placetype":"locality"
},
  "geometry": {"coordinates":[82.53178,29.29483],"type":"Point"}
}