{
  "type": "Feature",
  "properties": {
    "gn:admin1_code":"WR",
    "gn:admin2_code":"4.0",
    "gn:admin3_code":"38.0",
    "gn:admin4_code":"380038.0",
    "gn:asciiname":"Archale",
    "gn:country_code":"NP",
    "gn:dem":836,
    "gn:feature_class":"P",
    "gn:feature_code":"PPLL",
    "gn:name":"Archale",
    "gn:population":0,
    "gn:timezone":"Asia/Kathmandu",
    "iso:country":"NP",
    "name:ceb_x_preferred":[
        "Archale"
    ],
    "name:hin_x_preferred":[
        "\u0905\u0930\u094d\u091a\u0932\u0947"
    ],
    "name:msa_x_preferred":[
        "Archale"
    ],
    "name:nep_x_preferred":[
        "\u0905\u0930\u094d\u091a\u0932\u0947"
    ],
    "name:new_x_preferred":[
        "\u0905\u0930\u094d\u091a\u0932\u0947"
    ],
    "name:pol_x_preferred":[
        "Archale"
    ],
    "wof:name":"Archale",
    "wof:placetype":"locality"
},
  "geometry": {"coordinates":[84.14248000000001,27.93794],"type":"Point"}
}