{
  "type": "Feature",
  "properties": {
    "gn:admin1_code":"FR",
    "gn:admin2_code":"14",
    "gn:admin3_code":"69.0",
    "gn:admin4_code":"690058.0",
    "gn:asciiname":"Katela",
    "gn:country_code":"NP",
    "gn:dem":1041,
    "gn:feature_class":"P",
    "gn:feature_code":"PPLL",
    "gn:name":"Katela",
    "gn:population":0,
    "gn:timezone":"Asia/Kathmandu",
    "iso:country":"NP",
    "name:est_x_preferred":[
        "Katela"
    ],
    "name:hye_x_preferred":[
        "\u053f\u0561\u057f\u0565\u056c\u0561"
    ],
    "name:pol_x_preferred":[
        "Katela"
    ],
    "name:vol_x_preferred":[
        "Katela"
    ],
    "wof:name":"Katela",
    "wof:placetype":"locality"
},
  "geometry": {"coordinates":[81.55724000000002,28.78424],"type":"Point"}
}