{
  "type": "Feature",
  "properties": {
    "gn:admin1_code":"WR",
    "gn:admin2_code":"8",
    "gn:admin3_code":"49",
    "gn:admin4_code":"490071",
    "gn:asciiname":"Karaujiya",
    "gn:country_code":"NP",
    "gn:dem":123,
    "gn:feature_class":"P",
    "gn:feature_code":"PPLL",
    "gn:name":"Karaujiya",
    "gn:population":0,
    "gn:timezone":"Asia/Kathmandu",
    "iso:country":"NP",
    "wof:name":"Karaujiya",
    "wof:placetype":"locality"
},
  "geometry": {"coordinates":[83.45738,27.60463],"type":"Point"}
}