{
  "type": "Feature",
  "properties": {
    "gn:admin1_code":"WR",
    "gn:admin2_code":"8",
    "gn:admin3_code":"49",
    "gn:admin4_code":"490054",
    "gn:asciiname":"Amawa",
    "gn:country_code":"NP",
    "gn:dem":112,
    "gn:feature_class":"P",
    "gn:feature_code":"PPLL",
    "gn:name":"Amawa",
    "gn:population":0,
    "gn:timezone":"Asia/Kathmandu",
    "iso:country":"NP",
    "wof:name":"Amawa",
    "wof:placetype":"locality"
},
  "geometry": {"coordinates":[83.51118000000002,27.47757],"type":"Point"}
}