{
  "type": "Feature",
  "properties": {
    "gn:admin1_code":"FR",
    "gn:admin2_code":"14",
    "gn:admin3_code":"69",
    "gn:admin4_code":"690039",
    "gn:asciiname":"Tallo Tuka",
    "gn:country_code":"NP",
    "gn:dem":1679,
    "gn:feature_class":"P",
    "gn:feature_code":"PPLL",
    "gn:name":"Tallo Tuka",
    "gn:population":0,
    "gn:timezone":"Asia/Kathmandu",
    "iso:country":"NP",
    "wof:name":"Tallo Tuka",
    "wof:placetype":"locality"
},
  "geometry": {"coordinates":[81.21252,29.33157000000001],"type":"Point"}
}