{
  "type": "Feature",
  "properties": {
    "gn:admin1_code":"ER",
    "gn:admin2_code":"13",
    "gn:admin3_code":"13.0",
    "gn:admin4_code":"130027.0",
    "gn:asciiname":"Manedandagaun",
    "gn:country_code":"NP",
    "gn:dem":1973,
    "gn:feature_class":"P",
    "gn:feature_code":"PPLL",
    "gn:name":"Manedandagaun",
    "gn:population":0,
    "gn:timezone":"Asia/Kathmandu",
    "iso:country":"NP",
    "wof:name":"Manedandagaun",
    "wof:placetype":"locality"
},
  "geometry": {"coordinates":[86.84506,27.22104],"type":"Point"}
}