{
  "type": "Feature",
  "properties": {
    "gn:admin1_code":"CR",
    "gn:admin2_code":"11",
    "gn:admin3_code":"35.0",
    "gn:admin4_code":"350024.0",
    "gn:asciiname":"Bagakurti",
    "gn:country_code":"NP",
    "gn:dem":1377,
    "gn:feature_class":"P",
    "gn:feature_code":"PPLL",
    "gn:name":"Bagakurti",
    "gn:population":0,
    "gn:timezone":"Asia/Kathmandu",
    "iso:country":"NP",
    "wof:name":"Bagakurti",
    "wof:placetype":"locality"
},
  "geometry": {"coordinates":[84.78775999999998,27.68515],"type":"Point"}
}