{
  "type": "Feature",
  "properties": {
    "gn:admin1_code":"ER",
    "gn:admin2_code":"10",
    "gn:admin3_code":"3.0",
    "gn:admin4_code":"30019.0",
    "gn:asciiname":"Guranse",
    "gn:country_code":"NP",
    "gn:dem":2880,
    "gn:feature_class":"P",
    "gn:feature_code":"PPLL",
    "gn:name":"Guranse",
    "gn:population":0,
    "gn:timezone":"Asia/Kathmandu",
    "iso:country":"NP",
    "wof:name":"Guranse",
    "wof:placetype":"locality"
},
  "geometry": {"coordinates":[88.0763,27.02861],"type":"Point"}
}