{
  "type": "Feature",
  "properties": {
    "gn:admin1_code":"CR",
    "gn:admin2_code":"11",
    "gn:admin3_code":"31",
    "gn:admin4_code":"310038",
    "gn:asciiname":"Gotheri",
    "gn:country_code":"NP",
    "gn:dem":408,
    "gn:feature_class":"P",
    "gn:feature_code":"PPLL",
    "gn:name":"Gotheri",
    "gn:population":0,
    "gn:timezone":"Asia/Kathmandu",
    "iso:country":"NP",
    "wof:name":"Gotheri",
    "wof:placetype":"locality"
},
  "geometry": {"coordinates":[84.88094,27.52614],"type":"Point"}
}