{
  "type": "Feature",
  "properties": {
    "gn:admin1_code":"CR",
    "gn:admin2_code":"5",
    "gn:admin3_code":"22.0",
    "gn:admin4_code":"220008.0",
    "gn:asciiname":"Boch",
    "gn:country_code":"NP",
    "gn:dem":1872,
    "gn:feature_class":"P",
    "gn:feature_code":"PPLL",
    "gn:name":"Boch",
    "gn:population":0,
    "gn:timezone":"Asia/Kathmandu",
    "iso:country":"NP",
    "name:deu_x_preferred":[
        "Boch"
    ],
    "name:fra_x_preferred":[
        "Boch"
    ],
    "name:lim_x_preferred":[
        "B\u00f3ch"
    ],
    "wof:name":"Boch",
    "wof:placetype":"locality"
},
  "geometry": {"coordinates":[85.98763000000002,27.68412],"type":"Point"}
}