{
  "type": "Feature",
  "properties": {
    "gn:admin1_code":"ER",
    "gn:admin2_code":"13",
    "gn:admin3_code":"13",
    "gn:admin4_code":"130044",
    "gn:asciiname":"Kalchunde",
    "gn:country_code":"NP",
    "gn:dem":860,
    "gn:feature_class":"P",
    "gn:feature_code":"PPLL",
    "gn:name":"Kalchunde",
    "gn:population":0,
    "gn:timezone":"Asia/Kathmandu",
    "iso:country":"NP",
    "wof:name":"Kalchunde",
    "wof:placetype":"locality"
},
  "geometry": {"coordinates":[86.79361999999998,27.1659],"type":"Point"}
}