{
  "type": "Feature",
  "properties": {
    "gn:admin1_code":"WR",
    "gn:admin2_code":"4",
    "gn:admin3_code":"36.0",
    "gn:admin4_code":"360050.0",
    "gn:asciiname":"Terhakilo",
    "gn:country_code":"NP",
    "gn:dem":460,
    "gn:feature_class":"P",
    "gn:feature_code":"PPLL",
    "gn:name":"Terhakilo",
    "gn:population":0,
    "gn:timezone":"Asia/Kathmandu",
    "iso:country":"NP",
    "wof:name":"Terhakilo",
    "wof:placetype":"locality"
},
  "geometry": {"coordinates":[84.57628000000003,27.98383],"type":"Point"}
}