{
  "type": "Feature",
  "properties": {
    "gn:admin1_code":"WR",
    "gn:admin2_code":"4.0",
    "gn:admin3_code":"38.0",
    "gn:admin4_code":"380021.0",
    "gn:asciiname":"Marat",
    "gn:country_code":"NP",
    "gn:dem":532,
    "gn:feature_class":"P",
    "gn:feature_code":"PPLL",
    "gn:name":"Marat",
    "gn:population":0,
    "gn:timezone":"Asia/Kathmandu",
    "iso:country":"NP",
    "wof:name":"Marat",
    "wof:placetype":"locality"
},
  "geometry": {"coordinates":[84.03721,28.09602000000001],"type":"Point"}
}