{
  "type": "Feature",
  "properties": {
    "gn:admin1_code":"WR",
    "gn:admin2_code":"4.0",
    "gn:admin3_code":"38.0",
    "gn:admin4_code":"380021.0",
    "gn:asciiname":"Marat",
    "gn:country_code":"NP",
    "gn:dem":532,
    "gn:feature_class":"P",
    "gn:feature_code":"PPLL",
    "gn:name":"Marat",
    "gn:population":0,
    "gn:timezone":"Asia/Kathmandu",
    "iso:country":"NP",
    "name:bre_x_preferred":[
        "Marat"
    ],
    "name:ceb_x_preferred":[
        "Marat"
    ],
    "name:ces_x_preferred":[
        "Marat"
    ],
    "name:deu_x_preferred":[
        "Marat"
    ],
    "name:est_x_preferred":[
        "Marat"
    ],
    "name:fin_x_preferred":[
        "Marat"
    ],
    "name:fra_x_preferred":[
        "Marat"
    ],
    "name:hun_x_preferred":[
        "Marat"
    ],
    "name:ita_x_preferred":[
        "Marat"
    ],
    "name:jpn_x_preferred":[
        "\u30de\u30e9\u30fc\u30c8"
    ],
    "name:nld_x_preferred":[
        "Marat"
    ],
    "name:pol_x_preferred":[
        "Marat"
    ],
    "name:ron_x_preferred":[
        "Marat"
    ],
    "name:rus_x_preferred":[
        "\u041c\u0430\u0440\u0430\u0442"
    ],
    "name:slk_x_preferred":[
        "Marat"
    ],
    "name:spa_x_preferred":[
        "Marat"
    ],
    "name:swe_x_preferred":[
        "Marat"
    ],
    "name:ukr_x_preferred":[
        "\u041c\u0430\u0440\u0430\u0442"
    ],
    "wof:name":"Marat",
    "wof:placetype":"locality"
},
  "geometry": {"coordinates":[84.03721,28.09602000000001],"type":"Point"}
}