{
  "type": "Feature",
  "properties": {
    "gn:admin1_code":"ER",
    "gn:admin2_code":"10",
    "gn:admin3_code":"2",
    "gn:admin4_code":"20040.0",
    "gn:asciiname":"Thangnapa",
    "gn:country_code":"NP",
    "gn:dem":1644,
    "gn:feature_class":"P",
    "gn:feature_code":"PPLL",
    "gn:name":"Thangnapa",
    "gn:population":0,
    "gn:timezone":"Asia/Kathmandu",
    "iso:country":"NP",
    "wof:name":"Thangnapa",
    "wof:placetype":"locality"
},
  "geometry": {"coordinates":[87.81586999999998,27.16219],"type":"Point"}
}