{
  "type": "Feature",
  "properties": {
    "gn:admin1_code":"00",
    "gn:asciiname":"Bandadandi",
    "gn:country_code":"NP",
    "gn:dem":186,
    "gn:feature_class":"P",
    "gn:feature_code":"PPL",
    "gn:name":"B\u0101nd\u0101d\u0101ndi",
    "gn:population":0,
    "gn:timezone":"Asia/Kathmandu",
    "iso:country":"NP",
    "name:und_x_variant":[
        "Boradandi",
        "B\u0101nd\u0101d\u0101ndi"
    ],
    "wof:name":"Bandadandi",
    "wof:placetype":"locality"
},
  "geometry": {"coordinates":[80.53819,28.73381],"type":"Point"}
}