{
  "type": "Feature",
  "properties": {
    "gn:admin1_code":"00",
    "gn:asciiname":"Dhade",
    "gn:country_code":"NP",
    "gn:dem":1854,
    "gn:feature_class":"P",
    "gn:feature_code":"PPL",
    "gn:name":"\u1e0ch\u0101\u0303\u1e0de",
    "gn:population":0,
    "gn:timezone":"Asia/Kathmandu",
    "iso:country":"NP",
    "wof:name":"Dhade",
    "wof:placetype":"locality"
},
  "geometry": {"coordinates":[86.61219,27.43731],"type":"Point"}
}