{
  "type": "Feature",
  "properties": {
    "gn:admin1_code":"MR",
    "gn:admin2_code":"12",
    "gn:admin3_code":"55",
    "gn:admin4_code":"550031",
    "gn:asciiname":"Pilsigetol",
    "gn:country_code":"NP",
    "gn:dem":1351,
    "gn:feature_class":"P",
    "gn:feature_code":"PPLL",
    "gn:name":"Pilsigetol",
    "gn:population":0,
    "gn:timezone":"Asia/Kathmandu",
    "iso:country":"NP",
    "wof:name":"Pilsigetol",
    "wof:placetype":"locality"
},
  "geometry": {"coordinates":[82.00544000000002,28.41451],"type":"Point"}
}