{
  "type": "Feature",
  "properties": {
    "gn:admin1_code":"FR",
    "gn:admin2_code":"14",
    "gn:admin3_code":"71.0",
    "gn:admin4_code":"710001.0",
    "gn:asciiname":"Dudejhari",
    "gn:country_code":"NP",
    "gn:dem":204,
    "gn:feature_class":"P",
    "gn:feature_code":"PPLL",
    "gn:name":"Dudejhari",
    "gn:population":0,
    "gn:timezone":"Asia/Kathmandu",
    "iso:country":"NP",
    "wof:name":"Dudejhari",
    "wof:placetype":"locality"
},
  "geometry": {"coordinates":[81.20817,28.61917],"type":"Point"}
}