{
  "type": "Feature",
  "properties": {
    "gn:country":"NP",
    "gn:fcode":"PPLA",
    "gn:population":22084,
    "iso:country":"NP",
    "name:bho_x_preferred":[
        "\u0927\u0928\u0915\u0941\u091f\u093e"
    ],
    "name:ceb_x_preferred":[
        "Dhankut\u0101"
    ],
    "name:deu_x_preferred":[
        "Dhankuta"
    ],
    "name:eng_x_preferred":[
        "Dhankuta"
    ],
    "name:eus_x_preferred":[
        "Dhankuta"
    ],
    "name:fra_x_preferred":[
        "Dhankuta"
    ],
    "name:hin_x_preferred":[
        "\u0927\u0928\u0915\u0941\u091f\u093e"
    ],
    "name:ita_x_preferred":[
        "Dhanakuta"
    ],
    "name:jpn_x_preferred":[
        "\u30c0\u30f3\u30af\u30bf"
    ],
    "name:kur_x_preferred":[
        "Dhankuta"
    ],
    "name:mai_x_preferred":[
        "\u0927\u0928\u0915\u0941\u091f\u093e \u0928\u0917\u0930\u092a\u093e\u0932\u093f\u0915\u093e"
    ],
    "name:nep_x_preferred":[
        "\u0927\u0928\u0915\u0941\u091f\u093e \u0928\u0917\u0930\u092a\u093e\u0932\u093f\u0915\u093e"
    ],
    "name:nld_x_preferred":[
        "Dhankuta"
    ],
    "name:pol_x_preferred":[
        "Dhankuta"
    ],
    "name:por_x_preferred":[
        "Dhankuta"
    ],
    "name:rus_x_preferred":[
        "\u0414\u0430\u043d\u043a\u0443\u0442\u0430"
    ],
    "name:rus_x_variant":[
        "\u0414\u0445\u0430\u043d\u043a\u0443\u0442\u0430"
    ],
    "name:ukr_x_preferred":[
        "\u0414\u0445\u0430\u043d\u043a\u0443\u0442\u0430"
    ],
    "name:und_x_variant":[
        "Dhankutta"
    ],
    "name:zho_x_preferred":[
        "\u4e39\u5eab\u5854"
    ],
    "qs:name":"Dhankut\u0101",
    "qs:photos_9r":0,
    "qs:photos_sr":0,
    "qs:pop_sr":"7",
    "wd:wordcount":319,
    "wof:name":"Dhankut\u0101",
    "wof:placetype":"locality",
    "wof:population":22084
},
  "geometry": {"coordinates":[87.33333,26.98333],"type":"Point"}
}