{
  "type": "Feature",
  "properties": {
    "gn:admin1_code":"MR",
    "gn:admin2_code":"12",
    "gn:admin3_code":"53",
    "gn:admin4_code":"530011",
    "gn:asciiname":"Gang",
    "gn:country_code":"NP",
    "gn:dem":1687,
    "gn:feature_class":"P",
    "gn:feature_code":"PPLL",
    "gn:name":"Gang",
    "gn:population":0,
    "gn:timezone":"Asia/Kathmandu",
    "iso:country":"NP",
    "wof:name":"Gang",
    "wof:placetype":"locality"
},
  "geometry": {"coordinates":[82.51873000000001,28.32754000000001],"type":"Point"}
}