{
  "type": "Feature",
  "properties": {
    "gn:admin1_code":"MR",
    "gn:admin2_code":"12",
    "gn:admin3_code":"53",
    "gn:admin4_code":"530011",
    "gn:asciiname":"Gang",
    "gn:country_code":"NP",
    "gn:dem":1687,
    "gn:feature_class":"P",
    "gn:feature_code":"PPLL",
    "gn:name":"Gang",
    "gn:population":0,
    "gn:timezone":"Asia/Kathmandu",
    "iso:country":"NP",
    "name:aze_x_preferred":[
        "Banda"
    ],
    "name:bre_x_preferred":[
        "Gang"
    ],
    "name:bul_x_preferred":[
        "\u0411\u0430\u043d\u0434\u0430"
    ],
    "name:ces_x_preferred":[
        "Gang"
    ],
    "name:dan_x_preferred":[
        "Bande"
    ],
    "name:deu_x_preferred":[
        "Bande"
    ],
    "name:epo_x_preferred":[
        "Bando"
    ],
    "name:eus_x_preferred":[
        "Mara"
    ],
    "name:fas_x_preferred":[
        "\u0628\u0627\u0646\u062f \u062e\u0644\u0627\u0641\u06a9\u0627\u0631\u0627\u0646"
    ],
    "name:fin_x_preferred":[
        "Katujengi"
    ],
    "name:fra_x_preferred":[
        "Bande criminelle"
    ],
    "name:fry_x_preferred":[
        "Binde"
    ],
    "name:gle_x_preferred":[
        "Drong"
    ],
    "name:heb_x_preferred":[
        "\u05db\u05e0\u05d5\u05e4\u05d9\u05d4"
    ],
    "name:hin_x_preferred":[
        "\u0917\u093f\u0930\u094b\u0939"
    ],
    "name:ind_x_preferred":[
        "Geng"
    ],
    "name:ita_x_preferred":[
        "Banda"
    ],
    "name:jpn_x_preferred":[
        "\u30ae\u30e3\u30f3\u30b0"
    ],
    "name:kor_x_preferred":[
        "\ud3ed\ub825 \uc870\uc9c1"
    ],
    "name:lav_x_preferred":[
        "Banda"
    ],
    "name:msa_x_preferred":[
        "Geng"
    ],
    "name:mya_x_preferred":[
        "\u1002\u102d\u102f\u100f\u103a\u1038"
    ],
    "name:nld_x_preferred":[
        "Bende"
    ],
    "name:pol_x_preferred":[
        "Gang"
    ],
    "name:por_x_preferred":[
        "Quadrilha"
    ],
    "name:scn_x_preferred":[
        "Cricca"
    ],
    "name:slk_x_preferred":[
        "Gang"
    ],
    "name:som_x_preferred":[
        "Ciyaal suuq"
    ],
    "name:spa_x_preferred":[
        "Pandilla"
    ],
    "name:srp_x_preferred":[
        "\u0411\u0430\u043d\u0434\u0430"
    ],
    "name:swe_x_preferred":[
        "G\u00e4ng"
    ],
    "name:tel_x_preferred":[
        "\u0c17\u0c3e\u0c02\u0c17\u0c4d"
    ],
    "name:tur_x_preferred":[
        "\u00c7ete"
    ],
    "wof:name":"Gang",
    "wof:placetype":"locality"
},
  "geometry": {"coordinates":[82.51873000000001,28.32754000000001],"type":"Point"}
}