{
  "type": "Feature",
  "properties": {
    "gn:admin1_code":"WR",
    "gn:admin2_code":"3",
    "gn:admin3_code":"43",
    "gn:admin4_code":"430027",
    "gn:asciiname":"Dada Kateri",
    "gn:country_code":"NP",
    "gn:dem":2118,
    "gn:feature_class":"P",
    "gn:feature_code":"PPLL",
    "gn:name":"Dada Kateri",
    "gn:population":0,
    "gn:timezone":"Asia/Kathmandu",
    "iso:country":"NP",
    "wof:name":"Dada Kateri",
    "wof:placetype":"locality"
},
  "geometry": {"coordinates":[83.36917,28.38793],"type":"Point"}
}