{
  "type": "Feature",
  "properties": {
    "gn:admin1_code":"CR",
    "gn:admin2_code":"1",
    "gn:admin3_code":"28",
    "gn:admin4_code":"280056",
    "gn:asciiname":"Salme",
    "gn:country_code":"NP",
    "gn:dem":1613,
    "gn:feature_class":"P",
    "gn:feature_code":"PPLL",
    "gn:name":"Salme",
    "gn:population":0,
    "gn:timezone":"Asia/Kathmandu",
    "iso:country":"NP",
    "wof:name":"Salme",
    "wof:placetype":"locality"
},
  "geometry": {"coordinates":[85.43185,27.86181],"type":"Point"}
}