{
  "type": "Feature",
  "properties": {
    "gn:admin1_code":"CR",
    "gn:admin2_code":"5",
    "gn:admin3_code":"20",
    "gn:admin4_code":"200037",
    "gn:asciiname":"Bandipur",
    "gn:country_code":"NP",
    "gn:dem":1562,
    "gn:feature_class":"P",
    "gn:feature_code":"PPLL",
    "gn:name":"Bandipur",
    "gn:population":0,
    "gn:timezone":"Asia/Kathmandu",
    "iso:country":"NP",
    "wof:name":"Bandipur",
    "wof:placetype":"locality"
},
  "geometry": {"coordinates":[85.75306999999999,27.37088],"type":"Point"}
}