{
  "type": "Feature",
  "properties": {
    "gn:admin1_code":"CR",
    "gn:admin2_code":"5",
    "gn:admin3_code":"20",
    "gn:admin4_code":"200037",
    "gn:asciiname":"Bandipur",
    "gn:country_code":"NP",
    "gn:dem":1562,
    "gn:feature_class":"P",
    "gn:feature_code":"PPLL",
    "gn:name":"Bandipur",
    "gn:population":0,
    "gn:timezone":"Asia/Kathmandu",
    "iso:country":"NP",
    "name:ceb_x_preferred":[
        "Band\u012bpur"
    ],
    "name:deu_x_preferred":[
        "Bandipur"
    ],
    "name:eus_x_preferred":[
        "Bandipur"
    ],
    "name:fra_x_preferred":[
        "Bandipur"
    ],
    "name:hin_x_preferred":[
        "\u092c\u0928\u094d\u0926\u0940\u092a\u0941\u0930 \u0928\u0917\u0930\u092a\u093e\u0932\u093f\u0915\u093e"
    ],
    "name:mai_x_preferred":[
        "\u092c\u0928\u094d\u0926\u0940\u092a\u0941\u0930 \u0917\u093e\u0909\u0901\u092a\u093e\u0932\u093f\u0915\u093e"
    ],
    "name:mal_x_preferred":[
        "\u0d2c\u0d28\u0d4d\u0d26\u0d3f\u0d2a\u0d4d\u0d2a\u0d42\u0d7c"
    ],
    "name:msa_x_preferred":[
        "Bandipur"
    ],
    "name:nep_x_preferred":[
        "\u092c\u0928\u094d\u0926\u0940\u092a\u0941\u0930 \u0917\u093e\u0909\u0901\u092a\u093e\u0932\u093f\u0915\u093e"
    ],
    "name:new_x_preferred":[
        "\u092c\u0928\u094d\u0926\u0940\u092a\u0941\u0930"
    ],
    "name:pol_x_preferred":[
        "Bandipur"
    ],
    "name:urd_x_preferred":[
        "\u0628\u0646\u062f\u06cc \u067e\u0648\u0631"
    ],
    "wof:name":"Bandipur",
    "wof:placetype":"locality"
},
  "geometry": {"coordinates":[85.75306999999999,27.37088],"type":"Point"}
}