{
  "type": "Feature",
  "properties": {
    "gn:admin1_code":"MR",
    "gn:admin2_code":"12",
    "gn:admin3_code":"52",
    "gn:admin4_code":"520043",
    "gn:asciiname":"Gaekharka",
    "gn:country_code":"NP",
    "gn:dem":994,
    "gn:feature_class":"P",
    "gn:feature_code":"PPLL",
    "gn:name":"Gaekharka",
    "gn:population":0,
    "gn:timezone":"Asia/Kathmandu",
    "iso:country":"NP",
    "wof:name":"Gaekharka",
    "wof:placetype":"locality"
},
  "geometry": {"coordinates":[82.72941,28.17821],"type":"Point"}
}