{
  "type": "Feature",
  "properties": {
    "gn:admin1_code":"ER",
    "gn:admin2_code":"7",
    "gn:admin3_code":"7.0",
    "gn:admin4_code":"70019.0",
    "gn:asciiname":"Katuwalgaun",
    "gn:country_code":"NP",
    "gn:dem":1541,
    "gn:feature_class":"P",
    "gn:feature_code":"PPLL",
    "gn:name":"Katuwalgaun",
    "gn:population":0,
    "gn:timezone":"Asia/Kathmandu",
    "iso:country":"NP",
    "wof:name":"Katuwalgaun",
    "wof:placetype":"locality"
},
  "geometry": {"coordinates":[87.33551999999997,27.07063],"type":"Point"}
}