{
  "type": "Feature",
  "properties": {
    "gn:admin1_code":"CR",
    "gn:admin2_code":"11",
    "gn:admin3_code":"31",
    "gn:admin4_code":"310019",
    "gn:asciiname":"Sano Gahate",
    "gn:country_code":"NP",
    "gn:dem":490,
    "gn:feature_class":"P",
    "gn:feature_code":"PPLL",
    "gn:name":"Sano Gahate",
    "gn:population":0,
    "gn:timezone":"Asia/Kathmandu",
    "iso:country":"NP",
    "wof:name":"Sano Gahate",
    "wof:placetype":"locality"
},
  "geometry": {"coordinates":[85.11322,27.37481],"type":"Point"}
}