{
  "type": "Feature",
  "properties": {
    "gn:admin1_code":"CR",
    "gn:admin2_code":"1",
    "gn:admin3_code":"24.0",
    "gn:admin4_code":"240042.0",
    "gn:asciiname":"Chiyandanda",
    "gn:country_code":"NP",
    "gn:dem":1468,
    "gn:feature_class":"P",
    "gn:feature_code":"PPLL",
    "gn:name":"Chiyandanda",
    "gn:population":0,
    "gn:timezone":"Asia/Kathmandu",
    "iso:country":"NP",
    "wof:name":"Chiyandanda",
    "wof:placetype":"locality"
},
  "geometry": {"coordinates":[85.58353000000002,27.51942],"type":"Point"}
}