{
  "type": "Feature",
  "properties": {
    "gn:admin1_code":"FR",
    "gn:admin2_code":"14",
    "gn:admin3_code":"70.0",
    "gn:admin4_code":"700046.0",
    "gn:asciiname":"Isura",
    "gn:country_code":"NP",
    "gn:dem":1488,
    "gn:feature_class":"P",
    "gn:feature_code":"PPLL",
    "gn:name":"Isura",
    "gn:population":0,
    "gn:timezone":"Asia/Kathmandu",
    "iso:country":"NP",
    "wof:name":"Isura",
    "wof:placetype":"locality"
},
  "geometry": {"coordinates":[81.01391,29.03886],"type":"Point"}
}