{
  "type": "Feature",
  "properties": {
    "gn:admin1_code":"CR",
    "gn:admin2_code":"1",
    "gn:admin3_code":"24.0",
    "gn:admin4_code":"240069.0",
    "gn:asciiname":"Narayansthan",
    "gn:country_code":"NP",
    "gn:dem":1706,
    "gn:feature_class":"P",
    "gn:feature_code":"PPLL",
    "gn:name":"Narayansthan",
    "gn:population":0,
    "gn:timezone":"Asia/Kathmandu",
    "iso:country":"NP",
    "wof:name":"Narayansthan",
    "wof:placetype":"locality"
},
  "geometry": {"coordinates":[85.74099,27.52172],"type":"Point"}
}