{
  "type": "Feature",
  "properties": {
    "gn:admin1_code":"00",
    "gn:asciiname":"Pajun",
    "gn:country_code":"NP",
    "gn:dem":1942,
    "gn:feature_class":"P",
    "gn:feature_code":"PPL",
    "gn:name":"Paju\u1e45",
    "gn:population":0,
    "gn:timezone":"Asia/Kathmandu",
    "iso:country":"NP",
    "wof:name":"Pajun",
    "wof:placetype":"locality"
},
  "geometry": {"coordinates":[85.32796999999999,28.18599],"type":"Point"}
}