{
  "type": "Feature",
  "properties": {
    "gn:admin1_code":"MR",
    "gn:admin2_code":"2.0",
    "gn:admin3_code":"57.0",
    "gn:admin4_code":"570034.0",
    "gn:asciiname":"Bisambharpur",
    "gn:country_code":"NP",
    "gn:dem":139,
    "gn:feature_class":"P",
    "gn:feature_code":"PPLL",
    "gn:name":"Bisambharpur",
    "gn:population":0,
    "gn:timezone":"Asia/Kathmandu",
    "iso:country":"NP",
    "wof:name":"Bisambharpur",
    "wof:placetype":"locality"
},
  "geometry": {"coordinates":[81.75386999999998,28.01955],"type":"Point"}
}