{
  "type": "Feature",
  "properties": {
    "gn:admin1_code":"CR",
    "gn:admin2_code":"5",
    "gn:admin3_code":"17.0",
    "gn:admin4_code":"170049.0",
    "gn:asciiname":"Jhatiyahi",
    "gn:country_code":"NP",
    "gn:dem":89,
    "gn:feature_class":"P",
    "gn:feature_code":"PPLL",
    "gn:name":"Jhatiyahi",
    "gn:population":0,
    "gn:timezone":"Asia/Kathmandu",
    "iso:country":"NP",
    "name:ceb_x_preferred":[
        "Jhatiyahi"
    ],
    "name:mai_x_preferred":[
        "\u091d\u091f\u093f\u092f\u093e\u0939\u0940"
    ],
    "name:msa_x_preferred":[
        "Jhatiyahi"
    ],
    "name:nep_x_preferred":[
        "\u091d\u091f\u093f\u092f\u093e\u0939\u0940"
    ],
    "name:new_x_preferred":[
        "\u091d\u093e\u0924\u093f\u092f\u093e\u0939\u0940"
    ],
    "name:pol_x_preferred":[
        "Jhatiyahi"
    ],
    "wof:name":"Jhatiyahi",
    "wof:placetype":"locality"
},
  "geometry": {"coordinates":[86.05615999999998,26.77958],"type":"Point"}
}