{
  "type": "Feature",
  "properties": {
    "gn:admin1_code":"FR",
    "gn:admin2_code":"14",
    "gn:admin3_code":"69",
    "gn:admin4_code":"690027",
    "gn:asciiname":"Liusain",
    "gn:country_code":"NP",
    "gn:dem":1716,
    "gn:feature_class":"P",
    "gn:feature_code":"PPLL",
    "gn:name":"Liusain",
    "gn:population":0,
    "gn:timezone":"Asia/Kathmandu",
    "iso:country":"NP",
    "wof:name":"Liusain",
    "wof:placetype":"locality"
},
  "geometry": {"coordinates":[81.10925999999998,29.26408],"type":"Point"}
}