{
  "type": "Feature",
  "properties": {
    "gn:admin1_code":"WR",
    "gn:admin2_code":"4.0",
    "gn:admin3_code":"39.0",
    "gn:admin4_code":"390037.0",
    "gn:asciiname":"Phaudi",
    "gn:country_code":"NP",
    "gn:dem":957,
    "gn:feature_class":"P",
    "gn:feature_code":"PPLL",
    "gn:name":"Phaudi",
    "gn:population":0,
    "gn:timezone":"Asia/Kathmandu",
    "iso:country":"NP",
    "wof:name":"Phaudi",
    "wof:placetype":"locality"
},
  "geometry": {"coordinates":[83.90619000000002,28.06028],"type":"Point"}
}