{
  "type": "Feature",
  "properties": {
    "gn:admin1_code":"FR",
    "gn:admin2_code":"9",
    "gn:admin3_code":"73.0",
    "gn:admin4_code":"730013.0",
    "gn:asciiname":"Jadzayothali",
    "gn:country_code":"NP",
    "gn:dem":1177,
    "gn:feature_class":"P",
    "gn:feature_code":"PPLL",
    "gn:name":"Jadzayothali",
    "gn:population":0,
    "gn:timezone":"Asia/Kathmandu",
    "iso:country":"NP",
    "wof:name":"Jadzayothali",
    "wof:placetype":"locality"
},
  "geometry": {"coordinates":[80.38499,29.05264],"type":"Point"}
}