{
  "type": "Feature",
  "properties": {
    "gn:admin1_code":"CR",
    "gn:admin2_code":"1",
    "gn:admin3_code":"30.0",
    "gn:admin4_code":"300049.0",
    "gn:asciiname":"Kamigaun",
    "gn:country_code":"NP",
    "gn:dem":2048,
    "gn:feature_class":"P",
    "gn:feature_code":"PPLL",
    "gn:name":"Kamigaun",
    "gn:population":0,
    "gn:timezone":"Asia/Kathmandu",
    "iso:country":"NP",
    "wof:name":"Kamigaun",
    "wof:placetype":"locality"
},
  "geometry": {"coordinates":[85.1063,28.18032],"type":"Point"}
}