{
  "type": "Feature",
  "properties": {
    "gn:admin1_code":"MR",
    "gn:admin2_code":"6",
    "gn:admin3_code":"66.0",
    "gn:admin4_code":"660007.0",
    "gn:asciiname":"Lek Tangin",
    "gn:country_code":"NP",
    "gn:dem":3448,
    "gn:feature_class":"P",
    "gn:feature_code":"PPLL",
    "gn:name":"Lek Tangin",
    "gn:population":0,
    "gn:timezone":"Asia/Kathmandu",
    "iso:country":"NP",
    "wof:name":"Lek Tangin",
    "wof:placetype":"locality"
},
  "geometry": {"coordinates":[81.82226999999997,30.04655],"type":"Point"}
}