{
  "type": "Feature",
  "properties": {
    "gn:admin1_code":"ER",
    "gn:admin2_code":"13",
    "gn:admin3_code":"13",
    "gn:admin4_code":"130051",
    "gn:asciiname":"Parung",
    "gn:country_code":"NP",
    "gn:dem":1373,
    "gn:feature_class":"P",
    "gn:feature_code":"PPLL",
    "gn:name":"Parung",
    "gn:population":0,
    "gn:timezone":"Asia/Kathmandu",
    "iso:country":"NP",
    "wof:name":"Parung",
    "wof:placetype":"locality"
},
  "geometry": {"coordinates":[86.83587,27.1667],"type":"Point"}
}