{
  "type": "Feature",
  "properties": {
    "gn:admin1_code":"00",
    "gn:asciiname":"Majinthok",
    "gn:country_code":"NP",
    "gn:dem":789,
    "gn:feature_class":"P",
    "gn:feature_code":"PPL",
    "gn:name":"M\u0101jinthok",
    "gn:population":0,
    "gn:timezone":"Asia/Kathmandu",
    "iso:country":"NP",
    "name:nep_x_preferred":[
        "M\u0101jinthok"
    ],
    "name:und_x_variant":[
        "\u1e0cubin\u1e0d\u0101\u0303\u1e0d\u0101"
    ],
    "wof:name":"Majinthok",
    "wof:placetype":"locality"
},
  "geometry": {"coordinates":[84.78239000000001,28.03403],"type":"Point"}
}