{
  "type": "Feature",
  "properties": {
    "gn:admin1_code":"ER",
    "gn:admin2_code":"10.0",
    "gn:admin3_code":"1.0",
    "gn:admin4_code":"10044.0",
    "gn:asciiname":"Khoyang",
    "gn:country_code":"NP",
    "gn:dem":1037,
    "gn:feature_class":"P",
    "gn:feature_code":"PPLL",
    "gn:name":"Khoyang",
    "gn:population":0,
    "gn:timezone":"Asia/Kathmandu",
    "iso:country":"NP",
    "wof:name":"Khoyang",
    "wof:placetype":"locality"
},
  "geometry": {"coordinates":[87.86060999999999,27.35743],"type":"Point"}
}