{
  "type": "Feature",
  "properties": {
    "gn:admin1_code":"WR",
    "gn:admin2_code":"8",
    "gn:admin3_code":"46.0",
    "gn:admin4_code":"460073.0",
    "gn:asciiname":"Sirseni",
    "gn:country_code":"NP",
    "gn:dem":1297,
    "gn:feature_class":"P",
    "gn:feature_code":"PPLL",
    "gn:name":"Sirseni",
    "gn:population":0,
    "gn:timezone":"Asia/Kathmandu",
    "iso:country":"NP",
    "wof:name":"Sirseni",
    "wof:placetype":"locality"
},
  "geometry": {"coordinates":[83.09652,28.20046],"type":"Point"}
}