{
  "type": "Feature",
  "properties": {
    "gn:admin1_code":"MR",
    "gn:admin2_code":"2",
    "gn:admin3_code":"60.0",
    "gn:admin4_code":"600035.0",
    "gn:asciiname":"Belghari",
    "gn:country_code":"NP",
    "gn:dem":796,
    "gn:feature_class":"P",
    "gn:feature_code":"PPLL",
    "gn:name":"Belghari",
    "gn:population":0,
    "gn:timezone":"Asia/Kathmandu",
    "iso:country":"NP",
    "name:bih_x_preferred":[
        "\u092c\u0947\u0932\u0918\u093e\u0930\u0940"
    ],
    "name:ceb_x_preferred":[
        "Belghari"
    ],
    "name:fra_x_preferred":[
        "Belghari"
    ],
    "name:mai_x_preferred":[
        "\u092c\u0947\u0932\u0918\u093e\u0930\u0940"
    ],
    "name:msa_x_preferred":[
        "Belghari"
    ],
    "name:nep_x_preferred":[
        "\u092c\u0947\u0932\u0918\u093e\u0930\u0940"
    ],
    "name:pol_x_preferred":[
        "Belghari"
    ],
    "wof:name":"Belghari",
    "wof:placetype":"locality"
},
  "geometry": {"coordinates":[81.69436,28.80652000000001],"type":"Point"}
}