{
  "type": "Feature",
  "properties": {
    "gn:admin1_code":"ER",
    "gn:admin2_code":"7",
    "gn:admin3_code":"10.0",
    "gn:admin4_code":"100049.0",
    "gn:asciiname":"Guinche",
    "gn:country_code":"NP",
    "gn:dem":577,
    "gn:feature_class":"P",
    "gn:feature_code":"PPLL",
    "gn:name":"Guinche",
    "gn:population":0,
    "gn:timezone":"Asia/Kathmandu",
    "iso:country":"NP",
    "wof:name":"Guinche",
    "wof:placetype":"locality"
},
  "geometry": {"coordinates":[87.1537,27.05584],"type":"Point"}
}