{
  "type": "Feature",
  "properties": {
    "gn:admin1_code":"MR",
    "gn:admin2_code":"12",
    "gn:admin3_code":"54",
    "gn:admin4_code":"540038",
    "gn:asciiname":"Ranja",
    "gn:country_code":"NP",
    "gn:dem":829,
    "gn:feature_class":"P",
    "gn:feature_code":"PPLL",
    "gn:name":"Ranja",
    "gn:population":0,
    "gn:timezone":"Asia/Kathmandu",
    "iso:country":"NP",
    "wof:name":"Ranja",
    "wof:placetype":"locality"
},
  "geometry": {"coordinates":[82.36959,28.65583],"type":"Point"}
}