{
  "type": "Feature",
  "properties": {
    "gn:admin1_code":"00",
    "gn:asciiname":"Paiyamadi",
    "gn:country_code":"NP",
    "gn:dem":75,
    "gn:feature_class":"P",
    "gn:feature_code":"PPL",
    "gn:name":"Paiy\u0101\u0303m\u0101\u1e0di\u0307\u0304",
    "gn:population":0,
    "gn:timezone":"Asia/Kathmandu",
    "iso:country":"NP",
    "name:nep_x_preferred":[
        "Paiy\u0101\u0303m\u0101\u1e0di\u0307\u0304"
    ],
    "wof:name":"Paiyamadi",
    "wof:placetype":"locality"
},
  "geometry": {"coordinates":[87.61869,26.43706],"type":"Point"}
}