{
  "type": "Feature",
  "properties": {
    "gn:admin1_code":"CR",
    "gn:admin2_code":"5",
    "gn:admin3_code":"20",
    "gn:admin4_code":"200044",
    "gn:asciiname":"Kolbot",
    "gn:country_code":"NP",
    "gn:dem":1192,
    "gn:feature_class":"P",
    "gn:feature_code":"PPLL",
    "gn:name":"Kolbot",
    "gn:population":0,
    "gn:timezone":"Asia/Kathmandu",
    "iso:country":"NP",
    "wof:name":"Kolbot",
    "wof:placetype":"locality"
},
  "geometry": {"coordinates":[86.31010000000001,27.15758],"type":"Point"}
}