{
  "type": "Feature",
  "properties": {
    "gn:admin1_code":"ER",
    "gn:admin2_code":"10.0",
    "gn:admin3_code":"1.0",
    "gn:admin4_code":"10037.0",
    "gn:asciiname":"Temba",
    "gn:country_code":"NP",
    "gn:dem":1822,
    "gn:feature_class":"P",
    "gn:feature_code":"PPLL",
    "gn:name":"Temba",
    "gn:population":0,
    "gn:timezone":"Asia/Kathmandu",
    "iso:country":"NP",
    "wof:name":"Temba",
    "wof:placetype":"locality"
},
  "geometry": {"coordinates":[87.63082,27.49821],"type":"Point"}
}