{
  "type": "Feature",
  "properties": {
    "gn:admin1_code":"CR",
    "gn:admin2_code":"5",
    "gn:admin3_code":"17.0",
    "gn:admin4_code":"170030.0",
    "gn:asciiname":"Kemalipur",
    "gn:country_code":"NP",
    "gn:dem":199,
    "gn:feature_class":"P",
    "gn:feature_code":"PPLL",
    "gn:name":"Kemalipur",
    "gn:population":0,
    "gn:timezone":"Asia/Kathmandu",
    "iso:country":"NP",
    "wof:name":"Kemalipur",
    "wof:placetype":"locality"
},
  "geometry": {"coordinates":[85.9654,26.94606],"type":"Point"}
}