{
  "type": "Feature",
  "properties": {
    "gn:admin1_code":"WR",
    "gn:admin2_code":"3",
    "gn:admin3_code":"45.0",
    "gn:admin4_code":"450035.0",
    "gn:asciiname":"Sahela",
    "gn:country_code":"NP",
    "gn:dem":806,
    "gn:feature_class":"P",
    "gn:feature_code":"PPLL",
    "gn:name":"Sahela",
    "gn:population":0,
    "gn:timezone":"Asia/Kathmandu",
    "iso:country":"NP",
    "wof:name":"Sahela",
    "wof:placetype":"locality"
},
  "geometry": {"coordinates":[83.64293000000001,28.23795],"type":"Point"}
}