{
  "type": "Feature",
  "properties": {
    "gn:admin1_code":"MR",
    "gn:admin2_code":"6",
    "gn:admin3_code":"66.0",
    "gn:admin4_code":"660024.0",
    "gn:asciiname":"Mahatara",
    "gn:country_code":"NP",
    "gn:dem":1989,
    "gn:feature_class":"P",
    "gn:feature_code":"PPLL",
    "gn:name":"Mahatara",
    "gn:population":0,
    "gn:timezone":"Asia/Kathmandu",
    "iso:country":"NP",
    "wof:name":"Mahatara",
    "wof:placetype":"locality"
},
  "geometry": {"coordinates":[81.86,29.64582],"type":"Point"}
}