{
  "type": "Feature",
  "properties": {
    "gn:admin1_code":"FR",
    "gn:admin2_code":"14",
    "gn:admin3_code":"70.0",
    "gn:admin4_code":"700003.0",
    "gn:asciiname":"Halokate",
    "gn:country_code":"NP",
    "gn:dem":1147,
    "gn:feature_class":"P",
    "gn:feature_code":"PPLL",
    "gn:name":"Halokate",
    "gn:population":0,
    "gn:timezone":"Asia/Kathmandu",
    "iso:country":"NP",
    "wof:name":"Halokate",
    "wof:placetype":"locality"
},
  "geometry": {"coordinates":[80.86839000000001,28.99037],"type":"Point"}
}