{
  "type": "Feature",
  "properties": {
    "gn:admin1_code":"ER",
    "gn:admin2_code":"7",
    "gn:admin3_code":"10.0",
    "gn:admin4_code":"100031.0",
    "gn:asciiname":"Dube",
    "gn:country_code":"NP",
    "gn:dem":559,
    "gn:feature_class":"P",
    "gn:feature_code":"PPLL",
    "gn:name":"Dube",
    "gn:population":0,
    "gn:timezone":"Asia/Kathmandu",
    "iso:country":"NP",
    "wof:name":"Dube",
    "wof:placetype":"locality"
},
  "geometry": {"coordinates":[87.16781999999998,27.36595],"type":"Point"}
}