{
  "type": "Feature",
  "properties": {
    "gn:admin1_code":"MR",
    "gn:admin2_code":"2",
    "gn:admin3_code":"61.0",
    "gn:admin4_code":"610004.0",
    "gn:asciiname":"Kapra",
    "gn:country_code":"NP",
    "gn:dem":2362,
    "gn:feature_class":"P",
    "gn:feature_code":"PPLL",
    "gn:name":"Kapra",
    "gn:population":0,
    "gn:timezone":"Asia/Kathmandu",
    "iso:country":"NP",
    "name:bpy_x_preferred":[
        "\u0995\u09be\u09aa\u09b0\u09be"
    ],
    "name:ceb_x_preferred":[
        "K\u0101pra"
    ],
    "name:fas_x_preferred":[
        "\u06a9\u0627\u067e\u0631\u0627"
    ],
    "name:fra_x_preferred":[
        "Kapra"
    ],
    "name:ita_x_preferred":[
        "Kapra"
    ],
    "name:mlg_x_preferred":[
        "Kapra"
    ],
    "name:msa_x_preferred":[
        "Kapra"
    ],
    "name:new_x_preferred":[
        "\u0915\u092a\u094d\u0930\u093e"
    ],
    "name:pnb_x_preferred":[
        "\u06a9\u067e\u0631\u0627"
    ],
    "name:por_x_preferred":[
        "Kapra"
    ],
    "name:swe_x_preferred":[
        "K\u0101pra"
    ],
    "name:tel_x_preferred":[
        "\u0c15\u0c3e\u0c2a\u0c4d\u0c30\u0c3e"
    ],
    "name:urd_x_preferred":[
        "\u06a9\u067e\u0631\u0627"
    ],
    "name:vie_x_preferred":[
        "Kapra"
    ],
    "name:zho_x_preferred":[
        "\u5361\u666e\u62c9"
    ],
    "wof:name":"Kapra",
    "wof:placetype":"locality"
},
  "geometry": {"coordinates":[81.94331,28.9333],"type":"Point"}
}