{
  "type": "Feature",
  "properties": {
    "gn:admin1_code":"WR",
    "gn:admin2_code":"4",
    "gn:admin3_code":"40.0",
    "gn:admin4_code":"400032.0",
    "gn:asciiname":"Purandhara",
    "gn:country_code":"NP",
    "gn:dem":872,
    "gn:feature_class":"P",
    "gn:feature_code":"PPLL",
    "gn:name":"Purandhara",
    "gn:population":0,
    "gn:timezone":"Asia/Kathmandu",
    "iso:country":"NP",
    "name:mai_x_preferred":[
        "\u092a\u0941\u0930\u0928\u094d\u0927\u093e\u0930\u093e \u0917\u093e.\u0935\u093f.\u0938."
    ],
    "name:msa_x_preferred":[
        "Purandhara"
    ],
    "name:nep_x_preferred":[
        "\u092a\u0941\u0930\u0928\u094d\u0927\u093e\u0930\u093e"
    ],
    "name:new_x_preferred":[
        "\u092a\u0941\u0930\u093e\u0928\u0927\u093e\u0930\u093e"
    ],
    "name:pol_x_preferred":[
        "Purandhara"
    ],
    "wof:name":"Purandhara",
    "wof:placetype":"locality"
},
  "geometry": {"coordinates":[84.00451,28.21919],"type":"Point"}
}