{
  "type": "Feature",
  "properties": {
    "gn:admin1_code":"00",
    "gn:asciiname":"Dharapani",
    "gn:country_code":"NP",
    "gn:dem":942,
    "gn:feature_class":"P",
    "gn:feature_code":"PPL",
    "gn:name":"Dh\u0101r\u0101p\u0101ni\u0307\u0304",
    "gn:population":0,
    "gn:timezone":"Asia/Kathmandu",
    "iso:country":"NP",
    "name:und_x_variant":[
        "Dh\u0101r\u0101p\u0101ni\u0307\u0304",
        "Dh\u0101r\u0101p\u0101n\u012b"
    ],
    "wof:name":"Dharapani",
    "wof:placetype":"locality"
},
  "geometry": {"coordinates":[85.21454,27.87029],"type":"Point"}
}