{
  "type": "Feature",
  "properties": {
    "gn:admin1_code":"WR",
    "gn:admin2_code":"4.0",
    "gn:admin3_code":"39.0",
    "gn:admin4_code":"390004.0",
    "gn:asciiname":"Khadketari",
    "gn:country_code":"NP",
    "gn:dem":1007,
    "gn:feature_class":"P",
    "gn:feature_code":"PPLL",
    "gn:name":"Khadketari",
    "gn:population":0,
    "gn:timezone":"Asia/Kathmandu",
    "iso:country":"NP",
    "wof:name":"Khadketari",
    "wof:placetype":"locality"
},
  "geometry": {"coordinates":[83.87794,28.15351],"type":"Point"}
}