{
  "type": "Feature",
  "properties": {
    "gn:admin1_code":"FR",
    "gn:admin2_code":"14",
    "gn:admin3_code":"69.0",
    "gn:admin4_code":"690074.0",
    "gn:asciiname":"Bango",
    "gn:country_code":"NP",
    "gn:dem":535,
    "gn:feature_class":"P",
    "gn:feature_code":"PPLL",
    "gn:name":"Bango",
    "gn:population":0,
    "gn:timezone":"Asia/Kathmandu",
    "iso:country":"NP",
    "name:ceb_x_preferred":[
        "Bango"
    ],
    "name:deu_x_preferred":[
        "Bango"
    ],
    "name:swe_x_preferred":[
        "Bango"
    ],
    "wof:name":"Bango",
    "wof:placetype":"locality"
},
  "geometry": {"coordinates":[81.14371,28.94799],"type":"Point"}
}