{
  "type": "Feature",
  "properties": {
    "gn:admin1_code":"MR",
    "gn:admin2_code":"6",
    "gn:admin3_code":"64.0",
    "gn:admin4_code":"640005.0",
    "gn:asciiname":"Pateuti",
    "gn:country_code":"NP",
    "gn:dem":2817,
    "gn:feature_class":"P",
    "gn:feature_code":"PPLL",
    "gn:name":"Pateuti",
    "gn:population":0,
    "gn:timezone":"Asia/Kathmandu",
    "iso:country":"NP",
    "wof:name":"Pateuti",
    "wof:placetype":"locality"
},
  "geometry": {"coordinates":[81.82073000000003,29.40022],"type":"Point"}
}