{
  "type": "Feature",
  "properties": {
    "gn:admin1_code":"MR",
    "gn:admin2_code":"2",
    "gn:admin3_code":"60.0",
    "gn:admin4_code":"600014.0",
    "gn:asciiname":"Kalsiyadhunga",
    "gn:country_code":"NP",
    "gn:dem":1506,
    "gn:feature_class":"P",
    "gn:feature_code":"PPLL",
    "gn:name":"Kalsiyadhunga",
    "gn:population":0,
    "gn:timezone":"Asia/Kathmandu",
    "iso:country":"NP",
    "wof:name":"Kalsiyadhunga",
    "wof:placetype":"locality"
},
  "geometry": {"coordinates":[81.76940999999999,28.74242000000001],"type":"Point"}
}