{
  "type": "Feature",
  "properties": {
    "gn:admin1_code":"ER",
    "gn:admin2_code":"13.0",
    "gn:admin3_code":"14.0",
    "gn:admin4_code":"140035.0",
    "gn:asciiname":"Ahale",
    "gn:country_code":"NP",
    "gn:dem":566,
    "gn:feature_class":"P",
    "gn:feature_code":"PPLL",
    "gn:name":"Ahale",
    "gn:population":0,
    "gn:timezone":"Asia/Kathmandu",
    "iso:country":"NP",
    "name:ceb_x_preferred":[
        "Ahale"
    ],
    "name:fas_x_preferred":[
        "\u0627\u0647\u0627\u0644"
    ],
    "name:mai_x_preferred":[
        "\u0906\u0939\u093e\u0932\u0947"
    ],
    "name:nep_x_preferred":[
        "\u0906\u0939\u093e\u0932\u0947"
    ],
    "name:new_x_preferred":[
        "\u0905\u0939\u0932\u0947"
    ],
    "name:pol_x_preferred":[
        "Ahale"
    ],
    "name:urd_x_preferred":[
        "\u0627\u06c1\u0627\u0644"
    ],
    "wof:name":"Ahale",
    "wof:placetype":"locality"
},
  "geometry": {"coordinates":[86.42577,27.02045],"type":"Point"}
}