{
  "type": "Feature",
  "properties": {
    "gn:admin1_code":"MR",
    "gn:admin2_code":"12",
    "gn:admin3_code":"54",
    "gn:admin4_code":"540017",
    "gn:asciiname":"Kanda",
    "gn:country_code":"NP",
    "gn:dem":2188,
    "gn:feature_class":"P",
    "gn:feature_code":"PPLL",
    "gn:name":"Kanda",
    "gn:population":0,
    "gn:timezone":"Asia/Kathmandu",
    "iso:country":"NP",
    "wof:name":"Kanda",
    "wof:placetype":"locality"
},
  "geometry": {"coordinates":[82.64895,28.59769],"type":"Point"}
}