{
  "type": "Feature",
  "properties": {
    "gn:admin1_code":"WR",
    "gn:admin2_code":"4",
    "gn:admin3_code":"36.0",
    "gn:admin4_code":"360067.0",
    "gn:asciiname":"Isidanda",
    "gn:country_code":"NP",
    "gn:dem":1578,
    "gn:feature_class":"P",
    "gn:feature_code":"PPLL",
    "gn:name":"Isidanda",
    "gn:population":0,
    "gn:timezone":"Asia/Kathmandu",
    "iso:country":"NP",
    "wof:name":"Isidanda",
    "wof:placetype":"locality"
},
  "geometry": {"coordinates":[84.73278000000001,28.2004],"type":"Point"}
}