{
  "type": "Feature",
  "properties": {
    "gn:admin1_code":"CR",
    "gn:admin2_code":"5",
    "gn:admin3_code":"20",
    "gn:admin4_code":"200007",
    "gn:asciiname":"Nyure",
    "gn:country_code":"NP",
    "gn:dem":598,
    "gn:feature_class":"P",
    "gn:feature_code":"PPLL",
    "gn:name":"Nyure",
    "gn:population":0,
    "gn:timezone":"Asia/Kathmandu",
    "iso:country":"NP",
    "wof:name":"Nyure",
    "wof:placetype":"locality"
},
  "geometry": {"coordinates":[86.00729,27.14188],"type":"Point"}
}