{
  "type": "Feature",
  "properties": {
    "gn:admin1_code":"MR",
    "gn:admin2_code":"6",
    "gn:admin3_code":"66.0",
    "gn:admin4_code":"660006.0",
    "gn:asciiname":"Mastamandau",
    "gn:country_code":"NP",
    "gn:dem":2058,
    "gn:feature_class":"P",
    "gn:feature_code":"PPLL",
    "gn:name":"Mastamandau",
    "gn:population":0,
    "gn:timezone":"Asia/Kathmandu",
    "iso:country":"NP",
    "name:ceb_x_preferred":[
        "Mastamandau"
    ],
    "name:fra_x_preferred":[
        "Mastamandau"
    ],
    "name:msa_x_preferred":[
        "Mastamandau"
    ],
    "name:nep_x_preferred":[
        "\u092e\u0937\u094d\u091f\u093e\u092e\u093e\u0923\u094d\u0921\u094c"
    ],
    "name:new_x_preferred":[
        "\u092e\u0938\u094d\u0924\u093e\u092e\u093e\u0923\u094d\u0921\u094c"
    ],
    "name:pol_x_preferred":[
        "Mastamandau"
    ],
    "wof:name":"Mastamandau",
    "wof:placetype":"locality"
},
  "geometry": {"coordinates":[81.98975,29.77201],"type":"Point"}
}