{
  "type": "Feature",
  "properties": {
    "gn:admin1_code":"MR",
    "gn:admin2_code":"6",
    "gn:admin3_code":"66.0",
    "gn:admin4_code":"660006.0",
    "gn:asciiname":"Mastamandau",
    "gn:country_code":"NP",
    "gn:dem":2058,
    "gn:feature_class":"P",
    "gn:feature_code":"PPLL",
    "gn:name":"Mastamandau",
    "gn:population":0,
    "gn:timezone":"Asia/Kathmandu",
    "iso:country":"NP",
    "wof:name":"Mastamandau",
    "wof:placetype":"locality"
},
  "geometry": {"coordinates":[81.98975,29.77201],"type":"Point"}
}