{
  "type": "Feature",
  "properties": {
    "gn:admin1_code":"00",
    "gn:asciiname":"Yamkan",
    "gn:country_code":"NP",
    "gn:dem":1833,
    "gn:feature_class":"P",
    "gn:feature_code":"PPL",
    "gn:name":"Y\u0101mk\u0101\u1e45",
    "gn:population":0,
    "gn:timezone":"Asia/Kathmandu",
    "iso:country":"NP",
    "name:nep_x_preferred":[
        "Y\u0101mk\u0101\u1e45"
    ],
    "wof:name":"Yamkan",
    "wof:placetype":"locality"
},
  "geometry": {"coordinates":[84.84973000000002,28.20554000000001],"type":"Point"}
}