{
  "type": "Feature",
  "properties": {
    "gn:admin1_code":"MR",
    "gn:admin2_code":"6",
    "gn:admin3_code":"65",
    "gn:admin4_code":"650001",
    "gn:asciiname":"Kosedi",
    "gn:country_code":"NP",
    "gn:dem":2297,
    "gn:feature_class":"P",
    "gn:feature_code":"PPLL",
    "gn:name":"Kosedi",
    "gn:population":0,
    "gn:timezone":"Asia/Kathmandu",
    "iso:country":"NP",
    "wof:name":"Kosedi",
    "wof:placetype":"locality"
},
  "geometry": {"coordinates":[81.889,29.6338],"type":"Point"}
}