{
  "type": "Feature",
  "properties": {
    "gn:admin1_code":"MR",
    "gn:admin2_code":"2.0",
    "gn:admin3_code":"57.0",
    "gn:admin4_code":"570034.0",
    "gn:asciiname":"Goriyanpurwa",
    "gn:country_code":"NP",
    "gn:dem":141,
    "gn:feature_class":"P",
    "gn:feature_code":"PPLL",
    "gn:name":"Goriyanpurwa",
    "gn:population":0,
    "gn:timezone":"Asia/Kathmandu",
    "iso:country":"NP",
    "wof:name":"Goriyanpurwa",
    "wof:placetype":"locality"
},
  "geometry": {"coordinates":[81.74169000000001,28.07154],"type":"Point"}
}