{
  "type": "Feature",
  "properties": {
    "gn:admin1_code":"CR",
    "gn:admin2_code":"1",
    "gn:admin3_code":"24.0",
    "gn:admin4_code":"240089.0",
    "gn:asciiname":"Thakalmath",
    "gn:country_code":"NP",
    "gn:dem":1958,
    "gn:feature_class":"P",
    "gn:feature_code":"PPLL",
    "gn:name":"Thakalmath",
    "gn:population":0,
    "gn:timezone":"Asia/Kathmandu",
    "iso:country":"NP",
    "wof:name":"Thakalmath",
    "wof:placetype":"locality"
},
  "geometry": {"coordinates":[85.50833,27.68844],"type":"Point"}
}