{
  "type": "Feature",
  "properties": {
    "gn:admin1_code":"MR",
    "gn:admin2_code":"6",
    "gn:admin3_code":"65",
    "gn:admin4_code":"650005",
    "gn:asciiname":"Badu Lek",
    "gn:country_code":"NP",
    "gn:dem":2181,
    "gn:feature_class":"P",
    "gn:feature_code":"PPLL",
    "gn:name":"Badu Lek",
    "gn:population":0,
    "gn:timezone":"Asia/Kathmandu",
    "iso:country":"NP",
    "wof:name":"Badu Lek",
    "wof:placetype":"locality"
},
  "geometry": {"coordinates":[81.81368000000001,29.54239],"type":"Point"}
}