{
  "type": "Feature",
  "properties": {
    "gn:admin1_code":"WR",
    "gn:admin2_code":"8",
    "gn:admin3_code":"50.0",
    "gn:admin4_code":"500062.0",
    "gn:asciiname":"Bagahi",
    "gn:country_code":"NP",
    "gn:dem":98,
    "gn:feature_class":"P",
    "gn:feature_code":"PPLL",
    "gn:name":"Bagahi",
    "gn:population":0,
    "gn:timezone":"Asia/Kathmandu",
    "iso:country":"NP",
    "name:fra_x_preferred":[
        "Bagahi"
    ],
    "name:pol_x_preferred":[
        "Bagahi"
    ],
    "wof:name":"Bagahi",
    "wof:placetype":"locality"
},
  "geometry": {"coordinates":[82.84363,27.50523],"type":"Point"}
}