{
  "type": "Feature",
  "properties": {
    "gn:admin1_code":"CR",
    "gn:admin2_code":"11.0",
    "gn:admin3_code":"33.0",
    "gn:admin4_code":"330090.0",
    "gn:asciiname":"Jataha",
    "gn:country_code":"NP",
    "gn:dem":118,
    "gn:feature_class":"P",
    "gn:feature_code":"PPLL",
    "gn:name":"Jataha",
    "gn:population":0,
    "gn:timezone":"Asia/Kathmandu",
    "iso:country":"NP",
    "wof:name":"Jataha",
    "wof:placetype":"locality"
},
  "geometry": {"coordinates":[85.14453,27.09589],"type":"Point"}
}