{
  "type": "Feature",
  "properties": {
    "gn:admin1_code":"WR",
    "gn:admin2_code":"8",
    "gn:admin3_code":"47",
    "gn:admin4_code":"470034",
    "gn:asciiname":"Charghare",
    "gn:country_code":"NP",
    "gn:dem":1185,
    "gn:feature_class":"P",
    "gn:feature_code":"PPLL",
    "gn:name":"Charghare",
    "gn:population":0,
    "gn:timezone":"Asia/Kathmandu",
    "iso:country":"NP",
    "name:ceb_x_preferred":[
        "Charghare"
    ],
    "name:fra_x_preferred":[
        "Charghare"
    ],
    "name:mai_x_preferred":[
        "\u091a\u093e\u0930\u0918\u0930\u0947"
    ],
    "name:msa_x_preferred":[
        "Charghare"
    ],
    "name:nep_x_preferred":[
        "\u091a\u093e\u0930\u0918\u0930\u0947"
    ],
    "name:new_x_preferred":[
        "\u091a\u093e\u0930\u0918\u0930\u0947"
    ],
    "name:pol_x_preferred":[
        "Charghare"
    ],
    "wof:name":"Charghare",
    "wof:placetype":"locality"
},
  "geometry": {"coordinates":[83.83339000000002,27.77039000000001],"type":"Point"}
}