{
  "type": "Feature",
  "properties": {
    "gn:admin1_code":"CR",
    "gn:admin2_code":"1",
    "gn:admin3_code":"28",
    "gn:admin4_code":"280031",
    "gn:asciiname":"Alamdanda",
    "gn:country_code":"NP",
    "gn:dem":765,
    "gn:feature_class":"P",
    "gn:feature_code":"PPLL",
    "gn:name":"Alamdanda",
    "gn:population":0,
    "gn:timezone":"Asia/Kathmandu",
    "iso:country":"NP",
    "wof:name":"Alamdanda",
    "wof:placetype":"locality"
},
  "geometry": {"coordinates":[85.09904,27.88477],"type":"Point"}
}