{
  "type": "Feature",
  "properties": {
    "gn:admin1_code":"WR",
    "gn:admin2_code":"4.0",
    "gn:admin3_code":"39.0",
    "gn:admin4_code":"390023.0",
    "gn:asciiname":"Gajaudi",
    "gn:country_code":"NP",
    "gn:dem":1083,
    "gn:feature_class":"P",
    "gn:feature_code":"PPLL",
    "gn:name":"Gajaudi",
    "gn:population":0,
    "gn:timezone":"Asia/Kathmandu",
    "iso:country":"NP",
    "wof:name":"Gajaudi",
    "wof:placetype":"locality"
},
  "geometry": {"coordinates":[83.80221,27.97676],"type":"Point"}
}