{
  "type": "Feature",
  "properties": {
    "gn:admin1_code":"ER",
    "gn:admin2_code":"10",
    "gn:admin3_code":"2",
    "gn:admin4_code":"20012",
    "gn:asciiname":"Sereja",
    "gn:country_code":"NP",
    "gn:dem":1372,
    "gn:feature_class":"P",
    "gn:feature_code":"PPLL",
    "gn:name":"Sereja",
    "gn:population":0,
    "gn:timezone":"Asia/Kathmandu",
    "iso:country":"NP",
    "wof:name":"Sereja",
    "wof:placetype":"locality"
},
  "geometry": {"coordinates":[87.92296,27.27785],"type":"Point"}
}