{
  "type": "Feature",
  "properties": {
    "gn:admin1_code":"WR",
    "gn:admin2_code":"4.0",
    "gn:admin3_code":"39.0",
    "gn:admin4_code":"390040.0",
    "gn:asciiname":"Dhuwarkot",
    "gn:country_code":"NP",
    "gn:dem":1221,
    "gn:feature_class":"P",
    "gn:feature_code":"PPLL",
    "gn:name":"Dhuwarkot",
    "gn:population":0,
    "gn:timezone":"Asia/Kathmandu",
    "iso:country":"NP",
    "wof:name":"Dhuwarkot",
    "wof:placetype":"locality"
},
  "geometry": {"coordinates":[83.93053,28.14589],"type":"Point"}
}