{
  "type": "Feature",
  "properties": {
    "gn:admin1_code":"MR",
    "gn:admin2_code":"2",
    "gn:admin3_code":"60.0",
    "gn:admin4_code":"600017.0",
    "gn:asciiname":"Khartibada",
    "gn:country_code":"NP",
    "gn:dem":1438,
    "gn:feature_class":"P",
    "gn:feature_code":"PPLL",
    "gn:name":"Khartibada",
    "gn:population":0,
    "gn:timezone":"Asia/Kathmandu",
    "iso:country":"NP",
    "wof:name":"Khartibada",
    "wof:placetype":"locality"
},
  "geometry": {"coordinates":[81.65909000000001,28.78073],"type":"Point"}
}