{
  "type": "Feature",
  "properties": {
    "gn:admin1_code":"MR",
    "gn:admin2_code":"6",
    "gn:admin3_code":"64.0",
    "gn:admin4_code":"640013.0",
    "gn:asciiname":"Syanla",
    "gn:country_code":"NP",
    "gn:dem":1315,
    "gn:feature_class":"P",
    "gn:feature_code":"PPLL",
    "gn:name":"Syanla",
    "gn:population":0,
    "gn:timezone":"Asia/Kathmandu",
    "iso:country":"NP",
    "wof:name":"Syanla",
    "wof:placetype":"locality"
},
  "geometry": {"coordinates":[81.61771999999998,29.1639],"type":"Point"}
}