{
  "type": "Feature",
  "properties": {
    "gn:admin1_code":"CR",
    "gn:admin2_code":"5",
    "gn:admin3_code":"21",
    "gn:admin4_code":"210020",
    "gn:asciiname":"Gothpani",
    "gn:country_code":"NP",
    "gn:dem":634,
    "gn:feature_class":"P",
    "gn:feature_code":"PPLL",
    "gn:name":"Gothpani",
    "gn:population":0,
    "gn:timezone":"Asia/Kathmandu",
    "iso:country":"NP",
    "name:bih_x_preferred":[
        "\u0917\u094b\u0920\u092a\u093e\u0928\u0940"
    ],
    "name:ceb_x_preferred":[
        "Gothpani"
    ],
    "name:fra_x_preferred":[
        "Gothpani"
    ],
    "name:mai_x_preferred":[
        "\u0917\u094b\u0920\u092a\u093e\u0928\u0940"
    ],
    "name:msa_x_preferred":[
        "Gothpani"
    ],
    "name:nep_x_preferred":[
        "\u0917\u094b\u0920\u092a\u093e\u0928\u0940"
    ],
    "name:new_x_preferred":[
        "\u0917\u094b\u0920\u093f\u092a\u093e\u0928\u0940"
    ],
    "name:pol_x_preferred":[
        "Gothpani"
    ],
    "wof:name":"Gothpani",
    "wof:placetype":"locality"
},
  "geometry": {"coordinates":[86.22166,27.3852],"type":"Point"}
}