{
  "type": "Feature",
  "properties": {
    "gn:admin1_code":"MR",
    "gn:admin2_code":"2",
    "gn:admin3_code":"60.0",
    "gn:admin4_code":"600027.0",
    "gn:asciiname":"Manma",
    "gn:country_code":"NP",
    "gn:dem":1579,
    "gn:feature_class":"P",
    "gn:feature_code":"PPLL",
    "gn:name":"Manma",
    "gn:population":0,
    "gn:timezone":"Asia/Kathmandu",
    "iso:country":"NP",
    "wof:name":"Manma",
    "wof:placetype":"locality"
},
  "geometry": {"coordinates":[81.62168,28.99935],"type":"Point"}
}