{
  "type": "Feature",
  "properties": {
    "gn:admin1_code":"MR",
    "gn:admin2_code":"2",
    "gn:admin3_code":"60.0",
    "gn:admin4_code":"600027.0",
    "gn:asciiname":"Manma",
    "gn:country_code":"NP",
    "gn:dem":1579,
    "gn:feature_class":"P",
    "gn:feature_code":"PPLL",
    "gn:name":"Manma",
    "gn:population":0,
    "gn:timezone":"Asia/Kathmandu",
    "iso:country":"NP",
    "name:ceb_x_preferred":[
        "Manma"
    ],
    "name:deu_x_preferred":[
        "Manma"
    ],
    "name:dty_x_preferred":[
        "\u092e\u093e\u0928\u094d\u092e\u093e"
    ],
    "name:fra_x_preferred":[
        "Manma"
    ],
    "name:ita_x_preferred":[
        "Manma"
    ],
    "name:mai_x_preferred":[
        "\u092e\u093e\u0928\u094d\u092e\u093e"
    ],
    "name:nep_x_preferred":[
        "\u092e\u093e\u0928\u094d\u092e\u093e"
    ],
    "name:new_x_preferred":[
        "\u092e\u0902\u092e\u093e"
    ],
    "name:nld_x_preferred":[
        "Manma"
    ],
    "name:pol_x_preferred":[
        "Manma"
    ],
    "name:por_x_preferred":[
        "Manma"
    ],
    "name:urd_x_preferred":[
        "\u0645\u0627\u0646\u0645\u0627"
    ],
    "wof:name":"Manma",
    "wof:placetype":"locality"
},
  "geometry": {"coordinates":[81.62168,28.99935],"type":"Point"}
}