{
  "type": "Feature",
  "properties": {
    "gn:admin1_code":"ER",
    "gn:admin2_code":"10",
    "gn:admin3_code":"3.0",
    "gn:admin4_code":"30045.0",
    "gn:asciiname":"Balbani",
    "gn:country_code":"NP",
    "gn:dem":488,
    "gn:feature_class":"P",
    "gn:feature_code":"PPLL",
    "gn:name":"Balbani",
    "gn:population":0,
    "gn:timezone":"Asia/Kathmandu",
    "iso:country":"NP",
    "wof:name":"Balbani",
    "wof:placetype":"locality"
},
  "geometry": {"coordinates":[87.82739000000002,26.83205],"type":"Point"}
}