{
  "type": "Feature",
  "properties": {
    "gn:admin1_code":"WR",
    "gn:admin2_code":"4.0",
    "gn:admin3_code":"38.0",
    "gn:admin4_code":"380031.0",
    "gn:asciiname":"Sisamtar",
    "gn:country_code":"NP",
    "gn:dem":397,
    "gn:feature_class":"P",
    "gn:feature_code":"PPLL",
    "gn:name":"Sisamtar",
    "gn:population":0,
    "gn:timezone":"Asia/Kathmandu",
    "iso:country":"NP",
    "wof:name":"Sisamtar",
    "wof:placetype":"locality"
},
  "geometry": {"coordinates":[84.2705,28.03596],"type":"Point"}
}