{
  "type": "Feature",
  "properties": {
    "gn:admin1_code":"MR",
    "gn:admin2_code":"6",
    "gn:admin3_code":"66.0",
    "gn:admin4_code":"660018.0",
    "gn:asciiname":"Laya",
    "gn:country_code":"NP",
    "gn:dem":3505,
    "gn:feature_class":"P",
    "gn:feature_code":"PPLL",
    "gn:name":"Laya",
    "gn:population":0,
    "gn:timezone":"Asia/Kathmandu",
    "iso:country":"NP",
    "name:ceb_x_preferred":[
        "Laya"
    ],
    "name:deu_x_preferred":[
        "Laya"
    ],
    "name:pol_x_preferred":[
        "Laya"
    ],
    "name:que_x_preferred":[
        "Laya"
    ],
    "name:rus_x_preferred":[
        "\u041b\u0430\u0439\u044f"
    ],
    "name:swe_x_preferred":[
        "Laya"
    ],
    "wof:name":"Laya",
    "wof:placetype":"locality"
},
  "geometry": {"coordinates":[81.46446,30.09947],"type":"Point"}
}