{
  "type": "Feature",
  "properties": {
    "gn:admin1_code":"FR",
    "gn:admin2_code":"14.0",
    "gn:admin3_code":"68.0",
    "gn:admin4_code":"680046.0",
    "gn:asciiname":"Jhusu Koirela",
    "gn:country_code":"NP",
    "gn:dem":2077,
    "gn:feature_class":"P",
    "gn:feature_code":"PPLL",
    "gn:name":"Jhusu Koirela",
    "gn:population":0,
    "gn:timezone":"Asia/Kathmandu",
    "iso:country":"NP",
    "wof:name":"Jhusu Koirela",
    "wof:placetype":"locality"
},
  "geometry": {"coordinates":[81.10665,29.62951],"type":"Point"}
}