{
  "type": "Feature",
  "properties": {
    "gn:admin1_code":"ER",
    "gn:admin2_code":"13",
    "gn:admin3_code":"11",
    "gn:admin4_code":"110005",
    "gn:asciiname":"Saddi",
    "gn:country_code":"NP",
    "gn:dem":1288,
    "gn:feature_class":"P",
    "gn:feature_code":"PPLL",
    "gn:name":"Saddi",
    "gn:population":0,
    "gn:timezone":"Asia/Kathmandu",
    "iso:country":"NP",
    "wof:name":"Saddi",
    "wof:placetype":"locality"
},
  "geometry": {"coordinates":[86.81655000000001,27.49726],"type":"Point"}
}