{
  "type": "Feature",
  "properties": {
    "gn:admin1_code":"ER",
    "gn:admin2_code":"10",
    "gn:admin3_code":"3.0",
    "gn:admin4_code":"30007.0",
    "gn:asciiname":"Sambaretar",
    "gn:country_code":"NP",
    "gn:dem":370,
    "gn:feature_class":"P",
    "gn:feature_code":"PPLL",
    "gn:name":"Sambaretar",
    "gn:population":0,
    "gn:timezone":"Asia/Kathmandu",
    "iso:country":"NP",
    "wof:name":"Sambaretar",
    "wof:placetype":"locality"
},
  "geometry": {"coordinates":[87.79201,26.82081],"type":"Point"}
}