{
  "type": "Feature",
  "properties": {
    "gn:admin1_code":"WR",
    "gn:admin2_code":"8",
    "gn:admin3_code":"46.0",
    "gn:admin4_code":"460032.0",
    "gn:asciiname":"Kotkarigaun",
    "gn:country_code":"NP",
    "gn:dem":1500,
    "gn:feature_class":"P",
    "gn:feature_code":"PPLL",
    "gn:name":"Kotkarigaun",
    "gn:population":0,
    "gn:timezone":"Asia/Kathmandu",
    "iso:country":"NP",
    "wof:name":"Kotkarigaun",
    "wof:placetype":"locality"
},
  "geometry": {"coordinates":[83.23299999999998,28.18664],"type":"Point"}
}