{
  "type": "Feature",
  "properties": {
    "gn:admin1_code":"WR",
    "gn:admin2_code":"8",
    "gn:admin3_code":"48",
    "gn:admin4_code":"480039",
    "gn:asciiname":"Atharahati",
    "gn:country_code":"NP",
    "gn:dem":119,
    "gn:feature_class":"P",
    "gn:feature_code":"PPLL",
    "gn:name":"Atharahati",
    "gn:population":0,
    "gn:timezone":"Asia/Kathmandu",
    "iso:country":"NP",
    "wof:name":"Atharahati",
    "wof:placetype":"locality"
},
  "geometry": {"coordinates":[83.72821999999999,27.54912],"type":"Point"}
}