{
  "type": "Feature",
  "properties": {
    "gn:admin1_code":"ER",
    "gn:admin2_code":"13.0",
    "gn:admin3_code":"14.0",
    "gn:admin4_code":"140037.0",
    "gn:asciiname":"Pyakholagaun",
    "gn:country_code":"NP",
    "gn:dem":297,
    "gn:feature_class":"P",
    "gn:feature_code":"PPLL",
    "gn:name":"Pyakholagaun",
    "gn:population":0,
    "gn:timezone":"Asia/Kathmandu",
    "iso:country":"NP",
    "wof:name":"Pyakholagaun",
    "wof:placetype":"locality"
},
  "geometry": {"coordinates":[86.66167,27.12042000000001],"type":"Point"}
}