{
  "type": "Feature",
  "properties": {
    "gn:admin1_code":"WR",
    "gn:admin2_code":"4",
    "gn:admin3_code":"40.0",
    "gn:admin4_code":"400033.0",
    "gn:asciiname":"Ramkot",
    "gn:country_code":"NP",
    "gn:dem":1289,
    "gn:feature_class":"P",
    "gn:feature_code":"PPLL",
    "gn:name":"Ramkot",
    "gn:population":0,
    "gn:timezone":"Asia/Kathmandu",
    "iso:country":"NP",
    "wof:name":"Ramkot",
    "wof:placetype":"locality"
},
  "geometry": {"coordinates":[83.91011999999998,28.17718],"type":"Point"}
}