{
  "type": "Feature",
  "properties": {
    "gn:admin1_code":"MR",
    "gn:admin2_code":"12",
    "gn:admin3_code":"53",
    "gn:admin4_code":"530042",
    "gn:asciiname":"Dhungbang",
    "gn:country_code":"NP",
    "gn:dem":1651,
    "gn:feature_class":"P",
    "gn:feature_code":"PPLL",
    "gn:name":"Dhungbang",
    "gn:population":0,
    "gn:timezone":"Asia/Kathmandu",
    "iso:country":"NP",
    "wof:name":"Dhungbang",
    "wof:placetype":"locality"
},
  "geometry": {"coordinates":[82.83036,28.36921],"type":"Point"}
}