{
  "type": "Feature",
  "properties": {
    "gn:admin1_code":"CR",
    "gn:admin2_code":"5",
    "gn:admin3_code":"19",
    "gn:admin4_code":"190018",
    "gn:asciiname":"Mansiptol",
    "gn:country_code":"NP",
    "gn:dem":128,
    "gn:feature_class":"P",
    "gn:feature_code":"PPLL",
    "gn:name":"Mansiptol",
    "gn:population":0,
    "gn:timezone":"Asia/Kathmandu",
    "iso:country":"NP",
    "wof:name":"Mansiptol",
    "wof:placetype":"locality"
},
  "geometry": {"coordinates":[85.66693000000002,26.97612],"type":"Point"}
}