{
  "type": "Feature",
  "properties": {
    "gn:admin1_code":"00",
    "gn:asciiname":"Temran",
    "gn:country_code":"NP",
    "gn:dem":1916,
    "gn:feature_class":"P",
    "gn:feature_code":"PPL",
    "gn:name":"Temr\u0101\u1e45",
    "gn:population":0,
    "gn:timezone":"Asia/Kathmandu",
    "iso:country":"NP",
    "wof:name":"Temran",
    "wof:placetype":"locality"
},
  "geometry": {"coordinates":[85.2188,28.02639000000001],"type":"Point"}
}