{
  "type": "Feature",
  "properties": {
    "gn:admin1_code":"FR",
    "gn:admin2_code":"14.0",
    "gn:admin3_code":"69.0",
    "gn:admin4_code":"690048.0",
    "gn:asciiname":"Birkhamba",
    "gn:country_code":"NP",
    "gn:dem":1538,
    "gn:feature_class":"P",
    "gn:feature_code":"PPLL",
    "gn:name":"Birkhamba",
    "gn:population":0,
    "gn:timezone":"Asia/Kathmandu",
    "iso:country":"NP",
    "wof:name":"Birkhamba",
    "wof:placetype":"locality"
},
  "geometry": {"coordinates":[81.13524,29.23231],"type":"Point"}
}