{
  "type": "Feature",
  "properties": {
    "gn:admin1_code":"WR",
    "gn:admin2_code":"8",
    "gn:admin3_code":"50.0",
    "gn:admin4_code":"500068.0",
    "gn:asciiname":"Shiwagadhi",
    "gn:country_code":"NP",
    "gn:dem":773,
    "gn:feature_class":"P",
    "gn:feature_code":"PPLL",
    "gn:name":"Shiwagadhi",
    "gn:population":0,
    "gn:timezone":"Asia/Kathmandu",
    "iso:country":"NP",
    "wof:name":"Shiwagadhi",
    "wof:placetype":"locality"
},
  "geometry": {"coordinates":[82.80941999999997,27.75664],"type":"Point"}
}