{
  "type": "Feature",
  "properties": {
    "gn:admin1_code":"MR",
    "gn:admin2_code":"6",
    "gn:admin3_code":"65",
    "gn:admin4_code":"650018",
    "gn:asciiname":"Renchi Kanti",
    "gn:country_code":"NP",
    "gn:dem":2536,
    "gn:feature_class":"P",
    "gn:feature_code":"PPLL",
    "gn:name":"Renchi Kanti",
    "gn:population":0,
    "gn:timezone":"Asia/Kathmandu",
    "iso:country":"NP",
    "wof:name":"Renchi Kanti",
    "wof:placetype":"locality"
},
  "geometry": {"coordinates":[82.21186,29.54131],"type":"Point"}
}