{
  "type": "Feature",
  "properties": {
    "gn:admin1_code":"WR",
    "gn:admin2_code":"4.0",
    "gn:admin3_code":"38.0",
    "gn:admin4_code":"380025.0",
    "gn:asciiname":"Musimarang",
    "gn:country_code":"NP",
    "gn:dem":1029,
    "gn:feature_class":"P",
    "gn:feature_code":"PPLL",
    "gn:name":"Musimarang",
    "gn:population":0,
    "gn:timezone":"Asia/Kathmandu",
    "iso:country":"NP",
    "wof:name":"Musimarang",
    "wof:placetype":"locality"
},
  "geometry": {"coordinates":[84.25196,27.90439000000001],"type":"Point"}
}