{
  "type": "Feature",
  "properties": {
    "gn:admin1_code":"CR",
    "gn:admin2_code":"11.0",
    "gn:admin3_code":"33.0",
    "gn:admin4_code":"330068.0",
    "gn:asciiname":"Bhamaratol",
    "gn:country_code":"NP",
    "gn:dem":182,
    "gn:feature_class":"P",
    "gn:feature_code":"PPLL",
    "gn:name":"Bhamaratol",
    "gn:population":0,
    "gn:timezone":"Asia/Kathmandu",
    "iso:country":"NP",
    "wof:name":"Bhamaratol",
    "wof:placetype":"locality"
},
  "geometry": {"coordinates":[85.19948000000002,27.20601],"type":"Point"}
}