{
  "type": "Feature",
  "properties": {
    "gn:admin1_code":"ER",
    "gn:admin2_code":"13",
    "gn:admin3_code":"12",
    "gn:admin4_code":"120012",
    "gn:asciiname":"Bogrichhap",
    "gn:country_code":"NP",
    "gn:dem":990,
    "gn:feature_class":"P",
    "gn:feature_code":"PPLL",
    "gn:name":"Bogrichhap",
    "gn:population":0,
    "gn:timezone":"Asia/Kathmandu",
    "iso:country":"NP",
    "wof:name":"Bogrichhap",
    "wof:placetype":"locality"
},
  "geometry": {"coordinates":[86.63051,27.30831],"type":"Point"}
}