{
  "type": "Feature",
  "properties": {
    "gn:admin1_code":"ER",
    "gn:admin2_code":"7",
    "gn:admin3_code":"9",
    "gn:admin4_code":"90029.0",
    "gn:asciiname":"Paukhamtar",
    "gn:country_code":"NP",
    "gn:dem":1677,
    "gn:feature_class":"P",
    "gn:feature_code":"PPLL",
    "gn:name":"Paukhamtar",
    "gn:population":0,
    "gn:timezone":"Asia/Kathmandu",
    "iso:country":"NP",
    "wof:name":"Paukhamtar",
    "wof:placetype":"locality"
},
  "geometry": {"coordinates":[87.02278000000003,27.50683],"type":"Point"}
}