{
  "type": "Feature",
  "properties": {
    "gn:admin1_code":"MR",
    "gn:admin2_code":"12",
    "gn:admin3_code":"55",
    "gn:admin4_code":"550004",
    "gn:asciiname":"Dandagoth",
    "gn:country_code":"NP",
    "gn:dem":1148,
    "gn:feature_class":"P",
    "gn:feature_code":"PPLL",
    "gn:name":"Dandagoth",
    "gn:population":0,
    "gn:timezone":"Asia/Kathmandu",
    "iso:country":"NP",
    "wof:name":"Dandagoth",
    "wof:placetype":"locality"
},
  "geometry": {"coordinates":[82.0393,28.62426],"type":"Point"}
}