{
  "type": "Feature",
  "properties": {
    "gn:admin1_code":"ER",
    "gn:admin2_code":"13.0",
    "gn:admin3_code":"14.0",
    "gn:admin4_code":"140029.0",
    "gn:asciiname":"Khanitar",
    "gn:country_code":"NP",
    "gn:dem":366,
    "gn:feature_class":"P",
    "gn:feature_code":"PPLL",
    "gn:name":"Khanitar",
    "gn:population":0,
    "gn:timezone":"Asia/Kathmandu",
    "iso:country":"NP",
    "wof:name":"Khanitar",
    "wof:placetype":"locality"
},
  "geometry": {"coordinates":[86.62863,26.89857],"type":"Point"}
}