{
  "type": "Feature",
  "properties": {
    "gn:admin1_code":"00",
    "gn:asciiname":"Kulikhani",
    "gn:country_code":"NP",
    "gn:dem":1844,
    "gn:feature_class":"P",
    "gn:feature_code":"PPL",
    "gn:name":"Kul\u012bkh\u0101ni",
    "gn:population":0,
    "gn:timezone":"Asia/Kathmandu",
    "iso:country":"NP",
    "wof:name":"Kulikhani",
    "wof:placetype":"locality"
},
  "geometry": {"coordinates":[85.14834,27.59411],"type":"Point"}
}