{
  "type": "Feature",
  "properties": {
    "gn:admin1_code":"WR",
    "gn:admin2_code":"8",
    "gn:admin3_code":"47",
    "gn:admin4_code":"470054.0",
    "gn:asciiname":"Sanding",
    "gn:country_code":"NP",
    "gn:dem":1136,
    "gn:feature_class":"P",
    "gn:feature_code":"PPLL",
    "gn:name":"Sanding",
    "gn:population":0,
    "gn:timezone":"Asia/Kathmandu",
    "iso:country":"NP",
    "wof:name":"Sanding",
    "wof:placetype":"locality"
},
  "geometry": {"coordinates":[83.79397,27.83113],"type":"Point"}
}