{
  "type": "Feature",
  "properties": {
    "gn:admin1_code":"MR",
    "gn:admin2_code":"2.0",
    "gn:admin3_code":"59.0",
    "gn:admin4_code":"590003.0",
    "gn:asciiname":"Kalapani",
    "gn:country_code":"NP",
    "gn:dem":381,
    "gn:feature_class":"P",
    "gn:feature_code":"PPLL",
    "gn:name":"Kalapani",
    "gn:population":0,
    "gn:timezone":"Asia/Kathmandu",
    "iso:country":"NP",
    "wof:name":"Kalapani",
    "wof:placetype":"locality"
},
  "geometry": {"coordinates":[81.4034,28.78866],"type":"Point"}
}