{
  "type": "Feature",
  "properties": {
    "gn:admin1_code":"ER",
    "gn:admin2_code":"7",
    "gn:admin3_code":"5",
    "gn:admin4_code":"50060",
    "gn:asciiname":"Jalukeni",
    "gn:country_code":"NP",
    "gn:dem":515,
    "gn:feature_class":"P",
    "gn:feature_code":"PPLL",
    "gn:name":"Jalukeni",
    "gn:population":0,
    "gn:timezone":"Asia/Kathmandu",
    "iso:country":"NP",
    "wof:name":"Jalukeni",
    "wof:placetype":"locality"
},
  "geometry": {"coordinates":[87.61736999999999,26.78262],"type":"Point"}
}