{
  "type": "Feature",
  "properties": {
    "gn:admin1_code":"ER",
    "gn:admin2_code":"7",
    "gn:admin3_code":"10.0",
    "gn:admin4_code":"100043.0",
    "gn:asciiname":"Simle",
    "gn:country_code":"NP",
    "gn:dem":945,
    "gn:feature_class":"P",
    "gn:feature_code":"PPLL",
    "gn:name":"Simle",
    "gn:population":0,
    "gn:timezone":"Asia/Kathmandu",
    "iso:country":"NP",
    "wof:name":"Simle",
    "wof:placetype":"locality"
},
  "geometry": {"coordinates":[87.10953000000001,27.40225],"type":"Point"}
}