{
  "type": "Feature",
  "properties": {
    "gn:admin1_code":"WR",
    "gn:admin2_code":"8",
    "gn:admin3_code":"48",
    "gn:admin4_code":"480016",
    "gn:asciiname":"Barari",
    "gn:country_code":"NP",
    "gn:dem":111,
    "gn:feature_class":"P",
    "gn:feature_code":"PPLL",
    "gn:name":"Barari",
    "gn:population":0,
    "gn:timezone":"Asia/Kathmandu",
    "iso:country":"NP",
    "wof:name":"Barari",
    "wof:placetype":"locality"
},
  "geometry": {"coordinates":[83.70424,27.49153],"type":"Point"}
}