{
  "type": "Feature",
  "properties": {
    "gn:admin1_code":"ER",
    "gn:admin2_code":"10",
    "gn:admin3_code":"3.0",
    "gn:admin4_code":"30015.0",
    "gn:asciiname":"Keureni",
    "gn:country_code":"NP",
    "gn:dem":774,
    "gn:feature_class":"P",
    "gn:feature_code":"PPLL",
    "gn:name":"Keureni",
    "gn:population":0,
    "gn:timezone":"Asia/Kathmandu",
    "iso:country":"NP",
    "wof:name":"Keureni",
    "wof:placetype":"locality"
},
  "geometry": {"coordinates":[87.89981,26.87488],"type":"Point"}
}