{
  "type": "Feature",
  "properties": {
    "gn:admin1_code":"MR",
    "gn:admin2_code":"2.0",
    "gn:admin3_code":"57.0",
    "gn:admin4_code":"570002.0",
    "gn:asciiname":"Jigaun",
    "gn:country_code":"NP",
    "gn:dem":163,
    "gn:feature_class":"P",
    "gn:feature_code":"PPLL",
    "gn:name":"Jigaun",
    "gn:population":0,
    "gn:timezone":"Asia/Kathmandu",
    "iso:country":"NP",
    "wof:name":"Jigaun",
    "wof:placetype":"locality"
},
  "geometry": {"coordinates":[81.60772,28.19606],"type":"Point"}
}