{
  "type": "Feature",
  "properties": {
    "gn:admin1_code":"CR",
    "gn:admin2_code":"11",
    "gn:admin3_code":"35.0",
    "gn:admin4_code":"350035.0",
    "gn:asciiname":"Supar",
    "gn:country_code":"NP",
    "gn:dem":942,
    "gn:feature_class":"P",
    "gn:feature_code":"PPLL",
    "gn:name":"Supar",
    "gn:population":0,
    "gn:timezone":"Asia/Kathmandu",
    "iso:country":"NP",
    "wof:name":"Supar",
    "wof:placetype":"locality"
},
  "geometry": {"coordinates":[84.60544,27.75277],"type":"Point"}
}