{
  "type": "Feature",
  "properties": {
    "gn:admin1_code":"MR",
    "gn:admin2_code":"6",
    "gn:admin3_code":"63.0",
    "gn:admin4_code":"630017.0",
    "gn:asciiname":"Puwarkholi",
    "gn:country_code":"NP",
    "gn:dem":3173,
    "gn:feature_class":"P",
    "gn:feature_code":"PPLL",
    "gn:name":"Puwarkholi",
    "gn:population":0,
    "gn:timezone":"Asia/Kathmandu",
    "iso:country":"NP",
    "wof:name":"Puwarkholi",
    "wof:placetype":"locality"
},
  "geometry": {"coordinates":[82.08145,29.26404],"type":"Point"}
}