{
  "type": "Feature",
  "properties": {
    "gn:admin1_code":"FR",
    "gn:admin2_code":"9",
    "gn:admin3_code":"75.0",
    "gn:admin4_code":"750031.0",
    "gn:asciiname":"Parigaun",
    "gn:country_code":"NP",
    "gn:dem":2286,
    "gn:feature_class":"P",
    "gn:feature_code":"PPLL",
    "gn:name":"Parigaun",
    "gn:population":0,
    "gn:timezone":"Asia/Kathmandu",
    "iso:country":"NP",
    "wof:name":"Parigaun",
    "wof:placetype":"locality"
},
  "geometry": {"coordinates":[80.71986,29.94593],"type":"Point"}
}