{
  "type": "Feature",
  "properties": {
    "gn:admin1_code":"MR",
    "gn:admin2_code":"2",
    "gn:admin3_code":"61.0",
    "gn:admin4_code":"610011.0",
    "gn:asciiname":"Daha",
    "gn:country_code":"NP",
    "gn:dem":1109,
    "gn:feature_class":"P",
    "gn:feature_code":"PPLL",
    "gn:name":"Daha",
    "gn:population":0,
    "gn:timezone":"Asia/Kathmandu",
    "iso:country":"NP",
    "wof:name":"Daha",
    "wof:placetype":"locality"
},
  "geometry": {"coordinates":[81.93429999999999,28.68433],"type":"Point"}
}