{
  "type": "Feature",
  "properties": {
    "gn:admin1_code":"MR",
    "gn:admin2_code":"12",
    "gn:admin3_code":"54",
    "gn:admin4_code":"540031",
    "gn:asciiname":"Chakhlimela",
    "gn:country_code":"NP",
    "gn:dem":1440,
    "gn:feature_class":"P",
    "gn:feature_code":"PPLL",
    "gn:name":"Chakhlimela",
    "gn:population":0,
    "gn:timezone":"Asia/Kathmandu",
    "iso:country":"NP",
    "wof:name":"Chakhlimela",
    "wof:placetype":"locality"
},
  "geometry": {"coordinates":[82.26829000000002,28.66083],"type":"Point"}
}