{
  "type": "Feature",
  "properties": {
    "gn:admin1_code":"ER",
    "gn:admin2_code":"13",
    "gn:admin3_code":"13",
    "gn:admin4_code":"130045",
    "gn:asciiname":"Basbote",
    "gn:country_code":"NP",
    "gn:dem":1617,
    "gn:feature_class":"P",
    "gn:feature_code":"PPLL",
    "gn:name":"Basbote",
    "gn:population":0,
    "gn:timezone":"Asia/Kathmandu",
    "iso:country":"NP",
    "wof:name":"Basbote",
    "wof:placetype":"locality"
},
  "geometry": {"coordinates":[86.67775,27.23043],"type":"Point"}
}