{
  "type": "Feature",
  "properties": {
    "gn:admin1_code":"CR",
    "gn:admin2_code":"1",
    "gn:admin3_code":"30.0",
    "gn:admin4_code":"300037.0",
    "gn:asciiname":"Sikharbesi",
    "gn:country_code":"NP",
    "gn:dem":829,
    "gn:feature_class":"P",
    "gn:feature_code":"PPLL",
    "gn:name":"Sikharbesi",
    "gn:population":0,
    "gn:timezone":"Asia/Kathmandu",
    "iso:country":"NP",
    "wof:name":"Sikharbesi",
    "wof:placetype":"locality"
},
  "geometry": {"coordinates":[84.88419,27.75714],"type":"Point"}
}