{
  "type": "Feature",
  "properties": {
    "gn:admin1_code":"WR",
    "gn:admin2_code":"4",
    "gn:admin3_code":"36.0",
    "gn:admin4_code":"360060.0",
    "gn:asciiname":"Kumaltari",
    "gn:country_code":"NP",
    "gn:dem":918,
    "gn:feature_class":"P",
    "gn:feature_code":"PPLL",
    "gn:name":"Kumaltari",
    "gn:population":0,
    "gn:timezone":"Asia/Kathmandu",
    "iso:country":"NP",
    "wof:name":"Kumaltari",
    "wof:placetype":"locality"
},
  "geometry": {"coordinates":[84.68649000000001,28.10165],"type":"Point"}
}