{
  "type": "Feature",
  "properties": {
    "gn:admin1_code":"MR",
    "gn:admin2_code":"12",
    "gn:admin3_code":"55",
    "gn:admin4_code":"550044",
    "gn:asciiname":"Thapachaur",
    "gn:country_code":"NP",
    "gn:dem":775,
    "gn:feature_class":"P",
    "gn:feature_code":"PPLL",
    "gn:name":"Thapachaur",
    "gn:population":0,
    "gn:timezone":"Asia/Kathmandu",
    "iso:country":"NP",
    "wof:name":"Thapachaur",
    "wof:placetype":"locality"
},
  "geometry": {"coordinates":[82.17243000000001,28.59421],"type":"Point"}
}