{
  "type": "Feature",
  "properties": {
    "gn:admin1_code":"MR",
    "gn:admin2_code":"2.0",
    "gn:admin3_code":"59.0",
    "gn:admin4_code":"590004.0",
    "gn:asciiname":"Maineni",
    "gn:country_code":"NP",
    "gn:dem":1102,
    "gn:feature_class":"P",
    "gn:feature_code":"PPLL",
    "gn:name":"Maineni",
    "gn:population":0,
    "gn:timezone":"Asia/Kathmandu",
    "iso:country":"NP",
    "wof:name":"Maineni",
    "wof:placetype":"locality"
},
  "geometry": {"coordinates":[81.96315,28.54618],"type":"Point"}
}