{
  "type": "Feature",
  "properties": {
    "gn:admin1_code":"WR",
    "gn:admin2_code":"4",
    "gn:admin3_code":"41",
    "gn:admin4_code":"410001",
    "gn:asciiname":"Mugje",
    "gn:country_code":"NP",
    "gn:dem":3529,
    "gn:feature_class":"P",
    "gn:feature_code":"PPLL",
    "gn:name":"Mugje",
    "gn:population":0,
    "gn:timezone":"Asia/Kathmandu",
    "iso:country":"NP",
    "wof:name":"Mugje",
    "wof:placetype":"locality"
},
  "geometry": {"coordinates":[84.05627,28.65147],"type":"Point"}
}