{
  "type": "Feature",
  "properties": {
    "gn:admin1_code":"FR",
    "gn:admin2_code":"9",
    "gn:admin3_code":"74",
    "gn:admin4_code":"740027",
    "gn:asciiname":"Balpata",
    "gn:country_code":"NP",
    "gn:dem":911,
    "gn:feature_class":"P",
    "gn:feature_code":"PPLL",
    "gn:name":"Balpata",
    "gn:population":0,
    "gn:timezone":"Asia/Kathmandu",
    "iso:country":"NP",
    "wof:name":"Balpata",
    "wof:placetype":"locality"
},
  "geometry": {"coordinates":[80.46762,29.40191],"type":"Point"}
}