{
  "type": "Feature",
  "properties": {
    "gn:admin1_code":"FR",
    "gn:admin2_code":"9",
    "gn:admin3_code":"75.0",
    "gn:admin4_code":"750004.0",
    "gn:asciiname":"Talla Kauwa",
    "gn:country_code":"NP",
    "gn:dem":3315,
    "gn:feature_class":"P",
    "gn:feature_code":"PPLL",
    "gn:name":"Talla Kauwa",
    "gn:population":0,
    "gn:timezone":"Asia/Kathmandu",
    "iso:country":"NP",
    "wof:name":"Talla Kauwa",
    "wof:placetype":"locality"
},
  "geometry": {"coordinates":[80.87553,30.1642],"type":"Point"}
}