{
  "type": "Feature",
  "properties": {
    "gn:admin1_code":"WR",
    "gn:admin2_code":"8",
    "gn:admin3_code":"51.0",
    "gn:admin4_code":"510041.0",
    "gn:asciiname":"Tarai",
    "gn:country_code":"NP",
    "gn:dem":642,
    "gn:feature_class":"P",
    "gn:feature_code":"PPLL",
    "gn:name":"Tarai",
    "gn:population":0,
    "gn:timezone":"Asia/Kathmandu",
    "iso:country":"NP",
    "wof:name":"Tarai",
    "wof:placetype":"locality"
},
  "geometry": {"coordinates":[83.05094,27.7841],"type":"Point"}
}