{
  "type": "Feature",
  "properties": {
    "gn:admin1_code":"WR",
    "gn:admin2_code":"8",
    "gn:admin3_code":"48",
    "gn:admin4_code":"480007",
    "gn:asciiname":"Sardi",
    "gn:country_code":"NP",
    "gn:dem":188,
    "gn:feature_class":"P",
    "gn:feature_code":"PPLL",
    "gn:name":"Sardi",
    "gn:population":0,
    "gn:timezone":"Asia/Kathmandu",
    "iso:country":"NP",
    "name:ceb_x_preferred":[
        "Sardi"
    ],
    "name:deu_x_preferred":[
        "Sardi"
    ],
    "name:fra_x_preferred":[
        "Sardi"
    ],
    "name:ita_x_preferred":[
        "Sardi"
    ],
    "name:swe_x_preferred":[
        "Sardi"
    ],
    "wof:name":"Sardi",
    "wof:placetype":"locality"
},
  "geometry": {"coordinates":[83.83208,27.67306],"type":"Point"}
}