{
  "type": "Feature",
  "properties": {
    "gn:admin1_code":"ER",
    "gn:admin2_code":"7",
    "gn:admin3_code":"5",
    "gn:admin4_code":"50009",
    "gn:asciiname":"Dahidhap",
    "gn:country_code":"NP",
    "gn:dem":115,
    "gn:feature_class":"P",
    "gn:feature_code":"PPLL",
    "gn:name":"Dahidhap",
    "gn:population":0,
    "gn:timezone":"Asia/Kathmandu",
    "iso:country":"NP",
    "wof:name":"Dahidhap",
    "wof:placetype":"locality"
},
  "geometry": {"coordinates":[87.53013,26.62352000000001],"type":"Point"}
}