{
  "type": "Feature",
  "properties": {
    "gn:admin1_code":"CR",
    "gn:admin2_code":"5",
    "gn:admin3_code":"21",
    "gn:admin4_code":"210046.0",
    "gn:asciiname":"Kolunjor",
    "gn:country_code":"NP",
    "gn:dem":1143,
    "gn:feature_class":"P",
    "gn:feature_code":"PPLL",
    "gn:name":"Kolunjor",
    "gn:population":0,
    "gn:timezone":"Asia/Kathmandu",
    "iso:country":"NP",
    "wof:name":"Kolunjor",
    "wof:placetype":"locality"
},
  "geometry": {"coordinates":[86.18453000000002,27.27959],"type":"Point"}
}