{
  "type": "Feature",
  "properties": {
    "gn:admin1_code":"CR",
    "gn:admin2_code":"1",
    "gn:admin3_code":"30.0",
    "gn:admin4_code":"300011.0",
    "gn:asciiname":"Rudin",
    "gn:country_code":"NP",
    "gn:dem":1051,
    "gn:feature_class":"P",
    "gn:feature_code":"PPLL",
    "gn:name":"Rudin",
    "gn:population":0,
    "gn:timezone":"Asia/Kathmandu",
    "iso:country":"NP",
    "name:ara_x_preferred":[
        "\u0631\u0648\u062f\u064a\u0646"
    ],
    "name:deu_x_preferred":[
        "Rudin"
    ],
    "name:fas_x_preferred":[
        "\u0631\u0648\u062f\u06cc\u0646"
    ],
    "name:fra_x_preferred":[
        "Roudine"
    ],
    "name:hun_x_preferred":[
        "Rugyin"
    ],
    "name:hye_x_preferred":[
        "\u054c\u0578\u0582\u0564\u056b\u0576"
    ],
    "name:pan_x_preferred":[
        "\u0a30\u0a42\u0a26\u0a3f\u0a28"
    ],
    "name:pnb_x_preferred":[
        "\u0631\u0648\u062f\u0646"
    ],
    "name:pol_x_preferred":[
        "Rudin"
    ],
    "name:rus_x_preferred":[
        "\u0420\u0443\u0434\u0438\u043d"
    ],
    "wof:name":"Rudin",
    "wof:placetype":"locality"
},
  "geometry": {"coordinates":[84.72264,27.75509000000001],"type":"Point"}
}