{
  "type": "Feature",
  "properties": {
    "gn:admin1_code":"CR",
    "gn:admin2_code":"1",
    "gn:admin3_code":"30.0",
    "gn:admin4_code":"300033.0",
    "gn:asciiname":"Khirre Bhanjyang",
    "gn:country_code":"NP",
    "gn:dem":1180,
    "gn:feature_class":"P",
    "gn:feature_code":"PPLL",
    "gn:name":"Khirre Bhanjyang",
    "gn:population":0,
    "gn:timezone":"Asia/Kathmandu",
    "iso:country":"NP",
    "wof:name":"Khirre Bhanjyang",
    "wof:placetype":"locality"
},
  "geometry": {"coordinates":[84.81475,27.86743],"type":"Point"}
}