{
  "type": "Feature",
  "properties": {
    "gn:admin1_code":"ER",
    "gn:admin2_code":"7.0",
    "gn:admin3_code":"8.0",
    "gn:admin4_code":"80031.0",
    "gn:asciiname":"Myanglung Bajar",
    "gn:country_code":"NP",
    "gn:dem":1572,
    "gn:feature_class":"P",
    "gn:feature_code":"PPLL",
    "gn:name":"Myanglung Bajar",
    "gn:population":0,
    "gn:timezone":"Asia/Kathmandu",
    "iso:country":"NP",
    "wof:name":"Myanglung Bajar",
    "wof:placetype":"locality"
},
  "geometry": {"coordinates":[87.54347,27.12408],"type":"Point"}
}