{
  "type": "Feature",
  "properties": {
    "gn:admin1_code":"FR",
    "gn:admin2_code":"9",
    "gn:admin3_code":"73.0",
    "gn:admin4_code":"730015.0",
    "gn:asciiname":"Setigaun",
    "gn:country_code":"NP",
    "gn:dem":1460,
    "gn:feature_class":"P",
    "gn:feature_code":"PPLL",
    "gn:name":"Setigaun",
    "gn:population":0,
    "gn:timezone":"Asia/Kathmandu",
    "iso:country":"NP",
    "wof:name":"Setigaun",
    "wof:placetype":"locality"
},
  "geometry": {"coordinates":[80.6592,29.35325],"type":"Point"}
}