{
  "type": "Feature",
  "properties": {
    "gn:admin1_code":"ER",
    "gn:admin2_code":"10",
    "gn:admin3_code":"3.0",
    "gn:admin4_code":"30043.0",
    "gn:asciiname":"Kharbani",
    "gn:country_code":"NP",
    "gn:dem":301,
    "gn:feature_class":"P",
    "gn:feature_code":"PPLL",
    "gn:name":"Kharbani",
    "gn:population":0,
    "gn:timezone":"Asia/Kathmandu",
    "iso:country":"NP",
    "wof:name":"Kharbani",
    "wof:placetype":"locality"
},
  "geometry": {"coordinates":[87.99593,26.76399],"type":"Point"}
}