{
  "type": "Feature",
  "properties": {
    "gn:admin1_code":"WR",
    "gn:admin2_code":"8",
    "gn:admin3_code":"49",
    "gn:admin4_code":"490036",
    "gn:asciiname":"Mahubari",
    "gn:country_code":"NP",
    "gn:dem":122,
    "gn:feature_class":"P",
    "gn:feature_code":"PPLL",
    "gn:name":"Mahubari",
    "gn:population":0,
    "gn:timezone":"Asia/Kathmandu",
    "iso:country":"NP",
    "wof:name":"Mahubari",
    "wof:placetype":"locality"
},
  "geometry": {"coordinates":[83.37309999999999,27.64598],"type":"Point"}
}