{
  "type": "Feature",
  "properties": {
    "gn:admin1_code":"CR",
    "gn:admin2_code":"5.0",
    "gn:admin3_code":"21.0",
    "gn:asciiname":"Ramechhap",
    "gn:country_code":"NP",
    "gn:dem":1258,
    "gn:feature_class":"P",
    "gn:feature_code":"PPLA3",
    "gn:name":"R\u0101mechh\u0101p",
    "gn:population":0,
    "gn:timezone":"Asia/Kathmandu",
    "iso:country":"NP",
    "name:ben_x_preferred":[
        "\u09b0"
    ],
    "name:ell_x_preferred":[
        "\u03a1\u03b1\u03bc\u03b5\u03c7\u03ac\u03c0"
    ],
    "name:fas_x_preferred":[
        "\u0631\u0627\u0645\u0686\u0647\u0627\u0628"
    ],
    "name:heb_x_preferred":[
        "\u05e8\u05de\u05e6'\u05d0\u05e4"
    ],
    "name:hin_x_preferred":[
        "\u0930\u093e\u092e\u0947\u091b\u093e\u092a"
    ],
    "name:hun_x_preferred":[
        "Ramechhap"
    ],
    "name:ind_x_preferred":[
        "Ramechhap"
    ],
    "name:jpn_x_preferred":[
        "\u30e9\u30e1\u30c1\u30e3\u30c3\u30d7"
    ],
    "name:kor_x_preferred":[
        "\ub77c\uba54\ud569"
    ],
    "name:rus_x_preferred":[
        "\u0420\u0430\u043c\u0435\u0447\u0445\u0430\u043f"
    ],
    "name:spa_x_preferred":[
        "Ramechhap"
    ],
    "name:swe_x_preferred":[
        "Ramechhap"
    ],
    "name:tur_x_preferred":[
        "Ramechhap"
    ],
    "name:ukr_x_preferred":[
        "\u0420\u0430\u043c\u0435\u0447\u0445\u0430\u043f"
    ],
    "name:urd_x_preferred":[
        "\u0631\u06cc\u0645\u0648\u0686\u067e"
    ],
    "name:vie_x_preferred":[
        "Ramechhap"
    ],
    "wof:name":"Ramechhap",
    "wof:placetype":"locality"
},
  "geometry": {"coordinates":[86.08768000000001,27.3256],"type":"Point"}
}