{
  "type": "Feature",
  "properties": {
    "gn:admin1_code":"CR",
    "gn:admin2_code":"5.0",
    "gn:admin3_code":"21.0",
    "gn:asciiname":"Ramechhap",
    "gn:country_code":"NP",
    "gn:dem":1258,
    "gn:feature_class":"P",
    "gn:feature_code":"PPLA3",
    "gn:name":"R\u0101mechh\u0101p",
    "gn:population":0,
    "gn:timezone":"Asia/Kathmandu",
    "iso:country":"NP",
    "wof:name":"Ramechhap",
    "wof:placetype":"locality"
},
  "geometry": {"coordinates":[86.08768000000001,27.3256],"type":"Point"}
}