{
  "type": "Feature",
  "properties": {
    "gn:admin1_code":"00",
    "gn:asciiname":"Hunga",
    "gn:country_code":"NP",
    "gn:dem":2565,
    "gn:feature_class":"P",
    "gn:feature_code":"PPL",
    "gn:name":"Hung\u0101",
    "gn:population":0,
    "gn:timezone":"Asia/Kathmandu",
    "iso:country":"NP",
    "name:ceb_x_preferred":[
        "Hunga"
    ],
    "name:fra_x_preferred":[
        "Hunga"
    ],
    "name:ita_x_preferred":[
        "Hunga"
    ],
    "name:new_x_preferred":[
        "\u0939\u0941\u0919\u094d\u0917\u093e"
    ],
    "name:por_x_preferred":[
        "Hunga"
    ],
    "name:spa_x_preferred":[
        "Hunga"
    ],
    "name:swe_x_preferred":[
        "Hunga"
    ],
    "name:war_x_preferred":[
        "Hunga"
    ],
    "wof:name":"Hunga",
    "wof:placetype":"locality"
},
  "geometry": {"coordinates":[86.28301,27.52439],"type":"Point"}
}