{
  "type": "Feature",
  "properties": {
    "gn:admin1_code":"CR",
    "gn:admin2_code":"5",
    "gn:admin3_code":"19",
    "gn:admin4_code":"190002",
    "gn:asciiname":"Arnaha Bhansartol",
    "gn:country_code":"NP",
    "gn:dem":79,
    "gn:feature_class":"P",
    "gn:feature_code":"PPLL",
    "gn:name":"Arnaha Bhansartol",
    "gn:population":0,
    "gn:timezone":"Asia/Kathmandu",
    "iso:country":"NP",
    "wof:name":"Arnaha Bhansartol",
    "wof:placetype":"locality"
},
  "geometry": {"coordinates":[85.4006,26.78542],"type":"Point"}
}