{
  "type": "Feature",
  "properties": {
    "gn:admin1_code":"MR",
    "gn:admin2_code":"2",
    "gn:admin3_code":"60.0",
    "gn:admin4_code":"600049.0",
    "gn:asciiname":"Ata",
    "gn:country_code":"NP",
    "gn:dem":1728,
    "gn:feature_class":"P",
    "gn:feature_code":"PPLL",
    "gn:name":"Ata",
    "gn:population":0,
    "gn:timezone":"Asia/Kathmandu",
    "iso:country":"NP",
    "wof:name":"Ata",
    "wof:placetype":"locality"
},
  "geometry": {"coordinates":[81.82300000000002,28.87529],"type":"Point"}
}