{
  "type": "Feature",
  "properties": {
    "gn:admin1_code":"ER",
    "gn:admin2_code":"13",
    "gn:admin3_code":"16",
    "gn:admin4_code":"160100",
    "gn:asciiname":"Sitapur",
    "gn:country_code":"NP",
    "gn:dem":99,
    "gn:feature_class":"P",
    "gn:feature_code":"PPLL",
    "gn:name":"Sitapur",
    "gn:population":0,
    "gn:timezone":"Asia/Kathmandu",
    "iso:country":"NP",
    "name:bpy_x_preferred":[
        "\u09b8\u09bf\u09a4\u09be\u09aa\u09c1\u09b0"
    ],
    "name:cat_x_preferred":[
        "Sitapur"
    ],
    "name:ceb_x_preferred":[
        "S\u012bt\u0101pur"
    ],
    "name:deu_x_preferred":[
        "Sitapur"
    ],
    "name:fas_x_preferred":[
        "\u0633\u06cc\u062a\u0627\u067e\u0648\u0631"
    ],
    "name:fra_x_preferred":[
        "Sitapur"
    ],
    "name:guj_x_preferred":[
        "\u0ab8\u0ac0\u0aa4\u0abe\u0aaa\u0ac1\u0ab0"
    ],
    "name:heb_x_preferred":[
        "\u05e1\u05d9\u05d8\u05e4\u05d5\u05e8"
    ],
    "name:hin_x_preferred":[
        "\u0938\u0940\u0924\u093e\u092a\u0941\u0930"
    ],
    "name:hun_x_preferred":[
        "Sitapur"
    ],
    "name:ita_x_preferred":[
        "Sitapur"
    ],
    "name:jpn_x_preferred":[
        "\u30b7\u30fc\u30bf\u30fc\u30d7\u30eb"
    ],
    "name:mlg_x_preferred":[
        "Sitapur"
    ],
    "name:msa_x_preferred":[
        "Sitapur"
    ],
    "name:new_x_preferred":[
        "\u0938\u0940\u0924\u093e\u092a\u0941\u0930"
    ],
    "name:nld_x_preferred":[
        "Sitapur"
    ],
    "name:ori_x_preferred":[
        "\u0b38\u0b3f\u0b24\u0b3e\u0b2a\u0b41\u0b30"
    ],
    "name:pam_x_preferred":[
        "Sitapur"
    ],
    "name:pnb_x_preferred":[
        "\u0633\u06cc\u062a\u0627\u067e\u0648\u0631"
    ],
    "name:pol_x_preferred":[
        "Sitapur"
    ],
    "name:rus_x_preferred":[
        "\u0421\u0438\u0442\u0430\u043f\u0443\u0440"
    ],
    "name:san_x_preferred":[
        "\u0938\u0940\u0924\u093e\u092a\u0941\u0930\u092e\u094d"
    ],
    "name:swe_x_preferred":[
        "Sitapur"
    ],
    "name:tel_x_preferred":[
        "\u0c38\u0c40\u0c24\u0c3e\u0c2a\u0c42\u0c30\u0c4d"
    ],
    "name:urd_x_preferred":[
        "\u0633\u06cc\u062a\u0627\u067e\u0648\u0631"
    ],
    "name:vie_x_preferred":[
        "Sitapur"
    ],
    "name:war_x_preferred":[
        "Sitapur"
    ],
    "name:zho_x_preferred":[
        "\u897f\u5854\u666e\u5c14"
    ],
    "wof:name":"Sitapur",
    "wof:placetype":"locality"
},
  "geometry": {"coordinates":[86.43056,26.66132],"type":"Point"}
}