{
  "type": "Feature",
  "properties": {
    "gn:admin1_code":"MR",
    "gn:admin2_code":"2.0",
    "gn:admin3_code":"58.0",
    "gn:admin4_code":"580011.0",
    "gn:asciiname":"Gujarana",
    "gn:country_code":"NP",
    "gn:dem":150,
    "gn:feature_class":"P",
    "gn:feature_code":"PPLL",
    "gn:name":"Gujarana",
    "gn:population":0,
    "gn:timezone":"Asia/Kathmandu",
    "iso:country":"NP",
    "wof:name":"Gujarana",
    "wof:placetype":"locality"
},
  "geometry": {"coordinates":[81.3105,28.2636],"type":"Point"}
}