{
  "type": "Feature",
  "properties": {
    "gn:admin1_code":"CR",
    "gn:admin2_code":"1",
    "gn:admin3_code":"28",
    "gn:admin4_code":"280047",
    "gn:asciiname":"Glementho (Ghalegaun)",
    "gn:country_code":"NP",
    "gn:dem":1638,
    "gn:feature_class":"P",
    "gn:feature_code":"PPLL",
    "gn:name":"Glementho (Ghalegaun)",
    "gn:population":0,
    "gn:timezone":"Asia/Kathmandu",
    "iso:country":"NP",
    "wof:name":"Glementho (Ghalegaun)",
    "wof:placetype":"locality"
},
  "geometry": {"coordinates":[85.08735,28.02118],"type":"Point"}
}