{
  "type": "Feature",
  "properties": {
    "gn:admin1_code":"FR",
    "gn:admin2_code":"14",
    "gn:admin3_code":"68",
    "gn:admin4_code":"680031",
    "gn:asciiname":"Ghattala",
    "gn:country_code":"NP",
    "gn:dem":2319,
    "gn:feature_class":"P",
    "gn:feature_code":"PPLL",
    "gn:name":"Ghattala",
    "gn:population":0,
    "gn:timezone":"Asia/Kathmandu",
    "iso:country":"NP",
    "wof:name":"Ghattala",
    "wof:placetype":"locality"
},
  "geometry": {"coordinates":[81.29321999999998,29.54414],"type":"Point"}
}