{
  "type": "Feature",
  "properties": {
    "gn:admin1_code":"CR",
    "gn:admin2_code":"5",
    "gn:admin3_code":"18",
    "gn:admin4_code":"180022",
    "gn:asciiname":"Sirsiya",
    "gn:country_code":"NP",
    "gn:dem":68,
    "gn:feature_class":"P",
    "gn:feature_code":"PPLL",
    "gn:name":"Sirsiya",
    "gn:population":0,
    "gn:timezone":"Asia/Kathmandu",
    "iso:country":"NP",
    "name:msa_x_preferred":[
        "Sirsiya"
    ],
    "wof:name":"Sirsiya",
    "wof:placetype":"locality"
},
  "geometry": {"coordinates":[85.85633,26.65721],"type":"Point"}
}