{
  "type": "Feature",
  "properties": {
    "gn:admin1_code":"ER",
    "gn:admin2_code":"13",
    "gn:admin3_code":"13.0",
    "gn:admin4_code":"130007.0",
    "gn:asciiname":"Pipaldanda",
    "gn:country_code":"NP",
    "gn:dem":1413,
    "gn:feature_class":"P",
    "gn:feature_code":"PPLL",
    "gn:name":"Pipaldanda",
    "gn:population":0,
    "gn:timezone":"Asia/Kathmandu",
    "iso:country":"NP",
    "wof:name":"Pipaldanda",
    "wof:placetype":"locality"
},
  "geometry": {"coordinates":[86.83745,27.33923],"type":"Point"}
}