{
  "type": "Feature",
  "properties": {
    "gn:admin1_code":"CR",
    "gn:admin2_code":"11",
    "gn:admin3_code":"31",
    "gn:admin4_code":"310032.0",
    "gn:asciiname":"Bardeu",
    "gn:country_code":"NP",
    "gn:dem":2127,
    "gn:feature_class":"P",
    "gn:feature_code":"PPLL",
    "gn:name":"Bardeu",
    "gn:population":0,
    "gn:timezone":"Asia/Kathmandu",
    "iso:country":"NP",
    "wof:name":"Bardeu",
    "wof:placetype":"locality"
},
  "geometry": {"coordinates":[85.03393,27.60157],"type":"Point"}
}