{
  "type": "Feature",
  "properties": {
    "gn:admin1_code":"CR",
    "gn:admin2_code":"11",
    "gn:admin3_code":"31",
    "gn:admin4_code":"310039",
    "gn:asciiname":"Panchghare",
    "gn:country_code":"NP",
    "gn:dem":824,
    "gn:feature_class":"P",
    "gn:feature_code":"PPLL",
    "gn:name":"Panchghare",
    "gn:population":0,
    "gn:timezone":"Asia/Kathmandu",
    "iso:country":"NP",
    "wof:name":"Panchghare",
    "wof:placetype":"locality"
},
  "geometry": {"coordinates":[85.31147,27.41631],"type":"Point"}
}