{
  "type": "Feature",
  "properties": {
    "gn:admin1_code":"CR",
    "gn:admin2_code":"11",
    "gn:admin3_code":"35.0",
    "gn:admin4_code":"350029.0",
    "gn:asciiname":"Parbatipur",
    "gn:country_code":"NP",
    "gn:dem":186,
    "gn:feature_class":"P",
    "gn:feature_code":"PPLL",
    "gn:name":"Parbatipur",
    "gn:population":0,
    "gn:timezone":"Asia/Kathmandu",
    "iso:country":"NP",
    "name:ceb_x_preferred":[
        "Parbatipur"
    ],
    "name:swe_x_preferred":[
        "Parbatipur"
    ],
    "wof:name":"Parbatipur",
    "wof:placetype":"locality"
},
  "geometry": {"coordinates":[84.33371,27.60539],"type":"Point"}
}