{
  "type": "Feature",
  "properties": {
    "gn:admin1_code":"FR",
    "gn:admin2_code":"9",
    "gn:admin3_code":"73.0",
    "gn:admin4_code":"730002.0",
    "gn:asciiname":"Bhunda",
    "gn:country_code":"NP",
    "gn:dem":602,
    "gn:feature_class":"P",
    "gn:feature_code":"PPLL",
    "gn:name":"Bhunda",
    "gn:population":0,
    "gn:timezone":"Asia/Kathmandu",
    "iso:country":"NP",
    "wof:name":"Bhunda",
    "wof:placetype":"locality"
},
  "geometry": {"coordinates":[80.45,29.13051],"type":"Point"}
}