{
  "type": "Feature",
  "properties": {
    "gn:admin1_code":"MR",
    "gn:admin2_code":"6",
    "gn:admin3_code":"62.0",
    "gn:admin4_code":"620014.0",
    "gn:asciiname":"Kareli Kanda",
    "gn:country_code":"NP",
    "gn:dem":2734,
    "gn:feature_class":"P",
    "gn:feature_code":"PPLL",
    "gn:name":"Kareli Kanda",
    "gn:population":0,
    "gn:timezone":"Asia/Kathmandu",
    "iso:country":"NP",
    "wof:name":"Kareli Kanda",
    "wof:placetype":"locality"
},
  "geometry": {"coordinates":[82.79019,29.05044],"type":"Point"}
}