{
  "type": "Feature",
  "properties": {
    "gn:admin1_code":"CR",
    "gn:admin2_code":"5",
    "gn:admin3_code":"20",
    "gn:admin4_code":"200042",
    "gn:asciiname":"Dhansardadagau",
    "gn:country_code":"NP",
    "gn:dem":556,
    "gn:feature_class":"P",
    "gn:feature_code":"PPLL",
    "gn:name":"Dhansardadagau",
    "gn:population":0,
    "gn:timezone":"Asia/Kathmandu",
    "iso:country":"NP",
    "wof:name":"Dhansardadagau",
    "wof:placetype":"locality"
},
  "geometry": {"coordinates":[85.98071999999998,27.18491],"type":"Point"}
}