{
  "type": "Feature",
  "properties": {
    "gn:admin1_code":"WR",
    "gn:admin2_code":"3",
    "gn:admin3_code":"45.0",
    "gn:admin4_code":"450002.0",
    "gn:asciiname":"Bausechaur",
    "gn:country_code":"NP",
    "gn:dem":1311,
    "gn:feature_class":"P",
    "gn:feature_code":"PPLL",
    "gn:name":"Bausechaur",
    "gn:population":0,
    "gn:timezone":"Asia/Kathmandu",
    "iso:country":"NP",
    "wof:name":"Bausechaur",
    "wof:placetype":"locality"
},
  "geometry": {"coordinates":[83.63445,28.19467],"type":"Point"}
}