{
  "type": "Feature",
  "properties": {
    "gn:admin1_code":"FR",
    "gn:admin2_code":"9",
    "gn:admin3_code":"73.0",
    "gn:admin4_code":"730002.0",
    "gn:asciiname":"Dhullawa",
    "gn:country_code":"NP",
    "gn:dem":563,
    "gn:feature_class":"P",
    "gn:feature_code":"PPLL",
    "gn:name":"Dhullawa",
    "gn:population":0,
    "gn:timezone":"Asia/Kathmandu",
    "iso:country":"NP",
    "wof:name":"Dhullawa",
    "wof:placetype":"locality"
},
  "geometry": {"coordinates":[80.44356999999999,29.1315],"type":"Point"}
}