{
  "type": "Feature",
  "properties": {
    "gn:admin1_code":"FR",
    "gn:admin2_code":"9",
    "gn:admin3_code":"72.0",
    "gn:admin4_code":"720016.0",
    "gn:asciiname":"Pataiya",
    "gn:country_code":"NP",
    "gn:dem":194,
    "gn:feature_class":"P",
    "gn:feature_code":"PPLL",
    "gn:name":"Pataiya",
    "gn:population":0,
    "gn:timezone":"Asia/Kathmandu",
    "iso:country":"NP",
    "wof:name":"Pataiya",
    "wof:placetype":"locality"
},
  "geometry": {"coordinates":[80.24151999999999,28.89228],"type":"Point"}
}