{
  "type": "Feature",
  "properties": {
    "gn:admin1_code":"00",
    "gn:asciiname":"Ramrin",
    "gn:country_code":"NP",
    "gn:dem":1473,
    "gn:feature_class":"P",
    "gn:feature_code":"PPL",
    "gn:name":"R\u0101mri\u1e45",
    "gn:population":0,
    "gn:timezone":"Asia/Kathmandu",
    "iso:country":"NP",
    "wof:name":"Ramrin",
    "wof:placetype":"locality"
},
  "geometry": {"coordinates":[85.74581999999999,27.41712],"type":"Point"}
}