{
  "type": "Feature",
  "properties": {
    "gn:admin1_code":"WR",
    "gn:admin2_code":"4.0",
    "gn:admin3_code":"38.0",
    "gn:admin4_code":"380015.0",
    "gn:asciiname":"Batasedanda",
    "gn:country_code":"NP",
    "gn:dem":658,
    "gn:feature_class":"P",
    "gn:feature_code":"PPLL",
    "gn:name":"Batasedanda",
    "gn:population":0,
    "gn:timezone":"Asia/Kathmandu",
    "iso:country":"NP",
    "wof:name":"Batasedanda",
    "wof:placetype":"locality"
},
  "geometry": {"coordinates":[84.43800999999998,28.09837000000001],"type":"Point"}
}