{
  "type": "Feature",
  "properties": {
    "gn:admin1_code":"MR",
    "gn:admin2_code":"12",
    "gn:admin3_code":"56.0",
    "gn:admin4_code":"560030.0",
    "gn:asciiname":"Timlachaur",
    "gn:country_code":"NP",
    "gn:dem":970,
    "gn:feature_class":"P",
    "gn:feature_code":"PPLL",
    "gn:name":"Timlachaur",
    "gn:population":0,
    "gn:timezone":"Asia/Kathmandu",
    "iso:country":"NP",
    "wof:name":"Timlachaur",
    "wof:placetype":"locality"
},
  "geometry": {"coordinates":[82.52979999999999,28.08628],"type":"Point"}
}