{
  "type": "Feature",
  "properties": {
    "gn:admin1_code":"WR",
    "gn:admin2_code":"3",
    "gn:admin3_code":"43",
    "gn:admin4_code":"430029",
    "gn:asciiname":"Gajbang",
    "gn:country_code":"NP",
    "gn:dem":2324,
    "gn:feature_class":"P",
    "gn:feature_code":"PPLL",
    "gn:name":"Gajbang",
    "gn:population":0,
    "gn:timezone":"Asia/Kathmandu",
    "iso:country":"NP",
    "wof:name":"Gajbang",
    "wof:placetype":"locality"
},
  "geometry": {"coordinates":[83.46448000000002,28.4416],"type":"Point"}
}