{
  "type": "Feature",
  "properties": {
    "gn:admin1_code":"FR",
    "gn:admin2_code":"9",
    "gn:admin3_code":"73.0",
    "gn:admin4_code":"730016.0",
    "gn:asciiname":"Pyuman",
    "gn:country_code":"NP",
    "gn:dem":1373,
    "gn:feature_class":"P",
    "gn:feature_code":"PPLL",
    "gn:name":"Pyuman",
    "gn:population":0,
    "gn:timezone":"Asia/Kathmandu",
    "iso:country":"NP",
    "wof:name":"Pyuman",
    "wof:placetype":"locality"
},
  "geometry": {"coordinates":[80.67622,29.34049000000001],"type":"Point"}
}