{
  "type": "Feature",
  "properties": {
    "gn:admin1_code":"CR",
    "gn:admin2_code":"1",
    "gn:admin3_code":"27.0",
    "gn:admin4_code":"270009.0",
    "gn:asciiname":"Bosan",
    "gn:country_code":"NP",
    "gn:dem":1418,
    "gn:feature_class":"P",
    "gn:feature_code":"PPLL",
    "gn:name":"Bosan",
    "gn:population":0,
    "gn:timezone":"Asia/Kathmandu",
    "iso:country":"NP",
    "name:fas_x_preferred":[
        "\u0628\u0648\u0633\u0646"
    ],
    "name:urd_x_preferred":[
        "\u0628\u0648\u0633\u0646"
    ],
    "wof:name":"Bosan",
    "wof:placetype":"locality"
},
  "geometry": {"coordinates":[85.27323,27.64774],"type":"Point"}
}