{
  "type": "Feature",
  "properties": {
    "gn:admin1_code":"ER",
    "gn:admin2_code":"7.0",
    "gn:admin3_code":"8.0",
    "gn:admin4_code":"80003.0",
    "gn:asciiname":"Sabra",
    "gn:country_code":"NP",
    "gn:dem":1996,
    "gn:feature_class":"P",
    "gn:feature_code":"PPLL",
    "gn:name":"Sabra",
    "gn:population":0,
    "gn:timezone":"Asia/Kathmandu",
    "iso:country":"NP",
    "name:cat_x_preferred":[
        "Sabra"
    ],
    "name:deu_x_preferred":[
        "Sabra"
    ],
    "name:fra_x_preferred":[
        "Sabra"
    ],
    "name:heb_x_preferred":[
        "\u05e1\u05d1\u05e8\u05d4"
    ],
    "name:ind_x_preferred":[
        "Sabra"
    ],
    "name:ita_x_preferred":[
        "Sabra"
    ],
    "name:nld_x_preferred":[
        "Sabra"
    ],
    "name:nor_x_preferred":[
        "Sabra"
    ],
    "name:pol_x_preferred":[
        "Sabra"
    ],
    "name:por_x_preferred":[
        "Sabra"
    ],
    "name:rus_x_preferred":[
        "\u0421\u0430\u0431\u0440\u0430"
    ],
    "name:spa_x_preferred":[
        "Sabra"
    ],
    "name:swe_x_preferred":[
        "Sabra"
    ],
    "wof:name":"Sabra",
    "wof:placetype":"locality"
},
  "geometry": {"coordinates":[87.42671999999997,27.1532],"type":"Point"}
}