{
  "type": "Feature",
  "properties": {
    "gn:admin1_code":"MR",
    "gn:admin2_code":"12",
    "gn:admin3_code":"55",
    "gn:admin4_code":"550005",
    "gn:asciiname":"Masina",
    "gn:country_code":"NP",
    "gn:dem":1395,
    "gn:feature_class":"P",
    "gn:feature_code":"PPLL",
    "gn:name":"Masina",
    "gn:population":0,
    "gn:timezone":"Asia/Kathmandu",
    "iso:country":"NP",
    "name:ceb_x_preferred":[
        "Masina"
    ],
    "name:deu_x_preferred":[
        "Masina"
    ],
    "name:fra_x_preferred":[
        "Masina"
    ],
    "name:ind_x_preferred":[
        "Masina"
    ],
    "name:ita_x_preferred":[
        "Masina"
    ],
    "name:pol_x_preferred":[
        "Masina"
    ],
    "name:rus_x_preferred":[
        "\u041c\u0430\u0437\u0438\u043d\u0430"
    ],
    "name:srp_x_preferred":[
        "\u041c\u0430\u0441\u0438\u043d\u0430"
    ],
    "name:swe_x_preferred":[
        "Masina"
    ],
    "wof:name":"Masina",
    "wof:placetype":"locality"
},
  "geometry": {"coordinates":[82.27168,28.5339],"type":"Point"}
}