{
  "type": "Feature",
  "properties": {
    "gn:admin1_code":"ER",
    "gn:admin2_code":"10.0",
    "gn:admin3_code":"1.0",
    "gn:admin4_code":"10026.0",
    "gn:asciiname":"Sano Loden",
    "gn:country_code":"NP",
    "gn:dem":4767,
    "gn:feature_class":"P",
    "gn:feature_code":"PPLL",
    "gn:name":"Sano Loden",
    "gn:population":0,
    "gn:timezone":"Asia/Kathmandu",
    "iso:country":"NP",
    "wof:name":"Sano Loden",
    "wof:placetype":"locality"
},
  "geometry": {"coordinates":[87.73040999999998,27.65508],"type":"Point"}
}