{
  "type": "Feature",
  "properties": {
    "gn:admin1_code":"ER",
    "gn:admin2_code":"10",
    "gn:admin3_code":"4.0",
    "gn:admin4_code":"40037.0",
    "gn:asciiname":"Purba Pharam",
    "gn:country_code":"NP",
    "gn:dem":136,
    "gn:feature_class":"P",
    "gn:feature_code":"PPLL",
    "gn:name":"Purba Pharam",
    "gn:population":0,
    "gn:timezone":"Asia/Kathmandu",
    "iso:country":"NP",
    "wof:name":"Purba Pharam",
    "wof:placetype":"locality"
},
  "geometry": {"coordinates":[88.10488000000002,26.67611],"type":"Point"}
}