{
  "type": "Feature",
  "properties": {
    "gn:admin1_code":"FR",
    "gn:admin2_code":"14",
    "gn:admin3_code":"69.0",
    "gn:admin4_code":"690058.0",
    "gn:asciiname":"Bhulu",
    "gn:country_code":"NP",
    "gn:dem":1346,
    "gn:feature_class":"P",
    "gn:feature_code":"PPLL",
    "gn:name":"Bhulu",
    "gn:population":0,
    "gn:timezone":"Asia/Kathmandu",
    "iso:country":"NP",
    "wof:name":"Bhulu",
    "wof:placetype":"locality"
},
  "geometry": {"coordinates":[81.50615000000001,28.85739],"type":"Point"}
}