{
  "type": "Feature",
  "properties": {
    "gn:admin1_code":"MR",
    "gn:admin2_code":"12",
    "gn:admin3_code":"53",
    "gn:admin4_code":"530012",
    "gn:asciiname":"Bojupujne",
    "gn:country_code":"NP",
    "gn:dem":2126,
    "gn:feature_class":"P",
    "gn:feature_code":"PPLL",
    "gn:name":"Bojupujne",
    "gn:population":0,
    "gn:timezone":"Asia/Kathmandu",
    "iso:country":"NP",
    "wof:name":"Bojupujne",
    "wof:placetype":"locality"
},
  "geometry": {"coordinates":[82.68715999999998,28.30581],"type":"Point"}
}