{
  "type": "Feature",
  "properties": {
    "gn:admin1_code":"00",
    "gn:asciiname":"Muglaha",
    "gn:cc2":"NP",
    "gn:country_code":"NP",
    "gn:dem":97,
    "gn:feature_class":"P",
    "gn:feature_code":"PPL",
    "gn:name":"Muglaha",
    "gn:population":0,
    "gn:timezone":"Asia/Kathmandu",
    "iso:country":"NP",
    "name:und_x_variant":[
        "Mughla",
        "Muglaha"
    ],
    "wof:name":"Muglaha",
    "wof:placetype":"locality"
},
  "geometry": {"coordinates":[83.23333000000002,27.48333],"type":"Point"}
}