{
  "type": "Feature",
  "properties": {
    "gn:admin1_code":"MR",
    "gn:admin2_code":"2.0",
    "gn:admin3_code":"59.0",
    "gn:admin4_code":"590049.0",
    "gn:asciiname":"Patare",
    "gn:country_code":"NP",
    "gn:dem":463,
    "gn:feature_class":"P",
    "gn:feature_code":"PPLL",
    "gn:name":"Patare",
    "gn:population":0,
    "gn:timezone":"Asia/Kathmandu",
    "iso:country":"NP",
    "wof:name":"Patare",
    "wof:placetype":"locality"
},
  "geometry": {"coordinates":[81.41981,28.63475],"type":"Point"}
}