{
  "type": "Feature",
  "properties": {
    "gn:admin1_code":"ER",
    "gn:admin2_code":"7",
    "gn:admin3_code":"10.0",
    "gn:admin4_code":"100034.0",
    "gn:asciiname":"Panglung",
    "gn:country_code":"NP",
    "gn:dem":1592,
    "gn:feature_class":"P",
    "gn:feature_code":"PPLL",
    "gn:name":"Panglung",
    "gn:population":0,
    "gn:timezone":"Asia/Kathmandu",
    "iso:country":"NP",
    "name:mai_x_preferred":[
        "\u092a\u093e\u0919\u094d\u0917\u0932\u0941\u0919\u094d\u0917"
    ],
    "name:nep_x_preferred":[
        "\u092a\u093e\u0919\u094d\u0917\u0932\u0941\u0919\u094d\u0917"
    ],
    "wof:name":"Panglung",
    "wof:placetype":"locality"
},
  "geometry": {"coordinates":[87.03579999999999,27.40614],"type":"Point"}
}