{
  "type": "Feature",
  "properties": {
    "gn:admin1_code":"MR",
    "gn:admin2_code":"12",
    "gn:admin3_code":"56.0",
    "gn:admin4_code":"560033.0",
    "gn:asciiname":"Saunepani",
    "gn:country_code":"NP",
    "gn:dem":700,
    "gn:feature_class":"P",
    "gn:feature_code":"PPLL",
    "gn:name":"Saunepani",
    "gn:population":0,
    "gn:timezone":"Asia/Kathmandu",
    "iso:country":"NP",
    "wof:name":"Saunepani",
    "wof:placetype":"locality"
},
  "geometry": {"coordinates":[82.20227,28.17123],"type":"Point"}
}