{
  "type": "Feature",
  "properties": {
    "gn:admin1_code":"WR",
    "gn:admin2_code":"3",
    "gn:admin3_code":"43",
    "gn:admin4_code":"430012",
    "gn:asciiname":"Hanskholagaun",
    "gn:country_code":"NP",
    "gn:dem":2193,
    "gn:feature_class":"P",
    "gn:feature_code":"PPLL",
    "gn:name":"Hanskholagaun",
    "gn:population":0,
    "gn:timezone":"Asia/Kathmandu",
    "iso:country":"NP",
    "wof:name":"Hanskholagaun",
    "wof:placetype":"locality"
},
  "geometry": {"coordinates":[83.32630999999998,28.45397],"type":"Point"}
}