{
  "type": "Feature",
  "properties": {
    "gn:admin1_code":"FR",
    "gn:admin2_code":"14.0",
    "gn:admin3_code":"69.0",
    "gn:admin4_code":"690052.0",
    "gn:asciiname":"Dupalta",
    "gn:country_code":"NP",
    "gn:dem":1596,
    "gn:feature_class":"P",
    "gn:feature_code":"PPLL",
    "gn:name":"Dupalta",
    "gn:population":0,
    "gn:timezone":"Asia/Kathmandu",
    "iso:country":"NP",
    "wof:name":"Dupalta",
    "wof:placetype":"locality"
},
  "geometry": {"coordinates":[81.28923,29.24777000000001],"type":"Point"}
}