{
  "type": "Feature",
  "properties": {
    "gn:admin1_code":"WR",
    "gn:admin2_code":"8",
    "gn:admin3_code":"46.0",
    "gn:admin4_code":"460009.0",
    "gn:asciiname":"Thaple",
    "gn:country_code":"NP",
    "gn:dem":1059,
    "gn:feature_class":"P",
    "gn:feature_code":"PPLL",
    "gn:name":"Thaple",
    "gn:population":0,
    "gn:timezone":"Asia/Kathmandu",
    "iso:country":"NP",
    "wof:name":"Thaple",
    "wof:placetype":"locality"
},
  "geometry": {"coordinates":[83.36043000000002,28.19389],"type":"Point"}
}