{
  "type": "Feature",
  "properties": {
    "gn:admin1_code":"WR",
    "gn:admin2_code":"4.0",
    "gn:admin3_code":"38.0",
    "gn:admin4_code":"380034.0",
    "gn:asciiname":"Thamdanda",
    "gn:country_code":"NP",
    "gn:dem":495,
    "gn:feature_class":"P",
    "gn:feature_code":"PPLL",
    "gn:name":"Thamdanda",
    "gn:population":0,
    "gn:timezone":"Asia/Kathmandu",
    "iso:country":"NP",
    "wof:name":"Thamdanda",
    "wof:placetype":"locality"
},
  "geometry": {"coordinates":[84.31939,27.95802],"type":"Point"}
}