{
  "type": "Feature",
  "properties": {
    "gn:admin1_code":"MR",
    "gn:admin2_code":"2",
    "gn:admin3_code":"60.0",
    "gn:admin4_code":"600014.0",
    "gn:asciiname":"Mathillo Dunggeswar",
    "gn:country_code":"NP",
    "gn:dem":798,
    "gn:feature_class":"P",
    "gn:feature_code":"PPLL",
    "gn:name":"Mathillo Dunggeswar",
    "gn:population":0,
    "gn:timezone":"Asia/Kathmandu",
    "iso:country":"NP",
    "wof:name":"Mathillo Dunggeswar",
    "wof:placetype":"locality"
},
  "geometry": {"coordinates":[81.66606999999998,28.76229],"type":"Point"}
}