{
  "type": "Feature",
  "properties": {
    "gn:admin1_code":"MR",
    "gn:admin2_code":"12",
    "gn:admin3_code":"53",
    "gn:admin4_code":"530048",
    "gn:asciiname":"Kotaldhara",
    "gn:country_code":"NP",
    "gn:dem":1896,
    "gn:feature_class":"P",
    "gn:feature_code":"PPLL",
    "gn:name":"Kotaldhara",
    "gn:population":0,
    "gn:timezone":"Asia/Kathmandu",
    "iso:country":"NP",
    "wof:name":"Kotaldhara",
    "wof:placetype":"locality"
},
  "geometry": {"coordinates":[82.80794,28.4295],"type":"Point"}
}