{
  "type": "Feature",
  "properties": {
    "gn:admin1_code":"ER",
    "gn:admin2_code":"13",
    "gn:admin3_code":"16",
    "gn:admin4_code":"160022.0",
    "gn:asciiname":"Chamartol",
    "gn:country_code":"NP",
    "gn:dem":180,
    "gn:feature_class":"P",
    "gn:feature_code":"PPLL",
    "gn:name":"Chamartol",
    "gn:population":0,
    "gn:timezone":"Asia/Kathmandu",
    "iso:country":"NP",
    "wof:name":"Chamartol",
    "wof:placetype":"locality"
},
  "geometry": {"coordinates":[86.40276,26.79814],"type":"Point"}
}