{
  "type": "Feature",
  "properties": {
    "gn:admin1_code":"ER",
    "gn:admin2_code":"10",
    "gn:admin3_code":"3.0",
    "gn:admin4_code":"30011.0",
    "gn:asciiname":"Tinkhopre",
    "gn:country_code":"NP",
    "gn:dem":918,
    "gn:feature_class":"P",
    "gn:feature_code":"PPLL",
    "gn:name":"Tinkhopre",
    "gn:population":0,
    "gn:timezone":"Asia/Kathmandu",
    "iso:country":"NP",
    "wof:name":"Tinkhopre",
    "wof:placetype":"locality"
},
  "geometry": {"coordinates":[88.07465999999999,26.8051],"type":"Point"}
}