{
  "type": "Feature",
  "properties": {
    "gn:admin1_code":"CR",
    "gn:admin2_code":"1",
    "gn:admin3_code":"30.0",
    "gn:admin4_code":"300020.0",
    "gn:asciiname":"Gaindanda",
    "gn:country_code":"NP",
    "gn:dem":1094,
    "gn:feature_class":"P",
    "gn:feature_code":"PPLL",
    "gn:name":"Gaindanda",
    "gn:population":0,
    "gn:timezone":"Asia/Kathmandu",
    "iso:country":"NP",
    "wof:name":"Gaindanda",
    "wof:placetype":"locality"
},
  "geometry": {"coordinates":[84.96841999999999,27.83669],"type":"Point"}
}