{
  "type": "Feature",
  "properties": {
    "gn:admin1_code":"WR",
    "gn:admin2_code":"8",
    "gn:admin3_code":"46.0",
    "gn:admin4_code":"460078.0",
    "gn:asciiname":"Ajamir",
    "gn:country_code":"NP",
    "gn:dem":1044,
    "gn:feature_class":"P",
    "gn:feature_code":"PPLL",
    "gn:name":"Ajamir",
    "gn:population":0,
    "gn:timezone":"Asia/Kathmandu",
    "iso:country":"NP",
    "wof:name":"Ajamir",
    "wof:placetype":"locality"
},
  "geometry": {"coordinates":[83.12689,28.17499],"type":"Point"}
}