{
  "type": "Feature",
  "properties": {
    "gn:admin1_code":"MR",
    "gn:admin2_code":"12",
    "gn:admin3_code":"54",
    "gn:admin4_code":"540036",
    "gn:asciiname":"Kala Pokhara",
    "gn:country_code":"NP",
    "gn:dem":2250,
    "gn:feature_class":"P",
    "gn:feature_code":"PPLL",
    "gn:name":"Kala Pokhara",
    "gn:population":0,
    "gn:timezone":"Asia/Kathmandu",
    "iso:country":"NP",
    "wof:name":"Kala Pokhara",
    "wof:placetype":"locality"
},
  "geometry": {"coordinates":[82.48519,28.53845],"type":"Point"}
}