{
  "type": "Feature",
  "properties": {
    "gn:admin1_code":"FR",
    "gn:admin2_code":"14",
    "gn:admin3_code":"70.0",
    "gn:admin4_code":"700021.0",
    "gn:asciiname":"Patal",
    "gn:country_code":"NP",
    "gn:dem":1512,
    "gn:feature_class":"P",
    "gn:feature_code":"PPLL",
    "gn:name":"Patal",
    "gn:population":0,
    "gn:timezone":"Asia/Kathmandu",
    "iso:country":"NP",
    "name:fas_x_preferred":[
        "\u067e\u0627\u062a\u0644"
    ],
    "wof:name":"Patal",
    "wof:placetype":"locality"
},
  "geometry": {"coordinates":[80.78234999999999,29.25673],"type":"Point"}
}