{
  "type": "Feature",
  "properties": {
    "gn:admin1_code":"WR",
    "gn:admin2_code":"4",
    "gn:admin3_code":"40.0",
    "gn:admin4_code":"400025.0",
    "gn:asciiname":"Audi",
    "gn:country_code":"NP",
    "gn:dem":1566,
    "gn:feature_class":"P",
    "gn:feature_code":"PPLL",
    "gn:name":"Audi",
    "gn:population":0,
    "gn:timezone":"Asia/Kathmandu",
    "iso:country":"NP",
    "wof:name":"Audi",
    "wof:placetype":"locality"
},
  "geometry": {"coordinates":[83.97595,28.39208],"type":"Point"}
}