{
  "type": "Feature",
  "properties": {
    "gn:admin1_code":"CR",
    "gn:admin2_code":"1",
    "gn:admin3_code":"28",
    "gn:admin4_code":"280003",
    "gn:asciiname":"Yabra",
    "gn:country_code":"NP",
    "gn:dem":1449,
    "gn:feature_class":"P",
    "gn:feature_code":"PPLL",
    "gn:name":"Yabra",
    "gn:population":0,
    "gn:timezone":"Asia/Kathmandu",
    "iso:country":"NP",
    "wof:name":"Yabra",
    "wof:placetype":"locality"
},
  "geometry": {"coordinates":[85.01845,28.01277],"type":"Point"}
}