{
  "type": "Feature",
  "properties": {
    "gn:admin1_code":"MR",
    "gn:admin2_code":"12",
    "gn:admin3_code":"55",
    "gn:admin4_code":"550013",
    "gn:asciiname":"Khamnechaur",
    "gn:country_code":"NP",
    "gn:dem":640,
    "gn:feature_class":"P",
    "gn:feature_code":"PPLL",
    "gn:name":"Khamnechaur",
    "gn:population":0,
    "gn:timezone":"Asia/Kathmandu",
    "iso:country":"NP",
    "wof:name":"Khamnechaur",
    "wof:placetype":"locality"
},
  "geometry": {"coordinates":[82.04959000000002,28.51195],"type":"Point"}
}