{
  "type": "Feature",
  "properties": {
    "gn:admin1_code":"ER",
    "gn:admin2_code":"10",
    "gn:admin3_code":"3.0",
    "gn:admin4_code":"30025.0",
    "gn:asciiname":"Chuligaun",
    "gn:country_code":"NP",
    "gn:dem":265,
    "gn:feature_class":"P",
    "gn:feature_code":"PPLL",
    "gn:name":"Chuligaun",
    "gn:population":0,
    "gn:timezone":"Asia/Kathmandu",
    "iso:country":"NP",
    "wof:name":"Chuligaun",
    "wof:placetype":"locality"
},
  "geometry": {"coordinates":[87.81716999999998,26.74456],"type":"Point"}
}