{
  "type": "Feature",
  "properties": {
    "gn:admin1_code":"WR",
    "gn:admin2_code":"4",
    "gn:admin3_code":"40.0",
    "gn:admin4_code":"400001.0",
    "gn:asciiname":"Jarkate",
    "gn:country_code":"NP",
    "gn:dem":874,
    "gn:feature_class":"P",
    "gn:feature_code":"PPLL",
    "gn:name":"Jarkate",
    "gn:population":0,
    "gn:timezone":"Asia/Kathmandu",
    "iso:country":"NP",
    "wof:name":"Jarkate",
    "wof:placetype":"locality"
},
  "geometry": {"coordinates":[84.05609,28.22362],"type":"Point"}
}