{
  "type": "Feature",
  "properties": {
    "gn:admin1_code":"MR",
    "gn:admin2_code":"2",
    "gn:admin3_code":"60.0",
    "gn:admin4_code":"600002.0",
    "gn:asciiname":"Dunggri",
    "gn:country_code":"NP",
    "gn:dem":1014,
    "gn:feature_class":"P",
    "gn:feature_code":"PPLL",
    "gn:name":"Dunggri",
    "gn:population":0,
    "gn:timezone":"Asia/Kathmandu",
    "iso:country":"NP",
    "wof:name":"Dunggri",
    "wof:placetype":"locality"
},
  "geometry": {"coordinates":[81.69439,28.87499],"type":"Point"}
}