{
  "type": "Feature",
  "properties": {
    "gn:admin1_code":"FR",
    "gn:admin2_code":"14",
    "gn:admin3_code":"70.0",
    "gn:admin4_code":"700013.0",
    "gn:asciiname":"Kimana",
    "gn:country_code":"NP",
    "gn:dem":1690,
    "gn:feature_class":"P",
    "gn:feature_code":"PPLL",
    "gn:name":"Kimana",
    "gn:population":0,
    "gn:timezone":"Asia/Kathmandu",
    "iso:country":"NP",
    "name:azb_x_preferred":[
        "\u06a9\u06cc\u0645\u0627\u0646\u0627"
    ],
    "name:fas_x_preferred":[
        "\u06a9\u06cc\u0645\u0627\u0646\u0627"
    ],
    "wof:name":"Kimana",
    "wof:placetype":"locality"
},
  "geometry": {"coordinates":[81.0136,29.28655],"type":"Point"}
}