{
  "type": "Feature",
  "properties": {
    "gn:admin1_code":"CR",
    "gn:admin2_code":"5",
    "gn:admin3_code":"22.0",
    "gn:admin4_code":"220051.0",
    "gn:asciiname":"Rabu",
    "gn:country_code":"NP",
    "gn:dem":2193,
    "gn:feature_class":"P",
    "gn:feature_code":"PPLL",
    "gn:name":"Rabu",
    "gn:population":0,
    "gn:timezone":"Asia/Kathmandu",
    "iso:country":"NP",
    "name:ara_x_preferred":[
        "\u0631\u0628\u0639\u0648"
    ],
    "name:fas_x_preferred":[
        "\u0631\u0628\u0639\u0648"
    ],
    "name:pol_x_preferred":[
        "Rabu"
    ],
    "name:vie_x_preferred":[
        "Rabu"
    ],
    "wof:name":"Rabu",
    "wof:placetype":"locality"
},
  "geometry": {"coordinates":[86.295,27.64284],"type":"Point"}
}