{
  "type": "Feature",
  "properties": {
    "gn:admin1_code":"00",
    "gn:asciiname":"Kerunkholagau",
    "gn:country_code":"NP",
    "gn:dem":366,
    "gn:feature_class":"P",
    "gn:feature_code":"PPL",
    "gn:name":"Keru\u1e45khol\u0101g\u0101\u0169",
    "gn:population":0,
    "gn:timezone":"Asia/Kathmandu",
    "iso:country":"NP",
    "name:nep_x_preferred":[
        "Keru\u1e45khol\u0101g\u0101\u0169"
    ],
    "name:nep_x_variant":[
        "Keru\u1e45khol\u0101g\u0101un"
    ],
    "wof:name":"Kerunkholagau",
    "wof:placetype":"locality"
},
  "geometry": {"coordinates":[85.97452,27.09315],"type":"Point"}
}