{
  "type": "Feature",
  "properties": {
    "gn:admin1_code":"CR",
    "gn:admin2_code":"1",
    "gn:admin3_code":"28",
    "gn:admin4_code":"280023",
    "gn:asciiname":"Selelo",
    "gn:country_code":"NP",
    "gn:dem":2032,
    "gn:feature_class":"P",
    "gn:feature_code":"PPLL",
    "gn:name":"Selelo",
    "gn:population":0,
    "gn:timezone":"Asia/Kathmandu",
    "iso:country":"NP",
    "wof:name":"Selelo",
    "wof:placetype":"locality"
},
  "geometry": {"coordinates":[85.4533,27.99926],"type":"Point"}
}