{
  "type": "Feature",
  "properties": {
    "gn:admin1_code":"ER",
    "gn:admin2_code":"10",
    "gn:admin3_code":"2",
    "gn:admin4_code":"20030",
    "gn:asciiname":"Thulo Ghyang",
    "gn:country_code":"NP",
    "gn:dem":3234,
    "gn:feature_class":"P",
    "gn:feature_code":"PPLL",
    "gn:name":"Thulo Ghyang",
    "gn:population":0,
    "gn:timezone":"Asia/Kathmandu",
    "iso:country":"NP",
    "wof:name":"Thulo Ghyang",
    "wof:placetype":"locality"
},
  "geometry": {"coordinates":[88.00735,27.15281],"type":"Point"}
}