{
  "type": "Feature",
  "properties": {
    "gn:admin1_code":"ER",
    "gn:admin2_code":"7",
    "gn:admin3_code":"5",
    "gn:admin4_code":"50004",
    "gn:asciiname":"Bhaluwa",
    "gn:country_code":"NP",
    "gn:dem":71,
    "gn:feature_class":"P",
    "gn:feature_code":"PPLL",
    "gn:name":"Bhaluwa",
    "gn:population":0,
    "gn:timezone":"Asia/Kathmandu",
    "iso:country":"NP",
    "wof:name":"Bhaluwa",
    "wof:placetype":"locality"
},
  "geometry": {"coordinates":[87.43198000000002,26.47053],"type":"Point"}
}