{
  "type": "Feature",
  "properties": {
    "gn:admin1_code":"CR",
    "gn:admin2_code":"11",
    "gn:admin3_code":"32",
    "gn:admin4_code":"320052",
    "gn:asciiname":"Butuwakhor",
    "gn:country_code":"NP",
    "gn:dem":115,
    "gn:feature_class":"P",
    "gn:feature_code":"PPLL",
    "gn:name":"Butuwakhor",
    "gn:population":0,
    "gn:timezone":"Asia/Kathmandu",
    "iso:country":"NP",
    "wof:name":"Butuwakhor",
    "wof:placetype":"locality"
},
  "geometry": {"coordinates":[85.22374000000001,27.07414],"type":"Point"}
}