{
  "type": "Feature",
  "properties": {
    "gn:admin1_code":"WR",
    "gn:admin2_code":"3",
    "gn:admin3_code":"44",
    "gn:admin4_code":"440042",
    "gn:asciiname":"Shrikang",
    "gn:country_code":"NP",
    "gn:dem":1142,
    "gn:feature_class":"P",
    "gn:feature_code":"PPLL",
    "gn:name":"Shrikang",
    "gn:population":0,
    "gn:timezone":"Asia/Kathmandu",
    "iso:country":"NP",
    "wof:name":"Shrikang",
    "wof:placetype":"locality"
},
  "geometry": {"coordinates":[83.6412,28.12354],"type":"Point"}
}