{
  "type": "Feature",
  "properties": {
    "gn:admin1_code":"CR",
    "gn:admin2_code":"5.0",
    "gn:asciiname":"Bunbune",
    "gn:country_code":"NP",
    "gn:dem":887,
    "gn:feature_class":"P",
    "gn:feature_code":"PPL",
    "gn:name":"Bu\u1e45bu\u1e45e",
    "gn:population":0,
    "gn:timezone":"Asia/Kathmandu",
    "iso:country":"NP",
    "name:nep_x_preferred":[
        "Bu\u1e45bu\u1e45e"
    ],
    "wof:name":"Bunbune",
    "wof:placetype":"locality"
},
  "geometry": {"coordinates":[86.25946999999999,27.0823],"type":"Point"}
}