{
  "type": "Feature",
  "properties": {
    "gn:admin1_code":"WR",
    "gn:admin2_code":"4",
    "gn:admin3_code":"37",
    "gn:admin4_code":"370014",
    "gn:asciiname":"Bhulbhule",
    "gn:country_code":"NP",
    "gn:dem":843,
    "gn:feature_class":"P",
    "gn:feature_code":"PPLL",
    "gn:name":"Bhulbhule",
    "gn:population":0,
    "gn:timezone":"Asia/Kathmandu",
    "iso:country":"NP",
    "name:ceb_x_preferred":[
        "Bhulbhule"
    ],
    "name:fra_x_preferred":[
        "Bhulbhule"
    ],
    "name:msa_x_preferred":[
        "Bhulbhule"
    ],
    "name:nep_x_preferred":[
        "\u092d\u0941\u0932\u094d\u092d\u0941\u0932\u0947"
    ],
    "name:new_x_preferred":[
        "\u092d\u0941\u0932\u094d\u092d\u0941\u0932\u0947"
    ],
    "name:pol_x_preferred":[
        "Bhulbhule"
    ],
    "wof:name":"Bhulbhule",
    "wof:placetype":"locality"
},
  "geometry": {"coordinates":[84.36829,28.28916],"type":"Point"}
}