{
  "type": "Feature",
  "properties": {
    "gn:admin1_code":"FR",
    "gn:admin2_code":"9",
    "gn:admin3_code":"74",
    "gn:admin4_code":"740016",
    "gn:asciiname":"Nagini",
    "gn:country_code":"NP",
    "gn:dem":789,
    "gn:feature_class":"P",
    "gn:feature_code":"PPLL",
    "gn:name":"Nagini",
    "gn:population":0,
    "gn:timezone":"Asia/Kathmandu",
    "iso:country":"NP",
    "name:ceb_x_preferred":[
        "Nagini"
    ],
    "name:rus_x_preferred":[
        "\u041d\u0430\u0433\u0430\u0439\u043d\u0430"
    ],
    "name:spa_x_preferred":[
        "Nagini"
    ],
    "name:swe_x_preferred":[
        "Nagini"
    ],
    "wof:name":"Nagini",
    "wof:placetype":"locality"
},
  "geometry": {"coordinates":[80.56475999999998,29.67355],"type":"Point"}
}