{
  "type": "Feature",
  "properties": {
    "gn:admin1_code":"ER",
    "gn:admin2_code":"13",
    "gn:admin3_code":"12",
    "gn:admin4_code":"120031",
    "gn:asciiname":"Baredanda",
    "gn:country_code":"NP",
    "gn:dem":1541,
    "gn:feature_class":"P",
    "gn:feature_code":"PPLL",
    "gn:name":"Baredanda",
    "gn:population":0,
    "gn:timezone":"Asia/Kathmandu",
    "iso:country":"NP",
    "wof:name":"Baredanda",
    "wof:placetype":"locality"
},
  "geometry": {"coordinates":[86.40401,27.26102],"type":"Point"}
}