{
  "type": "Feature",
  "properties": {
    "gn:admin1_code":"FR",
    "gn:admin2_code":"9",
    "gn:admin3_code":"72.0",
    "gn:admin4_code":"720011.0",
    "gn:asciiname":"Bramhadev",
    "gn:country_code":"NP",
    "gn:dem":251,
    "gn:feature_class":"P",
    "gn:feature_code":"PPLL",
    "gn:name":"Bramhadev",
    "gn:population":0,
    "gn:timezone":"Asia/Kathmandu",
    "iso:country":"NP",
    "wof:name":"Bramhadev",
    "wof:placetype":"locality"
},
  "geometry": {"coordinates":[80.13578000000003,29.06499],"type":"Point"}
}