{
  "type": "Feature",
  "properties": {
    "gn:admin1_code":"FR",
    "gn:admin2_code":"9",
    "gn:admin3_code":"72.0",
    "gn:admin4_code":"720011.0",
    "gn:asciiname":"Bramhadev",
    "gn:country_code":"NP",
    "gn:dem":251,
    "gn:feature_class":"P",
    "gn:feature_code":"PPLL",
    "gn:name":"Bramhadev",
    "gn:population":0,
    "gn:timezone":"Asia/Kathmandu",
    "iso:country":"NP",
    "name:ceb_x_preferred":[
        "Bramhadev"
    ],
    "name:fra_x_preferred":[
        "Brahmadev"
    ],
    "name:msa_x_preferred":[
        "Bramhadev"
    ],
    "name:nep_x_preferred":[
        "\u092c\u094d\u0930\u0939\u094d\u092e\u0926\u0947\u0935"
    ],
    "name:new_x_preferred":[
        "\u092c\u094d\u0930\u0939\u094d\u092e\u0926\u0947\u0935"
    ],
    "name:pol_x_preferred":[
        "Bramhadev"
    ],
    "wof:name":"Bramhadev",
    "wof:placetype":"locality"
},
  "geometry": {"coordinates":[80.13578000000003,29.06499],"type":"Point"}
}