{
  "type": "Feature",
  "properties": {
    "gn:admin1_code":"WR",
    "gn:admin2_code":"8",
    "gn:admin3_code":"46.0",
    "gn:admin4_code":"460032.0",
    "gn:asciiname":"Dohali",
    "gn:country_code":"NP",
    "gn:dem":1441,
    "gn:feature_class":"P",
    "gn:feature_code":"PPLL",
    "gn:name":"Dohali",
    "gn:population":0,
    "gn:timezone":"Asia/Kathmandu",
    "iso:country":"NP",
    "name:ceb_x_preferred":[
        "Dohali"
    ],
    "name:fra_x_preferred":[
        "Dohali"
    ],
    "name:mai_x_preferred":[
        "\u0926\u094b\u0939\u0932\u0940"
    ],
    "name:msa_x_preferred":[
        "Dohali"
    ],
    "name:nep_x_preferred":[
        "\u0926\u094b\u0939\u0932\u0940"
    ],
    "name:new_x_preferred":[
        "\u0926\u094b\u0939\u0932\u0940"
    ],
    "name:pol_x_preferred":[
        "Dohali"
    ],
    "wof:name":"Dohali",
    "wof:placetype":"locality"
},
  "geometry": {"coordinates":[83.23567,28.17375],"type":"Point"}
}