{
  "type": "Feature",
  "properties": {
    "gn:admin1_code":"MR",
    "gn:admin2_code":"12",
    "gn:admin3_code":"55",
    "gn:admin4_code":"550013",
    "gn:asciiname":"Biunaradanda",
    "gn:country_code":"NP",
    "gn:dem":812,
    "gn:feature_class":"P",
    "gn:feature_code":"PPLL",
    "gn:name":"Biunaradanda",
    "gn:population":0,
    "gn:timezone":"Asia/Kathmandu",
    "iso:country":"NP",
    "wof:name":"Biunaradanda",
    "wof:placetype":"locality"
},
  "geometry": {"coordinates":[82.02238,28.45322],"type":"Point"}
}