{
  "type": "Feature",
  "properties": {
    "gn:admin1_code":"FR",
    "gn:admin2_code":"9",
    "gn:admin3_code":"74",
    "gn:admin4_code":"740047",
    "gn:asciiname":"Kulthada",
    "gn:country_code":"NP",
    "gn:dem":948,
    "gn:feature_class":"P",
    "gn:feature_code":"PPLL",
    "gn:name":"Kulthada",
    "gn:population":0,
    "gn:timezone":"Asia/Kathmandu",
    "iso:country":"NP",
    "wof:name":"Kulthada",
    "wof:placetype":"locality"
},
  "geometry": {"coordinates":[80.61404,29.68354],"type":"Point"}
}