{
  "type": "Feature",
  "properties": {
    "gn:admin1_code":"MR",
    "gn:admin2_code":"2",
    "gn:admin3_code":"60.0",
    "gn:admin4_code":"600019.0",
    "gn:asciiname":"Panikhal Tol",
    "gn:country_code":"NP",
    "gn:dem":1693,
    "gn:feature_class":"P",
    "gn:feature_code":"PPLL",
    "gn:name":"Panikhal Tol",
    "gn:population":0,
    "gn:timezone":"Asia/Kathmandu",
    "iso:country":"NP",
    "wof:name":"Panikhal Tol",
    "wof:placetype":"locality"
},
  "geometry": {"coordinates":[81.86028,28.77576],"type":"Point"}
}