{
  "type": "Feature",
  "properties": {
    "gn:admin1_code":"ER",
    "gn:admin2_code":"13",
    "gn:admin3_code":"11",
    "gn:admin4_code":"110018",
    "gn:asciiname":"Thore",
    "gn:country_code":"NP",
    "gn:dem":4438,
    "gn:feature_class":"P",
    "gn:feature_code":"PPLL",
    "gn:name":"Thore",
    "gn:population":0,
    "gn:timezone":"Asia/Kathmandu",
    "iso:country":"NP",
    "wof:name":"Thore",
    "wof:placetype":"locality"
},
  "geometry": {"coordinates":[86.72881,27.89487],"type":"Point"}
}