{
  "type": "Feature",
  "properties": {
    "gn:admin1_code":"FR",
    "gn:admin2_code":"14",
    "gn:admin3_code":"68",
    "gn:admin4_code":"680006",
    "gn:asciiname":"Pitha Lek",
    "gn:country_code":"NP",
    "gn:dem":2434,
    "gn:feature_class":"P",
    "gn:feature_code":"PPLL",
    "gn:name":"Pitha Lek",
    "gn:population":0,
    "gn:timezone":"Asia/Kathmandu",
    "iso:country":"NP",
    "wof:name":"Pitha Lek",
    "wof:placetype":"locality"
},
  "geometry": {"coordinates":[81.19896,29.58033],"type":"Point"}
}