{
  "type": "Feature",
  "properties": {
    "gn:admin1_code":"WR",
    "gn:admin2_code":"4",
    "gn:admin3_code":"36.0",
    "gn:admin4_code":"360014.0",
    "gn:asciiname":"Phimaldanda",
    "gn:country_code":"NP",
    "gn:dem":854,
    "gn:feature_class":"P",
    "gn:feature_code":"PPLL",
    "gn:name":"Phimaldanda",
    "gn:population":0,
    "gn:timezone":"Asia/Kathmandu",
    "iso:country":"NP",
    "wof:name":"Phimaldanda",
    "wof:placetype":"locality"
},
  "geometry": {"coordinates":[84.6005,28.05041],"type":"Point"}
}