{
  "type": "Feature",
  "properties": {
    "gn:admin1_code":"WR",
    "gn:admin2_code":"8",
    "gn:admin3_code":"47",
    "gn:admin4_code":"470021",
    "gn:asciiname":"Somahar",
    "gn:country_code":"NP",
    "gn:dem":1332,
    "gn:feature_class":"P",
    "gn:feature_code":"PPLL",
    "gn:name":"Somahar",
    "gn:population":0,
    "gn:timezone":"Asia/Kathmandu",
    "iso:country":"NP",
    "wof:name":"Somahar",
    "wof:placetype":"locality"
},
  "geometry": {"coordinates":[83.40392,27.85955],"type":"Point"}
}