{
  "type": "Feature",
  "properties": {
    "gn:admin1_code":"WR",
    "gn:admin2_code":"4",
    "gn:admin3_code":"36.0",
    "gn:admin4_code":"360041.0",
    "gn:asciiname":"Tinghare",
    "gn:country_code":"NP",
    "gn:dem":737,
    "gn:feature_class":"P",
    "gn:feature_code":"PPLL",
    "gn:name":"Tinghare",
    "gn:population":0,
    "gn:timezone":"Asia/Kathmandu",
    "iso:country":"NP",
    "wof:name":"Tinghare",
    "wof:placetype":"locality"
},
  "geometry": {"coordinates":[84.56475999999998,27.87025],"type":"Point"}
}