{
  "type": "Feature",
  "properties": {
    "gn:admin1_code":"ER",
    "gn:admin2_code":"13.0",
    "gn:admin3_code":"14.0",
    "gn:admin4_code":"140026.0",
    "gn:asciiname":"Pipal Bhanjyang",
    "gn:country_code":"NP",
    "gn:dem":902,
    "gn:feature_class":"P",
    "gn:feature_code":"PPLL",
    "gn:name":"Pipal Bhanjyang",
    "gn:population":0,
    "gn:timezone":"Asia/Kathmandu",
    "iso:country":"NP",
    "wof:name":"Pipal Bhanjyang",
    "wof:placetype":"locality"
},
  "geometry": {"coordinates":[86.49429000000001,27.08327],"type":"Point"}
}