{
  "type": "Feature",
  "properties": {
    "gn:admin1_code":"ER",
    "gn:admin2_code":"13",
    "gn:admin3_code":"11",
    "gn:admin4_code":"110010",
    "gn:asciiname":"Bhasme",
    "gn:country_code":"NP",
    "gn:dem":2323,
    "gn:feature_class":"P",
    "gn:feature_code":"PPLL",
    "gn:name":"Bhasme",
    "gn:population":0,
    "gn:timezone":"Asia/Kathmandu",
    "iso:country":"NP",
    "wof:name":"Bhasme",
    "wof:placetype":"locality"
},
  "geometry": {"coordinates":[86.5937,27.44907000000001],"type":"Point"}
}