{
  "type": "Feature",
  "properties": {
    "gn:admin1_code":"WR",
    "gn:admin2_code":"8",
    "gn:admin3_code":"51.0",
    "gn:admin4_code":"510022.0",
    "gn:asciiname":"Arlanga",
    "gn:country_code":"NP",
    "gn:dem":1057,
    "gn:feature_class":"P",
    "gn:feature_code":"PPLL",
    "gn:name":"Arlanga",
    "gn:population":0,
    "gn:timezone":"Asia/Kathmandu",
    "iso:country":"NP",
    "wof:name":"Arlanga",
    "wof:placetype":"locality"
},
  "geometry": {"coordinates":[83.2392,28.00374],"type":"Point"}
}