{
  "type": "Feature",
  "properties": {
    "gn:admin1_code":"CR",
    "gn:admin2_code":"1",
    "gn:admin3_code":"27.0",
    "gn:admin4_code":"270031.0",
    "gn:asciiname":"Ghattekulo",
    "gn:country_code":"NP",
    "gn:dem":1304,
    "gn:feature_class":"P",
    "gn:feature_code":"PPLL",
    "gn:name":"Ghattekulo",
    "gn:population":0,
    "gn:timezone":"Asia/Kathmandu",
    "iso:country":"NP",
    "wof:name":"Ghattekulo",
    "wof:placetype":"locality"
},
  "geometry": {"coordinates":[85.3331,27.70309],"type":"Point"}
}