{
  "type": "Feature",
  "properties": {
    "gn:admin1_code":"WR",
    "gn:admin2_code":"4.0",
    "gn:admin3_code":"39.0",
    "gn:admin4_code":"390054.0",
    "gn:asciiname":"Beldanda",
    "gn:country_code":"NP",
    "gn:dem":777,
    "gn:feature_class":"P",
    "gn:feature_code":"PPLL",
    "gn:name":"Beldanda",
    "gn:population":0,
    "gn:timezone":"Asia/Kathmandu",
    "iso:country":"NP",
    "wof:name":"Beldanda",
    "wof:placetype":"locality"
},
  "geometry": {"coordinates":[83.76145,28.03334000000001],"type":"Point"}
}