{
  "type": "Feature",
  "properties": {
    "gn:admin1_code":"FR",
    "gn:admin2_code":"14.0",
    "gn:admin3_code":"69.0",
    "gn:admin4_code":"690047.0",
    "gn:asciiname":"Mangalsen",
    "gn:country_code":"NP",
    "gn:dem":1233,
    "gn:feature_class":"P",
    "gn:feature_code":"PPLL",
    "gn:name":"Mangalsen",
    "gn:population":0,
    "gn:timezone":"Asia/Kathmandu",
    "iso:country":"NP",
    "name:bih_x_preferred":[
        "\u092e\u0902\u0917\u0932\u0938\u0947\u0928"
    ],
    "name:ceb_x_preferred":[
        "Mangalsen"
    ],
    "name:deu_x_preferred":[
        "Mangalsen"
    ],
    "name:dty_x_preferred":[
        "\u092e\u0902\u0917\u0932\u0938\u0947\u0928 \u0928\u0917\u0930\u092a\u093e\u0932\u093f\u0915\u093e"
    ],
    "name:fra_x_preferred":[
        "Mangalsen"
    ],
    "name:ita_x_preferred":[
        "Mangalsen"
    ],
    "name:nep_x_preferred":[
        "\u092e\u0902\u0917\u0932\u0938\u0947\u0928"
    ],
    "name:new_x_preferred":[
        "\u092e\u0902\u0917\u0932\u0938\u0947\u0928"
    ],
    "name:nld_x_preferred":[
        "Mangalsen"
    ],
    "name:pol_x_preferred":[
        "Mangalsen"
    ],
    "name:por_x_preferred":[
        "Mangalsen"
    ],
    "name:urd_x_preferred":[
        "\u0645\u0627\u0646\u06af\u0627\u0644\u0633\u06cc\u0646"
    ],
    "wof:name":"Mangalsen",
    "wof:placetype":"locality"
},
  "geometry": {"coordinates":[81.25908000000003,29.14256],"type":"Point"}
}