{
  "type": "Feature",
  "properties": {
    "gn:admin1_code":"FR",
    "gn:admin2_code":"14.0",
    "gn:admin3_code":"69.0",
    "gn:admin4_code":"690047.0",
    "gn:asciiname":"Mangalsen",
    "gn:country_code":"NP",
    "gn:dem":1233,
    "gn:feature_class":"P",
    "gn:feature_code":"PPLL",
    "gn:name":"Mangalsen",
    "gn:population":0,
    "gn:timezone":"Asia/Kathmandu",
    "iso:country":"NP",
    "wof:name":"Mangalsen",
    "wof:placetype":"locality"
},
  "geometry": {"coordinates":[81.25908000000003,29.14256],"type":"Point"}
}