{
  "type": "Feature",
  "properties": {
    "gn:admin1_code":"CR",
    "gn:admin2_code":"1",
    "gn:admin3_code":"23",
    "gn:admin4_code":"230042.0",
    "gn:asciiname":"Taju",
    "gn:country_code":"NP",
    "gn:dem":1688,
    "gn:feature_class":"P",
    "gn:feature_code":"PPLL",
    "gn:name":"Taju",
    "gn:population":0,
    "gn:timezone":"Asia/Kathmandu",
    "iso:country":"NP",
    "wof:name":"Taju",
    "wof:placetype":"locality"
},
  "geometry": {"coordinates":[85.85229,27.64221],"type":"Point"}
}