{
  "type": "Feature",
  "properties": {
    "gn:admin1_code":"MR",
    "gn:admin2_code":"2.0",
    "gn:admin3_code":"59.0",
    "gn:admin4_code":"590021.0",
    "gn:asciiname":"Gutu",
    "gn:country_code":"NP",
    "gn:dem":382,
    "gn:feature_class":"P",
    "gn:feature_code":"PPLL",
    "gn:name":"Gutu",
    "gn:population":0,
    "gn:timezone":"Asia/Kathmandu",
    "iso:country":"NP",
    "name:bar_x_preferred":[
        "Gutu"
    ],
    "name:ceb_x_preferred":[
        "Gutu District"
    ],
    "name:deu_x_preferred":[
        "Gutu"
    ],
    "name:nor_x_preferred":[
        "Gutu"
    ],
    "name:swe_x_preferred":[
        "Gutu"
    ],
    "wof:name":"Gutu",
    "wof:placetype":"locality"
},
  "geometry": {"coordinates":[81.32289,28.84393],"type":"Point"}
}