{
  "type": "Feature",
  "properties": {
    "gn:admin1_code":"ER",
    "gn:admin2_code":"10",
    "gn:admin3_code":"4.0",
    "gn:admin4_code":"40009.0",
    "gn:asciiname":"Kalidasbari",
    "gn:country_code":"NP",
    "gn:dem":92,
    "gn:feature_class":"P",
    "gn:feature_code":"PPLL",
    "gn:name":"Kalidasbari",
    "gn:population":0,
    "gn:timezone":"Asia/Kathmandu",
    "iso:country":"NP",
    "wof:name":"Kalidasbari",
    "wof:placetype":"locality"
},
  "geometry": {"coordinates":[87.91620999999998,26.54836],"type":"Point"}
}