{
  "type": "Feature",
  "properties": {
    "gn:admin1_code":"CR",
    "gn:admin2_code":"1",
    "gn:admin3_code":"24.0",
    "gn:admin4_code":"240065.0",
    "gn:asciiname":"Patikharka",
    "gn:country_code":"NP",
    "gn:dem":1537,
    "gn:feature_class":"P",
    "gn:feature_code":"PPLL",
    "gn:name":"Patikharka",
    "gn:population":0,
    "gn:timezone":"Asia/Kathmandu",
    "iso:country":"NP",
    "wof:name":"Patikharka",
    "wof:placetype":"locality"
},
  "geometry": {"coordinates":[85.52431,27.55584],"type":"Point"}
}