{
  "type": "Feature",
  "properties": {
    "gn:admin1_code":"MR",
    "gn:admin2_code":"2.0",
    "gn:admin3_code":"59.0",
    "gn:admin4_code":"590005.0",
    "gn:asciiname":"Balle Mohada",
    "gn:country_code":"NP",
    "gn:dem":298,
    "gn:feature_class":"P",
    "gn:feature_code":"PPLL",
    "gn:name":"Balle Mohada",
    "gn:population":0,
    "gn:timezone":"Asia/Kathmandu",
    "iso:country":"NP",
    "wof:name":"Balle Mohada",
    "wof:placetype":"locality"
},
  "geometry": {"coordinates":[81.19569,28.86173],"type":"Point"}
}