{
  "type": "Feature",
  "properties": {
    "gn:admin1_code":"FR",
    "gn:admin2_code":"14",
    "gn:admin3_code":"71.0",
    "gn:admin4_code":"710038.0",
    "gn:asciiname":"Mauri",
    "gn:country_code":"NP",
    "gn:dem":1017,
    "gn:feature_class":"P",
    "gn:feature_code":"PPLL",
    "gn:name":"Mauri",
    "gn:population":0,
    "gn:timezone":"Asia/Kathmandu",
    "iso:country":"NP",
    "name:bos_x_preferred":[
        "Mauri"
    ],
    "name:bre_x_preferred":[
        "Mauri"
    ],
    "name:ceb_x_preferred":[
        "Mauri"
    ],
    "name:deu_x_preferred":[
        "Mauri"
    ],
    "name:fin_x_preferred":[
        "Mauri"
    ],
    "name:fra_x_preferred":[
        "Mauri"
    ],
    "name:ita_x_preferred":[
        "Mauri"
    ],
    "name:rus_x_preferred":[
        "\u041c\u0430\u0443\u0440\u0438"
    ],
    "name:spa_x_preferred":[
        "Mauri"
    ],
    "wof:name":"Mauri",
    "wof:placetype":"locality"
},
  "geometry": {"coordinates":[80.58771999999998,28.96446],"type":"Point"}
}