{
  "type": "Feature",
  "properties": {
    "gn:admin1_code":"MR",
    "gn:admin2_code":"2.0",
    "gn:admin3_code":"59.0",
    "gn:admin4_code":"590021.0",
    "gn:asciiname":"Matisara Bajar",
    "gn:country_code":"NP",
    "gn:dem":394,
    "gn:feature_class":"P",
    "gn:feature_code":"PPLL",
    "gn:name":"Matisara Bajar",
    "gn:population":0,
    "gn:timezone":"Asia/Kathmandu",
    "iso:country":"NP",
    "wof:name":"Matisara Bajar",
    "wof:placetype":"locality"
},
  "geometry": {"coordinates":[81.32286999999999,28.84091],"type":"Point"}
}