{
  "type": "Feature",
  "properties": {
    "gn:admin1_code":"00",
    "gn:asciiname":"Rangedada",
    "gn:country_code":"NP",
    "gn:dem":91,
    "gn:feature_class":"P",
    "gn:feature_code":"PPL",
    "gn:name":"Ra\u1e45ge\u1e0d\u0101\u0303\u1e0d\u0101",
    "gn:population":0,
    "gn:timezone":"Asia/Kathmandu",
    "iso:country":"NP",
    "name:nep_x_preferred":[
        "Ra\u1e45ge\u1e0d\u0101\u0303\u1e0d\u0101"
    ],
    "wof:name":"Rangedada",
    "wof:placetype":"locality"
},
  "geometry": {"coordinates":[88.05627,26.53143],"type":"Point"}
}