{
  "type": "Feature",
  "properties": {
    "gn:admin1_code":"WR",
    "gn:admin2_code":"4.0",
    "gn:admin3_code":"38.0",
    "gn:admin4_code":"380035.0",
    "gn:asciiname":"Baliphant",
    "gn:country_code":"NP",
    "gn:dem":452,
    "gn:feature_class":"P",
    "gn:feature_code":"PPLL",
    "gn:name":"Baliphant",
    "gn:population":0,
    "gn:timezone":"Asia/Kathmandu",
    "iso:country":"NP",
    "wof:name":"Baliphant",
    "wof:placetype":"locality"
},
  "geometry": {"coordinates":[84.46366999999999,28.04304],"type":"Point"}
}