{
  "type": "Feature",
  "properties": {
    "gn:admin1_code":"WR",
    "gn:admin2_code":"3",
    "gn:admin3_code":"44",
    "gn:admin4_code":"440013",
    "gn:asciiname":"Bachchhabot",
    "gn:country_code":"NP",
    "gn:dem":1074,
    "gn:feature_class":"P",
    "gn:feature_code":"PPLL",
    "gn:name":"Bachchhabot",
    "gn:population":0,
    "gn:timezone":"Asia/Kathmandu",
    "iso:country":"NP",
    "wof:name":"Bachchhabot",
    "wof:placetype":"locality"
},
  "geometry": {"coordinates":[83.58534,28.07281],"type":"Point"}
}