{
  "type": "Feature",
  "properties": {
    "gn:admin1_code":"WR",
    "gn:admin2_code":"8",
    "gn:admin3_code":"51.0",
    "gn:admin4_code":"510040.0",
    "gn:asciiname":"Karmdip",
    "gn:country_code":"NP",
    "gn:dem":1267,
    "gn:feature_class":"P",
    "gn:feature_code":"PPLL",
    "gn:name":"Karmdip",
    "gn:population":0,
    "gn:timezone":"Asia/Kathmandu",
    "iso:country":"NP",
    "wof:name":"Karmdip",
    "wof:placetype":"locality"
},
  "geometry": {"coordinates":[83.16476999999998,27.86898],"type":"Point"}
}