{
  "type": "Feature",
  "properties": {
    "gn:admin1_code":"WR",
    "gn:admin2_code":"8",
    "gn:admin3_code":"47",
    "gn:admin4_code":"470061.0",
    "gn:asciiname":"Sekibas",
    "gn:country_code":"NP",
    "gn:dem":1085,
    "gn:feature_class":"P",
    "gn:feature_code":"PPLL",
    "gn:name":"Sekibas",
    "gn:population":0,
    "gn:timezone":"Asia/Kathmandu",
    "iso:country":"NP",
    "wof:name":"Sekibas",
    "wof:placetype":"locality"
},
  "geometry": {"coordinates":[83.73449000000002,27.83897],"type":"Point"}
}