{
  "type": "Feature",
  "properties": {
    "gn:admin1_code":"CR",
    "gn:admin2_code":"11",
    "gn:admin3_code":"31",
    "gn:admin4_code":"310033",
    "gn:asciiname":"Lekpanrang",
    "gn:country_code":"NP",
    "gn:dem":778,
    "gn:feature_class":"P",
    "gn:feature_code":"PPLL",
    "gn:name":"Lekpanrang",
    "gn:population":0,
    "gn:timezone":"Asia/Kathmandu",
    "iso:country":"NP",
    "wof:name":"Lekpanrang",
    "wof:placetype":"locality"
},
  "geometry": {"coordinates":[85.07796,27.50727],"type":"Point"}
}