{
  "type": "Feature",
  "properties": {
    "gn:admin1_code":"WR",
    "gn:admin2_code":"3",
    "gn:admin3_code":"43",
    "gn:admin4_code":"430011",
    "gn:asciiname":"Lambela",
    "gn:country_code":"NP",
    "gn:dem":1699,
    "gn:feature_class":"P",
    "gn:feature_code":"PPLL",
    "gn:name":"Lambela",
    "gn:population":0,
    "gn:timezone":"Asia/Kathmandu",
    "iso:country":"NP",
    "wof:name":"Lambela",
    "wof:placetype":"locality"
},
  "geometry": {"coordinates":[83.40430000000001,28.41145],"type":"Point"}
}