{
  "type": "Feature",
  "properties": {
    "gn:admin1_code":"00",
    "gn:asciiname":"Bhartabas",
    "gn:country_code":"NP",
    "gn:dem":181,
    "gn:feature_class":"P",
    "gn:feature_code":"PPL",
    "gn:name":"Bhart\u0101b\u0101s",
    "gn:population":0,
    "gn:timezone":"Asia/Kathmandu",
    "iso:country":"NP",
    "wof:name":"Bhartabas",
    "wof:placetype":"locality"
},
  "geometry": {"coordinates":[83.11478000000002,27.75674],"type":"Point"}
}