{
  "type": "Feature",
  "properties": {
    "gn:admin1_code":"CR",
    "gn:admin2_code":"5",
    "gn:admin3_code":"20",
    "gn:admin4_code":"200007",
    "gn:asciiname":"Thakuritar",
    "gn:country_code":"NP",
    "gn:dem":428,
    "gn:feature_class":"P",
    "gn:feature_code":"PPLL",
    "gn:name":"Thakuritar",
    "gn:population":0,
    "gn:timezone":"Asia/Kathmandu",
    "iso:country":"NP",
    "wof:name":"Thakuritar",
    "wof:placetype":"locality"
},
  "geometry": {"coordinates":[86.03686,27.14052],"type":"Point"}
}