{
  "type": "Feature",
  "properties": {
    "gn:admin1_code":"CR",
    "gn:admin2_code":"5",
    "gn:admin3_code":"22.0",
    "gn:admin4_code":"220031.0",
    "gn:asciiname":"Bulungsi",
    "gn:country_code":"NP",
    "gn:dem":1901,
    "gn:feature_class":"P",
    "gn:feature_code":"PPLL",
    "gn:name":"Bulungsi",
    "gn:population":0,
    "gn:timezone":"Asia/Kathmandu",
    "iso:country":"NP",
    "wof:name":"Bulungsi",
    "wof:placetype":"locality"
},
  "geometry": {"coordinates":[86.16254000000001,27.76985],"type":"Point"}
}