{
  "type": "Feature",
  "properties": {
    "gn:admin1_code":"00",
    "gn:asciiname":"Manthala",
    "gn:country_code":"NP",
    "gn:dem":1731,
    "gn:feature_class":"P",
    "gn:feature_code":"PPL",
    "gn:name":"Manthal\u0101",
    "gn:population":0,
    "gn:timezone":"Asia/Kathmandu",
    "iso:country":"NP",
    "wof:name":"Manthala",
    "wof:placetype":"locality"
},
  "geometry": {"coordinates":[86.18498000000002,27.76644000000001],"type":"Point"}
}