{
  "type": "Feature",
  "properties": {
    "gn:admin1_code":"ER",
    "gn:admin2_code":"13.0",
    "gn:admin3_code":"14.0",
    "gn:admin4_code":"140020.0",
    "gn:asciiname":"Ratmate",
    "gn:country_code":"NP",
    "gn:dem":951,
    "gn:feature_class":"P",
    "gn:feature_code":"PPLL",
    "gn:name":"Ratmate",
    "gn:population":0,
    "gn:timezone":"Asia/Kathmandu",
    "iso:country":"NP",
    "wof:name":"Ratmate",
    "wof:placetype":"locality"
},
  "geometry": {"coordinates":[86.69239,27.02799000000001],"type":"Point"}
}