{
  "type": "Feature",
  "properties": {
    "gn:admin1_code":"00",
    "gn:asciiname":"Jarankha",
    "gn:country_code":"NP",
    "gn:dem":1373,
    "gn:feature_class":"P",
    "gn:feature_code":"PPL",
    "gn:name":"Jara\u1e45kh\u0101",
    "gn:population":0,
    "gn:timezone":"Asia/Kathmandu",
    "iso:country":"NP",
    "wof:name":"Jarankha",
    "wof:placetype":"locality"
},
  "geometry": {"coordinates":[86.81186,27.3378],"type":"Point"}
}