{
  "type": "Feature",
  "properties": {
    "gn:admin1_code":"MR",
    "gn:admin2_code":"12",
    "gn:admin3_code":"53",
    "gn:admin4_code":"530028",
    "gn:asciiname":"Phalleghar",
    "gn:country_code":"NP",
    "gn:dem":1688,
    "gn:feature_class":"P",
    "gn:feature_code":"PPLL",
    "gn:name":"Phalleghar",
    "gn:population":0,
    "gn:timezone":"Asia/Kathmandu",
    "iso:country":"NP",
    "wof:name":"Phalleghar",
    "wof:placetype":"locality"
},
  "geometry": {"coordinates":[82.55835999999999,28.36103],"type":"Point"}
}