{
  "type": "Feature",
  "properties": {
    "gn:admin1_code":"00",
    "gn:asciiname":"Totibari",
    "gn:country_code":"NP",
    "gn:dem":392,
    "gn:feature_class":"P",
    "gn:feature_code":"PPL",
    "gn:name":"Toti\u0307\u0304b\u0101ri\u0307\u0304",
    "gn:population":0,
    "gn:timezone":"Asia/Kathmandu",
    "iso:country":"NP",
    "name:und_x_variant":[
        "Toti\u0307\u0304b\u0101ri\u0307\u0304",
        "Tot\u012bb\u0101r\u012b"
    ],
    "wof:name":"Totibari",
    "wof:placetype":"locality"
},
  "geometry": {"coordinates":[85.35781999999998,27.30056],"type":"Point"}
}