{
  "type": "Feature",
  "properties": {
    "gn:admin1_code":"ER",
    "gn:admin2_code":"13.0",
    "gn:admin3_code":"14.0",
    "gn:admin4_code":"140017.0",
    "gn:asciiname":"Sisaghari",
    "gn:country_code":"NP",
    "gn:dem":221,
    "gn:feature_class":"P",
    "gn:feature_code":"PPLL",
    "gn:name":"Sisaghari",
    "gn:population":0,
    "gn:timezone":"Asia/Kathmandu",
    "iso:country":"NP",
    "wof:name":"Sisaghari",
    "wof:placetype":"locality"
},
  "geometry": {"coordinates":[86.40168,26.96841],"type":"Point"}
}