{
  "type": "Feature",
  "properties": {
    "gn:admin1_code":"ER",
    "gn:admin2_code":"13.0",
    "gn:admin3_code":"14.0",
    "gn:admin4_code":"140007.0",
    "gn:asciiname":"Thanpokhari",
    "gn:country_code":"NP",
    "gn:dem":137,
    "gn:feature_class":"P",
    "gn:feature_code":"PPLL",
    "gn:name":"Thanpokhari",
    "gn:population":0,
    "gn:timezone":"Asia/Kathmandu",
    "iso:country":"NP",
    "wof:name":"Thanpokhari",
    "wof:placetype":"locality"
},
  "geometry": {"coordinates":[86.87047,26.78974],"type":"Point"}
}