{
  "type": "Feature",
  "properties": {
    "gn:admin1_code":"FR",
    "gn:admin2_code":"14",
    "gn:admin3_code":"71.0",
    "gn:admin4_code":"710008.0",
    "gn:asciiname":"Bisnu Kantipur",
    "gn:country_code":"NP",
    "gn:dem":147,
    "gn:feature_class":"P",
    "gn:feature_code":"PPLL",
    "gn:name":"Bisnu Kantipur",
    "gn:population":0,
    "gn:timezone":"Asia/Kathmandu",
    "iso:country":"NP",
    "wof:name":"Bisnu Kantipur",
    "wof:placetype":"locality"
},
  "geometry": {"coordinates":[81.06963,28.45469000000001],"type":"Point"}
}