{
  "type": "Feature",
  "properties": {
    "gn:admin1_code":"CR",
    "gn:admin2_code":"5",
    "gn:admin3_code":"18",
    "gn:admin4_code":"180053",
    "gn:asciiname":"Parsa Dewad",
    "gn:country_code":"NP",
    "gn:dem":90,
    "gn:feature_class":"P",
    "gn:feature_code":"PPLL",
    "gn:name":"Parsa Dewad",
    "gn:population":0,
    "gn:timezone":"Asia/Kathmandu",
    "iso:country":"NP",
    "wof:name":"Parsa Dewad",
    "wof:placetype":"locality"
},
  "geometry": {"coordinates":[85.75491,26.82605],"type":"Point"}
}