{
  "type": "Feature",
  "properties": {
    "gn:admin1_code":"ER",
    "gn:admin2_code":"10",
    "gn:admin3_code":"3.0",
    "gn:admin4_code":"30019.0",
    "gn:asciiname":"Dhaje",
    "gn:country_code":"NP",
    "gn:dem":1993,
    "gn:feature_class":"P",
    "gn:feature_code":"PPLL",
    "gn:name":"Dhaje",
    "gn:population":0,
    "gn:timezone":"Asia/Kathmandu",
    "iso:country":"NP",
    "wof:name":"Dhaje",
    "wof:placetype":"locality"
},
  "geometry": {"coordinates":[88.03893000000002,27.00297],"type":"Point"}
}