{
  "type": "Feature",
  "properties": {
    "gn:admin1_code":"CR",
    "gn:admin2_code":"1",
    "gn:admin3_code":"24.0",
    "gn:admin4_code":"240061.0",
    "gn:asciiname":"Kilpu Adhikaritol",
    "gn:country_code":"NP",
    "gn:dem":1203,
    "gn:feature_class":"P",
    "gn:feature_code":"PPLL",
    "gn:name":"Kilpu Adhikaritol",
    "gn:population":0,
    "gn:timezone":"Asia/Kathmandu",
    "iso:country":"NP",
    "wof:name":"Kilpu Adhikaritol",
    "wof:placetype":"locality"
},
  "geometry": {"coordinates":[85.86194,27.60013],"type":"Point"}
}