{
  "type": "Feature",
  "properties": {
    "gn:admin1_code":"CR",
    "gn:admin2_code":"1",
    "gn:admin3_code":"24.0",
    "gn:admin4_code":"240027.0",
    "gn:asciiname":"Kyamunchaur",
    "gn:country_code":"NP",
    "gn:dem":878,
    "gn:feature_class":"P",
    "gn:feature_code":"PPLL",
    "gn:name":"Kyamunchaur",
    "gn:population":0,
    "gn:timezone":"Asia/Kathmandu",
    "iso:country":"NP",
    "wof:name":"Kyamunchaur",
    "wof:placetype":"locality"
},
  "geometry": {"coordinates":[85.72955,27.62152],"type":"Point"}
}