{
  "type": "Feature",
  "properties": {
    "gn:admin1_code":"ER",
    "gn:admin2_code":"7",
    "gn:admin3_code":"10.0",
    "gn:admin4_code":"100037.0",
    "gn:asciiname":"Bhotegaun",
    "gn:country_code":"NP",
    "gn:dem":1617,
    "gn:feature_class":"P",
    "gn:feature_code":"PPLL",
    "gn:name":"Bhotegaun",
    "gn:population":0,
    "gn:timezone":"Asia/Kathmandu",
    "iso:country":"NP",
    "wof:name":"Bhotegaun",
    "wof:placetype":"locality"
},
  "geometry": {"coordinates":[87.0401,27.37329],"type":"Point"}
}