{
  "type": "Feature",
  "properties": {
    "gn:admin1_code":"FR",
    "gn:admin2_code":"14",
    "gn:admin3_code":"69.0",
    "gn:admin4_code":"690015.0",
    "gn:asciiname":"Banskatiya",
    "gn:country_code":"NP",
    "gn:dem":985,
    "gn:feature_class":"P",
    "gn:feature_code":"PPLL",
    "gn:name":"Banskatiya",
    "gn:population":0,
    "gn:timezone":"Asia/Kathmandu",
    "iso:country":"NP",
    "wof:name":"Banskatiya",
    "wof:placetype":"locality"
},
  "geometry": {"coordinates":[81.19413,29.27557],"type":"Point"}
}