{
  "type": "Feature",
  "properties": {
    "gn:admin1_code":"FR",
    "gn:admin2_code":"14",
    "gn:admin3_code":"70.0",
    "gn:admin4_code":"700027.0",
    "gn:asciiname":"Lotani",
    "gn:country_code":"NP",
    "gn:dem":853,
    "gn:feature_class":"P",
    "gn:feature_code":"PPLL",
    "gn:name":"Lotani",
    "gn:population":0,
    "gn:timezone":"Asia/Kathmandu",
    "iso:country":"NP",
    "wof:name":"Lotani",
    "wof:placetype":"locality"
},
  "geometry": {"coordinates":[81.05956999999999,28.98734],"type":"Point"}
}