{
  "type": "Feature",
  "properties": {
    "gn:admin1_code":"CR",
    "gn:admin2_code":"5",
    "gn:admin3_code":"18",
    "gn:admin4_code":"180017",
    "gn:asciiname":"Madai",
    "gn:country_code":"NP",
    "gn:dem":72,
    "gn:feature_class":"P",
    "gn:feature_code":"PPLL",
    "gn:name":"Madai",
    "gn:population":0,
    "gn:timezone":"Asia/Kathmandu",
    "iso:country":"NP",
    "wof:name":"Madai",
    "wof:placetype":"locality"
},
  "geometry": {"coordinates":[85.81099,26.70298],"type":"Point"}
}