{
  "type": "Feature",
  "properties": {
    "gn:admin1_code":"MR",
    "gn:admin2_code":"2.0",
    "gn:admin3_code":"59.0",
    "gn:admin4_code":"590004.0",
    "gn:asciiname":"Pilka",
    "gn:country_code":"NP",
    "gn:dem":1062,
    "gn:feature_class":"P",
    "gn:feature_code":"PPLL",
    "gn:name":"Pilka",
    "gn:population":0,
    "gn:timezone":"Asia/Kathmandu",
    "iso:country":"NP",
    "wof:name":"Pilka",
    "wof:placetype":"locality"
},
  "geometry": {"coordinates":[81.97559,28.56766],"type":"Point"}
}