{
  "type": "Feature",
  "properties": {
    "gn:admin1_code":"CR",
    "gn:admin2_code":"1",
    "gn:admin3_code":"30.0",
    "gn:admin4_code":"300001.0",
    "gn:asciiname":"Hansepasal",
    "gn:country_code":"NP",
    "gn:dem":516,
    "gn:feature_class":"P",
    "gn:feature_code":"PPLL",
    "gn:name":"Hansepasal",
    "gn:population":0,
    "gn:timezone":"Asia/Kathmandu",
    "iso:country":"NP",
    "wof:name":"Hansepasal",
    "wof:placetype":"locality"
},
  "geometry": {"coordinates":[84.85495999999998,28.00035],"type":"Point"}
}