{
  "type": "Feature",
  "properties": {
    "gn:admin1_code":"ER",
    "gn:admin2_code":"7.0",
    "gn:admin3_code":"6.0",
    "gn:admin4_code":"60040.0",
    "gn:asciiname":"Laukahi",
    "gn:country_code":"NP",
    "gn:dem":85,
    "gn:feature_class":"P",
    "gn:feature_code":"PPLL",
    "gn:name":"Laukahi",
    "gn:population":0,
    "gn:timezone":"Asia/Kathmandu",
    "iso:country":"NP",
    "name:bih_x_preferred":[
        "\u0932\u094c\u0915\u0939\u0940"
    ],
    "name:ceb_x_preferred":[
        "Laukahi"
    ],
    "name:fra_x_preferred":[
        "Laukahi"
    ],
    "name:mai_x_preferred":[
        "\u0932\u094c\u0915\u0939\u0940"
    ],
    "name:msa_x_preferred":[
        "Laukahi"
    ],
    "name:nep_x_preferred":[
        "\u0932\u094c\u0915\u0939\u0940"
    ],
    "name:new_x_preferred":[
        "\u0932\u094c\u0915\u093e\u0939\u0940"
    ],
    "name:pol_x_preferred":[
        "Laukahi"
    ],
    "wof:name":"Laukahi",
    "wof:placetype":"locality"
},
  "geometry": {"coordinates":[87.06635,26.60458],"type":"Point"}
}