{
  "type": "Feature",
  "properties": {
    "iso:country":"NP",
    "name:unk_x_variant":[
        "Mayangdi"
    ],
    "qs:gn_country":"NP",
    "qs:gn_fcode":"ADM3",
    "qs:gn_pop":117417,
    "qs:name":"Myagdi",
    "qs:name_adm0":"Nepal",
    "qs:name_adm1":"Pashchimanchal",
    "qs:photos":7,
    "qs:photos_1k":1,
    "qs:photos_9k":4,
    "qs:photos_9r":6,
    "qs:photos_all":805,
    "qs:photos_sr":1,
    "qs:placetype":"LocalAdmin",
    "qs:pop_sr":"9",
    "qs:woe_adm0":23424911,
    "wof:name":"Myagdi",
    "wof:placetype":"localadmin",
    "wof:population":117417
},
  "geometry": {"coordinates":[83.33333,28.58333],"type":"Point"}
}