{
  "type": "Feature",
  "properties": {
    "gn:admin1_code":"FR",
    "gn:admin2_code":"14.0",
    "gn:admin3_code":"67.0",
    "gn:admin4_code":"670016.0",
    "gn:asciiname":"Dudhekhada",
    "gn:country_code":"NP",
    "gn:dem":2917,
    "gn:feature_class":"P",
    "gn:feature_code":"PPLL",
    "gn:name":"Dudhekhada",
    "gn:population":0,
    "gn:timezone":"Asia/Kathmandu",
    "iso:country":"NP",
    "wof:name":"Dudhekhada",
    "wof:placetype":"locality"
},
  "geometry": {"coordinates":[81.77013000000002,29.46118],"type":"Point"}
}