{
  "type": "Feature",
  "properties": {
    "gn:admin1_code":"CR",
    "gn:admin2_code":"1",
    "gn:admin3_code":"29",
    "gn:admin4_code":"290011",
    "gn:asciiname":"Peri",
    "gn:country_code":"NP",
    "gn:dem":6053,
    "gn:feature_class":"P",
    "gn:feature_code":"PPLL",
    "gn:name":"Peri",
    "gn:population":0,
    "gn:timezone":"Asia/Kathmandu",
    "iso:country":"NP",
    "name:ara_x_preferred":[
        "\u062d\u0648\u0631\u064a\u0629"
    ],
    "name:bak_x_preferred":[
        "\u0411\u04d9\u0440\u0435\u0439"
    ],
    "name:ceb_x_preferred":[
        "Pari"
    ],
    "name:deu_x_preferred":[
        "Pari"
    ],
    "name:fas_x_preferred":[
        "\u067e\u0631\u06cc"
    ],
    "name:fra_x_preferred":[
        "P\u00e9ri"
    ],
    "name:ind_x_preferred":[
        "Peri"
    ],
    "name:kaz_x_preferred":[
        "\u041f\u0435\u0440\u0456"
    ],
    "name:nor_x_preferred":[
        "Peri"
    ],
    "name:rus_x_preferred":[
        "\u041f\u0435\u0440\u0438"
    ],
    "name:spa_x_preferred":[
        "Peri"
    ],
    "name:swe_x_preferred":[
        "Peri"
    ],
    "name:tgl_x_preferred":[
        "Pari"
    ],
    "name:ukr_x_preferred":[
        "\u041f\u0435\u0440\u0456"
    ],
    "name:uzb_x_preferred":[
        "Pari"
    ],
    "wof:name":"Peri",
    "wof:placetype":"locality"
},
  "geometry": {"coordinates":[85.72111,28.35559000000001],"type":"Point"}
}