{
  "type": "Feature",
  "properties": {
    "gn:admin1_code":"CR",
    "gn:admin2_code":"11",
    "gn:admin3_code":"34",
    "gn:admin4_code":"340009",
    "gn:asciiname":"Musaili",
    "gn:country_code":"NP",
    "gn:dem":105,
    "gn:feature_class":"P",
    "gn:feature_code":"PPLL",
    "gn:name":"Musaili",
    "gn:population":0,
    "gn:timezone":"Asia/Kathmandu",
    "iso:country":"NP",
    "wof:name":"Musaili",
    "wof:placetype":"locality"
},
  "geometry": {"coordinates":[84.90590999999998,27.12382],"type":"Point"}
}