{
  "type": "Feature",
  "properties": {
    "gn:admin1_code":"CR",
    "gn:admin2_code":"11",
    "gn:admin3_code":"31",
    "gn:admin4_code":"310020.0",
    "gn:asciiname":"Saraswati",
    "gn:country_code":"NP",
    "gn:dem":454,
    "gn:feature_class":"P",
    "gn:feature_code":"PPLL",
    "gn:name":"Saraswati",
    "gn:population":0,
    "gn:timezone":"Asia/Kathmandu",
    "iso:country":"NP",
    "wof:name":"Saraswati",
    "wof:placetype":"locality"
},
  "geometry": {"coordinates":[84.99588,27.44493],"type":"Point"}
}