{
  "type": "Feature",
  "properties": {
    "gn:admin1_code":"MR",
    "gn:admin2_code":"12",
    "gn:admin3_code":"52",
    "gn:admin4_code":"520024",
    "gn:asciiname":"Rumbang",
    "gn:country_code":"NP",
    "gn:dem":1626,
    "gn:feature_class":"P",
    "gn:feature_code":"PPLL",
    "gn:name":"Rumbang",
    "gn:population":0,
    "gn:timezone":"Asia/Kathmandu",
    "iso:country":"NP",
    "wof:name":"Rumbang",
    "wof:placetype":"locality"
},
  "geometry": {"coordinates":[82.93114,28.24546],"type":"Point"}
}