{
  "type": "Feature",
  "properties": {
    "gn:admin1_code":"ER",
    "gn:admin2_code":"7",
    "gn:admin3_code":"10.0",
    "gn:admin4_code":"100038.0",
    "gn:asciiname":"Kulung",
    "gn:country_code":"NP",
    "gn:dem":877,
    "gn:feature_class":"P",
    "gn:feature_code":"PPLL",
    "gn:name":"Kulung",
    "gn:population":0,
    "gn:timezone":"Asia/Kathmandu",
    "iso:country":"NP",
    "wof:name":"Kulung",
    "wof:placetype":"locality"
},
  "geometry": {"coordinates":[87.11490000000001,27.4381],"type":"Point"}
}