{
  "type": "Feature",
  "properties": {
    "gn:admin1_code":"FR",
    "gn:admin2_code":"14.0",
    "gn:admin3_code":"67.0",
    "gn:admin4_code":"670019.0",
    "gn:asciiname":"Bhirgaun",
    "gn:country_code":"NP",
    "gn:dem":1847,
    "gn:feature_class":"P",
    "gn:feature_code":"PPLL",
    "gn:name":"Bhirgaun",
    "gn:population":0,
    "gn:timezone":"Asia/Kathmandu",
    "iso:country":"NP",
    "name:bih_x_preferred":[
        "\u092d\u093f\u0930\u0917\u093e\u0909\u0901"
    ],
    "name:ceb_x_preferred":[
        "Bhirgaun"
    ],
    "name:mai_x_preferred":[
        "\u092d\u093f\u0930\u0917\u093e\u0909\u0901"
    ],
    "name:nep_x_preferred":[
        "\u092d\u093f\u0930\u0917\u093e\u0909\u0901"
    ],
    "name:pol_x_preferred":[
        "Bhirgau"
    ],
    "wof:name":"Bhirgaun",
    "wof:placetype":"locality"
},
  "geometry": {"coordinates":[81.62361,29.52199],"type":"Point"}
}