{
  "type": "Feature",
  "properties": {
    "gn:admin1_code":"MR",
    "gn:admin2_code":"12",
    "gn:admin3_code":"54",
    "gn:admin4_code":"540024",
    "gn:asciiname":"Khamnai",
    "gn:country_code":"NP",
    "gn:dem":1915,
    "gn:feature_class":"P",
    "gn:feature_code":"PPLL",
    "gn:name":"Khamnai",
    "gn:population":0,
    "gn:timezone":"Asia/Kathmandu",
    "iso:country":"NP",
    "wof:name":"Khamnai",
    "wof:placetype":"locality"
},
  "geometry": {"coordinates":[82.62151999999998,28.54121],"type":"Point"}
}