{
  "type": "Feature",
  "properties": {
    "gn:admin1_code":"ER",
    "gn:admin2_code":"13",
    "gn:admin3_code":"11",
    "gn:admin4_code":"110018.0",
    "gn:asciiname":"Phang",
    "gn:country_code":"NP",
    "gn:dem":4370,
    "gn:feature_class":"P",
    "gn:feature_code":"PPLL",
    "gn:name":"Phang",
    "gn:population":0,
    "gn:timezone":"Asia/Kathmandu",
    "iso:country":"NP",
    "wof:name":"Phang",
    "wof:placetype":"locality"
},
  "geometry": {"coordinates":[86.71505999999999,27.91702],"type":"Point"}
}