{
  "type": "Feature",
  "properties": {
    "gn:admin1_code":"MR",
    "gn:admin2_code":"12",
    "gn:admin3_code":"55",
    "gn:admin4_code":"550002",
    "gn:asciiname":"Kholakhal",
    "gn:country_code":"NP",
    "gn:dem":1780,
    "gn:feature_class":"P",
    "gn:feature_code":"PPLL",
    "gn:name":"Kholakhal",
    "gn:population":0,
    "gn:timezone":"Asia/Kathmandu",
    "iso:country":"NP",
    "wof:name":"Kholakhal",
    "wof:placetype":"locality"
},
  "geometry": {"coordinates":[82.38887,28.47167],"type":"Point"}
}