{
  "type": "Feature",
  "properties": {
    "gn:admin1_code":"00",
    "gn:asciiname":"Sugarkhal",
    "gn:country_code":"NP",
    "gn:dem":1375,
    "gn:feature_class":"P",
    "gn:feature_code":"PPL",
    "gn:name":"Sugarkh\u0101l",
    "gn:population":0,
    "gn:timezone":"Asia/Kathmandu",
    "iso:country":"NP",
    "name:ceb_x_preferred":[
        "Sugarkhal"
    ],
    "name:mai_x_preferred":[
        "\u0938\u0941\u0901\u0917\u0941\u0930\u0916\u093e\u0932"
    ],
    "name:msa_x_preferred":[
        "Sugarkhal"
    ],
    "name:nep_x_preferred":[
        "\u0938\u0941\u0901\u0917\u0941\u0930\u0916\u093e\u0932"
    ],
    "name:new_x_preferred":[
        "\u0938\u0941\u0901\u0917\u0930\u0916\u093e\u0932"
    ],
    "name:pol_x_preferred":[
        "Sugarkhal"
    ],
    "name:und_x_variant":[
        "Sungarkh\u0101l",
        "Sugarkh\u0101l"
    ],
    "wof:name":"Sugarkhal",
    "wof:placetype":"locality"
},
  "geometry": {"coordinates":[81.14681,28.74229],"type":"Point"}
}