{
  "type": "Feature",
  "properties": {
    "gn:admin1_code":"WR",
    "gn:admin2_code":"4",
    "gn:admin3_code":"36.0",
    "gn:admin4_code":"360043.0",
    "gn:asciiname":"Devithan",
    "gn:country_code":"NP",
    "gn:dem":883,
    "gn:feature_class":"P",
    "gn:feature_code":"PPLL",
    "gn:name":"Devithan",
    "gn:population":0,
    "gn:timezone":"Asia/Kathmandu",
    "iso:country":"NP",
    "wof:name":"Devithan",
    "wof:placetype":"locality"
},
  "geometry": {"coordinates":[84.70224,28.04808],"type":"Point"}
}