{
  "type": "Feature",
  "properties": {
    "gn:admin1_code":"MR",
    "gn:admin2_code":"12",
    "gn:admin3_code":"55",
    "gn:admin4_code":"550017.0",
    "gn:asciiname":"Jyamire",
    "gn:country_code":"NP",
    "gn:dem":955,
    "gn:feature_class":"P",
    "gn:feature_code":"PPLL",
    "gn:name":"Jyamire",
    "gn:population":0,
    "gn:timezone":"Asia/Kathmandu",
    "iso:country":"NP",
    "name:fra_x_preferred":[
        "Jyamire"
    ],
    "name:new_x_preferred":[
        "\u091c\u094d\u092f\u093e\u092e\u093f\u0930\u0947"
    ],
    "name:pol_x_preferred":[
        "Jyamire"
    ],
    "wof:name":"Jyamire",
    "wof:placetype":"locality"
},
  "geometry": {"coordinates":[81.86440999999998,28.3271],"type":"Point"}
}