{
  "type": "Feature",
  "properties": {
    "gn:admin1_code":"MR",
    "gn:admin2_code":"6",
    "gn:admin3_code":"63.0",
    "gn:admin4_code":"630025.0",
    "gn:asciiname":"Matachaur",
    "gn:country_code":"NP",
    "gn:dem":2721,
    "gn:feature_class":"P",
    "gn:feature_code":"PPLL",
    "gn:name":"Matachaur",
    "gn:population":0,
    "gn:timezone":"Asia/Kathmandu",
    "iso:country":"NP",
    "wof:name":"Matachaur",
    "wof:placetype":"locality"
},
  "geometry": {"coordinates":[82.35711999999999,29.29667],"type":"Point"}
}