{
  "type": "Feature",
  "properties": {
    "gn:admin1_code":"WR",
    "gn:admin2_code":"8",
    "gn:admin3_code":"47",
    "gn:admin4_code":"470020",
    "gn:asciiname":"Dansingkot",
    "gn:country_code":"NP",
    "gn:dem":827,
    "gn:feature_class":"P",
    "gn:feature_code":"PPLL",
    "gn:name":"Dansingkot",
    "gn:population":0,
    "gn:timezone":"Asia/Kathmandu",
    "iso:country":"NP",
    "wof:name":"Dansingkot",
    "wof:placetype":"locality"
},
  "geometry": {"coordinates":[83.55103000000003,27.71901],"type":"Point"}
}