{
  "type": "Feature",
  "properties": {
    "gn:admin1_code":"CR",
    "gn:admin2_code":"11",
    "gn:admin3_code":"31",
    "gn:admin4_code":"310022",
    "gn:asciiname":"Sallegaun",
    "gn:country_code":"NP",
    "gn:dem":1775,
    "gn:feature_class":"P",
    "gn:feature_code":"PPLL",
    "gn:name":"Sallegaun",
    "gn:population":0,
    "gn:timezone":"Asia/Kathmandu",
    "iso:country":"NP",
    "wof:name":"Sallegaun",
    "wof:placetype":"locality"
},
  "geometry": {"coordinates":[85.20574999999999,27.50242],"type":"Point"}
}