{
  "type": "Feature",
  "properties": {
    "gn:admin1_code":"00",
    "gn:asciiname":"Pankhun",
    "gn:country_code":"NP",
    "gn:dem":1946,
    "gn:feature_class":"P",
    "gn:feature_code":"PPL",
    "gn:name":"P\u0101\u1e45khu\u1e45",
    "gn:population":0,
    "gn:timezone":"Asia/Kathmandu",
    "iso:country":"NP",
    "wof:name":"Pankhun",
    "wof:placetype":"locality"
},
  "geometry": {"coordinates":[86.99328,27.26586],"type":"Point"}
}