{
  "type": "Feature",
  "properties": {
    "gn:admin1_code":"MR",
    "gn:admin2_code":"6",
    "gn:admin3_code":"62.0",
    "gn:admin4_code":"620010.0",
    "gn:asciiname":"Karailchaur",
    "gn:country_code":"NP",
    "gn:dem":2597,
    "gn:feature_class":"P",
    "gn:feature_code":"PPLL",
    "gn:name":"Karailchaur",
    "gn:population":0,
    "gn:timezone":"Asia/Kathmandu",
    "iso:country":"NP",
    "wof:name":"Karailchaur",
    "wof:placetype":"locality"
},
  "geometry": {"coordinates":[82.72216999999998,29.05421],"type":"Point"}
}