{
  "type": "Feature",
  "properties": {
    "gn:admin1_code":"ER",
    "gn:admin2_code":"7",
    "gn:admin3_code":"10.0",
    "gn:admin4_code":"100020.0",
    "gn:asciiname":"Radun",
    "gn:country_code":"NP",
    "gn:dem":1593,
    "gn:feature_class":"P",
    "gn:feature_code":"PPLL",
    "gn:name":"Radun",
    "gn:population":0,
    "gn:timezone":"Asia/Kathmandu",
    "iso:country":"NP",
    "name:ceb_x_preferred":[
        "Radun"
    ],
    "name:deu_x_preferred":[
        "Radun"
    ],
    "name:pol_x_preferred":[
        "Radu\u0144"
    ],
    "name:rus_x_preferred":[
        "\u0420\u0430\u0434\u0443\u043d\u044c"
    ],
    "name:srp_x_preferred":[
        "\u0420\u0430\u0434\u0443\u045a"
    ],
    "name:swe_x_preferred":[
        "Radun"
    ],
    "name:ukr_x_preferred":[
        "\u0420\u0430\u0434\u0443\u043d\u044c"
    ],
    "wof:name":"Radun",
    "wof:placetype":"locality"
},
  "geometry": {"coordinates":[87.06208000000002,27.01656],"type":"Point"}
}