{
  "type": "Feature",
  "properties": {
    "gn:admin1_code":"ER",
    "gn:admin2_code":"10",
    "gn:admin3_code":"3.0",
    "gn:admin4_code":"30023.0",
    "gn:asciiname":"Malteni",
    "gn:country_code":"NP",
    "gn:dem":1512,
    "gn:feature_class":"P",
    "gn:feature_code":"PPLL",
    "gn:name":"Malteni",
    "gn:population":0,
    "gn:timezone":"Asia/Kathmandu",
    "iso:country":"NP",
    "wof:name":"Malteni",
    "wof:placetype":"locality"
},
  "geometry": {"coordinates":[87.70245,26.92286],"type":"Point"}
}