{
  "type": "Feature",
  "properties": {
    "gn:admin1_code":"FR",
    "gn:admin2_code":"9",
    "gn:admin3_code":"74",
    "gn:admin4_code":"740016",
    "gn:asciiname":"Dhan",
    "gn:country_code":"NP",
    "gn:dem":1373,
    "gn:feature_class":"P",
    "gn:feature_code":"PPLL",
    "gn:name":"Dhan",
    "gn:population":0,
    "gn:timezone":"Asia/Kathmandu",
    "iso:country":"NP",
    "wof:name":"Dhan",
    "wof:placetype":"locality"
},
  "geometry": {"coordinates":[80.61171999999998,29.63505],"type":"Point"}
}