{
  "type": "Feature",
  "properties": {
    "gn:admin1_code":"FR",
    "gn:admin2_code":"9",
    "gn:admin3_code":"74",
    "gn:admin4_code":"740016",
    "gn:asciiname":"Khetagaun",
    "gn:country_code":"NP",
    "gn:dem":1401,
    "gn:feature_class":"P",
    "gn:feature_code":"PPLL",
    "gn:name":"Khetagaun",
    "gn:population":0,
    "gn:timezone":"Asia/Kathmandu",
    "iso:country":"NP",
    "wof:name":"Khetagaun",
    "wof:placetype":"locality"
},
  "geometry": {"coordinates":[80.59657,29.65568],"type":"Point"}
}