{
  "type": "Feature",
  "properties": {
    "gn:admin1_code":"WR",
    "gn:admin2_code":"8",
    "gn:admin3_code":"47",
    "gn:admin4_code":"470044",
    "gn:asciiname":"Tinpiple",
    "gn:country_code":"NP",
    "gn:dem":959,
    "gn:feature_class":"P",
    "gn:feature_code":"PPLL",
    "gn:name":"Tinpiple",
    "gn:population":0,
    "gn:timezone":"Asia/Kathmandu",
    "iso:country":"NP",
    "wof:name":"Tinpiple",
    "wof:placetype":"locality"
},
  "geometry": {"coordinates":[83.56686999999999,27.81376],"type":"Point"}
}