{
  "type": "Feature",
  "properties": {
    "gn:admin1_code":"CR",
    "gn:admin2_code":"11.0",
    "gn:admin3_code":"33.0",
    "gn:admin4_code":"330079.0",
    "gn:asciiname":"Dhuraha",
    "gn:country_code":"NP",
    "gn:dem":84,
    "gn:feature_class":"P",
    "gn:feature_code":"PPLL",
    "gn:name":"Dhuraha",
    "gn:population":0,
    "gn:timezone":"Asia/Kathmandu",
    "iso:country":"NP",
    "wof:name":"Dhuraha",
    "wof:placetype":"locality"
},
  "geometry": {"coordinates":[85.00999,26.9386],"type":"Point"}
}