{
  "type": "Feature",
  "properties": {
    "gn:admin1_code":"CR",
    "gn:admin2_code":"1",
    "gn:admin3_code":"24.0",
    "gn:admin4_code":"240001.0",
    "gn:asciiname":"Jaldhunga",
    "gn:country_code":"NP",
    "gn:dem":976,
    "gn:feature_class":"P",
    "gn:feature_code":"PPLL",
    "gn:name":"Jaldhunga",
    "gn:population":0,
    "gn:timezone":"Asia/Kathmandu",
    "iso:country":"NP",
    "wof:name":"Jaldhunga",
    "wof:placetype":"locality"
},
  "geometry": {"coordinates":[85.59291999999998,27.66901],"type":"Point"}
}