{
  "type": "Feature",
  "properties": {
    "gn:admin1_code":"FR",
    "gn:admin2_code":"14",
    "gn:admin3_code":"69.0",
    "gn:admin4_code":"690060.0",
    "gn:asciiname":"Tosi",
    "gn:country_code":"NP",
    "gn:dem":1314,
    "gn:feature_class":"P",
    "gn:feature_code":"PPLL",
    "gn:name":"Tosi",
    "gn:population":0,
    "gn:timezone":"Asia/Kathmandu",
    "iso:country":"NP",
    "name:ceb_x_preferred":[
        "Tosi"
    ],
    "name:deu_x_preferred":[
        "Tosi"
    ],
    "name:fin_x_preferred":[
        "Tosi"
    ],
    "name:fra_x_preferred":[
        "Tosi"
    ],
    "name:ita_x_preferred":[
        "Tosi"
    ],
    "name:rus_x_preferred":[
        "\u0422\u043e\u0437\u0438"
    ],
    "name:spa_x_preferred":[
        "Tosi"
    ],
    "name:srp_x_preferred":[
        "Tozi"
    ],
    "name:swe_x_preferred":[
        "Tosi"
    ],
    "wof:name":"Tosi",
    "wof:placetype":"locality"
},
  "geometry": {"coordinates":[81.37900999999999,28.98127],"type":"Point"}
}