{
  "type": "Feature",
  "properties": {
    "gn:admin1_code":"00",
    "gn:asciiname":"Sanam",
    "gn:country_code":"NP",
    "gn:dem":3107,
    "gn:feature_class":"P",
    "gn:feature_code":"PPL",
    "gn:name":"S\u0101nam",
    "gn:population":0,
    "gn:timezone":"Asia/Kathmandu",
    "iso:country":"NP",
    "wof:name":"Sanam",
    "wof:placetype":"locality"
},
  "geometry": {"coordinates":[86.89716,27.46157],"type":"Point"}
}