{
  "type": "Feature",
  "properties": {
    "gn:admin1_code":"CR",
    "gn:admin2_code":"1",
    "gn:admin3_code":"23",
    "gn:admin4_code":"230029",
    "gn:asciiname":"Tarkeghyang",
    "gn:country_code":"NP",
    "gn:dem":2628,
    "gn:feature_class":"P",
    "gn:feature_code":"PPLL",
    "gn:name":"Tarkeghyang",
    "gn:population":0,
    "gn:timezone":"Asia/Kathmandu",
    "iso:country":"NP",
    "wof:name":"Tarkeghyang",
    "wof:placetype":"locality"
},
  "geometry": {"coordinates":[85.55663,28.00097],"type":"Point"}
}