{
  "type": "Feature",
  "properties": {
    "gn:admin1_code":"WR",
    "gn:admin2_code":"3",
    "gn:admin3_code":"43",
    "gn:admin4_code":"430025",
    "gn:asciiname":"Sinbang",
    "gn:country_code":"NP",
    "gn:dem":1733,
    "gn:feature_class":"P",
    "gn:feature_code":"PPLL",
    "gn:name":"Sinbang",
    "gn:population":0,
    "gn:timezone":"Asia/Kathmandu",
    "iso:country":"NP",
    "wof:name":"Sinbang",
    "wof:placetype":"locality"
},
  "geometry": {"coordinates":[83.34613,28.50787],"type":"Point"}
}