{
  "type": "Feature",
  "properties": {
    "gn:admin1_code":"MR",
    "gn:admin2_code":"6",
    "gn:admin3_code":"63.0",
    "gn:admin4_code":"630009.0",
    "gn:asciiname":"Gothichaur",
    "gn:country_code":"NP",
    "gn:dem":2888,
    "gn:feature_class":"P",
    "gn:feature_code":"PPLL",
    "gn:name":"Gothichaur",
    "gn:population":0,
    "gn:timezone":"Asia/Kathmandu",
    "iso:country":"NP",
    "name:fra_x_preferred":[
        "Guthichaur"
    ],
    "name:mai_x_preferred":[
        "\u0917\u0941\u0920\u0940\u091a\u094c\u0930"
    ],
    "name:msa_x_preferred":[
        "Gothichaur"
    ],
    "name:nep_x_preferred":[
        "\u0917\u0941\u0920\u0940\u091a\u094c\u0930"
    ],
    "name:new_x_preferred":[
        "\u0917\u094b\u0920\u093f\u091a\u094c\u0930"
    ],
    "name:pol_x_preferred":[
        "Guthichaur"
    ],
    "wof:name":"Gothichaur",
    "wof:placetype":"locality"
},
  "geometry": {"coordinates":[82.28943000000002,29.23398],"type":"Point"}
}