{
  "type": "Feature",
  "properties": {
    "gn:admin1_code":"MR",
    "gn:admin2_code":"12",
    "gn:admin3_code":"53",
    "gn:admin4_code":"530038",
    "gn:asciiname":"Bhalukot",
    "gn:country_code":"NP",
    "gn:dem":2386,
    "gn:feature_class":"P",
    "gn:feature_code":"PPLL",
    "gn:name":"Bhalukot",
    "gn:population":0,
    "gn:timezone":"Asia/Kathmandu",
    "iso:country":"NP",
    "wof:name":"Bhalukot",
    "wof:placetype":"locality"
},
  "geometry": {"coordinates":[82.57734000000001,28.51053],"type":"Point"}
}