{
  "type": "Feature",
  "properties": {
    "gn:admin1_code":"CR",
    "gn:admin2_code":"11",
    "gn:admin3_code":"35.0",
    "gn:admin4_code":"350035.0",
    "gn:asciiname":"Latauli",
    "gn:country_code":"NP",
    "gn:dem":807,
    "gn:feature_class":"P",
    "gn:feature_code":"PPLL",
    "gn:name":"Latauli",
    "gn:population":0,
    "gn:timezone":"Asia/Kathmandu",
    "iso:country":"NP",
    "wof:name":"Latauli",
    "wof:placetype":"locality"
},
  "geometry": {"coordinates":[84.61605,27.73218],"type":"Point"}
}