{
  "type": "Feature",
  "properties": {
    "gn:admin1_code":"CR",
    "gn:admin2_code":"11",
    "gn:admin3_code":"31",
    "gn:admin4_code":"310037",
    "gn:asciiname":"Jirke",
    "gn:country_code":"NP",
    "gn:dem":914,
    "gn:feature_class":"P",
    "gn:feature_code":"PPLL",
    "gn:name":"Jirke",
    "gn:population":0,
    "gn:timezone":"Asia/Kathmandu",
    "iso:country":"NP",
    "wof:name":"Jirke",
    "wof:placetype":"locality"
},
  "geometry": {"coordinates":[84.83176,27.57739],"type":"Point"}
}