{
  "type": "Feature",
  "properties": {
    "gn:admin1_code":"FR",
    "gn:admin2_code":"14",
    "gn:admin3_code":"69.0",
    "gn:admin4_code":"690007.0",
    "gn:asciiname":"Kamal Bajar",
    "gn:country_code":"NP",
    "gn:dem":1935,
    "gn:feature_class":"P",
    "gn:feature_code":"PPLL",
    "gn:name":"Kamal Bajar",
    "gn:population":0,
    "gn:timezone":"Asia/Kathmandu",
    "iso:country":"NP",
    "wof:name":"Kamal Bajar",
    "wof:placetype":"locality"
},
  "geometry": {"coordinates":[81.34159,29.05486],"type":"Point"}
}