{
  "type": "Feature",
  "properties": {
    "gn:admin1_code":"MR",
    "gn:admin2_code":"6",
    "gn:admin3_code":"66.0",
    "gn:admin4_code":"660010.0",
    "gn:asciiname":"Chhote Kad",
    "gn:country_code":"NP",
    "gn:dem":4634,
    "gn:feature_class":"P",
    "gn:feature_code":"PPLL",
    "gn:name":"Chhote Kad",
    "gn:population":0,
    "gn:timezone":"Asia/Kathmandu",
    "iso:country":"NP",
    "wof:name":"Chhote Kad",
    "wof:placetype":"locality"
},
  "geometry": {"coordinates":[81.66809000000001,29.96369],"type":"Point"}
}