{
  "type": "Feature",
  "properties": {
    "gn:admin1_code":"CR",
    "gn:admin2_code":"1",
    "gn:admin3_code":"30.0",
    "gn:admin4_code":"300044.0",
    "gn:asciiname":"Chautara",
    "gn:country_code":"NP",
    "gn:dem":1693,
    "gn:feature_class":"P",
    "gn:feature_code":"PPLL",
    "gn:name":"Chautara",
    "gn:population":0,
    "gn:timezone":"Asia/Kathmandu",
    "iso:country":"NP",
    "wof:name":"Chautara",
    "wof:placetype":"locality"
},
  "geometry": {"coordinates":[85.00456,27.98161],"type":"Point"}
}