{
  "type": "Feature",
  "properties": {
    "gn:admin1_code":"00",
    "gn:asciiname":"Amdada",
    "gn:country_code":"NP",
    "gn:dem":697,
    "gn:feature_class":"P",
    "gn:feature_code":"PPL",
    "gn:name":"\u0100m\u1e0d\u0101\u0303\u1e0d\u0101",
    "gn:population":0,
    "gn:timezone":"Asia/Kathmandu",
    "iso:country":"NP",
    "name:nep_x_preferred":[
        "\u0100m\u1e0d\u0101\u0303\u1e0d\u0101"
    ],
    "wof:name":"Amdada",
    "wof:placetype":"locality"
},
  "geometry": {"coordinates":[84.79092,27.76845],"type":"Point"}
}