{
  "type": "Feature",
  "properties": {
    "gn:admin1_code":"WR",
    "gn:admin2_code":"8",
    "gn:admin3_code":"46.0",
    "gn:admin4_code":"460038.0",
    "gn:asciiname":"Kallabot",
    "gn:country_code":"NP",
    "gn:dem":1162,
    "gn:feature_class":"P",
    "gn:feature_code":"PPLL",
    "gn:name":"Kallabot",
    "gn:population":0,
    "gn:timezone":"Asia/Kathmandu",
    "iso:country":"NP",
    "wof:name":"Kallabot",
    "wof:placetype":"locality"
},
  "geometry": {"coordinates":[83.1301,28.10432],"type":"Point"}
}