{
  "type": "Feature",
  "properties": {
    "gn:admin1_code":"WR",
    "gn:admin2_code":"4.0",
    "gn:admin3_code":"38.0",
    "gn:admin4_code":"380045.0",
    "gn:asciiname":"Bisghare",
    "gn:country_code":"NP",
    "gn:dem":351,
    "gn:feature_class":"P",
    "gn:feature_code":"PPLL",
    "gn:name":"Bisghare",
    "gn:population":0,
    "gn:timezone":"Asia/Kathmandu",
    "iso:country":"NP",
    "wof:name":"Bisghare",
    "wof:placetype":"locality"
},
  "geometry": {"coordinates":[84.26989,27.97219],"type":"Point"}
}