{
  "type": "Feature",
  "properties": {
    "gn:admin1_code":"WR",
    "gn:admin2_code":"4.0",
    "gn:admin3_code":"38.0",
    "gn:admin4_code":"380028.0",
    "gn:asciiname":"Pokhari Bhanjyang",
    "gn:country_code":"NP",
    "gn:dem":872,
    "gn:feature_class":"P",
    "gn:feature_code":"PPLL",
    "gn:name":"Pokhari Bhanjyang",
    "gn:population":0,
    "gn:timezone":"Asia/Kathmandu",
    "iso:country":"NP",
    "name:hin_x_preferred":[
        "\u092a\u094b\u0916\u0930\u0940 \u092d\u091e\u094d\u091c\u094d\u092f\u093e\u0919"
    ],
    "name:mai_x_preferred":[
        "\u092a\u094b\u0916\u0930\u0940 \u092d\u091e\u094d\u091c\u094d\u092f\u093e\u0919"
    ],
    "name:msa_x_preferred":[
        "Pokhari Bhanjyang"
    ],
    "name:nep_x_preferred":[
        "\u092a\u094b\u0916\u0930\u0940 \u092d\u091e\u094d\u091c\u094d\u092f\u093e\u0919"
    ],
    "name:new_x_preferred":[
        "\u092a\u094b\u0916\u0930\u0940 \u092d\u091e\u094d\u091c\u094d\u092f\u093e\u0919"
    ],
    "name:pol_x_preferred":[
        "Pokhari Bhanjyang"
    ],
    "wof:name":"Pokhari Bhanjyang",
    "wof:placetype":"locality"
},
  "geometry": {"coordinates":[83.98868,27.93172],"type":"Point"}
}