{
  "type": "Feature",
  "properties": {
    "gn:admin1_code":"MR",
    "gn:admin2_code":"12",
    "gn:admin3_code":"56.0",
    "gn:admin4_code":"560008.0",
    "gn:asciiname":"Bhojpur",
    "gn:country_code":"NP",
    "gn:dem":576,
    "gn:feature_class":"P",
    "gn:feature_code":"PPLL",
    "gn:name":"Bhojpur",
    "gn:population":0,
    "gn:timezone":"Asia/Kathmandu",
    "iso:country":"NP",
    "name:ara_x_preferred":[
        "\u0628\u0648\u062c \u0628\u0648\u0631"
    ],
    "name:ceb_x_preferred":[
        "Bhojpur"
    ],
    "name:deu_x_preferred":[
        "Bhojpur"
    ],
    "name:fra_x_preferred":[
        "Bhojpur"
    ],
    "name:hin_x_preferred":[
        "\u092d\u094b\u091c\u092a\u0941\u0930"
    ],
    "name:nld_x_preferred":[
        "Bhojpur"
    ],
    "name:swe_x_preferred":[
        "Bhojpur"
    ],
    "name:vie_x_preferred":[
        "Bhojpur"
    ],
    "wof:name":"Bhojpur",
    "wof:placetype":"locality"
},
  "geometry": {"coordinates":[82.29420999999998,28.03465],"type":"Point"}
}