{
  "type": "Feature",
  "properties": {
    "gn:admin1_code":"CR",
    "gn:admin2_code":"1",
    "gn:admin3_code":"24.0",
    "gn:admin4_code":"240075.0",
    "gn:asciiname":"Bhantar",
    "gn:country_code":"NP",
    "gn:dem":1220,
    "gn:feature_class":"P",
    "gn:feature_code":"PPLL",
    "gn:name":"Bhantar",
    "gn:population":0,
    "gn:timezone":"Asia/Kathmandu",
    "iso:country":"NP",
    "wof:name":"Bhantar",
    "wof:placetype":"locality"
},
  "geometry": {"coordinates":[85.54004999999999,27.40956],"type":"Point"}
}