{
  "type": "Feature",
  "properties": {
    "gn:admin1_code":"CR",
    "gn:admin2_code":"5",
    "gn:admin3_code":"21",
    "gn:admin4_code":"210042",
    "gn:asciiname":"Chilaune",
    "gn:country_code":"NP",
    "gn:dem":1268,
    "gn:feature_class":"P",
    "gn:feature_code":"PPLL",
    "gn:name":"Chilaune",
    "gn:population":0,
    "gn:timezone":"Asia/Kathmandu",
    "iso:country":"NP",
    "wof:name":"Chilaune",
    "wof:placetype":"locality"
},
  "geometry": {"coordinates":[86.32384,27.50429],"type":"Point"}
}