{
  "type": "Feature",
  "properties": {
    "gn:admin1_code":"MR",
    "gn:admin2_code":"2",
    "gn:admin3_code":"61.0",
    "gn:admin4_code":"610006.0",
    "gn:asciiname":"Bahunparka",
    "gn:country_code":"NP",
    "gn:dem":1937,
    "gn:feature_class":"P",
    "gn:feature_code":"PPLL",
    "gn:name":"Bahunparka",
    "gn:population":0,
    "gn:timezone":"Asia/Kathmandu",
    "iso:country":"NP",
    "wof:name":"Bahunparka",
    "wof:placetype":"locality"
},
  "geometry": {"coordinates":[81.95129,28.76249],"type":"Point"}
}