{
  "type": "Feature",
  "properties": {
    "gn:admin1_code":"ER",
    "gn:admin2_code":"7",
    "gn:admin3_code":"10.0",
    "gn:admin4_code":"100062.0",
    "gn:asciiname":"Dhunge",
    "gn:country_code":"NP",
    "gn:dem":903,
    "gn:feature_class":"P",
    "gn:feature_code":"PPLL",
    "gn:name":"Dhunge",
    "gn:population":0,
    "gn:timezone":"Asia/Kathmandu",
    "iso:country":"NP",
    "wof:name":"Dhunge",
    "wof:placetype":"locality"
},
  "geometry": {"coordinates":[87.21006,27.13334],"type":"Point"}
}