{
  "type": "Feature",
  "properties": {
    "gn:admin1_code":"CR",
    "gn:admin2_code":"1",
    "gn:admin3_code":"23",
    "gn:admin4_code":"230062",
    "gn:asciiname":"Dhungechhap",
    "gn:country_code":"NP",
    "gn:dem":1392,
    "gn:feature_class":"P",
    "gn:feature_code":"PPLL",
    "gn:name":"Dhungechhap",
    "gn:population":0,
    "gn:timezone":"Asia/Kathmandu",
    "iso:country":"NP",
    "wof:name":"Dhungechhap",
    "wof:placetype":"locality"
},
  "geometry": {"coordinates":[85.51845,27.81591],"type":"Point"}
}