{
  "type": "Feature",
  "properties": {
    "gn:admin1_code":"FR",
    "gn:admin2_code":"14",
    "gn:admin3_code":"70.0",
    "gn:admin4_code":"700017.0",
    "gn:asciiname":"Nagada",
    "gn:country_code":"NP",
    "gn:dem":1629,
    "gn:feature_class":"P",
    "gn:feature_code":"PPLL",
    "gn:name":"Nagada",
    "gn:population":0,
    "gn:timezone":"Asia/Kathmandu",
    "iso:country":"NP",
    "name:bel_x_preferred":[
        "\u041d\u0430\u043a\u0430\u0434\u0430"
    ],
    "name:deu_x_preferred":[
        "Naqada"
    ],
    "name:fra_x_preferred":[
        "Nagada"
    ],
    "name:ita_x_preferred":[
        "Nagada"
    ],
    "name:nld_x_preferred":[
        "Naqada"
    ],
    "name:por_x_preferred":[
        "Nacada"
    ],
    "name:spa_x_preferred":[
        "Naqada"
    ],
    "name:vie_x_preferred":[
        "Nagada"
    ],
    "wof:name":"Nagada",
    "wof:placetype":"locality"
},
  "geometry": {"coordinates":[81.07245999999998,29.31117],"type":"Point"}
}