{
  "type": "Feature",
  "properties": {
    "gn:admin1_code":"CR",
    "gn:admin2_code":"1",
    "gn:admin3_code":"23",
    "gn:admin4_code":"230030.0",
    "gn:asciiname":"Pipaldanda",
    "gn:country_code":"NP",
    "gn:dem":1210,
    "gn:feature_class":"P",
    "gn:feature_code":"PPLL",
    "gn:name":"Pipaldanda",
    "gn:population":0,
    "gn:timezone":"Asia/Kathmandu",
    "iso:country":"NP",
    "wof:name":"Pipaldanda",
    "wof:placetype":"locality"
},
  "geometry": {"coordinates":[85.53388000000002,27.90998],"type":"Point"}
}