{
  "type": "Feature",
  "properties": {
    "gn:admin1_code":"CR",
    "gn:admin2_code":"11",
    "gn:admin3_code":"32",
    "gn:admin4_code":"320012",
    "gn:asciiname":"Basabitti Jingadiya",
    "gn:country_code":"NP",
    "gn:dem":87,
    "gn:feature_class":"P",
    "gn:feature_code":"PPLL",
    "gn:name":"Basabitti Jingadiya",
    "gn:population":0,
    "gn:timezone":"Asia/Kathmandu",
    "iso:country":"NP",
    "wof:name":"Basabitti Jingadiya",
    "wof:placetype":"locality"
},
  "geometry": {"coordinates":[85.32420999999999,26.9668],"type":"Point"}
}