{
  "type": "Feature",
  "properties": {
    "gn:admin1_code":"CR",
    "gn:admin2_code":"5",
    "gn:admin3_code":"22.0",
    "gn:admin4_code":"220037.0",
    "gn:asciiname":"Bhirkharka",
    "gn:country_code":"NP",
    "gn:dem":2282,
    "gn:feature_class":"P",
    "gn:feature_code":"PPLL",
    "gn:name":"Bhirkharka",
    "gn:population":0,
    "gn:timezone":"Asia/Kathmandu",
    "iso:country":"NP",
    "wof:name":"Bhirkharka",
    "wof:placetype":"locality"
},
  "geometry": {"coordinates":[86.28591999999998,27.61948],"type":"Point"}
}