{
  "type": "Feature",
  "properties": {
    "gn:admin1_code":"MR",
    "gn:admin2_code":"2.0",
    "gn:admin3_code":"59.0",
    "gn:admin4_code":"590042.0",
    "gn:asciiname":"Durakholagaun",
    "gn:country_code":"NP",
    "gn:dem":633,
    "gn:feature_class":"P",
    "gn:feature_code":"PPLL",
    "gn:name":"Durakholagaun",
    "gn:population":0,
    "gn:timezone":"Asia/Kathmandu",
    "iso:country":"NP",
    "wof:name":"Durakholagaun",
    "wof:placetype":"locality"
},
  "geometry": {"coordinates":[82.00131,28.54571],"type":"Point"}
}