{
  "type": "Feature",
  "properties": {
    "gn:admin1_code":"WR",
    "gn:admin2_code":"4.0",
    "gn:asciiname":"Bange",
    "gn:country_code":"NP",
    "gn:dem":1030,
    "gn:feature_class":"P",
    "gn:feature_code":"PPL",
    "gn:name":"Bange",
    "gn:population":0,
    "gn:timezone":"Asia/Kathmandu",
    "iso:country":"NP",
    "wof:name":"Bange",
    "wof:placetype":"locality"
},
  "geometry": {"coordinates":[84.28270999999999,28.15957],"type":"Point"}
}