{
  "type": "Feature",
  "properties": {
    "gn:admin1_code":"WR",
    "gn:admin2_code":"4.0",
    "gn:admin3_code":"38.0",
    "gn:admin4_code":"380001.0",
    "gn:asciiname":"Tilbari",
    "gn:country_code":"NP",
    "gn:dem":638,
    "gn:feature_class":"P",
    "gn:feature_code":"PPLL",
    "gn:name":"Tilbari",
    "gn:population":0,
    "gn:timezone":"Asia/Kathmandu",
    "iso:country":"NP",
    "wof:name":"Tilbari",
    "wof:placetype":"locality"
},
  "geometry": {"coordinates":[84.49296,27.90566],"type":"Point"}
}