{
  "type": "Feature",
  "properties": {
    "gn:admin1_code":"CR",
    "gn:admin2_code":"1",
    "gn:admin3_code":"30.0",
    "gn:admin4_code":"300039.0",
    "gn:asciiname":"Arsatar",
    "gn:country_code":"NP",
    "gn:dem":376,
    "gn:feature_class":"P",
    "gn:feature_code":"PPLL",
    "gn:name":"Arsatar",
    "gn:population":0,
    "gn:timezone":"Asia/Kathmandu",
    "iso:country":"NP",
    "wof:name":"Arsatar",
    "wof:placetype":"locality"
},
  "geometry": {"coordinates":[84.8231,27.81153],"type":"Point"}
}