{
  "type": "Feature",
  "properties": {
    "gn:admin1_code":"FR",
    "gn:admin2_code":"14",
    "gn:admin3_code":"70.0",
    "gn:admin4_code":"700006.0",
    "gn:asciiname":"Golsa",
    "gn:country_code":"NP",
    "gn:dem":1084,
    "gn:feature_class":"P",
    "gn:feature_code":"PPLL",
    "gn:name":"Golsa",
    "gn:population":0,
    "gn:timezone":"Asia/Kathmandu",
    "iso:country":"NP",
    "wof:name":"Golsa",
    "wof:placetype":"locality"
},
  "geometry": {"coordinates":[81.05159,29.05932],"type":"Point"}
}