{
  "type": "Feature",
  "properties": {
    "gn:admin1_code":"MR",
    "gn:admin2_code":"12",
    "gn:admin3_code":"53",
    "gn:admin4_code":"530001",
    "gn:asciiname":"Bahariphedi",
    "gn:country_code":"NP",
    "gn:dem":1470,
    "gn:feature_class":"P",
    "gn:feature_code":"PPLL",
    "gn:name":"Bahariphedi",
    "gn:population":0,
    "gn:timezone":"Asia/Kathmandu",
    "iso:country":"NP",
    "wof:name":"Bahariphedi",
    "wof:placetype":"locality"
},
  "geometry": {"coordinates":[82.75664999999999,28.21785],"type":"Point"}
}