{
  "type": "Feature",
  "properties": {
    "gn:admin1_code":"FR",
    "gn:admin2_code":"9",
    "gn:admin3_code":"72.0",
    "gn:admin4_code":"720009.0",
    "gn:asciiname":"Khalla Dhaya",
    "gn:country_code":"NP",
    "gn:dem":216,
    "gn:feature_class":"P",
    "gn:feature_code":"PPLL",
    "gn:name":"Khalla Dhaya",
    "gn:population":0,
    "gn:timezone":"Asia/Kathmandu",
    "iso:country":"NP",
    "wof:name":"Khalla Dhaya",
    "wof:placetype":"locality"
},
  "geometry": {"coordinates":[80.49335000000001,28.86055],"type":"Point"}
}