{
  "type": "Feature",
  "properties": {
    "gn:admin1_code":"WR",
    "gn:admin2_code":"3",
    "gn:admin3_code":"45.0",
    "gn:admin4_code":"450036.0",
    "gn:asciiname":"Gahate",
    "gn:country_code":"NP",
    "gn:dem":1773,
    "gn:feature_class":"P",
    "gn:feature_code":"PPLL",
    "gn:name":"Gahate",
    "gn:population":0,
    "gn:timezone":"Asia/Kathmandu",
    "iso:country":"NP",
    "wof:name":"Gahate",
    "wof:placetype":"locality"
},
  "geometry": {"coordinates":[83.51838000000002,28.2913],"type":"Point"}
}