{
  "type": "Feature",
  "properties": {
    "gn:admin1_code":"ER",
    "gn:admin2_code":"13.0",
    "gn:admin3_code":"14.0",
    "gn:admin4_code":"140043.0",
    "gn:asciiname":"Chaukibari",
    "gn:country_code":"NP",
    "gn:dem":180,
    "gn:feature_class":"P",
    "gn:feature_code":"PPLL",
    "gn:name":"Chaukibari",
    "gn:population":0,
    "gn:timezone":"Asia/Kathmandu",
    "iso:country":"NP",
    "wof:name":"Chaukibari",
    "wof:placetype":"locality"
},
  "geometry": {"coordinates":[86.66298,26.82038],"type":"Point"}
}