{
  "type": "Feature",
  "properties": {
    "gn:admin1_code":"MR",
    "gn:admin2_code":"2",
    "gn:admin3_code":"61.0",
    "gn:admin4_code":"610012.0",
    "gn:asciiname":"Jhangrisalla",
    "gn:country_code":"NP",
    "gn:dem":882,
    "gn:feature_class":"P",
    "gn:feature_code":"PPLL",
    "gn:name":"Jhangrisalla",
    "gn:population":0,
    "gn:timezone":"Asia/Kathmandu",
    "iso:country":"NP",
    "wof:name":"Jhangrisalla",
    "wof:placetype":"locality"
},
  "geometry": {"coordinates":[82.02472,28.68074],"type":"Point"}
}