{
  "type": "Feature",
  "properties": {
    "gn:admin1_code":"ER",
    "gn:admin2_code":"7",
    "gn:admin3_code":"10.0",
    "gn:admin4_code":"100022.0",
    "gn:asciiname":"Birauta",
    "gn:country_code":"NP",
    "gn:dem":2359,
    "gn:feature_class":"P",
    "gn:feature_code":"PPLL",
    "gn:name":"Birauta",
    "gn:population":0,
    "gn:timezone":"Asia/Kathmandu",
    "iso:country":"NP",
    "wof:name":"Birauta",
    "wof:placetype":"locality"
},
  "geometry": {"coordinates":[86.98600999999999,27.4179],"type":"Point"}
}