{
  "type": "Feature",
  "properties": {
    "gn:admin1_code":"ER",
    "gn:admin2_code":"7",
    "gn:admin3_code":"7.0",
    "gn:admin4_code":"70005.0",
    "gn:asciiname":"Belharabesi",
    "gn:country_code":"NP",
    "gn:dem":313,
    "gn:feature_class":"P",
    "gn:feature_code":"PPLL",
    "gn:name":"Belharabesi",
    "gn:population":0,
    "gn:timezone":"Asia/Kathmandu",
    "iso:country":"NP",
    "wof:name":"Belharabesi",
    "wof:placetype":"locality"
},
  "geometry": {"coordinates":[87.28794000000001,26.92992000000001],"type":"Point"}
}