{
  "type": "Feature",
  "properties": {
    "gn:admin1_code":"CR",
    "gn:admin2_code":"1",
    "gn:admin3_code":"28",
    "gn:admin4_code":"280052",
    "gn:asciiname":"Tikhe Pakha",
    "gn:country_code":"NP",
    "gn:dem":1517,
    "gn:feature_class":"P",
    "gn:feature_code":"PPLL",
    "gn:name":"Tikhe Pakha",
    "gn:population":0,
    "gn:timezone":"Asia/Kathmandu",
    "iso:country":"NP",
    "wof:name":"Tikhe Pakha",
    "wof:placetype":"locality"
},
  "geometry": {"coordinates":[85.36168000000001,27.84019],"type":"Point"}
}