{
  "type": "Feature",
  "properties": {
    "gn:admin1_code":"MR",
    "gn:admin2_code":"12",
    "gn:admin3_code":"52",
    "gn:admin4_code":"520005",
    "gn:asciiname":"Maudhara",
    "gn:country_code":"NP",
    "gn:dem":907,
    "gn:feature_class":"P",
    "gn:feature_code":"PPLL",
    "gn:name":"Maudhara",
    "gn:population":0,
    "gn:timezone":"Asia/Kathmandu",
    "iso:country":"NP",
    "wof:name":"Maudhara",
    "wof:placetype":"locality"
},
  "geometry": {"coordinates":[82.76506999999999,28.12978],"type":"Point"}
}