{
  "type": "Feature",
  "properties": {
    "gn:admin1_code":"MR",
    "gn:admin2_code":"6",
    "gn:admin3_code":"62.0",
    "gn:admin4_code":"620013.0",
    "gn:asciiname":"Thargaun",
    "gn:country_code":"NP",
    "gn:dem":2280,
    "gn:feature_class":"P",
    "gn:feature_code":"PPLL",
    "gn:name":"Thargaun",
    "gn:population":0,
    "gn:timezone":"Asia/Kathmandu",
    "iso:country":"NP",
    "wof:name":"Thargaun",
    "wof:placetype":"locality"
},
  "geometry": {"coordinates":[82.51344,29.05755],"type":"Point"}
}