{
  "type": "Feature",
  "properties": {
    "gn:admin1_code":"MR",
    "gn:admin2_code":"6",
    "gn:admin3_code":"63.0",
    "gn:admin4_code":"630025.0",
    "gn:asciiname":"Kasi Dalpha",
    "gn:country_code":"NP",
    "gn:dem":6259,
    "gn:feature_class":"P",
    "gn:feature_code":"PPLL",
    "gn:name":"Kasi Dalpha",
    "gn:population":0,
    "gn:timezone":"Asia/Kathmandu",
    "iso:country":"NP",
    "wof:name":"Kasi Dalpha",
    "wof:placetype":"locality"
},
  "geometry": {"coordinates":[82.5514,29.28257],"type":"Point"}
}