{
  "type": "Feature",
  "properties": {
    "gn:admin1_code":"MR",
    "gn:admin2_code":"12",
    "gn:admin3_code":"52",
    "gn:admin4_code":"520028",
    "gn:asciiname":"Gothantidanda",
    "gn:country_code":"NP",
    "gn:dem":1949,
    "gn:feature_class":"P",
    "gn:feature_code":"PPLL",
    "gn:name":"Gothantidanda",
    "gn:population":0,
    "gn:timezone":"Asia/Kathmandu",
    "iso:country":"NP",
    "wof:name":"Gothantidanda",
    "wof:placetype":"locality"
},
  "geometry": {"coordinates":[82.95910000000001,28.21321],"type":"Point"}
}