{
  "type": "Feature",
  "properties": {
    "gn:admin1_code":"ER",
    "gn:admin2_code":"10",
    "gn:admin3_code":"2",
    "gn:admin4_code":"20007",
    "gn:asciiname":"Kolbote",
    "gn:country_code":"NP",
    "gn:dem":1333,
    "gn:feature_class":"P",
    "gn:feature_code":"PPLL",
    "gn:name":"Kolbote",
    "gn:population":0,
    "gn:timezone":"Asia/Kathmandu",
    "iso:country":"NP",
    "wof:name":"Kolbote",
    "wof:placetype":"locality"
},
  "geometry": {"coordinates":[87.74561,27.1295],"type":"Point"}
}