{
  "type": "Feature",
  "properties": {
    "gn:admin1_code":"FR",
    "gn:admin2_code":"14",
    "gn:admin3_code":"71.0",
    "gn:admin4_code":"710015.0",
    "gn:asciiname":"Salghari",
    "gn:country_code":"NP",
    "gn:dem":1064,
    "gn:feature_class":"P",
    "gn:feature_code":"PPLL",
    "gn:name":"Salghari",
    "gn:population":0,
    "gn:timezone":"Asia/Kathmandu",
    "iso:country":"NP",
    "name:mai_x_preferred":[
        "\u0918\u0930\u094d\u0924\u093f\u0917\u093e\u0909\u0901"
    ],
    "name:nep_x_preferred":[
        "\u0918\u0930\u094d\u0924\u093f\u0917\u093e\u0909\u0901"
    ],
    "wof:name":"Salghari",
    "wof:placetype":"locality"
},
  "geometry": {"coordinates":[80.58454,28.93714000000001],"type":"Point"}
}