{
  "type": "Feature",
  "properties": {
    "gn:admin1_code":"WR",
    "gn:admin2_code":"8",
    "gn:admin3_code":"47",
    "gn:admin4_code":"470050",
    "gn:asciiname":"Bichhadi",
    "gn:country_code":"NP",
    "gn:dem":1153,
    "gn:feature_class":"P",
    "gn:feature_code":"PPLL",
    "gn:name":"Bichhadi",
    "gn:population":0,
    "gn:timezone":"Asia/Kathmandu",
    "iso:country":"NP",
    "wof:name":"Bichhadi",
    "wof:placetype":"locality"
},
  "geometry": {"coordinates":[83.69104,27.83467000000001],"type":"Point"}
}