{
  "type": "Feature",
  "properties": {
    "gn:admin1_code":"ER",
    "gn:admin2_code":"7",
    "gn:admin3_code":"10.0",
    "gn:admin4_code":"100050.0",
    "gn:asciiname":"Tintale",
    "gn:country_code":"NP",
    "gn:dem":2096,
    "gn:feature_class":"P",
    "gn:feature_code":"PPLL",
    "gn:name":"Tintale",
    "gn:population":0,
    "gn:timezone":"Asia/Kathmandu",
    "iso:country":"NP",
    "name:nep_x_preferred":[
        "\u0924\u093f\u0928\u0924\u0932\u0947"
    ],
    "wof:name":"Tintale",
    "wof:placetype":"locality"
},
  "geometry": {"coordinates":[87.07484000000002,27.30119],"type":"Point"}
}