{
  "type": "Feature",
  "properties": {
    "gn:admin1_code":"CR",
    "gn:admin2_code":"5",
    "gn:admin3_code":"22.0",
    "gn:admin4_code":"220027.0",
    "gn:asciiname":"Pelegaun",
    "gn:country_code":"NP",
    "gn:dem":2102,
    "gn:feature_class":"P",
    "gn:feature_code":"PPLL",
    "gn:name":"Pelegaun",
    "gn:population":0,
    "gn:timezone":"Asia/Kathmandu",
    "iso:country":"NP",
    "wof:name":"Pelegaun",
    "wof:placetype":"locality"
},
  "geometry": {"coordinates":[86.05725,27.79949],"type":"Point"}
}