{
  "type": "Feature",
  "properties": {
    "gn:admin1_code":"CR",
    "gn:admin2_code":"5",
    "gn:admin3_code":"21",
    "gn:admin4_code":"210019",
    "gn:asciiname":"Phyangre",
    "gn:country_code":"NP",
    "gn:dem":2192,
    "gn:feature_class":"P",
    "gn:feature_code":"PPLL",
    "gn:name":"Phyangre",
    "gn:population":0,
    "gn:timezone":"Asia/Kathmandu",
    "iso:country":"NP",
    "wof:name":"Phyangre",
    "wof:placetype":"locality"
},
  "geometry": {"coordinates":[85.94601,27.58462],"type":"Point"}
}