{
  "type": "Feature",
  "properties": {
    "gn:admin1_code":"WR",
    "gn:admin2_code":"3",
    "gn:admin3_code":"45.0",
    "gn:admin4_code":"450044.0",
    "gn:asciiname":"Waba",
    "gn:country_code":"NP",
    "gn:dem":1999,
    "gn:feature_class":"P",
    "gn:feature_code":"PPLL",
    "gn:name":"Waba",
    "gn:population":0,
    "gn:timezone":"Asia/Kathmandu",
    "iso:country":"NP",
    "wof:name":"Waba",
    "wof:placetype":"locality"
},
  "geometry": {"coordinates":[83.43131,28.29594],"type":"Point"}
}