{
  "type": "Feature",
  "properties": {
    "gn:admin1_code":"FR",
    "gn:admin2_code":"9",
    "gn:admin3_code":"75.0",
    "gn:admin4_code":"750001.0",
    "gn:asciiname":"Melkhet",
    "gn:country_code":"NP",
    "gn:dem":998,
    "gn:feature_class":"P",
    "gn:feature_code":"PPLL",
    "gn:name":"Melkhet",
    "gn:population":0,
    "gn:timezone":"Asia/Kathmandu",
    "iso:country":"NP",
    "wof:name":"Melkhet",
    "wof:placetype":"locality"
},
  "geometry": {"coordinates":[80.44005,29.75173],"type":"Point"}
}