{
  "type": "Feature",
  "properties": {
    "gn:admin1_code":"CR",
    "gn:admin2_code":"5",
    "gn:admin3_code":"20",
    "gn:admin4_code":"200018",
    "gn:asciiname":"Dakaha",
    "gn:country_code":"NP",
    "gn:dem":239,
    "gn:feature_class":"P",
    "gn:feature_code":"PPLL",
    "gn:name":"Dakaha",
    "gn:population":0,
    "gn:timezone":"Asia/Kathmandu",
    "iso:country":"NP",
    "wof:name":"Dakaha",
    "wof:placetype":"locality"
},
  "geometry": {"coordinates":[86.15406999999998,27.02623],"type":"Point"}
}