{
  "type": "Feature",
  "properties": {
    "gn:admin1_code":"WR",
    "gn:admin2_code":"8",
    "gn:admin3_code":"47",
    "gn:admin4_code":"470020",
    "gn:asciiname":"Patan",
    "gn:country_code":"NP",
    "gn:dem":1417,
    "gn:feature_class":"P",
    "gn:feature_code":"PPLL",
    "gn:name":"Patan",
    "gn:population":0,
    "gn:timezone":"Asia/Kathmandu",
    "iso:country":"NP",
    "name:bpy_x_preferred":[
        "\u09aa\u09be\u09a4\u09be\u09a8"
    ],
    "name:cat_x_preferred":[
        "Patan"
    ],
    "name:ceb_x_preferred":[
        "Patan"
    ],
    "name:ces_x_preferred":[
        "P\u00e1tan"
    ],
    "name:deu_x_preferred":[
        "Patan"
    ],
    "name:fin_x_preferred":[
        "Patan"
    ],
    "name:fra_x_preferred":[
        "Patan"
    ],
    "name:hin_x_preferred":[
        "\u092a\u093e\u091f\u0928"
    ],
    "name:ita_x_preferred":[
        "Patan"
    ],
    "name:new_x_preferred":[
        "\u092a\u093e\u091f\u0928"
    ],
    "name:nld_x_preferred":[
        "Patan"
    ],
    "name:pol_x_preferred":[
        "Patan"
    ],
    "name:por_x_preferred":[
        "Patan"
    ],
    "name:spa_x_preferred":[
        "Patan"
    ],
    "name:swe_x_preferred":[
        "Patan"
    ],
    "wof:name":"Patan",
    "wof:placetype":"locality"
},
  "geometry": {"coordinates":[83.45695000000001,27.7918],"type":"Point"}
}