{
  "type": "Feature",
  "properties": {
    "gn:admin1_code":"WR",
    "gn:admin2_code":"4",
    "gn:admin3_code":"40.0",
    "gn:admin4_code":"400037.0",
    "gn:asciiname":"Togi",
    "gn:country_code":"NP",
    "gn:dem":1256,
    "gn:feature_class":"P",
    "gn:feature_code":"PPLL",
    "gn:name":"Togi",
    "gn:population":0,
    "gn:timezone":"Asia/Kathmandu",
    "iso:country":"NP",
    "wof:name":"Togi",
    "wof:placetype":"locality"
},
  "geometry": {"coordinates":[84.12831,28.25356],"type":"Point"}
}