{
  "type": "Feature",
  "properties": {
    "gn:admin1_code":"CR",
    "gn:admin2_code":"11",
    "gn:admin3_code":"31",
    "gn:admin4_code":"310007",
    "gn:asciiname":"Aingtar",
    "gn:country_code":"NP",
    "gn:dem":1212,
    "gn:feature_class":"P",
    "gn:feature_code":"PPLL",
    "gn:name":"Aingtar",
    "gn:population":0,
    "gn:timezone":"Asia/Kathmandu",
    "iso:country":"NP",
    "wof:name":"Aingtar",
    "wof:placetype":"locality"
},
  "geometry": {"coordinates":[84.88925,27.64163],"type":"Point"}
}