{
  "type": "Feature",
  "properties": {
    "gn:admin1_code":"CR",
    "gn:admin2_code":"1",
    "gn:admin3_code":"30.0",
    "gn:admin4_code":"300010.0",
    "gn:asciiname":"Simkhadagua",
    "gn:country_code":"NP",
    "gn:dem":891,
    "gn:feature_class":"P",
    "gn:feature_code":"PPLL",
    "gn:name":"Simkhadagua",
    "gn:population":0,
    "gn:timezone":"Asia/Kathmandu",
    "iso:country":"NP",
    "wof:name":"Simkhadagua",
    "wof:placetype":"locality"
},
  "geometry": {"coordinates":[84.82543000000003,27.91501],"type":"Point"}
}