{
  "type": "Feature",
  "properties": {
    "gn:admin1_code":"FR",
    "gn:admin2_code":"14.0",
    "gn:admin3_code":"69.0",
    "gn:admin4_code":"690047.0",
    "gn:asciiname":"Bisakot",
    "gn:country_code":"NP",
    "gn:dem":1184,
    "gn:feature_class":"P",
    "gn:feature_code":"PPLL",
    "gn:name":"Bisakot",
    "gn:population":0,
    "gn:timezone":"Asia/Kathmandu",
    "iso:country":"NP",
    "wof:name":"Bisakot",
    "wof:placetype":"locality"
},
  "geometry": {"coordinates":[81.24753,29.13845],"type":"Point"}
}