{
  "type": "Feature",
  "properties": {
    "gn:admin1_code":"WR",
    "gn:admin2_code":"4.0",
    "gn:admin3_code":"39.0",
    "gn:admin4_code":"390052.0",
    "gn:asciiname":"Gauli Bhanjyang",
    "gn:country_code":"NP",
    "gn:dem":932,
    "gn:feature_class":"P",
    "gn:feature_code":"PPLL",
    "gn:name":"Gauli Bhanjyang",
    "gn:population":0,
    "gn:timezone":"Asia/Kathmandu",
    "iso:country":"NP",
    "wof:name":"Gauli Bhanjyang",
    "wof:placetype":"locality"
},
  "geometry": {"coordinates":[83.59376999999998,27.96307],"type":"Point"}
}