{
  "type": "Feature",
  "properties": {
    "gn:admin1_code":"WR",
    "gn:admin2_code":"3",
    "gn:admin3_code":"45.0",
    "gn:admin4_code":"450024.0",
    "gn:asciiname":"Kokaldip",
    "gn:country_code":"NP",
    "gn:dem":1760,
    "gn:feature_class":"P",
    "gn:feature_code":"PPLL",
    "gn:name":"Kokaldip",
    "gn:population":0,
    "gn:timezone":"Asia/Kathmandu",
    "iso:country":"NP",
    "wof:name":"Kokaldip",
    "wof:placetype":"locality"
},
  "geometry": {"coordinates":[83.53045999999998,28.15147],"type":"Point"}
}