{
  "type": "Feature",
  "properties": {
    "gn:admin1_code":"WR",
    "gn:admin2_code":"8",
    "gn:admin3_code":"48",
    "gn:admin4_code":"480038",
    "gn:asciiname":"Makar",
    "gn:country_code":"NP",
    "gn:dem":121,
    "gn:feature_class":"P",
    "gn:feature_code":"PPLL",
    "gn:name":"Makar",
    "gn:population":0,
    "gn:timezone":"Asia/Kathmandu",
    "iso:country":"NP",
    "name:deu_x_preferred":[
        "Makar"
    ],
    "name:fra_x_preferred":[
        "Makar"
    ],
    "name:msa_x_preferred":[
        "Makar"
    ],
    "name:new_x_preferred":[
        "\u092e\u0915\u0930"
    ],
    "name:nor_x_preferred":[
        "Makar"
    ],
    "name:sco_x_preferred":[
        "Makar"
    ],
    "wof:name":"Makar",
    "wof:placetype":"locality"
},
  "geometry": {"coordinates":[83.78335,27.52046],"type":"Point"}
}