{
  "type": "Feature",
  "properties": {
    "gn:admin1_code":"ER",
    "gn:admin2_code":"13",
    "gn:admin3_code":"13.0",
    "gn:admin4_code":"130011.0",
    "gn:asciiname":"Naula",
    "gn:country_code":"NP",
    "gn:dem":1001,
    "gn:feature_class":"P",
    "gn:feature_code":"PPLL",
    "gn:name":"Naula",
    "gn:population":0,
    "gn:timezone":"Asia/Kathmandu",
    "iso:country":"NP",
    "name:sin_x_preferred":[
        "\u0db1\u0dcf\u0d8b\u0dbd"
    ],
    "wof:name":"Naula",
    "wof:placetype":"locality"
},
  "geometry": {"coordinates":[86.73299999999998,27.08318],"type":"Point"}
}