{
  "type": "Feature",
  "properties": {
    "gn:admin1_code":"CR",
    "gn:admin2_code":"11",
    "gn:admin3_code":"32",
    "gn:admin4_code":"320047",
    "gn:asciiname":"Jangalsaiya",
    "gn:country_code":"NP",
    "gn:dem":108,
    "gn:feature_class":"P",
    "gn:feature_code":"PPLL",
    "gn:name":"Jangalsaiya",
    "gn:population":0,
    "gn:timezone":"Asia/Kathmandu",
    "iso:country":"NP",
    "wof:name":"Jangalsaiya",
    "wof:placetype":"locality"
},
  "geometry": {"coordinates":[85.24455999999998,27.06065],"type":"Point"}
}