{
  "type": "Feature",
  "properties": {
    "gn:admin1_code":"ER",
    "gn:admin2_code":"7",
    "gn:admin3_code":"10.0",
    "gn:admin4_code":"100033.0",
    "gn:asciiname":"Sano Dingla",
    "gn:country_code":"NP",
    "gn:dem":1407,
    "gn:feature_class":"P",
    "gn:feature_code":"PPLL",
    "gn:name":"Sano Dingla",
    "gn:population":0,
    "gn:timezone":"Asia/Kathmandu",
    "iso:country":"NP",
    "wof:name":"Sano Dingla",
    "wof:placetype":"locality"
},
  "geometry": {"coordinates":[87.06305,27.33461],"type":"Point"}
}