{
  "type": "Feature",
  "properties": {
    "iso:country":"NP",
    "name:bho_x_preferred":[
        "\u092c\u0928\u0947\u092a\u093e"
    ],
    "name:ceb_x_preferred":[
        "Banep\u0101"
    ],
    "name:deu_x_preferred":[
        "Banepa"
    ],
    "name:eng_x_preferred":[
        "Banepa"
    ],
    "name:fra_x_preferred":[
        "Banepa"
    ],
    "name:hin_x_preferred":[
        "\u092c\u0928\u0947\u092a\u093e"
    ],
    "name:jpn_x_preferred":[
        "\u30d0\u30cd\u30d1"
    ],
    "name:mai_x_preferred":[
        "\u092c\u0928\u0947\u092a\u093e \u0928\u0917\u0930\u092a\u093e\u0932\u093f\u0915\u093e"
    ],
    "name:msa_x_preferred":[
        "Banepa"
    ],
    "name:nep_x_preferred":[
        "\u092c\u0928\u0947\u092a\u093e \u0928\u0917\u0930\u092a\u093e\u0932\u093f\u0915\u093e"
    ],
    "name:new_x_preferred":[
        "\u092d\u094b\u0924 \u0928\u0917\u0930\u092a\u093e\u0932\u093f\u0915\u093e"
    ],
    "name:nld_x_preferred":[
        "Banepa"
    ],
    "name:pol_x_preferred":[
        "Banepa"
    ],
    "name:por_x_preferred":[
        "Banepa"
    ],
    "name:rus_x_preferred":[
        "\u0411\u0430\u043d\u0435\u043f\u0430"
    ],
    "name:sah_x_preferred":[
        "\u0411\u0430\u043d\u0435\u043f\u0430"
    ],
    "name:und_x_variant":[
        "Panepa"
    ],
    "name:urd_x_preferred":[
        "\u0628\u0627\u0646\u06cc\u067e\u0627"
    ],
    "name:vie_x_preferred":[
        "Banepa"
    ],
    "name:zho_x_preferred":[
        "\u5df4\u5167\u5e15"
    ],
    "qs:gn_country":"NP",
    "qs:gn_fcode":"PPL",
    "qs:gn_pop":17153,
    "qs:name":"Banepa",
    "qs:name_adm0":"Nepal",
    "qs:name_adm1":"Madhyamanchal",
    "qs:photos":175,
    "qs:photos_1k":35,
    "qs:photos_9k":1,
    "qs:photos_9r":4,
    "qs:photos_all":175,
    "qs:photos_sr":4,
    "qs:placetype":"Town",
    "qs:pop_sr":"6",
    "qs:woe_adm0":23424911,
    "wd:wordcount":763,
    "wof:name":"Banepa",
    "wof:placetype":"locality",
    "wof:population":17153
},
  "geometry": {"coordinates":[85.52137999999999,27.62979],"type":"Point"}
}