{
  "type": "Feature",
  "properties": {
    "gn:admin1_code":"CR",
    "gn:admin2_code":"1",
    "gn:admin3_code":"27.0",
    "gn:admin4_code":"270044.0",
    "gn:asciiname":"Bomthali",
    "gn:country_code":"NP",
    "gn:dem":1367,
    "gn:feature_class":"P",
    "gn:feature_code":"PPLL",
    "gn:name":"Bomthali",
    "gn:population":0,
    "gn:timezone":"Asia/Kathmandu",
    "iso:country":"NP",
    "wof:name":"Bomthali",
    "wof:placetype":"locality"
},
  "geometry": {"coordinates":[85.40607,27.74739000000001],"type":"Point"}
}