{
  "type": "Feature",
  "properties": {
    "gn:admin1_code":"MR",
    "gn:admin2_code":"2.0",
    "gn:admin3_code":"58.0",
    "gn:admin4_code":"580010.0",
    "gn:asciiname":"Gidarpur",
    "gn:country_code":"NP",
    "gn:dem":169,
    "gn:feature_class":"P",
    "gn:feature_code":"PPLL",
    "gn:name":"Gidarpur",
    "gn:population":0,
    "gn:timezone":"Asia/Kathmandu",
    "iso:country":"NP",
    "wof:name":"Gidarpur",
    "wof:placetype":"locality"
},
  "geometry": {"coordinates":[81.21356999999998,28.5217],"type":"Point"}
}