{
  "type": "Feature",
  "properties": {
    "gn:admin1_code":"ER",
    "gn:admin2_code":"10",
    "gn:admin3_code":"2",
    "gn:admin4_code":"20021",
    "gn:asciiname":"Chitok",
    "gn:country_code":"NP",
    "gn:dem":1839,
    "gn:feature_class":"P",
    "gn:feature_code":"PPLL",
    "gn:name":"Chitok",
    "gn:population":0,
    "gn:timezone":"Asia/Kathmandu",
    "iso:country":"NP",
    "wof:name":"Chitok",
    "wof:placetype":"locality"
},
  "geometry": {"coordinates":[87.79599,27.25017],"type":"Point"}
}