{
  "type": "Feature",
  "properties": {
    "gn:admin1_code":"ER",
    "gn:admin2_code":"7",
    "gn:admin3_code":"10.0",
    "gn:admin4_code":"100011.0",
    "gn:asciiname":"Khamare",
    "gn:country_code":"NP",
    "gn:dem":1735,
    "gn:feature_class":"P",
    "gn:feature_code":"PPLL",
    "gn:name":"Khamare",
    "gn:population":0,
    "gn:timezone":"Asia/Kathmandu",
    "iso:country":"NP",
    "wof:name":"Khamare",
    "wof:placetype":"locality"
},
  "geometry": {"coordinates":[87.03641,27.19482],"type":"Point"}
}