{
  "type": "Feature",
  "properties": {
    "gn:admin1_code":"MR",
    "gn:admin2_code":"12",
    "gn:admin3_code":"55",
    "gn:admin4_code":"550042",
    "gn:asciiname":"Jyula",
    "gn:country_code":"NP",
    "gn:dem":1513,
    "gn:feature_class":"P",
    "gn:feature_code":"PPLL",
    "gn:name":"Jyula",
    "gn:population":0,
    "gn:timezone":"Asia/Kathmandu",
    "iso:country":"NP",
    "wof:name":"Jyula",
    "wof:placetype":"locality"
},
  "geometry": {"coordinates":[82.18886999999999,28.45588],"type":"Point"}
}