{
  "type": "Feature",
  "properties": {
    "gn:admin1_code":"MR",
    "gn:admin2_code":"12",
    "gn:admin3_code":"54",
    "gn:admin4_code":"540018",
    "gn:asciiname":"Chipalgaira",
    "gn:country_code":"NP",
    "gn:dem":2662,
    "gn:feature_class":"P",
    "gn:feature_code":"PPLL",
    "gn:name":"Chipalgaira",
    "gn:population":0,
    "gn:timezone":"Asia/Kathmandu",
    "iso:country":"NP",
    "wof:name":"Chipalgaira",
    "wof:placetype":"locality"
},
  "geometry": {"coordinates":[82.75833,28.56385],"type":"Point"}
}