{
  "type": "Feature",
  "properties": {
    "gn:admin1_code":"ER",
    "gn:admin2_code":"7",
    "gn:admin3_code":"6",
    "gn:admin4_code":"60010",
    "gn:asciiname":"Pachira",
    "gn:country_code":"NP",
    "gn:dem":86,
    "gn:feature_class":"P",
    "gn:feature_code":"PPLL",
    "gn:name":"Pachira",
    "gn:population":0,
    "gn:timezone":"Asia/Kathmandu",
    "iso:country":"NP",
    "name:ara_x_preferred":[
        "\u0628\u062e\u064a\u0631\u0629"
    ],
    "name:ceb_x_preferred":[
        "Pachira"
    ],
    "name:ces_x_preferred":[
        "Pachira"
    ],
    "name:fra_x_preferred":[
        "Pachira"
    ],
    "name:jpn_x_preferred":[
        "\u30d1\u30ad\u30e9\u5c5e"
    ],
    "name:nld_x_preferred":[
        "Pachira"
    ],
    "name:por_x_preferred":[
        "Pachira"
    ],
    "name:rus_x_preferred":[
        "\u041f\u0430\u0445\u0438\u0440\u0430"
    ],
    "name:spa_x_preferred":[
        "Pachira"
    ],
    "name:swe_x_preferred":[
        "Strandkastanjesl\u00e4ktet"
    ],
    "name:vie_x_preferred":[
        "Pachira"
    ],
    "name:war_x_preferred":[
        "Pachira"
    ],
    "name:zho_x_preferred":[
        "\u4e2d\u7f8e\u6728\u68c9\u5c5e"
    ],
    "wof:name":"Pachira",
    "wof:placetype":"locality"
},
  "geometry": {"coordinates":[87.25289000000002,26.55012],"type":"Point"}
}