{
  "type": "Feature",
  "properties": {
    "gn:admin1_code":"MR",
    "gn:admin2_code":"12",
    "gn:admin3_code":"55",
    "gn:admin4_code":"550036",
    "gn:asciiname":"Rikhe Bagar",
    "gn:country_code":"NP",
    "gn:dem":841,
    "gn:feature_class":"P",
    "gn:feature_code":"PPLL",
    "gn:name":"Rikhe Bagar",
    "gn:population":0,
    "gn:timezone":"Asia/Kathmandu",
    "iso:country":"NP",
    "wof:name":"Rikhe Bagar",
    "wof:placetype":"locality"
},
  "geometry": {"coordinates":[82.19627,28.2878],"type":"Point"}
}