{
  "type": "Feature",
  "properties": {
    "gn:admin1_code":"MR",
    "gn:admin2_code":"2.0",
    "gn:admin3_code":"59.0",
    "gn:admin4_code":"590010.0",
    "gn:asciiname":"Darkhase",
    "gn:country_code":"NP",
    "gn:dem":837,
    "gn:feature_class":"P",
    "gn:feature_code":"PPLL",
    "gn:name":"Darkhase",
    "gn:population":0,
    "gn:timezone":"Asia/Kathmandu",
    "iso:country":"NP",
    "wof:name":"Darkhase",
    "wof:placetype":"locality"
},
  "geometry": {"coordinates":[81.74039999999999,28.38875],"type":"Point"}
}