{
  "type": "Feature",
  "properties": {
    "gn:admin1_code":"ER",
    "gn:admin2_code":"13",
    "gn:admin3_code":"12",
    "gn:admin4_code":"120035",
    "gn:asciiname":"Tarkin",
    "gn:country_code":"NP",
    "gn:dem":2743,
    "gn:feature_class":"P",
    "gn:feature_code":"PPLL",
    "gn:name":"Tarkin",
    "gn:population":0,
    "gn:timezone":"Asia/Kathmandu",
    "iso:country":"NP",
    "wof:name":"Tarkin",
    "wof:placetype":"locality"
},
  "geometry": {"coordinates":[86.3865,27.45476],"type":"Point"}
}