{
  "type": "Feature",
  "properties": {
    "gn:admin1_code":"WR",
    "gn:admin2_code":"3",
    "gn:admin3_code":"44",
    "gn:admin4_code":"440009.0",
    "gn:asciiname":"Kauledadathar",
    "gn:country_code":"NP",
    "gn:dem":1465,
    "gn:feature_class":"P",
    "gn:feature_code":"PPLL",
    "gn:name":"Kauledadathar",
    "gn:population":0,
    "gn:timezone":"Asia/Kathmandu",
    "iso:country":"NP",
    "wof:name":"Kauledadathar",
    "wof:placetype":"locality"
},
  "geometry": {"coordinates":[83.71680000000001,28.14678],"type":"Point"}
}