{
  "type": "Feature",
  "properties": {
    "gn:admin1_code":"WR",
    "gn:admin2_code":"4",
    "gn:admin3_code":"37",
    "gn:admin4_code":"370030",
    "gn:asciiname":"Lage",
    "gn:country_code":"NP",
    "gn:dem":1179,
    "gn:feature_class":"P",
    "gn:feature_code":"PPLL",
    "gn:name":"Lage",
    "gn:population":0,
    "gn:timezone":"Asia/Kathmandu",
    "iso:country":"NP",
    "name:ceb_x_preferred":[
        "Lage"
    ],
    "name:deu_x_preferred":[
        "Lage"
    ],
    "name:epo_x_preferred":[
        "Lage"
    ],
    "name:fra_x_preferred":[
        "Lage"
    ],
    "name:jpn_x_preferred":[
        "\u30e9\u30fc\u30b2"
    ],
    "name:nld_x_preferred":[
        "Lage"
    ],
    "name:pol_x_preferred":[
        "Lage"
    ],
    "name:por_x_preferred":[
        "Lage"
    ],
    "name:rus_x_preferred":[
        "\u041b\u0430\u0433\u0435"
    ],
    "name:spa_x_preferred":[
        "Lage"
    ],
    "name:srp_x_preferred":[
        "\u041b\u0430\u0433\u0435"
    ],
    "name:swe_x_preferred":[
        "Lage"
    ],
    "name:vol_x_preferred":[
        "Lage"
    ],
    "wof:name":"Lage",
    "wof:placetype":"locality"
},
  "geometry": {"coordinates":[84.22241,28.22174],"type":"Point"}
}