{
  "type": "Feature",
  "properties": {
    "gn:admin1_code":"WR",
    "gn:admin2_code":"4",
    "gn:admin3_code":"37",
    "gn:admin4_code":"370030",
    "gn:asciiname":"Lage",
    "gn:country_code":"NP",
    "gn:dem":1179,
    "gn:feature_class":"P",
    "gn:feature_code":"PPLL",
    "gn:name":"Lage",
    "gn:population":0,
    "gn:timezone":"Asia/Kathmandu",
    "iso:country":"NP",
    "wof:name":"Lage",
    "wof:placetype":"locality"
},
  "geometry": {"coordinates":[84.22241,28.22174],"type":"Point"}
}