{
  "type": "Feature",
  "properties": {
    "gn:admin1_code":"MR",
    "gn:admin2_code":"12",
    "gn:admin3_code":"54",
    "gn:admin4_code":"540035",
    "gn:asciiname":"Dharagaun",
    "gn:country_code":"NP",
    "gn:dem":2308,
    "gn:feature_class":"P",
    "gn:feature_code":"PPLL",
    "gn:name":"Dharagaun",
    "gn:population":0,
    "gn:timezone":"Asia/Kathmandu",
    "iso:country":"NP",
    "wof:name":"Dharagaun",
    "wof:placetype":"locality"
},
  "geometry": {"coordinates":[82.88988000000001,28.67755],"type":"Point"}
}