{
  "type": "Feature",
  "properties": {
    "gn:admin1_code":"FR",
    "gn:admin2_code":"9",
    "gn:admin3_code":"75.0",
    "gn:admin4_code":"750013.0",
    "gn:asciiname":"Manikpata",
    "gn:country_code":"NP",
    "gn:dem":2829,
    "gn:feature_class":"P",
    "gn:feature_code":"PPLL",
    "gn:name":"Manikpata",
    "gn:population":0,
    "gn:timezone":"Asia/Kathmandu",
    "iso:country":"NP",
    "wof:name":"Manikpata",
    "wof:placetype":"locality"
},
  "geometry": {"coordinates":[80.71531999999998,29.85647],"type":"Point"}
}