{
  "type": "Feature",
  "properties": {
    "gn:admin1_code":"FR",
    "gn:admin2_code":"9",
    "gn:admin3_code":"72.0",
    "gn:admin4_code":"720007.0",
    "gn:asciiname":"Bhamarbhoj",
    "gn:country_code":"NP",
    "gn:dem":242,
    "gn:feature_class":"P",
    "gn:feature_code":"PPLL",
    "gn:name":"Bhamarbhoj",
    "gn:population":0,
    "gn:timezone":"Asia/Kathmandu",
    "iso:country":"NP",
    "wof:name":"Bhamarbhoj",
    "wof:placetype":"locality"
},
  "geometry": {"coordinates":[80.37603,28.9512],"type":"Point"}
}