{
  "type": "Feature",
  "properties": {
    "gn:admin1_code":"MR",
    "gn:admin2_code":"2.0",
    "gn:admin3_code":"58.0",
    "gn:admin4_code":"580006.0",
    "gn:asciiname":"Himalipur",
    "gn:country_code":"NP",
    "gn:dem":156,
    "gn:feature_class":"P",
    "gn:feature_code":"PPLL",
    "gn:name":"Himalipur",
    "gn:population":0,
    "gn:timezone":"Asia/Kathmandu",
    "iso:country":"NP",
    "wof:name":"Himalipur",
    "wof:placetype":"locality"
},
  "geometry": {"coordinates":[81.15125999999999,28.4839],"type":"Point"}
}