{
  "type": "Feature",
  "properties": {
    "gn:admin1_code":"WR",
    "gn:admin2_code":"8",
    "gn:admin3_code":"51.0",
    "gn:admin4_code":"510005.0",
    "gn:asciiname":"Arbung",
    "gn:country_code":"NP",
    "gn:dem":1050,
    "gn:feature_class":"P",
    "gn:feature_code":"PPLL",
    "gn:name":"Arbung",
    "gn:population":0,
    "gn:timezone":"Asia/Kathmandu",
    "iso:country":"NP",
    "wof:name":"Arbung",
    "wof:placetype":"locality"
},
  "geometry": {"coordinates":[83.26406999999998,27.97517],"type":"Point"}
}