{
  "type": "Feature",
  "properties": {
    "gn:admin1_code":"WR",
    "gn:admin2_code":"8",
    "gn:admin3_code":"47",
    "gn:admin4_code":"470064",
    "gn:asciiname":"Gundratung",
    "gn:country_code":"NP",
    "gn:dem":1116,
    "gn:feature_class":"P",
    "gn:feature_code":"PPLL",
    "gn:name":"Gundratung",
    "gn:population":0,
    "gn:timezone":"Asia/Kathmandu",
    "iso:country":"NP",
    "wof:name":"Gundratung",
    "wof:placetype":"locality"
},
  "geometry": {"coordinates":[83.45996,27.81917],"type":"Point"}
}