{
  "type": "Feature",
  "properties": {
    "gn:admin1_code":"WR",
    "gn:admin2_code":"8",
    "gn:admin3_code":"46.0",
    "gn:admin4_code":"460054.0",
    "gn:asciiname":"Dharmpani",
    "gn:country_code":"NP",
    "gn:dem":1038,
    "gn:feature_class":"P",
    "gn:feature_code":"PPLL",
    "gn:name":"Dharmpani",
    "gn:population":0,
    "gn:timezone":"Asia/Kathmandu",
    "iso:country":"NP",
    "wof:name":"Dharmpani",
    "wof:placetype":"locality"
},
  "geometry": {"coordinates":[83.34206999999998,27.97538],"type":"Point"}
}