{
  "type": "Feature",
  "properties": {
    "gn:admin1_code":"WR",
    "gn:admin2_code":"3",
    "gn:admin3_code":"45.0",
    "gn:admin4_code":"450028.0",
    "gn:asciiname":"Nayangaun",
    "gn:country_code":"NP",
    "gn:dem":1209,
    "gn:feature_class":"P",
    "gn:feature_code":"PPLL",
    "gn:name":"Nayangaun",
    "gn:population":0,
    "gn:timezone":"Asia/Kathmandu",
    "iso:country":"NP",
    "wof:name":"Nayangaun",
    "wof:placetype":"locality"
},
  "geometry": {"coordinates":[83.16701,28.28445],"type":"Point"}
}