{
  "type": "Feature",
  "properties": {
    "gn:admin1_code":"ER",
    "gn:admin2_code":"13",
    "gn:admin3_code":"11",
    "gn:admin4_code":"110013",
    "gn:asciiname":"Tumau",
    "gn:country_code":"NP",
    "gn:dem":1834,
    "gn:feature_class":"P",
    "gn:feature_code":"PPLL",
    "gn:name":"Tumau",
    "gn:population":0,
    "gn:timezone":"Asia/Kathmandu",
    "iso:country":"NP",
    "wof:name":"Tumau",
    "wof:placetype":"locality"
},
  "geometry": {"coordinates":[86.8657,27.51086],"type":"Point"}
}