{
  "type": "Feature",
  "properties": {
    "gn:admin1_code":"WR",
    "gn:admin2_code":"4.0",
    "gn:admin3_code":"38.0",
    "gn:admin4_code":"380046.0",
    "gn:asciiname":"Gairathok",
    "gn:country_code":"NP",
    "gn:dem":1015,
    "gn:feature_class":"P",
    "gn:feature_code":"PPLL",
    "gn:name":"Gairathok",
    "gn:population":0,
    "gn:timezone":"Asia/Kathmandu",
    "iso:country":"NP",
    "wof:name":"Gairathok",
    "wof:placetype":"locality"
},
  "geometry": {"coordinates":[84.13684000000001,28.09354],"type":"Point"}
}