{
  "type": "Feature",
  "properties": {
    "gn:admin1_code":"MR",
    "gn:admin2_code":"12",
    "gn:admin3_code":"56.0",
    "gn:admin4_code":"560002.0",
    "gn:asciiname":"Siriya naka",
    "gn:country_code":"NP",
    "gn:dem":259,
    "gn:feature_class":"P",
    "gn:feature_code":"PPLL",
    "gn:name":"Siriya naka",
    "gn:population":0,
    "gn:timezone":"Asia/Kathmandu",
    "iso:country":"NP",
    "wof:name":"Siriya naka",
    "wof:placetype":"locality"
},
  "geometry": {"coordinates":[82.39190000000001,27.71734],"type":"Point"}
}