{
  "type": "Feature",
  "properties": {
    "gn:admin1_code":"WR",
    "gn:admin2_code":"8",
    "gn:admin3_code":"48",
    "gn:admin4_code":"480074",
    "gn:asciiname":"Chuli Bojha",
    "gn:country_code":"NP",
    "gn:dem":1052,
    "gn:feature_class":"P",
    "gn:feature_code":"PPLL",
    "gn:name":"Chuli Bojha",
    "gn:population":0,
    "gn:timezone":"Asia/Kathmandu",
    "iso:country":"NP",
    "wof:name":"Chuli Bojha",
    "wof:placetype":"locality"
},
  "geometry": {"coordinates":[84.15501,27.76687],"type":"Point"}
}