{
  "type": "Feature",
  "properties": {
    "gn:admin1_code":"00",
    "gn:asciiname":"Lopchandhi",
    "gn:country_code":"NP",
    "gn:dem":295,
    "gn:feature_class":"P",
    "gn:feature_code":"PPL",
    "gn:name":"Lopchan\u1e0dhi\u0307\u0304",
    "gn:population":0,
    "gn:timezone":"Asia/Kathmandu",
    "iso:country":"NP",
    "name:und_x_variant":[
        "Lopchan\u1e0dhi\u0307\u0304",
        "Lopchan\u1e0dh\u012b"
    ],
    "wof:name":"Lopchandhi",
    "wof:placetype":"locality"
},
  "geometry": {"coordinates":[85.68875,27.16317],"type":"Point"}
}