{
  "type": "Feature",
  "properties": {
    "gn:admin1_code":"WR",
    "gn:admin2_code":"4.0",
    "gn:admin3_code":"38.0",
    "gn:admin4_code":"380015.0",
    "gn:asciiname":"Hatiya",
    "gn:country_code":"NP",
    "gn:dem":1083,
    "gn:feature_class":"P",
    "gn:feature_code":"PPLL",
    "gn:name":"Hatiya",
    "gn:population":0,
    "gn:timezone":"Asia/Kathmandu",
    "iso:country":"NP",
    "name:ceb_x_preferred":[
        "Hatiya"
    ],
    "name:fra_x_preferred":[
        "Hatiya"
    ],
    "name:pol_x_preferred":[
        "Hatiya"
    ],
    "name:swe_x_preferred":[
        "Hatiya"
    ],
    "wof:name":"Hatiya",
    "wof:placetype":"locality"
},
  "geometry": {"coordinates":[84.41835999999998,28.10002],"type":"Point"}
}