{
  "type": "Feature",
  "properties": {
    "gn:admin1_code":"WR",
    "gn:admin2_code":"4.0",
    "gn:admin3_code":"38.0",
    "gn:admin4_code":"380029.0",
    "gn:asciiname":"Naram",
    "gn:country_code":"NP",
    "gn:dem":1108,
    "gn:feature_class":"P",
    "gn:feature_code":"PPLL",
    "gn:name":"Naram",
    "gn:population":0,
    "gn:timezone":"Asia/Kathmandu",
    "iso:country":"NP",
    "name:ceb_x_preferred":[
        "Naram"
    ],
    "name:fra_x_preferred":[
        "Naram"
    ],
    "name:mai_x_preferred":[
        "\u0928\u0930\u092e"
    ],
    "name:msa_x_preferred":[
        "Naram"
    ],
    "name:nep_x_preferred":[
        "\u0928\u0930\u092e"
    ],
    "name:new_x_preferred":[
        "\u0928\u0930\u092e"
    ],
    "name:pol_x_preferred":[
        "Naram"
    ],
    "wof:name":"Naram",
    "wof:placetype":"locality"
},
  "geometry": {"coordinates":[84.34017,27.81266],"type":"Point"}
}