{
  "type": "Feature",
  "properties": {
    "gn:admin1_code":"MR",
    "gn:admin2_code":"6",
    "gn:admin3_code":"64.0",
    "gn:admin4_code":"640026.0",
    "gn:asciiname":"Ringnepani",
    "gn:country_code":"NP",
    "gn:dem":2656,
    "gn:feature_class":"P",
    "gn:feature_code":"PPLL",
    "gn:name":"Ringnepani",
    "gn:population":0,
    "gn:timezone":"Asia/Kathmandu",
    "iso:country":"NP",
    "wof:name":"Ringnepani",
    "wof:placetype":"locality"
},
  "geometry": {"coordinates":[81.56879000000001,29.2164],"type":"Point"}
}