{
  "type": "Feature",
  "properties": {
    "gn:admin1_code":"ER",
    "gn:admin2_code":"10",
    "gn:admin3_code":"2",
    "gn:admin4_code":"20005",
    "gn:asciiname":"Tahari",
    "gn:country_code":"NP",
    "gn:dem":1004,
    "gn:feature_class":"P",
    "gn:feature_code":"PPLL",
    "gn:name":"Tahari",
    "gn:population":0,
    "gn:timezone":"Asia/Kathmandu",
    "iso:country":"NP",
    "wof:name":"Tahari",
    "wof:placetype":"locality"
},
  "geometry": {"coordinates":[87.77086,27.17379],"type":"Point"}
}