{
  "type": "Feature",
  "properties": {
    "gn:admin1_code":"MR",
    "gn:admin2_code":"12",
    "gn:admin3_code":"53",
    "gn:admin4_code":"530049",
    "gn:asciiname":"Kalapohar",
    "gn:country_code":"NP",
    "gn:dem":1563,
    "gn:feature_class":"P",
    "gn:feature_code":"PPLL",
    "gn:name":"Kalapohar",
    "gn:population":0,
    "gn:timezone":"Asia/Kathmandu",
    "iso:country":"NP",
    "wof:name":"Kalapohar",
    "wof:placetype":"locality"
},
  "geometry": {"coordinates":[82.77960999999998,28.27818],"type":"Point"}
}