{
  "type": "Feature",
  "properties": {
    "gn:admin1_code":"ER",
    "gn:admin2_code":"10",
    "gn:admin3_code":"4.0",
    "gn:admin4_code":"40040.0",
    "gn:asciiname":"Bogalamari",
    "gn:country_code":"NP",
    "gn:dem":68,
    "gn:feature_class":"P",
    "gn:feature_code":"PPLL",
    "gn:name":"Bogalamari",
    "gn:population":0,
    "gn:timezone":"Asia/Kathmandu",
    "iso:country":"NP",
    "wof:name":"Bogalamari",
    "wof:placetype":"locality"
},
  "geometry": {"coordinates":[88.00881,26.42445],"type":"Point"}
}