{
  "type": "Feature",
  "properties": {
    "gn:admin1_code":"WR",
    "gn:admin2_code":"4.0",
    "gn:admin3_code":"38.0",
    "gn:admin4_code":"380028.0",
    "gn:asciiname":"Miyagaun",
    "gn:country_code":"NP",
    "gn:dem":949,
    "gn:feature_class":"P",
    "gn:feature_code":"PPLL",
    "gn:name":"Miyagaun",
    "gn:population":0,
    "gn:timezone":"Asia/Kathmandu",
    "iso:country":"NP",
    "wof:name":"Miyagaun",
    "wof:placetype":"locality"
},
  "geometry": {"coordinates":[83.99163,27.93741],"type":"Point"}
}