{
  "type": "Feature",
  "properties": {
    "gn:admin1_code":"FR",
    "gn:admin2_code":"9",
    "gn:admin3_code":"73.0",
    "gn:admin4_code":"730008.0",
    "gn:asciiname":"Bogata Pandegaun",
    "gn:country_code":"NP",
    "gn:dem":1042,
    "gn:feature_class":"P",
    "gn:feature_code":"PPLL",
    "gn:name":"Bogata Pandegaun",
    "gn:population":0,
    "gn:timezone":"Asia/Kathmandu",
    "iso:country":"NP",
    "wof:name":"Bogata Pandegaun",
    "wof:placetype":"locality"
},
  "geometry": {"coordinates":[80.40275,29.32034],"type":"Point"}
}