{
  "type": "Feature",
  "properties": {
    "gn:admin1_code":"ER",
    "gn:admin2_code":"13",
    "gn:admin3_code":"16",
    "gn:admin4_code":"160069.0",
    "gn:asciiname":"Paindubbi",
    "gn:country_code":"NP",
    "gn:dem":97,
    "gn:feature_class":"P",
    "gn:feature_code":"PPLL",
    "gn:name":"Paindubbi",
    "gn:population":0,
    "gn:timezone":"Asia/Kathmandu",
    "iso:country":"NP",
    "wof:name":"Paindubbi",
    "wof:placetype":"locality"
},
  "geometry": {"coordinates":[86.47174,26.63553],"type":"Point"}
}