{
  "type": "Feature",
  "properties": {
    "gn:admin1_code":"ER",
    "gn:admin2_code":"13",
    "gn:admin3_code":"13",
    "gn:admin4_code":"130067",
    "gn:asciiname":"Thanagaun",
    "gn:country_code":"NP",
    "gn:dem":1525,
    "gn:feature_class":"P",
    "gn:feature_code":"PPLL",
    "gn:name":"Thanagaun",
    "gn:population":0,
    "gn:timezone":"Asia/Kathmandu",
    "iso:country":"NP",
    "wof:name":"Thanagaun",
    "wof:placetype":"locality"
},
  "geometry": {"coordinates":[86.78716,27.32795],"type":"Point"}
}