{
  "type": "Feature",
  "properties": {
    "gn:admin1_code":"ER",
    "gn:admin2_code":"13",
    "gn:admin3_code":"12",
    "gn:admin4_code":"120028.0",
    "gn:asciiname":"Kattike",
    "gn:country_code":"NP",
    "gn:dem":2663,
    "gn:feature_class":"P",
    "gn:feature_code":"PPLL",
    "gn:name":"Kattike",
    "gn:population":0,
    "gn:timezone":"Asia/Kathmandu",
    "iso:country":"NP",
    "wof:name":"Kattike",
    "wof:placetype":"locality"
},
  "geometry": {"coordinates":[86.54401,27.37655],"type":"Point"}
}