{
  "type": "Feature",
  "properties": {
    "gn:admin1_code":"ER",
    "gn:admin2_code":"7.0",
    "gn:admin3_code":"6.0",
    "gn:admin4_code":"60029.0",
    "gn:asciiname":"Kodh",
    "gn:country_code":"NP",
    "gn:dem":73,
    "gn:feature_class":"P",
    "gn:feature_code":"PPLL",
    "gn:name":"Kodh",
    "gn:population":0,
    "gn:timezone":"Asia/Kathmandu",
    "iso:country":"NP",
    "wof:name":"Kodh",
    "wof:placetype":"locality"
},
  "geometry": {"coordinates":[87.15649999999999,26.41711],"type":"Point"}
}