{
  "type": "Feature",
  "properties": {
    "gn:admin1_code":"FR",
    "gn:admin2_code":"14",
    "gn:admin3_code":"71.0",
    "gn:admin4_code":"710003.0",
    "gn:asciiname":"Mallo Matiyari",
    "gn:country_code":"NP",
    "gn:dem":187,
    "gn:feature_class":"P",
    "gn:feature_code":"PPLL",
    "gn:name":"Mallo Matiyari",
    "gn:population":0,
    "gn:timezone":"Asia/Kathmandu",
    "iso:country":"NP",
    "wof:name":"Mallo Matiyari",
    "wof:placetype":"locality"
},
  "geometry": {"coordinates":[80.59885,28.7384],"type":"Point"}
}