{
  "type": "Feature",
  "properties": {
    "gn:admin1_code":"WR",
    "gn:admin2_code":"4.0",
    "gn:admin3_code":"38.0",
    "gn:admin4_code":"380023.0",
    "gn:asciiname":"Paling",
    "gn:country_code":"NP",
    "gn:dem":518,
    "gn:feature_class":"P",
    "gn:feature_code":"PPLL",
    "gn:name":"Paling",
    "gn:population":0,
    "gn:timezone":"Asia/Kathmandu",
    "iso:country":"NP",
    "wof:name":"Paling",
    "wof:placetype":"locality"
},
  "geometry": {"coordinates":[84.33154,27.98803],"type":"Point"}
}