{
  "type": "Feature",
  "properties": {
    "gn:admin1_code":"MR",
    "gn:admin2_code":"2",
    "gn:admin3_code":"60.0",
    "gn:admin4_code":"600052.0",
    "gn:asciiname":"Kujyad",
    "gn:country_code":"NP",
    "gn:dem":774,
    "gn:feature_class":"P",
    "gn:feature_code":"PPLL",
    "gn:name":"Kujyad",
    "gn:population":0,
    "gn:timezone":"Asia/Kathmandu",
    "iso:country":"NP",
    "wof:name":"Kujyad",
    "wof:placetype":"locality"
},
  "geometry": {"coordinates":[81.44542,29.03215],"type":"Point"}
}