{
  "type": "Feature",
  "properties": {
    "gn:admin1_code":"ER",
    "gn:admin2_code":"7",
    "gn:admin3_code":"10.0",
    "gn:admin4_code":"100055.0",
    "gn:asciiname":"Parpani",
    "gn:country_code":"NP",
    "gn:dem":926,
    "gn:feature_class":"P",
    "gn:feature_code":"PPLL",
    "gn:name":"Parpani",
    "gn:population":0,
    "gn:timezone":"Asia/Kathmandu",
    "iso:country":"NP",
    "wof:name":"Parpani",
    "wof:placetype":"locality"
},
  "geometry": {"coordinates":[87.07321999999998,27.13685],"type":"Point"}
}