{
  "type": "Feature",
  "properties": {
    "gn:admin1_code":"00",
    "gn:asciiname":"Chihandada",
    "gn:country_code":"NP",
    "gn:dem":826,
    "gn:feature_class":"P",
    "gn:feature_code":"PPL",
    "gn:name":"Chih\u0101n\u1e0d\u0101\u0303\u1e0d\u0101",
    "gn:population":0,
    "gn:timezone":"Asia/Kathmandu",
    "iso:country":"NP",
    "name:und_x_variant":[
        "Chih\u0101n\u1e0d\u0101\u0303\u1e0d\u0101",
        "Chih\u0101n\u1e0d\u0101n\u1e0d\u0101"
    ],
    "wof:name":"Chihandada",
    "wof:placetype":"locality"
},
  "geometry": {"coordinates":[86.22384,27.09169],"type":"Point"}
}