{
  "type": "Feature",
  "properties": {
    "gn:admin1_code":"CR",
    "gn:admin2_code":"1",
    "gn:admin3_code":"24.0",
    "gn:admin4_code":"240066.0",
    "gn:asciiname":"Lamdihi",
    "gn:country_code":"NP",
    "gn:dem":870,
    "gn:feature_class":"P",
    "gn:feature_code":"PPLL",
    "gn:name":"Lamdihi",
    "gn:population":0,
    "gn:timezone":"Asia/Kathmandu",
    "iso:country":"NP",
    "wof:name":"Lamdihi",
    "wof:placetype":"locality"
},
  "geometry": {"coordinates":[85.61176,27.64859],"type":"Point"}
}