{
  "type": "Feature",
  "properties": {
    "gn:admin1_code":"00",
    "gn:asciiname":"Bhartan",
    "gn:country_code":"NP",
    "gn:dem":564,
    "gn:feature_class":"P",
    "gn:feature_code":"PPL",
    "gn:name":"Bh\u0101rt\u0101n",
    "gn:population":0,
    "gn:timezone":"Asia/Kathmandu",
    "iso:country":"NP",
    "name:nep_x_preferred":[
        "Bh\u0101rt\u0101n"
    ],
    "wof:name":"Bhartan",
    "wof:placetype":"locality"
},
  "geometry": {"coordinates":[87.18625,26.88639],"type":"Point"}
}