{
  "type": "Feature",
  "properties": {
    "gn:admin1_code":"CR",
    "gn:admin2_code":"5",
    "gn:admin3_code":"17.0",
    "gn:admin4_code":"170072.0",
    "gn:asciiname":"Radhopur",
    "gn:country_code":"NP",
    "gn:dem":69,
    "gn:feature_class":"P",
    "gn:feature_code":"PPLL",
    "gn:name":"Radhopur",
    "gn:population":0,
    "gn:timezone":"Asia/Kathmandu",
    "iso:country":"NP",
    "name:ceb_x_preferred":[
        "Radhopur"
    ],
    "name:msa_x_preferred":[
        "Radhopur"
    ],
    "name:nep_x_preferred":[
        "\u0930\u093e\u0927\u094b\u092a\u0941\u0930"
    ],
    "name:new_x_preferred":[
        "\u0930\u093e\u0927\u094b\u092a\u0941\u0930"
    ],
    "name:pol_x_preferred":[
        "Radhopur"
    ],
    "wof:name":"Radhopur",
    "wof:placetype":"locality"
},
  "geometry": {"coordinates":[85.94035,26.62842],"type":"Point"}
}