{
  "type": "Feature",
  "properties": {
    "gn:admin1_code":"WR",
    "gn:admin2_code":"4",
    "gn:admin3_code":"36.0",
    "gn:admin4_code":"360016.0",
    "gn:asciiname":"Budhikuwa",
    "gn:country_code":"NP",
    "gn:dem":472,
    "gn:feature_class":"P",
    "gn:feature_code":"PPLL",
    "gn:name":"Budhikuwa",
    "gn:population":0,
    "gn:timezone":"Asia/Kathmandu",
    "iso:country":"NP",
    "wof:name":"Budhikuwa",
    "wof:placetype":"locality"
},
  "geometry": {"coordinates":[84.44126999999997,27.96466],"type":"Point"}
}