{
  "type": "Feature",
  "properties": {
    "gn:admin1_code":"FR",
    "gn:admin2_code":"14",
    "gn:admin3_code":"69.0",
    "gn:admin4_code":"690068.0",
    "gn:asciiname":"Sutar",
    "gn:country_code":"NP",
    "gn:dem":1658,
    "gn:feature_class":"P",
    "gn:feature_code":"PPLL",
    "gn:name":"Sutar",
    "gn:population":0,
    "gn:timezone":"Asia/Kathmandu",
    "iso:country":"NP",
    "name:bih_x_preferred":[
        "\u0938\u0941\u0924\u093e\u0930"
    ],
    "name:ceb_x_preferred":[
        "Sutar"
    ],
    "name:fra_x_preferred":[
        "Sutar"
    ],
    "name:msa_x_preferred":[
        "Sutar"
    ],
    "name:nep_x_preferred":[
        "\u0938\u0941\u0924\u093e\u0930"
    ],
    "name:new_x_preferred":[
        "\u0938\u0941\u0924\u093e\u0930"
    ],
    "name:pol_x_preferred":[
        "Sutar"
    ],
    "wof:name":"Sutar",
    "wof:placetype":"locality"
},
  "geometry": {"coordinates":[81.37133,29.18713],"type":"Point"}
}