{
  "type": "Feature",
  "properties": {
    "gn:admin1_code":"WR",
    "gn:admin2_code":"8",
    "gn:admin3_code":"47",
    "gn:admin4_code":"470061",
    "gn:asciiname":"Humln",
    "gn:country_code":"NP",
    "gn:dem":1282,
    "gn:feature_class":"P",
    "gn:feature_code":"PPLL",
    "gn:name":"Humln",
    "gn:population":0,
    "gn:timezone":"Asia/Kathmandu",
    "iso:country":"NP",
    "wof:name":"Humln",
    "wof:placetype":"locality"
},
  "geometry": {"coordinates":[83.70163000000002,27.83007000000001],"type":"Point"}
}