{
  "type": "Feature",
  "properties": {
    "gn:admin1_code":"00",
    "gn:asciiname":"Tadi",
    "gn:country_code":"NP",
    "gn:dem":235,
    "gn:feature_class":"P",
    "gn:feature_code":"PPL",
    "gn:name":"\u1e6c\u0101\u0303\u1e0d\u012b",
    "gn:population":0,
    "gn:timezone":"Asia/Kathmandu",
    "iso:country":"NP",
    "name:nep_x_preferred":[
        "\u1e6c\u0101\u0303\u1e0d\u012b"
    ],
    "wof:name":"Tadi",
    "wof:placetype":"locality"
},
  "geometry": {"coordinates":[86.51063000000001,26.8365],"type":"Point"}
}