{
  "type": "Feature",
  "properties": {
    "gn:admin1_code":"WR",
    "gn:admin2_code":"8",
    "gn:admin3_code":"48",
    "gn:admin4_code":"480068",
    "gn:asciiname":"Naduwa Tola",
    "gn:country_code":"NP",
    "gn:dem":126,
    "gn:feature_class":"P",
    "gn:feature_code":"PPLL",
    "gn:name":"Naduwa Tola",
    "gn:population":0,
    "gn:timezone":"Asia/Kathmandu",
    "iso:country":"NP",
    "wof:name":"Naduwa Tola",
    "wof:placetype":"locality"
},
  "geometry": {"coordinates":[83.65683,27.60357],"type":"Point"}
}