{
  "type": "Feature",
  "properties": {
    "gn:admin1_code":"ER",
    "gn:admin2_code":"7",
    "gn:admin3_code":"10.0",
    "gn:admin4_code":"100034.0",
    "gn:asciiname":"Swanre",
    "gn:country_code":"NP",
    "gn:dem":1862,
    "gn:feature_class":"P",
    "gn:feature_code":"PPLL",
    "gn:name":"Swanre",
    "gn:population":0,
    "gn:timezone":"Asia/Kathmandu",
    "iso:country":"NP",
    "wof:name":"Swanre",
    "wof:placetype":"locality"
},
  "geometry": {"coordinates":[87.00903000000002,27.41549],"type":"Point"}
}