{
  "type": "Feature",
  "properties": {
    "gn:admin1_code":"00",
    "gn:asciiname":"Mannewa",
    "gn:country_code":"NP",
    "gn:dem":2092,
    "gn:feature_class":"P",
    "gn:feature_code":"PPL",
    "gn:name":"Ma\u1e45new\u0101",
    "gn:population":0,
    "gn:timezone":"Asia/Kathmandu",
    "iso:country":"NP",
    "wof:name":"Mannewa",
    "wof:placetype":"locality"
},
  "geometry": {"coordinates":[85.69009,27.93645],"type":"Point"}
}