{
  "type": "Feature",
  "properties": {
    "gn:admin1_code":"CR",
    "gn:admin2_code":"11",
    "gn:admin3_code":"31",
    "gn:admin4_code":"310002",
    "gn:asciiname":"Babiyodanda",
    "gn:country_code":"NP",
    "gn:dem":1090,
    "gn:feature_class":"P",
    "gn:feature_code":"PPLL",
    "gn:name":"Babiyodanda",
    "gn:population":0,
    "gn:timezone":"Asia/Kathmandu",
    "iso:country":"NP",
    "wof:name":"Babiyodanda",
    "wof:placetype":"locality"
},
  "geometry": {"coordinates":[85.12250999999998,27.446],"type":"Point"}
}