{
  "type": "Feature",
  "properties": {
    "gn:admin1_code":"ER",
    "gn:admin2_code":"7.0",
    "gn:admin3_code":"6.0",
    "gn:admin4_code":"60024.0",
    "gn:asciiname":"Musaharitol",
    "gn:country_code":"NP",
    "gn:dem":80,
    "gn:feature_class":"P",
    "gn:feature_code":"PPLL",
    "gn:name":"Musaharitol",
    "gn:population":0,
    "gn:timezone":"Asia/Kathmandu",
    "iso:country":"NP",
    "wof:name":"Musaharitol",
    "wof:placetype":"locality"
},
  "geometry": {"coordinates":[87.12729,26.50901],"type":"Point"}
}