{
  "type": "Feature",
  "properties": {
    "gn:admin1_code":"CR",
    "gn:admin2_code":"5",
    "gn:admin3_code":"21",
    "gn:admin4_code":"210044",
    "gn:asciiname":"Lubu",
    "gn:country_code":"NP",
    "gn:dem":682,
    "gn:feature_class":"P",
    "gn:feature_code":"PPLL",
    "gn:name":"Lubu",
    "gn:population":0,
    "gn:timezone":"Asia/Kathmandu",
    "iso:country":"NP",
    "name:ceb_x_preferred":[
        "Lubu"
    ],
    "name:fra_x_preferred":[
        "Lubu"
    ],
    "name:swe_x_preferred":[
        "Lubu"
    ],
    "wof:name":"Lubu",
    "wof:placetype":"locality"
},
  "geometry": {"coordinates":[85.81778,27.45495],"type":"Point"}
}