{
  "type": "Feature",
  "properties": {
    "gn:admin1_code":"ER",
    "gn:admin2_code":"7",
    "gn:admin3_code":"6",
    "gn:admin4_code":"60005",
    "gn:asciiname":"Chaudharitol",
    "gn:country_code":"NP",
    "gn:dem":81,
    "gn:feature_class":"P",
    "gn:feature_code":"PPLL",
    "gn:name":"Chaudharitol",
    "gn:population":0,
    "gn:timezone":"Asia/Kathmandu",
    "iso:country":"NP",
    "wof:name":"Chaudharitol",
    "wof:placetype":"locality"
},
  "geometry": {"coordinates":[87.14673000000001,26.56004],"type":"Point"}
}