{
  "type": "Feature",
  "properties": {
    "gn:admin1_code":"MR",
    "gn:admin2_code":"12",
    "gn:admin3_code":"55",
    "gn:admin4_code":"550025",
    "gn:asciiname":"Babiyachaur",
    "gn:country_code":"NP",
    "gn:dem":1170,
    "gn:feature_class":"P",
    "gn:feature_code":"PPLL",
    "gn:name":"Babiyachaur",
    "gn:population":0,
    "gn:timezone":"Asia/Kathmandu",
    "iso:country":"NP",
    "name:fra_x_preferred":[
        "Babiyachaur"
    ],
    "name:pol_x_preferred":[
        "Babiyachaur"
    ],
    "wof:name":"Babiyachaur",
    "wof:placetype":"locality"
},
  "geometry": {"coordinates":[82.23005000000001,28.30467],"type":"Point"}
}