{
  "type": "Feature",
  "properties": {
    "gn:admin1_code":"WR",
    "gn:admin2_code":"3",
    "gn:admin3_code":"45.0",
    "gn:admin4_code":"450047.0",
    "gn:asciiname":"Srisgaun",
    "gn:country_code":"NP",
    "gn:dem":1600,
    "gn:feature_class":"P",
    "gn:feature_code":"PPLL",
    "gn:name":"Srisgaun",
    "gn:population":0,
    "gn:timezone":"Asia/Kathmandu",
    "iso:country":"NP",
    "wof:name":"Srisgaun",
    "wof:placetype":"locality"
},
  "geometry": {"coordinates":[83.55592,28.14772],"type":"Point"}
}