{
  "type": "Feature",
  "properties": {
    "gn:admin1_code":"ER",
    "gn:admin2_code":"13",
    "gn:admin3_code":"12",
    "gn:admin4_code":"120014",
    "gn:asciiname":"Kartike",
    "gn:country_code":"NP",
    "gn:dem":1241,
    "gn:feature_class":"P",
    "gn:feature_code":"PPLL",
    "gn:name":"Kartike",
    "gn:population":0,
    "gn:timezone":"Asia/Kathmandu",
    "iso:country":"NP",
    "wof:name":"Kartike",
    "wof:placetype":"locality"
},
  "geometry": {"coordinates":[86.29679,27.33177],"type":"Point"}
}