{
  "type": "Feature",
  "properties": {
    "gn:admin1_code":"CR",
    "gn:admin2_code":"11",
    "gn:admin3_code":"31",
    "gn:admin4_code":"310040",
    "gn:asciiname":"Andheri",
    "gn:country_code":"NP",
    "gn:dem":282,
    "gn:feature_class":"P",
    "gn:feature_code":"PPLL",
    "gn:name":"Andheri",
    "gn:population":0,
    "gn:timezone":"Asia/Kathmandu",
    "iso:country":"NP",
    "name:deu_x_preferred":[
        "Andheri"
    ],
    "name:fra_x_preferred":[
        "Andheri"
    ],
    "name:guj_x_preferred":[
        "\u0a85\u0a82\u0aa7\u0ac7\u0ab0\u0ac0"
    ],
    "name:hin_x_preferred":[
        "\u0905\u0902\u0927\u0947\u0930\u0940"
    ],
    "name:mal_x_preferred":[
        "\u0d05\u0d28\u0d4d\u0d27\u0d47\u0d30\u0d3f"
    ],
    "name:mar_x_preferred":[
        "\u0905\u0902\u0927\u0947\u0930\u0940"
    ],
    "name:por_x_preferred":[
        "Anderi"
    ],
    "name:tam_x_preferred":[
        "\u0b85\u0ba8\u0bcd\u0ba4\u0bc7\u0bb0\u0bbf"
    ],
    "wof:name":"Andheri",
    "wof:placetype":"locality"
},
  "geometry": {"coordinates":[85.19826,27.28969],"type":"Point"}
}