{
  "type": "Feature",
  "properties": {
    "gn:admin1_code":"ER",
    "gn:admin2_code":"10",
    "gn:admin3_code":"4.0",
    "gn:admin4_code":"40024.0",
    "gn:asciiname":"Shikaribari",
    "gn:country_code":"NP",
    "gn:dem":91,
    "gn:feature_class":"P",
    "gn:feature_code":"PPLL",
    "gn:name":"Shikaribari",
    "gn:population":0,
    "gn:timezone":"Asia/Kathmandu",
    "iso:country":"NP",
    "wof:name":"Shikaribari",
    "wof:placetype":"locality"
},
  "geometry": {"coordinates":[88.03345,26.53344],"type":"Point"}
}