{
  "type": "Feature",
  "properties": {
    "gn:admin1_code":"ER",
    "gn:admin2_code":"13",
    "gn:admin3_code":"15",
    "gn:admin4_code":"150045",
    "gn:asciiname":"Kuraha",
    "gn:country_code":"NP",
    "gn:dem":132,
    "gn:feature_class":"P",
    "gn:feature_code":"PPLL",
    "gn:name":"Kuraha",
    "gn:population":0,
    "gn:timezone":"Asia/Kathmandu",
    "iso:country":"NP",
    "wof:name":"Kuraha",
    "wof:placetype":"locality"
},
  "geometry": {"coordinates":[86.54687,26.7538],"type":"Point"}
}