{
  "type": "Feature",
  "properties": {
    "gn:admin1_code":"FR",
    "gn:admin2_code":"14",
    "gn:admin3_code":"68",
    "gn:admin4_code":"680018",
    "gn:asciiname":"Asibisena",
    "gn:country_code":"NP",
    "gn:dem":2611,
    "gn:feature_class":"P",
    "gn:feature_code":"PPLL",
    "gn:name":"Asibisena",
    "gn:population":0,
    "gn:timezone":"Asia/Kathmandu",
    "iso:country":"NP",
    "wof:name":"Asibisena",
    "wof:placetype":"locality"
},
  "geometry": {"coordinates":[81.23557,29.49556],"type":"Point"}
}