{
  "type": "Feature",
  "properties": {
    "gn:admin1_code":"CR",
    "gn:admin2_code":"5",
    "gn:admin3_code":"20",
    "gn:admin4_code":"200023",
    "gn:asciiname":"Kudule Ratmate",
    "gn:country_code":"NP",
    "gn:dem":476,
    "gn:feature_class":"P",
    "gn:feature_code":"PPLL",
    "gn:name":"Kudule Ratmate",
    "gn:population":0,
    "gn:timezone":"Asia/Kathmandu",
    "iso:country":"NP",
    "wof:name":"Kudule Ratmate",
    "wof:placetype":"locality"
},
  "geometry": {"coordinates":[86.36123000000001,27.04821],"type":"Point"}
}