{
  "type": "Feature",
  "properties": {
    "gn:admin1_code":"CR",
    "gn:admin2_code":"5",
    "gn:admin3_code":"22.0",
    "gn:admin4_code":"220018.0",
    "gn:asciiname":"Simigaun",
    "gn:country_code":"NP",
    "gn:dem":2084,
    "gn:feature_class":"P",
    "gn:feature_code":"PPLL",
    "gn:name":"Simigaun",
    "gn:population":0,
    "gn:timezone":"Asia/Kathmandu",
    "iso:country":"NP",
    "wof:name":"Simigaun",
    "wof:placetype":"locality"
},
  "geometry": {"coordinates":[86.23652,27.87221],"type":"Point"}
}