{
  "type": "Feature",
  "properties": {
    "gn:admin1_code":"CR",
    "gn:admin2_code":"5",
    "gn:admin3_code":"21",
    "gn:admin4_code":"210002.0",
    "gn:asciiname":"Chapleti",
    "gn:country_code":"NP",
    "gn:dem":2124,
    "gn:feature_class":"P",
    "gn:feature_code":"PPLL",
    "gn:name":"Chapleti",
    "gn:population":0,
    "gn:timezone":"Asia/Kathmandu",
    "iso:country":"NP",
    "wof:name":"Chapleti",
    "wof:placetype":"locality"
},
  "geometry": {"coordinates":[86.18163,27.52379],"type":"Point"}
}