{
  "type": "Feature",
  "properties": {
    "gn:admin1_code":"00",
    "gn:asciiname":"Simdada",
    "gn:country_code":"NP",
    "gn:dem":1146,
    "gn:feature_class":"P",
    "gn:feature_code":"PPL",
    "gn:name":"Sim\u1e0d\u0101\u0303\u1e0d\u0101",
    "gn:population":0,
    "gn:timezone":"Asia/Kathmandu",
    "iso:country":"NP",
    "name:nep_x_preferred":[
        "Sim\u1e0d\u0101\u0303\u1e0d\u0101"
    ],
    "wof:name":"Simdada",
    "wof:placetype":"locality"
},
  "geometry": {"coordinates":[87.45121999999998,26.91373],"type":"Point"}
}