{
  "type": "Feature",
  "properties": {
    "gn:admin1_code":"CR",
    "gn:admin2_code":"11",
    "gn:admin3_code":"31",
    "gn:admin4_code":"310041",
    "gn:asciiname":"Kuntar",
    "gn:country_code":"NP",
    "gn:dem":1162,
    "gn:feature_class":"P",
    "gn:feature_code":"PPLL",
    "gn:name":"Kuntar",
    "gn:population":0,
    "gn:timezone":"Asia/Kathmandu",
    "iso:country":"NP",
    "wof:name":"Kuntar",
    "wof:placetype":"locality"
},
  "geometry": {"coordinates":[85.22957,27.55092],"type":"Point"}
}