{
  "type": "Feature",
  "properties": {
    "gn:admin1_code":"WR",
    "gn:admin2_code":"4",
    "gn:admin3_code":"36.0",
    "gn:admin4_code":"360033.0",
    "gn:asciiname":"Regmigaun",
    "gn:country_code":"NP",
    "gn:dem":1159,
    "gn:feature_class":"P",
    "gn:feature_code":"PPLL",
    "gn:name":"Regmigaun",
    "gn:population":0,
    "gn:timezone":"Asia/Kathmandu",
    "iso:country":"NP",
    "wof:name":"Regmigaun",
    "wof:placetype":"locality"
},
  "geometry": {"coordinates":[84.58534,28.12851],"type":"Point"}
}