{
  "type": "Feature",
  "properties": {
    "gn:admin1_code":"WR",
    "gn:admin2_code":"3",
    "gn:admin3_code":"45.0",
    "gn:admin4_code":"450006.0",
    "gn:asciiname":"Timlapata",
    "gn:country_code":"NP",
    "gn:dem":1421,
    "gn:feature_class":"P",
    "gn:feature_code":"PPLL",
    "gn:name":"Timlapata",
    "gn:population":0,
    "gn:timezone":"Asia/Kathmandu",
    "iso:country":"NP",
    "wof:name":"Timlapata",
    "wof:placetype":"locality"
},
  "geometry": {"coordinates":[83.46458,28.14648],"type":"Point"}
}