{
  "type": "Feature",
  "properties": {
    "gn:admin1_code":"MR",
    "gn:admin2_code":"2.0",
    "gn:admin3_code":"59.0",
    "gn:admin4_code":"590006.0",
    "gn:asciiname":"Daha",
    "gn:country_code":"NP",
    "gn:dem":1073,
    "gn:feature_class":"P",
    "gn:feature_code":"PPLL",
    "gn:name":"Daha",
    "gn:population":0,
    "gn:timezone":"Asia/Kathmandu",
    "iso:country":"NP",
    "name:ceb_x_preferred":[
        "Daha"
    ],
    "name:fra_x_preferred":[
        "Daha"
    ],
    "name:ind_x_preferred":[
        "Daha"
    ],
    "name:ita_x_preferred":[
        "Daha"
    ],
    "name:swe_x_preferred":[
        "Daha"
    ],
    "name:uzb_x_preferred":[
        "Daha"
    ],
    "wof:name":"Daha",
    "wof:placetype":"locality"
},
  "geometry": {"coordinates":[81.39404,28.83868],"type":"Point"}
}