{
  "type": "Feature",
  "properties": {
    "gn:admin1_code":"MR",
    "gn:admin2_code":"2.0",
    "gn:admin3_code":"58.0",
    "gn:admin4_code":"580001.0",
    "gn:asciiname":"Dayarampur",
    "gn:country_code":"NP",
    "gn:dem":148,
    "gn:feature_class":"P",
    "gn:feature_code":"PPLL",
    "gn:name":"Dayarampur",
    "gn:population":0,
    "gn:timezone":"Asia/Kathmandu",
    "iso:country":"NP",
    "wof:name":"Dayarampur",
    "wof:placetype":"locality"
},
  "geometry": {"coordinates":[81.15517,28.432],"type":"Point"}
}