{
  "type": "Feature",
  "properties": {
    "gn:admin1_code":"WR",
    "gn:admin2_code":"4",
    "gn:admin3_code":"37",
    "gn:admin4_code":"370033",
    "gn:asciiname":"Karaputar",
    "gn:country_code":"NP",
    "gn:dem":576,
    "gn:feature_class":"P",
    "gn:feature_code":"PPLL",
    "gn:name":"Karaputar",
    "gn:population":0,
    "gn:timezone":"Asia/Kathmandu",
    "iso:country":"NP",
    "name:deu_x_preferred":[
        "Karaputar"
    ],
    "name:mai_x_preferred":[
        "\u0915\u0930\u093e\u092a\u0941\u091f\u093e\u0930 \u0928\u0917\u0930\u092a\u093e\u0932\u093f\u0915\u093e"
    ],
    "name:nep_x_preferred":[
        "\u0915\u0930\u093e\u092a\u0941\u091f\u093e\u0930 \u0928\u0917\u0930\u092a\u093e\u0932\u093f\u0915\u093e"
    ],
    "wof:name":"Karaputar",
    "wof:placetype":"locality"
},
  "geometry": {"coordinates":[84.22946999999998,28.16222],"type":"Point"}
}