{
  "type": "Feature",
  "properties": {
    "gn:admin1_code":"00",
    "gn:asciiname":"Bagar",
    "gn:country_code":"NP",
    "gn:dem":1370,
    "gn:feature_class":"P",
    "gn:feature_code":"PPL",
    "gn:name":"Bagar",
    "gn:population":0,
    "gn:timezone":"Asia/Kathmandu",
    "iso:country":"NP",
    "name:ceb_x_preferred":[
        "Bagar"
    ],
    "name:slv_x_preferred":[
        "Bagar"
    ],
    "name:swe_x_preferred":[
        "Bagar"
    ],
    "wof:name":"Bagar",
    "wof:placetype":"locality"
},
  "geometry": {"coordinates":[80.76248000000002,29.05959],"type":"Point"}
}