{
  "type": "Feature",
  "properties": {
    "gn:admin1_code":"FR",
    "gn:admin2_code":"14",
    "gn:admin3_code":"68",
    "gn:admin4_code":"680022",
    "gn:asciiname":"Bijgada",
    "gn:country_code":"NP",
    "gn:dem":1366,
    "gn:feature_class":"P",
    "gn:feature_code":"PPLL",
    "gn:name":"Bijgada",
    "gn:population":0,
    "gn:timezone":"Asia/Kathmandu",
    "iso:country":"NP",
    "wof:name":"Bijgada",
    "wof:placetype":"locality"
},
  "geometry": {"coordinates":[80.86759000000001,29.59912000000001],"type":"Point"}
}