{
  "type": "Feature",
  "properties": {
    "gn:admin1_code":"ER",
    "gn:admin2_code":"13",
    "gn:admin3_code":"13.0",
    "gn:admin4_code":"130010.0",
    "gn:asciiname":"Chhiprung",
    "gn:country_code":"NP",
    "gn:dem":1846,
    "gn:feature_class":"P",
    "gn:feature_code":"PPLL",
    "gn:name":"Chhiprung",
    "gn:population":0,
    "gn:timezone":"Asia/Kathmandu",
    "iso:country":"NP",
    "wof:name":"Chhiprung",
    "wof:placetype":"locality"
},
  "geometry": {"coordinates":[86.85921999999999,27.31754],"type":"Point"}
}