{
  "type": "Feature",
  "properties": {
    "gn:admin1_code":"MR",
    "gn:admin2_code":"12",
    "gn:admin3_code":"54",
    "gn:admin4_code":"540005",
    "gn:asciiname":"Kharchebang",
    "gn:country_code":"NP",
    "gn:dem":1999,
    "gn:feature_class":"P",
    "gn:feature_code":"PPLL",
    "gn:name":"Kharchebang",
    "gn:population":0,
    "gn:timezone":"Asia/Kathmandu",
    "iso:country":"NP",
    "wof:name":"Kharchebang",
    "wof:placetype":"locality"
},
  "geometry": {"coordinates":[82.48508000000002,28.5767],"type":"Point"}
}