{
  "type": "Feature",
  "properties": {
    "gn:admin1_code":"00",
    "gn:asciiname":"Miyatol",
    "gn:country_code":"NP",
    "gn:dem":112,
    "gn:feature_class":"P",
    "gn:feature_code":"PPL",
    "gn:name":"Miy\u0101\u0303\u1e6dol",
    "gn:population":0,
    "gn:timezone":"Asia/Kathmandu",
    "iso:country":"NP",
    "name:nep_x_preferred":[
        "Miy\u0101\u0303\u1e6dol"
    ],
    "wof:name":"Miyatol",
    "wof:placetype":"locality"
},
  "geometry": {"coordinates":[85.68284,26.93577],"type":"Point"}
}