{
  "type": "Feature",
  "properties": {
    "gn:admin1_code":"00",
    "gn:asciiname":"Bardada",
    "gn:country_code":"NP",
    "gn:dem":641,
    "gn:feature_class":"P",
    "gn:feature_code":"PPL",
    "gn:name":"Bar\u1e0d\u0101\u0303\u1e0d\u0101",
    "gn:population":0,
    "gn:timezone":"Asia/Kathmandu",
    "iso:country":"NP",
    "name:nep_x_preferred":[
        "Bar\u1e0d\u0101\u0303\u1e0d\u0101"
    ],
    "wof:name":"Bardada",
    "wof:placetype":"locality"
},
  "geometry": {"coordinates":[86.74174000000002,26.87383],"type":"Point"}
}