{
  "type": "Feature",
  "properties": {
    "gn:admin1_code":"CR",
    "gn:admin2_code":"5",
    "gn:admin3_code":"19",
    "gn:admin4_code":"190024.0",
    "gn:asciiname":"Shahpur",
    "gn:country_code":"NP",
    "gn:dem":111,
    "gn:feature_class":"P",
    "gn:feature_code":"PPLL",
    "gn:name":"Shahpur",
    "gn:population":0,
    "gn:timezone":"Asia/Kathmandu",
    "iso:country":"NP",
    "name:ben_x_preferred":[
        "\u09b6\u09be\u09b9\u09aa\u09c1\u09b0"
    ],
    "name:cat_x_preferred":[
        "Shapur"
    ],
    "name:nld_x_preferred":[
        "Shahpur"
    ],
    "name:pol_x_preferred":[
        "Shahpur"
    ],
    "name:por_x_preferred":[
        "Shahpur"
    ],
    "wof:name":"Shahpur",
    "wof:placetype":"locality"
},
  "geometry": {"coordinates":[85.66897,26.93306],"type":"Point"}
}