{
  "type": "Feature",
  "properties": {
    "gn:admin1_code":"WR",
    "gn:admin2_code":"8",
    "gn:admin3_code":"48",
    "gn:admin4_code":"480065",
    "gn:asciiname":"Rithepani",
    "gn:country_code":"NP",
    "gn:dem":237,
    "gn:feature_class":"P",
    "gn:feature_code":"PPLL",
    "gn:name":"Rithepani",
    "gn:population":0,
    "gn:timezone":"Asia/Kathmandu",
    "iso:country":"NP",
    "wof:name":"Rithepani",
    "wof:placetype":"locality"
},
  "geometry": {"coordinates":[84.14879999999999,27.68044],"type":"Point"}
}