{
  "type": "Feature",
  "properties": {
    "gn:admin1_code":"CR",
    "gn:admin2_code":"11",
    "gn:admin3_code":"34",
    "gn:admin4_code":"340028",
    "gn:asciiname":"Gamhariya",
    "gn:country_code":"NP",
    "gn:dem":90,
    "gn:feature_class":"P",
    "gn:feature_code":"PPLL",
    "gn:name":"Gamhariya",
    "gn:population":0,
    "gn:timezone":"Asia/Kathmandu",
    "iso:country":"NP",
    "wof:name":"Gamhariya",
    "wof:placetype":"locality"
},
  "geometry": {"coordinates":[84.83699,27.08891],"type":"Point"}
}