{
  "type": "Feature",
  "properties": {
    "gn:admin1_code":"00",
    "gn:asciiname":"Joshipur",
    "gn:country_code":"NP",
    "gn:dem":151,
    "gn:feature_class":"P",
    "gn:feature_code":"PPL",
    "gn:name":"Joshi\u0307\u0304pur",
    "gn:population":0,
    "gn:timezone":"Asia/Kathmandu",
    "iso:country":"NP",
    "name:ceb_x_preferred":[
        "Joshipur"
    ],
    "name:mai_x_preferred":[
        "\u091c\u094b\u0936\u0940\u092a\u0941\u0930"
    ],
    "name:msa_x_preferred":[
        "Joshipur"
    ],
    "name:nep_x_preferred":[
        "Joshi\u0307\u0304pur"
    ],
    "name:nep_x_variant":[
        "\u091c\u094b\u0936\u0940\u092a\u0941\u0930"
    ],
    "name:new_x_preferred":[
        "\u091c\u094b\u0936\u0940\u092a\u0941\u0930"
    ],
    "name:pol_x_preferred":[
        "Joshipur"
    ],
    "wof:name":"Joshipur",
    "wof:placetype":"locality"
},
  "geometry": {"coordinates":[81.02073,28.56455],"type":"Point"}
}