{
  "type": "Feature",
  "properties": {
    "gn:admin1_code":"MR",
    "gn:admin2_code":"6",
    "gn:admin3_code":"64.0",
    "gn:admin4_code":"640022.0",
    "gn:asciiname":"Khairkate",
    "gn:country_code":"NP",
    "gn:dem":942,
    "gn:feature_class":"P",
    "gn:feature_code":"PPLL",
    "gn:name":"Khairkate",
    "gn:population":0,
    "gn:timezone":"Asia/Kathmandu",
    "iso:country":"NP",
    "wof:name":"Khairkate",
    "wof:placetype":"locality"
},
  "geometry": {"coordinates":[81.66908000000002,29.23583],"type":"Point"}
}