{
  "type": "Feature",
  "properties": {
    "gn:admin1_code":"WR",
    "gn:admin2_code":"4",
    "gn:admin3_code":"41",
    "gn:admin4_code":"410010.0",
    "gn:asciiname":"Shingkar kharka",
    "gn:country_code":"NP",
    "gn:dem":3895,
    "gn:feature_class":"P",
    "gn:feature_code":"PPLL",
    "gn:name":"Shingkar kharka",
    "gn:population":0,
    "gn:timezone":"Asia/Kathmandu",
    "iso:country":"NP",
    "wof:name":"Shingkar kharka",
    "wof:placetype":"locality"
},
  "geometry": {"coordinates":[84.20591,28.52749],"type":"Point"}
}