{
  "type": "Feature",
  "properties": {
    "gn:admin1_code":"WR",
    "gn:admin2_code":"4",
    "gn:admin3_code":"36.0",
    "gn:admin4_code":"360024.0",
    "gn:asciiname":"Damaigaun",
    "gn:country_code":"NP",
    "gn:dem":655,
    "gn:feature_class":"P",
    "gn:feature_code":"PPLL",
    "gn:name":"Damaigaun",
    "gn:population":0,
    "gn:timezone":"Asia/Kathmandu",
    "iso:country":"NP",
    "wof:name":"Damaigaun",
    "wof:placetype":"locality"
},
  "geometry": {"coordinates":[84.63258,28.05454000000001],"type":"Point"}
}