{
  "type": "Feature",
  "properties": {
    "gn:admin1_code":"WR",
    "gn:admin2_code":"4.0",
    "gn:admin3_code":"39.0",
    "gn:admin4_code":"390050.0",
    "gn:asciiname":"Shyamkholagaun",
    "gn:country_code":"NP",
    "gn:dem":595,
    "gn:feature_class":"P",
    "gn:feature_code":"PPLL",
    "gn:name":"Shyamkholagaun",
    "gn:population":0,
    "gn:timezone":"Asia/Kathmandu",
    "iso:country":"NP",
    "wof:name":"Shyamkholagaun",
    "wof:placetype":"locality"
},
  "geometry": {"coordinates":[83.87730999999999,27.94185],"type":"Point"}
}