{
  "type": "Feature",
  "properties": {
    "gn:admin1_code":"WR",
    "gn:admin2_code":"3",
    "gn:admin3_code":"43",
    "gn:admin4_code":"430019",
    "gn:asciiname":"Salyan",
    "gn:country_code":"NP",
    "gn:dem":1360,
    "gn:feature_class":"P",
    "gn:feature_code":"PPLL",
    "gn:name":"Salyan",
    "gn:population":0,
    "gn:timezone":"Asia/Kathmandu",
    "iso:country":"NP",
    "name:ara_x_preferred":[
        "\u0633\u0627\u0644\u064a\u0627\u0646"
    ],
    "name:ceb_x_preferred":[
        "Salyan"
    ],
    "name:deu_x_preferred":[
        "Salyan"
    ],
    "name:ell_x_preferred":[
        "\u03a3\u03b1\u03bb\u03b9\u03ac\u03bd"
    ],
    "name:epo_x_preferred":[
        "Salyan"
    ],
    "name:fas_x_preferred":[
        "\u0633\u0627\u0644\u06cc\u0627\u0646"
    ],
    "name:fra_x_preferred":[
        "Salyan"
    ],
    "name:heb_x_preferred":[
        "\u05e1\u05d0\u05dc\u05d9\u05d0\u05df"
    ],
    "name:hin_x_preferred":[
        "\u0938\u0948\u0932\u094d\u092f\u0928"
    ],
    "name:hun_x_preferred":[
        "Salyan"
    ],
    "name:ind_x_preferred":[
        "Salyan"
    ],
    "name:ita_x_preferred":[
        "Salyan"
    ],
    "name:kor_x_preferred":[
        "\uc0b4\ub9ac\uc548"
    ],
    "name:nld_x_preferred":[
        "Salyan"
    ],
    "name:pol_x_preferred":[
        "Salyan"
    ],
    "name:por_x_preferred":[
        "Salyan"
    ],
    "name:rus_x_preferred":[
        "\u0421\u0430\u043b\u044c\u044f\u043d"
    ],
    "name:spa_x_preferred":[
        "Salyan"
    ],
    "name:swe_x_preferred":[
        "Salyan"
    ],
    "name:tur_x_preferred":[
        "Salyan"
    ],
    "name:ukr_x_preferred":[
        "\u0421\u0430\u043b\u044c\u044f\u043d"
    ],
    "name:vie_x_preferred":[
        "Salyan"
    ],
    "name:zho_cn_x_preferred":[
        "\u8428\u5229\u5b89"
    ],
    "name:zho_tw_x_preferred":[
        "\u85a9\u5229\u63da"
    ],
    "wof:name":"Salyan",
    "wof:placetype":"locality"
},
  "geometry": {"coordinates":[83.46476,28.39361],"type":"Point"}
}