{
  "type": "Feature",
  "properties": {
    "gn:admin1_code":"WR",
    "gn:admin2_code":"3",
    "gn:admin3_code":"43",
    "gn:admin4_code":"430019",
    "gn:asciiname":"Salyan",
    "gn:country_code":"NP",
    "gn:dem":1360,
    "gn:feature_class":"P",
    "gn:feature_code":"PPLL",
    "gn:name":"Salyan",
    "gn:population":0,
    "gn:timezone":"Asia/Kathmandu",
    "iso:country":"NP",
    "name:ceb_x_preferred":[
        "Salyan"
    ],
    "name:deu_x_preferred":[
        "Salyan"
    ],
    "name:epo_x_preferred":[
        "Salyan"
    ],
    "name:fas_x_preferred":[
        "\u0633\u0627\u0644\u06cc\u0627\u0646"
    ],
    "name:fra_x_preferred":[
        "Salyan"
    ],
    "name:nld_x_preferred":[
        "Salyan"
    ],
    "name:por_x_preferred":[
        "Salyan"
    ],
    "name:rus_x_preferred":[
        "\u0421\u0430\u043b\u044c\u044f\u043d"
    ],
    "name:swe_x_preferred":[
        "Salyan"
    ],
    "wof:name":"Salyan",
    "wof:placetype":"locality"
},
  "geometry": {"coordinates":[83.46476,28.39361],"type":"Point"}
}