{
  "type": "Feature",
  "properties": {
    "gn:admin1_code":"CR",
    "gn:admin2_code":"5",
    "gn:admin3_code":"20",
    "gn:admin4_code":"200041.0",
    "gn:asciiname":"Sunkhani",
    "gn:country_code":"NP",
    "gn:dem":313,
    "gn:feature_class":"P",
    "gn:feature_code":"PPLL",
    "gn:name":"Sunkhani",
    "gn:population":0,
    "gn:timezone":"Asia/Kathmandu",
    "iso:country":"NP",
    "name:fra_x_preferred":[
        "Sunkhani"
    ],
    "name:new_x_preferred":[
        "\u0938\u0941\u0928 \u0916\u093e\u0928\u0940"
    ],
    "name:pol_x_preferred":[
        "Sunkhani"
    ],
    "wof:name":"Sunkhani",
    "wof:placetype":"locality"
},
  "geometry": {"coordinates":[86.02674,27.07005],"type":"Point"}
}