{
  "type": "Feature",
  "properties": {
    "gn:admin1_code":"MR",
    "gn:admin2_code":"6.0",
    "gn:asciiname":"Jumla Khalanga",
    "gn:country_code":"NP",
    "gn:dem":2352,
    "gn:feature_class":"P",
    "gn:feature_code":"PPLL",
    "gn:name":"Jumla Khalanga",
    "gn:population":0,
    "gn:timezone":"Asia/Kathmandu",
    "iso:country":"NP",
    "wof:name":"Jumla Khalanga",
    "wof:placetype":"locality"
},
  "geometry": {"coordinates":[82.18333,29.27528],"type":"Point"}
}