{
  "type": "Feature",
  "properties": {
    "gn:admin1_code":"ER",
    "gn:admin2_code":"7",
    "gn:admin3_code":"9",
    "gn:admin4_code":"90013.0",
    "gn:asciiname":"Ryalebesi",
    "gn:country_code":"NP",
    "gn:dem":515,
    "gn:feature_class":"P",
    "gn:feature_code":"PPLL",
    "gn:name":"Ryalebesi",
    "gn:population":0,
    "gn:timezone":"Asia/Kathmandu",
    "iso:country":"NP",
    "wof:name":"Ryalebesi",
    "wof:placetype":"locality"
},
  "geometry": {"coordinates":[87.18714,27.36657],"type":"Point"}
}