{
  "type": "Feature",
  "properties": {
    "gn:admin1_code":"CR",
    "gn:admin2_code":"11",
    "gn:admin3_code":"32",
    "gn:admin4_code":"320072",
    "gn:asciiname":"Pipariya",
    "gn:country_code":"NP",
    "gn:dem":87,
    "gn:feature_class":"P",
    "gn:feature_code":"PPLL",
    "gn:name":"Pipariya",
    "gn:population":0,
    "gn:timezone":"Asia/Kathmandu",
    "iso:country":"NP",
    "name:ceb_x_preferred":[
        "Pipariya"
    ],
    "name:hin_x_preferred":[
        "\u092a\u093f\u092a\u0930\u093f\u092f\u093e"
    ],
    "name:ita_x_preferred":[
        "Pipariya"
    ],
    "name:pol_x_preferred":[
        "Pipariya"
    ],
    "wof:name":"Pipariya",
    "wof:placetype":"locality"
},
  "geometry": {"coordinates":[85.22148,26.8843],"type":"Point"}
}