{
  "type": "Feature",
  "properties": {
    "gn:admin1_code":"00",
    "gn:asciiname":"Un",
    "gn:country_code":"NP",
    "gn:dem":2859,
    "gn:feature_class":"P",
    "gn:feature_code":"PPL",
    "gn:name":"U\u1e45",
    "gn:population":0,
    "gn:timezone":"Asia/Kathmandu",
    "iso:country":"NP",
    "wof:name":"Un",
    "wof:placetype":"locality"
},
  "geometry": {"coordinates":[84.82932,28.51664],"type":"Point"}
}