{
  "type": "Feature",
  "properties": {
    "gn:admin1_code":"CR",
    "gn:admin2_code":"1.0",
    "gn:admin3_code":"26.0",
    "gn:admin4_code":"260001.0",
    "gn:asciiname":"Banpedheri",
    "gn:country_code":"NP",
    "gn:dem":1529,
    "gn:feature_class":"P",
    "gn:feature_code":"PPLL",
    "gn:name":"Banpedheri",
    "gn:population":0,
    "gn:timezone":"Asia/Kathmandu",
    "iso:country":"NP",
    "wof:name":"Banpedheri",
    "wof:placetype":"locality"
},
  "geometry": {"coordinates":[85.48323000000001,27.7037],"type":"Point"}
}