{
  "type": "Feature",
  "properties": {
    "gn:admin1_code":"WR",
    "gn:admin2_code":"8",
    "gn:admin3_code":"48",
    "gn:admin4_code":"480026",
    "gn:asciiname":"Piparhawa",
    "gn:country_code":"NP",
    "gn:dem":106,
    "gn:feature_class":"P",
    "gn:feature_code":"PPLL",
    "gn:name":"Piparhawa",
    "gn:population":0,
    "gn:timezone":"Asia/Kathmandu",
    "iso:country":"NP",
    "wof:name":"Piparhawa",
    "wof:placetype":"locality"
},
  "geometry": {"coordinates":[83.68006,27.45736],"type":"Point"}
}