{
  "type": "Feature",
  "properties": {
    "gn:admin1_code":"MR",
    "gn:admin2_code":"2",
    "gn:admin3_code":"60.0",
    "gn:admin4_code":"600046.0",
    "gn:asciiname":"Simseligaira",
    "gn:country_code":"NP",
    "gn:dem":1389,
    "gn:feature_class":"P",
    "gn:feature_code":"PPLL",
    "gn:name":"Simseligaira",
    "gn:population":0,
    "gn:timezone":"Asia/Kathmandu",
    "iso:country":"NP",
    "wof:name":"Simseligaira",
    "wof:placetype":"locality"
},
  "geometry": {"coordinates":[81.69004,28.95235],"type":"Point"}
}