{
  "type": "Feature",
  "properties": {
    "gn:admin1_code":"WR",
    "gn:admin2_code":"4",
    "gn:admin3_code":"40.0",
    "gn:admin4_code":"400036.0",
    "gn:asciiname":"Bhirchok",
    "gn:country_code":"NP",
    "gn:dem":1215,
    "gn:feature_class":"P",
    "gn:feature_code":"PPLL",
    "gn:name":"Bhirchok",
    "gn:population":0,
    "gn:timezone":"Asia/Kathmandu",
    "iso:country":"NP",
    "wof:name":"Bhirchok",
    "wof:placetype":"locality"
},
  "geometry": {"coordinates":[84.14830000000001,28.15479],"type":"Point"}
}