{
  "type": "Feature",
  "properties": {
    "gn:admin1_code":"MR",
    "gn:admin2_code":"12",
    "gn:admin3_code":"53",
    "gn:admin4_code":"530050",
    "gn:asciiname":"Pathihalna",
    "gn:country_code":"NP",
    "gn:dem":2652,
    "gn:feature_class":"P",
    "gn:feature_code":"PPLL",
    "gn:name":"Pathihalna",
    "gn:population":0,
    "gn:timezone":"Asia/Kathmandu",
    "iso:country":"NP",
    "wof:name":"Pathihalna",
    "wof:placetype":"locality"
},
  "geometry": {"coordinates":[82.65286,28.42034],"type":"Point"}
}