{
  "type": "Feature",
  "properties": {
    "gn:admin1_code":"MR",
    "gn:admin2_code":"12",
    "gn:admin3_code":"53",
    "gn:admin4_code":"530014",
    "gn:asciiname":"Thumpaki",
    "gn:country_code":"NP",
    "gn:dem":1117,
    "gn:feature_class":"P",
    "gn:feature_code":"PPLL",
    "gn:name":"Thumpaki",
    "gn:population":0,
    "gn:timezone":"Asia/Kathmandu",
    "iso:country":"NP",
    "wof:name":"Thumpaki",
    "wof:placetype":"locality"
},
  "geometry": {"coordinates":[82.63682,28.22423],"type":"Point"}
}