{
  "type": "Feature",
  "properties": {
    "gn:admin1_code":"WR",
    "gn:admin2_code":"3",
    "gn:admin3_code":"44",
    "gn:admin4_code":"440031.0",
    "gn:asciiname":"Chhahadi",
    "gn:country_code":"NP",
    "gn:dem":858,
    "gn:feature_class":"P",
    "gn:feature_code":"PPLL",
    "gn:name":"Chhahadi",
    "gn:population":0,
    "gn:timezone":"Asia/Kathmandu",
    "iso:country":"NP",
    "wof:name":"Chhahadi",
    "wof:placetype":"locality"
},
  "geometry": {"coordinates":[83.64426999999998,28.14341],"type":"Point"}
}