{
  "type": "Feature",
  "properties": {
    "gn:admin1_code":"CR",
    "gn:admin2_code":"5",
    "gn:admin3_code":"17.0",
    "gn:admin4_code":"170089.0",
    "gn:asciiname":"Hathmunda Labhakatol",
    "gn:country_code":"NP",
    "gn:dem":86,
    "gn:feature_class":"P",
    "gn:feature_code":"PPLL",
    "gn:name":"Hathmunda Labhakatol",
    "gn:population":0,
    "gn:timezone":"Asia/Kathmandu",
    "iso:country":"NP",
    "wof:name":"Hathmunda Labhakatol",
    "wof:placetype":"locality"
},
  "geometry": {"coordinates":[86.16381,26.73381],"type":"Point"}
}