{
  "type": "Feature",
  "properties": {
    "gn:admin1_code":"FR",
    "gn:admin2_code":"9",
    "gn:admin3_code":"72.0",
    "gn:admin4_code":"720009.0",
    "gn:asciiname":"Sisne",
    "gn:country_code":"NP",
    "gn:dem":852,
    "gn:feature_class":"P",
    "gn:feature_code":"PPLL",
    "gn:name":"Sisne",
    "gn:population":0,
    "gn:timezone":"Asia/Kathmandu",
    "iso:country":"NP",
    "name:ceb_x_preferred":[
        "Sisne"
    ],
    "name:fra_x_preferred":[
        "Sisne"
    ],
    "name:mai_x_preferred":[
        "\u0938\u093f\u0938\u094d\u0928\u0947"
    ],
    "name:msa_x_preferred":[
        "Sisne"
    ],
    "name:nep_x_preferred":[
        "\u0938\u093f\u0938\u094d\u0928\u0947"
    ],
    "name:new_x_preferred":[
        "\u0938\u093f\u0938\u094d\u0928\u0947"
    ],
    "name:pol_x_preferred":[
        "Sisne"
    ],
    "wof:name":"Sisne",
    "wof:placetype":"locality"
},
  "geometry": {"coordinates":[80.45909,28.99645],"type":"Point"}
}