{
  "type": "Feature",
  "properties": {
    "gn:admin1_code":"WR",
    "gn:admin2_code":"8",
    "gn:admin3_code":"46.0",
    "gn:admin4_code":"460051.0",
    "gn:asciiname":"Juniyagaun",
    "gn:country_code":"NP",
    "gn:dem":1632,
    "gn:feature_class":"P",
    "gn:feature_code":"PPLL",
    "gn:name":"Juniyagaun",
    "gn:population":0,
    "gn:timezone":"Asia/Kathmandu",
    "iso:country":"NP",
    "wof:name":"Juniyagaun",
    "wof:placetype":"locality"
},
  "geometry": {"coordinates":[83.43018000000002,28.05857],"type":"Point"}
}