{
  "type": "Feature",
  "properties": {
    "gn:admin1_code":"FR",
    "gn:admin2_code":"9",
    "gn:admin3_code":"75.0",
    "gn:admin4_code":"750002.0",
    "gn:asciiname":"Talchora",
    "gn:country_code":"NP",
    "gn:dem":984,
    "gn:feature_class":"P",
    "gn:feature_code":"PPLL",
    "gn:name":"Talchora",
    "gn:population":0,
    "gn:timezone":"Asia/Kathmandu",
    "iso:country":"NP",
    "wof:name":"Talchora",
    "wof:placetype":"locality"
},
  "geometry": {"coordinates":[80.53265999999998,29.67361],"type":"Point"}
}