{
  "type": "Feature",
  "properties": {
    "gn:admin1_code":"MR",
    "gn:admin2_code":"2",
    "gn:admin3_code":"60.0",
    "gn:admin4_code":"600022.0",
    "gn:asciiname":"Shirpali",
    "gn:country_code":"NP",
    "gn:dem":1944,
    "gn:feature_class":"P",
    "gn:feature_code":"PPLL",
    "gn:name":"Shirpali",
    "gn:population":0,
    "gn:timezone":"Asia/Kathmandu",
    "iso:country":"NP",
    "wof:name":"Shirpali",
    "wof:placetype":"locality"
},
  "geometry": {"coordinates":[81.87703,28.91052],"type":"Point"}
}