{
  "type": "Feature",
  "properties": {
    "gn:gn_country":"NP",
    "gn:gn_fcode":"PPL",
    "gn:gn_pop":24657,
    "gn:population":24657,
    "iso:country":"NP",
    "name:chi_x_preferred":[
        "\u932b\u62c9\u54c8"
    ],
    "name:dut_x_preferred":[
        "Siraha"
    ],
    "name:eng_x_preferred":[
        "Siraha"
    ],
    "name:fre_x_preferred":[
        "Siraha"
    ],
    "name:ger_x_preferred":[
        "Siraha"
    ],
    "name:mai_x_preferred":[
        "\u0938\u093f\u0930\u093e\u0939\u093e \u0928\u0917\u0930\u092a\u093e\u0932\u093f\u0915\u093e"
    ],
    "name:may_x_preferred":[
        "Siraha"
    ],
    "name:nep_x_preferred":[
        "Siraha"
    ],
    "name:new_x_preferred":[
        "\u0938\u093f\u0930\u093e\u0939\u093e \u0928\u0917\u0930\u092a\u093e\u0932\u093f\u0915\u093e"
    ],
    "name:pol_x_preferred":[
        "Siraha"
    ],
    "name:por_x_preferred":[
        "Siraha"
    ],
    "name:rus_x_preferred":[
        "\u0421\u0438\u0440\u0430\u0445\u0430"
    ],
    "name:unk_x_variant":[
        "Shirha"
    ],
    "name:urd_x_preferred":[
        "\u0633\u06cc\u0631\u0627\u06c1\u0627"
    ],
    "qs_pg:aaroncc":"NP",
    "qs_pg:gn_country":"NP",
    "qs_pg:gn_fcode":"PPL",
    "qs_pg:gn_pop":24657,
    "qs_pg:name":"Sir\u0101h\u0101",
    "qs_pg:photos_9r":0,
    "qs_pg:photos_sr":0,
    "qs_pg:pop_sr":7,
    "qs_pg:qs_pg_placetype":"locality",
    "wof:name":"Sir\u0101h\u0101",
    "wof:placetype":"locality",
    "wof:population":24657
},
  "geometry": {"coordinates":[86.20869999999999,26.65411],"type":"Point"}
}