{
  "type": "Feature",
  "properties": {
    "gn:country":"NP",
    "gn:fcode":"PPL",
    "gn:population":24657,
    "iso:country":"NP",
    "name:bho_x_preferred":[
        "\u0938\u093f\u0930\u093e\u0939\u093e"
    ],
    "name:ceb_x_preferred":[
        "Sir\u0101h\u0101"
    ],
    "name:deu_x_preferred":[
        "Siraha"
    ],
    "name:dty_x_preferred":[
        "\u0938\u093f\u0930\u093e\u0939\u093e \u0928\u0917\u0930\u092a\u093e\u0932\u093f\u0915\u093e"
    ],
    "name:eng_x_preferred":[
        "Siraha"
    ],
    "name:fra_x_preferred":[
        "Siraha"
    ],
    "name:heb_x_preferred":[
        "\u05e1\u05d9\u05e8\u05d0\u05d4\u05d4"
    ],
    "name:ita_x_preferred":[
        "Siraha"
    ],
    "name:jpn_x_preferred":[
        "\u30b7\u30e9\u30cf"
    ],
    "name:kur_x_preferred":[
        "Siraha"
    ],
    "name:mai_x_preferred":[
        "\u0938\u093f\u0930\u093e\u0939\u093e \u0928\u0917\u0930\u092a\u093e\u0932\u093f\u0915\u093e"
    ],
    "name:mal_x_preferred":[
        "\u0d38\u0d3f\u0d30\u0d39"
    ],
    "name:msa_x_preferred":[
        "Siraha"
    ],
    "name:nep_x_preferred":[
        "Siraha"
    ],
    "name:nep_x_variant":[
        "\u0938\u093f\u0930\u093e\u0939\u093e \u0928\u0917\u0930\u092a\u093e\u0932\u093f\u0915\u093e"
    ],
    "name:new_x_preferred":[
        "\u0938\u093f\u0930\u093e\u0939\u093e \u0928\u0917\u0930\u092a\u093e\u0932\u093f\u0915\u093e"
    ],
    "name:nld_x_preferred":[
        "Siraha"
    ],
    "name:pol_x_preferred":[
        "Siraha"
    ],
    "name:por_x_preferred":[
        "Siraha"
    ],
    "name:rus_x_preferred":[
        "\u0421\u0438\u0440\u0430\u0445\u0430"
    ],
    "name:und_x_variant":[
        "Shirha"
    ],
    "name:urd_x_preferred":[
        "\u0633\u06cc\u0631\u0627\u06c1\u0627"
    ],
    "name:zho_x_preferred":[
        "\u932b\u62c9\u54c8"
    ],
    "qs_pg:aaroncc":"NP",
    "qs_pg:gn_country":"NP",
    "qs_pg:gn_fcode":"PPL",
    "qs_pg:gn_pop":24657,
    "qs_pg:name":"Sir\u0101h\u0101",
    "qs_pg:photos_9r":0,
    "qs_pg:photos_sr":0,
    "qs_pg:pop_sr":7,
    "qs_pg:qs_pg_placetype":"locality",
    "wof:name":"Sir\u0101h\u0101",
    "wof:placetype":"locality",
    "wof:population":24657
},
  "geometry": {"coordinates":[86.20869999999999,26.65411],"type":"Point"}
}