{
  "type": "Feature",
  "properties": {
    "gn:admin1_code":"WR",
    "gn:admin2_code":"4.0",
    "gn:admin3_code":"38.0",
    "gn:admin4_code":"380026.0",
    "gn:asciiname":"Nayangaun",
    "gn:country_code":"NP",
    "gn:dem":922,
    "gn:feature_class":"P",
    "gn:feature_code":"PPLL",
    "gn:name":"Nayangaun",
    "gn:population":0,
    "gn:timezone":"Asia/Kathmandu",
    "iso:country":"NP",
    "wof:name":"Nayangaun",
    "wof:placetype":"locality"
},
  "geometry": {"coordinates":[84.34228,27.89516],"type":"Point"}
}