{
  "type": "Feature",
  "properties": {
    "gn:admin1_code":"00",
    "gn:asciiname":"Gondal",
    "gn:country_code":"NP",
    "gn:dem":924,
    "gn:feature_class":"P",
    "gn:feature_code":"PPL",
    "gn:name":"Go\u1e45dal",
    "gn:population":0,
    "gn:timezone":"Asia/Kathmandu",
    "iso:country":"NP",
    "name:nep_x_preferred":[
        "Go\u1e45dal"
    ],
    "wof:name":"Gondal",
    "wof:placetype":"locality"
},
  "geometry": {"coordinates":[85.88646,27.31654],"type":"Point"}
}