{
  "type": "Feature",
  "properties": {
    "gn:admin1_code":"FR",
    "gn:admin2_code":"9",
    "gn:admin3_code":"75.0",
    "gn:admin4_code":"750032.0",
    "gn:asciiname":"Kharkagaun",
    "gn:country_code":"NP",
    "gn:dem":1298,
    "gn:feature_class":"P",
    "gn:feature_code":"PPLL",
    "gn:name":"Kharkagaun",
    "gn:population":0,
    "gn:timezone":"Asia/Kathmandu",
    "iso:country":"NP",
    "wof:name":"Kharkagaun",
    "wof:placetype":"locality"
},
  "geometry": {"coordinates":[80.47454,29.66956],"type":"Point"}
}