{
  "type": "Feature",
  "properties": {
    "gn:admin1_code":"WR",
    "gn:admin2_code":"8",
    "gn:admin3_code":"46.0",
    "gn:admin4_code":"460005.0",
    "gn:asciiname":"Thula Bajar",
    "gn:country_code":"NP",
    "gn:dem":799,
    "gn:feature_class":"P",
    "gn:feature_code":"PPLL",
    "gn:name":"Thula Bajar",
    "gn:population":0,
    "gn:timezone":"Asia/Kathmandu",
    "iso:country":"NP",
    "wof:name":"Thula Bajar",
    "wof:placetype":"locality"
},
  "geometry": {"coordinates":[83.59444000000001,28.01207],"type":"Point"}
}