{
  "type": "Feature",
  "properties": {
    "gn:admin1_code":"FR",
    "gn:admin2_code":"9",
    "gn:admin3_code":"74",
    "gn:admin4_code":"740010",
    "gn:asciiname":"Latkawali",
    "gn:country_code":"NP",
    "gn:dem":1131,
    "gn:feature_class":"P",
    "gn:feature_code":"PPLL",
    "gn:name":"Latkawali",
    "gn:population":0,
    "gn:timezone":"Asia/Kathmandu",
    "iso:country":"NP",
    "wof:name":"Latkawali",
    "wof:placetype":"locality"
},
  "geometry": {"coordinates":[80.43725999999999,29.5928],"type":"Point"}
}