{
  "type": "Feature",
  "properties": {
    "gn:admin1_code":"WR",
    "gn:admin2_code":"3",
    "gn:admin3_code":"43",
    "gn:admin4_code":"430016.0",
    "gn:asciiname":"Matheni",
    "gn:country_code":"NP",
    "gn:dem":2522,
    "gn:feature_class":"P",
    "gn:feature_code":"PPLL",
    "gn:name":"Matheni",
    "gn:population":0,
    "gn:timezone":"Asia/Kathmandu",
    "iso:country":"NP",
    "wof:name":"Matheni",
    "wof:placetype":"locality"
},
  "geometry": {"coordinates":[83.64879000000001,28.4147],"type":"Point"}
}