{
  "type": "Feature",
  "properties": {
    "gn:admin1_code":"MR",
    "gn:admin2_code":"2.0",
    "gn:admin3_code":"59.0",
    "gn:admin4_code":"590029.0",
    "gn:asciiname":"Simali",
    "gn:country_code":"NP",
    "gn:dem":691,
    "gn:feature_class":"P",
    "gn:feature_code":"PPLL",
    "gn:name":"Simali",
    "gn:population":0,
    "gn:timezone":"Asia/Kathmandu",
    "iso:country":"NP",
    "wof:name":"Simali",
    "wof:placetype":"locality"
},
  "geometry": {"coordinates":[81.01841,28.93685],"type":"Point"}
}