{
  "type": "Feature",
  "properties": {
    "gn:admin1_code":"ER",
    "gn:admin2_code":"7",
    "gn:admin3_code":"9",
    "gn:admin4_code":"90029",
    "gn:asciiname":"Bangdewa",
    "gn:country_code":"NP",
    "gn:dem":825,
    "gn:feature_class":"P",
    "gn:feature_code":"PPLL",
    "gn:name":"Bangdewa",
    "gn:population":0,
    "gn:timezone":"Asia/Kathmandu",
    "iso:country":"NP",
    "wof:name":"Bangdewa",
    "wof:placetype":"locality"
},
  "geometry": {"coordinates":[87.09182,27.46653],"type":"Point"}
}