{
  "type": "Feature",
  "properties": {
    "gn:admin1_code":"ER",
    "gn:admin2_code":"13",
    "gn:admin3_code":"13",
    "gn:admin4_code":"130074",
    "gn:asciiname":"Bagpachyang",
    "gn:country_code":"NP",
    "gn:dem":1820,
    "gn:feature_class":"P",
    "gn:feature_code":"PPLL",
    "gn:name":"Bagpachyang",
    "gn:population":0,
    "gn:timezone":"Asia/Kathmandu",
    "iso:country":"NP",
    "wof:name":"Bagpachyang",
    "wof:placetype":"locality"
},
  "geometry": {"coordinates":[86.87732,27.07892],"type":"Point"}
}