{
  "type": "Feature",
  "properties": {
    "gn:admin1_code":"FR",
    "gn:admin2_code":"14",
    "gn:admin3_code":"71.0",
    "gn:admin4_code":"710028.0",
    "gn:asciiname":"Badera",
    "gn:country_code":"NP",
    "gn:dem":726,
    "gn:feature_class":"P",
    "gn:feature_code":"PPLL",
    "gn:name":"Badera",
    "gn:population":0,
    "gn:timezone":"Asia/Kathmandu",
    "iso:country":"NP",
    "wof:name":"Badera",
    "wof:placetype":"locality"
},
  "geometry": {"coordinates":[80.77214000000002,28.98287],"type":"Point"}
}