{
  "type": "Feature",
  "properties": {
    "gn:admin1_code":"MR",
    "gn:admin2_code":"2",
    "gn:admin3_code":"60.0",
    "gn:admin4_code":"600051.0",
    "gn:asciiname":"Dhanbari",
    "gn:country_code":"NP",
    "gn:dem":1778,
    "gn:feature_class":"P",
    "gn:feature_code":"PPLL",
    "gn:name":"Dhanbari",
    "gn:population":0,
    "gn:timezone":"Asia/Kathmandu",
    "iso:country":"NP",
    "wof:name":"Dhanbari",
    "wof:placetype":"locality"
},
  "geometry": {"coordinates":[81.62617,28.70647],"type":"Point"}
}