{
  "type": "Feature",
  "properties": {
    "gn:admin1_code":"CR",
    "gn:admin2_code":"1",
    "gn:admin3_code":"23",
    "gn:admin4_code":"230058",
    "gn:asciiname":"Pauwathok",
    "gn:country_code":"NP",
    "gn:dem":1104,
    "gn:feature_class":"P",
    "gn:feature_code":"PPLL",
    "gn:name":"Pauwathok",
    "gn:population":0,
    "gn:timezone":"Asia/Kathmandu",
    "iso:country":"NP",
    "wof:name":"Pauwathok",
    "wof:placetype":"locality"
},
  "geometry": {"coordinates":[85.71304000000001,27.67884],"type":"Point"}
}