{
  "type": "Feature",
  "properties": {
    "gn:admin1_code":"CR",
    "gn:admin2_code":"1",
    "gn:admin3_code":"23",
    "gn:admin4_code":"230004",
    "gn:asciiname":"Banskharka",
    "gn:country_code":"NP",
    "gn:dem":1296,
    "gn:feature_class":"P",
    "gn:feature_code":"PPLL",
    "gn:name":"Banskharka",
    "gn:population":0,
    "gn:timezone":"Asia/Kathmandu",
    "iso:country":"NP",
    "wof:name":"Banskharka",
    "wof:placetype":"locality"
},
  "geometry": {"coordinates":[85.60687,27.88938],"type":"Point"}
}