{
  "type": "Feature",
  "properties": {
    "gn:admin1_code":"ER",
    "gn:admin2_code":"10",
    "gn:admin3_code":"2",
    "gn:admin4_code":"20039",
    "gn:asciiname":"Mude",
    "gn:country_code":"NP",
    "gn:dem":1858,
    "gn:feature_class":"P",
    "gn:feature_code":"PPLL",
    "gn:name":"Mude",
    "gn:population":0,
    "gn:timezone":"Asia/Kathmandu",
    "iso:country":"NP",
    "wof:name":"Mude",
    "wof:placetype":"locality"
},
  "geometry": {"coordinates":[87.84713000000001,27.23737],"type":"Point"}
}