{
  "type": "Feature",
  "properties": {
    "gn:admin1_code":"WR",
    "gn:admin2_code":"8",
    "gn:admin3_code":"47",
    "gn:admin4_code":"470029",
    "gn:asciiname":"Maslang",
    "gn:country_code":"NP",
    "gn:dem":797,
    "gn:feature_class":"P",
    "gn:feature_code":"PPLL",
    "gn:name":"Maslang",
    "gn:population":0,
    "gn:timezone":"Asia/Kathmandu",
    "iso:country":"NP",
    "wof:name":"Maslang",
    "wof:placetype":"locality"
},
  "geometry": {"coordinates":[83.72354,27.88233],"type":"Point"}
}