{
  "type": "Feature",
  "properties": {
    "gn:admin1_code":"MR",
    "gn:admin2_code":"12",
    "gn:admin3_code":"56.0",
    "gn:admin4_code":"560029.0",
    "gn:asciiname":"Palase",
    "gn:country_code":"NP",
    "gn:dem":671,
    "gn:feature_class":"P",
    "gn:feature_code":"PPLL",
    "gn:name":"Palase",
    "gn:population":0,
    "gn:timezone":"Asia/Kathmandu",
    "iso:country":"NP",
    "wof:name":"Palase",
    "wof:placetype":"locality"
},
  "geometry": {"coordinates":[82.52774000000002,27.9887],"type":"Point"}
}