{
  "type": "Feature",
  "properties": {
    "gn:admin1_code":"CR",
    "gn:admin2_code":"1",
    "gn:admin3_code":"28",
    "gn:admin4_code":"280005",
    "gn:asciiname":"Khorsal",
    "gn:country_code":"NP",
    "gn:dem":1914,
    "gn:feature_class":"P",
    "gn:feature_code":"PPLL",
    "gn:name":"Khorsal",
    "gn:population":0,
    "gn:timezone":"Asia/Kathmandu",
    "iso:country":"NP",
    "wof:name":"Khorsal",
    "wof:placetype":"locality"
},
  "geometry": {"coordinates":[85.46396,27.91124000000001],"type":"Point"}
}