{
  "type": "Feature",
  "properties": {
    "gn:admin1_code":"FR",
    "gn:admin2_code":"9",
    "gn:admin3_code":"74",
    "gn:admin4_code":"740026",
    "gn:asciiname":"Jhokali",
    "gn:country_code":"NP",
    "gn:dem":1822,
    "gn:feature_class":"P",
    "gn:feature_code":"PPLL",
    "gn:name":"Jhokali",
    "gn:population":0,
    "gn:timezone":"Asia/Kathmandu",
    "iso:country":"NP",
    "wof:name":"Jhokali",
    "wof:placetype":"locality"
},
  "geometry": {"coordinates":[80.50990999999998,29.54129],"type":"Point"}
}