{
  "type": "Feature",
  "properties": {
    "gn:admin1_code":"MR",
    "gn:admin2_code":"12",
    "gn:admin3_code":"56.0",
    "gn:admin4_code":"560029.0",
    "gn:asciiname":"Suka",
    "gn:country_code":"NP",
    "gn:dem":580,
    "gn:feature_class":"P",
    "gn:feature_code":"PPLL",
    "gn:name":"Suka",
    "gn:population":0,
    "gn:timezone":"Asia/Kathmandu",
    "iso:country":"NP",
    "name:ceb_x_preferred":[
        "Suka"
    ],
    "name:deu_x_preferred":[
        "Suka"
    ],
    "name:nld_x_preferred":[
        "Suka"
    ],
    "name:pol_x_preferred":[
        "Suka"
    ],
    "name:rus_x_preferred":[
        "\u0421\u0443\u043a\u0430"
    ],
    "name:slk_x_preferred":[
        "Suka"
    ],
    "name:swe_x_preferred":[
        "Suka"
    ],
    "name:tgl_x_preferred":[
        "Suka"
    ],
    "name:ukr_x_preferred":[
        "\u0421\u0443\u043a\u0430"
    ],
    "wof:name":"Suka",
    "wof:placetype":"locality"
},
  "geometry": {"coordinates":[82.59716,27.97688],"type":"Point"}
}