{
  "type": "Feature",
  "properties": {
    "gn:admin1_code":"CR",
    "gn:admin2_code":"1",
    "gn:admin3_code":"30.0",
    "gn:admin4_code":"300041.0",
    "gn:asciiname":"Sanagaun",
    "gn:country_code":"NP",
    "gn:dem":688,
    "gn:feature_class":"P",
    "gn:feature_code":"PPLL",
    "gn:name":"Sanagaun",
    "gn:population":0,
    "gn:timezone":"Asia/Kathmandu",
    "iso:country":"NP",
    "name:ceb_x_preferred":[
        "Sanagau"
    ],
    "name:mai_x_preferred":[
        "\u0938\u093e\u0928\u093e \u0917\u093e\u0909\u0901"
    ],
    "name:msa_x_preferred":[
        "Sanagau"
    ],
    "name:new_x_preferred":[
        "\u0938\u093e\u0928\u093e\u0917\u093e\u0909\u0902"
    ],
    "name:pol_x_preferred":[
        "Sanagau"
    ],
    "wof:name":"Sanagaun",
    "wof:placetype":"locality"
},
  "geometry": {"coordinates":[84.8241,28.02967],"type":"Point"}
}