{
  "type": "Feature",
  "properties": {
    "gn:admin1_code":"CR",
    "gn:admin2_code":"1",
    "gn:admin3_code":"30.0",
    "gn:admin4_code":"300041.0",
    "gn:asciiname":"Sanagaun",
    "gn:country_code":"NP",
    "gn:dem":688,
    "gn:feature_class":"P",
    "gn:feature_code":"PPLL",
    "gn:name":"Sanagaun",
    "gn:population":0,
    "gn:timezone":"Asia/Kathmandu",
    "iso:country":"NP",
    "wof:name":"Sanagaun",
    "wof:placetype":"locality"
},
  "geometry": {"coordinates":[84.8241,28.02967],"type":"Point"}
}