{
  "type": "Feature",
  "properties": {
    "gn:admin1_code":"CR",
    "gn:admin2_code":"11",
    "gn:admin3_code":"31",
    "gn:admin4_code":"310028",
    "gn:asciiname":"Lendanda",
    "gn:country_code":"NP",
    "gn:dem":871,
    "gn:feature_class":"P",
    "gn:feature_code":"PPLL",
    "gn:name":"Lendanda",
    "gn:population":0,
    "gn:timezone":"Asia/Kathmandu",
    "iso:country":"NP",
    "wof:name":"Lendanda",
    "wof:placetype":"locality"
},
  "geometry": {"coordinates":[85.20368000000001,27.41907],"type":"Point"}
}