{
  "type": "Feature",
  "properties": {
    "gn:admin1_code":"MR",
    "gn:admin2_code":"6",
    "gn:admin3_code":"65",
    "gn:admin4_code":"650014",
    "gn:asciiname":"Pina",
    "gn:country_code":"NP",
    "gn:dem":2353,
    "gn:feature_class":"P",
    "gn:feature_code":"PPLL",
    "gn:name":"Pina",
    "gn:population":0,
    "gn:timezone":"Asia/Kathmandu",
    "iso:country":"NP",
    "name:hun_x_preferred":[
        "Pina"
    ],
    "name:mai_x_preferred":[
        "\u092a\u093f\u0928\u093e \u0917\u093e\u0935\u093f\u0938"
    ],
    "name:msa_x_preferred":[
        "Pina"
    ],
    "name:nep_x_preferred":[
        "\u092a\u093f\u0928\u093e \u0917\u093e\u0935\u093f\u0938"
    ],
    "name:pol_x_preferred":[
        "Pina"
    ],
    "wof:name":"Pina",
    "wof:placetype":"locality"
},
  "geometry": {"coordinates":[82.14706,29.49448],"type":"Point"}
}