{
  "type": "Feature",
  "properties": {
    "gn:admin1_code":"MR",
    "gn:admin2_code":"12",
    "gn:admin3_code":"55",
    "gn:admin4_code":"550021",
    "gn:asciiname":"Pharula",
    "gn:country_code":"NP",
    "gn:dem":1440,
    "gn:feature_class":"P",
    "gn:feature_code":"PPLL",
    "gn:name":"Pharula",
    "gn:population":0,
    "gn:timezone":"Asia/Kathmandu",
    "iso:country":"NP",
    "wof:name":"Pharula",
    "wof:placetype":"locality"
},
  "geometry": {"coordinates":[82.06865000000001,28.32565],"type":"Point"}
}