{
  "type": "Feature",
  "properties": {
    "gn:admin1_code":"CR",
    "gn:admin2_code":"5",
    "gn:admin3_code":"21",
    "gn:admin4_code":"210028",
    "gn:asciiname":"Phalampokhari",
    "gn:country_code":"NP",
    "gn:dem":1933,
    "gn:feature_class":"P",
    "gn:feature_code":"PPLL",
    "gn:name":"Phalampokhari",
    "gn:population":0,
    "gn:timezone":"Asia/Kathmandu",
    "iso:country":"NP",
    "wof:name":"Phalampokhari",
    "wof:placetype":"locality"
},
  "geometry": {"coordinates":[85.89796,27.47168],"type":"Point"}
}