{
  "type": "Feature",
  "properties": {
    "gn:admin1_code":"ER",
    "gn:admin2_code":"13",
    "gn:admin3_code":"13",
    "gn:admin4_code":"130063",
    "gn:asciiname":"Salme",
    "gn:country_code":"NP",
    "gn:dem":1442,
    "gn:feature_class":"P",
    "gn:feature_code":"PPLL",
    "gn:name":"Salme",
    "gn:population":0,
    "gn:timezone":"Asia/Kathmandu",
    "iso:country":"NP",
    "wof:name":"Salme",
    "wof:placetype":"locality"
},
  "geometry": {"coordinates":[86.85235,27.18179],"type":"Point"}
}