{
  "type": "Feature",
  "properties": {
    "gn:admin1_code":"WR",
    "gn:admin2_code":"8",
    "gn:admin3_code":"50.0",
    "gn:admin4_code":"500023.0",
    "gn:asciiname":"Jugadihawa",
    "gn:country_code":"NP",
    "gn:dem":129,
    "gn:feature_class":"P",
    "gn:feature_code":"PPLL",
    "gn:name":"Jugadihawa",
    "gn:population":0,
    "gn:timezone":"Asia/Kathmandu",
    "iso:country":"NP",
    "wof:name":"Jugadihawa",
    "wof:placetype":"locality"
},
  "geometry": {"coordinates":[82.99979,27.71379],"type":"Point"}
}