{
  "type": "Feature",
  "properties": {
    "gn:admin1_code":"ER",
    "gn:admin2_code":"7",
    "gn:admin3_code":"5",
    "gn:admin4_code":"50054",
    "gn:asciiname":"Phaiba",
    "gn:country_code":"NP",
    "gn:dem":1431,
    "gn:feature_class":"P",
    "gn:feature_code":"PPLL",
    "gn:name":"Phaiba",
    "gn:population":0,
    "gn:timezone":"Asia/Kathmandu",
    "iso:country":"NP",
    "wof:name":"Phaiba",
    "wof:placetype":"locality"
},
  "geometry": {"coordinates":[87.4954,26.85766],"type":"Point"}
}