{
  "type": "Feature",
  "properties": {
    "gn:admin1_code":"MR",
    "gn:admin2_code":"2.0",
    "gn:admin3_code":"59.0",
    "gn:admin4_code":"590050.0",
    "gn:asciiname":"Kholi Bajar",
    "gn:country_code":"NP",
    "gn:dem":267,
    "gn:feature_class":"P",
    "gn:feature_code":"PPLL",
    "gn:name":"Kholi Bajar",
    "gn:population":0,
    "gn:timezone":"Asia/Kathmandu",
    "iso:country":"NP",
    "wof:name":"Kholi Bajar",
    "wof:placetype":"locality"
},
  "geometry": {"coordinates":[81.27683,28.7285],"type":"Point"}
}