{
  "type": "Feature",
  "properties": {
    "gn:admin1_code":"ER",
    "gn:admin2_code":"7",
    "gn:admin3_code":"6",
    "gn:admin4_code":"60011",
    "gn:asciiname":"Kalindra Bajar",
    "gn:country_code":"NP",
    "gn:dem":132,
    "gn:feature_class":"P",
    "gn:feature_code":"PPLL",
    "gn:name":"Kalindra Bajar",
    "gn:population":0,
    "gn:timezone":"Asia/Kathmandu",
    "iso:country":"NP",
    "wof:name":"Kalindra Bajar",
    "wof:placetype":"locality"
},
  "geometry": {"coordinates":[87.17789,26.77677000000001],"type":"Point"}
}