{
  "type": "Feature",
  "properties": {
    "gn:admin1_code":"ER",
    "gn:admin2_code":"13.0",
    "gn:admin3_code":"14.0",
    "gn:admin4_code":"140017.0",
    "gn:asciiname":"Rajabas",
    "gn:country_code":"NP",
    "gn:dem":219,
    "gn:feature_class":"P",
    "gn:feature_code":"PPLL",
    "gn:name":"Rajabas",
    "gn:population":0,
    "gn:timezone":"Asia/Kathmandu",
    "iso:country":"NP",
    "wof:name":"Rajabas",
    "wof:placetype":"locality"
},
  "geometry": {"coordinates":[86.36847,26.95761],"type":"Point"}
}