{
  "type": "Feature",
  "properties": {
    "gn:admin1_code":"WR",
    "gn:admin2_code":"4",
    "gn:admin3_code":"40.0",
    "gn:admin4_code":"400023.0",
    "gn:asciiname":"Lumle",
    "gn:country_code":"NP",
    "gn:dem":1781,
    "gn:feature_class":"P",
    "gn:feature_code":"PPLL",
    "gn:name":"Lumle",
    "gn:population":0,
    "gn:timezone":"Asia/Kathmandu",
    "iso:country":"NP",
    "name:ceb_x_preferred":[
        "Lumle"
    ],
    "name:deu_x_preferred":[
        "Lumle"
    ],
    "name:mai_x_preferred":[
        "\u0932\u0941\u092e\u094d\u0932\u0947"
    ],
    "name:msa_x_preferred":[
        "Lumle"
    ],
    "name:nep_x_preferred":[
        "\u0932\u0941\u092e\u094d\u0932\u0947"
    ],
    "name:new_x_preferred":[
        "\u0932\u0941\u092e\u094d\u0932\u0947"
    ],
    "name:pol_x_preferred":[
        "Lumle"
    ],
    "name:slv_x_preferred":[
        "Lumle"
    ],
    "wof:name":"Lumle",
    "wof:placetype":"locality"
},
  "geometry": {"coordinates":[83.80465,28.30249],"type":"Point"}
}