{
  "type": "Feature",
  "properties": {
    "gn:admin1_code":"ER",
    "gn:admin2_code":"7",
    "gn:admin3_code":"9",
    "gn:admin4_code":"90025.0",
    "gn:asciiname":"Bhainsikharka",
    "gn:country_code":"NP",
    "gn:dem":1761,
    "gn:feature_class":"P",
    "gn:feature_code":"PPLL",
    "gn:name":"Bhainsikharka",
    "gn:population":0,
    "gn:timezone":"Asia/Kathmandu",
    "iso:country":"NP",
    "wof:name":"Bhainsikharka",
    "wof:placetype":"locality"
},
  "geometry": {"coordinates":[87.35422,27.58318],"type":"Point"}
}