{
  "type": "Feature",
  "properties": {
    "gn:admin1_code":"WR",
    "gn:admin2_code":"8",
    "gn:admin3_code":"48",
    "gn:admin4_code":"480017",
    "gn:asciiname":"Ramche",
    "gn:country_code":"NP",
    "gn:dem":1229,
    "gn:feature_class":"P",
    "gn:feature_code":"PPLL",
    "gn:name":"Ramche",
    "gn:population":0,
    "gn:timezone":"Asia/Kathmandu",
    "iso:country":"NP",
    "name:fra_x_preferred":[
        "Ramche"
    ],
    "name:new_x_preferred":[
        "\u0930\u093e\u092e\u094d\u091a\u0947"
    ],
    "name:pol_x_preferred":[
        "Ramche"
    ],
    "wof:name":"Ramche",
    "wof:placetype":"locality"
},
  "geometry": {"coordinates":[84.10991,27.76879000000001],"type":"Point"}
}