{
  "type": "Feature",
  "properties": {
    "gn:admin1_code":"MR",
    "gn:admin2_code":"12",
    "gn:admin3_code":"54",
    "gn:admin4_code":"540031",
    "gn:asciiname":"Arsekada",
    "gn:country_code":"NP",
    "gn:dem":1464,
    "gn:feature_class":"P",
    "gn:feature_code":"PPLL",
    "gn:name":"Arsekada",
    "gn:population":0,
    "gn:timezone":"Asia/Kathmandu",
    "iso:country":"NP",
    "wof:name":"Arsekada",
    "wof:placetype":"locality"
},
  "geometry": {"coordinates":[82.23366,28.67804000000001],"type":"Point"}
}