{
  "type": "Feature",
  "properties": {
    "gn:admin1_code":"FR",
    "gn:admin2_code":"14",
    "gn:admin3_code":"71.0",
    "gn:admin4_code":"710007.0",
    "gn:asciiname":"Bhojpur",
    "gn:country_code":"NP",
    "gn:dem":193,
    "gn:feature_class":"P",
    "gn:feature_code":"PPLL",
    "gn:name":"Bhojpur",
    "gn:population":0,
    "gn:timezone":"Asia/Kathmandu",
    "iso:country":"NP",
    "name:ara_x_preferred":[
        "\u0628\u0648\u062c \u0628\u0648\u0631"
    ],
    "name:ceb_x_preferred":[
        "Bhojpur"
    ],
    "name:deu_x_preferred":[
        "Bhojpur"
    ],
    "name:fra_x_preferred":[
        "Bhojpur"
    ],
    "name:hin_x_preferred":[
        "\u092d\u094b\u091c\u092a\u0941\u0930"
    ],
    "name:nld_x_preferred":[
        "Bhojpur"
    ],
    "name:swe_x_preferred":[
        "Bhojpur"
    ],
    "name:vie_x_preferred":[
        "Bhojpur"
    ],
    "wof:name":"Bhojpur",
    "wof:placetype":"locality"
},
  "geometry": {"coordinates":[80.71840999999998,28.77146],"type":"Point"}
}