{
  "type": "Feature",
  "properties": {
    "gn:admin1_code":"ER",
    "gn:admin2_code":"10",
    "gn:admin3_code":"2",
    "gn:admin4_code":"20013",
    "gn:asciiname":"Tilkeni",
    "gn:country_code":"NP",
    "gn:dem":1085,
    "gn:feature_class":"P",
    "gn:feature_code":"PPLL",
    "gn:name":"Tilkeni",
    "gn:population":0,
    "gn:timezone":"Asia/Kathmandu",
    "iso:country":"NP",
    "wof:name":"Tilkeni",
    "wof:placetype":"locality"
},
  "geometry": {"coordinates":[87.5745,26.94175],"type":"Point"}
}