{
  "type": "Feature",
  "properties": {
    "gn:admin1_code":"MR",
    "gn:admin2_code":"12",
    "gn:admin3_code":"55",
    "gn:admin4_code":"550029",
    "gn:asciiname":"Dangdungge",
    "gn:country_code":"NP",
    "gn:dem":1103,
    "gn:feature_class":"P",
    "gn:feature_code":"PPLL",
    "gn:name":"Dangdungge",
    "gn:population":0,
    "gn:timezone":"Asia/Kathmandu",
    "iso:country":"NP",
    "wof:name":"Dangdungge",
    "wof:placetype":"locality"
},
  "geometry": {"coordinates":[82.14113,28.28308],"type":"Point"}
}