{
  "type": "Feature",
  "properties": {
    "gn:admin1_code":"WR",
    "gn:admin2_code":"3",
    "gn:admin3_code":"45.0",
    "gn:admin4_code":"450013.0",
    "gn:asciiname":"Chhapdanda",
    "gn:country_code":"NP",
    "gn:dem":1591,
    "gn:feature_class":"P",
    "gn:feature_code":"PPLL",
    "gn:name":"Chhapdanda",
    "gn:population":0,
    "gn:timezone":"Asia/Kathmandu",
    "iso:country":"NP",
    "wof:name":"Chhapdanda",
    "wof:placetype":"locality"
},
  "geometry": {"coordinates":[83.14555,28.37014000000001],"type":"Point"}
}