{
  "type": "Feature",
  "properties": {
    "gn:admin1_code":"ER",
    "gn:admin2_code":"10",
    "gn:admin3_code":"2",
    "gn:admin4_code":"20020",
    "gn:asciiname":"Lumbingdang",
    "gn:country_code":"NP",
    "gn:dem":1628,
    "gn:feature_class":"P",
    "gn:feature_code":"PPLL",
    "gn:name":"Lumbingdang",
    "gn:population":0,
    "gn:timezone":"Asia/Kathmandu",
    "iso:country":"NP",
    "wof:name":"Lumbingdang",
    "wof:placetype":"locality"
},
  "geometry": {"coordinates":[87.91288,27.1893],"type":"Point"}
}