{
  "type": "Feature",
  "properties": {
    "gn:admin1_code":"WR",
    "gn:admin2_code":"3",
    "gn:admin3_code":"43",
    "gn:admin4_code":"430029",
    "gn:asciiname":"Malka Pahad",
    "gn:country_code":"NP",
    "gn:dem":3158,
    "gn:feature_class":"P",
    "gn:feature_code":"PPLL",
    "gn:name":"Malka Pahad",
    "gn:population":0,
    "gn:timezone":"Asia/Kathmandu",
    "iso:country":"NP",
    "wof:name":"Malka Pahad",
    "wof:placetype":"locality"
},
  "geometry": {"coordinates":[83.44221999999998,28.46106],"type":"Point"}
}