{
  "type": "Feature",
  "properties": {
    "gn:admin1_code":"CR",
    "gn:admin2_code":"11",
    "gn:admin3_code":"31",
    "gn:admin4_code":"310042",
    "gn:asciiname":"Kiteni",
    "gn:country_code":"NP",
    "gn:dem":1121,
    "gn:feature_class":"P",
    "gn:feature_code":"PPLL",
    "gn:name":"Kiteni",
    "gn:population":0,
    "gn:timezone":"Asia/Kathmandu",
    "iso:country":"NP",
    "wof:name":"Kiteni",
    "wof:placetype":"locality"
},
  "geometry": {"coordinates":[85.16928,27.4634],"type":"Point"}
}