{
  "type": "Feature",
  "properties": {
    "gn:admin1_code":"FR",
    "gn:admin2_code":"9",
    "gn:admin3_code":"75.0",
    "gn:admin4_code":"750041.0",
    "gn:asciiname":"Dinsee",
    "gn:country_code":"NP",
    "gn:dem":633,
    "gn:feature_class":"P",
    "gn:feature_code":"PPLL",
    "gn:name":"Dinsee",
    "gn:population":0,
    "gn:timezone":"Asia/Kathmandu",
    "iso:country":"NP",
    "wof:name":"Dinsee",
    "wof:placetype":"locality"
},
  "geometry": {"coordinates":[80.3916,29.75905],"type":"Point"}
}