{
  "type": "Feature",
  "properties": {
    "gn:admin1_code":"FR",
    "gn:admin2_code":"14",
    "gn:admin3_code":"71.0",
    "gn:admin4_code":"710015.0",
    "gn:asciiname":"Bandrekhal (Birendrapur)",
    "gn:country_code":"NP",
    "gn:dem":281,
    "gn:feature_class":"P",
    "gn:feature_code":"PPLL",
    "gn:name":"Bandrekhal (Birendrapur)",
    "gn:population":0,
    "gn:timezone":"Asia/Kathmandu",
    "iso:country":"NP",
    "wof:name":"Bandrekhal (Birendrapur)",
    "wof:placetype":"locality"
},
  "geometry": {"coordinates":[80.51744000000002,28.9134],"type":"Point"}
}