{
  "type": "Feature",
  "properties": {
    "gn:admin1_code":"CR",
    "gn:admin2_code":"1",
    "gn:admin3_code":"28",
    "gn:admin4_code":"280025",
    "gn:asciiname":"Lapse",
    "gn:country_code":"NP",
    "gn:dem":1469,
    "gn:feature_class":"P",
    "gn:feature_code":"PPLL",
    "gn:name":"Lapse",
    "gn:population":0,
    "gn:timezone":"Asia/Kathmandu",
    "iso:country":"NP",
    "wof:name":"Lapse",
    "wof:placetype":"locality"
},
  "geometry": {"coordinates":[85.11020000000001,27.83322],"type":"Point"}
}