{
  "type": "Feature",
  "properties": {
    "gn:admin1_code":"00",
    "gn:asciiname":"Sunkhani",
    "gn:country_code":"NP",
    "gn:dem":1379,
    "gn:feature_class":"P",
    "gn:feature_code":"PPL",
    "gn:name":"Sunkh\u0101ni\u0307\u0304",
    "gn:population":0,
    "gn:timezone":"Asia/Kathmandu",
    "iso:country":"NP",
    "name:fra_x_preferred":[
        "Sunkhani"
    ],
    "name:nep_x_preferred":[
        "Sunkh\u0101ni\u0307\u0304"
    ],
    "name:nep_x_variant":[
        "Sunkh\u0101n\u012b"
    ],
    "name:new_x_preferred":[
        "\u0938\u0941\u0928 \u0916\u093e\u0928\u0940"
    ],
    "name:pol_x_preferred":[
        "Sunkhani"
    ],
    "wof:name":"Sunkhani",
    "wof:placetype":"locality"
},
  "geometry": {"coordinates":[85.88145,27.79836],"type":"Point"}
}