{
  "type": "Feature",
  "properties": {
    "gn:admin1_code":"MR",
    "gn:admin2_code":"6",
    "gn:admin3_code":"65",
    "gn:admin4_code":"650017",
    "gn:asciiname":"Siddigad Goth",
    "gn:country_code":"NP",
    "gn:dem":1414,
    "gn:feature_class":"P",
    "gn:feature_code":"PPLL",
    "gn:name":"Siddigad Goth",
    "gn:population":0,
    "gn:timezone":"Asia/Kathmandu",
    "iso:country":"NP",
    "wof:name":"Siddigad Goth",
    "wof:placetype":"locality"
},
  "geometry": {"coordinates":[81.94001999999998,29.60821],"type":"Point"}
}