{
  "type": "Feature",
  "properties": {
    "gn:admin1_code":"ER",
    "gn:admin2_code":"7.0",
    "gn:admin3_code":"10.0",
    "gn:admin4_code":"100003.0",
    "gn:asciiname":"Kanyadaha",
    "gn:country_code":"NP",
    "gn:dem":1334,
    "gn:feature_class":"P",
    "gn:feature_code":"PPLL",
    "gn:name":"Kanyadaha",
    "gn:population":0,
    "gn:timezone":"Asia/Kathmandu",
    "iso:country":"NP",
    "wof:name":"Kanyadaha",
    "wof:placetype":"locality"
},
  "geometry": {"coordinates":[86.98801999999998,27.07529000000001],"type":"Point"}
}