{
  "type": "Feature",
  "properties": {
    "gn:admin1_code":"WR",
    "gn:admin2_code":"4.0",
    "gn:admin3_code":"38.0",
    "gn:admin4_code":"380001.0",
    "gn:asciiname":"Giranchaur",
    "gn:country_code":"NP",
    "gn:dem":917,
    "gn:feature_class":"P",
    "gn:feature_code":"PPLL",
    "gn:name":"Giranchaur",
    "gn:population":0,
    "gn:timezone":"Asia/Kathmandu",
    "iso:country":"NP",
    "wof:name":"Giranchaur",
    "wof:placetype":"locality"
},
  "geometry": {"coordinates":[84.46250999999999,27.91425],"type":"Point"}
}