{
  "type": "Feature",
  "properties": {
    "gn:admin1_code":"CR",
    "gn:admin2_code":"1",
    "gn:admin3_code":"28",
    "gn:admin4_code":"280023",
    "gn:asciiname":"Ghyangphedi",
    "gn:country_code":"NP",
    "gn:dem":1589,
    "gn:feature_class":"P",
    "gn:feature_code":"PPLL",
    "gn:name":"Ghyangphedi",
    "gn:population":0,
    "gn:timezone":"Asia/Kathmandu",
    "iso:country":"NP",
    "name:ceb_x_preferred":[
        "Ghyangphedi"
    ],
    "name:fra_x_preferred":[
        "Ghyangphedi"
    ],
    "name:mai_x_preferred":[
        "\u0918\u094d\u092f\u093e\u0919\u094d\u0917\u092b\u0947\u0926\u0940"
    ],
    "name:msa_x_preferred":[
        "Ghyangphedi"
    ],
    "name:nep_x_preferred":[
        "\u0918\u094d\u092f\u093e\u0919\u094d\u0917\u092b\u0947\u0926\u0940"
    ],
    "name:new_x_preferred":[
        "\u0918\u094d\u092f\u093e\u0919\u092b\u0947\u0926\u0940"
    ],
    "name:pol_x_preferred":[
        "Ghyangphedi"
    ],
    "wof:name":"Ghyangphedi",
    "wof:placetype":"locality"
},
  "geometry": {"coordinates":[85.44438000000002,27.97914],"type":"Point"}
}