{
  "type": "Feature",
  "properties": {
    "gn:admin1_code":"ER",
    "gn:admin2_code":"7.0",
    "gn:admin3_code":"8.0",
    "gn:admin4_code":"80010.0",
    "gn:asciiname":"Bijore",
    "gn:country_code":"NP",
    "gn:dem":662,
    "gn:feature_class":"P",
    "gn:feature_code":"PPLL",
    "gn:name":"Bijore",
    "gn:population":0,
    "gn:timezone":"Asia/Kathmandu",
    "iso:country":"NP",
    "wof:name":"Bijore",
    "wof:placetype":"locality"
},
  "geometry": {"coordinates":[87.68156,27.25706],"type":"Point"}
}