{
  "type": "Feature",
  "properties": {
    "gn:admin1_code":"MR",
    "gn:admin2_code":"2.0",
    "gn:admin3_code":"57.0",
    "gn:admin4_code":"570045.0",
    "gn:asciiname":"Gurudayalpur",
    "gn:country_code":"NP",
    "gn:dem":151,
    "gn:feature_class":"P",
    "gn:feature_code":"PPLL",
    "gn:name":"Gurudayalpur",
    "gn:population":0,
    "gn:timezone":"Asia/Kathmandu",
    "iso:country":"NP",
    "wof:name":"Gurudayalpur",
    "wof:placetype":"locality"
},
  "geometry": {"coordinates":[81.53476999999999,28.19522000000001],"type":"Point"}
}