{
  "type": "Feature",
  "properties": {
    "gn:admin1_code":"ER",
    "gn:admin2_code":"7",
    "gn:admin3_code":"10.0",
    "gn:admin4_code":"100038.0",
    "gn:asciiname":"Gaudeni",
    "gn:country_code":"NP",
    "gn:dem":354,
    "gn:feature_class":"P",
    "gn:feature_code":"PPLL",
    "gn:name":"Gaudeni",
    "gn:population":0,
    "gn:timezone":"Asia/Kathmandu",
    "iso:country":"NP",
    "wof:name":"Gaudeni",
    "wof:placetype":"locality"
},
  "geometry": {"coordinates":[87.12768,27.41509000000001],"type":"Point"}
}