{
  "type": "Feature",
  "properties": {
    "gn:admin1_code":"WR",
    "gn:admin2_code":"4",
    "gn:admin3_code":"37",
    "gn:admin4_code":"370006",
    "gn:asciiname":"Purano Duwar",
    "gn:country_code":"NP",
    "gn:dem":1287,
    "gn:feature_class":"P",
    "gn:feature_code":"PPLL",
    "gn:name":"Purano Duwar",
    "gn:population":0,
    "gn:timezone":"Asia/Kathmandu",
    "iso:country":"NP",
    "wof:name":"Purano Duwar",
    "wof:placetype":"locality"
},
  "geometry": {"coordinates":[84.43228000000001,28.24322],"type":"Point"}
}