{
  "type": "Feature",
  "properties": {
    "gn:admin1_code":"MR",
    "gn:admin2_code":"2",
    "gn:admin3_code":"60.0",
    "gn:admin4_code":"600021.0",
    "gn:asciiname":"Lamsu",
    "gn:country_code":"NP",
    "gn:dem":1526,
    "gn:feature_class":"P",
    "gn:feature_code":"PPLL",
    "gn:name":"Lamsu",
    "gn:population":0,
    "gn:timezone":"Asia/Kathmandu",
    "iso:country":"NP",
    "wof:name":"Lamsu",
    "wof:placetype":"locality"
},
  "geometry": {"coordinates":[81.64745000000001,28.808],"type":"Point"}
}