{
  "type": "Feature",
  "properties": {
    "gn:admin1_code":"FR",
    "gn:admin2_code":"9",
    "gn:admin3_code":"74",
    "gn:admin4_code":"740059",
    "gn:asciiname":"Parsa",
    "gn:country_code":"NP",
    "gn:dem":1141,
    "gn:feature_class":"P",
    "gn:feature_code":"PPLL",
    "gn:name":"Parsa",
    "gn:population":0,
    "gn:timezone":"Asia/Kathmandu",
    "iso:country":"NP",
    "name:bak_x_preferred":[
        "\u041f\u0430\u0440\u0441\u0430"
    ],
    "name:cat_x_preferred":[
        "Parsuwaix"
    ],
    "name:ceb_x_preferred":[
        "Parsa"
    ],
    "name:deu_x_preferred":[
        "Parsa"
    ],
    "name:fas_x_preferred":[
        "\u067e\u0627\u0631\u0633\u0627"
    ],
    "name:hin_x_preferred":[
        "\u092a\u0930\u094d\u0938\u093e"
    ],
    "name:rus_x_preferred":[
        "\u041f\u0430\u0440\u0441\u0430"
    ],
    "name:swe_x_preferred":[
        "Parsa"
    ],
    "wof:name":"Parsa",
    "wof:placetype":"locality"
},
  "geometry": {"coordinates":[80.47945,29.57333],"type":"Point"}
}