{
  "type": "Feature",
  "properties": {
    "gn:admin1_code":"WR",
    "gn:admin2_code":"8",
    "gn:admin3_code":"49",
    "gn:admin4_code":"490019",
    "gn:asciiname":"Saranntandi",
    "gn:country_code":"NP",
    "gn:dem":265,
    "gn:feature_class":"P",
    "gn:feature_code":"PPLL",
    "gn:name":"Saranntandi",
    "gn:population":0,
    "gn:timezone":"Asia/Kathmandu",
    "iso:country":"NP",
    "wof:name":"Saranntandi",
    "wof:placetype":"locality"
},
  "geometry": {"coordinates":[83.57841999999999,27.68085],"type":"Point"}
}