{
  "type": "Feature",
  "properties": {
    "gn:admin1_code":"FR",
    "gn:admin2_code":"14",
    "gn:admin3_code":"69.0",
    "gn:admin4_code":"690054.0",
    "gn:asciiname":"Danda",
    "gn:country_code":"NP",
    "gn:dem":936,
    "gn:feature_class":"P",
    "gn:feature_code":"PPLL",
    "gn:name":"Danda",
    "gn:population":0,
    "gn:timezone":"Asia/Kathmandu",
    "iso:country":"NP",
    "wof:name":"Danda",
    "wof:placetype":"locality"
},
  "geometry": {"coordinates":[81.27748000000003,29.15341],"type":"Point"}
}