{
  "type": "Feature",
  "properties": {
    "gn:admin1_code":"FR",
    "gn:admin2_code":"14",
    "gn:admin3_code":"69.0",
    "gn:admin4_code":"690054.0",
    "gn:asciiname":"Danda",
    "gn:country_code":"NP",
    "gn:dem":936,
    "gn:feature_class":"P",
    "gn:feature_code":"PPLL",
    "gn:name":"Danda",
    "gn:population":0,
    "gn:timezone":"Asia/Kathmandu",
    "iso:country":"NP",
    "name:ara_x_preferred":[
        "\u062f\u0627\u0646\u062f\u0627"
    ],
    "name:deu_x_preferred":[
        "Danda"
    ],
    "name:ell_x_preferred":[
        "\u039d\u03c4\u03ac\u03bd\u03c4\u03b1"
    ],
    "name:fra_x_preferred":[
        "Da\u1e47\u1e0da"
    ],
    "name:hin_x_preferred":[
        "\u0926\u0923\u094d\u0921"
    ],
    "name:pol_x_preferred":[
        "Danda"
    ],
    "name:tam_x_preferred":[
        "\u0ba4\u0ba3\u0bcd\u0b9f\u0b95 \u0ba8\u0bbe\u0b9f\u0bc1"
    ],
    "name:tgl_x_preferred":[
        "Danda"
    ],
    "wof:name":"Danda",
    "wof:placetype":"locality"
},
  "geometry": {"coordinates":[81.27748000000003,29.15341],"type":"Point"}
}