{
  "type": "Feature",
  "properties": {
    "gn:admin1_code":"CR",
    "gn:admin2_code":"11",
    "gn:admin3_code":"31",
    "gn:admin4_code":"310032",
    "gn:asciiname":"Baghmara",
    "gn:country_code":"NP",
    "gn:dem":1186,
    "gn:feature_class":"P",
    "gn:feature_code":"PPLL",
    "gn:name":"Baghmara",
    "gn:population":0,
    "gn:timezone":"Asia/Kathmandu",
    "iso:country":"NP",
    "wof:name":"Baghmara",
    "wof:placetype":"locality"
},
  "geometry": {"coordinates":[85.02949,27.55217],"type":"Point"}
}