{
  "type": "Feature",
  "properties": {
    "gn:admin1_code":"MR",
    "gn:admin2_code":"12",
    "gn:admin3_code":"52",
    "gn:admin4_code":"520015",
    "gn:asciiname":"Chhap",
    "gn:country_code":"NP",
    "gn:dem":1164,
    "gn:feature_class":"P",
    "gn:feature_code":"PPLL",
    "gn:name":"Chhap",
    "gn:population":0,
    "gn:timezone":"Asia/Kathmandu",
    "iso:country":"NP",
    "name:ceb_x_preferred":[
        "Chhap"
    ],
    "name:fra_x_preferred":[
        "Chhap"
    ],
    "name:mai_x_preferred":[
        "\u091b\u093e\u092a"
    ],
    "name:msa_x_preferred":[
        "Chhap"
    ],
    "name:nep_x_preferred":[
        "\u091b\u093e\u092a"
    ],
    "name:new_x_preferred":[
        "\u091b\u093e\u092a"
    ],
    "name:pol_x_preferred":[
        "Chhap"
    ],
    "wof:name":"Chhap",
    "wof:placetype":"locality"
},
  "geometry": {"coordinates":[82.91773000000001,28.07598],"type":"Point"}
}