{
  "type": "Feature",
  "properties": {
    "gn:admin1_code":"MR",
    "gn:admin2_code":"2.0",
    "gn:admin3_code":"59.0",
    "gn:admin4_code":"590010.0",
    "gn:asciiname":"Murlikholagaun",
    "gn:country_code":"NP",
    "gn:dem":719,
    "gn:feature_class":"P",
    "gn:feature_code":"PPLL",
    "gn:name":"Murlikholagaun",
    "gn:population":0,
    "gn:timezone":"Asia/Kathmandu",
    "iso:country":"NP",
    "wof:name":"Murlikholagaun",
    "wof:placetype":"locality"
},
  "geometry": {"coordinates":[81.70094,28.42442],"type":"Point"}
}