{
  "type": "Feature",
  "properties": {
    "gn:admin1_code":"MR",
    "gn:admin2_code":"6",
    "gn:admin3_code":"62.0",
    "gn:admin4_code":"620020.0",
    "gn:asciiname":"Sepane",
    "gn:country_code":"NP",
    "gn:dem":2822,
    "gn:feature_class":"P",
    "gn:feature_code":"PPLL",
    "gn:name":"Sepane",
    "gn:population":0,
    "gn:timezone":"Asia/Kathmandu",
    "iso:country":"NP",
    "wof:name":"Sepane",
    "wof:placetype":"locality"
},
  "geometry": {"coordinates":[82.47004,29.06168],"type":"Point"}
}