{
  "type": "Feature",
  "properties": {
    "gn:admin1_code":"MR",
    "gn:admin2_code":"12",
    "gn:admin3_code":"53",
    "gn:admin4_code":"530008",
    "gn:asciiname":"Rappa",
    "gn:country_code":"NP",
    "gn:dem":1676,
    "gn:feature_class":"P",
    "gn:feature_code":"PPLL",
    "gn:name":"Rappa",
    "gn:population":0,
    "gn:timezone":"Asia/Kathmandu",
    "iso:country":"NP",
    "wof:name":"Rappa",
    "wof:placetype":"locality"
},
  "geometry": {"coordinates":[82.52401999999999,28.51096],"type":"Point"}
}