{
  "type": "Feature",
  "properties": {
    "gn:admin1_code":"MR",
    "gn:admin2_code":"12",
    "gn:admin3_code":"53",
    "gn:admin4_code":"530051",
    "gn:asciiname":"Bhittabang",
    "gn:country_code":"NP",
    "gn:dem":1453,
    "gn:feature_class":"P",
    "gn:feature_code":"PPLL",
    "gn:name":"Bhittabang",
    "gn:population":0,
    "gn:timezone":"Asia/Kathmandu",
    "iso:country":"NP",
    "wof:name":"Bhittabang",
    "wof:placetype":"locality"
},
  "geometry": {"coordinates":[82.47613,28.402],"type":"Point"}
}