{
  "type": "Feature",
  "properties": {
    "gn:admin1_code":"MR",
    "gn:admin2_code":"2.0",
    "gn:admin3_code":"57.0",
    "gn:admin4_code":"570020.0",
    "gn:asciiname":"Mathebans",
    "gn:country_code":"NP",
    "gn:dem":178,
    "gn:feature_class":"P",
    "gn:feature_code":"PPLL",
    "gn:name":"Mathebans",
    "gn:population":0,
    "gn:timezone":"Asia/Kathmandu",
    "iso:country":"NP",
    "wof:name":"Mathebans",
    "wof:placetype":"locality"
},
  "geometry": {"coordinates":[81.90553,28.05728],"type":"Point"}
}