{
  "type": "Feature",
  "properties": {
    "gn:admin1_code":"CR",
    "gn:admin2_code":"1",
    "gn:admin3_code":"28",
    "gn:admin4_code":"280013",
    "gn:asciiname":"Ritthechaur",
    "gn:country_code":"NP",
    "gn:dem":789,
    "gn:feature_class":"P",
    "gn:feature_code":"PPLL",
    "gn:name":"Ritthechaur",
    "gn:population":0,
    "gn:timezone":"Asia/Kathmandu",
    "iso:country":"NP",
    "wof:name":"Ritthechaur",
    "wof:placetype":"locality"
},
  "geometry": {"coordinates":[85.27821,27.90407],"type":"Point"}
}