{
  "type": "Feature",
  "properties": {
    "gn:admin1_code":"ER",
    "gn:admin2_code":"10.0",
    "gn:admin3_code":"1.0",
    "gn:admin4_code":"10006.0",
    "gn:asciiname":"Bejambu",
    "gn:country_code":"NP",
    "gn:dem":1813,
    "gn:feature_class":"P",
    "gn:feature_code":"PPLL",
    "gn:name":"Bejambu",
    "gn:population":0,
    "gn:timezone":"Asia/Kathmandu",
    "iso:country":"NP",
    "wof:name":"Bejambu",
    "wof:placetype":"locality"
},
  "geometry": {"coordinates":[87.69283,27.33935],"type":"Point"}
}