{
  "type": "Feature",
  "properties": {
    "gn:admin1_code":"00",
    "gn:asciiname":"Manten",
    "gn:country_code":"NP",
    "gn:dem":615,
    "gn:feature_class":"P",
    "gn:feature_code":"PPL",
    "gn:name":"M\u0101\u1e45\u1e6de\u1e45",
    "gn:population":0,
    "gn:timezone":"Asia/Kathmandu",
    "iso:country":"NP",
    "name:jpn_x_preferred":[
        "\u307e\u3093\u3066\u3093"
    ],
    "name:nep_x_preferred":[
        "M\u0101\u1e45\u1e6de\u1e45"
    ],
    "wof:name":"Manten",
    "wof:placetype":"locality"
},
  "geometry": {"coordinates":[87.15624,26.90082],"type":"Point"}
}