{
  "type": "Feature",
  "properties": {
    "gn:admin1_code":"ER",
    "gn:admin2_code":"10",
    "gn:admin3_code":"2",
    "gn:admin4_code":"20002",
    "gn:asciiname":"Dapsu",
    "gn:country_code":"NP",
    "gn:dem":1530,
    "gn:feature_class":"P",
    "gn:feature_code":"PPLL",
    "gn:name":"Dapsu",
    "gn:population":0,
    "gn:timezone":"Asia/Kathmandu",
    "iso:country":"NP",
    "wof:name":"Dapsu",
    "wof:placetype":"locality"
},
  "geometry": {"coordinates":[87.70423000000002,27.04052],"type":"Point"}
}