{
  "type": "Feature",
  "properties": {
    "gn:admin1_code":"WR",
    "gn:admin2_code":"4",
    "gn:admin3_code":"37",
    "gn:admin4_code":"370021",
    "gn:asciiname":"Gothkharka",
    "gn:country_code":"NP",
    "gn:dem":3123,
    "gn:feature_class":"P",
    "gn:feature_code":"PPLL",
    "gn:name":"Gothkharka",
    "gn:population":0,
    "gn:timezone":"Asia/Kathmandu",
    "iso:country":"NP",
    "wof:name":"Gothkharka",
    "wof:placetype":"locality"
},
  "geometry": {"coordinates":[84.57718,28.27993],"type":"Point"}
}