{
  "type": "Feature",
  "properties": {
    "gn:admin1_code":"MR",
    "gn:admin2_code":"12",
    "gn:admin3_code":"55",
    "gn:admin4_code":"550008",
    "gn:asciiname":"Dahagaun",
    "gn:country_code":"NP",
    "gn:dem":1656,
    "gn:feature_class":"P",
    "gn:feature_code":"PPLL",
    "gn:name":"Dahagaun",
    "gn:population":0,
    "gn:timezone":"Asia/Kathmandu",
    "iso:country":"NP",
    "wof:name":"Dahagaun",
    "wof:placetype":"locality"
},
  "geometry": {"coordinates":[82.33481,28.40049],"type":"Point"}
}