{
  "type": "Feature",
  "properties": {
    "gn:admin1_code":"MR",
    "gn:admin2_code":"2.0",
    "gn:admin3_code":"57.0",
    "gn:admin4_code":"570032.0",
    "gn:asciiname":"Bhrikuti Nagar",
    "gn:country_code":"NP",
    "gn:dem":152,
    "gn:feature_class":"P",
    "gn:feature_code":"PPLL",
    "gn:name":"Bhrikuti Nagar",
    "gn:population":0,
    "gn:timezone":"Asia/Kathmandu",
    "iso:country":"NP",
    "wof:name":"Bhrikuti Nagar",
    "wof:placetype":"locality"
},
  "geometry": {"coordinates":[81.6126,28.05748],"type":"Point"}
}