{
  "type": "Feature",
  "properties": {
    "gn:admin1_code":"MR",
    "gn:admin2_code":"12",
    "gn:admin3_code":"54",
    "gn:admin4_code":"540002",
    "gn:asciiname":"Thula Chaur",
    "gn:country_code":"NP",
    "gn:dem":1597,
    "gn:feature_class":"P",
    "gn:feature_code":"PPLL",
    "gn:name":"Thula Chaur",
    "gn:population":0,
    "gn:timezone":"Asia/Kathmandu",
    "iso:country":"NP",
    "wof:name":"Thula Chaur",
    "wof:placetype":"locality"
},
  "geometry": {"coordinates":[82.37669,28.78216],"type":"Point"}
}