{
  "type": "Feature",
  "properties": {
    "gn:admin1_code":"ER",
    "gn:admin2_code":"13",
    "gn:admin3_code":"15",
    "gn:admin4_code":"150080",
    "gn:asciiname":"Dhanti Bajar",
    "gn:country_code":"NP",
    "gn:dem":99,
    "gn:feature_class":"P",
    "gn:feature_code":"PPLL",
    "gn:name":"Dhanti Bajar",
    "gn:population":0,
    "gn:timezone":"Asia/Kathmandu",
    "iso:country":"NP",
    "wof:name":"Dhanti Bajar",
    "wof:placetype":"locality"
},
  "geometry": {"coordinates":[86.53440000000001,26.64359],"type":"Point"}
}