{
  "type": "Feature",
  "properties": {
    "gn:admin1_code":"00",
    "gn:asciiname":"Soisan",
    "gn:country_code":"NP",
    "gn:dem":2225,
    "gn:feature_class":"P",
    "gn:feature_code":"PPL",
    "gn:name":"Sois\u0101\u1e45",
    "gn:population":0,
    "gn:timezone":"Asia/Kathmandu",
    "iso:country":"NP",
    "wof:name":"Soisan",
    "wof:placetype":"locality"
},
  "geometry": {"coordinates":[86.15758000000002,27.78914],"type":"Point"}
}