{
  "type": "Feature",
  "properties": {
    "gn:admin1_code":"CR",
    "gn:admin2_code":"1",
    "gn:admin3_code":"23",
    "gn:admin4_code":"230052",
    "gn:asciiname":"Isin",
    "gn:country_code":"NP",
    "gn:dem":1737,
    "gn:feature_class":"P",
    "gn:feature_code":"PPLL",
    "gn:name":"Isin",
    "gn:population":0,
    "gn:timezone":"Asia/Kathmandu",
    "iso:country":"NP",
    "name:amh_x_preferred":[
        "\u12a2\u1232\u1295"
    ],
    "name:ara_x_preferred":[
        "\u0625\u064a\u0633\u0646"
    ],
    "name:bak_x_preferred":[
        "\u0418\u0441\u0438\u043d"
    ],
    "name:cat_x_preferred":[
        "Isin"
    ],
    "name:ces_x_preferred":[
        "Isin"
    ],
    "name:deu_x_preferred":[
        "Isin"
    ],
    "name:eus_x_preferred":[
        "Isin"
    ],
    "name:fas_x_preferred":[
        "\u0627\u06cc\u0633\u0646"
    ],
    "name:fin_x_preferred":[
        "Isin"
    ],
    "name:fra_x_preferred":[
        "Isin"
    ],
    "name:glg_x_preferred":[
        "Is\u00edn"
    ],
    "name:heb_x_preferred":[
        "\u05d0\u05d9\u05e1\u05d9\u05df"
    ],
    "name:hun_x_preferred":[
        "\u00cdsz\u00edn"
    ],
    "name:ind_x_preferred":[
        "Isin"
    ],
    "name:ita_x_preferred":[
        "Isin"
    ],
    "name:jpn_x_preferred":[
        "\u30a4\u30b7\u30f3"
    ],
    "name:kor_x_preferred":[
        "\uc774\uc2e0"
    ],
    "name:lit_x_preferred":[
        "Isinas"
    ],
    "name:nld_x_preferred":[
        "Isin"
    ],
    "name:nor_x_preferred":[
        "Isin"
    ],
    "name:oci_x_preferred":[
        "Isin"
    ],
    "name:pol_x_preferred":[
        "Isin"
    ],
    "name:por_x_preferred":[
        "Isin"
    ],
    "name:ron_x_preferred":[
        "Isin"
    ],
    "name:rus_x_preferred":[
        "\u0418\u0441\u0438\u043d"
    ],
    "name:slk_x_preferred":[
        "Isin"
    ],
    "name:slv_x_preferred":[
        "Isin"
    ],
    "name:spa_x_preferred":[
        "Isin"
    ],
    "name:srp_x_preferred":[
        "\u0418\u0441\u0438\u043d"
    ],
    "name:swe_x_preferred":[
        "Isin"
    ],
    "name:tgl_x_preferred":[
        "Isin"
    ],
    "name:tur_x_preferred":[
        "\u0130sin Krall\u0131\u011f\u0131"
    ],
    "name:ukr_x_preferred":[
        "\u0406\u0441\u0456\u043d"
    ],
    "wof:name":"Isin",
    "wof:placetype":"locality"
},
  "geometry": {"coordinates":[85.57002,27.89544],"type":"Point"}
}