{
  "type": "Feature",
  "properties": {
    "gn:admin1_code":"WR",
    "gn:admin2_code":"8",
    "gn:admin3_code":"46.0",
    "gn:admin4_code":"460026.0",
    "gn:asciiname":"Harre Thumka",
    "gn:country_code":"NP",
    "gn:dem":1216,
    "gn:feature_class":"P",
    "gn:feature_code":"PPLL",
    "gn:name":"Harre Thumka",
    "gn:population":0,
    "gn:timezone":"Asia/Kathmandu",
    "iso:country":"NP",
    "wof:name":"Harre Thumka",
    "wof:placetype":"locality"
},
  "geometry": {"coordinates":[83.18285999999998,28.11142000000001],"type":"Point"}
}