{
  "type": "Feature",
  "properties": {
    "gn:admin1_code":"WR",
    "gn:admin2_code":"8",
    "gn:admin3_code":"47",
    "gn:admin4_code":"470023",
    "gn:asciiname":"Sakhardi",
    "gn:country_code":"NP",
    "gn:dem":601,
    "gn:feature_class":"P",
    "gn:feature_code":"PPLL",
    "gn:name":"Sakhardi",
    "gn:population":0,
    "gn:timezone":"Asia/Kathmandu",
    "iso:country":"NP",
    "wof:name":"Sakhardi",
    "wof:placetype":"locality"
},
  "geometry": {"coordinates":[83.98685,27.84467],"type":"Point"}
}