{
  "type": "Feature",
  "properties": {
    "gn:admin1_code":"MR",
    "gn:admin2_code":"6",
    "gn:admin3_code":"62.0",
    "gn:admin4_code":"620020.0",
    "gn:asciiname":"Horta",
    "gn:country_code":"NP",
    "gn:dem":2961,
    "gn:feature_class":"P",
    "gn:feature_code":"PPLL",
    "gn:name":"Horta",
    "gn:population":0,
    "gn:timezone":"Asia/Kathmandu",
    "iso:country":"NP",
    "name:cat_x_preferred":[
        "Horta"
    ],
    "name:ceb_x_preferred":[
        "Horta"
    ],
    "name:deu_x_preferred":[
        "Horta"
    ],
    "name:epo_x_preferred":[
        "Horta"
    ],
    "name:fin_x_preferred":[
        "Horta"
    ],
    "name:fra_x_preferred":[
        "Horta"
    ],
    "name:glg_x_preferred":[
        "Horta"
    ],
    "name:hun_x_preferred":[
        "Horta"
    ],
    "name:ita_x_preferred":[
        "Horta"
    ],
    "name:lat_x_preferred":[
        "Horta"
    ],
    "name:nld_x_preferred":[
        "Horta"
    ],
    "name:pol_x_preferred":[
        "Horta"
    ],
    "name:por_x_preferred":[
        "Horta"
    ],
    "name:spa_x_preferred":[
        "Horta"
    ],
    "name:swe_x_preferred":[
        "Horta"
    ],
    "name:tur_x_preferred":[
        "Horta"
    ],
    "wof:name":"Horta",
    "wof:placetype":"locality"
},
  "geometry": {"coordinates":[82.45007,29.07579],"type":"Point"}
}