{
  "type": "Feature",
  "properties": {
    "gn:admin1_code":"MR",
    "gn:admin2_code":"2",
    "gn:admin3_code":"60.0",
    "gn:admin4_code":"600024.0",
    "gn:asciiname":"Kuiya",
    "gn:country_code":"NP",
    "gn:dem":1767,
    "gn:feature_class":"P",
    "gn:feature_code":"PPLL",
    "gn:name":"Kuiya",
    "gn:population":0,
    "gn:timezone":"Asia/Kathmandu",
    "iso:country":"NP",
    "wof:name":"Kuiya",
    "wof:placetype":"locality"
},
  "geometry": {"coordinates":[81.80370000000001,28.75948],"type":"Point"}
}