{
  "type": "Feature",
  "properties": {
    "gn:admin1_code":"ER",
    "gn:admin2_code":"10",
    "gn:admin3_code":"3.0",
    "gn:admin4_code":"30041.0",
    "gn:asciiname":"Sanrumba",
    "gn:country_code":"NP",
    "gn:dem":810,
    "gn:feature_class":"P",
    "gn:feature_code":"PPLL",
    "gn:name":"Sanrumba",
    "gn:population":0,
    "gn:timezone":"Asia/Kathmandu",
    "iso:country":"NP",
    "wof:name":"Sanrumba",
    "wof:placetype":"locality"
},
  "geometry": {"coordinates":[87.88457,26.88434],"type":"Point"}
}