{
  "type": "Feature",
  "properties": {
    "gn:admin1_code":"WR",
    "gn:admin2_code":"4",
    "gn:admin3_code":"37",
    "gn:admin4_code":"370032",
    "gn:asciiname":"Jamune",
    "gn:country_code":"NP",
    "gn:dem":1191,
    "gn:feature_class":"P",
    "gn:feature_code":"PPLL",
    "gn:name":"Jamune",
    "gn:population":0,
    "gn:timezone":"Asia/Kathmandu",
    "iso:country":"NP",
    "wof:name":"Jamune",
    "wof:placetype":"locality"
},
  "geometry": {"coordinates":[84.60309000000002,28.16667],"type":"Point"}
}