{
  "type": "Feature",
  "properties": {
    "gn:admin1_code":"00",
    "gn:asciiname":"Koslin",
    "gn:country_code":"NP",
    "gn:dem":2020,
    "gn:feature_class":"P",
    "gn:feature_code":"PPL",
    "gn:name":"Kosli\u1e45",
    "gn:population":0,
    "gn:timezone":"Asia/Kathmandu",
    "iso:country":"NP",
    "wof:name":"Koslin",
    "wof:placetype":"locality"
},
  "geometry": {"coordinates":[85.68415999999998,27.85445],"type":"Point"}
}