{
  "type": "Feature",
  "properties": {
    "gn:admin1_code":"MR",
    "gn:admin2_code":"12",
    "gn:admin3_code":"55",
    "gn:admin4_code":"550001",
    "gn:asciiname":"Chhirchhirya Banjh",
    "gn:country_code":"NP",
    "gn:dem":1427,
    "gn:feature_class":"P",
    "gn:feature_code":"PPLL",
    "gn:name":"Chhirchhirya Banjh",
    "gn:population":0,
    "gn:timezone":"Asia/Kathmandu",
    "iso:country":"NP",
    "wof:name":"Chhirchhirya Banjh",
    "wof:placetype":"locality"
},
  "geometry": {"coordinates":[82.24563000000001,28.53825],"type":"Point"}
}