{
  "type": "Feature",
  "properties": {
    "gn:admin1_code":"ER",
    "gn:admin2_code":"13",
    "gn:admin3_code":"13",
    "gn:admin4_code":"130060",
    "gn:asciiname":"Chapleti",
    "gn:country_code":"NP",
    "gn:dem":962,
    "gn:feature_class":"P",
    "gn:feature_code":"PPLL",
    "gn:name":"Chapleti",
    "gn:population":0,
    "gn:timezone":"Asia/Kathmandu",
    "iso:country":"NP",
    "wof:name":"Chapleti",
    "wof:placetype":"locality"
},
  "geometry": {"coordinates":[86.70385,27.10851],"type":"Point"}
}