{
  "type": "Feature",
  "properties": {
    "gn:admin1_code":"WR",
    "gn:admin2_code":"4",
    "gn:admin3_code":"36.0",
    "gn:admin4_code":"360009.0",
    "gn:asciiname":"Apchaur",
    "gn:country_code":"NP",
    "gn:dem":1492,
    "gn:feature_class":"P",
    "gn:feature_code":"PPLL",
    "gn:name":"Apchaur",
    "gn:population":0,
    "gn:timezone":"Asia/Kathmandu",
    "iso:country":"NP",
    "wof:name":"Apchaur",
    "wof:placetype":"locality"
},
  "geometry": {"coordinates":[84.70026999999997,27.84695],"type":"Point"}
}