{
  "type": "Feature",
  "properties": {
    "gn:admin1_code":"MR",
    "gn:admin2_code":"2.0",
    "gn:admin3_code":"57.0",
    "gn:admin4_code":"570014.0",
    "gn:asciiname":"Sikhanpurwa",
    "gn:country_code":"NP",
    "gn:dem":144,
    "gn:feature_class":"P",
    "gn:feature_code":"PPLL",
    "gn:name":"Sikhanpurwa",
    "gn:population":0,
    "gn:timezone":"Asia/Kathmandu",
    "iso:country":"NP",
    "wof:name":"Sikhanpurwa",
    "wof:placetype":"locality"
},
  "geometry": {"coordinates":[81.65671999999998,28.01668],"type":"Point"}
}