{
  "type": "Feature",
  "properties": {
    "gn:admin1_code":"FR",
    "gn:admin2_code":"9",
    "gn:admin3_code":"72.0",
    "gn:admin4_code":"720009.0",
    "gn:asciiname":"Palgadi",
    "gn:country_code":"NP",
    "gn:dem":1159,
    "gn:feature_class":"P",
    "gn:feature_code":"PPLL",
    "gn:name":"Palgadi",
    "gn:population":0,
    "gn:timezone":"Asia/Kathmandu",
    "iso:country":"NP",
    "wof:name":"Palgadi",
    "wof:placetype":"locality"
},
  "geometry": {"coordinates":[80.45933000000002,29.02069],"type":"Point"}
}