{
  "type": "Feature",
  "properties": {
    "gn:admin1_code":"MR",
    "gn:admin2_code":"6",
    "gn:admin3_code":"63.0",
    "gn:admin4_code":"630027.0",
    "gn:asciiname":"Pahada",
    "gn:country_code":"NP",
    "gn:dem":3208,
    "gn:feature_class":"P",
    "gn:feature_code":"PPLL",
    "gn:name":"Pahada",
    "gn:population":0,
    "gn:timezone":"Asia/Kathmandu",
    "iso:country":"NP",
    "name:ceb_x_preferred":[
        "Pahada"
    ],
    "name:fra_x_preferred":[
        "Pahada"
    ],
    "name:mai_x_preferred":[
        "\u092a\u0939\u093e\u0921\u093e"
    ],
    "name:msa_x_preferred":[
        "Pahada"
    ],
    "name:nep_x_preferred":[
        "\u092a\u0939\u093e\u0921\u093e"
    ],
    "name:new_x_preferred":[
        "\u092a\u0939\u093e\u0921\u093e"
    ],
    "name:pol_x_preferred":[
        "Pahada"
    ],
    "wof:name":"Pahada",
    "wof:placetype":"locality"
},
  "geometry": {"coordinates":[82.06596,29.29624],"type":"Point"}
}