{
  "type": "Feature",
  "properties": {
    "gn:admin1_code":"WR",
    "gn:admin2_code":"4",
    "gn:admin3_code":"40.0",
    "gn:admin4_code":"400018.0",
    "gn:asciiname":"Pateswara",
    "gn:country_code":"NP",
    "gn:dem":1638,
    "gn:feature_class":"P",
    "gn:feature_code":"PPLL",
    "gn:name":"Pateswara",
    "gn:population":0,
    "gn:timezone":"Asia/Kathmandu",
    "iso:country":"NP",
    "wof:name":"Pateswara",
    "wof:placetype":"locality"
},
  "geometry": {"coordinates":[83.92952,28.2612],"type":"Point"}
}