{
  "type": "Feature",
  "properties": {
    "gn:admin1_code":"ER",
    "gn:admin2_code":"7",
    "gn:admin3_code":"7.0",
    "gn:admin4_code":"70036.0",
    "gn:asciiname":"Malbase",
    "gn:country_code":"NP",
    "gn:dem":576,
    "gn:feature_class":"P",
    "gn:feature_code":"PPLL",
    "gn:name":"Malbase",
    "gn:population":0,
    "gn:timezone":"Asia/Kathmandu",
    "iso:country":"NP",
    "wof:name":"Malbase",
    "wof:placetype":"locality"
},
  "geometry": {"coordinates":[87.33243,26.88148],"type":"Point"}
}