{
  "type": "Feature",
  "properties": {
    "gn:admin1_code":"CR",
    "gn:admin2_code":"1",
    "gn:admin3_code":"29",
    "gn:admin4_code":"290003",
    "gn:asciiname":"Mendo",
    "gn:country_code":"NP",
    "gn:dem":1814,
    "gn:feature_class":"P",
    "gn:feature_code":"PPLL",
    "gn:name":"Mendo",
    "gn:population":0,
    "gn:timezone":"Asia/Kathmandu",
    "iso:country":"NP",
    "wof:name":"Mendo",
    "wof:placetype":"locality"
},
  "geometry": {"coordinates":[85.34183,28.19188],"type":"Point"}
}