{
  "type": "Feature",
  "properties": {
    "gn:admin1_code":"ER",
    "gn:admin2_code":"13",
    "gn:admin3_code":"11",
    "gn:admin4_code":"110031",
    "gn:asciiname":"Chitre",
    "gn:country_code":"NP",
    "gn:dem":2667,
    "gn:feature_class":"P",
    "gn:feature_code":"PPLL",
    "gn:name":"Chitre",
    "gn:population":0,
    "gn:timezone":"Asia/Kathmandu",
    "iso:country":"NP",
    "name:ceb_x_preferred":[
        "Chitre"
    ],
    "name:ell_x_preferred":[
        "\u03a4\u03c3\u03af\u03c4\u03c1\u03b5"
    ],
    "name:mai_x_preferred":[
        "\u091a\u093f\u0924\u094d\u0930\u0947"
    ],
    "name:msa_x_preferred":[
        "Chitre"
    ],
    "name:nep_x_preferred":[
        "\u091a\u093f\u0924\u094d\u0930\u0947"
    ],
    "name:new_x_preferred":[
        "\u091a\u093f\u0924\u094d\u0930\u0947"
    ],
    "name:pol_x_preferred":[
        "Chitre"
    ],
    "wof:name":"Chitre",
    "wof:placetype":"locality"
},
  "geometry": {"coordinates":[86.80161,27.44298],"type":"Point"}
}