{
  "type": "Feature",
  "properties": {
    "gn:admin1_code":"ER",
    "gn:admin2_code":"7",
    "gn:admin3_code":"5",
    "gn:admin4_code":"50036",
    "gn:asciiname":"Lakhantari",
    "gn:country_code":"NP",
    "gn:dem":87,
    "gn:feature_class":"P",
    "gn:feature_code":"PPLL",
    "gn:name":"Lakhantari",
    "gn:population":0,
    "gn:timezone":"Asia/Kathmandu",
    "iso:country":"NP",
    "name:ceb_x_preferred":[
        "Lakhantari"
    ],
    "name:mai_x_preferred":[
        "\u0932\u0916\u0928\u094d\u0924\u0930\u0940"
    ],
    "name:msa_x_preferred":[
        "Lakhantari"
    ],
    "name:new_x_preferred":[
        "\u0932\u0916\u0928\u091f\u093e\u0930\u0940"
    ],
    "name:pol_x_preferred":[
        "Lakhantari"
    ],
    "name:urd_x_preferred":[
        "\u0644\u06a9\u06be\u0627\u0646\u0679\u0627\u0631\u06cc"
    ],
    "wof:name":"Lakhantari",
    "wof:placetype":"locality"
},
  "geometry": {"coordinates":[87.32108000000002,26.54594],"type":"Point"}
}