{
  "type": "Feature",
  "properties": {
    "gn:admin1_code":"ER",
    "gn:admin2_code":"7",
    "gn:admin3_code":"9",
    "gn:admin4_code":"90027",
    "gn:asciiname":"Tupuwa",
    "gn:country_code":"NP",
    "gn:dem":1469,
    "gn:feature_class":"P",
    "gn:feature_code":"PPLL",
    "gn:name":"Tupuwa",
    "gn:population":0,
    "gn:timezone":"Asia/Kathmandu",
    "iso:country":"NP",
    "wof:name":"Tupuwa",
    "wof:placetype":"locality"
},
  "geometry": {"coordinates":[87.43618000000002,27.30745],"type":"Point"}
}