{
  "type": "Feature",
  "properties": {
    "gn:admin1_code":"MR",
    "gn:admin2_code":"12",
    "gn:admin3_code":"56.0",
    "gn:admin4_code":"560014.0",
    "gn:asciiname":"Mata",
    "gn:country_code":"NP",
    "gn:dem":565,
    "gn:feature_class":"P",
    "gn:feature_code":"PPLL",
    "gn:name":"Mata",
    "gn:population":0,
    "gn:timezone":"Asia/Kathmandu",
    "iso:country":"NP",
    "wof:name":"Mata",
    "wof:placetype":"locality"
},
  "geometry": {"coordinates":[82.65475000000001,27.91974],"type":"Point"}
}