{
  "type": "Feature",
  "properties": {
    "gn:admin1_code":"CR",
    "gn:admin2_code":"5",
    "gn:admin3_code":"17.0",
    "gn:admin4_code":"170019.0",
    "gn:asciiname":"Dhatiyatol",
    "gn:country_code":"NP",
    "gn:dem":121,
    "gn:feature_class":"P",
    "gn:feature_code":"PPLL",
    "gn:name":"Dhatiyatol",
    "gn:population":0,
    "gn:timezone":"Asia/Kathmandu",
    "iso:country":"NP",
    "wof:name":"Dhatiyatol",
    "wof:placetype":"locality"
},
  "geometry": {"coordinates":[85.90111999999998,26.8769],"type":"Point"}
}