{
  "type": "Feature",
  "properties": {
    "gn:admin1_code":"WR",
    "gn:admin2_code":"3",
    "gn:admin3_code":"45",
    "gn:admin4_code":"450058.0",
    "gn:asciiname":"Jurdhunga",
    "gn:country_code":"NP",
    "gn:dem":1961,
    "gn:feature_class":"P",
    "gn:feature_code":"PPLL",
    "gn:name":"Jurdhunga",
    "gn:population":0,
    "gn:timezone":"Asia/Kathmandu",
    "iso:country":"NP",
    "wof:name":"Jurdhunga",
    "wof:placetype":"locality"
},
  "geometry": {"coordinates":[83.24785,28.24388],"type":"Point"}
}