{
  "type": "Feature",
  "properties": {
    "gn:admin1_code":"WR",
    "gn:admin2_code":"8",
    "gn:admin3_code":"46.0",
    "gn:admin4_code":"460018.0",
    "gn:asciiname":"Dalban",
    "gn:country_code":"NP",
    "gn:dem":1055,
    "gn:feature_class":"P",
    "gn:feature_code":"PPLL",
    "gn:name":"Dalban",
    "gn:population":0,
    "gn:timezone":"Asia/Kathmandu",
    "iso:country":"NP",
    "wof:name":"Dalban",
    "wof:placetype":"locality"
},
  "geometry": {"coordinates":[83.334,28.03334000000001],"type":"Point"}
}