{
  "type": "Feature",
  "properties": {
    "gn:admin1_code":"CR",
    "gn:admin2_code":"1",
    "gn:admin3_code":"29",
    "gn:admin4_code":"290009",
    "gn:asciiname":"Bhadaure",
    "gn:country_code":"NP",
    "gn:dem":1381,
    "gn:feature_class":"P",
    "gn:feature_code":"PPLL",
    "gn:name":"Bhadaure",
    "gn:population":0,
    "gn:timezone":"Asia/Kathmandu",
    "iso:country":"NP",
    "name:pol_x_preferred":[
        "Bhadaure"
    ],
    "wof:name":"Bhadaure",
    "wof:placetype":"locality"
},
  "geometry": {"coordinates":[85.22449,27.989],"type":"Point"}
}