{
  "type": "Feature",
  "properties": {
    "gn:admin1_code":"WR",
    "gn:admin2_code":"4",
    "gn:admin3_code":"40.0",
    "gn:admin4_code":"400016.0",
    "gn:asciiname":"Sunesidanda",
    "gn:country_code":"NP",
    "gn:dem":847,
    "gn:feature_class":"P",
    "gn:feature_code":"PPLL",
    "gn:name":"Sunesidanda",
    "gn:population":0,
    "gn:timezone":"Asia/Kathmandu",
    "iso:country":"NP",
    "wof:name":"Sunesidanda",
    "wof:placetype":"locality"
},
  "geometry": {"coordinates":[84.0239,28.2225],"type":"Point"}
}