{
  "type": "Feature",
  "properties": {
    "gn:admin1_code":"FR",
    "gn:admin2_code":"9",
    "gn:admin3_code":"74",
    "gn:admin4_code":"740024.0",
    "gn:asciiname":"Bungaghar",
    "gn:country_code":"NP",
    "gn:dem":1843,
    "gn:feature_class":"P",
    "gn:feature_code":"PPLL",
    "gn:name":"Bungaghar",
    "gn:population":0,
    "gn:timezone":"Asia/Kathmandu",
    "iso:country":"NP",
    "wof:name":"Bungaghar",
    "wof:placetype":"locality"
},
  "geometry": {"coordinates":[80.42661,29.50679],"type":"Point"}
}