{
  "type": "Feature",
  "properties": {
    "gn:admin1_code":"ER",
    "gn:admin2_code":"13",
    "gn:admin3_code":"13",
    "gn:admin4_code":"130054",
    "gn:asciiname":"Pelung",
    "gn:country_code":"NP",
    "gn:dem":1561,
    "gn:feature_class":"P",
    "gn:feature_code":"PPLL",
    "gn:name":"Pelung",
    "gn:population":0,
    "gn:timezone":"Asia/Kathmandu",
    "iso:country":"NP",
    "wof:name":"Pelung",
    "wof:placetype":"locality"
},
  "geometry": {"coordinates":[86.89335,27.20963],"type":"Point"}
}