{
  "type": "Feature",
  "properties": {
    "gn:admin1_code":"ER",
    "gn:admin2_code":"13",
    "gn:admin3_code":"12",
    "gn:admin4_code":"120055",
    "gn:asciiname":"Sodhu",
    "gn:country_code":"NP",
    "gn:dem":549,
    "gn:feature_class":"P",
    "gn:feature_code":"PPLL",
    "gn:name":"Sodhu",
    "gn:population":0,
    "gn:timezone":"Asia/Kathmandu",
    "iso:country":"NP",
    "wof:name":"Sodhu",
    "wof:placetype":"locality"
},
  "geometry": {"coordinates":[86.49678,27.18923],"type":"Point"}
}