{
  "type": "Feature",
  "properties": {
    "gn:admin1_code":"MR",
    "gn:admin2_code":"2.0",
    "gn:admin3_code":"57.0",
    "gn:admin4_code":"570031.0",
    "gn:asciiname":"Chaukipur",
    "gn:country_code":"NP",
    "gn:dem":169,
    "gn:feature_class":"P",
    "gn:feature_code":"PPLL",
    "gn:name":"Chaukipur",
    "gn:population":0,
    "gn:timezone":"Asia/Kathmandu",
    "iso:country":"NP",
    "wof:name":"Chaukipur",
    "wof:placetype":"locality"
},
  "geometry": {"coordinates":[81.64704,28.24371],"type":"Point"}
}