{
  "type": "Feature",
  "properties": {
    "gn:admin1_code":"MR",
    "gn:admin2_code":"2",
    "gn:admin3_code":"60.0",
    "gn:admin4_code":"600024.0",
    "gn:asciiname":"Sanigaun",
    "gn:country_code":"NP",
    "gn:dem":1554,
    "gn:feature_class":"P",
    "gn:feature_code":"PPLL",
    "gn:name":"Sanigaun",
    "gn:population":0,
    "gn:timezone":"Asia/Kathmandu",
    "iso:country":"NP",
    "name:mai_x_preferred":[
        "\u0936\u0928\u0940\u0917\u093e\u090a\u0901"
    ],
    "name:msa_x_preferred":[
        "Sanigaun"
    ],
    "name:nep_x_preferred":[
        "\u0936\u0928\u0940\u0917\u093e\u090a\u0901"
    ],
    "name:new_x_preferred":[
        "\u0938\u093e\u0928\u0940\u0917\u093e\u0909\u0902"
    ],
    "name:pol_x_preferred":[
        "Sanigaun"
    ],
    "wof:name":"Sanigaun",
    "wof:placetype":"locality"
},
  "geometry": {"coordinates":[81.82174999999999,28.75549],"type":"Point"}
}