{
  "type": "Feature",
  "properties": {
    "gn:admin1_code":"FR",
    "gn:admin2_code":"14",
    "gn:admin3_code":"68",
    "gn:admin4_code":"680035",
    "gn:asciiname":"Madasain",
    "gn:country_code":"NP",
    "gn:dem":1054,
    "gn:feature_class":"P",
    "gn:feature_code":"PPLL",
    "gn:name":"Madasain",
    "gn:population":0,
    "gn:timezone":"Asia/Kathmandu",
    "iso:country":"NP",
    "wof:name":"Madasain",
    "wof:placetype":"locality"
},
  "geometry": {"coordinates":[80.99313000000002,29.46695],"type":"Point"}
}