{
  "type": "Feature",
  "properties": {
    "gn:admin1_code":"WR",
    "gn:admin2_code":"8",
    "gn:admin3_code":"47",
    "gn:admin4_code":"470046.0",
    "gn:asciiname":"Bhirpani",
    "gn:country_code":"NP",
    "gn:dem":1191,
    "gn:feature_class":"P",
    "gn:feature_code":"PPLL",
    "gn:name":"Bhirpani",
    "gn:population":0,
    "gn:timezone":"Asia/Kathmandu",
    "iso:country":"NP",
    "name:ceb_x_preferred":[
        "Bhirpani"
    ],
    "name:msa_x_preferred":[
        "Bhirpani"
    ],
    "name:pol_x_preferred":[
        "Bhirpani"
    ],
    "wof:name":"Bhirpani",
    "wof:placetype":"locality"
},
  "geometry": {"coordinates":[83.86966,27.76356],"type":"Point"}
}