{
  "type": "Feature",
  "properties": {
    "gn:admin1_code":"MR",
    "gn:admin2_code":"12",
    "gn:admin3_code":"55",
    "gn:admin4_code":"550046",
    "gn:asciiname":"Timile",
    "gn:country_code":"NP",
    "gn:dem":1543,
    "gn:feature_class":"P",
    "gn:feature_code":"PPLL",
    "gn:name":"Timile",
    "gn:population":0,
    "gn:timezone":"Asia/Kathmandu",
    "iso:country":"NP",
    "wof:name":"Timile",
    "wof:placetype":"locality"
},
  "geometry": {"coordinates":[82.29850999999999,28.49685],"type":"Point"}
}