{
  "type": "Feature",
  "properties": {
    "gn:admin1_code":"FR",
    "gn:admin2_code":"14",
    "gn:admin3_code":"71.0",
    "gn:admin4_code":"710036.0",
    "gn:asciiname":"Narayanpur",
    "gn:country_code":"NP",
    "gn:dem":155,
    "gn:feature_class":"P",
    "gn:feature_code":"PPLL",
    "gn:name":"Narayanpur",
    "gn:population":0,
    "gn:timezone":"Asia/Kathmandu",
    "iso:country":"NP",
    "name:ceb_x_preferred":[
        "Narayanpur"
    ],
    "name:fra_x_preferred":[
        "Narayanpur"
    ],
    "name:pol_x_preferred":[
        "Narayanpur"
    ],
    "name:swe_x_preferred":[
        "Narayanpur"
    ],
    "name:tel_x_preferred":[
        "\u0c28\u0c3e\u0c30\u0c3e\u0c2f\u0c23\u0c4d\u200c\u0c2a\u0c42\u0c30\u0c4d"
    ],
    "wof:name":"Narayanpur",
    "wof:placetype":"locality"
},
  "geometry": {"coordinates":[80.82075999999998,28.5408],"type":"Point"}
}