{
  "type": "Feature",
  "properties": {
    "gn:admin1_code":"ER",
    "gn:admin2_code":"10.0",
    "gn:admin3_code":"1.0",
    "gn:admin4_code":"10036.0",
    "gn:asciiname":"Eku",
    "gn:country_code":"NP",
    "gn:dem":1763,
    "gn:feature_class":"P",
    "gn:feature_code":"PPLL",
    "gn:name":"Eku",
    "gn:population":0,
    "gn:timezone":"Asia/Kathmandu",
    "iso:country":"NP",
    "name:bul_x_preferred":[
        "\u0415\u043a\u0443"
    ],
    "name:deu_x_preferred":[
        "W\u0113ku"
    ],
    "name:fas_x_preferred":[
        "\u0627\u06a9\u0648"
    ],
    "name:fin_x_preferred":[
        "Eiku"
    ],
    "name:fra_x_preferred":[
        "Eku"
    ],
    "name:ita_x_preferred":[
        "Eku"
    ],
    "name:jpn_x_preferred":[
        "\u6ac2"
    ],
    "name:lit_x_preferred":[
        "Eku"
    ],
    "name:spa_x_preferred":[
        "Eku"
    ],
    "wof:name":"Eku",
    "wof:placetype":"locality"
},
  "geometry": {"coordinates":[87.58074000000001,27.38933],"type":"Point"}
}