{
  "type": "Feature",
  "properties": {
    "gn:admin1_code":"WR",
    "gn:admin2_code":"4",
    "gn:admin3_code":"36.0",
    "gn:admin4_code":"360027.0",
    "gn:asciiname":"Jhahare",
    "gn:country_code":"NP",
    "gn:dem":889,
    "gn:feature_class":"P",
    "gn:feature_code":"PPLL",
    "gn:name":"Jhahare",
    "gn:population":0,
    "gn:timezone":"Asia/Kathmandu",
    "iso:country":"NP",
    "wof:name":"Jhahare",
    "wof:placetype":"locality"
},
  "geometry": {"coordinates":[84.79640999999999,27.77836],"type":"Point"}
}