{
  "type": "Feature",
  "properties": {
    "gn:admin1_code":"00",
    "gn:asciiname":"Tokha",
    "gn:country_code":"NP",
    "gn:dem":1003,
    "gn:feature_class":"P",
    "gn:feature_code":"PPL",
    "gn:name":"\u1e6cokh\u0101",
    "gn:population":0,
    "gn:timezone":"Asia/Kathmandu",
    "iso:country":"NP",
    "name:nep_x_preferred":[
        "\u1e6cokh\u0101"
    ],
    "wof:name":"Tokha",
    "wof:placetype":"locality"
},
  "geometry": {"coordinates":[87.54451999999998,26.93564000000001],"type":"Point"}
}