{
  "type": "Feature",
  "properties": {
    "gn:admin1_code":"00",
    "gn:asciiname":"Tokha",
    "gn:country_code":"NP",
    "gn:dem":1003,
    "gn:feature_class":"P",
    "gn:feature_code":"PPL",
    "gn:name":"\u1e6cokh\u0101",
    "gn:population":0,
    "gn:timezone":"Asia/Kathmandu",
    "iso:country":"NP",
    "name:ara_x_preferred":[
        "\u062a\u0648\u062e\u0627"
    ],
    "name:deu_x_preferred":[
        "Tokha"
    ],
    "name:mai_x_preferred":[
        "\u091f\u094b\u0916\u093e \u0928\u0917\u0930\u092a\u093e\u0932\u093f\u0915\u093e"
    ],
    "name:nep_x_preferred":[
        "\u1e6cokh\u0101"
    ],
    "name:nep_x_variant":[
        "\u091f\u094b\u0916\u093e \u0928\u0917\u0930\u092a\u093e\u0932\u093f\u0915\u093e"
    ],
    "name:tam_x_preferred":[
        "\u0ba4\u0bcb\u0b95\u0bbe"
    ],
    "wof:name":"Tokha",
    "wof:placetype":"locality"
},
  "geometry": {"coordinates":[87.54451999999998,26.93564000000001],"type":"Point"}
}