{
  "type": "Feature",
  "properties": {
    "gn:admin1_code":"FR",
    "gn:admin2_code":"9",
    "gn:admin3_code":"74",
    "gn:admin4_code":"740045",
    "gn:asciiname":"Tal",
    "gn:country_code":"NP",
    "gn:dem":1884,
    "gn:feature_class":"P",
    "gn:feature_code":"PPLL",
    "gn:name":"Tal",
    "gn:population":0,
    "gn:timezone":"Asia/Kathmandu",
    "iso:country":"NP",
    "wof:name":"Tal",
    "wof:placetype":"locality"
},
  "geometry": {"coordinates":[80.37553,29.46096],"type":"Point"}
}