{
  "type": "Feature",
  "properties": {
    "gn:admin1_code":"FR",
    "gn:admin2_code":"9",
    "gn:admin3_code":"73.0",
    "gn:admin4_code":"730017.0",
    "gn:asciiname":"Musurekaphal",
    "gn:country_code":"NP",
    "gn:dem":1231,
    "gn:feature_class":"P",
    "gn:feature_code":"PPLL",
    "gn:name":"Musurekaphal",
    "gn:population":0,
    "gn:timezone":"Asia/Kathmandu",
    "iso:country":"NP",
    "wof:name":"Musurekaphal",
    "wof:placetype":"locality"
},
  "geometry": {"coordinates":[80.714,29.29408],"type":"Point"}
}