{
  "type": "Feature",
  "properties": {
    "gn:admin1_code":"WR",
    "gn:admin2_code":"4.0",
    "gn:admin3_code":"39.0",
    "gn:admin4_code":"390059.0",
    "gn:asciiname":"Dimik",
    "gn:country_code":"NP",
    "gn:dem":587,
    "gn:feature_class":"P",
    "gn:feature_code":"PPLL",
    "gn:name":"Dimik",
    "gn:population":0,
    "gn:timezone":"Asia/Kathmandu",
    "iso:country":"NP",
    "wof:name":"Dimik",
    "wof:placetype":"locality"
},
  "geometry": {"coordinates":[83.68557,27.93213],"type":"Point"}
}