{
  "type": "Feature",
  "properties": {
    "gn:admin1_code":"CR",
    "gn:admin2_code":"5",
    "gn:admin3_code":"21",
    "gn:admin4_code":"210045",
    "gn:asciiname":"Golmatar",
    "gn:country_code":"NP",
    "gn:dem":794,
    "gn:feature_class":"P",
    "gn:feature_code":"PPLL",
    "gn:name":"Golmatar",
    "gn:population":0,
    "gn:timezone":"Asia/Kathmandu",
    "iso:country":"NP",
    "wof:name":"Golmatar",
    "wof:placetype":"locality"
},
  "geometry": {"coordinates":[86.03341999999998,27.31718],"type":"Point"}
}