{
  "type": "Feature",
  "properties": {
    "gn:admin1_code":"WR",
    "gn:admin2_code":"3",
    "gn:admin3_code":"44",
    "gn:admin4_code":"440041",
    "gn:asciiname":"Pang",
    "gn:country_code":"NP",
    "gn:dem":1062,
    "gn:feature_class":"P",
    "gn:feature_code":"PPLL",
    "gn:name":"Pang",
    "gn:population":0,
    "gn:timezone":"Asia/Kathmandu",
    "iso:country":"NP",
    "name:ceb_x_preferred":[
        "Pang"
    ],
    "name:msa_x_preferred":[
        "Pang"
    ],
    "name:nep_x_preferred":[
        "\u092a\u093e\u0919"
    ],
    "name:new_x_preferred":[
        "\u092a\u093e\u0919"
    ],
    "name:pol_x_preferred":[
        "Pang"
    ],
    "wof:name":"Pang",
    "wof:placetype":"locality"
},
  "geometry": {"coordinates":[83.62308,28.26251],"type":"Point"}
}