{
  "type": "Feature",
  "properties": {
    "gn:admin1_code":"CR",
    "gn:admin2_code":"1",
    "gn:admin3_code":"30.0",
    "gn:admin4_code":"300007.0",
    "gn:asciiname":"Pakhagaun",
    "gn:country_code":"NP",
    "gn:dem":631,
    "gn:feature_class":"P",
    "gn:feature_code":"PPLL",
    "gn:name":"Pakhagaun",
    "gn:population":0,
    "gn:timezone":"Asia/Kathmandu",
    "iso:country":"NP",
    "wof:name":"Pakhagaun",
    "wof:placetype":"locality"
},
  "geometry": {"coordinates":[84.80297,27.97148],"type":"Point"}
}