{
  "type": "Feature",
  "properties": {
    "gn:admin1_code":"ER",
    "gn:admin2_code":"13",
    "gn:admin3_code":"15",
    "gn:admin4_code":"150079",
    "gn:asciiname":"Kumaraul",
    "gn:country_code":"NP",
    "gn:dem":101,
    "gn:feature_class":"P",
    "gn:feature_code":"PPLL",
    "gn:name":"Kumaraul",
    "gn:population":0,
    "gn:timezone":"Asia/Kathmandu",
    "iso:country":"NP",
    "wof:name":"Kumaraul",
    "wof:placetype":"locality"
},
  "geometry": {"coordinates":[86.75118000000001,26.57684],"type":"Point"}
}