{
  "type": "Feature",
  "properties": {
    "gn:admin1_code":"WR",
    "gn:admin2_code":"3",
    "gn:admin3_code":"45.0",
    "gn:admin4_code":"450053.0",
    "gn:asciiname":"Dhunge Bisauna",
    "gn:country_code":"NP",
    "gn:dem":1325,
    "gn:feature_class":"P",
    "gn:feature_code":"PPLL",
    "gn:name":"Dhunge Bisauna",
    "gn:population":0,
    "gn:timezone":"Asia/Kathmandu",
    "iso:country":"NP",
    "wof:name":"Dhunge Bisauna",
    "wof:placetype":"locality"
},
  "geometry": {"coordinates":[83.52129000000002,28.25078],"type":"Point"}
}