{
  "type": "Feature",
  "properties": {
    "gn:admin1_code":"FR",
    "gn:admin2_code":"9",
    "gn:admin3_code":"74",
    "gn:admin4_code":"740006",
    "gn:asciiname":"Salyad",
    "gn:country_code":"NP",
    "gn:dem":2027,
    "gn:feature_class":"P",
    "gn:feature_code":"PPLL",
    "gn:name":"Salyad",
    "gn:population":0,
    "gn:timezone":"Asia/Kathmandu",
    "iso:country":"NP",
    "wof:name":"Salyad",
    "wof:placetype":"locality"
},
  "geometry": {"coordinates":[80.64059,29.57063],"type":"Point"}
}