{
  "type": "Feature",
  "properties": {
    "gn:admin1_code":"CR",
    "gn:admin2_code":"11.0",
    "gn:admin3_code":"33.0",
    "gn:admin4_code":"330099.0",
    "gn:asciiname":"Pipara",
    "gn:country_code":"NP",
    "gn:dem":106,
    "gn:feature_class":"P",
    "gn:feature_code":"PPLL",
    "gn:name":"Pipara",
    "gn:population":0,
    "gn:timezone":"Asia/Kathmandu",
    "iso:country":"NP",
    "wof:name":"Pipara",
    "wof:placetype":"locality"
},
  "geometry": {"coordinates":[85.12124,27.06806],"type":"Point"}
}