{
  "type": "Feature",
  "properties": {
    "gn:admin1_code":"CR",
    "gn:admin2_code":"11",
    "gn:admin3_code":"35.0",
    "gn:admin4_code":"350033.0",
    "gn:asciiname":"Jamunapur",
    "gn:country_code":"NP",
    "gn:dem":215,
    "gn:feature_class":"P",
    "gn:feature_code":"PPLL",
    "gn:name":"Jamunapur",
    "gn:population":0,
    "gn:timezone":"Asia/Kathmandu",
    "iso:country":"NP",
    "wof:name":"Jamunapur",
    "wof:placetype":"locality"
},
  "geometry": {"coordinates":[84.51461999999999,27.65639],"type":"Point"}
}