{
  "type": "Feature",
  "properties": {
    "gn:admin1_code":"MR",
    "gn:admin2_code":"12",
    "gn:admin3_code":"53",
    "gn:admin4_code":"530031",
    "gn:asciiname":"Baigaun",
    "gn:country_code":"NP",
    "gn:dem":1615,
    "gn:feature_class":"P",
    "gn:feature_code":"PPLL",
    "gn:name":"Baigaun",
    "gn:population":0,
    "gn:timezone":"Asia/Kathmandu",
    "iso:country":"NP",
    "wof:name":"Baigaun",
    "wof:placetype":"locality"
},
  "geometry": {"coordinates":[82.65120999999998,28.31386],"type":"Point"}
}