{
  "type": "Feature",
  "properties": {
    "gn:admin1_code":"00",
    "gn:asciiname":"Hagabari",
    "gn:country_code":"NP",
    "gn:dem":104,
    "gn:feature_class":"P",
    "gn:feature_code":"PPL",
    "gn:name":"H\u0101\u0303gab\u0101ri\u0307\u0304",
    "gn:population":0,
    "gn:timezone":"Asia/Kathmandu",
    "iso:country":"NP",
    "name:nep_x_preferred":[
        "H\u0101\u0303gab\u0101ri\u0307\u0304"
    ],
    "wof:name":"Hagabari",
    "wof:placetype":"locality"
},
  "geometry": {"coordinates":[88.02285999999999,26.56677],"type":"Point"}
}