{
  "type": "Feature",
  "properties": {
    "gn:admin1_code":"ER",
    "gn:admin2_code":"7",
    "gn:admin3_code":"7.0",
    "gn:admin4_code":"70004.0",
    "gn:asciiname":"Sartopa",
    "gn:country_code":"NP",
    "gn:dem":1325,
    "gn:feature_class":"P",
    "gn:feature_code":"PPLL",
    "gn:name":"Sartopa",
    "gn:population":0,
    "gn:timezone":"Asia/Kathmandu",
    "iso:country":"NP",
    "wof:name":"Sartopa",
    "wof:placetype":"locality"
},
  "geometry": {"coordinates":[87.47611999999999,26.88195],"type":"Point"}
}