{
  "type": "Feature",
  "properties": {
    "gn:admin1_code":"CR",
    "gn:admin2_code":"1",
    "gn:admin3_code":"30.0",
    "gn:admin4_code":"300036.0",
    "gn:asciiname":"Lapsibot",
    "gn:country_code":"NP",
    "gn:dem":1326,
    "gn:feature_class":"P",
    "gn:feature_code":"PPLL",
    "gn:name":"Lapsibot",
    "gn:population":0,
    "gn:timezone":"Asia/Kathmandu",
    "iso:country":"NP",
    "wof:name":"Lapsibot",
    "wof:placetype":"locality"
},
  "geometry": {"coordinates":[84.91608000000002,28.06465],"type":"Point"}
}