{
  "type": "Feature",
  "properties": {
    "gn:admin1_code":"00",
    "gn:asciiname":"Tarenggaon",
    "gn:country_code":"NP",
    "gn:dem":3733,
    "gn:feature_class":"P",
    "gn:feature_code":"PPL",
    "gn:name":"Tarenggaon",
    "gn:population":0,
    "gn:timezone":"Asia/Kathmandu",
    "iso:country":"NP",
    "wof:name":"Tarenggaon",
    "wof:placetype":"locality"
},
  "geometry": {"coordinates":[83.35483000000001,28.87696],"type":"Point"}
}