{
  "type": "Feature",
  "properties": {
    "gn:admin1_code":"CR",
    "gn:admin2_code":"11",
    "gn:admin3_code":"32",
    "gn:admin4_code":"320090.0",
    "gn:asciiname":"Sarkitol",
    "gn:country_code":"NP",
    "gn:dem":121,
    "gn:feature_class":"P",
    "gn:feature_code":"PPLL",
    "gn:name":"Sarkitol",
    "gn:population":0,
    "gn:timezone":"Asia/Kathmandu",
    "iso:country":"NP",
    "wof:name":"Sarkitol",
    "wof:placetype":"locality"
},
  "geometry": {"coordinates":[85.31806999999998,27.07153],"type":"Point"}
}