{
  "type": "Feature",
  "properties": {
    "gn:admin1_code":"WR",
    "gn:admin2_code":"4",
    "gn:admin3_code":"36.0",
    "gn:admin4_code":"360044.0",
    "gn:asciiname":"Chanaute",
    "gn:country_code":"NP",
    "gn:dem":602,
    "gn:feature_class":"P",
    "gn:feature_code":"PPLL",
    "gn:name":"Chanaute",
    "gn:population":0,
    "gn:timezone":"Asia/Kathmandu",
    "iso:country":"NP",
    "wof:name":"Chanaute",
    "wof:placetype":"locality"
},
  "geometry": {"coordinates":[84.66741,28.11494],"type":"Point"}
}