{
  "type": "Feature",
  "properties": {
    "gn:admin1_code":"00",
    "gn:asciiname":"Palase",
    "gn:country_code":"NP",
    "gn:dem":502,
    "gn:feature_class":"P",
    "gn:feature_code":"PPL",
    "gn:name":"Pal\u0101\u0303se",
    "gn:population":0,
    "gn:timezone":"Asia/Kathmandu",
    "iso:country":"NP",
    "name:nep_x_preferred":[
        "Pal\u0101nse"
    ],
    "name:und_x_variant":[
        "Pal\u0101\u0303se"
    ],
    "wof:name":"Palase",
    "wof:placetype":"locality"
},
  "geometry": {"coordinates":[85.93593,27.39067],"type":"Point"}
}