{
  "type": "Feature",
  "properties": {
    "gn:admin1_code":"WR",
    "gn:admin2_code":"8",
    "gn:admin3_code":"51.0",
    "gn:admin4_code":"510009.0",
    "gn:asciiname":"Siudeni",
    "gn:country_code":"NP",
    "gn:dem":1015,
    "gn:feature_class":"P",
    "gn:feature_code":"PPLL",
    "gn:name":"Siudeni",
    "gn:population":0,
    "gn:timezone":"Asia/Kathmandu",
    "iso:country":"NP",
    "wof:name":"Siudeni",
    "wof:placetype":"locality"
},
  "geometry": {"coordinates":[83.22036999999997,28.00657],"type":"Point"}
}