{
  "type": "Feature",
  "properties": {
    "gn:admin1_code":"MR",
    "gn:admin2_code":"6",
    "gn:admin3_code":"66.0",
    "gn:admin4_code":"660023.0",
    "gn:asciiname":"Mankhetikharka",
    "gn:country_code":"NP",
    "gn:dem":3890,
    "gn:feature_class":"P",
    "gn:feature_code":"PPLL",
    "gn:name":"Mankhetikharka",
    "gn:population":0,
    "gn:timezone":"Asia/Kathmandu",
    "iso:country":"NP",
    "wof:name":"Mankhetikharka",
    "wof:placetype":"locality"
},
  "geometry": {"coordinates":[82.05015999999998,29.84034],"type":"Point"}
}