{
  "type": "Feature",
  "properties": {
    "gn:admin1_code":"ER",
    "gn:admin2_code":"7",
    "gn:admin3_code":"7.0",
    "gn:admin4_code":"70030.0",
    "gn:asciiname":"Kaseni",
    "gn:country_code":"NP",
    "gn:dem":1098,
    "gn:feature_class":"P",
    "gn:feature_code":"PPLL",
    "gn:name":"Kaseni",
    "gn:population":0,
    "gn:timezone":"Asia/Kathmandu",
    "iso:country":"NP",
    "name:pol_x_preferred":[
        "Kaseni"
    ],
    "wof:name":"Kaseni",
    "wof:placetype":"locality"
},
  "geometry": {"coordinates":[87.26534000000002,27.03659],"type":"Point"}
}