{
  "type": "Feature",
  "properties": {
    "gn:admin1_code":"ER",
    "gn:admin2_code":"13",
    "gn:admin3_code":"16",
    "gn:admin4_code":"160080",
    "gn:asciiname":"Baldara",
    "gn:country_code":"NP",
    "gn:dem":166,
    "gn:feature_class":"P",
    "gn:feature_code":"PPLL",
    "gn:name":"Baldara",
    "gn:population":0,
    "gn:timezone":"Asia/Kathmandu",
    "iso:country":"NP",
    "name:hin_x_preferred":[
        "\u092c\u093e\u0932\u0926\u0921\u093c\u093e"
    ],
    "wof:name":"Baldara",
    "wof:placetype":"locality"
},
  "geometry": {"coordinates":[86.37251999999999,26.80311],"type":"Point"}
}