{
  "type": "Feature",
  "properties": {
    "gn:admin1_code":"ER",
    "gn:admin2_code":"7",
    "gn:admin3_code":"9",
    "gn:admin4_code":"90031",
    "gn:asciiname":"Kusuwa",
    "gn:country_code":"NP",
    "gn:dem":1123,
    "gn:feature_class":"P",
    "gn:feature_code":"PPLL",
    "gn:name":"Kusuwa",
    "gn:population":0,
    "gn:timezone":"Asia/Kathmandu",
    "iso:country":"NP",
    "wof:name":"Kusuwa",
    "wof:placetype":"locality"
},
  "geometry": {"coordinates":[87.33606999999998,27.38373],"type":"Point"}
}