{
  "type": "Feature",
  "properties": {
    "gn:admin1_code":"ER",
    "gn:admin2_code":"13",
    "gn:admin3_code":"11",
    "gn:admin4_code":"110021",
    "gn:asciiname":"Lokhim",
    "gn:country_code":"NP",
    "gn:dem":1934,
    "gn:feature_class":"P",
    "gn:feature_code":"PPLL",
    "gn:name":"Lokhim",
    "gn:population":0,
    "gn:timezone":"Asia/Kathmandu",
    "iso:country":"NP",
    "name:bih_x_preferred":[
        "\u0932\u094b\u0916\u093f\u092e"
    ],
    "name:ceb_x_preferred":[
        "Lokhim"
    ],
    "name:fra_x_preferred":[
        "Lokhim"
    ],
    "name:hin_x_preferred":[
        "\u0932\u094b\u0916\u093f\u092e"
    ],
    "name:mai_x_preferred":[
        "\u0932\u094b\u0916\u093f\u092e"
    ],
    "name:msa_x_preferred":[
        "Lokhim"
    ],
    "name:nep_x_preferred":[
        "\u0932\u094b\u0916\u093f\u092e"
    ],
    "name:new_x_preferred":[
        "\u0932\u094b\u0916\u093f\u092e"
    ],
    "name:pol_x_preferred":[
        "Lokhim"
    ],
    "wof:name":"Lokhim",
    "wof:placetype":"locality"
},
  "geometry": {"coordinates":[86.75513000000002,27.43848],"type":"Point"}
}