{
  "type": "Feature",
  "properties": {
    "gn:admin1_code":"MR",
    "gn:admin2_code":"12",
    "gn:admin3_code":"55",
    "gn:admin4_code":"550041",
    "gn:asciiname":"Amraikholi",
    "gn:country_code":"NP",
    "gn:dem":1582,
    "gn:feature_class":"P",
    "gn:feature_code":"PPLL",
    "gn:name":"Amraikholi",
    "gn:population":0,
    "gn:timezone":"Asia/Kathmandu",
    "iso:country":"NP",
    "wof:name":"Amraikholi",
    "wof:placetype":"locality"
},
  "geometry": {"coordinates":[82.33708,28.51512],"type":"Point"}
}