{
  "type": "Feature",
  "properties": {
    "gn:admin1_code":"ER",
    "gn:admin2_code":"7",
    "gn:admin3_code":"9",
    "gn:admin4_code":"90004",
    "gn:asciiname":"Khanigaun",
    "gn:country_code":"NP",
    "gn:dem":908,
    "gn:feature_class":"P",
    "gn:feature_code":"PPLL",
    "gn:name":"Khanigaun",
    "gn:population":0,
    "gn:timezone":"Asia/Kathmandu",
    "iso:country":"NP",
    "wof:name":"Khanigaun",
    "wof:placetype":"locality"
},
  "geometry": {"coordinates":[87.24760999999999,27.32575],"type":"Point"}
}