{
  "type": "Feature",
  "properties": {
    "gn:admin1_code":"CR",
    "gn:admin2_code":"5",
    "gn:admin3_code":"20",
    "gn:admin4_code":"200009",
    "gn:asciiname":"Bhotechhap",
    "gn:country_code":"NP",
    "gn:dem":1162,
    "gn:feature_class":"P",
    "gn:feature_code":"PPLL",
    "gn:name":"Bhotechhap",
    "gn:population":0,
    "gn:timezone":"Asia/Kathmandu",
    "iso:country":"NP",
    "wof:name":"Bhotechhap",
    "wof:placetype":"locality"
},
  "geometry": {"coordinates":[85.96531999999998,27.31505],"type":"Point"}
}