{
  "type": "Feature",
  "properties": {
    "gn:admin1_code":"ER",
    "gn:admin2_code":"10",
    "gn:admin3_code":"3.0",
    "gn:admin4_code":"30039.0",
    "gn:asciiname":"Gairi",
    "gn:country_code":"NP",
    "gn:dem":1972,
    "gn:feature_class":"P",
    "gn:feature_code":"PPLL",
    "gn:name":"Gairi",
    "gn:population":0,
    "gn:timezone":"Asia/Kathmandu",
    "iso:country":"NP",
    "wof:name":"Gairi",
    "wof:placetype":"locality"
},
  "geometry": {"coordinates":[87.86152,26.98501],"type":"Point"}
}