{
  "type": "Feature",
  "properties": {
    "gn:admin1_code":"MR",
    "gn:admin2_code":"2.0",
    "gn:admin3_code":"58.0",
    "gn:admin4_code":"580032.0",
    "gn:asciiname":"Bahadurpur",
    "gn:country_code":"NP",
    "gn:dem":158,
    "gn:feature_class":"P",
    "gn:feature_code":"PPLL",
    "gn:name":"Bahadurpur",
    "gn:population":0,
    "gn:timezone":"Asia/Kathmandu",
    "iso:country":"NP",
    "wof:name":"Bahadurpur",
    "wof:placetype":"locality"
},
  "geometry": {"coordinates":[81.24485,28.43366],"type":"Point"}
}