{
  "type": "Feature",
  "properties": {
    "gn:admin1_code":"FR",
    "gn:admin2_code":"14",
    "gn:admin3_code":"69.0",
    "gn:admin4_code":"690012.0",
    "gn:asciiname":"Dhunge Kusiban",
    "gn:country_code":"NP",
    "gn:dem":1652,
    "gn:feature_class":"P",
    "gn:feature_code":"PPLL",
    "gn:name":"Dhunge Kusiban",
    "gn:population":0,
    "gn:timezone":"Asia/Kathmandu",
    "iso:country":"NP",
    "wof:name":"Dhunge Kusiban",
    "wof:placetype":"locality"
},
  "geometry": {"coordinates":[81.40193000000002,29.11849],"type":"Point"}
}