{
  "type": "Feature",
  "properties": {
    "gn:admin1_code":"WR",
    "gn:admin2_code":"3",
    "gn:admin3_code":"42",
    "gn:admin4_code":"420002",
    "gn:asciiname":"Thingar",
    "gn:country_code":"NP",
    "gn:dem":3971,
    "gn:feature_class":"P",
    "gn:feature_code":"PPLL",
    "gn:name":"Thingar",
    "gn:population":0,
    "gn:timezone":"Asia/Kathmandu",
    "iso:country":"NP",
    "wof:name":"Thingar",
    "wof:placetype":"locality"
},
  "geometry": {"coordinates":[83.94280999999999,29.20674],"type":"Point"}
}