{
  "type": "Feature",
  "properties": {
    "gn:admin1_code":"CR",
    "gn:admin2_code":"1.0",
    "gn:admin3_code":"26.0",
    "gn:admin4_code":"260006.0",
    "gn:asciiname":"Bhatedhikuro",
    "gn:country_code":"NP",
    "gn:dem":1328,
    "gn:feature_class":"P",
    "gn:feature_code":"PPLL",
    "gn:name":"Bhatedhikuro",
    "gn:population":0,
    "gn:timezone":"Asia/Kathmandu",
    "iso:country":"NP",
    "wof:name":"Bhatedhikuro",
    "wof:placetype":"locality"
},
  "geometry": {"coordinates":[85.44889999999999,27.66271],"type":"Point"}
}