{
  "type": "Feature",
  "properties": {
    "gn:admin1_code":"MR",
    "gn:admin2_code":"12",
    "gn:admin3_code":"54",
    "gn:admin4_code":"540030",
    "gn:asciiname":"Ratamata",
    "gn:country_code":"NP",
    "gn:dem":1548,
    "gn:feature_class":"P",
    "gn:feature_code":"PPLL",
    "gn:name":"Ratamata",
    "gn:population":0,
    "gn:timezone":"Asia/Kathmandu",
    "iso:country":"NP",
    "wof:name":"Ratamata",
    "wof:placetype":"locality"
},
  "geometry": {"coordinates":[82.62013,28.63676],"type":"Point"}
}