{
  "type": "Feature",
  "properties": {
    "gn:admin1_code":"ER",
    "gn:admin2_code":"10",
    "gn:admin3_code":"4.0",
    "gn:admin4_code":"40040.0",
    "gn:asciiname":"Durgabhitta",
    "gn:country_code":"NP",
    "gn:dem":78,
    "gn:feature_class":"P",
    "gn:feature_code":"PPLL",
    "gn:name":"Durgabhitta",
    "gn:population":0,
    "gn:timezone":"Asia/Kathmandu",
    "iso:country":"NP",
    "wof:name":"Durgabhitta",
    "wof:placetype":"locality"
},
  "geometry": {"coordinates":[87.99443000000002,26.45291],"type":"Point"}
}