{
  "type": "Feature",
  "properties": {
    "gn:admin1_code":"ER",
    "gn:admin2_code":"13",
    "gn:admin3_code":"16",
    "gn:admin4_code":"160094",
    "gn:asciiname":"Gamhariya katti",
    "gn:country_code":"NP",
    "gn:dem":84,
    "gn:feature_class":"P",
    "gn:feature_code":"PPLL",
    "gn:name":"Gamhariya katti",
    "gn:population":0,
    "gn:timezone":"Asia/Kathmandu",
    "iso:country":"NP",
    "wof:name":"Gamhariya katti",
    "wof:placetype":"locality"
},
  "geometry": {"coordinates":[86.21366999999999,26.69374],"type":"Point"}
}