{
  "type": "Feature",
  "properties": {
    "gn:admin1_code":"MR",
    "gn:admin2_code":"12",
    "gn:admin3_code":"53",
    "gn:admin4_code":"530026",
    "gn:asciiname":"Khewase",
    "gn:country_code":"NP",
    "gn:dem":1552,
    "gn:feature_class":"P",
    "gn:feature_code":"PPLL",
    "gn:name":"Khewase",
    "gn:population":0,
    "gn:timezone":"Asia/Kathmandu",
    "iso:country":"NP",
    "wof:name":"Khewase",
    "wof:placetype":"locality"
},
  "geometry": {"coordinates":[82.63655,28.26272],"type":"Point"}
}