{
  "type": "Feature",
  "properties": {
    "gn:admin1_code":"ER",
    "gn:admin2_code":"13",
    "gn:admin3_code":"13.0",
    "gn:admin4_code":"130021.0",
    "gn:asciiname":"Sikla",
    "gn:country_code":"NP",
    "gn:dem":1518,
    "gn:feature_class":"P",
    "gn:feature_code":"PPLL",
    "gn:name":"Sikla",
    "gn:population":0,
    "gn:timezone":"Asia/Kathmandu",
    "iso:country":"NP",
    "wof:name":"Sikla",
    "wof:placetype":"locality"
},
  "geometry": {"coordinates":[86.77783000000002,27.11999],"type":"Point"}
}