{
  "type": "Feature",
  "properties": {
    "gn:admin1_code":"FR",
    "gn:admin2_code":"9",
    "gn:admin3_code":"74",
    "gn:admin4_code":"740018",
    "gn:asciiname":"Dhanau",
    "gn:country_code":"NP",
    "gn:dem":2025,
    "gn:feature_class":"P",
    "gn:feature_code":"PPLL",
    "gn:name":"Dhanau",
    "gn:population":0,
    "gn:timezone":"Asia/Kathmandu",
    "iso:country":"NP",
    "name:hin_x_preferred":[
        "\u0927\u0928\u093e\u090a"
    ],
    "wof:name":"Dhanau",
    "wof:placetype":"locality"
},
  "geometry": {"coordinates":[80.43118,29.47927],"type":"Point"}
}