{
  "type": "Feature",
  "properties": {
    "gn:admin1_code":"WR",
    "gn:admin2_code":"8",
    "gn:admin3_code":"47",
    "gn:admin4_code":"470061",
    "gn:asciiname":"Tahunn",
    "gn:country_code":"NP",
    "gn:dem":1354,
    "gn:feature_class":"P",
    "gn:feature_code":"PPLL",
    "gn:name":"Tahunn",
    "gn:population":0,
    "gn:timezone":"Asia/Kathmandu",
    "iso:country":"NP",
    "wof:name":"Tahunn",
    "wof:placetype":"locality"
},
  "geometry": {"coordinates":[83.71486,27.8375],"type":"Point"}
}