{
  "type": "Feature",
  "properties": {
    "gn:admin1_code":"CR",
    "gn:admin2_code":"1",
    "gn:admin3_code":"27.0",
    "gn:admin4_code":"270036.0",
    "gn:asciiname":"Kisipindi",
    "gn:country_code":"NP",
    "gn:dem":1394,
    "gn:feature_class":"P",
    "gn:feature_code":"PPLL",
    "gn:name":"Kisipindi",
    "gn:population":0,
    "gn:timezone":"Asia/Kathmandu",
    "iso:country":"NP",
    "wof:name":"Kisipindi",
    "wof:placetype":"locality"
},
  "geometry": {"coordinates":[85.23820000000001,27.68859],"type":"Point"}
}