{
  "type": "Feature",
  "properties": {
    "gn:admin1_code":"FR",
    "gn:admin2_code":"14",
    "gn:admin3_code":"70.0",
    "gn:admin4_code":"700003.0",
    "gn:asciiname":"Osil",
    "gn:country_code":"NP",
    "gn:dem":1166,
    "gn:feature_class":"P",
    "gn:feature_code":"PPLL",
    "gn:name":"Osil",
    "gn:population":0,
    "gn:timezone":"Asia/Kathmandu",
    "iso:country":"NP",
    "wof:name":"Osil",
    "wof:placetype":"locality"
},
  "geometry": {"coordinates":[80.78323,29.02637],"type":"Point"}
}