{
  "type": "Feature",
  "properties": {
    "gn:admin1_code":"FR",
    "gn:admin2_code":"9",
    "gn:admin3_code":"74",
    "gn:admin4_code":"740058",
    "gn:asciiname":"Jalkuda",
    "gn:country_code":"NP",
    "gn:dem":1689,
    "gn:feature_class":"P",
    "gn:feature_code":"PPLL",
    "gn:name":"Jalkuda",
    "gn:population":0,
    "gn:timezone":"Asia/Kathmandu",
    "iso:country":"NP",
    "wof:name":"Jalkuda",
    "wof:placetype":"locality"
},
  "geometry": {"coordinates":[80.57838000000002,29.44196],"type":"Point"}
}