{
  "type": "Feature",
  "properties": {
    "gn:admin1_code":"WR",
    "gn:admin2_code":"8",
    "gn:admin3_code":"50.0",
    "gn:admin4_code":"500016.0",
    "gn:asciiname":"Sadawa",
    "gn:country_code":"NP",
    "gn:dem":123,
    "gn:feature_class":"P",
    "gn:feature_code":"PPLL",
    "gn:name":"Sadawa",
    "gn:population":0,
    "gn:timezone":"Asia/Kathmandu",
    "iso:country":"NP",
    "wof:name":"Sadawa",
    "wof:placetype":"locality"
},
  "geometry": {"coordinates":[82.84149000000002,27.61343],"type":"Point"}
}