{
  "type": "Feature",
  "properties": {
    "gn:admin1_code":"WR",
    "gn:admin2_code":"3",
    "gn:admin3_code":"45.0",
    "gn:admin4_code":"450016.0",
    "gn:asciiname":"Dum Chautara",
    "gn:country_code":"NP",
    "gn:dem":1591,
    "gn:feature_class":"P",
    "gn:feature_code":"PPLL",
    "gn:name":"Dum Chautara",
    "gn:population":0,
    "gn:timezone":"Asia/Kathmandu",
    "iso:country":"NP",
    "wof:name":"Dum Chautara",
    "wof:placetype":"locality"
},
  "geometry": {"coordinates":[83.57106999999998,28.12908],"type":"Point"}
}