{
  "type": "Feature",
  "properties": {
    "gn:admin1_code":"MR",
    "gn:admin2_code":"12",
    "gn:admin3_code":"56.0",
    "gn:admin4_code":"560021.0",
    "gn:asciiname":"Lahape",
    "gn:country_code":"NP",
    "gn:dem":1275,
    "gn:feature_class":"P",
    "gn:feature_code":"PPLL",
    "gn:name":"Lahape",
    "gn:population":0,
    "gn:timezone":"Asia/Kathmandu",
    "iso:country":"NP",
    "wof:name":"Lahape",
    "wof:placetype":"locality"
},
  "geometry": {"coordinates":[82.72669999999999,27.97503],"type":"Point"}
}