{
  "type": "Feature",
  "properties": {
    "gn:admin1_code":"MR",
    "gn:admin2_code":"12",
    "gn:admin3_code":"54",
    "gn:admin4_code":"540024",
    "gn:asciiname":"Bajure",
    "gn:country_code":"NP",
    "gn:dem":1806,
    "gn:feature_class":"P",
    "gn:feature_code":"PPLL",
    "gn:name":"Bajure",
    "gn:population":0,
    "gn:timezone":"Asia/Kathmandu",
    "iso:country":"NP",
    "wof:name":"Bajure",
    "wof:placetype":"locality"
},
  "geometry": {"coordinates":[82.63884,28.54961],"type":"Point"}
}