{
  "type": "Feature",
  "properties": {
    "gn:admin1_code":"ER",
    "gn:admin2_code":"7.0",
    "gn:admin3_code":"8.0",
    "gn:admin4_code":"80002.0",
    "gn:asciiname":"Dwangdwange",
    "gn:country_code":"NP",
    "gn:dem":2445,
    "gn:feature_class":"P",
    "gn:feature_code":"PPLL",
    "gn:name":"Dwangdwange",
    "gn:population":0,
    "gn:timezone":"Asia/Kathmandu",
    "iso:country":"NP",
    "wof:name":"Dwangdwange",
    "wof:placetype":"locality"
},
  "geometry": {"coordinates":[87.41705999999998,27.0856],"type":"Point"}
}