{
  "type": "Feature",
  "properties": {
    "gn:admin1_code":"MR",
    "gn:admin2_code":"6",
    "gn:admin3_code":"62.0",
    "gn:admin4_code":"620010.0",
    "gn:asciiname":"Meltali",
    "gn:country_code":"NP",
    "gn:dem":2454,
    "gn:feature_class":"P",
    "gn:feature_code":"PPLL",
    "gn:name":"Meltali",
    "gn:population":0,
    "gn:timezone":"Asia/Kathmandu",
    "iso:country":"NP",
    "wof:name":"Meltali",
    "wof:placetype":"locality"
},
  "geometry": {"coordinates":[82.73841999999998,29.04943],"type":"Point"}
}