{
  "type": "Feature",
  "properties": {
    "gn:admin1_code":"CR",
    "gn:admin2_code":"1",
    "gn:admin3_code":"28",
    "gn:admin4_code":"280014",
    "gn:asciiname":"Kalimaregaun",
    "gn:country_code":"NP",
    "gn:dem":1081,
    "gn:feature_class":"P",
    "gn:feature_code":"PPLL",
    "gn:name":"Kalimaregaun",
    "gn:population":0,
    "gn:timezone":"Asia/Kathmandu",
    "iso:country":"NP",
    "wof:name":"Kalimaregaun",
    "wof:placetype":"locality"
},
  "geometry": {"coordinates":[85.19925000000001,27.7798],"type":"Point"}
}