{
  "type": "Feature",
  "properties": {
    "gn:admin1_code":"ER",
    "gn:admin2_code":"7.0",
    "gn:admin3_code":"8.0",
    "gn:admin4_code":"80007.0",
    "gn:asciiname":"Isibu",
    "gn:country_code":"NP",
    "gn:dem":1398,
    "gn:feature_class":"P",
    "gn:feature_code":"PPLL",
    "gn:name":"Isibu",
    "gn:population":0,
    "gn:timezone":"Asia/Kathmandu",
    "iso:country":"NP",
    "wof:name":"Isibu",
    "wof:placetype":"locality"
},
  "geometry": {"coordinates":[87.59787,27.21282],"type":"Point"}
}