{
  "type": "Feature",
  "properties": {
    "gn:admin1_code":"00",
    "gn:asciiname":"Tamaspur",
    "gn:country_code":"NP",
    "gn:dem":146,
    "gn:feature_class":"P",
    "gn:feature_code":"PPL",
    "gn:name":"Tam\u0101spur",
    "gn:population":0,
    "gn:timezone":"Asia/Kathmandu",
    "iso:country":"NP",
    "name:nep_x_preferred":[
        "Tam\u0101spur"
    ],
    "wof:name":"Tamaspur",
    "wof:placetype":"locality"
},
  "geometry": {"coordinates":[83.94351999999998,27.56435],"type":"Point"}
}