{
  "type": "Feature",
  "properties": {
    "gn:admin1_code":"MR",
    "gn:admin2_code":"12",
    "gn:admin3_code":"53",
    "gn:admin4_code":"530010",
    "gn:asciiname":"Khimpu",
    "gn:country_code":"NP",
    "gn:dem":2017,
    "gn:feature_class":"P",
    "gn:feature_code":"PPLL",
    "gn:name":"Khimpu",
    "gn:population":0,
    "gn:timezone":"Asia/Kathmandu",
    "iso:country":"NP",
    "wof:name":"Khimpu",
    "wof:placetype":"locality"
},
  "geometry": {"coordinates":[82.88930000000001,28.3398],"type":"Point"}
}