{
  "type": "Feature",
  "properties": {
    "gn:admin1_code":"MR",
    "gn:admin2_code":"6",
    "gn:admin3_code":"64.0",
    "gn:admin4_code":"640004.0",
    "gn:asciiname":"Badachaur",
    "gn:country_code":"NP",
    "gn:dem":2253,
    "gn:feature_class":"P",
    "gn:feature_code":"PPLL",
    "gn:name":"Badachaur",
    "gn:population":0,
    "gn:timezone":"Asia/Kathmandu",
    "iso:country":"NP",
    "wof:name":"Badachaur",
    "wof:placetype":"locality"
},
  "geometry": {"coordinates":[81.68899999999999,29.1326],"type":"Point"}
}