{
  "type": "Feature",
  "properties": {
    "gn:admin1_code":"FR",
    "gn:admin2_code":"9",
    "gn:admin3_code":"74",
    "gn:admin4_code":"740049",
    "gn:asciiname":"Samaila",
    "gn:country_code":"NP",
    "gn:dem":1364,
    "gn:feature_class":"P",
    "gn:feature_code":"PPLL",
    "gn:name":"Samaila",
    "gn:population":0,
    "gn:timezone":"Asia/Kathmandu",
    "iso:country":"NP",
    "wof:name":"Samaila",
    "wof:placetype":"locality"
},
  "geometry": {"coordinates":[80.46239,29.45117],"type":"Point"}
}