{
  "type": "Feature",
  "properties": {
    "gn:admin1_code":"CR",
    "gn:admin2_code":"5",
    "gn:admin3_code":"20",
    "gn:admin4_code":"200041",
    "gn:asciiname":"Mathillo Ranibaas",
    "gn:country_code":"NP",
    "gn:dem":360,
    "gn:feature_class":"P",
    "gn:feature_code":"PPLL",
    "gn:name":"Mathillo Ranibaas",
    "gn:population":0,
    "gn:timezone":"Asia/Kathmandu",
    "iso:country":"NP",
    "wof:name":"Mathillo Ranibaas",
    "wof:placetype":"locality"
},
  "geometry": {"coordinates":[86.01584,27.08133],"type":"Point"}
}