{
  "type": "Feature",
  "properties": {
    "iso:country":"NP",
    "qs:gn_pop":0,
    "qs:name":"Singadurbar",
    "qs:name_adm0":"Nepal",
    "qs:name_adm1":"Madhyamanchal",
    "qs:photos":25,
    "qs:photos_1k":5,
    "qs:photos_9k":1,
    "qs:photos_9r":1,
    "qs:photos_all":25,
    "qs:photos_sr":1,
    "qs:placetype":"Town",
    "qs:pop_sr":"0",
    "qs:woe_adm0":23424911,
    "wof:name":"Singadurbar",
    "wof:placetype":"locality"
},
  "geometry": {"coordinates":[85.333085,27.706859],"type":"Point"}
}