{
  "type": "Feature",
  "properties": {
    "gn:admin1_code":"FR",
    "gn:admin2_code":"9",
    "gn:admin3_code":"72.0",
    "gn:admin4_code":"720007.0",
    "gn:asciiname":"Banjariya",
    "gn:country_code":"NP",
    "gn:dem":221,
    "gn:feature_class":"P",
    "gn:feature_code":"PPLL",
    "gn:name":"Banjariya",
    "gn:population":0,
    "gn:timezone":"Asia/Kathmandu",
    "iso:country":"NP",
    "name:fra_x_preferred":[
        "Banjariya"
    ],
    "name:new_x_preferred":[
        "\u092c\u0902\u091c\u0930\u093f\u092f\u093e"
    ],
    "name:pol_x_preferred":[
        "Banjariya"
    ],
    "wof:name":"Banjariya",
    "wof:placetype":"locality"
},
  "geometry": {"coordinates":[80.34798000000001,28.93326],"type":"Point"}
}