{
  "type": "Feature",
  "properties": {
    "gn:admin1_code":"CR",
    "gn:admin2_code":"11",
    "gn:admin3_code":"35.0",
    "gn:admin4_code":"350028.0",
    "gn:asciiname":"Khekadiya",
    "gn:country_code":"NP",
    "gn:dem":197,
    "gn:feature_class":"P",
    "gn:feature_code":"PPLL",
    "gn:name":"Khekadiya",
    "gn:population":0,
    "gn:timezone":"Asia/Kathmandu",
    "iso:country":"NP",
    "wof:name":"Khekadiya",
    "wof:placetype":"locality"
},
  "geometry": {"coordinates":[84.51899999999998,27.53792],"type":"Point"}
}