{
  "type": "Feature",
  "properties": {
    "gn:admin1_code":"WR",
    "gn:admin2_code":"8",
    "gn:admin3_code":"46.0",
    "gn:admin4_code":"460048.0",
    "gn:asciiname":"Rata Pokhara",
    "gn:country_code":"NP",
    "gn:dem":1108,
    "gn:feature_class":"P",
    "gn:feature_code":"PPLL",
    "gn:name":"Rata Pokhara",
    "gn:population":0,
    "gn:timezone":"Asia/Kathmandu",
    "iso:country":"NP",
    "wof:name":"Rata Pokhara",
    "wof:placetype":"locality"
},
  "geometry": {"coordinates":[83.15145,28.10178],"type":"Point"}
}