{
  "type": "Feature",
  "properties": {
    "gn:admin1_code":"00",
    "gn:asciiname":"Deupuje",
    "gn:country_code":"NP",
    "gn:dem":1259,
    "gn:feature_class":"P",
    "gn:feature_code":"PPL",
    "gn:name":"Deupuje",
    "gn:population":0,
    "gn:timezone":"Asia/Kathmandu",
    "iso:country":"NP",
    "wof:name":"Deupuje",
    "wof:placetype":"locality"
},
  "geometry": {"coordinates":[86.61709999999999,27.38952],"type":"Point"}
}