{
  "type": "Feature",
  "properties": {
    "gn:admin1_code":"CR",
    "gn:admin2_code":"1",
    "gn:admin3_code":"24.0",
    "gn:admin4_code":"240023.0",
    "gn:asciiname":"Suwaltol",
    "gn:country_code":"NP",
    "gn:dem":1515,
    "gn:feature_class":"P",
    "gn:feature_code":"PPLL",
    "gn:name":"Suwaltol",
    "gn:population":0,
    "gn:timezone":"Asia/Kathmandu",
    "iso:country":"NP",
    "wof:name":"Suwaltol",
    "wof:placetype":"locality"
},
  "geometry": {"coordinates":[85.54545999999998,27.6138],"type":"Point"}
}