{
  "type": "Feature",
  "properties": {
    "gn:admin1_code":"MR",
    "gn:admin2_code":"2.0",
    "gn:admin3_code":"58.0",
    "gn:admin4_code":"580025.0",
    "gn:asciiname":"Shanti Bajar",
    "gn:country_code":"NP",
    "gn:dem":166,
    "gn:feature_class":"P",
    "gn:feature_code":"PPLL",
    "gn:name":"Shanti Bajar",
    "gn:population":0,
    "gn:timezone":"Asia/Kathmandu",
    "iso:country":"NP",
    "wof:name":"Shanti Bajar",
    "wof:placetype":"locality"
},
  "geometry": {"coordinates":[81.1835,28.50844],"type":"Point"}
}