{
  "type": "Feature",
  "properties": {
    "gn:admin1_code":"MR",
    "gn:admin2_code":"12",
    "gn:admin3_code":"54",
    "gn:admin4_code":"540025",
    "gn:asciiname":"Rupcha",
    "gn:country_code":"NP",
    "gn:dem":1882,
    "gn:feature_class":"P",
    "gn:feature_code":"PPLL",
    "gn:name":"Rupcha",
    "gn:population":0,
    "gn:timezone":"Asia/Kathmandu",
    "iso:country":"NP",
    "name:bul_x_preferred":[
        "\u0420\u0443\u043f\u0447\u0430"
    ],
    "name:ceb_x_preferred":[
        "Rupcha"
    ],
    "name:fas_x_preferred":[
        "\u0631\u0648\u067e\u0686\u0627"
    ],
    "name:kaz_x_preferred":[
        "\u0420\u0443\u043f\u0447\u0430"
    ],
    "name:ron_x_preferred":[
        "Rupcea"
    ],
    "name:rus_x_preferred":[
        "\u0420\u0443\u043f\u0447\u0430"
    ],
    "name:swe_x_preferred":[
        "Ruptja"
    ],
    "name:tur_x_preferred":[
        "Rup\u00e7a"
    ],
    "name:ukr_x_preferred":[
        "\u0420\u0443\u043f\u0447\u0430"
    ],
    "wof:name":"Rupcha",
    "wof:placetype":"locality"
},
  "geometry": {"coordinates":[82.67976,28.56333],"type":"Point"}
}