{
  "type": "Feature",
  "properties": {
    "gn:admin1_code":"MR",
    "gn:admin2_code":"12",
    "gn:admin3_code":"54",
    "gn:admin4_code":"540025",
    "gn:asciiname":"Rupcha",
    "gn:country_code":"NP",
    "gn:dem":1882,
    "gn:feature_class":"P",
    "gn:feature_code":"PPLL",
    "gn:name":"Rupcha",
    "gn:population":0,
    "gn:timezone":"Asia/Kathmandu",
    "iso:country":"NP",
    "wof:name":"Rupcha",
    "wof:placetype":"locality"
},
  "geometry": {"coordinates":[82.67976,28.56333],"type":"Point"}
}