{
  "type": "Feature",
  "properties": {
    "gn:admin1_code":"WR",
    "gn:admin2_code":"8",
    "gn:admin3_code":"46.0",
    "gn:admin4_code":"460049.0",
    "gn:asciiname":"Lamsarang",
    "gn:country_code":"NP",
    "gn:dem":1510,
    "gn:feature_class":"P",
    "gn:feature_code":"PPLL",
    "gn:name":"Lamsarang",
    "gn:population":0,
    "gn:timezone":"Asia/Kathmandu",
    "iso:country":"NP",
    "wof:name":"Lamsarang",
    "wof:placetype":"locality"
},
  "geometry": {"coordinates":[83.53489,28.03275],"type":"Point"}
}