{
  "type": "Feature",
  "properties": {
    "gn:admin1_code":"MR",
    "gn:admin2_code":"12",
    "gn:admin3_code":"56.0",
    "gn:admin4_code":"560033.0",
    "gn:asciiname":"Thanti",
    "gn:country_code":"NP",
    "gn:dem":785,
    "gn:feature_class":"P",
    "gn:feature_code":"PPLL",
    "gn:name":"Thanti",
    "gn:population":0,
    "gn:timezone":"Asia/Kathmandu",
    "iso:country":"NP",
    "name:bih_x_preferred":[
        "\u0920\u093e\u0902\u091f\u0940"
    ],
    "name:ceb_x_preferred":[
        "Thanti"
    ],
    "name:fra_x_preferred":[
        "Thanti"
    ],
    "name:mai_x_preferred":[
        "\u0920\u093e\u0902\u091f\u0940"
    ],
    "name:msa_x_preferred":[
        "Thanti"
    ],
    "name:nep_x_preferred":[
        "\u0920\u093e\u0902\u091f\u0940"
    ],
    "name:new_x_preferred":[
        "\u0920\u093e\u0901\u091f\u0940"
    ],
    "name:pol_x_preferred":[
        "Thanti"
    ],
    "wof:name":"Thanti",
    "wof:placetype":"locality"
},
  "geometry": {"coordinates":[82.21299999999999,28.18701],"type":"Point"}
}