{
  "type": "Feature",
  "properties": {
    "gn:admin1_code":"ER",
    "gn:admin2_code":"10",
    "gn:admin3_code":"3.0",
    "gn:admin4_code":"30005.0",
    "gn:asciiname":"Malbanse",
    "gn:country_code":"NP",
    "gn:dem":781,
    "gn:feature_class":"P",
    "gn:feature_code":"PPLL",
    "gn:name":"Malbanse",
    "gn:population":0,
    "gn:timezone":"Asia/Kathmandu",
    "iso:country":"NP",
    "wof:name":"Malbanse",
    "wof:placetype":"locality"
},
  "geometry": {"coordinates":[87.92013,26.84121],"type":"Point"}
}