{
  "type": "Feature",
  "properties": {
    "gn:admin1_code":"WR",
    "gn:admin2_code":"3",
    "gn:admin3_code":"43",
    "gn:admin4_code":"430034",
    "gn:asciiname":"Thabang",
    "gn:country_code":"NP",
    "gn:dem":2277,
    "gn:feature_class":"P",
    "gn:feature_code":"PPLL",
    "gn:name":"Thabang",
    "gn:population":0,
    "gn:timezone":"Asia/Kathmandu",
    "iso:country":"NP",
    "wof:name":"Thabang",
    "wof:placetype":"locality"
},
  "geometry": {"coordinates":[83.65231,28.3728],"type":"Point"}
}