{
  "type": "Feature",
  "properties": {
    "gn:admin1_code":"WR",
    "gn:admin2_code":"3",
    "gn:admin3_code":"45.0",
    "gn:admin4_code":"450006.0",
    "gn:asciiname":"Dadra",
    "gn:country_code":"NP",
    "gn:dem":1571,
    "gn:feature_class":"P",
    "gn:feature_code":"PPLL",
    "gn:name":"Dadra",
    "gn:population":0,
    "gn:timezone":"Asia/Kathmandu",
    "iso:country":"NP",
    "name:deu_x_preferred":[
        "Dadra"
    ],
    "name:hin_x_preferred":[
        "\u0926\u093e\u0926\u0930\u093e"
    ],
    "name:mar_x_preferred":[
        "\u0926\u093e\u0926\u0930\u093e"
    ],
    "name:new_x_preferred":[
        "\u0926\u093e\u0926\u0930\u093e \u0924\u093e\u0932"
    ],
    "name:urd_x_preferred":[
        "\u062f\u0627\u062f\u0631\u0627"
    ],
    "wof:name":"Dadra",
    "wof:placetype":"locality"
},
  "geometry": {"coordinates":[83.45883000000001,28.15537],"type":"Point"}
}