{
  "type": "Feature",
  "properties": {
    "gn:admin1_code":"MR",
    "gn:admin2_code":"2.0",
    "gn:admin3_code":"59.0",
    "gn:admin4_code":"590033.0",
    "gn:asciiname":"Thati",
    "gn:country_code":"NP",
    "gn:dem":1172,
    "gn:feature_class":"P",
    "gn:feature_code":"PPLL",
    "gn:name":"Thati",
    "gn:population":0,
    "gn:timezone":"Asia/Kathmandu",
    "iso:country":"NP",
    "wof:name":"Thati",
    "wof:placetype":"locality"
},
  "geometry": {"coordinates":[81.82289,28.51095],"type":"Point"}
}