{
  "type": "Feature",
  "properties": {
    "gn:admin1_code":"MR",
    "gn:admin2_code":"12",
    "gn:admin3_code":"53",
    "gn:admin4_code":"530047",
    "gn:asciiname":"Bajdaiya",
    "gn:country_code":"NP",
    "gn:dem":2655,
    "gn:feature_class":"P",
    "gn:feature_code":"PPLL",
    "gn:name":"Bajdaiya",
    "gn:population":0,
    "gn:timezone":"Asia/Kathmandu",
    "iso:country":"NP",
    "wof:name":"Bajdaiya",
    "wof:placetype":"locality"
},
  "geometry": {"coordinates":[82.73350000000001,28.50112],"type":"Point"}
}