{
  "type": "Feature",
  "properties": {
    "gn:admin1_code":"CR",
    "gn:admin2_code":"1",
    "gn:admin3_code":"23",
    "gn:admin4_code":"230065",
    "gn:asciiname":"Budhathokigaun",
    "gn:country_code":"NP",
    "gn:dem":1306,
    "gn:feature_class":"P",
    "gn:feature_code":"PPLL",
    "gn:name":"Budhathokigaun",
    "gn:population":0,
    "gn:timezone":"Asia/Kathmandu",
    "iso:country":"NP",
    "wof:name":"Budhathokigaun",
    "wof:placetype":"locality"
},
  "geometry": {"coordinates":[85.80419000000001,27.71105],"type":"Point"}
}