{
  "type": "Feature",
  "properties": {
    "gn:admin1_code":"FR",
    "gn:admin2_code":"9",
    "gn:admin3_code":"73.0",
    "gn:admin4_code":"730013.0",
    "gn:asciiname":"Lamigada",
    "gn:country_code":"NP",
    "gn:dem":375,
    "gn:feature_class":"P",
    "gn:feature_code":"PPLL",
    "gn:name":"Lamigada",
    "gn:population":0,
    "gn:timezone":"Asia/Kathmandu",
    "iso:country":"NP",
    "wof:name":"Lamigada",
    "wof:placetype":"locality"
},
  "geometry": {"coordinates":[80.27008000000002,29.09738],"type":"Point"}
}