{
  "type": "Feature",
  "properties": {
    "gn:admin1_code":"ER",
    "gn:admin2_code":"7",
    "gn:admin3_code":"9",
    "gn:admin4_code":"90030",
    "gn:asciiname":"Tapase",
    "gn:country_code":"NP",
    "gn:dem":1128,
    "gn:feature_class":"P",
    "gn:feature_code":"PPLL",
    "gn:name":"Tapase",
    "gn:population":0,
    "gn:timezone":"Asia/Kathmandu",
    "iso:country":"NP",
    "wof:name":"Tapase",
    "wof:placetype":"locality"
},
  "geometry": {"coordinates":[87.1549,27.41655],"type":"Point"}
}