{
  "type": "Feature",
  "properties": {
    "gn:admin1_code":"MR",
    "gn:admin2_code":"12",
    "gn:admin3_code":"52",
    "gn:admin4_code":"520031",
    "gn:asciiname":"Kharibot",
    "gn:country_code":"NP",
    "gn:dem":879,
    "gn:feature_class":"P",
    "gn:feature_code":"PPLL",
    "gn:name":"Kharibot",
    "gn:population":0,
    "gn:timezone":"Asia/Kathmandu",
    "iso:country":"NP",
    "name:ceb_x_preferred":[
        "Kharibot"
    ],
    "name:mai_x_preferred":[
        "\u0916\u0930\u093f\u092c\u094b\u091f"
    ],
    "name:msa_x_preferred":[
        "Kharibot"
    ],
    "name:nep_x_preferred":[
        "\u0916\u0930\u093f\u092c\u094b\u091f"
    ],
    "name:new_x_preferred":[
        "\u0916\u0930\u0940\u092c\u094b\u091f"
    ],
    "name:pol_x_preferred":[
        "Kharibot"
    ],
    "wof:name":"Kharibot",
    "wof:placetype":"locality"
},
  "geometry": {"coordinates":[82.90316,28.1248],"type":"Point"}
}