{
  "type": "Feature",
  "properties": {
    "gn:admin1_code":"FR",
    "gn:admin2_code":"14",
    "gn:admin3_code":"71.0",
    "gn:admin4_code":"710015.0",
    "gn:asciiname":"Sitapur",
    "gn:country_code":"NP",
    "gn:dem":245,
    "gn:feature_class":"P",
    "gn:feature_code":"PPLL",
    "gn:name":"Sitapur",
    "gn:population":0,
    "gn:timezone":"Asia/Kathmandu",
    "iso:country":"NP",
    "wof:name":"Sitapur",
    "wof:placetype":"locality"
},
  "geometry": {"coordinates":[80.50913,28.88987],"type":"Point"}
}