{
  "type": "Feature",
  "properties": {
    "gn:admin1_code":"WR",
    "gn:admin2_code":"8",
    "gn:admin3_code":"46.0",
    "gn:admin4_code":"460036.0",
    "gn:asciiname":"Harewagaun",
    "gn:country_code":"NP",
    "gn:dem":1399,
    "gn:feature_class":"P",
    "gn:feature_code":"PPLL",
    "gn:name":"Harewagaun",
    "gn:population":0,
    "gn:timezone":"Asia/Kathmandu",
    "iso:country":"NP",
    "wof:name":"Harewagaun",
    "wof:placetype":"locality"
},
  "geometry": {"coordinates":[83.45836,28.10231],"type":"Point"}
}