{
  "type": "Feature",
  "properties": {
    "gn:admin1_code":"ER",
    "gn:admin2_code":"13",
    "gn:admin3_code":"13.0",
    "gn:admin4_code":"130024.0",
    "gn:asciiname":"Mude",
    "gn:country_code":"NP",
    "gn:dem":1959,
    "gn:feature_class":"P",
    "gn:feature_code":"PPLL",
    "gn:name":"Mude",
    "gn:population":0,
    "gn:timezone":"Asia/Kathmandu",
    "iso:country":"NP",
    "wof:name":"Mude",
    "wof:placetype":"locality"
},
  "geometry": {"coordinates":[86.78206,27.23596],"type":"Point"}
}