{
  "type": "Feature",
  "properties": {
    "gn:admin1_code":"WR",
    "gn:admin2_code":"8",
    "gn:admin3_code":"48",
    "gn:admin4_code":"480057",
    "gn:asciiname":"Santapur",
    "gn:country_code":"NP",
    "gn:dem":119,
    "gn:feature_class":"P",
    "gn:feature_code":"PPLL",
    "gn:name":"Santapur",
    "gn:population":0,
    "gn:timezone":"Asia/Kathmandu",
    "iso:country":"NP",
    "name:msa_x_preferred":[
        "Santapur"
    ],
    "name:nep_x_preferred":[
        "\u0938\u0928\u094d\u0924\u092a\u0942\u0930 \u0926\u094b\u0938\u094d\u0924\u0940\u092f\u093e"
    ],
    "name:pol_x_preferred":[
        "Santapur"
    ],
    "wof:name":"Santapur",
    "wof:placetype":"locality"
},
  "geometry": {"coordinates":[83.67765,27.56713],"type":"Point"}
}