{
  "type": "Feature",
  "properties": {
    "gn:admin1_code":"CR",
    "gn:admin2_code":"5",
    "gn:admin3_code":"18",
    "gn:admin4_code":"180041",
    "gn:asciiname":"Purano Kanti Bajar",
    "gn:country_code":"NP",
    "gn:dem":146,
    "gn:feature_class":"P",
    "gn:feature_code":"PPLL",
    "gn:name":"Purano Kanti Bajar",
    "gn:population":0,
    "gn:timezone":"Asia/Kathmandu",
    "iso:country":"NP",
    "wof:name":"Purano Kanti Bajar",
    "wof:placetype":"locality"
},
  "geometry": {"coordinates":[85.73676999999998,26.96715],"type":"Point"}
}