{
  "type": "Feature",
  "properties": {
    "gn:admin1_code":"FR",
    "gn:admin2_code":"9",
    "gn:admin3_code":"73.0",
    "gn:admin4_code":"730007.0",
    "gn:asciiname":"Loda",
    "gn:country_code":"NP",
    "gn:dem":2015,
    "gn:feature_class":"P",
    "gn:feature_code":"PPLL",
    "gn:name":"Loda",
    "gn:population":0,
    "gn:timezone":"Asia/Kathmandu",
    "iso:country":"NP",
    "name:ceb_x_preferred":[
        "Loda"
    ],
    "name:deu_x_preferred":[
        "Loda"
    ],
    "name:fra_x_preferred":[
        "Loda"
    ],
    "name:ita_x_preferred":[
        "Loda"
    ],
    "name:nld_x_preferred":[
        "Loda"
    ],
    "name:pol_x_preferred":[
        "Loda"
    ],
    "name:srp_x_preferred":[
        "Loda"
    ],
    "name:swe_x_preferred":[
        "Loda"
    ],
    "wof:name":"Loda",
    "wof:placetype":"locality"
},
  "geometry": {"coordinates":[80.53442,29.38114],"type":"Point"}
}