{
  "type": "Feature",
  "properties": {
    "gn:admin1_code":"FR",
    "gn:admin2_code":"14",
    "gn:admin3_code":"71.0",
    "gn:admin4_code":"710020.0",
    "gn:asciiname":"Dari",
    "gn:country_code":"NP",
    "gn:dem":935,
    "gn:feature_class":"P",
    "gn:feature_code":"PPLL",
    "gn:name":"Dari",
    "gn:population":0,
    "gn:timezone":"Asia/Kathmandu",
    "iso:country":"NP",
    "wof:name":"Dari",
    "wof:placetype":"locality"
},
  "geometry": {"coordinates":[80.79982,28.9413],"type":"Point"}
}