{
  "type": "Feature",
  "properties": {
    "gn:admin1_code":"FR",
    "gn:admin2_code":"9",
    "gn:admin3_code":"72.0",
    "gn:admin4_code":"720009.0",
    "gn:asciiname":"Mauriphata",
    "gn:country_code":"NP",
    "gn:dem":197,
    "gn:feature_class":"P",
    "gn:feature_code":"PPLL",
    "gn:name":"Mauriphata",
    "gn:population":0,
    "gn:timezone":"Asia/Kathmandu",
    "iso:country":"NP",
    "wof:name":"Mauriphata",
    "wof:placetype":"locality"
},
  "geometry": {"coordinates":[80.51100000000002,28.81295],"type":"Point"}
}