{
  "type": "Feature",
  "properties": {
    "gn:admin1_code":"MR",
    "gn:admin2_code":"2",
    "gn:admin3_code":"61.0",
    "gn:admin4_code":"610008.0",
    "gn:asciiname":"Santada",
    "gn:country_code":"NP",
    "gn:dem":1304,
    "gn:feature_class":"P",
    "gn:feature_code":"PPLL",
    "gn:name":"Santada",
    "gn:population":0,
    "gn:timezone":"Asia/Kathmandu",
    "iso:country":"NP",
    "name:bih_x_preferred":[
        "\u0938\u0928\u094d\u0924\u0921\u093e"
    ],
    "name:ceb_x_preferred":[
        "Santada"
    ],
    "name:fra_x_preferred":[
        "Santada"
    ],
    "name:mai_x_preferred":[
        "\u0938\u0928\u094d\u0924\u0921\u093e"
    ],
    "name:msa_x_preferred":[
        "Santada"
    ],
    "name:nep_x_preferred":[
        "\u0938\u0928\u094d\u0924\u0921\u093e"
    ],
    "name:new_x_preferred":[
        "\u0938\u093e\u0928\u094d\u0924\u0926\u093e"
    ],
    "name:pol_x_preferred":[
        "Santada"
    ],
    "wof:name":"Santada",
    "wof:placetype":"locality"
},
  "geometry": {"coordinates":[81.99749,28.79539],"type":"Point"}
}