{
  "type": "Feature",
  "properties": {
    "gn:admin1_code":"WR",
    "gn:admin2_code":"8",
    "gn:admin3_code":"46.0",
    "gn:admin4_code":"460005.0",
    "gn:asciiname":"Raksegaun",
    "gn:country_code":"NP",
    "gn:dem":681,
    "gn:feature_class":"P",
    "gn:feature_code":"PPLL",
    "gn:name":"Raksegaun",
    "gn:population":0,
    "gn:timezone":"Asia/Kathmandu",
    "iso:country":"NP",
    "wof:name":"Raksegaun",
    "wof:placetype":"locality"
},
  "geometry": {"coordinates":[83.57869000000002,28.03041],"type":"Point"}
}