{
  "type": "Feature",
  "properties": {
    "gn:admin1_code":"WR",
    "gn:admin2_code":"8",
    "gn:admin3_code":"46.0",
    "gn:admin4_code":"460029.0",
    "gn:asciiname":"Chhanchhum Phant",
    "gn:country_code":"NP",
    "gn:dem":1182,
    "gn:feature_class":"P",
    "gn:feature_code":"PPLL",
    "gn:name":"Chhanchhum Phant",
    "gn:population":0,
    "gn:timezone":"Asia/Kathmandu",
    "iso:country":"NP",
    "wof:name":"Chhanchhum Phant",
    "wof:placetype":"locality"
},
  "geometry": {"coordinates":[83.14333000000001,28.10205],"type":"Point"}
}