{
  "type": "Feature",
  "properties": {
    "gn:admin1_code":"MR",
    "gn:admin2_code":"12",
    "gn:admin3_code":"55",
    "gn:admin4_code":"550030",
    "gn:asciiname":"Mayani",
    "gn:country_code":"NP",
    "gn:dem":1389,
    "gn:feature_class":"P",
    "gn:feature_code":"PPLL",
    "gn:name":"Mayani",
    "gn:population":0,
    "gn:timezone":"Asia/Kathmandu",
    "iso:country":"NP",
    "wof:name":"Mayani",
    "wof:placetype":"locality"
},
  "geometry": {"coordinates":[82.29002,28.39897],"type":"Point"}
}