{
  "type": "Feature",
  "properties": {
    "gn:admin1_code":"WR",
    "gn:admin2_code":"8",
    "gn:admin3_code":"46.0",
    "gn:admin4_code":"460010.0",
    "gn:asciiname":"Golbighat",
    "gn:country_code":"NP",
    "gn:dem":613,
    "gn:feature_class":"P",
    "gn:feature_code":"PPLL",
    "gn:name":"Golbighat",
    "gn:population":0,
    "gn:timezone":"Asia/Kathmandu",
    "iso:country":"NP",
    "wof:name":"Golbighat",
    "wof:placetype":"locality"
},
  "geometry": {"coordinates":[83.50700999999999,27.97563],"type":"Point"}
}