{
  "type": "Feature",
  "properties": {
    "gn:admin1_code":"ER",
    "gn:admin2_code":"10",
    "gn:admin3_code":"4.0",
    "gn:admin4_code":"40029.0",
    "gn:asciiname":"Kyampa",
    "gn:country_code":"NP",
    "gn:dem":134,
    "gn:feature_class":"P",
    "gn:feature_code":"PPLL",
    "gn:name":"Kyampa",
    "gn:population":0,
    "gn:timezone":"Asia/Kathmandu",
    "iso:country":"NP",
    "wof:name":"Kyampa",
    "wof:placetype":"locality"
},
  "geometry": {"coordinates":[87.94606999999998,26.68193],"type":"Point"}
}