{
  "type": "Feature",
  "properties": {
    "gn:admin1_code":"WR",
    "gn:admin2_code":"3",
    "gn:admin3_code":"43",
    "gn:admin4_code":"430024",
    "gn:asciiname":"Churen Himal",
    "gn:country_code":"NP",
    "gn:dem":7185,
    "gn:feature_class":"P",
    "gn:feature_code":"PPLL",
    "gn:name":"Churen Himal",
    "gn:population":0,
    "gn:timezone":"Asia/Kathmandu",
    "iso:country":"NP",
    "wof:name":"Churen Himal",
    "wof:placetype":"locality"
},
  "geometry": {"coordinates":[83.21684999999999,28.73236],"type":"Point"}
}