{
  "type": "Feature",
  "properties": {
    "gn:admin1_code":"MR",
    "gn:admin2_code":"2.0",
    "gn:admin3_code":"59.0",
    "gn:admin4_code":"590035.0",
    "gn:asciiname":"Gurgaun",
    "gn:country_code":"NP",
    "gn:dem":1711,
    "gn:feature_class":"P",
    "gn:feature_code":"PPLL",
    "gn:name":"Gurgaun",
    "gn:population":0,
    "gn:timezone":"Asia/Kathmandu",
    "iso:country":"NP",
    "wof:name":"Gurgaun",
    "wof:placetype":"locality"
},
  "geometry": {"coordinates":[81.94447,28.38072],"type":"Point"}
}