{
  "type": "Feature",
  "properties": {
    "gn:admin1_code":"FR",
    "gn:admin2_code":"14",
    "gn:admin3_code":"68",
    "gn:admin4_code":"680039",
    "gn:asciiname":"Palti",
    "gn:country_code":"NP",
    "gn:dem":1345,
    "gn:feature_class":"P",
    "gn:feature_code":"PPLL",
    "gn:name":"Palti",
    "gn:population":0,
    "gn:timezone":"Asia/Kathmandu",
    "iso:country":"NP",
    "wof:name":"Palti",
    "wof:placetype":"locality"
},
  "geometry": {"coordinates":[80.95962,29.48835],"type":"Point"}
}