{
  "type": "Feature",
  "properties": {
    "gn:admin1_code":"00",
    "gn:asciiname":"Boske",
    "gn:country_code":"NP",
    "gn:dem":215,
    "gn:feature_class":"P",
    "gn:feature_code":"PPL",
    "gn:name":"Boske",
    "gn:population":0,
    "gn:timezone":"Asia/Kathmandu",
    "iso:country":"NP",
    "name:nep_x_preferred":[
        "Boske"
    ],
    "wof:name":"Boske",
    "wof:placetype":"locality"
},
  "geometry": {"coordinates":[86.69866999999998,26.81424],"type":"Point"}
}