{
  "type": "Feature",
  "properties": {
    "gn:admin1_code":"CR",
    "gn:admin2_code":"1",
    "gn:admin3_code":"29",
    "gn:admin4_code":"290008",
    "gn:asciiname":"Tiru",
    "gn:country_code":"NP",
    "gn:dem":2156,
    "gn:feature_class":"P",
    "gn:feature_code":"PPLL",
    "gn:name":"Tiru",
    "gn:population":0,
    "gn:timezone":"Asia/Kathmandu",
    "iso:country":"NP",
    "wof:name":"Tiru",
    "wof:placetype":"locality"
},
  "geometry": {"coordinates":[85.21025999999998,28.09738],"type":"Point"}
}