{
  "type": "Feature",
  "properties": {
    "gn:admin1_code":"MR",
    "gn:admin2_code":"12",
    "gn:admin3_code":"55",
    "gn:admin4_code":"550047",
    "gn:asciiname":"Tribenighat",
    "gn:country_code":"NP",
    "gn:dem":893,
    "gn:feature_class":"P",
    "gn:feature_code":"PPLL",
    "gn:name":"Tribenighat",
    "gn:population":0,
    "gn:timezone":"Asia/Kathmandu",
    "iso:country":"NP",
    "wof:name":"Tribenighat",
    "wof:placetype":"locality"
},
  "geometry": {"coordinates":[82.25990999999998,28.29335],"type":"Point"}
}