{
  "type": "Feature",
  "properties": {
    "gn:admin1_code":"00",
    "gn:asciiname":"Manebun",
    "gn:country_code":"NP",
    "gn:dem":562,
    "gn:feature_class":"P",
    "gn:feature_code":"PPL",
    "gn:name":"M\u0101nebu\u1e45",
    "gn:population":0,
    "gn:timezone":"Asia/Kathmandu",
    "iso:country":"NP",
    "name:nep_x_preferred":[
        "M\u0101nebu\u1e45"
    ],
    "wof:name":"Manebun",
    "wof:placetype":"locality"
},
  "geometry": {"coordinates":[88.03468000000002,26.80655],"type":"Point"}
}