{
  "type": "Feature",
  "properties": {
    "gn:admin1_code":"ER",
    "gn:admin2_code":"10",
    "gn:admin3_code":"2",
    "gn:admin4_code":"20005",
    "gn:asciiname":"Gairigaun",
    "gn:country_code":"NP",
    "gn:dem":1428,
    "gn:feature_class":"P",
    "gn:feature_code":"PPLL",
    "gn:name":"Gairigaun",
    "gn:population":0,
    "gn:timezone":"Asia/Kathmandu",
    "iso:country":"NP",
    "wof:name":"Gairigaun",
    "wof:placetype":"locality"
},
  "geometry": {"coordinates":[87.78264,27.18196],"type":"Point"}
}