{
  "type": "Feature",
  "properties": {
    "iso:country":"NP",
    "qs:gn_country":"NP",
    "qs:gn_fcode":"PPL",
    "qs:gn_pop":0,
    "qs:name":"Nep\u00e5lganj",
    "qs:name_adm0":"Nepal",
    "qs:name_adm1":"Madhya Pashchimanchal",
    "qs:photos":83,
    "qs:photos_1k":17,
    "qs:photos_9k":1,
    "qs:photos_9r":3,
    "qs:photos_all":83,
    "qs:photos_sr":3,
    "qs:placetype":"Town",
    "qs:pop_sr":"12",
    "qs:woe_adm0":23424911,
    "wof:name":"Nep\u00e5lganj",
    "wof:placetype":"locality"
},
  "geometry": {"coordinates":[81.62436,28.05769],"type":"Point"}
}