{
  "type": "Feature",
  "properties": {
    "gn:admin1_code":"WR",
    "gn:admin2_code":"3",
    "gn:admin3_code":"45",
    "gn:admin4_code":"450057",
    "gn:asciiname":"Khal",
    "gn:country_code":"NP",
    "gn:dem":2358,
    "gn:feature_class":"P",
    "gn:feature_code":"PPLL",
    "gn:name":"Khal",
    "gn:population":0,
    "gn:timezone":"Asia/Kathmandu",
    "iso:country":"NP",
    "wof:name":"Khal",
    "wof:placetype":"locality"
},
  "geometry": {"coordinates":[83.05391999999998,28.35657],"type":"Point"}
}