{
  "type": "Feature",
  "properties": {
    "gn:admin1_code":"ER",
    "gn:admin2_code":"13.0",
    "gn:admin3_code":"14.0",
    "gn:admin4_code":"140045.0",
    "gn:asciiname":"Gal Bhanjyang",
    "gn:country_code":"NP",
    "gn:dem":1430,
    "gn:feature_class":"P",
    "gn:feature_code":"PPLL",
    "gn:name":"Gal Bhanjyang",
    "gn:population":0,
    "gn:timezone":"Asia/Kathmandu",
    "iso:country":"NP",
    "wof:name":"Gal Bhanjyang",
    "wof:placetype":"locality"
},
  "geometry": {"coordinates":[86.33757,27.11565],"type":"Point"}
}