{
  "type": "Feature",
  "properties": {
    "gn:admin1_code":"WR",
    "gn:admin2_code":"4",
    "gn:admin3_code":"37",
    "gn:admin4_code":"370002",
    "gn:asciiname":"Naiche",
    "gn:country_code":"NP",
    "gn:dem":1772,
    "gn:feature_class":"P",
    "gn:feature_code":"PPLL",
    "gn:name":"Naiche",
    "gn:population":0,
    "gn:timezone":"Asia/Kathmandu",
    "iso:country":"NP",
    "wof:name":"Naiche",
    "wof:placetype":"locality"
},
  "geometry": {"coordinates":[84.44395,28.34314],"type":"Point"}
}