{
  "type": "Feature",
  "properties": {
    "gn:admin1_code":"WR",
    "gn:admin2_code":"3",
    "gn:admin3_code":"44",
    "gn:admin4_code":"440028",
    "gn:asciiname":"Majhkharka",
    "gn:country_code":"NP",
    "gn:dem":850,
    "gn:feature_class":"P",
    "gn:feature_code":"PPLL",
    "gn:name":"Majhkharka",
    "gn:population":0,
    "gn:timezone":"Asia/Kathmandu",
    "iso:country":"NP",
    "wof:name":"Majhkharka",
    "wof:placetype":"locality"
},
  "geometry": {"coordinates":[83.68205999999998,28.20883],"type":"Point"}
}