{
  "type": "Feature",
  "properties": {
    "gn:admin1_code":"WR",
    "gn:admin2_code":"8",
    "gn:admin3_code":"49",
    "gn:admin4_code":"490059",
    "gn:asciiname":"Jhimjhimiya",
    "gn:country_code":"NP",
    "gn:dem":165,
    "gn:feature_class":"P",
    "gn:feature_code":"PPLL",
    "gn:name":"Jhimjhimiya",
    "gn:population":0,
    "gn:timezone":"Asia/Kathmandu",
    "iso:country":"NP",
    "wof:name":"Jhimjhimiya",
    "wof:placetype":"locality"
},
  "geometry": {"coordinates":[83.25564,27.71773],"type":"Point"}
}