{
  "type": "Feature",
  "properties": {
    "gn:admin1_code":"CR",
    "gn:admin2_code":"5",
    "gn:admin3_code":"20",
    "gn:admin4_code":"200020",
    "gn:asciiname":"Jarayotar",
    "gn:country_code":"NP",
    "gn:dem":472,
    "gn:feature_class":"P",
    "gn:feature_code":"PPLL",
    "gn:name":"Jarayotar",
    "gn:population":0,
    "gn:timezone":"Asia/Kathmandu",
    "iso:country":"NP",
    "name:bih_x_preferred":[
        "\u091c\u0930\u093e\u092f\u094b\u091f\u093e\u0930"
    ],
    "name:ceb_x_preferred":[
        "Jarayotar"
    ],
    "name:fra_x_preferred":[
        "Jarayotar"
    ],
    "name:mai_x_preferred":[
        "\u091c\u0930\u093e\u092f\u094b\u091f\u093e\u0930"
    ],
    "name:msa_x_preferred":[
        "Jarayotar"
    ],
    "name:nep_x_preferred":[
        "\u091c\u0930\u093e\u092f\u094b\u091f\u093e\u0930"
    ],
    "name:pol_x_preferred":[
        "Jarayotar"
    ],
    "name:urd_x_preferred":[
        "\u062c\u0631\u06d2\u0648\u062a\u0631"
    ],
    "wof:name":"Jarayotar",
    "wof:placetype":"locality"
},
  "geometry": {"coordinates":[86.11951999999999,27.11609],"type":"Point"}
}