{
  "type": "Feature",
  "properties": {
    "gn:admin1_code":"00",
    "gn:asciiname":"Khawatan",
    "gn:country_code":"NP",
    "gn:dem":256,
    "gn:feature_class":"P",
    "gn:feature_code":"PPL",
    "gn:name":"Kh\u0101w\u0101\u1e6d\u0101\u1e45",
    "gn:population":0,
    "gn:timezone":"Asia/Kathmandu",
    "iso:country":"NP",
    "name:nep_x_preferred":[
        "Kh\u0101w\u0101\u1e6d\u0101\u1e45"
    ],
    "wof:name":"Khawatan",
    "wof:placetype":"locality"
},
  "geometry": {"coordinates":[87.08891,26.91597],"type":"Point"}
}