{
  "type": "Feature",
  "properties": {
    "gn:admin1_code":"ER",
    "gn:admin2_code":"13",
    "gn:admin3_code":"13.0",
    "gn:admin4_code":"130011.0",
    "gn:asciiname":"Salleni",
    "gn:country_code":"NP",
    "gn:dem":955,
    "gn:feature_class":"P",
    "gn:feature_code":"PPLL",
    "gn:name":"Salleni",
    "gn:population":0,
    "gn:timezone":"Asia/Kathmandu",
    "iso:country":"NP",
    "wof:name":"Salleni",
    "wof:placetype":"locality"
},
  "geometry": {"coordinates":[86.74405,27.05839000000001],"type":"Point"}
}