{
  "type": "Feature",
  "properties": {
    "gn:admin1_code":"FR",
    "gn:admin2_code":"14",
    "gn:admin3_code":"69.0",
    "gn:admin4_code":"690016.0",
    "gn:asciiname":"Kudi",
    "gn:country_code":"NP",
    "gn:dem":903,
    "gn:feature_class":"P",
    "gn:feature_code":"PPLL",
    "gn:name":"Kudi",
    "gn:population":0,
    "gn:timezone":"Asia/Kathmandu",
    "iso:country":"NP",
    "wof:name":"Kudi",
    "wof:placetype":"locality"
},
  "geometry": {"coordinates":[81.38248,29.04717],"type":"Point"}
}