{
  "type": "Feature",
  "properties": {
    "gn:admin1_code":"WR",
    "gn:admin2_code":"4",
    "gn:admin3_code":"37",
    "gn:admin4_code":"370033",
    "gn:asciiname":"Ram Bajar",
    "gn:country_code":"NP",
    "gn:dem":511,
    "gn:feature_class":"P",
    "gn:feature_code":"PPLL",
    "gn:name":"Ram Bajar",
    "gn:population":0,
    "gn:timezone":"Asia/Kathmandu",
    "iso:country":"NP",
    "wof:name":"Ram Bajar",
    "wof:placetype":"locality"
},
  "geometry": {"coordinates":[84.22440999999998,28.1611],"type":"Point"}
}