{
  "type": "Feature",
  "properties": {
    "gn:admin1_code":"CR",
    "gn:admin2_code":"1",
    "gn:admin3_code":"25",
    "gn:admin4_code":"250025.0",
    "gn:asciiname":"Simtardanda",
    "gn:country_code":"NP",
    "gn:dem":1449,
    "gn:feature_class":"P",
    "gn:feature_code":"PPLL",
    "gn:name":"Simtardanda",
    "gn:population":0,
    "gn:timezone":"Asia/Kathmandu",
    "iso:country":"NP",
    "wof:name":"Simtardanda",
    "wof:placetype":"locality"
},
  "geometry": {"coordinates":[85.43799,27.48138],"type":"Point"}
}