{
  "type": "Feature",
  "properties": {
    "gn:admin1_code":"MR",
    "gn:admin2_code":"12",
    "gn:admin3_code":"56.0",
    "gn:admin4_code":"560041.0",
    "gn:asciiname":"Urhari",
    "gn:country_code":"NP",
    "gn:dem":566,
    "gn:feature_class":"P",
    "gn:feature_code":"PPLL",
    "gn:name":"Urhari",
    "gn:population":0,
    "gn:timezone":"Asia/Kathmandu",
    "iso:country":"NP",
    "wof:name":"Urhari",
    "wof:placetype":"locality"
},
  "geometry": {"coordinates":[82.24601,28.05611],"type":"Point"}
}