{
  "type": "Feature",
  "properties": {
    "gn:admin1_code":"MR",
    "gn:admin2_code":"6",
    "gn:admin3_code":"63.0",
    "gn:admin4_code":"630004.0",
    "gn:asciiname":"Devkota Bada",
    "gn:country_code":"NP",
    "gn:dem":2357,
    "gn:feature_class":"P",
    "gn:feature_code":"PPLL",
    "gn:name":"Devkota Bada",
    "gn:population":0,
    "gn:timezone":"Asia/Kathmandu",
    "iso:country":"NP",
    "wof:name":"Devkota Bada",
    "wof:placetype":"locality"
},
  "geometry": {"coordinates":[82.20274999999999,29.27428],"type":"Point"}
}