{
  "type": "Feature",
  "properties": {
    "gn:admin1_code":"MR",
    "gn:admin2_code":"2.0",
    "gn:admin3_code":"58.0",
    "gn:admin4_code":"580032.0",
    "gn:asciiname":"Chitkaiyan",
    "gn:country_code":"NP",
    "gn:dem":167,
    "gn:feature_class":"P",
    "gn:feature_code":"PPLL",
    "gn:name":"Chitkaiyan",
    "gn:population":0,
    "gn:timezone":"Asia/Kathmandu",
    "iso:country":"NP",
    "wof:name":"Chitkaiyan",
    "wof:placetype":"locality"
},
  "geometry": {"coordinates":[81.26957,28.46802000000001],"type":"Point"}
}