{
  "type": "Feature",
  "properties": {
    "gn:admin1_code":"FR",
    "gn:admin2_code":"9",
    "gn:admin3_code":"73.0",
    "gn:admin4_code":"730001.0",
    "gn:asciiname":"Sillingi",
    "gn:country_code":"NP",
    "gn:dem":1549,
    "gn:feature_class":"P",
    "gn:feature_code":"PPLL",
    "gn:name":"Sillingi",
    "gn:population":0,
    "gn:timezone":"Asia/Kathmandu",
    "iso:country":"NP",
    "wof:name":"Sillingi",
    "wof:placetype":"locality"
},
  "geometry": {"coordinates":[80.58395,29.36555],"type":"Point"}
}