{
  "type": "Feature",
  "properties": {
    "gn:admin1_code":"MR",
    "gn:admin2_code":"12",
    "gn:admin3_code":"53",
    "gn:admin4_code":"530031",
    "gn:asciiname":"Jail",
    "gn:country_code":"NP",
    "gn:dem":1192,
    "gn:feature_class":"P",
    "gn:feature_code":"PPLL",
    "gn:name":"Jail",
    "gn:population":0,
    "gn:timezone":"Asia/Kathmandu",
    "iso:country":"NP",
    "wof:name":"Jail",
    "wof:placetype":"locality"
},
  "geometry": {"coordinates":[82.64055,28.30634],"type":"Point"}
}