{
  "type": "Feature",
  "properties": {
    "gn:admin1_code":"WR",
    "gn:admin2_code":"8",
    "gn:admin3_code":"46.0",
    "gn:admin4_code":"460007.0",
    "gn:asciiname":"Tallo Bhand",
    "gn:country_code":"NP",
    "gn:dem":1176,
    "gn:feature_class":"P",
    "gn:feature_code":"PPLL",
    "gn:name":"Tallo Bhand",
    "gn:population":0,
    "gn:timezone":"Asia/Kathmandu",
    "iso:country":"NP",
    "wof:name":"Tallo Bhand",
    "wof:placetype":"locality"
},
  "geometry": {"coordinates":[83.25045,28.09511],"type":"Point"}
}