{
  "type": "Feature",
  "properties": {
    "gn:admin1_code":"ER",
    "gn:admin2_code":"13",
    "gn:admin3_code":"12",
    "gn:admin4_code":"120019",
    "gn:asciiname":"Tapkedanda",
    "gn:country_code":"NP",
    "gn:dem":1681,
    "gn:feature_class":"P",
    "gn:feature_code":"PPLL",
    "gn:name":"Tapkedanda",
    "gn:population":0,
    "gn:timezone":"Asia/Kathmandu",
    "iso:country":"NP",
    "wof:name":"Tapkedanda",
    "wof:placetype":"locality"
},
  "geometry": {"coordinates":[86.2786,27.29839],"type":"Point"}
}