{
  "type": "Feature",
  "properties": {
    "gn:admin1_code":"CR",
    "gn:admin2_code":"1",
    "gn:admin3_code":"28",
    "gn:admin4_code":"280038",
    "gn:asciiname":"Bhirkuna",
    "gn:country_code":"NP",
    "gn:dem":791,
    "gn:feature_class":"P",
    "gn:feature_code":"PPLL",
    "gn:name":"Bhirkuna",
    "gn:population":0,
    "gn:timezone":"Asia/Kathmandu",
    "iso:country":"NP",
    "wof:name":"Bhirkuna",
    "wof:placetype":"locality"
},
  "geometry": {"coordinates":[85.21382,27.84883],"type":"Point"}
}