{
  "type": "Feature",
  "properties": {
    "gn:admin1_code":"ER",
    "gn:admin2_code":"13",
    "gn:admin3_code":"16",
    "gn:admin4_code":"160030",
    "gn:asciiname":"Chhapdari",
    "gn:country_code":"NP",
    "gn:dem":128,
    "gn:feature_class":"P",
    "gn:feature_code":"PPLL",
    "gn:name":"Chhapdari",
    "gn:population":0,
    "gn:timezone":"Asia/Kathmandu",
    "iso:country":"NP",
    "wof:name":"Chhapdari",
    "wof:placetype":"locality"
},
  "geometry": {"coordinates":[86.42477,26.73903],"type":"Point"}
}