{
  "type": "Feature",
  "properties": {
    "gn:admin1_code":"CR",
    "gn:admin2_code":"1",
    "gn:admin3_code":"23",
    "gn:admin4_code":"230058",
    "gn:asciiname":"Chhap",
    "gn:country_code":"NP",
    "gn:dem":1144,
    "gn:feature_class":"P",
    "gn:feature_code":"PPLL",
    "gn:name":"Chhap",
    "gn:population":0,
    "gn:timezone":"Asia/Kathmandu",
    "iso:country":"NP",
    "name:ceb_x_preferred":[
        "Chhap"
    ],
    "name:fra_x_preferred":[
        "Chhap"
    ],
    "name:mai_x_preferred":[
        "\u091b\u093e\u092a"
    ],
    "name:msa_x_preferred":[
        "Chhap"
    ],
    "name:nep_x_preferred":[
        "\u091b\u093e\u092a"
    ],
    "name:new_x_preferred":[
        "\u091b\u093e\u092a"
    ],
    "name:pol_x_preferred":[
        "Chhap"
    ],
    "wof:name":"Chhap",
    "wof:placetype":"locality"
},
  "geometry": {"coordinates":[85.70366,27.70601],"type":"Point"}
}