{
  "type": "Feature",
  "properties": {
    "gn:admin1_code":"CR",
    "gn:admin2_code":"1",
    "gn:admin3_code":"30.0",
    "gn:admin4_code":"300040.0",
    "gn:asciiname":"Tilar",
    "gn:country_code":"NP",
    "gn:dem":999,
    "gn:feature_class":"P",
    "gn:feature_code":"PPLL",
    "gn:name":"Tilar",
    "gn:population":0,
    "gn:timezone":"Asia/Kathmandu",
    "iso:country":"NP",
    "wof:name":"Tilar",
    "wof:placetype":"locality"
},
  "geometry": {"coordinates":[84.89061,28.01969],"type":"Point"}
}