{
  "type": "Feature",
  "properties": {
    "gn:admin1_code":"MR",
    "gn:admin2_code":"2",
    "gn:admin3_code":"60.0",
    "gn:admin4_code":"600054.0",
    "gn:asciiname":"Amkana",
    "gn:country_code":"NP",
    "gn:dem":1079,
    "gn:feature_class":"P",
    "gn:feature_code":"PPLL",
    "gn:name":"Amkana",
    "gn:population":0,
    "gn:timezone":"Asia/Kathmandu",
    "iso:country":"NP",
    "wof:name":"Amkana",
    "wof:placetype":"locality"
},
  "geometry": {"coordinates":[81.48664000000002,29.04132],"type":"Point"}
}