{
  "type": "Feature",
  "properties": {
    "gn:admin1_code":"WR",
    "gn:admin2_code":"3",
    "gn:admin3_code":"44",
    "gn:admin4_code":"440018",
    "gn:asciiname":"Kalyani",
    "gn:country_code":"NP",
    "gn:dem":1174,
    "gn:feature_class":"P",
    "gn:feature_code":"PPLL",
    "gn:name":"Kalyani",
    "gn:population":0,
    "gn:timezone":"Asia/Kathmandu",
    "iso:country":"NP",
    "name:ben_x_preferred":[
        "\u0995\u09b2\u09cd\u09af\u09be\u09a3\u09c0"
    ],
    "name:bih_x_preferred":[
        "\u0915\u0932\u094d\u092f\u093e\u0923\u0940"
    ],
    "name:mal_x_preferred":[
        "\u0d15\u0d32\u0d4d\u0d2f\u0d3e\u0d23\u0d3f"
    ],
    "name:new_x_preferred":[
        "\u0915\u0932\u094d\u092f\u093e\u0923\u0940"
    ],
    "wof:name":"Kalyani",
    "wof:placetype":"locality"
},
  "geometry": {"coordinates":[83.75774,28.29602],"type":"Point"}
}