{
  "type": "Feature",
  "properties": {
    "gn:admin1_code":"WR",
    "gn:admin2_code":"3",
    "gn:admin3_code":"44",
    "gn:admin4_code":"440018",
    "gn:asciiname":"Kalyani",
    "gn:country_code":"NP",
    "gn:dem":1174,
    "gn:feature_class":"P",
    "gn:feature_code":"PPLL",
    "gn:name":"Kalyani",
    "gn:population":0,
    "gn:timezone":"Asia/Kathmandu",
    "iso:country":"NP",
    "wof:name":"Kalyani",
    "wof:placetype":"locality"
},
  "geometry": {"coordinates":[83.75774,28.29602],"type":"Point"}
}