{
  "type": "Feature",
  "properties": {
    "gn:admin1_code":"CR",
    "gn:admin2_code":"1",
    "gn:admin3_code":"27.0",
    "gn:admin4_code":"270015.0",
    "gn:asciiname":"Nimitol",
    "gn:country_code":"NP",
    "gn:dem":1512,
    "gn:feature_class":"P",
    "gn:feature_code":"PPLL",
    "gn:name":"Nimitol",
    "gn:population":0,
    "gn:timezone":"Asia/Kathmandu",
    "iso:country":"NP",
    "wof:name":"Nimitol",
    "wof:placetype":"locality"
},
  "geometry": {"coordinates":[85.27395,27.60851],"type":"Point"}
}