{
  "type": "Feature",
  "properties": {
    "gn:admin1_code":"FR",
    "gn:admin2_code":"14.0",
    "gn:admin3_code":"67.0",
    "gn:admin4_code":"670005.0",
    "gn:asciiname":"Thothorekharka",
    "gn:country_code":"NP",
    "gn:dem":4033,
    "gn:feature_class":"P",
    "gn:feature_code":"PPLL",
    "gn:name":"Thothorekharka",
    "gn:population":0,
    "gn:timezone":"Asia/Kathmandu",
    "iso:country":"NP",
    "wof:name":"Thothorekharka",
    "wof:placetype":"locality"
},
  "geometry": {"coordinates":[81.59040999999998,29.88622],"type":"Point"}
}