{
  "type": "Feature",
  "properties": {
    "gn:admin1_code":"CR",
    "gn:admin2_code":"1",
    "gn:admin3_code":"27.0",
    "gn:admin4_code":"270031.0",
    "gn:asciiname":"Marutol",
    "gn:country_code":"NP",
    "gn:dem":1307,
    "gn:feature_class":"P",
    "gn:feature_code":"PPLL",
    "gn:name":"Marutol",
    "gn:population":0,
    "gn:timezone":"Asia/Kathmandu",
    "iso:country":"NP",
    "wof:name":"Marutol",
    "wof:placetype":"locality"
},
  "geometry": {"coordinates":[85.30521999999998,27.70432000000001],"type":"Point"}
}