{
  "type": "Feature",
  "properties": {
    "gn:admin1_code":"MR",
    "gn:admin2_code":"2.0",
    "gn:admin3_code":"59.0",
    "gn:admin4_code":"590047.0",
    "gn:asciiname":"Palaite",
    "gn:country_code":"NP",
    "gn:dem":502,
    "gn:feature_class":"P",
    "gn:feature_code":"PPLL",
    "gn:name":"Palaite",
    "gn:population":0,
    "gn:timezone":"Asia/Kathmandu",
    "iso:country":"NP",
    "wof:name":"Palaite",
    "wof:placetype":"locality"
},
  "geometry": {"coordinates":[81.43131,28.79742],"type":"Point"}
}