{
  "type": "Feature",
  "properties": {
    "gn:admin1_code":"ER",
    "gn:admin2_code":"7",
    "gn:admin3_code":"10.0",
    "gn:admin4_code":"100007.0",
    "gn:asciiname":"Dandakharka",
    "gn:country_code":"NP",
    "gn:dem":1705,
    "gn:feature_class":"P",
    "gn:feature_code":"PPLL",
    "gn:name":"Dandakharka",
    "gn:population":0,
    "gn:timezone":"Asia/Kathmandu",
    "iso:country":"NP",
    "name:pol_x_preferred":[
        "Dandakharka"
    ],
    "wof:name":"Dandakharka",
    "wof:placetype":"locality"
},
  "geometry": {"coordinates":[87.08461,27.1992],"type":"Point"}
}