{
  "type": "Feature",
  "properties": {
    "gn:admin1_code":"FR",
    "gn:admin2_code":"14",
    "gn:admin3_code":"69",
    "gn:admin4_code":"690029",
    "gn:asciiname":"Dhungra",
    "gn:country_code":"NP",
    "gn:dem":1070,
    "gn:feature_class":"P",
    "gn:feature_code":"PPLL",
    "gn:name":"Dhungra",
    "gn:population":0,
    "gn:timezone":"Asia/Kathmandu",
    "iso:country":"NP",
    "wof:name":"Dhungra",
    "wof:placetype":"locality"
},
  "geometry": {"coordinates":[81.25227,29.25954],"type":"Point"}
}