{
  "type": "Feature",
  "properties": {
    "gn:admin1_code":"MR",
    "gn:admin2_code":"2.0",
    "gn:admin3_code":"58.0",
    "gn:admin4_code":"580024.0",
    "gn:asciiname":"Syanjalipur",
    "gn:country_code":"NP",
    "gn:dem":161,
    "gn:feature_class":"P",
    "gn:feature_code":"PPLL",
    "gn:name":"Syanjalipur",
    "gn:population":0,
    "gn:timezone":"Asia/Kathmandu",
    "iso:country":"NP",
    "wof:name":"Syanjalipur",
    "wof:placetype":"locality"
},
  "geometry": {"coordinates":[81.19731999999998,28.48146],"type":"Point"}
}