{
  "type": "Feature",
  "properties": {
    "gn:admin1_code":"WR",
    "gn:admin2_code":"8",
    "gn:admin3_code":"46.0",
    "gn:admin4_code":"460029.0",
    "gn:asciiname":"Kaphalpani Danda",
    "gn:country_code":"NP",
    "gn:dem":1228,
    "gn:feature_class":"P",
    "gn:feature_code":"PPLL",
    "gn:name":"Kaphalpani Danda",
    "gn:population":0,
    "gn:timezone":"Asia/Kathmandu",
    "iso:country":"NP",
    "wof:name":"Kaphalpani Danda",
    "wof:placetype":"locality"
},
  "geometry": {"coordinates":[83.15515000000001,28.12112],"type":"Point"}
}