{
  "type": "Feature",
  "properties": {
    "gn:admin1_code":"FR",
    "gn:admin2_code":"9",
    "gn:admin3_code":"74",
    "gn:admin4_code":"740013",
    "gn:asciiname":"Patali",
    "gn:country_code":"NP",
    "gn:dem":1504,
    "gn:feature_class":"P",
    "gn:feature_code":"PPLL",
    "gn:name":"Patali",
    "gn:population":0,
    "gn:timezone":"Asia/Kathmandu",
    "iso:country":"NP",
    "name:fas_x_preferred":[
        "\u067e\u0627\u062a\u0644\u06cc"
    ],
    "wof:name":"Patali",
    "wof:placetype":"locality"
},
  "geometry": {"coordinates":[80.57436,29.56481],"type":"Point"}
}