{
  "type": "Feature",
  "properties": {
    "gn:admin1_code":"CR",
    "gn:admin2_code":"5",
    "gn:admin3_code":"20",
    "gn:admin4_code":"200024",
    "gn:asciiname":"Shisaudamar",
    "gn:country_code":"NP",
    "gn:dem":358,
    "gn:feature_class":"P",
    "gn:feature_code":"PPLL",
    "gn:name":"Shisaudamar",
    "gn:population":0,
    "gn:timezone":"Asia/Kathmandu",
    "iso:country":"NP",
    "wof:name":"Shisaudamar",
    "wof:placetype":"locality"
},
  "geometry": {"coordinates":[85.69570999999998,27.19356],"type":"Point"}
}