{
  "type": "Feature",
  "properties": {
    "gn:admin1_code":"ER",
    "gn:admin2_code":"13",
    "gn:admin3_code":"12",
    "gn:admin4_code":"120007",
    "gn:asciiname":"Chhanga",
    "gn:country_code":"NP",
    "gn:dem":1131,
    "gn:feature_class":"P",
    "gn:feature_code":"PPLL",
    "gn:name":"Chhanga",
    "gn:population":0,
    "gn:timezone":"Asia/Kathmandu",
    "iso:country":"NP",
    "wof:name":"Chhanga",
    "wof:placetype":"locality"
},
  "geometry": {"coordinates":[86.61865,27.26045],"type":"Point"}
}