{
  "type": "Feature",
  "properties": {
    "gn:admin1_code":"ER",
    "gn:admin2_code":"13",
    "gn:admin3_code":"13",
    "gn:admin4_code":"130053",
    "gn:asciiname":"Nerpa",
    "gn:country_code":"NP",
    "gn:dem":1857,
    "gn:feature_class":"P",
    "gn:feature_code":"PPLL",
    "gn:name":"Nerpa",
    "gn:population":0,
    "gn:timezone":"Asia/Kathmandu",
    "iso:country":"NP",
    "name:ceb_x_preferred":[
        "Nerpa"
    ],
    "name:ces_x_preferred":[
        "N\u011brpa"
    ],
    "name:deu_x_preferred":[
        "Nerpa"
    ],
    "name:rus_x_preferred":[
        "\u041d\u0435\u0440\u043f\u0430"
    ],
    "name:swe_x_preferred":[
        "Nerpa"
    ],
    "wof:name":"Nerpa",
    "wof:placetype":"locality"
},
  "geometry": {"coordinates":[86.83093000000002,27.25595],"type":"Point"}
}