{
  "type": "Feature",
  "properties": {
    "gn:admin1_code":"WR",
    "gn:admin2_code":"8",
    "gn:admin3_code":"47",
    "gn:admin4_code":"470026",
    "gn:asciiname":"Garhabas",
    "gn:country_code":"NP",
    "gn:dem":938,
    "gn:feature_class":"P",
    "gn:feature_code":"PPLL",
    "gn:name":"Garhabas",
    "gn:population":0,
    "gn:timezone":"Asia/Kathmandu",
    "iso:country":"NP",
    "wof:name":"Garhabas",
    "wof:placetype":"locality"
},
  "geometry": {"coordinates":[83.61197,27.71489],"type":"Point"}
}