{
  "type": "Feature",
  "properties": {
    "gn:admin1_code":"FR",
    "gn:admin2_code":"14",
    "gn:admin3_code":"71.0",
    "gn:admin4_code":"710020.0",
    "gn:asciiname":"Rani Bhugada",
    "gn:country_code":"NP",
    "gn:dem":859,
    "gn:feature_class":"P",
    "gn:feature_code":"PPLL",
    "gn:name":"Rani Bhugada",
    "gn:population":0,
    "gn:timezone":"Asia/Kathmandu",
    "iso:country":"NP",
    "wof:name":"Rani Bhugada",
    "wof:placetype":"locality"
},
  "geometry": {"coordinates":[80.79115,28.91324],"type":"Point"}
}