{
  "type": "Feature",
  "properties": {
    "gn:admin1_code":"FR",
    "gn:admin2_code":"9",
    "gn:admin3_code":"74",
    "gn:admin4_code":"740060",
    "gn:asciiname":"Daha",
    "gn:country_code":"NP",
    "gn:dem":1647,
    "gn:feature_class":"P",
    "gn:feature_code":"PPLL",
    "gn:name":"Daha",
    "gn:population":0,
    "gn:timezone":"Asia/Kathmandu",
    "iso:country":"NP",
    "name:ceb_x_preferred":[
        "Daha"
    ],
    "name:fra_x_preferred":[
        "Daha"
    ],
    "name:ind_x_preferred":[
        "Daha"
    ],
    "name:ita_x_preferred":[
        "Daha"
    ],
    "name:swe_x_preferred":[
        "Daha"
    ],
    "name:uzb_x_preferred":[
        "Daha"
    ],
    "wof:name":"Daha",
    "wof:placetype":"locality"
},
  "geometry": {"coordinates":[80.50964999999999,29.56462],"type":"Point"}
}