{
  "type": "Feature",
  "properties": {
    "gn:admin1_code":"CR",
    "gn:admin2_code":"5",
    "gn:admin3_code":"21",
    "gn:admin4_code":"210049",
    "gn:asciiname":"Kaijale",
    "gn:country_code":"NP",
    "gn:dem":1559,
    "gn:feature_class":"P",
    "gn:feature_code":"PPLL",
    "gn:name":"Kaijale",
    "gn:population":0,
    "gn:timezone":"Asia/Kathmandu",
    "iso:country":"NP",
    "wof:name":"Kaijale",
    "wof:placetype":"locality"
},
  "geometry": {"coordinates":[86.15016,27.36118],"type":"Point"}
}