{
  "type": "Feature",
  "properties": {
    "gn:admin1_code":"ER",
    "gn:admin2_code":"7",
    "gn:admin3_code":"9",
    "gn:admin4_code":"90016",
    "gn:asciiname":"Chyangring",
    "gn:country_code":"NP",
    "gn:dem":1036,
    "gn:feature_class":"P",
    "gn:feature_code":"PPLL",
    "gn:name":"Chyangring",
    "gn:population":0,
    "gn:timezone":"Asia/Kathmandu",
    "iso:country":"NP",
    "wof:name":"Chyangring",
    "wof:placetype":"locality"
},
  "geometry": {"coordinates":[87.37878000000001,27.2881],"type":"Point"}
}