{
  "type": "Feature",
  "properties": {
    "gn:admin1_code":"FR",
    "gn:admin2_code":"14",
    "gn:admin3_code":"71.0",
    "gn:admin4_code":"710038.0",
    "gn:asciiname":"Magarau",
    "gn:country_code":"NP",
    "gn:dem":1281,
    "gn:feature_class":"P",
    "gn:feature_code":"PPLL",
    "gn:name":"Magarau",
    "gn:population":0,
    "gn:timezone":"Asia/Kathmandu",
    "iso:country":"NP",
    "wof:name":"Magarau",
    "wof:placetype":"locality"
},
  "geometry": {"coordinates":[80.62808000000003,29.02551],"type":"Point"}
}