{
  "type": "Feature",
  "properties": {
    "gn:admin1_code":"FR",
    "gn:admin2_code":"14",
    "gn:admin3_code":"69",
    "gn:admin4_code":"690005",
    "gn:asciiname":"Taulipipal",
    "gn:country_code":"NP",
    "gn:dem":872,
    "gn:feature_class":"P",
    "gn:feature_code":"PPLL",
    "gn:name":"Taulipipal",
    "gn:population":0,
    "gn:timezone":"Asia/Kathmandu",
    "iso:country":"NP",
    "wof:name":"Taulipipal",
    "wof:placetype":"locality"
},
  "geometry": {"coordinates":[81.17613,29.05498],"type":"Point"}
}