{
  "type": "Feature",
  "properties": {
    "gn:admin1_code":"CR",
    "gn:admin2_code":"1",
    "gn:admin3_code":"27.0",
    "gn:admin4_code":"270047.0",
    "gn:asciiname":"Jagatgaun",
    "gn:country_code":"NP",
    "gn:dem":1514,
    "gn:feature_class":"P",
    "gn:feature_code":"PPLL",
    "gn:name":"Jagatgaun",
    "gn:population":0,
    "gn:timezone":"Asia/Kathmandu",
    "iso:country":"NP",
    "wof:name":"Jagatgaun",
    "wof:placetype":"locality"
},
  "geometry": {"coordinates":[85.32337,27.8012],"type":"Point"}
}