{
  "type": "Feature",
  "properties": {
    "gn:admin1_code":"FR",
    "gn:admin2_code":"14.0",
    "gn:admin3_code":"67.0",
    "gn:admin4_code":"670007.0",
    "gn:asciiname":"Jadanga",
    "gn:country_code":"NP",
    "gn:dem":1270,
    "gn:feature_class":"P",
    "gn:feature_code":"PPLL",
    "gn:name":"Jadanga",
    "gn:population":0,
    "gn:timezone":"Asia/Kathmandu",
    "iso:country":"NP",
    "wof:name":"Jadanga",
    "wof:placetype":"locality"
},
  "geometry": {"coordinates":[81.42900999999998,29.41662],"type":"Point"}
}