{
  "type": "Feature",
  "properties": {
    "gn:admin1_code":"FR",
    "gn:admin2_code":"9",
    "gn:admin3_code":"72.0",
    "gn:admin4_code":"720004.0",
    "gn:asciiname":"Dangra Daiji",
    "gn:country_code":"NP",
    "gn:dem":209,
    "gn:feature_class":"P",
    "gn:feature_code":"PPLL",
    "gn:name":"Dangra Daiji",
    "gn:population":0,
    "gn:timezone":"Asia/Kathmandu",
    "iso:country":"NP",
    "wof:name":"Dangra Daiji",
    "wof:placetype":"locality"
},
  "geometry": {"coordinates":[80.27391999999998,28.94862],"type":"Point"}
}