{
  "type": "Feature",
  "properties": {
    "gn:admin1_code":"CR",
    "gn:admin2_code":"1",
    "gn:admin3_code":"28",
    "gn:admin4_code":"280004",
    "gn:asciiname":"Upallo Tigaun",
    "gn:country_code":"NP",
    "gn:dem":1219,
    "gn:feature_class":"P",
    "gn:feature_code":"PPLL",
    "gn:name":"Upallo Tigaun",
    "gn:population":0,
    "gn:timezone":"Asia/Kathmandu",
    "iso:country":"NP",
    "wof:name":"Upallo Tigaun",
    "wof:placetype":"locality"
},
  "geometry": {"coordinates":[85.16839,27.83447],"type":"Point"}
}