{
  "type": "Feature",
  "properties": {
    "gn:admin1_code":"ER",
    "gn:admin2_code":"10",
    "gn:admin3_code":"2",
    "gn:admin4_code":"20010.0",
    "gn:asciiname":"Madibung",
    "gn:country_code":"NP",
    "gn:dem":1539,
    "gn:feature_class":"P",
    "gn:feature_code":"PPLL",
    "gn:name":"Madibung",
    "gn:population":0,
    "gn:timezone":"Asia/Kathmandu",
    "iso:country":"NP",
    "wof:name":"Madibung",
    "wof:placetype":"locality"
},
  "geometry": {"coordinates":[87.87179999999999,27.19973],"type":"Point"}
}