{
  "type": "Feature",
  "properties": {
    "gn:admin1_code":"ER",
    "gn:admin2_code":"7",
    "gn:admin3_code":"7.0",
    "gn:admin4_code":"70025.0",
    "gn:asciiname":"Chhyalung",
    "gn:country_code":"NP",
    "gn:dem":1726,
    "gn:feature_class":"P",
    "gn:feature_code":"PPLL",
    "gn:name":"Chhyalung",
    "gn:population":0,
    "gn:timezone":"Asia/Kathmandu",
    "iso:country":"NP",
    "wof:name":"Chhyalung",
    "wof:placetype":"locality"
},
  "geometry": {"coordinates":[87.3579,27.14657],"type":"Point"}
}