{
  "type": "Feature",
  "properties": {
    "gn:admin1_code":"WR",
    "gn:admin2_code":"3",
    "gn:admin3_code":"43",
    "gn:admin4_code":"430003",
    "gn:asciiname":"Sahasradhara",
    "gn:country_code":"NP",
    "gn:dem":1287,
    "gn:feature_class":"P",
    "gn:feature_code":"PPLL",
    "gn:name":"Sahasradhara",
    "gn:population":0,
    "gn:timezone":"Asia/Kathmandu",
    "iso:country":"NP",
    "name:guj_x_preferred":[
        "\u0ab8\u0ab9\u0ab8\u0acd\u0aa4\u0acd\u0ab0\u0aa7\u0abe\u0ab0\u0abe"
    ],
    "name:hin_x_preferred":[
        "\u0938\u0939\u0938\u094d\u0930\u0927\u093e\u0930\u093e"
    ],
    "wof:name":"Sahasradhara",
    "wof:placetype":"locality"
},
  "geometry": {"coordinates":[83.42957,28.39834],"type":"Point"}
}