{
  "type": "Feature",
  "properties": {
    "gn:admin1_code":"WR",
    "gn:admin2_code":"3",
    "gn:admin3_code":"44",
    "gn:admin4_code":"440050",
    "gn:asciiname":"Khalte",
    "gn:country_code":"NP",
    "gn:dem":1129,
    "gn:feature_class":"P",
    "gn:feature_code":"PPLL",
    "gn:name":"Khalte",
    "gn:population":0,
    "gn:timezone":"Asia/Kathmandu",
    "iso:country":"NP",
    "wof:name":"Khalte",
    "wof:placetype":"locality"
},
  "geometry": {"coordinates":[83.69098000000002,28.15226],"type":"Point"}
}