{
  "type": "Feature",
  "properties": {
    "gn:admin1_code":"WR",
    "gn:admin2_code":"8",
    "gn:admin3_code":"47",
    "gn:admin4_code":"470064.0",
    "gn:asciiname":"Gnorli Kharka",
    "gn:country_code":"NP",
    "gn:dem":1372,
    "gn:feature_class":"P",
    "gn:feature_code":"PPLL",
    "gn:name":"Gnorli Kharka",
    "gn:population":0,
    "gn:timezone":"Asia/Kathmandu",
    "iso:country":"NP",
    "wof:name":"Gnorli Kharka",
    "wof:placetype":"locality"
},
  "geometry": {"coordinates":[83.45465,27.8378],"type":"Point"}
}