{
  "type": "Feature",
  "properties": {
    "gn:admin1_code":"FR",
    "gn:admin2_code":"9",
    "gn:admin3_code":"74",
    "gn:admin4_code":"740054",
    "gn:asciiname":"Lek Halniya",
    "gn:country_code":"NP",
    "gn:dem":1884,
    "gn:feature_class":"P",
    "gn:feature_code":"PPLL",
    "gn:name":"Lek Halniya",
    "gn:population":0,
    "gn:timezone":"Asia/Kathmandu",
    "iso:country":"NP",
    "wof:name":"Lek Halniya",
    "wof:placetype":"locality"
},
  "geometry": {"coordinates":[80.79761999999999,29.46233],"type":"Point"}
}