{
  "type": "Feature",
  "properties": {
    "gn:admin1_code":"CR",
    "gn:admin2_code":"5",
    "gn:admin3_code":"20",
    "gn:admin4_code":"200025",
    "gn:asciiname":"Bhandar",
    "gn:country_code":"NP",
    "gn:dem":521,
    "gn:feature_class":"P",
    "gn:feature_code":"PPLL",
    "gn:name":"Bhandar",
    "gn:population":0,
    "gn:timezone":"Asia/Kathmandu",
    "iso:country":"NP",
    "wof:name":"Bhandar",
    "wof:placetype":"locality"
},
  "geometry": {"coordinates":[85.95572,27.13813],"type":"Point"}
}