{
  "type": "Feature",
  "properties": {
    "gn:admin1_code":"FR",
    "gn:admin2_code":"14.0",
    "gn:admin3_code":"67.0",
    "gn:admin4_code":"670019.0",
    "gn:asciiname":"Lade",
    "gn:country_code":"NP",
    "gn:dem":2959,
    "gn:feature_class":"P",
    "gn:feature_code":"PPLL",
    "gn:name":"Lade",
    "gn:population":0,
    "gn:timezone":"Asia/Kathmandu",
    "iso:country":"NP",
    "name:dan_x_preferred":[
        "Lade"
    ],
    "name:deu_x_preferred":[
        "Lade"
    ],
    "name:ita_x_preferred":[
        "Lade"
    ],
    "name:nds_x_preferred":[
        "Lade"
    ],
    "name:swe_x_preferred":[
        "Lade"
    ],
    "wof:name":"Lade",
    "wof:placetype":"locality"
},
  "geometry": {"coordinates":[81.62613,29.56529],"type":"Point"}
}