{
  "type": "Feature",
  "properties": {
    "gn:admin1_code":"MR",
    "gn:admin2_code":"12",
    "gn:admin3_code":"55",
    "gn:admin4_code":"550023",
    "gn:asciiname":"Tinukhada",
    "gn:country_code":"NP",
    "gn:dem":1367,
    "gn:feature_class":"P",
    "gn:feature_code":"PPLL",
    "gn:name":"Tinukhada",
    "gn:population":0,
    "gn:timezone":"Asia/Kathmandu",
    "iso:country":"NP",
    "wof:name":"Tinukhada",
    "wof:placetype":"locality"
},
  "geometry": {"coordinates":[82.16481,28.24538],"type":"Point"}
}