{
  "type": "Feature",
  "properties": {
    "gn:admin1_code":"MR",
    "gn:admin2_code":"12",
    "gn:admin3_code":"55",
    "gn:admin4_code":"550012",
    "gn:asciiname":"Bhalukholagaun",
    "gn:country_code":"NP",
    "gn:dem":1699,
    "gn:feature_class":"P",
    "gn:feature_code":"PPLL",
    "gn:name":"Bhalukholagaun",
    "gn:population":0,
    "gn:timezone":"Asia/Kathmandu",
    "iso:country":"NP",
    "wof:name":"Bhalukholagaun",
    "wof:placetype":"locality"
},
  "geometry": {"coordinates":[82.3638,28.5544],"type":"Point"}
}