{
  "type": "Feature",
  "properties": {
    "gn:admin1_code":"ER",
    "gn:admin2_code":"7",
    "gn:admin3_code":"10.0",
    "gn:admin4_code":"100036.0",
    "gn:asciiname":"Bakkhim",
    "gn:country_code":"NP",
    "gn:dem":1126,
    "gn:feature_class":"P",
    "gn:feature_code":"PPLL",
    "gn:name":"Bakkhim",
    "gn:population":0,
    "gn:timezone":"Asia/Kathmandu",
    "iso:country":"NP",
    "wof:name":"Bakkhim",
    "wof:placetype":"locality"
},
  "geometry": {"coordinates":[87.00545,27.17155],"type":"Point"}
}