{
  "type": "Feature",
  "properties": {
    "gn:admin1_code":"WR",
    "gn:admin2_code":"4.0",
    "gn:admin3_code":"38.0",
    "gn:admin4_code":"380043.0",
    "gn:asciiname":"Kriyapani",
    "gn:country_code":"NP",
    "gn:dem":1104,
    "gn:feature_class":"P",
    "gn:feature_code":"PPLL",
    "gn:name":"Kriyapani",
    "gn:population":0,
    "gn:timezone":"Asia/Kathmandu",
    "iso:country":"NP",
    "wof:name":"Kriyapani",
    "wof:placetype":"locality"
},
  "geometry": {"coordinates":[84.19165,28.0696],"type":"Point"}
}