{
  "type": "Feature",
  "properties": {
    "gn:admin1_code":"ER",
    "gn:admin2_code":"10",
    "gn:admin3_code":"2",
    "gn:admin4_code":"20019",
    "gn:asciiname":"Mauwa",
    "gn:country_code":"NP",
    "gn:dem":669,
    "gn:feature_class":"P",
    "gn:feature_code":"PPLL",
    "gn:name":"Mauwa",
    "gn:population":0,
    "gn:timezone":"Asia/Kathmandu",
    "iso:country":"NP",
    "name:ceb_x_preferred":[
        "Mauwa"
    ],
    "name:mai_x_preferred":[
        "\u092e\u094c\u0935\u093e"
    ],
    "name:msa_x_preferred":[
        "Mauwa"
    ],
    "name:nep_x_preferred":[
        "\u092e\u094c\u0935\u093e"
    ],
    "name:new_x_preferred":[
        "\u092e\u094c\u0935\u093e"
    ],
    "name:pol_x_preferred":[
        "Mauwa"
    ],
    "wof:name":"Mauwa",
    "wof:placetype":"locality"
},
  "geometry": {"coordinates":[87.55828000000002,27.00766],"type":"Point"}
}