{
  "type": "Feature",
  "properties": {
    "gn:admin1_code":"WR",
    "gn:admin2_code":"4.0",
    "gn:admin3_code":"39.0",
    "gn:admin4_code":"390043.0",
    "gn:asciiname":"Ramidanda",
    "gn:country_code":"NP",
    "gn:dem":1290,
    "gn:feature_class":"P",
    "gn:feature_code":"PPLL",
    "gn:name":"Ramidanda",
    "gn:population":0,
    "gn:timezone":"Asia/Kathmandu",
    "iso:country":"NP",
    "wof:name":"Ramidanda",
    "wof:placetype":"locality"
},
  "geometry": {"coordinates":[83.64967,28.00922000000001],"type":"Point"}
}