{
  "type": "Feature",
  "properties": {
    "gn:admin1_code":"CR",
    "gn:admin2_code":"1",
    "gn:admin3_code":"23",
    "gn:admin4_code":"230007.0",
    "gn:asciiname":"Khasreghyang",
    "gn:country_code":"NP",
    "gn:dem":2070,
    "gn:feature_class":"P",
    "gn:feature_code":"PPLL",
    "gn:name":"Khasreghyang",
    "gn:population":0,
    "gn:timezone":"Asia/Kathmandu",
    "iso:country":"NP",
    "wof:name":"Khasreghyang",
    "wof:placetype":"locality"
},
  "geometry": {"coordinates":[85.61539,27.93945],"type":"Point"}
}