{
  "type": "Feature",
  "properties": {
    "gn:admin1_code":"CR",
    "gn:admin2_code":"1",
    "gn:admin3_code":"30.0",
    "gn:admin4_code":"300034.0",
    "gn:asciiname":"Koiralagaun",
    "gn:country_code":"NP",
    "gn:dem":849,
    "gn:feature_class":"P",
    "gn:feature_code":"PPLL",
    "gn:name":"Koiralagaun",
    "gn:population":0,
    "gn:timezone":"Asia/Kathmandu",
    "iso:country":"NP",
    "wof:name":"Koiralagaun",
    "wof:placetype":"locality"
},
  "geometry": {"coordinates":[85.14213000000002,27.72555],"type":"Point"}
}