{
  "type": "Feature",
  "properties": {
    "gn:admin1_code":"WR",
    "gn:admin2_code":"8",
    "gn:admin3_code":"47",
    "gn:admin4_code":"470020",
    "gn:asciiname":"Madhuban",
    "gn:country_code":"NP",
    "gn:dem":1044,
    "gn:feature_class":"P",
    "gn:feature_code":"PPLL",
    "gn:name":"Madhuban",
    "gn:population":0,
    "gn:timezone":"Asia/Kathmandu",
    "iso:country":"NP",
    "wof:name":"Madhuban",
    "wof:placetype":"locality"
},
  "geometry": {"coordinates":[83.4787,27.78],"type":"Point"}
}