{
  "type": "Feature",
  "properties": {
    "gn:admin1_code":"FR",
    "gn:admin2_code":"9",
    "gn:admin3_code":"72.0",
    "gn:admin4_code":"720014.0",
    "gn:asciiname":"Rajghat",
    "gn:country_code":"NP",
    "gn:dem":183,
    "gn:feature_class":"P",
    "gn:feature_code":"PPLL",
    "gn:name":"Rajghat",
    "gn:population":0,
    "gn:timezone":"Asia/Kathmandu",
    "iso:country":"NP",
    "name:ceb_x_preferred":[
        "Rajghat"
    ],
    "name:fra_x_preferred":[
        "Rajghat"
    ],
    "name:new_x_preferred":[
        "\u0930\u093e\u091c\u0918\u093e\u091f \u0917\u093e\u0935\u093f\u0938"
    ],
    "name:pol_x_preferred":[
        "Rajghat"
    ],
    "wof:name":"Rajghat",
    "wof:placetype":"locality"
},
  "geometry": {"coordinates":[80.54165999999999,28.74397],"type":"Point"}
}