{
  "type": "Feature",
  "properties": {
    "gn:admin1_code":"ER",
    "gn:admin2_code":"10.0",
    "gn:admin3_code":"1.0",
    "gn:admin4_code":"10013.0",
    "gn:asciiname":"Sibu",
    "gn:country_code":"NP",
    "gn:dem":1786,
    "gn:feature_class":"P",
    "gn:feature_code":"PPLL",
    "gn:name":"Sibu",
    "gn:population":0,
    "gn:timezone":"Asia/Kathmandu",
    "iso:country":"NP",
    "name:ara_x_preferred":[
        "\u0633\u064a\u0628\u0648"
    ],
    "name:bul_x_preferred":[
        "\u0421\u0438\u0431\u0443"
    ],
    "name:cdo_x_preferred":[
        "Sibu"
    ],
    "name:ceb_x_preferred":[
        "Sibu"
    ],
    "name:dan_x_preferred":[
        "Sibu"
    ],
    "name:epo_x_preferred":[
        "Sibu"
    ],
    "name:fas_x_preferred":[
        "\u0633\u06cc\u0628\u0648"
    ],
    "name:fra_x_preferred":[
        "Sibu"
    ],
    "name:ind_x_preferred":[
        "Sibu"
    ],
    "name:ita_x_preferred":[
        "Sibu"
    ],
    "name:msa_x_preferred":[
        "Sibu"
    ],
    "name:nld_x_preferred":[
        "Sibu"
    ],
    "name:nno_x_preferred":[
        "Sibu"
    ],
    "name:nor_x_preferred":[
        "Sibu"
    ],
    "name:pol_x_preferred":[
        "Sibu"
    ],
    "name:rus_x_preferred":[
        "\u0421\u0438\u0431\u0443"
    ],
    "name:spa_x_preferred":[
        "Sibu"
    ],
    "name:swe_x_preferred":[
        "Sibu"
    ],
    "name:tam_x_preferred":[
        "\u0b9a\u0bbf\u0baa\u0bc1"
    ],
    "name:tha_x_preferred":[
        "\u0e0b\u0e35\u0e1a\u0e39"
    ],
    "name:tur_x_preferred":[
        "Sibu"
    ],
    "name:urd_x_preferred":[
        "\u0633\u06cc\u0628\u0648"
    ],
    "name:vie_x_preferred":[
        "Sibu"
    ],
    "name:war_x_preferred":[
        "Sibu"
    ],
    "wof:name":"Sibu",
    "wof:placetype":"locality"
},
  "geometry": {"coordinates":[87.68028000000002,27.46233],"type":"Point"}
}