{
  "type": "Feature",
  "properties": {
    "gn:admin1_code":"00",
    "gn:asciiname":"Jeljale",
    "gn:country_code":"NP",
    "gn:dem":1952,
    "gn:feature_class":"P",
    "gn:feature_code":"PPL",
    "gn:name":"Jeljale",
    "gn:population":0,
    "gn:timezone":"Asia/Kathmandu",
    "iso:country":"NP",
    "name:nep_x_preferred":[
        "Jeljale"
    ],
    "wof:name":"Jeljale",
    "wof:placetype":"locality"
},
  "geometry": {"coordinates":[86.27204,27.14228],"type":"Point"}
}