{
  "type": "Feature",
  "properties": {
    "gn:admin1_code":"ER",
    "gn:admin2_code":"13",
    "gn:admin3_code":"13",
    "gn:admin4_code":"130069",
    "gn:asciiname":"Nagi",
    "gn:country_code":"NP",
    "gn:dem":1672,
    "gn:feature_class":"P",
    "gn:feature_code":"PPLL",
    "gn:name":"Nagi",
    "gn:population":0,
    "gn:timezone":"Asia/Kathmandu",
    "iso:country":"NP",
    "wof:name":"Nagi",
    "wof:placetype":"locality"
},
  "geometry": {"coordinates":[86.88974,27.06713],"type":"Point"}
}