{
  "type": "Feature",
  "properties": {
    "gn:admin1_code":"ER",
    "gn:admin2_code":"7",
    "gn:admin3_code":"5",
    "gn:admin4_code":"50008",
    "gn:asciiname":"Chunimadi",
    "gn:country_code":"NP",
    "gn:dem":73,
    "gn:feature_class":"P",
    "gn:feature_code":"PPLL",
    "gn:name":"Chunimadi",
    "gn:population":0,
    "gn:timezone":"Asia/Kathmandu",
    "iso:country":"NP",
    "name:nep_x_preferred":[
        "Chuni\u0307\u0304m\u0101\u1e0di\u0307\u0304"
    ],
    "name:und_x_variant":[
        "Chunem\u0101ri"
    ],
    "wof:name":"Chunimadi",
    "wof:placetype":"locality"
},
  "geometry": {"coordinates":[87.61529,26.40789],"type":"Point"}
}