{
  "type": "Feature",
  "properties": {
    "gn:admin1_code":"FR",
    "gn:admin2_code":"14",
    "gn:admin3_code":"71.0",
    "gn:admin4_code":"710041.0",
    "gn:asciiname":"Tingharawa",
    "gn:country_code":"NP",
    "gn:dem":150,
    "gn:feature_class":"P",
    "gn:feature_code":"PPLL",
    "gn:name":"Tingharawa",
    "gn:population":0,
    "gn:timezone":"Asia/Kathmandu",
    "iso:country":"NP",
    "wof:name":"Tingharawa",
    "wof:placetype":"locality"
},
  "geometry": {"coordinates":[81.00754000000001,28.53245],"type":"Point"}
}