{
  "type": "Feature",
  "properties": {
    "gn:admin1_code":"00",
    "gn:asciiname":"Dinthan",
    "gn:country_code":"NP",
    "gn:dem":2319,
    "gn:feature_class":"P",
    "gn:feature_code":"PPL",
    "gn:name":"Dinth\u0101\u1e45",
    "gn:population":0,
    "gn:timezone":"Asia/Kathmandu",
    "iso:country":"NP",
    "name:nep_x_preferred":[
        "Dinth\u0101\u1e45"
    ],
    "wof:name":"Dinthan",
    "wof:placetype":"locality"
},
  "geometry": {"coordinates":[85.96124,27.86071],"type":"Point"}
}