{
  "type": "Feature",
  "properties": {
    "gn:admin1_code":"MR",
    "gn:admin2_code":"12",
    "gn:admin3_code":"52",
    "gn:admin4_code":"520038",
    "gn:asciiname":"Kolchaur",
    "gn:country_code":"NP",
    "gn:dem":1642,
    "gn:feature_class":"P",
    "gn:feature_code":"PPLL",
    "gn:name":"Kolchaur",
    "gn:population":0,
    "gn:timezone":"Asia/Kathmandu",
    "iso:country":"NP",
    "wof:name":"Kolchaur",
    "wof:placetype":"locality"
},
  "geometry": {"coordinates":[83.02324,28.22039],"type":"Point"}
}