{
  "type": "Feature",
  "properties": {
    "gn:admin1_code":"FR",
    "gn:admin2_code":"14",
    "gn:admin3_code":"69.0",
    "gn:admin4_code":"690067.0",
    "gn:asciiname":"Kathal",
    "gn:country_code":"NP",
    "gn:dem":1377,
    "gn:feature_class":"P",
    "gn:feature_code":"PPLL",
    "gn:name":"Kathal",
    "gn:population":0,
    "gn:timezone":"Asia/Kathmandu",
    "iso:country":"NP",
    "wof:name":"Kathal",
    "wof:placetype":"locality"
},
  "geometry": {"coordinates":[81.09480000000001,29.19247],"type":"Point"}
}