{
  "type": "Feature",
  "properties": {
    "gn:admin1_code":"WR",
    "gn:admin2_code":"4.0",
    "gn:admin3_code":"39.0",
    "gn:admin4_code":"390044.0",
    "gn:asciiname":"Karkidanda",
    "gn:country_code":"NP",
    "gn:dem":1081,
    "gn:feature_class":"P",
    "gn:feature_code":"PPLL",
    "gn:name":"Karkidanda",
    "gn:population":0,
    "gn:timezone":"Asia/Kathmandu",
    "iso:country":"NP",
    "wof:name":"Karkidanda",
    "wof:placetype":"locality"
},
  "geometry": {"coordinates":[83.81546,28.1094],"type":"Point"}
}