{
  "type": "Feature",
  "properties": {
    "gn:admin1_code":"ER",
    "gn:admin2_code":"13",
    "gn:admin3_code":"13.0",
    "gn:admin4_code":"130002.0",
    "gn:asciiname":"Dukseli",
    "gn:country_code":"NP",
    "gn:dem":1188,
    "gn:feature_class":"P",
    "gn:feature_code":"PPLL",
    "gn:name":"Dukseli",
    "gn:population":0,
    "gn:timezone":"Asia/Kathmandu",
    "iso:country":"NP",
    "wof:name":"Dukseli",
    "wof:placetype":"locality"
},
  "geometry": {"coordinates":[86.67327,27.21557],"type":"Point"}
}