{
  "type": "Feature",
  "properties": {
    "gn:admin1_code":"ER",
    "gn:admin2_code":"10",
    "gn:admin3_code":"2",
    "gn:admin4_code":"20023",
    "gn:asciiname":"Kerabari",
    "gn:country_code":"NP",
    "gn:dem":1431,
    "gn:feature_class":"P",
    "gn:feature_code":"PPLL",
    "gn:name":"Kerabari",
    "gn:population":0,
    "gn:timezone":"Asia/Kathmandu",
    "iso:country":"NP",
    "wof:name":"Kerabari",
    "wof:placetype":"locality"
},
  "geometry": {"coordinates":[87.74741,27.06317],"type":"Point"}
}