{
  "type": "Feature",
  "properties": {
    "gn:admin1_code":"CR",
    "gn:admin2_code":"1",
    "gn:admin3_code":"30.0",
    "gn:admin4_code":"300011.0",
    "gn:asciiname":"Mathillo Dhusa",
    "gn:country_code":"NP",
    "gn:dem":593,
    "gn:feature_class":"P",
    "gn:feature_code":"PPLL",
    "gn:name":"Mathillo Dhusa",
    "gn:population":0,
    "gn:timezone":"Asia/Kathmandu",
    "iso:country":"NP",
    "wof:name":"Mathillo Dhusa",
    "wof:placetype":"locality"
},
  "geometry": {"coordinates":[84.75963,27.78216],"type":"Point"}
}