{
  "type": "Feature",
  "properties": {
    "gn:admin1_code":"WR",
    "gn:admin2_code":"3",
    "gn:admin3_code":"43",
    "gn:admin4_code":"430011.0",
    "gn:asciiname":"Chharchhare",
    "gn:country_code":"NP",
    "gn:dem":1320,
    "gn:feature_class":"P",
    "gn:feature_code":"PPLL",
    "gn:name":"Chharchhare",
    "gn:population":0,
    "gn:timezone":"Asia/Kathmandu",
    "iso:country":"NP",
    "wof:name":"Chharchhare",
    "wof:placetype":"locality"
},
  "geometry": {"coordinates":[83.39383000000002,28.41123],"type":"Point"}
}