{
  "type": "Feature",
  "properties": {
    "gn:admin1_code":"WR",
    "gn:admin2_code":"4.0",
    "gn:admin3_code":"39.0",
    "gn:admin4_code":"390012.0",
    "gn:asciiname":"Bartun",
    "gn:country_code":"NP",
    "gn:dem":1040,
    "gn:feature_class":"P",
    "gn:feature_code":"PPLL",
    "gn:name":"Bartun",
    "gn:population":0,
    "gn:timezone":"Asia/Kathmandu",
    "iso:country":"NP",
    "wof:name":"Bartun",
    "wof:placetype":"locality"
},
  "geometry": {"coordinates":[83.48496,27.93727],"type":"Point"}
}