{
  "type": "Feature",
  "properties": {
    "gn:admin1_code":"FR",
    "gn:admin2_code":"9",
    "gn:admin3_code":"74",
    "gn:admin4_code":"740009",
    "gn:asciiname":"Khand",
    "gn:country_code":"NP",
    "gn:dem":1768,
    "gn:feature_class":"P",
    "gn:feature_code":"PPLL",
    "gn:name":"Khand",
    "gn:population":0,
    "gn:timezone":"Asia/Kathmandu",
    "iso:country":"NP",
    "name:fra_x_preferred":[
        "Khand"
    ],
    "name:nld_x_preferred":[
        "Khand"
    ],
    "wof:name":"Khand",
    "wof:placetype":"locality"
},
  "geometry": {"coordinates":[80.77794,29.49235],"type":"Point"}
}