{
  "type": "Feature",
  "properties": {
    "gn:admin1_code":"00",
    "gn:asciiname":"Olang",
    "gn:country_code":"NP",
    "gn:dem":1522,
    "gn:feature_class":"P",
    "gn:feature_code":"PPL",
    "gn:name":"Ol\u0101ng",
    "gn:population":0,
    "gn:timezone":"Asia/Kathmandu",
    "iso:country":"NP",
    "name:azb_x_preferred":[
        "\u0627\u0648\u0644\u0627\u0646\u0642"
    ],
    "name:bar_x_preferred":[
        "Oaling"
    ],
    "name:bel_x_preferred":[
        "\u0412\u0430\u043b\u044c\u0434\u0430\u043e\u0440\u0430"
    ],
    "name:bul_x_preferred":[
        "\u0412\u0430\u043b\u0434\u0430\u043e\u0440\u0430"
    ],
    "name:cat_x_preferred":[
        "Olang"
    ],
    "name:ceb_x_preferred":[
        "Valdaora"
    ],
    "name:deu_x_preferred":[
        "Olang"
    ],
    "name:ell_x_preferred":[
        "\u0392\u03b1\u03bb\u03bd\u03c4\u03b1\u03cc\u03c1\u03b1"
    ],
    "name:epo_x_preferred":[
        "Olang"
    ],
    "name:est_x_preferred":[
        "Olang"
    ],
    "name:eus_x_preferred":[
        "Olang"
    ],
    "name:fas_x_preferred":[
        "\u0627\u0648\u0644\u0627\u0646\u06af"
    ],
    "name:fra_x_preferred":[
        "Valdaora"
    ],
    "name:hun_x_preferred":[
        "Valdaora"
    ],
    "name:hye_x_preferred":[
        "\u054e\u0561\u056c\u0564\u0561\u0578\u0580\u0561"
    ],
    "name:ina_x_preferred":[
        "Valdaora"
    ],
    "name:ita_x_preferred":[
        "Valdaora"
    ],
    "name:jpn_x_preferred":[
        "\u30f4\u30a1\u30eb\u30c0\u30fc\u30aa\u30e9"
    ],
    "name:kaz_x_preferred":[
        "\u0412\u0430\u043b\u044c\u0434\u0430\u043e\u0440\u0430"
    ],
    "name:lat_x_preferred":[
        "Olaga"
    ],
    "name:lmo_x_preferred":[
        "Valdaora"
    ],
    "name:msa_x_preferred":[
        "Olang"
    ],
    "name:nap_x_preferred":[
        "Valdaora"
    ],
    "name:nld_x_preferred":[
        "Olang"
    ],
    "name:pms_x_preferred":[
        "Olang"
    ],
    "name:pol_x_preferred":[
        "Olang"
    ],
    "name:por_x_preferred":[
        "Valdaora"
    ],
    "name:ron_x_preferred":[
        "Valdaora"
    ],
    "name:rus_x_preferred":[
        "\u0412\u0430\u043b\u044c\u0434\u0430\u043e\u0440\u0430"
    ],
    "name:scn_x_preferred":[
        "Valdaora"
    ],
    "name:spa_x_preferred":[
        "Valdaora"
    ],
    "name:srp_x_preferred":[
        "\u0412\u0430\u043b\u0434\u0430\u043e\u0440\u0430"
    ],
    "name:tgl_x_preferred":[
        "Olang"
    ],
    "name:ukr_x_preferred":[
        "\u0412\u0430\u043b\u044c\u0434\u0430\u043e\u0440\u0430"
    ],
    "name:uzb_x_preferred":[
        "Olang"
    ],
    "name:vie_x_preferred":[
        "Valdaora"
    ],
    "name:vol_x_preferred":[
        "Valdaora"
    ],
    "name:war_x_preferred":[
        "Olang"
    ],
    "name:zho_x_preferred":[
        "\u74e6\u5c14\u9053\u62c9"
    ],
    "wof:name":"Olang",
    "wof:placetype":"locality"
},
  "geometry": {"coordinates":[84.63448000000002,28.231],"type":"Point"}
}