{
  "type": "Feature",
  "properties": {
    "gn:admin1_code":"00",
    "gn:asciiname":"Olang",
    "gn:country_code":"NP",
    "gn:dem":1522,
    "gn:feature_class":"P",
    "gn:feature_code":"PPL",
    "gn:name":"Ol\u0101ng",
    "gn:population":0,
    "gn:timezone":"Asia/Kathmandu",
    "iso:country":"NP",
    "wof:name":"Olang",
    "wof:placetype":"locality"
},
  "geometry": {"coordinates":[84.63448000000002,28.231],"type":"Point"}
}