{
  "type": "Feature",
  "properties": {
    "gn:admin1_code":"MR",
    "gn:admin2_code":"2.0",
    "gn:admin3_code":"59.0",
    "gn:admin4_code":"590048.0",
    "gn:asciiname":"Bankuna",
    "gn:country_code":"NP",
    "gn:dem":826,
    "gn:feature_class":"P",
    "gn:feature_code":"PPLL",
    "gn:name":"Bankuna",
    "gn:population":0,
    "gn:timezone":"Asia/Kathmandu",
    "iso:country":"NP",
    "wof:name":"Bankuna",
    "wof:placetype":"locality"
},
  "geometry": {"coordinates":[81.67849,28.61833],"type":"Point"}
}