{
  "type": "Feature",
  "properties": {
    "gn:admin1_code":"CR",
    "gn:admin2_code":"1",
    "gn:admin3_code":"23",
    "gn:admin4_code":"230051",
    "gn:asciiname":"Dadeti",
    "gn:country_code":"NP",
    "gn:dem":1064,
    "gn:feature_class":"P",
    "gn:feature_code":"PPLL",
    "gn:name":"Dadeti",
    "gn:population":0,
    "gn:timezone":"Asia/Kathmandu",
    "iso:country":"NP",
    "wof:name":"Dadeti",
    "wof:placetype":"locality"
},
  "geometry": {"coordinates":[85.8601,27.74782],"type":"Point"}
}