{
  "type": "Feature",
  "properties": {
    "gn:admin1_code":"WR",
    "gn:admin2_code":"3",
    "gn:admin3_code":"45.0",
    "gn:admin4_code":"450010.0",
    "gn:asciiname":"Kumaldanda",
    "gn:country_code":"NP",
    "gn:dem":1093,
    "gn:feature_class":"P",
    "gn:feature_code":"PPLL",
    "gn:name":"Kumaldanda",
    "gn:population":0,
    "gn:timezone":"Asia/Kathmandu",
    "iso:country":"NP",
    "wof:name":"Kumaldanda",
    "wof:placetype":"locality"
},
  "geometry": {"coordinates":[83.57344999999999,28.25961],"type":"Point"}
}