{
  "type": "Feature",
  "properties": {
    "gn:admin1_code":"WR",
    "gn:admin2_code":"4.0",
    "gn:admin3_code":"39.0",
    "gn:admin4_code":"390057.0",
    "gn:asciiname":"Barhabise",
    "gn:country_code":"NP",
    "gn:dem":872,
    "gn:feature_class":"P",
    "gn:feature_code":"PPLL",
    "gn:name":"Barhabise",
    "gn:population":0,
    "gn:timezone":"Asia/Kathmandu",
    "iso:country":"NP",
    "name:pol_x_preferred":[
        "Barhabise"
    ],
    "wof:name":"Barhabise",
    "wof:placetype":"locality"
},
  "geometry": {"coordinates":[83.71233000000002,27.98283],"type":"Point"}
}