{
  "type": "Feature",
  "properties": {
    "gn:admin1_code":"FR",
    "gn:admin2_code":"14",
    "gn:admin3_code":"69",
    "gn:admin4_code":"690004",
    "gn:asciiname":"Malkatte",
    "gn:country_code":"NP",
    "gn:dem":1819,
    "gn:feature_class":"P",
    "gn:feature_code":"PPLL",
    "gn:name":"Malkatte",
    "gn:population":0,
    "gn:timezone":"Asia/Kathmandu",
    "iso:country":"NP",
    "wof:name":"Malkatte",
    "wof:placetype":"locality"
},
  "geometry": {"coordinates":[81.30549999999999,29.20154],"type":"Point"}
}