{
  "type": "Feature",
  "properties": {
    "gn:admin1_code":"WR",
    "gn:admin2_code":"3",
    "gn:admin3_code":"45.0",
    "gn:admin4_code":"450019.0",
    "gn:asciiname":"Baulung",
    "gn:country_code":"NP",
    "gn:dem":1825,
    "gn:feature_class":"P",
    "gn:feature_code":"PPLL",
    "gn:name":"Baulung",
    "gn:population":0,
    "gn:timezone":"Asia/Kathmandu",
    "iso:country":"NP",
    "wof:name":"Baulung",
    "wof:placetype":"locality"
},
  "geometry": {"coordinates":[83.57053000000001,28.29506],"type":"Point"}
}