{
  "type": "Feature",
  "properties": {
    "gn:admin1_code":"FR",
    "gn:admin2_code":"14",
    "gn:admin3_code":"69.0",
    "gn:admin4_code":"690002.0",
    "gn:asciiname":"Dandasugada",
    "gn:country_code":"NP",
    "gn:dem":783,
    "gn:feature_class":"P",
    "gn:feature_code":"PPLL",
    "gn:name":"Dandasugada",
    "gn:population":0,
    "gn:timezone":"Asia/Kathmandu",
    "iso:country":"NP",
    "wof:name":"Dandasugada",
    "wof:placetype":"locality"
},
  "geometry": {"coordinates":[81.19261999999998,29.19786],"type":"Point"}
}