{
  "type": "Feature",
  "properties": {
    "gn:admin1_code":"ER",
    "gn:admin2_code":"7",
    "gn:admin3_code":"7.0",
    "gn:admin4_code":"70026.0",
    "gn:asciiname":"Maunabudhuk",
    "gn:country_code":"NP",
    "gn:dem":1393,
    "gn:feature_class":"P",
    "gn:feature_code":"PPLL",
    "gn:name":"Maunabudhuk",
    "gn:population":0,
    "gn:timezone":"Asia/Kathmandu",
    "iso:country":"NP",
    "wof:name":"Maunabudhuk",
    "wof:placetype":"locality"
},
  "geometry": {"coordinates":[87.44362,26.90928],"type":"Point"}
}