{
  "type": "Feature",
  "properties": {
    "gn:admin1_code":"00",
    "gn:asciiname":"Phorse",
    "gn:country_code":"NP",
    "gn:dem":976,
    "gn:feature_class":"P",
    "gn:feature_code":"PPL",
    "gn:name":"Phorse",
    "gn:population":0,
    "gn:timezone":"Asia/Kathmandu",
    "iso:country":"NP",
    "wof:name":"Phorse",
    "wof:placetype":"locality"
},
  "geometry": {"coordinates":[86.03498,27.43045],"type":"Point"}
}