{
  "type": "Feature",
  "properties": {
    "gn:admin1_code":"WR",
    "gn:admin2_code":"4",
    "gn:admin3_code":"40.0",
    "gn:admin4_code":"400016.0",
    "gn:asciiname":"Baralthar",
    "gn:country_code":"NP",
    "gn:dem":1133,
    "gn:feature_class":"P",
    "gn:feature_code":"PPLL",
    "gn:name":"Baralthar",
    "gn:population":0,
    "gn:timezone":"Asia/Kathmandu",
    "iso:country":"NP",
    "wof:name":"Baralthar",
    "wof:placetype":"locality"
},
  "geometry": {"coordinates":[84.01456999999998,28.2298],"type":"Point"}
}