{
  "type": "Feature",
  "properties": {
    "gn:admin1_code":"ER",
    "gn:admin2_code":"13",
    "gn:admin3_code":"13.0",
    "gn:admin4_code":"130005.0",
    "gn:asciiname":"Chuwabot",
    "gn:country_code":"NP",
    "gn:dem":641,
    "gn:feature_class":"P",
    "gn:feature_code":"PPLL",
    "gn:name":"Chuwabot",
    "gn:population":0,
    "gn:timezone":"Asia/Kathmandu",
    "iso:country":"NP",
    "wof:name":"Chuwabot",
    "wof:placetype":"locality"
},
  "geometry": {"coordinates":[86.45517,27.1607],"type":"Point"}
}