{
  "type": "Feature",
  "properties": {
    "gn:admin1_code":"CR",
    "gn:admin2_code":"5",
    "gn:admin3_code":"17.0",
    "gn:admin4_code":"170040.0",
    "gn:asciiname":"Harsar",
    "gn:country_code":"NP",
    "gn:dem":108,
    "gn:feature_class":"P",
    "gn:feature_code":"PPLL",
    "gn:name":"Harsar",
    "gn:population":0,
    "gn:timezone":"Asia/Kathmandu",
    "iso:country":"NP",
    "wof:name":"Harsar",
    "wof:placetype":"locality"
},
  "geometry": {"coordinates":[85.97859,26.82667],"type":"Point"}
}