{
  "type": "Feature",
  "properties": {
    "gn:admin1_code":"CR",
    "gn:admin2_code":"11",
    "gn:admin3_code":"34",
    "gn:admin4_code":"340021.0",
    "gn:asciiname":"Bhediyahi",
    "gn:country_code":"NP",
    "gn:dem":108,
    "gn:feature_class":"P",
    "gn:feature_code":"PPLL",
    "gn:name":"Bhediyahi",
    "gn:population":0,
    "gn:timezone":"Asia/Kathmandu",
    "iso:country":"NP",
    "name:ceb_x_preferred":[
        "Bhediyahi"
    ],
    "name:msa_x_preferred":[
        "Bhediyahi"
    ],
    "name:pol_x_preferred":[
        "Bhediyahi"
    ],
    "wof:name":"Bhediyahi",
    "wof:placetype":"locality"
},
  "geometry": {"coordinates":[84.92664000000001,27.12579],"type":"Point"}
}