{
  "type": "Feature",
  "properties": {
    "gn:admin1_code":"FR",
    "gn:admin2_code":"14",
    "gn:admin3_code":"71.0",
    "gn:admin4_code":"710024.0",
    "gn:asciiname":"Aitha",
    "gn:country_code":"NP",
    "gn:dem":175,
    "gn:feature_class":"P",
    "gn:feature_code":"PPLL",
    "gn:name":"Aitha",
    "gn:population":0,
    "gn:timezone":"Asia/Kathmandu",
    "iso:country":"NP",
    "name:urd_x_preferred":[
        "\u0627\u06cc\u0679\u06be\u0627"
    ],
    "wof:name":"Aitha",
    "wof:placetype":"locality"
},
  "geometry": {"coordinates":[80.84045999999999,28.69945],"type":"Point"}
}