{
  "type": "Feature",
  "properties": {
    "gn:admin1_code":"FR",
    "gn:admin2_code":"9",
    "gn:admin3_code":"75.0",
    "gn:admin4_code":"750022.0",
    "gn:asciiname":"Jaijhul",
    "gn:country_code":"NP",
    "gn:dem":1143,
    "gn:feature_class":"P",
    "gn:feature_code":"PPLL",
    "gn:name":"Jaijhul",
    "gn:population":0,
    "gn:timezone":"Asia/Kathmandu",
    "iso:country":"NP",
    "wof:name":"Jaijhul",
    "wof:placetype":"locality"
},
  "geometry": {"coordinates":[80.56073000000001,29.83958],"type":"Point"}
}