{
  "type": "Feature",
  "properties": {
    "gn:admin1_code":"MR",
    "gn:admin2_code":"12",
    "gn:admin3_code":"56.0",
    "gn:admin4_code":"560024.0",
    "gn:asciiname":"Kalitara",
    "gn:country_code":"NP",
    "gn:dem":528,
    "gn:feature_class":"P",
    "gn:feature_code":"PPLL",
    "gn:name":"Kalitara",
    "gn:population":0,
    "gn:timezone":"Asia/Kathmandu",
    "iso:country":"NP",
    "wof:name":"Kalitara",
    "wof:placetype":"locality"
},
  "geometry": {"coordinates":[82.11026,28.15275],"type":"Point"}
}