{
  "type": "Feature",
  "properties": {
    "gn:admin1_code":"WR",
    "gn:admin2_code":"4",
    "gn:admin3_code":"40.0",
    "gn:admin4_code":"400013.0",
    "gn:asciiname":"Komrongdanda",
    "gn:country_code":"NP",
    "gn:dem":2589,
    "gn:feature_class":"P",
    "gn:feature_code":"PPLL",
    "gn:name":"Komrongdanda",
    "gn:population":0,
    "gn:timezone":"Asia/Kathmandu",
    "iso:country":"NP",
    "wof:name":"Komrongdanda",
    "wof:placetype":"locality"
},
  "geometry": {"coordinates":[83.78605999999998,28.38819],"type":"Point"}
}