{
  "type": "Feature",
  "properties": {
    "gn:admin1_code":"ER",
    "gn:admin2_code":"13",
    "gn:admin3_code":"12",
    "gn:admin4_code":"120014",
    "gn:asciiname":"Phulbari",
    "gn:country_code":"NP",
    "gn:dem":1486,
    "gn:feature_class":"P",
    "gn:feature_code":"PPLL",
    "gn:name":"Phulbari",
    "gn:population":0,
    "gn:timezone":"Asia/Kathmandu",
    "iso:country":"NP",
    "wof:name":"Phulbari",
    "wof:placetype":"locality"
},
  "geometry": {"coordinates":[86.31901999999999,27.32437],"type":"Point"}
}