{
  "type": "Feature",
  "properties": {
    "gn:admin1_code":"FR",
    "gn:admin2_code":"14",
    "gn:admin3_code":"70.0",
    "gn:admin4_code":"700032.0",
    "gn:asciiname":"Gairegada",
    "gn:country_code":"NP",
    "gn:dem":1477,
    "gn:feature_class":"P",
    "gn:feature_code":"PPLL",
    "gn:name":"Gairegada",
    "gn:population":0,
    "gn:timezone":"Asia/Kathmandu",
    "iso:country":"NP",
    "wof:name":"Gairegada",
    "wof:placetype":"locality"
},
  "geometry": {"coordinates":[80.92873,29.04348],"type":"Point"}
}