{
  "type": "Feature",
  "properties": {
    "gn:admin1_code":"ER",
    "gn:admin2_code":"10",
    "gn:admin3_code":"3.0",
    "gn:admin4_code":"30002.0",
    "gn:asciiname":"Phuike",
    "gn:country_code":"NP",
    "gn:dem":348,
    "gn:feature_class":"P",
    "gn:feature_code":"PPLL",
    "gn:name":"Phuike",
    "gn:population":0,
    "gn:timezone":"Asia/Kathmandu",
    "iso:country":"NP",
    "wof:name":"Phuike",
    "wof:placetype":"locality"
},
  "geometry": {"coordinates":[87.69896999999997,26.76026],"type":"Point"}
}