{
  "type": "Feature",
  "properties": {
    "gn:admin1_code":"MR",
    "gn:admin2_code":"6",
    "gn:admin3_code":"65",
    "gn:admin4_code":"650011",
    "gn:asciiname":"Humla Patan",
    "gn:country_code":"NP",
    "gn:dem":5353,
    "gn:feature_class":"P",
    "gn:feature_code":"PPLL",
    "gn:name":"Humla Patan",
    "gn:population":0,
    "gn:timezone":"Asia/Kathmandu",
    "iso:country":"NP",
    "wof:name":"Humla Patan",
    "wof:placetype":"locality"
},
  "geometry": {"coordinates":[82.50098,29.94493],"type":"Point"}
}