{
  "type": "Feature",
  "properties": {
    "gn:admin1_code":"WR",
    "gn:admin2_code":"3",
    "gn:admin3_code":"44",
    "gn:admin4_code":"440050",
    "gn:asciiname":"Birabari",
    "gn:country_code":"NP",
    "gn:dem":1196,
    "gn:feature_class":"P",
    "gn:feature_code":"PPLL",
    "gn:name":"Birabari",
    "gn:population":0,
    "gn:timezone":"Asia/Kathmandu",
    "iso:country":"NP",
    "wof:name":"Birabari",
    "wof:placetype":"locality"
},
  "geometry": {"coordinates":[83.68855000000001,28.15489],"type":"Point"}
}