{
  "type": "Feature",
  "properties": {
    "gn:admin1_code":"MR",
    "gn:admin2_code":"12",
    "gn:admin3_code":"56.0",
    "gn:admin4_code":"560010.0",
    "gn:asciiname":"Ghusukpurw",
    "gn:country_code":"NP",
    "gn:dem":279,
    "gn:feature_class":"P",
    "gn:feature_code":"PPLL",
    "gn:name":"Ghusukpurw",
    "gn:population":0,
    "gn:timezone":"Asia/Kathmandu",
    "iso:country":"NP",
    "wof:name":"Ghusukpurw",
    "wof:placetype":"locality"
},
  "geometry": {"coordinates":[82.59829000000001,27.80435],"type":"Point"}
}