{
  "type": "Feature",
  "properties": {
    "gn:admin1_code":"WR",
    "gn:admin2_code":"3",
    "gn:admin3_code":"43",
    "gn:admin4_code":"430024",
    "gn:asciiname":"Khar",
    "gn:country_code":"NP",
    "gn:dem":1521,
    "gn:feature_class":"P",
    "gn:feature_code":"PPLL",
    "gn:name":"Khar",
    "gn:population":0,
    "gn:timezone":"Asia/Kathmandu",
    "iso:country":"NP",
    "name:ceb_x_preferred":[
        "Khar"
    ],
    "name:deu_x_preferred":[
        "Khar"
    ],
    "name:swe_x_preferred":[
        "Khar"
    ],
    "wof:name":"Khar",
    "wof:placetype":"locality"
},
  "geometry": {"coordinates":[83.35868000000001,28.49683],"type":"Point"}
}