{
  "type": "Feature",
  "properties": {
    "gn:admin1_code":"CR",
    "gn:admin2_code":"5",
    "gn:admin3_code":"21",
    "gn:admin4_code":"210011",
    "gn:asciiname":"Jhankritol",
    "gn:country_code":"NP",
    "gn:dem":1975,
    "gn:feature_class":"P",
    "gn:feature_code":"PPLL",
    "gn:name":"Jhankritol",
    "gn:population":0,
    "gn:timezone":"Asia/Kathmandu",
    "iso:country":"NP",
    "wof:name":"Jhankritol",
    "wof:placetype":"locality"
},
  "geometry": {"coordinates":[86.31314999999999,27.6221],"type":"Point"}
}