{
  "type": "Feature",
  "properties": {
    "gn:admin1_code":"FR",
    "gn:admin2_code":"9",
    "gn:admin3_code":"73.0",
    "gn:admin4_code":"730015.0",
    "gn:asciiname":"Sunkot",
    "gn:country_code":"NP",
    "gn:dem":1276,
    "gn:feature_class":"P",
    "gn:feature_code":"PPLL",
    "gn:name":"Sunkot",
    "gn:population":0,
    "gn:timezone":"Asia/Kathmandu",
    "iso:country":"NP",
    "wof:name":"Sunkot",
    "wof:placetype":"locality"
},
  "geometry": {"coordinates":[80.64882,29.32383],"type":"Point"}
}