{
  "type": "Feature",
  "properties": {
    "gn:admin1_code":"WR",
    "gn:admin2_code":"3",
    "gn:admin3_code":"45.0",
    "gn:admin4_code":"450048.0",
    "gn:asciiname":"Rayadanda",
    "gn:country_code":"NP",
    "gn:dem":1719,
    "gn:feature_class":"P",
    "gn:feature_code":"PPLL",
    "gn:name":"Rayadanda",
    "gn:population":0,
    "gn:timezone":"Asia/Kathmandu",
    "iso:country":"NP",
    "name:ceb_x_preferred":[
        "Rayadanda"
    ],
    "name:fra_x_preferred":[
        "Rayadanda"
    ],
    "name:nep_x_preferred":[
        "\u0930\u093e\u092f\u0921\u093e\u0901\u0921\u093e"
    ],
    "name:new_x_preferred":[
        "\u0930\u093e\u092f\u0921\u0902\u0921\u093e"
    ],
    "name:pol_x_preferred":[
        "Rayadada"
    ],
    "wof:name":"Rayadanda",
    "wof:placetype":"locality"
},
  "geometry": {"coordinates":[83.57661,28.2177],"type":"Point"}
}