{
  "type": "Feature",
  "properties": {
    "gn:admin1_code":"CR",
    "gn:admin2_code":"5",
    "gn:admin3_code":"20",
    "gn:admin4_code":"200008",
    "gn:asciiname":"Siundheni",
    "gn:country_code":"NP",
    "gn:dem":943,
    "gn:feature_class":"P",
    "gn:feature_code":"PPLL",
    "gn:name":"Siundheni",
    "gn:population":0,
    "gn:timezone":"Asia/Kathmandu",
    "iso:country":"NP",
    "wof:name":"Siundheni",
    "wof:placetype":"locality"
},
  "geometry": {"coordinates":[85.95291999999998,27.26359],"type":"Point"}
}