{
  "type": "Feature",
  "properties": {
    "gn:admin1_code":"ER",
    "gn:admin2_code":"10.0",
    "gn:admin3_code":"1.0",
    "gn:admin4_code":"10046.0",
    "gn:asciiname":"Yakteli",
    "gn:country_code":"NP",
    "gn:dem":1879,
    "gn:feature_class":"P",
    "gn:feature_code":"PPLL",
    "gn:name":"Yakteli",
    "gn:population":0,
    "gn:timezone":"Asia/Kathmandu",
    "iso:country":"NP",
    "wof:name":"Yakteli",
    "wof:placetype":"locality"
},
  "geometry": {"coordinates":[87.56296999999998,27.39331],"type":"Point"}
}