{
  "type": "Feature",
  "properties": {
    "gn:admin1_code":"WR",
    "gn:admin2_code":"4",
    "gn:admin3_code":"36.0",
    "gn:admin4_code":"360035.0",
    "gn:asciiname":"Kharibot",
    "gn:country_code":"NP",
    "gn:dem":1398,
    "gn:feature_class":"P",
    "gn:feature_code":"PPLL",
    "gn:name":"Kharibot",
    "gn:population":0,
    "gn:timezone":"Asia/Kathmandu",
    "iso:country":"NP",
    "name:ceb_x_preferred":[
        "Kharibot"
    ],
    "name:mai_x_preferred":[
        "\u0916\u0930\u093f\u092c\u094b\u091f"
    ],
    "name:msa_x_preferred":[
        "Kharibot"
    ],
    "name:nep_x_preferred":[
        "\u0916\u0930\u093f\u092c\u094b\u091f"
    ],
    "name:new_x_preferred":[
        "\u0916\u0930\u0940\u092c\u094b\u091f"
    ],
    "name:pol_x_preferred":[
        "Kharibot"
    ],
    "wof:name":"Kharibot",
    "wof:placetype":"locality"
},
  "geometry": {"coordinates":[84.64898000000002,28.19884],"type":"Point"}
}