{
  "type": "Feature",
  "properties": {
    "gn:admin1_code":"CR",
    "gn:admin2_code":"1",
    "gn:admin3_code":"28",
    "gn:admin4_code":"280039",
    "gn:asciiname":"Syaule",
    "gn:country_code":"NP",
    "gn:dem":1718,
    "gn:feature_class":"P",
    "gn:feature_code":"PPLL",
    "gn:name":"Syaule",
    "gn:population":0,
    "gn:timezone":"Asia/Kathmandu",
    "iso:country":"NP",
    "wof:name":"Syaule",
    "wof:placetype":"locality"
},
  "geometry": {"coordinates":[85.34245,27.88705],"type":"Point"}
}