{
  "type": "Feature",
  "properties": {
    "gn:admin1_code":"CR",
    "gn:admin2_code":"5",
    "gn:admin3_code":"20",
    "gn:admin4_code":"200038",
    "gn:asciiname":"Tallo Khuttepani",
    "gn:country_code":"NP",
    "gn:dem":267,
    "gn:feature_class":"P",
    "gn:feature_code":"PPLL",
    "gn:name":"Tallo Khuttepani",
    "gn:population":0,
    "gn:timezone":"Asia/Kathmandu",
    "iso:country":"NP",
    "wof:name":"Tallo Khuttepani",
    "wof:placetype":"locality"
},
  "geometry": {"coordinates":[86.10055,27.02806],"type":"Point"}
}