{
  "type": "Feature",
  "properties": {
    "gn:admin1_code":"WR",
    "gn:admin2_code":"4.0",
    "gn:admin3_code":"39.0",
    "gn:admin4_code":"390025.0",
    "gn:asciiname":"Kabhre",
    "gn:country_code":"NP",
    "gn:dem":1385,
    "gn:feature_class":"P",
    "gn:feature_code":"PPLL",
    "gn:name":"Kabhre",
    "gn:population":0,
    "gn:timezone":"Asia/Kathmandu",
    "iso:country":"NP",
    "name:new_x_preferred":[
        "\u0915\u093e\u092c\u094d\u0930\u0947"
    ],
    "wof:name":"Kabhre",
    "wof:placetype":"locality"
},
  "geometry": {"coordinates":[83.70981,28.03382],"type":"Point"}
}