{
  "type": "Feature",
  "properties": {
    "gn:admin1_code":"ER",
    "gn:admin2_code":"7",
    "gn:admin3_code":"5",
    "gn:admin4_code":"50046",
    "gn:asciiname":"Ratmate",
    "gn:country_code":"NP",
    "gn:dem":1091,
    "gn:feature_class":"P",
    "gn:feature_code":"PPLL",
    "gn:name":"Ratmate",
    "gn:population":0,
    "gn:timezone":"Asia/Kathmandu",
    "iso:country":"NP",
    "wof:name":"Ratmate",
    "wof:placetype":"locality"
},
  "geometry": {"coordinates":[87.42180999999999,26.83457000000001],"type":"Point"}
}