{
  "type": "Feature",
  "properties": {
    "gn:admin1_code":"WR",
    "gn:admin2_code":"4",
    "gn:admin3_code":"37",
    "gn:admin4_code":"370027",
    "gn:asciiname":"Dhadgaun",
    "gn:country_code":"NP",
    "gn:dem":738,
    "gn:feature_class":"P",
    "gn:feature_code":"PPLL",
    "gn:name":"Dhadgaun",
    "gn:population":0,
    "gn:timezone":"Asia/Kathmandu",
    "iso:country":"NP",
    "wof:name":"Dhadgaun",
    "wof:placetype":"locality"
},
  "geometry": {"coordinates":[84.39753,28.19697],"type":"Point"}
}