{
  "type": "Feature",
  "properties": {
    "gn:admin1_code":"WR",
    "gn:admin2_code":"8",
    "gn:admin3_code":"46.0",
    "gn:admin4_code":"460044.0",
    "gn:asciiname":"Harpukotgaun",
    "gn:country_code":"NP",
    "gn:dem":1170,
    "gn:feature_class":"P",
    "gn:feature_code":"PPLL",
    "gn:name":"Harpukotgaun",
    "gn:population":0,
    "gn:timezone":"Asia/Kathmandu",
    "iso:country":"NP",
    "wof:name":"Harpukotgaun",
    "wof:placetype":"locality"
},
  "geometry": {"coordinates":[83.24150999999998,28.14927],"type":"Point"}
}