{
  "type": "Feature",
  "properties": {
    "gn:admin1_code":"WR",
    "gn:admin2_code":"4.0",
    "gn:admin3_code":"39.0",
    "gn:admin4_code":"390046.0",
    "gn:asciiname":"Sirindanda",
    "gn:country_code":"NP",
    "gn:dem":1114,
    "gn:feature_class":"P",
    "gn:feature_code":"PPLL",
    "gn:name":"Sirindanda",
    "gn:population":0,
    "gn:timezone":"Asia/Kathmandu",
    "iso:country":"NP",
    "wof:name":"Sirindanda",
    "wof:placetype":"locality"
},
  "geometry": {"coordinates":[83.76604,28.10998],"type":"Point"}
}