{
  "type": "Feature",
  "properties": {
    "gn:admin1_code":"ER",
    "gn:admin2_code":"10",
    "gn:admin3_code":"4.0",
    "gn:admin4_code":"40044.0",
    "gn:asciiname":"Dudhe Kaijale",
    "gn:country_code":"NP",
    "gn:dem":153,
    "gn:feature_class":"P",
    "gn:feature_code":"PPLL",
    "gn:name":"Dudhe Kaijale",
    "gn:population":0,
    "gn:timezone":"Asia/Kathmandu",
    "iso:country":"NP",
    "wof:name":"Dudhe Kaijale",
    "wof:placetype":"locality"
},
  "geometry": {"coordinates":[87.82974,26.65627000000001],"type":"Point"}
}