{
  "type": "Feature",
  "properties": {
    "gn:admin1_code":"FR",
    "gn:admin2_code":"14",
    "gn:admin3_code":"70.0",
    "gn:admin4_code":"700022.0",
    "gn:asciiname":"Budakot",
    "gn:country_code":"NP",
    "gn:dem":1622,
    "gn:feature_class":"P",
    "gn:feature_code":"PPLL",
    "gn:name":"Budakot",
    "gn:population":0,
    "gn:timezone":"Asia/Kathmandu",
    "iso:country":"NP",
    "wof:name":"Budakot",
    "wof:placetype":"locality"
},
  "geometry": {"coordinates":[81.10573000000002,29.29278],"type":"Point"}
}