{
  "type": "Feature",
  "properties": {
    "gn:admin1_code":"MR",
    "gn:admin2_code":"12",
    "gn:admin3_code":"52",
    "gn:admin4_code":"520003",
    "gn:asciiname":"Kharkholagaun",
    "gn:country_code":"NP",
    "gn:dem":361,
    "gn:feature_class":"P",
    "gn:feature_code":"PPLL",
    "gn:name":"Kharkholagaun",
    "gn:population":0,
    "gn:timezone":"Asia/Kathmandu",
    "iso:country":"NP",
    "wof:name":"Kharkholagaun",
    "wof:placetype":"locality"
},
  "geometry": {"coordinates":[82.80306999999998,27.88455],"type":"Point"}
}