{
  "type": "Feature",
  "properties": {
    "gn:admin1_code":"MR",
    "gn:admin2_code":"6",
    "gn:admin3_code":"63.0",
    "gn:admin4_code":"630027.0",
    "gn:asciiname":"Patikholagaun",
    "gn:country_code":"NP",
    "gn:dem":3225,
    "gn:feature_class":"P",
    "gn:feature_code":"PPLL",
    "gn:name":"Patikholagaun",
    "gn:population":0,
    "gn:timezone":"Asia/Kathmandu",
    "iso:country":"NP",
    "wof:name":"Patikholagaun",
    "wof:placetype":"locality"
},
  "geometry": {"coordinates":[82.06565999999999,29.31826],"type":"Point"}
}