{
  "type": "Feature",
  "properties": {
    "gn:admin1_code":"CR",
    "gn:admin2_code":"5",
    "gn:admin3_code":"22.0",
    "gn:admin4_code":"220003.0",
    "gn:asciiname":"Bhedpu",
    "gn:country_code":"NP",
    "gn:dem":1531,
    "gn:feature_class":"P",
    "gn:feature_code":"PPLL",
    "gn:name":"Bhedpu",
    "gn:population":0,
    "gn:timezone":"Asia/Kathmandu",
    "iso:country":"NP",
    "wof:name":"Bhedpu",
    "wof:placetype":"locality"
},
  "geometry": {"coordinates":[86.05821999999998,27.5331],"type":"Point"}
}