{
  "type": "Feature",
  "properties": {
    "gn:admin1_code":"MR",
    "gn:admin2_code":"12",
    "gn:admin3_code":"53",
    "gn:admin4_code":"530034",
    "gn:asciiname":"Bahunpaun",
    "gn:country_code":"NP",
    "gn:dem":1616,
    "gn:feature_class":"P",
    "gn:feature_code":"PPLL",
    "gn:name":"Bahunpaun",
    "gn:population":0,
    "gn:timezone":"Asia/Kathmandu",
    "iso:country":"NP",
    "wof:name":"Bahunpaun",
    "wof:placetype":"locality"
},
  "geometry": {"coordinates":[82.49235,28.24406],"type":"Point"}
}