{
  "type": "Feature",
  "properties": {
    "gn:admin1_code":"CR",
    "gn:admin2_code":"1",
    "gn:admin3_code":"23",
    "gn:admin4_code":"230077",
    "gn:asciiname":"Dauthe",
    "gn:country_code":"NP",
    "gn:dem":1128,
    "gn:feature_class":"P",
    "gn:feature_code":"PPLL",
    "gn:name":"Dauthe",
    "gn:population":0,
    "gn:timezone":"Asia/Kathmandu",
    "iso:country":"NP",
    "wof:name":"Dauthe",
    "wof:placetype":"locality"
},
  "geometry": {"coordinates":[85.70038000000002,27.74417],"type":"Point"}
}