{
  "type": "Feature",
  "properties": {
    "gn:admin1_code":"MR",
    "gn:admin2_code":"2.0",
    "gn:admin3_code":"59.0",
    "gn:admin4_code":"590024.0",
    "gn:asciiname":"Maina Pokhari",
    "gn:country_code":"NP",
    "gn:dem":587,
    "gn:feature_class":"P",
    "gn:feature_code":"PPLL",
    "gn:name":"Maina Pokhari",
    "gn:population":0,
    "gn:timezone":"Asia/Kathmandu",
    "iso:country":"NP",
    "wof:name":"Maina Pokhari",
    "wof:placetype":"locality"
},
  "geometry": {"coordinates":[81.71007,28.54903],"type":"Point"}
}