{
  "type": "Feature",
  "properties": {
    "gn:admin1_code":"FR",
    "gn:admin2_code":"14",
    "gn:admin3_code":"68",
    "gn:admin4_code":"680009",
    "gn:asciiname":"Pipalkot",
    "gn:country_code":"NP",
    "gn:dem":990,
    "gn:feature_class":"P",
    "gn:feature_code":"PPLL",
    "gn:name":"Pipalkot",
    "gn:population":0,
    "gn:timezone":"Asia/Kathmandu",
    "iso:country":"NP",
    "name:nep_x_preferred":[
        "\u092a\u093f\u092a\u0932\u0915\u094b\u091f"
    ],
    "name:pol_x_preferred":[
        "Pipalkot"
    ],
    "wof:name":"Pipalkot",
    "wof:placetype":"locality"
},
  "geometry": {"coordinates":[80.91925000000001,29.45053],"type":"Point"}
}