{
  "type": "Feature",
  "properties": {
    "gn:admin1_code":"00",
    "gn:asciiname":"Dansintar",
    "gn:country_code":"NP",
    "gn:dem":1289,
    "gn:feature_class":"P",
    "gn:feature_code":"PPL",
    "gn:name":"D\u0101\u1e45si\u1e45\u1e6d\u0101r",
    "gn:population":0,
    "gn:timezone":"Asia/Kathmandu",
    "iso:country":"NP",
    "wof:name":"Dansintar",
    "wof:placetype":"locality"
},
  "geometry": {"coordinates":[86.13453,27.29403],"type":"Point"}
}