{
  "type": "Feature",
  "properties": {
    "gn:admin1_code":"CR",
    "gn:admin2_code":"1",
    "gn:admin3_code":"30.0",
    "gn:admin4_code":"300033.0",
    "gn:asciiname":"Jysmirewara",
    "gn:country_code":"NP",
    "gn:dem":1040,
    "gn:feature_class":"P",
    "gn:feature_code":"PPLL",
    "gn:name":"Jysmirewara",
    "gn:population":0,
    "gn:timezone":"Asia/Kathmandu",
    "iso:country":"NP",
    "wof:name":"Jysmirewara",
    "wof:placetype":"locality"
},
  "geometry": {"coordinates":[84.82959,27.87477],"type":"Point"}
}