{
  "type": "Feature",
  "properties": {
    "gn:admin1_code":"CR",
    "gn:admin2_code":"11",
    "gn:admin3_code":"34",
    "gn:admin4_code":"340015.0",
    "gn:asciiname":"Bhedihari",
    "gn:country_code":"NP",
    "gn:dem":90,
    "gn:feature_class":"P",
    "gn:feature_code":"PPLL",
    "gn:name":"Bhedihari",
    "gn:population":0,
    "gn:timezone":"Asia/Kathmandu",
    "iso:country":"NP",
    "name:ceb_x_preferred":[
        "Bhedihari"
    ],
    "name:fra_x_preferred":[
        "Bhedihari"
    ],
    "name:mai_x_preferred":[
        "\u092d\u0947\u0921\u093f\u0939\u093e\u0930\u0940"
    ],
    "name:msa_x_preferred":[
        "Bhedihari"
    ],
    "name:nep_x_preferred":[
        "\u092d\u0947\u0921\u093f\u0939\u093e\u0930\u0940"
    ],
    "name:pol_x_preferred":[
        "Bhedihari"
    ],
    "wof:name":"Bhedihari",
    "wof:placetype":"locality"
},
  "geometry": {"coordinates":[84.72349,27.05207],"type":"Point"}
}