{
  "type": "Feature",
  "properties": {
    "gn:admin1_code":"CR",
    "gn:admin2_code":"5",
    "gn:admin3_code":"20",
    "gn:admin4_code":"200020",
    "gn:asciiname":"Sandane",
    "gn:country_code":"NP",
    "gn:dem":916,
    "gn:feature_class":"P",
    "gn:feature_code":"PPLL",
    "gn:name":"Sandane",
    "gn:population":0,
    "gn:timezone":"Asia/Kathmandu",
    "iso:country":"NP",
    "name:ceb_x_preferred":[
        "Sandane"
    ],
    "name:dan_x_preferred":[
        "Sandane"
    ],
    "name:fin_x_preferred":[
        "Sandane"
    ],
    "name:ita_x_preferred":[
        "Sandane"
    ],
    "name:msa_x_preferred":[
        "Sandane"
    ],
    "name:nld_x_preferred":[
        "Sandane"
    ],
    "name:nno_x_preferred":[
        "Sandane"
    ],
    "name:nor_x_preferred":[
        "Sandane"
    ],
    "name:pol_x_preferred":[
        "Sandane"
    ],
    "name:spa_x_preferred":[
        "Sandane"
    ],
    "wof:name":"Sandane",
    "wof:placetype":"locality"
},
  "geometry": {"coordinates":[86.16123,27.14875],"type":"Point"}
}