{
  "type": "Feature",
  "properties": {
    "gn:admin1_code":"00",
    "gn:asciiname":"Bhadure",
    "gn:country_code":"NP",
    "gn:dem":1148,
    "gn:feature_class":"P",
    "gn:feature_code":"PPL",
    "gn:name":"Bhadure",
    "gn:population":0,
    "gn:timezone":"Asia/Kathmandu",
    "iso:country":"NP",
    "wof:name":"Bhadure",
    "wof:placetype":"locality"
},
  "geometry": {"coordinates":[85.23857,27.94431],"type":"Point"}
}