{
  "type": "Feature",
  "properties": {
    "gn:admin1_code":"WR",
    "gn:admin2_code":"4",
    "gn:admin3_code":"36.0",
    "gn:admin4_code":"360056.0",
    "gn:asciiname":"Gumjed",
    "gn:country_code":"NP",
    "gn:dem":1852,
    "gn:feature_class":"P",
    "gn:feature_code":"PPLL",
    "gn:name":"Gumjed",
    "gn:population":0,
    "gn:timezone":"Asia/Kathmandu",
    "iso:country":"NP",
    "wof:name":"Gumjed",
    "wof:placetype":"locality"
},
  "geometry": {"coordinates":[84.899,28.37945],"type":"Point"}
}