{
  "type": "Feature",
  "properties": {
    "gn:admin1_code":"ER",
    "gn:admin2_code":"13",
    "gn:admin3_code":"13.0",
    "gn:admin4_code":"130005.0",
    "gn:asciiname":"Jayaramtar",
    "gn:country_code":"NP",
    "gn:dem":532,
    "gn:feature_class":"P",
    "gn:feature_code":"PPLL",
    "gn:name":"Jayaramtar",
    "gn:population":0,
    "gn:timezone":"Asia/Kathmandu",
    "iso:country":"NP",
    "wof:name":"Jayaramtar",
    "wof:placetype":"locality"
},
  "geometry": {"coordinates":[86.47802,27.17542000000001],"type":"Point"}
}