{
  "type": "Feature",
  "properties": {
    "gn:admin1_code":"CR",
    "gn:admin2_code":"1",
    "gn:admin3_code":"25",
    "gn:admin4_code":"250041.0",
    "gn:asciiname":"Khasroghari",
    "gn:country_code":"NP",
    "gn:dem":1640,
    "gn:feature_class":"P",
    "gn:feature_code":"PPLL",
    "gn:name":"Khasroghari",
    "gn:population":0,
    "gn:timezone":"Asia/Kathmandu",
    "iso:country":"NP",
    "wof:name":"Khasroghari",
    "wof:placetype":"locality"
},
  "geometry": {"coordinates":[85.39046999999999,27.46239000000001],"type":"Point"}
}