{
  "type": "Feature",
  "properties": {
    "gn:admin1_code":"ER",
    "gn:admin2_code":"7",
    "gn:admin3_code":"9",
    "gn:admin4_code":"90003",
    "gn:asciiname":"Salghari",
    "gn:country_code":"NP",
    "gn:dem":709,
    "gn:feature_class":"P",
    "gn:feature_code":"PPLL",
    "gn:name":"Salghari",
    "gn:population":0,
    "gn:timezone":"Asia/Kathmandu",
    "iso:country":"NP",
    "wof:name":"Salghari",
    "wof:placetype":"locality"
},
  "geometry": {"coordinates":[87.08381999999997,27.47969],"type":"Point"}
}