{
  "type": "Feature",
  "properties": {
    "gn:admin1_code":"MR",
    "gn:admin2_code":"6",
    "gn:admin3_code":"64.0",
    "gn:admin4_code":"640014.0",
    "gn:asciiname":"Chilkopade",
    "gn:country_code":"NP",
    "gn:dem":1003,
    "gn:feature_class":"P",
    "gn:feature_code":"PPLL",
    "gn:name":"Chilkopade",
    "gn:population":0,
    "gn:timezone":"Asia/Kathmandu",
    "iso:country":"NP",
    "wof:name":"Chilkopade",
    "wof:placetype":"locality"
},
  "geometry": {"coordinates":[81.5558,29.11733],"type":"Point"}
}