{
  "type": "Feature",
  "properties": {
    "gn:admin1_code":"FR",
    "gn:admin2_code":"14",
    "gn:admin3_code":"70.0",
    "gn:admin4_code":"700051.0",
    "gn:asciiname":"Liudekanda",
    "gn:country_code":"NP",
    "gn:dem":815,
    "gn:feature_class":"P",
    "gn:feature_code":"PPLL",
    "gn:name":"Liudekanda",
    "gn:population":0,
    "gn:timezone":"Asia/Kathmandu",
    "iso:country":"NP",
    "wof:name":"Liudekanda",
    "wof:placetype":"locality"
},
  "geometry": {"coordinates":[80.79178,29.31578],"type":"Point"}
}