{
  "type": "Feature",
  "properties": {
    "gn:admin1_code":"CR",
    "gn:admin2_code":"5",
    "gn:admin3_code":"20",
    "gn:admin4_code":"200046",
    "gn:asciiname":"Kunai",
    "gn:country_code":"NP",
    "gn:dem":385,
    "gn:feature_class":"P",
    "gn:feature_code":"PPLL",
    "gn:name":"Kunai",
    "gn:population":0,
    "gn:timezone":"Asia/Kathmandu",
    "iso:country":"NP",
    "name:cat_x_preferred":[
        "Kunai"
    ],
    "name:deu_x_preferred":[
        "Kunai"
    ],
    "name:epo_x_preferred":[
        "Kunajo"
    ],
    "name:eus_x_preferred":[
        "Kunai"
    ],
    "name:fas_x_preferred":[
        "\u06a9\u0648\u0646\u0627\u06cc"
    ],
    "name:fin_x_preferred":[
        "Kunai"
    ],
    "name:fra_x_preferred":[
        "Kuna\u00ef"
    ],
    "name:hun_x_preferred":[
        "Kunai"
    ],
    "name:ind_x_preferred":[
        "Kunai"
    ],
    "name:ita_x_preferred":[
        "Kunai"
    ],
    "name:jpn_x_preferred":[
        "\u304f\u306a\u3044"
    ],
    "name:kor_x_preferred":[
        "\uad6c\ub098\uc774"
    ],
    "name:lit_x_preferred":[
        "Kunai"
    ],
    "name:pol_x_preferred":[
        "Kunai"
    ],
    "name:por_x_preferred":[
        "Kunai"
    ],
    "name:rus_x_preferred":[
        "\u041a\u0443\u043d\u0430\u0439"
    ],
    "name:spa_x_preferred":[
        "Kunai"
    ],
    "name:swe_x_preferred":[
        "Kunai"
    ],
    "name:tha_x_preferred":[
        "\u0e04\u0e38\u0e19\u0e30\u0e2d\u0e34"
    ],
    "name:tur_x_preferred":[
        "Kunai"
    ],
    "name:ukr_x_preferred":[
        "\u041a\u0443\u043d\u0430\u0439"
    ],
    "name:vie_x_preferred":[
        "Kunai"
    ],
    "wof:name":"Kunai",
    "wof:placetype":"locality"
},
  "geometry": {"coordinates":[86.21550000000001,27.03631],"type":"Point"}
}