{
  "type": "Feature",
  "properties": {
    "gn:admin1_code":"ER",
    "gn:admin2_code":"7",
    "gn:admin3_code":"7.0",
    "gn:admin4_code":"70021.0",
    "gn:asciiname":"Khuwaphok",
    "gn:country_code":"NP",
    "gn:dem":1245,
    "gn:feature_class":"P",
    "gn:feature_code":"PPLL",
    "gn:name":"Khuwaphok",
    "gn:population":0,
    "gn:timezone":"Asia/Kathmandu",
    "iso:country":"NP",
    "name:bih_x_preferred":[
        "\u0916\u0941\u0935\u093e\u092b\u094b\u0915"
    ],
    "name:ceb_x_preferred":[
        "Khuwafok"
    ],
    "name:mai_x_preferred":[
        "\u0916\u0941\u0935\u093e\u092b\u094b\u0915"
    ],
    "name:nep_x_preferred":[
        "\u0916\u0941\u0935\u093e\u092b\u094b\u0915"
    ],
    "name:new_x_preferred":[
        "\u0916\u0941\u0935\u093e\u092b\u094b\u0915"
    ],
    "name:pol_x_preferred":[
        "Khuwafok"
    ],
    "wof:name":"Khuwaphok",
    "wof:placetype":"locality"
},
  "geometry": {"coordinates":[87.38808,26.91321],"type":"Point"}
}