{
  "type": "Feature",
  "properties": {
    "gn:admin1_code":"MR",
    "gn:admin2_code":"12",
    "gn:admin3_code":"55",
    "gn:admin4_code":"550040",
    "gn:asciiname":"Bajbot",
    "gn:country_code":"NP",
    "gn:dem":1835,
    "gn:feature_class":"P",
    "gn:feature_code":"PPLL",
    "gn:name":"Bajbot",
    "gn:population":0,
    "gn:timezone":"Asia/Kathmandu",
    "iso:country":"NP",
    "wof:name":"Bajbot",
    "wof:placetype":"locality"
},
  "geometry": {"coordinates":[82.43028000000002,28.24845],"type":"Point"}
}