{
  "type": "Feature",
  "properties": {
    "gn:admin1_code":"ER",
    "gn:admin2_code":"10.0",
    "gn:admin3_code":"1.0",
    "gn:admin4_code":"10040.0",
    "gn:asciiname":"Kunjari",
    "gn:country_code":"NP",
    "gn:dem":1990,
    "gn:feature_class":"P",
    "gn:feature_code":"PPLL",
    "gn:name":"Kunjari",
    "gn:population":0,
    "gn:timezone":"Asia/Kathmandu",
    "iso:country":"NP",
    "wof:name":"Kunjari",
    "wof:placetype":"locality"
},
  "geometry": {"coordinates":[87.80237,27.37843],"type":"Point"}
}