{
  "type": "Feature",
  "properties": {
    "gn:admin1_code":"MR",
    "gn:admin2_code":"2",
    "gn:admin3_code":"60.0",
    "gn:admin4_code":"600041.0",
    "gn:asciiname":"Chimtola",
    "gn:country_code":"NP",
    "gn:dem":2099,
    "gn:feature_class":"P",
    "gn:feature_code":"PPLL",
    "gn:name":"Chimtola",
    "gn:population":0,
    "gn:timezone":"Asia/Kathmandu",
    "iso:country":"NP",
    "wof:name":"Chimtola",
    "wof:placetype":"locality"
},
  "geometry": {"coordinates":[81.82038,28.81291],"type":"Point"}
}