{
  "type": "Feature",
  "properties": {
    "gn:admin1_code":"ER",
    "gn:admin2_code":"7",
    "gn:admin3_code":"10.0",
    "gn:admin4_code":"100016.0",
    "gn:asciiname":"Gopinichaur",
    "gn:country_code":"NP",
    "gn:dem":853,
    "gn:feature_class":"P",
    "gn:feature_code":"PPLL",
    "gn:name":"Gopinichaur",
    "gn:population":0,
    "gn:timezone":"Asia/Kathmandu",
    "iso:country":"NP",
    "wof:name":"Gopinichaur",
    "wof:placetype":"locality"
},
  "geometry": {"coordinates":[87.08431,27.41482],"type":"Point"}
}