{
  "type": "Feature",
  "properties": {
    "gn:admin1_code":"00",
    "gn:asciiname":"Hansamaran",
    "gn:country_code":"NP",
    "gn:dem":372,
    "gn:feature_class":"P",
    "gn:feature_code":"PPL",
    "gn:name":"Hansamar\u0101\u1e45",
    "gn:population":0,
    "gn:timezone":"Asia/Kathmandu",
    "iso:country":"NP",
    "name:nep_x_preferred":[
        "Hansamar\u0101\u1e45"
    ],
    "wof:name":"Hansamaran",
    "wof:placetype":"locality"
},
  "geometry": {"coordinates":[87.44028,26.96645],"type":"Point"}
}