{
  "type": "Feature",
  "properties": {
    "gn:admin1_code":"WR",
    "gn:admin2_code":"4",
    "gn:admin3_code":"40.0",
    "gn:admin4_code":"400032.0",
    "gn:asciiname":"Milan Chok",
    "gn:country_code":"NP",
    "gn:dem":830,
    "gn:feature_class":"P",
    "gn:feature_code":"PPLL",
    "gn:name":"Milan Chok",
    "gn:population":0,
    "gn:timezone":"Asia/Kathmandu",
    "iso:country":"NP",
    "wof:name":"Milan Chok",
    "wof:placetype":"locality"
},
  "geometry": {"coordinates":[83.97368,28.208],"type":"Point"}
}