{
  "type": "Feature",
  "properties": {
    "gn:admin1_code":"ER",
    "gn:admin2_code":"7",
    "gn:admin3_code":"5",
    "gn:admin4_code":"50053",
    "gn:asciiname":"Chakretol",
    "gn:country_code":"NP",
    "gn:dem":77,
    "gn:feature_class":"P",
    "gn:feature_code":"PPLL",
    "gn:name":"Chakretol",
    "gn:population":0,
    "gn:timezone":"Asia/Kathmandu",
    "iso:country":"NP",
    "wof:name":"Chakretol",
    "wof:placetype":"locality"
},
  "geometry": {"coordinates":[87.60857,26.46295],"type":"Point"}
}