{
  "type": "Feature",
  "properties": {
    "gn:admin1_code":"WR",
    "gn:admin2_code":"4",
    "gn:admin3_code":"40.0",
    "gn:admin4_code":"400027.0",
    "gn:asciiname":"Biruwadanda",
    "gn:country_code":"NP",
    "gn:dem":1838,
    "gn:feature_class":"P",
    "gn:feature_code":"PPLL",
    "gn:name":"Biruwadanda",
    "gn:population":0,
    "gn:timezone":"Asia/Kathmandu",
    "iso:country":"NP",
    "wof:name":"Biruwadanda",
    "wof:placetype":"locality"
},
  "geometry": {"coordinates":[84.03659,28.28573],"type":"Point"}
}