{
  "type": "Feature",
  "properties": {
    "gn:admin1_code":"ER",
    "gn:admin2_code":"10.0",
    "gn:admin3_code":"1.0",
    "gn:admin4_code":"10031.0",
    "gn:asciiname":"Dandagaun",
    "gn:country_code":"NP",
    "gn:dem":1641,
    "gn:feature_class":"P",
    "gn:feature_code":"PPLL",
    "gn:name":"Dandagaun",
    "gn:population":0,
    "gn:timezone":"Asia/Kathmandu",
    "iso:country":"NP",
    "name:pol_x_preferred":[
        "Dandagaun"
    ],
    "wof:name":"Dandagaun",
    "wof:placetype":"locality"
},
  "geometry": {"coordinates":[87.66043000000001,27.29477],"type":"Point"}
}