{
  "type": "Feature",
  "properties": {
    "gn:admin1_code":"ER",
    "gn:admin2_code":"13",
    "gn:admin3_code":"13.0",
    "gn:admin4_code":"130031.0",
    "gn:asciiname":"Dhartum",
    "gn:country_code":"NP",
    "gn:dem":1353,
    "gn:feature_class":"P",
    "gn:feature_code":"PPLL",
    "gn:name":"Dhartum",
    "gn:population":0,
    "gn:timezone":"Asia/Kathmandu",
    "iso:country":"NP",
    "wof:name":"Dhartum",
    "wof:placetype":"locality"
},
  "geometry": {"coordinates":[86.82550999999999,26.92974],"type":"Point"}
}