{
  "type": "Feature",
  "properties": {
    "gn:admin1_code":"CR",
    "gn:admin2_code":"1",
    "gn:admin3_code":"23",
    "gn:admin4_code":"230071",
    "gn:asciiname":"Kapre",
    "gn:country_code":"NP",
    "gn:dem":1648,
    "gn:feature_class":"P",
    "gn:feature_code":"PPLL",
    "gn:name":"Kapre",
    "gn:population":0,
    "gn:timezone":"Asia/Kathmandu",
    "iso:country":"NP",
    "name:fra_x_preferred":[
        "Kapre"
    ],
    "name:por_x_preferred":[
        "Kapre"
    ],
    "name:tgl_x_preferred":[
        "Kapre"
    ],
    "wof:name":"Kapre",
    "wof:placetype":"locality"
},
  "geometry": {"coordinates":[85.48231,27.84795],"type":"Point"}
}