{
  "type": "Feature",
  "properties": {
    "gn:admin1_code":"CR",
    "gn:admin2_code":"1",
    "gn:admin3_code":"23",
    "gn:admin4_code":"230049",
    "gn:asciiname":"Ksumti",
    "gn:country_code":"NP",
    "gn:dem":1782,
    "gn:feature_class":"P",
    "gn:feature_code":"PPLL",
    "gn:name":"Ksumti",
    "gn:population":0,
    "gn:timezone":"Asia/Kathmandu",
    "iso:country":"NP",
    "wof:name":"Ksumti",
    "wof:placetype":"locality"
},
  "geometry": {"coordinates":[85.65893,27.98205],"type":"Point"}
}