{
  "type": "Feature",
  "properties": {
    "gn:admin1_code":"ER",
    "gn:admin2_code":"10.0",
    "gn:admin3_code":"1.0",
    "gn:admin4_code":"10004.0",
    "gn:asciiname":"Porokmi",
    "gn:country_code":"NP",
    "gn:dem":1489,
    "gn:feature_class":"P",
    "gn:feature_code":"PPLL",
    "gn:name":"Porokmi",
    "gn:population":0,
    "gn:timezone":"Asia/Kathmandu",
    "iso:country":"NP",
    "wof:name":"Porokmi",
    "wof:placetype":"locality"
},
  "geometry": {"coordinates":[87.59285,27.32195],"type":"Point"}
}