{
  "type": "Feature",
  "properties": {
    "gn:admin1_code":"WR",
    "gn:admin2_code":"8",
    "gn:admin3_code":"50.0",
    "gn:admin4_code":"500054.0",
    "gn:asciiname":"Nandanagar Sano",
    "gn:country_code":"NP",
    "gn:dem":99,
    "gn:feature_class":"P",
    "gn:feature_code":"PPLL",
    "gn:name":"Nandanagar Sano",
    "gn:population":0,
    "gn:timezone":"Asia/Kathmandu",
    "iso:country":"NP",
    "wof:name":"Nandanagar Sano",
    "wof:placetype":"locality"
},
  "geometry": {"coordinates":[83.19913000000003,27.52835],"type":"Point"}
}