{
  "type": "Feature",
  "properties": {
    "gn:admin1_code":"CR",
    "gn:admin2_code":"1",
    "gn:admin3_code":"25",
    "gn:admin4_code":"250032",
    "gn:asciiname":"Puranogaun",
    "gn:country_code":"NP",
    "gn:dem":1649,
    "gn:feature_class":"P",
    "gn:feature_code":"PPLL",
    "gn:name":"Puranogaun",
    "gn:population":0,
    "gn:timezone":"Asia/Kathmandu",
    "iso:country":"NP",
    "wof:name":"Puranogaun",
    "wof:placetype":"locality"
},
  "geometry": {"coordinates":[85.3793,27.49113],"type":"Point"}
}