{
  "type": "Feature",
  "properties": {
    "gn:admin1_code":"FR",
    "gn:admin2_code":"14",
    "gn:admin3_code":"71.0",
    "gn:admin4_code":"710025.0",
    "gn:asciiname":"Katauje",
    "gn:country_code":"NP",
    "gn:dem":990,
    "gn:feature_class":"P",
    "gn:feature_code":"PPLL",
    "gn:name":"Katauje",
    "gn:population":0,
    "gn:timezone":"Asia/Kathmandu",
    "iso:country":"NP",
    "wof:name":"Katauje",
    "wof:placetype":"locality"
},
  "geometry": {"coordinates":[80.88160999999999,28.89978],"type":"Point"}
}