{
  "type": "Feature",
  "properties": {
    "gn:admin1_code":"WR",
    "gn:admin2_code":"4",
    "gn:admin3_code":"40.0",
    "gn:admin4_code":"400008.0",
    "gn:asciiname":"Dotelkuna",
    "gn:country_code":"NP",
    "gn:dem":652,
    "gn:feature_class":"P",
    "gn:feature_code":"PPLL",
    "gn:name":"Dotelkuna",
    "gn:population":0,
    "gn:timezone":"Asia/Kathmandu",
    "iso:country":"NP",
    "wof:name":"Dotelkuna",
    "wof:placetype":"locality"
},
  "geometry": {"coordinates":[84.13091,28.1109],"type":"Point"}
}