{
  "type": "Feature",
  "properties": {
    "gn:admin1_code":"WR",
    "gn:admin2_code":"8",
    "gn:admin3_code":"46.0",
    "gn:admin4_code":"460007.0",
    "gn:asciiname":"Chekmi",
    "gn:country_code":"NP",
    "gn:dem":1446,
    "gn:feature_class":"P",
    "gn:feature_code":"PPLL",
    "gn:name":"Chekmi",
    "gn:population":0,
    "gn:timezone":"Asia/Kathmandu",
    "iso:country":"NP",
    "wof:name":"Chekmi",
    "wof:placetype":"locality"
},
  "geometry": {"coordinates":[83.21087,28.07656],"type":"Point"}
}