{
  "type": "Feature",
  "properties": {
    "gn:admin1_code":"MR",
    "gn:admin2_code":"12",
    "gn:admin3_code":"52",
    "gn:admin4_code":"520013",
    "gn:asciiname":"Sano Damri",
    "gn:country_code":"NP",
    "gn:dem":1709,
    "gn:feature_class":"P",
    "gn:feature_code":"PPLL",
    "gn:name":"Sano Damri",
    "gn:population":0,
    "gn:timezone":"Asia/Kathmandu",
    "iso:country":"NP",
    "wof:name":"Sano Damri",
    "wof:placetype":"locality"
},
  "geometry": {"coordinates":[82.86645,28.24543],"type":"Point"}
}