{
  "type": "Feature",
  "properties": {
    "gn:admin1_code":"FR",
    "gn:admin2_code":"14.0",
    "gn:admin3_code":"67.0",
    "gn:admin4_code":"670012.0",
    "gn:asciiname":"Dhanalta",
    "gn:country_code":"NP",
    "gn:dem":1704,
    "gn:feature_class":"P",
    "gn:feature_code":"PPLL",
    "gn:name":"Dhanalta",
    "gn:population":0,
    "gn:timezone":"Asia/Kathmandu",
    "iso:country":"NP",
    "wof:name":"Dhanalta",
    "wof:placetype":"locality"
},
  "geometry": {"coordinates":[81.30279,29.38417],"type":"Point"}
}