{
  "type": "Feature",
  "properties": {
    "gn:admin1_code":"CR",
    "gn:admin2_code":"5",
    "gn:admin3_code":"20",
    "gn:admin4_code":"200050",
    "gn:asciiname":"Lapse",
    "gn:country_code":"NP",
    "gn:dem":1739,
    "gn:feature_class":"P",
    "gn:feature_code":"PPLL",
    "gn:name":"Lapse",
    "gn:population":0,
    "gn:timezone":"Asia/Kathmandu",
    "iso:country":"NP",
    "wof:name":"Lapse",
    "wof:placetype":"locality"
},
  "geometry": {"coordinates":[85.79283000000002,27.37327],"type":"Point"}
}