{
  "type": "Feature",
  "properties": {
    "gn:admin1_code":"MR",
    "gn:admin2_code":"12",
    "gn:admin3_code":"54",
    "gn:admin4_code":"540036",
    "gn:asciiname":"Lasune",
    "gn:country_code":"NP",
    "gn:dem":1767,
    "gn:feature_class":"P",
    "gn:feature_code":"PPLL",
    "gn:name":"Lasune",
    "gn:population":0,
    "gn:timezone":"Asia/Kathmandu",
    "iso:country":"NP",
    "wof:name":"Lasune",
    "wof:placetype":"locality"
},
  "geometry": {"coordinates":[82.46789,28.56981],"type":"Point"}
}