{
  "type": "Feature",
  "properties": {
    "gn:admin1_code":"WR",
    "gn:admin2_code":"8",
    "gn:admin3_code":"47",
    "gn:admin4_code":"470057",
    "gn:asciiname":"Dhungrikhola Gaun",
    "gn:country_code":"NP",
    "gn:dem":993,
    "gn:feature_class":"P",
    "gn:feature_code":"PPLL",
    "gn:name":"Dhungrikhola Gaun",
    "gn:population":0,
    "gn:timezone":"Asia/Kathmandu",
    "iso:country":"NP",
    "wof:name":"Dhungrikhola Gaun",
    "wof:placetype":"locality"
},
  "geometry": {"coordinates":[83.25983000000002,27.7892],"type":"Point"}
}