{
  "type": "Feature",
  "properties": {
    "gn:admin1_code":"ER",
    "gn:admin2_code":"10",
    "gn:admin3_code":"3.0",
    "gn:admin4_code":"30007.0",
    "gn:asciiname":"Tungganitar",
    "gn:country_code":"NP",
    "gn:dem":210,
    "gn:feature_class":"P",
    "gn:feature_code":"PPLL",
    "gn:name":"Tungganitar",
    "gn:population":0,
    "gn:timezone":"Asia/Kathmandu",
    "iso:country":"NP",
    "wof:name":"Tungganitar",
    "wof:placetype":"locality"
},
  "geometry": {"coordinates":[87.91983,26.77535],"type":"Point"}
}