{
  "type": "Feature",
  "properties": {
    "gn:admin1_code":"ER",
    "gn:admin2_code":"13.0",
    "gn:admin3_code":"14.0",
    "gn:admin4_code":"140004.0",
    "gn:asciiname":"Raitima",
    "gn:country_code":"NP",
    "gn:dem":985,
    "gn:feature_class":"P",
    "gn:feature_code":"PPLL",
    "gn:name":"Raitima",
    "gn:population":0,
    "gn:timezone":"Asia/Kathmandu",
    "iso:country":"NP",
    "wof:name":"Raitima",
    "wof:placetype":"locality"
},
  "geometry": {"coordinates":[86.56532,27.00011],"type":"Point"}
}