{
  "type": "Feature",
  "properties": {
    "gn:admin1_code":"FR",
    "gn:admin2_code":"9",
    "gn:admin3_code":"72.0",
    "gn:admin4_code":"720017.0",
    "gn:asciiname":"Chhoti Parsiya",
    "gn:country_code":"NP",
    "gn:dem":187,
    "gn:feature_class":"P",
    "gn:feature_code":"PPLL",
    "gn:name":"Chhoti Parsiya",
    "gn:population":0,
    "gn:timezone":"Asia/Kathmandu",
    "iso:country":"NP",
    "wof:name":"Chhoti Parsiya",
    "wof:placetype":"locality"
},
  "geometry": {"coordinates":[80.37994999999999,28.76541],"type":"Point"}
}