{
  "type": "Feature",
  "properties": {
    "gn:admin1_code":"ER",
    "gn:admin2_code":"13.0",
    "gn:admin3_code":"14.0",
    "gn:admin4_code":"140012.0",
    "gn:asciiname":"Arna",
    "gn:country_code":"NP",
    "gn:dem":730,
    "gn:feature_class":"P",
    "gn:feature_code":"PPLL",
    "gn:name":"Arna",
    "gn:population":0,
    "gn:timezone":"Asia/Kathmandu",
    "iso:country":"NP",
    "name:cat_x_preferred":[
        "Arna"
    ],
    "name:ceb_x_preferred":[
        "Arna"
    ],
    "name:deu_x_preferred":[
        "Arna"
    ],
    "name:hye_x_preferred":[
        "\u0531\u057c\u0576\u0561"
    ],
    "name:kaz_x_preferred":[
        "\u0410\u0440\u043d\u0430"
    ],
    "name:nld_x_preferred":[
        "Arna"
    ],
    "name:rus_x_preferred":[
        "\u0410\u0440\u043d\u0430"
    ],
    "name:swe_x_preferred":[
        "Arna"
    ],
    "name:ukr_x_preferred":[
        "\u0410\u0440\u043d\u0430"
    ],
    "wof:name":"Arna",
    "wof:placetype":"locality"
},
  "geometry": {"coordinates":[86.39105000000001,27.05254],"type":"Point"}
}