{
  "type": "Feature",
  "properties": {
    "gn:admin1_code":"CR",
    "gn:admin2_code":"1",
    "gn:admin3_code":"24.0",
    "gn:admin4_code":"240069.0",
    "gn:asciiname":"Thilwal",
    "gn:country_code":"NP",
    "gn:dem":1095,
    "gn:feature_class":"P",
    "gn:feature_code":"PPLL",
    "gn:name":"Thilwal",
    "gn:population":0,
    "gn:timezone":"Asia/Kathmandu",
    "iso:country":"NP",
    "wof:name":"Thilwal",
    "wof:placetype":"locality"
},
  "geometry": {"coordinates":[85.73659000000001,27.50068],"type":"Point"}
}