{
  "type": "Feature",
  "properties": {
    "gn:admin1_code":"00",
    "gn:asciiname":"Majinthok",
    "gn:country_code":"NP",
    "gn:dem":856,
    "gn:feature_class":"P",
    "gn:feature_code":"PPL",
    "gn:name":"Majinthok",
    "gn:population":0,
    "gn:timezone":"Asia/Kathmandu",
    "iso:country":"NP",
    "name:nep_x_preferred":[
        "Majinthok"
    ],
    "name:und_x_variant":[
        "N\u0101\u1e45ge"
    ],
    "wof:name":"Majinthok",
    "wof:placetype":"locality"
},
  "geometry": {"coordinates":[84.80014,28.03965],"type":"Point"}
}