{
  "type": "Feature",
  "properties": {
    "gn:admin1_code":"ER",
    "gn:admin2_code":"13.0",
    "gn:admin3_code":"14.0",
    "gn:admin4_code":"140016.0",
    "gn:asciiname":"Khudiyahi",
    "gn:country_code":"NP",
    "gn:dem":143,
    "gn:feature_class":"P",
    "gn:feature_code":"PPLL",
    "gn:name":"Khudiyahi",
    "gn:population":0,
    "gn:timezone":"Asia/Kathmandu",
    "iso:country":"NP",
    "wof:name":"Khudiyahi",
    "wof:placetype":"locality"
},
  "geometry": {"coordinates":[86.78066,26.75816],"type":"Point"}
}