{
  "type": "Feature",
  "properties": {
    "gn:admin1_code":"CR",
    "gn:admin2_code":"1",
    "gn:admin3_code":"28",
    "gn:admin4_code":"280052",
    "gn:asciiname":"Tallo Pundi",
    "gn:country_code":"NP",
    "gn:dem":1124,
    "gn:feature_class":"P",
    "gn:feature_code":"PPLL",
    "gn:name":"Tallo Pundi",
    "gn:population":0,
    "gn:timezone":"Asia/Kathmandu",
    "iso:country":"NP",
    "wof:name":"Tallo Pundi",
    "wof:placetype":"locality"
},
  "geometry": {"coordinates":[85.38434000000002,27.85503],"type":"Point"}
}