{
  "type": "Feature",
  "properties": {
    "gn:admin1_code":"MR",
    "gn:admin2_code":"12",
    "gn:admin3_code":"53",
    "gn:admin4_code":"530005",
    "gn:asciiname":"Bajhange",
    "gn:country_code":"NP",
    "gn:dem":2304,
    "gn:feature_class":"P",
    "gn:feature_code":"PPLL",
    "gn:name":"Bajhange",
    "gn:population":0,
    "gn:timezone":"Asia/Kathmandu",
    "iso:country":"NP",
    "wof:name":"Bajhange",
    "wof:placetype":"locality"
},
  "geometry": {"coordinates":[82.65884,28.39867000000001],"type":"Point"}
}