{
  "type": "Feature",
  "properties": {
    "gn:admin1_code":"FR",
    "gn:admin2_code":"14",
    "gn:admin3_code":"71.0",
    "gn:admin4_code":"710020.0",
    "gn:asciiname":"Baluwagada",
    "gn:country_code":"NP",
    "gn:dem":359,
    "gn:feature_class":"P",
    "gn:feature_code":"PPLL",
    "gn:name":"Baluwagada",
    "gn:population":0,
    "gn:timezone":"Asia/Kathmandu",
    "iso:country":"NP",
    "wof:name":"Baluwagada",
    "wof:placetype":"locality"
},
  "geometry": {"coordinates":[80.81310999999999,28.81955],"type":"Point"}
}