{
  "type": "Feature",
  "properties": {
    "gn:admin1_code":"FR",
    "gn:admin2_code":"9",
    "gn:admin3_code":"74",
    "gn:admin4_code":"740053.0",
    "gn:asciiname":"Kaireli",
    "gn:country_code":"NP",
    "gn:dem":1941,
    "gn:feature_class":"P",
    "gn:feature_code":"PPLL",
    "gn:name":"Kaireli",
    "gn:population":0,
    "gn:timezone":"Asia/Kathmandu",
    "iso:country":"NP",
    "wof:name":"Kaireli",
    "wof:placetype":"locality"
},
  "geometry": {"coordinates":[80.65101,29.53291],"type":"Point"}
}