{
  "type": "Feature",
  "properties": {
    "gn:admin1_code":"CR",
    "gn:admin2_code":"5",
    "gn:admin3_code":"20",
    "gn:admin4_code":"200022.0",
    "gn:asciiname":"Akasepakha",
    "gn:country_code":"NP",
    "gn:dem":1531,
    "gn:feature_class":"P",
    "gn:feature_code":"PPLL",
    "gn:name":"Akasepakha",
    "gn:population":0,
    "gn:timezone":"Asia/Kathmandu",
    "iso:country":"NP",
    "wof:name":"Akasepakha",
    "wof:placetype":"locality"
},
  "geometry": {"coordinates":[86.25726999999998,27.12359],"type":"Point"}
}