{
  "type": "Feature",
  "properties": {
    "gn:admin1_code":"MR",
    "gn:admin2_code":"12",
    "gn:admin3_code":"54",
    "gn:admin4_code":"540017",
    "gn:asciiname":"Pasane",
    "gn:country_code":"NP",
    "gn:dem":2471,
    "gn:feature_class":"P",
    "gn:feature_code":"PPLL",
    "gn:name":"Pasane",
    "gn:population":0,
    "gn:timezone":"Asia/Kathmandu",
    "iso:country":"NP",
    "wof:name":"Pasane",
    "wof:placetype":"locality"
},
  "geometry": {"coordinates":[82.68561,28.60171],"type":"Point"}
}