{
  "type": "Feature",
  "properties": {
    "gn:admin1_code":"CR",
    "gn:admin2_code":"1",
    "gn:admin3_code":"23",
    "gn:admin4_code":"230056",
    "gn:asciiname":"Jaljale",
    "gn:country_code":"NP",
    "gn:dem":2107,
    "gn:feature_class":"P",
    "gn:feature_code":"PPLL",
    "gn:name":"Jaljale",
    "gn:population":0,
    "gn:timezone":"Asia/Kathmandu",
    "iso:country":"NP",
    "name:bih_x_preferred":[
        "\u091c\u0932\u091c\u0932\u0947"
    ],
    "name:ceb_x_preferred":[
        "Jaljale"
    ],
    "name:mai_x_preferred":[
        "\u091c\u0932\u091c\u0932\u0947"
    ],
    "name:msa_x_preferred":[
        "Jaljale"
    ],
    "name:nep_x_preferred":[
        "\u091c\u0932\u091c\u0932\u0947"
    ],
    "name:new_x_preferred":[
        "\u091c\u0932\u094d\u091c\u0932\u0947"
    ],
    "name:pol_x_preferred":[
        "Jaljale"
    ],
    "name:urd_x_preferred":[
        "\u062c\u0644\u062c\u0644\u06d2"
    ],
    "wof:name":"Jaljale",
    "wof:placetype":"locality"
},
  "geometry": {"coordinates":[85.93765,27.72917],"type":"Point"}
}