{
  "type": "Feature",
  "properties": {
    "gn:admin1_code":"WR",
    "gn:admin2_code":"4",
    "gn:admin3_code":"36.0",
    "gn:admin4_code":"360029.0",
    "gn:asciiname":"Tutan",
    "gn:country_code":"NP",
    "gn:dem":1279,
    "gn:feature_class":"P",
    "gn:feature_code":"PPLL",
    "gn:name":"Tutan",
    "gn:population":0,
    "gn:timezone":"Asia/Kathmandu",
    "iso:country":"NP",
    "name:fas_x_preferred":[
        "\u062a\u0648\u062a\u0627\u0646"
    ],
    "wof:name":"Tutan",
    "wof:placetype":"locality"
},
  "geometry": {"coordinates":[84.62154,28.16001],"type":"Point"}
}