{
  "type": "Feature",
  "properties": {
    "gn:admin1_code":"MR",
    "gn:admin2_code":"2",
    "gn:admin3_code":"61.0",
    "gn:admin4_code":"610017.0",
    "gn:asciiname":"Dandakot",
    "gn:country_code":"NP",
    "gn:dem":1315,
    "gn:feature_class":"P",
    "gn:feature_code":"PPLL",
    "gn:name":"Dandakot",
    "gn:population":0,
    "gn:timezone":"Asia/Kathmandu",
    "iso:country":"NP",
    "wof:name":"Dandakot",
    "wof:placetype":"locality"
},
  "geometry": {"coordinates":[81.94309,28.82995],"type":"Point"}
}