{
  "type": "Feature",
  "properties": {
    "gn:admin1_code":"CR",
    "gn:admin2_code":"5",
    "gn:admin3_code":"19",
    "gn:admin4_code":"190073",
    "gn:asciiname":"Jangaltol",
    "gn:country_code":"NP",
    "gn:dem":138,
    "gn:feature_class":"P",
    "gn:feature_code":"PPLL",
    "gn:name":"Jangaltol",
    "gn:population":0,
    "gn:timezone":"Asia/Kathmandu",
    "iso:country":"NP",
    "wof:name":"Jangaltol",
    "wof:placetype":"locality"
},
  "geometry": {"coordinates":[85.58968,27.06069],"type":"Point"}
}