{
  "type": "Feature",
  "properties": {
    "gn:admin1_code":"MR",
    "gn:admin2_code":"12",
    "gn:admin3_code":"55",
    "gn:admin4_code":"550025",
    "gn:asciiname":"Khaprakanda",
    "gn:country_code":"NP",
    "gn:dem":1353,
    "gn:feature_class":"P",
    "gn:feature_code":"PPLL",
    "gn:name":"Khaprakanda",
    "gn:population":0,
    "gn:timezone":"Asia/Kathmandu",
    "iso:country":"NP",
    "wof:name":"Khaprakanda",
    "wof:placetype":"locality"
},
  "geometry": {"coordinates":[82.27018000000002,28.34807],"type":"Point"}
}