{
  "type": "Feature",
  "properties": {
    "gn:admin1_code":"MR",
    "gn:admin2_code":"2",
    "gn:admin3_code":"60.0",
    "gn:admin4_code":"600044.0",
    "gn:asciiname":"Khatina",
    "gn:country_code":"NP",
    "gn:dem":1377,
    "gn:feature_class":"P",
    "gn:feature_code":"PPLL",
    "gn:name":"Khatina",
    "gn:population":0,
    "gn:timezone":"Asia/Kathmandu",
    "iso:country":"NP",
    "wof:name":"Khatina",
    "wof:placetype":"locality"
},
  "geometry": {"coordinates":[81.62560999999999,28.82055],"type":"Point"}
}