{
  "type": "Feature",
  "properties": {
    "gn:admin1_code":"FR",
    "gn:admin2_code":"14.0",
    "gn:admin3_code":"67.0",
    "gn:admin4_code":"670003.0",
    "gn:asciiname":"Ribra",
    "gn:country_code":"NP",
    "gn:dem":1924,
    "gn:feature_class":"P",
    "gn:feature_code":"PPLL",
    "gn:name":"Ribra",
    "gn:population":0,
    "gn:timezone":"Asia/Kathmandu",
    "iso:country":"NP",
    "wof:name":"Ribra",
    "wof:placetype":"locality"
},
  "geometry": {"coordinates":[81.74453000000003,29.47375],"type":"Point"}
}