{
  "type": "Feature",
  "properties": {
    "gn:admin1_code":"FR",
    "gn:admin2_code":"9",
    "gn:admin3_code":"73.0",
    "gn:admin4_code":"730006.0",
    "gn:asciiname":"Belapur",
    "gn:country_code":"NP",
    "gn:dem":1530,
    "gn:feature_class":"P",
    "gn:feature_code":"PPLL",
    "gn:name":"Belapur",
    "gn:population":0,
    "gn:timezone":"Asia/Kathmandu",
    "iso:country":"NP",
    "wof:name":"Belapur",
    "wof:placetype":"locality"
},
  "geometry": {"coordinates":[80.71764,29.36413],"type":"Point"}
}