{
  "type": "Feature",
  "properties": {
    "gn:admin1_code":"MR",
    "gn:admin2_code":"12",
    "gn:admin3_code":"54",
    "gn:admin4_code":"540029",
    "gn:asciiname":"Ramri",
    "gn:country_code":"NP",
    "gn:dem":2262,
    "gn:feature_class":"P",
    "gn:feature_code":"PPLL",
    "gn:name":"Ramri",
    "gn:population":0,
    "gn:timezone":"Asia/Kathmandu",
    "iso:country":"NP",
    "wof:name":"Ramri",
    "wof:placetype":"locality"
},
  "geometry": {"coordinates":[82.52531999999999,28.68083],"type":"Point"}
}