{
  "type": "Feature",
  "properties": {
    "gn:admin1_code":"CR",
    "gn:admin2_code":"1",
    "gn:admin3_code":"25",
    "gn:admin4_code":"250007",
    "gn:asciiname":"Jyawalakhel",
    "gn:country_code":"NP",
    "gn:dem":1333,
    "gn:feature_class":"P",
    "gn:feature_code":"PPLL",
    "gn:name":"Jyawalakhel",
    "gn:population":0,
    "gn:timezone":"Asia/Kathmandu",
    "iso:country":"NP",
    "wof:name":"Jyawalakhel",
    "wof:placetype":"locality"
},
  "geometry": {"coordinates":[85.30911999999999,27.63098],"type":"Point"}
}