{
  "type": "Feature",
  "properties": {
    "gn:admin1_code":"ER",
    "gn:admin2_code":"13",
    "gn:admin3_code":"13",
    "gn:admin4_code":"130048",
    "gn:asciiname":"Ilim",
    "gn:country_code":"NP",
    "gn:dem":1151,
    "gn:feature_class":"P",
    "gn:feature_code":"PPLL",
    "gn:name":"Ilim",
    "gn:population":0,
    "gn:timezone":"Asia/Kathmandu",
    "iso:country":"NP",
    "wof:name":"Ilim",
    "wof:placetype":"locality"
},
  "geometry": {"coordinates":[86.76033000000002,27.32847000000001],"type":"Point"}
}