{
  "type": "Feature",
  "properties": {
    "gn:admin1_code":"ER",
    "gn:admin2_code":"10.0",
    "gn:admin3_code":"1.0",
    "gn:admin4_code":"10014.0",
    "gn:asciiname":"Lungthung",
    "gn:country_code":"NP",
    "gn:dem":1872,
    "gn:feature_class":"P",
    "gn:feature_code":"PPLL",
    "gn:name":"Lungthung",
    "gn:population":0,
    "gn:timezone":"Asia/Kathmandu",
    "iso:country":"NP",
    "wof:name":"Lungthung",
    "wof:placetype":"locality"
},
  "geometry": {"coordinates":[87.90430000000001,27.39128],"type":"Point"}
}