{
  "type": "Feature",
  "properties": {
    "gn:admin1_code":"CR",
    "gn:admin2_code":"11.0",
    "gn:admin3_code":"33.0",
    "gn:admin4_code":"330068.0",
    "gn:asciiname":"Ghaderitol",
    "gn:country_code":"NP",
    "gn:dem":195,
    "gn:feature_class":"P",
    "gn:feature_code":"PPLL",
    "gn:name":"Ghaderitol",
    "gn:population":0,
    "gn:timezone":"Asia/Kathmandu",
    "iso:country":"NP",
    "wof:name":"Ghaderitol",
    "wof:placetype":"locality"
},
  "geometry": {"coordinates":[85.18841,27.2218],"type":"Point"}
}