{
  "type": "Feature",
  "properties": {
    "gn:admin1_code":"ER",
    "gn:admin2_code":"7",
    "gn:admin3_code":"5",
    "gn:admin4_code":"50048.0",
    "gn:asciiname":"Nalbari",
    "gn:country_code":"NP",
    "gn:dem":114,
    "gn:feature_class":"P",
    "gn:feature_code":"PPLL",
    "gn:name":"Nalbari",
    "gn:population":0,
    "gn:timezone":"Asia/Kathmandu",
    "iso:country":"NP",
    "name:ara_x_preferred":[
        "\u0646\u0627\u0644\u0628\u0627\u0631\u064a"
    ],
    "name:asm_x_preferred":[
        "\u09a8\u09b2\u09ac\u09be\u09f0\u09c0 \u09a8\u0997\u09f0"
    ],
    "name:ceb_x_preferred":[
        "Nalb\u0101ri"
    ],
    "name:fra_x_preferred":[
        "Nalbari"
    ],
    "name:hin_x_preferred":[
        "\u0928\u0932\u092c\u093e\u0921\u093c\u0940"
    ],
    "name:ita_x_preferred":[
        "Nalbari"
    ],
    "name:mar_x_preferred":[
        "\u0928\u0932\u092c\u093e\u0930\u0940"
    ],
    "name:mlg_x_preferred":[
        "Nalbari"
    ],
    "name:msa_x_preferred":[
        "Nalbari"
    ],
    "name:new_x_preferred":[
        "\u0928\u0932\u092c\u093e\u0930\u0940"
    ],
    "name:nld_x_preferred":[
        "Nalbari"
    ],
    "name:oci_x_preferred":[
        "Nalbari"
    ],
    "name:ori_x_preferred":[
        "\u0b28\u0b3e\u0b32\u0b2c\u0b30\u0b3f"
    ],
    "name:por_x_preferred":[
        "Nalbari"
    ],
    "name:san_x_preferred":[
        "\u0928\u0932\u092c\u093e\u0930\u093f-\u0928\u0917\u0930\u092e\u094d"
    ],
    "name:spa_x_preferred":[
        "Nalbari"
    ],
    "name:swe_x_preferred":[
        "Nalbari"
    ],
    "name:urd_x_preferred":[
        "\u0646\u0644\u0628\u0627\u0631\u06cc"
    ],
    "name:vie_x_preferred":[
        "Nalbari"
    ],
    "name:zho_x_preferred":[
        "\u7eb3\u5c14\u5df4\u91cc"
    ],
    "wof:name":"Nalbari",
    "wof:placetype":"locality"
},
  "geometry": {"coordinates":[87.64264,26.63941],"type":"Point"}
}