{
  "type": "Feature",
  "properties": {
    "gn:admin1_code":"MR",
    "gn:admin2_code":"2",
    "gn:admin3_code":"60.0",
    "gn:admin4_code":"600056.0",
    "gn:asciiname":"Syaule Kanda",
    "gn:country_code":"NP",
    "gn:dem":1807,
    "gn:feature_class":"P",
    "gn:feature_code":"PPLL",
    "gn:name":"Syaule Kanda",
    "gn:population":0,
    "gn:timezone":"Asia/Kathmandu",
    "iso:country":"NP",
    "wof:name":"Syaule Kanda",
    "wof:placetype":"locality"
},
  "geometry": {"coordinates":[81.50535000000001,29.00803],"type":"Point"}
}