{
  "type": "Feature",
  "properties": {
    "gn:admin1_code":"CR",
    "gn:admin2_code":"5",
    "gn:admin3_code":"19",
    "gn:admin4_code":"190040.0",
    "gn:asciiname":"Betali",
    "gn:country_code":"NP",
    "gn:dem":163,
    "gn:feature_class":"P",
    "gn:feature_code":"PPLL",
    "gn:name":"Betali",
    "gn:population":0,
    "gn:timezone":"Asia/Kathmandu",
    "iso:country":"NP",
    "name:ceb_x_preferred":[
        "Betali"
    ],
    "name:msa_x_preferred":[
        "Betali"
    ],
    "name:pol_x_preferred":[
        "Betali"
    ],
    "wof:name":"Betali",
    "wof:placetype":"locality"
},
  "geometry": {"coordinates":[85.56322,27.10984],"type":"Point"}
}