{
  "type": "Feature",
  "properties": {
    "gn:admin1_code":"00",
    "gn:asciiname":"Tiu",
    "gn:country_code":"NP",
    "gn:dem":2620,
    "gn:feature_class":"P",
    "gn:feature_code":"PPL",
    "gn:name":"Ti\u0169",
    "gn:population":0,
    "gn:timezone":"Asia/Kathmandu",
    "iso:country":"NP",
    "name:afr_x_preferred":[
        "Tiu"
    ],
    "name:deu_x_preferred":[
        "Tiu"
    ],
    "name:fas_x_preferred":[
        "\u062a\u06cc\u0648"
    ],
    "name:fin_x_preferred":[
        "Tiu"
    ],
    "name:rus_x_preferred":[
        "\u0422\u0438\u0443"
    ],
    "wof:name":"Tiu",
    "wof:placetype":"locality"
},
  "geometry": {"coordinates":[86.88285999999999,27.46486],"type":"Point"}
}