{
  "type": "Feature",
  "properties": {
    "gn:admin1_code":"00",
    "gn:asciiname":"Pakadtola",
    "gn:country_code":"NP",
    "gn:dem":105,
    "gn:feature_class":"P",
    "gn:feature_code":"PPL",
    "gn:name":"Paka\u1e0d\u1e6dol\u0101",
    "gn:population":0,
    "gn:timezone":"Asia/Kathmandu",
    "iso:country":"NP",
    "wof:name":"Pakadtola",
    "wof:placetype":"locality"
},
  "geometry": {"coordinates":[85.02131999999997,27.05285],"type":"Point"}
}