{
  "type": "Feature",
  "properties": {
    "gn:admin1_code":"ER",
    "gn:admin2_code":"7",
    "gn:admin3_code":"7.0",
    "gn:admin4_code":"70024.0",
    "gn:asciiname":"Kuruletar",
    "gn:country_code":"NP",
    "gn:dem":223,
    "gn:feature_class":"P",
    "gn:feature_code":"PPLL",
    "gn:name":"Kuruletar",
    "gn:population":0,
    "gn:timezone":"Asia/Kathmandu",
    "iso:country":"NP",
    "wof:name":"Kuruletar",
    "wof:placetype":"locality"
},
  "geometry": {"coordinates":[87.26054999999999,26.92447],"type":"Point"}
}