{
  "type": "Feature",
  "properties": {
    "gn:admin1_code":"CR",
    "gn:admin2_code":"1",
    "gn:admin3_code":"30.0",
    "gn:admin4_code":"300013.0",
    "gn:asciiname":"Amiltar",
    "gn:country_code":"NP",
    "gn:dem":455,
    "gn:feature_class":"P",
    "gn:feature_code":"PPLL",
    "gn:name":"Amiltar",
    "gn:population":0,
    "gn:timezone":"Asia/Kathmandu",
    "iso:country":"NP",
    "wof:name":"Amiltar",
    "wof:placetype":"locality"
},
  "geometry": {"coordinates":[84.83953000000002,27.79355],"type":"Point"}
}