{
  "type": "Feature",
  "properties": {
    "gn:admin1_code":"CR",
    "gn:admin2_code":"1",
    "gn:admin3_code":"27.0",
    "gn:admin4_code":"270002.0",
    "gn:asciiname":"Band Bhanjyang",
    "gn:country_code":"NP",
    "gn:dem":1458,
    "gn:feature_class":"P",
    "gn:feature_code":"PPLL",
    "gn:name":"Band Bhanjyang",
    "gn:population":0,
    "gn:timezone":"Asia/Kathmandu",
    "iso:country":"NP",
    "wof:name":"Band Bhanjyang",
    "wof:placetype":"locality"
},
  "geometry": {"coordinates":[85.20694,27.70331],"type":"Point"}
}