{
  "type": "Feature",
  "properties": {
    "gn:admin1_code":"CR",
    "gn:admin2_code":"1",
    "gn:admin3_code":"28",
    "gn:admin4_code":"280019",
    "gn:asciiname":"Satdobate",
    "gn:country_code":"NP",
    "gn:dem":1449,
    "gn:feature_class":"P",
    "gn:feature_code":"PPLL",
    "gn:name":"Satdobate",
    "gn:population":0,
    "gn:timezone":"Asia/Kathmandu",
    "iso:country":"NP",
    "wof:name":"Satdobate",
    "wof:placetype":"locality"
},
  "geometry": {"coordinates":[85.16234,28.007],"type":"Point"}
}