{
  "type": "Feature",
  "properties": {
    "gn:admin1_code":"ER",
    "gn:admin2_code":"7.0",
    "gn:admin3_code":"8.0",
    "gn:admin4_code":"80019.0",
    "gn:asciiname":"Batase",
    "gn:country_code":"NP",
    "gn:dem":885,
    "gn:feature_class":"P",
    "gn:feature_code":"PPLL",
    "gn:name":"Batase",
    "gn:population":0,
    "gn:timezone":"Asia/Kathmandu",
    "iso:country":"NP",
    "name:ceb_x_preferred":[
        "Batase"
    ],
    "name:pol_x_preferred":[
        "Batase"
    ],
    "wof:name":"Batase",
    "wof:placetype":"locality"
},
  "geometry": {"coordinates":[87.51885,27.02725],"type":"Point"}
}