{
  "type": "Feature",
  "properties": {
    "gn:admin1_code":"WR",
    "gn:admin2_code":"3",
    "gn:admin3_code":"45.0",
    "gn:admin4_code":"450023.0",
    "gn:asciiname":"Sumsaghat",
    "gn:country_code":"NP",
    "gn:dem":696,
    "gn:feature_class":"P",
    "gn:feature_code":"PPLL",
    "gn:name":"Sumsaghat",
    "gn:population":0,
    "gn:timezone":"Asia/Kathmandu",
    "iso:country":"NP",
    "wof:name":"Sumsaghat",
    "wof:placetype":"locality"
},
  "geometry": {"coordinates":[83.63256,28.15043],"type":"Point"}
}