{
  "type": "Feature",
  "properties": {
    "gn:admin1_code":"MR",
    "gn:admin2_code":"12",
    "gn:admin3_code":"55",
    "gn:admin4_code":"550020",
    "gn:asciiname":"Belghat",
    "gn:country_code":"NP",
    "gn:dem":538,
    "gn:feature_class":"P",
    "gn:feature_code":"PPLL",
    "gn:name":"Belghat",
    "gn:population":0,
    "gn:timezone":"Asia/Kathmandu",
    "iso:country":"NP",
    "wof:name":"Belghat",
    "wof:placetype":"locality"
},
  "geometry": {"coordinates":[81.96715999999998,28.32241],"type":"Point"}
}