{
  "type": "Feature",
  "properties": {
    "gn:admin1_code":"FR",
    "gn:admin2_code":"14",
    "gn:admin3_code":"70.0",
    "gn:admin4_code":"700032.0",
    "gn:asciiname":"Sim",
    "gn:country_code":"NP",
    "gn:dem":2052,
    "gn:feature_class":"P",
    "gn:feature_code":"PPLL",
    "gn:name":"Sim",
    "gn:population":0,
    "gn:timezone":"Asia/Kathmandu",
    "iso:country":"NP",
    "name:bre_x_preferred":[
        "Sim"
    ],
    "name:cat_x_preferred":[
        "Sim"
    ],
    "name:ceb_x_preferred":[
        "Sim"
    ],
    "name:kat_x_preferred":[
        "\u10e1\u10d8\u10db\u10d8"
    ],
    "name:nld_x_preferred":[
        "Sim"
    ],
    "name:nor_x_preferred":[
        "Sim"
    ],
    "name:por_x_preferred":[
        "Sim"
    ],
    "name:spa_x_preferred":[
        "Sim"
    ],
    "name:swe_x_preferred":[
        "SIM"
    ],
    "name:vie_x_preferred":[
        "Sim"
    ],
    "wof:name":"Sim",
    "wof:placetype":"locality"
},
  "geometry": {"coordinates":[80.91315,29.0572],"type":"Point"}
}