{
  "type": "Feature",
  "properties": {
    "gn:admin1_code":"MR",
    "gn:admin2_code":"12",
    "gn:admin3_code":"55",
    "gn:admin4_code":"550019",
    "gn:asciiname":"Kot",
    "gn:country_code":"NP",
    "gn:dem":1327,
    "gn:feature_class":"P",
    "gn:feature_code":"PPLL",
    "gn:name":"Kot",
    "gn:population":0,
    "gn:timezone":"Asia/Kathmandu",
    "iso:country":"NP",
    "name:pol_x_preferred":[
        "Kot"
    ],
    "wof:name":"Kot",
    "wof:placetype":"locality"
},
  "geometry": {"coordinates":[82.22858000000002,28.58861],"type":"Point"}
}