{
  "type": "Feature",
  "properties": {
    "gn:admin1_code":"FR",
    "gn:admin2_code":"14.0",
    "gn:admin3_code":"67.0",
    "gn:admin4_code":"670009.0",
    "gn:asciiname":"Jariyachauka",
    "gn:country_code":"NP",
    "gn:dem":1781,
    "gn:feature_class":"P",
    "gn:feature_code":"PPLL",
    "gn:name":"Jariyachauka",
    "gn:population":0,
    "gn:timezone":"Asia/Kathmandu",
    "iso:country":"NP",
    "wof:name":"Jariyachauka",
    "wof:placetype":"locality"
},
  "geometry": {"coordinates":[81.42766999999998,29.504],"type":"Point"}
}