{
  "type": "Feature",
  "properties": {
    "gn:admin1_code":"ER",
    "gn:admin2_code":"10",
    "gn:admin3_code":"4.0",
    "gn:admin4_code":"40012.0",
    "gn:asciiname":"Bhalukhudi",
    "gn:country_code":"NP",
    "gn:dem":156,
    "gn:feature_class":"P",
    "gn:feature_code":"PPLL",
    "gn:name":"Bhalukhudi",
    "gn:population":0,
    "gn:timezone":"Asia/Kathmandu",
    "iso:country":"NP",
    "wof:name":"Bhalukhudi",
    "wof:placetype":"locality"
},
  "geometry": {"coordinates":[87.69055999999998,26.70252],"type":"Point"}
}