{
  "type": "Feature",
  "properties": {
    "gn:admin1_code":"CR",
    "gn:admin2_code":"1",
    "gn:admin3_code":"29",
    "gn:admin4_code":"290018",
    "gn:asciiname":"Ghormu",
    "gn:country_code":"NP",
    "gn:dem":2012,
    "gn:feature_class":"P",
    "gn:feature_code":"PPLL",
    "gn:name":"Ghormu",
    "gn:population":0,
    "gn:timezone":"Asia/Kathmandu",
    "iso:country":"NP",
    "wof:name":"Ghormu",
    "wof:placetype":"locality"
},
  "geometry": {"coordinates":[85.25848000000001,28.03047],"type":"Point"}
}