{
  "type": "Feature",
  "properties": {
    "gn:admin1_code":"WR",
    "gn:admin2_code":"4",
    "gn:admin3_code":"36.0",
    "gn:admin4_code":"360006.0",
    "gn:asciiname":"Pokharel",
    "gn:country_code":"NP",
    "gn:dem":1023,
    "gn:feature_class":"P",
    "gn:feature_code":"PPLL",
    "gn:name":"Pokharel",
    "gn:population":0,
    "gn:timezone":"Asia/Kathmandu",
    "iso:country":"NP",
    "wof:name":"Pokharel",
    "wof:placetype":"locality"
},
  "geometry": {"coordinates":[84.71342,28.02944],"type":"Point"}
}