{
  "type": "Feature",
  "properties": {
    "gn:admin1_code":"CR",
    "gn:admin2_code":"5",
    "gn:admin3_code":"21",
    "gn:admin4_code":"210047",
    "gn:asciiname":"Dandatol",
    "gn:country_code":"NP",
    "gn:dem":1691,
    "gn:feature_class":"P",
    "gn:feature_code":"PPLL",
    "gn:name":"Dandatol",
    "gn:population":0,
    "gn:timezone":"Asia/Kathmandu",
    "iso:country":"NP",
    "wof:name":"Dandatol",
    "wof:placetype":"locality"
},
  "geometry": {"coordinates":[86.18751999999998,27.55306],"type":"Point"}
}