{
  "type": "Feature",
  "properties": {
    "gn:admin1_code":"MR",
    "gn:admin2_code":"6",
    "gn:admin3_code":"62.0",
    "gn:admin4_code":"620004.0",
    "gn:asciiname":"Karpa",
    "gn:country_code":"NP",
    "gn:dem":2940,
    "gn:feature_class":"P",
    "gn:feature_code":"PPLL",
    "gn:name":"Karpa",
    "gn:population":0,
    "gn:timezone":"Asia/Kathmandu",
    "iso:country":"NP",
    "name:deu_x_preferred":[
        "Karpa"
    ],
    "name:pol_x_preferred":[
        "Karpa"
    ],
    "name:ukr_x_preferred":[
        "\u041a\u0430\u0440\u043f\u0430"
    ],
    "wof:name":"Karpa",
    "wof:placetype":"locality"
},
  "geometry": {"coordinates":[82.89943000000002,28.91339],"type":"Point"}
}