{
  "type": "Feature",
  "properties": {
    "gn:admin1_code":"WR",
    "gn:admin2_code":"4",
    "gn:admin3_code":"36.0",
    "gn:admin4_code":"360015.0",
    "gn:asciiname":"Gyamsetkharka",
    "gn:country_code":"NP",
    "gn:dem":4671,
    "gn:feature_class":"P",
    "gn:feature_code":"PPLL",
    "gn:name":"Gyamsetkharka",
    "gn:population":0,
    "gn:timezone":"Asia/Kathmandu",
    "iso:country":"NP",
    "wof:name":"Gyamsetkharka",
    "wof:placetype":"locality"
},
  "geometry": {"coordinates":[85.00615000000001,28.5364],"type":"Point"}
}