{
  "type": "Feature",
  "properties": {
    "gn:admin1_code":"00",
    "gn:asciiname":"Balankha",
    "gn:country_code":"NP",
    "gn:dem":1497,
    "gn:feature_class":"P",
    "gn:feature_code":"PPL",
    "gn:name":"Bala\u1e45kh\u0101",
    "gn:population":0,
    "gn:timezone":"Asia/Kathmandu",
    "iso:country":"NP",
    "name:nep_x_preferred":[
        "Bala\u1e45kh\u0101"
    ],
    "wof:name":"Balankha",
    "wof:placetype":"locality"
},
  "geometry": {"coordinates":[86.69842,26.94346],"type":"Point"}
}