{
  "type": "Feature",
  "properties": {
    "gn:admin1_code":"CR",
    "gn:admin2_code":"1",
    "gn:admin3_code":"23",
    "gn:admin4_code":"230013",
    "gn:asciiname":"Chokati",
    "gn:country_code":"NP",
    "gn:dem":1605,
    "gn:feature_class":"P",
    "gn:feature_code":"PPLL",
    "gn:name":"Chokati",
    "gn:population":0,
    "gn:timezone":"Asia/Kathmandu",
    "iso:country":"NP",
    "wof:name":"Chokati",
    "wof:placetype":"locality"
},
  "geometry": {"coordinates":[85.96141,27.77567],"type":"Point"}
}