{
  "type": "Feature",
  "properties": {
    "gn:admin1_code":"CR",
    "gn:admin2_code":"1",
    "gn:admin3_code":"28",
    "gn:admin4_code":"280059",
    "gn:asciiname":"Sheradil",
    "gn:country_code":"NP",
    "gn:dem":587,
    "gn:feature_class":"P",
    "gn:feature_code":"PPLL",
    "gn:name":"Sheradil",
    "gn:population":0,
    "gn:timezone":"Asia/Kathmandu",
    "iso:country":"NP",
    "wof:name":"Sheradil",
    "wof:placetype":"locality"
},
  "geometry": {"coordinates":[85.26054000000001,27.88164],"type":"Point"}
}