{
  "type": "Feature",
  "properties": {
    "gn:admin1_code":"FR",
    "gn:admin2_code":"9",
    "gn:admin3_code":"74",
    "gn:admin4_code":"740010",
    "gn:asciiname":"Sera",
    "gn:country_code":"NP",
    "gn:dem":669,
    "gn:feature_class":"P",
    "gn:feature_code":"PPLL",
    "gn:name":"Sera",
    "gn:population":0,
    "gn:timezone":"Asia/Kathmandu",
    "iso:country":"NP",
    "name:bul_x_preferred":[
        "\u0421\u0435\u0440\u0430"
    ],
    "name:ceb_x_preferred":[
        "Sera"
    ],
    "name:deu_x_preferred":[
        "Sera"
    ],
    "name:fin_x_preferred":[
        "Sera"
    ],
    "name:fra_x_preferred":[
        "Sera"
    ],
    "name:ita_x_preferred":[
        "Sera"
    ],
    "name:nld_x_preferred":[
        "Sera"
    ],
    "name:rus_x_preferred":[
        "\u0421\u0435\u0440\u0430"
    ],
    "name:srp_x_preferred":[
        "\u0421\u0435\u0440\u0430"
    ],
    "name:swe_x_preferred":[
        "Sera"
    ],
    "name:ukr_x_preferred":[
        "\u0421\u0435\u0440\u0430"
    ],
    "wof:name":"Sera",
    "wof:placetype":"locality"
},
  "geometry": {"coordinates":[80.41271,29.59522],"type":"Point"}
}