{
  "type": "Feature",
  "properties": {
    "gn:admin1_code":"MR",
    "gn:admin2_code":"2.0",
    "gn:admin3_code":"58.0",
    "gn:admin4_code":"580004.0",
    "gn:asciiname":"Kimire Chareti",
    "gn:country_code":"NP",
    "gn:dem":882,
    "gn:feature_class":"P",
    "gn:feature_code":"PPLL",
    "gn:name":"Kimire Chareti",
    "gn:population":0,
    "gn:timezone":"Asia/Kathmandu",
    "iso:country":"NP",
    "wof:name":"Kimire Chareti",
    "wof:placetype":"locality"
},
  "geometry": {"coordinates":[81.71028000000003,28.33127],"type":"Point"}
}