{
  "type": "Feature",
  "properties": {
    "gn:admin1_code":"MR",
    "gn:admin2_code":"6",
    "gn:admin3_code":"63.0",
    "gn:admin4_code":"630011.0",
    "gn:asciiname":"Khabmu Lagna",
    "gn:country_code":"NP",
    "gn:dem":4401,
    "gn:feature_class":"P",
    "gn:feature_code":"PPLL",
    "gn:name":"Khabmu Lagna",
    "gn:population":0,
    "gn:timezone":"Asia/Kathmandu",
    "iso:country":"NP",
    "wof:name":"Khabmu Lagna",
    "wof:placetype":"locality"
},
  "geometry": {"coordinates":[82.41653000000002,29.09858],"type":"Point"}
}