{
  "type": "Feature",
  "properties": {
    "gn:admin1_code":"FR",
    "gn:admin2_code":"14",
    "gn:admin3_code":"69.0",
    "gn:admin4_code":"690019.0",
    "gn:asciiname":"Salkatne",
    "gn:country_code":"NP",
    "gn:dem":1310,
    "gn:feature_class":"P",
    "gn:feature_code":"PPLL",
    "gn:name":"Salkatne",
    "gn:population":0,
    "gn:timezone":"Asia/Kathmandu",
    "iso:country":"NP",
    "wof:name":"Salkatne",
    "wof:placetype":"locality"
},
  "geometry": {"coordinates":[81.35885,29.1756],"type":"Point"}
}