{
  "type": "Feature",
  "properties": {
    "gn:admin1_code":"CR",
    "gn:admin2_code":"5",
    "gn:admin3_code":"21",
    "gn:admin4_code":"210045",
    "gn:asciiname":"Patighar",
    "gn:country_code":"NP",
    "gn:dem":1328,
    "gn:feature_class":"P",
    "gn:feature_code":"PPLL",
    "gn:name":"Patighar",
    "gn:population":0,
    "gn:timezone":"Asia/Kathmandu",
    "iso:country":"NP",
    "wof:name":"Patighar",
    "wof:placetype":"locality"
},
  "geometry": {"coordinates":[86.07164,27.33174],"type":"Point"}
}