{
  "type": "Feature",
  "properties": {
    "gn:admin1_code":"MR",
    "gn:admin2_code":"12",
    "gn:admin3_code":"54",
    "gn:admin4_code":"540024",
    "gn:asciiname":"Lamduwali",
    "gn:country_code":"NP",
    "gn:dem":1585,
    "gn:feature_class":"P",
    "gn:feature_code":"PPLL",
    "gn:name":"Lamduwali",
    "gn:population":0,
    "gn:timezone":"Asia/Kathmandu",
    "iso:country":"NP",
    "wof:name":"Lamduwali",
    "wof:placetype":"locality"
},
  "geometry": {"coordinates":[82.67234000000001,28.56207],"type":"Point"}
}