{
  "type": "Feature",
  "properties": {
    "gn:admin1_code":"ER",
    "gn:admin2_code":"7",
    "gn:admin3_code":"5",
    "gn:admin4_code":"50065",
    "gn:asciiname":"Malmase",
    "gn:country_code":"NP",
    "gn:dem":759,
    "gn:feature_class":"P",
    "gn:feature_code":"PPLL",
    "gn:name":"Malmase",
    "gn:population":0,
    "gn:timezone":"Asia/Kathmandu",
    "iso:country":"NP",
    "wof:name":"Malmase",
    "wof:placetype":"locality"
},
  "geometry": {"coordinates":[87.50191,26.81509],"type":"Point"}
}