{
  "type": "Feature",
  "properties": {
    "gn:admin1_code":"MR",
    "gn:admin2_code":"2.0",
    "gn:admin3_code":"57.0",
    "gn:admin4_code":"570019.0",
    "gn:asciiname":"Chhagadhawa",
    "gn:country_code":"NP",
    "gn:dem":146,
    "gn:feature_class":"P",
    "gn:feature_code":"PPLL",
    "gn:name":"Chhagadhawa",
    "gn:population":0,
    "gn:timezone":"Asia/Kathmandu",
    "iso:country":"NP",
    "wof:name":"Chhagadhawa",
    "wof:placetype":"locality"
},
  "geometry": {"coordinates":[81.69226999999999,28.07582],"type":"Point"}
}