{
  "type": "Feature",
  "properties": {
    "gn:admin1_code":"WR",
    "gn:admin2_code":"3",
    "gn:admin3_code":"45.0",
    "gn:admin4_code":"450014.0",
    "gn:asciiname":"Pandar",
    "gn:country_code":"NP",
    "gn:dem":2524,
    "gn:feature_class":"P",
    "gn:feature_code":"PPLL",
    "gn:name":"Pandar",
    "gn:population":0,
    "gn:timezone":"Asia/Kathmandu",
    "iso:country":"NP",
    "name:ceb_x_preferred":[
        "Pandar"
    ],
    "name:fas_x_preferred":[
        "\u067e\u0646\u062f\u0631"
    ],
    "name:swe_x_preferred":[
        "Pandar"
    ],
    "wof:name":"Pandar",
    "wof:placetype":"locality"
},
  "geometry": {"coordinates":[82.96955,28.43889],"type":"Point"}
}