{
  "type": "Feature",
  "properties": {
    "gn:admin1_code":"CR",
    "gn:admin2_code":"5",
    "gn:admin3_code":"22.0",
    "gn:admin4_code":"220025.0",
    "gn:asciiname":"Nakarpa",
    "gn:country_code":"NP",
    "gn:dem":1317,
    "gn:feature_class":"P",
    "gn:feature_code":"PPLL",
    "gn:name":"Nakarpa",
    "gn:population":0,
    "gn:timezone":"Asia/Kathmandu",
    "iso:country":"NP",
    "wof:name":"Nakarpa",
    "wof:placetype":"locality"
},
  "geometry": {"coordinates":[86.17814,27.70331],"type":"Point"}
}