{
  "type": "Feature",
  "properties": {
    "gn:admin1_code":"ER",
    "gn:admin2_code":"13",
    "gn:admin3_code":"11",
    "gn:admin4_code":"110021",
    "gn:asciiname":"Chandane",
    "gn:country_code":"NP",
    "gn:dem":2244,
    "gn:feature_class":"P",
    "gn:feature_code":"PPLL",
    "gn:name":"Chandane",
    "gn:population":0,
    "gn:timezone":"Asia/Kathmandu",
    "iso:country":"NP",
    "wof:name":"Chandane",
    "wof:placetype":"locality"
},
  "geometry": {"coordinates":[86.76402,27.43202],"type":"Point"}
}