{
  "type": "Feature",
  "properties": {
    "gn:admin1_code":"CR",
    "gn:admin2_code":"11",
    "gn:admin3_code":"32",
    "gn:admin4_code":"320092",
    "gn:asciiname":"Kathariyatola",
    "gn:country_code":"NP",
    "gn:dem":81,
    "gn:feature_class":"P",
    "gn:feature_code":"PPLL",
    "gn:name":"Kathariyatola",
    "gn:population":0,
    "gn:timezone":"Asia/Kathmandu",
    "iso:country":"NP",
    "wof:name":"Kathariyatola",
    "wof:placetype":"locality"
},
  "geometry": {"coordinates":[85.29595999999999,26.8262],"type":"Point"}
}