{
  "type": "Feature",
  "properties": {
    "gn:admin1_code":"CR",
    "gn:admin2_code":"1",
    "gn:admin3_code":"24.0",
    "gn:admin4_code":"240049.0",
    "gn:asciiname":"Thapagaun",
    "gn:country_code":"NP",
    "gn:dem":1599,
    "gn:feature_class":"P",
    "gn:feature_code":"PPLL",
    "gn:name":"Thapagaun",
    "gn:population":0,
    "gn:timezone":"Asia/Kathmandu",
    "iso:country":"NP",
    "wof:name":"Thapagaun",
    "wof:placetype":"locality"
},
  "geometry": {"coordinates":[85.48915,27.59236],"type":"Point"}
}