{
  "type": "Feature",
  "properties": {
    "gn:admin1_code":"FR",
    "gn:admin2_code":"9",
    "gn:admin3_code":"74",
    "gn:admin4_code":"740005",
    "gn:asciiname":"Kalkatti",
    "gn:country_code":"NP",
    "gn:dem":1587,
    "gn:feature_class":"P",
    "gn:feature_code":"PPLL",
    "gn:name":"Kalkatti",
    "gn:population":0,
    "gn:timezone":"Asia/Kathmandu",
    "iso:country":"NP",
    "wof:name":"Kalkatti",
    "wof:placetype":"locality"
},
  "geometry": {"coordinates":[80.54323000000002,29.49125],"type":"Point"}
}