{
  "type": "Feature",
  "properties": {
    "gn:admin1_code":"WR",
    "gn:admin2_code":"8",
    "gn:admin3_code":"46.0",
    "gn:admin4_code":"460016.0",
    "gn:asciiname":"Dabhung",
    "gn:country_code":"NP",
    "gn:dem":1564,
    "gn:feature_class":"P",
    "gn:feature_code":"PPLL",
    "gn:name":"Dabhung",
    "gn:population":0,
    "gn:timezone":"Asia/Kathmandu",
    "iso:country":"NP",
    "wof:name":"Dabhung",
    "wof:placetype":"locality"
},
  "geometry": {"coordinates":[83.41323,28.07396],"type":"Point"}
}