{
  "type": "Feature",
  "properties": {
    "gn:admin1_code":"MR",
    "gn:admin2_code":"12",
    "gn:admin3_code":"54",
    "gn:admin4_code":"540001",
    "gn:asciiname":"Pokhara",
    "gn:country_code":"NP",
    "gn:dem":1841,
    "gn:feature_class":"P",
    "gn:feature_code":"PPLL",
    "gn:name":"Pokhara",
    "gn:population":0,
    "gn:timezone":"Asia/Kathmandu",
    "iso:country":"NP",
    "wof:name":"Pokhara",
    "wof:placetype":"locality"
},
  "geometry": {"coordinates":[82.3728,28.74989],"type":"Point"}
}