{
  "type": "Feature",
  "properties": {
    "gn:admin1_code":"CR",
    "gn:admin2_code":"5",
    "gn:admin3_code":"20",
    "gn:admin4_code":"200026.0",
    "gn:asciiname":"Kamati",
    "gn:country_code":"NP",
    "gn:dem":447,
    "gn:feature_class":"P",
    "gn:feature_code":"PPLL",
    "gn:name":"Kamati",
    "gn:population":0,
    "gn:timezone":"Asia/Kathmandu",
    "iso:country":"NP",
    "wof:name":"Kamati",
    "wof:placetype":"locality"
},
  "geometry": {"coordinates":[85.72243,27.27796],"type":"Point"}
}