{
  "type": "Feature",
  "properties": {
    "gn:admin1_code":"CR",
    "gn:admin2_code":"11",
    "gn:admin3_code":"31",
    "gn:admin4_code":"310023.0",
    "gn:asciiname":"Dhusrang",
    "gn:country_code":"NP",
    "gn:dem":680,
    "gn:feature_class":"P",
    "gn:feature_code":"PPLL",
    "gn:name":"Dhusrang",
    "gn:population":0,
    "gn:timezone":"Asia/Kathmandu",
    "iso:country":"NP",
    "wof:name":"Dhusrang",
    "wof:placetype":"locality"
},
  "geometry": {"coordinates":[84.89806,27.56181],"type":"Point"}
}