{
  "type": "Feature",
  "properties": {
    "gn:admin1_code":"WR",
    "gn:admin2_code":"4",
    "gn:admin3_code":"40.0",
    "gn:admin4_code":"400029.0",
    "gn:asciiname":"Kasi",
    "gn:country_code":"NP",
    "gn:dem":2881,
    "gn:feature_class":"P",
    "gn:feature_code":"PPLL",
    "gn:name":"Kasi",
    "gn:population":0,
    "gn:timezone":"Asia/Kathmandu",
    "iso:country":"NP",
    "name:ceb_x_preferred":[
        "Kasi"
    ],
    "name:swe_x_preferred":[
        "Kasi"
    ],
    "wof:name":"Kasi",
    "wof:placetype":"locality"
},
  "geometry": {"coordinates":[84.13809999999999,28.42194000000001],"type":"Point"}
}