{
  "type": "Feature",
  "properties": {
    "gn:admin1_code":"ER",
    "gn:admin2_code":"7",
    "gn:admin3_code":"10.0",
    "gn:admin4_code":"100028.0",
    "gn:asciiname":"Baksirang",
    "gn:country_code":"NP",
    "gn:dem":803,
    "gn:feature_class":"P",
    "gn:feature_code":"PPLL",
    "gn:name":"Baksirang",
    "gn:population":0,
    "gn:timezone":"Asia/Kathmandu",
    "iso:country":"NP",
    "wof:name":"Baksirang",
    "wof:placetype":"locality"
},
  "geometry": {"coordinates":[87.17593000000002,27.0129],"type":"Point"}
}