{
  "type": "Feature",
  "properties": {
    "gn:admin1_code":"ER",
    "gn:admin2_code":"10",
    "gn:admin3_code":"2",
    "gn:admin4_code":"20026",
    "gn:asciiname":"Salinge",
    "gn:country_code":"NP",
    "gn:dem":931,
    "gn:feature_class":"P",
    "gn:feature_code":"PPLL",
    "gn:name":"Salinge",
    "gn:population":0,
    "gn:timezone":"Asia/Kathmandu",
    "iso:country":"NP",
    "wof:name":"Salinge",
    "wof:placetype":"locality"
},
  "geometry": {"coordinates":[87.7705,27.23026],"type":"Point"}
}