{
  "type": "Feature",
  "properties": {
    "gn:admin1_code":"ER",
    "gn:admin2_code":"10.0",
    "gn:admin3_code":"1.0",
    "gn:admin4_code":"10045.0",
    "gn:asciiname":"Khemakham",
    "gn:country_code":"NP",
    "gn:dem":1286,
    "gn:feature_class":"P",
    "gn:feature_code":"PPLL",
    "gn:name":"Khemakham",
    "gn:population":0,
    "gn:timezone":"Asia/Kathmandu",
    "iso:country":"NP",
    "wof:name":"Khemakham",
    "wof:placetype":"locality"
},
  "geometry": {"coordinates":[87.74144,27.29558],"type":"Point"}
}