{
  "type": "Feature",
  "properties": {
    "gn:admin1_code":"FR",
    "gn:admin2_code":"9",
    "gn:admin3_code":"73.0",
    "gn:admin4_code":"730002.0",
    "gn:asciiname":"Kurjani",
    "gn:country_code":"NP",
    "gn:dem":952,
    "gn:feature_class":"P",
    "gn:feature_code":"PPLL",
    "gn:name":"Kurjani",
    "gn:population":0,
    "gn:timezone":"Asia/Kathmandu",
    "iso:country":"NP",
    "wof:name":"Kurjani",
    "wof:placetype":"locality"
},
  "geometry": {"coordinates":[80.48263,29.10231],"type":"Point"}
}