{
  "type": "Feature",
  "properties": {
    "gn:admin1_code":"FR",
    "gn:admin2_code":"14",
    "gn:admin3_code":"68",
    "gn:admin4_code":"680037",
    "gn:asciiname":"Khan",
    "gn:country_code":"NP",
    "gn:dem":1782,
    "gn:feature_class":"P",
    "gn:feature_code":"PPLL",
    "gn:name":"Khan",
    "gn:population":0,
    "gn:timezone":"Asia/Kathmandu",
    "iso:country":"NP",
    "name:ara_x_preferred":[
        "\u062e\u0627\u0646"
    ],
    "name:azb_x_preferred":[
        "\u062e\u0627\u0646"
    ],
    "name:cat_x_preferred":[
        "Khan"
    ],
    "name:ceb_x_preferred":[
        "Khan"
    ],
    "name:ces_x_preferred":[
        "Khan"
    ],
    "name:deu_x_preferred":[
        "Khan"
    ],
    "name:fas_x_preferred":[
        "\u062e\u0627\u0646"
    ],
    "name:fin_x_preferred":[
        "Khan"
    ],
    "name:fra_x_preferred":[
        "Khan"
    ],
    "name:ido_x_preferred":[
        "Khan"
    ],
    "name:ita_x_preferred":[
        "Khan"
    ],
    "name:jpn_x_preferred":[
        "\u30ab\u30fc\u30f3"
    ],
    "name:nld_x_preferred":[
        "Khan"
    ],
    "name:por_x_preferred":[
        "Khan"
    ],
    "name:urd_x_preferred":[
        "\u062e\u0627\u0646"
    ],
    "name:zho_x_preferred":[
        "Khan"
    ],
    "wof:name":"Khan",
    "wof:placetype":"locality"
},
  "geometry": {"coordinates":[81.11721999999997,29.46335],"type":"Point"}
}