{
  "type": "Feature",
  "properties": {
    "gn:admin1_code":"FR",
    "gn:admin2_code":"14",
    "gn:admin3_code":"68",
    "gn:admin4_code":"680037",
    "gn:asciiname":"Khan",
    "gn:country_code":"NP",
    "gn:dem":1782,
    "gn:feature_class":"P",
    "gn:feature_code":"PPLL",
    "gn:name":"Khan",
    "gn:population":0,
    "gn:timezone":"Asia/Kathmandu",
    "iso:country":"NP",
    "wof:name":"Khan",
    "wof:placetype":"locality"
},
  "geometry": {"coordinates":[81.11721999999997,29.46335],"type":"Point"}
}