{
  "type": "Feature",
  "properties": {
    "gn:admin1_code":"MR",
    "gn:admin2_code":"12",
    "gn:admin3_code":"54",
    "gn:admin4_code":"540001",
    "gn:asciiname":"Damar",
    "gn:country_code":"NP",
    "gn:dem":1560,
    "gn:feature_class":"P",
    "gn:feature_code":"PPLL",
    "gn:name":"Damar",
    "gn:population":0,
    "gn:timezone":"Asia/Kathmandu",
    "iso:country":"NP",
    "name:aze_x_preferred":[
        "Damar sistemi"
    ],
    "name:ceb_x_preferred":[
        "Damar"
    ],
    "name:deu_x_preferred":[
        "Damar"
    ],
    "name:ind_x_preferred":[
        "Damar"
    ],
    "name:ita_x_preferred":[
        "Damar"
    ],
    "name:jav_x_preferred":[
        "Damar"
    ],
    "name:msa_x_preferred":[
        "Damar"
    ],
    "name:nld_x_preferred":[
        "Damar"
    ],
    "name:por_x_preferred":[
        "Damar"
    ],
    "name:swe_x_preferred":[
        "Damar"
    ],
    "name:tur_x_preferred":[
        "Damar"
    ],
    "wof:name":"Damar",
    "wof:placetype":"locality"
},
  "geometry": {"coordinates":[82.40244,28.74245],"type":"Point"}
}