{
  "type": "Feature",
  "properties": {
    "gn:admin1_code":"CR",
    "gn:admin2_code":"11",
    "gn:admin3_code":"31",
    "gn:admin4_code":"310044",
    "gn:asciiname":"Dhuseni",
    "gn:country_code":"NP",
    "gn:dem":1425,
    "gn:feature_class":"P",
    "gn:feature_code":"PPLL",
    "gn:name":"Dhuseni",
    "gn:population":0,
    "gn:timezone":"Asia/Kathmandu",
    "iso:country":"NP",
    "wof:name":"Dhuseni",
    "wof:placetype":"locality"
},
  "geometry": {"coordinates":[85.08161,27.68816],"type":"Point"}
}