{
  "type": "Feature",
  "properties": {
    "gn:admin1_code":"WR",
    "gn:admin2_code":"3",
    "gn:admin3_code":"44",
    "gn:admin4_code":"440042.0",
    "gn:asciiname":"Sulikot",
    "gn:country_code":"NP",
    "gn:dem":1793,
    "gn:feature_class":"P",
    "gn:feature_code":"PPLL",
    "gn:name":"Sulikot",
    "gn:population":0,
    "gn:timezone":"Asia/Kathmandu",
    "iso:country":"NP",
    "wof:name":"Sulikot",
    "wof:placetype":"locality"
},
  "geometry": {"coordinates":[83.6454,28.10904],"type":"Point"}
}