{
  "type": "Feature",
  "properties": {
    "gn:admin1_code":"WR",
    "gn:admin2_code":"4",
    "gn:admin3_code":"37",
    "gn:admin4_code":"370018",
    "gn:asciiname":"Jalkeni",
    "gn:country_code":"NP",
    "gn:dem":960,
    "gn:feature_class":"P",
    "gn:feature_code":"PPLL",
    "gn:name":"Jalkeni",
    "gn:population":0,
    "gn:timezone":"Asia/Kathmandu",
    "iso:country":"NP",
    "wof:name":"Jalkeni",
    "wof:placetype":"locality"
},
  "geometry": {"coordinates":[84.35217,28.16026],"type":"Point"}
}