{
  "type": "Feature",
  "properties": {
    "gn:admin1_code":"MR",
    "gn:admin2_code":"2",
    "gn:admin3_code":"60.0",
    "gn:admin4_code":"600015.0",
    "gn:asciiname":"Saglena",
    "gn:country_code":"NP",
    "gn:dem":985,
    "gn:feature_class":"P",
    "gn:feature_code":"PPLL",
    "gn:name":"Saglena",
    "gn:population":0,
    "gn:timezone":"Asia/Kathmandu",
    "iso:country":"NP",
    "wof:name":"Saglena",
    "wof:placetype":"locality"
},
  "geometry": {"coordinates":[81.62743,28.85562],"type":"Point"}
}