{
  "type": "Feature",
  "properties": {
    "gn:admin1_code":"ER",
    "gn:admin2_code":"7",
    "gn:admin3_code":"10.0",
    "gn:admin4_code":"100049.0",
    "gn:asciiname":"Dopkile",
    "gn:country_code":"NP",
    "gn:dem":885,
    "gn:feature_class":"P",
    "gn:feature_code":"PPLL",
    "gn:name":"Dopkile",
    "gn:population":0,
    "gn:timezone":"Asia/Kathmandu",
    "iso:country":"NP",
    "wof:name":"Dopkile",
    "wof:placetype":"locality"
},
  "geometry": {"coordinates":[87.11978000000001,27.05228],"type":"Point"}
}