{
  "type": "Feature",
  "properties": {
    "gn:admin1_code":"WR",
    "gn:admin2_code":"4",
    "gn:admin3_code":"37",
    "gn:admin4_code":"370023",
    "gn:asciiname":"Kallebesi",
    "gn:country_code":"NP",
    "gn:dem":1009,
    "gn:feature_class":"P",
    "gn:feature_code":"PPLL",
    "gn:name":"Kallebesi",
    "gn:population":0,
    "gn:timezone":"Asia/Kathmandu",
    "iso:country":"NP",
    "wof:name":"Kallebesi",
    "wof:placetype":"locality"
},
  "geometry": {"coordinates":[84.62153000000001,28.182],"type":"Point"}
}