{
  "type": "Feature",
  "properties": {
    "gn:admin1_code":"CR",
    "gn:admin2_code":"1",
    "gn:admin3_code":"25",
    "gn:admin4_code":"250013",
    "gn:asciiname":"Mathillo Burangchule",
    "gn:country_code":"NP",
    "gn:dem":1666,
    "gn:feature_class":"P",
    "gn:feature_code":"PPLL",
    "gn:name":"Mathillo Burangchule",
    "gn:population":0,
    "gn:timezone":"Asia/Kathmandu",
    "iso:country":"NP",
    "wof:name":"Mathillo Burangchule",
    "wof:placetype":"locality"
},
  "geometry": {"coordinates":[85.29709,27.5626],"type":"Point"}
}