{
  "type": "Feature",
  "properties": {
    "gn:admin1_code":"CR",
    "gn:admin2_code":"11.0",
    "gn:admin3_code":"33.0",
    "gn:admin4_code":"330034.0",
    "gn:asciiname":"Sundarbasti",
    "gn:country_code":"NP",
    "gn:dem":127,
    "gn:feature_class":"P",
    "gn:feature_code":"PPLL",
    "gn:name":"Sundarbasti",
    "gn:population":0,
    "gn:timezone":"Asia/Kathmandu",
    "iso:country":"NP",
    "wof:name":"Sundarbasti",
    "wof:placetype":"locality"
},
  "geometry": {"coordinates":[85.01615,27.14165],"type":"Point"}
}