{
  "type": "Feature",
  "properties": {
    "gn:admin1_code":"ER",
    "gn:admin2_code":"10",
    "gn:admin3_code":"4.0",
    "gn:admin4_code":"40001.0",
    "gn:asciiname":"Jhanjibari",
    "gn:country_code":"NP",
    "gn:dem":129,
    "gn:feature_class":"P",
    "gn:feature_code":"PPLL",
    "gn:name":"Jhanjibari",
    "gn:population":0,
    "gn:timezone":"Asia/Kathmandu",
    "iso:country":"NP",
    "wof:name":"Jhanjibari",
    "wof:placetype":"locality"
},
  "geometry": {"coordinates":[88.00784,26.64046],"type":"Point"}
}