{
  "type": "Feature",
  "properties": {
    "gn:admin1_code":"ER",
    "gn:admin2_code":"7",
    "gn:admin3_code":"9",
    "gn:admin4_code":"90034",
    "gn:asciiname":"Bastala",
    "gn:country_code":"NP",
    "gn:dem":1308,
    "gn:feature_class":"P",
    "gn:feature_code":"PPLL",
    "gn:name":"Bastala",
    "gn:population":0,
    "gn:timezone":"Asia/Kathmandu",
    "iso:country":"NP",
    "wof:name":"Bastala",
    "wof:placetype":"locality"
},
  "geometry": {"coordinates":[87.21736999999997,27.53995],"type":"Point"}
}