{
  "type": "Feature",
  "properties": {
    "gn:admin1_code":"FR",
    "gn:admin2_code":"9",
    "gn:admin3_code":"73.0",
    "gn:admin4_code":"730011.0",
    "gn:asciiname":"Arkattegaun",
    "gn:country_code":"NP",
    "gn:dem":1229,
    "gn:feature_class":"P",
    "gn:feature_code":"PPLL",
    "gn:name":"Arkattegaun",
    "gn:population":0,
    "gn:timezone":"Asia/Kathmandu",
    "iso:country":"NP",
    "wof:name":"Arkattegaun",
    "wof:placetype":"locality"
},
  "geometry": {"coordinates":[80.67695999999999,29.30167],"type":"Point"}
}