{
  "type": "Feature",
  "properties": {
    "gn:admin1_code":"CR",
    "gn:admin2_code":"1",
    "gn:admin3_code":"25",
    "gn:admin4_code":"250026.0",
    "gn:asciiname":"Sano Khokana",
    "gn:country_code":"NP",
    "gn:dem":1313,
    "gn:feature_class":"P",
    "gn:feature_code":"PPLL",
    "gn:name":"Sano Khokana",
    "gn:population":0,
    "gn:timezone":"Asia/Kathmandu",
    "iso:country":"NP",
    "wof:name":"Sano Khokana",
    "wof:placetype":"locality"
},
  "geometry": {"coordinates":[85.29629,27.64628],"type":"Point"}
}