{
  "type": "Feature",
  "properties": {
    "gn:admin1_code":"ER",
    "gn:admin2_code":"10",
    "gn:admin3_code":"2",
    "gn:admin4_code":"20004",
    "gn:asciiname":"Phedapa",
    "gn:country_code":"NP",
    "gn:dem":1041,
    "gn:feature_class":"P",
    "gn:feature_code":"PPLL",
    "gn:name":"Phedapa",
    "gn:population":0,
    "gn:timezone":"Asia/Kathmandu",
    "iso:country":"NP",
    "wof:name":"Phedapa",
    "wof:placetype":"locality"
},
  "geometry": {"coordinates":[87.77346999999997,27.26363],"type":"Point"}
}