{
  "type": "Feature",
  "properties": {
    "gn:admin1_code":"ER",
    "gn:admin2_code":"13",
    "gn:admin3_code":"11",
    "gn:admin4_code":"110020",
    "gn:asciiname":"Dojum Surke",
    "gn:country_code":"NP",
    "gn:dem":2404,
    "gn:feature_class":"P",
    "gn:feature_code":"PPLL",
    "gn:name":"Dojum Surke",
    "gn:population":0,
    "gn:timezone":"Asia/Kathmandu",
    "iso:country":"NP",
    "wof:name":"Dojum Surke",
    "wof:placetype":"locality"
},
  "geometry": {"coordinates":[86.54658000000001,27.53615],"type":"Point"}
}