{
  "type": "Feature",
  "properties": {
    "gn:admin1_code":"FR",
    "gn:admin2_code":"9",
    "gn:admin3_code":"74",
    "gn:admin4_code":"740030",
    "gn:asciiname":"DhamiIjar",
    "gn:country_code":"NP",
    "gn:dem":1999,
    "gn:feature_class":"P",
    "gn:feature_code":"PPLL",
    "gn:name":"DhamiIjar",
    "gn:population":0,
    "gn:timezone":"Asia/Kathmandu",
    "iso:country":"NP",
    "wof:name":"DhamiIjar",
    "wof:placetype":"locality"
},
  "geometry": {"coordinates":[80.77225,29.68494],"type":"Point"}
}