{
  "type": "Feature",
  "properties": {
    "gn:admin1_code":"WR",
    "gn:admin2_code":"4",
    "gn:admin3_code":"36.0",
    "gn:admin4_code":"360039.0",
    "gn:asciiname":"Hokam",
    "gn:country_code":"NP",
    "gn:dem":2476,
    "gn:feature_class":"P",
    "gn:feature_code":"PPLL",
    "gn:name":"Hokam",
    "gn:population":0,
    "gn:timezone":"Asia/Kathmandu",
    "iso:country":"NP",
    "wof:name":"Hokam",
    "wof:placetype":"locality"
},
  "geometry": {"coordinates":[84.78558000000002,28.53368],"type":"Point"}
}