{
  "type": "Feature",
  "properties": {
    "gn:admin1_code":"ER",
    "gn:admin2_code":"10.0",
    "gn:admin3_code":"1.0",
    "gn:admin4_code":"10013.0",
    "gn:asciiname":"Tingdu",
    "gn:country_code":"NP",
    "gn:dem":1716,
    "gn:feature_class":"P",
    "gn:feature_code":"PPLL",
    "gn:name":"Tingdu",
    "gn:population":0,
    "gn:timezone":"Asia/Kathmandu",
    "iso:country":"NP",
    "wof:name":"Tingdu",
    "wof:placetype":"locality"
},
  "geometry": {"coordinates":[87.68604000000001,27.45012],"type":"Point"}
}