{
  "type": "Feature",
  "properties": {
    "gn:admin1_code":"ER",
    "gn:admin2_code":"7",
    "gn:admin3_code":"10.0",
    "gn:admin4_code":"100010.0",
    "gn:asciiname":"Mansaram",
    "gn:country_code":"NP",
    "gn:dem":1045,
    "gn:feature_class":"P",
    "gn:feature_code":"PPLL",
    "gn:name":"Mansaram",
    "gn:population":0,
    "gn:timezone":"Asia/Kathmandu",
    "iso:country":"NP",
    "wof:name":"Mansaram",
    "wof:placetype":"locality"
},
  "geometry": {"coordinates":[87.00846,27.09226],"type":"Point"}
}