{
  "type": "Feature",
  "properties": {
    "gn:admin1_code":"CR",
    "gn:admin2_code":"1",
    "gn:admin3_code":"24.0",
    "gn:admin4_code":"240012.0",
    "gn:asciiname":"Salmegaun",
    "gn:country_code":"NP",
    "gn:dem":2046,
    "gn:feature_class":"P",
    "gn:feature_code":"PPLL",
    "gn:name":"Salmegaun",
    "gn:population":0,
    "gn:timezone":"Asia/Kathmandu",
    "iso:country":"NP",
    "wof:name":"Salmegaun",
    "wof:placetype":"locality"
},
  "geometry": {"coordinates":[85.67345,27.44098],"type":"Point"}
}