{
  "type": "Feature",
  "properties": {
    "gn:admin1_code":"FR",
    "gn:admin2_code":"14",
    "gn:admin3_code":"70.0",
    "gn:admin4_code":"700040.0",
    "gn:asciiname":"Kotigaun",
    "gn:country_code":"NP",
    "gn:dem":1147,
    "gn:feature_class":"P",
    "gn:feature_code":"PPLL",
    "gn:name":"Kotigaun",
    "gn:population":0,
    "gn:timezone":"Asia/Kathmandu",
    "iso:country":"NP",
    "wof:name":"Kotigaun",
    "wof:placetype":"locality"
},
  "geometry": {"coordinates":[80.83925000000001,29.25191],"type":"Point"}
}