{
  "type": "Feature",
  "properties": {
    "gn:admin1_code":"MR",
    "gn:admin2_code":"6",
    "gn:admin3_code":"65",
    "gn:admin4_code":"650013",
    "gn:asciiname":"Patre Chattan",
    "gn:country_code":"NP",
    "gn:dem":3364,
    "gn:feature_class":"P",
    "gn:feature_code":"PPLL",
    "gn:name":"Patre Chattan",
    "gn:population":0,
    "gn:timezone":"Asia/Kathmandu",
    "iso:country":"NP",
    "wof:name":"Patre Chattan",
    "wof:placetype":"locality"
},
  "geometry": {"coordinates":[82.07833000000002,29.68844],"type":"Point"}
}