{
  "type": "Feature",
  "properties": {
    "gn:admin1_code":"MR",
    "gn:admin2_code":"6",
    "gn:admin3_code":"65",
    "gn:admin4_code":"650018",
    "gn:asciiname":"Jhakot",
    "gn:country_code":"NP",
    "gn:dem":2332,
    "gn:feature_class":"P",
    "gn:feature_code":"PPLL",
    "gn:name":"Jhakot",
    "gn:population":0,
    "gn:timezone":"Asia/Kathmandu",
    "iso:country":"NP",
    "wof:name":"Jhakot",
    "wof:placetype":"locality"
},
  "geometry": {"coordinates":[82.19287,29.52853],"type":"Point"}
}