{
  "type": "Feature",
  "properties": {
    "gn:admin1_code":"WR",
    "gn:admin2_code":"3",
    "gn:admin3_code":"43",
    "gn:admin4_code":"430020",
    "gn:asciiname":"Panela",
    "gn:country_code":"NP",
    "gn:dem":2127,
    "gn:feature_class":"P",
    "gn:feature_code":"PPLL",
    "gn:name":"Panela",
    "gn:population":0,
    "gn:timezone":"Asia/Kathmandu",
    "iso:country":"NP",
    "name:cat_x_preferred":[
        "Panela"
    ],
    "name:deu_x_preferred":[
        "Panela"
    ],
    "name:fra_x_preferred":[
        "Panela"
    ],
    "name:glg_x_preferred":[
        "Panela"
    ],
    "name:ita_x_preferred":[
        "Panela"
    ],
    "name:mwl_x_preferred":[
        "Rapadura"
    ],
    "name:nld_x_preferred":[
        "Oersuiker"
    ],
    "name:por_x_preferred":[
        "Rapadura"
    ],
    "name:scn_x_preferred":[
        "Arraspata"
    ],
    "name:spa_x_preferred":[
        "Panela"
    ],
    "wof:name":"Panela",
    "wof:placetype":"locality"
},
  "geometry": {"coordinates":[83.52275,28.551],"type":"Point"}
}