{
  "type": "Feature",
  "properties": {
    "gn:admin1_code":"WR",
    "gn:admin2_code":"4",
    "gn:admin3_code":"37",
    "gn:admin4_code":"370057",
    "gn:asciiname":"Bhitola",
    "gn:country_code":"NP",
    "gn:dem":1166,
    "gn:feature_class":"P",
    "gn:feature_code":"PPLL",
    "gn:name":"Bhitola",
    "gn:population":0,
    "gn:timezone":"Asia/Kathmandu",
    "iso:country":"NP",
    "wof:name":"Bhitola",
    "wof:placetype":"locality"
},
  "geometry": {"coordinates":[84.28421999999998,28.13484],"type":"Point"}
}