{
  "type": "Feature",
  "properties": {
    "gn:admin1_code":"MR",
    "gn:admin2_code":"12",
    "gn:admin3_code":"53",
    "gn:admin4_code":"530042",
    "gn:asciiname":"Molchabang",
    "gn:country_code":"NP",
    "gn:dem":1624,
    "gn:feature_class":"P",
    "gn:feature_code":"PPLL",
    "gn:name":"Molchabang",
    "gn:population":0,
    "gn:timezone":"Asia/Kathmandu",
    "iso:country":"NP",
    "wof:name":"Molchabang",
    "wof:placetype":"locality"
},
  "geometry": {"coordinates":[82.81565999999999,28.37561],"type":"Point"}
}