{
  "type": "Feature",
  "properties": {
    "gn:admin1_code":"WR",
    "gn:admin2_code":"4",
    "gn:admin3_code":"36.0",
    "gn:admin4_code":"360030.0",
    "gn:asciiname":"Mallatar",
    "gn:country_code":"NP",
    "gn:dem":740,
    "gn:feature_class":"P",
    "gn:feature_code":"PPLL",
    "gn:name":"Mallatar",
    "gn:population":0,
    "gn:timezone":"Asia/Kathmandu",
    "iso:country":"NP",
    "wof:name":"Mallatar",
    "wof:placetype":"locality"
},
  "geometry": {"coordinates":[84.53757,28.09202],"type":"Point"}
}