{
  "type": "Feature",
  "properties": {
    "gn:admin1_code":"ER",
    "gn:admin2_code":"10",
    "gn:admin3_code":"2",
    "gn:admin4_code":"20029",
    "gn:asciiname":"Dhodeni",
    "gn:country_code":"NP",
    "gn:dem":1577,
    "gn:feature_class":"P",
    "gn:feature_code":"PPLL",
    "gn:name":"Dhodeni",
    "gn:population":0,
    "gn:timezone":"Asia/Kathmandu",
    "iso:country":"NP",
    "wof:name":"Dhodeni",
    "wof:placetype":"locality"
},
  "geometry": {"coordinates":[87.78922,27.12894],"type":"Point"}
}