{
  "type": "Feature",
  "properties": {
    "gn:admin1_code":"ER",
    "gn:admin2_code":"10",
    "gn:admin3_code":"2",
    "gn:admin4_code":"20029",
    "gn:asciiname":"Dhodeni",
    "gn:country_code":"NP",
    "gn:dem":1577,
    "gn:feature_class":"P",
    "gn:feature_code":"PPLL",
    "gn:name":"Dhodeni",
    "gn:population":0,
    "gn:timezone":"Asia/Kathmandu",
    "iso:country":"NP",
    "name:ceb_x_preferred":[
        "Dhodeni"
    ],
    "name:fra_x_preferred":[
        "Dhodeni"
    ],
    "name:hin_x_preferred":[
        "\u0927\u094b\u0926\u0947\u0928\u0940"
    ],
    "name:msa_x_preferred":[
        "Dhodeni"
    ],
    "name:nep_x_preferred":[
        "\u0927\u094b\u0926\u0947\u0928\u0940"
    ],
    "name:new_x_preferred":[
        "\u0927\u094b\u0926\u0947\u0928\u0940"
    ],
    "name:pol_x_preferred":[
        "Dhodeni"
    ],
    "wof:name":"Dhodeni",
    "wof:placetype":"locality"
},
  "geometry": {"coordinates":[87.78922,27.12894],"type":"Point"}
}