{
  "type": "Feature",
  "properties": {
    "gn:admin1_code":"MR",
    "gn:admin2_code":"2.0",
    "gn:admin3_code":"59.0",
    "gn:admin4_code":"590034.0",
    "gn:asciiname":"Kich",
    "gn:country_code":"NP",
    "gn:dem":579,
    "gn:feature_class":"P",
    "gn:feature_code":"PPLL",
    "gn:name":"Kich",
    "gn:population":0,
    "gn:timezone":"Asia/Kathmandu",
    "iso:country":"NP",
    "wof:name":"Kich",
    "wof:placetype":"locality"
},
  "geometry": {"coordinates":[81.7706,28.42683],"type":"Point"}
}