{
  "type": "Feature",
  "properties": {
    "gn:admin1_code":"CR",
    "gn:admin2_code":"1",
    "gn:admin3_code":"24.0",
    "gn:admin4_code":"240047.0",
    "gn:asciiname":"Upretithok",
    "gn:country_code":"NP",
    "gn:dem":921,
    "gn:feature_class":"P",
    "gn:feature_code":"PPLL",
    "gn:name":"Upretithok",
    "gn:population":0,
    "gn:timezone":"Asia/Kathmandu",
    "iso:country":"NP",
    "wof:name":"Upretithok",
    "wof:placetype":"locality"
},
  "geometry": {"coordinates":[85.71041,27.60304],"type":"Point"}
}