{
  "type": "Feature",
  "properties": {
    "gn:admin1_code":"CR",
    "gn:admin2_code":"1",
    "gn:admin3_code":"30.0",
    "gn:admin4_code":"300030.0",
    "gn:asciiname":"Barsanchet",
    "gn:country_code":"NP",
    "gn:dem":1091,
    "gn:feature_class":"P",
    "gn:feature_code":"PPLL",
    "gn:name":"Barsanchet",
    "gn:population":0,
    "gn:timezone":"Asia/Kathmandu",
    "iso:country":"NP",
    "wof:name":"Barsanchet",
    "wof:placetype":"locality"
},
  "geometry": {"coordinates":[84.99254999999999,28.01478],"type":"Point"}
}