{
  "type": "Feature",
  "properties": {
    "gn:admin1_code":"WR",
    "gn:admin2_code":"8",
    "gn:admin3_code":"46.0",
    "gn:admin4_code":"460058.0",
    "gn:asciiname":"Namatgaun",
    "gn:country_code":"NP",
    "gn:dem":1293,
    "gn:feature_class":"P",
    "gn:feature_code":"PPLL",
    "gn:name":"Namatgaun",
    "gn:population":0,
    "gn:timezone":"Asia/Kathmandu",
    "iso:country":"NP",
    "wof:name":"Namatgaun",
    "wof:placetype":"locality"
},
  "geometry": {"coordinates":[83.12684,28.19837],"type":"Point"}
}