{
  "type": "Feature",
  "properties": {
    "gn:admin1_code":"FR",
    "gn:admin2_code":"9",
    "gn:admin3_code":"74",
    "gn:admin4_code":"740012",
    "gn:asciiname":"Khola",
    "gn:country_code":"NP",
    "gn:dem":1447,
    "gn:feature_class":"P",
    "gn:feature_code":"PPLL",
    "gn:name":"Khola",
    "gn:population":0,
    "gn:timezone":"Asia/Kathmandu",
    "iso:country":"NP",
    "name:deu_x_preferred":[
        "Khola"
    ],
    "wof:name":"Khola",
    "wof:placetype":"locality"
},
  "geometry": {"coordinates":[80.52500999999999,29.5899],"type":"Point"}
}