{
  "type": "Feature",
  "properties": {
    "gn:admin1_code":"CR",
    "gn:admin2_code":"5",
    "gn:admin3_code":"19",
    "gn:admin4_code":"190020.0",
    "gn:asciiname":"Dharmapurtol",
    "gn:country_code":"NP",
    "gn:dem":94,
    "gn:feature_class":"P",
    "gn:feature_code":"PPLL",
    "gn:name":"Dharmapurtol",
    "gn:population":0,
    "gn:timezone":"Asia/Kathmandu",
    "iso:country":"NP",
    "wof:name":"Dharmapurtol",
    "wof:placetype":"locality"
},
  "geometry": {"coordinates":[85.59753000000001,26.90059],"type":"Point"}
}