{
  "type": "Feature",
  "properties": {
    "gn:admin1_code":"MR",
    "gn:admin2_code":"2.0",
    "gn:admin3_code":"59.0",
    "gn:admin4_code":"590032.0",
    "gn:asciiname":"Sinkauli",
    "gn:country_code":"NP",
    "gn:dem":702,
    "gn:feature_class":"P",
    "gn:feature_code":"PPLL",
    "gn:name":"Sinkauli",
    "gn:population":0,
    "gn:timezone":"Asia/Kathmandu",
    "iso:country":"NP",
    "wof:name":"Sinkauli",
    "wof:placetype":"locality"
},
  "geometry": {"coordinates":[81.54985000000001,28.51742],"type":"Point"}
}