{
  "type": "Feature",
  "properties": {
    "gn:admin1_code":"MR",
    "gn:admin2_code":"12",
    "gn:admin3_code":"56.0",
    "gn:admin4_code":"560035.0",
    "gn:asciiname":"Sisanikhuti",
    "gn:country_code":"NP",
    "gn:dem":590,
    "gn:feature_class":"P",
    "gn:feature_code":"PPLL",
    "gn:name":"Sisanikhuti",
    "gn:population":0,
    "gn:timezone":"Asia/Kathmandu",
    "iso:country":"NP",
    "wof:name":"Sisanikhuti",
    "wof:placetype":"locality"
},
  "geometry": {"coordinates":[82.65508,27.91345],"type":"Point"}
}