{
  "type": "Feature",
  "properties": {
    "gn:admin1_code":"WR",
    "gn:admin2_code":"8",
    "gn:admin3_code":"48",
    "gn:admin4_code":"480018",
    "gn:asciiname":"Baskhola",
    "gn:country_code":"NP",
    "gn:dem":607,
    "gn:feature_class":"P",
    "gn:feature_code":"PPLL",
    "gn:name":"Baskhola",
    "gn:population":0,
    "gn:timezone":"Asia/Kathmandu",
    "iso:country":"NP",
    "wof:name":"Baskhola",
    "wof:placetype":"locality"
},
  "geometry": {"coordinates":[83.80662,27.59468],"type":"Point"}
}