{
  "type": "Feature",
  "properties": {
    "gn:admin1_code":"CR",
    "gn:admin2_code":"5",
    "gn:admin3_code":"21",
    "gn:admin4_code":"210026",
    "gn:asciiname":"Thanti",
    "gn:country_code":"NP",
    "gn:dem":1352,
    "gn:feature_class":"P",
    "gn:feature_code":"PPLL",
    "gn:name":"Thanti",
    "gn:population":0,
    "gn:timezone":"Asia/Kathmandu",
    "iso:country":"NP",
    "wof:name":"Thanti",
    "wof:placetype":"locality"
},
  "geometry": {"coordinates":[86.12549,27.3921],"type":"Point"}
}