{
  "type": "Feature",
  "properties": {
    "gn:admin1_code":"MR",
    "gn:admin2_code":"12",
    "gn:admin3_code":"54",
    "gn:admin4_code":"540006",
    "gn:asciiname":"Beteni",
    "gn:country_code":"NP",
    "gn:dem":1078,
    "gn:feature_class":"P",
    "gn:feature_code":"PPLL",
    "gn:name":"Beteni",
    "gn:population":0,
    "gn:timezone":"Asia/Kathmandu",
    "iso:country":"NP",
    "name:mai_x_preferred":[
        "\u092c\u0947\u0924\u093f\u0928\u0940"
    ],
    "name:msa_x_preferred":[
        "Beteni"
    ],
    "name:pol_x_preferred":[
        "Beteni"
    ],
    "wof:name":"Beteni",
    "wof:placetype":"locality"
},
  "geometry": {"coordinates":[82.24160999999999,28.63023],"type":"Point"}
}