{
  "type": "Feature",
  "properties": {
    "gn:admin1_code":"ER",
    "gn:admin2_code":"7",
    "gn:admin3_code":"10.0",
    "gn:admin4_code":"100056.0",
    "gn:asciiname":"Punungukholagaun",
    "gn:country_code":"NP",
    "gn:dem":922,
    "gn:feature_class":"P",
    "gn:feature_code":"PPLL",
    "gn:name":"Punungukholagaun",
    "gn:population":0,
    "gn:timezone":"Asia/Kathmandu",
    "iso:country":"NP",
    "wof:name":"Punungukholagaun",
    "wof:placetype":"locality"
},
  "geometry": {"coordinates":[87.01964,26.97273],"type":"Point"}
}