{
  "type": "Feature",
  "properties": {
    "gn:admin1_code":"FR",
    "gn:admin2_code":"14",
    "gn:admin3_code":"70.0",
    "gn:admin4_code":"700031.0",
    "gn:asciiname":"Dhari",
    "gn:country_code":"NP",
    "gn:dem":1587,
    "gn:feature_class":"P",
    "gn:feature_code":"PPLL",
    "gn:name":"Dhari",
    "gn:population":0,
    "gn:timezone":"Asia/Kathmandu",
    "iso:country":"NP",
    "name:ceb_x_preferred":[
        "Dhari"
    ],
    "name:swe_x_preferred":[
        "Dhari"
    ],
    "wof:name":"Dhari",
    "wof:placetype":"locality"
},
  "geometry": {"coordinates":[80.8098,29.33973],"type":"Point"}
}