{
  "type": "Feature",
  "properties": {
    "gn:admin1_code":"WR",
    "gn:admin2_code":"4.0",
    "gn:admin3_code":"38.0",
    "gn:admin4_code":"380015.0",
    "gn:asciiname":"Kali Pokhari",
    "gn:country_code":"NP",
    "gn:dem":890,
    "gn:feature_class":"P",
    "gn:feature_code":"PPLL",
    "gn:name":"Kali Pokhari",
    "gn:population":0,
    "gn:timezone":"Asia/Kathmandu",
    "iso:country":"NP",
    "wof:name":"Kali Pokhari",
    "wof:placetype":"locality"
},
  "geometry": {"coordinates":[84.40606,28.11216],"type":"Point"}
}