{
  "type": "Feature",
  "properties": {
    "gn:admin1_code":"ER",
    "gn:admin2_code":"13",
    "gn:admin3_code":"13",
    "gn:admin4_code":"130045",
    "gn:asciiname":"Daphe",
    "gn:country_code":"NP",
    "gn:dem":2066,
    "gn:feature_class":"P",
    "gn:feature_code":"PPLL",
    "gn:name":"Daphe",
    "gn:population":0,
    "gn:timezone":"Asia/Kathmandu",
    "iso:country":"NP",
    "wof:name":"Daphe",
    "wof:placetype":"locality"
},
  "geometry": {"coordinates":[86.71171,27.23964],"type":"Point"}
}