{
  "type": "Feature",
  "properties": {
    "gn:admin1_code":"CR",
    "gn:admin2_code":"5",
    "gn:admin3_code":"21",
    "gn:admin4_code":"210018",
    "gn:asciiname":"Shikharal",
    "gn:country_code":"NP",
    "gn:dem":1198,
    "gn:feature_class":"P",
    "gn:feature_code":"PPLL",
    "gn:name":"Shikharal",
    "gn:population":0,
    "gn:timezone":"Asia/Kathmandu",
    "iso:country":"NP",
    "wof:name":"Shikharal",
    "wof:placetype":"locality"
},
  "geometry": {"coordinates":[86.08866,27.46746],"type":"Point"}
}