{
  "type": "Feature",
  "properties": {
    "gn:admin1_code":"ER",
    "gn:admin2_code":"13",
    "gn:admin3_code":"13",
    "gn:admin4_code":"130056.0",
    "gn:asciiname":"Suwajung",
    "gn:country_code":"NP",
    "gn:dem":1432,
    "gn:feature_class":"P",
    "gn:feature_code":"PPLL",
    "gn:name":"Suwajung",
    "gn:population":0,
    "gn:timezone":"Asia/Kathmandu",
    "iso:country":"NP",
    "wof:name":"Suwajung",
    "wof:placetype":"locality"
},
  "geometry": {"coordinates":[86.87548000000002,27.29901],"type":"Point"}
}