{
  "type": "Feature",
  "properties": {
    "gn:admin1_code":"FR",
    "gn:admin2_code":"9",
    "gn:admin3_code":"75.0",
    "gn:admin4_code":"750014.0",
    "gn:asciiname":"Ghusa",
    "gn:country_code":"NP",
    "gn:dem":2186,
    "gn:feature_class":"P",
    "gn:feature_code":"PPLL",
    "gn:name":"Ghusa",
    "gn:population":0,
    "gn:timezone":"Asia/Kathmandu",
    "iso:country":"NP",
    "wof:name":"Ghusa",
    "wof:placetype":"locality"
},
  "geometry": {"coordinates":[80.87281999999998,29.82944],"type":"Point"}
}