{
  "type": "Feature",
  "properties": {
    "gn:admin1_code":"WR",
    "gn:admin2_code":"3",
    "gn:admin3_code":"44",
    "gn:admin4_code":"440052",
    "gn:asciiname":"Fair (Chaitra-Astami)",
    "gn:country_code":"NP",
    "gn:dem":1487,
    "gn:feature_class":"P",
    "gn:feature_code":"PPLL",
    "gn:name":"Fair (Chaitra-Astami)",
    "gn:population":0,
    "gn:timezone":"Asia/Kathmandu",
    "iso:country":"NP",
    "wof:name":"Fair (Chaitra-Astami)",
    "wof:placetype":"locality"
},
  "geometry": {"coordinates":[83.73765,28.20797],"type":"Point"}
}