{
  "type": "Feature",
  "properties": {
    "gn:admin1_code":"FR",
    "gn:admin2_code":"14",
    "gn:admin3_code":"69",
    "gn:admin4_code":"690027",
    "gn:asciiname":"Selpakha",
    "gn:country_code":"NP",
    "gn:dem":1382,
    "gn:feature_class":"P",
    "gn:feature_code":"PPLL",
    "gn:name":"Selpakha",
    "gn:population":0,
    "gn:timezone":"Asia/Kathmandu",
    "iso:country":"NP",
    "wof:name":"Selpakha",
    "wof:placetype":"locality"
},
  "geometry": {"coordinates":[81.12529000000001,29.25596],"type":"Point"}
}