{
  "type": "Feature",
  "properties": {
    "gn:admin1_code":"MR",
    "gn:admin2_code":"12",
    "gn:admin3_code":"56.0",
    "gn:admin4_code":"560040.0",
    "gn:asciiname":"Ranagaun",
    "gn:country_code":"NP",
    "gn:dem":868,
    "gn:feature_class":"P",
    "gn:feature_code":"PPLL",
    "gn:name":"Ranagaun",
    "gn:population":0,
    "gn:timezone":"Asia/Kathmandu",
    "iso:country":"NP",
    "name:msa_x_preferred":[
        "Ranagau"
    ],
    "name:new_x_preferred":[
        "\u0930\u093e\u0928\u093e\u0917\u093e\u0909\u0902"
    ],
    "name:pol_x_preferred":[
        "Ranagau"
    ],
    "wof:name":"Ranagaun",
    "wof:placetype":"locality"
},
  "geometry": {"coordinates":[82.31729,28.18518],"type":"Point"}
}