{
  "type": "Feature",
  "properties": {
    "gn:admin1_code":"WR",
    "gn:admin2_code":"4.0",
    "gn:admin3_code":"38.0",
    "gn:admin4_code":"380001.0",
    "gn:asciiname":"Raudikholagaun",
    "gn:country_code":"NP",
    "gn:dem":801,
    "gn:feature_class":"P",
    "gn:feature_code":"PPLL",
    "gn:name":"Raudikholagaun",
    "gn:population":0,
    "gn:timezone":"Asia/Kathmandu",
    "iso:country":"NP",
    "wof:name":"Raudikholagaun",
    "wof:placetype":"locality"
},
  "geometry": {"coordinates":[84.4713,27.90456],"type":"Point"}
}