{
  "type": "Feature",
  "properties": {
    "gn:admin1_code":"FR",
    "gn:admin2_code":"14",
    "gn:admin3_code":"69.0",
    "gn:admin4_code":"690009.0",
    "gn:asciiname":"Tolipani",
    "gn:country_code":"NP",
    "gn:dem":877,
    "gn:feature_class":"P",
    "gn:feature_code":"PPLL",
    "gn:name":"Tolipani",
    "gn:population":0,
    "gn:timezone":"Asia/Kathmandu",
    "iso:country":"NP",
    "wof:name":"Tolipani",
    "wof:placetype":"locality"
},
  "geometry": {"coordinates":[81.44542,28.92902],"type":"Point"}
}