{
  "type": "Feature",
  "properties": {
    "gn:admin1_code":"ER",
    "gn:admin2_code":"7",
    "gn:admin3_code":"9",
    "gn:admin4_code":"90032",
    "gn:asciiname":"Phungling",
    "gn:country_code":"NP",
    "gn:dem":1635,
    "gn:feature_class":"P",
    "gn:feature_code":"PPLL",
    "gn:name":"Phungling",
    "gn:population":0,
    "gn:timezone":"Asia/Kathmandu",
    "iso:country":"NP",
    "wof:name":"Phungling",
    "wof:placetype":"locality"
},
  "geometry": {"coordinates":[87.3951,27.20832],"type":"Point"}
}