{
  "type": "Feature",
  "properties": {
    "gn:admin1_code":"MR",
    "gn:admin2_code":"12",
    "gn:admin3_code":"55",
    "gn:admin4_code":"550033",
    "gn:asciiname":"Jogingada",
    "gn:country_code":"NP",
    "gn:dem":1161,
    "gn:feature_class":"P",
    "gn:feature_code":"PPLL",
    "gn:name":"Jogingada",
    "gn:population":0,
    "gn:timezone":"Asia/Kathmandu",
    "iso:country":"NP",
    "wof:name":"Jogingada",
    "wof:placetype":"locality"
},
  "geometry": {"coordinates":[82.20709000000002,28.55518],"type":"Point"}
}