{
  "type": "Feature",
  "properties": {
    "gn:admin1_code":"CR",
    "gn:admin2_code":"5",
    "gn:admin3_code":"20",
    "gn:admin4_code":"200003",
    "gn:asciiname":"Sombare",
    "gn:country_code":"NP",
    "gn:dem":1172,
    "gn:feature_class":"P",
    "gn:feature_code":"PPLL",
    "gn:name":"Sombare",
    "gn:population":0,
    "gn:timezone":"Asia/Kathmandu",
    "iso:country":"NP",
    "wof:name":"Sombare",
    "wof:placetype":"locality"
},
  "geometry": {"coordinates":[86.20269999999999,27.16491],"type":"Point"}
}