{
  "type": "Feature",
  "properties": {
    "gn:admin1_code":"MR",
    "gn:admin2_code":"12",
    "gn:admin3_code":"52",
    "gn:admin4_code":"520027.0",
    "gn:asciiname":"Dobata",
    "gn:country_code":"NP",
    "gn:dem":1628,
    "gn:feature_class":"P",
    "gn:feature_code":"PPLL",
    "gn:name":"Dobata",
    "gn:population":0,
    "gn:timezone":"Asia/Kathmandu",
    "iso:country":"NP",
    "wof:name":"Dobata",
    "wof:placetype":"locality"
},
  "geometry": {"coordinates":[82.89833,28.24188],"type":"Point"}
}