{
  "type": "Feature",
  "properties": {
    "gn:admin1_code":"CR",
    "gn:admin2_code":"5",
    "gn:admin3_code":"19",
    "gn:admin4_code":"190071",
    "gn:asciiname":"Saimane",
    "gn:country_code":"NP",
    "gn:dem":284,
    "gn:feature_class":"P",
    "gn:feature_code":"PPLL",
    "gn:name":"Saimane",
    "gn:population":0,
    "gn:timezone":"Asia/Kathmandu",
    "iso:country":"NP",
    "wof:name":"Saimane",
    "wof:placetype":"locality"
},
  "geometry": {"coordinates":[85.68208,27.16383],"type":"Point"}
}