{
  "type": "Feature",
  "properties": {
    "gn:admin1_code":"WR",
    "gn:admin2_code":"4",
    "gn:admin3_code":"37",
    "gn:admin4_code":"370001",
    "gn:asciiname":"Sankhar",
    "gn:country_code":"NP",
    "gn:dem":742,
    "gn:feature_class":"P",
    "gn:feature_code":"PPLL",
    "gn:name":"Sankhar",
    "gn:population":0,
    "gn:timezone":"Asia/Kathmandu",
    "iso:country":"NP",
    "name:ceb_x_preferred":[
        "Sakhar"
    ],
    "name:hin_x_preferred":[
        "\u0938\u093e\u0901\u0916\u0930"
    ],
    "name:mai_x_preferred":[
        "\u0938\u093e\u0901\u0916\u0930"
    ],
    "name:msa_x_preferred":[
        "Sakhar"
    ],
    "name:nep_x_preferred":[
        "\u0938\u093e\u0901\u0916\u0930"
    ],
    "name:new_x_preferred":[
        "\u0938\u0916\u0930"
    ],
    "name:pol_x_preferred":[
        "Sakhar"
    ],
    "name:san_x_preferred":[
        "\u0938\u093e\u0901\u0916\u0930"
    ],
    "wof:name":"Sankhar",
    "wof:placetype":"locality"
},
  "geometry": {"coordinates":[84.44905,28.15362],"type":"Point"}
}