{
  "type": "Feature",
  "properties": {
    "gn:admin1_code":"WR",
    "gn:admin2_code":"4",
    "gn:admin3_code":"37",
    "gn:admin4_code":"370001",
    "gn:asciiname":"Sankhar",
    "gn:country_code":"NP",
    "gn:dem":742,
    "gn:feature_class":"P",
    "gn:feature_code":"PPLL",
    "gn:name":"Sankhar",
    "gn:population":0,
    "gn:timezone":"Asia/Kathmandu",
    "iso:country":"NP",
    "wof:name":"Sankhar",
    "wof:placetype":"locality"
},
  "geometry": {"coordinates":[84.44905,28.15362],"type":"Point"}
}