{
  "type": "Feature",
  "properties": {
    "gn:admin1_code":"CR",
    "gn:admin2_code":"1",
    "gn:admin3_code":"30.0",
    "gn:admin4_code":"300046.0",
    "gn:asciiname":"Patenegaun",
    "gn:country_code":"NP",
    "gn:dem":1480,
    "gn:feature_class":"P",
    "gn:feature_code":"PPLL",
    "gn:name":"Patenegaun",
    "gn:population":0,
    "gn:timezone":"Asia/Kathmandu",
    "iso:country":"NP",
    "wof:name":"Patenegaun",
    "wof:placetype":"locality"
},
  "geometry": {"coordinates":[84.9299,27.86638],"type":"Point"}
}