{
  "type": "Feature",
  "properties": {
    "gn:admin1_code":"WR",
    "gn:admin2_code":"3",
    "gn:admin3_code":"45.0",
    "gn:admin4_code":"450052.0",
    "gn:asciiname":"Bhaddanda",
    "gn:country_code":"NP",
    "gn:dem":1039,
    "gn:feature_class":"P",
    "gn:feature_code":"PPLL",
    "gn:name":"Bhaddanda",
    "gn:population":0,
    "gn:timezone":"Asia/Kathmandu",
    "iso:country":"NP",
    "wof:name":"Bhaddanda",
    "wof:placetype":"locality"
},
  "geometry": {"coordinates":[83.63359,28.16534],"type":"Point"}
}