{
  "type": "Feature",
  "properties": {
    "gn:admin1_code":"ER",
    "gn:admin2_code":"13",
    "gn:admin3_code":"13.0",
    "gn:admin4_code":"130001.0",
    "gn:asciiname":"Nepane",
    "gn:country_code":"NP",
    "gn:dem":1694,
    "gn:feature_class":"P",
    "gn:feature_code":"PPLL",
    "gn:name":"Nepane",
    "gn:population":0,
    "gn:timezone":"Asia/Kathmandu",
    "iso:country":"NP",
    "wof:name":"Nepane",
    "wof:placetype":"locality"
},
  "geometry": {"coordinates":[86.76888000000002,27.36942],"type":"Point"}
}