{
  "type": "Feature",
  "properties": {
    "gn:admin1_code":"CR",
    "gn:admin2_code":"5",
    "gn:admin3_code":"22.0",
    "gn:admin4_code":"220026.0",
    "gn:asciiname":"Uniyanchaur",
    "gn:country_code":"NP",
    "gn:dem":1935,
    "gn:feature_class":"P",
    "gn:feature_code":"PPLL",
    "gn:name":"Uniyanchaur",
    "gn:population":0,
    "gn:timezone":"Asia/Kathmandu",
    "iso:country":"NP",
    "wof:name":"Uniyanchaur",
    "wof:placetype":"locality"
},
  "geometry": {"coordinates":[86.15955,27.6386],"type":"Point"}
}