{
  "type": "Feature",
  "properties": {
    "gn:admin1_code":"00",
    "gn:asciiname":"Bolbot",
    "gn:country_code":"NP",
    "gn:dem":991,
    "gn:feature_class":"P",
    "gn:feature_code":"PPL",
    "gn:name":"Bolbo\u1e6d",
    "gn:population":0,
    "gn:timezone":"Asia/Kathmandu",
    "iso:country":"NP",
    "wof:name":"Bolbot",
    "wof:placetype":"locality"
},
  "geometry": {"coordinates":[85.60333,27.36426],"type":"Point"}
}