{
  "type": "Feature",
  "properties": {
    "gn:admin1_code":"CR",
    "gn:admin2_code":"5",
    "gn:admin3_code":"20",
    "gn:admin4_code":"200032",
    "gn:asciiname":"Syangkti",
    "gn:country_code":"NP",
    "gn:dem":1045,
    "gn:feature_class":"P",
    "gn:feature_code":"PPLL",
    "gn:name":"Syangkti",
    "gn:population":0,
    "gn:timezone":"Asia/Kathmandu",
    "iso:country":"NP",
    "wof:name":"Syangkti",
    "wof:placetype":"locality"
},
  "geometry": {"coordinates":[86.18744000000002,27.15262],"type":"Point"}
}