{
  "type": "Feature",
  "properties": {
    "gn:admin1_code":"ER",
    "gn:admin2_code":"7",
    "gn:admin3_code":"10.0",
    "gn:admin4_code":"100061.0",
    "gn:asciiname":"Balangkha",
    "gn:country_code":"NP",
    "gn:dem":1529,
    "gn:feature_class":"P",
    "gn:feature_code":"PPLL",
    "gn:name":"Balangkha",
    "gn:population":0,
    "gn:timezone":"Asia/Kathmandu",
    "iso:country":"NP",
    "wof:name":"Balangkha",
    "wof:placetype":"locality"
},
  "geometry": {"coordinates":[86.98576,26.97763],"type":"Point"}
}