{
  "type": "Feature",
  "properties": {
    "gn:admin1_code":"CR",
    "gn:admin2_code":"1",
    "gn:admin3_code":"28",
    "gn:admin4_code":"280048",
    "gn:asciiname":"Taksar",
    "gn:country_code":"NP",
    "gn:dem":1352,
    "gn:feature_class":"P",
    "gn:feature_code":"PPLL",
    "gn:name":"Taksar",
    "gn:population":0,
    "gn:timezone":"Asia/Kathmandu",
    "iso:country":"NP",
    "name:pol_x_preferred":[
        "Taksar"
    ],
    "wof:name":"Taksar",
    "wof:placetype":"locality"
},
  "geometry": {"coordinates":[85.02068,27.95831],"type":"Point"}
}