{
  "type": "Feature",
  "properties": {
    "gn:admin1_code":"WR",
    "gn:admin2_code":"4",
    "gn:admin3_code":"37",
    "gn:admin4_code":"370057",
    "gn:asciiname":"Bhusal Dihi",
    "gn:country_code":"NP",
    "gn:dem":502,
    "gn:feature_class":"P",
    "gn:feature_code":"PPLL",
    "gn:name":"Bhusal Dihi",
    "gn:population":0,
    "gn:timezone":"Asia/Kathmandu",
    "iso:country":"NP",
    "wof:name":"Bhusal Dihi",
    "wof:placetype":"locality"
},
  "geometry": {"coordinates":[84.28466,28.10602],"type":"Point"}
}