{
  "type": "Feature",
  "properties": {
    "gn:admin1_code":"ER",
    "gn:admin2_code":"13",
    "gn:admin3_code":"13.0",
    "gn:admin4_code":"130007.0",
    "gn:asciiname":"Lwangkha",
    "gn:country_code":"NP",
    "gn:dem":1156,
    "gn:feature_class":"P",
    "gn:feature_code":"PPLL",
    "gn:name":"Lwangkha",
    "gn:population":0,
    "gn:timezone":"Asia/Kathmandu",
    "iso:country":"NP",
    "wof:name":"Lwangkha",
    "wof:placetype":"locality"
},
  "geometry": {"coordinates":[86.81572,27.34244],"type":"Point"}
}