{
  "type": "Feature",
  "properties": {
    "gn:admin1_code":"WR",
    "gn:admin2_code":"8",
    "gn:admin3_code":"48",
    "gn:admin4_code":"480004",
    "gn:asciiname":"Badhara",
    "gn:country_code":"NP",
    "gn:dem":111,
    "gn:feature_class":"P",
    "gn:feature_code":"PPLL",
    "gn:name":"Badhara",
    "gn:population":0,
    "gn:timezone":"Asia/Kathmandu",
    "iso:country":"NP",
    "wof:name":"Badhara",
    "wof:placetype":"locality"
},
  "geometry": {"coordinates":[83.73307,27.47796],"type":"Point"}
}