{
  "type": "Feature",
  "properties": {
    "gn:admin1_code":"ER",
    "gn:admin2_code":"10",
    "gn:admin3_code":"4.0",
    "gn:admin4_code":"40008.0",
    "gn:asciiname":"Budhabare",
    "gn:country_code":"NP",
    "gn:dem":190,
    "gn:feature_class":"P",
    "gn:feature_code":"PPLL",
    "gn:name":"Budhabare",
    "gn:population":0,
    "gn:timezone":"Asia/Kathmandu",
    "iso:country":"NP",
    "name:pol_x_preferred":[
        "Budhabare"
    ],
    "wof:name":"Budhabare",
    "wof:placetype":"locality"
},
  "geometry": {"coordinates":[88.05495000000001,26.7228],"type":"Point"}
}