{
  "type": "Feature",
  "properties": {
    "gn:admin1_code":"CR",
    "gn:admin2_code":"1",
    "gn:admin3_code":"24.0",
    "gn:admin4_code":"240085.0",
    "gn:asciiname":"Neupane",
    "gn:country_code":"NP",
    "gn:dem":1753,
    "gn:feature_class":"P",
    "gn:feature_code":"PPLL",
    "gn:name":"Neupane",
    "gn:population":0,
    "gn:timezone":"Asia/Kathmandu",
    "iso:country":"NP",
    "name:nep_x_preferred":[
        "\u0928\u0947\u0909\u092a\u093e\u0928\u0947"
    ],
    "wof:name":"Neupane",
    "wof:placetype":"locality"
},
  "geometry": {"coordinates":[85.79875,27.64375],"type":"Point"}
}