{
  "type": "Feature",
  "properties": {
    "gn:admin1_code":"CR",
    "gn:admin2_code":"5",
    "gn:admin3_code":"20",
    "gn:admin4_code":"200013",
    "gn:asciiname":"Kharkholagaun",
    "gn:country_code":"NP",
    "gn:dem":376,
    "gn:feature_class":"P",
    "gn:feature_code":"PPLL",
    "gn:name":"Kharkholagaun",
    "gn:population":0,
    "gn:timezone":"Asia/Kathmandu",
    "iso:country":"NP",
    "wof:name":"Kharkholagaun",
    "wof:placetype":"locality"
},
  "geometry": {"coordinates":[85.81429,27.25855],"type":"Point"}
}