{
  "type": "Feature",
  "properties": {
    "gn:admin1_code":"ER",
    "gn:admin2_code":"13.0",
    "gn:admin3_code":"14.0",
    "gn:admin4_code":"140026.0",
    "gn:asciiname":"Okhale",
    "gn:country_code":"NP",
    "gn:dem":1550,
    "gn:feature_class":"P",
    "gn:feature_code":"PPLL",
    "gn:name":"Okhale",
    "gn:population":0,
    "gn:timezone":"Asia/Kathmandu",
    "iso:country":"NP",
    "name:bih_x_preferred":[
        "\u0913\u0916\u0932\u0947"
    ],
    "name:ceb_x_preferred":[
        "Okhale"
    ],
    "name:fra_x_preferred":[
        "Okhale"
    ],
    "name:ita_x_preferred":[
        "Okhale"
    ],
    "name:mai_x_preferred":[
        "\u0913\u0916\u0932\u0947"
    ],
    "name:msa_x_preferred":[
        "Okhale"
    ],
    "name:nep_x_preferred":[
        "\u0913\u0916\u0932\u0947"
    ],
    "name:new_x_preferred":[
        "\u0913\u0916\u094d\u0932\u0947"
    ],
    "name:pol_x_preferred":[
        "Okhale"
    ],
    "wof:name":"Okhale",
    "wof:placetype":"locality"
},
  "geometry": {"coordinates":[86.49373,27.04912],"type":"Point"}
}