{
  "type": "Feature",
  "properties": {
    "gn:admin1_code":"CR",
    "gn:admin2_code":"1",
    "gn:admin3_code":"27.0",
    "gn:admin4_code":"270006.0",
    "gn:asciiname":"Nayangaun",
    "gn:country_code":"NP",
    "gn:dem":1375,
    "gn:feature_class":"P",
    "gn:feature_code":"PPLL",
    "gn:name":"Nayangaun",
    "gn:population":0,
    "gn:timezone":"Asia/Kathmandu",
    "iso:country":"NP",
    "wof:name":"Nayangaun",
    "wof:placetype":"locality"
},
  "geometry": {"coordinates":[85.41934999999999,27.73931],"type":"Point"}
}