{
  "type": "Feature",
  "properties": {
    "gn:admin1_code":"MR",
    "gn:admin2_code":"12",
    "gn:admin3_code":"53",
    "gn:admin4_code":"530049",
    "gn:asciiname":"Sewar",
    "gn:country_code":"NP",
    "gn:dem":1665,
    "gn:feature_class":"P",
    "gn:feature_code":"PPLL",
    "gn:name":"Sewar",
    "gn:population":0,
    "gn:timezone":"Asia/Kathmandu",
    "iso:country":"NP",
    "wof:name":"Sewar",
    "wof:placetype":"locality"
},
  "geometry": {"coordinates":[82.77466,28.2852],"type":"Point"}
}