{
  "type": "Feature",
  "properties": {
    "gn:admin1_code":"00",
    "gn:asciiname":"Purano Kanthapur",
    "gn:country_code":"NP",
    "gn:dem":144,
    "gn:feature_class":"P",
    "gn:feature_code":"PPL",
    "gn:name":"Pur\u0101no Ka\u1e47\u1e6dhapur",
    "gn:population":0,
    "gn:timezone":"Asia/Kathmandu",
    "iso:country":"NP",
    "name:nep_x_preferred":[
        "Pur\u0101no Ka\u1e47\u1e6dhapur"
    ],
    "name:und_x_variant":[
        "Kanthapur",
        "Kantu Purwa"
    ],
    "wof:name":"Purano Kanthapur",
    "wof:placetype":"locality"
},
  "geometry": {"coordinates":[81.44409,28.16882],"type":"Point"}
}