{
  "type": "Feature",
  "properties": {
    "gn:admin1_code":"WR",
    "gn:admin2_code":"8",
    "gn:admin3_code":"50.0",
    "gn:admin4_code":"500053.0",
    "gn:asciiname":"Bot Gaun",
    "gn:country_code":"NP",
    "gn:dem":141,
    "gn:feature_class":"P",
    "gn:feature_code":"PPLL",
    "gn:name":"Bot Gaun",
    "gn:population":0,
    "gn:timezone":"Asia/Kathmandu",
    "iso:country":"NP",
    "wof:name":"Bot Gaun",
    "wof:placetype":"locality"
},
  "geometry": {"coordinates":[83.16095,27.69601],"type":"Point"}
}