{
  "type": "Feature",
  "properties": {
    "gn:admin1_code":"MR",
    "gn:admin2_code":"12",
    "gn:admin3_code":"54",
    "gn:admin4_code":"540019",
    "gn:asciiname":"Jhulka",
    "gn:country_code":"NP",
    "gn:dem":1550,
    "gn:feature_class":"P",
    "gn:feature_code":"PPLL",
    "gn:name":"Jhulka",
    "gn:population":0,
    "gn:timezone":"Asia/Kathmandu",
    "iso:country":"NP",
    "wof:name":"Jhulka",
    "wof:placetype":"locality"
},
  "geometry": {"coordinates":[82.45792,28.54623],"type":"Point"}
}