{
  "type": "Feature",
  "properties": {
    "gn:admin1_code":"ER",
    "gn:admin2_code":"10.0",
    "gn:admin3_code":"1.0",
    "gn:admin4_code":"10032.0",
    "gn:asciiname":"Segumba",
    "gn:country_code":"NP",
    "gn:dem":951,
    "gn:feature_class":"P",
    "gn:feature_code":"PPLL",
    "gn:name":"Segumba",
    "gn:population":0,
    "gn:timezone":"Asia/Kathmandu",
    "iso:country":"NP",
    "wof:name":"Segumba",
    "wof:placetype":"locality"
},
  "geometry": {"coordinates":[87.66349,27.37917],"type":"Point"}
}