{
  "type": "Feature",
  "properties": {
    "gn:admin1_code":"MR",
    "gn:admin2_code":"12",
    "gn:admin3_code":"56.0",
    "gn:admin4_code":"560029.0",
    "gn:asciiname":"Bastikot",
    "gn:country_code":"NP",
    "gn:dem":1107,
    "gn:feature_class":"P",
    "gn:feature_code":"PPLL",
    "gn:name":"Bastikot",
    "gn:population":0,
    "gn:timezone":"Asia/Kathmandu",
    "iso:country":"NP",
    "wof:name":"Bastikot",
    "wof:placetype":"locality"
},
  "geometry": {"coordinates":[82.57661,28.00314],"type":"Point"}
}