{
  "type": "Feature",
  "properties": {
    "gn:admin1_code":"FR",
    "gn:admin2_code":"14",
    "gn:admin3_code":"71.0",
    "gn:admin4_code":"710035.0",
    "gn:asciiname":"Pharam",
    "gn:country_code":"NP",
    "gn:dem":193,
    "gn:feature_class":"P",
    "gn:feature_code":"PPLL",
    "gn:name":"Pharam",
    "gn:population":0,
    "gn:timezone":"Asia/Kathmandu",
    "iso:country":"NP",
    "wof:name":"Pharam",
    "wof:placetype":"locality"
},
  "geometry": {"coordinates":[80.92149000000001,28.75377000000001],"type":"Point"}
}