{
  "type": "Feature",
  "properties": {
    "gn:admin1_code":"WR",
    "gn:admin2_code":"4.0",
    "gn:admin3_code":"39.0",
    "gn:admin4_code":"390044.0",
    "gn:asciiname":"Kabhre",
    "gn:country_code":"NP",
    "gn:dem":908,
    "gn:feature_class":"P",
    "gn:feature_code":"PPLL",
    "gn:name":"Kabhre",
    "gn:population":0,
    "gn:timezone":"Asia/Kathmandu",
    "iso:country":"NP",
    "wof:name":"Kabhre",
    "wof:placetype":"locality"
},
  "geometry": {"coordinates":[83.87959000000002,28.09168],"type":"Point"}
}