{
  "type": "Feature",
  "properties": {
    "gn:admin1_code":"MR",
    "gn:admin2_code":"12",
    "gn:admin3_code":"53",
    "gn:admin4_code":"530006",
    "gn:asciiname":"Deurali Lekh",
    "gn:country_code":"NP",
    "gn:dem":1534,
    "gn:feature_class":"P",
    "gn:feature_code":"PPLL",
    "gn:name":"Deurali Lekh",
    "gn:population":0,
    "gn:timezone":"Asia/Kathmandu",
    "iso:country":"NP",
    "wof:name":"Deurali Lekh",
    "wof:placetype":"locality"
},
  "geometry": {"coordinates":[82.46101,28.15816],"type":"Point"}
}