{
  "type": "Feature",
  "properties": {
    "gn:admin1_code":"ER",
    "gn:admin2_code":"10.0",
    "gn:admin3_code":"1.0",
    "gn:admin4_code":"10050.0",
    "gn:asciiname":"Barule",
    "gn:country_code":"NP",
    "gn:dem":2978,
    "gn:feature_class":"P",
    "gn:feature_code":"PPLL",
    "gn:name":"Barule",
    "gn:population":0,
    "gn:timezone":"Asia/Kathmandu",
    "iso:country":"NP",
    "wof:name":"Barule",
    "wof:placetype":"locality"
},
  "geometry": {"coordinates":[87.96647,27.48331],"type":"Point"}
}