{
  "type": "Feature",
  "properties": {
    "gn:admin1_code":"MR",
    "gn:admin2_code":"2",
    "gn:admin3_code":"60.0",
    "gn:admin4_code":"600004.0",
    "gn:asciiname":"Koiala",
    "gn:country_code":"NP",
    "gn:dem":916,
    "gn:feature_class":"P",
    "gn:feature_code":"PPLL",
    "gn:name":"Koiala",
    "gn:population":0,
    "gn:timezone":"Asia/Kathmandu",
    "iso:country":"NP",
    "wof:name":"Koiala",
    "wof:placetype":"locality"
},
  "geometry": {"coordinates":[81.6464,28.90479],"type":"Point"}
}