{
  "type": "Feature",
  "properties": {
    "gn:admin1_code":"MR",
    "gn:admin2_code":"2.0",
    "gn:admin3_code":"58.0",
    "gn:admin4_code":"580009.0",
    "gn:asciiname":"Gamakka",
    "gn:country_code":"NP",
    "gn:dem":163,
    "gn:feature_class":"P",
    "gn:feature_code":"PPLL",
    "gn:name":"Gamakka",
    "gn:population":0,
    "gn:timezone":"Asia/Kathmandu",
    "iso:country":"NP",
    "wof:name":"Gamakka",
    "wof:placetype":"locality"
},
  "geometry": {"coordinates":[81.26125999999999,28.35884],"type":"Point"}
}