{
  "type": "Feature",
  "properties": {
    "gn:admin1_code":"WR",
    "gn:admin2_code":"4.0",
    "gn:admin3_code":"38.0",
    "gn:admin4_code":"380037.0",
    "gn:asciiname":"Chalise",
    "gn:country_code":"NP",
    "gn:dem":791,
    "gn:feature_class":"P",
    "gn:feature_code":"PPLL",
    "gn:name":"Chalise",
    "gn:population":0,
    "gn:timezone":"Asia/Kathmandu",
    "iso:country":"NP",
    "name:nep_x_preferred":[
        "\u091a\u093e\u0932\u093f\u0938\u0947"
    ],
    "wof:name":"Chalise",
    "wof:placetype":"locality"
},
  "geometry": {"coordinates":[84.21552,27.89742],"type":"Point"}
}