{
  "type": "Feature",
  "properties": {
    "gn:admin1_code":"WR",
    "gn:admin2_code":"4",
    "gn:admin3_code":"37",
    "gn:admin4_code":"370029",
    "gn:asciiname":"Sanchapugaun",
    "gn:country_code":"NP",
    "gn:dem":2076,
    "gn:feature_class":"P",
    "gn:feature_code":"PPLL",
    "gn:name":"Sanchapugaun",
    "gn:population":0,
    "gn:timezone":"Asia/Kathmandu",
    "iso:country":"NP",
    "wof:name":"Sanchapugaun",
    "wof:placetype":"locality"
},
  "geometry": {"coordinates":[84.42169,28.37486],"type":"Point"}
}