{
  "type": "Feature",
  "properties": {
    "gn:admin1_code":"CR",
    "gn:admin2_code":"1",
    "gn:admin3_code":"30.0",
    "gn:admin4_code":"300046.0",
    "gn:asciiname":"Ranagaun",
    "gn:country_code":"NP",
    "gn:dem":1478,
    "gn:feature_class":"P",
    "gn:feature_code":"PPLL",
    "gn:name":"Ranagaun",
    "gn:population":0,
    "gn:timezone":"Asia/Kathmandu",
    "iso:country":"NP",
    "wof:name":"Ranagaun",
    "wof:placetype":"locality"
},
  "geometry": {"coordinates":[84.92605999999998,27.86738],"type":"Point"}
}