{
  "type": "Feature",
  "properties": {
    "gn:admin1_code":"ER",
    "gn:admin2_code":"13.0",
    "gn:admin3_code":"14.0",
    "gn:admin4_code":"140004.0",
    "gn:asciiname":"Barre",
    "gn:country_code":"NP",
    "gn:dem":943,
    "gn:feature_class":"P",
    "gn:feature_code":"PPLL",
    "gn:name":"Barre",
    "gn:population":0,
    "gn:timezone":"Asia/Kathmandu",
    "iso:country":"NP",
    "name:bre_x_preferred":[
        "Barre"
    ],
    "name:cat_x_preferred":[
        "Barre"
    ],
    "name:ceb_x_preferred":[
        "Barre"
    ],
    "name:dan_x_preferred":[
        "Barre"
    ],
    "name:deu_x_preferred":[
        "Barre"
    ],
    "name:fra_x_preferred":[
        "Barre"
    ],
    "name:ita_x_preferred":[
        "Barre"
    ],
    "name:nld_x_preferred":[
        "Barre"
    ],
    "name:nor_x_preferred":[
        "Barre"
    ],
    "name:pol_x_preferred":[
        "Barre"
    ],
    "name:rus_x_preferred":[
        "\u0411\u0430\u0440\u0440\u0435"
    ],
    "name:scn_x_preferred":[
        "Barre"
    ],
    "name:slv_x_preferred":[
        "Barr\u00e9"
    ],
    "name:swe_x_preferred":[
        "Barre"
    ],
    "name:ukr_x_preferred":[
        "\u0411\u0430\u0440\u0440\u0435"
    ],
    "name:vol_x_preferred":[
        "Barre"
    ],
    "wof:name":"Barre",
    "wof:placetype":"locality"
},
  "geometry": {"coordinates":[86.55133000000002,26.98589],"type":"Point"}
}