{
  "type": "Feature",
  "properties": {
    "gn:admin1_code":"WR",
    "gn:admin2_code":"4",
    "gn:admin3_code":"40.0",
    "gn:admin4_code":"400030.0",
    "gn:asciiname":"Shivalaya",
    "gn:country_code":"NP",
    "gn:dem":975,
    "gn:feature_class":"P",
    "gn:feature_code":"PPLL",
    "gn:name":"Shivalaya",
    "gn:population":0,
    "gn:timezone":"Asia/Kathmandu",
    "iso:country":"NP",
    "name:ceb_x_preferred":[
        "Shivalaya"
    ],
    "name:swe_x_preferred":[
        "Shivalaya"
    ],
    "wof:name":"Shivalaya",
    "wof:placetype":"locality"
},
  "geometry": {"coordinates":[83.9868,28.16084],"type":"Point"}
}