{
  "type": "Feature",
  "properties": {
    "gn:admin1_code":"ER",
    "gn:admin2_code":"7",
    "gn:admin3_code":"5",
    "gn:admin4_code":"50024",
    "gn:asciiname":"Tilathi",
    "gn:country_code":"NP",
    "gn:dem":93,
    "gn:feature_class":"P",
    "gn:feature_code":"PPLL",
    "gn:name":"Tilathi",
    "gn:population":0,
    "gn:timezone":"Asia/Kathmandu",
    "iso:country":"NP",
    "name:bih_x_preferred":[
        "\u0924\u093f\u0932\u093e\u0920\u0940"
    ],
    "name:ceb_x_preferred":[
        "Tilathi"
    ],
    "name:fra_x_preferred":[
        "Tilathi"
    ],
    "name:mai_x_preferred":[
        "\u0924\u093f\u0932\u093e\u0920\u0940"
    ],
    "name:msa_x_preferred":[
        "Tilathi"
    ],
    "name:nep_x_preferred":[
        "\u0924\u093f\u0932\u093e\u0920\u0940"
    ],
    "name:new_x_preferred":[
        "\u0924\u093f\u0932\u0925\u0940"
    ],
    "name:pol_x_preferred":[
        "Tilathi"
    ],
    "wof:name":"Tilathi",
    "wof:placetype":"locality"
},
  "geometry": {"coordinates":[87.31184,26.57835],"type":"Point"}
}