{
  "type": "Feature",
  "properties": {
    "gn:admin1_code":"MR",
    "gn:admin2_code":"12",
    "gn:admin3_code":"54",
    "gn:admin4_code":"540004",
    "gn:asciiname":"Bargaun",
    "gn:country_code":"NP",
    "gn:dem":1797,
    "gn:feature_class":"P",
    "gn:feature_code":"PPLL",
    "gn:name":"Bargaun",
    "gn:population":0,
    "gn:timezone":"Asia/Kathmandu",
    "iso:country":"NP",
    "name:ceb_x_preferred":[
        "Bargaun"
    ],
    "name:mai_x_preferred":[
        "\u092c\u0930\u0917\u093e\u0909\u0901"
    ],
    "name:msa_x_preferred":[
        "Bargaun"
    ],
    "name:nep_x_preferred":[
        "\u092c\u0930\u0917\u093e\u0909\u0901"
    ],
    "name:pol_x_preferred":[
        "Bargaun"
    ],
    "wof:name":"Bargaun",
    "wof:placetype":"locality"
},
  "geometry": {"coordinates":[82.46633,28.69987],"type":"Point"}
}