{
  "type": "Feature",
  "properties": {
    "gn:admin1_code":"WR",
    "gn:admin2_code":"3",
    "gn:admin3_code":"43",
    "gn:admin4_code":"430021",
    "gn:asciiname":"Barse Block",
    "gn:country_code":"NP",
    "gn:dem":4192,
    "gn:feature_class":"P",
    "gn:feature_code":"PPLL",
    "gn:name":"Barse Block",
    "gn:population":0,
    "gn:timezone":"Asia/Kathmandu",
    "iso:country":"NP",
    "wof:name":"Barse Block",
    "wof:placetype":"locality"
},
  "geometry": {"coordinates":[83.15522,28.55827],"type":"Point"}
}