{
  "type": "Feature",
  "properties": {
    "gn:admin1_code":"ER",
    "gn:admin2_code":"10.0",
    "gn:admin3_code":"1.0",
    "gn:admin4_code":"10046.0",
    "gn:asciiname":"Tenthap",
    "gn:country_code":"NP",
    "gn:dem":1286,
    "gn:feature_class":"P",
    "gn:feature_code":"PPLL",
    "gn:name":"Tenthap",
    "gn:population":0,
    "gn:timezone":"Asia/Kathmandu",
    "iso:country":"NP",
    "wof:name":"Tenthap",
    "wof:placetype":"locality"
},
  "geometry": {"coordinates":[87.56545,27.37582],"type":"Point"}
}