{
  "type": "Feature",
  "properties": {
    "gn:admin1_code":"MR",
    "gn:admin2_code":"2",
    "gn:admin3_code":"60.0",
    "gn:admin4_code":"600023.0",
    "gn:asciiname":"Lohose",
    "gn:country_code":"NP",
    "gn:dem":1280,
    "gn:feature_class":"P",
    "gn:feature_code":"PPLL",
    "gn:name":"Lohose",
    "gn:population":0,
    "gn:timezone":"Asia/Kathmandu",
    "iso:country":"NP",
    "wof:name":"Lohose",
    "wof:placetype":"locality"
},
  "geometry": {"coordinates":[81.70885,28.97186],"type":"Point"}
}