{
  "type": "Feature",
  "properties": {
    "gn:admin1_code":"CR",
    "gn:admin2_code":"11",
    "gn:admin3_code":"31",
    "gn:admin4_code":"310040",
    "gn:asciiname":"Hiramuni",
    "gn:country_code":"NP",
    "gn:dem":345,
    "gn:feature_class":"P",
    "gn:feature_code":"PPLL",
    "gn:name":"Hiramuni",
    "gn:population":0,
    "gn:timezone":"Asia/Kathmandu",
    "iso:country":"NP",
    "wof:name":"Hiramuni",
    "wof:placetype":"locality"
},
  "geometry": {"coordinates":[85.25119000000002,27.32089],"type":"Point"}
}