{
  "type": "Feature",
  "properties": {
    "gn:admin1_code":"WR",
    "gn:admin2_code":"4",
    "gn:admin3_code":"40.0",
    "gn:admin4_code":"400022.0",
    "gn:asciiname":"Dhunge Patan",
    "gn:country_code":"NP",
    "gn:dem":667,
    "gn:feature_class":"P",
    "gn:feature_code":"PPLL",
    "gn:name":"Dhunge Patan",
    "gn:population":0,
    "gn:timezone":"Asia/Kathmandu",
    "iso:country":"NP",
    "wof:name":"Dhunge Patan",
    "wof:placetype":"locality"
},
  "geometry": {"coordinates":[84.08185999999998,28.14408],"type":"Point"}
}