{
  "type": "Feature",
  "properties": {
    "gn:admin1_code":"CR",
    "gn:admin2_code":"1",
    "gn:admin3_code":"27.0",
    "gn:admin4_code":"270024.0",
    "gn:asciiname":"Boratar",
    "gn:country_code":"NP",
    "gn:dem":1444,
    "gn:feature_class":"P",
    "gn:feature_code":"PPLL",
    "gn:name":"Boratar",
    "gn:population":0,
    "gn:timezone":"Asia/Kathmandu",
    "iso:country":"NP",
    "wof:name":"Boratar",
    "wof:placetype":"locality"
},
  "geometry": {"coordinates":[85.29901,27.73716],"type":"Point"}
}