{
  "type": "Feature",
  "properties": {
    "gn:admin1_code":"FR",
    "gn:admin2_code":"9",
    "gn:admin3_code":"72.0",
    "gn:admin4_code":"720011.0",
    "gn:asciiname":"Bhasigaun",
    "gn:country_code":"NP",
    "gn:dem":223,
    "gn:feature_class":"P",
    "gn:feature_code":"PPLL",
    "gn:name":"Bhasigaun",
    "gn:population":0,
    "gn:timezone":"Asia/Kathmandu",
    "iso:country":"NP",
    "wof:name":"Bhasigaun",
    "wof:placetype":"locality"
},
  "geometry": {"coordinates":[80.19261999999998,28.97872000000001],"type":"Point"}
}