{
  "type": "Feature",
  "properties": {
    "gn:admin1_code":"WR",
    "gn:admin2_code":"4",
    "gn:admin3_code":"36.0",
    "gn:admin4_code":"360017.0",
    "gn:asciiname":"Raithok",
    "gn:country_code":"NP",
    "gn:dem":821,
    "gn:feature_class":"P",
    "gn:feature_code":"PPLL",
    "gn:name":"Raithok",
    "gn:population":0,
    "gn:timezone":"Asia/Kathmandu",
    "iso:country":"NP",
    "wof:name":"Raithok",
    "wof:placetype":"locality"
},
  "geometry": {"coordinates":[84.74108000000003,27.85937],"type":"Point"}
}