{
  "type": "Feature",
  "properties": {
    "gn:admin1_code":"MR",
    "gn:admin2_code":"12",
    "gn:admin3_code":"56.0",
    "gn:admin4_code":"560028.0",
    "gn:asciiname":"Motipur",
    "gn:country_code":"NP",
    "gn:dem":232,
    "gn:feature_class":"P",
    "gn:feature_code":"PPLL",
    "gn:name":"Motipur",
    "gn:population":0,
    "gn:timezone":"Asia/Kathmandu",
    "iso:country":"NP",
    "name:fra_x_preferred":[
        "Motipur"
    ],
    "name:pol_x_preferred":[
        "Motipur"
    ],
    "wof:name":"Motipur",
    "wof:placetype":"locality"
},
  "geometry": {"coordinates":[82.39319999999999,27.86645],"type":"Point"}
}