{
  "type": "Feature",
  "properties": {
    "gn:admin1_code":"CR",
    "gn:admin2_code":"11",
    "gn:admin3_code":"31",
    "gn:admin4_code":"310025",
    "gn:asciiname":"Medansi",
    "gn:country_code":"NP",
    "gn:dem":1169,
    "gn:feature_class":"P",
    "gn:feature_code":"PPLL",
    "gn:name":"Medansi",
    "gn:population":0,
    "gn:timezone":"Asia/Kathmandu",
    "iso:country":"NP",
    "wof:name":"Medansi",
    "wof:placetype":"locality"
},
  "geometry": {"coordinates":[84.88218000000001,27.65293],"type":"Point"}
}