{
  "type": "Feature",
  "properties": {
    "gn:admin1_code":"ER",
    "gn:admin2_code":"13",
    "gn:admin3_code":"11",
    "gn:admin4_code":"110024",
    "gn:asciiname":"Hilajung",
    "gn:country_code":"NP",
    "gn:dem":3852,
    "gn:feature_class":"P",
    "gn:feature_code":"PPLL",
    "gn:name":"Hilajung",
    "gn:population":0,
    "gn:timezone":"Asia/Kathmandu",
    "iso:country":"NP",
    "wof:name":"Hilajung",
    "wof:placetype":"locality"
},
  "geometry": {"coordinates":[86.64860999999998,27.84424000000001],"type":"Point"}
}