{
  "type": "Feature",
  "properties": {
    "gn:admin1_code":"WR",
    "gn:admin2_code":"4",
    "gn:admin3_code":"36.0",
    "gn:admin4_code":"360016.0",
    "gn:asciiname":"Biruwatar",
    "gn:country_code":"NP",
    "gn:dem":494,
    "gn:feature_class":"P",
    "gn:feature_code":"PPLL",
    "gn:name":"Biruwatar",
    "gn:population":0,
    "gn:timezone":"Asia/Kathmandu",
    "iso:country":"NP",
    "wof:name":"Biruwatar",
    "wof:placetype":"locality"
},
  "geometry": {"coordinates":[84.44792,27.97402],"type":"Point"}
}