{
  "type": "Feature",
  "properties": {
    "gn:admin1_code":"CR",
    "gn:admin2_code":"5",
    "gn:admin3_code":"20",
    "gn:admin4_code":"200018",
    "gn:asciiname":"Gairi",
    "gn:country_code":"NP",
    "gn:dem":732,
    "gn:feature_class":"P",
    "gn:feature_code":"PPLL",
    "gn:name":"Gairi",
    "gn:population":0,
    "gn:timezone":"Asia/Kathmandu",
    "iso:country":"NP",
    "wof:name":"Gairi",
    "wof:placetype":"locality"
},
  "geometry": {"coordinates":[86.12352,27.07308],"type":"Point"}
}