{
  "type": "Feature",
  "properties": {
    "gn:admin1_code":"CR",
    "gn:admin2_code":"1",
    "gn:admin3_code":"24.0",
    "gn:admin4_code":"240065.0",
    "gn:asciiname":"Satyalgaun",
    "gn:country_code":"NP",
    "gn:dem":1462,
    "gn:feature_class":"P",
    "gn:feature_code":"PPLL",
    "gn:name":"Satyalgaun",
    "gn:population":0,
    "gn:timezone":"Asia/Kathmandu",
    "iso:country":"NP",
    "wof:name":"Satyalgaun",
    "wof:placetype":"locality"
},
  "geometry": {"coordinates":[85.53296999999998,27.56446],"type":"Point"}
}