{
  "type": "Feature",
  "properties": {
    "gn:admin1_code":"MR",
    "gn:admin2_code":"12",
    "gn:admin3_code":"54",
    "gn:admin4_code":"540009",
    "gn:asciiname":"Bijaura",
    "gn:country_code":"NP",
    "gn:dem":2419,
    "gn:feature_class":"P",
    "gn:feature_code":"PPLL",
    "gn:name":"Bijaura",
    "gn:population":0,
    "gn:timezone":"Asia/Kathmandu",
    "iso:country":"NP",
    "name:ceb_x_preferred":[
        "Bijaura"
    ],
    "name:fra_x_preferred":[
        "Bijaura"
    ],
    "name:mai_x_preferred":[
        "\u0935\u093f\u091c\u094c\u0930\u093e"
    ],
    "name:msa_x_preferred":[
        "Bijaura"
    ],
    "name:nep_x_preferred":[
        "\u092c\u093f\u091c\u094c\u0930\u093e"
    ],
    "name:new_x_preferred":[
        "\u092c\u093f\u091c\u094c\u0930\u093e"
    ],
    "name:pol_x_preferred":[
        "Bijaura"
    ],
    "wof:name":"Bijaura",
    "wof:placetype":"locality"
},
  "geometry": {"coordinates":[82.60093000000001,28.53646],"type":"Point"}
}