{
  "type": "Feature",
  "properties": {
    "gn:admin1_code":"MR",
    "gn:admin2_code":"2.0",
    "gn:admin3_code":"59.0",
    "gn:admin4_code":"590032.0",
    "gn:asciiname":"Gotheri",
    "gn:country_code":"NP",
    "gn:dem":671,
    "gn:feature_class":"P",
    "gn:feature_code":"PPLL",
    "gn:name":"Gotheri",
    "gn:population":0,
    "gn:timezone":"Asia/Kathmandu",
    "iso:country":"NP",
    "wof:name":"Gotheri",
    "wof:placetype":"locality"
},
  "geometry": {"coordinates":[81.57111999999999,28.50538],"type":"Point"}
}