{
  "type": "Feature",
  "properties": {
    "gn:admin1_code":"ER",
    "gn:admin2_code":"7.0",
    "gn:admin3_code":"8.0",
    "gn:admin4_code":"80004.0",
    "gn:asciiname":"Hoda",
    "gn:country_code":"NP",
    "gn:dem":1090,
    "gn:feature_class":"P",
    "gn:feature_code":"PPLL",
    "gn:name":"Hoda",
    "gn:population":0,
    "gn:timezone":"Asia/Kathmandu",
    "iso:country":"NP",
    "wof:name":"Hoda",
    "wof:placetype":"locality"
},
  "geometry": {"coordinates":[87.72277,27.21043],"type":"Point"}
}