{
  "type": "Feature",
  "properties": {
    "gn:admin1_code":"ER",
    "gn:admin2_code":"7",
    "gn:admin3_code":"5",
    "gn:admin4_code":"50019",
    "gn:asciiname":"Pharsadangi",
    "gn:country_code":"NP",
    "gn:dem":83,
    "gn:feature_class":"P",
    "gn:feature_code":"PPLL",
    "gn:name":"Pharsadangi",
    "gn:population":0,
    "gn:timezone":"Asia/Kathmandu",
    "iso:country":"NP",
    "wof:name":"Pharsadangi",
    "wof:placetype":"locality"
},
  "geometry": {"coordinates":[87.49375999999999,26.51337],"type":"Point"}
}