{
  "type": "Feature",
  "properties": {
    "gn:admin1_code":"CR",
    "gn:admin2_code":"1",
    "gn:admin3_code":"23",
    "gn:admin4_code":"230066.0",
    "gn:asciiname":"Dungdung",
    "gn:country_code":"NP",
    "gn:dem":1605,
    "gn:feature_class":"P",
    "gn:feature_code":"PPLL",
    "gn:name":"Dungdung",
    "gn:population":0,
    "gn:timezone":"Asia/Kathmandu",
    "iso:country":"NP",
    "wof:name":"Dungdung",
    "wof:placetype":"locality"
},
  "geometry": {"coordinates":[85.7037,27.82618],"type":"Point"}
}