{
  "type": "Feature",
  "properties": {
    "gn:admin1_code":"MR",
    "gn:admin2_code":"2",
    "gn:admin3_code":"60.0",
    "gn:admin4_code":"600053.0",
    "gn:asciiname":"Suanda",
    "gn:country_code":"NP",
    "gn:dem":1664,
    "gn:feature_class":"P",
    "gn:feature_code":"PPLL",
    "gn:name":"Suanda",
    "gn:population":0,
    "gn:timezone":"Asia/Kathmandu",
    "iso:country":"NP",
    "wof:name":"Suanda",
    "wof:placetype":"locality"
},
  "geometry": {"coordinates":[81.51429,29.03245],"type":"Point"}
}