{
  "type": "Feature",
  "properties": {
    "gn:admin1_code":"ER",
    "gn:admin2_code":"7.0",
    "gn:admin3_code":"6.0",
    "gn:admin4_code":"60039.0",
    "gn:asciiname":"Chaukidanda",
    "gn:country_code":"NP",
    "gn:dem":273,
    "gn:feature_class":"P",
    "gn:feature_code":"PPLL",
    "gn:name":"Chaukidanda",
    "gn:population":0,
    "gn:timezone":"Asia/Kathmandu",
    "iso:country":"NP",
    "wof:name":"Chaukidanda",
    "wof:placetype":"locality"
},
  "geometry": {"coordinates":[87.32315,26.76888],"type":"Point"}
}