{
  "type": "Feature",
  "properties": {
    "gn:admin1_code":"MR",
    "gn:admin2_code":"12",
    "gn:admin3_code":"54",
    "gn:admin4_code":"540012",
    "gn:asciiname":"Bayelle",
    "gn:country_code":"NP",
    "gn:dem":2233,
    "gn:feature_class":"P",
    "gn:feature_code":"PPLL",
    "gn:name":"Bayelle",
    "gn:population":0,
    "gn:timezone":"Asia/Kathmandu",
    "iso:country":"NP",
    "wof:name":"Bayelle",
    "wof:placetype":"locality"
},
  "geometry": {"coordinates":[82.45609,28.86002],"type":"Point"}
}