{
  "type": "Feature",
  "properties": {
    "gn:admin1_code":"WR",
    "gn:admin2_code":"4.0",
    "gn:admin3_code":"38.0",
    "gn:admin4_code":"380034.0",
    "gn:asciiname":"Kantheko Phed",
    "gn:country_code":"NP",
    "gn:dem":347,
    "gn:feature_class":"P",
    "gn:feature_code":"PPLL",
    "gn:name":"Kantheko Phed",
    "gn:population":0,
    "gn:timezone":"Asia/Kathmandu",
    "iso:country":"NP",
    "wof:name":"Kantheko Phed",
    "wof:placetype":"locality"
},
  "geometry": {"coordinates":[84.29224000000001,27.96669],"type":"Point"}
}