{
  "type": "Feature",
  "properties": {
    "gn:admin1_code":"FR",
    "gn:admin2_code":"14",
    "gn:admin3_code":"69.0",
    "gn:admin4_code":"690067.0",
    "gn:asciiname":"Gaguda",
    "gn:country_code":"NP",
    "gn:dem":1597,
    "gn:feature_class":"P",
    "gn:feature_code":"PPLL",
    "gn:name":"Gaguda",
    "gn:population":0,
    "gn:timezone":"Asia/Kathmandu",
    "iso:country":"NP",
    "name:ceb_x_preferred":[
        "Gaguda"
    ],
    "name:msa_x_preferred":[
        "Gaguda"
    ],
    "name:nep_x_preferred":[
        "\u0917\u0917\u0941\u0921\u093e"
    ],
    "name:new_x_preferred":[
        "\u0917\u0917\u0941\u0921\u093e"
    ],
    "name:pol_x_preferred":[
        "Gaguda"
    ],
    "wof:name":"Gaguda",
    "wof:placetype":"locality"
},
  "geometry": {"coordinates":[81.10605,29.20886],"type":"Point"}
}