{
  "type": "Feature",
  "properties": {
    "gn:admin1_code":"CR",
    "gn:admin2_code":"1",
    "gn:admin3_code":"27.0",
    "gn:admin4_code":"270018.0",
    "gn:asciiname":"Karkigaun",
    "gn:country_code":"NP",
    "gn:dem":1362,
    "gn:feature_class":"P",
    "gn:feature_code":"PPLL",
    "gn:name":"Karkigaun",
    "gn:population":0,
    "gn:timezone":"Asia/Kathmandu",
    "iso:country":"NP",
    "name:ceb_x_preferred":[
        "Karkigaun"
    ],
    "name:mai_x_preferred":[
        "\u0915\u093e\u0930\u094d\u0915\u0940\u0917\u093e\u0909\u0901"
    ],
    "name:msa_x_preferred":[
        "Karkigaun"
    ],
    "name:nep_x_preferred":[
        "\u0915\u093e\u0930\u094d\u0915\u0940\u0917\u093e\u0909\u0901"
    ],
    "name:new_x_preferred":[
        "\u0915\u093e\u0930\u094d\u0915\u0940\u0917\u093e\u0909\u0901"
    ],
    "name:pol_x_preferred":[
        "Karkigaun"
    ],
    "wof:name":"Karkigaun",
    "wof:placetype":"locality"
},
  "geometry": {"coordinates":[85.31522,27.77163],"type":"Point"}
}