{
  "type": "Feature",
  "properties": {
    "gn:admin1_code":"ER",
    "gn:admin2_code":"7",
    "gn:admin3_code":"10.0",
    "gn:admin4_code":"100045.0",
    "gn:asciiname":"Setogargare",
    "gn:country_code":"NP",
    "gn:dem":444,
    "gn:feature_class":"P",
    "gn:feature_code":"PPLL",
    "gn:name":"Setogargare",
    "gn:population":0,
    "gn:timezone":"Asia/Kathmandu",
    "iso:country":"NP",
    "wof:name":"Setogargare",
    "wof:placetype":"locality"
},
  "geometry": {"coordinates":[86.96141,26.91314],"type":"Point"}
}