{
  "type": "Feature",
  "properties": {
    "gn:admin1_code":"FR",
    "gn:admin2_code":"14",
    "gn:admin3_code":"68",
    "gn:admin4_code":"680007",
    "gn:asciiname":"Tomtana",
    "gn:country_code":"NP",
    "gn:dem":1342,
    "gn:feature_class":"P",
    "gn:feature_code":"PPLL",
    "gn:name":"Tomtana",
    "gn:population":0,
    "gn:timezone":"Asia/Kathmandu",
    "iso:country":"NP",
    "wof:name":"Tomtana",
    "wof:placetype":"locality"
},
  "geometry": {"coordinates":[81.04693,29.50189],"type":"Point"}
}