{
  "type": "Feature",
  "properties": {
    "gn:admin1_code":"MR",
    "gn:admin2_code":"2.0",
    "gn:admin3_code":"58.0",
    "gn:admin4_code":"580006.0",
    "gn:asciiname":"Tihuni",
    "gn:country_code":"NP",
    "gn:dem":161,
    "gn:feature_class":"P",
    "gn:feature_code":"PPLL",
    "gn:name":"Tihuni",
    "gn:population":0,
    "gn:timezone":"Asia/Kathmandu",
    "iso:country":"NP",
    "wof:name":"Tihuni",
    "wof:placetype":"locality"
},
  "geometry": {"coordinates":[81.16141999999998,28.49334],"type":"Point"}
}