{
  "type": "Feature",
  "properties": {
    "gn:admin1_code":"MR",
    "gn:admin2_code":"6",
    "gn:admin3_code":"62.0",
    "gn:admin4_code":"620008.0",
    "gn:asciiname":"Leparma",
    "gn:country_code":"NP",
    "gn:dem":2528,
    "gn:feature_class":"P",
    "gn:feature_code":"PPLL",
    "gn:name":"Leparma",
    "gn:population":0,
    "gn:timezone":"Asia/Kathmandu",
    "iso:country":"NP",
    "wof:name":"Leparma",
    "wof:placetype":"locality"
},
  "geometry": {"coordinates":[82.98652,28.89344],"type":"Point"}
}