{
  "type": "Feature",
  "properties": {
    "gn:admin1_code":"ER",
    "gn:admin2_code":"13",
    "gn:admin3_code":"13",
    "gn:admin4_code":"130055",
    "gn:asciiname":"Khamla",
    "gn:country_code":"NP",
    "gn:dem":1876,
    "gn:feature_class":"P",
    "gn:feature_code":"PPLL",
    "gn:name":"Khamla",
    "gn:population":0,
    "gn:timezone":"Asia/Kathmandu",
    "iso:country":"NP",
    "wof:name":"Khamla",
    "wof:placetype":"locality"
},
  "geometry": {"coordinates":[86.75145000000001,27.25538],"type":"Point"}
}