{
  "type": "Feature",
  "properties": {
    "gn:admin1_code":"MR",
    "gn:admin2_code":"2.0",
    "gn:admin3_code":"59.0",
    "gn:admin4_code":"590012.0",
    "gn:asciiname":"Tota Pakha",
    "gn:country_code":"NP",
    "gn:dem":1490,
    "gn:feature_class":"P",
    "gn:feature_code":"PPLL",
    "gn:name":"Tota Pakha",
    "gn:population":0,
    "gn:timezone":"Asia/Kathmandu",
    "iso:country":"NP",
    "wof:name":"Tota Pakha",
    "wof:placetype":"locality"
},
  "geometry": {"coordinates":[81.93589,28.49702000000001],"type":"Point"}
}