{
  "type": "Feature",
  "properties": {
    "gn:admin1_code":"CR",
    "gn:admin2_code":"1",
    "gn:admin3_code":"23",
    "gn:admin4_code":"230030",
    "gn:asciiname":"Singhyang",
    "gn:country_code":"NP",
    "gn:dem":1707,
    "gn:feature_class":"P",
    "gn:feature_code":"PPLL",
    "gn:name":"Singhyang",
    "gn:population":0,
    "gn:timezone":"Asia/Kathmandu",
    "iso:country":"NP",
    "wof:name":"Singhyang",
    "wof:placetype":"locality"
},
  "geometry": {"coordinates":[85.51739000000001,27.91441],"type":"Point"}
}