{
  "type": "Feature",
  "properties": {
    "gn:admin1_code":"WR",
    "gn:admin2_code":"4",
    "gn:admin3_code":"36.0",
    "gn:admin4_code":"360036.0",
    "gn:asciiname":"Lapsichaur",
    "gn:country_code":"NP",
    "gn:dem":816,
    "gn:feature_class":"P",
    "gn:feature_code":"PPLL",
    "gn:name":"Lapsichaur",
    "gn:population":0,
    "gn:timezone":"Asia/Kathmandu",
    "iso:country":"NP",
    "wof:name":"Lapsichaur",
    "wof:placetype":"locality"
},
  "geometry": {"coordinates":[84.53161999999998,28.03943],"type":"Point"}
}