{
  "type": "Feature",
  "properties": {
    "gn:admin1_code":"ER",
    "gn:admin2_code":"13",
    "gn:admin3_code":"11",
    "gn:admin4_code":"110032",
    "gn:asciiname":"Chhulemu",
    "gn:country_code":"NP",
    "gn:dem":2258,
    "gn:feature_class":"P",
    "gn:feature_code":"PPLL",
    "gn:name":"Chhulemu",
    "gn:population":0,
    "gn:timezone":"Asia/Kathmandu",
    "iso:country":"NP",
    "wof:name":"Chhulemu",
    "wof:placetype":"locality"
},
  "geometry": {"coordinates":[86.6339,27.60577],"type":"Point"}
}