{
  "type": "Feature",
  "properties": {
    "gn:admin1_code":"MR",
    "gn:admin2_code":"2.0",
    "gn:admin3_code":"57.0",
    "gn:admin4_code":"570024.0",
    "gn:asciiname":"Dulakhuti",
    "gn:country_code":"NP",
    "gn:dem":294,
    "gn:feature_class":"P",
    "gn:feature_code":"PPLL",
    "gn:name":"Dulakhuti",
    "gn:population":0,
    "gn:timezone":"Asia/Kathmandu",
    "iso:country":"NP",
    "wof:name":"Dulakhuti",
    "wof:placetype":"locality"
},
  "geometry": {"coordinates":[82.04335,27.96679],"type":"Point"}
}