{
  "type": "Feature",
  "properties": {
    "gn:admin1_code":"00",
    "gn:asciiname":"Thangjet",
    "gn:country_code":"NP",
    "gn:dem":1784,
    "gn:feature_class":"P",
    "gn:feature_code":"PPL",
    "gn:name":"Th\u0101ngjet",
    "gn:population":0,
    "gn:timezone":"Asia/Kathmandu",
    "iso:country":"NP",
    "wof:name":"Thangjet",
    "wof:placetype":"locality"
},
  "geometry": {"coordinates":[85.30875999999998,28.17755],"type":"Point"}
}