{
  "type": "Feature",
  "properties": {
    "gn:admin1_code":"WR",
    "gn:admin2_code":"3",
    "gn:admin3_code":"45.0",
    "gn:admin4_code":"450012.0",
    "gn:asciiname":"Tallo Dhiri",
    "gn:country_code":"NP",
    "gn:dem":2550,
    "gn:feature_class":"P",
    "gn:feature_code":"PPLL",
    "gn:name":"Tallo Dhiri",
    "gn:population":0,
    "gn:timezone":"Asia/Kathmandu",
    "iso:country":"NP",
    "wof:name":"Tallo Dhiri",
    "wof:placetype":"locality"
},
  "geometry": {"coordinates":[83.25991999999999,28.35808],"type":"Point"}
}