{
  "type": "Feature",
  "properties": {
    "gn:admin1_code":"CR",
    "gn:admin2_code":"5.0",
    "gn:asciiname":"Chhantardada",
    "gn:country_code":"NP",
    "gn:dem":1324,
    "gn:feature_class":"P",
    "gn:feature_code":"PPL",
    "gn:name":"Chh\u0101n\u1e6d\u0101r\u1e0d\u0101\u0303\u1e0d\u0101",
    "gn:population":0,
    "gn:timezone":"Asia/Kathmandu",
    "iso:country":"NP",
    "name:und_x_variant":[
        "Chh\u0101n\u1e6d\u0101r\u1e0d\u0101\u0303\u1e0d\u0101",
        "Chh\u0101n\u1e6d\u0101r\u1e0d\u0101n\u1e0d\u0101"
    ],
    "wof:name":"Chhantardada",
    "wof:placetype":"locality"
},
  "geometry": {"coordinates":[86.24320999999998,27.10919],"type":"Point"}
}