{
  "type": "Feature",
  "properties": {
    "gn:admin1_code":"ER",
    "gn:admin2_code":"13",
    "gn:admin3_code":"12",
    "gn:admin4_code":"120034.0",
    "gn:asciiname":"Dharapani",
    "gn:country_code":"NP",
    "gn:dem":1402,
    "gn:feature_class":"P",
    "gn:feature_code":"PPLL",
    "gn:name":"Dharapani",
    "gn:population":0,
    "gn:timezone":"Asia/Kathmandu",
    "iso:country":"NP",
    "name:fra_x_preferred":[
        "Dharapani"
    ],
    "name:new_x_preferred":[
        "\u0927\u093e\u0930\u093e\u092a\u093e\u0928\u0940"
    ],
    "name:pol_x_preferred":[
        "Dharapani"
    ],
    "wof:name":"Dharapani",
    "wof:placetype":"locality"
},
  "geometry": {"coordinates":[86.27774000000002,27.28321],"type":"Point"}
}