{
  "type": "Feature",
  "properties": {
    "gn:admin1_code":"MR",
    "gn:admin2_code":"2",
    "gn:admin3_code":"61.0",
    "gn:admin4_code":"610015.0",
    "gn:asciiname":"Sirpa",
    "gn:country_code":"NP",
    "gn:dem":1895,
    "gn:feature_class":"P",
    "gn:feature_code":"PPLL",
    "gn:name":"Sirpa",
    "gn:population":0,
    "gn:timezone":"Asia/Kathmandu",
    "iso:country":"NP",
    "name:ceb_x_preferred":[
        "Sirpa"
    ],
    "name:fra_x_preferred":[
        "Sirpa"
    ],
    "name:mai_x_preferred":[
        "\u0938\u093f\u0930\u094d\u092a"
    ],
    "name:msa_x_preferred":[
        "Sirpa"
    ],
    "name:nep_x_preferred":[
        "\u0938\u093f\u0930\u094d\u092a"
    ],
    "name:new_x_preferred":[
        "\u0938\u093f\u0930\u094d\u092a\u093e"
    ],
    "name:pol_x_preferred":[
        "Sirpa"
    ],
    "wof:name":"Sirpa",
    "wof:placetype":"locality"
},
  "geometry": {"coordinates":[81.95635,28.88273],"type":"Point"}
}