{
  "type": "Feature",
  "properties": {
    "gn:admin1_code":"CR",
    "gn:admin2_code":"11",
    "gn:admin3_code":"32",
    "gn:admin4_code":"320086",
    "gn:asciiname":"Sakhuawa",
    "gn:country_code":"NP",
    "gn:dem":94,
    "gn:feature_class":"P",
    "gn:feature_code":"PPLL",
    "gn:name":"Sakhuawa",
    "gn:population":0,
    "gn:timezone":"Asia/Kathmandu",
    "iso:country":"NP",
    "wof:name":"Sakhuawa",
    "wof:placetype":"locality"
},
  "geometry": {"coordinates":[85.32313000000001,27.00241],"type":"Point"}
}