{
  "type": "Feature",
  "properties": {
    "gn:admin1_code":"FR",
    "gn:admin2_code":"14.0",
    "gn:admin3_code":"69.0",
    "gn:admin4_code":"690049.0",
    "gn:asciiname":"Bhuntoli",
    "gn:country_code":"NP",
    "gn:dem":1772,
    "gn:feature_class":"P",
    "gn:feature_code":"PPLL",
    "gn:name":"Bhuntoli",
    "gn:population":0,
    "gn:timezone":"Asia/Kathmandu",
    "iso:country":"NP",
    "wof:name":"Bhuntoli",
    "wof:placetype":"locality"
},
  "geometry": {"coordinates":[81.33367,29.03478],"type":"Point"}
}