{
  "type": "Feature",
  "properties": {
    "gn:admin1_code":"ER",
    "gn:admin2_code":"7",
    "gn:admin3_code":"9",
    "gn:admin4_code":"90002",
    "gn:asciiname":"Phukam",
    "gn:country_code":"NP",
    "gn:dem":1616,
    "gn:feature_class":"P",
    "gn:feature_code":"PPLL",
    "gn:name":"Phukam",
    "gn:population":0,
    "gn:timezone":"Asia/Kathmandu",
    "iso:country":"NP",
    "wof:name":"Phukam",
    "wof:placetype":"locality"
},
  "geometry": {"coordinates":[87.31089,27.46838],"type":"Point"}
}