{
  "type": "Feature",
  "properties": {
    "gn:admin1_code":"ER",
    "gn:admin2_code":"10",
    "gn:admin3_code":"4.0",
    "gn:admin4_code":"40039.0",
    "gn:asciiname":"Nayanbari",
    "gn:country_code":"NP",
    "gn:dem":64,
    "gn:feature_class":"P",
    "gn:feature_code":"PPLL",
    "gn:name":"Nayanbari",
    "gn:population":0,
    "gn:timezone":"Asia/Kathmandu",
    "iso:country":"NP",
    "wof:name":"Nayanbari",
    "wof:placetype":"locality"
},
  "geometry": {"coordinates":[88.04788000000001,26.40611],"type":"Point"}
}