{
  "type": "Feature",
  "properties": {
    "gn:admin1_code":"CR",
    "gn:admin2_code":"1",
    "gn:admin3_code":"28",
    "gn:admin4_code":"280010",
    "gn:asciiname":"Gairaphum",
    "gn:country_code":"NP",
    "gn:dem":1208,
    "gn:feature_class":"P",
    "gn:feature_code":"PPLL",
    "gn:name":"Gairaphum",
    "gn:population":0,
    "gn:timezone":"Asia/Kathmandu",
    "iso:country":"NP",
    "wof:name":"Gairaphum",
    "wof:placetype":"locality"
},
  "geometry": {"coordinates":[85.11695999999998,27.99131],"type":"Point"}
}