{
  "type": "Feature",
  "properties": {
    "gn:admin1_code":"ER",
    "gn:admin2_code":"7.0",
    "gn:admin3_code":"8.0",
    "gn:admin4_code":"80017.0",
    "gn:asciiname":"Jaubari",
    "gn:country_code":"NP",
    "gn:dem":2125,
    "gn:feature_class":"P",
    "gn:feature_code":"PPLL",
    "gn:name":"Jaubari",
    "gn:population":0,
    "gn:timezone":"Asia/Kathmandu",
    "iso:country":"NP",
    "name:ceb_x_preferred":[
        "Jaubari"
    ],
    "name:deu_x_preferred":[
        "Jaubari"
    ],
    "name:fra_x_preferred":[
        "Jaubari"
    ],
    "name:new_x_preferred":[
        "\u091c\u094c\u092c\u093e\u0930\u0940"
    ],
    "wof:name":"Jaubari",
    "wof:placetype":"locality"
},
  "geometry": {"coordinates":[87.56065,27.21343],"type":"Point"}
}