{
  "type": "Feature",
  "properties": {
    "gn:admin1_code":"MR",
    "gn:admin2_code":"12",
    "gn:admin3_code":"54",
    "gn:admin4_code":"540017",
    "gn:asciiname":"Tila",
    "gn:country_code":"NP",
    "gn:dem":1572,
    "gn:feature_class":"P",
    "gn:feature_code":"PPLL",
    "gn:name":"Tila",
    "gn:population":0,
    "gn:timezone":"Asia/Kathmandu",
    "iso:country":"NP",
    "wof:name":"Tila",
    "wof:placetype":"locality"
},
  "geometry": {"coordinates":[82.63535,28.59855],"type":"Point"}
}