{
  "type": "Feature",
  "properties": {
    "gn:admin1_code":"MR",
    "gn:admin2_code":"2.0",
    "gn:admin3_code":"57.0",
    "gn:admin4_code":"570029.0",
    "gn:asciiname":"Jamunaha",
    "gn:country_code":"NP",
    "gn:dem":137,
    "gn:feature_class":"P",
    "gn:feature_code":"PPLL",
    "gn:name":"Jamunaha",
    "gn:population":0,
    "gn:timezone":"Asia/Kathmandu",
    "iso:country":"NP",
    "wof:name":"Jamunaha",
    "wof:placetype":"locality"
},
  "geometry": {"coordinates":[81.81905999999999,27.91215],"type":"Point"}
}