{
  "type": "Feature",
  "properties": {
    "gn:admin1_code":"FR",
    "gn:admin2_code":"9",
    "gn:admin3_code":"73.0",
    "gn:admin4_code":"730011.0",
    "gn:asciiname":"Khanmadagaun",
    "gn:country_code":"NP",
    "gn:dem":1695,
    "gn:feature_class":"P",
    "gn:feature_code":"PPLL",
    "gn:name":"Khanmadagaun",
    "gn:population":0,
    "gn:timezone":"Asia/Kathmandu",
    "iso:country":"NP",
    "wof:name":"Khanmadagaun",
    "wof:placetype":"locality"
},
  "geometry": {"coordinates":[80.67874,29.26895],"type":"Point"}
}