{
  "type": "Feature",
  "properties": {
    "gn:admin1_code":"CR",
    "gn:admin2_code":"11",
    "gn:admin3_code":"31",
    "gn:admin4_code":"310004",
    "gn:asciiname":"Jambu",
    "gn:country_code":"NP",
    "gn:dem":498,
    "gn:feature_class":"P",
    "gn:feature_code":"PPLL",
    "gn:name":"Jambu",
    "gn:population":0,
    "gn:timezone":"Asia/Kathmandu",
    "iso:country":"NP",
    "name:ceb_x_preferred":[
        "Jambu"
    ],
    "name:deu_x_preferred":[
        "Jambu"
    ],
    "name:nld_x_preferred":[
        "Jambu"
    ],
    "name:swe_x_preferred":[
        "Jambu"
    ],
    "wof:name":"Jambu",
    "wof:placetype":"locality"
},
  "geometry": {"coordinates":[84.95354,27.46843],"type":"Point"}
}