{
  "type": "Feature",
  "properties": {
    "gn:admin1_code":"WR",
    "gn:admin2_code":"4",
    "gn:admin3_code":"37",
    "gn:admin4_code":"370009",
    "gn:asciiname":"Bharatebesi",
    "gn:country_code":"NP",
    "gn:dem":870,
    "gn:feature_class":"P",
    "gn:feature_code":"PPLL",
    "gn:name":"Bharatebesi",
    "gn:population":0,
    "gn:timezone":"Asia/Kathmandu",
    "iso:country":"NP",
    "wof:name":"Bharatebesi",
    "wof:placetype":"locality"
},
  "geometry": {"coordinates":[84.46449,28.15651],"type":"Point"}
}