{
  "type": "Feature",
  "properties": {
    "gn:admin1_code":"WR",
    "gn:admin2_code":"4",
    "gn:admin3_code":"36.0",
    "gn:admin4_code":"360001.0",
    "gn:asciiname":"Bhandarthok",
    "gn:country_code":"NP",
    "gn:dem":573,
    "gn:feature_class":"P",
    "gn:feature_code":"PPLL",
    "gn:name":"Bhandarthok",
    "gn:population":0,
    "gn:timezone":"Asia/Kathmandu",
    "iso:country":"NP",
    "wof:name":"Bhandarthok",
    "wof:placetype":"locality"
},
  "geometry": {"coordinates":[84.48526,28.0832],"type":"Point"}
}