{
  "type": "Feature",
  "properties": {
    "gn:admin1_code":"FR",
    "gn:admin2_code":"14",
    "gn:admin3_code":"69.0",
    "gn:admin4_code":"690074.0",
    "gn:asciiname":"Syanglaban Kholagaun",
    "gn:country_code":"NP",
    "gn:dem":1127,
    "gn:feature_class":"P",
    "gn:feature_code":"PPLL",
    "gn:name":"Syanglaban Kholagaun",
    "gn:population":0,
    "gn:timezone":"Asia/Kathmandu",
    "iso:country":"NP",
    "wof:name":"Syanglaban Kholagaun",
    "wof:placetype":"locality"
},
  "geometry": {"coordinates":[81.18329,28.98987],"type":"Point"}
}