{
  "type": "Feature",
  "properties": {
    "gn:admin1_code":"MR",
    "gn:admin2_code":"12",
    "gn:admin3_code":"52",
    "gn:admin4_code":"520044",
    "gn:asciiname":"Dhanbang",
    "gn:country_code":"NP",
    "gn:dem":1207,
    "gn:feature_class":"P",
    "gn:feature_code":"PPLL",
    "gn:name":"Dhanbang",
    "gn:population":0,
    "gn:timezone":"Asia/Kathmandu",
    "iso:country":"NP",
    "wof:name":"Dhanbang",
    "wof:placetype":"locality"
},
  "geometry": {"coordinates":[82.66508,28.1495],"type":"Point"}
}