{
  "type": "Feature",
  "properties": {
    "gn:admin1_code":"ER",
    "gn:admin2_code":"10",
    "gn:admin3_code":"3.0",
    "gn:admin4_code":"30047.0",
    "gn:asciiname":"Kharidanda",
    "gn:country_code":"NP",
    "gn:dem":1188,
    "gn:feature_class":"P",
    "gn:feature_code":"PPLL",
    "gn:name":"Kharidanda",
    "gn:population":0,
    "gn:timezone":"Asia/Kathmandu",
    "iso:country":"NP",
    "wof:name":"Kharidanda",
    "wof:placetype":"locality"
},
  "geometry": {"coordinates":[87.96256,26.93921],"type":"Point"}
}