{
  "type": "Feature",
  "properties": {
    "gn:admin1_code":"FR",
    "gn:admin2_code":"9",
    "gn:admin3_code":"73.0",
    "gn:admin4_code":"730013.0",
    "gn:asciiname":"Baddimalas",
    "gn:country_code":"NP",
    "gn:dem":1206,
    "gn:feature_class":"P",
    "gn:feature_code":"PPLL",
    "gn:name":"Baddimalas",
    "gn:population":0,
    "gn:timezone":"Asia/Kathmandu",
    "iso:country":"NP",
    "wof:name":"Baddimalas",
    "wof:placetype":"locality"
},
  "geometry": {"coordinates":[80.21339999999999,29.0685],"type":"Point"}
}