{
  "type": "Feature",
  "properties": {
    "gn:admin1_code":"MR",
    "gn:admin2_code":"6",
    "gn:admin3_code":"66.0",
    "gn:admin4_code":"660001.0",
    "gn:asciiname":"Lek Barai",
    "gn:country_code":"NP",
    "gn:dem":3123,
    "gn:feature_class":"P",
    "gn:feature_code":"PPLL",
    "gn:name":"Lek Barai",
    "gn:population":0,
    "gn:timezone":"Asia/Kathmandu",
    "iso:country":"NP",
    "wof:name":"Lek Barai",
    "wof:placetype":"locality"
},
  "geometry": {"coordinates":[81.93629,29.80312],"type":"Point"}
}