{
  "type": "Feature",
  "properties": {
    "gn:admin1_code":"WR",
    "gn:admin2_code":"4",
    "gn:admin3_code":"36.0",
    "gn:admin4_code":"360056.0",
    "gn:asciiname":"Nyak",
    "gn:country_code":"NP",
    "gn:dem":2281,
    "gn:feature_class":"P",
    "gn:feature_code":"PPLL",
    "gn:name":"Nyak",
    "gn:population":0,
    "gn:timezone":"Asia/Kathmandu",
    "iso:country":"NP",
    "wof:name":"Nyak",
    "wof:placetype":"locality"
},
  "geometry": {"coordinates":[84.89228,28.44472],"type":"Point"}
}