{
  "type": "Feature",
  "properties": {
    "gn:admin1_code":"MR",
    "gn:admin2_code":"6",
    "gn:admin3_code":"63.0",
    "gn:admin4_code":"630019.0",
    "gn:asciiname":"Jol",
    "gn:country_code":"NP",
    "gn:dem":3115,
    "gn:feature_class":"P",
    "gn:feature_code":"PPLL",
    "gn:name":"Jol",
    "gn:population":0,
    "gn:timezone":"Asia/Kathmandu",
    "iso:country":"NP",
    "name:deu_x_preferred":[
        "Jol"
    ],
    "name:fra_x_preferred":[
        "Jol"
    ],
    "name:nld_x_preferred":[
        "Jol"
    ],
    "name:nno_x_preferred":[
        "Jol"
    ],
    "name:nor_x_preferred":[
        "Jol"
    ],
    "wof:name":"Jol",
    "wof:placetype":"locality"
},
  "geometry": {"coordinates":[81.86224,29.24577],"type":"Point"}
}