{
  "type": "Feature",
  "properties": {
    "gn:admin1_code":"00",
    "gn:asciiname":"Gachhitola",
    "gn:country_code":"NP",
    "gn:dem":115,
    "gn:feature_class":"P",
    "gn:feature_code":"PPL",
    "gn:name":"G\u0101chhi\u0307\u0304\u1e6dol\u0101",
    "gn:population":0,
    "gn:timezone":"Asia/Kathmandu",
    "iso:country":"NP",
    "name:und_x_variant":[
        "G\u0101chhi\u0307\u0304\u1e6dol\u0101",
        "G\u0101chh\u012b\u1e6dol\u0101"
    ],
    "wof:name":"Gachhitola",
    "wof:placetype":"locality"
},
  "geometry": {"coordinates":[85.21049000000002,27.06767],"type":"Point"}
}