{
  "type": "Feature",
  "properties": {
    "gn:admin1_code":"WR",
    "gn:admin2_code":"3",
    "gn:admin3_code":"45.0",
    "gn:admin4_code":"450028.0",
    "gn:asciiname":"Nigalpani",
    "gn:country_code":"NP",
    "gn:dem":1748,
    "gn:feature_class":"P",
    "gn:feature_code":"PPLL",
    "gn:name":"Nigalpani",
    "gn:population":0,
    "gn:timezone":"Asia/Kathmandu",
    "iso:country":"NP",
    "wof:name":"Nigalpani",
    "wof:placetype":"locality"
},
  "geometry": {"coordinates":[83.12085,28.26523],"type":"Point"}
}