{
  "type": "Feature",
  "properties": {
    "gn:admin1_code":"CR",
    "gn:admin2_code":"11",
    "gn:admin3_code":"34",
    "gn:admin4_code":"340083",
    "gn:asciiname":"Barwaratar",
    "gn:country_code":"NP",
    "gn:dem":88,
    "gn:feature_class":"P",
    "gn:feature_code":"PPLL",
    "gn:name":"Barwaratar",
    "gn:population":0,
    "gn:timezone":"Asia/Kathmandu",
    "iso:country":"NP",
    "wof:name":"Barwaratar",
    "wof:placetype":"locality"
},
  "geometry": {"coordinates":[84.82951,27.09057],"type":"Point"}
}