{
  "type": "Feature",
  "properties": {
    "gn:admin1_code":"MR",
    "gn:admin2_code":"12",
    "gn:admin3_code":"56.0",
    "gn:admin4_code":"560032.0",
    "gn:asciiname":"Kanariya",
    "gn:country_code":"NP",
    "gn:dem":596,
    "gn:feature_class":"P",
    "gn:feature_code":"PPLL",
    "gn:name":"Kanariya",
    "gn:population":0,
    "gn:timezone":"Asia/Kathmandu",
    "iso:country":"NP",
    "name:fra_x_preferred":[
        "Kanariya"
    ],
    "name:glg_x_preferred":[
        "Kanariya"
    ],
    "name:ita_x_preferred":[
        "Kanariya"
    ],
    "name:jpn_x_preferred":[
        "Kanariya"
    ],
    "name:pol_x_preferred":[
        "Kanariya"
    ],
    "name:spa_x_preferred":[
        "Kanariya"
    ],
    "name:tha_x_preferred":[
        "\u0e04\u0e32\u0e19\u0e32\u0e23\u0e34\u0e22\u0e30"
    ],
    "name:zho_x_preferred":[
        "Kanariya"
    ],
    "wof:name":"Kanariya",
    "wof:placetype":"locality"
},
  "geometry": {"coordinates":[82.40243000000002,28.011],"type":"Point"}
}