{
  "type": "Feature",
  "properties": {
    "gn:admin1_code":"MR",
    "gn:admin2_code":"12",
    "gn:admin3_code":"56.0",
    "gn:admin4_code":"560011.0",
    "gn:asciiname":"Kalakanti",
    "gn:country_code":"NP",
    "gn:dem":304,
    "gn:feature_class":"P",
    "gn:feature_code":"PPLL",
    "gn:name":"Kalakanti",
    "gn:population":0,
    "gn:timezone":"Asia/Kathmandu",
    "iso:country":"NP",
    "wof:name":"Kalakanti",
    "wof:placetype":"locality"
},
  "geometry": {"coordinates":[82.76449000000002,27.81013],"type":"Point"}
}