{
  "type": "Feature",
  "properties": {
    "gn:admin1_code":"ER",
    "gn:admin2_code":"10.0",
    "gn:admin3_code":"1.0",
    "gn:admin4_code":"10016.0",
    "gn:asciiname":"Pathibhara Khas (Pyramid Peak)",
    "gn:country_code":"NP",
    "gn:dem":6633,
    "gn:feature_class":"P",
    "gn:feature_code":"PPLL",
    "gn:name":"Pathibhara Khas (Pyramid Peak)",
    "gn:population":0,
    "gn:timezone":"Asia/Kathmandu",
    "iso:country":"NP",
    "wof:name":"Pathibhara Khas (Pyramid Peak)",
    "wof:placetype":"locality"
},
  "geometry": {"coordinates":[88.167,27.82371],"type":"Point"}
}