{
  "type": "Feature",
  "properties": {
    "gn:admin1_code":"FR",
    "gn:admin2_code":"14",
    "gn:admin3_code":"71.0",
    "gn:admin4_code":"710030.0",
    "gn:asciiname":"Danigauda",
    "gn:country_code":"NP",
    "gn:dem":542,
    "gn:feature_class":"P",
    "gn:feature_code":"PPLL",
    "gn:name":"Danigauda",
    "gn:population":0,
    "gn:timezone":"Asia/Kathmandu",
    "iso:country":"NP",
    "wof:name":"Danigauda",
    "wof:placetype":"locality"
},
  "geometry": {"coordinates":[81.03414000000002,28.88717],"type":"Point"}
}