{
  "type": "Feature",
  "properties": {
    "gn:admin1_code":"FR",
    "gn:admin2_code":"14",
    "gn:admin3_code":"71.0",
    "gn:admin4_code":"710044.0",
    "gn:asciiname":"Tilakpur",
    "gn:country_code":"NP",
    "gn:dem":178,
    "gn:feature_class":"P",
    "gn:feature_code":"PPLL",
    "gn:name":"Tilakpur",
    "gn:population":0,
    "gn:timezone":"Asia/Kathmandu",
    "iso:country":"NP",
    "name:ceb_x_preferred":[
        "Tilakpur"
    ],
    "name:hin_x_preferred":[
        "\u0924\u093f\u0932\u0915\u092a\u0941\u0930"
    ],
    "name:msa_x_preferred":[
        "Tilakpur"
    ],
    "name:new_x_preferred":[
        "\u0924\u093f\u0932\u0915\u092a\u0941\u0930"
    ],
    "name:pol_x_preferred":[
        "Tilakpur"
    ],
    "wof:name":"Tilakpur",
    "wof:placetype":"locality"
},
  "geometry": {"coordinates":[80.72836,28.7106],"type":"Point"}
}