{
  "type": "Feature",
  "properties": {
    "gn:admin1_code":"CR",
    "gn:admin2_code":"5",
    "gn:admin3_code":"22.0",
    "gn:admin4_code":"220014.0",
    "gn:asciiname":"Date",
    "gn:country_code":"NP",
    "gn:dem":2103,
    "gn:feature_class":"P",
    "gn:feature_code":"PPLL",
    "gn:name":"Date",
    "gn:population":0,
    "gn:timezone":"Asia/Kathmandu",
    "iso:country":"NP",
    "wof:name":"Date",
    "wof:placetype":"locality"
},
  "geometry": {"coordinates":[85.99865,27.51908],"type":"Point"}
}