{
  "type": "Feature",
  "properties": {
    "gn:admin1_code":"WR",
    "gn:admin2_code":"4",
    "gn:admin3_code":"36.0",
    "gn:admin4_code":"360027.0",
    "gn:asciiname":"Tallokatrok",
    "gn:country_code":"NP",
    "gn:dem":480,
    "gn:feature_class":"P",
    "gn:feature_code":"PPLL",
    "gn:name":"Tallokatrok",
    "gn:population":0,
    "gn:timezone":"Asia/Kathmandu",
    "iso:country":"NP",
    "wof:name":"Tallokatrok",
    "wof:placetype":"locality"
},
  "geometry": {"coordinates":[84.83183000000002,27.79753],"type":"Point"}
}