{
  "type": "Feature",
  "properties": {
    "gn:admin1_code":"MR",
    "gn:admin2_code":"2",
    "gn:admin3_code":"60.0",
    "gn:admin4_code":"600031.0",
    "gn:asciiname":"Sirsain",
    "gn:country_code":"NP",
    "gn:dem":744,
    "gn:feature_class":"P",
    "gn:feature_code":"PPLL",
    "gn:name":"Sirsain",
    "gn:population":0,
    "gn:timezone":"Asia/Kathmandu",
    "iso:country":"NP",
    "wof:name":"Sirsain",
    "wof:placetype":"locality"
},
  "geometry": {"coordinates":[81.50765,28.9238],"type":"Point"}
}