{
  "type": "Feature",
  "properties": {
    "gn:admin1_code":"CR",
    "gn:admin2_code":"1",
    "gn:admin3_code":"28",
    "gn:admin4_code":"280039",
    "gn:asciiname":"Thapatol",
    "gn:country_code":"NP",
    "gn:dem":1286,
    "gn:feature_class":"P",
    "gn:feature_code":"PPLL",
    "gn:name":"Thapatol",
    "gn:population":0,
    "gn:timezone":"Asia/Kathmandu",
    "iso:country":"NP",
    "wof:name":"Thapatol",
    "wof:placetype":"locality"
},
  "geometry": {"coordinates":[85.367,27.875],"type":"Point"}
}