{
  "type": "Feature",
  "properties": {
    "gn:admin1_code":"00",
    "gn:asciiname":"Gotamsiyala",
    "gn:country_code":"NP",
    "gn:dem":1630,
    "gn:feature_class":"P",
    "gn:feature_code":"PPL",
    "gn:name":"Got\u0101msiy\u0101l\u0101",
    "gn:population":0,
    "gn:timezone":"Asia/Kathmandu",
    "iso:country":"NP",
    "name:und_x_variant":[
        "Got\u0101m",
        "Got\u0101msiy\u0101l\u0101"
    ],
    "wof:name":"Gotamsiyala",
    "wof:placetype":"locality"
},
  "geometry": {"coordinates":[82.48560999999999,28.85703],"type":"Point"}
}