{
  "type": "Feature",
  "properties": {
    "gn:admin1_code":"FR",
    "gn:admin2_code":"9",
    "gn:admin3_code":"74",
    "gn:admin4_code":"740059",
    "gn:asciiname":"Dhungepani",
    "gn:country_code":"NP",
    "gn:dem":1532,
    "gn:feature_class":"P",
    "gn:feature_code":"PPLL",
    "gn:name":"Dhungepani",
    "gn:population":0,
    "gn:timezone":"Asia/Kathmandu",
    "iso:country":"NP",
    "wof:name":"Dhungepani",
    "wof:placetype":"locality"
},
  "geometry": {"coordinates":[80.48299,29.57843],"type":"Point"}
}