{
  "type": "Feature",
  "properties": {
    "gn:admin1_code":"WR",
    "gn:admin2_code":"3",
    "gn:admin3_code":"45.0",
    "gn:admin4_code":"450009.0",
    "gn:asciiname":"Bhanj",
    "gn:country_code":"NP",
    "gn:dem":1464,
    "gn:feature_class":"P",
    "gn:feature_code":"PPLL",
    "gn:name":"Bhanj",
    "gn:population":0,
    "gn:timezone":"Asia/Kathmandu",
    "iso:country":"NP",
    "wof:name":"Bhanj",
    "wof:placetype":"locality"
},
  "geometry": {"coordinates":[83.15748000000001,28.30358],"type":"Point"}
}