{
  "type": "Feature",
  "properties": {
    "gn:admin1_code":"CR",
    "gn:admin2_code":"5",
    "gn:admin3_code":"21",
    "gn:admin4_code":"210054",
    "gn:asciiname":"Darimbot",
    "gn:country_code":"NP",
    "gn:dem":1446,
    "gn:feature_class":"P",
    "gn:feature_code":"PPLL",
    "gn:name":"Darimbot",
    "gn:population":0,
    "gn:timezone":"Asia/Kathmandu",
    "iso:country":"NP",
    "wof:name":"Darimbot",
    "wof:placetype":"locality"
},
  "geometry": {"coordinates":[86.12586999999998,27.42603],"type":"Point"}
}