{
  "type": "Feature",
  "properties": {
    "gn:admin1_code":"CR",
    "gn:admin2_code":"1",
    "gn:admin3_code":"30.0",
    "gn:admin4_code":"300035.0",
    "gn:asciiname":"Pandhare",
    "gn:country_code":"NP",
    "gn:dem":953,
    "gn:feature_class":"P",
    "gn:feature_code":"PPLL",
    "gn:name":"Pandhare",
    "gn:population":0,
    "gn:timezone":"Asia/Kathmandu",
    "iso:country":"NP",
    "wof:name":"Pandhare",
    "wof:placetype":"locality"
},
  "geometry": {"coordinates":[84.92655000000001,27.91424],"type":"Point"}
}