{
  "type": "Feature",
  "properties": {
    "gn:admin1_code":"CR",
    "gn:admin2_code":"11",
    "gn:admin3_code":"31",
    "gn:admin4_code":"310016",
    "gn:asciiname":"Jhurjhure Thali",
    "gn:country_code":"NP",
    "gn:dem":296,
    "gn:feature_class":"P",
    "gn:feature_code":"PPLL",
    "gn:name":"Jhurjhure Thali",
    "gn:population":0,
    "gn:timezone":"Asia/Kathmandu",
    "iso:country":"NP",
    "wof:name":"Jhurjhure Thali",
    "wof:placetype":"locality"
},
  "geometry": {"coordinates":[85.40999000000002,27.31588],"type":"Point"}
}