{
  "type": "Feature",
  "properties": {
    "gn:admin1_code":"CR",
    "gn:admin2_code":"11",
    "gn:admin3_code":"32",
    "gn:admin4_code":"320084",
    "gn:asciiname":"Rangapur",
    "gn:country_code":"NP",
    "gn:dem":111,
    "gn:feature_class":"P",
    "gn:feature_code":"PPLL",
    "gn:name":"Rangapur",
    "gn:population":0,
    "gn:timezone":"Asia/Kathmandu",
    "iso:country":"NP",
    "name:pol_x_preferred":[
        "Rangapur"
    ],
    "wof:name":"Rangapur",
    "wof:placetype":"locality"
},
  "geometry": {"coordinates":[85.29588000000003,27.06753],"type":"Point"}
}