{
  "type": "Feature",
  "properties": {
    "gn:admin1_code":"MR",
    "gn:admin2_code":"6",
    "gn:admin3_code":"66.0",
    "gn:admin4_code":"660003.0",
    "gn:asciiname":"Maja",
    "gn:country_code":"NP",
    "gn:dem":2254,
    "gn:feature_class":"P",
    "gn:feature_code":"PPLL",
    "gn:name":"Maja",
    "gn:population":0,
    "gn:timezone":"Asia/Kathmandu",
    "iso:country":"NP",
    "name:bos_x_preferred":[
        "Maja"
    ],
    "name:ceb_x_preferred":[
        "Maja"
    ],
    "name:ces_x_preferred":[
        "Maja"
    ],
    "name:deu_x_preferred":[
        "Maja"
    ],
    "name:epo_x_preferred":[
        "Maja"
    ],
    "name:est_x_preferred":[
        "Maja"
    ],
    "name:fin_x_preferred":[
        "Maja"
    ],
    "name:fra_x_preferred":[
        "Maja"
    ],
    "name:fry_x_preferred":[
        "Maja"
    ],
    "name:hrv_x_preferred":[
        "Maja"
    ],
    "name:hun_x_preferred":[
        "Maja"
    ],
    "name:ind_x_preferred":[
        "Maja"
    ],
    "name:ita_x_preferred":[
        "Maja"
    ],
    "name:jpn_x_preferred":[
        "\u30de\u30fc\u30e4"
    ],
    "name:lit_x_preferred":[
        "Maja"
    ],
    "name:mkd_x_preferred":[
        "\u041c\u0430\u0458\u0430"
    ],
    "name:nld_x_preferred":[
        "Maja"
    ],
    "name:pol_x_preferred":[
        "Maja"
    ],
    "name:por_x_preferred":[
        "Maja"
    ],
    "name:slk_x_preferred":[
        "Maja"
    ],
    "name:slv_x_preferred":[
        "Maja"
    ],
    "name:srp_x_preferred":[
        "\u041c\u0430\u0458\u0430"
    ],
    "name:swe_x_preferred":[
        "Maja"
    ],
    "name:tur_x_preferred":[
        "Maja"
    ],
    "wof:name":"Maja",
    "wof:placetype":"locality"
},
  "geometry": {"coordinates":[81.86194,29.92995],"type":"Point"}
}