{
  "type": "Feature",
  "properties": {
    "gn:admin1_code":"ER",
    "gn:admin2_code":"7",
    "gn:admin3_code":"7.0",
    "gn:admin4_code":"70035.0",
    "gn:asciiname":"Teliya",
    "gn:country_code":"NP",
    "gn:dem":1032,
    "gn:feature_class":"P",
    "gn:feature_code":"PPLL",
    "gn:name":"Teliya",
    "gn:population":0,
    "gn:timezone":"Asia/Kathmandu",
    "iso:country":"NP",
    "wof:name":"Teliya",
    "wof:placetype":"locality"
},
  "geometry": {"coordinates":[87.41874,27.00812],"type":"Point"}
}