{
  "type": "Feature",
  "properties": {
    "gn:admin1_code":"WR",
    "gn:admin2_code":"8",
    "gn:admin3_code":"46.0",
    "gn:admin4_code":"460056.0",
    "gn:asciiname":"Masina",
    "gn:country_code":"NP",
    "gn:dem":2071,
    "gn:feature_class":"P",
    "gn:feature_code":"PPLL",
    "gn:name":"Masina",
    "gn:population":0,
    "gn:timezone":"Asia/Kathmandu",
    "iso:country":"NP",
    "wof:name":"Masina",
    "wof:placetype":"locality"
},
  "geometry": {"coordinates":[83.50303000000002,28.03056],"type":"Point"}
}