{
  "type": "Feature",
  "properties": {
    "gn:admin1_code":"CR",
    "gn:admin2_code":"5",
    "gn:admin3_code":"17.0",
    "gn:admin4_code":"170035.0",
    "gn:asciiname":"Karmahi Katti",
    "gn:country_code":"NP",
    "gn:dem":77,
    "gn:feature_class":"P",
    "gn:feature_code":"PPLL",
    "gn:name":"Karmahi Katti",
    "gn:population":0,
    "gn:timezone":"Asia/Kathmandu",
    "iso:country":"NP",
    "wof:name":"Karmahi Katti",
    "wof:placetype":"locality"
},
  "geometry": {"coordinates":[86.05991,26.68464],"type":"Point"}
}