{
  "type": "Feature",
  "properties": {
    "gn:admin1_code":"CR",
    "gn:admin2_code":"5",
    "gn:admin3_code":"19",
    "gn:admin4_code":"190090",
    "gn:asciiname":"Gelaha",
    "gn:country_code":"NP",
    "gn:dem":158,
    "gn:feature_class":"P",
    "gn:feature_code":"PPLL",
    "gn:name":"Gelaha",
    "gn:population":0,
    "gn:timezone":"Asia/Kathmandu",
    "iso:country":"NP",
    "wof:name":"Gelaha",
    "wof:placetype":"locality"
},
  "geometry": {"coordinates":[85.59354,27.09554],"type":"Point"}
}