{
  "type": "Feature",
  "properties": {
    "gn:admin1_code":"FR",
    "gn:admin2_code":"14",
    "gn:admin3_code":"70.0",
    "gn:admin4_code":"700021.0",
    "gn:asciiname":"Sunda",
    "gn:country_code":"NP",
    "gn:dem":1388,
    "gn:feature_class":"P",
    "gn:feature_code":"PPLL",
    "gn:name":"Sunda",
    "gn:population":0,
    "gn:timezone":"Asia/Kathmandu",
    "iso:country":"NP",
    "wof:name":"Sunda",
    "wof:placetype":"locality"
},
  "geometry": {"coordinates":[80.76474,29.25997000000001],"type":"Point"}
}