{
  "type": "Feature",
  "properties": {
    "gn:admin1_code":"WR",
    "gn:admin2_code":"8",
    "gn:admin3_code":"46.0",
    "gn:admin4_code":"460065.0",
    "gn:asciiname":"Bansa Rukh",
    "gn:country_code":"NP",
    "gn:dem":1348,
    "gn:feature_class":"P",
    "gn:feature_code":"PPLL",
    "gn:name":"Bansa Rukh",
    "gn:population":0,
    "gn:timezone":"Asia/Kathmandu",
    "iso:country":"NP",
    "wof:name":"Bansa Rukh",
    "wof:placetype":"locality"
},
  "geometry": {"coordinates":[83.14739,28.0892],"type":"Point"}
}