{
  "type": "Feature",
  "properties": {
    "gn:admin1_code":"FR",
    "gn:admin2_code":"9",
    "gn:admin3_code":"75.0",
    "gn:admin4_code":"750038.0",
    "gn:asciiname":"Tallo Phute Pairogaun",
    "gn:country_code":"NP",
    "gn:dem":2323,
    "gn:feature_class":"P",
    "gn:feature_code":"PPLL",
    "gn:name":"Tallo Phute Pairogaun",
    "gn:population":0,
    "gn:timezone":"Asia/Kathmandu",
    "iso:country":"NP",
    "wof:name":"Tallo Phute Pairogaun",
    "wof:placetype":"locality"
},
  "geometry": {"coordinates":[80.78952,29.78465],"type":"Point"}
}