{
  "type": "Feature",
  "properties": {
    "gn:admin1_code":"WR",
    "gn:admin2_code":"3",
    "gn:admin3_code":"45.0",
    "gn:admin4_code":"450054.0",
    "gn:asciiname":"Wainkuna",
    "gn:country_code":"NP",
    "gn:dem":1029,
    "gn:feature_class":"P",
    "gn:feature_code":"PPLL",
    "gn:name":"Wainkuna",
    "gn:population":0,
    "gn:timezone":"Asia/Kathmandu",
    "iso:country":"NP",
    "wof:name":"Wainkuna",
    "wof:placetype":"locality"
},
  "geometry": {"coordinates":[83.57727,28.09295],"type":"Point"}
}