{
  "type": "Feature",
  "properties": {
    "gn:admin1_code":"ER",
    "gn:admin2_code":"7.0",
    "gn:admin3_code":"6.0",
    "gn:admin4_code":"60039.0",
    "gn:asciiname":"Hardiya",
    "gn:country_code":"NP",
    "gn:dem":921,
    "gn:feature_class":"P",
    "gn:feature_code":"PPLL",
    "gn:name":"Hardiya",
    "gn:population":0,
    "gn:timezone":"Asia/Kathmandu",
    "iso:country":"NP",
    "name:fra_x_preferred":[
        "Hardiya"
    ],
    "name:new_x_preferred":[
        "\u0939\u0930\u094d\u0926\u093f\u092f\u093e"
    ],
    "name:pol_x_preferred":[
        "Hardiya"
    ],
    "wof:name":"Hardiya",
    "wof:placetype":"locality"
},
  "geometry": {"coordinates":[87.34671999999998,26.82372],"type":"Point"}
}