{
  "type": "Feature",
  "properties": {
    "gn:admin1_code":"WR",
    "gn:admin2_code":"4.0",
    "gn:admin3_code":"38.0",
    "gn:admin4_code":"380002.0",
    "gn:asciiname":"Karanswanra",
    "gn:country_code":"NP",
    "gn:dem":708,
    "gn:feature_class":"P",
    "gn:feature_code":"PPLL",
    "gn:name":"Karanswanra",
    "gn:population":0,
    "gn:timezone":"Asia/Kathmandu",
    "iso:country":"NP",
    "wof:name":"Karanswanra",
    "wof:placetype":"locality"
},
  "geometry": {"coordinates":[84.04992,27.97855],"type":"Point"}
}