{
  "type": "Feature",
  "properties": {
    "gn:admin1_code":"CR",
    "gn:admin2_code":"5",
    "gn:admin3_code":"18",
    "gn:admin4_code":"180041",
    "gn:asciiname":"Baderwa",
    "gn:country_code":"NP",
    "gn:dem":151,
    "gn:feature_class":"P",
    "gn:feature_code":"PPLL",
    "gn:name":"Baderwa",
    "gn:population":0,
    "gn:timezone":"Asia/Kathmandu",
    "iso:country":"NP",
    "wof:name":"Baderwa",
    "wof:placetype":"locality"
},
  "geometry": {"coordinates":[85.7822,26.96482],"type":"Point"}
}