{
  "type": "Feature",
  "properties": {
    "gn:admin1_code":"CR",
    "gn:admin2_code":"1",
    "gn:admin3_code":"28",
    "gn:admin4_code":"280041",
    "gn:asciiname":"Sathiya",
    "gn:country_code":"NP",
    "gn:dem":846,
    "gn:feature_class":"P",
    "gn:feature_code":"PPLL",
    "gn:name":"Sathiya",
    "gn:population":0,
    "gn:timezone":"Asia/Kathmandu",
    "iso:country":"NP",
    "wof:name":"Sathiya",
    "wof:placetype":"locality"
},
  "geometry": {"coordinates":[85.30563000000002,27.94598],"type":"Point"}
}