{
  "type": "Feature",
  "properties": {
    "gn:admin1_code":"00",
    "gn:asciiname":"Chukhung",
    "gn:country_code":"NP",
    "gn:dem":4842,
    "gn:feature_class":"P",
    "gn:feature_code":"PPL",
    "gn:name":"Chukhung",
    "gn:population":0,
    "gn:timezone":"Asia/Kathmandu",
    "iso:country":"NP",
    "wof:name":"Chukhung",
    "wof:placetype":"locality"
},
  "geometry": {"coordinates":[86.85811,27.90721],"type":"Point"}
}