{
  "type": "Feature",
  "properties": {
    "gn:admin1_code":"00",
    "gn:asciiname":"Santapurmatiyon",
    "gn:country_code":"NP",
    "gn:dem":115,
    "gn:feature_class":"P",
    "gn:feature_code":"PPL",
    "gn:name":"Santapurma\u1e6diyon",
    "gn:population":0,
    "gn:timezone":"Asia/Kathmandu",
    "iso:country":"NP",
    "wof:name":"Santapurmatiyon",
    "wof:placetype":"locality"
},
  "geometry": {"coordinates":[85.33102,27.08052],"type":"Point"}
}