{
  "type": "Feature",
  "properties": {
    "gn:admin1_code":"WR",
    "gn:admin2_code":"3",
    "gn:admin3_code":"43",
    "gn:admin4_code":"430024.0",
    "gn:asciiname":"Tsaurabong",
    "gn:country_code":"NP",
    "gn:dem":5958,
    "gn:feature_class":"P",
    "gn:feature_code":"PPLL",
    "gn:name":"Tsaurabong",
    "gn:population":0,
    "gn:timezone":"Asia/Kathmandu",
    "iso:country":"NP",
    "wof:name":"Tsaurabong",
    "wof:placetype":"locality"
},
  "geometry": {"coordinates":[83.38471,28.69127000000001],"type":"Point"}
}