{
  "type": "Feature",
  "properties": {
    "gn:admin1_code":"CR",
    "gn:admin2_code":"5",
    "gn:admin3_code":"20",
    "gn:admin4_code":"200037",
    "gn:asciiname":"Charghare",
    "gn:country_code":"NP",
    "gn:dem":1423,
    "gn:feature_class":"P",
    "gn:feature_code":"PPLL",
    "gn:name":"Charghare",
    "gn:population":0,
    "gn:timezone":"Asia/Kathmandu",
    "iso:country":"NP",
    "name:ceb_x_preferred":[
        "Charghare"
    ],
    "name:fra_x_preferred":[
        "Charghare"
    ],
    "name:mai_x_preferred":[
        "\u091a\u093e\u0930\u0918\u0930\u0947"
    ],
    "name:msa_x_preferred":[
        "Charghare"
    ],
    "name:nep_x_preferred":[
        "\u091a\u093e\u0930\u0918\u0930\u0947"
    ],
    "name:new_x_preferred":[
        "\u091a\u093e\u0930\u0918\u0930\u0947"
    ],
    "name:pol_x_preferred":[
        "Charghare"
    ],
    "wof:name":"Charghare",
    "wof:placetype":"locality"
},
  "geometry": {"coordinates":[85.75933000000001,27.37542],"type":"Point"}
}