{
  "type": "Feature",
  "properties": {
    "gn:admin1_code":"CR",
    "gn:admin2_code":"1",
    "gn:admin3_code":"23",
    "gn:admin4_code":"230016",
    "gn:asciiname":"Bicharichaurtol",
    "gn:country_code":"NP",
    "gn:dem":1783,
    "gn:feature_class":"P",
    "gn:feature_code":"PPLL",
    "gn:name":"Bicharichaurtol",
    "gn:population":0,
    "gn:timezone":"Asia/Kathmandu",
    "iso:country":"NP",
    "wof:name":"Bicharichaurtol",
    "wof:placetype":"locality"
},
  "geometry": {"coordinates":[85.56985,27.88065],"type":"Point"}
}