{
  "type": "Feature",
  "properties": {
    "gn:admin1_code":"WR",
    "gn:admin2_code":"3",
    "gn:admin3_code":"45.0",
    "gn:admin4_code":"450009.0",
    "gn:asciiname":"Kut",
    "gn:country_code":"NP",
    "gn:dem":1920,
    "gn:feature_class":"P",
    "gn:feature_code":"PPLL",
    "gn:name":"Kut",
    "gn:population":0,
    "gn:timezone":"Asia/Kathmandu",
    "iso:country":"NP",
    "name:ara_x_preferred":[
        "\u0627\u0644\u0643\u0648\u062a"
    ],
    "name:arz_x_preferred":[
        "\u0627\u0644\u0643\u0648\u062a"
    ],
    "name:bul_x_preferred":[
        "\u041a\u0443\u0442"
    ],
    "name:cat_x_preferred":[
        "Kut al-Amara"
    ],
    "name:ceb_x_preferred":[
        "Al K\u016bt"
    ],
    "name:ces_x_preferred":[
        "K\u00fat"
    ],
    "name:dan_x_preferred":[
        "Kut"
    ],
    "name:deu_x_preferred":[
        "Kut"
    ],
    "name:epo_x_preferred":[
        "Kut"
    ],
    "name:est_x_preferred":[
        "Al-K\u016bt"
    ],
    "name:eus_x_preferred":[
        "Kut"
    ],
    "name:fas_x_preferred":[
        "\u06a9\u0648\u062a"
    ],
    "name:fin_x_preferred":[
        "Al-Kut"
    ],
    "name:fra_x_preferred":[
        "Kut"
    ],
    "name:heb_x_preferred":[
        "\u05d0\u05dc-\u05db\u05d5\u05ea"
    ],
    "name:hun_x_preferred":[
        "K\u00fat"
    ],
    "name:ind_x_preferred":[
        "Al-Kut"
    ],
    "name:ita_x_preferred":[
        "Al-Kut"
    ],
    "name:jpn_x_preferred":[
        "\u30af\u30fc\u30c8"
    ],
    "name:kat_x_preferred":[
        "\u10d4\u10da-\u10d9\u10e3\u10d7\u10d8"
    ],
    "name:kaz_x_preferred":[
        "\u042d\u043b\u044c-\u041a\u0443\u0442"
    ],
    "name:msa_x_preferred":[
        "Al-Kut"
    ],
    "name:mzn_x_preferred":[
        "\u06a9\u0648\u062a"
    ],
    "name:nld_x_preferred":[
        "Al Koet"
    ],
    "name:nor_x_preferred":[
        "Kut"
    ],
    "name:pnb_x_preferred":[
        "\u06a9\u0648\u062a"
    ],
    "name:pol_x_preferred":[
        "Al-Kut"
    ],
    "name:por_x_preferred":[
        "Kut"
    ],
    "name:ron_x_preferred":[
        "Kut"
    ],
    "name:rus_x_preferred":[
        "\u042d\u043b\u044c-\u041a\u0443\u0442"
    ],
    "name:slv_x_preferred":[
        "Kut"
    ],
    "name:spa_x_preferred":[
        "Kut"
    ],
    "name:swe_x_preferred":[
        "Al-Kut"
    ],
    "name:tur_x_preferred":[
        "Kut"
    ],
    "name:ukr_x_preferred":[
        "\u0415\u043b\u044c-\u041a\u0443\u0442"
    ],
    "name:urd_x_preferred":[
        "\u06a9\u0648\u062a \u0627\u0644\u0639\u0645\u0627\u0631\u06c1"
    ],
    "name:war_x_preferred":[
        "Kut"
    ],
    "name:zho_x_preferred":[
        "\u5eab\u7279"
    ],
    "wof:name":"Kut",
    "wof:placetype":"locality"
},
  "geometry": {"coordinates":[83.13056,28.31323],"type":"Point"}
}