{
  "type": "Feature",
  "properties": {
    "gn:admin1_code":"CR",
    "gn:admin2_code":"5",
    "gn:admin3_code":"22.0",
    "gn:admin4_code":"220036.0",
    "gn:asciiname":"Parigaun",
    "gn:country_code":"NP",
    "gn:dem":1841,
    "gn:feature_class":"P",
    "gn:feature_code":"PPLL",
    "gn:name":"Parigaun",
    "gn:population":0,
    "gn:timezone":"Asia/Kathmandu",
    "iso:country":"NP",
    "wof:name":"Parigaun",
    "wof:placetype":"locality"
},
  "geometry": {"coordinates":[85.99772,27.65059],"type":"Point"}
}