{
  "type": "Feature",
  "properties": {
    "gn:admin1_code":"MR",
    "gn:admin2_code":"12",
    "gn:admin3_code":"56.0",
    "gn:admin4_code":"560028.0",
    "gn:asciiname":"Jaluke",
    "gn:country_code":"NP",
    "gn:dem":262,
    "gn:feature_class":"P",
    "gn:feature_code":"PPLL",
    "gn:name":"Jaluke",
    "gn:population":0,
    "gn:timezone":"Asia/Kathmandu",
    "iso:country":"NP",
    "wof:name":"Jaluke",
    "wof:placetype":"locality"
},
  "geometry": {"coordinates":[82.19225,27.93264000000001],"type":"Point"}
}