{
  "type": "Feature",
  "properties": {
    "gn:admin1_code":"WR",
    "gn:admin2_code":"8",
    "gn:admin3_code":"47",
    "gn:admin4_code":"470027",
    "gn:asciiname":"Heklang",
    "gn:country_code":"NP",
    "gn:dem":417,
    "gn:feature_class":"P",
    "gn:feature_code":"PPLL",
    "gn:name":"Heklang",
    "gn:population":0,
    "gn:timezone":"Asia/Kathmandu",
    "iso:country":"NP",
    "wof:name":"Heklang",
    "wof:placetype":"locality"
},
  "geometry": {"coordinates":[83.74632,27.90619],"type":"Point"}
}