{
  "type": "Feature",
  "properties": {
    "gn:admin1_code":"MR",
    "gn:admin2_code":"6",
    "gn:admin3_code":"65",
    "gn:admin4_code":"650002",
    "gn:asciiname":"Rokaya Bado",
    "gn:country_code":"NP",
    "gn:dem":1988,
    "gn:feature_class":"P",
    "gn:feature_code":"PPLL",
    "gn:name":"Rokaya Bado",
    "gn:population":0,
    "gn:timezone":"Asia/Kathmandu",
    "iso:country":"NP",
    "wof:name":"Rokaya Bado",
    "wof:placetype":"locality"
},
  "geometry": {"coordinates":[81.86103,29.6077],"type":"Point"}
}