{
  "type": "Feature",
  "properties": {
    "gn:admin1_code":"WR",
    "gn:admin2_code":"3",
    "gn:admin3_code":"44",
    "gn:admin4_code":"440041",
    "gn:asciiname":"Sidhali",
    "gn:country_code":"NP",
    "gn:dem":1656,
    "gn:feature_class":"P",
    "gn:feature_code":"PPLL",
    "gn:name":"Sidhali",
    "gn:population":0,
    "gn:timezone":"Asia/Kathmandu",
    "iso:country":"NP",
    "wof:name":"Sidhali",
    "wof:placetype":"locality"
},
  "geometry": {"coordinates":[83.64801,28.2731],"type":"Point"}
}