{
  "type": "Feature",
  "properties": {
    "gn:admin1_code":"ER",
    "gn:admin2_code":"10",
    "gn:admin3_code":"3.0",
    "gn:admin4_code":"30026.0",
    "gn:asciiname":"Serpe",
    "gn:country_code":"NP",
    "gn:dem":2091,
    "gn:feature_class":"P",
    "gn:feature_code":"PPLL",
    "gn:name":"Serpe",
    "gn:population":0,
    "gn:timezone":"Asia/Kathmandu",
    "iso:country":"NP",
    "wof:name":"Serpe",
    "wof:placetype":"locality"
},
  "geometry": {"coordinates":[87.93205999999998,27.06982],"type":"Point"}
}