{
  "type": "Feature",
  "properties": {
    "gn:admin1_code":"CR",
    "gn:admin2_code":"5",
    "gn:admin3_code":"21",
    "gn:admin4_code":"210025",
    "gn:asciiname":"Sargaun",
    "gn:country_code":"NP",
    "gn:dem":1311,
    "gn:feature_class":"P",
    "gn:feature_code":"PPLL",
    "gn:name":"Sargaun",
    "gn:population":0,
    "gn:timezone":"Asia/Kathmandu",
    "iso:country":"NP",
    "wof:name":"Sargaun",
    "wof:placetype":"locality"
},
  "geometry": {"coordinates":[86.20974,27.30084],"type":"Point"}
}