{
  "type": "Feature",
  "properties": {
    "gn:admin1_code":"MR",
    "gn:admin2_code":"6",
    "gn:admin3_code":"62.0",
    "gn:admin4_code":"620019.0",
    "gn:asciiname":"Pongra",
    "gn:country_code":"NP",
    "gn:dem":4015,
    "gn:feature_class":"P",
    "gn:feature_code":"PPLL",
    "gn:name":"Pongra",
    "gn:population":0,
    "gn:timezone":"Asia/Kathmandu",
    "iso:country":"NP",
    "wof:name":"Pongra",
    "wof:placetype":"locality"
},
  "geometry": {"coordinates":[83.09705,29.39308],"type":"Point"}
}