{
  "type": "Feature",
  "properties": {
    "gn:admin1_code":"FR",
    "gn:admin2_code":"14",
    "gn:admin3_code":"70.0",
    "gn:admin4_code":"700028.0",
    "gn:asciiname":"Aluswadi",
    "gn:country_code":"NP",
    "gn:dem":2368,
    "gn:feature_class":"P",
    "gn:feature_code":"PPLL",
    "gn:name":"Aluswadi",
    "gn:population":0,
    "gn:timezone":"Asia/Kathmandu",
    "iso:country":"NP",
    "wof:name":"Aluswadi",
    "wof:placetype":"locality"
},
  "geometry": {"coordinates":[80.97077,29.32397000000001],"type":"Point"}
}