{
  "type": "Feature",
  "properties": {
    "gn:admin1_code":"FR",
    "gn:admin2_code":"9",
    "gn:admin3_code":"74",
    "gn:admin4_code":"740050",
    "gn:asciiname":"Beru",
    "gn:country_code":"NP",
    "gn:dem":1089,
    "gn:feature_class":"P",
    "gn:feature_code":"PPLL",
    "gn:name":"Beru",
    "gn:population":0,
    "gn:timezone":"Asia/Kathmandu",
    "iso:country":"NP",
    "name:ceb_x_preferred":[
        "Beru"
    ],
    "name:deu_x_preferred":[
        "Beru"
    ],
    "name:ind_x_preferred":[
        "Beru"
    ],
    "name:nld_x_preferred":[
        "Beru"
    ],
    "name:rus_x_preferred":[
        "\u0411\u0435\u0440\u0443"
    ],
    "name:swe_x_preferred":[
        "Beru"
    ],
    "wof:name":"Beru",
    "wof:placetype":"locality"
},
  "geometry": {"coordinates":[80.30583,29.34029],"type":"Point"}
}