{
  "type": "Feature",
  "properties": {
    "gn:admin1_code":"MR",
    "gn:admin2_code":"12",
    "gn:admin3_code":"55",
    "gn:admin4_code":"550003",
    "gn:asciiname":"Patare",
    "gn:country_code":"NP",
    "gn:dem":1490,
    "gn:feature_class":"P",
    "gn:feature_code":"PPLL",
    "gn:name":"Patare",
    "gn:population":0,
    "gn:timezone":"Asia/Kathmandu",
    "iso:country":"NP",
    "wof:name":"Patare",
    "wof:placetype":"locality"
},
  "geometry": {"coordinates":[82.23623000000001,28.44567],"type":"Point"}
}