{
  "type": "Feature",
  "properties": {
    "gn:admin1_code":"WR",
    "gn:admin2_code":"4",
    "gn:admin3_code":"36.0",
    "gn:admin4_code":"360050.0",
    "gn:asciiname":"Purangaun",
    "gn:country_code":"NP",
    "gn:dem":751,
    "gn:feature_class":"P",
    "gn:feature_code":"PPLL",
    "gn:name":"Purangaun",
    "gn:population":0,
    "gn:timezone":"Asia/Kathmandu",
    "iso:country":"NP",
    "wof:name":"Purangaun",
    "wof:placetype":"locality"
},
  "geometry": {"coordinates":[84.59255,27.94466],"type":"Point"}
}