{
  "type": "Feature",
  "properties": {
    "gn:admin1_code":"ER",
    "gn:admin2_code":"13",
    "gn:admin3_code":"11",
    "gn:admin4_code":"110007",
    "gn:asciiname":"Chhermading",
    "gn:country_code":"NP",
    "gn:dem":2597,
    "gn:feature_class":"P",
    "gn:feature_code":"PPLL",
    "gn:name":"Chhermading",
    "gn:population":0,
    "gn:timezone":"Asia/Kathmandu",
    "iso:country":"NP",
    "wof:name":"Chhermading",
    "wof:placetype":"locality"
},
  "geometry": {"coordinates":[86.71096,27.73339],"type":"Point"}
}