{
  "type": "Feature",
  "properties": {
    "gn:admin1_code":"MR",
    "gn:admin2_code":"2",
    "gn:admin3_code":"60.0",
    "gn:admin4_code":"600042.0",
    "gn:asciiname":"Nuwakharka",
    "gn:country_code":"NP",
    "gn:dem":1918,
    "gn:feature_class":"P",
    "gn:feature_code":"PPLL",
    "gn:name":"Nuwakharka",
    "gn:population":0,
    "gn:timezone":"Asia/Kathmandu",
    "iso:country":"NP",
    "wof:name":"Nuwakharka",
    "wof:placetype":"locality"
},
  "geometry": {"coordinates":[81.70134,28.67102],"type":"Point"}
}