{
  "type": "Feature",
  "properties": {
    "gn:admin1_code":"MR",
    "gn:admin2_code":"6",
    "gn:admin3_code":"66.0",
    "gn:admin4_code":"660011.0",
    "gn:asciiname":"Kharpel",
    "gn:country_code":"NP",
    "gn:dem":2733,
    "gn:feature_class":"P",
    "gn:feature_code":"PPLL",
    "gn:name":"Kharpel",
    "gn:population":0,
    "gn:timezone":"Asia/Kathmandu",
    "iso:country":"NP",
    "wof:name":"Kharpel",
    "wof:placetype":"locality"
},
  "geometry": {"coordinates":[81.88150999999998,29.93279],"type":"Point"}
}