{
  "type": "Feature",
  "properties": {
    "gn:admin1_code":"CR",
    "gn:admin2_code":"11",
    "gn:admin3_code":"32",
    "gn:admin4_code":"320009",
    "gn:asciiname":"Chilmiliya",
    "gn:country_code":"NP",
    "gn:dem":90,
    "gn:feature_class":"P",
    "gn:feature_code":"PPLL",
    "gn:name":"Chilmiliya",
    "gn:population":0,
    "gn:timezone":"Asia/Kathmandu",
    "iso:country":"NP",
    "wof:name":"Chilmiliya",
    "wof:placetype":"locality"
},
  "geometry": {"coordinates":[85.35123,26.95201],"type":"Point"}
}