{
  "type": "Feature",
  "properties": {
    "gn:admin1_code":"WR",
    "gn:admin2_code":"8",
    "gn:admin3_code":"49",
    "gn:admin4_code":"490023",
    "gn:asciiname":"Karamhawa",
    "gn:country_code":"NP",
    "gn:dem":103,
    "gn:feature_class":"P",
    "gn:feature_code":"PPLL",
    "gn:name":"Karamhawa",
    "gn:population":0,
    "gn:timezone":"Asia/Kathmandu",
    "iso:country":"NP",
    "wof:name":"Karamhawa",
    "wof:placetype":"locality"
},
  "geometry": {"coordinates":[83.27636,27.52708],"type":"Point"}
}