{
  "type": "Feature",
  "properties": {
    "gn:admin1_code":"MR",
    "gn:admin2_code":"12",
    "gn:admin3_code":"56.0",
    "gn:admin4_code":"560031.0",
    "gn:asciiname":"Gidhaniya",
    "gn:country_code":"NP",
    "gn:dem":231,
    "gn:feature_class":"P",
    "gn:feature_code":"PPLL",
    "gn:name":"Gidhaniya",
    "gn:population":0,
    "gn:timezone":"Asia/Kathmandu",
    "iso:country":"NP",
    "wof:name":"Gidhaniya",
    "wof:placetype":"locality"
},
  "geometry": {"coordinates":[82.43179000000001,27.87425],"type":"Point"}
}