{
  "type": "Feature",
  "properties": {
    "gn:admin1_code":"ER",
    "gn:admin2_code":"13",
    "gn:admin3_code":"13.0",
    "gn:admin4_code":"130039.0",
    "gn:asciiname":"Kharpa",
    "gn:country_code":"NP",
    "gn:dem":776,
    "gn:feature_class":"P",
    "gn:feature_code":"PPLL",
    "gn:name":"Kharpa",
    "gn:population":0,
    "gn:timezone":"Asia/Kathmandu",
    "iso:country":"NP",
    "wof:name":"Kharpa",
    "wof:placetype":"locality"
},
  "geometry": {"coordinates":[86.6947,27.26616],"type":"Point"}
}