{
  "type": "Feature",
  "properties": {
    "gn:admin1_code":"WR",
    "gn:admin2_code":"8",
    "gn:admin3_code":"51.0",
    "gn:admin4_code":"510015.0",
    "gn:asciiname":"Charepani",
    "gn:country_code":"NP",
    "gn:dem":1560,
    "gn:feature_class":"P",
    "gn:feature_code":"PPLL",
    "gn:name":"Charepani",
    "gn:population":0,
    "gn:timezone":"Asia/Kathmandu",
    "iso:country":"NP",
    "wof:name":"Charepani",
    "wof:placetype":"locality"
},
  "geometry": {"coordinates":[83.11249000000002,27.92255],"type":"Point"}
}