{
  "type": "Feature",
  "properties": {
    "gn:admin1_code":"FR",
    "gn:admin2_code":"9",
    "gn:admin3_code":"75.0",
    "gn:admin4_code":"750012.0",
    "gn:asciiname":"Hopari",
    "gn:country_code":"NP",
    "gn:dem":1187,
    "gn:feature_class":"P",
    "gn:feature_code":"PPLL",
    "gn:name":"Hopari",
    "gn:population":0,
    "gn:timezone":"Asia/Kathmandu",
    "iso:country":"NP",
    "wof:name":"Hopari",
    "wof:placetype":"locality"
},
  "geometry": {"coordinates":[80.67021,29.74529],"type":"Point"}
}