{
  "type": "Feature",
  "properties": {
    "gn:admin1_code":"MR",
    "gn:admin2_code":"2",
    "gn:admin3_code":"60.0",
    "gn:admin4_code":"600007.0",
    "gn:asciiname":"Ratikholagaun",
    "gn:country_code":"NP",
    "gn:dem":1229,
    "gn:feature_class":"P",
    "gn:feature_code":"PPLL",
    "gn:name":"Ratikholagaun",
    "gn:population":0,
    "gn:timezone":"Asia/Kathmandu",
    "iso:country":"NP",
    "wof:name":"Ratikholagaun",
    "wof:placetype":"locality"
},
  "geometry": {"coordinates":[81.63785,28.7417],"type":"Point"}
}