{
  "type": "Feature",
  "properties": {
    "gn:admin1_code":"MR",
    "gn:admin2_code":"2.0",
    "gn:admin3_code":"59.0",
    "gn:admin4_code":"590003.0",
    "gn:asciiname":"Chanali",
    "gn:country_code":"NP",
    "gn:dem":1146,
    "gn:feature_class":"P",
    "gn:feature_code":"PPLL",
    "gn:name":"Chanali",
    "gn:population":0,
    "gn:timezone":"Asia/Kathmandu",
    "iso:country":"NP",
    "wof:name":"Chanali",
    "wof:placetype":"locality"
},
  "geometry": {"coordinates":[81.43575,28.82969000000001],"type":"Point"}
}