{
  "type": "Feature",
  "properties": {
    "gn:admin1_code":"WR",
    "gn:admin2_code":"4",
    "gn:admin3_code":"40.0",
    "gn:admin4_code":"400009.0",
    "gn:asciiname":"Suhure",
    "gn:country_code":"NP",
    "gn:dem":1772,
    "gn:feature_class":"P",
    "gn:feature_code":"PPLL",
    "gn:name":"Suhure",
    "gn:population":0,
    "gn:timezone":"Asia/Kathmandu",
    "iso:country":"NP",
    "wof:name":"Suhure",
    "wof:placetype":"locality"
},
  "geometry": {"coordinates":[83.84735000000001,28.2981],"type":"Point"}
}