{
  "type": "Feature",
  "properties": {
    "gn:admin1_code":"MR",
    "gn:admin2_code":"12",
    "gn:admin3_code":"54",
    "gn:admin4_code":"540034",
    "gn:asciiname":"Gothbang",
    "gn:country_code":"NP",
    "gn:dem":2022,
    "gn:feature_class":"P",
    "gn:feature_code":"PPLL",
    "gn:name":"Gothbang",
    "gn:population":0,
    "gn:timezone":"Asia/Kathmandu",
    "iso:country":"NP",
    "wof:name":"Gothbang",
    "wof:placetype":"locality"
},
  "geometry": {"coordinates":[82.69596999999997,28.65255],"type":"Point"}
}