{
  "type": "Feature",
  "properties": {
    "gn:admin1_code":"CR",
    "gn:admin2_code":"11",
    "gn:admin3_code":"34",
    "gn:admin4_code":"340067",
    "gn:asciiname":"Thapatandi",
    "gn:country_code":"NP",
    "gn:dem":106,
    "gn:feature_class":"P",
    "gn:feature_code":"PPLL",
    "gn:name":"Thapatandi",
    "gn:population":0,
    "gn:timezone":"Asia/Kathmandu",
    "iso:country":"NP",
    "wof:name":"Thapatandi",
    "wof:placetype":"locality"
},
  "geometry": {"coordinates":[84.82807,27.17618],"type":"Point"}
}