{
  "type": "Feature",
  "properties": {
    "gn:admin1_code":"MR",
    "gn:admin2_code":"12",
    "gn:admin3_code":"54",
    "gn:admin4_code":"540040",
    "gn:asciiname":"Chachchugaira",
    "gn:country_code":"NP",
    "gn:dem":2098,
    "gn:feature_class":"P",
    "gn:feature_code":"PPLL",
    "gn:name":"Chachchugaira",
    "gn:population":0,
    "gn:timezone":"Asia/Kathmandu",
    "iso:country":"NP",
    "wof:name":"Chachchugaira",
    "wof:placetype":"locality"
},
  "geometry": {"coordinates":[82.61272,28.57632000000001],"type":"Point"}
}