{
  "type": "Feature",
  "properties": {
    "gn:admin1_code":"CR",
    "gn:admin2_code":"1",
    "gn:admin3_code":"23",
    "gn:admin4_code":"230006.0",
    "gn:asciiname":"Dharapa",
    "gn:country_code":"NP",
    "gn:dem":1488,
    "gn:feature_class":"P",
    "gn:feature_code":"PPLL",
    "gn:name":"Dharapa",
    "gn:population":0,
    "gn:timezone":"Asia/Kathmandu",
    "iso:country":"NP",
    "wof:name":"Dharapa",
    "wof:placetype":"locality"
},
  "geometry": {"coordinates":[85.92100000000001,27.81104],"type":"Point"}
}