{
  "type": "Feature",
  "properties": {
    "gn:admin1_code":"WR",
    "gn:admin2_code":"3",
    "gn:admin3_code":"43",
    "gn:admin4_code":"430002",
    "gn:asciiname":"Majhkhet",
    "gn:country_code":"NP",
    "gn:dem":987,
    "gn:feature_class":"P",
    "gn:feature_code":"PPLL",
    "gn:name":"Majhkhet",
    "gn:population":0,
    "gn:timezone":"Asia/Kathmandu",
    "iso:country":"NP",
    "wof:name":"Majhkhet",
    "wof:placetype":"locality"
},
  "geometry": {"coordinates":[83.54263,28.34132],"type":"Point"}
}