{
  "type": "Feature",
  "properties": {
    "gn:admin1_code":"ER",
    "gn:admin2_code":"7",
    "gn:admin3_code":"9",
    "gn:admin4_code":"90034",
    "gn:asciiname":"Wangtang",
    "gn:country_code":"NP",
    "gn:dem":804,
    "gn:feature_class":"P",
    "gn:feature_code":"PPLL",
    "gn:name":"Wangtang",
    "gn:population":0,
    "gn:timezone":"Asia/Kathmandu",
    "iso:country":"NP",
    "wof:name":"Wangtang",
    "wof:placetype":"locality"
},
  "geometry": {"coordinates":[87.16634999999999,27.49219],"type":"Point"}
}