{
  "type": "Feature",
  "properties": {
    "gn:admin1_code":"00",
    "gn:asciiname":"Chheradada",
    "gn:country_code":"NP",
    "gn:dem":1399,
    "gn:feature_class":"P",
    "gn:feature_code":"PPL",
    "gn:name":"Chher\u0101\u1e0d\u0101\u0303\u1e0d\u0101",
    "gn:population":0,
    "gn:timezone":"Asia/Kathmandu",
    "iso:country":"NP",
    "wof:name":"Chheradada",
    "wof:placetype":"locality"
},
  "geometry": {"coordinates":[86.78945,27.33285],"type":"Point"}
}