{
  "type": "Feature",
  "properties": {
    "gn:admin1_code":"WR",
    "gn:admin2_code":"4.0",
    "gn:admin3_code":"38.0",
    "gn:admin4_code":"380015.0",
    "gn:asciiname":"Simlchaur",
    "gn:country_code":"NP",
    "gn:dem":602,
    "gn:feature_class":"P",
    "gn:feature_code":"PPLL",
    "gn:name":"Simlchaur",
    "gn:population":0,
    "gn:timezone":"Asia/Kathmandu",
    "iso:country":"NP",
    "wof:name":"Simlchaur",
    "wof:placetype":"locality"
},
  "geometry": {"coordinates":[84.43082,28.10836],"type":"Point"}
}