{
  "type": "Feature",
  "properties": {
    "gn:admin1_code":"WR",
    "gn:admin2_code":"8",
    "gn:admin3_code":"47",
    "gn:admin4_code":"470005",
    "gn:asciiname":"Jukia",
    "gn:country_code":"NP",
    "gn:dem":905,
    "gn:feature_class":"P",
    "gn:feature_code":"PPLL",
    "gn:name":"Jukia",
    "gn:population":0,
    "gn:timezone":"Asia/Kathmandu",
    "iso:country":"NP",
    "wof:name":"Jukia",
    "wof:placetype":"locality"
},
  "geometry": {"coordinates":[83.51866,27.84509000000001],"type":"Point"}
}