{
  "type": "Feature",
  "properties": {
    "gn:admin1_code":"ER",
    "gn:admin2_code":"13",
    "gn:admin3_code":"13",
    "gn:admin4_code":"130076",
    "gn:asciiname":"Yamkha",
    "gn:country_code":"NP",
    "gn:dem":1308,
    "gn:feature_class":"P",
    "gn:feature_code":"PPLL",
    "gn:name":"Yamkha",
    "gn:population":0,
    "gn:timezone":"Asia/Kathmandu",
    "iso:country":"NP",
    "wof:name":"Yamkha",
    "wof:placetype":"locality"
},
  "geometry": {"coordinates":[86.77998000000002,27.13788],"type":"Point"}
}