{
  "type": "Feature",
  "properties": {
    "gn:admin1_code":"WR",
    "gn:admin2_code":"8",
    "gn:admin3_code":"46.0",
    "gn:admin4_code":"460042.0",
    "gn:asciiname":"Ding",
    "gn:country_code":"NP",
    "gn:dem":672,
    "gn:feature_class":"P",
    "gn:feature_code":"PPLL",
    "gn:name":"Ding",
    "gn:population":0,
    "gn:timezone":"Asia/Kathmandu",
    "iso:country":"NP",
    "wof:name":"Ding",
    "wof:placetype":"locality"
},
  "geometry": {"coordinates":[83.56116,27.97908],"type":"Point"}
}