{
  "type": "Feature",
  "properties": {
    "gn:admin1_code":"MR",
    "gn:admin2_code":"12",
    "gn:admin3_code":"53",
    "gn:admin4_code":"530036",
    "gn:asciiname":"Phulbas",
    "gn:country_code":"NP",
    "gn:dem":1905,
    "gn:feature_class":"P",
    "gn:feature_code":"PPLL",
    "gn:name":"Phulbas",
    "gn:population":0,
    "gn:timezone":"Asia/Kathmandu",
    "iso:country":"NP",
    "wof:name":"Phulbas",
    "wof:placetype":"locality"
},
  "geometry": {"coordinates":[82.42661,28.46052],"type":"Point"}
}