{
  "type": "Feature",
  "properties": {
    "gn:admin1_code":"00",
    "gn:asciiname":"Silgarhi-Doti",
    "gn:country_code":"NP",
    "gn:dem":1002,
    "gn:feature_class":"P",
    "gn:feature_code":"PPL",
    "gn:name":"Silgarhi-Dot\u012b",
    "gn:population":0,
    "gn:timezone":"Asia/Kathmandu",
    "iso:country":"NP",
    "name:und_x_variant":[
        "Doti",
        "Siliguri",
        "Silgarhi Dot",
        "Silgadhi",
        "Silgadhi-Doti",
        "Silgarhi-Dot\u012b"
    ],
    "wof:name":"Silgarhi-Doti",
    "wof:placetype":"locality"
},
  "geometry": {"coordinates":[80.97119000000001,29.267],"type":"Point"}
}