{
  "type": "Feature",
  "properties": {
    "gn:admin1_code":"CR",
    "gn:admin2_code":"1",
    "gn:admin3_code":"30.0",
    "gn:admin4_code":"300048.0",
    "gn:asciiname":"Thakre",
    "gn:country_code":"NP",
    "gn:dem":955,
    "gn:feature_class":"P",
    "gn:feature_code":"PPLL",
    "gn:name":"Thakre",
    "gn:population":0,
    "gn:timezone":"Asia/Kathmandu",
    "iso:country":"NP",
    "wof:name":"Thakre",
    "wof:placetype":"locality"
},
  "geometry": {"coordinates":[85.1023,27.73594000000001],"type":"Point"}
}