{
  "type": "Feature",
  "properties": {
    "gn:admin1_code":"MR",
    "gn:admin2_code":"12",
    "gn:admin3_code":"55",
    "gn:admin4_code":"550020",
    "gn:asciiname":"Dhurchaur",
    "gn:country_code":"NP",
    "gn:dem":1033,
    "gn:feature_class":"P",
    "gn:feature_code":"PPLL",
    "gn:name":"Dhurchaur",
    "gn:population":0,
    "gn:timezone":"Asia/Kathmandu",
    "iso:country":"NP",
    "wof:name":"Dhurchaur",
    "wof:placetype":"locality"
},
  "geometry": {"coordinates":[81.99814000000001,28.32914],"type":"Point"}
}