{
  "type": "Feature",
  "properties": {
    "gn:admin1_code":"WR",
    "gn:admin2_code":"4.0",
    "gn:admin3_code":"38.0",
    "gn:admin4_code":"380022.0",
    "gn:asciiname":"Ghurlichhap",
    "gn:country_code":"NP",
    "gn:dem":831,
    "gn:feature_class":"P",
    "gn:feature_code":"PPLL",
    "gn:name":"Ghurlichhap",
    "gn:population":0,
    "gn:timezone":"Asia/Kathmandu",
    "iso:country":"NP",
    "wof:name":"Ghurlichhap",
    "wof:placetype":"locality"
},
  "geometry": {"coordinates":[83.98631,27.89475],"type":"Point"}
}