{
  "type": "Feature",
  "properties": {
    "gn:admin1_code":"ER",
    "gn:admin2_code":"13",
    "gn:admin3_code":"16",
    "gn:admin4_code":"160048",
    "gn:asciiname":"Sundarpur",
    "gn:country_code":"NP",
    "gn:dem":79,
    "gn:feature_class":"P",
    "gn:feature_code":"PPLL",
    "gn:name":"Sundarpur",
    "gn:population":0,
    "gn:timezone":"Asia/Kathmandu",
    "iso:country":"NP",
    "wof:name":"Sundarpur",
    "wof:placetype":"locality"
},
  "geometry": {"coordinates":[86.26983,26.63073],"type":"Point"}
}