{
  "type": "Feature",
  "properties": {
    "gn:admin1_code":"MR",
    "gn:admin2_code":"12",
    "gn:admin3_code":"53",
    "gn:admin4_code":"530023",
    "gn:asciiname":"Dandagau",
    "gn:country_code":"NP",
    "gn:dem":1888,
    "gn:feature_class":"P",
    "gn:feature_code":"PPLL",
    "gn:name":"Dandagau",
    "gn:population":0,
    "gn:timezone":"Asia/Kathmandu",
    "iso:country":"NP",
    "wof:name":"Dandagau",
    "wof:placetype":"locality"
},
  "geometry": {"coordinates":[82.41436999999998,28.43731],"type":"Point"}
}