{
  "type": "Feature",
  "properties": {
    "gn:admin1_code":"WR",
    "gn:admin2_code":"4",
    "gn:admin3_code":"40.0",
    "gn:admin4_code":"400045.0",
    "gn:asciiname":"Ryalechaur",
    "gn:country_code":"NP",
    "gn:dem":1077,
    "gn:feature_class":"P",
    "gn:feature_code":"PPLL",
    "gn:name":"Ryalechaur",
    "gn:population":0,
    "gn:timezone":"Asia/Kathmandu",
    "iso:country":"NP",
    "wof:name":"Ryalechaur",
    "wof:placetype":"locality"
},
  "geometry": {"coordinates":[84.01290999999998,28.25234],"type":"Point"}
}