{
  "type": "Feature",
  "properties": {
    "gn:admin1_code":"ER",
    "gn:admin2_code":"7",
    "gn:admin3_code":"10.0",
    "gn:admin4_code":"100048.0",
    "gn:asciiname":"Nawalpur",
    "gn:country_code":"NP",
    "gn:dem":1167,
    "gn:feature_class":"P",
    "gn:feature_code":"PPLL",
    "gn:name":"Nawalpur",
    "gn:population":0,
    "gn:timezone":"Asia/Kathmandu",
    "iso:country":"NP",
    "name:ceb_x_preferred":[
        "Nawalpur"
    ],
    "name:msa_x_preferred":[
        "Nawalpur"
    ],
    "name:nep_x_preferred":[
        "\u0928\u0935\u0932\u092a\u0941\u0930"
    ],
    "name:new_x_preferred":[
        "\u0928\u0935\u0932\u092a\u0941\u0930"
    ],
    "name:pol_x_preferred":[
        "Nawalpur"
    ],
    "wof:name":"Nawalpur",
    "wof:placetype":"locality"
},
  "geometry": {"coordinates":[87.1627,27.21225],"type":"Point"}
}