{
  "type": "Feature",
  "properties": {
    "gn:admin1_code":"00",
    "gn:asciiname":"Hasdol",
    "gn:country_code":"NP",
    "gn:dem":1398,
    "gn:feature_class":"P",
    "gn:feature_code":"PPL",
    "gn:name":"H\u0101s\u1e0dol",
    "gn:population":0,
    "gn:timezone":"Asia/Kathmandu",
    "iso:country":"NP",
    "wof:name":"Hasdol",
    "wof:placetype":"locality"
},
  "geometry": {"coordinates":[85.27269,27.58495],"type":"Point"}
}