{
  "type": "Feature",
  "properties": {
    "gn:admin1_code":"MR",
    "gn:admin2_code":"2",
    "gn:admin3_code":"60.0",
    "gn:admin4_code":"600039.0",
    "gn:asciiname":"Dhada",
    "gn:country_code":"NP",
    "gn:dem":1258,
    "gn:feature_class":"P",
    "gn:feature_code":"PPLL",
    "gn:name":"Dhada",
    "gn:population":0,
    "gn:timezone":"Asia/Kathmandu",
    "iso:country":"NP",
    "name:hif_x_preferred":[
        "Dhada"
    ],
    "name:tel_x_preferred":[
        "\u0c26\u0c21"
    ],
    "wof:name":"Dhada",
    "wof:placetype":"locality"
},
  "geometry": {"coordinates":[81.81504,28.93251],"type":"Point"}
}