{
  "type": "Feature",
  "properties": {
    "gn:admin1_code":"00",
    "gn:asciiname":"Dewari",
    "gn:country_code":"NP",
    "gn:dem":101,
    "gn:feature_class":"P",
    "gn:feature_code":"PPL",
    "gn:name":"Dew\u0101ri\u0307\u0304",
    "gn:population":0,
    "gn:timezone":"Asia/Kathmandu",
    "iso:country":"NP",
    "name:nep_x_preferred":[
        "Dew\u0101ri\u0307\u0304"
    ],
    "wof:name":"Dewari",
    "wof:placetype":"locality"
},
  "geometry": {"coordinates":[86.42185000000001,26.65761],"type":"Point"}
}