{
  "type": "Feature",
  "properties": {
    "gn:admin1_code":"FR",
    "gn:admin2_code":"9",
    "gn:admin3_code":"74",
    "gn:admin4_code":"740054.0",
    "gn:asciiname":"Chindole",
    "gn:country_code":"NP",
    "gn:dem":1933,
    "gn:feature_class":"P",
    "gn:feature_code":"PPLL",
    "gn:name":"Chindole",
    "gn:population":0,
    "gn:timezone":"Asia/Kathmandu",
    "iso:country":"NP",
    "wof:name":"Chindole",
    "wof:placetype":"locality"
},
  "geometry": {"coordinates":[80.80297,29.45199],"type":"Point"}
}