{
  "type": "Feature",
  "properties": {
    "gn:admin1_code":"CR",
    "gn:admin2_code":"11",
    "gn:admin3_code":"32",
    "gn:admin4_code":"320016",
    "gn:asciiname":"Bhawanipur",
    "gn:country_code":"NP",
    "gn:dem":95,
    "gn:feature_class":"P",
    "gn:feature_code":"PPLL",
    "gn:name":"Bhawanipur",
    "gn:population":0,
    "gn:timezone":"Asia/Kathmandu",
    "iso:country":"NP",
    "wof:name":"Bhawanipur",
    "wof:placetype":"locality"
},
  "geometry": {"coordinates":[85.35420000000001,26.98897],"type":"Point"}
}