{
  "type": "Feature",
  "properties": {
    "gn:admin1_code":"MR",
    "gn:admin2_code":"6",
    "gn:admin3_code":"66.0",
    "gn:admin4_code":"660014.0",
    "gn:asciiname":"Naikala",
    "gn:country_code":"NP",
    "gn:dem":1880,
    "gn:feature_class":"P",
    "gn:feature_code":"PPLL",
    "gn:name":"Naikala",
    "gn:population":0,
    "gn:timezone":"Asia/Kathmandu",
    "iso:country":"NP",
    "wof:name":"Naikala",
    "wof:placetype":"locality"
},
  "geometry": {"coordinates":[81.75474,29.66213],"type":"Point"}
}