{
  "type": "Feature",
  "properties": {
    "gn:admin1_code":"WR",
    "gn:admin2_code":"3",
    "gn:admin3_code":"43",
    "gn:admin4_code":"430026",
    "gn:asciiname":"Gadkhane",
    "gn:country_code":"NP",
    "gn:dem":2421,
    "gn:feature_class":"P",
    "gn:feature_code":"PPLL",
    "gn:name":"Gadkhane",
    "gn:population":0,
    "gn:timezone":"Asia/Kathmandu",
    "iso:country":"NP",
    "wof:name":"Gadkhane",
    "wof:placetype":"locality"
},
  "geometry": {"coordinates":[83.65849,28.55491],"type":"Point"}
}