{
  "type": "Feature",
  "properties": {
    "gn:admin1_code":"MR",
    "gn:admin2_code":"12",
    "gn:admin3_code":"52",
    "gn:admin4_code":"520035",
    "gn:asciiname":"Koiralpata",
    "gn:country_code":"NP",
    "gn:dem":1044,
    "gn:feature_class":"P",
    "gn:feature_code":"PPLL",
    "gn:name":"Koiralpata",
    "gn:population":0,
    "gn:timezone":"Asia/Kathmandu",
    "iso:country":"NP",
    "wof:name":"Koiralpata",
    "wof:placetype":"locality"
},
  "geometry": {"coordinates":[82.99131,28.158],"type":"Point"}
}