{
  "type": "Feature",
  "properties": {
    "gn:admin1_code":"WR",
    "gn:admin2_code":"4",
    "gn:admin3_code":"37",
    "gn:admin4_code":"370048",
    "gn:asciiname":"Ford(March to June)",
    "gn:country_code":"NP",
    "gn:dem":817,
    "gn:feature_class":"P",
    "gn:feature_code":"PPLL",
    "gn:name":"Ford(March to June)",
    "gn:population":0,
    "gn:timezone":"Asia/Kathmandu",
    "iso:country":"NP",
    "wof:name":"Ford(March to June)",
    "wof:placetype":"locality"
},
  "geometry": {"coordinates":[84.54799,28.14227],"type":"Point"}
}