{
  "type": "Feature",
  "properties": {
    "gn:admin1_code":"CR",
    "gn:admin2_code":"1",
    "gn:admin3_code":"23",
    "gn:admin4_code":"230052",
    "gn:asciiname":"Maitar",
    "gn:country_code":"NP",
    "gn:dem":1004,
    "gn:feature_class":"P",
    "gn:feature_code":"PPLL",
    "gn:name":"Maitar",
    "gn:population":0,
    "gn:timezone":"Asia/Kathmandu",
    "iso:country":"NP",
    "wof:name":"Maitar",
    "wof:placetype":"locality"
},
  "geometry": {"coordinates":[85.54392,27.87822],"type":"Point"}
}