{
  "type": "Feature",
  "properties": {
    "gn:admin1_code":"WR",
    "gn:admin2_code":"3",
    "gn:admin3_code":"45",
    "gn:admin4_code":"450056",
    "gn:asciiname":"Patihalna",
    "gn:country_code":"NP",
    "gn:dem":3328,
    "gn:feature_class":"P",
    "gn:feature_code":"PPLL",
    "gn:name":"Patihalna",
    "gn:population":0,
    "gn:timezone":"Asia/Kathmandu",
    "iso:country":"NP",
    "wof:name":"Patihalna",
    "wof:placetype":"locality"
},
  "geometry": {"coordinates":[83.21160999999999,28.50481],"type":"Point"}
}