{
  "type": "Feature",
  "properties": {
    "gn:admin1_code":"CR",
    "gn:admin2_code":"1",
    "gn:admin3_code":"30.0",
    "gn:admin4_code":"300034.0",
    "gn:asciiname":"Barthumki",
    "gn:country_code":"NP",
    "gn:dem":870,
    "gn:feature_class":"P",
    "gn:feature_code":"PPLL",
    "gn:name":"Barthumki",
    "gn:population":0,
    "gn:timezone":"Asia/Kathmandu",
    "iso:country":"NP",
    "wof:name":"Barthumki",
    "wof:placetype":"locality"
},
  "geometry": {"coordinates":[85.15258,27.72994000000001],"type":"Point"}
}