{
  "type": "Feature",
  "properties": {
    "gn:admin1_code":"WR",
    "gn:admin2_code":"4",
    "gn:admin3_code":"37",
    "gn:admin4_code":"370048",
    "gn:asciiname":"Olkeswanra",
    "gn:country_code":"NP",
    "gn:dem":1004,
    "gn:feature_class":"P",
    "gn:feature_code":"PPLL",
    "gn:name":"Olkeswanra",
    "gn:population":0,
    "gn:timezone":"Asia/Kathmandu",
    "iso:country":"NP",
    "wof:name":"Olkeswanra",
    "wof:placetype":"locality"
},
  "geometry": {"coordinates":[84.50175,28.14691],"type":"Point"}
}