{
  "type": "Feature",
  "properties": {
    "gn:admin1_code":"WR",
    "gn:admin2_code":"3",
    "gn:admin3_code":"44",
    "gn:admin4_code":"440049",
    "gn:asciiname":"Dhungekharka",
    "gn:country_code":"NP",
    "gn:dem":869,
    "gn:feature_class":"P",
    "gn:feature_code":"PPLL",
    "gn:name":"Dhungekharka",
    "gn:population":0,
    "gn:timezone":"Asia/Kathmandu",
    "iso:country":"NP",
    "wof:name":"Dhungekharka",
    "wof:placetype":"locality"
},
  "geometry": {"coordinates":[83.62812,28.02538],"type":"Point"}
}