{
  "type": "Feature",
  "properties": {
    "gn:admin1_code":"WR",
    "gn:admin2_code":"4",
    "gn:admin3_code":"37",
    "gn:admin4_code":"370042",
    "gn:asciiname":"Kupling",
    "gn:country_code":"NP",
    "gn:dem":1261,
    "gn:feature_class":"P",
    "gn:feature_code":"PPLL",
    "gn:name":"Kupling",
    "gn:population":0,
    "gn:timezone":"Asia/Kathmandu",
    "iso:country":"NP",
    "wof:name":"Kupling",
    "wof:placetype":"locality"
},
  "geometry": {"coordinates":[84.46561,28.20983],"type":"Point"}
}