{
  "type": "Feature",
  "properties": {
    "gn:admin1_code":"ER",
    "gn:admin2_code":"10.0",
    "gn:admin3_code":"1.0",
    "gn:admin4_code":"10003.0",
    "gn:asciiname":"Make",
    "gn:country_code":"NP",
    "gn:dem":971,
    "gn:feature_class":"P",
    "gn:feature_code":"PPLL",
    "gn:name":"Make",
    "gn:population":0,
    "gn:timezone":"Asia/Kathmandu",
    "iso:country":"NP",
    "name:ceb_x_preferred":[
        "Make"
    ],
    "name:dan_x_preferred":[
        "Make"
    ],
    "name:ita_x_preferred":[
        "Make"
    ],
    "name:jpn_x_preferred":[
        "\u30e1\u30a4\u30af"
    ],
    "name:kor_x_preferred":[
        "\uba54\uc774\ud06c"
    ],
    "name:nld_x_preferred":[
        "Make"
    ],
    "name:swe_x_preferred":[
        "Make"
    ],
    "wof:name":"Make",
    "wof:placetype":"locality"
},
  "geometry": {"coordinates":[87.77898,27.27866],"type":"Point"}
}