{
  "type": "Feature",
  "properties": {
    "gn:admin1_code":"FR",
    "gn:admin2_code":"14.0",
    "gn:admin3_code":"69.0",
    "gn:admin4_code":"690042.0",
    "gn:asciiname":"Mandhungani",
    "gn:country_code":"NP",
    "gn:dem":1566,
    "gn:feature_class":"P",
    "gn:feature_code":"PPLL",
    "gn:name":"Mandhungani",
    "gn:population":0,
    "gn:timezone":"Asia/Kathmandu",
    "iso:country":"NP",
    "wof:name":"Mandhungani",
    "wof:placetype":"locality"
},
  "geometry": {"coordinates":[81.21044000000001,29.09541],"type":"Point"}
}