{
  "type": "Feature",
  "properties": {
    "gn:admin1_code":"CR",
    "gn:admin2_code":"5",
    "gn:admin3_code":"20",
    "gn:admin4_code":"200022",
    "gn:asciiname":"Thakledanda",
    "gn:country_code":"NP",
    "gn:dem":760,
    "gn:feature_class":"P",
    "gn:feature_code":"PPLL",
    "gn:name":"Thakledanda",
    "gn:population":0,
    "gn:timezone":"Asia/Kathmandu",
    "iso:country":"NP",
    "wof:name":"Thakledanda",
    "wof:placetype":"locality"
},
  "geometry": {"coordinates":[86.22799000000001,27.08373],"type":"Point"}
}