{
  "type": "Feature",
  "properties": {
    "iso:country":"NP",
    "name:bul_x_preferred":[
        "\u0411\u0445\u0430\u043a\u0442\u0430\u043f\u0443\u0440"
    ],
    "name:cat_x_preferred":[
        "Bhaktapur"
    ],
    "name:deu_x_preferred":[
        "Bhaktapur"
    ],
    "name:epo_x_preferred":[
        "Bhaktapur"
    ],
    "name:eus_x_preferred":[
        "Bhaktapur"
    ],
    "name:fin_x_preferred":[
        "Bhaktapur"
    ],
    "name:fra_x_preferred":[
        "Bhaktapur"
    ],
    "name:hbs_x_preferred":[
        "Bhaktapur"
    ],
    "name:hin_x_preferred":[
        "\u092d\u0915\u094d\u0924\u092a\u0941\u0930"
    ],
    "name:hrv_x_preferred":[
        "Bhaktapur"
    ],
    "name:hun_x_preferred":[
        "Bhaktapur"
    ],
    "name:ita_x_preferred":[
        "Bhaktapur"
    ],
    "name:jpn_x_preferred":[
        "\u30d0\u30af\u30bf\u30d7\u30eb"
    ],
    "name:kor_x_preferred":[
        "\ubc15\ud0c0\ud478\ub974"
    ],
    "name:lit_x_preferred":[
        "Bhaktapuras"
    ],
    "name:ltz_x_preferred":[
        "Bhaktapur"
    ],
    "name:msa_x_preferred":[
        "Bhaktapur"
    ],
    "name:nep_x_preferred":[
        "\u092d\u0915\u094d\u0924\u092a\u0941\u0930 \u0928\u0917\u0930\u092a\u093e\u0932\u093f\u0915\u093e"
    ],
    "name:new_x_preferred":[
        "\u0916\u094d\u0935\u092a \u0928\u0917\u0930\u092a\u093e\u0932\u093f\u0915\u093e"
    ],
    "name:nld_x_preferred":[
        "Bhaktapur"
    ],
    "name:nor_x_preferred":[
        "Bhaktapur"
    ],
    "name:pol_x_preferred":[
        "Bhaktapur"
    ],
    "name:por_x_preferred":[
        "Bhaktapur"
    ],
    "name:rus_x_preferred":[
        "\u0411\u0445\u0430\u043a\u0442\u0430\u043f\u0443\u0440"
    ],
    "name:spa_x_preferred":[
        "Bhaktapur"
    ],
    "name:swe_x_preferred":[
        "Bhaktapur"
    ],
    "name:tha_x_preferred":[
        "\u0e20\u0e31\u0e01\u0e15\u0e1b\u0e38\u0e23\u0e30"
    ],
    "name:tur_x_preferred":[
        "Bhaktapur"
    ],
    "name:ukr_x_preferred":[
        "\u0411\u0430\u043a\u0442\u0430\u043f\u0443\u0440"
    ],
    "name:unk_x_variant":[
        "Bakthpur"
    ],
    "name:urd_x_preferred":[
        "\u0628\u06be\u06af\u062a\u0627\u067e\u0648\u0631"
    ],
    "name:zho_x_preferred":[
        "\u5df4\u514b\u5854\u666e\u723e"
    ],
    "qs:gn_country":"NP",
    "qs:gn_fcode":"ADM3",
    "qs:gn_pop":76886,
    "qs:name":"Bhaktapur",
    "qs:name_adm0":"Nepal",
    "qs:name_adm1":"Madhyamanchal",
    "qs:photos":783,
    "qs:photos_1k":159,
    "qs:photos_9k":13,
    "qs:photos_9r":11,
    "qs:photos_all":2942,
    "qs:photos_sr":9,
    "qs:placetype":"LocalAdmin",
    "qs:pop_sr":"8",
    "qs:woe_adm0":23424911,
    "wd:wordcount":2236,
    "wof:name":"Bhaktapur",
    "wof:placetype":"localadmin",
    "wof:population":76886
},
  "geometry": {"coordinates":[85.41673,27.66734],"type":"Point"}
}