{
  "type": "Feature",
  "properties": {
    "gn:admin1_code":"ER",
    "gn:admin2_code":"7.0",
    "gn:admin3_code":"6.0",
    "gn:admin4_code":"60015.0",
    "gn:asciiname":"Phaudarsthan",
    "gn:country_code":"NP",
    "gn:dem":80,
    "gn:feature_class":"P",
    "gn:feature_code":"PPLL",
    "gn:name":"Phaudarsthan",
    "gn:population":0,
    "gn:timezone":"Asia/Kathmandu",
    "iso:country":"NP",
    "wof:name":"Phaudarsthan",
    "wof:placetype":"locality"
},
  "geometry": {"coordinates":[87.19915,26.50746],"type":"Point"}
}