{
  "type": "Feature",
  "properties": {
    "gn:admin1_code":"ER",
    "gn:admin2_code":"10.0",
    "gn:admin3_code":"1.0",
    "gn:admin4_code":"10015.0",
    "gn:asciiname":"Thamtar",
    "gn:country_code":"NP",
    "gn:dem":1720,
    "gn:feature_class":"P",
    "gn:feature_code":"PPLL",
    "gn:name":"Thamtar",
    "gn:population":0,
    "gn:timezone":"Asia/Kathmandu",
    "iso:country":"NP",
    "wof:name":"Thamtar",
    "wof:placetype":"locality"
},
  "geometry": {"coordinates":[87.65623000000002,27.40685],"type":"Point"}
}