{
  "type": "Feature",
  "properties": {
    "gn:admin1_code":"WR",
    "gn:admin2_code":"8",
    "gn:admin3_code":"51.0",
    "gn:admin4_code":"510025.0",
    "gn:asciiname":"Laha Pokhara",
    "gn:country_code":"NP",
    "gn:dem":1614,
    "gn:feature_class":"P",
    "gn:feature_code":"PPLL",
    "gn:name":"Laha Pokhara",
    "gn:population":0,
    "gn:timezone":"Asia/Kathmandu",
    "iso:country":"NP",
    "wof:name":"Laha Pokhara",
    "wof:placetype":"locality"
},
  "geometry": {"coordinates":[83.11855,28.07597],"type":"Point"}
}