{
  "type": "Feature",
  "properties": {
    "gn:admin1_code":"MR",
    "gn:admin2_code":"12",
    "gn:admin3_code":"53",
    "gn:admin4_code":"530004",
    "gn:asciiname":"Chhepa",
    "gn:country_code":"NP",
    "gn:dem":1341,
    "gn:feature_class":"P",
    "gn:feature_code":"PPLL",
    "gn:name":"Chhepa",
    "gn:population":0,
    "gn:timezone":"Asia/Kathmandu",
    "iso:country":"NP",
    "wof:name":"Chhepa",
    "wof:placetype":"locality"
},
  "geometry": {"coordinates":[82.44015,28.29867],"type":"Point"}
}