{
  "type": "Feature",
  "properties": {
    "gn:admin1_code":"WR",
    "gn:admin2_code":"4.0",
    "gn:admin3_code":"39.0",
    "gn:admin4_code":"390048.0",
    "gn:asciiname":"Sarlahi",
    "gn:country_code":"NP",
    "gn:dem":395,
    "gn:feature_class":"P",
    "gn:feature_code":"PPLL",
    "gn:name":"Sarlahi",
    "gn:population":0,
    "gn:timezone":"Asia/Kathmandu",
    "iso:country":"NP",
    "wof:name":"Sarlahi",
    "wof:placetype":"locality"
},
  "geometry": {"coordinates":[83.92816999999999,27.88244000000001],"type":"Point"}
}