{
  "type": "Feature",
  "properties": {
    "gn:admin1_code":"FR",
    "gn:admin2_code":"14",
    "gn:admin3_code":"71.0",
    "gn:admin4_code":"710029.0",
    "gn:asciiname":"Kota",
    "gn:country_code":"NP",
    "gn:dem":158,
    "gn:feature_class":"P",
    "gn:feature_code":"PPLL",
    "gn:name":"Kota",
    "gn:population":0,
    "gn:timezone":"Asia/Kathmandu",
    "iso:country":"NP",
    "wof:name":"Kota",
    "wof:placetype":"locality"
},
  "geometry": {"coordinates":[80.91284,28.6231],"type":"Point"}
}