{
  "type": "Feature",
  "properties": {
    "gn:admin1_code":"WR",
    "gn:admin2_code":"4",
    "gn:admin3_code":"40.0",
    "gn:admin4_code":"400003.0",
    "gn:asciiname":"Jhaure",
    "gn:country_code":"NP",
    "gn:dem":962,
    "gn:feature_class":"P",
    "gn:feature_code":"PPLL",
    "gn:name":"Jhaure",
    "gn:population":0,
    "gn:timezone":"Asia/Kathmandu",
    "iso:country":"NP",
    "wof:name":"Jhaure",
    "wof:placetype":"locality"
},
  "geometry": {"coordinates":[84.1674,28.25001],"type":"Point"}
}