{
  "type": "Feature",
  "properties": {
    "gn:admin1_code":"WR",
    "gn:admin2_code":"8",
    "gn:admin3_code":"47",
    "gn:admin4_code":"470050",
    "gn:asciiname":"Agaha Khola",
    "gn:country_code":"NP",
    "gn:dem":945,
    "gn:feature_class":"P",
    "gn:feature_code":"PPLL",
    "gn:name":"Agaha Khola",
    "gn:population":0,
    "gn:timezone":"Asia/Kathmandu",
    "iso:country":"NP",
    "wof:name":"Agaha Khola",
    "wof:placetype":"locality"
},
  "geometry": {"coordinates":[83.6811,27.84267],"type":"Point"}
}