{
  "type": "Feature",
  "properties": {
    "gn:admin1_code":"WR",
    "gn:admin2_code":"3",
    "gn:admin3_code":"44",
    "gn:admin4_code":"440053",
    "gn:asciiname":"Dimuwa",
    "gn:country_code":"NP",
    "gn:dem":1099,
    "gn:feature_class":"P",
    "gn:feature_code":"PPLL",
    "gn:name":"Dimuwa",
    "gn:population":0,
    "gn:timezone":"Asia/Kathmandu",
    "iso:country":"NP",
    "wof:name":"Dimuwa",
    "wof:placetype":"locality"
},
  "geometry": {"coordinates":[83.74648000000001,28.2748],"type":"Point"}
}