{
  "type": "Feature",
  "properties": {
    "gn:admin1_code":"MR",
    "gn:admin2_code":"6",
    "gn:admin3_code":"65",
    "gn:admin4_code":"650010",
    "gn:asciiname":"Niju Tupu",
    "gn:country_code":"NP",
    "gn:dem":4262,
    "gn:feature_class":"P",
    "gn:feature_code":"PPLL",
    "gn:name":"Niju Tupu",
    "gn:population":0,
    "gn:timezone":"Asia/Kathmandu",
    "iso:country":"NP",
    "wof:name":"Niju Tupu",
    "wof:placetype":"locality"
},
  "geometry": {"coordinates":[82.34685,29.6601],"type":"Point"}
}