{
  "type": "Feature",
  "properties": {
    "gn:admin1_code":"WR",
    "gn:admin2_code":"3",
    "gn:admin3_code":"45.0",
    "gn:admin4_code":"450049.0",
    "gn:asciiname":"Ghanghang",
    "gn:country_code":"NP",
    "gn:dem":1762,
    "gn:feature_class":"P",
    "gn:feature_code":"PPLL",
    "gn:name":"Ghanghang",
    "gn:population":0,
    "gn:timezone":"Asia/Kathmandu",
    "iso:country":"NP",
    "wof:name":"Ghanghang",
    "wof:placetype":"locality"
},
  "geometry": {"coordinates":[83.28231,28.2466],"type":"Point"}
}