{
  "type": "Feature",
  "properties": {
    "gn:admin1_code":"CR",
    "gn:admin2_code":"5",
    "gn:admin3_code":"21",
    "gn:admin4_code":"210003",
    "gn:asciiname":"Bhalbari",
    "gn:country_code":"NP",
    "gn:dem":1128,
    "gn:feature_class":"P",
    "gn:feature_code":"PPLL",
    "gn:name":"Bhalbari",
    "gn:population":0,
    "gn:timezone":"Asia/Kathmandu",
    "iso:country":"NP",
    "wof:name":"Bhalbari",
    "wof:placetype":"locality"
},
  "geometry": {"coordinates":[85.82975999999999,27.5045],"type":"Point"}
}