{
  "type": "Feature",
  "properties": {
    "gn:admin1_code":"MR",
    "gn:admin2_code":"12",
    "gn:admin3_code":"53",
    "gn:admin4_code":"530005",
    "gn:asciiname":"Dhanpokhara",
    "gn:country_code":"NP",
    "gn:dem":2461,
    "gn:feature_class":"P",
    "gn:feature_code":"PPLL",
    "gn:name":"Dhanpokhara",
    "gn:population":0,
    "gn:timezone":"Asia/Kathmandu",
    "iso:country":"NP",
    "wof:name":"Dhanpokhara",
    "wof:placetype":"locality"
},
  "geometry": {"coordinates":[82.66684000000002,28.40009],"type":"Point"}
}