{
  "type": "Feature",
  "properties": {
    "gn:admin1_code":"WR",
    "gn:admin2_code":"3",
    "gn:admin3_code":"45.0",
    "gn:admin4_code":"450017.0",
    "gn:asciiname":"Arupate",
    "gn:country_code":"NP",
    "gn:dem":1139,
    "gn:feature_class":"P",
    "gn:feature_code":"PPLL",
    "gn:name":"Arupate",
    "gn:population":0,
    "gn:timezone":"Asia/Kathmandu",
    "iso:country":"NP",
    "wof:name":"Arupate",
    "wof:placetype":"locality"
},
  "geometry": {"coordinates":[83.60658000000002,28.25171],"type":"Point"}
}