{
  "type": "Feature",
  "properties": {
    "gn:admin1_code":"ER",
    "gn:admin2_code":"13",
    "gn:admin3_code":"13.0",
    "gn:admin4_code":"130018.0",
    "gn:asciiname":"Khokma",
    "gn:country_code":"NP",
    "gn:dem":1712,
    "gn:feature_class":"P",
    "gn:feature_code":"PPLL",
    "gn:name":"Khokma",
    "gn:population":0,
    "gn:timezone":"Asia/Kathmandu",
    "iso:country":"NP",
    "wof:name":"Khokma",
    "wof:placetype":"locality"
},
  "geometry": {"coordinates":[86.89015999999999,27.19125],"type":"Point"}
}