{
  "type": "Feature",
  "properties": {
    "gn:admin1_code":"FR",
    "gn:admin2_code":"14",
    "gn:admin3_code":"68",
    "gn:admin4_code":"680007",
    "gn:asciiname":"Mori Bagar",
    "gn:country_code":"NP",
    "gn:dem":1018,
    "gn:feature_class":"P",
    "gn:feature_code":"PPLL",
    "gn:name":"Mori Bagar",
    "gn:population":0,
    "gn:timezone":"Asia/Kathmandu",
    "iso:country":"NP",
    "wof:name":"Mori Bagar",
    "wof:placetype":"locality"
},
  "geometry": {"coordinates":[81.05273000000003,29.48832],"type":"Point"}
}