{
  "type": "Feature",
  "properties": {
    "gn:admin1_code":"MR",
    "gn:admin2_code":"12",
    "gn:admin3_code":"52",
    "gn:admin4_code":"520017",
    "gn:asciiname":"Burdi",
    "gn:country_code":"NP",
    "gn:dem":738,
    "gn:feature_class":"P",
    "gn:feature_code":"PPLL",
    "gn:name":"Burdi",
    "gn:population":0,
    "gn:timezone":"Asia/Kathmandu",
    "iso:country":"NP",
    "name:snd_x_preferred":[
        "\u0628\u0699\u062f\u064a"
    ],
    "wof:name":"Burdi",
    "wof:placetype":"locality"
},
  "geometry": {"coordinates":[82.73668000000001,28.04077],"type":"Point"}
}