{
  "type": "Feature",
  "properties": {
    "gn:admin1_code":"MR",
    "gn:admin2_code":"12",
    "gn:admin3_code":"54",
    "gn:admin4_code":"540006",
    "gn:asciiname":"Tikachaur",
    "gn:country_code":"NP",
    "gn:dem":891,
    "gn:feature_class":"P",
    "gn:feature_code":"PPLL",
    "gn:name":"Tikachaur",
    "gn:population":0,
    "gn:timezone":"Asia/Kathmandu",
    "iso:country":"NP",
    "wof:name":"Tikachaur",
    "wof:placetype":"locality"
},
  "geometry": {"coordinates":[82.2234,28.60795],"type":"Point"}
}