{
  "type": "Feature",
  "properties": {
    "gn:admin1_code":"WR",
    "gn:admin2_code":"3",
    "gn:admin3_code":"45.0",
    "gn:admin4_code":"450005.0",
    "gn:asciiname":"Galthari Kharka",
    "gn:country_code":"NP",
    "gn:dem":2612,
    "gn:feature_class":"P",
    "gn:feature_code":"PPLL",
    "gn:name":"Galthari Kharka",
    "gn:population":0,
    "gn:timezone":"Asia/Kathmandu",
    "iso:country":"NP",
    "wof:name":"Galthari Kharka",
    "wof:placetype":"locality"
},
  "geometry": {"coordinates":[83.05446999999999,28.40984000000001],"type":"Point"}
}