{
  "type": "Feature",
  "properties": {
    "gn:admin1_code":"ER",
    "gn:admin2_code":"13",
    "gn:admin3_code":"11",
    "gn:admin4_code":"110002",
    "gn:asciiname":"Thuldhunga",
    "gn:country_code":"NP",
    "gn:dem":1601,
    "gn:feature_class":"P",
    "gn:feature_code":"PPLL",
    "gn:name":"Thuldhunga",
    "gn:population":0,
    "gn:timezone":"Asia/Kathmandu",
    "iso:country":"NP",
    "wof:name":"Thuldhunga",
    "wof:placetype":"locality"
},
  "geometry": {"coordinates":[86.68409,27.55845],"type":"Point"}
}