{
  "type": "Feature",
  "properties": {
    "gn:admin1_code":"FR",
    "gn:admin2_code":"9",
    "gn:admin3_code":"74",
    "gn:admin4_code":"740022",
    "gn:asciiname":"Ayanrpani",
    "gn:country_code":"NP",
    "gn:dem":1500,
    "gn:feature_class":"P",
    "gn:feature_code":"PPLL",
    "gn:name":"Ayanrpani",
    "gn:population":0,
    "gn:timezone":"Asia/Kathmandu",
    "iso:country":"NP",
    "wof:name":"Ayanrpani",
    "wof:placetype":"locality"
},
  "geometry": {"coordinates":[80.58422,29.4769],"type":"Point"}
}