{
  "type": "Feature",
  "properties": {
    "gn:admin1_code":"FR",
    "gn:admin2_code":"9",
    "gn:admin3_code":"73.0",
    "gn:admin4_code":"730020.0",
    "gn:asciiname":"Kharkhet",
    "gn:country_code":"NP",
    "gn:dem":1521,
    "gn:feature_class":"P",
    "gn:feature_code":"PPLL",
    "gn:name":"Kharkhet",
    "gn:population":0,
    "gn:timezone":"Asia/Kathmandu",
    "iso:country":"NP",
    "wof:name":"Kharkhet",
    "wof:placetype":"locality"
},
  "geometry": {"coordinates":[80.57283000000002,29.36715],"type":"Point"}
}