{
  "type": "Feature",
  "properties": {
    "gn:admin1_code":"WR",
    "gn:admin2_code":"3",
    "gn:admin3_code":"45.0",
    "gn:admin4_code":"450012.0",
    "gn:asciiname":"Lukurban",
    "gn:country_code":"NP",
    "gn:dem":1614,
    "gn:feature_class":"P",
    "gn:feature_code":"PPLL",
    "gn:name":"Lukurban",
    "gn:population":0,
    "gn:timezone":"Asia/Kathmandu",
    "iso:country":"NP",
    "wof:name":"Lukurban",
    "wof:placetype":"locality"
},
  "geometry": {"coordinates":[83.21406999999998,28.35199],"type":"Point"}
}