{
  "type": "Feature",
  "properties": {
    "gn:admin1_code":"CR",
    "gn:admin2_code":"11",
    "gn:admin3_code":"31",
    "gn:admin4_code":"310012",
    "gn:asciiname":"Dobate",
    "gn:country_code":"NP",
    "gn:dem":1804,
    "gn:feature_class":"P",
    "gn:feature_code":"PPLL",
    "gn:name":"Dobate",
    "gn:population":0,
    "gn:timezone":"Asia/Kathmandu",
    "iso:country":"NP",
    "wof:name":"Dobate",
    "wof:placetype":"locality"
},
  "geometry": {"coordinates":[85.08471,27.63012],"type":"Point"}
}