{
  "type": "Feature",
  "properties": {
    "gn:admin1_code":"ER",
    "gn:admin2_code":"10.0",
    "gn:admin3_code":"1.0",
    "gn:admin4_code":"10042.0",
    "gn:asciiname":"Burumkhim",
    "gn:country_code":"NP",
    "gn:dem":1687,
    "gn:feature_class":"P",
    "gn:feature_code":"PPLL",
    "gn:name":"Burumkhim",
    "gn:population":0,
    "gn:timezone":"Asia/Kathmandu",
    "iso:country":"NP",
    "wof:name":"Burumkhim",
    "wof:placetype":"locality"
},
  "geometry": {"coordinates":[87.93146,27.37768],"type":"Point"}
}