{
  "type": "Feature",
  "properties": {
    "gn:admin1_code":"FR",
    "gn:admin2_code":"14",
    "gn:admin3_code":"70.0",
    "gn:admin4_code":"700002.0",
    "gn:asciiname":"Amani",
    "gn:country_code":"NP",
    "gn:dem":728,
    "gn:feature_class":"P",
    "gn:feature_code":"PPLL",
    "gn:name":"Amani",
    "gn:population":0,
    "gn:timezone":"Asia/Kathmandu",
    "iso:country":"NP",
    "wof:name":"Amani",
    "wof:placetype":"locality"
},
  "geometry": {"coordinates":[80.77162,29.28748],"type":"Point"}
}