{
  "type": "Feature",
  "properties": {
    "gn:admin1_code":"ER",
    "gn:admin2_code":"7.0",
    "gn:admin3_code":"8.0",
    "gn:admin4_code":"80012.0",
    "gn:asciiname":"Amphuwa",
    "gn:country_code":"NP",
    "gn:dem":1406,
    "gn:feature_class":"P",
    "gn:feature_code":"PPLL",
    "gn:name":"Amphuwa",
    "gn:population":0,
    "gn:timezone":"Asia/Kathmandu",
    "iso:country":"NP",
    "wof:name":"Amphuwa",
    "wof:placetype":"locality"
},
  "geometry": {"coordinates":[87.50069999999999,27.1501],"type":"Point"}
}