{
  "type": "Feature",
  "properties": {
    "gn:admin1_code":"WR",
    "gn:admin2_code":"4",
    "gn:admin3_code":"37",
    "gn:admin4_code":"370041",
    "gn:asciiname":"Kamere",
    "gn:country_code":"NP",
    "gn:dem":851,
    "gn:feature_class":"P",
    "gn:feature_code":"PPLL",
    "gn:name":"Kamere",
    "gn:population":0,
    "gn:timezone":"Asia/Kathmandu",
    "iso:country":"NP",
    "wof:name":"Kamere",
    "wof:placetype":"locality"
},
  "geometry": {"coordinates":[84.29203000000003,28.21139],"type":"Point"}
}