{
  "type": "Feature",
  "properties": {
    "gn:admin1_code":"MR",
    "gn:admin2_code":"6",
    "gn:admin3_code":"66.0",
    "gn:admin4_code":"660010.0",
    "gn:asciiname":"Kapakaru",
    "gn:country_code":"NP",
    "gn:dem":2695,
    "gn:feature_class":"P",
    "gn:feature_code":"PPLL",
    "gn:name":"Kapakaru",
    "gn:population":0,
    "gn:timezone":"Asia/Kathmandu",
    "iso:country":"NP",
    "wof:name":"Kapakaru",
    "wof:placetype":"locality"
},
  "geometry": {"coordinates":[81.682,30.04137],"type":"Point"}
}