{
  "type": "Feature",
  "properties": {
    "gn:admin1_code":"FR",
    "gn:admin2_code":"9",
    "gn:admin3_code":"73.0",
    "gn:admin4_code":"730009.0",
    "gn:asciiname":"Bhatyadi",
    "gn:country_code":"NP",
    "gn:dem":1478,
    "gn:feature_class":"P",
    "gn:feature_code":"PPLL",
    "gn:name":"Bhatyadi",
    "gn:population":0,
    "gn:timezone":"Asia/Kathmandu",
    "iso:country":"NP",
    "wof:name":"Bhatyadi",
    "wof:placetype":"locality"
},
  "geometry": {"coordinates":[80.49590999999999,29.37545],"type":"Point"}
}