{
  "type": "Feature",
  "properties": {
    "gn:admin1_code":"MR",
    "gn:admin2_code":"2",
    "gn:admin3_code":"60.0",
    "gn:admin4_code":"600024.0",
    "gn:asciiname":"Lamkatiya",
    "gn:country_code":"NP",
    "gn:dem":1086,
    "gn:feature_class":"P",
    "gn:feature_code":"PPLL",
    "gn:name":"Lamkatiya",
    "gn:population":0,
    "gn:timezone":"Asia/Kathmandu",
    "iso:country":"NP",
    "wof:name":"Lamkatiya",
    "wof:placetype":"locality"
},
  "geometry": {"coordinates":[81.81406,28.78251],"type":"Point"}
}