{
  "type": "Feature",
  "properties": {
    "gn:admin1_code":"ER",
    "gn:admin2_code":"13",
    "gn:admin3_code":"13.0",
    "gn:admin4_code":"130009.0",
    "gn:asciiname":"Chilaunetar",
    "gn:country_code":"NP",
    "gn:dem":1380,
    "gn:feature_class":"P",
    "gn:feature_code":"PPLL",
    "gn:name":"Chilaunetar",
    "gn:population":0,
    "gn:timezone":"Asia/Kathmandu",
    "iso:country":"NP",
    "wof:name":"Chilaunetar",
    "wof:placetype":"locality"
},
  "geometry": {"coordinates":[86.8116,26.9656],"type":"Point"}
}