{
  "type": "Feature",
  "properties": {
    "gn:admin1_code":"ER",
    "gn:admin2_code":"10",
    "gn:admin3_code":"4.0",
    "gn:admin4_code":"40008.0",
    "gn:asciiname":"Charchabari Aathnambarchok",
    "gn:country_code":"NP",
    "gn:dem":169,
    "gn:feature_class":"P",
    "gn:feature_code":"PPLL",
    "gn:name":"Charchabari Aathnambarchok",
    "gn:population":0,
    "gn:timezone":"Asia/Kathmandu",
    "iso:country":"NP",
    "wof:name":"Charchabari Aathnambarchok",
    "wof:placetype":"locality"
},
  "geometry": {"coordinates":[88.05905,26.70286],"type":"Point"}
}