{
  "type": "Feature",
  "properties": {
    "gn:admin1_code":"00",
    "gn:asciiname":"Gamphathang",
    "gn:country_code":"NP",
    "gn:dem":1747,
    "gn:feature_class":"P",
    "gn:feature_code":"PPL",
    "gn:name":"Gamph\u0101th\u0101ng",
    "gn:population":0,
    "gn:timezone":"Asia/Kathmandu",
    "iso:country":"NP",
    "wof:name":"Gamphathang",
    "wof:placetype":"locality"
},
  "geometry": {"coordinates":[85.80168,27.96804],"type":"Point"}
}