{
  "type": "Feature",
  "properties": {
    "gn:admin1_code":"ER",
    "gn:admin2_code":"13.0",
    "gn:admin3_code":"14.0",
    "gn:admin4_code":"140031.0",
    "gn:asciiname":"Salle",
    "gn:country_code":"NP",
    "gn:dem":1364,
    "gn:feature_class":"P",
    "gn:feature_code":"PPLL",
    "gn:name":"Salle",
    "gn:population":0,
    "gn:timezone":"Asia/Kathmandu",
    "iso:country":"NP",
    "name:ceb_x_preferred":[
        "Salle"
    ],
    "name:deu_x_preferred":[
        "Salle"
    ],
    "name:fra_x_preferred":[
        "Salle"
    ],
    "name:mai_x_preferred":[
        "\u0938\u0932\u094d\u0932\u0947"
    ],
    "name:nld_x_preferred":[
        "Salle"
    ],
    "name:pol_x_preferred":[
        "Salle"
    ],
    "name:rus_x_preferred":[
        "\u0421\u0430\u043b\u043b\u044c"
    ],
    "name:swe_x_preferred":[
        "Salle"
    ],
    "wof:name":"Salle",
    "wof:placetype":"locality"
},
  "geometry": {"coordinates":[86.56744,27.08551],"type":"Point"}
}