{
  "type": "Feature",
  "properties": {
    "gn:admin1_code":"WR",
    "gn:admin2_code":"4.0",
    "gn:admin3_code":"39.0",
    "gn:admin4_code":"390023.0",
    "gn:asciiname":"Majuwa",
    "gn:country_code":"NP",
    "gn:dem":1290,
    "gn:feature_class":"P",
    "gn:feature_code":"PPLL",
    "gn:name":"Majuwa",
    "gn:population":0,
    "gn:timezone":"Asia/Kathmandu",
    "iso:country":"NP",
    "wof:name":"Majuwa",
    "wof:placetype":"locality"
},
  "geometry": {"coordinates":[83.8206,27.97301],"type":"Point"}
}