{
  "type": "Feature",
  "properties": {
    "gn:admin1_code":"MR",
    "gn:admin2_code":"2",
    "gn:admin3_code":"61.0",
    "gn:admin4_code":"610011.0",
    "gn:asciiname":"Sudari",
    "gn:country_code":"NP",
    "gn:dem":735,
    "gn:feature_class":"P",
    "gn:feature_code":"PPLL",
    "gn:name":"Sudari",
    "gn:population":0,
    "gn:timezone":"Asia/Kathmandu",
    "iso:country":"NP",
    "wof:name":"Sudari",
    "wof:placetype":"locality"
},
  "geometry": {"coordinates":[82.00542,28.69957],"type":"Point"}
}