{
  "type": "Feature",
  "properties": {
    "gn:admin1_code":"WR",
    "gn:admin2_code":"4",
    "gn:admin3_code":"40.0",
    "gn:admin4_code":"400029.0",
    "gn:asciiname":"Talwa Goth",
    "gn:country_code":"NP",
    "gn:dem":2744,
    "gn:feature_class":"P",
    "gn:feature_code":"PPLL",
    "gn:name":"Talwa Goth",
    "gn:population":0,
    "gn:timezone":"Asia/Kathmandu",
    "iso:country":"NP",
    "wof:name":"Talwa Goth",
    "wof:placetype":"locality"
},
  "geometry": {"coordinates":[84.13283,28.41877],"type":"Point"}
}