{
  "type": "Feature",
  "properties": {
    "gn:admin1_code":"00",
    "gn:asciiname":"Idu",
    "gn:country_code":"NP",
    "gn:dem":1146,
    "gn:feature_class":"P",
    "gn:feature_code":"PPL",
    "gn:name":"\u0128du",
    "gn:population":0,
    "gn:timezone":"Asia/Kathmandu",
    "iso:country":"NP",
    "name:nep_x_preferred":[
        "\u0128du"
    ],
    "wof:name":"Idu",
    "wof:placetype":"locality"
},
  "geometry": {"coordinates":[84.93810000000001,28.04015],"type":"Point"}
}