{
  "type": "Feature",
  "properties": {
    "gn:admin1_code":"ER",
    "gn:admin2_code":"13",
    "gn:admin3_code":"16",
    "gn:admin4_code":"160034",
    "gn:asciiname":"Ghat",
    "gn:country_code":"NP",
    "gn:dem":208,
    "gn:feature_class":"P",
    "gn:feature_code":"PPLL",
    "gn:name":"Ghat",
    "gn:population":0,
    "gn:timezone":"Asia/Kathmandu",
    "iso:country":"NP",
    "wof:name":"Ghat",
    "wof:placetype":"locality"
},
  "geometry": {"coordinates":[86.34023000000001,26.85971],"type":"Point"}
}