{
  "type": "Feature",
  "properties": {
    "gn:admin1_code":"ER",
    "gn:admin2_code":"7.0",
    "gn:admin3_code":"6.0",
    "gn:admin4_code":"60039.0",
    "gn:asciiname":"Patranbari",
    "gn:country_code":"NP",
    "gn:dem":604,
    "gn:feature_class":"P",
    "gn:feature_code":"PPLL",
    "gn:name":"Patranbari",
    "gn:population":0,
    "gn:timezone":"Asia/Kathmandu",
    "iso:country":"NP",
    "wof:name":"Patranbari",
    "wof:placetype":"locality"
},
  "geometry": {"coordinates":[87.31265,26.81832],"type":"Point"}
}