{
  "type": "Feature",
  "properties": {
    "gn:admin1_code":"FR",
    "gn:admin2_code":"14",
    "gn:admin3_code":"70.0",
    "gn:admin4_code":"700036.0",
    "gn:asciiname":"Bitharbata",
    "gn:country_code":"NP",
    "gn:dem":1704,
    "gn:feature_class":"P",
    "gn:feature_code":"PPLL",
    "gn:name":"Bitharbata",
    "gn:population":0,
    "gn:timezone":"Asia/Kathmandu",
    "iso:country":"NP",
    "wof:name":"Bitharbata",
    "wof:placetype":"locality"
},
  "geometry": {"coordinates":[80.87068000000002,29.06295],"type":"Point"}
}