{
  "type": "Feature",
  "properties": {
    "gn:admin1_code":"WR",
    "gn:admin2_code":"4.0",
    "gn:admin3_code":"39.0",
    "gn:admin4_code":"390043.0",
    "gn:asciiname":"Nigali",
    "gn:country_code":"NP",
    "gn:dem":1360,
    "gn:feature_class":"P",
    "gn:feature_code":"PPLL",
    "gn:name":"Nigali",
    "gn:population":0,
    "gn:timezone":"Asia/Kathmandu",
    "iso:country":"NP",
    "name:ceb_x_preferred":[
        "Nigali"
    ],
    "name:fra_x_preferred":[
        "Nigali"
    ],
    "name:mai_x_preferred":[
        "\u0928\u093f\u0917\u093e\u0932\u0940"
    ],
    "name:msa_x_preferred":[
        "Nigali"
    ],
    "name:nep_x_preferred":[
        "\u0928\u093f\u0917\u093e\u0932\u0940"
    ],
    "name:new_x_preferred":[
        "\u0928\u093f\u0917\u093e\u0932\u0940"
    ],
    "name:pol_x_preferred":[
        "Nigali"
    ],
    "wof:name":"Nigali",
    "wof:placetype":"locality"
},
  "geometry": {"coordinates":[83.64506999999998,27.98051],"type":"Point"}
}