{
  "type": "Feature",
  "properties": {
    "gn:admin1_code":"FR",
    "gn:admin2_code":"14",
    "gn:admin3_code":"69",
    "gn:admin4_code":"690024",
    "gn:asciiname":"Lanchi",
    "gn:country_code":"NP",
    "gn:dem":1407,
    "gn:feature_class":"P",
    "gn:feature_code":"PPLL",
    "gn:name":"Lanchi",
    "gn:population":0,
    "gn:timezone":"Asia/Kathmandu",
    "iso:country":"NP",
    "wof:name":"Lanchi",
    "wof:placetype":"locality"
},
  "geometry": {"coordinates":[81.32278000000002,29.03001],"type":"Point"}
}