{
  "type": "Feature",
  "properties": {
    "gn:admin1_code":"FR",
    "gn:admin2_code":"9",
    "gn:admin3_code":"75.0",
    "gn:admin4_code":"750008.0",
    "gn:asciiname":"Salikhet",
    "gn:country_code":"NP",
    "gn:dem":933,
    "gn:feature_class":"P",
    "gn:feature_code":"PPLL",
    "gn:name":"Salikhet",
    "gn:population":0,
    "gn:timezone":"Asia/Kathmandu",
    "iso:country":"NP",
    "wof:name":"Salikhet",
    "wof:placetype":"locality"
},
  "geometry": {"coordinates":[80.60765000000001,29.71077],"type":"Point"}
}