{
  "type": "Feature",
  "properties": {
    "gn:admin1_code":"CR",
    "gn:admin2_code":"11.0",
    "gn:admin3_code":"33.0",
    "gn:admin4_code":"330045.0",
    "gn:asciiname":"Gamhariya",
    "gn:country_code":"NP",
    "gn:dem":86,
    "gn:feature_class":"P",
    "gn:feature_code":"PPLL",
    "gn:name":"Gamhariya",
    "gn:population":0,
    "gn:timezone":"Asia/Kathmandu",
    "iso:country":"NP",
    "name:fra_x_preferred":[
        "Gamhariya"
    ],
    "name:new_x_preferred":[
        "\u0917\u092e\u094d\u0939\u0930\u093f\u092f\u093e"
    ],
    "name:pol_x_preferred":[
        "Gamhariya"
    ],
    "wof:name":"Gamhariya",
    "wof:placetype":"locality"
},
  "geometry": {"coordinates":[85.00168000000002,26.94106],"type":"Point"}
}