{
  "type": "Feature",
  "properties": {
    "gn:admin1_code":"WR",
    "gn:admin2_code":"8",
    "gn:admin3_code":"49",
    "gn:admin4_code":"490052",
    "gn:asciiname":"Sworwali",
    "gn:country_code":"NP",
    "gn:dem":173,
    "gn:feature_class":"P",
    "gn:feature_code":"PPLL",
    "gn:name":"Sworwali",
    "gn:population":0,
    "gn:timezone":"Asia/Kathmandu",
    "iso:country":"NP",
    "wof:name":"Sworwali",
    "wof:placetype":"locality"
},
  "geometry": {"coordinates":[83.36899,27.69346],"type":"Point"}
}