{
  "type": "Feature",
  "properties": {
    "gn:admin1_code":"CR",
    "gn:admin2_code":"5",
    "gn:admin3_code":"17.0",
    "gn:admin4_code":"170100.0",
    "gn:asciiname":"Saraswatipur",
    "gn:country_code":"NP",
    "gn:dem":174,
    "gn:feature_class":"P",
    "gn:feature_code":"PPLL",
    "gn:name":"Saraswatipur",
    "gn:population":0,
    "gn:timezone":"Asia/Kathmandu",
    "iso:country":"NP",
    "wof:name":"Saraswatipur",
    "wof:placetype":"locality"
},
  "geometry": {"coordinates":[86.03288000000001,26.92334],"type":"Point"}
}