{
  "type": "Feature",
  "properties": {
    "gn:admin1_code":"00",
    "gn:asciiname":"Khandada",
    "gn:country_code":"NP",
    "gn:dem":1865,
    "gn:feature_class":"P",
    "gn:feature_code":"PPL",
    "gn:name":"Kh\u0101n\u1e0d\u0101\u0303\u1e0d\u0101",
    "gn:population":0,
    "gn:timezone":"Asia/Kathmandu",
    "iso:country":"NP",
    "wof:name":"Khandada",
    "wof:placetype":"locality"
},
  "geometry": {"coordinates":[86.81692,27.2936],"type":"Point"}
}