{
  "type": "Feature",
  "properties": {
    "gn:admin1_code":"ER",
    "gn:admin2_code":"13",
    "gn:admin3_code":"15",
    "gn:admin4_code":"150104",
    "gn:asciiname":"Dangrahi",
    "gn:country_code":"NP",
    "gn:dem":119,
    "gn:feature_class":"P",
    "gn:feature_code":"PPLL",
    "gn:name":"Dangrahi",
    "gn:population":0,
    "gn:timezone":"Asia/Kathmandu",
    "iso:country":"NP",
    "wof:name":"Dangrahi",
    "wof:placetype":"locality"
},
  "geometry": {"coordinates":[86.69622,26.61923],"type":"Point"}
}