{
  "type": "Feature",
  "properties": {
    "gn:admin1_code":"MR",
    "gn:admin2_code":"2.0",
    "gn:admin3_code":"57.0",
    "gn:admin4_code":"570034.0",
    "gn:asciiname":"Jharbaira",
    "gn:country_code":"NP",
    "gn:dem":135,
    "gn:feature_class":"P",
    "gn:feature_code":"PPLL",
    "gn:name":"Jharbaira",
    "gn:population":0,
    "gn:timezone":"Asia/Kathmandu",
    "iso:country":"NP",
    "wof:name":"Jharbaira",
    "wof:placetype":"locality"
},
  "geometry": {"coordinates":[81.75657,28.01148],"type":"Point"}
}