{
  "type": "Feature",
  "properties": {
    "gn:admin1_code":"ER",
    "gn:admin2_code":"10",
    "gn:admin3_code":"2",
    "gn:admin4_code":"20025",
    "gn:asciiname":"Chotrok",
    "gn:country_code":"NP",
    "gn:dem":1226,
    "gn:feature_class":"P",
    "gn:feature_code":"PPLL",
    "gn:name":"Chotrok",
    "gn:population":0,
    "gn:timezone":"Asia/Kathmandu",
    "iso:country":"NP",
    "wof:name":"Chotrok",
    "wof:placetype":"locality"
},
  "geometry": {"coordinates":[87.90006,27.28245],"type":"Point"}
}