{
  "type": "Feature",
  "properties": {
    "gn:admin1_code":"ER",
    "gn:admin2_code":"10",
    "gn:admin3_code":"2",
    "gn:admin4_code":"20016",
    "gn:asciiname":"Halhale",
    "gn:country_code":"NP",
    "gn:dem":2584,
    "gn:feature_class":"P",
    "gn:feature_code":"PPLL",
    "gn:name":"Halhale",
    "gn:population":0,
    "gn:timezone":"Asia/Kathmandu",
    "iso:country":"NP",
    "wof:name":"Halhale",
    "wof:placetype":"locality"
},
  "geometry": {"coordinates":[87.8711,27.07981],"type":"Point"}
}