{
  "type": "Feature",
  "properties": {
    "gn:admin1_code":"WR",
    "gn:admin2_code":"3",
    "gn:admin3_code":"44",
    "gn:admin4_code":"440034",
    "gn:asciiname":"Berneta",
    "gn:country_code":"NP",
    "gn:dem":1017,
    "gn:feature_class":"P",
    "gn:feature_code":"PPLL",
    "gn:name":"Berneta",
    "gn:population":0,
    "gn:timezone":"Asia/Kathmandu",
    "iso:country":"NP",
    "wof:name":"Berneta",
    "wof:placetype":"locality"
},
  "geometry": {"coordinates":[83.66693000000002,28.1583],"type":"Point"}
}