{
  "type": "Feature",
  "properties": {
    "gn:admin1_code":"FR",
    "gn:admin2_code":"9",
    "gn:admin3_code":"75.0",
    "gn:admin4_code":"750009.0",
    "gn:asciiname":"Tham",
    "gn:country_code":"NP",
    "gn:dem":1028,
    "gn:feature_class":"P",
    "gn:feature_code":"PPLL",
    "gn:name":"Tham",
    "gn:population":0,
    "gn:timezone":"Asia/Kathmandu",
    "iso:country":"NP",
    "wof:name":"Tham",
    "wof:placetype":"locality"
},
  "geometry": {"coordinates":[80.46348,29.79686],"type":"Point"}
}