{
  "type": "Feature",
  "properties": {
    "gn:admin1_code":"ER",
    "gn:admin2_code":"13",
    "gn:admin3_code":"16",
    "gn:admin4_code":"160040",
    "gn:asciiname":"Bhasuwa",
    "gn:country_code":"NP",
    "gn:dem":220,
    "gn:feature_class":"P",
    "gn:feature_code":"PPLL",
    "gn:name":"Bhasuwa",
    "gn:population":0,
    "gn:timezone":"Asia/Kathmandu",
    "iso:country":"NP",
    "wof:name":"Bhasuwa",
    "wof:placetype":"locality"
},
  "geometry": {"coordinates":[86.50308000000003,26.8445],"type":"Point"}
}