{
  "type": "Feature",
  "properties": {
    "gn:admin1_code":"MR",
    "gn:admin2_code":"6",
    "gn:admin3_code":"65",
    "gn:admin4_code":"650010",
    "gn:asciiname":"Lajok",
    "gn:country_code":"NP",
    "gn:dem":3074,
    "gn:feature_class":"P",
    "gn:feature_code":"PPLL",
    "gn:name":"Lajok",
    "gn:population":0,
    "gn:timezone":"Asia/Kathmandu",
    "iso:country":"NP",
    "wof:name":"Lajok",
    "wof:placetype":"locality"
},
  "geometry": {"coordinates":[82.30691999999998,29.60696],"type":"Point"}
}