{
  "type": "Feature",
  "properties": {
    "gn:admin1_code":"ER",
    "gn:admin2_code":"7",
    "gn:admin3_code":"10.0",
    "gn:admin4_code":"100023.0",
    "gn:asciiname":"Pipalbote",
    "gn:country_code":"NP",
    "gn:dem":329,
    "gn:feature_class":"P",
    "gn:feature_code":"PPLL",
    "gn:name":"Pipalbote",
    "gn:population":0,
    "gn:timezone":"Asia/Kathmandu",
    "iso:country":"NP",
    "wof:name":"Pipalbote",
    "wof:placetype":"locality"
},
  "geometry": {"coordinates":[87.08044,26.92309],"type":"Point"}
}