{
  "type": "Feature",
  "properties": {
    "iso:country":"NP",
    "name:und_x_variant":[
        "Panauti Village"
    ],
    "qs:gn_country":"NP",
    "qs:gn_fcode":"PPL",
    "qs:gn_pop":27602,
    "qs:name":"Panaoti",
    "qs:name_adm0":"Nepal",
    "qs:name_adm1":"Madhyamanchal",
    "qs:photos":319,
    "qs:photos_1k":65,
    "qs:photos_9k":1,
    "qs:photos_9r":5,
    "qs:photos_all":319,
    "qs:photos_sr":5,
    "qs:placetype":"Town",
    "qs:pop_sr":"7",
    "qs:woe_adm0":23424911,
    "wof:name":"Panaoti",
    "wof:placetype":"locality",
    "wof:population":27602
},
  "geometry": {"coordinates":[85.5124,27.58138],"type":"Point"}
}