{
  "type": "Feature",
  "properties": {
    "gn:admin1_code":"MR",
    "gn:admin2_code":"12",
    "gn:admin3_code":"53",
    "gn:admin4_code":"530033",
    "gn:asciiname":"Khayar Jharki",
    "gn:country_code":"NP",
    "gn:dem":1096,
    "gn:feature_class":"P",
    "gn:feature_code":"PPLL",
    "gn:name":"Khayar Jharki",
    "gn:population":0,
    "gn:timezone":"Asia/Kathmandu",
    "iso:country":"NP",
    "wof:name":"Khayar Jharki",
    "wof:placetype":"locality"
},
  "geometry": {"coordinates":[82.72789,28.26721],"type":"Point"}
}