{
  "type": "Feature",
  "properties": {
    "gn:admin1_code":"CR",
    "gn:admin2_code":"1",
    "gn:admin3_code":"30.0",
    "gn:admin4_code":"300002.0",
    "gn:asciiname":"Rahudandagaun",
    "gn:country_code":"NP",
    "gn:dem":720,
    "gn:feature_class":"P",
    "gn:feature_code":"PPLL",
    "gn:name":"Rahudandagaun",
    "gn:population":0,
    "gn:timezone":"Asia/Kathmandu",
    "iso:country":"NP",
    "wof:name":"Rahudandagaun",
    "wof:placetype":"locality"
},
  "geometry": {"coordinates":[84.97969000000001,27.78752],"type":"Point"}
}