{
  "type": "Feature",
  "properties": {
    "gn:admin1_code":"MR",
    "gn:admin2_code":"2.0",
    "gn:admin3_code":"59.0",
    "gn:admin4_code":"590026.0",
    "gn:asciiname":"Khannekharka",
    "gn:country_code":"NP",
    "gn:dem":551,
    "gn:feature_class":"P",
    "gn:feature_code":"PPLL",
    "gn:name":"Khannekharka",
    "gn:population":0,
    "gn:timezone":"Asia/Kathmandu",
    "iso:country":"NP",
    "wof:name":"Khannekharka",
    "wof:placetype":"locality"
},
  "geometry": {"coordinates":[81.97447,28.44654],"type":"Point"}
}