{
  "type": "Feature",
  "properties": {
    "gn:admin1_code":"FR",
    "gn:admin2_code":"14",
    "gn:admin3_code":"70.0",
    "gn:admin4_code":"700016.0",
    "gn:asciiname":"Balekhad",
    "gn:country_code":"NP",
    "gn:dem":717,
    "gn:feature_class":"P",
    "gn:feature_code":"PPLL",
    "gn:name":"Balekhad",
    "gn:population":0,
    "gn:timezone":"Asia/Kathmandu",
    "iso:country":"NP",
    "wof:name":"Balekhad",
    "wof:placetype":"locality"
},
  "geometry": {"coordinates":[81.06283000000001,29.12542],"type":"Point"}
}