{
  "type": "Feature",
  "properties": {
    "gn:admin1_code":"FR",
    "gn:admin2_code":"9",
    "gn:admin3_code":"75.0",
    "gn:admin4_code":"750021.0",
    "gn:asciiname":"Mulla",
    "gn:country_code":"NP",
    "gn:dem":1755,
    "gn:feature_class":"P",
    "gn:feature_code":"PPLL",
    "gn:name":"Mulla",
    "gn:population":0,
    "gn:timezone":"Asia/Kathmandu",
    "iso:country":"NP",
    "name:ceb_x_preferred":[
        "Mulla"
    ],
    "name:fas_x_preferred":[
        "\u0645\u0644\u0627"
    ],
    "name:rus_x_preferred":[
        "\u041c\u0443\u043b\u043b\u0430"
    ],
    "name:swe_x_preferred":[
        "Mulla"
    ],
    "wof:name":"Mulla",
    "wof:placetype":"locality"
},
  "geometry": {"coordinates":[80.60989000000002,29.81477000000001],"type":"Point"}
}