{
  "type": "Feature",
  "properties": {
    "gn:admin1_code":"MR",
    "gn:admin2_code":"12",
    "gn:admin3_code":"52",
    "gn:admin4_code":"520002",
    "gn:asciiname":"Dadra",
    "gn:country_code":"NP",
    "gn:dem":1394,
    "gn:feature_class":"P",
    "gn:feature_code":"PPLL",
    "gn:name":"Dadra",
    "gn:population":0,
    "gn:timezone":"Asia/Kathmandu",
    "iso:country":"NP",
    "wof:name":"Dadra",
    "wof:placetype":"locality"
},
  "geometry": {"coordinates":[83.04611,28.14235],"type":"Point"}
}