{
  "type": "Feature",
  "properties": {
    "gn:admin1_code":"ER",
    "gn:admin2_code":"10",
    "gn:admin3_code":"2",
    "gn:admin4_code":"20032",
    "gn:asciiname":"Medibung",
    "gn:country_code":"NP",
    "gn:dem":1204,
    "gn:feature_class":"P",
    "gn:feature_code":"PPLL",
    "gn:name":"Medibung",
    "gn:population":0,
    "gn:timezone":"Asia/Kathmandu",
    "iso:country":"NP",
    "wof:name":"Medibung",
    "wof:placetype":"locality"
},
  "geometry": {"coordinates":[87.65266,27.10665],"type":"Point"}
}