{
  "type": "Feature",
  "properties": {
    "gn:admin1_code":"CR",
    "gn:admin2_code":"1",
    "gn:admin3_code":"28",
    "gn:admin4_code":"280036",
    "gn:asciiname":"Ungaun",
    "gn:country_code":"NP",
    "gn:dem":1536,
    "gn:feature_class":"P",
    "gn:feature_code":"PPLL",
    "gn:name":"Ungaun",
    "gn:population":0,
    "gn:timezone":"Asia/Kathmandu",
    "iso:country":"NP",
    "wof:name":"Ungaun",
    "wof:placetype":"locality"
},
  "geometry": {"coordinates":[85.27508,27.95564],"type":"Point"}
}