{
  "type": "Feature",
  "properties": {
    "gn:admin1_code":"FR",
    "gn:admin2_code":"14",
    "gn:admin3_code":"68",
    "gn:admin4_code":"680025",
    "gn:asciiname":"Dungrakot",
    "gn:country_code":"NP",
    "gn:dem":1813,
    "gn:feature_class":"P",
    "gn:feature_code":"PPLL",
    "gn:name":"Dungrakot",
    "gn:population":0,
    "gn:timezone":"Asia/Kathmandu",
    "iso:country":"NP",
    "wof:name":"Dungrakot",
    "wof:placetype":"locality"
},
  "geometry": {"coordinates":[81.23593000000002,29.5421],"type":"Point"}
}