{
  "type": "Feature",
  "properties": {
    "gn:admin1_code":"FR",
    "gn:admin2_code":"14",
    "gn:admin3_code":"70.0",
    "gn:admin4_code":"700019.0",
    "gn:asciiname":"Kilauda",
    "gn:country_code":"NP",
    "gn:dem":1799,
    "gn:feature_class":"P",
    "gn:feature_code":"PPLL",
    "gn:name":"Kilauda",
    "gn:population":0,
    "gn:timezone":"Asia/Kathmandu",
    "iso:country":"NP",
    "wof:name":"Kilauda",
    "wof:placetype":"locality"
},
  "geometry": {"coordinates":[80.57536,29.1292],"type":"Point"}
}