{
  "type": "Feature",
  "properties": {
    "gn:admin1_code":"ER",
    "gn:admin2_code":"13",
    "gn:admin3_code":"12",
    "gn:admin4_code":"120022",
    "gn:asciiname":"Parangas",
    "gn:country_code":"NP",
    "gn:dem":1364,
    "gn:feature_class":"P",
    "gn:feature_code":"PPLL",
    "gn:name":"Parangas",
    "gn:population":0,
    "gn:timezone":"Asia/Kathmandu",
    "iso:country":"NP",
    "wof:name":"Parangas",
    "wof:placetype":"locality"
},
  "geometry": {"coordinates":[86.47324999999999,27.24862000000001],"type":"Point"}
}