{
  "type": "Feature",
  "properties": {
    "gn:admin1_code":"WR",
    "gn:admin2_code":"8",
    "gn:admin3_code":"47",
    "gn:admin4_code":"470034",
    "gn:asciiname":"Lama Pokhara",
    "gn:country_code":"NP",
    "gn:dem":886,
    "gn:feature_class":"P",
    "gn:feature_code":"PPLL",
    "gn:name":"Lama Pokhara",
    "gn:population":0,
    "gn:timezone":"Asia/Kathmandu",
    "iso:country":"NP",
    "wof:name":"Lama Pokhara",
    "wof:placetype":"locality"
},
  "geometry": {"coordinates":[83.82738000000001,27.72032],"type":"Point"}
}