{
  "type": "Feature",
  "properties": {
    "gn:admin1_code":"FR",
    "gn:admin2_code":"14",
    "gn:admin3_code":"71.0",
    "gn:admin4_code":"710025.0",
    "gn:asciiname":"Simgaun",
    "gn:country_code":"NP",
    "gn:dem":1007,
    "gn:feature_class":"P",
    "gn:feature_code":"PPLL",
    "gn:name":"Simgaun",
    "gn:population":0,
    "gn:timezone":"Asia/Kathmandu",
    "iso:country":"NP",
    "wof:name":"Simgaun",
    "wof:placetype":"locality"
},
  "geometry": {"coordinates":[80.85850000000001,28.87699000000001],"type":"Point"}
}