{
  "type": "Feature",
  "properties": {
    "gn:admin1_code":"MR",
    "gn:admin2_code":"12",
    "gn:admin3_code":"54",
    "gn:admin4_code":"540011",
    "gn:asciiname":"Chaukhe",
    "gn:country_code":"NP",
    "gn:dem":1153,
    "gn:feature_class":"P",
    "gn:feature_code":"PPLL",
    "gn:name":"Chaukhe",
    "gn:population":0,
    "gn:timezone":"Asia/Kathmandu",
    "iso:country":"NP",
    "wof:name":"Chaukhe",
    "wof:placetype":"locality"
},
  "geometry": {"coordinates":[82.37545,28.66074],"type":"Point"}
}