{
  "type": "Feature",
  "properties": {
    "gn:admin1_code":"WR",
    "gn:admin2_code":"8",
    "gn:admin3_code":"48",
    "gn:admin4_code":"480070",
    "gn:asciiname":"Chormara",
    "gn:country_code":"NP",
    "gn:dem":192,
    "gn:feature_class":"P",
    "gn:feature_code":"PPLL",
    "gn:name":"Chormara",
    "gn:population":0,
    "gn:timezone":"Asia/Kathmandu",
    "iso:country":"NP",
    "wof:name":"Chormara",
    "wof:placetype":"locality"
},
  "geometry": {"coordinates":[84.01909000000001,27.61588],"type":"Point"}
}