{
  "type": "Feature",
  "properties": {
    "gn:admin1_code":"FR",
    "gn:admin2_code":"14",
    "gn:admin3_code":"68",
    "gn:admin4_code":"680029",
    "gn:asciiname":"Khatribada",
    "gn:country_code":"NP",
    "gn:dem":1732,
    "gn:feature_class":"P",
    "gn:feature_code":"PPLL",
    "gn:name":"Khatribada",
    "gn:population":0,
    "gn:timezone":"Asia/Kathmandu",
    "iso:country":"NP",
    "wof:name":"Khatribada",
    "wof:placetype":"locality"
},
  "geometry": {"coordinates":[81.14242,29.44861],"type":"Point"}
}