{
  "type": "Feature",
  "properties": {
    "gn:admin1_code":"ER",
    "gn:admin2_code":"13",
    "gn:admin3_code":"11",
    "gn:admin4_code":"110019",
    "gn:asciiname":"Bagam",
    "gn:country_code":"NP",
    "gn:dem":2442,
    "gn:feature_class":"P",
    "gn:feature_code":"PPLL",
    "gn:name":"Bagam",
    "gn:population":0,
    "gn:timezone":"Asia/Kathmandu",
    "iso:country":"NP",
    "wof:name":"Bagam",
    "wof:placetype":"locality"
},
  "geometry": {"coordinates":[86.52811,27.41717],"type":"Point"}
}