{
  "type": "Feature",
  "properties": {
    "gn:admin1_code":"CR",
    "gn:admin2_code":"5",
    "gn:admin3_code":"22.0",
    "gn:admin4_code":"220024.0",
    "gn:asciiname":"Ghunsa",
    "gn:country_code":"NP",
    "gn:dem":1838,
    "gn:feature_class":"P",
    "gn:feature_code":"PPLL",
    "gn:name":"Ghunsa",
    "gn:population":0,
    "gn:timezone":"Asia/Kathmandu",
    "iso:country":"NP",
    "wof:name":"Ghunsa",
    "wof:placetype":"locality"
},
  "geometry": {"coordinates":[86.23166999999999,27.61987],"type":"Point"}
}