{
  "type": "Feature",
  "properties": {
    "gn:admin1_code":"ER",
    "gn:admin2_code":"13",
    "gn:admin3_code":"15",
    "gn:admin4_code":"150012",
    "gn:asciiname":"Dalaba Uttartol",
    "gn:country_code":"NP",
    "gn:dem":73,
    "gn:feature_class":"P",
    "gn:feature_code":"PPLL",
    "gn:name":"Dalaba Uttartol",
    "gn:population":0,
    "gn:timezone":"Asia/Kathmandu",
    "iso:country":"NP",
    "wof:name":"Dalaba Uttartol",
    "wof:placetype":"locality"
},
  "geometry": {"coordinates":[86.82298,26.47397],"type":"Point"}
}