{
  "type": "Feature",
  "properties": {
    "gn:admin1_code":"CR",
    "gn:admin2_code":"5",
    "gn:admin3_code":"20",
    "gn:admin4_code":"200044",
    "gn:asciiname":"Gaganpani",
    "gn:country_code":"NP",
    "gn:dem":1289,
    "gn:feature_class":"P",
    "gn:feature_code":"PPLL",
    "gn:name":"Gaganpani",
    "gn:population":0,
    "gn:timezone":"Asia/Kathmandu",
    "iso:country":"NP",
    "wof:name":"Gaganpani",
    "wof:placetype":"locality"
},
  "geometry": {"coordinates":[86.34017,27.18626],"type":"Point"}
}