{
  "type": "Feature",
  "properties": {
    "gn:admin1_code":"WR",
    "gn:admin2_code":"4.0",
    "gn:admin3_code":"38.0",
    "gn:admin4_code":"380033.0",
    "gn:asciiname":"Dharapani",
    "gn:country_code":"NP",
    "gn:dem":729,
    "gn:feature_class":"P",
    "gn:feature_code":"PPLL",
    "gn:name":"Dharapani",
    "gn:population":0,
    "gn:timezone":"Asia/Kathmandu",
    "iso:country":"NP",
    "name:fra_x_preferred":[
        "Dharapani"
    ],
    "name:new_x_preferred":[
        "\u0927\u093e\u0930\u093e\u092a\u093e\u0928\u0940"
    ],
    "name:pol_x_preferred":[
        "Dharapani"
    ],
    "wof:name":"Dharapani",
    "wof:placetype":"locality"
},
  "geometry": {"coordinates":[84.19105,28.02163],"type":"Point"}
}