{
  "type": "Feature",
  "properties": {
    "gn:admin1_code":"CR",
    "gn:admin2_code":"5",
    "gn:admin3_code":"21",
    "gn:admin4_code":"210045",
    "gn:asciiname":"Pakhera",
    "gn:country_code":"NP",
    "gn:dem":1463,
    "gn:feature_class":"P",
    "gn:feature_code":"PPLL",
    "gn:name":"Pakhera",
    "gn:population":0,
    "gn:timezone":"Asia/Kathmandu",
    "iso:country":"NP",
    "wof:name":"Pakhera",
    "wof:placetype":"locality"
},
  "geometry": {"coordinates":[86.06007,27.33255],"type":"Point"}
}