{
  "type": "Feature",
  "properties": {
    "gn:admin1_code":"00",
    "gn:asciiname":"Khadwari",
    "gn:country_code":"NP",
    "gn:dem":559,
    "gn:feature_class":"P",
    "gn:feature_code":"PPL",
    "gn:name":"Kh\u0101\u0303dw\u0101ri",
    "gn:population":0,
    "gn:timezone":"Asia/Kathmandu",
    "iso:country":"NP",
    "name:und_x_variant":[
        "Kh\u0101\u0303dw\u0101ri",
        "Kh\u0101ndw\u0101ri"
    ],
    "wof:name":"Khadwari",
    "wof:placetype":"locality"
},
  "geometry": {"coordinates":[86.06191,27.3798],"type":"Point"}
}