{
  "type": "Feature",
  "properties": {
    "gn:admin1_code":"00",
    "gn:asciiname":"Banashthali",
    "gn:country_code":"NP",
    "gn:dem":1404,
    "gn:feature_class":"P",
    "gn:feature_code":"PPL",
    "gn:name":"B\u0101nashthali\u0307\u0304",
    "gn:population":0,
    "gn:timezone":"Asia/Kathmandu",
    "iso:country":"NP",
    "name:und_x_variant":[
        "B\u0101nashthali\u0307\u0304",
        "B\u0101nashthal\u012b"
    ],
    "wof:name":"Banashthali",
    "wof:placetype":"locality"
},
  "geometry": {"coordinates":[85.2317,27.69361],"type":"Point"}
}