{
  "type": "Feature",
  "properties": {
    "gn:admin1_code":"00",
    "gn:asciiname":"Ranpur",
    "gn:country_code":"NP",
    "gn:dem":99,
    "gn:feature_class":"P",
    "gn:feature_code":"PPL",
    "gn:name":"Ra\u1e45pur",
    "gn:population":0,
    "gn:timezone":"Asia/Kathmandu",
    "iso:country":"NP",
    "name:cat_x_preferred":[
        "Ranpur"
    ],
    "name:guj_x_preferred":[
        "\u0ab0\u0abe\u0aa3\u0aaa\u0ac1\u0ab0"
    ],
    "name:hin_x_preferred":[
        "\u0930\u093e\u0923\u092a\u0941\u0930"
    ],
    "wof:name":"Ranpur",
    "wof:placetype":"locality"
},
  "geometry": {"coordinates":[85.00044,27.01341],"type":"Point"}
}