{
  "type": "Feature",
  "properties": {
    "gn:admin1_code":"WR",
    "gn:admin2_code":"4.0",
    "gn:admin3_code":"38.0",
    "gn:admin4_code":"380005.0",
    "gn:asciiname":"Syauli",
    "gn:country_code":"NP",
    "gn:dem":471,
    "gn:feature_class":"P",
    "gn:feature_code":"PPLL",
    "gn:name":"Syauli",
    "gn:population":0,
    "gn:timezone":"Asia/Kathmandu",
    "iso:country":"NP",
    "wof:name":"Syauli",
    "wof:placetype":"locality"
},
  "geometry": {"coordinates":[84.38457,28.02509],"type":"Point"}
}