{
  "type": "Feature",
  "properties": {
    "gn:admin1_code":"ER",
    "gn:admin2_code":"13",
    "gn:admin3_code":"12",
    "gn:admin4_code":"120052",
    "gn:asciiname":"Jakma",
    "gn:country_code":"NP",
    "gn:dem":628,
    "gn:feature_class":"P",
    "gn:feature_code":"PPLL",
    "gn:name":"Jakma",
    "gn:population":0,
    "gn:timezone":"Asia/Kathmandu",
    "iso:country":"NP",
    "wof:name":"Jakma",
    "wof:placetype":"locality"
},
  "geometry": {"coordinates":[86.46381,27.17203],"type":"Point"}
}