{
  "type": "Feature",
  "properties": {
    "gn:admin1_code":"WR",
    "gn:admin2_code":"3",
    "gn:admin3_code":"44",
    "gn:admin4_code":"440002",
    "gn:asciiname":"Bachchhagaun",
    "gn:country_code":"NP",
    "gn:dem":891,
    "gn:feature_class":"P",
    "gn:feature_code":"PPLL",
    "gn:name":"Bachchhagaun",
    "gn:population":0,
    "gn:timezone":"Asia/Kathmandu",
    "iso:country":"NP",
    "wof:name":"Bachchhagaun",
    "wof:placetype":"locality"
},
  "geometry": {"coordinates":[83.61369000000001,28.10502],"type":"Point"}
}