{
  "type": "Feature",
  "properties": {
    "gn:admin1_code":"CR",
    "gn:admin2_code":"11",
    "gn:admin3_code":"31",
    "gn:admin4_code":"310042",
    "gn:asciiname":"Neupanetar",
    "gn:country_code":"NP",
    "gn:dem":834,
    "gn:feature_class":"P",
    "gn:feature_code":"PPLL",
    "gn:name":"Neupanetar",
    "gn:population":0,
    "gn:timezone":"Asia/Kathmandu",
    "iso:country":"NP",
    "wof:name":"Neupanetar",
    "wof:placetype":"locality"
},
  "geometry": {"coordinates":[85.15774,27.45639000000001],"type":"Point"}
}