{
  "type": "Feature",
  "properties": {
    "gn:admin1_code":"ER",
    "gn:admin2_code":"13",
    "gn:admin3_code":"12",
    "gn:admin4_code":"120030",
    "gn:asciiname":"Nipane",
    "gn:country_code":"NP",
    "gn:dem":806,
    "gn:feature_class":"P",
    "gn:feature_code":"PPLL",
    "gn:name":"Nipane",
    "gn:population":0,
    "gn:timezone":"Asia/Kathmandu",
    "iso:country":"NP",
    "name:ceb_x_preferred":[
        "Nipane"
    ],
    "name:deu_x_preferred":[
        "Nipane"
    ],
    "wof:name":"Nipane",
    "wof:placetype":"locality"
},
  "geometry": {"coordinates":[86.54419,27.22895],"type":"Point"}
}