{
  "type": "Feature",
  "properties": {
    "gn:admin1_code":"FR",
    "gn:admin2_code":"14.0",
    "gn:admin3_code":"69.0",
    "gn:admin4_code":"690052.0",
    "gn:asciiname":"Gwalekot",
    "gn:country_code":"NP",
    "gn:dem":1513,
    "gn:feature_class":"P",
    "gn:feature_code":"PPLL",
    "gn:name":"Gwalekot",
    "gn:population":0,
    "gn:timezone":"Asia/Kathmandu",
    "iso:country":"NP",
    "wof:name":"Gwalekot",
    "wof:placetype":"locality"
},
  "geometry": {"coordinates":[81.28286,29.22284],"type":"Point"}
}