{
  "type": "Feature",
  "properties": {
    "gn:admin1_code":"FR",
    "gn:admin2_code":"14",
    "gn:admin3_code":"70.0",
    "gn:admin4_code":"700011.0",
    "gn:asciiname":"Daha",
    "gn:country_code":"NP",
    "gn:dem":1352,
    "gn:feature_class":"P",
    "gn:feature_code":"PPLL",
    "gn:name":"Daha",
    "gn:population":0,
    "gn:timezone":"Asia/Kathmandu",
    "iso:country":"NP",
    "wof:name":"Daha",
    "wof:placetype":"locality"
},
  "geometry": {"coordinates":[80.94065999999999,28.99216],"type":"Point"}
}