{
  "type": "Feature",
  "properties": {
    "gn:admin1_code":"00",
    "gn:asciiname":"Ghyandada",
    "gn:country_code":"NP",
    "gn:dem":1787,
    "gn:feature_class":"P",
    "gn:feature_code":"PPL",
    "gn:name":"Ghy\u0101\u1e45\u1e0d\u0101\u0303\u1e0d\u0101",
    "gn:population":0,
    "gn:timezone":"Asia/Kathmandu",
    "iso:country":"NP",
    "name:und_x_variant":[
        "Ghy\u0101\u1e45\u1e0d\u0101\u0303\u1e0d\u0101",
        "Ghy\u0101\u1e45\u1e0d\u0101n\u1e0d\u0101"
    ],
    "wof:name":"Ghyandada",
    "wof:placetype":"locality"
},
  "geometry": {"coordinates":[86.0508,27.47599],"type":"Point"}
}