{
  "type": "Feature",
  "properties": {
    "gn:admin1_code":"MR",
    "gn:admin2_code":"12",
    "gn:admin3_code":"52",
    "gn:admin4_code":"520047",
    "gn:asciiname":"Bista Tol",
    "gn:country_code":"NP",
    "gn:dem":1021,
    "gn:feature_class":"P",
    "gn:feature_code":"PPLL",
    "gn:name":"Bista Tol",
    "gn:population":0,
    "gn:timezone":"Asia/Kathmandu",
    "iso:country":"NP",
    "wof:name":"Bista Tol",
    "wof:placetype":"locality"
},
  "geometry": {"coordinates":[82.92395999999999,28.13684000000001],"type":"Point"}
}