{
  "type": "Feature",
  "properties": {
    "gn:admin1_code":"FR",
    "gn:admin2_code":"14.0",
    "gn:admin3_code":"67.0",
    "gn:admin4_code":"670003.0",
    "gn:asciiname":"Chhapu",
    "gn:country_code":"NP",
    "gn:dem":1235,
    "gn:feature_class":"P",
    "gn:feature_code":"PPLL",
    "gn:name":"Chhapu",
    "gn:population":0,
    "gn:timezone":"Asia/Kathmandu",
    "iso:country":"NP",
    "wof:name":"Chhapu",
    "wof:placetype":"locality"
},
  "geometry": {"coordinates":[81.71741,29.47045],"type":"Point"}
}