{
  "type": "Feature",
  "properties": {
    "gn:admin1_code":"ER",
    "gn:admin2_code":"13.0",
    "gn:admin3_code":"14.0",
    "gn:admin4_code":"140016.0",
    "gn:asciiname":"Habeli",
    "gn:country_code":"NP",
    "gn:dem":134,
    "gn:feature_class":"P",
    "gn:feature_code":"PPLL",
    "gn:name":"Habeli",
    "gn:population":0,
    "gn:timezone":"Asia/Kathmandu",
    "iso:country":"NP",
    "wof:name":"Habeli",
    "wof:placetype":"locality"
},
  "geometry": {"coordinates":[86.77070999999999,26.76786],"type":"Point"}
}