{
  "type": "Feature",
  "properties": {
    "gn:admin1_code":"CR",
    "gn:admin2_code":"5",
    "gn:admin3_code":"21",
    "gn:admin4_code":"210013",
    "gn:asciiname":"Mahatgaun",
    "gn:country_code":"NP",
    "gn:dem":1029,
    "gn:feature_class":"P",
    "gn:feature_code":"PPLL",
    "gn:name":"Mahatgaun",
    "gn:population":0,
    "gn:timezone":"Asia/Kathmandu",
    "iso:country":"NP",
    "wof:name":"Mahatgaun",
    "wof:placetype":"locality"
},
  "geometry": {"coordinates":[86.18798000000002,27.36077],"type":"Point"}
}