{
  "type": "Feature",
  "properties": {
    "gn:admin1_code":"WR",
    "gn:admin2_code":"8",
    "gn:admin3_code":"47",
    "gn:admin4_code":"470004",
    "gn:asciiname":"Kahule",
    "gn:country_code":"NP",
    "gn:dem":1009,
    "gn:feature_class":"P",
    "gn:feature_code":"PPLL",
    "gn:name":"Kahule",
    "gn:population":0,
    "gn:timezone":"Asia/Kathmandu",
    "iso:country":"NP",
    "wof:name":"Kahule",
    "wof:placetype":"locality"
},
  "geometry": {"coordinates":[83.313,27.79246],"type":"Point"}
}