{
  "type": "Feature",
  "properties": {
    "gn:admin1_code":"00",
    "gn:admin2_code":"9",
    "gn:admin3_code":"72.0",
    "gn:admin4_code":"720001.0",
    "gn:asciiname":"Pachkadiya",
    "gn:country_code":"NP",
    "gn:dem":165,
    "gn:feature_class":"P",
    "gn:feature_code":"PPL",
    "gn:name":"Pachka\u1e0diy\u0101",
    "gn:population":0,
    "gn:timezone":"Asia/Kathmandu",
    "iso:country":"NP",
    "name:nep_x_preferred":[
        "Pachka\u1e0diy\u0101"
    ],
    "name:und_x_variant":[
        "Pachkaria"
    ],
    "wof:name":"Pachkadiya",
    "wof:placetype":"locality"
},
  "geometry": {"coordinates":[80.50124,28.67882],"type":"Point"}
}