{
  "type": "Feature",
  "properties": {
    "gn:admin1_code":"ER",
    "gn:admin2_code":"7",
    "gn:admin3_code":"7.0",
    "gn:admin4_code":"70010.0",
    "gn:asciiname":"Beltar",
    "gn:country_code":"NP",
    "gn:dem":276,
    "gn:feature_class":"P",
    "gn:feature_code":"PPLL",
    "gn:name":"Beltar",
    "gn:population":0,
    "gn:timezone":"Asia/Kathmandu",
    "iso:country":"NP",
    "wof:name":"Beltar",
    "wof:placetype":"locality"
},
  "geometry": {"coordinates":[87.27812,27.15472],"type":"Point"}
}