{
  "type": "Feature",
  "properties": {
    "gn:admin1_code":"MR",
    "gn:admin2_code":"2.0",
    "gn:admin3_code":"59.0",
    "gn:admin4_code":"590005.0",
    "gn:asciiname":"Sugurbadhane",
    "gn:country_code":"NP",
    "gn:dem":1112,
    "gn:feature_class":"P",
    "gn:feature_code":"PPLL",
    "gn:name":"Sugurbadhane",
    "gn:population":0,
    "gn:timezone":"Asia/Kathmandu",
    "iso:country":"NP",
    "wof:name":"Sugurbadhane",
    "wof:placetype":"locality"
},
  "geometry": {"coordinates":[81.13706999999999,28.92339],"type":"Point"}
}