{
  "type": "Feature",
  "properties": {
    "gn:admin1_code":"FR",
    "gn:admin2_code":"14.0",
    "gn:admin3_code":"69.0",
    "gn:admin4_code":"690040.0",
    "gn:asciiname":"Shantikholagaun",
    "gn:country_code":"NP",
    "gn:dem":1867,
    "gn:feature_class":"P",
    "gn:feature_code":"PPLL",
    "gn:name":"Shantikholagaun",
    "gn:population":0,
    "gn:timezone":"Asia/Kathmandu",
    "iso:country":"NP",
    "wof:name":"Shantikholagaun",
    "wof:placetype":"locality"
},
  "geometry": {"coordinates":[81.35105,29.24692000000001],"type":"Point"}
}