{
  "type": "Feature",
  "properties": {
    "gn:admin1_code":"MR",
    "gn:admin2_code":"12",
    "gn:admin3_code":"53",
    "gn:admin4_code":"530036",
    "gn:asciiname":"Kuineta",
    "gn:country_code":"NP",
    "gn:dem":1813,
    "gn:feature_class":"P",
    "gn:feature_code":"PPLL",
    "gn:name":"Kuineta",
    "gn:population":0,
    "gn:timezone":"Asia/Kathmandu",
    "iso:country":"NP",
    "wof:name":"Kuineta",
    "wof:placetype":"locality"
},
  "geometry": {"coordinates":[82.41930000000001,28.47249],"type":"Point"}
}