{
  "type": "Feature",
  "properties": {
    "gn:admin1_code":"WR",
    "gn:admin2_code":"8",
    "gn:admin3_code":"49",
    "gn:admin4_code":"490004",
    "gn:asciiname":"Nidiahawa",
    "gn:country_code":"NP",
    "gn:dem":93,
    "gn:feature_class":"P",
    "gn:feature_code":"PPLL",
    "gn:name":"Nidiahawa",
    "gn:population":0,
    "gn:timezone":"Asia/Kathmandu",
    "iso:country":"NP",
    "wof:name":"Nidiahawa",
    "wof:placetype":"locality"
},
  "geometry": {"coordinates":[83.33175,27.39061],"type":"Point"}
}