{
  "type": "Feature",
  "properties": {
    "gn:admin1_code":"ER",
    "gn:admin2_code":"7",
    "gn:admin3_code":"5",
    "gn:admin4_code":"50053",
    "gn:asciiname":"Jorpainibandh",
    "gn:country_code":"NP",
    "gn:dem":80,
    "gn:feature_class":"P",
    "gn:feature_code":"PPLL",
    "gn:name":"Jorpainibandh",
    "gn:population":0,
    "gn:timezone":"Asia/Kathmandu",
    "iso:country":"NP",
    "wof:name":"Jorpainibandh",
    "wof:placetype":"locality"
},
  "geometry": {"coordinates":[87.60458,26.48525],"type":"Point"}
}