{
  "type": "Feature",
  "properties": {
    "gn:admin1_code":"MR",
    "gn:admin2_code":"2",
    "gn:admin3_code":"61.0",
    "gn:admin4_code":"610028.0",
    "gn:asciiname":"Abgan",
    "gn:country_code":"NP",
    "gn:dem":1295,
    "gn:feature_class":"P",
    "gn:feature_code":"PPLL",
    "gn:name":"Abgan",
    "gn:population":0,
    "gn:timezone":"Asia/Kathmandu",
    "iso:country":"NP",
    "wof:name":"Abgan",
    "wof:placetype":"locality"
},
  "geometry": {"coordinates":[82.00478000000003,28.77965],"type":"Point"}
}