{
  "type": "Feature",
  "properties": {
    "gn:admin1_code":"CR",
    "gn:admin2_code":"1",
    "gn:admin3_code":"23",
    "gn:admin4_code":"230062",
    "gn:asciiname":"Kathar Bagar",
    "gn:country_code":"NP",
    "gn:dem":1214,
    "gn:feature_class":"P",
    "gn:feature_code":"PPLL",
    "gn:name":"Kathar Bagar",
    "gn:population":0,
    "gn:timezone":"Asia/Kathmandu",
    "iso:country":"NP",
    "wof:name":"Kathar Bagar",
    "wof:placetype":"locality"
},
  "geometry": {"coordinates":[85.52313000000002,27.81082],"type":"Point"}
}