{
  "type": "Feature",
  "properties": {
    "gn:admin1_code":"WR",
    "gn:admin2_code":"3",
    "gn:admin3_code":"45.0",
    "gn:admin4_code":"450029.0",
    "gn:asciiname":"Kaphalthuta",
    "gn:country_code":"NP",
    "gn:dem":1613,
    "gn:feature_class":"P",
    "gn:feature_code":"PPLL",
    "gn:name":"Kaphalthuta",
    "gn:population":0,
    "gn:timezone":"Asia/Kathmandu",
    "iso:country":"NP",
    "wof:name":"Kaphalthuta",
    "wof:placetype":"locality"
},
  "geometry": {"coordinates":[83.49134000000002,28.12573],"type":"Point"}
}