{
  "type": "Feature",
  "properties": {
    "gn:admin1_code":"CR",
    "gn:admin2_code":"11.0",
    "gn:admin3_code":"33.0",
    "gn:admin4_code":"330039.0",
    "gn:asciiname":"Nayan Basti",
    "gn:country_code":"NP",
    "gn:dem":116,
    "gn:feature_class":"P",
    "gn:feature_code":"PPLL",
    "gn:name":"Nayan Basti",
    "gn:population":0,
    "gn:timezone":"Asia/Kathmandu",
    "iso:country":"NP",
    "wof:name":"Nayan Basti",
    "wof:placetype":"locality"
},
  "geometry": {"coordinates":[85.09035,27.0867],"type":"Point"}
}