{
  "type": "Feature",
  "properties": {
    "gn:admin1_code":"WR",
    "gn:admin2_code":"4",
    "gn:admin3_code":"37",
    "gn:admin4_code":"370049",
    "gn:asciiname":"Sangkarekuna",
    "gn:country_code":"NP",
    "gn:dem":522,
    "gn:feature_class":"P",
    "gn:feature_code":"PPLL",
    "gn:name":"Sangkarekuna",
    "gn:population":0,
    "gn:timezone":"Asia/Kathmandu",
    "iso:country":"NP",
    "wof:name":"Sangkarekuna",
    "wof:placetype":"locality"
},
  "geometry": {"coordinates":[84.23863,28.09336],"type":"Point"}
}