{
  "type": "Feature",
  "properties": {
    "gn:admin1_code":"CR",
    "gn:admin2_code":"11",
    "gn:admin3_code":"35.0",
    "gn:admin4_code":"350018.0",
    "gn:asciiname":"Chipleti",
    "gn:country_code":"NP",
    "gn:dem":742,
    "gn:feature_class":"P",
    "gn:feature_code":"PPLL",
    "gn:name":"Chipleti",
    "gn:population":0,
    "gn:timezone":"Asia/Kathmandu",
    "iso:country":"NP",
    "wof:name":"Chipleti",
    "wof:placetype":"locality"
},
  "geometry": {"coordinates":[84.46863,27.80826],"type":"Point"}
}