{
  "type": "Feature",
  "properties": {
    "gn:admin1_code":"ER",
    "gn:admin2_code":"13.0",
    "gn:admin3_code":"14.0",
    "gn:admin4_code":"140017.0",
    "gn:asciiname":"Jahadi",
    "gn:country_code":"NP",
    "gn:dem":227,
    "gn:feature_class":"P",
    "gn:feature_code":"PPLL",
    "gn:name":"Jahadi",
    "gn:population":0,
    "gn:timezone":"Asia/Kathmandu",
    "iso:country":"NP",
    "name:ceb_x_preferred":[
        "Jahadi"
    ],
    "name:msa_x_preferred":[
        "Jahadi"
    ],
    "name:nep_x_preferred":[
        "\u091c\u0939\u0926\u0940"
    ],
    "name:new_x_preferred":[
        "\u091c\u0939\u0926\u0940"
    ],
    "name:pol_x_preferred":[
        "Jahadi"
    ],
    "name:urd_x_preferred":[
        "\u062c\u06c1\u0627\u062f\u06cc"
    ],
    "wof:name":"Jahadi",
    "wof:placetype":"locality"
},
  "geometry": {"coordinates":[86.37850999999998,26.97053],"type":"Point"}
}