{
  "type": "Feature",
  "properties": {
    "gn:admin1_code":"WR",
    "gn:admin2_code":"4",
    "gn:admin3_code":"36.0",
    "gn:admin4_code":"360047.0",
    "gn:asciiname":"Bohoragaun",
    "gn:country_code":"NP",
    "gn:dem":1039,
    "gn:feature_class":"P",
    "gn:feature_code":"PPLL",
    "gn:name":"Bohoragaun",
    "gn:population":0,
    "gn:timezone":"Asia/Kathmandu",
    "iso:country":"NP",
    "wof:name":"Bohoragaun",
    "wof:placetype":"locality"
},
  "geometry": {"coordinates":[84.51912,28.05317],"type":"Point"}
}