{
  "type": "Feature",
  "properties": {
    "gn:admin1_code":"CR",
    "gn:admin2_code":"1",
    "gn:admin3_code":"27.0",
    "gn:admin4_code":"270035.0",
    "gn:asciiname":"Thapagaun",
    "gn:country_code":"NP",
    "gn:dem":1449,
    "gn:feature_class":"P",
    "gn:feature_code":"PPLL",
    "gn:name":"Thapagaun",
    "gn:population":0,
    "gn:timezone":"Asia/Kathmandu",
    "iso:country":"NP",
    "wof:name":"Thapagaun",
    "wof:placetype":"locality"
},
  "geometry": {"coordinates":[85.25163000000001,27.66647],"type":"Point"}
}