{
  "type": "Feature",
  "properties": {
    "gn:admin1_code":"FR",
    "gn:admin2_code":"9",
    "gn:admin3_code":"73.0",
    "gn:admin4_code":"730021.0",
    "gn:asciiname":"Umlekgaun",
    "gn:country_code":"NP",
    "gn:dem":1202,
    "gn:feature_class":"P",
    "gn:feature_code":"PPLL",
    "gn:name":"Umlekgaun",
    "gn:population":0,
    "gn:timezone":"Asia/Kathmandu",
    "iso:country":"NP",
    "wof:name":"Umlekgaun",
    "wof:placetype":"locality"
},
  "geometry": {"coordinates":[80.39372,29.18337],"type":"Point"}
}