{
  "type": "Feature",
  "properties": {
    "gn:admin1_code":"ER",
    "gn:admin2_code":"13",
    "gn:admin3_code":"11",
    "gn:admin4_code":"110013",
    "gn:asciiname":"Walabura",
    "gn:country_code":"NP",
    "gn:dem":1750,
    "gn:feature_class":"P",
    "gn:feature_code":"PPLL",
    "gn:name":"Walabura",
    "gn:population":0,
    "gn:timezone":"Asia/Kathmandu",
    "iso:country":"NP",
    "wof:name":"Walabura",
    "wof:placetype":"locality"
},
  "geometry": {"coordinates":[86.81005999999999,27.48128],"type":"Point"}
}