{
  "type": "Feature",
  "properties": {
    "gn:admin1_code":"FR",
    "gn:admin2_code":"14.0",
    "gn:admin3_code":"67.0",
    "gn:admin4_code":"670004.0",
    "gn:asciiname":"Juwapani",
    "gn:country_code":"NP",
    "gn:dem":1827,
    "gn:feature_class":"P",
    "gn:feature_code":"PPLL",
    "gn:name":"Juwapani",
    "gn:population":0,
    "gn:timezone":"Asia/Kathmandu",
    "iso:country":"NP",
    "wof:name":"Juwapani",
    "wof:placetype":"locality"
},
  "geometry": {"coordinates":[81.28364000000001,29.34988],"type":"Point"}
}