{
  "type": "Feature",
  "properties": {
    "gn:admin1_code":"ER",
    "gn:admin2_code":"10",
    "gn:admin3_code":"4.0",
    "gn:admin4_code":"40041.0",
    "gn:asciiname":"Gaurishankar",
    "gn:country_code":"NP",
    "gn:dem":102,
    "gn:feature_class":"P",
    "gn:feature_code":"PPLL",
    "gn:name":"Gaurishankar",
    "gn:population":0,
    "gn:timezone":"Asia/Kathmandu",
    "iso:country":"NP",
    "name:ben_x_preferred":[
        "\u0997\u09cc\u09b0\u09c0\u09b6\u0999\u09cd\u0995\u09b0"
    ],
    "name:ceb_x_preferred":[
        "Gauri Sankar"
    ],
    "name:ces_x_preferred":[
        "Gaur\u00ed\u0161ankar"
    ],
    "name:deu_x_preferred":[
        "Gauri Sankar"
    ],
    "name:dty_x_preferred":[
        "\u0917\u094c\u0930\u0940\u0936\u0902\u0915\u0930 \u0939\u093f\u092e\u093e\u0932"
    ],
    "name:fra_x_preferred":[
        "Gauri Sankar"
    ],
    "name:hin_x_preferred":[
        "\u0917\u094c\u0930\u0940\u0936\u0902\u0915\u0930"
    ],
    "name:hun_x_preferred":[
        "Gaurisankar"
    ],
    "name:hye_x_preferred":[
        "\u0533\u0561\u0580\u0578\u0582\u0580\u056b \u0547\u0561\u0576\u056f\u0561\u0580"
    ],
    "name:ita_x_preferred":[
        "Gauri Sankar"
    ],
    "name:lit_x_preferred":[
        "Gauri\u0161ankaras"
    ],
    "name:mai_x_preferred":[
        "\u0917\u094c\u0930\u0940\u0936\u0902\u0915\u0930 \u0939\u093f\u092e\u093e\u0932"
    ],
    "name:msa_x_preferred":[
        "Gauri Sankar"
    ],
    "name:nep_x_preferred":[
        "\u0917\u094c\u0930\u0940\u0936\u0902\u0915\u0930 \u0939\u093f\u092e\u093e\u0932"
    ],
    "name:new_x_preferred":[
        "\u0917\u094c\u0930\u0940 \u0936\u0902\u0915\u0930"
    ],
    "name:nld_x_preferred":[
        "Gauri Shankar"
    ],
    "name:pol_x_preferred":[
        "Gauri Sankar"
    ],
    "name:ron_x_preferred":[
        "Gauri Sankar"
    ],
    "name:rus_x_preferred":[
        "\u0413\u0430\u0443\u0440\u0438\u0448\u0430\u043d\u043a\u0430\u0440"
    ],
    "name:swe_x_preferred":[
        "Gauri Sankar"
    ],
    "name:ukr_x_preferred":[
        "\u0413\u0430\u0443\u0440\u0438\u0448\u0430\u043d\u043a\u0430\u0440"
    ],
    "name:zho_x_preferred":[
        "\u9ad8\u91cc\u4e09\u5580\u5cf0"
    ],
    "wof:name":"Gaurishankar",
    "wof:placetype":"locality"
},
  "geometry": {"coordinates":[88.0621,26.49315],"type":"Point"}
}