{
  "type": "Feature",
  "properties": {
    "gn:admin1_code":"ER",
    "gn:admin2_code":"7",
    "gn:admin3_code":"10.0",
    "gn:admin4_code":"100025.0",
    "gn:asciiname":"Chapleti",
    "gn:country_code":"NP",
    "gn:dem":1818,
    "gn:feature_class":"P",
    "gn:feature_code":"PPLL",
    "gn:name":"Chapleti",
    "gn:population":0,
    "gn:timezone":"Asia/Kathmandu",
    "iso:country":"NP",
    "wof:name":"Chapleti",
    "wof:placetype":"locality"
},
  "geometry": {"coordinates":[87.00501,27.22171],"type":"Point"}
}