{
  "type": "Feature",
  "properties": {
    "gn:admin1_code":"WR",
    "gn:admin2_code":"4.0",
    "gn:admin3_code":"39.0",
    "gn:admin4_code":"390011.0",
    "gn:asciiname":"Marenda",
    "gn:country_code":"NP",
    "gn:dem":788,
    "gn:feature_class":"P",
    "gn:feature_code":"PPLL",
    "gn:name":"Marenda",
    "gn:population":0,
    "gn:timezone":"Asia/Kathmandu",
    "iso:country":"NP",
    "wof:name":"Marenda",
    "wof:placetype":"locality"
},
  "geometry": {"coordinates":[83.54649000000001,27.96026],"type":"Point"}
}