{
  "type": "Feature",
  "properties": {
    "gn:admin1_code":"ER",
    "gn:admin2_code":"13",
    "gn:admin3_code":"11",
    "gn:admin4_code":"110030",
    "gn:asciiname":"Bhitte",
    "gn:country_code":"NP",
    "gn:dem":1039,
    "gn:feature_class":"P",
    "gn:feature_code":"PPLL",
    "gn:name":"Bhitte",
    "gn:population":0,
    "gn:timezone":"Asia/Kathmandu",
    "iso:country":"NP",
    "wof:name":"Bhitte",
    "wof:placetype":"locality"
},
  "geometry": {"coordinates":[86.63981,27.37371],"type":"Point"}
}