{
  "type": "Feature",
  "properties": {
    "gn:admin1_code":"WR",
    "gn:admin2_code":"4.0",
    "gn:admin3_code":"38.0",
    "gn:admin4_code":"380004.0",
    "gn:asciiname":"Ranipani Pauwa",
    "gn:country_code":"NP",
    "gn:dem":882,
    "gn:feature_class":"P",
    "gn:feature_code":"PPLL",
    "gn:name":"Ranipani Pauwa",
    "gn:population":0,
    "gn:timezone":"Asia/Kathmandu",
    "iso:country":"NP",
    "wof:name":"Ranipani Pauwa",
    "wof:placetype":"locality"
},
  "geometry": {"coordinates":[84.40159,27.9319],"type":"Point"}
}