{
  "type": "Feature",
  "properties": {
    "gn:admin1_code":"CR",
    "gn:admin2_code":"1",
    "gn:admin3_code":"24.0",
    "gn:admin4_code":"240060.0",
    "gn:asciiname":"Boran",
    "gn:country_code":"NP",
    "gn:dem":433,
    "gn:feature_class":"P",
    "gn:feature_code":"PPLL",
    "gn:name":"Boran",
    "gn:population":0,
    "gn:timezone":"Asia/Kathmandu",
    "iso:country":"NP",
    "wof:name":"Boran",
    "wof:placetype":"locality"
},
  "geometry": {"coordinates":[85.43026999999999,27.41184],"type":"Point"}
}