{
  "type": "Feature",
  "properties": {
    "gn:admin1_code":"WR",
    "gn:admin2_code":"8",
    "gn:admin3_code":"50.0",
    "gn:admin4_code":"500072.0",
    "gn:asciiname":"Sisawa",
    "gn:country_code":"NP",
    "gn:dem":102,
    "gn:feature_class":"P",
    "gn:feature_code":"PPLL",
    "gn:name":"Sisawa",
    "gn:population":0,
    "gn:timezone":"Asia/Kathmandu",
    "iso:country":"NP",
    "name:ceb_x_preferred":[
        "Sisawa"
    ],
    "name:hin_x_preferred":[
        "\u0938\u093f\u0938\u0935\u093e"
    ],
    "name:msa_x_preferred":[
        "Sisawa"
    ],
    "name:new_x_preferred":[
        "\u0938\u093f\u0938\u0935\u093e"
    ],
    "name:pol_x_preferred":[
        "Sisawa"
    ],
    "wof:name":"Sisawa",
    "wof:placetype":"locality"
},
  "geometry": {"coordinates":[82.94228000000003,27.52705],"type":"Point"}
}