{
  "type": "Feature",
  "properties": {
    "gn:admin1_code":"MR",
    "gn:admin2_code":"2.0",
    "gn:admin3_code":"59.0",
    "gn:admin4_code":"590021.0",
    "gn:asciiname":"Saune",
    "gn:country_code":"NP",
    "gn:dem":544,
    "gn:feature_class":"P",
    "gn:feature_code":"PPLL",
    "gn:name":"Saune",
    "gn:population":0,
    "gn:timezone":"Asia/Kathmandu",
    "iso:country":"NP",
    "name:bih_x_preferred":[
        "\u0938\u093e\u0909\u0928\u0947"
    ],
    "name:ceb_x_preferred":[
        "Saune"
    ],
    "name:ita_x_preferred":[
        "Saune"
    ],
    "name:mai_x_preferred":[
        "\u0938\u093e\u0909\u0928\u0947"
    ],
    "name:msa_x_preferred":[
        "Saune"
    ],
    "name:nep_x_preferred":[
        "\u0938\u093e\u0909\u0928\u0947"
    ],
    "name:new_x_preferred":[
        "\u0938\u093e\u0909\u0928\u0947"
    ],
    "name:pol_x_preferred":[
        "Saune"
    ],
    "wof:name":"Saune",
    "wof:placetype":"locality"
},
  "geometry": {"coordinates":[81.29589,28.85835],"type":"Point"}
}