{
  "type": "Feature",
  "properties": {
    "gn:admin1_code":"MR",
    "gn:admin2_code":"2.0",
    "gn:admin3_code":"59.0",
    "gn:admin4_code":"590021.0",
    "gn:asciiname":"Saune",
    "gn:country_code":"NP",
    "gn:dem":544,
    "gn:feature_class":"P",
    "gn:feature_code":"PPLL",
    "gn:name":"Saune",
    "gn:population":0,
    "gn:timezone":"Asia/Kathmandu",
    "iso:country":"NP",
    "wof:name":"Saune",
    "wof:placetype":"locality"
},
  "geometry": {"coordinates":[81.29589,28.85835],"type":"Point"}
}