{
  "type": "Feature",
  "properties": {
    "gn:admin1_code":"FR",
    "gn:admin2_code":"14.0",
    "gn:admin3_code":"69.0",
    "gn:admin4_code":"690053.0",
    "gn:asciiname":"Khokela",
    "gn:country_code":"NP",
    "gn:dem":684,
    "gn:feature_class":"P",
    "gn:feature_code":"PPLL",
    "gn:name":"Khokela",
    "gn:population":0,
    "gn:timezone":"Asia/Kathmandu",
    "iso:country":"NP",
    "wof:name":"Khokela",
    "wof:placetype":"locality"
},
  "geometry": {"coordinates":[81.23035,29.23203],"type":"Point"}
}