{
  "type": "Feature",
  "properties": {
    "gn:admin1_code":"WR",
    "gn:admin2_code":"4.0",
    "gn:admin3_code":"38.0",
    "gn:admin4_code":"380013.0",
    "gn:asciiname":"Barlunghol",
    "gn:country_code":"NP",
    "gn:dem":692,
    "gn:feature_class":"P",
    "gn:feature_code":"PPLL",
    "gn:name":"Barlunghol",
    "gn:population":0,
    "gn:timezone":"Asia/Kathmandu",
    "iso:country":"NP",
    "wof:name":"Barlunghol",
    "wof:placetype":"locality"
},
  "geometry": {"coordinates":[84.50941999999998,27.83575],"type":"Point"}
}