{
  "type": "Feature",
  "properties": {
    "gn:admin1_code":"00",
    "gn:asciiname":"Phalate",
    "gn:country_code":"NP",
    "gn:dem":2195,
    "gn:feature_class":"P",
    "gn:feature_code":"PPL",
    "gn:name":"Phal\u0101\u0303\u1e6de",
    "gn:population":0,
    "gn:timezone":"Asia/Kathmandu",
    "iso:country":"NP",
    "wof:name":"Phalate",
    "wof:placetype":"locality"
},
  "geometry": {"coordinates":[86.78171,27.2792],"type":"Point"}
}