{
  "type": "Feature",
  "properties": {
    "gn:admin1_code":"00",
    "gn:asciiname":"Phalate",
    "gn:country_code":"NP",
    "gn:dem":2195,
    "gn:feature_class":"P",
    "gn:feature_code":"PPL",
    "gn:name":"Phal\u0101\u0303\u1e6de",
    "gn:population":0,
    "gn:timezone":"Asia/Kathmandu",
    "iso:country":"NP",
    "name:bih_x_preferred":[
        "\u092b\u0932\u093e\u0901\u091f\u0947"
    ],
    "name:nep_x_preferred":[
        "\u092b\u0932\u093e\u0901\u091f\u0947"
    ],
    "name:new_x_preferred":[
        "\u092b\u0932\u093e\u0924\u0947"
    ],
    "name:pol_x_preferred":[
        "Falate"
    ],
    "name:urd_x_preferred":[
        "\u0641\u0627\u0644\u0627\u0679\u06cc"
    ],
    "wof:name":"Phalate",
    "wof:placetype":"locality"
},
  "geometry": {"coordinates":[86.78171,27.2792],"type":"Point"}
}