{
  "type": "Feature",
  "properties": {
    "gn:admin1_code":"MR",
    "gn:admin2_code":"12",
    "gn:admin3_code":"55",
    "gn:admin4_code":"550036",
    "gn:asciiname":"Birkhe",
    "gn:country_code":"NP",
    "gn:dem":1467,
    "gn:feature_class":"P",
    "gn:feature_code":"PPLL",
    "gn:name":"Birkhe",
    "gn:population":0,
    "gn:timezone":"Asia/Kathmandu",
    "iso:country":"NP",
    "wof:name":"Birkhe",
    "wof:placetype":"locality"
},
  "geometry": {"coordinates":[82.24911999999998,28.24979],"type":"Point"}
}