{
  "type": "Feature",
  "properties": {
    "gn:admin1_code":"FR",
    "gn:admin2_code":"9",
    "gn:admin3_code":"74",
    "gn:admin4_code":"740004",
    "gn:asciiname":"Thulagada",
    "gn:country_code":"NP",
    "gn:dem":2210,
    "gn:feature_class":"P",
    "gn:feature_code":"PPLL",
    "gn:name":"Thulagada",
    "gn:population":0,
    "gn:timezone":"Asia/Kathmandu",
    "iso:country":"NP",
    "wof:name":"Thulagada",
    "wof:placetype":"locality"
},
  "geometry": {"coordinates":[80.77633,29.61394],"type":"Point"}
}