{
  "type": "Feature",
  "properties": {
    "gn:admin1_code":"ER",
    "gn:admin2_code":"13",
    "gn:admin3_code":"15",
    "gn:admin4_code":"150080",
    "gn:asciiname":"Bhajaka Puranotol",
    "gn:country_code":"NP",
    "gn:dem":102,
    "gn:feature_class":"P",
    "gn:feature_code":"PPLL",
    "gn:name":"Bhajaka Puranotol",
    "gn:population":0,
    "gn:timezone":"Asia/Kathmandu",
    "iso:country":"NP",
    "wof:name":"Bhajaka Puranotol",
    "wof:placetype":"locality"
},
  "geometry": {"coordinates":[86.54128,26.64326],"type":"Point"}
}