{
  "type": "Feature",
  "properties": {
    "gn:admin1_code":"ER",
    "gn:admin2_code":"7",
    "gn:admin3_code":"7.0",
    "gn:admin4_code":"70027.0",
    "gn:asciiname":"Batase",
    "gn:country_code":"NP",
    "gn:dem":914,
    "gn:feature_class":"P",
    "gn:feature_code":"PPLL",
    "gn:name":"Batase",
    "gn:population":0,
    "gn:timezone":"Asia/Kathmandu",
    "iso:country":"NP",
    "wof:name":"Batase",
    "wof:placetype":"locality"
},
  "geometry": {"coordinates":[87.51846,26.92553],"type":"Point"}
}