{
  "type": "Feature",
  "properties": {
    "gn:admin1_code":"FR",
    "gn:admin2_code":"14.0",
    "gn:admin3_code":"67.0",
    "gn:admin4_code":"670005.0",
    "gn:asciiname":"Tharagikharka",
    "gn:country_code":"NP",
    "gn:dem":3670,
    "gn:feature_class":"P",
    "gn:feature_code":"PPLL",
    "gn:name":"Tharagikharka",
    "gn:population":0,
    "gn:timezone":"Asia/Kathmandu",
    "iso:country":"NP",
    "wof:name":"Tharagikharka",
    "wof:placetype":"locality"
},
  "geometry": {"coordinates":[81.6332,29.8974],"type":"Point"}
}