{
  "type": "Feature",
  "properties": {
    "gn:admin1_code":"WR",
    "gn:admin2_code":"4",
    "gn:admin3_code":"40.0",
    "gn:admin4_code":"400033.0",
    "gn:asciiname":"Badahare",
    "gn:country_code":"NP",
    "gn:dem":856,
    "gn:feature_class":"P",
    "gn:feature_code":"PPLL",
    "gn:name":"Badahare",
    "gn:population":0,
    "gn:timezone":"Asia/Kathmandu",
    "iso:country":"NP",
    "name:bih_x_preferred":[
        "\u092c\u0921\u0939\u0930\u0947"
    ],
    "name:ceb_x_preferred":[
        "Badahare"
    ],
    "name:mai_x_preferred":[
        "\u092c\u0921\u0939\u0930\u0947"
    ],
    "name:msa_x_preferred":[
        "Badahare"
    ],
    "name:nep_x_preferred":[
        "\u092c\u0921\u0939\u0930\u0947"
    ],
    "name:new_x_preferred":[
        "\u092c\u0921\u093e\u0939\u0930\u0947"
    ],
    "name:pol_x_preferred":[
        "Badahare"
    ],
    "wof:name":"Badahare",
    "wof:placetype":"locality"
},
  "geometry": {"coordinates":[83.91882,28.1819],"type":"Point"}
}