{
  "type": "Feature",
  "properties": {
    "gn:admin1_code":"FR",
    "gn:admin2_code":"9",
    "gn:admin3_code":"74",
    "gn:admin4_code":"740041",
    "gn:asciiname":"Dhamichaur",
    "gn:country_code":"NP",
    "gn:dem":2252,
    "gn:feature_class":"P",
    "gn:feature_code":"PPLL",
    "gn:name":"Dhamichaur",
    "gn:population":0,
    "gn:timezone":"Asia/Kathmandu",
    "iso:country":"NP",
    "wof:name":"Dhamichaur",
    "wof:placetype":"locality"
},
  "geometry": {"coordinates":[80.71214000000001,29.64579],"type":"Point"}
}