{
  "type": "Feature",
  "properties": {
    "gn:admin1_code":"FR",
    "gn:admin2_code":"14.0",
    "gn:admin3_code":"69.0",
    "gn:admin4_code":"690049.0",
    "gn:asciiname":"Relti",
    "gn:country_code":"NP",
    "gn:dem":1744,
    "gn:feature_class":"P",
    "gn:feature_code":"PPLL",
    "gn:name":"Relti",
    "gn:population":0,
    "gn:timezone":"Asia/Kathmandu",
    "iso:country":"NP",
    "wof:name":"Relti",
    "wof:placetype":"locality"
},
  "geometry": {"coordinates":[81.33183000000002,29.03911],"type":"Point"}
}