{
  "type": "Feature",
  "properties": {
    "gn:admin1_code":"CR",
    "gn:admin2_code":"1",
    "gn:admin3_code":"28",
    "gn:admin4_code":"280027",
    "gn:asciiname":"Bhetwalthok",
    "gn:country_code":"NP",
    "gn:dem":1024,
    "gn:feature_class":"P",
    "gn:feature_code":"PPLL",
    "gn:name":"Bhetwalthok",
    "gn:population":0,
    "gn:timezone":"Asia/Kathmandu",
    "iso:country":"NP",
    "wof:name":"Bhetwalthok",
    "wof:placetype":"locality"
},
  "geometry": {"coordinates":[85.27334999999999,27.839],"type":"Point"}
}