{
  "type": "Feature",
  "properties": {
    "gn:admin1_code":"WR",
    "gn:admin2_code":"3",
    "gn:admin3_code":"45.0",
    "gn:admin4_code":"450056.0",
    "gn:asciiname":"Lamdanda Kharka",
    "gn:country_code":"NP",
    "gn:dem":2746,
    "gn:feature_class":"P",
    "gn:feature_code":"PPLL",
    "gn:name":"Lamdanda Kharka",
    "gn:population":0,
    "gn:timezone":"Asia/Kathmandu",
    "iso:country":"NP",
    "wof:name":"Lamdanda Kharka",
    "wof:placetype":"locality"
},
  "geometry": {"coordinates":[83.19683000000001,28.44228],"type":"Point"}
}