{
  "type": "Feature",
  "properties": {
    "gn:admin1_code":"WR",
    "gn:admin2_code":"8",
    "gn:admin3_code":"47",
    "gn:admin4_code":"470001",
    "gn:asciiname":"Rannguwa",
    "gn:country_code":"NP",
    "gn:dem":951,
    "gn:feature_class":"P",
    "gn:feature_code":"PPLL",
    "gn:name":"Rannguwa",
    "gn:population":0,
    "gn:timezone":"Asia/Kathmandu",
    "iso:country":"NP",
    "wof:name":"Rannguwa",
    "wof:placetype":"locality"
},
  "geometry": {"coordinates":[83.86202,27.7667],"type":"Point"}
}