{
  "type": "Feature",
  "properties": {
    "gn:admin1_code":"WR",
    "gn:admin2_code":"8",
    "gn:admin3_code":"50.0",
    "gn:admin4_code":"500048.0",
    "gn:asciiname":"Pachakaiya",
    "gn:country_code":"NP",
    "gn:dem":129,
    "gn:feature_class":"P",
    "gn:feature_code":"PPLL",
    "gn:name":"Pachakaiya",
    "gn:population":0,
    "gn:timezone":"Asia/Kathmandu",
    "iso:country":"NP",
    "wof:name":"Pachakaiya",
    "wof:placetype":"locality"
},
  "geometry": {"coordinates":[83.0371,27.6901],"type":"Point"}
}