{
  "type": "Feature",
  "properties": {
    "gn:admin1_code":"WR",
    "gn:admin2_code":"4",
    "gn:admin3_code":"40.0",
    "gn:admin4_code":"400044.0",
    "gn:asciiname":"Deupurbesi",
    "gn:country_code":"NP",
    "gn:dem":513,
    "gn:feature_class":"P",
    "gn:feature_code":"PPLL",
    "gn:name":"Deupurbesi",
    "gn:population":0,
    "gn:timezone":"Asia/Kathmandu",
    "iso:country":"NP",
    "wof:name":"Deupurbesi",
    "wof:placetype":"locality"
},
  "geometry": {"coordinates":[84.20753000000001,28.13106],"type":"Point"}
}