{
  "type": "Feature",
  "properties": {
    "gn:admin1_code":"CR",
    "gn:admin2_code":"5",
    "gn:admin3_code":"19",
    "gn:admin4_code":"190014",
    "gn:asciiname":"Bhelahi",
    "gn:country_code":"NP",
    "gn:dem":88,
    "gn:feature_class":"P",
    "gn:feature_code":"PPLL",
    "gn:name":"Bhelahi",
    "gn:population":0,
    "gn:timezone":"Asia/Kathmandu",
    "iso:country":"NP",
    "wof:name":"Bhelahi",
    "wof:placetype":"locality"
},
  "geometry": {"coordinates":[85.59236,26.87449],"type":"Point"}
}