{
  "type": "Feature",
  "properties": {
    "gn:admin1_code":"00",
    "gn:asciiname":"Gauthale",
    "gn:country_code":"NP",
    "gn:dem":1770,
    "gn:feature_class":"P",
    "gn:feature_code":"PPL",
    "gn:name":"Gauthale",
    "gn:population":0,
    "gn:timezone":"Asia/Kathmandu",
    "iso:country":"NP",
    "wof:name":"Gauthale",
    "wof:placetype":"locality"
},
  "geometry": {"coordinates":[86.18978,27.57601],"type":"Point"}
}