{
  "type": "Feature",
  "properties": {
    "gn:admin1_code":"WR",
    "gn:admin2_code":"8",
    "gn:admin3_code":"47",
    "gn:admin4_code":"470062",
    "gn:asciiname":"Basantapur",
    "gn:country_code":"NP",
    "gn:dem":1464,
    "gn:feature_class":"P",
    "gn:feature_code":"PPLL",
    "gn:name":"Basantapur",
    "gn:population":0,
    "gn:timezone":"Asia/Kathmandu",
    "iso:country":"NP",
    "name:fra_x_preferred":[
        "Basantapur"
    ],
    "name:pol_x_preferred":[
        "Basantapur"
    ],
    "wof:name":"Basantapur",
    "wof:placetype":"locality"
},
  "geometry": {"coordinates":[83.54229000000002,27.87255],"type":"Point"}
}