{
  "type": "Feature",
  "properties": {
    "gn:admin1_code":"WR",
    "gn:admin2_code":"4",
    "gn:admin3_code":"41",
    "gn:admin4_code":"410004",
    "gn:asciiname":"Sahasar",
    "gn:country_code":"NP",
    "gn:dem":5857,
    "gn:feature_class":"P",
    "gn:feature_code":"PPLL",
    "gn:name":"Sahasar",
    "gn:population":0,
    "gn:timezone":"Asia/Kathmandu",
    "iso:country":"NP",
    "wof:name":"Sahasar",
    "wof:placetype":"locality"
},
  "geometry": {"coordinates":[84.20766999999999,28.85826],"type":"Point"}
}