{
  "type": "Feature",
  "properties": {
    "gn:admin1_code":"WR",
    "gn:admin2_code":"3",
    "gn:admin3_code":"45.0",
    "gn:admin4_code":"450050.0",
    "gn:asciiname":"Manewapata",
    "gn:country_code":"NP",
    "gn:dem":1071,
    "gn:feature_class":"P",
    "gn:feature_code":"PPLL",
    "gn:name":"Manewapata",
    "gn:population":0,
    "gn:timezone":"Asia/Kathmandu",
    "iso:country":"NP",
    "wof:name":"Manewapata",
    "wof:placetype":"locality"
},
  "geometry": {"coordinates":[83.32143000000001,28.19293],"type":"Point"}
}