{
  "type": "Feature",
  "properties": {
    "gn:admin1_code":"FR",
    "gn:admin2_code":"14",
    "gn:admin3_code":"68",
    "gn:admin4_code":"680039",
    "gn:asciiname":"Ratapani",
    "gn:country_code":"NP",
    "gn:dem":1009,
    "gn:feature_class":"P",
    "gn:feature_code":"PPLL",
    "gn:name":"Ratapani",
    "gn:population":0,
    "gn:timezone":"Asia/Kathmandu",
    "iso:country":"NP",
    "wof:name":"Ratapani",
    "wof:placetype":"locality"
},
  "geometry": {"coordinates":[80.90835,29.45843],"type":"Point"}
}