{
  "type": "Feature",
  "properties": {
    "gn:admin1_code":"WR",
    "gn:admin2_code":"8",
    "gn:admin3_code":"51.0",
    "gn:admin4_code":"510017.0",
    "gn:asciiname":"Haldi",
    "gn:country_code":"NP",
    "gn:dem":1502,
    "gn:feature_class":"P",
    "gn:feature_code":"PPLL",
    "gn:name":"Haldi",
    "gn:population":0,
    "gn:timezone":"Asia/Kathmandu",
    "iso:country":"NP",
    "wof:name":"Haldi",
    "wof:placetype":"locality"
},
  "geometry": {"coordinates":[83.02104,28.07901],"type":"Point"}
}