{
  "type": "Feature",
  "properties": {
    "gn:admin1_code":"CR",
    "gn:admin2_code":"11",
    "gn:admin3_code":"31",
    "gn:admin4_code":"310002",
    "gn:asciiname":"Chillebas",
    "gn:country_code":"NP",
    "gn:dem":774,
    "gn:feature_class":"P",
    "gn:feature_code":"PPLL",
    "gn:name":"Chillebas",
    "gn:population":0,
    "gn:timezone":"Asia/Kathmandu",
    "iso:country":"NP",
    "wof:name":"Chillebas",
    "wof:placetype":"locality"
},
  "geometry": {"coordinates":[85.09178,27.45294],"type":"Point"}
}