{
  "type": "Feature",
  "properties": {
    "gn:admin1_code":"MR",
    "gn:admin2_code":"12",
    "gn:admin3_code":"53",
    "gn:admin4_code":"530011",
    "gn:asciiname":"Sardhara",
    "gn:country_code":"NP",
    "gn:dem":1530,
    "gn:feature_class":"P",
    "gn:feature_code":"PPLL",
    "gn:name":"Sardhara",
    "gn:population":0,
    "gn:timezone":"Asia/Kathmandu",
    "iso:country":"NP",
    "wof:name":"Sardhara",
    "wof:placetype":"locality"
},
  "geometry": {"coordinates":[82.51359000000002,28.30908],"type":"Point"}
}