{
  "type": "Feature",
  "properties": {
    "gn:admin1_code":"00",
    "gn:asciiname":"Hajminiyatola",
    "gn:country_code":"NP",
    "gn:dem":79,
    "gn:feature_class":"P",
    "gn:feature_code":"PPL",
    "gn:name":"Hajmini\u0307\u0304y\u0101\u1e6dol\u0101",
    "gn:population":0,
    "gn:timezone":"Asia/Kathmandu",
    "iso:country":"NP",
    "name:und_x_variant":[
        "Hajmini\u0307\u0304y\u0101\u1e6dol\u0101",
        "Hajminia"
    ],
    "wof:name":"Hajminiyatola",
    "wof:placetype":"locality"
},
  "geometry": {"coordinates":[85.31005999999999,26.78639],"type":"Point"}
}