{
  "type": "Feature",
  "properties": {
    "gn:admin1_code":"WR",
    "gn:admin2_code":"3",
    "gn:admin3_code":"44",
    "gn:admin4_code":"440012",
    "gn:asciiname":"Namruni",
    "gn:country_code":"NP",
    "gn:dem":1653,
    "gn:feature_class":"P",
    "gn:feature_code":"PPLL",
    "gn:name":"Namruni",
    "gn:population":0,
    "gn:timezone":"Asia/Kathmandu",
    "iso:country":"NP",
    "wof:name":"Namruni",
    "wof:placetype":"locality"
},
  "geometry": {"coordinates":[83.72490999999999,28.34903],"type":"Point"}
}