{
  "type": "Feature",
  "properties": {
    "gn:admin1_code":"ER",
    "gn:admin2_code":"7",
    "gn:admin3_code":"5",
    "gn:admin4_code":"50059",
    "gn:asciiname":"Takuwa",
    "gn:country_code":"NP",
    "gn:dem":75,
    "gn:feature_class":"P",
    "gn:feature_code":"PPLL",
    "gn:name":"Takuwa",
    "gn:population":0,
    "gn:timezone":"Asia/Kathmandu",
    "iso:country":"NP",
    "wof:name":"Takuwa",
    "wof:placetype":"locality"
},
  "geometry": {"coordinates":[87.52314,26.46891],"type":"Point"}
}