{
  "type": "Feature",
  "properties": {
    "gn:admin1_code":"WR",
    "gn:admin2_code":"3",
    "gn:admin3_code":"45.0",
    "gn:admin4_code":"450041.0",
    "gn:asciiname":"Lamdara",
    "gn:country_code":"NP",
    "gn:dem":1665,
    "gn:feature_class":"P",
    "gn:feature_code":"PPLL",
    "gn:name":"Lamdara",
    "gn:population":0,
    "gn:timezone":"Asia/Kathmandu",
    "iso:country":"NP",
    "wof:name":"Lamdara",
    "wof:placetype":"locality"
},
  "geometry": {"coordinates":[83.45633000000002,28.2355],"type":"Point"}
}