{
  "type": "Feature",
  "properties": {
    "gn:admin1_code":"00",
    "gn:asciiname":"Bajgau",
    "gn:country_code":"NP",
    "gn:dem":604,
    "gn:feature_class":"P",
    "gn:feature_code":"PPL",
    "gn:name":"B\u0101\u0303jg\u0101\u0169",
    "gn:population":0,
    "gn:timezone":"Asia/Kathmandu",
    "iso:country":"NP",
    "name:nep_x_preferred":[
        "B\u0101\u0303jg\u0101\u0169"
    ],
    "name:nep_x_variant":[
        "B\u0101njg\u0101un"
    ],
    "wof:name":"Bajgau",
    "wof:placetype":"locality"
},
  "geometry": {"coordinates":[85.50176999999999,27.38356],"type":"Point"}
}