{
  "type": "Feature",
  "properties": {
    "gn:admin1_code":"WR",
    "gn:admin2_code":"8",
    "gn:admin3_code":"51.0",
    "gn:admin4_code":"510032.0",
    "gn:asciiname":"Baleban",
    "gn:country_code":"NP",
    "gn:dem":897,
    "gn:feature_class":"P",
    "gn:feature_code":"PPLL",
    "gn:name":"Baleban",
    "gn:population":0,
    "gn:timezone":"Asia/Kathmandu",
    "iso:country":"NP",
    "wof:name":"Baleban",
    "wof:placetype":"locality"
},
  "geometry": {"coordinates":[83.20560999999999,27.95101],"type":"Point"}
}