{
  "type": "Feature",
  "properties": {
    "gn:admin1_code":"CR",
    "gn:admin2_code":"5",
    "gn:admin3_code":"18",
    "gn:admin4_code":"180030.0",
    "gn:asciiname":"Bhanghiya",
    "gn:country_code":"NP",
    "gn:dem":72,
    "gn:feature_class":"P",
    "gn:feature_code":"PPLL",
    "gn:name":"Bhanghiya",
    "gn:population":0,
    "gn:timezone":"Asia/Kathmandu",
    "iso:country":"NP",
    "wof:name":"Bhanghiya",
    "wof:placetype":"locality"
},
  "geometry": {"coordinates":[85.74712,26.68309],"type":"Point"}
}