{
  "type": "Feature",
  "properties": {
    "gn:admin1_code":"ER",
    "gn:admin2_code":"13",
    "gn:admin3_code":"12",
    "gn:admin4_code":"120003",
    "gn:asciiname":"Takitar",
    "gn:country_code":"NP",
    "gn:dem":1445,
    "gn:feature_class":"P",
    "gn:feature_code":"PPLL",
    "gn:name":"Takitar",
    "gn:population":0,
    "gn:timezone":"Asia/Kathmandu",
    "iso:country":"NP",
    "wof:name":"Takitar",
    "wof:placetype":"locality"
},
  "geometry": {"coordinates":[86.32474999999999,27.26476],"type":"Point"}
}