{
  "type": "Feature",
  "properties": {
    "gn:admin1_code":"WR",
    "gn:admin2_code":"4",
    "gn:admin3_code":"41",
    "gn:admin4_code":"410010",
    "gn:asciiname":"Tarkang Goth",
    "gn:country_code":"NP",
    "gn:dem":3287,
    "gn:feature_class":"P",
    "gn:feature_code":"PPLL",
    "gn:name":"Tarkang Goth",
    "gn:population":0,
    "gn:timezone":"Asia/Kathmandu",
    "iso:country":"NP",
    "wof:name":"Tarkang Goth",
    "wof:placetype":"locality"
},
  "geometry": {"coordinates":[84.16996,28.60994],"type":"Point"}
}