{
  "type": "Feature",
  "properties": {
    "gn:admin1_code":"WR",
    "gn:admin2_code":"8",
    "gn:admin3_code":"46.0",
    "gn:admin4_code":"460079.0",
    "gn:asciiname":"Bhendawa",
    "gn:country_code":"NP",
    "gn:dem":1248,
    "gn:feature_class":"P",
    "gn:feature_code":"PPLL",
    "gn:name":"Bhendawa",
    "gn:population":0,
    "gn:timezone":"Asia/Kathmandu",
    "iso:country":"NP",
    "wof:name":"Bhendawa",
    "wof:placetype":"locality"
},
  "geometry": {"coordinates":[83.30549000000001,28.16571],"type":"Point"}
}