{
  "type": "Feature",
  "properties": {
    "gn:admin1_code":"CR",
    "gn:admin2_code":"5",
    "gn:admin3_code":"21",
    "gn:admin4_code":"210022",
    "gn:asciiname":"Khimti",
    "gn:country_code":"NP",
    "gn:dem":1642,
    "gn:feature_class":"P",
    "gn:feature_code":"PPLL",
    "gn:name":"Khimti",
    "gn:population":0,
    "gn:timezone":"Asia/Kathmandu",
    "iso:country":"NP",
    "name:bih_x_preferred":[
        "\u0916\u093f\u092e\u094d\u0924\u0940"
    ],
    "name:ceb_x_preferred":[
        "Khimti"
    ],
    "name:mai_x_preferred":[
        "\u0916\u093f\u092e\u094d\u0924\u0940"
    ],
    "name:msa_x_preferred":[
        "Khimti"
    ],
    "name:nep_x_preferred":[
        "\u0916\u093f\u092e\u094d\u0924\u0940"
    ],
    "name:new_x_preferred":[
        "\u0916\u093f\u092e\u094d\u0924\u0940"
    ],
    "name:pol_x_preferred":[
        "Khimti"
    ],
    "wof:name":"Khimti",
    "wof:placetype":"locality"
},
  "geometry": {"coordinates":[85.85043,27.53009],"type":"Point"}
}