{
  "type": "Feature",
  "properties": {
    "gn:admin1_code":"MR",
    "gn:admin2_code":"2.0",
    "gn:admin3_code":"59.0",
    "gn:admin4_code":"590036.0",
    "gn:asciiname":"Mathi Tule",
    "gn:country_code":"NP",
    "gn:dem":1304,
    "gn:feature_class":"P",
    "gn:feature_code":"PPLL",
    "gn:name":"Mathi Tule",
    "gn:population":0,
    "gn:timezone":"Asia/Kathmandu",
    "iso:country":"NP",
    "wof:name":"Mathi Tule",
    "wof:placetype":"locality"
},
  "geometry": {"coordinates":[81.82250999999999,28.64515],"type":"Point"}
}