{
  "type": "Feature",
  "properties": {
    "gn:admin1_code":"CR",
    "gn:admin2_code":"5",
    "gn:admin3_code":"22.0",
    "gn:admin4_code":"220017.0",
    "gn:asciiname":"Pakhera",
    "gn:country_code":"NP",
    "gn:dem":1649,
    "gn:feature_class":"P",
    "gn:feature_code":"PPLL",
    "gn:name":"Pakhera",
    "gn:population":0,
    "gn:timezone":"Asia/Kathmandu",
    "iso:country":"NP",
    "wof:name":"Pakhera",
    "wof:placetype":"locality"
},
  "geometry": {"coordinates":[86.12615,27.59791],"type":"Point"}
}