{
  "type": "Feature",
  "properties": {
    "gn:admin1_code":"MR",
    "gn:admin2_code":"2.0",
    "gn:admin3_code":"59.0",
    "gn:admin4_code":"590040.0",
    "gn:asciiname":"Kalyankadh",
    "gn:country_code":"NP",
    "gn:dem":1189,
    "gn:feature_class":"P",
    "gn:feature_code":"PPLL",
    "gn:name":"Kalyankadh",
    "gn:population":0,
    "gn:timezone":"Asia/Kathmandu",
    "iso:country":"NP",
    "wof:name":"Kalyankadh",
    "wof:placetype":"locality"
},
  "geometry": {"coordinates":[81.50209,28.74114],"type":"Point"}
}