{
  "type": "Feature",
  "properties": {
    "gn:admin1_code":"ER",
    "gn:admin2_code":"13.0",
    "gn:admin3_code":"14.0",
    "gn:admin4_code":"140019.0",
    "gn:asciiname":"Baruwagaun",
    "gn:country_code":"NP",
    "gn:dem":1073,
    "gn:feature_class":"P",
    "gn:feature_code":"PPLL",
    "gn:name":"Baruwagaun",
    "gn:population":0,
    "gn:timezone":"Asia/Kathmandu",
    "iso:country":"NP",
    "wof:name":"Baruwagaun",
    "wof:placetype":"locality"
},
  "geometry": {"coordinates":[86.71576,26.91934],"type":"Point"}
}