{
  "type": "Feature",
  "properties": {
    "gn:admin1_code":"WR",
    "gn:admin2_code":"8",
    "gn:admin3_code":"47",
    "gn:admin4_code":"470009",
    "gn:asciiname":"Silingbhanjang",
    "gn:country_code":"NP",
    "gn:dem":1275,
    "gn:feature_class":"P",
    "gn:feature_code":"PPLL",
    "gn:name":"Silingbhanjang",
    "gn:population":0,
    "gn:timezone":"Asia/Kathmandu",
    "iso:country":"NP",
    "wof:name":"Silingbhanjang",
    "wof:placetype":"locality"
},
  "geometry": {"coordinates":[83.76108000000001,27.83651],"type":"Point"}
}