{
  "type": "Feature",
  "properties": {
    "gn:admin1_code":"ER",
    "gn:admin2_code":"13",
    "gn:admin3_code":"13.0",
    "gn:admin4_code":"130023.0",
    "gn:asciiname":"Gairi",
    "gn:country_code":"NP",
    "gn:dem":1003,
    "gn:feature_class":"P",
    "gn:feature_code":"PPLL",
    "gn:name":"Gairi",
    "gn:population":0,
    "gn:timezone":"Asia/Kathmandu",
    "iso:country":"NP",
    "wof:name":"Gairi",
    "wof:placetype":"locality"
},
  "geometry": {"coordinates":[86.64685,27.17229],"type":"Point"}
}