{
  "type": "Feature",
  "properties": {
    "gn:admin1_code":"CR",
    "gn:admin2_code":"5",
    "gn:admin3_code":"21",
    "gn:admin4_code":"210046",
    "gn:asciiname":"Basantapur",
    "gn:country_code":"NP",
    "gn:dem":976,
    "gn:feature_class":"P",
    "gn:feature_code":"PPLL",
    "gn:name":"Basantapur",
    "gn:population":0,
    "gn:timezone":"Asia/Kathmandu",
    "iso:country":"NP",
    "name:fra_x_preferred":[
        "Basantapur"
    ],
    "name:pol_x_preferred":[
        "Basantapur"
    ],
    "wof:name":"Basantapur",
    "wof:placetype":"locality"
},
  "geometry": {"coordinates":[86.13155999999999,27.2776],"type":"Point"}
}