{
  "type": "Feature",
  "properties": {
    "gn:admin1_code":"ER",
    "gn:admin2_code":"13",
    "gn:admin3_code":"16",
    "gn:admin4_code":"160017",
    "gn:asciiname":"Shivanagar",
    "gn:country_code":"NP",
    "gn:dem":115,
    "gn:feature_class":"P",
    "gn:feature_code":"PPLL",
    "gn:name":"Shivanagar",
    "gn:population":0,
    "gn:timezone":"Asia/Kathmandu",
    "iso:country":"NP",
    "name:msa_x_preferred":[
        "Shivanagar"
    ],
    "name:pol_x_preferred":[
        "Shipanagar"
    ],
    "wof:name":"Shivanagar",
    "wof:placetype":"locality"
},
  "geometry": {"coordinates":[86.39471999999998,26.72194],"type":"Point"}
}