{
  "type": "Feature",
  "properties": {
    "gn:admin1_code":"ER",
    "gn:admin2_code":"13",
    "gn:admin3_code":"11",
    "gn:admin4_code":"110019",
    "gn:asciiname":"Mahabhir",
    "gn:country_code":"NP",
    "gn:dem":2604,
    "gn:feature_class":"P",
    "gn:feature_code":"PPLL",
    "gn:name":"Mahabhir",
    "gn:population":0,
    "gn:timezone":"Asia/Kathmandu",
    "iso:country":"NP",
    "wof:name":"Mahabhir",
    "wof:placetype":"locality"
},
  "geometry": {"coordinates":[86.53950999999998,27.42229],"type":"Point"}
}