{
  "type": "Feature",
  "properties": {
    "gn:admin1_code":"ER",
    "gn:admin2_code":"10.0",
    "gn:admin3_code":"1.0",
    "gn:admin4_code":"10026.0",
    "gn:asciiname":"Ghangjen Sara",
    "gn:country_code":"NP",
    "gn:dem":5701,
    "gn:feature_class":"P",
    "gn:feature_code":"PPLL",
    "gn:name":"Ghangjen Sara",
    "gn:population":0,
    "gn:timezone":"Asia/Kathmandu",
    "iso:country":"NP",
    "wof:name":"Ghangjen Sara",
    "wof:placetype":"locality"
},
  "geometry": {"coordinates":[87.78248000000001,27.85456],"type":"Point"}
}