{
  "type": "Feature",
  "properties": {
    "gn:admin1_code":"ER",
    "gn:admin2_code":"7.0",
    "gn:admin3_code":"10.0",
    "gn:admin4_code":"100004.0",
    "gn:asciiname":"Khaktang",
    "gn:country_code":"NP",
    "gn:dem":1599,
    "gn:feature_class":"P",
    "gn:feature_code":"PPLL",
    "gn:name":"Khaktang",
    "gn:population":0,
    "gn:timezone":"Asia/Kathmandu",
    "iso:country":"NP",
    "wof:name":"Khaktang",
    "wof:placetype":"locality"
},
  "geometry": {"coordinates":[87.02789,27.05113],"type":"Point"}
}