{
  "type": "Feature",
  "properties": {
    "gn:admin1_code":"WR",
    "gn:admin2_code":"4",
    "gn:admin3_code":"37",
    "gn:admin4_code":"370027.0",
    "gn:asciiname":"Manjhgaun",
    "gn:country_code":"NP",
    "gn:dem":1260,
    "gn:feature_class":"P",
    "gn:feature_code":"PPLL",
    "gn:name":"Manjhgaun",
    "gn:population":0,
    "gn:timezone":"Asia/Kathmandu",
    "iso:country":"NP",
    "wof:name":"Manjhgaun",
    "wof:placetype":"locality"
},
  "geometry": {"coordinates":[84.38305,28.18273],"type":"Point"}
}