{
  "type": "Feature",
  "properties": {
    "gn:admin1_code":"ER",
    "gn:admin2_code":"7.0",
    "gn:admin3_code":"8.0",
    "gn:admin4_code":"80023.0",
    "gn:asciiname":"Jirikhimti",
    "gn:country_code":"NP",
    "gn:dem":1589,
    "gn:feature_class":"P",
    "gn:feature_code":"PPLL",
    "gn:name":"Jirikhimti",
    "gn:population":0,
    "gn:timezone":"Asia/Kathmandu",
    "iso:country":"NP",
    "wof:name":"Jirikhimti",
    "wof:placetype":"locality"
},
  "geometry": {"coordinates":[87.51734999999999,27.16242],"type":"Point"}
}