{
  "type": "Feature",
  "properties": {
    "gn:admin1_code":"WR",
    "gn:admin2_code":"4.0",
    "gn:admin3_code":"39.0",
    "gn:admin4_code":"390036.0",
    "gn:asciiname":"Huktung",
    "gn:country_code":"NP",
    "gn:dem":957,
    "gn:feature_class":"P",
    "gn:feature_code":"PPLL",
    "gn:name":"Huktung",
    "gn:population":0,
    "gn:timezone":"Asia/Kathmandu",
    "iso:country":"NP",
    "wof:name":"Huktung",
    "wof:placetype":"locality"
},
  "geometry": {"coordinates":[83.60805999999999,27.974],"type":"Point"}
}