{
  "type": "Feature",
  "properties": {
    "gn:admin1_code":"MR",
    "gn:admin2_code":"12",
    "gn:admin3_code":"54",
    "gn:admin4_code":"540011",
    "gn:asciiname":"Mulpani",
    "gn:country_code":"NP",
    "gn:dem":969,
    "gn:feature_class":"P",
    "gn:feature_code":"PPLL",
    "gn:name":"Mulpani",
    "gn:population":0,
    "gn:timezone":"Asia/Kathmandu",
    "iso:country":"NP",
    "wof:name":"Mulpani",
    "wof:placetype":"locality"
},
  "geometry": {"coordinates":[82.36915999999999,28.66123],"type":"Point"}
}