{
  "type": "Feature",
  "properties": {
    "gn:admin1_code":"CR",
    "gn:admin2_code":"5.0",
    "gn:asciiname":"Khijikati",
    "gn:country_code":"NP",
    "gn:dem":1896,
    "gn:feature_class":"P",
    "gn:feature_code":"PPLL",
    "gn:name":"Khijikati",
    "gn:population":0,
    "gn:timezone":"Asia/Kathmandu",
    "iso:country":"NP",
    "wof:name":"Khijikati",
    "wof:placetype":"locality"
},
  "geometry": {"coordinates":[86.33091999999998,27.48457],"type":"Point"}
}