{
  "type": "Feature",
  "properties": {
    "gn:admin1_code":"ER",
    "gn:admin2_code":"10",
    "gn:admin3_code":"4.0",
    "gn:admin4_code":"40019.0",
    "gn:asciiname":"Kadamgachhi",
    "gn:country_code":"NP",
    "gn:dem":74,
    "gn:feature_class":"P",
    "gn:feature_code":"PPLL",
    "gn:name":"Kadamgachhi",
    "gn:population":0,
    "gn:timezone":"Asia/Kathmandu",
    "iso:country":"NP",
    "wof:name":"Kadamgachhi",
    "wof:placetype":"locality"
},
  "geometry": {"coordinates":[87.72298000000001,26.43998],"type":"Point"}
}