{
  "type": "Feature",
  "properties": {
    "gn:admin1_code":"00",
    "gn:asciiname":"Samlin",
    "gn:country_code":"NP",
    "gn:dem":4824,
    "gn:feature_class":"P",
    "gn:feature_code":"PPL",
    "gn:name":"S\u0101mli\u1e45",
    "gn:population":0,
    "gn:timezone":"Asia/Kathmandu",
    "iso:country":"NP",
    "wof:name":"Samlin",
    "wof:placetype":"locality"
},
  "geometry": {"coordinates":[86.15879,27.92262],"type":"Point"}
}