{
  "type": "Feature",
  "properties": {
    "gn:admin1_code":"ER",
    "gn:admin2_code":"10.0",
    "gn:admin3_code":"1.0",
    "gn:admin4_code":"10012.0",
    "gn:asciiname":"Sulumphi",
    "gn:country_code":"NP",
    "gn:dem":1228,
    "gn:feature_class":"P",
    "gn:feature_code":"PPLL",
    "gn:name":"Sulumphi",
    "gn:population":0,
    "gn:timezone":"Asia/Kathmandu",
    "iso:country":"NP",
    "wof:name":"Sulumphi",
    "wof:placetype":"locality"
},
  "geometry": {"coordinates":[87.61105999999999,27.38842],"type":"Point"}
}