{
  "type": "Feature",
  "properties": {
    "gn:admin1_code":"CR",
    "gn:admin2_code":"5",
    "gn:admin3_code":"21",
    "gn:admin4_code":"210013",
    "gn:asciiname":"Lamte",
    "gn:country_code":"NP",
    "gn:dem":1185,
    "gn:feature_class":"P",
    "gn:feature_code":"PPLL",
    "gn:name":"Lamte",
    "gn:population":0,
    "gn:timezone":"Asia/Kathmandu",
    "iso:country":"NP",
    "wof:name":"Lamte",
    "wof:placetype":"locality"
},
  "geometry": {"coordinates":[86.1802,27.38206],"type":"Point"}
}