{
  "type": "Feature",
  "properties": {
    "gn:admin1_code":"CR",
    "gn:admin2_code":"11",
    "gn:admin3_code":"31",
    "gn:admin4_code":"310022",
    "gn:asciiname":"Saktedandagaun",
    "gn:country_code":"NP",
    "gn:dem":995,
    "gn:feature_class":"P",
    "gn:feature_code":"PPLL",
    "gn:name":"Saktedandagaun",
    "gn:population":0,
    "gn:timezone":"Asia/Kathmandu",
    "iso:country":"NP",
    "wof:name":"Saktedandagaun",
    "wof:placetype":"locality"
},
  "geometry": {"coordinates":[85.24588,27.4715],"type":"Point"}
}