{
  "type": "Feature",
  "properties": {
    "gn:admin1_code":"MR",
    "gn:admin2_code":"12",
    "gn:admin3_code":"54",
    "gn:admin4_code":"540018",
    "gn:asciiname":"Madudekharka",
    "gn:country_code":"NP",
    "gn:dem":3302,
    "gn:feature_class":"P",
    "gn:feature_code":"PPLL",
    "gn:name":"Madudekharka",
    "gn:population":0,
    "gn:timezone":"Asia/Kathmandu",
    "iso:country":"NP",
    "wof:name":"Madudekharka",
    "wof:placetype":"locality"
},
  "geometry": {"coordinates":[82.84577,28.50651],"type":"Point"}
}