{
  "type": "Feature",
  "properties": {
    "gn:admin1_code":"FR",
    "gn:admin2_code":"14",
    "gn:admin3_code":"70.0",
    "gn:admin4_code":"700039.0",
    "gn:asciiname":"Bhawanbata",
    "gn:country_code":"NP",
    "gn:dem":992,
    "gn:feature_class":"P",
    "gn:feature_code":"PPLL",
    "gn:name":"Bhawanbata",
    "gn:population":0,
    "gn:timezone":"Asia/Kathmandu",
    "iso:country":"NP",
    "wof:name":"Bhawanbata",
    "wof:placetype":"locality"
},
  "geometry": {"coordinates":[80.75363,29.06872000000001],"type":"Point"}
}