{
  "type": "Feature",
  "properties": {
    "gn:admin1_code":"WR",
    "gn:admin2_code":"3",
    "gn:admin3_code":"44",
    "gn:admin4_code":"440041.0",
    "gn:asciiname":"Gam",
    "gn:country_code":"NP",
    "gn:dem":1801,
    "gn:feature_class":"P",
    "gn:feature_code":"PPLL",
    "gn:name":"Gam",
    "gn:population":0,
    "gn:timezone":"Asia/Kathmandu",
    "iso:country":"NP",
    "name:ceb_x_preferred":[
        "Gam"
    ],
    "name:spa_x_preferred":[
        "Gam"
    ],
    "wof:name":"Gam",
    "wof:placetype":"locality"
},
  "geometry": {"coordinates":[83.65364,28.27397],"type":"Point"}
}