{
  "type": "Feature",
  "properties": {
    "gn:admin1_code":"ER",
    "gn:admin2_code":"10",
    "gn:admin3_code":"3.0",
    "gn:admin4_code":"30029.0",
    "gn:asciiname":"Gaddidanda",
    "gn:country_code":"NP",
    "gn:dem":761,
    "gn:feature_class":"P",
    "gn:feature_code":"PPLL",
    "gn:name":"Gaddidanda",
    "gn:population":0,
    "gn:timezone":"Asia/Kathmandu",
    "iso:country":"NP",
    "wof:name":"Gaddidanda",
    "wof:placetype":"locality"
},
  "geometry": {"coordinates":[87.96389000000001,26.89557000000001],"type":"Point"}
}