{
  "type": "Feature",
  "properties": {
    "gn:admin1_code":"FR",
    "gn:admin2_code":"14",
    "gn:admin3_code":"70.0",
    "gn:admin4_code":"700034.0",
    "gn:asciiname":"Sirad",
    "gn:country_code":"NP",
    "gn:dem":1664,
    "gn:feature_class":"P",
    "gn:feature_code":"PPLL",
    "gn:name":"Sirad",
    "gn:population":0,
    "gn:timezone":"Asia/Kathmandu",
    "iso:country":"NP",
    "wof:name":"Sirad",
    "wof:placetype":"locality"
},
  "geometry": {"coordinates":[80.71368000000002,29.08745],"type":"Point"}
}