{
  "type": "Feature",
  "properties": {
    "gn:admin1_code":"FR",
    "gn:admin2_code":"9",
    "gn:admin3_code":"74",
    "gn:admin4_code":"740022",
    "gn:asciiname":"Raikoda",
    "gn:country_code":"NP",
    "gn:dem":1643,
    "gn:feature_class":"P",
    "gn:feature_code":"PPLL",
    "gn:name":"Raikoda",
    "gn:population":0,
    "gn:timezone":"Asia/Kathmandu",
    "iso:country":"NP",
    "wof:name":"Raikoda",
    "wof:placetype":"locality"
},
  "geometry": {"coordinates":[80.58814,29.48137],"type":"Point"}
}