{
  "type": "Feature",
  "properties": {
    "gn:admin1_code":"CR",
    "gn:admin2_code":"1",
    "gn:admin3_code":"30.0",
    "gn:admin4_code":"300023.0",
    "gn:asciiname":"Phyakse",
    "gn:country_code":"NP",
    "gn:dem":1015,
    "gn:feature_class":"P",
    "gn:feature_code":"PPLL",
    "gn:name":"Phyakse",
    "gn:population":0,
    "gn:timezone":"Asia/Kathmandu",
    "iso:country":"NP",
    "wof:name":"Phyakse",
    "wof:placetype":"locality"
},
  "geometry": {"coordinates":[84.95759,27.87357],"type":"Point"}
}