{
  "type": "Feature",
  "properties": {
    "gn:admin1_code":"WR",
    "gn:admin2_code":"4",
    "gn:admin3_code":"40.0",
    "gn:admin4_code":"400028.0",
    "gn:asciiname":"Chijudanda",
    "gn:country_code":"NP",
    "gn:dem":1212,
    "gn:feature_class":"P",
    "gn:feature_code":"PPLL",
    "gn:name":"Chijudanda",
    "gn:population":0,
    "gn:timezone":"Asia/Kathmandu",
    "iso:country":"NP",
    "wof:name":"Chijudanda",
    "wof:placetype":"locality"
},
  "geometry": {"coordinates":[84.17142,28.25725],"type":"Point"}
}