{
  "type": "Feature",
  "properties": {
    "gn:admin1_code":"ER",
    "gn:admin2_code":"13",
    "gn:admin3_code":"12",
    "gn:admin4_code":"120019.0",
    "gn:asciiname":"Dih",
    "gn:country_code":"NP",
    "gn:dem":993,
    "gn:feature_class":"P",
    "gn:feature_code":"PPLL",
    "gn:name":"Dih",
    "gn:population":0,
    "gn:timezone":"Asia/Kathmandu",
    "iso:country":"NP",
    "wof:name":"Dih",
    "wof:placetype":"locality"
},
  "geometry": {"coordinates":[86.25208000000001,27.29942],"type":"Point"}
}