{
  "type": "Feature",
  "properties": {
    "gn:admin1_code":"WR",
    "gn:admin2_code":"3",
    "gn:admin3_code":"44",
    "gn:admin4_code":"440023",
    "gn:asciiname":"Kumalgaun",
    "gn:country_code":"NP",
    "gn:dem":862,
    "gn:feature_class":"P",
    "gn:feature_code":"PPLL",
    "gn:name":"Kumalgaun",
    "gn:population":0,
    "gn:timezone":"Asia/Kathmandu",
    "iso:country":"NP",
    "name:ceb_x_preferred":[
        "Kumalgaun"
    ],
    "name:dty_x_preferred":[
        "\u0915\u0941\u092e\u093e\u0932\u0917\u093e\u0909\u0901"
    ],
    "name:mai_x_preferred":[
        "\u0915\u0941\u092e\u093e\u0932\u0917\u093e\u0909\u0901"
    ],
    "name:msa_x_preferred":[
        "Kumalgaun"
    ],
    "name:nep_x_preferred":[
        "\u0915\u0941\u092e\u093e\u0932\u0917\u093e\u0909\u0901"
    ],
    "name:pol_x_preferred":[
        "Kumalgaun"
    ],
    "wof:name":"Kumalgaun",
    "wof:placetype":"locality"
},
  "geometry": {"coordinates":[83.65033000000003,28.16088],"type":"Point"}
}