{
  "type": "Feature",
  "properties": {
    "gn:admin1_code":"WR",
    "gn:admin2_code":"8",
    "gn:admin3_code":"46.0",
    "gn:admin4_code":"460040.0",
    "gn:asciiname":"Chhap Gaun",
    "gn:country_code":"NP",
    "gn:dem":1227,
    "gn:feature_class":"P",
    "gn:feature_code":"PPLL",
    "gn:name":"Chhap Gaun",
    "gn:population":0,
    "gn:timezone":"Asia/Kathmandu",
    "iso:country":"NP",
    "wof:name":"Chhap Gaun",
    "wof:placetype":"locality"
},
  "geometry": {"coordinates":[83.34952,27.99334],"type":"Point"}
}