{
  "type": "Feature",
  "properties": {
    "gn:admin1_code":"CR",
    "gn:admin2_code":"1",
    "gn:admin3_code":"30.0",
    "gn:admin4_code":"300048.0",
    "gn:asciiname":"Regmigaun",
    "gn:country_code":"NP",
    "gn:dem":1079,
    "gn:feature_class":"P",
    "gn:feature_code":"PPLL",
    "gn:name":"Regmigaun",
    "gn:population":0,
    "gn:timezone":"Asia/Kathmandu",
    "iso:country":"NP",
    "wof:name":"Regmigaun",
    "wof:placetype":"locality"
},
  "geometry": {"coordinates":[85.09473,27.73297],"type":"Point"}
}