{
  "type": "Feature",
  "properties": {
    "gn:admin1_code":"FR",
    "gn:admin2_code":"14",
    "gn:admin3_code":"70.0",
    "gn:admin4_code":"700006.0",
    "gn:asciiname":"Kubekot",
    "gn:country_code":"NP",
    "gn:dem":903,
    "gn:feature_class":"P",
    "gn:feature_code":"PPLL",
    "gn:name":"Kubekot",
    "gn:population":0,
    "gn:timezone":"Asia/Kathmandu",
    "iso:country":"NP",
    "wof:name":"Kubekot",
    "wof:placetype":"locality"
},
  "geometry": {"coordinates":[81.05604,29.097],"type":"Point"}
}