{
  "type": "Feature",
  "properties": {
    "gn:admin1_code":"WR",
    "gn:admin2_code":"4.0",
    "gn:admin3_code":"38.0",
    "gn:admin4_code":"380024.0",
    "gn:asciiname":"Dirpu",
    "gn:country_code":"NP",
    "gn:dem":647,
    "gn:feature_class":"P",
    "gn:feature_code":"PPLL",
    "gn:name":"Dirpu",
    "gn:population":0,
    "gn:timezone":"Asia/Kathmandu",
    "iso:country":"NP",
    "wof:name":"Dirpu",
    "wof:placetype":"locality"
},
  "geometry": {"coordinates":[84.22162,27.98926],"type":"Point"}
}