{
  "type": "Feature",
  "properties": {
    "gn:admin1_code":"WR",
    "gn:admin2_code":"8",
    "gn:admin3_code":"50.0",
    "gn:admin4_code":"500034.0",
    "gn:asciiname":"Bankatawa",
    "gn:country_code":"NP",
    "gn:dem":112,
    "gn:feature_class":"P",
    "gn:feature_code":"PPLL",
    "gn:name":"Bankatawa",
    "gn:population":0,
    "gn:timezone":"Asia/Kathmandu",
    "iso:country":"NP",
    "wof:name":"Bankatawa",
    "wof:placetype":"locality"
},
  "geometry": {"coordinates":[83.1564,27.60092],"type":"Point"}
}