{
  "type": "Feature",
  "properties": {
    "gn:admin1_code":"CR",
    "gn:admin2_code":"1",
    "gn:admin3_code":"30.0",
    "gn:admin4_code":"300013.0",
    "gn:asciiname":"Purasimha",
    "gn:country_code":"NP",
    "gn:dem":1098,
    "gn:feature_class":"P",
    "gn:feature_code":"PPLL",
    "gn:name":"Purasimha",
    "gn:population":0,
    "gn:timezone":"Asia/Kathmandu",
    "iso:country":"NP",
    "wof:name":"Purasimha",
    "wof:placetype":"locality"
},
  "geometry": {"coordinates":[84.85911,27.75932],"type":"Point"}
}