{
  "type": "Feature",
  "properties": {
    "gn:admin1_code":"CR",
    "gn:admin2_code":"1",
    "gn:admin3_code":"28",
    "gn:admin4_code":"280018",
    "gn:asciiname":"Bedpani",
    "gn:country_code":"NP",
    "gn:dem":932,
    "gn:feature_class":"P",
    "gn:feature_code":"PPLL",
    "gn:name":"Bedpani",
    "gn:population":0,
    "gn:timezone":"Asia/Kathmandu",
    "iso:country":"NP",
    "wof:name":"Bedpani",
    "wof:placetype":"locality"
},
  "geometry": {"coordinates":[85.0813,27.83637],"type":"Point"}
}