{
  "type": "Feature",
  "properties": {
    "gn:admin1_code":"ER",
    "gn:admin2_code":"7.0",
    "gn:admin3_code":"8.0",
    "gn:admin4_code":"80027.0",
    "gn:asciiname":"Poklawan",
    "gn:country_code":"NP",
    "gn:dem":1720,
    "gn:feature_class":"P",
    "gn:feature_code":"PPLL",
    "gn:name":"Poklawan",
    "gn:population":0,
    "gn:timezone":"Asia/Kathmandu",
    "iso:country":"NP",
    "wof:name":"Poklawan",
    "wof:placetype":"locality"
},
  "geometry": {"coordinates":[87.59539000000002,27.14796],"type":"Point"}
}