{
  "type": "Feature",
  "properties": {
    "gn:admin1_code":"WR",
    "gn:admin2_code":"3",
    "gn:admin3_code":"43",
    "gn:admin4_code":"430001",
    "gn:asciiname":"Tikabung",
    "gn:country_code":"NP",
    "gn:dem":1919,
    "gn:feature_class":"P",
    "gn:feature_code":"PPLL",
    "gn:name":"Tikabung",
    "gn:population":0,
    "gn:timezone":"Asia/Kathmandu",
    "iso:country":"NP",
    "wof:name":"Tikabung",
    "wof:placetype":"locality"
},
  "geometry": {"coordinates":[83.39629000000002,28.37551],"type":"Point"}
}