{
  "type": "Feature",
  "properties": {
    "gn:admin1_code":"FR",
    "gn:admin2_code":"9",
    "gn:admin3_code":"75.0",
    "gn:admin4_code":"750036.0",
    "gn:asciiname":"Bagadi",
    "gn:country_code":"NP",
    "gn:dem":805,
    "gn:feature_class":"P",
    "gn:feature_code":"PPLL",
    "gn:name":"Bagadi",
    "gn:population":0,
    "gn:timezone":"Asia/Kathmandu",
    "iso:country":"NP",
    "wof:name":"Bagadi",
    "wof:placetype":"locality"
},
  "geometry": {"coordinates":[80.6367,29.69048],"type":"Point"}
}