{
  "type": "Feature",
  "properties": {
    "gn:admin1_code":"MR",
    "gn:admin2_code":"2.0",
    "gn:admin3_code":"57.0",
    "gn:admin4_code":"570025.0",
    "gn:asciiname":"Naharko Dandagaun",
    "gn:country_code":"NP",
    "gn:dem":162,
    "gn:feature_class":"P",
    "gn:feature_code":"PPLL",
    "gn:name":"Naharko Dandagaun",
    "gn:population":0,
    "gn:timezone":"Asia/Kathmandu",
    "iso:country":"NP",
    "wof:name":"Naharko Dandagaun",
    "wof:placetype":"locality"
},
  "geometry": {"coordinates":[81.67858000000003,28.16579],"type":"Point"}
}