{
  "type": "Feature",
  "properties": {
    "gn:admin1_code":"CR",
    "gn:admin2_code":"1",
    "gn:admin3_code":"23",
    "gn:admin4_code":"230074",
    "gn:asciiname":"Tinghare",
    "gn:country_code":"NP",
    "gn:dem":1313,
    "gn:feature_class":"P",
    "gn:feature_code":"PPLL",
    "gn:name":"Tinghare",
    "gn:population":0,
    "gn:timezone":"Asia/Kathmandu",
    "iso:country":"NP",
    "wof:name":"Tinghare",
    "wof:placetype":"locality"
},
  "geometry": {"coordinates":[85.77636,27.67799],"type":"Point"}
}