{
  "type": "Feature",
  "properties": {
    "gn:admin1_code":"WR",
    "gn:admin2_code":"4",
    "gn:admin3_code":"40.0",
    "gn:admin4_code":"400026.0",
    "gn:asciiname":"Lamichhanegaun",
    "gn:country_code":"NP",
    "gn:dem":1088,
    "gn:feature_class":"P",
    "gn:feature_code":"PPLL",
    "gn:name":"Lamichhanegaun",
    "gn:population":0,
    "gn:timezone":"Asia/Kathmandu",
    "iso:country":"NP",
    "wof:name":"Lamichhanegaun",
    "wof:placetype":"locality"
},
  "geometry": {"coordinates":[84.10597,28.20793],"type":"Point"}
}