{
  "type": "Feature",
  "properties": {
    "gn:admin1_code":"WR",
    "gn:admin2_code":"4.0",
    "gn:admin3_code":"39.0",
    "gn:admin4_code":"390023.0",
    "gn:asciiname":"Jagat Bhanjyang",
    "gn:country_code":"NP",
    "gn:dem":1052,
    "gn:feature_class":"P",
    "gn:feature_code":"PPLL",
    "gn:name":"Jagat Bhanjyang",
    "gn:population":0,
    "gn:timezone":"Asia/Kathmandu",
    "iso:country":"NP",
    "name:hin_x_preferred":[
        "\u091c\u0917\u0924 \u092d\u091e\u094d\u091c\u094d\u092f\u093e\u0919"
    ],
    "name:mai_x_preferred":[
        "\u091c\u0917\u0924 \u092d\u091e\u094d\u091c\u094d\u092f\u093e\u0919"
    ],
    "name:msa_x_preferred":[
        "Jagat Bhanjyang"
    ],
    "name:nep_x_preferred":[
        "\u091c\u0917\u0924 \u092d\u091e\u094d\u091c\u094d\u092f\u093e\u0919"
    ],
    "name:new_x_preferred":[
        "\u091c\u0917\u0924 \u092d\u091e\u094d\u091c\u094d\u092f\u093e\u0919\u094d"
    ],
    "name:pol_x_preferred":[
        "Jagat Bhanjyang"
    ],
    "name:urd_x_preferred":[
        "\u062c\u0627\u06af\u062a \u0628\u06be\u0627\u0646\u062c\u06cc\u0646\u06af"
    ],
    "wof:name":"Jagat Bhanjyang",
    "wof:placetype":"locality"
},
  "geometry": {"coordinates":[83.81704000000001,27.96351],"type":"Point"}
}