{
  "type": "Feature",
  "properties": {
    "gn:admin1_code":"CR",
    "gn:admin2_code":"1",
    "gn:admin3_code":"30.0",
    "gn:admin4_code":"300020.0",
    "gn:asciiname":"Ghartitar",
    "gn:country_code":"NP",
    "gn:dem":529,
    "gn:feature_class":"P",
    "gn:feature_code":"PPLL",
    "gn:name":"Ghartitar",
    "gn:population":0,
    "gn:timezone":"Asia/Kathmandu",
    "iso:country":"NP",
    "wof:name":"Ghartitar",
    "wof:placetype":"locality"
},
  "geometry": {"coordinates":[85.00321,27.81077],"type":"Point"}
}