{
  "type": "Feature",
  "properties": {
    "gn:admin1_code":"MR",
    "gn:admin2_code":"12",
    "gn:admin3_code":"52",
    "gn:admin4_code":"520019",
    "gn:asciiname":"Hattikhal",
    "gn:country_code":"NP",
    "gn:dem":717,
    "gn:feature_class":"P",
    "gn:feature_code":"PPLL",
    "gn:name":"Hattikhal",
    "gn:population":0,
    "gn:timezone":"Asia/Kathmandu",
    "iso:country":"NP",
    "wof:name":"Hattikhal",
    "wof:placetype":"locality"
},
  "geometry": {"coordinates":[82.76104000000002,27.9523],"type":"Point"}
}