{
  "type": "Feature",
  "properties": {
    "gn:admin1_code":"CR",
    "gn:admin2_code":"11.0",
    "gn:admin3_code":"33.0",
    "gn:admin4_code":"330088.0",
    "gn:asciiname":"Ghorekchhyalgaun",
    "gn:country_code":"NP",
    "gn:dem":651,
    "gn:feature_class":"P",
    "gn:feature_code":"PPLL",
    "gn:name":"Ghorekchhyalgaun",
    "gn:population":0,
    "gn:timezone":"Asia/Kathmandu",
    "iso:country":"NP",
    "wof:name":"Ghorekchhyalgaun",
    "wof:placetype":"locality"
},
  "geometry": {"coordinates":[85.09281,27.29469000000001],"type":"Point"}
}