{
  "type": "Feature",
  "properties": {
    "gn:admin1_code":"MR",
    "gn:admin2_code":"2",
    "gn:admin3_code":"61.0",
    "gn:admin4_code":"610011.0",
    "gn:asciiname":"Khadkagaun",
    "gn:country_code":"NP",
    "gn:dem":1134,
    "gn:feature_class":"P",
    "gn:feature_code":"PPLL",
    "gn:name":"Khadkagaun",
    "gn:population":0,
    "gn:timezone":"Asia/Kathmandu",
    "iso:country":"NP",
    "wof:name":"Khadkagaun",
    "wof:placetype":"locality"
},
  "geometry": {"coordinates":[81.97439,28.70474],"type":"Point"}
}