{
  "type": "Feature",
  "properties": {
    "gn:admin1_code":"WR",
    "gn:admin2_code":"8",
    "gn:admin3_code":"46.0",
    "gn:admin4_code":"460004.0",
    "gn:asciiname":"Tallaphant Gaun",
    "gn:country_code":"NP",
    "gn:dem":690,
    "gn:feature_class":"P",
    "gn:feature_code":"PPLL",
    "gn:name":"Tallaphant Gaun",
    "gn:population":0,
    "gn:timezone":"Asia/Kathmandu",
    "iso:country":"NP",
    "wof:name":"Tallaphant Gaun",
    "wof:placetype":"locality"
},
  "geometry": {"coordinates":[83.33443,28.10637],"type":"Point"}
}