{
  "type": "Feature",
  "properties": {
    "gn:admin1_code":"MR",
    "gn:admin2_code":"12",
    "gn:admin3_code":"52",
    "gn:admin4_code":"520006",
    "gn:asciiname":"Salabang",
    "gn:country_code":"NP",
    "gn:dem":1535,
    "gn:feature_class":"P",
    "gn:feature_code":"PPLL",
    "gn:name":"Salabang",
    "gn:population":0,
    "gn:timezone":"Asia/Kathmandu",
    "iso:country":"NP",
    "wof:name":"Salabang",
    "wof:placetype":"locality"
},
  "geometry": {"coordinates":[82.76445,28.17091],"type":"Point"}
}