{
  "type": "Feature",
  "properties": {
    "gn:admin1_code":"CR",
    "gn:admin2_code":"5",
    "gn:admin3_code":"20",
    "gn:admin4_code":"200023.0",
    "gn:asciiname":"Hattimara",
    "gn:country_code":"NP",
    "gn:dem":419,
    "gn:feature_class":"P",
    "gn:feature_code":"PPLL",
    "gn:name":"Hattimara",
    "gn:population":0,
    "gn:timezone":"Asia/Kathmandu",
    "iso:country":"NP",
    "wof:name":"Hattimara",
    "wof:placetype":"locality"
},
  "geometry": {"coordinates":[86.36246,27.0504],"type":"Point"}
}