{
  "type": "Feature",
  "properties": {
    "gn:admin1_code":"CR",
    "gn:admin2_code":"1",
    "gn:admin3_code":"24.0",
    "gn:admin4_code":"240076.0",
    "gn:asciiname":"Sardardanda",
    "gn:country_code":"NP",
    "gn:dem":1543,
    "gn:feature_class":"P",
    "gn:feature_code":"PPLL",
    "gn:name":"Sardardanda",
    "gn:population":0,
    "gn:timezone":"Asia/Kathmandu",
    "iso:country":"NP",
    "wof:name":"Sardardanda",
    "wof:placetype":"locality"
},
  "geometry": {"coordinates":[85.57569000000002,27.57968],"type":"Point"}
}