{
  "type": "Feature",
  "properties": {
    "gn:admin1_code":"ER",
    "gn:admin2_code":"13.0",
    "gn:admin3_code":"14.0",
    "gn:admin4_code":"140015.0",
    "gn:asciiname":"Himma",
    "gn:country_code":"NP",
    "gn:dem":927,
    "gn:feature_class":"P",
    "gn:feature_code":"PPLL",
    "gn:name":"Himma",
    "gn:population":0,
    "gn:timezone":"Asia/Kathmandu",
    "iso:country":"NP",
    "name:ceb_x_preferred":[
        "Himma"
    ],
    "name:deu_x_preferred":[
        "Himma"
    ],
    "name:est_x_preferred":[
        "Himma"
    ],
    "name:hye_x_preferred":[
        "\u0540\u056b\u0574\u0574\u0561"
    ],
    "name:pol_x_preferred":[
        "Himma"
    ],
    "name:sco_x_preferred":[
        "Himma"
    ],
    "name:spa_x_preferred":[
        "Himma"
    ],
    "name:swe_x_preferred":[
        "Himma"
    ],
    "name:ukr_x_preferred":[
        "\u0425\u0456\u043c\u043c\u0430"
    ],
    "name:vol_x_preferred":[
        "Himma"
    ],
    "wof:name":"Himma",
    "wof:placetype":"locality"
},
  "geometry": {"coordinates":[86.68395,27.03582],"type":"Point"}
}