{
  "type": "Feature",
  "properties": {
    "gn:admin1_code":"ER",
    "gn:admin2_code":"13.0",
    "gn:admin3_code":"14.0",
    "gn:admin4_code":"140015.0",
    "gn:asciiname":"Himma",
    "gn:country_code":"NP",
    "gn:dem":927,
    "gn:feature_class":"P",
    "gn:feature_code":"PPLL",
    "gn:name":"Himma",
    "gn:population":0,
    "gn:timezone":"Asia/Kathmandu",
    "iso:country":"NP",
    "wof:name":"Himma",
    "wof:placetype":"locality"
},
  "geometry": {"coordinates":[86.68395,27.03582],"type":"Point"}
}