{
  "type": "Feature",
  "properties": {
    "gn:admin1_code":"ER",
    "gn:admin2_code":"13",
    "gn:admin3_code":"13",
    "gn:admin4_code":"130060",
    "gn:asciiname":"Puranogaun",
    "gn:country_code":"NP",
    "gn:dem":720,
    "gn:feature_class":"P",
    "gn:feature_code":"PPLL",
    "gn:name":"Puranogaun",
    "gn:population":0,
    "gn:timezone":"Asia/Kathmandu",
    "iso:country":"NP",
    "wof:name":"Puranogaun",
    "wof:placetype":"locality"
},
  "geometry": {"coordinates":[86.70858,27.10309],"type":"Point"}
}