{
  "type": "Feature",
  "properties": {
    "gn:admin1_code":"ER",
    "gn:admin2_code":"10",
    "gn:admin3_code":"4.0",
    "gn:admin4_code":"40050.0",
    "gn:asciiname":"Kerkha Bajar",
    "gn:country_code":"NP",
    "gn:dem":137,
    "gn:feature_class":"P",
    "gn:feature_code":"PPLL",
    "gn:name":"Kerkha Bajar",
    "gn:population":0,
    "gn:timezone":"Asia/Kathmandu",
    "iso:country":"NP",
    "wof:name":"Kerkha Bajar",
    "wof:placetype":"locality"
},
  "geometry": {"coordinates":[87.76058,26.64989000000001],"type":"Point"}
}