{
  "type": "Feature",
  "properties": {
    "gn:admin1_code":"MR",
    "gn:admin2_code":"12",
    "gn:admin3_code":"56.0",
    "gn:admin4_code":"560033.0",
    "gn:asciiname":"Lalpur",
    "gn:country_code":"NP",
    "gn:dem":964,
    "gn:feature_class":"P",
    "gn:feature_code":"PPLL",
    "gn:name":"Lalpur",
    "gn:population":0,
    "gn:timezone":"Asia/Kathmandu",
    "iso:country":"NP",
    "wof:name":"Lalpur",
    "wof:placetype":"locality"
},
  "geometry": {"coordinates":[82.23396,28.18454],"type":"Point"}
}