{
  "type": "Feature",
  "properties": {
    "gn:admin1_code":"WR",
    "gn:admin2_code":"3",
    "gn:admin3_code":"45.0",
    "gn:admin4_code":"450010.0",
    "gn:asciiname":"Majhmela",
    "gn:country_code":"NP",
    "gn:dem":1528,
    "gn:feature_class":"P",
    "gn:feature_code":"PPLL",
    "gn:name":"Majhmela",
    "gn:population":0,
    "gn:timezone":"Asia/Kathmandu",
    "iso:country":"NP",
    "wof:name":"Majhmela",
    "wof:placetype":"locality"
},
  "geometry": {"coordinates":[83.58726999999998,28.24226],"type":"Point"}
}