{
  "type": "Feature",
  "properties": {
    "gn:admin1_code":"FR",
    "gn:admin2_code":"14",
    "gn:admin3_code":"70.0",
    "gn:admin4_code":"700015.0",
    "gn:asciiname":"Alibata",
    "gn:country_code":"NP",
    "gn:dem":1098,
    "gn:feature_class":"P",
    "gn:feature_code":"PPLL",
    "gn:name":"Alibata",
    "gn:population":0,
    "gn:timezone":"Asia/Kathmandu",
    "iso:country":"NP",
    "wof:name":"Alibata",
    "wof:placetype":"locality"
},
  "geometry": {"coordinates":[80.77679000000001,29.07266],"type":"Point"}
}