{
  "type": "Feature",
  "properties": {
    "gn:admin1_code":"00",
    "gn:asciiname":"Singane",
    "gn:country_code":"NP",
    "gn:dem":1899,
    "gn:feature_class":"P",
    "gn:feature_code":"PPL",
    "gn:name":"Si\u1e45g\u0101ne",
    "gn:population":0,
    "gn:timezone":"Asia/Kathmandu",
    "iso:country":"NP",
    "wof:name":"Singane",
    "wof:placetype":"locality"
},
  "geometry": {"coordinates":[86.89049,27.34628],"type":"Point"}
}