{
  "type": "Feature",
  "properties": {
    "gn:admin1_code":"MR",
    "gn:admin2_code":"12",
    "gn:admin3_code":"54",
    "gn:admin4_code":"540018",
    "gn:asciiname":"Panchase",
    "gn:country_code":"NP",
    "gn:dem":2541,
    "gn:feature_class":"P",
    "gn:feature_code":"PPLL",
    "gn:name":"Panchase",
    "gn:population":0,
    "gn:timezone":"Asia/Kathmandu",
    "iso:country":"NP",
    "wof:name":"Panchase",
    "wof:placetype":"locality"
},
  "geometry": {"coordinates":[82.81201,28.51671],"type":"Point"}
}