{
  "type": "Feature",
  "properties": {
    "gn:admin1_code":"CR",
    "gn:admin2_code":"1",
    "gn:admin3_code":"28",
    "gn:admin4_code":"280023.0",
    "gn:asciiname":"Ghyalme",
    "gn:country_code":"NP",
    "gn:dem":1575,
    "gn:feature_class":"P",
    "gn:feature_code":"PPLL",
    "gn:name":"Ghyalme",
    "gn:population":0,
    "gn:timezone":"Asia/Kathmandu",
    "iso:country":"NP",
    "wof:name":"Ghyalme",
    "wof:placetype":"locality"
},
  "geometry": {"coordinates":[85.4361,27.97395],"type":"Point"}
}