{
  "type": "Feature",
  "properties": {
    "gn:admin1_code":"CR",
    "gn:admin2_code":"5",
    "gn:admin3_code":"20",
    "gn:admin4_code":"200020",
    "gn:asciiname":"Mathallo Pancharang",
    "gn:country_code":"NP",
    "gn:dem":520,
    "gn:feature_class":"P",
    "gn:feature_code":"PPLL",
    "gn:name":"Mathallo Pancharang",
    "gn:population":0,
    "gn:timezone":"Asia/Kathmandu",
    "iso:country":"NP",
    "wof:name":"Mathallo Pancharang",
    "wof:placetype":"locality"
},
  "geometry": {"coordinates":[86.14149999999999,27.11301],"type":"Point"}
}