{
  "type": "Feature",
  "properties": {
    "gn:admin1_code":"MR",
    "gn:admin2_code":"12",
    "gn:admin3_code":"52",
    "gn:admin4_code":"520025",
    "gn:asciiname":"Deurali",
    "gn:country_code":"NP",
    "gn:dem":1821,
    "gn:feature_class":"P",
    "gn:feature_code":"PPLL",
    "gn:name":"Deurali",
    "gn:population":0,
    "gn:timezone":"Asia/Kathmandu",
    "iso:country":"NP",
    "wof:name":"Deurali",
    "wof:placetype":"locality"
},
  "geometry": {"coordinates":[83.02504,28.17959],"type":"Point"}
}