{
  "type": "Feature",
  "properties": {
    "gn:admin1_code":"MR",
    "gn:admin2_code":"6",
    "gn:admin3_code":"62.0",
    "gn:admin4_code":"620005.0",
    "gn:asciiname":"Kalagauda",
    "gn:country_code":"NP",
    "gn:dem":2099,
    "gn:feature_class":"P",
    "gn:feature_code":"PPLL",
    "gn:name":"Kalagauda",
    "gn:population":0,
    "gn:timezone":"Asia/Kathmandu",
    "iso:country":"NP",
    "wof:name":"Kalagauda",
    "wof:placetype":"locality"
},
  "geometry": {"coordinates":[82.84671999999998,28.97729],"type":"Point"}
}