{
  "type": "Feature",
  "properties": {
    "gn:admin1_code":"FR",
    "gn:admin2_code":"9",
    "gn:admin3_code":"73.0",
    "gn:admin4_code":"730008.0",
    "gn:asciiname":"Dhaulpada",
    "gn:country_code":"NP",
    "gn:dem":650,
    "gn:feature_class":"P",
    "gn:feature_code":"PPLL",
    "gn:name":"Dhaulpada",
    "gn:population":0,
    "gn:timezone":"Asia/Kathmandu",
    "iso:country":"NP",
    "wof:name":"Dhaulpada",
    "wof:placetype":"locality"
},
  "geometry": {"coordinates":[80.39034000000002,29.35024],"type":"Point"}
}