{
  "type": "Feature",
  "properties": {
    "gn:admin1_code":"WR",
    "gn:admin2_code":"8",
    "gn:admin3_code":"50.0",
    "gn:admin4_code":"500044.0",
    "gn:asciiname":"Legana",
    "gn:country_code":"NP",
    "gn:dem":101,
    "gn:feature_class":"P",
    "gn:feature_code":"PPLL",
    "gn:name":"Legana",
    "gn:population":0,
    "gn:timezone":"Asia/Kathmandu",
    "iso:country":"NP",
    "name:ceb_x_preferred":[
        "Legana"
    ],
    "name:swe_x_preferred":[
        "Legana"
    ],
    "wof:name":"Legana",
    "wof:placetype":"locality"
},
  "geometry": {"coordinates":[82.90795,27.53453],"type":"Point"}
}