{
  "type": "Feature",
  "properties": {
    "gn:admin1_code":"ER",
    "gn:admin2_code":"13",
    "gn:admin3_code":"15",
    "gn:admin4_code":"150111",
    "gn:asciiname":"Jagmohan",
    "gn:country_code":"NP",
    "gn:dem":125,
    "gn:feature_class":"P",
    "gn:feature_code":"PPLL",
    "gn:name":"Jagmohan",
    "gn:population":0,
    "gn:timezone":"Asia/Kathmandu",
    "iso:country":"NP",
    "name:hin_x_preferred":[
        "\u091c\u0917 \u092e\u094b\u0939\u0928"
    ],
    "name:ind_x_preferred":[
        "Jagmohan"
    ],
    "name:mar_x_preferred":[
        "\u091c\u0917\u092e\u094b\u0939\u0928"
    ],
    "name:spa_x_preferred":[
        "Jagmohan"
    ],
    "wof:name":"Jagmohan",
    "wof:placetype":"locality"
},
  "geometry": {"coordinates":[86.74308000000001,26.62775],"type":"Point"}
}