{
  "type": "Feature",
  "properties": {
    "gn:admin1_code":"00",
    "gn:asciiname":"Lotin",
    "gn:country_code":"NP",
    "gn:dem":1875,
    "gn:feature_class":"P",
    "gn:feature_code":"PPL",
    "gn:name":"Lo\u1e6di\u1e45",
    "gn:population":0,
    "gn:timezone":"Asia/Kathmandu",
    "iso:country":"NP",
    "wof:name":"Lotin",
    "wof:placetype":"locality"
},
  "geometry": {"coordinates":[86.10535,27.82252],"type":"Point"}
}