{
  "type": "Feature",
  "properties": {
    "gn:admin1_code":"MR",
    "gn:admin2_code":"6",
    "gn:admin3_code":"64.0",
    "gn:admin4_code":"640019.0",
    "gn:asciiname":"Raksar",
    "gn:country_code":"NP",
    "gn:dem":1729,
    "gn:feature_class":"P",
    "gn:feature_code":"PPLL",
    "gn:name":"Raksar",
    "gn:population":0,
    "gn:timezone":"Asia/Kathmandu",
    "iso:country":"NP",
    "wof:name":"Raksar",
    "wof:placetype":"locality"
},
  "geometry": {"coordinates":[81.75882,29.08003],"type":"Point"}
}