{
  "type": "Feature",
  "properties": {
    "gn:admin1_code":"ER",
    "gn:admin2_code":"7",
    "gn:admin3_code":"10.0",
    "gn:admin4_code":"100019.0",
    "gn:asciiname":"Buchakot",
    "gn:country_code":"NP",
    "gn:dem":770,
    "gn:feature_class":"P",
    "gn:feature_code":"PPLL",
    "gn:name":"Buchakot",
    "gn:population":0,
    "gn:timezone":"Asia/Kathmandu",
    "iso:country":"NP",
    "wof:name":"Buchakot",
    "wof:placetype":"locality"
},
  "geometry": {"coordinates":[87.17362,27.30578],"type":"Point"}
}