{
  "type": "Feature",
  "properties": {
    "gn:admin1_code":"00",
    "gn:asciiname":"Kadhaghari",
    "gn:country_code":"NP",
    "gn:dem":1317,
    "gn:feature_class":"P",
    "gn:feature_code":"PPL",
    "gn:name":"K\u0101\u0303\u1e0dh\u0101gh\u0101ri\u0307\u0304",
    "gn:population":0,
    "gn:timezone":"Asia/Kathmandu",
    "iso:country":"NP",
    "name:und_x_variant":[
        "K\u0101\u0303\u1e0dh\u0101gh\u0101ri\u0307\u0304",
        "K\u0101n\u1e0dh\u0101gh\u0101r\u012b"
    ],
    "wof:name":"Kadhaghari",
    "wof:placetype":"locality"
},
  "geometry": {"coordinates":[85.36405000000001,27.69424],"type":"Point"}
}