{
  "type": "Feature",
  "properties": {
    "gn:admin1_code":"ER",
    "gn:admin2_code":"7",
    "gn:admin3_code":"5",
    "gn:admin4_code":"50005",
    "gn:asciiname":"Hoklabaridipu",
    "gn:country_code":"NP",
    "gn:dem":90,
    "gn:feature_class":"P",
    "gn:feature_code":"PPLL",
    "gn:name":"Hoklabaridipu",
    "gn:population":0,
    "gn:timezone":"Asia/Kathmandu",
    "iso:country":"NP",
    "wof:name":"Hoklabaridipu",
    "wof:placetype":"locality"
},
  "geometry": {"coordinates":[87.46319,26.5602],"type":"Point"}
}