{
  "type": "Feature",
  "properties": {
    "gn:admin1_code":"CR",
    "gn:admin2_code":"5",
    "gn:admin3_code":"19",
    "gn:admin4_code":"190076",
    "gn:asciiname":"Sano Phuljordobhan",
    "gn:country_code":"NP",
    "gn:dem":399,
    "gn:feature_class":"P",
    "gn:feature_code":"PPLL",
    "gn:name":"Sano Phuljordobhan",
    "gn:population":0,
    "gn:timezone":"Asia/Kathmandu",
    "iso:country":"NP",
    "wof:name":"Sano Phuljordobhan",
    "wof:placetype":"locality"
},
  "geometry": {"coordinates":[85.76680999999998,27.10681],"type":"Point"}
}