{
  "type": "Feature",
  "properties": {
    "gn:admin1_code":"CR",
    "gn:admin2_code":"1",
    "gn:admin3_code":"30.0",
    "gn:admin4_code":"300034.0",
    "gn:asciiname":"Baniyatar",
    "gn:country_code":"NP",
    "gn:dem":836,
    "gn:feature_class":"P",
    "gn:feature_code":"PPLL",
    "gn:name":"Baniyatar",
    "gn:population":0,
    "gn:timezone":"Asia/Kathmandu",
    "iso:country":"NP",
    "wof:name":"Baniyatar",
    "wof:placetype":"locality"
},
  "geometry": {"coordinates":[85.13569,27.72915],"type":"Point"}
}