{
  "type": "Feature",
  "properties": {
    "gn:admin1_code":"WR",
    "gn:admin2_code":"4",
    "gn:admin3_code":"41",
    "gn:admin4_code":"410013",
    "gn:asciiname":"Plamne",
    "gn:country_code":"NP",
    "gn:dem":2291,
    "gn:feature_class":"P",
    "gn:feature_code":"PPLL",
    "gn:name":"Plamne",
    "gn:population":0,
    "gn:timezone":"Asia/Kathmandu",
    "iso:country":"NP",
    "wof:name":"Plamne",
    "wof:placetype":"locality"
},
  "geometry": {"coordinates":[84.37885,28.54219],"type":"Point"}
}