{
  "type": "Feature",
  "properties": {
    "gn:admin1_code":"WR",
    "gn:admin2_code":"4",
    "gn:admin3_code":"37",
    "gn:admin4_code":"370012",
    "gn:asciiname":"Ghokreswanra",
    "gn:country_code":"NP",
    "gn:dem":724,
    "gn:feature_class":"P",
    "gn:feature_code":"PPLL",
    "gn:name":"Ghokreswanra",
    "gn:population":0,
    "gn:timezone":"Asia/Kathmandu",
    "iso:country":"NP",
    "wof:name":"Ghokreswanra",
    "wof:placetype":"locality"
},
  "geometry": {"coordinates":[84.43621,28.15346],"type":"Point"}
}