{
  "type": "Feature",
  "properties": {
    "gn:admin1_code":"ER",
    "gn:admin2_code":"13",
    "gn:admin3_code":"13.0",
    "gn:admin4_code":"130013.0",
    "gn:asciiname":"Bijgaun",
    "gn:country_code":"NP",
    "gn:dem":1438,
    "gn:feature_class":"P",
    "gn:feature_code":"PPLL",
    "gn:name":"Bijgaun",
    "gn:population":0,
    "gn:timezone":"Asia/Kathmandu",
    "iso:country":"NP",
    "wof:name":"Bijgaun",
    "wof:placetype":"locality"
},
  "geometry": {"coordinates":[86.73559,27.21724],"type":"Point"}
}