{
  "type": "Feature",
  "properties": {
    "gn:admin1_code":"CR",
    "gn:admin2_code":"5",
    "gn:admin3_code":"19",
    "gn:admin4_code":"190043",
    "gn:asciiname":"Barantol",
    "gn:country_code":"NP",
    "gn:dem":169,
    "gn:feature_class":"P",
    "gn:feature_code":"PPLL",
    "gn:name":"Barantol",
    "gn:population":0,
    "gn:timezone":"Asia/Kathmandu",
    "iso:country":"NP",
    "wof:name":"Barantol",
    "wof:placetype":"locality"
},
  "geometry": {"coordinates":[85.66960999999998,27.02873],"type":"Point"}
}