{
  "type": "Feature",
  "properties": {
    "gn:admin1_code":"WR",
    "gn:admin2_code":"4",
    "gn:admin3_code":"36.0",
    "gn:admin4_code":"360021.0",
    "gn:asciiname":"Thapathok",
    "gn:country_code":"NP",
    "gn:dem":1311,
    "gn:feature_class":"P",
    "gn:feature_code":"PPLL",
    "gn:name":"Thapathok",
    "gn:population":0,
    "gn:timezone":"Asia/Kathmandu",
    "iso:country":"NP",
    "wof:name":"Thapathok",
    "wof:placetype":"locality"
},
  "geometry": {"coordinates":[84.64503000000001,28.01599],"type":"Point"}
}