{
  "type": "Feature",
  "properties": {
    "gn:admin1_code":"WR",
    "gn:admin2_code":"3",
    "gn:admin3_code":"45.0",
    "gn:admin4_code":"450013.0",
    "gn:asciiname":"Chamidwar",
    "gn:country_code":"NP",
    "gn:dem":2320,
    "gn:feature_class":"P",
    "gn:feature_code":"PPLL",
    "gn:name":"Chamidwar",
    "gn:population":0,
    "gn:timezone":"Asia/Kathmandu",
    "iso:country":"NP",
    "wof:name":"Chamidwar",
    "wof:placetype":"locality"
},
  "geometry": {"coordinates":[83.09322,28.43875],"type":"Point"}
}