{
  "type": "Feature",
  "properties": {
    "gn:admin1_code":"00",
    "gn:asciiname":"Tilpun",
    "gn:country_code":"NP",
    "gn:dem":1718,
    "gn:feature_class":"P",
    "gn:feature_code":"PPL",
    "gn:name":"Tilpu\u1e45",
    "gn:population":0,
    "gn:timezone":"Asia/Kathmandu",
    "iso:country":"NP",
    "name:nep_x_preferred":[
        "Tilpu\u1e45"
    ],
    "wof:name":"Tilpun",
    "wof:placetype":"locality"
},
  "geometry": {"coordinates":[87.56483,26.88441],"type":"Point"}
}