{
  "type": "Feature",
  "properties": {
    "gn:admin1_code":"MR",
    "gn:admin2_code":"12",
    "gn:admin3_code":"55",
    "gn:admin4_code":"550023",
    "gn:asciiname":"Kolkate",
    "gn:country_code":"NP",
    "gn:dem":1492,
    "gn:feature_class":"P",
    "gn:feature_code":"PPLL",
    "gn:name":"Kolkate",
    "gn:population":0,
    "gn:timezone":"Asia/Kathmandu",
    "iso:country":"NP",
    "wof:name":"Kolkate",
    "wof:placetype":"locality"
},
  "geometry": {"coordinates":[82.14234,28.24391],"type":"Point"}
}