{
  "type": "Feature",
  "properties": {
    "gn:admin1_code":"MR",
    "gn:admin2_code":"6",
    "gn:admin3_code":"63.0",
    "gn:admin4_code":"630028.0",
    "gn:asciiname":"Talium",
    "gn:country_code":"NP",
    "gn:dem":2582,
    "gn:feature_class":"P",
    "gn:feature_code":"PPLL",
    "gn:name":"Talium",
    "gn:population":0,
    "gn:timezone":"Asia/Kathmandu",
    "iso:country":"NP",
    "wof:name":"Talium",
    "wof:placetype":"locality"
},
  "geometry": {"coordinates":[82.13724999999999,29.26446],"type":"Point"}
}