{
  "type": "Feature",
  "properties": {
    "gn:admin1_code":"WR",
    "gn:admin2_code":"4.0",
    "gn:admin3_code":"38.0",
    "gn:admin4_code":"380009.0",
    "gn:asciiname":"Katuwa",
    "gn:country_code":"NP",
    "gn:dem":679,
    "gn:feature_class":"P",
    "gn:feature_code":"PPLL",
    "gn:name":"Katuwa",
    "gn:population":0,
    "gn:timezone":"Asia/Kathmandu",
    "iso:country":"NP",
    "wof:name":"Katuwa",
    "wof:placetype":"locality"
},
  "geometry": {"coordinates":[84.07210000000001,27.99459],"type":"Point"}
}