{
  "type": "Feature",
  "properties": {
    "gn:admin1_code":"MR",
    "gn:admin2_code":"12",
    "gn:admin3_code":"52",
    "gn:admin4_code":"520026",
    "gn:asciiname":"Bhompa",
    "gn:country_code":"NP",
    "gn:dem":1247,
    "gn:feature_class":"P",
    "gn:feature_code":"PPLL",
    "gn:name":"Bhompa",
    "gn:population":0,
    "gn:timezone":"Asia/Kathmandu",
    "iso:country":"NP",
    "wof:name":"Bhompa",
    "wof:placetype":"locality"
},
  "geometry": {"coordinates":[82.61319,28.10106],"type":"Point"}
}