{
  "type": "Feature",
  "properties": {
    "gn:admin1_code":"MR",
    "gn:admin2_code":"12",
    "gn:admin3_code":"52",
    "gn:admin4_code":"520049",
    "gn:asciiname":"Kauchhe Khanda",
    "gn:country_code":"NP",
    "gn:dem":1554,
    "gn:feature_class":"P",
    "gn:feature_code":"PPLL",
    "gn:name":"Kauchhe Khanda",
    "gn:population":0,
    "gn:timezone":"Asia/Kathmandu",
    "iso:country":"NP",
    "wof:name":"Kauchhe Khanda",
    "wof:placetype":"locality"
},
  "geometry": {"coordinates":[82.98184999999999,28.10707],"type":"Point"}
}