{
  "type": "Feature",
  "properties": {
    "gn:admin1_code":"CR",
    "gn:admin2_code":"5",
    "gn:admin3_code":"20",
    "gn:admin4_code":"200047",
    "gn:asciiname":"Sarkigairo",
    "gn:country_code":"NP",
    "gn:dem":709,
    "gn:feature_class":"P",
    "gn:feature_code":"PPLL",
    "gn:name":"Sarkigairo",
    "gn:population":0,
    "gn:timezone":"Asia/Kathmandu",
    "iso:country":"NP",
    "wof:name":"Sarkigairo",
    "wof:placetype":"locality"
},
  "geometry": {"coordinates":[85.96364,27.35714],"type":"Point"}
}