{
  "type": "Feature",
  "properties": {
    "gn:admin1_code":"WR",
    "gn:admin2_code":"4",
    "gn:admin3_code":"37",
    "gn:admin4_code":"370058",
    "gn:asciiname":"Khahare",
    "gn:country_code":"NP",
    "gn:dem":638,
    "gn:feature_class":"P",
    "gn:feature_code":"PPLL",
    "gn:name":"Khahare",
    "gn:population":0,
    "gn:timezone":"Asia/Kathmandu",
    "iso:country":"NP",
    "wof:name":"Khahare",
    "wof:placetype":"locality"
},
  "geometry": {"coordinates":[84.4028,28.14349],"type":"Point"}
}