{
  "type": "Feature",
  "properties": {
    "gn:admin1_code":"00",
    "gn:asciiname":"Bhrankharka",
    "gn:country_code":"NP",
    "gn:dem":3200,
    "gn:feature_class":"P",
    "gn:feature_code":"PPL",
    "gn:name":"Bhr\u0101\u1e45kharka",
    "gn:population":0,
    "gn:timezone":"Asia/Kathmandu",
    "iso:country":"NP",
    "wof:name":"Bhrankharka",
    "wof:placetype":"locality"
},
  "geometry": {"coordinates":[85.39910999999999,28.2459],"type":"Point"}
}