{
  "type": "Feature",
  "properties": {
    "gn:admin1_code":"CR",
    "gn:admin2_code":"1",
    "gn:admin3_code":"24.0",
    "gn:admin4_code":"240002.0",
    "gn:asciiname":"Balawa",
    "gn:country_code":"NP",
    "gn:dem":1624,
    "gn:feature_class":"P",
    "gn:feature_code":"PPLL",
    "gn:name":"Balawa",
    "gn:population":0,
    "gn:timezone":"Asia/Kathmandu",
    "iso:country":"NP",
    "name:bih_x_preferred":[
        "\u092c\u0932\u0935\u093e"
    ],
    "name:ceb_x_preferred":[
        "Balawa"
    ],
    "name:mai_x_preferred":[
        "\u092c\u0932\u0935\u093e"
    ],
    "name:msa_x_preferred":[
        "Balawa"
    ],
    "name:nep_x_preferred":[
        "\u092c\u0932\u0935\u093e"
    ],
    "name:new_x_preferred":[
        "\u092c\u0932\u0935\u093e"
    ],
    "name:pol_x_preferred":[
        "Balawa"
    ],
    "wof:name":"Balawa",
    "wof:placetype":"locality"
},
  "geometry": {"coordinates":[85.53933000000001,27.53197],"type":"Point"}
}