{
  "type": "Feature",
  "properties": {
    "gn:admin1_code":"WR",
    "gn:admin2_code":"4.0",
    "gn:admin3_code":"38.0",
    "gn:admin4_code":"380006.0",
    "gn:asciiname":"Archale Bhanjyang",
    "gn:country_code":"NP",
    "gn:dem":747,
    "gn:feature_class":"P",
    "gn:feature_code":"PPLL",
    "gn:name":"Archale Bhanjyang",
    "gn:population":0,
    "gn:timezone":"Asia/Kathmandu",
    "iso:country":"NP",
    "wof:name":"Archale Bhanjyang",
    "wof:placetype":"locality"
},
  "geometry": {"coordinates":[84.38913000000002,28.05235],"type":"Point"}
}