{
  "type": "Feature",
  "properties": {
    "gn:admin1_code":"WR",
    "gn:admin2_code":"8",
    "gn:admin3_code":"47",
    "gn:admin4_code":"470062",
    "gn:asciiname":"Pakalwa",
    "gn:country_code":"NP",
    "gn:dem":711,
    "gn:feature_class":"P",
    "gn:feature_code":"PPLL",
    "gn:name":"Pakalwa",
    "gn:population":0,
    "gn:timezone":"Asia/Kathmandu",
    "iso:country":"NP",
    "wof:name":"Pakalwa",
    "wof:placetype":"locality"
},
  "geometry": {"coordinates":[83.56219,27.83541],"type":"Point"}
}