{
  "type": "Feature",
  "properties": {
    "gn:admin1_code":"00",
    "gn:asciiname":"Barbote",
    "gn:country_code":"NP",
    "gn:dem":1308,
    "gn:feature_class":"P",
    "gn:feature_code":"PPL",
    "gn:name":"Barbo\u1e6de",
    "gn:population":0,
    "gn:timezone":"Asia/Kathmandu",
    "iso:country":"NP",
    "name:bih_x_preferred":[
        "\u092c\u0930\u092c\u094b\u091f\u0947"
    ],
    "name:ceb_x_preferred":[
        "Barbote"
    ],
    "name:mai_x_preferred":[
        "\u092c\u0930\u092c\u094b\u091f\u0947"
    ],
    "name:msa_x_preferred":[
        "Barbote"
    ],
    "name:nep_x_preferred":[
        "\u092c\u0930\u092c\u094b\u091f\u0947"
    ],
    "name:nld_x_preferred":[
        "Barbote"
    ],
    "name:pol_x_preferred":[
        "Barbote"
    ],
    "wof:name":"Barbote",
    "wof:placetype":"locality"
},
  "geometry": {"coordinates":[86.78945,27.32227],"type":"Point"}
}