{
  "type": "Feature",
  "properties": {
    "gn:admin1_code":"FR",
    "gn:admin2_code":"9",
    "gn:admin3_code":"73.0",
    "gn:admin4_code":"730010.0",
    "gn:asciiname":"Bakal",
    "gn:country_code":"NP",
    "gn:dem":919,
    "gn:feature_class":"P",
    "gn:feature_code":"PPLL",
    "gn:name":"Bakal",
    "gn:population":0,
    "gn:timezone":"Asia/Kathmandu",
    "iso:country":"NP",
    "wof:name":"Bakal",
    "wof:placetype":"locality"
},
  "geometry": {"coordinates":[80.41897,29.35347],"type":"Point"}
}