{
  "type": "Feature",
  "properties": {
    "gn:admin1_code":"MR",
    "gn:admin2_code":"12",
    "gn:admin3_code":"55",
    "gn:admin4_code":"550032",
    "gn:asciiname":"Katigaun",
    "gn:country_code":"NP",
    "gn:dem":1571,
    "gn:feature_class":"P",
    "gn:feature_code":"PPLL",
    "gn:name":"Katigaun",
    "gn:population":0,
    "gn:timezone":"Asia/Kathmandu",
    "iso:country":"NP",
    "wof:name":"Katigaun",
    "wof:placetype":"locality"
},
  "geometry": {"coordinates":[82.12120999999998,28.3796],"type":"Point"}
}