{
  "type": "Feature",
  "properties": {
    "gn:admin1_code":"FR",
    "gn:admin2_code":"9",
    "gn:admin3_code":"74",
    "gn:admin4_code":"740051",
    "gn:asciiname":"Bagwar",
    "gn:country_code":"NP",
    "gn:dem":1494,
    "gn:feature_class":"P",
    "gn:feature_code":"PPLL",
    "gn:name":"Bagwar",
    "gn:population":0,
    "gn:timezone":"Asia/Kathmandu",
    "iso:country":"NP",
    "wof:name":"Bagwar",
    "wof:placetype":"locality"
},
  "geometry": {"coordinates":[80.62161999999999,29.52065],"type":"Point"}
}