{
  "type": "Feature",
  "properties": {
    "gn:admin1_code":"WR",
    "gn:admin2_code":"4",
    "gn:admin3_code":"36.0",
    "gn:admin4_code":"360050.0",
    "gn:asciiname":"Birenchok",
    "gn:country_code":"NP",
    "gn:dem":727,
    "gn:feature_class":"P",
    "gn:feature_code":"PPLL",
    "gn:name":"Birenchok",
    "gn:population":0,
    "gn:timezone":"Asia/Kathmandu",
    "iso:country":"NP",
    "wof:name":"Birenchok",
    "wof:placetype":"locality"
},
  "geometry": {"coordinates":[84.59348,27.97064],"type":"Point"}
}