{
  "type": "Feature",
  "properties": {
    "gn:admin1_code":"CR",
    "gn:admin2_code":"11",
    "gn:admin3_code":"35.0",
    "gn:admin4_code":"350024.0",
    "gn:asciiname":"Kyansirang",
    "gn:country_code":"NP",
    "gn:dem":821,
    "gn:feature_class":"P",
    "gn:feature_code":"PPLL",
    "gn:name":"Kyansirang",
    "gn:population":0,
    "gn:timezone":"Asia/Kathmandu",
    "iso:country":"NP",
    "wof:name":"Kyansirang",
    "wof:placetype":"locality"
},
  "geometry": {"coordinates":[84.75275000000001,27.67131],"type":"Point"}
}