{
  "type": "Feature",
  "properties": {
    "gn:admin1_code":"MR",
    "gn:admin2_code":"12",
    "gn:admin3_code":"54",
    "gn:admin4_code":"540015",
    "gn:asciiname":"Lal paun",
    "gn:country_code":"NP",
    "gn:dem":3858,
    "gn:feature_class":"P",
    "gn:feature_code":"PPLL",
    "gn:name":"Lal paun",
    "gn:population":0,
    "gn:timezone":"Asia/Kathmandu",
    "iso:country":"NP",
    "wof:name":"Lal paun",
    "wof:placetype":"locality"
},
  "geometry": {"coordinates":[82.75922,28.72842],"type":"Point"}
}