{
  "type": "Feature",
  "properties": {
    "gn:admin1_code":"MR",
    "gn:admin2_code":"2",
    "gn:admin3_code":"61.0",
    "gn:admin4_code":"610007.0",
    "gn:asciiname":"Garchhinakharka",
    "gn:country_code":"NP",
    "gn:dem":2684,
    "gn:feature_class":"P",
    "gn:feature_code":"PPLL",
    "gn:name":"Garchhinakharka",
    "gn:population":0,
    "gn:timezone":"Asia/Kathmandu",
    "iso:country":"NP",
    "wof:name":"Garchhinakharka",
    "wof:placetype":"locality"
},
  "geometry": {"coordinates":[82.22790999999999,28.86443],"type":"Point"}
}