{
  "type": "Feature",
  "properties": {
    "gn:admin1_code":"WR",
    "gn:admin2_code":"3",
    "gn:admin3_code":"45.0",
    "gn:admin4_code":"450047.0",
    "gn:asciiname":"Rankhani",
    "gn:country_code":"NP",
    "gn:dem":1567,
    "gn:feature_class":"P",
    "gn:feature_code":"PPLL",
    "gn:name":"Rankhani",
    "gn:population":0,
    "gn:timezone":"Asia/Kathmandu",
    "iso:country":"NP",
    "wof:name":"Rankhani",
    "wof:placetype":"locality"
},
  "geometry": {"coordinates":[83.56134,28.14903],"type":"Point"}
}