{
  "type": "Feature",
  "properties": {
    "gn:admin1_code":"00",
    "gn:asciiname":"Bhada",
    "gn:country_code":"NP",
    "gn:dem":172,
    "gn:feature_class":"P",
    "gn:feature_code":"PPL",
    "gn:name":"Bh\u0101d\u0101",
    "gn:population":0,
    "gn:timezone":"Asia/Kathmandu",
    "iso:country":"NP",
    "name:nep_x_preferred":[
        "Bh\u0101d\u0101"
    ],
    "name:und_x_variant":[
        "Bh\u0101da"
    ],
    "wof:name":"Bhada",
    "wof:placetype":"locality"
},
  "geometry": {"coordinates":[80.73463000000002,28.7052],"type":"Point"}
}