{
  "type": "Feature",
  "properties": {
    "gn:admin1_code":"CR",
    "gn:admin2_code":"5",
    "gn:admin3_code":"18",
    "gn:admin4_code":"180036",
    "gn:asciiname":"Banthapatol",
    "gn:country_code":"NP",
    "gn:dem":285,
    "gn:feature_class":"P",
    "gn:feature_code":"PPLL",
    "gn:name":"Banthapatol",
    "gn:population":0,
    "gn:timezone":"Asia/Kathmandu",
    "iso:country":"NP",
    "wof:name":"Banthapatol",
    "wof:placetype":"locality"
},
  "geometry": {"coordinates":[85.7872,27.06925],"type":"Point"}
}