{
  "type": "Feature",
  "properties": {
    "gn:admin1_code":"CR",
    "gn:admin2_code":"5",
    "gn:admin3_code":"20",
    "gn:admin4_code":"200025",
    "gn:asciiname":"Gadyauligaun",
    "gn:country_code":"NP",
    "gn:dem":509,
    "gn:feature_class":"P",
    "gn:feature_code":"PPLL",
    "gn:name":"Gadyauligaun",
    "gn:population":0,
    "gn:timezone":"Asia/Kathmandu",
    "iso:country":"NP",
    "wof:name":"Gadyauligaun",
    "wof:placetype":"locality"
},
  "geometry": {"coordinates":[85.92713000000001,27.19684],"type":"Point"}
}