{
  "type": "Feature",
  "properties": {
    "gn:admin1_code":"ER",
    "gn:admin2_code":"7",
    "gn:admin3_code":"10.0",
    "gn:admin4_code":"100044.0",
    "gn:asciiname":"Chewa",
    "gn:country_code":"NP",
    "gn:dem":1328,
    "gn:feature_class":"P",
    "gn:feature_code":"PPLL",
    "gn:name":"Chewa",
    "gn:population":0,
    "gn:timezone":"Asia/Kathmandu",
    "iso:country":"NP",
    "name:ceb_x_preferred":[
        "Chewa"
    ],
    "wof:name":"Chewa",
    "wof:placetype":"locality"
},
  "geometry": {"coordinates":[86.97301999999998,27.12374],"type":"Point"}
}