{
  "type": "Feature",
  "properties": {
    "gn:admin1_code":"MR",
    "gn:admin2_code":"12",
    "gn:admin3_code":"56.0",
    "gn:admin4_code":"560026.0",
    "gn:asciiname":"Sajkhuti",
    "gn:country_code":"NP",
    "gn:dem":623,
    "gn:feature_class":"P",
    "gn:feature_code":"PPLL",
    "gn:name":"Sajkhuti",
    "gn:population":0,
    "gn:timezone":"Asia/Kathmandu",
    "iso:country":"NP",
    "wof:name":"Sajkhuti",
    "wof:placetype":"locality"
},
  "geometry": {"coordinates":[82.31452,27.98533],"type":"Point"}
}