{
  "type": "Feature",
  "properties": {
    "gn:admin1_code":"MR",
    "gn:admin2_code":"12",
    "gn:admin3_code":"52",
    "gn:admin4_code":"520036",
    "gn:asciiname":"Bwanse",
    "gn:country_code":"NP",
    "gn:dem":1090,
    "gn:feature_class":"P",
    "gn:feature_code":"PPLL",
    "gn:name":"Bwanse",
    "gn:population":0,
    "gn:timezone":"Asia/Kathmandu",
    "iso:country":"NP",
    "wof:name":"Bwanse",
    "wof:placetype":"locality"
},
  "geometry": {"coordinates":[82.88328,27.97736],"type":"Point"}
}