{
  "type": "Feature",
  "properties": {
    "gn:admin1_code":"00",
    "gn:asciiname":"Tanbade",
    "gn:country_code":"NP",
    "gn:dem":1725,
    "gn:feature_class":"P",
    "gn:feature_code":"PPL",
    "gn:name":"T\u0101\u1e45ba\u1e0de",
    "gn:population":0,
    "gn:timezone":"Asia/Kathmandu",
    "iso:country":"NP",
    "name:nep_x_preferred":[
        "T\u0101\u1e45ba\u1e0de"
    ],
    "wof:name":"Tanbade",
    "wof:placetype":"locality"
},
  "geometry": {"coordinates":[84.92434,28.07164],"type":"Point"}
}