{
  "type": "Feature",
  "properties": {
    "gn:admin1_code":"CR",
    "gn:admin2_code":"1",
    "gn:admin3_code":"28",
    "gn:admin4_code":"280059.0",
    "gn:asciiname":"Chapabote",
    "gn:country_code":"NP",
    "gn:dem":762,
    "gn:feature_class":"P",
    "gn:feature_code":"PPLL",
    "gn:name":"Chapabote",
    "gn:population":0,
    "gn:timezone":"Asia/Kathmandu",
    "iso:country":"NP",
    "wof:name":"Chapabote",
    "wof:placetype":"locality"
},
  "geometry": {"coordinates":[85.2475,27.87392],"type":"Point"}
}