{
  "type": "Feature",
  "properties": {
    "gn:admin1_code":"CR",
    "gn:admin2_code":"5",
    "gn:admin3_code":"20",
    "gn:admin4_code":"200016",
    "gn:asciiname":"Goran",
    "gn:country_code":"NP",
    "gn:dem":445,
    "gn:feature_class":"P",
    "gn:feature_code":"PPLL",
    "gn:name":"Goran",
    "gn:population":0,
    "gn:timezone":"Asia/Kathmandu",
    "iso:country":"NP",
    "wof:name":"Goran",
    "wof:placetype":"locality"
},
  "geometry": {"coordinates":[85.55150999999999,27.34172],"type":"Point"}
}