{
  "type": "Feature",
  "properties": {
    "gn:admin1_code":"FR",
    "gn:admin2_code":"14",
    "gn:admin3_code":"71.0",
    "gn:admin4_code":"710040.0",
    "gn:asciiname":"Lamagara",
    "gn:country_code":"NP",
    "gn:dem":866,
    "gn:feature_class":"P",
    "gn:feature_code":"PPLL",
    "gn:name":"Lamagara",
    "gn:population":0,
    "gn:timezone":"Asia/Kathmandu",
    "iso:country":"NP",
    "wof:name":"Lamagara",
    "wof:placetype":"locality"
},
  "geometry": {"coordinates":[81.24128,28.66775],"type":"Point"}
}