{
  "type": "Feature",
  "properties": {
    "gn:admin1_code":"00",
    "gn:asciiname":"Phoksintar",
    "gn:country_code":"NP",
    "gn:dem":808,
    "gn:feature_class":"P",
    "gn:feature_code":"PPL",
    "gn:name":"Phoksi\u1e45\u1e6d\u0101r",
    "gn:population":0,
    "gn:timezone":"Asia/Kathmandu",
    "iso:country":"NP",
    "wof:name":"Phoksintar",
    "wof:placetype":"locality"
},
  "geometry": {"coordinates":[85.61614,27.37322],"type":"Point"}
}