{
  "type": "Feature",
  "properties": {
    "gn:admin1_code":"MR",
    "gn:admin2_code":"2.0",
    "gn:admin3_code":"59.0",
    "gn:admin4_code":"590029.0",
    "gn:asciiname":"Sundarpurdhamu",
    "gn:country_code":"NP",
    "gn:dem":405,
    "gn:feature_class":"P",
    "gn:feature_code":"PPLL",
    "gn:name":"Sundarpurdhamu",
    "gn:population":0,
    "gn:timezone":"Asia/Kathmandu",
    "iso:country":"NP",
    "wof:name":"Sundarpurdhamu",
    "wof:placetype":"locality"
},
  "geometry": {"coordinates":[81.05395,28.88335],"type":"Point"}
}