{
  "type": "Feature",
  "properties": {
    "gn:admin1_code":"MR",
    "gn:admin2_code":"12",
    "gn:admin3_code":"53",
    "gn:admin4_code":"530046",
    "gn:asciiname":"Kharikholagaun",
    "gn:country_code":"NP",
    "gn:dem":1822,
    "gn:feature_class":"P",
    "gn:feature_code":"PPLL",
    "gn:name":"Kharikholagaun",
    "gn:population":0,
    "gn:timezone":"Asia/Kathmandu",
    "iso:country":"NP",
    "wof:name":"Kharikholagaun",
    "wof:placetype":"locality"
},
  "geometry": {"coordinates":[82.79239,28.20497],"type":"Point"}
}