{
  "type": "Feature",
  "properties": {
    "gn:admin1_code":"CR",
    "gn:admin2_code":"5",
    "gn:admin3_code":"19",
    "gn:admin4_code":"190003",
    "gn:asciiname":"Betaligoldanda",
    "gn:country_code":"NP",
    "gn:dem":291,
    "gn:feature_class":"P",
    "gn:feature_code":"PPLL",
    "gn:name":"Betaligoldanda",
    "gn:population":0,
    "gn:timezone":"Asia/Kathmandu",
    "iso:country":"NP",
    "wof:name":"Betaligoldanda",
    "wof:placetype":"locality"
},
  "geometry": {"coordinates":[85.56814,27.12084],"type":"Point"}
}