{
  "type": "Feature",
  "properties": {
    "gn:admin1_code":"FR",
    "gn:admin2_code":"14",
    "gn:admin3_code":"70.0",
    "gn:admin4_code":"700011.0",
    "gn:asciiname":"Deuthan",
    "gn:country_code":"NP",
    "gn:dem":391,
    "gn:feature_class":"P",
    "gn:feature_code":"PPLL",
    "gn:name":"Deuthan",
    "gn:population":0,
    "gn:timezone":"Asia/Kathmandu",
    "iso:country":"NP",
    "wof:name":"Deuthan",
    "wof:placetype":"locality"
},
  "geometry": {"coordinates":[80.9243,28.946],"type":"Point"}
}