{
  "type": "Feature",
  "properties": {
    "gn:admin1_code":"FR",
    "gn:admin2_code":"9",
    "gn:admin3_code":"75.0",
    "gn:admin4_code":"750031.0",
    "gn:asciiname":"Rapla",
    "gn:country_code":"NP",
    "gn:dem":2329,
    "gn:feature_class":"P",
    "gn:feature_code":"PPLL",
    "gn:name":"Rapla",
    "gn:population":0,
    "gn:timezone":"Asia/Kathmandu",
    "iso:country":"NP",
    "name:ara_x_preferred":[
        "\u0631\u0627\u0628\u0644\u0627"
    ],
    "name:aze_x_preferred":[
        "Rapla"
    ],
    "name:bel_x_preferred":[
        "\u0420\u0430\u043f\u043b\u0430"
    ],
    "name:bul_x_preferred":[
        "\u0420\u0430\u043f\u043b\u0430"
    ],
    "name:ceb_x_preferred":[
        "Rapla"
    ],
    "name:ces_x_preferred":[
        "Rapla"
    ],
    "name:dan_x_preferred":[
        "Rapla"
    ],
    "name:deu_x_preferred":[
        "Rapla"
    ],
    "name:est_x_preferred":[
        "Rapla"
    ],
    "name:fas_x_preferred":[
        "\u0631\u067e\u0644\u0627"
    ],
    "name:fin_x_preferred":[
        "Rapla"
    ],
    "name:fra_x_preferred":[
        "Rapla"
    ],
    "name:heb_x_preferred":[
        "\u05e8\u05d0\u05e4\u05dc\u05d4"
    ],
    "name:hrv_x_preferred":[
        "Rapla"
    ],
    "name:hsb_x_preferred":[
        "Rapla"
    ],
    "name:hun_x_preferred":[
        "Rapla"
    ],
    "name:hye_x_preferred":[
        "\u054c\u0561\u057a\u056c\u0561"
    ],
    "name:ita_x_preferred":[
        "Rapla"
    ],
    "name:kat_x_preferred":[
        "\u10e0\u10d0\u10de\u10da\u10d0"
    ],
    "name:kor_x_preferred":[
        "\ub77c\ud50c\ub77c"
    ],
    "name:lav_x_preferred":[
        "Rapla"
    ],
    "name:lit_x_preferred":[
        "Rapla"
    ],
    "name:mhr_x_preferred":[
        "\u0420\u0430\u043f\u043b\u0430"
    ],
    "name:mrj_x_preferred":[
        "\u0420\u0430\u043f\u043b\u0430"
    ],
    "name:myv_x_preferred":[
        "\u0420\u0430\u043f\u043b\u0430 \u043e\u0448"
    ],
    "name:nld_x_preferred":[
        "Rapla"
    ],
    "name:nno_x_preferred":[
        "Rapla"
    ],
    "name:pol_x_preferred":[
        "Rapla"
    ],
    "name:por_x_preferred":[
        "Rapla"
    ],
    "name:rus_x_preferred":[
        "\u0420\u0430\u043f\u043b\u0430"
    ],
    "name:sco_x_preferred":[
        "Rapla"
    ],
    "name:spa_x_preferred":[
        "Rapla"
    ],
    "name:srp_x_preferred":[
        "\u0420\u0430\u043f\u043b\u0430"
    ],
    "name:swe_x_preferred":[
        "Rapla"
    ],
    "name:tur_x_preferred":[
        "Rapla"
    ],
    "name:udm_x_preferred":[
        "\u0420\u0430\u043f\u043b\u0430"
    ],
    "name:ukr_x_preferred":[
        "\u0420\u0430\u043f\u043b\u0430"
    ],
    "name:urd_x_preferred":[
        "\u0631\u067e\u0644\u0627"
    ],
    "name:vep_x_preferred":[
        "Rapl"
    ],
    "name:vie_x_preferred":[
        "Rapla"
    ],
    "name:vol_x_preferred":[
        "Rapla"
    ],
    "name:zho_x_preferred":[
        "\u62c9\u666e\u62c9"
    ],
    "wof:name":"Rapla",
    "wof:placetype":"locality"
},
  "geometry": {"coordinates":[80.71006,29.9576],"type":"Point"}
}