{
  "type": "Feature",
  "properties": {
    "gn:admin1_code":"CR",
    "gn:admin2_code":"1",
    "gn:admin3_code":"23",
    "gn:admin4_code":"230067",
    "gn:asciiname":"Thapagaun",
    "gn:country_code":"NP",
    "gn:dem":996,
    "gn:feature_class":"P",
    "gn:feature_code":"PPLL",
    "gn:name":"Thapagaun",
    "gn:population":0,
    "gn:timezone":"Asia/Kathmandu",
    "iso:country":"NP",
    "wof:name":"Thapagaun",
    "wof:placetype":"locality"
},
  "geometry": {"coordinates":[85.54253,27.8583],"type":"Point"}
}