{
  "type": "Feature",
  "properties": {
    "gn:admin1_code":"WR",
    "gn:admin2_code":"4",
    "gn:admin3_code":"37",
    "gn:admin4_code":"370056",
    "gn:asciiname":"Taghring",
    "gn:country_code":"NP",
    "gn:dem":1589,
    "gn:feature_class":"P",
    "gn:feature_code":"PPLL",
    "gn:name":"Taghring",
    "gn:population":0,
    "gn:timezone":"Asia/Kathmandu",
    "iso:country":"NP",
    "wof:name":"Taghring",
    "wof:placetype":"locality"
},
  "geometry": {"coordinates":[84.38764,28.37355],"type":"Point"}
}