{
  "type": "Feature",
  "properties": {
    "gn:admin1_code":"ER",
    "gn:admin2_code":"13",
    "gn:admin3_code":"15",
    "gn:admin4_code":"150103",
    "gn:asciiname":"Siddhipur",
    "gn:country_code":"NP",
    "gn:dem":99,
    "gn:feature_class":"P",
    "gn:feature_code":"PPLL",
    "gn:name":"Siddhipur",
    "gn:population":0,
    "gn:timezone":"Asia/Kathmandu",
    "iso:country":"NP",
    "name:bih_x_preferred":[
        "\u0938\u093f\u0926\u094d\u0927\u0940\u092a\u0941\u0930"
    ],
    "name:msa_x_preferred":[
        "Siddhipur"
    ],
    "name:nep_x_preferred":[
        "\u0938\u093f\u0926\u094d\u0927\u0940\u092a\u0941\u0930"
    ],
    "name:pol_x_preferred":[
        "Siddhipur"
    ],
    "wof:name":"Siddhipur",
    "wof:placetype":"locality"
},
  "geometry": {"coordinates":[86.89796,26.62659],"type":"Point"}
}