{
  "type": "Feature",
  "properties": {
    "gn:admin1_code":"WR",
    "gn:admin2_code":"4.0",
    "gn:admin3_code":"39.0",
    "gn:admin4_code":"390011.0",
    "gn:asciiname":"Phoksiyar",
    "gn:country_code":"NP",
    "gn:dem":811,
    "gn:feature_class":"P",
    "gn:feature_code":"PPLL",
    "gn:name":"Phoksiyar",
    "gn:population":0,
    "gn:timezone":"Asia/Kathmandu",
    "iso:country":"NP",
    "wof:name":"Phoksiyar",
    "wof:placetype":"locality"
},
  "geometry": {"coordinates":[83.57356999999998,27.96903],"type":"Point"}
}