{
  "type": "Feature",
  "properties": {
    "gn:admin1_code":"CR",
    "gn:admin2_code":"11",
    "gn:admin3_code":"31",
    "gn:admin4_code":"310023",
    "gn:asciiname":"Ghartigaun",
    "gn:country_code":"NP",
    "gn:dem":905,
    "gn:feature_class":"P",
    "gn:feature_code":"PPLL",
    "gn:name":"Ghartigaun",
    "gn:population":0,
    "gn:timezone":"Asia/Kathmandu",
    "iso:country":"NP",
    "wof:name":"Ghartigaun",
    "wof:placetype":"locality"
},
  "geometry": {"coordinates":[84.93864000000001,27.60357],"type":"Point"}
}