{
  "type": "Feature",
  "properties": {
    "gn:admin1_code":"ER",
    "gn:admin2_code":"7",
    "gn:admin3_code":"7.0",
    "gn:admin4_code":"70014.0",
    "gn:asciiname":"Magsila",
    "gn:country_code":"NP",
    "gn:dem":606,
    "gn:feature_class":"P",
    "gn:feature_code":"PPLL",
    "gn:name":"Magsila",
    "gn:population":0,
    "gn:timezone":"Asia/Kathmandu",
    "iso:country":"NP",
    "wof:name":"Magsila",
    "wof:placetype":"locality"
},
  "geometry": {"coordinates":[87.32613000000001,27.15317000000001],"type":"Point"}
}