{
  "type": "Feature",
  "properties": {
    "gn:admin1_code":"CR",
    "gn:admin2_code":"1",
    "gn:admin3_code":"23",
    "gn:admin4_code":"230051",
    "gn:asciiname":"Gharkaj",
    "gn:country_code":"NP",
    "gn:dem":863,
    "gn:feature_class":"P",
    "gn:feature_code":"PPLL",
    "gn:name":"Gharkaj",
    "gn:population":0,
    "gn:timezone":"Asia/Kathmandu",
    "iso:country":"NP",
    "wof:name":"Gharkaj",
    "wof:placetype":"locality"
},
  "geometry": {"coordinates":[85.84683000000003,27.74908],"type":"Point"}
}