{
  "type": "Feature",
  "properties": {
    "gn:admin1_code":"ER",
    "gn:admin2_code":"13.0",
    "gn:admin3_code":"14.0",
    "gn:admin4_code":"140018.0",
    "gn:asciiname":"Deuraje",
    "gn:country_code":"NP",
    "gn:dem":743,
    "gn:feature_class":"P",
    "gn:feature_code":"PPLL",
    "gn:name":"Deuraje",
    "gn:population":0,
    "gn:timezone":"Asia/Kathmandu",
    "iso:country":"NP",
    "wof:name":"Deuraje",
    "wof:placetype":"locality"
},
  "geometry": {"coordinates":[86.99412,26.86598],"type":"Point"}
}