{
  "type": "Feature",
  "properties": {
    "gn:admin1_code":"WR",
    "gn:admin2_code":"4.0",
    "gn:admin3_code":"39.0",
    "gn:admin4_code":"390021.0",
    "gn:asciiname":"Todke",
    "gn:country_code":"NP",
    "gn:dem":1277,
    "gn:feature_class":"P",
    "gn:feature_code":"PPLL",
    "gn:name":"Todke",
    "gn:population":0,
    "gn:timezone":"Asia/Kathmandu",
    "iso:country":"NP",
    "wof:name":"Todke",
    "wof:placetype":"locality"
},
  "geometry": {"coordinates":[83.83721,28.1209],"type":"Point"}
}