{
  "type": "Feature",
  "properties": {
    "gn:admin1_code":"MR",
    "gn:admin2_code":"12",
    "gn:admin3_code":"53",
    "gn:admin4_code":"530049",
    "gn:asciiname":"Sarpa",
    "gn:country_code":"NP",
    "gn:dem":1263,
    "gn:feature_class":"P",
    "gn:feature_code":"PPLL",
    "gn:name":"Sarpa",
    "gn:population":0,
    "gn:timezone":"Asia/Kathmandu",
    "iso:country":"NP",
    "wof:name":"Sarpa",
    "wof:placetype":"locality"
},
  "geometry": {"coordinates":[82.76348,28.25257],"type":"Point"}
}