{
  "type": "Feature",
  "properties": {
    "gn:admin1_code":"CR",
    "gn:admin2_code":"5",
    "gn:admin3_code":"20",
    "gn:admin4_code":"200034.0",
    "gn:asciiname":"Badara",
    "gn:country_code":"NP",
    "gn:dem":338,
    "gn:feature_class":"P",
    "gn:feature_code":"PPLL",
    "gn:name":"Badara",
    "gn:population":0,
    "gn:timezone":"Asia/Kathmandu",
    "iso:country":"NP",
    "wof:name":"Badara",
    "wof:placetype":"locality"
},
  "geometry": {"coordinates":[85.77834,27.24148],"type":"Point"}
}