{
  "type": "Feature",
  "properties": {
    "gn:admin1_code":"ER",
    "gn:admin2_code":"13",
    "gn:admin3_code":"11",
    "gn:admin4_code":"110031",
    "gn:asciiname":"Bakhabllam",
    "gn:country_code":"NP",
    "gn:dem":1962,
    "gn:feature_class":"P",
    "gn:feature_code":"PPLL",
    "gn:name":"Bakhabllam",
    "gn:population":0,
    "gn:timezone":"Asia/Kathmandu",
    "iso:country":"NP",
    "wof:name":"Bakhabllam",
    "wof:placetype":"locality"
},
  "geometry": {"coordinates":[86.79434999999999,27.50964],"type":"Point"}
}