{
  "type": "Feature",
  "properties": {
    "gn:admin1_code":"MR",
    "gn:admin2_code":"2.0",
    "gn:admin3_code":"57.0",
    "gn:admin4_code":"570031.0",
    "gn:asciiname":"Akalgharwa",
    "gn:country_code":"NP",
    "gn:dem":175,
    "gn:feature_class":"P",
    "gn:feature_code":"PPLL",
    "gn:name":"Akalgharwa",
    "gn:population":0,
    "gn:timezone":"Asia/Kathmandu",
    "iso:country":"NP",
    "wof:name":"Akalgharwa",
    "wof:placetype":"locality"
},
  "geometry": {"coordinates":[81.65732,28.2413],"type":"Point"}
}