{
  "type": "Feature",
  "properties": {
    "gn:admin1_code":"ER",
    "gn:admin2_code":"7.0",
    "gn:admin3_code":"10.0",
    "gn:admin4_code":"100004.0",
    "gn:asciiname":"Timma",
    "gn:country_code":"NP",
    "gn:dem":1418,
    "gn:feature_class":"P",
    "gn:feature_code":"PPLL",
    "gn:name":"Timma",
    "gn:population":0,
    "gn:timezone":"Asia/Kathmandu",
    "iso:country":"NP",
    "name:bih_x_preferred":[
        "\u0924\u093f\u092e\u094d\u092e\u093e"
    ],
    "name:ceb_x_preferred":[
        "Timma"
    ],
    "name:mai_x_preferred":[
        "\u0924\u093f\u092e\u094d\u092e\u093e"
    ],
    "name:msa_x_preferred":[
        "Timma"
    ],
    "name:nep_x_preferred":[
        "\u0924\u093f\u092e\u094d\u092e\u093e"
    ],
    "name:new_x_preferred":[
        "\u0924\u093f\u092e\u094d\u092e\u093e"
    ],
    "name:pol_x_preferred":[
        "Timma"
    ],
    "wof:name":"Timma",
    "wof:placetype":"locality"
},
  "geometry": {"coordinates":[87.03994,27.05938],"type":"Point"}
}