{
  "type": "Feature",
  "properties": {
    "gn:admin1_code":"WR",
    "gn:admin2_code":"4.0",
    "gn:admin3_code":"39.0",
    "gn:admin4_code":"390033.0",
    "gn:asciiname":"Jaukharka",
    "gn:country_code":"NP",
    "gn:dem":809,
    "gn:feature_class":"P",
    "gn:feature_code":"PPLL",
    "gn:name":"Jaukharka",
    "gn:population":0,
    "gn:timezone":"Asia/Kathmandu",
    "iso:country":"NP",
    "wof:name":"Jaukharka",
    "wof:placetype":"locality"
},
  "geometry": {"coordinates":[83.64248000000001,27.91888],"type":"Point"}
}