{
  "type": "Feature",
  "properties": {
    "gn:admin1_code":"CR",
    "gn:admin2_code":"11",
    "gn:admin3_code":"32",
    "gn:admin4_code":"320046",
    "gn:asciiname":"Judibela",
    "gn:country_code":"NP",
    "gn:dem":141,
    "gn:feature_class":"P",
    "gn:feature_code":"PPLL",
    "gn:name":"Judibela",
    "gn:population":0,
    "gn:timezone":"Asia/Kathmandu",
    "iso:country":"NP",
    "wof:name":"Judibela",
    "wof:placetype":"locality"
},
  "geometry": {"coordinates":[85.38925999999999,27.13026],"type":"Point"}
}