{
  "type": "Feature",
  "properties": {
    "gn:admin1_code":"MR",
    "gn:admin2_code":"12",
    "gn:admin3_code":"56.0",
    "gn:admin4_code":"560020.0",
    "gn:asciiname":"Mohan Nagar",
    "gn:country_code":"NP",
    "gn:dem":619,
    "gn:feature_class":"P",
    "gn:feature_code":"PPLL",
    "gn:name":"Mohan Nagar",
    "gn:population":0,
    "gn:timezone":"Asia/Kathmandu",
    "iso:country":"NP",
    "wof:name":"Mohan Nagar",
    "wof:placetype":"locality"
},
  "geometry": {"coordinates":[82.50038000000001,27.9689],"type":"Point"}
}