{
  "type": "Feature",
  "properties": {
    "gn:admin1_code":"ER",
    "gn:admin2_code":"13",
    "gn:admin3_code":"16",
    "gn:admin4_code":"160062",
    "gn:asciiname":"Piparatol",
    "gn:country_code":"NP",
    "gn:dem":72,
    "gn:feature_class":"P",
    "gn:feature_code":"PPLL",
    "gn:name":"Piparatol",
    "gn:population":0,
    "gn:timezone":"Asia/Kathmandu",
    "iso:country":"NP",
    "wof:name":"Piparatol",
    "wof:placetype":"locality"
},
  "geometry": {"coordinates":[86.21296,26.6082],"type":"Point"}
}