{
  "type": "Feature",
  "properties": {
    "gn:admin1_code":"WR",
    "gn:admin2_code":"4",
    "gn:admin3_code":"36.0",
    "gn:admin4_code":"360048.0",
    "gn:asciiname":"Mulabari",
    "gn:country_code":"NP",
    "gn:dem":1244,
    "gn:feature_class":"P",
    "gn:feature_code":"PPLL",
    "gn:name":"Mulabari",
    "gn:population":0,
    "gn:timezone":"Asia/Kathmandu",
    "iso:country":"NP",
    "wof:name":"Mulabari",
    "wof:placetype":"locality"
},
  "geometry": {"coordinates":[84.73324000000002,28.07977],"type":"Point"}
}