{
  "type": "Feature",
  "properties": {
    "gn:admin1_code":"WR",
    "gn:admin2_code":"3",
    "gn:admin3_code":"45.0",
    "gn:admin4_code":"450009.0",
    "gn:asciiname":"Kutula",
    "gn:country_code":"NP",
    "gn:dem":1368,
    "gn:feature_class":"P",
    "gn:feature_code":"PPLL",
    "gn:name":"Kutula",
    "gn:population":0,
    "gn:timezone":"Asia/Kathmandu",
    "iso:country":"NP",
    "wof:name":"Kutula",
    "wof:placetype":"locality"
},
  "geometry": {"coordinates":[83.14108,28.30785],"type":"Point"}
}