{
  "type": "Feature",
  "properties": {
    "gn:admin1_code":"FR",
    "gn:admin2_code":"9",
    "gn:admin3_code":"74",
    "gn:admin4_code":"740062",
    "gn:asciiname":"Pansaini",
    "gn:country_code":"NP",
    "gn:dem":1507,
    "gn:feature_class":"P",
    "gn:feature_code":"PPLL",
    "gn:name":"Pansaini",
    "gn:population":0,
    "gn:timezone":"Asia/Kathmandu",
    "iso:country":"NP",
    "wof:name":"Pansaini",
    "wof:placetype":"locality"
},
  "geometry": {"coordinates":[80.81872,29.40373],"type":"Point"}
}