{
  "type": "Feature",
  "properties": {
    "gn:admin1_code":"CR",
    "gn:admin2_code":"1",
    "gn:admin3_code":"23",
    "gn:admin4_code":"230072",
    "gn:asciiname":"Dhap",
    "gn:country_code":"NP",
    "gn:dem":1215,
    "gn:feature_class":"P",
    "gn:feature_code":"PPLL",
    "gn:name":"Dhap",
    "gn:population":0,
    "gn:timezone":"Asia/Kathmandu",
    "iso:country":"NP",
    "name:ceb_x_preferred":[
        "Dhap"
    ],
    "name:fra_x_preferred":[
        "Dhap"
    ],
    "name:msa_x_preferred":[
        "Dhap"
    ],
    "name:nep_x_preferred":[
        "\u0927\u093e\u092a"
    ],
    "name:new_x_preferred":[
        "\u0927\u093e\u092a"
    ],
    "name:pol_x_preferred":[
        "Dhap"
    ],
    "wof:name":"Dhap",
    "wof:placetype":"locality"
},
  "geometry": {"coordinates":[85.63998000000002,27.91411],"type":"Point"}
}