{
  "type": "Feature",
  "properties": {
    "gn:admin1_code":"WR",
    "gn:admin2_code":"4",
    "gn:admin3_code":"37",
    "gn:admin4_code":"370036.0",
    "gn:asciiname":"Purangaun",
    "gn:country_code":"NP",
    "gn:dem":2051,
    "gn:feature_class":"P",
    "gn:feature_code":"PPLL",
    "gn:name":"Purangaun",
    "gn:population":0,
    "gn:timezone":"Asia/Kathmandu",
    "iso:country":"NP",
    "wof:name":"Purangaun",
    "wof:placetype":"locality"
},
  "geometry": {"coordinates":[84.3489,28.30784],"type":"Point"}
}