{
  "type": "Feature",
  "properties": {
    "gn:admin1_code":"ER",
    "gn:admin2_code":"7",
    "gn:admin3_code":"10.0",
    "gn:admin4_code":"100015.0",
    "gn:asciiname":"Taputol",
    "gn:country_code":"NP",
    "gn:dem":790,
    "gn:feature_class":"P",
    "gn:feature_code":"PPLL",
    "gn:name":"Taputol",
    "gn:population":0,
    "gn:timezone":"Asia/Kathmandu",
    "iso:country":"NP",
    "wof:name":"Taputol",
    "wof:placetype":"locality"
},
  "geometry": {"coordinates":[87.21039,27.19318],"type":"Point"}
}