{
  "type": "Feature",
  "properties": {
    "gn:admin1_code":"FR",
    "gn:admin2_code":"14.0",
    "gn:admin3_code":"67.0",
    "gn:admin4_code":"670010.0",
    "gn:asciiname":"Bajhkot",
    "gn:country_code":"NP",
    "gn:dem":2218,
    "gn:feature_class":"P",
    "gn:feature_code":"PPLL",
    "gn:name":"Bajhkot",
    "gn:population":0,
    "gn:timezone":"Asia/Kathmandu",
    "iso:country":"NP",
    "wof:name":"Bajhkot",
    "wof:placetype":"locality"
},
  "geometry": {"coordinates":[81.26317,29.41619],"type":"Point"}
}