{
  "type": "Feature",
  "properties": {
    "gn:admin1_code":"00",
    "gn:asciiname":"Dadatol",
    "gn:country_code":"NP",
    "gn:dem":176,
    "gn:feature_class":"P",
    "gn:feature_code":"PPL",
    "gn:name":"\u1e0c\u0101\u0303\u1e0d\u0101\u1e6dol",
    "gn:population":0,
    "gn:timezone":"Asia/Kathmandu",
    "iso:country":"NP",
    "name:nep_x_preferred":[
        "\u1e0c\u0101\u0303\u1e0d\u0101\u1e6dol"
    ],
    "wof:name":"Dadatol",
    "wof:placetype":"locality"
},
  "geometry": {"coordinates":[86.66931,26.81619],"type":"Point"}
}