{
  "type": "Feature",
  "properties": {
    "gn:admin1_code":"WR",
    "gn:admin2_code":"8",
    "gn:admin3_code":"47",
    "gn:admin4_code":"470063",
    "gn:asciiname":"Gansai",
    "gn:country_code":"NP",
    "gn:dem":881,
    "gn:feature_class":"P",
    "gn:feature_code":"PPLL",
    "gn:name":"Gansai",
    "gn:population":0,
    "gn:timezone":"Asia/Kathmandu",
    "iso:country":"NP",
    "wof:name":"Gansai",
    "wof:placetype":"locality"
},
  "geometry": {"coordinates":[83.53653,27.84574000000001],"type":"Point"}
}