{
  "type": "Feature",
  "properties": {
    "gn:admin1_code":"FR",
    "gn:admin2_code":"14",
    "gn:admin3_code":"70.0",
    "gn:admin4_code":"700049.0",
    "gn:asciiname":"Sainigaun",
    "gn:country_code":"NP",
    "gn:dem":1715,
    "gn:feature_class":"P",
    "gn:feature_code":"PPLL",
    "gn:name":"Sainigaun",
    "gn:population":0,
    "gn:timezone":"Asia/Kathmandu",
    "iso:country":"NP",
    "wof:name":"Sainigaun",
    "wof:placetype":"locality"
},
  "geometry": {"coordinates":[81.01514,29.38948],"type":"Point"}
}