{
  "type": "Feature",
  "properties": {
    "gn:admin1_code":"WR",
    "gn:admin2_code":"4.0",
    "gn:admin3_code":"38.0",
    "gn:admin4_code":"380030.0",
    "gn:asciiname":"Banjhogara",
    "gn:country_code":"NP",
    "gn:dem":698,
    "gn:feature_class":"P",
    "gn:feature_code":"PPLL",
    "gn:name":"Banjhogara",
    "gn:population":0,
    "gn:timezone":"Asia/Kathmandu",
    "iso:country":"NP",
    "wof:name":"Banjhogara",
    "wof:placetype":"locality"
},
  "geometry": {"coordinates":[84.21485,27.94915],"type":"Point"}
}