{
  "type": "Feature",
  "properties": {
    "gn:admin1_code":"MR",
    "gn:admin2_code":"12",
    "gn:admin3_code":"53",
    "gn:admin4_code":"530010",
    "gn:asciiname":"Larmi",
    "gn:country_code":"NP",
    "gn:dem":1763,
    "gn:feature_class":"P",
    "gn:feature_code":"PPLL",
    "gn:name":"Larmi",
    "gn:population":0,
    "gn:timezone":"Asia/Kathmandu",
    "iso:country":"NP",
    "name:nno_x_preferred":[
        "Larmi"
    ],
    "name:urd_x_preferred":[
        "\u0644\u0627\u0631\u0645\u06cc"
    ],
    "wof:name":"Larmi",
    "wof:placetype":"locality"
},
  "geometry": {"coordinates":[82.85714,28.38066],"type":"Point"}
}