{
  "type": "Feature",
  "properties": {
    "gn:admin1_code":"FR",
    "gn:admin2_code":"14",
    "gn:admin3_code":"68",
    "gn:admin4_code":"680035",
    "gn:asciiname":"Simal Lek",
    "gn:country_code":"NP",
    "gn:dem":1667,
    "gn:feature_class":"P",
    "gn:feature_code":"PPLL",
    "gn:name":"Simal Lek",
    "gn:population":0,
    "gn:timezone":"Asia/Kathmandu",
    "iso:country":"NP",
    "wof:name":"Simal Lek",
    "wof:placetype":"locality"
},
  "geometry": {"coordinates":[81.01438,29.45067],"type":"Point"}
}