{
  "type": "Feature",
  "properties": {
    "gn:admin1_code":"FR",
    "gn:admin2_code":"14",
    "gn:admin3_code":"71.0",
    "gn:admin4_code":"710026.0",
    "gn:asciiname":"Golauri",
    "gn:country_code":"NP",
    "gn:dem":154,
    "gn:feature_class":"P",
    "gn:feature_code":"PPLL",
    "gn:name":"Golauri",
    "gn:population":0,
    "gn:timezone":"Asia/Kathmandu",
    "iso:country":"NP",
    "wof:name":"Golauri",
    "wof:placetype":"locality"
},
  "geometry": {"coordinates":[81.07786,28.53256],"type":"Point"}
}