{
  "type": "Feature",
  "properties": {
    "gn:admin1_code":"MR",
    "gn:admin2_code":"2.0",
    "gn:admin3_code":"58.0",
    "gn:admin4_code":"580008.0",
    "gn:asciiname":"Khaireni",
    "gn:country_code":"NP",
    "gn:dem":175,
    "gn:feature_class":"P",
    "gn:feature_code":"PPLL",
    "gn:name":"Khaireni",
    "gn:population":0,
    "gn:timezone":"Asia/Kathmandu",
    "iso:country":"NP",
    "wof:name":"Khaireni",
    "wof:placetype":"locality"
},
  "geometry": {"coordinates":[81.47091999999998,28.31086],"type":"Point"}
}