{
  "type": "Feature",
  "properties": {
    "gn:admin1_code":"ER",
    "gn:admin2_code":"10",
    "gn:admin3_code":"4.0",
    "gn:admin4_code":"40038.0",
    "gn:asciiname":"Panchgachhi",
    "gn:country_code":"NP",
    "gn:dem":89,
    "gn:feature_class":"P",
    "gn:feature_code":"PPLL",
    "gn:name":"Panchgachhi",
    "gn:population":0,
    "gn:timezone":"Asia/Kathmandu",
    "iso:country":"NP",
    "name:bih_x_preferred":[
        "\u092a\u093e\u0901\u091a\u0917\u093e\u091b\u0940"
    ],
    "name:dty_x_preferred":[
        "\u092a\u093e\u0901\u091a\u0917\u093e\u091b\u0940"
    ],
    "name:fra_x_preferred":[
        "Panchgachhi"
    ],
    "name:hin_x_preferred":[
        "\u092a\u093e\u0901\u091a\u0917\u093e\u091b\u0940"
    ],
    "name:mai_x_preferred":[
        "\u092a\u093e\u0901\u091a\u0917\u093e\u091b\u0940"
    ],
    "name:msa_x_preferred":[
        "Panchganchi"
    ],
    "name:nep_x_preferred":[
        "\u092a\u093e\u0901\u091a\u0917\u093e\u091b\u0940"
    ],
    "name:pol_x_preferred":[
        "Panchgachhi"
    ],
    "wof:name":"Panchgachhi",
    "wof:placetype":"locality"
},
  "geometry": {"coordinates":[87.7976,26.5399],"type":"Point"}
}