{
  "type": "Feature",
  "properties": {
    "gn:admin1_code":"ER",
    "gn:admin2_code":"13.0",
    "gn:admin3_code":"14.0",
    "gn:admin4_code":"140020.0",
    "gn:asciiname":"Bhorlini",
    "gn:country_code":"NP",
    "gn:dem":366,
    "gn:feature_class":"P",
    "gn:feature_code":"PPLL",
    "gn:name":"Bhorlini",
    "gn:population":0,
    "gn:timezone":"Asia/Kathmandu",
    "iso:country":"NP",
    "wof:name":"Bhorlini",
    "wof:placetype":"locality"
},
  "geometry": {"coordinates":[86.73766999999999,27.02966],"type":"Point"}
}