{
  "type": "Feature",
  "properties": {
    "gn:admin1_code":"WR",
    "gn:admin2_code":"4",
    "gn:admin3_code":"40.0",
    "gn:admin4_code":"400038.0",
    "gn:asciiname":"Paniswara",
    "gn:country_code":"NP",
    "gn:dem":1449,
    "gn:feature_class":"P",
    "gn:feature_code":"PPLL",
    "gn:name":"Paniswara",
    "gn:population":0,
    "gn:timezone":"Asia/Kathmandu",
    "iso:country":"NP",
    "wof:name":"Paniswara",
    "wof:placetype":"locality"
},
  "geometry": {"coordinates":[83.79916,28.2922],"type":"Point"}
}