{
  "type": "Feature",
  "properties": {
    "gn:country":"NP",
    "gn:fcode":"ADM3",
    "gn:pop":428385,
    "iso:country":"NP",
    "name:unk_x_variant":[
        "B\u0101nkey"
    ],
    "qs:name":"B\u0101nke",
    "qs:photos_9r":0,
    "qs:photos_sr":0,
    "qs:pop_sr":"10",
    "wof:name":"B\u0101nke",
    "wof:placetype":"localadmin",
    "wof:population":428385
},
  "geometry": {"coordinates":[81.83333,28.16667],"type":"Point"}
}