{
  "type": "Feature",
  "properties": {
    "gn:admin1_code":"ER",
    "gn:admin2_code":"13",
    "gn:admin3_code":"15",
    "gn:admin4_code":"150104",
    "gn:asciiname":"Narahi",
    "gn:country_code":"NP",
    "gn:dem":110,
    "gn:feature_class":"P",
    "gn:feature_code":"PPLL",
    "gn:name":"Narahi",
    "gn:population":0,
    "gn:timezone":"Asia/Kathmandu",
    "iso:country":"NP",
    "name:ceb_x_preferred":[
        "Narahi"
    ],
    "name:fra_x_preferred":[
        "Narahi"
    ],
    "name:hin_x_preferred":[
        "\u0928\u0930\u0939\u0940"
    ],
    "name:mai_x_preferred":[
        "\u0928\u0930\u0939\u0940"
    ],
    "name:msa_x_preferred":[
        "Narahi"
    ],
    "name:nep_x_preferred":[
        "\u0928\u0930\u0939\u0940"
    ],
    "name:new_x_preferred":[
        "\u0928\u0930\u0939\u0940"
    ],
    "name:pol_x_preferred":[
        "Narahi"
    ],
    "wof:name":"Narahi",
    "wof:placetype":"locality"
},
  "geometry": {"coordinates":[86.68755999999998,26.60552],"type":"Point"}
}