{
  "type": "Feature",
  "properties": {
    "gn:admin1_code":"00",
    "gn:asciiname":"Dadagau",
    "gn:country_code":"NP",
    "gn:dem":1375,
    "gn:feature_class":"P",
    "gn:feature_code":"PPL",
    "gn:name":"\u1e0c\u0101\u0303\u1e0d\u0101g\u0101\u0169",
    "gn:population":0,
    "gn:timezone":"Asia/Kathmandu",
    "iso:country":"NP",
    "wof:name":"Dadagau",
    "wof:placetype":"locality"
},
  "geometry": {"coordinates":[86.75093000000003,27.29193],"type":"Point"}
}