{
  "type": "Feature",
  "properties": {
    "gn:admin1_code":"WR",
    "gn:admin2_code":"4",
    "gn:admin3_code":"40.0",
    "gn:admin4_code":"400028.0",
    "gn:asciiname":"Sundaribesi",
    "gn:country_code":"NP",
    "gn:dem":1149,
    "gn:feature_class":"P",
    "gn:feature_code":"PPLL",
    "gn:name":"Sundaribesi",
    "gn:population":0,
    "gn:timezone":"Asia/Kathmandu",
    "iso:country":"NP",
    "wof:name":"Sundaribesi",
    "wof:placetype":"locality"
},
  "geometry": {"coordinates":[84.17394,28.24953],"type":"Point"}
}