{
  "type": "Feature",
  "properties": {
    "gn:admin1_code":"MR",
    "gn:admin2_code":"12",
    "gn:admin3_code":"56.0",
    "gn:admin4_code":"560026.0",
    "gn:asciiname":"Kotalyachaur",
    "gn:country_code":"NP",
    "gn:dem":596,
    "gn:feature_class":"P",
    "gn:feature_code":"PPLL",
    "gn:name":"Kotalyachaur",
    "gn:population":0,
    "gn:timezone":"Asia/Kathmandu",
    "iso:country":"NP",
    "wof:name":"Kotalyachaur",
    "wof:placetype":"locality"
},
  "geometry": {"coordinates":[82.23945999999999,28.01874],"type":"Point"}
}