{
  "type": "Feature",
  "properties": {
    "gn:admin1_code":"CR",
    "gn:admin2_code":"5",
    "gn:admin3_code":"20",
    "gn:admin4_code":"200023",
    "gn:asciiname":"Jyamitar",
    "gn:country_code":"NP",
    "gn:dem":544,
    "gn:feature_class":"P",
    "gn:feature_code":"PPLL",
    "gn:name":"Jyamitar",
    "gn:population":0,
    "gn:timezone":"Asia/Kathmandu",
    "iso:country":"NP",
    "wof:name":"Jyamitar",
    "wof:placetype":"locality"
},
  "geometry": {"coordinates":[86.34958,27.06101],"type":"Point"}
}