{
  "type": "Feature",
  "properties": {
    "gn:admin1_code":"CR",
    "gn:admin2_code":"11.0",
    "gn:admin3_code":"33.0",
    "gn:admin4_code":"330033.0",
    "gn:asciiname":"Amuwa",
    "gn:country_code":"NP",
    "gn:dem":105,
    "gn:feature_class":"P",
    "gn:feature_code":"PPLL",
    "gn:name":"Amuwa",
    "gn:population":0,
    "gn:timezone":"Asia/Kathmandu",
    "iso:country":"NP",
    "wof:name":"Amuwa",
    "wof:placetype":"locality"
},
  "geometry": {"coordinates":[85.03404999999999,27.05765],"type":"Point"}
}