{
  "type": "Feature",
  "properties": {
    "gn:admin1_code":"CR",
    "gn:admin2_code":"5",
    "gn:admin3_code":"21",
    "gn:admin4_code":"210038",
    "gn:asciiname":"Hudil",
    "gn:country_code":"NP",
    "gn:dem":1515,
    "gn:feature_class":"P",
    "gn:feature_code":"PPLL",
    "gn:name":"Hudil",
    "gn:population":0,
    "gn:timezone":"Asia/Kathmandu",
    "iso:country":"NP",
    "wof:name":"Hudil",
    "wof:placetype":"locality"
},
  "geometry": {"coordinates":[86.13261,27.31307],"type":"Point"}
}