{
  "type": "Feature",
  "properties": {
    "gn:admin1_code":"ER",
    "gn:admin2_code":"13.0",
    "gn:admin3_code":"14.0",
    "gn:admin4_code":"140044.0",
    "gn:asciiname":"Dame",
    "gn:country_code":"NP",
    "gn:dem":1394,
    "gn:feature_class":"P",
    "gn:feature_code":"PPLL",
    "gn:name":"Dame",
    "gn:population":0,
    "gn:timezone":"Asia/Kathmandu",
    "iso:country":"NP",
    "name:cat_x_preferred":[
        "Dama"
    ],
    "name:ces_x_preferred":[
        "D\u00e1ma"
    ],
    "name:dan_x_preferred":[
        "Dame"
    ],
    "name:deu_x_preferred":[
        "Dame"
    ],
    "name:epo_x_preferred":[
        "Damo"
    ],
    "name:hun_x_preferred":[
        "Dame"
    ],
    "name:ita_x_preferred":[
        "Dame"
    ],
    "name:nor_x_preferred":[
        "Dame"
    ],
    "name:pol_x_preferred":[
        "Dame"
    ],
    "name:por_x_preferred":[
        "Dame"
    ],
    "name:spa_x_preferred":[
        "Dame"
    ],
    "name:srp_x_preferred":[
        "\u0414\u0430\u043c\u0430"
    ],
    "name:swe_x_preferred":[
        "Dame"
    ],
    "name:tha_x_preferred":[
        "\u0e40\u0e14\u0e21"
    ],
    "name:zho_x_preferred":[
        "\u5973\u7235\u58eb"
    ],
    "wof:name":"Dame",
    "wof:placetype":"locality"
},
  "geometry": {"coordinates":[86.59371999999998,26.96173],"type":"Point"}
}