{
  "type": "Feature",
  "properties": {
    "gn:admin1_code":"FR",
    "gn:admin2_code":"9",
    "gn:admin3_code":"74",
    "gn:admin4_code":"740059",
    "gn:asciiname":"Sai",
    "gn:country_code":"NP",
    "gn:dem":1165,
    "gn:feature_class":"P",
    "gn:feature_code":"PPLL",
    "gn:name":"Sai",
    "gn:population":0,
    "gn:timezone":"Asia/Kathmandu",
    "iso:country":"NP",
    "name:ara_x_preferred":[
        "\u0633\u0627\u064a"
    ],
    "name:cat_x_preferred":[
        "Sai"
    ],
    "name:cdo_x_preferred":[
        "S\u0103i"
    ],
    "name:ceb_x_preferred":[
        "Sai"
    ],
    "name:est_x_preferred":[
        "Sai"
    ],
    "name:fra_x_preferred":[
        "Sai"
    ],
    "name:ind_x_preferred":[
        "Sai"
    ],
    "name:msa_x_preferred":[
        "Sai"
    ],
    "name:nld_x_preferred":[
        "Sai"
    ],
    "name:pol_x_preferred":[
        "Sai"
    ],
    "name:por_x_preferred":[
        "Sai"
    ],
    "name:spa_x_preferred":[
        "Sai"
    ],
    "name:swe_x_preferred":[
        "Sai"
    ],
    "wof:name":"Sai",
    "wof:placetype":"locality"
},
  "geometry": {"coordinates":[80.44853000000001,29.59709],"type":"Point"}
}