{
  "type": "Feature",
  "properties": {
    "gn:admin1_code":"ER",
    "gn:admin2_code":"13",
    "gn:admin3_code":"13",
    "gn:admin4_code":"130059",
    "gn:asciiname":"Phataksi",
    "gn:country_code":"NP",
    "gn:dem":1461,
    "gn:feature_class":"P",
    "gn:feature_code":"PPLL",
    "gn:name":"Phataksi",
    "gn:population":0,
    "gn:timezone":"Asia/Kathmandu",
    "iso:country":"NP",
    "wof:name":"Phataksi",
    "wof:placetype":"locality"
},
  "geometry": {"coordinates":[86.69601,27.35657],"type":"Point"}
}