{
  "type": "Feature",
  "properties": {
    "gn:admin1_code":"CR",
    "gn:admin2_code":"5",
    "gn:admin3_code":"22.0",
    "gn:admin4_code":"220041.0",
    "gn:asciiname":"Chilaunekharka",
    "gn:country_code":"NP",
    "gn:dem":1524,
    "gn:feature_class":"P",
    "gn:feature_code":"PPLL",
    "gn:name":"Chilaunekharka",
    "gn:population":0,
    "gn:timezone":"Asia/Kathmandu",
    "iso:country":"NP",
    "wof:name":"Chilaunekharka",
    "wof:placetype":"locality"
},
  "geometry": {"coordinates":[86.14883,27.62236],"type":"Point"}
}