{
  "type": "Feature",
  "properties": {
    "gn:admin1_code":"MR",
    "gn:admin2_code":"12",
    "gn:admin3_code":"55",
    "gn:admin4_code":"550005",
    "gn:asciiname":"Pukhatkholagaun",
    "gn:country_code":"NP",
    "gn:dem":1189,
    "gn:feature_class":"P",
    "gn:feature_code":"PPLL",
    "gn:name":"Pukhatkholagaun",
    "gn:population":0,
    "gn:timezone":"Asia/Kathmandu",
    "iso:country":"NP",
    "wof:name":"Pukhatkholagaun",
    "wof:placetype":"locality"
},
  "geometry": {"coordinates":[82.29253,28.53604],"type":"Point"}
}