{
  "type": "Feature",
  "properties": {
    "gn:admin1_code":"MR",
    "gn:admin2_code":"12",
    "gn:admin3_code":"52",
    "gn:admin4_code":"520006",
    "gn:asciiname":"Dahachaur",
    "gn:country_code":"NP",
    "gn:dem":782,
    "gn:feature_class":"P",
    "gn:feature_code":"PPLL",
    "gn:name":"Dahachaur",
    "gn:population":0,
    "gn:timezone":"Asia/Kathmandu",
    "iso:country":"NP",
    "name:ceb_x_preferred":[
        "Dahachaur"
    ],
    "name:fra_x_preferred":[
        "Dahachaur"
    ],
    "name:msa_x_preferred":[
        "Dahachaur"
    ],
    "name:nep_x_preferred":[
        "\u0926\u0939\u091a\u094c\u0930"
    ],
    "name:new_x_preferred":[
        "\u0926\u0939\u091a\u094c\u0930"
    ],
    "name:pol_x_preferred":[
        "Dahachaur"
    ],
    "wof:name":"Dahachaur",
    "wof:placetype":"locality"
},
  "geometry": {"coordinates":[82.73510999999998,28.14281],"type":"Point"}
}