{
  "type": "Feature",
  "properties": {
    "gn:admin1_code":"ER",
    "gn:admin2_code":"10",
    "gn:admin3_code":"3.0",
    "gn:admin4_code":"30022.0",
    "gn:asciiname":"Malbase",
    "gn:country_code":"NP",
    "gn:dem":934,
    "gn:feature_class":"P",
    "gn:feature_code":"PPLL",
    "gn:name":"Malbase",
    "gn:population":0,
    "gn:timezone":"Asia/Kathmandu",
    "iso:country":"NP",
    "wof:name":"Malbase",
    "wof:placetype":"locality"
},
  "geometry": {"coordinates":[88.00209,26.83503],"type":"Point"}
}