{
  "type": "Feature",
  "properties": {
    "gn:admin1_code":"WR",
    "gn:admin2_code":"3",
    "gn:admin3_code":"45.0",
    "gn:admin4_code":"450038.0",
    "gn:asciiname":"Tallo Hatiya",
    "gn:country_code":"NP",
    "gn:dem":1023,
    "gn:feature_class":"P",
    "gn:feature_code":"PPLL",
    "gn:name":"Tallo Hatiya",
    "gn:population":0,
    "gn:timezone":"Asia/Kathmandu",
    "iso:country":"NP",
    "wof:name":"Tallo Hatiya",
    "wof:placetype":"locality"
},
  "geometry": {"coordinates":[83.66204,28.22108],"type":"Point"}
}