{
  "type": "Feature",
  "properties": {
    "gn:admin1_code":"CR",
    "gn:admin2_code":"1",
    "gn:admin3_code":"28",
    "gn:admin4_code":"280040",
    "gn:asciiname":"Karkigaun",
    "gn:country_code":"NP",
    "gn:dem":1091,
    "gn:feature_class":"P",
    "gn:feature_code":"PPLL",
    "gn:name":"Karkigaun",
    "gn:population":0,
    "gn:timezone":"Asia/Kathmandu",
    "iso:country":"NP",
    "wof:name":"Karkigaun",
    "wof:placetype":"locality"
},
  "geometry": {"coordinates":[85.17593000000002,28.00104],"type":"Point"}
}