{
  "type": "Feature",
  "properties": {
    "gn:admin1_code":"FR",
    "gn:admin2_code":"14",
    "gn:admin3_code":"70.0",
    "gn:admin4_code":"700008.0",
    "gn:asciiname":"Dandakhali",
    "gn:country_code":"NP",
    "gn:dem":1542,
    "gn:feature_class":"P",
    "gn:feature_code":"PPLL",
    "gn:name":"Dandakhali",
    "gn:population":0,
    "gn:timezone":"Asia/Kathmandu",
    "iso:country":"NP",
    "name:ceb_x_preferred":[
        "Dandakhali"
    ],
    "name:fra_x_preferred":[
        "Dandakhali"
    ],
    "name:mai_x_preferred":[
        "\u0921\u093e\u0901\u0921\u093e\u0916\u093e\u0932\u0940"
    ],
    "name:msa_x_preferred":[
        "Dandakhali"
    ],
    "name:nep_x_preferred":[
        "\u0921\u093e\u0901\u0921\u093e\u0916\u093e\u0932\u0940"
    ],
    "name:new_x_preferred":[
        "\u0921\u093e\u0902\u0921\u093e\u0916\u0932\u0940"
    ],
    "name:pol_x_preferred":[
        "Dandakhali"
    ],
    "wof:name":"Dandakhali",
    "wof:placetype":"locality"
},
  "geometry": {"coordinates":[80.57468,29.06746],"type":"Point"}
}