{
  "type": "Feature",
  "properties": {
    "gn:admin1_code":"WR",
    "gn:admin2_code":"8",
    "gn:admin3_code":"47",
    "gn:admin4_code":"470020",
    "gn:asciiname":"Nuwakot",
    "gn:country_code":"NP",
    "gn:dem":784,
    "gn:feature_class":"P",
    "gn:feature_code":"PPLL",
    "gn:name":"Nuwakot",
    "gn:population":0,
    "gn:timezone":"Asia/Kathmandu",
    "iso:country":"NP",
    "name:pol_x_preferred":[
        "Nuwakot"
    ],
    "wof:name":"Nuwakot",
    "wof:placetype":"locality"
},
  "geometry": {"coordinates":[83.45352,27.73105],"type":"Point"}
}