{
  "type": "Feature",
  "properties": {
    "gn:admin1_code":"CR",
    "gn:admin2_code":"11",
    "gn:admin3_code":"32",
    "gn:admin4_code":"320083.0",
    "gn:asciiname":"Khap",
    "gn:country_code":"NP",
    "gn:dem":80,
    "gn:feature_class":"P",
    "gn:feature_code":"PPLL",
    "gn:name":"Khap",
    "gn:population":0,
    "gn:timezone":"Asia/Kathmandu",
    "iso:country":"NP",
    "name:hin_x_preferred":[
        "\u0916\u093e\u092a"
    ],
    "name:tam_x_preferred":[
        "\u0ba8\u0bbe\u0b9f\u0bcd\u0b9f\u0bbe\u0bae\u0bc8"
    ],
    "wof:name":"Khap",
    "wof:placetype":"locality"
},
  "geometry": {"coordinates":[85.19561999999998,26.8263],"type":"Point"}
}