{
  "type": "Feature",
  "properties": {
    "gn:admin1_code":"WR",
    "gn:admin2_code":"4",
    "gn:admin3_code":"37",
    "gn:admin4_code":"370045",
    "gn:asciiname":"Kharetar",
    "gn:country_code":"NP",
    "gn:dem":630,
    "gn:feature_class":"P",
    "gn:feature_code":"PPLL",
    "gn:name":"Kharetar",
    "gn:population":0,
    "gn:timezone":"Asia/Kathmandu",
    "iso:country":"NP",
    "wof:name":"Kharetar",
    "wof:placetype":"locality"
},
  "geometry": {"coordinates":[84.38906999999998,28.13144],"type":"Point"}
}