{
  "type": "Feature",
  "properties": {
    "gn:admin1_code":"WR",
    "gn:admin2_code":"3",
    "gn:admin3_code":"44",
    "gn:admin4_code":"440029",
    "gn:asciiname":"Hile",
    "gn:country_code":"NP",
    "gn:dem":1679,
    "gn:feature_class":"P",
    "gn:feature_code":"PPLL",
    "gn:name":"Hile",
    "gn:population":0,
    "gn:timezone":"Asia/Kathmandu",
    "iso:country":"NP",
    "name:nep_x_preferred":[
        "\u0939\u093f\u0932\u0947 \u092c\u091c\u093e\u0930"
    ],
    "wof:name":"Hile",
    "wof:placetype":"locality"
},
  "geometry": {"coordinates":[83.74824,28.18672],"type":"Point"}
}