{
  "type": "Feature",
  "properties": {
    "gn:admin1_code":"CR",
    "gn:admin2_code":"5",
    "gn:admin3_code":"21",
    "gn:admin4_code":"210032",
    "gn:asciiname":"Tahar",
    "gn:country_code":"NP",
    "gn:dem":778,
    "gn:feature_class":"P",
    "gn:feature_code":"PPLL",
    "gn:name":"Tahar",
    "gn:population":0,
    "gn:timezone":"Asia/Kathmandu",
    "iso:country":"NP",
    "wof:name":"Tahar",
    "wof:placetype":"locality"
},
  "geometry": {"coordinates":[85.91985,27.43237],"type":"Point"}
}