{
  "type": "Feature",
  "properties": {
    "gn:admin1_code":"00",
    "gn:asciiname":"Paiyupani",
    "gn:country_code":"NP",
    "gn:dem":1615,
    "gn:feature_class":"P",
    "gn:feature_code":"PPL",
    "gn:name":"Paiy\u0169p\u0101ni\u0307\u0304",
    "gn:population":0,
    "gn:timezone":"Asia/Kathmandu",
    "iso:country":"NP",
    "name:nep_x_preferred":[
        "Paiy\u0169p\u0101ni\u0307\u0304"
    ],
    "name:nep_x_variant":[
        "Paiyunp\u0101n\u012b"
    ],
    "wof:name":"Paiyupani",
    "wof:placetype":"locality"
},
  "geometry": {"coordinates":[85.50889000000002,27.77263],"type":"Point"}
}