{
  "type": "Feature",
  "properties": {
    "gn:admin1_code":"ER",
    "gn:admin2_code":"13.0",
    "gn:admin3_code":"14.0",
    "gn:admin4_code":"140025.0",
    "gn:asciiname":"Dahar",
    "gn:country_code":"NP",
    "gn:dem":1727,
    "gn:feature_class":"P",
    "gn:feature_code":"PPLL",
    "gn:name":"Dahar",
    "gn:population":0,
    "gn:timezone":"Asia/Kathmandu",
    "iso:country":"NP",
    "wof:name":"Dahar",
    "wof:placetype":"locality"
},
  "geometry": {"coordinates":[86.63450999999998,27.02858],"type":"Point"}
}