{
  "type": "Feature",
  "properties": {
    "gn:admin1_code":"FR",
    "gn:admin2_code":"14.0",
    "gn:admin3_code":"69.0",
    "gn:admin4_code":"690046.0",
    "gn:asciiname":"Ramdithala",
    "gn:country_code":"NP",
    "gn:dem":2194,
    "gn:feature_class":"P",
    "gn:feature_code":"PPLL",
    "gn:name":"Ramdithala",
    "gn:population":0,
    "gn:timezone":"Asia/Kathmandu",
    "iso:country":"NP",
    "wof:name":"Ramdithala",
    "wof:placetype":"locality"
},
  "geometry": {"coordinates":[81.34958,29.12534],"type":"Point"}
}