{
  "type": "Feature",
  "properties": {
    "gn:admin1_code":"ER",
    "gn:admin2_code":"10.0",
    "gn:admin3_code":"1.0",
    "gn:admin4_code":"10036.0",
    "gn:asciiname":"Santhakra",
    "gn:country_code":"NP",
    "gn:dem":1322,
    "gn:feature_class":"P",
    "gn:feature_code":"PPLL",
    "gn:name":"Santhakra",
    "gn:population":0,
    "gn:timezone":"Asia/Kathmandu",
    "iso:country":"NP",
    "name:bih_x_preferred":[
        "\u0938\u093e\u0928\u094d\u0925\u093e\u0915\u094d\u0930\u093e"
    ],
    "name:ceb_x_preferred":[
        "Santhakra"
    ],
    "name:fra_x_preferred":[
        "Santhakra"
    ],
    "name:mai_x_preferred":[
        "\u0938\u093e\u0928\u094d\u0925\u093e\u0915\u094d\u0930\u093e"
    ],
    "name:msa_x_preferred":[
        "Santhakra"
    ],
    "name:nep_x_preferred":[
        "\u0938\u093e\u0928\u094d\u0925\u093e\u0915\u094d\u0930\u093e"
    ],
    "name:new_x_preferred":[
        "\u0938\u0928\u094d\u0925\u0915\u094d\u0930\u093e"
    ],
    "name:pol_x_preferred":[
        "Santhakra"
    ],
    "wof:name":"Santhakra",
    "wof:placetype":"locality"
},
  "geometry": {"coordinates":[87.61093000000002,27.38335],"type":"Point"}
}