{
  "type": "Feature",
  "properties": {
    "gn:admin1_code":"WR",
    "gn:admin2_code":"8",
    "gn:admin3_code":"47",
    "gn:admin4_code":"470039",
    "gn:asciiname":"Bhujunge",
    "gn:country_code":"NP",
    "gn:dem":541,
    "gn:feature_class":"P",
    "gn:feature_code":"PPLL",
    "gn:name":"Bhujunge",
    "gn:population":0,
    "gn:timezone":"Asia/Kathmandu",
    "iso:country":"NP",
    "wof:name":"Bhujunge",
    "wof:placetype":"locality"
},
  "geometry": {"coordinates":[83.53426,27.93766],"type":"Point"}
}