{
  "type": "Feature",
  "properties": {
    "gn:admin1_code":"FR",
    "gn:admin2_code":"9",
    "gn:admin3_code":"75.0",
    "gn:admin4_code":"750024.0",
    "gn:asciiname":"Sundamunda",
    "gn:country_code":"NP",
    "gn:dem":2012,
    "gn:feature_class":"P",
    "gn:feature_code":"PPLL",
    "gn:name":"Sundamunda",
    "gn:population":0,
    "gn:timezone":"Asia/Kathmandu",
    "iso:country":"NP",
    "wof:name":"Sundamunda",
    "wof:placetype":"locality"
},
  "geometry": {"coordinates":[80.64105000000001,29.79737],"type":"Point"}
}