{
  "type": "Feature",
  "properties": {
    "gn:admin1_code":"FR",
    "gn:admin2_code":"14",
    "gn:admin3_code":"71.0",
    "gn:admin4_code":"710001.0",
    "gn:asciiname":"Chauri",
    "gn:country_code":"NP",
    "gn:dem":172,
    "gn:feature_class":"P",
    "gn:feature_code":"PPLL",
    "gn:name":"Chauri",
    "gn:population":0,
    "gn:timezone":"Asia/Kathmandu",
    "iso:country":"NP",
    "wof:name":"Chauri",
    "wof:placetype":"locality"
},
  "geometry": {"coordinates":[81.12858,28.61487],"type":"Point"}
}