{
  "type": "Feature",
  "properties": {
    "gn:admin1_code":"CR",
    "gn:admin2_code":"1",
    "gn:admin3_code":"28",
    "gn:admin4_code":"280007",
    "gn:asciiname":"Komo",
    "gn:country_code":"NP",
    "gn:dem":1634,
    "gn:feature_class":"P",
    "gn:feature_code":"PPLL",
    "gn:name":"Komo",
    "gn:population":0,
    "gn:timezone":"Asia/Kathmandu",
    "iso:country":"NP",
    "name:bul_x_preferred":[
        "\u041a\u043e\u043c\u043e"
    ],
    "name:deu_x_preferred":[
        "Komo"
    ],
    "name:fra_x_preferred":[
        "Komo"
    ],
    "name:lav_x_preferred":[
        "Komo"
    ],
    "name:mkd_x_preferred":[
        "\u041a\u043e\u043c\u043e"
    ],
    "name:oss_x_preferred":[
        "\u041a\u043e\u043c\u043e"
    ],
    "name:rus_x_preferred":[
        "\u041a\u043e\u043c\u043e"
    ],
    "name:srp_x_preferred":[
        "\u041a\u043e\u043c\u043e"
    ],
    "name:swe_x_preferred":[
        "Komo"
    ],
    "name:ukr_x_preferred":[
        "\u041a\u043e\u043c\u043e"
    ],
    "wof:name":"Komo",
    "wof:placetype":"locality"
},
  "geometry": {"coordinates":[85.11466999999998,28.0177],"type":"Point"}
}