{
  "type": "Feature",
  "properties": {
    "gn:admin1_code":"FR",
    "gn:admin2_code":"14",
    "gn:admin3_code":"69",
    "gn:admin4_code":"690026",
    "gn:asciiname":"Lamakanne",
    "gn:country_code":"NP",
    "gn:dem":1058,
    "gn:feature_class":"P",
    "gn:feature_code":"PPLL",
    "gn:name":"Lamakanne",
    "gn:population":0,
    "gn:timezone":"Asia/Kathmandu",
    "iso:country":"NP",
    "wof:name":"Lamakanne",
    "wof:placetype":"locality"
},
  "geometry": {"coordinates":[81.29822,28.95605],"type":"Point"}
}