{
  "type": "Feature",
  "properties": {
    "gn:admin1_code":"WR",
    "gn:admin2_code":"4.0",
    "gn:admin3_code":"39.0",
    "gn:admin4_code":"390056.0",
    "gn:asciiname":"Thula Dihi",
    "gn:country_code":"NP",
    "gn:dem":958,
    "gn:feature_class":"P",
    "gn:feature_code":"PPLL",
    "gn:name":"Thula Dihi",
    "gn:population":0,
    "gn:timezone":"Asia/Kathmandu",
    "iso:country":"NP",
    "wof:name":"Thula Dihi",
    "wof:placetype":"locality"
},
  "geometry": {"coordinates":[83.9229,28.10576],"type":"Point"}
}