{
  "type": "Feature",
  "properties": {
    "gn:admin1_code":"FR",
    "gn:admin2_code":"14.0",
    "gn:admin3_code":"67.0",
    "gn:admin4_code":"670024.0",
    "gn:asciiname":"Samalgaun",
    "gn:country_code":"NP",
    "gn:dem":1956,
    "gn:feature_class":"P",
    "gn:feature_code":"PPLL",
    "gn:name":"Samalgaun",
    "gn:population":0,
    "gn:timezone":"Asia/Kathmandu",
    "iso:country":"NP",
    "wof:name":"Samalgaun",
    "wof:placetype":"locality"
},
  "geometry": {"coordinates":[81.62090999999999,29.48728],"type":"Point"}
}