{
  "type": "Feature",
  "properties": {
    "gn:admin1_code":"FR",
    "gn:admin2_code":"14",
    "gn:admin3_code":"70.0",
    "gn:admin4_code":"700032.0",
    "gn:asciiname":"Lamakhadi",
    "gn:country_code":"NP",
    "gn:dem":1454,
    "gn:feature_class":"P",
    "gn:feature_code":"PPLL",
    "gn:name":"Lamakhadi",
    "gn:population":0,
    "gn:timezone":"Asia/Kathmandu",
    "iso:country":"NP",
    "wof:name":"Lamakhadi",
    "wof:placetype":"locality"
},
  "geometry": {"coordinates":[80.97351999999999,29.05461],"type":"Point"}
}