{
  "type": "Feature",
  "properties": {
    "gn:admin1_code":"CR",
    "gn:admin2_code":"5",
    "gn:admin3_code":"17.0",
    "gn:admin4_code":"170047.0",
    "gn:asciiname":"Tarahi",
    "gn:country_code":"NP",
    "gn:dem":73,
    "gn:feature_class":"P",
    "gn:feature_code":"PPLL",
    "gn:name":"Tarahi",
    "gn:population":0,
    "gn:timezone":"Asia/Kathmandu",
    "iso:country":"NP",
    "name:ceb_x_preferred":[
        "Tarahi"
    ],
    "name:msa_x_preferred":[
        "Tarahi"
    ],
    "name:new_x_preferred":[
        "\u0924\u0930\u093e\u0939\u0940"
    ],
    "name:pol_x_preferred":[
        "Tarahi"
    ],
    "wof:name":"Tarahi",
    "wof:placetype":"locality"
},
  "geometry": {"coordinates":[85.99436,26.66242],"type":"Point"}
}