{
  "type": "Feature",
  "properties": {
    "gn:admin1_code":"WR",
    "gn:admin2_code":"4.0",
    "gn:admin3_code":"38.0",
    "gn:admin4_code":"380025.0",
    "gn:asciiname":"Mathillo Setang",
    "gn:country_code":"NP",
    "gn:dem":946,
    "gn:feature_class":"P",
    "gn:feature_code":"PPLL",
    "gn:name":"Mathillo Setang",
    "gn:population":0,
    "gn:timezone":"Asia/Kathmandu",
    "iso:country":"NP",
    "wof:name":"Mathillo Setang",
    "wof:placetype":"locality"
},
  "geometry": {"coordinates":[84.25254,27.92319],"type":"Point"}
}