{
  "type": "Feature",
  "properties": {
    "gn:admin1_code":"WR",
    "gn:admin2_code":"4",
    "gn:admin3_code":"40.0",
    "gn:admin4_code":"400022.0",
    "gn:asciiname":"Male Patan",
    "gn:country_code":"NP",
    "gn:dem":632,
    "gn:feature_class":"P",
    "gn:feature_code":"PPLL",
    "gn:name":"Male Patan",
    "gn:population":0,
    "gn:timezone":"Asia/Kathmandu",
    "iso:country":"NP",
    "wof:name":"Male Patan",
    "wof:placetype":"locality"
},
  "geometry": {"coordinates":[84.1135,28.11148],"type":"Point"}
}