{
  "type": "Feature",
  "properties": {
    "gn:admin1_code":"WR",
    "gn:admin2_code":"3",
    "gn:admin3_code":"45.0",
    "gn:admin4_code":"450001.0",
    "gn:asciiname":"Bhujelthar",
    "gn:country_code":"NP",
    "gn:dem":2357,
    "gn:feature_class":"P",
    "gn:feature_code":"PPLL",
    "gn:name":"Bhujelthar",
    "gn:population":0,
    "gn:timezone":"Asia/Kathmandu",
    "iso:country":"NP",
    "wof:name":"Bhujelthar",
    "wof:placetype":"locality"
},
  "geometry": {"coordinates":[83.26852,28.41045],"type":"Point"}
}