{
  "type": "Feature",
  "properties": {
    "gn:admin1_code":"ER",
    "gn:admin2_code":"10",
    "gn:admin3_code":"2",
    "gn:admin4_code":"20029",
    "gn:asciiname":"Thade",
    "gn:country_code":"NP",
    "gn:dem":1988,
    "gn:feature_class":"P",
    "gn:feature_code":"PPLL",
    "gn:name":"Thade",
    "gn:population":0,
    "gn:timezone":"Asia/Kathmandu",
    "iso:country":"NP",
    "wof:name":"Thade",
    "wof:placetype":"locality"
},
  "geometry": {"coordinates":[87.77101999999999,27.11297],"type":"Point"}
}