{
  "type": "Feature",
  "properties": {
    "gn:admin1_code":"MR",
    "gn:admin2_code":"12",
    "gn:admin3_code":"53",
    "gn:admin4_code":"530009",
    "gn:asciiname":"Korbang",
    "gn:country_code":"NP",
    "gn:dem":2064,
    "gn:feature_class":"P",
    "gn:feature_code":"PPLL",
    "gn:name":"Korbang",
    "gn:population":0,
    "gn:timezone":"Asia/Kathmandu",
    "iso:country":"NP",
    "wof:name":"Korbang",
    "wof:placetype":"locality"
},
  "geometry": {"coordinates":[82.74500999999999,28.36014],"type":"Point"}
}