{
  "type": "Feature",
  "properties": {
    "gn:admin1_code":"ER",
    "gn:admin2_code":"7",
    "gn:admin3_code":"7.0",
    "gn:admin4_code":"70002.0",
    "gn:asciiname":"Kopchetol",
    "gn:country_code":"NP",
    "gn:dem":1206,
    "gn:feature_class":"P",
    "gn:feature_code":"PPLL",
    "gn:name":"Kopchetol",
    "gn:population":0,
    "gn:timezone":"Asia/Kathmandu",
    "iso:country":"NP",
    "wof:name":"Kopchetol",
    "wof:placetype":"locality"
},
  "geometry": {"coordinates":[87.26130999999999,26.95905],"type":"Point"}
}