{
  "type": "Feature",
  "properties": {
    "gn:admin1_code":"MR",
    "gn:admin2_code":"12",
    "gn:admin3_code":"56.0",
    "gn:admin4_code":"560019.0",
    "gn:asciiname":"Badaharkhuti",
    "gn:country_code":"NP",
    "gn:dem":303,
    "gn:feature_class":"P",
    "gn:feature_code":"PPLL",
    "gn:name":"Badaharkhuti",
    "gn:population":0,
    "gn:timezone":"Asia/Kathmandu",
    "iso:country":"NP",
    "wof:name":"Badaharkhuti",
    "wof:placetype":"locality"
},
  "geometry": {"coordinates":[82.73654000000001,27.84276],"type":"Point"}
}