{
  "type": "Feature",
  "properties": {
    "gn:admin1_code":"MR",
    "gn:admin2_code":"6",
    "gn:admin3_code":"62.0",
    "gn:admin4_code":"620008.0",
    "gn:asciiname":"Laina Odar",
    "gn:country_code":"NP",
    "gn:dem":3976,
    "gn:feature_class":"P",
    "gn:feature_code":"PPLL",
    "gn:name":"Laina Odar",
    "gn:population":0,
    "gn:timezone":"Asia/Kathmandu",
    "iso:country":"NP",
    "wof:name":"Laina Odar",
    "wof:placetype":"locality"
},
  "geometry": {"coordinates":[83.07975,28.99546],"type":"Point"}
}