{
  "type": "Feature",
  "properties": {
    "gn:admin1_code":"ER",
    "gn:admin2_code":"13",
    "gn:admin3_code":"11",
    "gn:admin4_code":"110029",
    "gn:asciiname":"Chiwang Gumba",
    "gn:country_code":"NP",
    "gn:dem":3069,
    "gn:feature_class":"P",
    "gn:feature_code":"PPLL",
    "gn:name":"Chiwang Gumba",
    "gn:population":0,
    "gn:timezone":"Asia/Kathmandu",
    "iso:country":"NP",
    "wof:name":"Chiwang Gumba",
    "wof:placetype":"locality"
},
  "geometry": {"coordinates":[86.60266999999997,27.5417],"type":"Point"}
}