{
  "type": "Feature",
  "properties": {
    "gn:admin1_code":"MR",
    "gn:admin2_code":"12",
    "gn:admin3_code":"53",
    "gn:admin4_code":"530040",
    "gn:asciiname":"Satdandagaun",
    "gn:country_code":"NP",
    "gn:dem":1766,
    "gn:feature_class":"P",
    "gn:feature_code":"PPLL",
    "gn:name":"Satdandagaun",
    "gn:population":0,
    "gn:timezone":"Asia/Kathmandu",
    "iso:country":"NP",
    "wof:name":"Satdandagaun",
    "wof:placetype":"locality"
},
  "geometry": {"coordinates":[82.45681,28.45073],"type":"Point"}
}