{
  "type": "Feature",
  "properties": {
    "gn:admin1_code":"ER",
    "gn:admin2_code":"7.0",
    "gn:admin3_code":"8.0",
    "gn:admin4_code":"80005.0",
    "gn:asciiname":"Mathillo Hattikharka",
    "gn:country_code":"NP",
    "gn:dem":1247,
    "gn:feature_class":"P",
    "gn:feature_code":"PPLL",
    "gn:name":"Mathillo Hattikharka",
    "gn:population":0,
    "gn:timezone":"Asia/Kathmandu",
    "iso:country":"NP",
    "wof:name":"Mathillo Hattikharka",
    "wof:placetype":"locality"
},
  "geometry": {"coordinates":[87.68191,27.167],"type":"Point"}
}