{
  "type": "Feature",
  "properties": {
    "gn:admin1_code":"CR",
    "gn:admin2_code":"5",
    "gn:admin3_code":"21",
    "gn:admin4_code":"210040",
    "gn:asciiname":"Karjang",
    "gn:country_code":"NP",
    "gn:dem":1691,
    "gn:feature_class":"P",
    "gn:feature_code":"PPLL",
    "gn:name":"Karjang",
    "gn:population":0,
    "gn:timezone":"Asia/Kathmandu",
    "iso:country":"NP",
    "wof:name":"Karjang",
    "wof:placetype":"locality"
},
  "geometry": {"coordinates":[86.03815999999998,27.48289],"type":"Point"}
}