{
  "type": "Feature",
  "properties": {
    "gn:admin1_code":"CR",
    "gn:admin2_code":"1",
    "gn:admin3_code":"30.0",
    "gn:admin4_code":"300040.0",
    "gn:asciiname":"Anpchaur",
    "gn:country_code":"NP",
    "gn:dem":601,
    "gn:feature_class":"P",
    "gn:feature_code":"PPLL",
    "gn:name":"Anpchaur",
    "gn:population":0,
    "gn:timezone":"Asia/Kathmandu",
    "iso:country":"NP",
    "wof:name":"Anpchaur",
    "wof:placetype":"locality"
},
  "geometry": {"coordinates":[84.91718,28.01065],"type":"Point"}
}