{
  "type": "Feature",
  "properties": {
    "gn:admin1_code":"FR",
    "gn:admin2_code":"14",
    "gn:admin3_code":"71.0",
    "gn:admin4_code":"710007.0",
    "gn:asciiname":"Maghi",
    "gn:country_code":"NP",
    "gn:dem":197,
    "gn:feature_class":"P",
    "gn:feature_code":"PPLL",
    "gn:name":"Maghi",
    "gn:population":0,
    "gn:timezone":"Asia/Kathmandu",
    "iso:country":"NP",
    "name:kan_x_preferred":[
        "\u0cae\u0cbe\u0c98\u0cbf"
    ],
    "name:mal_x_preferred":[
        "\u0d2e\u0d3e\u0d18\u0d3f"
    ],
    "name:nno_x_preferred":[
        "Maghi"
    ],
    "name:pan_x_preferred":[
        "\u0a2e\u0a3e\u0a18\u0a40"
    ],
    "name:pnb_x_preferred":[
        "\u0645\u0627\u06af\u06be\u06cc"
    ],
    "name:tam_x_preferred":[
        "\u0bae\u0b95\u0bbf"
    ],
    "name:tel_x_preferred":[
        "\u0c2e\u0c3e\u0c18\u0c40"
    ],
    "name:urd_x_preferred":[
        "\u0645\u06af\u06be\u06cc"
    ],
    "wof:name":"Maghi",
    "wof:placetype":"locality"
},
  "geometry": {"coordinates":[80.74621999999999,28.77646],"type":"Point"}
}