{
  "type": "Feature",
  "properties": {
    "gn:admin1_code":"WR",
    "gn:admin2_code":"3",
    "gn:admin3_code":"45.0",
    "gn:admin4_code":"450035.0",
    "gn:asciiname":"Kabhrabot",
    "gn:country_code":"NP",
    "gn:dem":1293,
    "gn:feature_class":"P",
    "gn:feature_code":"PPLL",
    "gn:name":"Kabhrabot",
    "gn:population":0,
    "gn:timezone":"Asia/Kathmandu",
    "iso:country":"NP",
    "wof:name":"Kabhrabot",
    "wof:placetype":"locality"
},
  "geometry": {"coordinates":[83.64567,28.2244],"type":"Point"}
}