{
  "type": "Feature",
  "properties": {
    "gn:admin1_code":"FR",
    "gn:admin2_code":"9",
    "gn:admin3_code":"73.0",
    "gn:admin4_code":"730015.0",
    "gn:asciiname":"Pleta",
    "gn:country_code":"NP",
    "gn:dem":1774,
    "gn:feature_class":"P",
    "gn:feature_code":"PPLL",
    "gn:name":"Pleta",
    "gn:population":0,
    "gn:timezone":"Asia/Kathmandu",
    "iso:country":"NP",
    "wof:name":"Pleta",
    "wof:placetype":"locality"
},
  "geometry": {"coordinates":[80.66095,29.38662],"type":"Point"}
}