{
  "type": "Feature",
  "properties": {
    "gn:admin1_code":"FR",
    "gn:admin2_code":"14.0",
    "gn:admin3_code":"69.0",
    "gn:admin4_code":"690052.0",
    "gn:asciiname":"Sarantola",
    "gn:country_code":"NP",
    "gn:dem":1639,
    "gn:feature_class":"P",
    "gn:feature_code":"PPLL",
    "gn:name":"Sarantola",
    "gn:population":0,
    "gn:timezone":"Asia/Kathmandu",
    "iso:country":"NP",
    "wof:name":"Sarantola",
    "wof:placetype":"locality"
},
  "geometry": {"coordinates":[81.29101999999997,29.23445],"type":"Point"}
}