{
  "type": "Feature",
  "properties": {
    "gn:admin1_code":"ER",
    "gn:admin2_code":"10",
    "gn:admin3_code":"3.0",
    "gn:admin4_code":"30027.0",
    "gn:asciiname":"Surke",
    "gn:country_code":"NP",
    "gn:dem":1856,
    "gn:feature_class":"P",
    "gn:feature_code":"PPLL",
    "gn:name":"Surke",
    "gn:population":0,
    "gn:timezone":"Asia/Kathmandu",
    "iso:country":"NP",
    "wof:name":"Surke",
    "wof:placetype":"locality"
},
  "geometry": {"coordinates":[87.93465999999999,26.99459],"type":"Point"}
}