{
  "type": "Feature",
  "properties": {
    "gn:admin1_code":"FR",
    "gn:admin2_code":"14",
    "gn:admin3_code":"69.0",
    "gn:admin4_code":"690014.0",
    "gn:asciiname":"Odarkhet",
    "gn:country_code":"NP",
    "gn:dem":1521,
    "gn:feature_class":"P",
    "gn:feature_code":"PPLL",
    "gn:name":"Odarkhet",
    "gn:population":0,
    "gn:timezone":"Asia/Kathmandu",
    "iso:country":"NP",
    "wof:name":"Odarkhet",
    "wof:placetype":"locality"
},
  "geometry": {"coordinates":[81.30374,29.09942],"type":"Point"}
}