{
  "type": "Feature",
  "properties": {
    "gn:admin1_code":"WR",
    "gn:admin2_code":"8",
    "gn:admin3_code":"51.0",
    "gn:admin4_code":"510019.0",
    "gn:asciiname":"Tharpaila",
    "gn:country_code":"NP",
    "gn:dem":1207,
    "gn:elevation":"1207.0",
    "gn:feature_class":"P",
    "gn:feature_code":"PPLL",
    "gn:name":"Tharpaila",
    "gn:population":350,
    "gn:timezone":"Asia/Kathmandu",
    "iso:country":"NP",
    "wof:name":"Tharpaila",
    "wof:placetype":"locality",
    "wof:population":350
},
  "geometry": {"coordinates":[83.04071,27.85793],"type":"Point"}
}