{
  "type": "Feature",
  "properties": {
    "gn:admin1_code":"ER",
    "gn:admin2_code":"10",
    "gn:admin3_code":"3.0",
    "gn:admin4_code":"30035.0",
    "gn:asciiname":"Saptamihat",
    "gn:country_code":"NP",
    "gn:dem":1873,
    "gn:feature_class":"P",
    "gn:feature_code":"PPLL",
    "gn:name":"Saptamihat",
    "gn:population":0,
    "gn:timezone":"Asia/Kathmandu",
    "iso:country":"NP",
    "wof:name":"Saptamihat",
    "wof:placetype":"locality"
},
  "geometry": {"coordinates":[87.68994000000001,26.96599],"type":"Point"}
}