{
  "type": "Feature",
  "properties": {
    "gn:admin1_code":"CR",
    "gn:admin2_code":"11",
    "gn:admin3_code":"31",
    "gn:admin4_code":"310033.0",
    "gn:asciiname":"Golpin",
    "gn:country_code":"NP",
    "gn:dem":966,
    "gn:feature_class":"P",
    "gn:feature_code":"PPLL",
    "gn:name":"Golpin",
    "gn:population":0,
    "gn:timezone":"Asia/Kathmandu",
    "iso:country":"NP",
    "wof:name":"Golpin",
    "wof:placetype":"locality"
},
  "geometry": {"coordinates":[85.09949,27.53428],"type":"Point"}
}