{
  "type": "Feature",
  "properties": {
    "gn:admin1_code":"CR",
    "gn:admin2_code":"1",
    "gn:admin3_code":"28",
    "gn:admin4_code":"280031",
    "gn:asciiname":"Appani",
    "gn:country_code":"NP",
    "gn:dem":699,
    "gn:feature_class":"P",
    "gn:feature_code":"PPLL",
    "gn:name":"Appani",
    "gn:population":0,
    "gn:timezone":"Asia/Kathmandu",
    "iso:country":"NP",
    "wof:name":"Appani",
    "wof:placetype":"locality"
},
  "geometry": {"coordinates":[85.09566,27.87342],"type":"Point"}
}