{
  "type": "Feature",
  "properties": {
    "gn:admin1_code":"MR",
    "gn:admin2_code":"12",
    "gn:admin3_code":"56.0",
    "gn:admin4_code":"560039.0",
    "gn:asciiname":"Rani Damar",
    "gn:country_code":"NP",
    "gn:dem":780,
    "gn:feature_class":"P",
    "gn:feature_code":"PPLL",
    "gn:name":"Rani Damar",
    "gn:population":0,
    "gn:timezone":"Asia/Kathmandu",
    "iso:country":"NP",
    "wof:name":"Rani Damar",
    "wof:placetype":"locality"
},
  "geometry": {"coordinates":[82.53684,28.03279],"type":"Point"}
}