{
  "type": "Feature",
  "properties": {
    "gn:admin1_code":"MR",
    "gn:admin2_code":"12",
    "gn:admin3_code":"55",
    "gn:admin4_code":"550041",
    "gn:asciiname":"Karagaun",
    "gn:country_code":"NP",
    "gn:dem":1644,
    "gn:feature_class":"P",
    "gn:feature_code":"PPLL",
    "gn:name":"Karagaun",
    "gn:population":0,
    "gn:timezone":"Asia/Kathmandu",
    "iso:country":"NP",
    "wof:name":"Karagaun",
    "wof:placetype":"locality"
},
  "geometry": {"coordinates":[82.32114,28.50563],"type":"Point"}
}