{
  "type": "Feature",
  "properties": {
    "gn:admin1_code":"WR",
    "gn:admin2_code":"8",
    "gn:admin3_code":"46.0",
    "gn:admin4_code":"460014.0",
    "gn:asciiname":"Khaireni Ghat",
    "gn:country_code":"NP",
    "gn:dem":959,
    "gn:feature_class":"P",
    "gn:feature_code":"PPLL",
    "gn:name":"Khaireni Ghat",
    "gn:population":0,
    "gn:timezone":"Asia/Kathmandu",
    "iso:country":"NP",
    "wof:name":"Khaireni Ghat",
    "wof:placetype":"locality"
},
  "geometry": {"coordinates":[83.3381,28.07562],"type":"Point"}
}