{
  "type": "Feature",
  "properties": {
    "gn:admin1_code":"FR",
    "gn:admin2_code":"14",
    "gn:admin3_code":"68",
    "gn:admin4_code":"680028",
    "gn:asciiname":"Subeda",
    "gn:country_code":"NP",
    "gn:dem":1200,
    "gn:feature_class":"P",
    "gn:feature_code":"PPLL",
    "gn:name":"Subeda",
    "gn:population":0,
    "gn:timezone":"Asia/Kathmandu",
    "iso:country":"NP",
    "wof:name":"Subeda",
    "wof:placetype":"locality"
},
  "geometry": {"coordinates":[81.16594000000001,29.52486],"type":"Point"}
}