{
  "type": "Feature",
  "properties": {
    "gn:admin1_code":"WR",
    "gn:admin2_code":"4",
    "gn:admin3_code":"37",
    "gn:admin4_code":"370013",
    "gn:asciiname":"Thulikharka",
    "gn:country_code":"NP",
    "gn:dem":1982,
    "gn:feature_class":"P",
    "gn:feature_code":"PPLL",
    "gn:name":"Thulikharka",
    "gn:population":0,
    "gn:timezone":"Asia/Kathmandu",
    "iso:country":"NP",
    "wof:name":"Thulikharka",
    "wof:placetype":"locality"
},
  "geometry": {"coordinates":[84.27599000000002,28.31084],"type":"Point"}
}