{
  "type": "Feature",
  "properties": {
    "gn:admin1_code":"FR",
    "gn:admin2_code":"9",
    "gn:admin3_code":"74",
    "gn:admin4_code":"740016",
    "gn:asciiname":"Majakatai",
    "gn:country_code":"NP",
    "gn:dem":1316,
    "gn:feature_class":"P",
    "gn:feature_code":"PPLL",
    "gn:name":"Majakatai",
    "gn:population":0,
    "gn:timezone":"Asia/Kathmandu",
    "iso:country":"NP",
    "wof:name":"Majakatai",
    "wof:placetype":"locality"
},
  "geometry": {"coordinates":[80.60604000000002,29.65678],"type":"Point"}
}