{
  "type": "Feature",
  "properties": {
    "gn:admin1_code":"FR",
    "gn:admin2_code":"14",
    "gn:admin3_code":"69.0",
    "gn:admin4_code":"690009.0",
    "gn:asciiname":"Chitasain",
    "gn:country_code":"NP",
    "gn:dem":1018,
    "gn:feature_class":"P",
    "gn:feature_code":"PPLL",
    "gn:name":"Chitasain",
    "gn:population":0,
    "gn:timezone":"Asia/Kathmandu",
    "iso:country":"NP",
    "wof:name":"Chitasain",
    "wof:placetype":"locality"
},
  "geometry": {"coordinates":[81.38892,28.95966],"type":"Point"}
}