{
  "type": "Feature",
  "properties": {
    "gn:admin1_code":"CR",
    "gn:admin2_code":"1",
    "gn:admin3_code":"25",
    "gn:admin4_code":"250008",
    "gn:asciiname":"Lamrang",
    "gn:country_code":"NP",
    "gn:dem":1711,
    "gn:feature_class":"P",
    "gn:feature_code":"PPLL",
    "gn:name":"Lamrang",
    "gn:population":0,
    "gn:timezone":"Asia/Kathmandu",
    "iso:country":"NP",
    "wof:name":"Lamrang",
    "wof:placetype":"locality"
},
  "geometry": {"coordinates":[85.40656,27.48761],"type":"Point"}
}