{
  "type": "Feature",
  "properties": {
    "gn:admin1_code":"FR",
    "gn:admin2_code":"14",
    "gn:admin3_code":"70.0",
    "gn:admin4_code":"700039.0",
    "gn:asciiname":"Kalikholi",
    "gn:country_code":"NP",
    "gn:dem":1164,
    "gn:feature_class":"P",
    "gn:feature_code":"PPLL",
    "gn:name":"Kalikholi",
    "gn:population":0,
    "gn:timezone":"Asia/Kathmandu",
    "iso:country":"NP",
    "wof:name":"Kalikholi",
    "wof:placetype":"locality"
},
  "geometry": {"coordinates":[80.75957,29.06108],"type":"Point"}
}