{
  "type": "Feature",
  "properties": {
    "gn:admin1_code":"WR",
    "gn:admin2_code":"4",
    "gn:admin3_code":"40.0",
    "gn:admin4_code":"400010.0",
    "gn:asciiname":"(Nagdanda)",
    "gn:country_code":"NP",
    "gn:dem":1319,
    "gn:feature_class":"P",
    "gn:feature_code":"PPLL",
    "gn:name":"(Nagdanda)",
    "gn:population":0,
    "gn:timezone":"Asia/Kathmandu",
    "iso:country":"NP",
    "wof:name":"(Nagdanda)",
    "wof:placetype":"locality"
},
  "geometry": {"coordinates":[83.86253000000001,28.28447],"type":"Point"}
}