{
  "type": "Feature",
  "properties": {
    "gn:admin1_code":"CR",
    "gn:admin2_code":"1",
    "gn:admin3_code":"28",
    "gn:admin4_code":"280035.0",
    "gn:asciiname":"Ekle",
    "gn:country_code":"NP",
    "gn:dem":960,
    "gn:feature_class":"P",
    "gn:feature_code":"PPLL",
    "gn:name":"Ekle",
    "gn:population":0,
    "gn:timezone":"Asia/Kathmandu",
    "iso:country":"NP",
    "wof:name":"Ekle",
    "wof:placetype":"locality"
},
  "geometry": {"coordinates":[85.1399,27.7745],"type":"Point"}
}