{
  "type": "Feature",
  "properties": {
    "gn:admin1_code":"WR",
    "gn:admin2_code":"4.0",
    "gn:admin3_code":"38.0",
    "gn:admin4_code":"380029.0",
    "gn:asciiname":"Kabhrakholagaun",
    "gn:country_code":"NP",
    "gn:dem":927,
    "gn:feature_class":"P",
    "gn:feature_code":"PPLL",
    "gn:name":"Kabhrakholagaun",
    "gn:population":0,
    "gn:timezone":"Asia/Kathmandu",
    "iso:country":"NP",
    "wof:name":"Kabhrakholagaun",
    "wof:placetype":"locality"
},
  "geometry": {"coordinates":[84.34595999999998,27.80454000000001],"type":"Point"}
}