{
  "type": "Feature",
  "properties": {
    "gn:admin1_code":"WR",
    "gn:admin2_code":"4",
    "gn:admin3_code":"37",
    "gn:admin4_code":"370033",
    "gn:asciiname":"Salghari",
    "gn:country_code":"NP",
    "gn:dem":706,
    "gn:feature_class":"P",
    "gn:feature_code":"PPLL",
    "gn:name":"Salghari",
    "gn:population":0,
    "gn:timezone":"Asia/Kathmandu",
    "iso:country":"NP",
    "name:mai_x_preferred":[
        "\u0918\u0930\u094d\u0924\u093f\u0917\u093e\u0909\u0901"
    ],
    "name:nep_x_preferred":[
        "\u0918\u0930\u094d\u0924\u093f\u0917\u093e\u0909\u0901"
    ],
    "wof:name":"Salghari",
    "wof:placetype":"locality"
},
  "geometry": {"coordinates":[84.22211999999998,28.17805],"type":"Point"}
}