{
  "type": "Feature",
  "properties": {
    "gn:admin1_code":"MR",
    "gn:admin2_code":"12",
    "gn:admin3_code":"53",
    "gn:admin4_code":"530020",
    "gn:asciiname":"Lapal",
    "gn:country_code":"NP",
    "gn:dem":1205,
    "gn:feature_class":"P",
    "gn:feature_code":"PPLL",
    "gn:name":"Lapal",
    "gn:population":0,
    "gn:timezone":"Asia/Kathmandu",
    "iso:country":"NP",
    "wof:name":"Lapal",
    "wof:placetype":"locality"
},
  "geometry": {"coordinates":[82.57210000000001,28.20611],"type":"Point"}
}