{
  "type": "Feature",
  "properties": {
    "gn:admin1_code":"ER",
    "gn:admin2_code":"13.0",
    "gn:admin3_code":"14.0",
    "gn:admin4_code":"140033.0",
    "gn:asciiname":"Lamauredanda",
    "gn:country_code":"NP",
    "gn:dem":600,
    "gn:feature_class":"P",
    "gn:feature_code":"PPLL",
    "gn:name":"Lamauredanda",
    "gn:population":0,
    "gn:timezone":"Asia/Kathmandu",
    "iso:country":"NP",
    "wof:name":"Lamauredanda",
    "wof:placetype":"locality"
},
  "geometry": {"coordinates":[86.48305000000001,27.09978],"type":"Point"}
}