{
  "type": "Feature",
  "properties": {
    "gn:admin1_code":"WR",
    "gn:admin2_code":"4.0",
    "gn:admin3_code":"39.0",
    "gn:admin4_code":"390044.0",
    "gn:asciiname":"Jaspur",
    "gn:country_code":"NP",
    "gn:dem":1073,
    "gn:feature_class":"P",
    "gn:feature_code":"PPLL",
    "gn:name":"Jaspur",
    "gn:population":0,
    "gn:timezone":"Asia/Kathmandu",
    "iso:country":"NP",
    "name:bpy_x_preferred":[
        "\u099c\u09b6\u09aa\u09c1\u09b0"
    ],
    "name:ceb_x_preferred":[
        "Jaspur"
    ],
    "name:hin_x_preferred":[
        "\u091c\u0938\u092a\u0941\u0930"
    ],
    "name:ita_x_preferred":[
        "Jaspur"
    ],
    "name:mlg_x_preferred":[
        "Jaspur"
    ],
    "name:msa_x_preferred":[
        "Jaspur"
    ],
    "name:new_x_preferred":[
        "\u091c\u0938\u094d\u092a\u0941\u0930"
    ],
    "name:nld_x_preferred":[
        "Jaspur"
    ],
    "name:pol_x_preferred":[
        "Jaspur"
    ],
    "name:por_x_preferred":[
        "Jaspur"
    ],
    "name:swe_x_preferred":[
        "Jaspur"
    ],
    "name:urd_x_preferred":[
        "\u062c\u0633\u067e\u0631"
    ],
    "name:vie_x_preferred":[
        "Jaspur"
    ],
    "name:zho_x_preferred":[
        "\u8d3e\u65af\u666e\u5c14"
    ],
    "wof:name":"Jaspur",
    "wof:placetype":"locality"
},
  "geometry": {"coordinates":[83.84756,28.10311],"type":"Point"}
}