{
  "type": "Feature",
  "properties": {
    "gn:admin1_code":"ER",
    "gn:admin2_code":"10",
    "gn:admin3_code":"2",
    "gn:admin4_code":"20026.0",
    "gn:asciiname":"Tilhar",
    "gn:country_code":"NP",
    "gn:dem":1045,
    "gn:feature_class":"P",
    "gn:feature_code":"PPLL",
    "gn:name":"Tilhar",
    "gn:population":0,
    "gn:timezone":"Asia/Kathmandu",
    "iso:country":"NP",
    "wof:name":"Tilhar",
    "wof:placetype":"locality"
},
  "geometry": {"coordinates":[87.74854000000001,27.24057],"type":"Point"}
}