{
  "type": "Feature",
  "properties": {
    "gn:admin1_code":"ER",
    "gn:admin2_code":"10",
    "gn:admin3_code":"2",
    "gn:admin4_code":"20026.0",
    "gn:asciiname":"Tilhar",
    "gn:country_code":"NP",
    "gn:dem":1045,
    "gn:feature_class":"P",
    "gn:feature_code":"PPLL",
    "gn:name":"Tilhar",
    "gn:population":0,
    "gn:timezone":"Asia/Kathmandu",
    "iso:country":"NP",
    "name:bpy_x_preferred":[
        "\u09a4\u09bf\u09b2\u09b9\u09b0"
    ],
    "name:ceb_x_preferred":[
        "Tilhar"
    ],
    "name:hif_x_preferred":[
        "Tilhar"
    ],
    "name:hin_x_preferred":[
        "\u0924\u093f\u0932\u0939\u0930"
    ],
    "name:ita_x_preferred":[
        "Tilhar"
    ],
    "name:mlg_x_preferred":[
        "Tilhar"
    ],
    "name:msa_x_preferred":[
        "Tilhar"
    ],
    "name:nld_x_preferred":[
        "Tilhar"
    ],
    "name:pnb_x_preferred":[
        "\u062a\u0644\u06c1\u0631"
    ],
    "name:pol_x_preferred":[
        "Tilhar"
    ],
    "name:por_x_preferred":[
        "Tilhar"
    ],
    "name:swe_x_preferred":[
        "Tilhar"
    ],
    "name:urd_x_preferred":[
        "\u062a\u0644\u06c1\u0631"
    ],
    "name:vie_x_preferred":[
        "Tilhar"
    ],
    "name:zho_x_preferred":[
        "\u8482\u5c14\u54c8\u5c14"
    ],
    "wof:name":"Tilhar",
    "wof:placetype":"locality"
},
  "geometry": {"coordinates":[87.74854000000001,27.24057],"type":"Point"}
}