{
  "type": "Feature",
  "properties": {
    "gn:admin1_code":"WR",
    "gn:admin2_code":"4",
    "gn:admin3_code":"36.0",
    "gn:admin4_code":"360064.0",
    "gn:asciiname":"Pam",
    "gn:country_code":"NP",
    "gn:dem":1736,
    "gn:feature_class":"P",
    "gn:feature_code":"PPLL",
    "gn:name":"Pam",
    "gn:population":0,
    "gn:timezone":"Asia/Kathmandu",
    "iso:country":"NP",
    "wof:name":"Pam",
    "wof:placetype":"locality"
},
  "geometry": {"coordinates":[84.59477,28.08816],"type":"Point"}
}