{
  "type": "Feature",
  "properties": {
    "gn:admin1_code":"MR",
    "gn:admin2_code":"6",
    "gn:admin3_code":"63.0",
    "gn:admin4_code":"630001.0",
    "gn:asciiname":"Tikimala",
    "gn:country_code":"NP",
    "gn:dem":2836,
    "gn:feature_class":"P",
    "gn:feature_code":"PPLL",
    "gn:name":"Tikimala",
    "gn:population":0,
    "gn:timezone":"Asia/Kathmandu",
    "iso:country":"NP",
    "wof:name":"Tikimala",
    "wof:placetype":"locality"
},
  "geometry": {"coordinates":[82.01333000000002,29.29645],"type":"Point"}
}