{
  "type": "Feature",
  "properties": {
    "gn:admin1_code":"CR",
    "gn:admin2_code":"1",
    "gn:admin3_code":"30.0",
    "gn:admin4_code":"300006.0",
    "gn:asciiname":"Chaunchuli",
    "gn:country_code":"NP",
    "gn:dem":772,
    "gn:feature_class":"P",
    "gn:feature_code":"PPLL",
    "gn:name":"Chaunchuli",
    "gn:population":0,
    "gn:timezone":"Asia/Kathmandu",
    "iso:country":"NP",
    "wof:name":"Chaunchuli",
    "wof:placetype":"locality"
},
  "geometry": {"coordinates":[84.83995999999998,28.08907],"type":"Point"}
}