{
  "type": "Feature",
  "properties": {
    "gn:admin1_code":"FR",
    "gn:admin2_code":"14",
    "gn:admin3_code":"71.0",
    "gn:admin4_code":"710040.0",
    "gn:asciiname":"Okhrekot",
    "gn:country_code":"NP",
    "gn:dem":363,
    "gn:feature_class":"P",
    "gn:feature_code":"PPLL",
    "gn:name":"Okhrekot",
    "gn:population":0,
    "gn:timezone":"Asia/Kathmandu",
    "iso:country":"NP",
    "wof:name":"Okhrekot",
    "wof:placetype":"locality"
},
  "geometry": {"coordinates":[81.23921,28.75368],"type":"Point"}
}