{
  "type": "Feature",
  "properties": {
    "gn:admin1_code":"WR",
    "gn:admin2_code":"8",
    "gn:admin3_code":"47",
    "gn:admin4_code":"470023",
    "gn:asciiname":"Gangate",
    "gn:country_code":"NP",
    "gn:dem":374,
    "gn:feature_class":"P",
    "gn:feature_code":"PPLL",
    "gn:name":"Gangate",
    "gn:population":0,
    "gn:timezone":"Asia/Kathmandu",
    "iso:country":"NP",
    "wof:name":"Gangate",
    "wof:placetype":"locality"
},
  "geometry": {"coordinates":[83.94327,27.85614],"type":"Point"}
}