{
  "type": "Feature",
  "properties": {
    "gn:admin1_code":"CR",
    "gn:admin2_code":"5",
    "gn:admin3_code":"19",
    "gn:admin4_code":"190044",
    "gn:asciiname":"Mejarganj",
    "gn:country_code":"NP",
    "gn:dem":137,
    "gn:feature_class":"P",
    "gn:feature_code":"PPLL",
    "gn:name":"Mejarganj",
    "gn:population":0,
    "gn:timezone":"Asia/Kathmandu",
    "iso:country":"NP",
    "wof:name":"Mejarganj",
    "wof:placetype":"locality"
},
  "geometry": {"coordinates":[85.62224999999999,27.04359],"type":"Point"}
}