{
  "type": "Feature",
  "properties": {
    "gn:admin1_code":"WR",
    "gn:admin2_code":"3",
    "gn:admin3_code":"45.0",
    "gn:admin4_code":"450038.0",
    "gn:asciiname":"Nabur",
    "gn:country_code":"NP",
    "gn:dem":825,
    "gn:feature_class":"P",
    "gn:feature_code":"PPLL",
    "gn:name":"Nabur",
    "gn:population":0,
    "gn:timezone":"Asia/Kathmandu",
    "iso:country":"NP",
    "name:azb_x_preferred":[
        "\u0646\u0627\u0628\u0648\u0631"
    ],
    "name:aze_x_preferred":[
        "Nabur"
    ],
    "name:ceb_x_preferred":[
        "Nabur"
    ],
    "name:fas_x_preferred":[
        "\u0646\u0627\u0628\u0648\u0631"
    ],
    "name:ita_x_preferred":[
        "Nabur"
    ],
    "name:kat_x_preferred":[
        "\u10dc\u10d0\u10d1\u10e3\u10e0\u10d8"
    ],
    "name:msa_x_preferred":[
        "Nabur"
    ],
    "name:swe_x_preferred":[
        "Nabur"
    ],
    "wof:name":"Nabur",
    "wof:placetype":"locality"
},
  "geometry": {"coordinates":[83.66425,28.20277],"type":"Point"}
}