{
  "type": "Feature",
  "properties": {
    "gn:admin1_code":"ER",
    "gn:admin2_code":"10",
    "gn:admin3_code":"3.0",
    "gn:admin4_code":"30007.0",
    "gn:asciiname":"Purbi Dobhan",
    "gn:country_code":"NP",
    "gn:dem":245,
    "gn:feature_class":"P",
    "gn:feature_code":"PPLL",
    "gn:name":"Purbi Dobhan",
    "gn:population":0,
    "gn:timezone":"Asia/Kathmandu",
    "iso:country":"NP",
    "wof:name":"Purbi Dobhan",
    "wof:placetype":"locality"
},
  "geometry": {"coordinates":[87.88600000000002,26.69749],"type":"Point"}
}