{
  "type": "Feature",
  "properties": {
    "gn:admin1_code":"MR",
    "gn:admin2_code":"2",
    "gn:admin3_code":"60.0",
    "gn:admin4_code":"600034.0",
    "gn:asciiname":"Tuda (Purba)",
    "gn:country_code":"NP",
    "gn:dem":1533,
    "gn:feature_class":"P",
    "gn:feature_code":"PPLL",
    "gn:name":"Tuda (Purba)",
    "gn:population":0,
    "gn:timezone":"Asia/Kathmandu",
    "iso:country":"NP",
    "wof:name":"Tuda (Purba)",
    "wof:placetype":"locality"
},
  "geometry": {"coordinates":[81.84881,28.82145],"type":"Point"}
}