{
  "type": "Feature",
  "properties": {
    "gn:admin1_code":"MR",
    "gn:admin2_code":"12",
    "gn:admin3_code":"56.0",
    "gn:admin4_code":"560039.0",
    "gn:asciiname":"Nayan Basti",
    "gn:country_code":"NP",
    "gn:dem":644,
    "gn:feature_class":"P",
    "gn:feature_code":"PPLL",
    "gn:name":"Nayan Basti",
    "gn:population":0,
    "gn:timezone":"Asia/Kathmandu",
    "iso:country":"NP",
    "wof:name":"Nayan Basti",
    "wof:placetype":"locality"
},
  "geometry": {"coordinates":[82.45477,28.04618],"type":"Point"}
}