{
  "type": "Feature",
  "properties": {
    "gn:admin1_code":"MR",
    "gn:admin2_code":"6",
    "gn:admin3_code":"66.0",
    "gn:admin4_code":"660006.0",
    "gn:asciiname":"Lek kuti",
    "gn:country_code":"NP",
    "gn:dem":3258,
    "gn:feature_class":"P",
    "gn:feature_code":"PPLL",
    "gn:name":"Lek kuti",
    "gn:population":0,
    "gn:timezone":"Asia/Kathmandu",
    "iso:country":"NP",
    "wof:name":"Lek kuti",
    "wof:placetype":"locality"
},
  "geometry": {"coordinates":[81.98520000000001,29.79486],"type":"Point"}
}