{
  "type": "Feature",
  "properties": {
    "gn:admin1_code":"MR",
    "gn:admin2_code":"12",
    "gn:admin3_code":"52",
    "gn:admin4_code":"520001",
    "gn:asciiname":"Rangjung",
    "gn:country_code":"NP",
    "gn:dem":2105,
    "gn:feature_class":"P",
    "gn:feature_code":"PPLL",
    "gn:name":"Rangjung",
    "gn:population":0,
    "gn:timezone":"Asia/Kathmandu",
    "iso:country":"NP",
    "name:rus_x_preferred":[
        "\u0420\u0430\u043d\u0433\u0434\u0436\u0443\u043d\u0433"
    ],
    "wof:name":"Rangjung",
    "wof:placetype":"locality"
},
  "geometry": {"coordinates":[83.07625999999998,28.2496],"type":"Point"}
}