{
  "type": "Feature",
  "properties": {
    "gn:admin1_code":"FR",
    "gn:admin2_code":"14",
    "gn:admin3_code":"69.0",
    "gn:admin4_code":"690017.0",
    "gn:asciiname":"Baskholagaun",
    "gn:country_code":"NP",
    "gn:dem":677,
    "gn:feature_class":"P",
    "gn:feature_code":"PPLL",
    "gn:name":"Baskholagaun",
    "gn:population":0,
    "gn:timezone":"Asia/Kathmandu",
    "iso:country":"NP",
    "wof:name":"Baskholagaun",
    "wof:placetype":"locality"
},
  "geometry": {"coordinates":[81.21835,29.19402],"type":"Point"}
}