{
  "type": "Feature",
  "properties": {
    "gn:admin1_code":"FR",
    "gn:admin2_code":"14",
    "gn:admin3_code":"70.0",
    "gn:admin4_code":"700048.0",
    "gn:asciiname":"Talkot",
    "gn:country_code":"NP",
    "gn:dem":451,
    "gn:feature_class":"P",
    "gn:feature_code":"PPLL",
    "gn:name":"Talkot",
    "gn:population":0,
    "gn:timezone":"Asia/Kathmandu",
    "iso:country":"NP",
    "wof:name":"Talkot",
    "wof:placetype":"locality"
},
  "geometry": {"coordinates":[81.04879,29.17015],"type":"Point"}
}