{
  "type": "Feature",
  "properties": {
    "gn:admin1_code":"WR",
    "gn:admin2_code":"4",
    "gn:admin3_code":"37",
    "gn:admin4_code":"370031",
    "gn:asciiname":"Kolgyu",
    "gn:country_code":"NP",
    "gn:dem":1577,
    "gn:feature_class":"P",
    "gn:feature_code":"PPLL",
    "gn:name":"Kolgyu",
    "gn:population":0,
    "gn:timezone":"Asia/Kathmandu",
    "iso:country":"NP",
    "wof:name":"Kolgyu",
    "wof:placetype":"locality"
},
  "geometry": {"coordinates":[84.42193,28.2285],"type":"Point"}
}