{
  "type": "Feature",
  "properties": {
    "gn:admin1_code":"CR",
    "gn:admin2_code":"5",
    "gn:admin3_code":"22.0",
    "gn:admin4_code":"220012.0",
    "gn:asciiname":"Syakhu",
    "gn:country_code":"NP",
    "gn:dem":2116,
    "gn:feature_class":"P",
    "gn:feature_code":"PPLL",
    "gn:name":"Syakhu",
    "gn:population":0,
    "gn:timezone":"Asia/Kathmandu",
    "iso:country":"NP",
    "wof:name":"Syakhu",
    "wof:placetype":"locality"
},
  "geometry": {"coordinates":[86.11595,27.84589],"type":"Point"}
}