{
  "type": "Feature",
  "properties": {
    "gn:admin1_code":"CR",
    "gn:admin2_code":"1",
    "gn:admin3_code":"23",
    "gn:admin4_code":"230056",
    "gn:asciiname":"Piskar",
    "gn:country_code":"NP",
    "gn:dem":2344,
    "gn:feature_class":"P",
    "gn:feature_code":"PPLL",
    "gn:name":"Piskar",
    "gn:population":0,
    "gn:timezone":"Asia/Kathmandu",
    "iso:country":"NP",
    "name:ceb_x_preferred":[
        "Piskar"
    ],
    "name:fra_x_preferred":[
        "Piskar"
    ],
    "name:msa_x_preferred":[
        "Piskar"
    ],
    "name:nep_x_preferred":[
        "\u092a\u093f\u0938\u094d\u0915\u0930"
    ],
    "name:new_x_preferred":[
        "\u092a\u093f\u0938\u094d\u0915\u093e\u0930"
    ],
    "name:pol_x_preferred":[
        "Piskar"
    ],
    "wof:name":"Piskar",
    "wof:placetype":"locality"
},
  "geometry": {"coordinates":[85.93285,27.74563],"type":"Point"}
}