{
  "type": "Feature",
  "properties": {
    "gn:admin1_code":"WR",
    "gn:admin2_code":"4.0",
    "gn:admin3_code":"38.0",
    "gn:admin4_code":"380001.0",
    "gn:asciiname":"Deurali",
    "gn:country_code":"NP",
    "gn:dem":328,
    "gn:feature_class":"P",
    "gn:feature_code":"PPLL",
    "gn:name":"Deurali",
    "gn:population":0,
    "gn:timezone":"Asia/Kathmandu",
    "iso:country":"NP",
    "wof:name":"Deurali",
    "wof:placetype":"locality"
},
  "geometry": {"coordinates":[84.54045000000001,27.9106],"type":"Point"}
}