{
  "type": "Feature",
  "properties": {
    "gn:admin1_code":"ER",
    "gn:admin2_code":"7",
    "gn:admin3_code":"10.0",
    "gn:admin4_code":"100049.0",
    "gn:asciiname":"Ranibas",
    "gn:country_code":"NP",
    "gn:dem":1525,
    "gn:feature_class":"P",
    "gn:feature_code":"PPLL",
    "gn:name":"Ranibas",
    "gn:population":0,
    "gn:timezone":"Asia/Kathmandu",
    "iso:country":"NP",
    "name:fra_x_preferred":[
        "Ranibas"
    ],
    "name:new_x_preferred":[
        "\u0930\u093e\u0928\u0940\u0935\u093e\u0938"
    ],
    "name:pol_x_preferred":[
        "Ranibas"
    ],
    "wof:name":"Ranibas",
    "wof:placetype":"locality"
},
  "geometry": {"coordinates":[87.09989,27.0254],"type":"Point"}
}