{
  "type": "Feature",
  "properties": {
    "gn:admin1_code":"CR",
    "gn:admin2_code":"1",
    "gn:admin3_code":"24.0",
    "gn:admin4_code":"240054.0",
    "gn:asciiname":"Chhapdanda",
    "gn:country_code":"NP",
    "gn:dem":1635,
    "gn:feature_class":"P",
    "gn:feature_code":"PPLL",
    "gn:name":"Chhapdanda",
    "gn:population":0,
    "gn:timezone":"Asia/Kathmandu",
    "iso:country":"NP",
    "wof:name":"Chhapdanda",
    "wof:placetype":"locality"
},
  "geometry": {"coordinates":[85.55041,27.52615],"type":"Point"}
}