{
  "type": "Feature",
  "properties": {
    "gn:admin1_code":"MR",
    "gn:admin2_code":"2.0",
    "gn:admin3_code":"59.0",
    "gn:admin4_code":"590032.0",
    "gn:asciiname":"Thulo Dungi",
    "gn:country_code":"NP",
    "gn:dem":660,
    "gn:feature_class":"P",
    "gn:feature_code":"PPLL",
    "gn:name":"Thulo Dungi",
    "gn:population":0,
    "gn:timezone":"Asia/Kathmandu",
    "iso:country":"NP",
    "wof:name":"Thulo Dungi",
    "wof:placetype":"locality"
},
  "geometry": {"coordinates":[81.68816,28.43898],"type":"Point"}
}