{
  "type": "Feature",
  "properties": {
    "gn:admin1_code":"ER",
    "gn:admin2_code":"10.0",
    "gn:admin3_code":"1.0",
    "gn:admin4_code":"10017.0",
    "gn:asciiname":"Ganduwa",
    "gn:country_code":"NP",
    "gn:dem":1971,
    "gn:feature_class":"P",
    "gn:feature_code":"PPLL",
    "gn:name":"Ganduwa",
    "gn:population":0,
    "gn:timezone":"Asia/Kathmandu",
    "iso:country":"NP",
    "wof:name":"Ganduwa",
    "wof:placetype":"locality"
},
  "geometry": {"coordinates":[87.89121999999998,27.32521],"type":"Point"}
}