{
  "type": "Feature",
  "properties": {
    "gn:admin1_code":"CR",
    "gn:admin2_code":"5",
    "gn:admin3_code":"18",
    "gn:admin4_code":"180032",
    "gn:asciiname":"Baingkatti",
    "gn:country_code":"NP",
    "gn:dem":149,
    "gn:feature_class":"P",
    "gn:feature_code":"PPLL",
    "gn:name":"Baingkatti",
    "gn:population":0,
    "gn:timezone":"Asia/Kathmandu",
    "iso:country":"NP",
    "wof:name":"Baingkatti",
    "wof:placetype":"locality"
},
  "geometry": {"coordinates":[85.855,26.93505],"type":"Point"}
}