{
  "type": "Feature",
  "properties": {
    "gn:admin1_code":"WR",
    "gn:admin2_code":"3",
    "gn:admin3_code":"43",
    "gn:admin4_code":"430033",
    "gn:asciiname":"Piple",
    "gn:country_code":"NP",
    "gn:dem":1554,
    "gn:feature_class":"P",
    "gn:feature_code":"PPLL",
    "gn:name":"Piple",
    "gn:population":0,
    "gn:timezone":"Asia/Kathmandu",
    "iso:country":"NP",
    "name:new_x_preferred":[
        "\u092a\u093f\u092a\u094d\u0932\u0947"
    ],
    "name:pol_x_preferred":[
        "Piple"
    ],
    "wof:name":"Piple",
    "wof:placetype":"locality"
},
  "geometry": {"coordinates":[83.57356999999998,28.39758],"type":"Point"}
}