{
  "type": "Feature",
  "properties": {
    "gn:admin1_code":"00",
    "gn:asciiname":"Waleng",
    "gn:country_code":"NP",
    "gn:dem":1239,
    "gn:feature_class":"P",
    "gn:feature_code":"PPL",
    "gn:name":"W\u0101leng",
    "gn:population":0,
    "gn:timezone":"Asia/Kathmandu",
    "iso:country":"NP",
    "wof:name":"Waleng",
    "wof:placetype":"locality"
},
  "geometry": {"coordinates":[87.18201999999999,27.52475],"type":"Point"}
}