{
  "type": "Feature",
  "properties": {
    "gn:admin1_code":"CR",
    "gn:admin2_code":"1",
    "gn:admin3_code":"30.0",
    "gn:admin4_code":"300035.0",
    "gn:asciiname":"Kerabari",
    "gn:country_code":"NP",
    "gn:dem":1176,
    "gn:feature_class":"P",
    "gn:feature_code":"PPLL",
    "gn:name":"Kerabari",
    "gn:population":0,
    "gn:timezone":"Asia/Kathmandu",
    "iso:country":"NP",
    "wof:name":"Kerabari",
    "wof:placetype":"locality"
},
  "geometry": {"coordinates":[84.94004,27.89748],"type":"Point"}
}