{
  "type": "Feature",
  "properties": {
    "gn:admin1_code":"MR",
    "gn:admin2_code":"2.0",
    "gn:admin3_code":"59.0",
    "gn:admin4_code":"590021.0",
    "gn:asciiname":"Sisne",
    "gn:country_code":"NP",
    "gn:dem":1246,
    "gn:feature_class":"P",
    "gn:feature_code":"PPLL",
    "gn:name":"Sisne",
    "gn:population":0,
    "gn:timezone":"Asia/Kathmandu",
    "iso:country":"NP",
    "name:ceb_x_preferred":[
        "Sisne"
    ],
    "name:fra_x_preferred":[
        "Sisne"
    ],
    "name:mai_x_preferred":[
        "\u0938\u093f\u0938\u094d\u0928\u0947"
    ],
    "name:msa_x_preferred":[
        "Sisne"
    ],
    "name:nep_x_preferred":[
        "\u0938\u093f\u0938\u094d\u0928\u0947"
    ],
    "name:new_x_preferred":[
        "\u0938\u093f\u0938\u094d\u0928\u0947"
    ],
    "name:pol_x_preferred":[
        "Sisne"
    ],
    "wof:name":"Sisne",
    "wof:placetype":"locality"
},
  "geometry": {"coordinates":[81.31440000000001,28.89601],"type":"Point"}
}