{
  "type": "Feature",
  "properties": {
    "gn:admin1_code":"ER",
    "gn:admin2_code":"10",
    "gn:admin3_code":"4.0",
    "gn:admin4_code":"40050.0",
    "gn:asciiname":"Saulmari",
    "gn:country_code":"NP",
    "gn:dem":97,
    "gn:feature_class":"P",
    "gn:feature_code":"PPLL",
    "gn:name":"Saulmari",
    "gn:population":0,
    "gn:timezone":"Asia/Kathmandu",
    "iso:country":"NP",
    "wof:name":"Saulmari",
    "wof:placetype":"locality"
},
  "geometry": {"coordinates":[87.75308000000003,26.5597],"type":"Point"}
}