{
  "type": "Feature",
  "properties": {
    "gn:admin1_code":"CR",
    "gn:admin2_code":"1",
    "gn:admin3_code":"27.0",
    "gn:admin4_code":"270005.0",
    "gn:asciiname":"Suntakhan",
    "gn:country_code":"NP",
    "gn:dem":1410,
    "gn:feature_class":"P",
    "gn:feature_code":"PPLL",
    "gn:name":"Suntakhan",
    "gn:population":0,
    "gn:timezone":"Asia/Kathmandu",
    "iso:country":"NP",
    "wof:name":"Suntakhan",
    "wof:placetype":"locality"
},
  "geometry": {"coordinates":[85.38941,27.76276],"type":"Point"}
}