{
  "type": "Feature",
  "properties": {
    "gn:admin1_code":"CR",
    "gn:admin2_code":"1",
    "gn:admin3_code":"29",
    "gn:admin4_code":"290013.0",
    "gn:asciiname":"Upallotar",
    "gn:country_code":"NP",
    "gn:dem":1782,
    "gn:feature_class":"P",
    "gn:feature_code":"PPLL",
    "gn:name":"Upallotar",
    "gn:population":0,
    "gn:timezone":"Asia/Kathmandu",
    "iso:country":"NP",
    "wof:name":"Upallotar",
    "wof:placetype":"locality"
},
  "geometry": {"coordinates":[85.28364000000001,27.98147],"type":"Point"}
}