{
  "type": "Feature",
  "properties": {
    "gn:admin1_code":"MR",
    "gn:admin2_code":"12",
    "gn:admin3_code":"53",
    "gn:admin4_code":"530020",
    "gn:asciiname":"Gorineta",
    "gn:country_code":"NP",
    "gn:dem":1653,
    "gn:feature_class":"P",
    "gn:feature_code":"PPLL",
    "gn:name":"Gorineta",
    "gn:population":0,
    "gn:timezone":"Asia/Kathmandu",
    "iso:country":"NP",
    "wof:name":"Gorineta",
    "wof:placetype":"locality"
},
  "geometry": {"coordinates":[82.59566,28.19068],"type":"Point"}
}