{
  "type": "Feature",
  "properties": {
    "gn:admin1_code":"MR",
    "gn:admin2_code":"2.0",
    "gn:admin3_code":"59.0",
    "gn:admin4_code":"590023.0",
    "gn:asciiname":"Nigalpani",
    "gn:country_code":"NP",
    "gn:dem":1925,
    "gn:feature_class":"P",
    "gn:feature_code":"PPLL",
    "gn:name":"Nigalpani",
    "gn:population":0,
    "gn:timezone":"Asia/Kathmandu",
    "iso:country":"NP",
    "wof:name":"Nigalpani",
    "wof:placetype":"locality"
},
  "geometry": {"coordinates":[81.64853000000002,28.6742],"type":"Point"}
}