{
  "type": "Feature",
  "properties": {
    "gn:admin1_code":"ER",
    "gn:admin2_code":"13.0",
    "gn:admin3_code":"14.0",
    "gn:admin4_code":"140020.0",
    "gn:asciiname":"Laphagaun",
    "gn:country_code":"NP",
    "gn:dem":1038,
    "gn:feature_class":"P",
    "gn:feature_code":"PPLL",
    "gn:name":"Laphagaun",
    "gn:population":0,
    "gn:timezone":"Asia/Kathmandu",
    "iso:country":"NP",
    "name:hin_x_preferred":[
        "\u0932\u093e\u092b\u093e\u0917\u093e\u0901\u0909"
    ],
    "name:ita_x_preferred":[
        "Laphagaun"
    ],
    "name:mai_x_preferred":[
        "\u0932\u093e\u092b\u093e\u0917\u093e\u0901\u0909"
    ],
    "name:msa_x_preferred":[
        "Laphagaun"
    ],
    "name:pol_x_preferred":[
        "Laphagau"
    ],
    "name:urd_x_preferred":[
        "\u0644\u0627\u067e\u06c1\u0627\u06af\u0648\u0646"
    ],
    "wof:name":"Laphagaun",
    "wof:placetype":"locality"
},
  "geometry": {"coordinates":[86.69821,27.03527],"type":"Point"}
}