{
  "type": "Feature",
  "properties": {
    "gn:admin1_code":"FR",
    "gn:admin2_code":"14",
    "gn:admin3_code":"70.0",
    "gn:admin4_code":"700025.0",
    "gn:asciiname":"Sutalaban",
    "gn:country_code":"NP",
    "gn:dem":1118,
    "gn:feature_class":"P",
    "gn:feature_code":"PPLL",
    "gn:name":"Sutalaban",
    "gn:population":0,
    "gn:timezone":"Asia/Kathmandu",
    "iso:country":"NP",
    "wof:name":"Sutalaban",
    "wof:placetype":"locality"
},
  "geometry": {"coordinates":[81.09309,29.02932],"type":"Point"}
}