{
  "type": "Feature",
  "properties": {
    "gn:admin1_code":"00",
    "gn:asciiname":"Thintol",
    "gn:country_code":"NP",
    "gn:dem":171,
    "gn:feature_class":"P",
    "gn:feature_code":"PPL",
    "gn:name":"Thi\u1e45\u1e6dol",
    "gn:population":0,
    "gn:timezone":"Asia/Kathmandu",
    "iso:country":"NP",
    "wof:name":"Thintol",
    "wof:placetype":"locality"
},
  "geometry": {"coordinates":[85.67915000000001,27.0443],"type":"Point"}
}