{
  "type": "Feature",
  "properties": {
    "gn:admin1_code":"ER",
    "gn:admin2_code":"13.0",
    "gn:admin3_code":"14.0",
    "gn:admin4_code":"140020.0",
    "gn:asciiname":"Pakana",
    "gn:country_code":"NP",
    "gn:dem":938,
    "gn:feature_class":"P",
    "gn:feature_code":"PPLL",
    "gn:name":"Pakana",
    "gn:population":0,
    "gn:timezone":"Asia/Kathmandu",
    "iso:country":"NP",
    "wof:name":"Pakana",
    "wof:placetype":"locality"
},
  "geometry": {"coordinates":[86.72096999999999,27.02406],"type":"Point"}
}