{
  "type": "Feature",
  "properties": {
    "gn:admin1_code":"CR",
    "gn:admin2_code":"11",
    "gn:admin3_code":"32",
    "gn:admin4_code":"320015",
    "gn:asciiname":"Balirmapur",
    "gn:country_code":"NP",
    "gn:dem":94,
    "gn:feature_class":"P",
    "gn:feature_code":"PPLL",
    "gn:name":"Balirmapur",
    "gn:population":0,
    "gn:timezone":"Asia/Kathmandu",
    "iso:country":"NP",
    "wof:name":"Balirmapur",
    "wof:placetype":"locality"
},
  "geometry": {"coordinates":[85.24388,26.97516],"type":"Point"}
}