{
  "type": "Feature",
  "properties": {
    "gn:admin1_code":"MR",
    "gn:admin2_code":"2.0",
    "gn:admin3_code":"58.0",
    "gn:admin4_code":"580026.0",
    "gn:asciiname":"Dalai",
    "gn:country_code":"NP",
    "gn:dem":146,
    "gn:feature_class":"P",
    "gn:feature_code":"PPLL",
    "gn:name":"Dalai",
    "gn:population":0,
    "gn:timezone":"Asia/Kathmandu",
    "iso:country":"NP",
    "wof:name":"Dalai",
    "wof:placetype":"locality"
},
  "geometry": {"coordinates":[81.09021,28.4363],"type":"Point"}
}