{
  "type": "Feature",
  "properties": {
    "gn:admin1_code":"CR",
    "gn:admin2_code":"1",
    "gn:admin3_code":"30.0",
    "gn:admin4_code":"300017.0",
    "gn:asciiname":"Paticho",
    "gn:country_code":"NP",
    "gn:dem":1971,
    "gn:feature_class":"P",
    "gn:feature_code":"PPLL",
    "gn:name":"Paticho",
    "gn:population":0,
    "gn:timezone":"Asia/Kathmandu",
    "iso:country":"NP",
    "wof:name":"Paticho",
    "wof:placetype":"locality"
},
  "geometry": {"coordinates":[85.03243000000001,28.10643],"type":"Point"}
}