{
  "type": "Feature",
  "properties": {
    "gn:admin1_code":"CR",
    "gn:admin2_code":"5",
    "gn:admin3_code":"22.0",
    "gn:admin4_code":"220020.0",
    "gn:asciiname":"Tallo Hawa",
    "gn:country_code":"NP",
    "gn:dem":1479,
    "gn:feature_class":"P",
    "gn:feature_code":"PPLL",
    "gn:name":"Tallo Hawa",
    "gn:population":0,
    "gn:timezone":"Asia/Kathmandu",
    "iso:country":"NP",
    "wof:name":"Tallo Hawa",
    "wof:placetype":"locality"
},
  "geometry": {"coordinates":[86.15923000000002,27.54994000000001],"type":"Point"}
}