{
  "type": "Feature",
  "properties": {
    "gn:admin1_code":"MR",
    "gn:admin2_code":"12",
    "gn:admin3_code":"52",
    "gn:admin4_code":"520014",
    "gn:asciiname":"Majhi Damar",
    "gn:country_code":"NP",
    "gn:dem":512,
    "gn:feature_class":"P",
    "gn:feature_code":"PPLL",
    "gn:name":"Majhi Damar",
    "gn:population":0,
    "gn:timezone":"Asia/Kathmandu",
    "iso:country":"NP",
    "wof:name":"Majhi Damar",
    "wof:placetype":"locality"
},
  "geometry": {"coordinates":[82.98987,27.93074],"type":"Point"}
}