{
  "type": "Feature",
  "properties": {
    "gn:admin1_code":"WR",
    "gn:admin2_code":"4.0",
    "gn:asciiname":"Middle Marsyangdi Hydroelectric Power Plant",
    "gn:country_code":"NP",
    "gn:dem":623,
    "gn:feature_class":"P",
    "gn:feature_code":"PPL",
    "gn:name":"Middle Marsyangdi Hydroelectric Power Plant",
    "gn:population":0,
    "gn:timezone":"Asia/Kathmandu",
    "iso:country":"NP",
    "wof:name":"Middle Marsyangdi Hydroelectric Power Plant",
    "wof:placetype":"locality"
},
  "geometry": {"coordinates":[84.4195,28.189],"type":"Point"}
}