{
  "type": "Feature",
  "properties": {
    "gn:admin1_code":"ER",
    "gn:admin2_code":"7",
    "gn:admin3_code":"7.0",
    "gn:admin4_code":"70004.0",
    "gn:asciiname":"Tallo Amdanda",
    "gn:country_code":"NP",
    "gn:dem":984,
    "gn:feature_class":"P",
    "gn:feature_code":"PPLL",
    "gn:name":"Tallo Amdanda",
    "gn:population":0,
    "gn:timezone":"Asia/Kathmandu",
    "iso:country":"NP",
    "wof:name":"Tallo Amdanda",
    "wof:placetype":"locality"
},
  "geometry": {"coordinates":[87.48106999999997,26.91283],"type":"Point"}
}