{
  "type": "Feature",
  "properties": {
    "gn:admin1_code":"CR",
    "gn:admin2_code":"1",
    "gn:admin3_code":"30.0",
    "gn:admin4_code":"300024.0",
    "gn:asciiname":"Simalswara",
    "gn:country_code":"NP",
    "gn:dem":927,
    "gn:feature_class":"P",
    "gn:feature_code":"PPLL",
    "gn:name":"Simalswara",
    "gn:population":0,
    "gn:timezone":"Asia/Kathmandu",
    "iso:country":"NP",
    "wof:name":"Simalswara",
    "wof:placetype":"locality"
},
  "geometry": {"coordinates":[84.81260999999998,27.93575],"type":"Point"}
}