{
  "type": "Feature",
  "properties": {
    "gn:admin1_code":"FR",
    "gn:admin2_code":"14",
    "gn:admin3_code":"69.0",
    "gn:admin4_code":"690014.0",
    "gn:asciiname":"Kimtola",
    "gn:country_code":"NP",
    "gn:dem":1785,
    "gn:feature_class":"P",
    "gn:feature_code":"PPLL",
    "gn:name":"Kimtola",
    "gn:population":0,
    "gn:timezone":"Asia/Kathmandu",
    "iso:country":"NP",
    "wof:name":"Kimtola",
    "wof:placetype":"locality"
},
  "geometry": {"coordinates":[81.32937,29.10584],"type":"Point"}
}