{
  "type": "Feature",
  "properties": {
    "gn:admin1_code":"MR",
    "gn:admin2_code":"12",
    "gn:admin3_code":"55",
    "gn:admin4_code":"550044",
    "gn:asciiname":"Kankanda",
    "gn:country_code":"NP",
    "gn:dem":1087,
    "gn:feature_class":"P",
    "gn:feature_code":"PPLL",
    "gn:name":"Kankanda",
    "gn:population":0,
    "gn:timezone":"Asia/Kathmandu",
    "iso:country":"NP",
    "wof:name":"Kankanda",
    "wof:placetype":"locality"
},
  "geometry": {"coordinates":[82.15405,28.56349],"type":"Point"}
}