{
  "type": "Feature",
  "properties": {
    "gn:admin1_code":"CR",
    "gn:admin2_code":"1",
    "gn:admin3_code":"24.0",
    "gn:admin4_code":"240049.0",
    "gn:asciiname":"Kumhidih",
    "gn:country_code":"NP",
    "gn:dem":1579,
    "gn:feature_class":"P",
    "gn:feature_code":"PPLL",
    "gn:name":"Kumhidih",
    "gn:population":0,
    "gn:timezone":"Asia/Kathmandu",
    "iso:country":"NP",
    "wof:name":"Kumhidih",
    "wof:placetype":"locality"
},
  "geometry": {"coordinates":[85.46318000000002,27.59748],"type":"Point"}
}