{
  "type": "Feature",
  "properties": {
    "gn:admin1_code":"WR",
    "gn:admin2_code":"4.0",
    "gn:admin3_code":"39.0",
    "gn:admin4_code":"390025.0",
    "gn:asciiname":"Saundi",
    "gn:country_code":"NP",
    "gn:dem":1330,
    "gn:feature_class":"P",
    "gn:feature_code":"PPLL",
    "gn:name":"Saundi",
    "gn:population":0,
    "gn:timezone":"Asia/Kathmandu",
    "iso:country":"NP",
    "wof:name":"Saundi",
    "wof:placetype":"locality"
},
  "geometry": {"coordinates":[83.70571,28.04371],"type":"Point"}
}