{
  "type": "Feature",
  "properties": {
    "gn:admin1_code":"CR",
    "gn:admin2_code":"11",
    "gn:admin3_code":"31",
    "gn:admin4_code":"310040",
    "gn:asciiname":"Pipale",
    "gn:country_code":"NP",
    "gn:dem":385,
    "gn:feature_class":"P",
    "gn:feature_code":"PPLL",
    "gn:name":"Pipale",
    "gn:population":0,
    "gn:timezone":"Asia/Kathmandu",
    "iso:country":"NP",
    "wof:name":"Pipale",
    "wof:placetype":"locality"
},
  "geometry": {"coordinates":[85.25731,27.37498],"type":"Point"}
}