{
  "type": "Feature",
  "properties": {
    "gn:admin1_code":"CR",
    "gn:admin2_code":"11",
    "gn:admin3_code":"31",
    "gn:admin4_code":"310028",
    "gn:asciiname":"Mareng",
    "gn:country_code":"NP",
    "gn:dem":637,
    "gn:feature_class":"P",
    "gn:feature_code":"PPLL",
    "gn:name":"Mareng",
    "gn:population":0,
    "gn:timezone":"Asia/Kathmandu",
    "iso:country":"NP",
    "name:bih_x_preferred":[
        "\u092e\u0930\u0947\u0919"
    ],
    "name:ceb_x_preferred":[
        "Mareng"
    ],
    "name:fra_x_preferred":[
        "Mareng"
    ],
    "name:mai_x_preferred":[
        "\u092e\u0930\u0947\u0919"
    ],
    "name:msa_x_preferred":[
        "Mareng"
    ],
    "name:nep_x_preferred":[
        "\u092e\u0930\u0947\u0919"
    ],
    "name:new_x_preferred":[
        "\u092e\u0930\u0947\u0919"
    ],
    "name:pol_x_preferred":[
        "Mareng"
    ],
    "wof:name":"Mareng",
    "wof:placetype":"locality"
},
  "geometry": {"coordinates":[85.08431,27.43033],"type":"Point"}
}