{
  "type": "Feature",
  "properties": {
    "gn:admin1_code":"CR",
    "gn:admin2_code":"1",
    "gn:admin3_code":"23",
    "gn:admin4_code":"230029",
    "gn:asciiname":"Kyayung",
    "gn:country_code":"NP",
    "gn:dem":2796,
    "gn:feature_class":"P",
    "gn:feature_code":"PPLL",
    "gn:name":"Kyayung",
    "gn:population":0,
    "gn:timezone":"Asia/Kathmandu",
    "iso:country":"NP",
    "wof:name":"Kyayung",
    "wof:placetype":"locality"
},
  "geometry": {"coordinates":[85.58719000000001,27.95994],"type":"Point"}
}