{
  "type": "Feature",
  "properties": {
    "gn:admin1_code":"MR",
    "gn:admin2_code":"12",
    "gn:admin3_code":"54",
    "gn:admin4_code":"540025",
    "gn:asciiname":"Nachnethela",
    "gn:country_code":"NP",
    "gn:dem":2116,
    "gn:feature_class":"P",
    "gn:feature_code":"PPLL",
    "gn:name":"Nachnethela",
    "gn:population":0,
    "gn:timezone":"Asia/Kathmandu",
    "iso:country":"NP",
    "wof:name":"Nachnethela",
    "wof:placetype":"locality"
},
  "geometry": {"coordinates":[82.69395,28.58106],"type":"Point"}
}