{
  "type": "Feature",
  "properties": {
    "gn:admin1_code":"MR",
    "gn:admin2_code":"6",
    "gn:admin3_code":"63.0",
    "gn:admin4_code":"630030.0",
    "gn:asciiname":"Rami Jyula",
    "gn:country_code":"NP",
    "gn:dem":2226,
    "gn:feature_class":"P",
    "gn:feature_code":"PPLL",
    "gn:name":"Rami Jyula",
    "gn:population":0,
    "gn:timezone":"Asia/Kathmandu",
    "iso:country":"NP",
    "wof:name":"Rami Jyula",
    "wof:placetype":"locality"
},
  "geometry": {"coordinates":[82.04156,29.22821],"type":"Point"}
}