{
  "type": "Feature",
  "properties": {
    "gn:admin1_code":"FR",
    "gn:admin2_code":"14",
    "gn:admin3_code":"69.0",
    "gn:admin4_code":"690023.0",
    "gn:asciiname":"Palchaur",
    "gn:country_code":"NP",
    "gn:dem":834,
    "gn:feature_class":"P",
    "gn:feature_code":"PPLL",
    "gn:name":"Palchaur",
    "gn:population":0,
    "gn:timezone":"Asia/Kathmandu",
    "iso:country":"NP",
    "wof:name":"Palchaur",
    "wof:placetype":"locality"
},
  "geometry": {"coordinates":[81.39194999999999,28.99405],"type":"Point"}
}