{
  "type": "Feature",
  "properties": {
    "gn:admin1_code":"00",
    "gn:asciiname":"Tikoli",
    "gn:country_code":"NP",
    "gn:dem":198,
    "gn:feature_class":"P",
    "gn:feature_code":"PPL",
    "gn:name":"Tikoli",
    "gn:population":0,
    "gn:timezone":"Asia/Kathmandu",
    "iso:country":"NP",
    "name:nep_x_preferred":[
        "\u1e6cikauli\u0307\u0304"
    ],
    "wof:name":"Tikoli",
    "wof:placetype":"locality"
},
  "geometry": {"coordinates":[84.49489,27.63041],"type":"Point"}
}