{
  "type": "Feature",
  "properties": {
    "gn:admin1_code":"FR",
    "gn:admin2_code":"9",
    "gn:admin3_code":"72.0",
    "gn:admin4_code":"720015.0",
    "gn:asciiname":"Nayanbasti",
    "gn:country_code":"NP",
    "gn:dem":181,
    "gn:feature_class":"P",
    "gn:feature_code":"PPLL",
    "gn:name":"Nayanbasti",
    "gn:population":0,
    "gn:timezone":"Asia/Kathmandu",
    "iso:country":"NP",
    "wof:name":"Nayanbasti",
    "wof:placetype":"locality"
},
  "geometry": {"coordinates":[80.31312,28.74862000000001],"type":"Point"}
}