{
  "type": "Feature",
  "properties": {
    "gn:admin1_code":"ER",
    "gn:admin2_code":"13",
    "gn:admin3_code":"16",
    "gn:admin4_code":"160055",
    "gn:asciiname":"Madewa",
    "gn:country_code":"NP",
    "gn:dem":99,
    "gn:feature_class":"P",
    "gn:feature_code":"PPLL",
    "gn:name":"Madewa",
    "gn:population":0,
    "gn:timezone":"Asia/Kathmandu",
    "iso:country":"NP",
    "name:msa_x_preferred":[
        "Kampung Madewa"
    ],
    "wof:name":"Madewa",
    "wof:placetype":"locality"
},
  "geometry": {"coordinates":[86.17549,26.82552],"type":"Point"}
}