{
  "type": "Feature",
  "properties": {
    "gn:admin1_code":"MR",
    "gn:admin2_code":"12",
    "gn:admin3_code":"53",
    "gn:admin4_code":"530011",
    "gn:asciiname":"Kaule",
    "gn:country_code":"NP",
    "gn:dem":1864,
    "gn:feature_class":"P",
    "gn:feature_code":"PPLL",
    "gn:name":"Kaule",
    "gn:population":0,
    "gn:timezone":"Asia/Kathmandu",
    "iso:country":"NP",
    "wof:name":"Kaule",
    "wof:placetype":"locality"
},
  "geometry": {"coordinates":[82.50993000000003,28.32075],"type":"Point"}
}