{
  "type": "Feature",
  "properties": {
    "gn:admin1_code":"MR",
    "gn:admin2_code":"12",
    "gn:admin3_code":"53",
    "gn:admin4_code":"530035",
    "gn:asciiname":"Syanla",
    "gn:country_code":"NP",
    "gn:dem":1689,
    "gn:feature_class":"P",
    "gn:feature_code":"PPLL",
    "gn:name":"Syanla",
    "gn:population":0,
    "gn:timezone":"Asia/Kathmandu",
    "iso:country":"NP",
    "wof:name":"Syanla",
    "wof:placetype":"locality"
},
  "geometry": {"coordinates":[82.53679,28.52867],"type":"Point"}
}