{
  "type": "Feature",
  "properties": {
    "gn:admin1_code":"CR",
    "gn:admin2_code":"5",
    "gn:admin3_code":"22.0",
    "gn:admin4_code":"220038.0",
    "gn:asciiname":"Phedi",
    "gn:country_code":"NP",
    "gn:dem":896,
    "gn:feature_class":"P",
    "gn:feature_code":"PPLL",
    "gn:name":"Phedi",
    "gn:population":0,
    "gn:timezone":"Asia/Kathmandu",
    "iso:country":"NP",
    "name:ceb_x_preferred":[
        "Phedi"
    ],
    "name:mai_x_preferred":[
        "\u092b\u0947\u0926\u0940"
    ],
    "name:msa_x_preferred":[
        "Phedi"
    ],
    "name:new_x_preferred":[
        "\u092b\u0947\u0926\u0940"
    ],
    "name:pol_x_preferred":[
        "Phedi"
    ],
    "wof:name":"Phedi",
    "wof:placetype":"locality"
},
  "geometry": {"coordinates":[86.09335,27.52589],"type":"Point"}
}