{
  "type": "Feature",
  "properties": {
    "gn:admin1_code":"WR",
    "gn:admin2_code":"3",
    "gn:admin3_code":"44",
    "gn:admin4_code":"440028",
    "gn:asciiname":"Modibeni",
    "gn:country_code":"NP",
    "gn:dem":860,
    "gn:feature_class":"P",
    "gn:feature_code":"PPLL",
    "gn:name":"Modibeni",
    "gn:population":0,
    "gn:timezone":"Asia/Kathmandu",
    "iso:country":"NP",
    "wof:name":"Modibeni",
    "wof:placetype":"locality"
},
  "geometry": {"coordinates":[83.68141,28.20176],"type":"Point"}
}