{
  "type": "Feature",
  "properties": {
    "gn:admin1_code":"MR",
    "gn:admin2_code":"6",
    "gn:admin3_code":"64.0",
    "gn:admin4_code":"640002.0",
    "gn:asciiname":"Saingadgaun",
    "gn:country_code":"NP",
    "gn:dem":2452,
    "gn:feature_class":"P",
    "gn:feature_code":"PPLL",
    "gn:name":"Saingadgaun",
    "gn:population":0,
    "gn:timezone":"Asia/Kathmandu",
    "iso:country":"NP",
    "wof:name":"Saingadgaun",
    "wof:placetype":"locality"
},
  "geometry": {"coordinates":[81.75709999999999,29.15704],"type":"Point"}
}