{
  "type": "Feature",
  "properties": {
    "gn:admin1_code":"WR",
    "gn:admin2_code":"4",
    "gn:admin3_code":"37",
    "gn:admin4_code":"370011",
    "gn:asciiname":"Hallesi",
    "gn:country_code":"NP",
    "gn:dem":620,
    "gn:feature_class":"P",
    "gn:feature_code":"PPLL",
    "gn:name":"Hallesi",
    "gn:population":0,
    "gn:timezone":"Asia/Kathmandu",
    "iso:country":"NP",
    "wof:name":"Hallesi",
    "wof:placetype":"locality"
},
  "geometry": {"coordinates":[84.23624000000002,28.14458],"type":"Point"}
}