{
  "type": "Feature",
  "properties": {
    "gn:admin1_code":"00",
    "gn:asciiname":"Bistbara",
    "gn:country_code":"NP",
    "gn:dem":2714,
    "gn:feature_class":"P",
    "gn:feature_code":"PPL",
    "gn:name":"Bistb\u0101ra",
    "gn:population":0,
    "gn:timezone":"Asia/Kathmandu",
    "iso:country":"NP",
    "wof:name":"Bistbara",
    "wof:placetype":"locality"
},
  "geometry": {"coordinates":[81.96196999999999,29.37253],"type":"Point"}
}