{
  "type": "Feature",
  "properties": {
    "gn:admin1_code":"ER",
    "gn:admin2_code":"10",
    "gn:admin3_code":"2",
    "gn:admin4_code":"20003",
    "gn:asciiname":"Solumba",
    "gn:country_code":"NP",
    "gn:dem":1252,
    "gn:feature_class":"P",
    "gn:feature_code":"PPLL",
    "gn:name":"Solumba",
    "gn:population":0,
    "gn:timezone":"Asia/Kathmandu",
    "iso:country":"NP",
    "wof:name":"Solumba",
    "wof:placetype":"locality"
},
  "geometry": {"coordinates":[87.63016,26.90841],"type":"Point"}
}