{
  "type": "Feature",
  "properties": {
    "gn:admin1_code":"CR",
    "gn:admin2_code":"5",
    "gn:admin3_code":"21",
    "gn:admin4_code":"210035.0",
    "gn:asciiname":"Sanpmare",
    "gn:country_code":"NP",
    "gn:dem":639,
    "gn:feature_class":"P",
    "gn:feature_code":"PPLL",
    "gn:name":"Sanpmare",
    "gn:population":0,
    "gn:timezone":"Asia/Kathmandu",
    "iso:country":"NP",
    "wof:name":"Sanpmare",
    "wof:placetype":"locality"
},
  "geometry": {"coordinates":[86.08283,27.37536],"type":"Point"}
}