{
  "type": "Feature",
  "properties": {
    "gn:admin1_code":"ER",
    "gn:admin2_code":"10",
    "gn:admin3_code":"2",
    "gn:admin4_code":"20018.0",
    "gn:asciiname":"Yakse",
    "gn:country_code":"NP",
    "gn:dem":1812,
    "gn:feature_class":"P",
    "gn:feature_code":"PPLL",
    "gn:name":"Yakse",
    "gn:population":0,
    "gn:timezone":"Asia/Kathmandu",
    "iso:country":"NP",
    "wof:name":"Yakse",
    "wof:placetype":"locality"
},
  "geometry": {"coordinates":[87.67752,27.01586],"type":"Point"}
}