{
  "type": "Feature",
  "properties": {
    "gn:admin1_code":"ER",
    "gn:admin2_code":"7.0",
    "gn:admin3_code":"6.0",
    "gn:admin4_code":"60013.0",
    "gn:asciiname":"Chiuribas",
    "gn:country_code":"NP",
    "gn:dem":1066,
    "gn:feature_class":"P",
    "gn:feature_code":"PPLL",
    "gn:name":"Chiuribas",
    "gn:population":0,
    "gn:timezone":"Asia/Kathmandu",
    "iso:country":"NP",
    "wof:name":"Chiuribas",
    "wof:placetype":"locality"
},
  "geometry": {"coordinates":[87.30499,26.86492],"type":"Point"}
}