{
  "type": "Feature",
  "properties": {
    "gn:admin1_code":"ER",
    "gn:admin2_code":"10",
    "gn:admin3_code":"4.0",
    "gn:admin4_code":"40045.0",
    "gn:asciiname":"Gadhigaun",
    "gn:country_code":"NP",
    "gn:dem":287,
    "gn:feature_class":"P",
    "gn:feature_code":"PPLL",
    "gn:name":"Gadhigaun",
    "gn:population":0,
    "gn:timezone":"Asia/Kathmandu",
    "iso:country":"NP",
    "wof:name":"Gadhigaun",
    "wof:placetype":"locality"
},
  "geometry": {"coordinates":[88.09246999999998,26.74841],"type":"Point"}
}