{
  "type": "Feature",
  "properties": {
    "gn:admin1_code":"CR",
    "gn:admin2_code":"5",
    "gn:admin3_code":"18",
    "gn:admin4_code":"180041",
    "gn:asciiname":"Tarechauri",
    "gn:country_code":"NP",
    "gn:dem":160,
    "gn:feature_class":"P",
    "gn:feature_code":"PPLL",
    "gn:name":"Tarechauri",
    "gn:population":0,
    "gn:timezone":"Asia/Kathmandu",
    "iso:country":"NP",
    "wof:name":"Tarechauri",
    "wof:placetype":"locality"
},
  "geometry": {"coordinates":[85.76605000000001,26.97524],"type":"Point"}
}