{
  "type": "Feature",
  "properties": {
    "gn:admin1_code":"WR",
    "gn:admin2_code":"3",
    "gn:admin3_code":"45.0",
    "gn:admin4_code":"450052.0",
    "gn:asciiname":"Badsir",
    "gn:country_code":"NP",
    "gn:dem":1042,
    "gn:feature_class":"P",
    "gn:feature_code":"PPLL",
    "gn:name":"Badsir",
    "gn:population":0,
    "gn:timezone":"Asia/Kathmandu",
    "iso:country":"NP",
    "wof:name":"Badsir",
    "wof:placetype":"locality"
},
  "geometry": {"coordinates":[83.587,28.15919],"type":"Point"}
}