{
  "type": "Feature",
  "properties": {
    "gn:admin1_code":"WR",
    "gn:admin2_code":"4",
    "gn:admin3_code":"36.0",
    "gn:admin4_code":"360061.0",
    "gn:asciiname":"Maithum (Tariphant)",
    "gn:country_code":"NP",
    "gn:dem":572,
    "gn:feature_class":"P",
    "gn:feature_code":"PPLL",
    "gn:name":"Maithum (Tariphant)",
    "gn:population":0,
    "gn:timezone":"Asia/Kathmandu",
    "iso:country":"NP",
    "wof:name":"Maithum (Tariphant)",
    "wof:placetype":"locality"
},
  "geometry": {"coordinates":[84.80514000000002,28.03434],"type":"Point"}
}