{
  "type": "Feature",
  "properties": {
    "gn:admin1_code":"MR",
    "gn:admin2_code":"2",
    "gn:admin3_code":"61.0",
    "gn:admin4_code":"610004.0",
    "gn:asciiname":"Padhne",
    "gn:country_code":"NP",
    "gn:dem":1998,
    "gn:feature_class":"P",
    "gn:feature_code":"PPLL",
    "gn:name":"Padhne",
    "gn:population":0,
    "gn:timezone":"Asia/Kathmandu",
    "iso:country":"NP",
    "wof:name":"Padhne",
    "wof:placetype":"locality"
},
  "geometry": {"coordinates":[81.90276,28.84679],"type":"Point"}
}