{
  "type": "Feature",
  "properties": {
    "gn:admin1_code":"FR",
    "gn:admin2_code":"14",
    "gn:admin3_code":"70.0",
    "gn:admin4_code":"700025.0",
    "gn:asciiname":"Lotekuda",
    "gn:country_code":"NP",
    "gn:dem":1240,
    "gn:feature_class":"P",
    "gn:feature_code":"PPLL",
    "gn:name":"Lotekuda",
    "gn:population":0,
    "gn:timezone":"Asia/Kathmandu",
    "iso:country":"NP",
    "wof:name":"Lotekuda",
    "wof:placetype":"locality"
},
  "geometry": {"coordinates":[81.07593,29.01356],"type":"Point"}
}