{
  "type": "Feature",
  "properties": {
    "gn:admin1_code":"WR",
    "gn:admin2_code":"3",
    "gn:admin3_code":"45.0",
    "gn:admin4_code":"450004.0",
    "gn:asciiname":"Saireni",
    "gn:country_code":"NP",
    "gn:dem":2047,
    "gn:feature_class":"P",
    "gn:feature_code":"PPLL",
    "gn:name":"Saireni",
    "gn:population":0,
    "gn:timezone":"Asia/Kathmandu",
    "iso:country":"NP",
    "wof:name":"Saireni",
    "wof:placetype":"locality"
},
  "geometry": {"coordinates":[83.22926,28.29853],"type":"Point"}
}