{
  "type": "Feature",
  "properties": {
    "gn:admin1_code":"MR",
    "gn:admin2_code":"2",
    "gn:admin3_code":"61.0",
    "gn:admin4_code":"610010.0",
    "gn:asciiname":"Airenikholagaun",
    "gn:country_code":"NP",
    "gn:dem":1559,
    "gn:feature_class":"P",
    "gn:feature_code":"PPLL",
    "gn:name":"Airenikholagaun",
    "gn:population":0,
    "gn:timezone":"Asia/Kathmandu",
    "iso:country":"NP",
    "wof:name":"Airenikholagaun",
    "wof:placetype":"locality"
},
  "geometry": {"coordinates":[82.07285999999998,28.72783],"type":"Point"}
}