{
  "type": "Feature",
  "properties": {
    "gn:admin1_code":"WR",
    "gn:admin2_code":"8",
    "gn:admin3_code":"50.0",
    "gn:admin4_code":"500038.0",
    "gn:asciiname":"Naya Basti",
    "gn:country_code":"NP",
    "gn:dem":117,
    "gn:feature_class":"P",
    "gn:feature_code":"PPLL",
    "gn:name":"Naya Basti",
    "gn:population":0,
    "gn:timezone":"Asia/Kathmandu",
    "iso:country":"NP",
    "wof:name":"Naya Basti",
    "wof:placetype":"locality"
},
  "geometry": {"coordinates":[83.02748000000003,27.6574],"type":"Point"}
}