{
  "type": "Feature",
  "properties": {
    "gn:admin1_code":"WR",
    "gn:admin2_code":"8",
    "gn:admin3_code":"46.0",
    "gn:admin4_code":"460002.0",
    "gn:asciiname":"Kharjyang",
    "gn:country_code":"NP",
    "gn:dem":801,
    "gn:feature_class":"P",
    "gn:feature_code":"PPLL",
    "gn:name":"Kharjyang",
    "gn:population":0,
    "gn:timezone":"Asia/Kathmandu",
    "iso:country":"NP",
    "wof:name":"Kharjyang",
    "wof:placetype":"locality"
},
  "geometry": {"coordinates":[83.30570999999998,27.96897],"type":"Point"}
}