{
  "type": "Feature",
  "properties": {
    "gn:admin1_code":"WR",
    "gn:admin2_code":"8",
    "gn:admin3_code":"47",
    "gn:admin4_code":"470029.0",
    "gn:asciiname":"Siudi",
    "gn:country_code":"NP",
    "gn:dem":398,
    "gn:feature_class":"P",
    "gn:feature_code":"PPLL",
    "gn:name":"Siudi",
    "gn:population":0,
    "gn:timezone":"Asia/Kathmandu",
    "iso:country":"NP",
    "name:bih_x_preferred":[
        "\u0938\u093f\u0909\u0921\u0940"
    ],
    "name:ceb_x_preferred":[
        "Siudi"
    ],
    "name:fra_x_preferred":[
        "Siudi"
    ],
    "name:hin_x_preferred":[
        "\u0938\u093f\u0909\u0921\u0940"
    ],
    "name:mai_x_preferred":[
        "\u0938\u093f\u0909\u0921\u0940"
    ],
    "name:msa_x_preferred":[
        "Siudi"
    ],
    "name:nep_x_preferred":[
        "\u0938\u093f\u0909\u0921\u0940"
    ],
    "name:new_x_preferred":[
        "\u0938\u093f\u0909\u0926\u0940"
    ],
    "name:pol_x_preferred":[
        "Siudi"
    ],
    "wof:name":"Siudi",
    "wof:placetype":"locality"
},
  "geometry": {"coordinates":[83.71935999999999,27.9146],"type":"Point"}
}