{
  "type": "Feature",
  "properties": {
    "gn:admin1_code":"CR",
    "gn:admin2_code":"5",
    "gn:admin3_code":"19",
    "gn:admin4_code":"190087",
    "gn:asciiname":"Salempur",
    "gn:country_code":"NP",
    "gn:dem":97,
    "gn:feature_class":"P",
    "gn:feature_code":"PPLL",
    "gn:name":"Salempur",
    "gn:population":0,
    "gn:timezone":"Asia/Kathmandu",
    "iso:country":"NP",
    "name:ceb_x_preferred":[
        "Salempur"
    ],
    "name:fra_x_preferred":[
        "Salempur"
    ],
    "name:mai_x_preferred":[
        "\u0938\u0932\u0947\u092e\u092a\u0941\u0930"
    ],
    "name:nep_x_preferred":[
        "\u0938\u0932\u0947\u092e\u092a\u0941\u0930"
    ],
    "name:new_x_preferred":[
        "\u0938\u0932\u0947\u092e\u092a\u0941\u0930"
    ],
    "name:pol_x_preferred":[
        "Salempur"
    ],
    "wof:name":"Salempur",
    "wof:placetype":"locality"
},
  "geometry": {"coordinates":[85.5607,26.91069],"type":"Point"}
}