{
  "type": "Feature",
  "properties": {
    "gn:admin1_code":"MR",
    "gn:admin2_code":"2",
    "gn:admin3_code":"60.0",
    "gn:admin4_code":"600012.0",
    "gn:asciiname":"Palta",
    "gn:country_code":"NP",
    "gn:dem":1549,
    "gn:feature_class":"P",
    "gn:feature_code":"PPLL",
    "gn:name":"Palta",
    "gn:population":0,
    "gn:timezone":"Asia/Kathmandu",
    "iso:country":"NP",
    "name:hrv_x_preferred":[
        "Palta"
    ],
    "name:spa_x_preferred":[
        "Paltas"
    ],
    "wof:name":"Palta",
    "wof:placetype":"locality"
},
  "geometry": {"coordinates":[81.61273,28.99841],"type":"Point"}
}