{
  "type": "Feature",
  "properties": {
    "gn:admin1_code":"MR",
    "gn:admin2_code":"6",
    "gn:admin3_code":"63.0",
    "gn:admin4_code":"630026.0",
    "gn:asciiname":"Kureli",
    "gn:country_code":"NP",
    "gn:dem":3411,
    "gn:feature_class":"P",
    "gn:feature_code":"PPLL",
    "gn:name":"Kureli",
    "gn:population":0,
    "gn:timezone":"Asia/Kathmandu",
    "iso:country":"NP",
    "name:ceb_x_preferred":[
        "Kureli"
    ],
    "name:fra_x_preferred":[
        "Kureli"
    ],
    "name:mai_x_preferred":[
        "\u0915\u0941\u0930\u0947\u0932\u0940"
    ],
    "name:msa_x_preferred":[
        "Kureli"
    ],
    "name:nep_x_preferred":[
        "\u0915\u0941\u0930\u0947\u0932\u0940"
    ],
    "name:new_x_preferred":[
        "\u0915\u0941\u0930\u0947\u0932\u0940"
    ],
    "name:pol_x_preferred":[
        "Kureli"
    ],
    "wof:name":"Kureli",
    "wof:placetype":"locality"
},
  "geometry": {"coordinates":[82.18052,29.39477],"type":"Point"}
}