{
  "type": "Feature",
  "properties": {
    "gn:admin1_code":"WR",
    "gn:admin2_code":"4.0",
    "gn:admin3_code":"39.0",
    "gn:admin4_code":"390033.0",
    "gn:asciiname":"Tallo Bajhadi",
    "gn:country_code":"NP",
    "gn:dem":1042,
    "gn:feature_class":"P",
    "gn:feature_code":"PPLL",
    "gn:name":"Tallo Bajhadi",
    "gn:population":0,
    "gn:timezone":"Asia/Kathmandu",
    "iso:country":"NP",
    "wof:name":"Tallo Bajhadi",
    "wof:placetype":"locality"
},
  "geometry": {"coordinates":[83.64537,27.91236],"type":"Point"}
}