{
  "type": "Feature",
  "properties": {
    "gn:admin1_code":"CR",
    "gn:admin2_code":"11",
    "gn:admin3_code":"35.0",
    "gn:admin4_code":"350037.0",
    "gn:asciiname":"Gamidung",
    "gn:country_code":"NP",
    "gn:dem":876,
    "gn:feature_class":"P",
    "gn:feature_code":"PPLL",
    "gn:name":"Gamidung",
    "gn:population":0,
    "gn:timezone":"Asia/Kathmandu",
    "iso:country":"NP",
    "wof:name":"Gamidung",
    "wof:placetype":"locality"
},
  "geometry": {"coordinates":[84.66346999999998,27.69246],"type":"Point"}
}