{
  "type": "Feature",
  "properties": {
    "gn:admin1_code":"FR",
    "gn:admin2_code":"14",
    "gn:admin3_code":"70.0",
    "gn:admin4_code":"700035.0",
    "gn:asciiname":"Bunala Gilla",
    "gn:country_code":"NP",
    "gn:dem":1321,
    "gn:feature_class":"P",
    "gn:feature_code":"PPLL",
    "gn:name":"Bunala Gilla",
    "gn:population":0,
    "gn:timezone":"Asia/Kathmandu",
    "iso:country":"NP",
    "wof:name":"Bunala Gilla",
    "wof:placetype":"locality"
},
  "geometry": {"coordinates":[80.8699,29.32213],"type":"Point"}
}