{
  "type": "Feature",
  "properties": {
    "gn:admin1_code":"ER",
    "gn:admin2_code":"10",
    "gn:admin3_code":"2",
    "gn:admin4_code":"20029",
    "gn:asciiname":"Odin",
    "gn:country_code":"NP",
    "gn:dem":1260,
    "gn:feature_class":"P",
    "gn:feature_code":"PPLL",
    "gn:name":"Odin",
    "gn:population":0,
    "gn:timezone":"Asia/Kathmandu",
    "iso:country":"NP",
    "wof:name":"Odin",
    "wof:placetype":"locality"
},
  "geometry": {"coordinates":[87.76403000000001,27.13629],"type":"Point"}
}