{
  "type": "Feature",
  "properties": {
    "gn:admin1_code":"FR",
    "gn:admin2_code":"14",
    "gn:admin3_code":"69.0",
    "gn:admin4_code":"690064.0",
    "gn:asciiname":"Humku",
    "gn:country_code":"NP",
    "gn:dem":1196,
    "gn:feature_class":"P",
    "gn:feature_code":"PPLL",
    "gn:name":"Humku",
    "gn:population":0,
    "gn:timezone":"Asia/Kathmandu",
    "iso:country":"NP",
    "wof:name":"Humku",
    "wof:placetype":"locality"
},
  "geometry": {"coordinates":[81.27215,29.05301],"type":"Point"}
}