{
  "type": "Feature",
  "properties": {
    "gn:admin1_code":"FR",
    "gn:admin2_code":"14",
    "gn:admin3_code":"69",
    "gn:admin4_code":"690040",
    "gn:asciiname":"Rajkot",
    "gn:country_code":"NP",
    "gn:dem":1866,
    "gn:feature_class":"P",
    "gn:feature_code":"PPLL",
    "gn:name":"Rajkot",
    "gn:population":0,
    "gn:timezone":"Asia/Kathmandu",
    "iso:country":"NP",
    "wof:name":"Rajkot",
    "wof:placetype":"locality"
},
  "geometry": {"coordinates":[81.34222,29.23387],"type":"Point"}
}