{
  "type": "Feature",
  "properties": {
    "gn:admin1_code":"MR",
    "gn:admin2_code":"6",
    "gn:admin3_code":"63.0",
    "gn:admin4_code":"630021.0",
    "gn:asciiname":"Jhulani",
    "gn:country_code":"NP",
    "gn:dem":2802,
    "gn:feature_class":"P",
    "gn:feature_code":"PPLL",
    "gn:name":"Jhulani",
    "gn:population":0,
    "gn:timezone":"Asia/Kathmandu",
    "iso:country":"NP",
    "wof:name":"Jhulani",
    "wof:placetype":"locality"
},
  "geometry": {"coordinates":[82.07533000000002,29.41694],"type":"Point"}
}