{
  "type": "Feature",
  "properties": {
    "gn:admin1_code":"CR",
    "gn:admin2_code":"1",
    "gn:admin3_code":"27.0",
    "gn:admin4_code":"270027.0",
    "gn:asciiname":"Chipalibot",
    "gn:country_code":"NP",
    "gn:dem":1488,
    "gn:feature_class":"P",
    "gn:feature_code":"PPLL",
    "gn:name":"Chipalibot",
    "gn:population":0,
    "gn:timezone":"Asia/Kathmandu",
    "iso:country":"NP",
    "wof:name":"Chipalibot",
    "wof:placetype":"locality"
},
  "geometry": {"coordinates":[85.26945000000001,27.76793],"type":"Point"}
}