{
  "type": "Feature",
  "properties": {
    "gn:admin1_code":"WR",
    "gn:admin2_code":"8",
    "gn:admin3_code":"46.0",
    "gn:admin4_code":"460046.0",
    "gn:asciiname":"Tolgagaun",
    "gn:country_code":"NP",
    "gn:dem":1059,
    "gn:feature_class":"P",
    "gn:feature_code":"PPLL",
    "gn:name":"Tolgagaun",
    "gn:population":0,
    "gn:timezone":"Asia/Kathmandu",
    "iso:country":"NP",
    "wof:name":"Tolgagaun",
    "wof:placetype":"locality"
},
  "geometry": {"coordinates":[83.38415000000001,28.04077],"type":"Point"}
}