{
  "type": "Feature",
  "properties": {
    "gn:admin1_code":"ER",
    "gn:admin2_code":"7",
    "gn:admin3_code":"7.0",
    "gn:admin4_code":"70020.0",
    "gn:asciiname":"Sahargaun",
    "gn:country_code":"NP",
    "gn:dem":1515,
    "gn:feature_class":"P",
    "gn:feature_code":"PPLL",
    "gn:name":"Sahargaun",
    "gn:population":0,
    "gn:timezone":"Asia/Kathmandu",
    "iso:country":"NP",
    "wof:name":"Sahargaun",
    "wof:placetype":"locality"
},
  "geometry": {"coordinates":[87.23361,26.96947],"type":"Point"}
}