{
  "type": "Feature",
  "properties": {
    "gn:admin1_code":"CR",
    "gn:admin2_code":"1",
    "gn:admin3_code":"30.0",
    "gn:admin4_code":"300035.0",
    "gn:asciiname":"Ijara",
    "gn:country_code":"NP",
    "gn:dem":791,
    "gn:feature_class":"P",
    "gn:feature_code":"PPLL",
    "gn:name":"Ijara",
    "gn:population":0,
    "gn:timezone":"Asia/Kathmandu",
    "iso:country":"NP",
    "wof:name":"Ijara",
    "wof:placetype":"locality"
},
  "geometry": {"coordinates":[84.91064,27.9086],"type":"Point"}
}