{
  "type": "Feature",
  "properties": {
    "gn:admin1_code":"ER",
    "gn:admin2_code":"13",
    "gn:admin3_code":"13",
    "gn:admin4_code":"130056",
    "gn:asciiname":"Sirubas",
    "gn:country_code":"NP",
    "gn:dem":1865,
    "gn:feature_class":"P",
    "gn:feature_code":"PPLL",
    "gn:name":"Sirubas",
    "gn:population":0,
    "gn:timezone":"Asia/Kathmandu",
    "iso:country":"NP",
    "wof:name":"Sirubas",
    "wof:placetype":"locality"
},
  "geometry": {"coordinates":[86.87871,27.29234000000001],"type":"Point"}
}