{
  "type": "Feature",
  "properties": {
    "gn:admin1_code":"WR",
    "gn:admin2_code":"8",
    "gn:admin3_code":"50.0",
    "gn:admin4_code":"500049.0",
    "gn:asciiname":"Bairihawa",
    "gn:country_code":"NP",
    "gn:dem":109,
    "gn:feature_class":"P",
    "gn:feature_code":"PPLL",
    "gn:name":"Bairihawa",
    "gn:population":0,
    "gn:timezone":"Asia/Kathmandu",
    "iso:country":"NP",
    "wof:name":"Bairihawa",
    "wof:placetype":"locality"
},
  "geometry": {"coordinates":[82.98100000000002,27.60568],"type":"Point"}
}