{
  "type": "Feature",
  "properties": {
    "gn:admin1_code":"ER",
    "gn:admin2_code":"7",
    "gn:admin3_code":"7.0",
    "gn:admin4_code":"70007.0",
    "gn:asciiname":"Hamela",
    "gn:country_code":"NP",
    "gn:dem":1111,
    "gn:feature_class":"P",
    "gn:feature_code":"PPLL",
    "gn:name":"Hamela",
    "gn:population":0,
    "gn:timezone":"Asia/Kathmandu",
    "iso:country":"NP",
    "wof:name":"Hamela",
    "wof:placetype":"locality"
},
  "geometry": {"coordinates":[87.42895,26.91695],"type":"Point"}
}