{
  "type": "Feature",
  "properties": {
    "gn:admin1_code":"CR",
    "gn:admin2_code":"11.0",
    "gn:admin3_code":"33.0",
    "gn:admin4_code":"330088.0",
    "gn:asciiname":"Chipletigaun",
    "gn:country_code":"NP",
    "gn:dem":342,
    "gn:feature_class":"P",
    "gn:feature_code":"PPLL",
    "gn:name":"Chipletigaun",
    "gn:population":0,
    "gn:timezone":"Asia/Kathmandu",
    "iso:country":"NP",
    "wof:name":"Chipletigaun",
    "wof:placetype":"locality"
},
  "geometry": {"coordinates":[85.06756,27.30344],"type":"Point"}
}