{
  "type": "Feature",
  "properties": {
    "gn:admin1_code":"MR",
    "gn:admin2_code":"12",
    "gn:admin3_code":"55",
    "gn:admin4_code":"550032",
    "gn:asciiname":"Salchaur",
    "gn:country_code":"NP",
    "gn:dem":1331,
    "gn:feature_class":"P",
    "gn:feature_code":"PPLL",
    "gn:name":"Salchaur",
    "gn:population":0,
    "gn:timezone":"Asia/Kathmandu",
    "iso:country":"NP",
    "wof:name":"Salchaur",
    "wof:placetype":"locality"
},
  "geometry": {"coordinates":[82.08367,28.35921],"type":"Point"}
}