{
  "type": "Feature",
  "properties": {
    "gn:admin1_code":"WR",
    "gn:admin2_code":"4.0",
    "gn:admin3_code":"39.0",
    "gn:admin4_code":"390007.0",
    "gn:asciiname":"Pathredhunga",
    "gn:country_code":"NP",
    "gn:dem":1067,
    "gn:feature_class":"P",
    "gn:feature_code":"PPLL",
    "gn:name":"Pathredhunga",
    "gn:population":0,
    "gn:timezone":"Asia/Kathmandu",
    "iso:country":"NP",
    "wof:name":"Pathredhunga",
    "wof:placetype":"locality"
},
  "geometry": {"coordinates":[83.83459999999999,28.03472],"type":"Point"}
}