{
  "type": "Feature",
  "properties": {
    "gn:admin1_code":"MR",
    "gn:admin2_code":"12",
    "gn:admin3_code":"54",
    "gn:admin4_code":"540036",
    "gn:asciiname":"Rungha",
    "gn:country_code":"NP",
    "gn:dem":1402,
    "gn:feature_class":"P",
    "gn:feature_code":"PPLL",
    "gn:name":"Rungha",
    "gn:population":0,
    "gn:timezone":"Asia/Kathmandu",
    "iso:country":"NP",
    "wof:name":"Rungha",
    "wof:placetype":"locality"
},
  "geometry": {"coordinates":[82.45504,28.56534000000001],"type":"Point"}
}