{
  "type": "Feature",
  "properties": {
    "gn:admin1_code":"MR",
    "gn:admin2_code":"6",
    "gn:admin3_code":"64.0",
    "gn:admin4_code":"640001.0",
    "gn:asciiname":"Lupiya",
    "gn:country_code":"NP",
    "gn:dem":2755,
    "gn:feature_class":"P",
    "gn:feature_code":"PPLL",
    "gn:name":"Lupiya",
    "gn:population":0,
    "gn:timezone":"Asia/Kathmandu",
    "iso:country":"NP",
    "wof:name":"Lupiya",
    "wof:placetype":"locality"
},
  "geometry": {"coordinates":[81.66216999999997,29.19612],"type":"Point"}
}