{
  "type": "Feature",
  "properties": {
    "gn:admin1_code":"CR",
    "gn:admin2_code":"1",
    "gn:admin3_code":"28",
    "gn:admin4_code":"280011",
    "gn:asciiname":"Bhorletar",
    "gn:country_code":"NP",
    "gn:dem":515,
    "gn:feature_class":"P",
    "gn:feature_code":"PPLL",
    "gn:name":"Bhorletar",
    "gn:population":0,
    "gn:timezone":"Asia/Kathmandu",
    "iso:country":"NP",
    "name:ceb_x_preferred":[
        "Bhorletar"
    ],
    "name:fra_x_preferred":[
        "Bhorletar"
    ],
    "name:msa_x_preferred":[
        "Bhorletar"
    ],
    "name:nep_x_preferred":[
        "\u092d\u094b\u0930\u094d\u0932\u0947\u091f\u093e\u0930"
    ],
    "name:new_x_preferred":[
        "\u092d\u094b\u0930\u094d\u0932\u0947\u091f\u093e\u0930"
    ],
    "name:pol_x_preferred":[
        "Bhorletar"
    ],
    "wof:name":"Bhorletar",
    "wof:placetype":"locality"
},
  "geometry": {"coordinates":[85.12155,27.8787],"type":"Point"}
}