{
  "type": "Feature",
  "properties": {
    "gn:admin1_code":"CR",
    "gn:admin2_code":"1",
    "gn:admin3_code":"29",
    "gn:admin4_code":"290011",
    "gn:asciiname":"Mundu",
    "gn:country_code":"NP",
    "gn:dem":3594,
    "gn:feature_class":"P",
    "gn:feature_code":"PPLL",
    "gn:name":"Mundu",
    "gn:population":0,
    "gn:timezone":"Asia/Kathmandu",
    "iso:country":"NP",
    "name:fra_x_preferred":[
        "Mundu"
    ],
    "name:mal_x_preferred":[
        "\u0d2e\u0d41\u0d23\u0d4d\u0d1f\u0d4d"
    ],
    "name:pol_x_preferred":[
        "Mundu"
    ],
    "wof:name":"Mundu",
    "wof:placetype":"locality"
},
  "geometry": {"coordinates":[85.52275,28.21794],"type":"Point"}
}