{
  "type": "Feature",
  "properties": {
    "gn:admin1_code":"WR",
    "gn:admin2_code":"3",
    "gn:admin3_code":"45",
    "gn:admin4_code":"450060",
    "gn:asciiname":"Ghartithar",
    "gn:country_code":"NP",
    "gn:dem":1549,
    "gn:feature_class":"P",
    "gn:feature_code":"PPLL",
    "gn:name":"Ghartithar",
    "gn:population":0,
    "gn:timezone":"Asia/Kathmandu",
    "iso:country":"NP",
    "wof:name":"Ghartithar",
    "wof:placetype":"locality"
},
  "geometry": {"coordinates":[83.56111,28.24242000000001],"type":"Point"}
}