{
  "type": "Feature",
  "properties": {
    "gn:admin1_code":"CR",
    "gn:admin2_code":"1.0",
    "gn:admin3_code":"26.0",
    "gn:admin4_code":"260017.0",
    "gn:asciiname":"Adikarigaun",
    "gn:country_code":"NP",
    "gn:dem":1840,
    "gn:feature_class":"P",
    "gn:feature_code":"PPLL",
    "gn:name":"Adikarigaun",
    "gn:population":0,
    "gn:timezone":"Asia/Kathmandu",
    "iso:country":"NP",
    "wof:name":"Adikarigaun",
    "wof:placetype":"locality"
},
  "geometry": {"coordinates":[85.50175,27.68579],"type":"Point"}
}