{
  "type": "Feature",
  "properties": {
    "gn:admin1_code":"ER",
    "gn:admin2_code":"10",
    "gn:admin3_code":"3.0",
    "gn:admin4_code":"30040.0",
    "gn:asciiname":"Gorakh",
    "gn:country_code":"NP",
    "gn:dem":1481,
    "gn:feature_class":"P",
    "gn:feature_code":"PPLL",
    "gn:name":"Gorakh",
    "gn:population":0,
    "gn:timezone":"Asia/Kathmandu",
    "iso:country":"NP",
    "wof:name":"Gorakh",
    "wof:placetype":"locality"
},
  "geometry": {"coordinates":[88.13766,26.86552],"type":"Point"}
}