{
  "type": "Feature",
  "properties": {
    "gn:admin1_code":"WR",
    "gn:admin2_code":"4.0",
    "gn:admin3_code":"39.0",
    "gn:admin4_code":"390046.0",
    "gn:asciiname":"Chhapkharka",
    "gn:country_code":"NP",
    "gn:dem":1213,
    "gn:feature_class":"P",
    "gn:feature_code":"PPLL",
    "gn:name":"Chhapkharka",
    "gn:population":0,
    "gn:timezone":"Asia/Kathmandu",
    "iso:country":"NP",
    "wof:name":"Chhapkharka",
    "wof:placetype":"locality"
},
  "geometry": {"coordinates":[83.76574000000002,28.0878],"type":"Point"}
}