{
  "type": "Feature",
  "properties": {
    "gn:admin1_code":"ER",
    "gn:admin2_code":"10",
    "gn:admin3_code":"4.0",
    "gn:admin4_code":"40024.0",
    "gn:asciiname":"Dhanusa Pokhari",
    "gn:country_code":"NP",
    "gn:dem":96,
    "gn:feature_class":"P",
    "gn:feature_code":"PPLL",
    "gn:name":"Dhanusa Pokhari",
    "gn:population":0,
    "gn:timezone":"Asia/Kathmandu",
    "iso:country":"NP",
    "wof:name":"Dhanusa Pokhari",
    "wof:placetype":"locality"
},
  "geometry": {"coordinates":[87.98772,26.54249],"type":"Point"}
}