{
  "type": "Feature",
  "properties": {
    "gn:admin1_code":"WR",
    "gn:admin2_code":"3",
    "gn:admin3_code":"44",
    "gn:admin4_code":"440024",
    "gn:asciiname":"Sarandi",
    "gn:country_code":"NP",
    "gn:dem":915,
    "gn:feature_class":"P",
    "gn:feature_code":"PPLL",
    "gn:name":"Sarandi",
    "gn:population":0,
    "gn:timezone":"Asia/Kathmandu",
    "iso:country":"NP",
    "name:ceb_x_preferred":[
        "Sarandi"
    ],
    "name:fra_x_preferred":[
        "Sarandi"
    ],
    "name:ita_x_preferred":[
        "Sarandi"
    ],
    "name:mlg_x_preferred":[
        "Sarandi"
    ],
    "name:nld_x_preferred":[
        "Sarandi"
    ],
    "name:nor_x_preferred":[
        "Sarandi"
    ],
    "name:por_x_preferred":[
        "Sarandi"
    ],
    "name:rus_x_preferred":[
        "\u0421\u0430\u0440\u0430\u043d\u0434\u0438"
    ],
    "name:sco_x_preferred":[
        "Sarandi"
    ],
    "name:spa_x_preferred":[
        "Sarandi"
    ],
    "name:swe_x_preferred":[
        "Sarandi"
    ],
    "name:vie_x_preferred":[
        "Sarandi"
    ],
    "name:vol_x_preferred":[
        "Sarandi"
    ],
    "wof:name":"Sarandi",
    "wof:placetype":"locality"
},
  "geometry": {"coordinates":[83.6799,28.16668],"type":"Point"}
}