{
  "type": "Feature",
  "properties": {
    "gn:admin1_code":"WR",
    "gn:admin2_code":"3",
    "gn:admin3_code":"44",
    "gn:admin4_code":"440024",
    "gn:asciiname":"Sarandi",
    "gn:country_code":"NP",
    "gn:dem":915,
    "gn:feature_class":"P",
    "gn:feature_code":"PPLL",
    "gn:name":"Sarandi",
    "gn:population":0,
    "gn:timezone":"Asia/Kathmandu",
    "iso:country":"NP",
    "wof:name":"Sarandi",
    "wof:placetype":"locality"
},
  "geometry": {"coordinates":[83.6799,28.16668],"type":"Point"}
}