{
  "type": "Feature",
  "properties": {
    "gn:admin1_code":"MR",
    "gn:admin2_code":"12",
    "gn:admin3_code":"53",
    "gn:admin4_code":"530018",
    "gn:asciiname":"Subikhani",
    "gn:country_code":"NP",
    "gn:dem":2604,
    "gn:feature_class":"P",
    "gn:feature_code":"PPLL",
    "gn:name":"Subikhani",
    "gn:population":0,
    "gn:timezone":"Asia/Kathmandu",
    "iso:country":"NP",
    "wof:name":"Subikhani",
    "wof:placetype":"locality"
},
  "geometry": {"coordinates":[82.77354,28.39844],"type":"Point"}
}