{
  "type": "Feature",
  "properties": {
    "gn:admin1_code":"FR",
    "gn:admin2_code":"9",
    "gn:admin3_code":"73.0",
    "gn:admin4_code":"730013.0",
    "gn:asciiname":"Naula",
    "gn:country_code":"NP",
    "gn:dem":1022,
    "gn:feature_class":"P",
    "gn:feature_code":"PPLL",
    "gn:name":"Naula",
    "gn:population":0,
    "gn:timezone":"Asia/Kathmandu",
    "iso:country":"NP",
    "name:sin_x_preferred":[
        "\u0db1\u0dcf\u0d8b\u0dbd"
    ],
    "wof:name":"Naula",
    "wof:placetype":"locality"
},
  "geometry": {"coordinates":[80.33757,29.05881],"type":"Point"}
}