{
  "type": "Feature",
  "properties": {
    "gn:admin1_code":"ER",
    "gn:admin2_code":"7",
    "gn:admin3_code":"5",
    "gn:admin4_code":"50064",
    "gn:asciiname":"Urlabari",
    "gn:country_code":"NP",
    "gn:dem":126,
    "gn:feature_class":"P",
    "gn:feature_code":"PPLL",
    "gn:name":"Urlabari",
    "gn:population":0,
    "gn:timezone":"Asia/Kathmandu",
    "iso:country":"NP",
    "name:ceb_x_preferred":[
        "Urlabari"
    ],
    "name:deu_x_preferred":[
        "Urlabari"
    ],
    "name:msa_x_preferred":[
        "Urlabari"
    ],
    "name:nep_x_preferred":[
        "\u0909\u0930\u094d\u0932\u093e\u0935\u093e\u0930\u0940 \u0928\u0917\u0930\u092a\u093e\u0932\u093f\u0915\u093e"
    ],
    "name:new_x_preferred":[
        "\u0909\u0930\u094d\u0932\u093e\u092c\u093e\u0930\u0940"
    ],
    "name:pol_x_preferred":[
        "Urlabari"
    ],
    "wof:name":"Urlabari",
    "wof:placetype":"locality"
},
  "geometry": {"coordinates":[87.63486,26.66996],"type":"Point"}
}