{
  "type": "Feature",
  "properties": {
    "gn:admin1_code":"MR",
    "gn:admin2_code":"12",
    "gn:admin3_code":"56.0",
    "gn:admin4_code":"560022.0",
    "gn:asciiname":"Campus",
    "gn:country_code":"NP",
    "gn:dem":640,
    "gn:feature_class":"P",
    "gn:feature_code":"PPLL",
    "gn:name":"Campus",
    "gn:population":0,
    "gn:timezone":"Asia/Kathmandu",
    "iso:country":"NP",
    "wof:name":"Campus",
    "wof:placetype":"locality"
},
  "geometry": {"coordinates":[82.36264,28.09436],"type":"Point"}
}