{
  "type": "Feature",
  "properties": {
    "gn:admin1_code":"MR",
    "gn:admin2_code":"12",
    "gn:admin3_code":"56.0",
    "gn:admin4_code":"560022.0",
    "gn:asciiname":"Campus",
    "gn:country_code":"NP",
    "gn:dem":640,
    "gn:feature_class":"P",
    "gn:feature_code":"PPLL",
    "gn:name":"Campus",
    "gn:population":0,
    "gn:timezone":"Asia/Kathmandu",
    "iso:country":"NP",
    "name:ara_x_preferred":[
        "\u062d\u0631\u0645 \u062c\u0627\u0645\u0639\u064a"
    ],
    "name:ast_x_preferred":[
        "Campus"
    ],
    "name:aze_x_preferred":[
        "Kampus"
    ],
    "name:bel_x_preferred":[
        "\u041a\u0430\u043c\u043f\u0443\u0441"
    ],
    "name:ben_x_preferred":[
        "\u0995\u09cd\u09af\u09be\u09ae\u09cd\u09aa\u09be\u09b8"
    ],
    "name:bul_x_preferred":[
        "\u041a\u0430\u043c\u043f\u0443\u0441"
    ],
    "name:cat_x_preferred":[
        "Campus"
    ],
    "name:ces_x_preferred":[
        "Kampus"
    ],
    "name:dan_x_preferred":[
        "Campus"
    ],
    "name:deu_x_preferred":[
        "Campus"
    ],
    "name:diq_x_preferred":[
        "Kampus"
    ],
    "name:ell_x_preferred":[
        "\u03a0\u03b1\u03bd\u03b5\u03c0\u03b9\u03c3\u03c4\u03b7\u03bc\u03b9\u03bf\u03cd\u03c0\u03bf\u03bb\u03b7"
    ],
    "name:epo_x_preferred":[
        "Kampuso"
    ],
    "name:est_x_preferred":[
        "\u00dclikoolilinnak"
    ],
    "name:eus_x_preferred":[
        "Campus"
    ],
    "name:fas_x_preferred":[
        "\u067e\u0631\u062f\u06cc\u0633 \u062f\u0627\u0646\u0634\u06af\u0627\u0647\u06cc"
    ],
    "name:fin_x_preferred":[
        "Kampus"
    ],
    "name:fra_x_preferred":[
        "Campus"
    ],
    "name:fry_x_preferred":[
        "Kampus"
    ],
    "name:glg_x_preferred":[
        "Campus"
    ],
    "name:heb_x_preferred":[
        "\u05e7\u05de\u05e4\u05d5\u05e1"
    ],
    "name:hye_x_preferred":[
        "\u053f\u0561\u0574\u057a\u0578\u0582\u057d"
    ],
    "name:ind_x_preferred":[
        "Kampus"
    ],
    "name:ita_x_preferred":[
        "Campus"
    ],
    "name:jav_x_preferred":[
        "Kampus"
    ],
    "name:jpn_x_preferred":[
        "\u30ad\u30e3\u30f3\u30d1\u30b9"
    ],
    "name:kor_x_preferred":[
        "\ucea0\ud37c\uc2a4"
    ],
    "name:lit_x_preferred":[
        "Universitetinis miestelis"
    ],
    "name:nld_x_preferred":[
        "Campus"
    ],
    "name:nno_x_preferred":[
        "Campus"
    ],
    "name:nor_x_preferred":[
        "Campus"
    ],
    "name:pol_x_preferred":[
        "Miasteczko akademickie"
    ],
    "name:por_x_preferred":[
        "Campus"
    ],
    "name:que_x_preferred":[
        "Campus"
    ],
    "name:rus_x_preferred":[
        "\u041a\u0430\u043c\u043f\u0443\u0441"
    ],
    "name:sin_x_preferred":[
        "\u0d85\u0db0\u0dca\u200d\u0dba\u0dba\u0db1 \u0db8\u0dab\u0dca\u0da9\u0db4"
    ],
    "name:slk_x_preferred":[
        "Kampus"
    ],
    "name:spa_x_preferred":[
        "Campus"
    ],
    "name:srp_x_preferred":[
        "\u041a\u0430\u043c\u043f\u0443\u0441"
    ],
    "name:swe_x_preferred":[
        "Campus"
    ],
    "name:tha_x_preferred":[
        "\u0e27\u0e34\u0e17\u0e22\u0e32\u0e40\u0e02\u0e15"
    ],
    "name:tur_x_preferred":[
        "Yerle\u015fke"
    ],
    "name:ukr_x_preferred":[
        "\u041a\u0430\u043c\u043f\u0443\u0441"
    ],
    "wof:name":"Campus",
    "wof:placetype":"locality"
},
  "geometry": {"coordinates":[82.36264,28.09436],"type":"Point"}
}