{
  "type": "Feature",
  "properties": {
    "gn:admin1_code":"CR",
    "gn:admin2_code":"5",
    "gn:admin3_code":"19",
    "gn:admin4_code":"190040",
    "gn:asciiname":"Hariaun",
    "gn:country_code":"NP",
    "gn:dem":161,
    "gn:feature_class":"P",
    "gn:feature_code":"PPLL",
    "gn:name":"Hariaun",
    "gn:population":0,
    "gn:timezone":"Asia/Kathmandu",
    "iso:country":"NP",
    "wof:name":"Hariaun",
    "wof:placetype":"locality"
},
  "geometry": {"coordinates":[85.5599,27.10145],"type":"Point"}
}