{
  "type": "Feature",
  "properties": {
    "gn:admin1_code":"WR",
    "gn:admin2_code":"3",
    "gn:admin3_code":"44",
    "gn:admin4_code":"440036",
    "gn:asciiname":"Nepane",
    "gn:country_code":"NP",
    "gn:dem":1089,
    "gn:feature_class":"P",
    "gn:feature_code":"PPLL",
    "gn:name":"Nepane",
    "gn:population":0,
    "gn:timezone":"Asia/Kathmandu",
    "iso:country":"NP",
    "wof:name":"Nepane",
    "wof:placetype":"locality"
},
  "geometry": {"coordinates":[83.57288,28.36769],"type":"Point"}
}