{
  "type": "Feature",
  "properties": {
    "gn:admin1_code":"ER",
    "gn:admin2_code":"13.0",
    "gn:admin3_code":"14.0",
    "gn:admin4_code":"140044.0",
    "gn:asciiname":"Thapatar",
    "gn:country_code":"NP",
    "gn:dem":378,
    "gn:feature_class":"P",
    "gn:feature_code":"PPLL",
    "gn:name":"Thapatar",
    "gn:population":0,
    "gn:timezone":"Asia/Kathmandu",
    "iso:country":"NP",
    "wof:name":"Thapatar",
    "wof:placetype":"locality"
},
  "geometry": {"coordinates":[86.56021,26.86123],"type":"Point"}
}