{
  "type": "Feature",
  "properties": {
    "gn:admin1_code":"CR",
    "gn:admin2_code":"1",
    "gn:admin3_code":"27.0",
    "gn:admin4_code":"270034.0",
    "gn:asciiname":"Tinpane",
    "gn:country_code":"NP",
    "gn:dem":1800,
    "gn:feature_class":"P",
    "gn:feature_code":"PPLL",
    "gn:name":"Tinpane",
    "gn:population":0,
    "gn:timezone":"Asia/Kathmandu",
    "iso:country":"NP",
    "wof:name":"Tinpane",
    "wof:placetype":"locality"
},
  "geometry": {"coordinates":[85.48269000000001,27.75928],"type":"Point"}
}