{
  "type": "Feature",
  "properties": {
    "gn:admin1_code":"FR",
    "gn:admin2_code":"9",
    "gn:admin3_code":"75.0",
    "gn:admin4_code":"750026.0",
    "gn:asciiname":"Lali",
    "gn:country_code":"NP",
    "gn:dem":726,
    "gn:feature_class":"P",
    "gn:feature_code":"PPLL",
    "gn:name":"Lali",
    "gn:population":0,
    "gn:timezone":"Asia/Kathmandu",
    "iso:country":"NP",
    "name:ceb_x_preferred":[
        "Lali"
    ],
    "name:deu_x_preferred":[
        "Lali"
    ],
    "name:fra_x_preferred":[
        "Lali"
    ],
    "name:pnb_x_preferred":[
        "\u0644\u0627\u0644\u06cc"
    ],
    "name:swe_x_preferred":[
        "Lali"
    ],
    "wof:name":"Lali",
    "wof:placetype":"locality"
},
  "geometry": {"coordinates":[80.40261,29.66711],"type":"Point"}
}