{
  "type": "Feature",
  "properties": {
    "gn:admin1_code":"MR",
    "gn:admin2_code":"2.0",
    "gn:admin3_code":"59.0",
    "gn:admin4_code":"590051.0",
    "gn:asciiname":"Daulatpur",
    "gn:country_code":"NP",
    "gn:dem":641,
    "gn:feature_class":"P",
    "gn:feature_code":"PPLL",
    "gn:name":"Daulatpur",
    "gn:population":0,
    "gn:timezone":"Asia/Kathmandu",
    "iso:country":"NP",
    "wof:name":"Daulatpur",
    "wof:placetype":"locality"
},
  "geometry": {"coordinates":[81.58949,28.5714],"type":"Point"}
}