{
  "type": "Feature",
  "properties": {
    "gn:admin1_code":"CR",
    "gn:admin2_code":"5",
    "gn:admin3_code":"18",
    "gn:admin4_code":"180036",
    "gn:asciiname":"Bhalujhoradobhan",
    "gn:country_code":"NP",
    "gn:dem":310,
    "gn:feature_class":"P",
    "gn:feature_code":"PPLL",
    "gn:name":"Bhalujhoradobhan",
    "gn:population":0,
    "gn:timezone":"Asia/Kathmandu",
    "iso:country":"NP",
    "wof:name":"Bhalujhoradobhan",
    "wof:placetype":"locality"
},
  "geometry": {"coordinates":[85.82191,27.06982],"type":"Point"}
}