{
  "type": "Feature",
  "properties": {
    "gn:admin1_code":"ER",
    "gn:admin2_code":"7",
    "gn:admin3_code":"10.0",
    "gn:admin4_code":"100057.0",
    "gn:asciiname":"Kongbang",
    "gn:country_code":"NP",
    "gn:dem":854,
    "gn:feature_class":"P",
    "gn:feature_code":"PPLL",
    "gn:name":"Kongbang",
    "gn:population":0,
    "gn:timezone":"Asia/Kathmandu",
    "iso:country":"NP",
    "wof:name":"Kongbang",
    "wof:placetype":"locality"
},
  "geometry": {"coordinates":[87.14336999999998,27.08267],"type":"Point"}
}