{
  "type": "Feature",
  "properties": {
    "gn:admin1_code":"WR",
    "gn:admin2_code":"4",
    "gn:admin3_code":"36.0",
    "gn:admin4_code":"360041.0",
    "gn:asciiname":"Pokharigaira",
    "gn:country_code":"NP",
    "gn:dem":1202,
    "gn:feature_class":"P",
    "gn:feature_code":"PPLL",
    "gn:name":"Pokharigaira",
    "gn:population":0,
    "gn:timezone":"Asia/Kathmandu",
    "iso:country":"NP",
    "wof:name":"Pokharigaira",
    "wof:placetype":"locality"
},
  "geometry": {"coordinates":[84.5864,27.90804],"type":"Point"}
}