{
  "type": "Feature",
  "properties": {
    "gn:admin1_code":"FR",
    "gn:admin2_code":"9",
    "gn:admin3_code":"74",
    "gn:admin4_code":"740007",
    "gn:asciiname":"Musale",
    "gn:country_code":"NP",
    "gn:dem":660,
    "gn:feature_class":"P",
    "gn:feature_code":"PPLL",
    "gn:name":"Musale",
    "gn:population":0,
    "gn:timezone":"Asia/Kathmandu",
    "iso:country":"NP",
    "wof:name":"Musale",
    "wof:placetype":"locality"
},
  "geometry": {"coordinates":[80.40535,29.35893],"type":"Point"}
}