{
  "type": "Feature",
  "properties": {
    "gn:admin1_code":"CR",
    "gn:admin2_code":"1",
    "gn:admin3_code":"24.0",
    "gn:admin4_code":"240032.0",
    "gn:asciiname":"Anptar",
    "gn:country_code":"NP",
    "gn:dem":458,
    "gn:feature_class":"P",
    "gn:feature_code":"PPLL",
    "gn:name":"Anptar",
    "gn:population":0,
    "gn:timezone":"Asia/Kathmandu",
    "iso:country":"NP",
    "wof:name":"Anptar",
    "wof:placetype":"locality"
},
  "geometry": {"coordinates":[85.54781,27.3543],"type":"Point"}
}