{
  "type": "Feature",
  "properties": {
    "gn:admin1_code":"CR",
    "gn:admin2_code":"1",
    "gn:admin3_code":"23",
    "gn:admin4_code":"230039",
    "gn:asciiname":"Chhap",
    "gn:country_code":"NP",
    "gn:dem":862,
    "gn:feature_class":"P",
    "gn:feature_code":"PPLL",
    "gn:name":"Chhap",
    "gn:population":0,
    "gn:timezone":"Asia/Kathmandu",
    "iso:country":"NP",
    "wof:name":"Chhap",
    "wof:placetype":"locality"
},
  "geometry": {"coordinates":[85.75119000000002,27.78782],"type":"Point"}
}