{
  "type": "Feature",
  "properties": {
    "gn:admin1_code":"ER",
    "gn:admin2_code":"10",
    "gn:admin3_code":"4.0",
    "gn:admin4_code":"40025.0",
    "gn:asciiname":"Sirani Bhurisimal",
    "gn:country_code":"NP",
    "gn:dem":83,
    "gn:feature_class":"P",
    "gn:feature_code":"PPLL",
    "gn:name":"Sirani Bhurisimal",
    "gn:population":0,
    "gn:timezone":"Asia/Kathmandu",
    "iso:country":"NP",
    "wof:name":"Sirani Bhurisimal",
    "wof:placetype":"locality"
},
  "geometry": {"coordinates":[87.7333,26.49343],"type":"Point"}
}