{
  "type": "Feature",
  "properties": {
    "gn:admin1_code":"00",
    "gn:asciiname":"Pakhye",
    "gn:country_code":"NP",
    "gn:dem":1789,
    "gn:feature_class":"P",
    "gn:feature_code":"PPL",
    "gn:name":"P\u0101khye",
    "gn:population":0,
    "gn:timezone":"Asia/Kathmandu",
    "iso:country":"NP",
    "wof:name":"Pakhye",
    "wof:placetype":"locality"
},
  "geometry": {"coordinates":[86.00505,27.51065],"type":"Point"}
}