{
  "type": "Feature",
  "properties": {
    "gn:admin1_code":"CR",
    "gn:admin2_code":"1.0",
    "gn:admin3_code":"26.0",
    "gn:admin4_code":"260012.0",
    "gn:asciiname":"Sano Thimi",
    "gn:country_code":"NP",
    "gn:dem":1326,
    "gn:feature_class":"P",
    "gn:feature_code":"PPLL",
    "gn:name":"Sano Thimi",
    "gn:population":0,
    "gn:timezone":"Asia/Kathmandu",
    "iso:country":"NP",
    "wof:name":"Sano Thimi",
    "wof:placetype":"locality"
},
  "geometry": {"coordinates":[85.37869999999999,27.68008],"type":"Point"}
}