{
  "type": "Feature",
  "properties": {
    "gn:admin1_code":"WR",
    "gn:admin2_code":"3",
    "gn:admin3_code":"43",
    "gn:admin4_code":"430006",
    "gn:asciiname":"Bimirabot",
    "gn:country_code":"NP",
    "gn:dem":1589,
    "gn:feature_class":"P",
    "gn:feature_code":"PPLL",
    "gn:name":"Bimirabot",
    "gn:population":0,
    "gn:timezone":"Asia/Kathmandu",
    "iso:country":"NP",
    "wof:name":"Bimirabot",
    "wof:placetype":"locality"
},
  "geometry": {"coordinates":[83.55234,28.3184],"type":"Point"}
}