{
  "type": "Feature",
  "properties": {
    "gn:admin1_code":"ER",
    "gn:admin2_code":"13.0",
    "gn:admin3_code":"14.0",
    "gn:admin4_code":"140013.0",
    "gn:asciiname":"Madire",
    "gn:country_code":"NP",
    "gn:dem":1718,
    "gn:feature_class":"P",
    "gn:feature_code":"PPLL",
    "gn:name":"Madire",
    "gn:population":0,
    "gn:timezone":"Asia/Kathmandu",
    "iso:country":"NP",
    "wof:name":"Madire",
    "wof:placetype":"locality"
},
  "geometry": {"coordinates":[86.58022,27.06824000000001],"type":"Point"}
}