{
  "type": "Feature",
  "properties": {
    "gn:admin1_code":"MR",
    "gn:admin2_code":"2.0",
    "gn:admin3_code":"57.0",
    "gn:admin4_code":"570019.0",
    "gn:asciiname":"Nanupurwa",
    "gn:country_code":"NP",
    "gn:dem":155,
    "gn:feature_class":"P",
    "gn:feature_code":"PPLL",
    "gn:name":"Nanupurwa",
    "gn:population":0,
    "gn:timezone":"Asia/Kathmandu",
    "iso:country":"NP",
    "wof:name":"Nanupurwa",
    "wof:placetype":"locality"
},
  "geometry": {"coordinates":[81.69202,28.08883],"type":"Point"}
}