{
  "type": "Feature",
  "properties": {
    "gn:admin1_code":"FR",
    "gn:admin2_code":"14",
    "gn:admin3_code":"70.0",
    "gn:admin4_code":"700036.0",
    "gn:asciiname":"Mallo Khetali",
    "gn:country_code":"NP",
    "gn:dem":1352,
    "gn:feature_class":"P",
    "gn:feature_code":"PPLL",
    "gn:name":"Mallo Khetali",
    "gn:population":0,
    "gn:timezone":"Asia/Kathmandu",
    "iso:country":"NP",
    "wof:name":"Mallo Khetali",
    "wof:placetype":"locality"
},
  "geometry": {"coordinates":[80.84416,29.03463],"type":"Point"}
}