{
  "type": "Feature",
  "properties": {
    "gn:admin1_code":"MR",
    "gn:admin2_code":"12",
    "gn:admin3_code":"54",
    "gn:admin4_code":"540024",
    "gn:asciiname":"Korjagaun",
    "gn:country_code":"NP",
    "gn:dem":2074,
    "gn:feature_class":"P",
    "gn:feature_code":"PPLL",
    "gn:name":"Korjagaun",
    "gn:population":0,
    "gn:timezone":"Asia/Kathmandu",
    "iso:country":"NP",
    "wof:name":"Korjagaun",
    "wof:placetype":"locality"
},
  "geometry": {"coordinates":[82.61955999999998,28.54451],"type":"Point"}
}