{
  "type": "Feature",
  "properties": {
    "gn:admin1_code":"CR",
    "gn:admin2_code":"1",
    "gn:admin3_code":"28",
    "gn:admin4_code":"280043",
    "gn:asciiname":"Manethok",
    "gn:country_code":"NP",
    "gn:dem":923,
    "gn:feature_class":"P",
    "gn:feature_code":"PPLL",
    "gn:name":"Manethok",
    "gn:population":0,
    "gn:timezone":"Asia/Kathmandu",
    "iso:country":"NP",
    "wof:name":"Manethok",
    "wof:placetype":"locality"
},
  "geometry": {"coordinates":[85.31121999999998,27.90752],"type":"Point"}
}