{
  "type": "Feature",
  "properties": {
    "gn:admin1_code":"ER",
    "gn:admin2_code":"7",
    "gn:admin3_code":"10.0",
    "gn:admin4_code":"100009.0",
    "gn:asciiname":"Bobek",
    "gn:country_code":"NP",
    "gn:dem":1609,
    "gn:feature_class":"P",
    "gn:feature_code":"PPLL",
    "gn:name":"Bobek",
    "gn:population":0,
    "gn:timezone":"Asia/Kathmandu",
    "iso:country":"NP",
    "name:ces_x_preferred":[
        "Bobek"
    ],
    "name:slv_x_preferred":[
        "Bobek"
    ],
    "wof:name":"Bobek",
    "wof:placetype":"locality"
},
  "geometry": {"coordinates":[87.03319999999999,27.01853],"type":"Point"}
}