{
  "type": "Feature",
  "properties": {
    "gn:admin1_code":"CR",
    "gn:admin2_code":"11",
    "gn:admin3_code":"31",
    "gn:admin4_code":"310037",
    "gn:asciiname":"Gothdanda",
    "gn:country_code":"NP",
    "gn:dem":1114,
    "gn:feature_class":"P",
    "gn:feature_code":"PPLL",
    "gn:name":"Gothdanda",
    "gn:population":0,
    "gn:timezone":"Asia/Kathmandu",
    "iso:country":"NP",
    "wof:name":"Gothdanda",
    "wof:placetype":"locality"
},
  "geometry": {"coordinates":[84.84881999999998,27.59278],"type":"Point"}
}