{
  "type": "Feature",
  "properties": {
    "gn:admin1_code":"WR",
    "gn:admin2_code":"3",
    "gn:admin3_code":"44",
    "gn:admin4_code":"440054",
    "gn:asciiname":"Arnas",
    "gn:country_code":"NP",
    "gn:dem":695,
    "gn:feature_class":"P",
    "gn:feature_code":"PPLL",
    "gn:name":"Arnas",
    "gn:population":0,
    "gn:timezone":"Asia/Kathmandu",
    "iso:country":"NP",
    "name:cat_x_preferred":[
        "Arnas"
    ],
    "name:ceb_x_preferred":[
        "Arnas"
    ],
    "name:deu_x_preferred":[
        "Arnas"
    ],
    "name:eus_x_preferred":[
        "Arnas"
    ],
    "name:fra_x_preferred":[
        "Arnas"
    ],
    "name:hun_x_preferred":[
        "Arnas"
    ],
    "name:ita_x_preferred":[
        "Arnas"
    ],
    "name:lmo_x_preferred":[
        "Arnas"
    ],
    "name:msa_x_preferred":[
        "Arnas"
    ],
    "name:nld_x_preferred":[
        "Arnas"
    ],
    "name:oci_x_preferred":[
        "Arnas"
    ],
    "name:pol_x_preferred":[
        "Arnas"
    ],
    "name:ron_x_preferred":[
        "Arnas"
    ],
    "name:slk_x_preferred":[
        "Arnas"
    ],
    "name:spa_x_preferred":[
        "Arnas"
    ],
    "name:sqi_x_preferred":[
        "Arnas"
    ],
    "name:srp_x_preferred":[
        "\u0410\u0440\u043d\u0430"
    ],
    "name:swe_x_preferred":[
        "Arnas"
    ],
    "name:ukr_x_preferred":[
        "\u0410\u0440\u043d\u0430"
    ],
    "name:uzb_x_preferred":[
        "Arnas"
    ],
    "name:vie_x_preferred":[
        "Arnas"
    ],
    "name:vol_x_preferred":[
        "Arnas"
    ],
    "name:war_x_preferred":[
        "Arnas"
    ],
    "name:zho_x_preferred":[
        "\u963f\u723e\u7d0d"
    ],
    "wof:name":"Arnas",
    "wof:placetype":"locality"
},
  "geometry": {"coordinates":[83.64515,28.03242],"type":"Point"}
}