{
  "type": "Feature",
  "properties": {
    "gn:admin1_code":"WR",
    "gn:admin2_code":"8",
    "gn:admin3_code":"47",
    "gn:admin4_code":"470053",
    "gn:asciiname":"Gaitar",
    "gn:country_code":"NP",
    "gn:dem":398,
    "gn:feature_class":"P",
    "gn:feature_code":"PPLL",
    "gn:name":"Gaitar",
    "gn:population":0,
    "gn:timezone":"Asia/Kathmandu",
    "iso:country":"NP",
    "wof:name":"Gaitar",
    "wof:placetype":"locality"
},
  "geometry": {"coordinates":[83.87965,27.86947],"type":"Point"}
}