{
  "type": "Feature",
  "properties": {
    "gn:admin1_code":"FR",
    "gn:admin2_code":"14",
    "gn:admin3_code":"70.0",
    "gn:admin4_code":"700011.0",
    "gn:asciiname":"Bansghari",
    "gn:country_code":"NP",
    "gn:dem":611,
    "gn:feature_class":"P",
    "gn:feature_code":"PPLL",
    "gn:name":"Bansghari",
    "gn:population":0,
    "gn:timezone":"Asia/Kathmandu",
    "iso:country":"NP",
    "wof:name":"Bansghari",
    "wof:placetype":"locality"
},
  "geometry": {"coordinates":[80.92232,28.94985],"type":"Point"}
}