{
  "type": "Feature",
  "properties": {
    "gn:admin1_code":"ER",
    "gn:admin2_code":"7",
    "gn:admin3_code":"10.0",
    "gn:admin4_code":"100017.0",
    "gn:asciiname":"Merung",
    "gn:country_code":"NP",
    "gn:dem":2717,
    "gn:feature_class":"P",
    "gn:feature_code":"PPLL",
    "gn:name":"Merung",
    "gn:population":0,
    "gn:timezone":"Asia/Kathmandu",
    "iso:country":"NP",
    "wof:name":"Merung",
    "wof:placetype":"locality"
},
  "geometry": {"coordinates":[86.90616,27.25304],"type":"Point"}
}