{
  "type": "Feature",
  "properties": {
    "gn:admin1_code":"WR",
    "gn:admin2_code":"8",
    "gn:admin3_code":"48",
    "gn:admin4_code":"480011",
    "gn:asciiname":"Dhawadi",
    "gn:country_code":"NP",
    "gn:dem":619,
    "gn:feature_class":"P",
    "gn:feature_code":"PPLL",
    "gn:name":"Dhawadi",
    "gn:population":0,
    "gn:timezone":"Asia/Kathmandu",
    "iso:country":"NP",
    "wof:name":"Dhawadi",
    "wof:placetype":"locality"
},
  "geometry": {"coordinates":[84.24811,27.81298],"type":"Point"}
}