{
  "type": "Feature",
  "properties": {
    "gn:admin1_code":"WR",
    "gn:admin2_code":"4",
    "gn:admin3_code":"37",
    "gn:admin4_code":"370021",
    "gn:asciiname":"Ambotebesi",
    "gn:country_code":"NP",
    "gn:dem":939,
    "gn:feature_class":"P",
    "gn:feature_code":"PPLL",
    "gn:name":"Ambotebesi",
    "gn:population":0,
    "gn:timezone":"Asia/Kathmandu",
    "iso:country":"NP",
    "wof:name":"Ambotebesi",
    "wof:placetype":"locality"
},
  "geometry": {"coordinates":[84.45402,28.22289],"type":"Point"}
}