{
  "type": "Feature",
  "properties": {
    "gn:admin1_code":"ER",
    "gn:admin2_code":"7",
    "gn:admin3_code":"5",
    "gn:admin4_code":"50007",
    "gn:asciiname":"Lohandrabasti",
    "gn:country_code":"NP",
    "gn:dem":99,
    "gn:feature_class":"P",
    "gn:feature_code":"PPLL",
    "gn:name":"Lohandrabasti",
    "gn:population":0,
    "gn:timezone":"Asia/Kathmandu",
    "iso:country":"NP",
    "wof:name":"Lohandrabasti",
    "wof:placetype":"locality"
},
  "geometry": {"coordinates":[87.38903000000001,26.58952],"type":"Point"}
}