{
  "type": "Feature",
  "properties": {
    "gn:admin1_code":"FR",
    "gn:admin2_code":"14",
    "gn:admin3_code":"69.0",
    "gn:admin4_code":"690012.0",
    "gn:asciiname":"Bhusagada",
    "gn:country_code":"NP",
    "gn:dem":1071,
    "gn:feature_class":"P",
    "gn:feature_code":"PPLL",
    "gn:name":"Bhusagada",
    "gn:population":0,
    "gn:timezone":"Asia/Kathmandu",
    "iso:country":"NP",
    "wof:name":"Bhusagada",
    "wof:placetype":"locality"
},
  "geometry": {"coordinates":[81.40725,29.09079],"type":"Point"}
}