{
  "type": "Feature",
  "properties": {
    "gn:admin1_code":"CR",
    "gn:admin2_code":"5",
    "gn:admin3_code":"17.0",
    "gn:admin4_code":"170038.0",
    "gn:asciiname":"Ghodghas",
    "gn:country_code":"NP",
    "gn:dem":74,
    "gn:feature_class":"P",
    "gn:feature_code":"PPLL",
    "gn:name":"Ghodghas",
    "gn:population":0,
    "gn:timezone":"Asia/Kathmandu",
    "iso:country":"NP",
    "wof:name":"Ghodghas",
    "wof:placetype":"locality"
},
  "geometry": {"coordinates":[85.91708,26.67319],"type":"Point"}
}