{
  "type": "Feature",
  "properties": {
    "gn:admin1_code":"WR",
    "gn:admin2_code":"8",
    "gn:admin3_code":"51.0",
    "gn:admin4_code":"510042.0",
    "gn:asciiname":"Rotepani",
    "gn:country_code":"NP",
    "gn:dem":1448,
    "gn:feature_class":"P",
    "gn:feature_code":"PPLL",
    "gn:name":"Rotepani",
    "gn:population":0,
    "gn:timezone":"Asia/Kathmandu",
    "iso:country":"NP",
    "wof:name":"Rotepani",
    "wof:placetype":"locality"
},
  "geometry": {"coordinates":[83.20470999999998,28.02243],"type":"Point"}
}