{
  "type": "Feature",
  "properties": {
    "gn:admin1_code":"CR",
    "gn:admin2_code":"11",
    "gn:admin3_code":"35.0",
    "gn:admin4_code":"350019.0",
    "gn:asciiname":"Samanpur",
    "gn:country_code":"NP",
    "gn:dem":207,
    "gn:feature_class":"P",
    "gn:feature_code":"PPLL",
    "gn:name":"Samanpur",
    "gn:population":0,
    "gn:timezone":"Asia/Kathmandu",
    "iso:country":"NP",
    "name:ceb_x_preferred":[
        "Samanpur"
    ],
    "name:mai_x_preferred":[
        "\u0938\u092e\u0928\u092a\u0942\u0930"
    ],
    "name:msa_x_preferred":[
        "Samanpur"
    ],
    "name:nep_x_preferred":[
        "\u0938\u092e\u0928\u092a\u0942\u0930"
    ],
    "name:new_x_preferred":[
        "\u0938\u093e\u092e\u093e\u0928\u092a\u0941\u0930"
    ],
    "name:pol_x_preferred":[
        "Samanpur"
    ],
    "wof:name":"Samanpur",
    "wof:placetype":"locality"
},
  "geometry": {"coordinates":[84.58993000000002,27.58396],"type":"Point"}
}