{
  "type": "Feature",
  "properties": {
    "gn:admin1_code":"CR",
    "gn:admin2_code":"11",
    "gn:admin3_code":"35.0",
    "gn:admin4_code":"350019.0",
    "gn:asciiname":"Samanpur",
    "gn:country_code":"NP",
    "gn:dem":207,
    "gn:feature_class":"P",
    "gn:feature_code":"PPLL",
    "gn:name":"Samanpur",
    "gn:population":0,
    "gn:timezone":"Asia/Kathmandu",
    "iso:country":"NP",
    "wof:name":"Samanpur",
    "wof:placetype":"locality"
},
  "geometry": {"coordinates":[84.58993000000002,27.58396],"type":"Point"}
}