{
  "type": "Feature",
  "properties": {
    "gn:admin1_code":"WR",
    "gn:admin2_code":"8",
    "gn:admin3_code":"48",
    "gn:admin4_code":"480020",
    "gn:asciiname":"Dumkibas",
    "gn:country_code":"NP",
    "gn:dem":164,
    "gn:feature_class":"P",
    "gn:feature_code":"PPLL",
    "gn:name":"Dumkibas",
    "gn:population":0,
    "gn:timezone":"Asia/Kathmandu",
    "iso:country":"NP",
    "wof:name":"Dumkibas",
    "wof:placetype":"locality"
},
  "geometry": {"coordinates":[83.87137,27.58767000000001],"type":"Point"}
}