{
  "type": "Feature",
  "properties": {
    "gn:admin1_code":"CR",
    "gn:admin2_code":"5",
    "gn:admin3_code":"20",
    "gn:admin4_code":"200042",
    "gn:asciiname":"Baje",
    "gn:country_code":"NP",
    "gn:dem":722,
    "gn:feature_class":"P",
    "gn:feature_code":"PPLL",
    "gn:name":"Baje",
    "gn:population":0,
    "gn:timezone":"Asia/Kathmandu",
    "iso:country":"NP",
    "wof:name":"Baje",
    "wof:placetype":"locality"
},
  "geometry": {"coordinates":[86.03270999999999,27.19427],"type":"Point"}
}