{
  "type": "Feature",
  "properties": {
    "gn:admin1_code":"WR",
    "gn:admin2_code":"8",
    "gn:admin3_code":"46.0",
    "gn:admin4_code":"460051.0",
    "gn:asciiname":"Netagaun",
    "gn:country_code":"NP",
    "gn:dem":1726,
    "gn:feature_class":"P",
    "gn:feature_code":"PPLL",
    "gn:name":"Netagaun",
    "gn:population":0,
    "gn:timezone":"Asia/Kathmandu",
    "iso:country":"NP",
    "wof:name":"Netagaun",
    "wof:placetype":"locality"
},
  "geometry": {"coordinates":[83.43748000000002,28.0596],"type":"Point"}
}