{
  "type": "Feature",
  "properties": {
    "gn:admin1_code":"MR",
    "gn:admin2_code":"12",
    "gn:admin3_code":"55",
    "gn:admin4_code":"550027",
    "gn:asciiname":"Bharale",
    "gn:country_code":"NP",
    "gn:dem":1406,
    "gn:feature_class":"P",
    "gn:feature_code":"PPLL",
    "gn:name":"Bharale",
    "gn:population":0,
    "gn:timezone":"Asia/Kathmandu",
    "iso:country":"NP",
    "wof:name":"Bharale",
    "wof:placetype":"locality"
},
  "geometry": {"coordinates":[82.28927,28.44647],"type":"Point"}
}