{
  "type": "Feature",
  "properties": {
    "gn:admin1_code":"FR",
    "gn:admin2_code":"9",
    "gn:admin3_code":"75.0",
    "gn:admin4_code":"750029.0",
    "gn:asciiname":"Patram",
    "gn:country_code":"NP",
    "gn:dem":2448,
    "gn:feature_class":"P",
    "gn:feature_code":"PPLL",
    "gn:name":"Patram",
    "gn:population":0,
    "gn:timezone":"Asia/Kathmandu",
    "iso:country":"NP",
    "wof:name":"Patram",
    "wof:placetype":"locality"
},
  "geometry": {"coordinates":[80.63020999999998,29.9174],"type":"Point"}
}