{
  "type": "Feature",
  "properties": {
    "gn:admin1_code":"CR",
    "gn:admin2_code":"11",
    "gn:admin3_code":"31",
    "gn:admin4_code":"310016",
    "gn:asciiname":"Phaparbari Thulogaun",
    "gn:country_code":"NP",
    "gn:dem":355,
    "gn:feature_class":"P",
    "gn:feature_code":"PPLL",
    "gn:name":"Phaparbari Thulogaun",
    "gn:population":0,
    "gn:timezone":"Asia/Kathmandu",
    "iso:country":"NP",
    "wof:name":"Phaparbari Thulogaun",
    "wof:placetype":"locality"
},
  "geometry": {"coordinates":[85.35799,27.35539],"type":"Point"}
}