{
  "type": "Feature",
  "properties": {
    "gn:admin1_code":"WR",
    "gn:admin2_code":"4",
    "gn:admin3_code":"36.0",
    "gn:admin4_code":"360021.0",
    "gn:asciiname":"Melbisauna",
    "gn:country_code":"NP",
    "gn:dem":1114,
    "gn:feature_class":"P",
    "gn:feature_code":"PPLL",
    "gn:name":"Melbisauna",
    "gn:population":0,
    "gn:timezone":"Asia/Kathmandu",
    "iso:country":"NP",
    "wof:name":"Melbisauna",
    "wof:placetype":"locality"
},
  "geometry": {"coordinates":[84.65658000000001,28.0227],"type":"Point"}
}