{
  "type": "Feature",
  "properties": {
    "gn:admin1_code":"WR",
    "gn:admin2_code":"8",
    "gn:admin3_code":"49",
    "gn:admin4_code":"490059",
    "gn:asciiname":"Talhi",
    "gn:country_code":"NP",
    "gn:dem":132,
    "gn:feature_class":"P",
    "gn:feature_code":"PPLL",
    "gn:name":"Talhi",
    "gn:population":0,
    "gn:timezone":"Asia/Kathmandu",
    "iso:country":"NP",
    "wof:name":"Talhi",
    "wof:placetype":"locality"
},
  "geometry": {"coordinates":[83.27184,27.6863],"type":"Point"}
}