{
  "type": "Feature",
  "properties": {
    "gn:admin1_code":"00",
    "gn:asciiname":"Babran",
    "gn:country_code":"NP",
    "gn:dem":1796,
    "gn:feature_class":"P",
    "gn:feature_code":"PPL",
    "gn:name":"Babr\u0101\u1e45",
    "gn:population":0,
    "gn:timezone":"Asia/Kathmandu",
    "iso:country":"NP",
    "wof:name":"Babran",
    "wof:placetype":"locality"
},
  "geometry": {"coordinates":[85.45668000000001,27.82909],"type":"Point"}
}