{
  "type": "Feature",
  "properties": {
    "gn:admin1_code":"WR",
    "gn:admin2_code":"4.0",
    "gn:admin3_code":"39.0",
    "gn:admin4_code":"390011.0",
    "gn:asciiname":"Kindi",
    "gn:country_code":"NP",
    "gn:dem":773,
    "gn:feature_class":"P",
    "gn:feature_code":"PPLL",
    "gn:name":"Kindi",
    "gn:population":0,
    "gn:timezone":"Asia/Kathmandu",
    "iso:country":"NP",
    "wof:name":"Kindi",
    "wof:placetype":"locality"
},
  "geometry": {"coordinates":[83.53641999999998,27.95389],"type":"Point"}
}