{
  "type": "Feature",
  "properties": {
    "gn:admin1_code":"FR",
    "gn:admin2_code":"14",
    "gn:admin3_code":"70.0",
    "gn:admin4_code":"700006.0",
    "gn:asciiname":"Latala",
    "gn:country_code":"NP",
    "gn:dem":835,
    "gn:feature_class":"P",
    "gn:feature_code":"PPLL",
    "gn:name":"Latala",
    "gn:population":0,
    "gn:timezone":"Asia/Kathmandu",
    "iso:country":"NP",
    "name:fas_x_preferred":[
        "\u0644\u0627\u0637\u0644\u0627"
    ],
    "name:urd_x_preferred":[
        "\u0644\u0627\u062a\u0627\u0644\u0627"
    ],
    "wof:name":"Latala",
    "wof:placetype":"locality"
},
  "geometry": {"coordinates":[81.02956999999998,29.09859],"type":"Point"}
}