{
  "type": "Feature",
  "properties": {
    "gn:admin1_code":"MR",
    "gn:admin2_code":"12",
    "gn:admin3_code":"56.0",
    "gn:admin4_code":"560013.0",
    "gn:asciiname":"Pahadi Banari",
    "gn:country_code":"NP",
    "gn:dem":814,
    "gn:feature_class":"P",
    "gn:feature_code":"PPLL",
    "gn:name":"Pahadi Banari",
    "gn:population":0,
    "gn:timezone":"Asia/Kathmandu",
    "iso:country":"NP",
    "wof:name":"Pahadi Banari",
    "wof:placetype":"locality"
},
  "geometry": {"coordinates":[82.34266,28.17086],"type":"Point"}
}