{
  "type": "Feature",
  "properties": {
    "gn:admin1_code":"WR",
    "gn:admin2_code":"8",
    "gn:admin3_code":"51.0",
    "gn:admin4_code":"510035.0",
    "gn:asciiname":"Lunkun",
    "gn:country_code":"NP",
    "gn:dem":1341,
    "gn:feature_class":"P",
    "gn:feature_code":"PPLL",
    "gn:name":"Lunkun",
    "gn:population":0,
    "gn:timezone":"Asia/Kathmandu",
    "iso:country":"NP",
    "wof:name":"Lunkun",
    "wof:placetype":"locality"
},
  "geometry": {"coordinates":[83.29223,27.84149],"type":"Point"}
}