{
  "type": "Feature",
  "properties": {
    "gn:admin1_code":"WR",
    "gn:admin2_code":"4",
    "gn:admin3_code":"37",
    "gn:admin4_code":"370061",
    "gn:asciiname":"Kamdung",
    "gn:country_code":"NP",
    "gn:dem":1089,
    "gn:feature_class":"P",
    "gn:feature_code":"PPLL",
    "gn:name":"Kamdung",
    "gn:population":0,
    "gn:timezone":"Asia/Kathmandu",
    "iso:country":"NP",
    "wof:name":"Kamdung",
    "wof:placetype":"locality"
},
  "geometry": {"coordinates":[84.28376999999998,28.25811],"type":"Point"}
}