{
  "type": "Feature",
  "properties": {
    "gn:admin1_code":"00",
    "gn:asciiname":"Karanlun",
    "gn:country_code":"NP",
    "gn:dem":1594,
    "gn:feature_class":"P",
    "gn:feature_code":"PPL",
    "gn:name":"K\u0101r\u0101\u1e45lu\u1e45",
    "gn:population":0,
    "gn:timezone":"Asia/Kathmandu",
    "iso:country":"NP",
    "wof:name":"Karanlun",
    "wof:placetype":"locality"
},
  "geometry": {"coordinates":[85.41582,27.83702000000001],"type":"Point"}
}