{
  "type": "Feature",
  "properties": {
    "gn:admin1_code":"MR",
    "gn:admin2_code":"12",
    "gn:admin3_code":"55",
    "gn:admin4_code":"550046",
    "gn:asciiname":"Putaleebas",
    "gn:country_code":"NP",
    "gn:dem":1569,
    "gn:feature_class":"P",
    "gn:feature_code":"PPLL",
    "gn:name":"Putaleebas",
    "gn:population":0,
    "gn:timezone":"Asia/Kathmandu",
    "iso:country":"NP",
    "wof:name":"Putaleebas",
    "wof:placetype":"locality"
},
  "geometry": {"coordinates":[82.25954,28.49145],"type":"Point"}
}