{
  "type": "Feature",
  "properties": {
    "gn:admin1_code":"FR",
    "gn:admin2_code":"9",
    "gn:admin3_code":"73.0",
    "gn:admin4_code":"730009.0",
    "gn:asciiname":"Gwanni",
    "gn:country_code":"NP",
    "gn:dem":1491,
    "gn:feature_class":"P",
    "gn:feature_code":"PPLL",
    "gn:name":"Gwanni",
    "gn:population":0,
    "gn:timezone":"Asia/Kathmandu",
    "iso:country":"NP",
    "wof:name":"Gwanni",
    "wof:placetype":"locality"
},
  "geometry": {"coordinates":[80.50168000000002,29.37373],"type":"Point"}
}