{
  "type": "Feature",
  "properties": {
    "gn:admin1_code":"WR",
    "gn:admin2_code":"4.0",
    "gn:admin3_code":"39.0",
    "gn:admin4_code":"390038.0",
    "gn:asciiname":"Sanliya",
    "gn:country_code":"NP",
    "gn:dem":692,
    "gn:feature_class":"P",
    "gn:feature_code":"PPLL",
    "gn:name":"Sanliya",
    "gn:population":0,
    "gn:timezone":"Asia/Kathmandu",
    "iso:country":"NP",
    "wof:name":"Sanliya",
    "wof:placetype":"locality"
},
  "geometry": {"coordinates":[83.76294,27.92552],"type":"Point"}
}