{
  "type": "Feature",
  "properties": {
    "gn:admin1_code":"CR",
    "gn:admin2_code":"5",
    "gn:admin3_code":"17.0",
    "gn:admin4_code":"170080.0",
    "gn:asciiname":"Marladhar",
    "gn:country_code":"NP",
    "gn:dem":162,
    "gn:feature_class":"P",
    "gn:feature_code":"PPLL",
    "gn:name":"Marladhar",
    "gn:population":0,
    "gn:timezone":"Asia/Kathmandu",
    "iso:country":"NP",
    "wof:name":"Marladhar",
    "wof:placetype":"locality"
},
  "geometry": {"coordinates":[85.98945000000001,26.91095],"type":"Point"}
}