{
  "type": "Feature",
  "properties": {
    "gn:admin1_code":"MR",
    "gn:admin2_code":"12",
    "gn:admin3_code":"55",
    "gn:admin4_code":"550023",
    "gn:asciiname":"Khajjar",
    "gn:country_code":"NP",
    "gn:dem":1569,
    "gn:feature_class":"P",
    "gn:feature_code":"PPLL",
    "gn:name":"Khajjar",
    "gn:population":0,
    "gn:timezone":"Asia/Kathmandu",
    "iso:country":"NP",
    "wof:name":"Khajjar",
    "wof:placetype":"locality"
},
  "geometry": {"coordinates":[82.13542,28.25369],"type":"Point"}
}