{
  "type": "Feature",
  "properties": {
    "gn:admin1_code":"MR",
    "gn:admin2_code":"6.0",
    "gn:asciiname":"Lhan",
    "gn:country_code":"NP",
    "gn:dem":2228,
    "gn:feature_class":"P",
    "gn:feature_code":"PPL",
    "gn:name":"Lhan",
    "gn:population":0,
    "gn:timezone":"Asia/Kathmandu",
    "iso:country":"NP",
    "wof:name":"Lhan",
    "wof:placetype":"locality"
},
  "geometry": {"coordinates":[82.67536,29.00395],"type":"Point"}
}