{
  "type": "Feature",
  "properties": {
    "gn:admin1_code":"FR",
    "gn:admin2_code":"14",
    "gn:admin3_code":"70.0",
    "gn:admin4_code":"700008.0",
    "gn:asciiname":"Melkholagaun",
    "gn:country_code":"NP",
    "gn:dem":1439,
    "gn:feature_class":"P",
    "gn:feature_code":"PPLL",
    "gn:name":"Melkholagaun",
    "gn:population":0,
    "gn:timezone":"Asia/Kathmandu",
    "iso:country":"NP",
    "wof:name":"Melkholagaun",
    "wof:placetype":"locality"
},
  "geometry": {"coordinates":[80.57911999999997,29.06288],"type":"Point"}
}