{
  "type": "Feature",
  "properties": {
    "gn:admin1_code":"WR",
    "gn:admin2_code":"8",
    "gn:admin3_code":"47",
    "gn:admin4_code":"470048",
    "gn:asciiname":"Chiditol",
    "gn:country_code":"NP",
    "gn:dem":1173,
    "gn:feature_class":"P",
    "gn:feature_code":"PPLL",
    "gn:name":"Chiditol",
    "gn:population":0,
    "gn:timezone":"Asia/Kathmandu",
    "iso:country":"NP",
    "wof:name":"Chiditol",
    "wof:placetype":"locality"
},
  "geometry": {"coordinates":[83.6165,27.85843],"type":"Point"}
}