{
  "type": "Feature",
  "properties": {
    "gn:admin1_code":"MR",
    "gn:admin2_code":"2",
    "gn:admin3_code":"61.0",
    "gn:admin4_code":"610016.0",
    "gn:asciiname":"Laha",
    "gn:country_code":"NP",
    "gn:dem":1570,
    "gn:feature_class":"P",
    "gn:feature_code":"PPLL",
    "gn:name":"Laha",
    "gn:population":0,
    "gn:timezone":"Asia/Kathmandu",
    "iso:country":"NP",
    "name:deu_x_preferred":[
        "Laha"
    ],
    "wof:name":"Laha",
    "wof:placetype":"locality"
},
  "geometry": {"coordinates":[82.262,28.80918],"type":"Point"}
}