{
  "type": "Feature",
  "properties": {
    "gn:admin1_code":"CR",
    "gn:admin2_code":"1",
    "gn:admin3_code":"27.0",
    "gn:admin4_code":"270055.0",
    "gn:asciiname":"Phakhel Bhaniyang",
    "gn:country_code":"NP",
    "gn:dem":1732,
    "gn:feature_class":"P",
    "gn:feature_code":"PPLL",
    "gn:name":"Phakhel Bhaniyang",
    "gn:population":0,
    "gn:timezone":"Asia/Kathmandu",
    "iso:country":"NP",
    "wof:name":"Phakhel Bhaniyang",
    "wof:placetype":"locality"
},
  "geometry": {"coordinates":[85.24683,27.60094],"type":"Point"}
}