{
  "type": "Feature",
  "properties": {
    "gn:admin1_code":"CR",
    "gn:admin2_code":"5",
    "gn:admin3_code":"17.0",
    "gn:admin4_code":"170024.0",
    "gn:asciiname":"Darkhoriya",
    "gn:country_code":"NP",
    "gn:dem":87,
    "gn:feature_class":"P",
    "gn:feature_code":"PPLL",
    "gn:name":"Darkhoriya",
    "gn:population":0,
    "gn:timezone":"Asia/Kathmandu",
    "iso:country":"NP",
    "wof:name":"Darkhoriya",
    "wof:placetype":"locality"
},
  "geometry": {"coordinates":[86.12166999999999,26.74687],"type":"Point"}
}