{
  "type": "Feature",
  "properties": {
    "gn:admin1_code":"CR",
    "gn:admin2_code":"1",
    "gn:admin3_code":"23",
    "gn:admin4_code":"230038",
    "gn:asciiname":"Tar",
    "gn:country_code":"NP",
    "gn:dem":1256,
    "gn:feature_class":"P",
    "gn:feature_code":"PPLL",
    "gn:name":"Tar",
    "gn:population":0,
    "gn:timezone":"Asia/Kathmandu",
    "iso:country":"NP",
    "wof:name":"Tar",
    "wof:placetype":"locality"
},
  "geometry": {"coordinates":[85.55365999999999,27.90986],"type":"Point"}
}