{
  "type": "Feature",
  "properties": {
    "gn:admin1_code":"WR",
    "gn:admin2_code":"8",
    "gn:admin3_code":"48",
    "gn:admin4_code":"480065",
    "gn:asciiname":"Bhattola",
    "gn:country_code":"NP",
    "gn:dem":229,
    "gn:feature_class":"P",
    "gn:feature_code":"PPLL",
    "gn:name":"Bhattola",
    "gn:population":0,
    "gn:timezone":"Asia/Kathmandu",
    "iso:country":"NP",
    "wof:name":"Bhattola",
    "wof:placetype":"locality"
},
  "geometry": {"coordinates":[84.13817,27.66597],"type":"Point"}
}