{
  "type": "Feature",
  "properties": {
    "gn:admin1_code":"WR",
    "gn:admin2_code":"4.0",
    "gn:admin3_code":"39.0",
    "gn:admin4_code":"390014.0",
    "gn:asciiname":"Badaharbari",
    "gn:country_code":"NP",
    "gn:dem":879,
    "gn:feature_class":"P",
    "gn:feature_code":"PPLL",
    "gn:name":"Badaharbari",
    "gn:population":0,
    "gn:timezone":"Asia/Kathmandu",
    "iso:country":"NP",
    "wof:name":"Badaharbari",
    "wof:placetype":"locality"
},
  "geometry": {"coordinates":[83.79863,27.99572],"type":"Point"}
}