{
  "type": "Feature",
  "properties": {
    "gn:admin1_code":"FR",
    "gn:admin2_code":"14",
    "gn:admin3_code":"70.0",
    "gn:admin4_code":"700012.0",
    "gn:asciiname":"Maedi",
    "gn:country_code":"NP",
    "gn:dem":1612,
    "gn:feature_class":"P",
    "gn:feature_code":"PPLL",
    "gn:name":"Maedi",
    "gn:population":0,
    "gn:timezone":"Asia/Kathmandu",
    "iso:country":"NP",
    "name:bul_x_preferred":[
        "\u041c\u0435\u0434\u0438"
    ],
    "name:cat_x_preferred":[
        "Maedi"
    ],
    "name:ell_x_preferred":[
        "\u039c\u03b1\u03af\u03b4\u03bf\u03b9"
    ],
    "name:ita_x_preferred":[
        "Maedi"
    ],
    "name:lmo_x_preferred":[
        "Maedi"
    ],
    "name:por_x_preferred":[
        "Medos"
    ],
    "name:ron_x_preferred":[
        "Medobitini"
    ],
    "wof:name":"Maedi",
    "wof:placetype":"locality"
},
  "geometry": {"coordinates":[80.96396999999997,29.10577],"type":"Point"}
}