{
  "type": "Feature",
  "properties": {
    "gn:admin1_code":"CR",
    "gn:admin2_code":"5",
    "gn:admin3_code":"20",
    "gn:admin4_code":"200002",
    "gn:asciiname":"Thapatar",
    "gn:country_code":"NP",
    "gn:dem":656,
    "gn:feature_class":"P",
    "gn:feature_code":"PPLL",
    "gn:name":"Thapatar",
    "gn:population":0,
    "gn:timezone":"Asia/Kathmandu",
    "iso:country":"NP",
    "wof:name":"Thapatar",
    "wof:placetype":"locality"
},
  "geometry": {"coordinates":[86.25438,27.05349],"type":"Point"}
}