{
  "type": "Feature",
  "properties": {
    "gn:admin1_code":"WR",
    "gn:admin2_code":"4.0",
    "gn:admin3_code":"39.0",
    "gn:admin4_code":"390013.0",
    "gn:asciiname":"Pakari",
    "gn:country_code":"NP",
    "gn:dem":453,
    "gn:feature_class":"P",
    "gn:feature_code":"PPLL",
    "gn:name":"Pakari",
    "gn:population":0,
    "gn:timezone":"Asia/Kathmandu",
    "iso:country":"NP",
    "name:bih_x_preferred":[
        "\u092a\u0915\u0930\u0940"
    ],
    "name:ceb_x_preferred":[
        "Pakari"
    ],
    "name:fra_x_preferred":[
        "Pakari"
    ],
    "name:hin_x_preferred":[
        "\u092a\u0915\u0930\u0940"
    ],
    "name:mai_x_preferred":[
        "\u092a\u0915\u0930\u0940"
    ],
    "name:msa_x_preferred":[
        "Pakari"
    ],
    "name:nep_x_preferred":[
        "\u092a\u0915\u0930\u0940"
    ],
    "name:new_x_preferred":[
        "\u092a\u0915\u0930\u0940"
    ],
    "name:pol_x_preferred":[
        "Pakari"
    ],
    "wof:name":"Pakari",
    "wof:placetype":"locality"
},
  "geometry": {"coordinates":[83.82210000000001,27.89357],"type":"Point"}
}