{
  "type": "Feature",
  "properties": {
    "gn:admin1_code":"FR",
    "gn:admin2_code":"9",
    "gn:admin3_code":"73.0",
    "gn:admin4_code":"730010.0",
    "gn:asciiname":"Gharijar",
    "gn:country_code":"NP",
    "gn:dem":1140,
    "gn:feature_class":"P",
    "gn:feature_code":"PPLL",
    "gn:name":"Gharijar",
    "gn:population":0,
    "gn:timezone":"Asia/Kathmandu",
    "iso:country":"NP",
    "wof:name":"Gharijar",
    "wof:placetype":"locality"
},
  "geometry": {"coordinates":[80.47789,29.33508],"type":"Point"}
}