{
  "type": "Feature",
  "properties": {
    "gn:admin1_code":"MR",
    "gn:admin2_code":"6",
    "gn:admin3_code":"62.0",
    "gn:admin4_code":"620002.0",
    "gn:asciiname":"Dukot",
    "gn:country_code":"NP",
    "gn:dem":3874,
    "gn:feature_class":"P",
    "gn:feature_code":"PPLL",
    "gn:name":"Dukot",
    "gn:population":0,
    "gn:timezone":"Asia/Kathmandu",
    "iso:country":"NP",
    "wof:name":"Dukot",
    "wof:placetype":"locality"
},
  "geometry": {"coordinates":[83.35382,28.95374],"type":"Point"}
}