{
  "type": "Feature",
  "properties": {
    "gn:admin1_code":"CR",
    "gn:admin2_code":"5",
    "gn:admin3_code":"20",
    "gn:admin4_code":"200031",
    "gn:asciiname":"Katle",
    "gn:country_code":"NP",
    "gn:dem":230,
    "gn:feature_class":"P",
    "gn:feature_code":"PPLL",
    "gn:name":"Katle",
    "gn:population":0,
    "gn:timezone":"Asia/Kathmandu",
    "iso:country":"NP",
    "wof:name":"Katle",
    "wof:placetype":"locality"
},
  "geometry": {"coordinates":[86.32433,26.99798],"type":"Point"}
}