{
  "type": "Feature",
  "properties": {
    "gn:admin1_code":"CR",
    "gn:admin2_code":"5",
    "gn:admin3_code":"22.0",
    "gn:admin4_code":"220039.0",
    "gn:asciiname":"Majhkharka",
    "gn:country_code":"NP",
    "gn:dem":2274,
    "gn:feature_class":"P",
    "gn:feature_code":"PPLL",
    "gn:name":"Majhkharka",
    "gn:population":0,
    "gn:timezone":"Asia/Kathmandu",
    "iso:country":"NP",
    "wof:name":"Majhkharka",
    "wof:placetype":"locality"
},
  "geometry": {"coordinates":[86.30998000000002,27.80646],"type":"Point"}
}