{
  "type": "Feature",
  "properties": {
    "gn:admin1_code":"CR",
    "gn:admin2_code":"5",
    "gn:admin3_code":"19",
    "gn:admin4_code":"190043",
    "gn:asciiname":"Manharwa",
    "gn:country_code":"NP",
    "gn:dem":120,
    "gn:feature_class":"P",
    "gn:feature_code":"PPLL",
    "gn:name":"Manharwa",
    "gn:population":0,
    "gn:timezone":"Asia/Kathmandu",
    "iso:country":"NP",
    "wof:name":"Manharwa",
    "wof:placetype":"locality"
},
  "geometry": {"coordinates":[85.61350999999998,26.9985],"type":"Point"}
}