{
  "type": "Feature",
  "properties": {
    "gn:admin1_code":"CR",
    "gn:admin2_code":"5",
    "gn:admin3_code":"20",
    "gn:admin4_code":"200004",
    "gn:asciiname":"Bhokteni",
    "gn:country_code":"NP",
    "gn:dem":1076,
    "gn:feature_class":"P",
    "gn:feature_code":"PPLL",
    "gn:name":"Bhokteni",
    "gn:population":0,
    "gn:timezone":"Asia/Kathmandu",
    "iso:country":"NP",
    "wof:name":"Bhokteni",
    "wof:placetype":"locality"
},
  "geometry": {"coordinates":[86.10616999999998,27.17811],"type":"Point"}
}