{
  "type": "Feature",
  "properties": {
    "gn:admin1_code":"WR",
    "gn:admin2_code":"4.0",
    "gn:admin3_code":"38.0",
    "gn:admin4_code":"380003.0",
    "gn:asciiname":"Khanibhitta",
    "gn:country_code":"NP",
    "gn:dem":429,
    "gn:feature_class":"P",
    "gn:feature_code":"PPLL",
    "gn:name":"Khanibhitta",
    "gn:population":0,
    "gn:timezone":"Asia/Kathmandu",
    "iso:country":"NP",
    "wof:name":"Khanibhitta",
    "wof:placetype":"locality"
},
  "geometry": {"coordinates":[84.33704,27.87716],"type":"Point"}
}