{
  "type": "Feature",
  "properties": {
    "gn:admin1_code":"WR",
    "gn:admin2_code":"3",
    "gn:admin3_code":"45.0",
    "gn:admin4_code":"450056.0",
    "gn:asciiname":"Pho",
    "gn:country_code":"NP",
    "gn:dem":2097,
    "gn:feature_class":"P",
    "gn:feature_code":"PPLL",
    "gn:name":"Pho",
    "gn:population":0,
    "gn:timezone":"Asia/Kathmandu",
    "iso:country":"NP",
    "name:afr_x_preferred":[
        "Ph\u1edf"
    ],
    "name:aze_x_preferred":[
        "Fo"
    ],
    "name:bel_x_preferred":[
        "\u0424\u043e"
    ],
    "name:cat_x_preferred":[
        "Ph\u1edf"
    ],
    "name:ces_x_preferred":[
        "Ph\u1edf"
    ],
    "name:dan_x_preferred":[
        "Ph\u1edf"
    ],
    "name:deu_x_preferred":[
        "Ph\u1edf"
    ],
    "name:epo_x_preferred":[
        "Ph\u1edf"
    ],
    "name:est_x_preferred":[
        "Ph\u1edf"
    ],
    "name:fin_x_preferred":[
        "Ph\u1edf"
    ],
    "name:fra_x_preferred":[
        "Ph\u1edf"
    ],
    "name:glg_x_preferred":[
        "Ph\u1edf"
    ],
    "name:heb_x_preferred":[
        "\u05de\u05e8\u05e7 \u05e4\u05d5"
    ],
    "name:hin_x_preferred":[
        "\u092b\u093c\u0905"
    ],
    "name:hrv_x_preferred":[
        "Ph\u1edf"
    ],
    "name:hun_x_preferred":[
        "Pho"
    ],
    "name:ind_x_preferred":[
        "Ph\u1edf"
    ],
    "name:ita_x_preferred":[
        "Ph\u1edf"
    ],
    "name:jpn_x_preferred":[
        "\u30d5\u30a9\u30fc"
    ],
    "name:lit_x_preferred":[
        "Fo"
    ],
    "name:msa_x_preferred":[
        "Ph\u1edf"
    ],
    "name:nld_x_preferred":[
        "Ph\u1edf"
    ],
    "name:nno_x_preferred":[
        "Pho"
    ],
    "name:nor_x_preferred":[
        "Ph\u1edf"
    ],
    "name:pol_x_preferred":[
        "Ph\u1edf"
    ],
    "name:por_x_preferred":[
        "Ph\u1edf"
    ],
    "name:ron_x_preferred":[
        "Ph\u1edf"
    ],
    "name:rus_x_preferred":[
        "\u0424\u043e"
    ],
    "name:sco_x_preferred":[
        "Pho"
    ],
    "name:slk_x_preferred":[
        "Ph\u1edf"
    ],
    "name:spa_x_preferred":[
        "Ph\u1edf"
    ],
    "name:swe_x_preferred":[
        "Ph\u1edf"
    ],
    "name:tgl_x_preferred":[
        "Ph\u1edf"
    ],
    "name:tha_x_preferred":[
        "\u0e40\u0e1d\u0e2d"
    ],
    "name:ukr_x_preferred":[
        "\u0424\u043e"
    ],
    "name:vie_x_preferred":[
        "Ph\u1edf"
    ],
    "name:zho_x_preferred":[
        "\u8d8a\u5357\u7c89"
    ],
    "wof:name":"Pho",
    "wof:placetype":"locality"
},
  "geometry": {"coordinates":[83.22541,28.42128],"type":"Point"}
}