{
  "type": "Feature",
  "properties": {
    "gn:admin1_code":"MR",
    "gn:admin2_code":"2.0",
    "gn:admin3_code":"59.0",
    "gn:admin4_code":"590033.0",
    "gn:asciiname":"Tallo Ratmate",
    "gn:country_code":"NP",
    "gn:dem":530,
    "gn:feature_class":"P",
    "gn:feature_code":"PPLL",
    "gn:name":"Tallo Ratmate",
    "gn:population":0,
    "gn:timezone":"Asia/Kathmandu",
    "iso:country":"NP",
    "wof:name":"Tallo Ratmate",
    "wof:placetype":"locality"
},
  "geometry": {"coordinates":[81.8052,28.45953],"type":"Point"}
}