{
  "type": "Feature",
  "properties": {
    "gn:admin1_code":"WR",
    "gn:admin2_code":"4",
    "gn:admin3_code":"37",
    "gn:admin4_code":"370026",
    "gn:asciiname":"Tari",
    "gn:country_code":"NP",
    "gn:dem":964,
    "gn:feature_class":"P",
    "gn:feature_code":"PPLL",
    "gn:name":"Tari",
    "gn:population":0,
    "gn:timezone":"Asia/Kathmandu",
    "iso:country":"NP",
    "wof:name":"Tari",
    "wof:placetype":"locality"
},
  "geometry": {"coordinates":[84.49274,28.1967],"type":"Point"}
}