{
  "type": "Feature",
  "properties": {
    "gn:admin1_code":"WR",
    "gn:admin2_code":"3",
    "gn:admin3_code":"44",
    "gn:admin4_code":"440003",
    "gn:asciiname":"Talatung",
    "gn:country_code":"NP",
    "gn:dem":1270,
    "gn:feature_class":"P",
    "gn:feature_code":"PPLL",
    "gn:name":"Talatung",
    "gn:population":0,
    "gn:timezone":"Asia/Kathmandu",
    "iso:country":"NP",
    "wof:name":"Talatung",
    "wof:placetype":"locality"
},
  "geometry": {"coordinates":[83.60526,28.04628],"type":"Point"}
}