{
  "type": "Feature",
  "properties": {
    "gn:admin1_code":"WR",
    "gn:admin2_code":"4",
    "gn:admin3_code":"40.0",
    "gn:admin4_code":"400029.0",
    "gn:asciiname":"Lamjung Himal",
    "gn:country_code":"NP",
    "gn:dem":6877,
    "gn:feature_class":"P",
    "gn:feature_code":"PPLL",
    "gn:name":"Lamjung Himal",
    "gn:population":0,
    "gn:timezone":"Asia/Kathmandu",
    "iso:country":"NP",
    "wof:name":"Lamjung Himal",
    "wof:placetype":"locality"
},
  "geometry": {"coordinates":[84.18720999999999,28.4913],"type":"Point"}
}