{
  "type": "Feature",
  "properties": {
    "gn:admin1_code":"WR",
    "gn:admin2_code":"3",
    "gn:admin3_code":"45.0",
    "gn:admin4_code":"450036.0",
    "gn:asciiname":"Pallo Sim",
    "gn:country_code":"NP",
    "gn:dem":1933,
    "gn:feature_class":"P",
    "gn:feature_code":"PPLL",
    "gn:name":"Pallo Sim",
    "gn:population":0,
    "gn:timezone":"Asia/Kathmandu",
    "iso:country":"NP",
    "wof:name":"Pallo Sim",
    "wof:placetype":"locality"
},
  "geometry": {"coordinates":[83.51918000000001,28.30071],"type":"Point"}
}