{
  "type": "Feature",
  "properties": {
    "gn:admin1_code":"CR",
    "gn:admin2_code":"11",
    "gn:admin3_code":"31",
    "gn:admin4_code":"310038.0",
    "gn:asciiname":"Balukhop",
    "gn:country_code":"NP",
    "gn:dem":829,
    "gn:feature_class":"P",
    "gn:feature_code":"PPLL",
    "gn:name":"Balukhop",
    "gn:population":0,
    "gn:timezone":"Asia/Kathmandu",
    "iso:country":"NP",
    "wof:name":"Balukhop",
    "wof:placetype":"locality"
},
  "geometry": {"coordinates":[84.86078000000001,27.52085],"type":"Point"}
}