{
  "type": "Feature",
  "properties": {
    "gn:admin1_code":"FR",
    "gn:admin2_code":"14",
    "gn:admin3_code":"69.0",
    "gn:admin4_code":"690066.0",
    "gn:asciiname":"Kopchepani",
    "gn:country_code":"NP",
    "gn:dem":1552,
    "gn:feature_class":"P",
    "gn:feature_code":"PPLL",
    "gn:name":"Kopchepani",
    "gn:population":0,
    "gn:timezone":"Asia/Kathmandu",
    "iso:country":"NP",
    "wof:name":"Kopchepani",
    "wof:placetype":"locality"
},
  "geometry": {"coordinates":[81.12704000000002,29.19192],"type":"Point"}
}