{
  "type": "Feature",
  "properties": {
    "gn:admin1_code":"MR",
    "gn:admin2_code":"12",
    "gn:admin3_code":"56.0",
    "gn:admin4_code":"560014.0",
    "gn:asciiname":"Dohote",
    "gn:country_code":"NP",
    "gn:dem":779,
    "gn:feature_class":"P",
    "gn:feature_code":"PPLL",
    "gn:name":"Dohote",
    "gn:population":0,
    "gn:timezone":"Asia/Kathmandu",
    "iso:country":"NP",
    "wof:name":"Dohote",
    "wof:placetype":"locality"
},
  "geometry": {"coordinates":[82.74542,27.95444],"type":"Point"}
}