{
  "type": "Feature",
  "properties": {
    "gn:admin1_code":"WR",
    "gn:admin2_code":"3",
    "gn:admin3_code":"45.0",
    "gn:admin4_code":"450035.0",
    "gn:asciiname":"Sannesi Chautara",
    "gn:country_code":"NP",
    "gn:dem":1057,
    "gn:feature_class":"P",
    "gn:feature_code":"PPLL",
    "gn:name":"Sannesi Chautara",
    "gn:population":0,
    "gn:timezone":"Asia/Kathmandu",
    "iso:country":"NP",
    "wof:name":"Sannesi Chautara",
    "wof:placetype":"locality"
},
  "geometry": {"coordinates":[83.64983000000002,28.23007],"type":"Point"}
}