{
  "type": "Feature",
  "properties": {
    "gn:admin1_code":"ER",
    "gn:admin2_code":"7",
    "gn:admin3_code":"5",
    "gn:admin4_code":"50063",
    "gn:asciiname":"Bintol",
    "gn:country_code":"NP",
    "gn:dem":84,
    "gn:feature_class":"P",
    "gn:feature_code":"PPLL",
    "gn:name":"Bintol",
    "gn:population":0,
    "gn:timezone":"Asia/Kathmandu",
    "iso:country":"NP",
    "wof:name":"Bintol",
    "wof:placetype":"locality"
},
  "geometry": {"coordinates":[87.40913,26.5243],"type":"Point"}
}