{
  "type": "Feature",
  "properties": {
    "gn:admin1_code":"WR",
    "gn:admin2_code":"4",
    "gn:admin3_code":"40.0",
    "gn:admin4_code":"400010.0",
    "gn:asciiname":"Dandakhet",
    "gn:country_code":"NP",
    "gn:dem":1208,
    "gn:feature_class":"P",
    "gn:feature_code":"PPLL",
    "gn:name":"Dandakhet",
    "gn:population":0,
    "gn:timezone":"Asia/Kathmandu",
    "iso:country":"NP",
    "wof:name":"Dandakhet",
    "wof:placetype":"locality"
},
  "geometry": {"coordinates":[83.84071,28.26661],"type":"Point"}
}