{
  "type": "Feature",
  "properties": {
    "gn:admin1_code":"00",
    "gn:asciiname":"Moldun",
    "gn:country_code":"NP",
    "gn:dem":1487,
    "gn:feature_class":"P",
    "gn:feature_code":"PPL",
    "gn:name":"Moldu\u1e45",
    "gn:population":0,
    "gn:timezone":"Asia/Kathmandu",
    "iso:country":"NP",
    "wof:name":"Moldun",
    "wof:placetype":"locality"
},
  "geometry": {"coordinates":[86.16708,27.74895],"type":"Point"}
}