{
  "type": "Feature",
  "properties": {
    "gn:admin1_code":"WR",
    "gn:admin2_code":"3",
    "gn:admin3_code":"45.0",
    "gn:admin4_code":"450003.0",
    "gn:asciiname":"Barlapur",
    "gn:country_code":"NP",
    "gn:dem":1555,
    "gn:feature_class":"P",
    "gn:feature_code":"PPLL",
    "gn:name":"Barlapur",
    "gn:population":0,
    "gn:timezone":"Asia/Kathmandu",
    "iso:country":"NP",
    "wof:name":"Barlapur",
    "wof:placetype":"locality"
},
  "geometry": {"coordinates":[83.42013,28.27822],"type":"Point"}
}