{
  "type": "Feature",
  "properties": {
    "gn:admin1_code":"ER",
    "gn:admin2_code":"13",
    "gn:admin3_code":"15",
    "gn:admin4_code":"150023",
    "gn:asciiname":"Damavati",
    "gn:country_code":"NP",
    "gn:dem":78,
    "gn:feature_class":"P",
    "gn:feature_code":"PPLL",
    "gn:name":"Damavati",
    "gn:population":0,
    "gn:timezone":"Asia/Kathmandu",
    "iso:country":"NP",
    "wof:name":"Damavati",
    "wof:placetype":"locality"
},
  "geometry": {"coordinates":[86.76566,26.50317],"type":"Point"}
}