{
  "type": "Feature",
  "properties": {
    "gn:admin1_code":"CR",
    "gn:admin2_code":"1",
    "gn:admin3_code":"25",
    "gn:admin4_code":"250004",
    "gn:asciiname":"Tinpane",
    "gn:country_code":"NP",
    "gn:dem":2120,
    "gn:feature_class":"P",
    "gn:feature_code":"PPLL",
    "gn:name":"Tinpane",
    "gn:population":0,
    "gn:timezone":"Asia/Kathmandu",
    "iso:country":"NP",
    "wof:name":"Tinpane",
    "wof:placetype":"locality"
},
  "geometry": {"coordinates":[85.29371999999999,27.53534],"type":"Point"}
}