{
  "type": "Feature",
  "properties": {
    "gn:admin1_code":"MR",
    "gn:admin2_code":"12",
    "gn:admin3_code":"55",
    "gn:admin4_code":"550005",
    "gn:asciiname":"Berukhet",
    "gn:country_code":"NP",
    "gn:dem":1228,
    "gn:feature_class":"P",
    "gn:feature_code":"PPLL",
    "gn:name":"Berukhet",
    "gn:population":0,
    "gn:timezone":"Asia/Kathmandu",
    "iso:country":"NP",
    "wof:name":"Berukhet",
    "wof:placetype":"locality"
},
  "geometry": {"coordinates":[82.29618000000001,28.5685],"type":"Point"}
}