{
  "type": "Feature",
  "properties": {
    "gn:admin1_code":"CR",
    "gn:admin2_code":"5",
    "gn:admin3_code":"17.0",
    "gn:admin4_code":"170018.0",
    "gn:asciiname":"Dandatol",
    "gn:country_code":"NP",
    "gn:dem":135,
    "gn:feature_class":"P",
    "gn:feature_code":"PPLL",
    "gn:name":"Dandatol",
    "gn:population":0,
    "gn:timezone":"Asia/Kathmandu",
    "iso:country":"NP",
    "wof:name":"Dandatol",
    "wof:placetype":"locality"
},
  "geometry": {"coordinates":[86.08548,26.89987],"type":"Point"}
}