{
  "type": "Feature",
  "properties": {
    "gn:admin1_code":"CR",
    "gn:admin2_code":"5",
    "gn:admin3_code":"22.0",
    "gn:admin4_code":"220052.0",
    "gn:asciiname":"Sallephedi",
    "gn:country_code":"NP",
    "gn:dem":1944,
    "gn:feature_class":"P",
    "gn:feature_code":"PPLL",
    "gn:name":"Sallephedi",
    "gn:population":0,
    "gn:timezone":"Asia/Kathmandu",
    "iso:country":"NP",
    "wof:name":"Sallephedi",
    "wof:placetype":"locality"
},
  "geometry": {"coordinates":[86.17605999999998,27.59732],"type":"Point"}
}