{
  "type": "Feature",
  "properties": {
    "gn:admin1_code":"CR",
    "gn:admin2_code":"1",
    "gn:admin3_code":"28",
    "gn:admin4_code":"280009",
    "gn:asciiname":"Darshantar",
    "gn:country_code":"NP",
    "gn:dem":600,
    "gn:feature_class":"P",
    "gn:feature_code":"PPLL",
    "gn:name":"Darshantar",
    "gn:population":0,
    "gn:timezone":"Asia/Kathmandu",
    "iso:country":"NP",
    "wof:name":"Darshantar",
    "wof:placetype":"locality"
},
  "geometry": {"coordinates":[85.05835,27.86217000000001],"type":"Point"}
}