{
  "type": "Feature",
  "properties": {
    "gn:admin1_code":"CR",
    "gn:admin2_code":"11",
    "gn:admin3_code":"35.0",
    "gn:admin4_code":"350035.0",
    "gn:asciiname":"Naibini",
    "gn:country_code":"NP",
    "gn:dem":1337,
    "gn:feature_class":"P",
    "gn:feature_code":"PPLL",
    "gn:name":"Naibini",
    "gn:population":0,
    "gn:timezone":"Asia/Kathmandu",
    "iso:country":"NP",
    "wof:name":"Naibini",
    "wof:placetype":"locality"
},
  "geometry": {"coordinates":[84.61121999999997,27.76337],"type":"Point"}
}