{
  "type": "Feature",
  "properties": {
    "gn:admin1_code":"ER",
    "gn:admin2_code":"13",
    "gn:admin3_code":"13",
    "gn:admin4_code":"130067",
    "gn:asciiname":"Masangkha",
    "gn:country_code":"NP",
    "gn:dem":1495,
    "gn:feature_class":"P",
    "gn:feature_code":"PPLL",
    "gn:name":"Masangkha",
    "gn:population":0,
    "gn:timezone":"Asia/Kathmandu",
    "iso:country":"NP",
    "wof:name":"Masangkha",
    "wof:placetype":"locality"
},
  "geometry": {"coordinates":[86.78661,27.33004],"type":"Point"}
}