{
  "type": "Feature",
  "properties": {
    "gn:admin1_code":"CR",
    "gn:admin2_code":"11",
    "gn:admin3_code":"35.0",
    "gn:admin4_code":"350023.0",
    "gn:asciiname":"Sisahani",
    "gn:country_code":"NP",
    "gn:dem":197,
    "gn:feature_class":"P",
    "gn:feature_code":"PPLL",
    "gn:name":"Sisahani",
    "gn:population":0,
    "gn:timezone":"Asia/Kathmandu",
    "iso:country":"NP",
    "wof:name":"Sisahani",
    "wof:placetype":"locality"
},
  "geometry": {"coordinates":[84.55949,27.58329],"type":"Point"}
}