{
  "type": "Feature",
  "properties": {
    "gn:admin1_code":"FR",
    "gn:admin2_code":"9",
    "gn:admin3_code":"75.0",
    "gn:admin4_code":"750037.0",
    "gn:asciiname":"Sipti",
    "gn:country_code":"NP",
    "gn:dem":1727,
    "gn:feature_class":"P",
    "gn:feature_code":"PPLL",
    "gn:name":"Sipti",
    "gn:population":0,
    "gn:timezone":"Asia/Kathmandu",
    "iso:country":"NP",
    "name:ceb_x_preferred":[
        "Sipti"
    ],
    "name:fra_x_preferred":[
        "Sipti"
    ],
    "name:mai_x_preferred":[
        "\u0938\u093f\u092a\u094d\u091f\u0940"
    ],
    "name:msa_x_preferred":[
        "Sipti"
    ],
    "name:nep_x_preferred":[
        "\u0938\u093f\u092a\u094d\u091f\u0940"
    ],
    "name:new_x_preferred":[
        "\u0938\u093f\u092a\u094d\u0924\u0940"
    ],
    "name:pol_x_preferred":[
        "Sipti"
    ],
    "wof:name":"Sipti",
    "wof:placetype":"locality"
},
  "geometry": {"coordinates":[80.69407,29.74819],"type":"Point"}
}