{
  "type": "Feature",
  "properties": {
    "gn:admin1_code":"ER",
    "gn:admin2_code":"7",
    "gn:admin3_code":"5",
    "gn:admin4_code":"50037",
    "gn:asciiname":"Paitisbigha",
    "gn:country_code":"NP",
    "gn:dem":210,
    "gn:feature_class":"P",
    "gn:feature_code":"PPLL",
    "gn:name":"Paitisbigha",
    "gn:population":0,
    "gn:timezone":"Asia/Kathmandu",
    "iso:country":"NP",
    "wof:name":"Paitisbigha",
    "wof:placetype":"locality"
},
  "geometry": {"coordinates":[87.46288,26.7216],"type":"Point"}
}