{
  "type": "Feature",
  "properties": {
    "gn:admin1_code":"CR",
    "gn:admin2_code":"1",
    "gn:admin3_code":"30.0",
    "gn:admin4_code":"300018.0",
    "gn:asciiname":"Laitak",
    "gn:country_code":"NP",
    "gn:dem":596,
    "gn:feature_class":"P",
    "gn:feature_code":"PPLL",
    "gn:name":"Laitak",
    "gn:population":0,
    "gn:timezone":"Asia/Kathmandu",
    "iso:country":"NP",
    "wof:name":"Laitak",
    "wof:placetype":"locality"
},
  "geometry": {"coordinates":[84.69003000000002,27.80619],"type":"Point"}
}