{
  "type": "Feature",
  "properties": {
    "gn:admin1_code":"FR",
    "gn:admin2_code":"14",
    "gn:admin3_code":"69.0",
    "gn:admin4_code":"690009.0",
    "gn:asciiname":"Damabada",
    "gn:country_code":"NP",
    "gn:dem":1137,
    "gn:feature_class":"P",
    "gn:feature_code":"PPLL",
    "gn:name":"Damabada",
    "gn:population":0,
    "gn:timezone":"Asia/Kathmandu",
    "iso:country":"NP",
    "wof:name":"Damabada",
    "wof:placetype":"locality"
},
  "geometry": {"coordinates":[81.4263,28.94913],"type":"Point"}
}