{
  "type": "Feature",
  "properties": {
    "gn:admin1_code":"WR",
    "gn:admin2_code":"4",
    "gn:admin3_code":"36.0",
    "gn:admin4_code":"360019.0",
    "gn:asciiname":"Digaun",
    "gn:country_code":"NP",
    "gn:dem":730,
    "gn:feature_class":"P",
    "gn:feature_code":"PPLL",
    "gn:name":"Digaun",
    "gn:population":0,
    "gn:timezone":"Asia/Kathmandu",
    "iso:country":"NP",
    "wof:name":"Digaun",
    "wof:placetype":"locality"
},
  "geometry": {"coordinates":[84.80370000000001,28.01874],"type":"Point"}
}