{
  "type": "Feature",
  "properties": {
    "gn:admin1_code":"FR",
    "gn:admin2_code":"9.0",
    "gn:asciiname":"Jhulaghat",
    "gn:country_code":"NP",
    "gn:dem":765,
    "gn:feature_class":"P",
    "gn:feature_code":"PPL",
    "gn:name":"Jhulaghat",
    "gn:population":0,
    "gn:timezone":"Asia/Kathmandu",
    "iso:country":"NP",
    "wof:name":"Jhulaghat",
    "wof:placetype":"locality"
},
  "geometry": {"coordinates":[80.38446999999999,29.56774],"type":"Point"}
}