{
  "type": "Feature",
  "properties": {
    "gn:admin1_code":"WR",
    "gn:admin2_code":"8",
    "gn:admin3_code":"48",
    "gn:admin4_code":"480014",
    "gn:asciiname":"Girwari",
    "gn:country_code":"NP",
    "gn:dem":245,
    "gn:feature_class":"P",
    "gn:feature_code":"PPLL",
    "gn:name":"Girwari",
    "gn:population":0,
    "gn:timezone":"Asia/Kathmandu",
    "iso:country":"NP",
    "wof:name":"Girwari",
    "wof:placetype":"locality"
},
  "geometry": {"coordinates":[84.05418,27.68022],"type":"Point"}
}