{
  "type": "Feature",
  "properties": {
    "gn:admin1_code":"FR",
    "gn:admin2_code":"9",
    "gn:admin3_code":"75.0",
    "gn:admin4_code":"750027.0",
    "gn:asciiname":"Duni",
    "gn:country_code":"NP",
    "gn:dem":1906,
    "gn:feature_class":"P",
    "gn:feature_code":"PPLL",
    "gn:name":"Duni",
    "gn:population":0,
    "gn:timezone":"Asia/Kathmandu",
    "iso:country":"NP",
    "wof:name":"Duni",
    "wof:placetype":"locality"
},
  "geometry": {"coordinates":[80.71984,29.70671],"type":"Point"}
}