{
  "type": "Feature",
  "properties": {
    "gn:admin1_code":"MR",
    "gn:admin2_code":"2.0",
    "gn:admin3_code":"57.0",
    "gn:admin4_code":"570027.0",
    "gn:asciiname":"Guruwagaun",
    "gn:country_code":"NP",
    "gn:dem":179,
    "gn:feature_class":"P",
    "gn:feature_code":"PPLL",
    "gn:name":"Guruwagaun",
    "gn:population":0,
    "gn:timezone":"Asia/Kathmandu",
    "iso:country":"NP",
    "wof:name":"Guruwagaun",
    "wof:placetype":"locality"
},
  "geometry": {"coordinates":[81.77883,28.16628],"type":"Point"}
}