{
  "type": "Feature",
  "properties": {
    "gn:admin1_code":"FR",
    "gn:admin2_code":"14.0",
    "gn:admin3_code":"67.0",
    "gn:admin4_code":"670019.0",
    "gn:asciiname":"Tanka",
    "gn:country_code":"NP",
    "gn:dem":2080,
    "gn:feature_class":"P",
    "gn:feature_code":"PPLL",
    "gn:name":"Tanka",
    "gn:population":0,
    "gn:timezone":"Asia/Kathmandu",
    "iso:country":"NP",
    "wof:name":"Tanka",
    "wof:placetype":"locality"
},
  "geometry": {"coordinates":[81.66466,29.5296],"type":"Point"}
}