{
  "type": "Feature",
  "properties": {
    "gn:admin1_code":"WR",
    "gn:admin2_code":"4.0",
    "gn:admin3_code":"39.0",
    "gn:admin4_code":"390055.0",
    "gn:asciiname":"Acharya",
    "gn:country_code":"NP",
    "gn:dem":584,
    "gn:feature_class":"P",
    "gn:feature_code":"PPLL",
    "gn:name":"Acharya",
    "gn:population":0,
    "gn:timezone":"Asia/Kathmandu",
    "iso:country":"NP",
    "wof:name":"Acharya",
    "wof:placetype":"locality"
},
  "geometry": {"coordinates":[84.0005,28.13192],"type":"Point"}
}