{
  "type": "Feature",
  "properties": {
    "gn:admin1_code":"WR",
    "gn:admin2_code":"4.0",
    "gn:admin3_code":"39.0",
    "gn:admin4_code":"390055.0",
    "gn:asciiname":"Acharya",
    "gn:country_code":"NP",
    "gn:dem":584,
    "gn:feature_class":"P",
    "gn:feature_code":"PPLL",
    "gn:name":"Acharya",
    "gn:population":0,
    "gn:timezone":"Asia/Kathmandu",
    "iso:country":"NP",
    "name:bul_x_preferred":[
        "\u0410\u0447\u0430\u0440\u0438\u044f"
    ],
    "name:deu_x_preferred":[
        "Acharya"
    ],
    "name:fra_x_preferred":[
        "\u0100c\u0101rya"
    ],
    "name:guj_x_preferred":[
        "\u0a86\u0a9a\u0abe\u0ab0\u0acd\u0aaf"
    ],
    "name:hin_x_preferred":[
        "\u0906\u091a\u093e\u0930\u094d\u092f"
    ],
    "name:hun_x_preferred":[
        "\u00c1cs\u00e1rja"
    ],
    "name:ita_x_preferred":[
        "\u0100c\u0101rya"
    ],
    "name:jpn_x_preferred":[
        "\u963f\u95cd\u68a8"
    ],
    "name:kan_x_preferred":[
        "\u0c86\u0c9a\u0cbe\u0cb0\u0ccd\u0caf"
    ],
    "name:kat_x_preferred":[
        "\u10d0\u10e9\u10d0\u10e0\u10d8\u10d0"
    ],
    "name:mar_x_preferred":[
        "\u0906\u091a\u093e\u0930\u094d\u092f"
    ],
    "name:nep_x_preferred":[
        "\u0906\u091a\u093e\u0930\u094d\u092f"
    ],
    "name:nld_x_preferred":[
        "Acharya"
    ],
    "name:pol_x_preferred":[
        "A\u0107arja"
    ],
    "name:por_x_preferred":[
        "Acharya"
    ],
    "name:rus_x_preferred":[
        "\u0410\u0447\u0430\u0440\u044c\u044f"
    ],
    "name:spa_x_preferred":[
        "Acharya"
    ],
    "name:tam_x_preferred":[
        "\u0b86\u0b9a\u0bcd\u0b9a\u0bbe\u0bb0\u0bbf\u0baf\u0bb0\u0bcd"
    ],
    "name:ukr_x_preferred":[
        "\u0410\u0447\u0430\u0440'\u044f"
    ],
    "name:vie_x_preferred":[
        "A-x\u00e0-l\u00ea"
    ],
    "name:zho_x_preferred":[
        "\u963f\u95cd\u9ece"
    ],
    "wof:name":"Acharya",
    "wof:placetype":"locality"
},
  "geometry": {"coordinates":[84.0005,28.13192],"type":"Point"}
}