{
  "type": "Feature",
  "properties": {
    "gn:admin1_code":"WR",
    "gn:admin2_code":"8",
    "gn:admin3_code":"49",
    "gn:admin4_code":"490003",
    "gn:asciiname":"Gohawa",
    "gn:country_code":"NP",
    "gn:dem":115,
    "gn:feature_class":"P",
    "gn:feature_code":"PPLL",
    "gn:name":"Gohawa",
    "gn:population":0,
    "gn:timezone":"Asia/Kathmandu",
    "iso:country":"NP",
    "wof:name":"Gohawa",
    "wof:placetype":"locality"
},
  "geometry": {"coordinates":[83.40015,27.57629],"type":"Point"}
}