{
  "type": "Feature",
  "properties": {
    "gn:admin1_code":"MR",
    "gn:admin2_code":"2",
    "gn:admin3_code":"60.0",
    "gn:admin4_code":"600042.0",
    "gn:asciiname":"Sisneri",
    "gn:country_code":"NP",
    "gn:dem":1041,
    "gn:feature_class":"P",
    "gn:feature_code":"PPLL",
    "gn:name":"Sisneri",
    "gn:population":0,
    "gn:timezone":"Asia/Kathmandu",
    "iso:country":"NP",
    "wof:name":"Sisneri",
    "wof:placetype":"locality"
},
  "geometry": {"coordinates":[81.73088,28.69609],"type":"Point"}
}