{
  "type": "Feature",
  "properties": {
    "gn:admin1_code":"MR",
    "gn:admin2_code":"2",
    "gn:admin3_code":"60.0",
    "gn:admin4_code":"600042.0",
    "gn:asciiname":"Sisneri",
    "gn:country_code":"NP",
    "gn:dem":1041,
    "gn:feature_class":"P",
    "gn:feature_code":"PPLL",
    "gn:name":"Sisneri",
    "gn:population":0,
    "gn:timezone":"Asia/Kathmandu",
    "iso:country":"NP",
    "name:msa_x_preferred":[
        "Sisneri"
    ],
    "name:nep_x_preferred":[
        "\u0938\u093f\u0938\u094d\u0928\u0947\u0930\u0940"
    ],
    "name:new_x_preferred":[
        "\u0938\u093f\u0938\u094d\u0928\u0947\u0930\u0940"
    ],
    "name:pol_x_preferred":[
        "Sisneri"
    ],
    "wof:name":"Sisneri",
    "wof:placetype":"locality"
},
  "geometry": {"coordinates":[81.73088,28.69609],"type":"Point"}
}