{
  "type": "Feature",
  "properties": {
    "gn:admin1_code":"WR",
    "gn:admin2_code":"4",
    "gn:admin3_code":"36.0",
    "gn:admin4_code":"360036.0",
    "gn:asciiname":"Khoplangbesi",
    "gn:country_code":"NP",
    "gn:dem":529,
    "gn:feature_class":"P",
    "gn:feature_code":"PPLL",
    "gn:name":"Khoplangbesi",
    "gn:population":0,
    "gn:timezone":"Asia/Kathmandu",
    "iso:country":"NP",
    "wof:name":"Khoplangbesi",
    "wof:placetype":"locality"
},
  "geometry": {"coordinates":[84.57653000000001,28.022],"type":"Point"}
}