{
  "type": "Feature",
  "properties": {
    "gn:admin1_code":"WR",
    "gn:admin2_code":"4",
    "gn:admin3_code":"36.0",
    "gn:admin4_code":"360018.0",
    "gn:asciiname":"Salangiri",
    "gn:country_code":"NP",
    "gn:dem":676,
    "gn:feature_class":"P",
    "gn:feature_code":"PPLL",
    "gn:name":"Salangiri",
    "gn:population":0,
    "gn:timezone":"Asia/Kathmandu",
    "iso:country":"NP",
    "wof:name":"Salangiri",
    "wof:placetype":"locality"
},
  "geometry": {"coordinates":[84.49587,27.9459],"type":"Point"}
}