{
  "type": "Feature",
  "properties": {
    "gn:admin1_code":"MR",
    "gn:admin2_code":"2",
    "gn:admin3_code":"60.0",
    "gn:admin4_code":"600023.0",
    "gn:asciiname":"Gaurigaun",
    "gn:country_code":"NP",
    "gn:dem":1675,
    "gn:feature_class":"P",
    "gn:feature_code":"PPLL",
    "gn:name":"Gaurigaun",
    "gn:population":0,
    "gn:timezone":"Asia/Kathmandu",
    "iso:country":"NP",
    "name:msa_x_preferred":[
        "Gaurigaun"
    ],
    "name:nep_x_preferred":[
        "\u0917\u0948\u0930\u0940\u0917\u093e\u0909\u0901"
    ],
    "wof:name":"Gaurigaun",
    "wof:placetype":"locality"
},
  "geometry": {"coordinates":[81.66320999999998,28.99251],"type":"Point"}
}