{
  "type": "Feature",
  "properties": {
    "gn:admin1_code":"00",
    "gn:asciiname":"Kandel",
    "gn:country_code":"NP",
    "gn:dem":2062,
    "gn:feature_class":"P",
    "gn:feature_code":"PPL",
    "gn:name":"K\u0101\u1e45del",
    "gn:population":0,
    "gn:timezone":"Asia/Kathmandu",
    "iso:country":"NP",
    "name:ara_x_preferred":[
        "\u0643\u0627\u0646\u062f\u0644"
    ],
    "name:azb_x_preferred":[
        "\u06a9\u0627\u0646\u062f\u0644"
    ],
    "name:ceb_x_preferred":[
        "Kandel"
    ],
    "name:deu_x_preferred":[
        "Kandel"
    ],
    "name:epo_x_preferred":[
        "Kandel"
    ],
    "name:fas_x_preferred":[
        "\u06a9\u0627\u0646\u062f\u0644"
    ],
    "name:fra_x_preferred":[
        "Kandel"
    ],
    "name:hun_x_preferred":[
        "Kandel"
    ],
    "name:ita_x_preferred":[
        "Kandel"
    ],
    "name:kaz_x_preferred":[
        "\u041a\u0430\u043d\u0434\u0435\u043b\u044c"
    ],
    "name:kir_x_preferred":[
        "\u041a\u0430\u043d\u0434\u0435\u043b\u044c"
    ],
    "name:msa_x_preferred":[
        "Kandel"
    ],
    "name:nld_x_preferred":[
        "Kandel"
    ],
    "name:pfl_x_preferred":[
        "Kandel"
    ],
    "name:pol_x_preferred":[
        "Kandel"
    ],
    "name:por_x_preferred":[
        "Kandel"
    ],
    "name:ron_x_preferred":[
        "Kandel"
    ],
    "name:rus_x_preferred":[
        "\u041a\u0430\u043d\u0434\u0435\u043b\u044c"
    ],
    "name:spa_x_preferred":[
        "Kandel"
    ],
    "name:srp_x_preferred":[
        "\u041a\u0430\u043d\u0434\u0435\u043b"
    ],
    "name:tur_x_preferred":[
        "Kandel"
    ],
    "name:ukr_x_preferred":[
        "\u041a\u0430\u043d\u0434\u0435\u043b\u044c"
    ],
    "name:uzb_x_preferred":[
        "Kandel"
    ],
    "name:vie_x_preferred":[
        "Kandel"
    ],
    "name:vol_x_preferred":[
        "Kandel"
    ],
    "name:war_x_preferred":[
        "Kandel"
    ],
    "name:zho_x_preferred":[
        "\u574e\u5fb7\u5c14"
    ],
    "wof:name":"Kandel",
    "wof:placetype":"locality"
},
  "geometry": {"coordinates":[86.61256,27.44218],"type":"Point"}
}