{
  "type": "Feature",
  "properties": {
    "gn:admin1_code":"00",
    "gn:asciiname":"Kandel",
    "gn:country_code":"NP",
    "gn:dem":2062,
    "gn:feature_class":"P",
    "gn:feature_code":"PPL",
    "gn:name":"K\u0101\u1e45del",
    "gn:population":0,
    "gn:timezone":"Asia/Kathmandu",
    "iso:country":"NP",
    "wof:name":"Kandel",
    "wof:placetype":"locality"
},
  "geometry": {"coordinates":[86.61256,27.44218],"type":"Point"}
}