{
  "type": "Feature",
  "properties": {
    "gn:admin1_code":"ER",
    "gn:admin2_code":"13",
    "gn:admin3_code":"16",
    "gn:admin4_code":"160031",
    "gn:asciiname":"Birnagar",
    "gn:country_code":"NP",
    "gn:dem":142,
    "gn:feature_class":"P",
    "gn:feature_code":"PPLL",
    "gn:name":"Birnagar",
    "gn:population":0,
    "gn:timezone":"Asia/Kathmandu",
    "iso:country":"NP",
    "wof:name":"Birnagar",
    "wof:placetype":"locality"
},
  "geometry": {"coordinates":[86.48168000000003,26.77532],"type":"Point"}
}