{
  "type": "Feature",
  "properties": {
    "gn:admin1_code":"WR",
    "gn:admin2_code":"8",
    "gn:admin3_code":"47",
    "gn:admin4_code":"470062",
    "gn:asciiname":"Arbathok",
    "gn:country_code":"NP",
    "gn:dem":1393,
    "gn:feature_class":"P",
    "gn:feature_code":"PPLL",
    "gn:name":"Arbathok",
    "gn:population":0,
    "gn:timezone":"Asia/Kathmandu",
    "iso:country":"NP",
    "wof:name":"Arbathok",
    "wof:placetype":"locality"
},
  "geometry": {"coordinates":[83.52059,27.86875],"type":"Point"}
}