{
  "type": "Feature",
  "properties": {
    "gn:admin1_code":"FR",
    "gn:admin2_code":"9",
    "gn:admin3_code":"74",
    "gn:admin4_code":"740048",
    "gn:asciiname":"Dansili",
    "gn:country_code":"NP",
    "gn:dem":1802,
    "gn:feature_class":"P",
    "gn:feature_code":"PPLL",
    "gn:name":"Dansili",
    "gn:population":0,
    "gn:timezone":"Asia/Kathmandu",
    "iso:country":"NP",
    "name:jpn_x_preferred":[
        "\u30c0\u30f3\u30b7\u30ea"
    ],
    "wof:name":"Dansili",
    "wof:placetype":"locality"
},
  "geometry": {"coordinates":[80.53874,29.41758],"type":"Point"}
}