{
  "type": "Feature",
  "properties": {
    "gn:admin1_code":"CR",
    "gn:admin2_code":"1",
    "gn:admin3_code":"25",
    "gn:admin4_code":"250031",
    "gn:asciiname":"Baguwa",
    "gn:country_code":"NP",
    "gn:dem":1159,
    "gn:feature_class":"P",
    "gn:feature_code":"PPLL",
    "gn:name":"Baguwa",
    "gn:population":0,
    "gn:timezone":"Asia/Kathmandu",
    "iso:country":"NP",
    "name:ceb_x_preferred":[
        "Baguwa"
    ],
    "name:mai_x_preferred":[
        "\u092c\u0917\u0941\u0935\u093e"
    ],
    "name:msa_x_preferred":[
        "Baguwa"
    ],
    "name:nep_x_preferred":[
        "\u092c\u0917\u0941\u0935\u093e"
    ],
    "name:new_x_preferred":[
        "\u092c\u0917\u0941\u0935\u093e"
    ],
    "name:pol_x_preferred":[
        "Baguwa"
    ],
    "wof:name":"Baguwa",
    "wof:placetype":"locality"
},
  "geometry": {"coordinates":[85.25185,27.48816],"type":"Point"}
}