{
  "type": "Feature",
  "properties": {
    "gn:admin1_code":"WR",
    "gn:admin2_code":"8",
    "gn:admin3_code":"49",
    "gn:admin4_code":"490053",
    "gn:asciiname":"Ramnagar",
    "gn:country_code":"NP",
    "gn:dem":110,
    "gn:feature_class":"P",
    "gn:feature_code":"PPLL",
    "gn:name":"Ramnagar",
    "gn:population":0,
    "gn:timezone":"Asia/Kathmandu",
    "iso:country":"NP",
    "name:ben_x_preferred":[
        "\u09b0\u09be\u09ae\u09a8\u0997\u09b0"
    ],
    "name:cat_x_preferred":[
        "Ramnagar"
    ],
    "name:ceb_x_preferred":[
        "Ramnagar"
    ],
    "name:fra_x_preferred":[
        "Ramnagar"
    ],
    "name:hin_x_preferred":[
        "\u0930\u093e\u092e\u0928\u0917\u0930"
    ],
    "name:new_x_preferred":[
        "\u0930\u093e\u092e\u0928\u0917\u0930"
    ],
    "name:nld_x_preferred":[
        "Ramnagar"
    ],
    "name:pol_x_preferred":[
        "Ramnagar"
    ],
    "name:rus_x_preferred":[
        "\u0420\u0430\u043c\u043d\u0430\u0433\u0430\u0440"
    ],
    "name:swe_x_preferred":[
        "Ramnagar"
    ],
    "wof:name":"Ramnagar",
    "wof:placetype":"locality"
},
  "geometry": {"coordinates":[83.51478,27.51362],"type":"Point"}
}