{
  "type": "Feature",
  "properties": {
    "gn:admin1_code":"CR",
    "gn:admin2_code":"5",
    "gn:admin3_code":"18",
    "gn:admin4_code":"180031",
    "gn:asciiname":"Ajagaiwa",
    "gn:country_code":"NP",
    "gn:dem":97,
    "gn:feature_class":"P",
    "gn:feature_code":"PPLL",
    "gn:name":"Ajagaiwa",
    "gn:population":0,
    "gn:timezone":"Asia/Kathmandu",
    "iso:country":"NP",
    "wof:name":"Ajagaiwa",
    "wof:placetype":"locality"
},
  "geometry": {"coordinates":[85.89161999999997,26.82673],"type":"Point"}
}