{
  "type": "Feature",
  "properties": {
    "gn:admin1_code":"ER",
    "gn:admin2_code":"13",
    "gn:admin3_code":"13.0",
    "gn:admin4_code":"130028.0",
    "gn:asciiname":"Chindeswanra",
    "gn:country_code":"NP",
    "gn:dem":899,
    "gn:feature_class":"P",
    "gn:feature_code":"PPLL",
    "gn:name":"Chindeswanra",
    "gn:population":0,
    "gn:timezone":"Asia/Kathmandu",
    "iso:country":"NP",
    "wof:name":"Chindeswanra",
    "wof:placetype":"locality"
},
  "geometry": {"coordinates":[86.73698,27.31123],"type":"Point"}
}