{
  "type": "Feature",
  "properties": {
    "gn:admin1_code":"00",
    "gn:asciiname":"Sundarpur",
    "gn:country_code":"NP",
    "gn:dem":98,
    "gn:feature_class":"P",
    "gn:feature_code":"PPL",
    "gn:name":"Sundarpur",
    "gn:population":0,
    "gn:timezone":"Asia/Kathmandu",
    "iso:country":"NP",
    "name:ceb_x_preferred":[
        "Sundarpur"
    ],
    "name:fra_x_preferred":[
        "Sundarpur"
    ],
    "name:ita_x_preferred":[
        "Sundarpur"
    ],
    "name:mai_x_preferred":[
        "\u0938\u0941\u0928\u094d\u0926\u0930\u092a\u0941\u0930"
    ],
    "name:new_x_preferred":[
        "\u0938\u0941\u0928\u094d\u0926\u0930\u092a\u0941\u0930"
    ],
    "name:pol_x_preferred":[
        "Sundarpur"
    ],
    "name:und_x_variant":[
        "Sunarpur",
        "Sundarpur"
    ],
    "wof:name":"Sundarpur",
    "wof:placetype":"locality"
},
  "geometry": {"coordinates":[85.12434,27.02355],"type":"Point"}
}