{
  "type": "Feature",
  "properties": {
    "gn:admin1_code":"ER",
    "gn:admin2_code":"10",
    "gn:admin3_code":"2",
    "gn:admin4_code":"20003",
    "gn:asciiname":"Sadhane",
    "gn:country_code":"NP",
    "gn:dem":1258,
    "gn:feature_class":"P",
    "gn:feature_code":"PPLL",
    "gn:name":"Sadhane",
    "gn:population":0,
    "gn:timezone":"Asia/Kathmandu",
    "iso:country":"NP",
    "wof:name":"Sadhane",
    "wof:placetype":"locality"
},
  "geometry": {"coordinates":[87.61960000000001,26.91625],"type":"Point"}
}