{
  "type": "Feature",
  "properties": {
    "gn:admin1_code":"ER",
    "gn:admin2_code":"7",
    "gn:admin3_code":"10.0",
    "gn:admin4_code":"100045.0",
    "gn:asciiname":"Thesuwaghat",
    "gn:country_code":"NP",
    "gn:dem":203,
    "gn:feature_class":"P",
    "gn:feature_code":"PPLL",
    "gn:name":"Thesuwaghat",
    "gn:population":0,
    "gn:timezone":"Asia/Kathmandu",
    "iso:country":"NP",
    "wof:name":"Thesuwaghat",
    "wof:placetype":"locality"
},
  "geometry": {"coordinates":[86.97004,26.90617],"type":"Point"}
}