{
  "type": "Feature",
  "properties": {
    "gn:admin1_code":"ER",
    "gn:admin2_code":"13",
    "gn:admin3_code":"13",
    "gn:admin4_code":"130071",
    "gn:asciiname":"Simkharka",
    "gn:country_code":"NP",
    "gn:dem":1599,
    "gn:feature_class":"P",
    "gn:feature_code":"PPLL",
    "gn:name":"Simkharka",
    "gn:population":0,
    "gn:timezone":"Asia/Kathmandu",
    "iso:country":"NP",
    "wof:name":"Simkharka",
    "wof:placetype":"locality"
},
  "geometry": {"coordinates":[86.85949000000002,27.35186],"type":"Point"}
}