{
  "type": "Feature",
  "properties": {
    "gn:admin1_code":"WR",
    "gn:admin2_code":"3",
    "gn:admin3_code":"42",
    "gn:admin4_code":"420012",
    "gn:asciiname":"Thulungphat",
    "gn:country_code":"NP",
    "gn:dem":3941,
    "gn:feature_class":"P",
    "gn:feature_code":"PPLL",
    "gn:name":"Thulungphat",
    "gn:population":0,
    "gn:timezone":"Asia/Kathmandu",
    "iso:country":"NP",
    "wof:name":"Thulungphat",
    "wof:placetype":"locality"
},
  "geometry": {"coordinates":[83.93884,29.16007],"type":"Point"}
}