{
  "type": "Feature",
  "properties": {
    "gn:admin1_code":"WR",
    "gn:admin2_code":"4.0",
    "gn:admin3_code":"39.0",
    "gn:admin4_code":"390020.0",
    "gn:asciiname":"Darbot",
    "gn:country_code":"NP",
    "gn:dem":1148,
    "gn:feature_class":"P",
    "gn:feature_code":"PPLL",
    "gn:name":"Darbot",
    "gn:population":0,
    "gn:timezone":"Asia/Kathmandu",
    "iso:country":"NP",
    "wof:name":"Darbot",
    "wof:placetype":"locality"
},
  "geometry": {"coordinates":[83.71168,28.07975],"type":"Point"}
}