{
  "type": "Feature",
  "properties": {
    "gn:admin1_code":"ER",
    "gn:admin2_code":"10",
    "gn:admin3_code":"4.0",
    "gn:admin4_code":"40050.0",
    "gn:asciiname":"Mayurbhitta",
    "gn:country_code":"NP",
    "gn:dem":119,
    "gn:feature_class":"P",
    "gn:feature_code":"PPLL",
    "gn:name":"Mayurbhitta",
    "gn:population":0,
    "gn:timezone":"Asia/Kathmandu",
    "iso:country":"NP",
    "wof:name":"Mayurbhitta",
    "wof:placetype":"locality"
},
  "geometry": {"coordinates":[87.74597,26.62356],"type":"Point"}
}