{
  "type": "Feature",
  "properties": {
    "gn:admin1_code":"ER",
    "gn:admin2_code":"10",
    "gn:admin3_code":"2",
    "gn:admin4_code":"20010",
    "gn:asciiname":"Tusare",
    "gn:country_code":"NP",
    "gn:dem":2170,
    "gn:feature_class":"P",
    "gn:feature_code":"PPLL",
    "gn:name":"Tusare",
    "gn:population":0,
    "gn:timezone":"Asia/Kathmandu",
    "iso:country":"NP",
    "wof:name":"Tusare",
    "wof:placetype":"locality"
},
  "geometry": {"coordinates":[87.88728,27.21937],"type":"Point"}
}