{
  "type": "Feature",
  "properties": {
    "gn:admin1_code":"FR",
    "gn:admin2_code":"14",
    "gn:admin3_code":"68",
    "gn:admin4_code":"680037",
    "gn:asciiname":"Salubyani",
    "gn:country_code":"NP",
    "gn:dem":2161,
    "gn:feature_class":"P",
    "gn:feature_code":"PPLL",
    "gn:name":"Salubyani",
    "gn:population":0,
    "gn:timezone":"Asia/Kathmandu",
    "iso:country":"NP",
    "wof:name":"Salubyani",
    "wof:placetype":"locality"
},
  "geometry": {"coordinates":[81.1267,29.42589000000001],"type":"Point"}
}