{
  "type": "Feature",
  "properties": {
    "gn:admin1_code":"MR",
    "gn:admin2_code":"12",
    "gn:admin3_code":"55",
    "gn:admin4_code":"550018",
    "gn:asciiname":"Sailakamad",
    "gn:country_code":"NP",
    "gn:dem":1321,
    "gn:feature_class":"P",
    "gn:feature_code":"PPLL",
    "gn:name":"Sailakamad",
    "gn:population":0,
    "gn:timezone":"Asia/Kathmandu",
    "iso:country":"NP",
    "wof:name":"Sailakamad",
    "wof:placetype":"locality"
},
  "geometry": {"coordinates":[82.14820999999998,28.39761],"type":"Point"}
}