{
  "type": "Feature",
  "properties": {
    "gn:admin1_code":"MR",
    "gn:admin2_code":"6",
    "gn:admin3_code":"64.0",
    "gn:admin4_code":"640003.0",
    "gn:asciiname":"Uktari",
    "gn:country_code":"NP",
    "gn:dem":2918,
    "gn:feature_class":"P",
    "gn:feature_code":"PPLL",
    "gn:name":"Uktari",
    "gn:population":0,
    "gn:timezone":"Asia/Kathmandu",
    "iso:country":"NP",
    "wof:name":"Uktari",
    "wof:placetype":"locality"
},
  "geometry": {"coordinates":[81.85394000000002,29.10786],"type":"Point"}
}