{
  "type": "Feature",
  "properties": {
    "gn:admin1_code":"FR",
    "gn:admin2_code":"14",
    "gn:admin3_code":"69.0",
    "gn:admin4_code":"690058.0",
    "gn:asciiname":"Lamgaun",
    "gn:country_code":"NP",
    "gn:dem":1108,
    "gn:feature_class":"P",
    "gn:feature_code":"PPLL",
    "gn:name":"Lamgaun",
    "gn:population":0,
    "gn:timezone":"Asia/Kathmandu",
    "iso:country":"NP",
    "wof:name":"Lamgaun",
    "wof:placetype":"locality"
},
  "geometry": {"coordinates":[81.56201,28.77787],"type":"Point"}
}