{
  "type": "Feature",
  "properties": {
    "gn:admin1_code":"ER",
    "gn:admin2_code":"7",
    "gn:admin3_code":"5",
    "gn:admin4_code":"50042",
    "gn:asciiname":"Lohasur",
    "gn:country_code":"NP",
    "gn:dem":92,
    "gn:feature_class":"P",
    "gn:feature_code":"PPLL",
    "gn:name":"Lohasur",
    "gn:population":0,
    "gn:timezone":"Asia/Kathmandu",
    "iso:country":"NP",
    "wof:name":"Lohasur",
    "wof:placetype":"locality"
},
  "geometry": {"coordinates":[87.38086,26.562],"type":"Point"}
}