{
  "type": "Feature",
  "properties": {
    "gn:admin1_code":"ER",
    "gn:admin2_code":"7",
    "gn:admin3_code":"5",
    "gn:admin4_code":"50041",
    "gn:asciiname":"Nepalitol",
    "gn:country_code":"NP",
    "gn:dem":65,
    "gn:feature_class":"P",
    "gn:feature_code":"PPLL",
    "gn:name":"Nepalitol",
    "gn:population":0,
    "gn:timezone":"Asia/Kathmandu",
    "iso:country":"NP",
    "wof:name":"Nepalitol",
    "wof:placetype":"locality"
},
  "geometry": {"coordinates":[87.32523,26.39029],"type":"Point"}
}