{
  "type": "Feature",
  "properties": {
    "gn:admin1_code":"WR",
    "gn:admin2_code":"4",
    "gn:admin3_code":"36.0",
    "gn:admin4_code":"360025.0",
    "gn:asciiname":"Bayakgaun",
    "gn:country_code":"NP",
    "gn:dem":1092,
    "gn:feature_class":"P",
    "gn:feature_code":"PPLL",
    "gn:name":"Bayakgaun",
    "gn:population":0,
    "gn:timezone":"Asia/Kathmandu",
    "iso:country":"NP",
    "wof:name":"Bayakgaun",
    "wof:placetype":"locality"
},
  "geometry": {"coordinates":[84.66901,27.94919],"type":"Point"}
}