{
  "type": "Feature",
  "properties": {
    "gn:admin1_code":"WR",
    "gn:admin2_code":"3",
    "gn:admin3_code":"44",
    "gn:admin4_code":"440044",
    "gn:asciiname":"Charkan",
    "gn:country_code":"NP",
    "gn:dem":712,
    "gn:feature_class":"P",
    "gn:feature_code":"PPLL",
    "gn:name":"Charkan",
    "gn:population":0,
    "gn:timezone":"Asia/Kathmandu",
    "iso:country":"NP",
    "wof:name":"Charkan",
    "wof:placetype":"locality"
},
  "geometry": {"coordinates":[83.61189,28.02947],"type":"Point"}
}