{
  "type": "Feature",
  "properties": {
    "gn:admin1_code":"CR",
    "gn:admin2_code":"1",
    "gn:admin3_code":"29",
    "gn:admin4_code":"290010",
    "gn:asciiname":"Choktar",
    "gn:country_code":"NP",
    "gn:dem":839,
    "gn:feature_class":"P",
    "gn:feature_code":"PPLL",
    "gn:name":"Choktar",
    "gn:population":0,
    "gn:timezone":"Asia/Kathmandu",
    "iso:country":"NP",
    "wof:name":"Choktar",
    "wof:placetype":"locality"
},
  "geometry": {"coordinates":[85.18626999999999,27.98977],"type":"Point"}
}