{
  "type": "Feature",
  "properties": {
    "gn:admin1_code":"CR",
    "gn:admin2_code":"1",
    "gn:admin3_code":"29",
    "gn:admin4_code":"290013",
    "gn:asciiname":"Larchyang",
    "gn:country_code":"NP",
    "gn:dem":1769,
    "gn:feature_class":"P",
    "gn:feature_code":"PPLL",
    "gn:name":"Larchyang",
    "gn:population":0,
    "gn:timezone":"Asia/Kathmandu",
    "iso:country":"NP",
    "wof:name":"Larchyang",
    "wof:placetype":"locality"
},
  "geometry": {"coordinates":[85.28711,28.02193],"type":"Point"}
}