{
  "type": "Feature",
  "properties": {
    "gn:admin1_code":"WR",
    "gn:admin2_code":"4",
    "gn:admin3_code":"36.0",
    "gn:admin4_code":"360062.0",
    "gn:asciiname":"Chhatatar",
    "gn:country_code":"NP",
    "gn:dem":386,
    "gn:feature_class":"P",
    "gn:feature_code":"PPLL",
    "gn:name":"Chhatatar",
    "gn:population":0,
    "gn:timezone":"Asia/Kathmandu",
    "iso:country":"NP",
    "wof:name":"Chhatatar",
    "wof:placetype":"locality"
},
  "geometry": {"coordinates":[84.65555999999999,27.86112],"type":"Point"}
}