{
  "type": "Feature",
  "properties": {
    "gn:admin1_code":"CR",
    "gn:admin2_code":"5",
    "gn:admin3_code":"22.0",
    "gn:admin4_code":"220007.0",
    "gn:asciiname":"Dandaghar",
    "gn:country_code":"NP",
    "gn:dem":1986,
    "gn:feature_class":"P",
    "gn:feature_code":"PPLL",
    "gn:name":"Dandaghar",
    "gn:population":0,
    "gn:timezone":"Asia/Kathmandu",
    "iso:country":"NP",
    "wof:name":"Dandaghar",
    "wof:placetype":"locality"
},
  "geometry": {"coordinates":[86.0792,27.82634],"type":"Point"}
}