{
  "type": "Feature",
  "properties": {
    "gn:admin1_code":"MR",
    "gn:admin2_code":"12",
    "gn:admin3_code":"56.0",
    "gn:admin4_code":"560004.0",
    "gn:asciiname":"Kolhai",
    "gn:country_code":"NP",
    "gn:dem":254,
    "gn:feature_class":"P",
    "gn:feature_code":"PPLL",
    "gn:name":"Kolhai",
    "gn:population":0,
    "gn:timezone":"Asia/Kathmandu",
    "iso:country":"NP",
    "wof:name":"Kolhai",
    "wof:placetype":"locality"
},
  "geometry": {"coordinates":[82.52771,27.86461],"type":"Point"}
}