{
  "type": "Feature",
  "properties": {
    "gn:admin1_code":"MR",
    "gn:admin2_code":"12",
    "gn:admin3_code":"56.0",
    "gn:admin4_code":"560002.0",
    "gn:asciiname":"Taule",
    "gn:country_code":"NP",
    "gn:dem":265,
    "gn:feature_class":"P",
    "gn:feature_code":"PPLL",
    "gn:name":"Taule",
    "gn:population":0,
    "gn:timezone":"Asia/Kathmandu",
    "iso:country":"NP",
    "wof:name":"Taule",
    "wof:placetype":"locality"
},
  "geometry": {"coordinates":[82.45033000000002,27.81551],"type":"Point"}
}