{
  "type": "Feature",
  "properties": {
    "gn:admin1_code":"MR",
    "gn:admin2_code":"12",
    "gn:admin3_code":"53",
    "gn:admin4_code":"530032",
    "gn:asciiname":"Darsabang",
    "gn:country_code":"NP",
    "gn:dem":1508,
    "gn:feature_class":"P",
    "gn:feature_code":"PPLL",
    "gn:name":"Darsabang",
    "gn:population":0,
    "gn:timezone":"Asia/Kathmandu",
    "iso:country":"NP",
    "wof:name":"Darsabang",
    "wof:placetype":"locality"
},
  "geometry": {"coordinates":[82.60231999999998,28.1597],"type":"Point"}
}