{
  "type": "Feature",
  "properties": {
    "gn:admin1_code":"WR",
    "gn:admin2_code":"4",
    "gn:admin3_code":"36.0",
    "gn:admin4_code":"360017.0",
    "gn:asciiname":"Eklephat",
    "gn:country_code":"NP",
    "gn:dem":353,
    "gn:feature_class":"P",
    "gn:feature_code":"PPLL",
    "gn:name":"Eklephat",
    "gn:population":0,
    "gn:timezone":"Asia/Kathmandu",
    "iso:country":"NP",
    "wof:name":"Eklephat",
    "wof:placetype":"locality"
},
  "geometry": {"coordinates":[84.75447,27.86425],"type":"Point"}
}