{
  "type": "Feature",
  "properties": {
    "gn:admin1_code":"WR",
    "gn:admin2_code":"8",
    "gn:admin3_code":"51.0",
    "gn:admin4_code":"510015.0",
    "gn:asciiname":"Salyandanda",
    "gn:country_code":"NP",
    "gn:dem":1338,
    "gn:feature_class":"P",
    "gn:feature_code":"PPLL",
    "gn:name":"Salyandanda",
    "gn:population":0,
    "gn:timezone":"Asia/Kathmandu",
    "iso:country":"NP",
    "wof:name":"Salyandanda",
    "wof:placetype":"locality"
},
  "geometry": {"coordinates":[83.10153000000003,27.95082],"type":"Point"}
}