{
  "type": "Feature",
  "properties": {
    "gn:admin1_code":"WR",
    "gn:admin2_code":"8",
    "gn:admin3_code":"51.0",
    "gn:admin4_code":"510041.0",
    "gn:asciiname":"Pach Pokhari",
    "gn:country_code":"NP",
    "gn:dem":1475,
    "gn:feature_class":"P",
    "gn:feature_code":"PPLL",
    "gn:name":"Pach Pokhari",
    "gn:population":0,
    "gn:timezone":"Asia/Kathmandu",
    "iso:country":"NP",
    "wof:name":"Pach Pokhari",
    "wof:placetype":"locality"
},
  "geometry": {"coordinates":[83.10496999999999,27.87932],"type":"Point"}
}