{
  "type": "Feature",
  "properties": {
    "gn:admin1_code":"WR",
    "gn:admin2_code":"8",
    "gn:admin3_code":"49",
    "gn:admin4_code":"490059",
    "gn:asciiname":"Jaumune Phant",
    "gn:country_code":"NP",
    "gn:dem":262,
    "gn:feature_class":"P",
    "gn:feature_code":"PPLL",
    "gn:name":"Jaumune Phant",
    "gn:population":0,
    "gn:timezone":"Asia/Kathmandu",
    "iso:country":"NP",
    "wof:name":"Jaumune Phant",
    "wof:placetype":"locality"
},
  "geometry": {"coordinates":[83.26220000000001,27.74539],"type":"Point"}
}