{
  "type": "Feature",
  "properties": {
    "gn:admin1_code":"00",
    "gn:asciiname":"Sunjhoda Dadagau",
    "gn:country_code":"NP",
    "gn:dem":299,
    "gn:feature_class":"P",
    "gn:feature_code":"PPL",
    "gn:name":"Sunjho\u1e0d\u0101 \u1e0c\u0101\u0303\u1e0d\u0101g\u0101\u0169",
    "gn:population":0,
    "gn:timezone":"Asia/Kathmandu",
    "iso:country":"NP",
    "name:nep_x_preferred":[
        "Sunjho\u1e0d\u0101 \u1e0c\u0101\u0303\u1e0d\u0101g\u0101\u0169"
    ],
    "wof:name":"Sunjhoda Dadagau",
    "wof:placetype":"locality"
},
  "geometry": {"coordinates":[87.85585,26.68448],"type":"Point"}
}