{
  "type": "Feature",
  "properties": {
    "gn:admin1_code":"WR",
    "gn:admin2_code":"3",
    "gn:admin3_code":"45.0",
    "gn:admin4_code":"450027.0",
    "gn:asciiname":"Dhustung",
    "gn:country_code":"NP",
    "gn:dem":1334,
    "gn:feature_class":"P",
    "gn:feature_code":"PPLL",
    "gn:name":"Dhustung",
    "gn:population":0,
    "gn:timezone":"Asia/Kathmandu",
    "iso:country":"NP",
    "wof:name":"Dhustung",
    "wof:placetype":"locality"
},
  "geometry": {"coordinates":[83.444,28.21162],"type":"Point"}
}