{
  "type": "Feature",
  "properties": {
    "gn:admin1_code":"CR",
    "gn:admin2_code":"1",
    "gn:admin3_code":"28",
    "gn:admin4_code":"280001",
    "gn:asciiname":"Katunje",
    "gn:country_code":"NP",
    "gn:dem":801,
    "gn:feature_class":"P",
    "gn:feature_code":"PPLL",
    "gn:name":"Katunje",
    "gn:population":0,
    "gn:timezone":"Asia/Kathmandu",
    "iso:country":"NP",
    "wof:name":"Katunje",
    "wof:placetype":"locality"
},
  "geometry": {"coordinates":[85.24988,27.97172],"type":"Point"}
}