{
  "type": "Feature",
  "properties": {
    "gn:admin1_code":"CR",
    "gn:admin2_code":"1",
    "gn:admin3_code":"28",
    "gn:admin4_code":"280001",
    "gn:asciiname":"Katunje",
    "gn:country_code":"NP",
    "gn:dem":801,
    "gn:feature_class":"P",
    "gn:feature_code":"PPLL",
    "gn:name":"Katunje",
    "gn:population":0,
    "gn:timezone":"Asia/Kathmandu",
    "iso:country":"NP",
    "name:bih_x_preferred":[
        "\u0915\u091f\u0941\u091e\u094d\u091c\u0947"
    ],
    "name:ceb_x_preferred":[
        "Katunje"
    ],
    "name:fra_x_preferred":[
        "Katunje"
    ],
    "name:hin_x_preferred":[
        "\u0915\u091f\u0941\u0902\u091c\u0947"
    ],
    "name:mai_x_preferred":[
        "\u0915\u091f\u0941\u091e\u094d\u091c\u0947"
    ],
    "name:msa_x_preferred":[
        "Katunje"
    ],
    "name:nep_x_preferred":[
        "\u0915\u091f\u0941\u091e\u094d\u091c\u0947"
    ],
    "name:new_x_preferred":[
        "\u0915\u091f\u0941\u0928\u094d\u091c\u0947"
    ],
    "name:pol_x_preferred":[
        "Katunje"
    ],
    "wof:name":"Katunje",
    "wof:placetype":"locality"
},
  "geometry": {"coordinates":[85.24988,27.97172],"type":"Point"}
}