{
  "type": "Feature",
  "properties": {
    "gn:admin1_code":"CR",
    "gn:admin2_code":"1",
    "gn:admin3_code":"30.0",
    "gn:admin4_code":"300020.0",
    "gn:asciiname":"Handikholagaun",
    "gn:country_code":"NP",
    "gn:dem":694,
    "gn:feature_class":"P",
    "gn:feature_code":"PPLL",
    "gn:name":"Handikholagaun",
    "gn:population":0,
    "gn:timezone":"Asia/Kathmandu",
    "iso:country":"NP",
    "wof:name":"Handikholagaun",
    "wof:placetype":"locality"
},
  "geometry": {"coordinates":[84.98005000000001,27.81206],"type":"Point"}
}