{
  "type": "Feature",
  "properties": {
    "gn:admin1_code":"FR",
    "gn:admin2_code":"14",
    "gn:admin3_code":"69.0",
    "gn:admin4_code":"690069.0",
    "gn:asciiname":"Rigdisainkharka",
    "gn:country_code":"NP",
    "gn:dem":2486,
    "gn:feature_class":"P",
    "gn:feature_code":"PPLL",
    "gn:name":"Rigdisainkharka",
    "gn:population":0,
    "gn:timezone":"Asia/Kathmandu",
    "iso:country":"NP",
    "wof:name":"Rigdisainkharka",
    "wof:placetype":"locality"
},
  "geometry": {"coordinates":[81.38313000000002,29.28981],"type":"Point"}
}