{
  "type": "Feature",
  "properties": {
    "gn:admin1_code":"CR",
    "gn:admin2_code":"11",
    "gn:admin3_code":"34",
    "gn:admin4_code":"340071",
    "gn:asciiname":"Simarbari",
    "gn:country_code":"NP",
    "gn:dem":89,
    "gn:feature_class":"P",
    "gn:feature_code":"PPLL",
    "gn:name":"Simarbari",
    "gn:population":0,
    "gn:timezone":"Asia/Kathmandu",
    "iso:country":"NP",
    "wof:name":"Simarbari",
    "wof:placetype":"locality"
},
  "geometry": {"coordinates":[84.77229,27.0765],"type":"Point"}
}