{
  "type": "Feature",
  "properties": {
    "gn:admin1_code":"CR",
    "gn:admin2_code":"5",
    "gn:admin3_code":"21",
    "gn:admin4_code":"210028",
    "gn:asciiname":"Dase",
    "gn:country_code":"NP",
    "gn:dem":892,
    "gn:feature_class":"P",
    "gn:feature_code":"PPLL",
    "gn:name":"Dase",
    "gn:population":0,
    "gn:timezone":"Asia/Kathmandu",
    "iso:country":"NP",
    "name:ceb_x_preferred":[
        "Dase"
    ],
    "name:deu_x_preferred":[
        "Dase"
    ],
    "wof:name":"Dase",
    "wof:placetype":"locality"
},
  "geometry": {"coordinates":[85.82786,27.47295],"type":"Point"}
}