{
  "type": "Feature",
  "properties": {
    "gn:admin1_code":"WR",
    "gn:admin2_code":"3",
    "gn:admin3_code":"45.0",
    "gn:admin4_code":"450013.0",
    "gn:asciiname":"Subjagaun",
    "gn:country_code":"NP",
    "gn:dem":1579,
    "gn:feature_class":"P",
    "gn:feature_code":"PPLL",
    "gn:name":"Subjagaun",
    "gn:population":0,
    "gn:timezone":"Asia/Kathmandu",
    "iso:country":"NP",
    "wof:name":"Subjagaun",
    "wof:placetype":"locality"
},
  "geometry": {"coordinates":[83.13494,28.36899],"type":"Point"}
}