{
  "type": "Feature",
  "properties": {
    "gn:admin1_code":"CR",
    "gn:admin2_code":"11",
    "gn:admin3_code":"31",
    "gn:admin4_code":"310024",
    "gn:asciiname":"Barkiche",
    "gn:country_code":"NP",
    "gn:dem":1631,
    "gn:feature_class":"P",
    "gn:feature_code":"PPLL",
    "gn:name":"Barkiche",
    "gn:population":0,
    "gn:timezone":"Asia/Kathmandu",
    "iso:country":"NP",
    "wof:name":"Barkiche",
    "wof:placetype":"locality"
},
  "geometry": {"coordinates":[84.81541,27.61507000000001],"type":"Point"}
}