{
  "type": "Feature",
  "properties": {
    "gn:admin1_code":"FR",
    "gn:admin2_code":"14",
    "gn:admin3_code":"70.0",
    "gn:admin4_code":"700003.0",
    "gn:asciiname":"Tunkatte",
    "gn:country_code":"NP",
    "gn:dem":1545,
    "gn:feature_class":"P",
    "gn:feature_code":"PPLL",
    "gn:name":"Tunkatte",
    "gn:population":0,
    "gn:timezone":"Asia/Kathmandu",
    "iso:country":"NP",
    "wof:name":"Tunkatte",
    "wof:placetype":"locality"
},
  "geometry": {"coordinates":[80.76212,29.0416],"type":"Point"}
}