{
  "type": "Feature",
  "properties": {
    "gn:admin1_code":"ER",
    "gn:admin2_code":"7",
    "gn:admin3_code":"10.0",
    "gn:admin4_code":"100050.0",
    "gn:asciiname":"Bhanjyang",
    "gn:country_code":"NP",
    "gn:dem":1244,
    "gn:feature_class":"P",
    "gn:feature_code":"PPLL",
    "gn:name":"Bhanjyang",
    "gn:population":0,
    "gn:timezone":"Asia/Kathmandu",
    "iso:country":"NP",
    "wof:name":"Bhanjyang",
    "wof:placetype":"locality"
},
  "geometry": {"coordinates":[87.13864000000002,27.30911],"type":"Point"}
}