{
  "type": "Feature",
  "properties": {
    "gn:admin1_code":"CR",
    "gn:admin2_code":"1",
    "gn:admin3_code":"28",
    "gn:admin4_code":"280060",
    "gn:asciiname":"Kulkule",
    "gn:country_code":"NP",
    "gn:dem":1521,
    "gn:feature_class":"P",
    "gn:feature_code":"PPLL",
    "gn:name":"Kulkule",
    "gn:population":0,
    "gn:timezone":"Asia/Kathmandu",
    "iso:country":"NP",
    "wof:name":"Kulkule",
    "wof:placetype":"locality"
},
  "geometry": {"coordinates":[85.34913,27.90446],"type":"Point"}
}