{
  "type": "Feature",
  "properties": {
    "gn:admin1_code":"ER",
    "gn:admin2_code":"7",
    "gn:admin3_code":"5",
    "gn:admin4_code":"50041",
    "gn:asciiname":"Milanchok",
    "gn:country_code":"NP",
    "gn:dem":66,
    "gn:feature_class":"P",
    "gn:feature_code":"PPLL",
    "gn:name":"Milanchok",
    "gn:population":0,
    "gn:timezone":"Asia/Kathmandu",
    "iso:country":"NP",
    "wof:name":"Milanchok",
    "wof:placetype":"locality"
},
  "geometry": {"coordinates":[87.31871,26.40632],"type":"Point"}
}