{
  "type": "Feature",
  "properties": {
    "gn:admin1_code":"WR",
    "gn:admin2_code":"4",
    "gn:admin3_code":"36.0",
    "gn:admin4_code":"360017.0",
    "gn:asciiname":"Kaudi",
    "gn:country_code":"NP",
    "gn:dem":736,
    "gn:feature_class":"P",
    "gn:feature_code":"PPLL",
    "gn:name":"Kaudi",
    "gn:population":0,
    "gn:timezone":"Asia/Kathmandu",
    "iso:country":"NP",
    "wof:name":"Kaudi",
    "wof:placetype":"locality"
},
  "geometry": {"coordinates":[84.71134000000001,27.89056],"type":"Point"}
}