{
  "type": "Feature",
  "properties": {
    "gn:admin1_code":"CR",
    "gn:admin2_code":"1",
    "gn:admin3_code":"28",
    "gn:admin4_code":"280036.0",
    "gn:asciiname":"Maharthum",
    "gn:country_code":"NP",
    "gn:dem":1187,
    "gn:feature_class":"P",
    "gn:feature_code":"PPLL",
    "gn:name":"Maharthum",
    "gn:population":0,
    "gn:timezone":"Asia/Kathmandu",
    "iso:country":"NP",
    "wof:name":"Maharthum",
    "wof:placetype":"locality"
},
  "geometry": {"coordinates":[85.28811999999998,27.95026],"type":"Point"}
}