{
  "type": "Feature",
  "properties": {
    "gn:admin1_code":"WR",
    "gn:admin2_code":"8",
    "gn:admin3_code":"49",
    "gn:admin4_code":"490069",
    "gn:asciiname":"Mahajidiya",
    "gn:country_code":"NP",
    "gn:dem":102,
    "gn:feature_class":"P",
    "gn:feature_code":"PPLL",
    "gn:name":"Mahajidiya",
    "gn:population":0,
    "gn:timezone":"Asia/Kathmandu",
    "iso:country":"NP",
    "wof:name":"Mahajidiya",
    "wof:placetype":"locality"
},
  "geometry": {"coordinates":[83.25440999999999,27.4887],"type":"Point"}
}