{
  "type": "Feature",
  "properties": {
    "gn:admin1_code":"MR",
    "gn:admin2_code":"2",
    "gn:admin3_code":"61.0",
    "gn:admin4_code":"610001.0",
    "gn:asciiname":"Thadi Bhauta",
    "gn:country_code":"NP",
    "gn:dem":2367,
    "gn:feature_class":"P",
    "gn:feature_code":"PPLL",
    "gn:name":"Thadi Bhauta",
    "gn:population":0,
    "gn:timezone":"Asia/Kathmandu",
    "iso:country":"NP",
    "wof:name":"Thadi Bhauta",
    "wof:placetype":"locality"
},
  "geometry": {"coordinates":[82.09033000000002,28.86108],"type":"Point"}
}