{
  "type": "Feature",
  "properties": {
    "gn:admin1_code":"WR",
    "gn:admin2_code":"4",
    "gn:admin3_code":"36.0",
    "gn:admin4_code":"360063.0",
    "gn:asciiname":"Baniyagaun",
    "gn:country_code":"NP",
    "gn:dem":1203,
    "gn:feature_class":"P",
    "gn:feature_code":"PPLL",
    "gn:name":"Baniyagaun",
    "gn:population":0,
    "gn:timezone":"Asia/Kathmandu",
    "iso:country":"NP",
    "wof:name":"Baniyagaun",
    "wof:placetype":"locality"
},
  "geometry": {"coordinates":[84.68160999999998,28.02199],"type":"Point"}
}