{
  "type": "Feature",
  "properties": {
    "gn:admin1_code":"ER",
    "gn:admin2_code":"10",
    "gn:admin3_code":"3.0",
    "gn:admin4_code":"30019.0",
    "gn:asciiname":"Megma",
    "gn:country_code":"NP",
    "gn:dem":2881,
    "gn:feature_class":"P",
    "gn:feature_code":"PPLL",
    "gn:name":"Megma",
    "gn:population":0,
    "gn:timezone":"Asia/Kathmandu",
    "iso:country":"NP",
    "wof:name":"Megma",
    "wof:placetype":"locality"
},
  "geometry": {"coordinates":[88.08349,27.0259],"type":"Point"}
}