{
  "type": "Feature",
  "properties": {
    "gn:admin1_code":"CR",
    "gn:admin2_code":"5",
    "gn:admin3_code":"22.0",
    "gn:admin4_code":"220014.0",
    "gn:asciiname":"Khadgaun",
    "gn:country_code":"NP",
    "gn:dem":1807,
    "gn:feature_class":"P",
    "gn:feature_code":"PPLL",
    "gn:name":"Khadgaun",
    "gn:population":0,
    "gn:timezone":"Asia/Kathmandu",
    "iso:country":"NP",
    "wof:name":"Khadgaun",
    "wof:placetype":"locality"
},
  "geometry": {"coordinates":[86.03222,27.51332],"type":"Point"}
}