{
  "type": "Feature",
  "properties": {
    "gn:admin1_code":"FR",
    "gn:admin2_code":"14",
    "gn:admin3_code":"70.0",
    "gn:admin4_code":"700018.0",
    "gn:asciiname":"Selane",
    "gn:country_code":"NP",
    "gn:dem":890,
    "gn:feature_class":"P",
    "gn:feature_code":"PPLL",
    "gn:name":"Selane",
    "gn:population":0,
    "gn:timezone":"Asia/Kathmandu",
    "iso:country":"NP",
    "wof:name":"Selane",
    "wof:placetype":"locality"
},
  "geometry": {"coordinates":[81.05243,29.247],"type":"Point"}
}