{
  "type": "Feature",
  "properties": {
    "gn:admin1_code":"ER",
    "gn:admin2_code":"7",
    "gn:admin3_code":"5",
    "gn:admin4_code":"50012",
    "gn:asciiname":"Bhogteni",
    "gn:country_code":"NP",
    "gn:dem":911,
    "gn:feature_class":"P",
    "gn:feature_code":"PPLL",
    "gn:name":"Bhogteni",
    "gn:population":0,
    "gn:timezone":"Asia/Kathmandu",
    "iso:country":"NP",
    "wof:name":"Bhogteni",
    "wof:placetype":"locality"
},
  "geometry": {"coordinates":[87.43284,26.79629000000001],"type":"Point"}
}