{
  "type": "Feature",
  "properties": {
    "gn:admin1_code":"FR",
    "gn:admin2_code":"9",
    "gn:admin3_code":"74",
    "gn:admin4_code":"740006",
    "gn:asciiname":"Magaraun",
    "gn:country_code":"NP",
    "gn:dem":1790,
    "gn:feature_class":"P",
    "gn:feature_code":"PPLL",
    "gn:name":"Magaraun",
    "gn:population":0,
    "gn:timezone":"Asia/Kathmandu",
    "iso:country":"NP",
    "wof:name":"Magaraun",
    "wof:placetype":"locality"
},
  "geometry": {"coordinates":[80.63405,29.57489],"type":"Point"}
}