{
  "type": "Feature",
  "properties": {
    "gn:admin1_code":"MR",
    "gn:admin2_code":"12",
    "gn:admin3_code":"52",
    "gn:admin4_code":"520046",
    "gn:asciiname":"Kimichaur",
    "gn:country_code":"NP",
    "gn:dem":929,
    "gn:feature_class":"P",
    "gn:feature_code":"PPLL",
    "gn:name":"Kimichaur",
    "gn:population":0,
    "gn:timezone":"Asia/Kathmandu",
    "iso:country":"NP",
    "wof:name":"Kimichaur",
    "wof:placetype":"locality"
},
  "geometry": {"coordinates":[82.77208,27.99777000000001],"type":"Point"}
}