{
  "type": "Feature",
  "properties": {
    "gn:admin1_code":"WR",
    "gn:admin2_code":"4.0",
    "gn:admin3_code":"39.0",
    "gn:admin4_code":"390027.0",
    "gn:asciiname":"Langkung",
    "gn:country_code":"NP",
    "gn:dem":999,
    "gn:feature_class":"P",
    "gn:feature_code":"PPLL",
    "gn:name":"Langkung",
    "gn:population":0,
    "gn:timezone":"Asia/Kathmandu",
    "iso:country":"NP",
    "wof:name":"Langkung",
    "wof:placetype":"locality"
},
  "geometry": {"coordinates":[83.78476999999999,27.94194],"type":"Point"}
}