{
  "type": "Feature",
  "properties": {
    "gn:admin1_code":"ER",
    "gn:admin2_code":"13",
    "gn:admin3_code":"11",
    "gn:admin4_code":"110001",
    "gn:asciiname":"Phapare",
    "gn:country_code":"NP",
    "gn:dem":1701,
    "gn:feature_class":"P",
    "gn:feature_code":"PPLL",
    "gn:name":"Phapare",
    "gn:population":0,
    "gn:timezone":"Asia/Kathmandu",
    "iso:country":"NP",
    "wof:name":"Phapare",
    "wof:placetype":"locality"
},
  "geometry": {"coordinates":[86.714,27.51878],"type":"Point"}
}