{
  "type": "Feature",
  "properties": {
    "gn:admin1_code":"WR",
    "gn:admin2_code":"4",
    "gn:admin3_code":"40.0",
    "gn:admin4_code":"400044.0",
    "gn:asciiname":"Sirkutan",
    "gn:country_code":"NP",
    "gn:dem":902,
    "gn:feature_class":"P",
    "gn:feature_code":"PPLL",
    "gn:name":"Sirkutan",
    "gn:population":0,
    "gn:timezone":"Asia/Kathmandu",
    "iso:country":"NP",
    "wof:name":"Sirkutan",
    "wof:placetype":"locality"
},
  "geometry": {"coordinates":[84.18538000000002,28.14867000000001],"type":"Point"}
}