{
  "type": "Feature",
  "properties": {
    "gn:admin1_code":"WR",
    "gn:admin2_code":"4",
    "gn:admin3_code":"36.0",
    "gn:admin4_code":"360008.0",
    "gn:asciiname":"Tiwari Diha",
    "gn:country_code":"NP",
    "gn:dem":487,
    "gn:feature_class":"P",
    "gn:feature_code":"PPLL",
    "gn:name":"Tiwari Diha",
    "gn:population":0,
    "gn:timezone":"Asia/Kathmandu",
    "iso:country":"NP",
    "wof:name":"Tiwari Diha",
    "wof:placetype":"locality"
},
  "geometry": {"coordinates":[84.54395,27.97],"type":"Point"}
}