{
  "type": "Feature",
  "properties": {
    "gn:admin1_code":"MR",
    "gn:admin2_code":"2.0",
    "gn:admin3_code":"59.0",
    "gn:admin4_code":"590008.0",
    "gn:asciiname":"Ganesh Chok",
    "gn:country_code":"NP",
    "gn:dem":711,
    "gn:feature_class":"P",
    "gn:feature_code":"PPLL",
    "gn:name":"Ganesh Chok",
    "gn:population":0,
    "gn:timezone":"Asia/Kathmandu",
    "iso:country":"NP",
    "wof:name":"Ganesh Chok",
    "wof:placetype":"locality"
},
  "geometry": {"coordinates":[81.61578,28.60266],"type":"Point"}
}