{
  "type": "Feature",
  "properties": {
    "gn:admin1_code":"MR",
    "gn:admin2_code":"12",
    "gn:admin3_code":"54",
    "gn:admin4_code":"540001",
    "gn:asciiname":"Tallo Magma",
    "gn:country_code":"NP",
    "gn:dem":1440,
    "gn:feature_class":"P",
    "gn:feature_code":"PPLL",
    "gn:name":"Tallo Magma",
    "gn:population":0,
    "gn:timezone":"Asia/Kathmandu",
    "iso:country":"NP",
    "wof:name":"Tallo Magma",
    "wof:placetype":"locality"
},
  "geometry": {"coordinates":[82.45328000000001,28.70307],"type":"Point"}
}