{
  "type": "Feature",
  "properties": {
    "gn:admin1_code":"WR",
    "gn:admin2_code":"4",
    "gn:admin3_code":"36.0",
    "gn:admin4_code":"360035.0",
    "gn:asciiname":"Khinpu",
    "gn:country_code":"NP",
    "gn:dem":1837,
    "gn:feature_class":"P",
    "gn:feature_code":"PPLL",
    "gn:name":"Khinpu",
    "gn:population":0,
    "gn:timezone":"Asia/Kathmandu",
    "iso:country":"NP",
    "wof:name":"Khinpu",
    "wof:placetype":"locality"
},
  "geometry": {"coordinates":[84.64959,28.21881],"type":"Point"}
}