{
  "type": "Feature",
  "properties": {
    "gn:admin1_code":"ER",
    "gn:admin2_code":"10",
    "gn:admin3_code":"3.0",
    "gn:admin4_code":"30004.0",
    "gn:asciiname":"Baksila",
    "gn:country_code":"NP",
    "gn:dem":1647,
    "gn:feature_class":"P",
    "gn:feature_code":"PPLL",
    "gn:name":"Baksila",
    "gn:population":0,
    "gn:timezone":"Asia/Kathmandu",
    "iso:country":"NP",
    "name:ceb_x_preferred":[
        "Baksila"
    ],
    "name:mai_x_preferred":[
        "\u092c\u093e\u0915\u094d\u0938\u093f\u0932\u093e"
    ],
    "name:msa_x_preferred":[
        "Baksila"
    ],
    "name:new_x_preferred":[
        "\u092c\u0915\u094d\u0938\u093f\u0932\u093e"
    ],
    "name:pol_x_preferred":[
        "Baksila"
    ],
    "wof:name":"Baksila",
    "wof:placetype":"locality"
},
  "geometry": {"coordinates":[87.84239000000002,27.00544],"type":"Point"}
}