{
  "type": "Feature",
  "properties": {
    "gn:admin1_code":"WR",
    "gn:admin2_code":"8",
    "gn:admin3_code":"48",
    "gn:admin4_code":"480048",
    "gn:asciiname":"Bhutaha",
    "gn:country_code":"NP",
    "gn:dem":124,
    "gn:feature_class":"P",
    "gn:feature_code":"PPLL",
    "gn:name":"Bhutaha",
    "gn:population":0,
    "gn:timezone":"Asia/Kathmandu",
    "iso:country":"NP",
    "wof:name":"Bhutaha",
    "wof:placetype":"locality"
},
  "geometry": {"coordinates":[83.75218000000002,27.55945],"type":"Point"}
}