{
  "type": "Feature",
  "properties": {
    "gn:admin1_code":"WR",
    "gn:admin2_code":"4.0",
    "gn:admin3_code":"39.0",
    "gn:admin4_code":"390056.0",
    "gn:asciiname":"Bharkot",
    "gn:country_code":"NP",
    "gn:dem":1137,
    "gn:feature_class":"P",
    "gn:feature_code":"PPLL",
    "gn:name":"Bharkot",
    "gn:population":0,
    "gn:timezone":"Asia/Kathmandu",
    "iso:country":"NP",
    "wof:name":"Bharkot",
    "wof:placetype":"locality"
},
  "geometry": {"coordinates":[83.94835999999999,28.10242],"type":"Point"}
}