{
  "type": "Feature",
  "properties": {
    "gn:admin1_code":"ER",
    "gn:admin2_code":"7",
    "gn:admin3_code":"10.0",
    "gn:admin4_code":"100040.0",
    "gn:asciiname":"Kuwapani",
    "gn:country_code":"NP",
    "gn:dem":1419,
    "gn:feature_class":"P",
    "gn:feature_code":"PPLL",
    "gn:name":"Kuwapani",
    "gn:population":0,
    "gn:timezone":"Asia/Kathmandu",
    "iso:country":"NP",
    "wof:name":"Kuwapani",
    "wof:placetype":"locality"
},
  "geometry": {"coordinates":[87.04576999999998,27.08492],"type":"Point"}
}