{
  "type": "Feature",
  "properties": {
    "gn:admin1_code":"CR",
    "gn:admin2_code":"5",
    "gn:admin3_code":"17.0",
    "gn:admin4_code":"170062.0",
    "gn:asciiname":"Kumharauda",
    "gn:country_code":"NP",
    "gn:dem":88,
    "gn:feature_class":"P",
    "gn:feature_code":"PPLL",
    "gn:name":"Kumharauda",
    "gn:population":0,
    "gn:timezone":"Asia/Kathmandu",
    "iso:country":"NP",
    "wof:name":"Kumharauda",
    "wof:placetype":"locality"
},
  "geometry": {"coordinates":[85.94280999999999,26.77889],"type":"Point"}
}