{
  "type": "Feature",
  "properties": {
    "gn:admin1_code":"CR",
    "gn:admin2_code":"1",
    "gn:admin3_code":"27.0",
    "gn:admin4_code":"270031.0",
    "gn:asciiname":"Paknajol",
    "gn:country_code":"NP",
    "gn:dem":1320,
    "gn:feature_class":"P",
    "gn:feature_code":"PPLL",
    "gn:name":"Paknajol",
    "gn:population":0,
    "gn:timezone":"Asia/Kathmandu",
    "iso:country":"NP",
    "wof:name":"Paknajol",
    "wof:placetype":"locality"
},
  "geometry": {"coordinates":[85.31138,27.71768],"type":"Point"}
}