{
  "type": "Feature",
  "properties": {
    "iso:country":"NP",
    "name:deu_x_preferred":[
        "Shikha"
    ],
    "name:eng_x_preferred":[
        "Shikha"
    ],
    "name:fre_x_preferred":[
        "Shikha"
    ],
    "name:ger_x_preferred":[
        "Shikha"
    ],
    "name:mal_x_preferred":[
        "\u0d15\u0d41\u0d1f\u0d41\u0d2e"
    ],
    "name:may_x_preferred":[
        "Shikha"
    ],
    "name:nep_x_preferred":[
        "\u0936\u093f\u0916\u093e"
    ],
    "name:new_x_preferred":[
        "\u0936\u093f\u0916\u093e"
    ],
    "name:pol_x_preferred":[
        "Shikha"
    ],
    "name:rus_x_preferred":[
        "\u0428\u0438\u043a\u0445\u0430"
    ],
    "qs:gn_country":"NP",
    "qs:gn_fcode":"PPL",
    "qs:gn_pop":0,
    "qs:name":"Sikha",
    "qs:name_adm0":"Nepal",
    "qs:name_adm1":"Pashchimanchal",
    "qs:photos":179,
    "qs:photos_1k":36,
    "qs:photos_9k":1,
    "qs:photos_9r":4,
    "qs:photos_all":179,
    "qs:photos_sr":4,
    "qs:placetype":"Town",
    "qs:pop_sr":"0",
    "qs:woe_adm0":23424911,
    "wd:wordcount":2023,
    "wof:name":"Sikha",
    "wof:placetype":"locality"
},
  "geometry": {"coordinates":[83.67179,28.4466],"type":"Point"}
}