{
  "type": "Feature",
  "properties": {
    "gn:admin1_code":"ER",
    "gn:admin2_code":"13.0",
    "gn:admin3_code":"14.0",
    "gn:admin4_code":"140037.0",
    "gn:asciiname":"Nakrepa",
    "gn:country_code":"NP",
    "gn:dem":1116,
    "gn:feature_class":"P",
    "gn:feature_code":"PPLL",
    "gn:name":"Nakrepa",
    "gn:population":0,
    "gn:timezone":"Asia/Kathmandu",
    "iso:country":"NP",
    "wof:name":"Nakrepa",
    "wof:placetype":"locality"
},
  "geometry": {"coordinates":[86.65666,27.10127],"type":"Point"}
}