{
  "type": "Feature",
  "properties": {
    "gn:admin1_code":"FR",
    "gn:admin2_code":"9",
    "gn:admin3_code":"73.0",
    "gn:admin4_code":"730020.0",
    "gn:asciiname":"Rola",
    "gn:country_code":"NP",
    "gn:dem":1404,
    "gn:feature_class":"P",
    "gn:feature_code":"PPLL",
    "gn:name":"Rola",
    "gn:population":0,
    "gn:timezone":"Asia/Kathmandu",
    "iso:country":"NP",
    "name:deu_x_preferred":[
        "Rola"
    ],
    "name:ita_x_preferred":[
        "Rola"
    ],
    "name:pol_x_preferred":[
        "Rola"
    ],
    "name:por_x_preferred":[
        "Rola"
    ],
    "name:slk_x_preferred":[
        "Rola"
    ],
    "name:srp_x_preferred":[
        "\u0420\u043e\u043b\u0430"
    ],
    "name:ukr_x_preferred":[
        "\u0420\u043e\u043b\u0430"
    ],
    "wof:name":"Rola",
    "wof:placetype":"locality"
},
  "geometry": {"coordinates":[80.56,29.34162],"type":"Point"}
}