{
  "type": "Feature",
  "properties": {
    "gn:admin1_code":"FR",
    "gn:admin2_code":"9",
    "gn:admin3_code":"74",
    "gn:admin4_code":"740013",
    "gn:asciiname":"Tatekhali",
    "gn:country_code":"NP",
    "gn:dem":1027,
    "gn:feature_class":"P",
    "gn:feature_code":"PPLL",
    "gn:name":"Tatekhali",
    "gn:population":0,
    "gn:timezone":"Asia/Kathmandu",
    "iso:country":"NP",
    "wof:name":"Tatekhali",
    "wof:placetype":"locality"
},
  "geometry": {"coordinates":[80.57106,29.63591],"type":"Point"}
}