{
  "type": "Feature",
  "properties": {
    "gn:admin1_code":"FR",
    "gn:admin2_code":"14",
    "gn:admin3_code":"69",
    "gn:admin4_code":"690036",
    "gn:asciiname":"Serigaun",
    "gn:country_code":"NP",
    "gn:dem":1041,
    "gn:feature_class":"P",
    "gn:feature_code":"PPLL",
    "gn:name":"Serigaun",
    "gn:population":0,
    "gn:timezone":"Asia/Kathmandu",
    "iso:country":"NP",
    "wof:name":"Serigaun",
    "wof:placetype":"locality"
},
  "geometry": {"coordinates":[81.49171,29.1061],"type":"Point"}
}