{
  "type": "Feature",
  "properties": {
    "gn:admin1_code":"MR",
    "gn:admin2_code":"12",
    "gn:admin3_code":"56.0",
    "gn:admin4_code":"560006.0",
    "gn:asciiname":"Thakalchaur",
    "gn:country_code":"NP",
    "gn:dem":476,
    "gn:feature_class":"P",
    "gn:feature_code":"PPLL",
    "gn:name":"Thakalchaur",
    "gn:population":0,
    "gn:timezone":"Asia/Kathmandu",
    "iso:country":"NP",
    "wof:name":"Thakalchaur",
    "wof:placetype":"locality"
},
  "geometry": {"coordinates":[82.43729999999999,27.93815],"type":"Point"}
}