{
  "type": "Feature",
  "properties": {
    "gn:admin1_code":"ER",
    "gn:admin2_code":"10.0",
    "gn:admin3_code":"1.0",
    "gn:admin4_code":"10015.0",
    "gn:asciiname":"Subbagaun",
    "gn:country_code":"NP",
    "gn:dem":1511,
    "gn:feature_class":"P",
    "gn:feature_code":"PPLL",
    "gn:name":"Subbagaun",
    "gn:population":0,
    "gn:timezone":"Asia/Kathmandu",
    "iso:country":"NP",
    "name:msa_x_preferred":[
        "Subbagaun"
    ],
    "wof:name":"Subbagaun",
    "wof:placetype":"locality"
},
  "geometry": {"coordinates":[87.66798,27.41222],"type":"Point"}
}