{
  "type": "Feature",
  "properties": {
    "gn:admin1_code":"CR",
    "gn:admin2_code":"1",
    "gn:admin3_code":"23",
    "gn:admin4_code":"230034",
    "gn:asciiname":"Khadkatol",
    "gn:country_code":"NP",
    "gn:dem":1232,
    "gn:feature_class":"P",
    "gn:feature_code":"PPLL",
    "gn:name":"Khadkatol",
    "gn:population":0,
    "gn:timezone":"Asia/Kathmandu",
    "iso:country":"NP",
    "wof:name":"Khadkatol",
    "wof:placetype":"locality"
},
  "geometry": {"coordinates":[85.59385,27.83676],"type":"Point"}
}