{
  "type": "Feature",
  "properties": {
    "gn:admin1_code":"WR",
    "gn:admin2_code":"3",
    "gn:admin3_code":"45",
    "gn:admin4_code":"450056",
    "gn:asciiname":"Mansung",
    "gn:country_code":"NP",
    "gn:dem":1448,
    "gn:feature_class":"P",
    "gn:feature_code":"PPLL",
    "gn:name":"Mansung",
    "gn:population":0,
    "gn:timezone":"Asia/Kathmandu",
    "iso:country":"NP",
    "wof:name":"Mansung",
    "wof:placetype":"locality"
},
  "geometry": {"coordinates":[83.19394,28.37962000000001],"type":"Point"}
}