{
  "type": "Feature",
  "properties": {
    "gn:admin1_code":"ER",
    "gn:admin2_code":"10",
    "gn:admin3_code":"3.0",
    "gn:admin4_code":"30018.0",
    "gn:asciiname":"Subedargaun",
    "gn:country_code":"NP",
    "gn:dem":1161,
    "gn:feature_class":"P",
    "gn:feature_code":"PPLL",
    "gn:name":"Subedargaun",
    "gn:population":0,
    "gn:timezone":"Asia/Kathmandu",
    "iso:country":"NP",
    "wof:name":"Subedargaun",
    "wof:placetype":"locality"
},
  "geometry": {"coordinates":[87.80846,26.86439],"type":"Point"}
}