{
  "type": "Feature",
  "properties": {
    "gn:admin1_code":"MR",
    "gn:admin2_code":"2.0",
    "gn:admin3_code":"59.0",
    "gn:admin4_code":"590027.0",
    "gn:asciiname":"Asantara",
    "gn:country_code":"NP",
    "gn:dem":1025,
    "gn:feature_class":"P",
    "gn:feature_code":"PPLL",
    "gn:name":"Asantara",
    "gn:population":0,
    "gn:timezone":"Asia/Kathmandu",
    "iso:country":"NP",
    "wof:name":"Asantara",
    "wof:placetype":"locality"
},
  "geometry": {"coordinates":[81.91455999999999,28.52808],"type":"Point"}
}