{
  "type": "Feature",
  "properties": {
    "gn:admin1_code":"FR",
    "gn:admin2_code":"9",
    "gn:admin3_code":"73.0",
    "gn:admin4_code":"730016.0",
    "gn:asciiname":"Katauji",
    "gn:country_code":"NP",
    "gn:dem":1486,
    "gn:feature_class":"P",
    "gn:feature_code":"PPLL",
    "gn:name":"Katauji",
    "gn:population":0,
    "gn:timezone":"Asia/Kathmandu",
    "iso:country":"NP",
    "wof:name":"Katauji",
    "wof:placetype":"locality"
},
  "geometry": {"coordinates":[80.66818000000001,29.3524],"type":"Point"}
}