{
  "type": "Feature",
  "properties": {
    "gn:admin1_code":"ER",
    "gn:admin2_code":"7",
    "gn:admin3_code":"9",
    "gn:admin4_code":"90017.0",
    "gn:asciiname":"Baruntse",
    "gn:country_code":"NP",
    "gn:dem":6770,
    "gn:feature_class":"P",
    "gn:feature_code":"PPLL",
    "gn:name":"Baruntse",
    "gn:population":0,
    "gn:timezone":"Asia/Kathmandu",
    "iso:country":"NP",
    "name:ces_x_preferred":[
        "Baruntse"
    ],
    "name:dan_x_preferred":[
        "Baruntse"
    ],
    "name:deu_x_preferred":[
        "Baruntse"
    ],
    "name:est_x_preferred":[
        "Baruntse"
    ],
    "name:fas_x_preferred":[
        "\u0628\u0627\u0631\u0648\u0646\u062a\u0633\u0647"
    ],
    "name:fra_x_preferred":[
        "Baruntse"
    ],
    "name:hin_x_preferred":[
        "\u092c\u0930\u0942\u0923\u0924\u094d\u0938\u0947"
    ],
    "name:ita_x_preferred":[
        "Baruntse"
    ],
    "name:msa_x_preferred":[
        "Gunung Baruntse"
    ],
    "name:nld_x_preferred":[
        "Baruntse"
    ],
    "name:pnb_x_preferred":[
        "\u0628\u0627\u0631\u0646\u0679\u0633\u06cc"
    ],
    "name:pol_x_preferred":[
        "Baruntse"
    ],
    "name:swe_x_preferred":[
        "Baruntse"
    ],
    "name:tam_x_preferred":[
        "\u0baa\u0bbe\u0bb0\u0bc1\u0ba9\u0bcd\u0b9f\u0bbf\u0bb8\u0bcd"
    ],
    "name:ukr_x_preferred":[
        "\u0411\u0430\u0440\u0443\u043d\u0446\u0437\u0435"
    ],
    "wof:name":"Baruntse",
    "wof:placetype":"locality"
},
  "geometry": {"coordinates":[86.98268,27.87316],"type":"Point"}
}