{
  "type": "Feature",
  "properties": {
    "gn:admin1_code":"ER",
    "gn:admin2_code":"7",
    "gn:admin3_code":"9",
    "gn:admin4_code":"90017.0",
    "gn:asciiname":"Baruntse",
    "gn:country_code":"NP",
    "gn:dem":6770,
    "gn:feature_class":"P",
    "gn:feature_code":"PPLL",
    "gn:name":"Baruntse",
    "gn:population":0,
    "gn:timezone":"Asia/Kathmandu",
    "iso:country":"NP",
    "wof:name":"Baruntse",
    "wof:placetype":"locality"
},
  "geometry": {"coordinates":[86.98268,27.87316],"type":"Point"}
}