{
  "type": "Feature",
  "properties": {
    "gn:admin1_code":"CR",
    "gn:admin2_code":"5",
    "gn:admin3_code":"22.0",
    "gn:admin4_code":"220005.0",
    "gn:asciiname":"Ekrate",
    "gn:country_code":"NP",
    "gn:dem":2063,
    "gn:feature_class":"P",
    "gn:feature_code":"PPLL",
    "gn:name":"Ekrate",
    "gn:population":0,
    "gn:timezone":"Asia/Kathmandu",
    "iso:country":"NP",
    "wof:name":"Ekrate",
    "wof:placetype":"locality"
},
  "geometry": {"coordinates":[86.11905,27.5792],"type":"Point"}
}