{
  "type": "Feature",
  "properties": {
    "gn:admin1_code":"00",
    "gn:asciiname":"Nagau",
    "gn:country_code":"NP",
    "gn:dem":4197,
    "gn:feature_class":"P",
    "gn:feature_code":"PPL",
    "gn:name":"N\u0101g\u0101\u0169",
    "gn:population":0,
    "gn:timezone":"Asia/Kathmandu",
    "iso:country":"NP",
    "name:und_x_variant":[
        "N\u0101g\u0101\u0169",
        "N\u0101ngaon",
        "N\u0101g\u0101un"
    ],
    "wof:name":"Nagau",
    "wof:placetype":"locality"
},
  "geometry": {"coordinates":[86.42716,27.88143],"type":"Point"}
}