{
  "type": "Feature",
  "properties": {
    "gn:admin1_code":"WR",
    "gn:admin2_code":"3",
    "gn:admin3_code":"45.0",
    "gn:admin4_code":"450014.0",
    "gn:asciiname":"Tigrapani",
    "gn:country_code":"NP",
    "gn:dem":2299,
    "gn:feature_class":"P",
    "gn:feature_code":"PPLL",
    "gn:name":"Tigrapani",
    "gn:population":0,
    "gn:timezone":"Asia/Kathmandu",
    "iso:country":"NP",
    "wof:name":"Tigrapani",
    "wof:placetype":"locality"
},
  "geometry": {"coordinates":[82.95808000000002,28.44339],"type":"Point"}
}