{
  "type": "Feature",
  "properties": {
    "gn:admin1_code":"MR",
    "gn:admin2_code":"6",
    "gn:admin3_code":"63.0",
    "gn:admin4_code":"630012.0",
    "gn:asciiname":"Hanku",
    "gn:country_code":"NP",
    "gn:dem":2282,
    "gn:feature_class":"P",
    "gn:feature_code":"PPLL",
    "gn:name":"Hanku",
    "gn:population":0,
    "gn:timezone":"Asia/Kathmandu",
    "iso:country":"NP",
    "wof:name":"Hanku",
    "wof:placetype":"locality"
},
  "geometry": {"coordinates":[82.11173000000002,29.24041],"type":"Point"}
}