{
  "type": "Feature",
  "properties": {
    "gn:admin1_code":"ER",
    "gn:admin2_code":"7",
    "gn:admin3_code":"7.0",
    "gn:admin4_code":"70016.0",
    "gn:asciiname":"Phakiswa Ksetritol",
    "gn:country_code":"NP",
    "gn:dem":1469,
    "gn:feature_class":"P",
    "gn:feature_code":"PPLL",
    "gn:name":"Phakiswa Ksetritol",
    "gn:population":0,
    "gn:timezone":"Asia/Kathmandu",
    "iso:country":"NP",
    "wof:name":"Phakiswa Ksetritol",
    "wof:placetype":"locality"
},
  "geometry": {"coordinates":[87.35934,26.90087],"type":"Point"}
}