{
  "type": "Feature",
  "properties": {
    "gn:admin1_code":"00",
    "gn:asciiname":"Salleri Karkigau",
    "gn:country_code":"NP",
    "gn:dem":1787,
    "gn:feature_class":"P",
    "gn:feature_code":"PPL",
    "gn:name":"Salleri\u0307\u0304 K\u0101rki\u0307\u0304g\u0101\u0169",
    "gn:population":0,
    "gn:timezone":"Asia/Kathmandu",
    "iso:country":"NP",
    "name:nep_x_preferred":[
        "Salleri\u0307\u0304 K\u0101rki\u0307\u0304g\u0101\u0169"
    ],
    "name:nep_x_variant":[
        "Saller\u012b K\u0101rk\u012bg\u0101un"
    ],
    "wof:name":"Salleri Karkigau",
    "wof:placetype":"locality"
},
  "geometry": {"coordinates":[85.99944000000001,27.64907],"type":"Point"}
}