{
  "type": "Feature",
  "properties": {
    "gn:admin1_code":"MR",
    "gn:admin2_code":"12",
    "gn:admin3_code":"54",
    "gn:admin4_code":"540017",
    "gn:asciiname":"Bhaldebang",
    "gn:country_code":"NP",
    "gn:dem":2016,
    "gn:feature_class":"P",
    "gn:feature_code":"PPLL",
    "gn:name":"Bhaldebang",
    "gn:population":0,
    "gn:timezone":"Asia/Kathmandu",
    "iso:country":"NP",
    "wof:name":"Bhaldebang",
    "wof:placetype":"locality"
},
  "geometry": {"coordinates":[82.66829,28.60611],"type":"Point"}
}