{
  "type": "Feature",
  "properties": {
    "gn:admin1_code":"CR",
    "gn:admin2_code":"1",
    "gn:admin3_code":"27.0",
    "gn:admin4_code":"270051.0",
    "gn:asciiname":"Ikhapokhari",
    "gn:country_code":"NP",
    "gn:dem":1496,
    "gn:feature_class":"P",
    "gn:feature_code":"PPLL",
    "gn:name":"Ikhapokhari",
    "gn:population":0,
    "gn:timezone":"Asia/Kathmandu",
    "iso:country":"NP",
    "wof:name":"Ikhapokhari",
    "wof:placetype":"locality"
},
  "geometry": {"coordinates":[85.27067,27.61394],"type":"Point"}
}