{
  "type": "Feature",
  "properties": {
    "gn:admin1_code":"WR",
    "gn:admin2_code":"4.0",
    "gn:admin3_code":"39.0",
    "gn:admin4_code":"390033.0",
    "gn:asciiname":"Mathillo Bajhadi",
    "gn:country_code":"NP",
    "gn:dem":695,
    "gn:feature_class":"P",
    "gn:feature_code":"PPLL",
    "gn:name":"Mathillo Bajhadi",
    "gn:population":0,
    "gn:timezone":"Asia/Kathmandu",
    "iso:country":"NP",
    "wof:name":"Mathillo Bajhadi",
    "wof:placetype":"locality"
},
  "geometry": {"coordinates":[83.6549,27.91561],"type":"Point"}
}