{
  "type": "Feature",
  "properties": {
    "gn:admin1_code":"MR",
    "gn:admin2_code":"12",
    "gn:admin3_code":"56.0",
    "gn:admin4_code":"560033.0",
    "gn:asciiname":"Ekrate",
    "gn:country_code":"NP",
    "gn:dem":1847,
    "gn:feature_class":"P",
    "gn:feature_code":"PPLL",
    "gn:name":"Ekrate",
    "gn:population":0,
    "gn:timezone":"Asia/Kathmandu",
    "iso:country":"NP",
    "wof:name":"Ekrate",
    "wof:placetype":"locality"
},
  "geometry": {"coordinates":[82.24304000000002,28.23278],"type":"Point"}
}