{
  "type": "Feature",
  "properties": {
    "gn:admin1_code":"ER",
    "gn:admin2_code":"7",
    "gn:admin3_code":"5",
    "gn:admin4_code":"50045",
    "gn:asciiname":"Pipalgachhi",
    "gn:country_code":"NP",
    "gn:dem":114,
    "gn:feature_class":"P",
    "gn:feature_code":"PPLL",
    "gn:name":"Pipalgachhi",
    "gn:population":0,
    "gn:timezone":"Asia/Kathmandu",
    "iso:country":"NP",
    "wof:name":"Pipalgachhi",
    "wof:placetype":"locality"
},
  "geometry": {"coordinates":[87.59161999999998,26.62576],"type":"Point"}
}