{
  "type": "Feature",
  "properties": {
    "gn:admin1_code":"FR",
    "gn:admin2_code":"14",
    "gn:admin3_code":"70.0",
    "gn:admin4_code":"700025.0",
    "gn:asciiname":"Kanachaur",
    "gn:country_code":"NP",
    "gn:dem":1517,
    "gn:feature_class":"P",
    "gn:feature_code":"PPLL",
    "gn:name":"Kanachaur",
    "gn:population":0,
    "gn:timezone":"Asia/Kathmandu",
    "iso:country":"NP",
    "name:ceb_x_preferred":[
        "Kanachaur"
    ],
    "name:dty_x_preferred":[
        "\u0915\u093e\u0928\u093e\u091a\u094c\u0930"
    ],
    "name:fra_x_preferred":[
        "Kanachaur"
    ],
    "name:mai_x_preferred":[
        "\u0915\u093e\u0928\u093e\u091a\u094c\u0930"
    ],
    "name:msa_x_preferred":[
        "Kanachaur"
    ],
    "name:nep_x_preferred":[
        "\u0915\u093e\u0928\u093e\u091a\u094c\u0930"
    ],
    "name:pol_x_preferred":[
        "Kanachaur"
    ],
    "wof:name":"Kanachaur",
    "wof:placetype":"locality"
},
  "geometry": {"coordinates":[81.0881,29.03285],"type":"Point"}
}