{
  "type": "Feature",
  "properties": {
    "gn:admin1_code":"CR",
    "gn:admin2_code":"5",
    "gn:admin3_code":"17.0",
    "gn:admin4_code":"170022.0",
    "gn:asciiname":"Nathpatti",
    "gn:country_code":"NP",
    "gn:dem":82,
    "gn:feature_class":"P",
    "gn:feature_code":"PPLL",
    "gn:name":"Nathpatti",
    "gn:population":0,
    "gn:timezone":"Asia/Kathmandu",
    "iso:country":"NP",
    "wof:name":"Nathpatti",
    "wof:placetype":"locality"
},
  "geometry": {"coordinates":[86.13298,26.71615],"type":"Point"}
}