{
  "type": "Feature",
  "properties": {
    "gn:admin1_code":"CR",
    "gn:admin2_code":"5",
    "gn:admin3_code":"22.0",
    "gn:admin4_code":"220051.0",
    "gn:asciiname":"Lwansa",
    "gn:country_code":"NP",
    "gn:dem":2192,
    "gn:feature_class":"P",
    "gn:feature_code":"PPLL",
    "gn:name":"Lwansa",
    "gn:population":0,
    "gn:timezone":"Asia/Kathmandu",
    "iso:country":"NP",
    "wof:name":"Lwansa",
    "wof:placetype":"locality"
},
  "geometry": {"coordinates":[86.33802,27.68322],"type":"Point"}
}