{
  "type": "Feature",
  "properties": {
    "gn:admin1_code":"WR",
    "gn:admin2_code":"3",
    "gn:admin3_code":"45.0",
    "gn:admin4_code":"450022.0",
    "gn:asciiname":"Pakhakharka",
    "gn:country_code":"NP",
    "gn:dem":2084,
    "gn:feature_class":"P",
    "gn:feature_code":"PPLL",
    "gn:name":"Pakhakharka",
    "gn:population":0,
    "gn:timezone":"Asia/Kathmandu",
    "iso:country":"NP",
    "wof:name":"Pakhakharka",
    "wof:placetype":"locality"
},
  "geometry": {"coordinates":[83.50100999999999,28.19835],"type":"Point"}
}