{
  "type": "Feature",
  "properties": {
    "gn:admin1_code":"MR",
    "gn:admin2_code":"12",
    "gn:admin3_code":"56.0",
    "gn:admin4_code":"560030.0",
    "gn:asciiname":"Bhaisikuti",
    "gn:country_code":"NP",
    "gn:dem":1010,
    "gn:feature_class":"P",
    "gn:feature_code":"PPLL",
    "gn:name":"Bhaisikuti",
    "gn:population":0,
    "gn:timezone":"Asia/Kathmandu",
    "iso:country":"NP",
    "wof:name":"Bhaisikuti",
    "wof:placetype":"locality"
},
  "geometry": {"coordinates":[82.55958000000003,28.135],"type":"Point"}
}