{
  "type": "Feature",
  "properties": {
    "gn:admin1_code":"MR",
    "gn:admin2_code":"2",
    "gn:admin3_code":"61.0",
    "gn:admin4_code":"610010.0",
    "gn:asciiname":"Machhaina",
    "gn:country_code":"NP",
    "gn:dem":2321,
    "gn:feature_class":"P",
    "gn:feature_code":"PPLL",
    "gn:name":"Machhaina",
    "gn:population":0,
    "gn:timezone":"Asia/Kathmandu",
    "iso:country":"NP",
    "wof:name":"Machhaina",
    "wof:placetype":"locality"
},
  "geometry": {"coordinates":[82.13845999999999,28.74049],"type":"Point"}
}