{
  "type": "Feature",
  "properties": {
    "gn:admin1_code":"WR",
    "gn:admin2_code":"4",
    "gn:admin3_code":"37",
    "gn:admin4_code":"370018",
    "gn:asciiname":"Haribase",
    "gn:country_code":"NP",
    "gn:dem":777,
    "gn:feature_class":"P",
    "gn:feature_code":"PPLL",
    "gn:name":"Haribase",
    "gn:population":0,
    "gn:timezone":"Asia/Kathmandu",
    "iso:country":"NP",
    "wof:name":"Haribase",
    "wof:placetype":"locality"
},
  "geometry": {"coordinates":[84.34228,28.14831],"type":"Point"}
}