{
  "type": "Feature",
  "properties": {
    "gn:admin1_code":"ER",
    "gn:admin2_code":"13.0",
    "gn:admin3_code":"14.0",
    "gn:admin4_code":"140009.0",
    "gn:asciiname":"Rupatar",
    "gn:country_code":"NP",
    "gn:dem":958,
    "gn:feature_class":"P",
    "gn:feature_code":"PPLL",
    "gn:name":"Rupatar",
    "gn:population":0,
    "gn:timezone":"Asia/Kathmandu",
    "iso:country":"NP",
    "name:bih_x_preferred":[
        "\u0930\u0942\u092a\u093e\u091f\u093e\u0930"
    ],
    "name:ceb_x_preferred":[
        "Rupatar"
    ],
    "name:fra_x_preferred":[
        "Rupatar"
    ],
    "name:ita_x_preferred":[
        "Rupatar"
    ],
    "name:mai_x_preferred":[
        "\u0930\u0942\u092a\u093e\u091f\u093e\u0930"
    ],
    "name:msa_x_preferred":[
        "Rupatar"
    ],
    "name:nep_x_preferred":[
        "\u0930\u0941\u092a\u093e\u091f\u093e\u0930"
    ],
    "name:new_x_preferred":[
        "\u0930\u0941\u092a\u093e\u091f\u093e\u0930"
    ],
    "name:pol_x_preferred":[
        "Rupatar"
    ],
    "wof:name":"Rupatar",
    "wof:placetype":"locality"
},
  "geometry": {"coordinates":[86.94518000000002,26.87772],"type":"Point"}
}