{
  "type": "Feature",
  "properties": {
    "gn:admin1_code":"ER",
    "gn:admin2_code":"7",
    "gn:admin3_code":"10.0",
    "gn:admin4_code":"100041.0",
    "gn:asciiname":"Udaypur",
    "gn:country_code":"NP",
    "gn:dem":558,
    "gn:feature_class":"P",
    "gn:feature_code":"PPLL",
    "gn:name":"Udaypur",
    "gn:population":0,
    "gn:timezone":"Asia/Kathmandu",
    "iso:country":"NP",
    "wof:name":"Udaypur",
    "wof:placetype":"locality"
},
  "geometry": {"coordinates":[87.12700000000002,27.38551],"type":"Point"}
}