{
  "type": "Feature",
  "properties": {
    "gn:admin1_code":"FR",
    "gn:admin2_code":"14.0",
    "gn:admin3_code":"69.0",
    "gn:admin4_code":"690041.0",
    "gn:asciiname":"Kaulekharka",
    "gn:country_code":"NP",
    "gn:dem":1751,
    "gn:feature_class":"P",
    "gn:feature_code":"PPLL",
    "gn:name":"Kaulekharka",
    "gn:population":0,
    "gn:timezone":"Asia/Kathmandu",
    "iso:country":"NP",
    "wof:name":"Kaulekharka",
    "wof:placetype":"locality"
},
  "geometry": {"coordinates":[81.36442,29.11839],"type":"Point"}
}