{
  "type": "Feature",
  "properties": {
    "gn:admin1_code":"WR",
    "gn:admin2_code":"4",
    "gn:admin3_code":"40.0",
    "gn:admin4_code":"400018.0",
    "gn:asciiname":"Dhaba",
    "gn:country_code":"NP",
    "gn:dem":1149,
    "gn:feature_class":"P",
    "gn:feature_code":"PPLL",
    "gn:name":"Dhaba",
    "gn:population":0,
    "gn:timezone":"Asia/Kathmandu",
    "iso:country":"NP",
    "name:afr_x_preferred":[
        "Dhaba"
    ],
    "name:fas_x_preferred":[
        "\u062f\u0628\u0647"
    ],
    "name:guj_x_preferred":[
        "\u0aa2\u0abe\u0aac\u0abe"
    ],
    "name:hin_x_preferred":[
        "\u0922\u093e\u092c\u093e"
    ],
    "name:spa_x_preferred":[
        "Dhaba"
    ],
    "wof:name":"Dhaba",
    "wof:placetype":"locality"
},
  "geometry": {"coordinates":[83.90475000000001,28.24998],"type":"Point"}
}