{
  "type": "Feature",
  "properties": {
    "gn:admin1_code":"MR",
    "gn:admin2_code":"2",
    "gn:admin3_code":"60.0",
    "gn:admin4_code":"600056.0",
    "gn:asciiname":"Bhadachaur",
    "gn:country_code":"NP",
    "gn:dem":1313,
    "gn:feature_class":"P",
    "gn:feature_code":"PPLL",
    "gn:name":"Bhadachaur",
    "gn:population":0,
    "gn:timezone":"Asia/Kathmandu",
    "iso:country":"NP",
    "wof:name":"Bhadachaur",
    "wof:placetype":"locality"
},
  "geometry": {"coordinates":[81.51881,28.96597],"type":"Point"}
}