{
  "type": "Feature",
  "properties": {
    "gn:admin1_code":"WR",
    "gn:admin2_code":"3",
    "gn:admin3_code":"45.0",
    "gn:admin4_code":"450032.0",
    "gn:asciiname":"Jharumaura",
    "gn:country_code":"NP",
    "gn:dem":1063,
    "gn:feature_class":"P",
    "gn:feature_code":"PPLL",
    "gn:name":"Jharumaura",
    "gn:population":0,
    "gn:timezone":"Asia/Kathmandu",
    "iso:country":"NP",
    "wof:name":"Jharumaura",
    "wof:placetype":"locality"
},
  "geometry": {"coordinates":[83.37940999999999,28.20204],"type":"Point"}
}