{
  "type": "Feature",
  "properties": {
    "gn:admin1_code":"WR",
    "gn:admin2_code":"8",
    "gn:admin3_code":"46.0",
    "gn:admin4_code":"460048.0",
    "gn:asciiname":"Korapani",
    "gn:country_code":"NP",
    "gn:dem":1274,
    "gn:feature_class":"P",
    "gn:feature_code":"PPLL",
    "gn:name":"Korapani",
    "gn:population":0,
    "gn:timezone":"Asia/Kathmandu",
    "iso:country":"NP",
    "wof:name":"Korapani",
    "wof:placetype":"locality"
},
  "geometry": {"coordinates":[83.18476,28.10249],"type":"Point"}
}