{
  "type": "Feature",
  "properties": {
    "gn:admin1_code":"ER",
    "gn:admin2_code":"13",
    "gn:admin3_code":"12",
    "gn:admin4_code":"120034",
    "gn:asciiname":"Badare",
    "gn:country_code":"NP",
    "gn:dem":1162,
    "gn:feature_class":"P",
    "gn:feature_code":"PPLL",
    "gn:name":"Badare",
    "gn:population":0,
    "gn:timezone":"Asia/Kathmandu",
    "iso:country":"NP",
    "wof:name":"Badare",
    "wof:placetype":"locality"
},
  "geometry": {"coordinates":[86.24011999999998,27.25806],"type":"Point"}
}