{
  "type": "Feature",
  "properties": {
    "gn:admin1_code":"CR",
    "gn:admin2_code":"5",
    "gn:admin3_code":"21",
    "gn:admin4_code":"210037",
    "gn:asciiname":"Bhulbhule",
    "gn:country_code":"NP",
    "gn:dem":1681,
    "gn:feature_class":"P",
    "gn:feature_code":"PPLL",
    "gn:name":"Bhulbhule",
    "gn:population":0,
    "gn:timezone":"Asia/Kathmandu",
    "iso:country":"NP",
    "wof:name":"Bhulbhule",
    "wof:placetype":"locality"
},
  "geometry": {"coordinates":[86.17669000000002,27.50257],"type":"Point"}
}