{
  "type": "Feature",
  "properties": {
    "gn:admin1_code":"MR",
    "gn:admin2_code":"6",
    "gn:admin3_code":"66.0",
    "gn:admin4_code":"660009.0",
    "gn:asciiname":"Dhimbada Goth",
    "gn:country_code":"NP",
    "gn:dem":2477,
    "gn:feature_class":"P",
    "gn:feature_code":"PPLL",
    "gn:name":"Dhimbada Goth",
    "gn:population":0,
    "gn:timezone":"Asia/Kathmandu",
    "iso:country":"NP",
    "wof:name":"Dhimbada Goth",
    "wof:placetype":"locality"
},
  "geometry": {"coordinates":[81.82302,29.69516],"type":"Point"}
}