{
  "type": "Feature",
  "properties": {
    "gn:admin1_code":"CR",
    "gn:admin2_code":"5",
    "gn:admin3_code":"21",
    "gn:admin4_code":"210051.0",
    "gn:asciiname":"Patle",
    "gn:country_code":"NP",
    "gn:dem":1155,
    "gn:feature_class":"P",
    "gn:feature_code":"PPLL",
    "gn:name":"Patle",
    "gn:population":0,
    "gn:timezone":"Asia/Kathmandu",
    "iso:country":"NP",
    "wof:name":"Patle",
    "wof:placetype":"locality"
},
  "geometry": {"coordinates":[86.09661,27.32802],"type":"Point"}
}