{
  "type": "Feature",
  "properties": {
    "gn:admin1_code":"ER",
    "gn:admin2_code":"7",
    "gn:admin3_code":"10.0",
    "gn:admin4_code":"100058.0",
    "gn:asciiname":"Timma",
    "gn:country_code":"NP",
    "gn:dem":2137,
    "gn:feature_class":"P",
    "gn:feature_code":"PPLL",
    "gn:name":"Timma",
    "gn:population":0,
    "gn:timezone":"Asia/Kathmandu",
    "iso:country":"NP",
    "wof:name":"Timma",
    "wof:placetype":"locality"
},
  "geometry": {"coordinates":[86.97866999999999,27.25797],"type":"Point"}
}