{
  "type": "Feature",
  "properties": {
    "gn:admin1_code":"FR",
    "gn:admin2_code":"14",
    "gn:admin3_code":"69",
    "gn:admin4_code":"690024",
    "gn:asciiname":"Kotagado",
    "gn:country_code":"NP",
    "gn:dem":1532,
    "gn:feature_class":"P",
    "gn:feature_code":"PPLL",
    "gn:name":"Kotagado",
    "gn:population":0,
    "gn:timezone":"Asia/Kathmandu",
    "iso:country":"NP",
    "wof:name":"Kotagado",
    "wof:placetype":"locality"
},
  "geometry": {"coordinates":[81.31671999999998,29.02056],"type":"Point"}
}