{
  "type": "Feature",
  "properties": {
    "gn:admin1_code":"ER",
    "gn:admin2_code":"7",
    "gn:admin3_code":"10.0",
    "gn:admin4_code":"100025.0",
    "gn:asciiname":"Wachhala",
    "gn:country_code":"NP",
    "gn:dem":1778,
    "gn:feature_class":"P",
    "gn:feature_code":"PPLL",
    "gn:name":"Wachhala",
    "gn:population":0,
    "gn:timezone":"Asia/Kathmandu",
    "iso:country":"NP",
    "wof:name":"Wachhala",
    "wof:placetype":"locality"
},
  "geometry": {"coordinates":[86.99656999999998,27.2271],"type":"Point"}
}