{
  "type": "Feature",
  "properties": {
    "gn:admin1_code":"ER",
    "gn:admin2_code":"13",
    "gn:admin3_code":"13",
    "gn:admin4_code":"130058",
    "gn:asciiname":"Sabda",
    "gn:country_code":"NP",
    "gn:dem":1848,
    "gn:feature_class":"P",
    "gn:feature_code":"PPLL",
    "gn:name":"Sabda",
    "gn:population":0,
    "gn:timezone":"Asia/Kathmandu",
    "iso:country":"NP",
    "wof:name":"Sabda",
    "wof:placetype":"locality"
},
  "geometry": {"coordinates":[86.91918000000003,27.29125],"type":"Point"}
}