{
  "type": "Feature",
  "properties": {
    "gn:admin1_code":"WR",
    "gn:admin2_code":"4",
    "gn:admin3_code":"37",
    "gn:admin4_code":"370024",
    "gn:asciiname":"Pathe Bhanjyang",
    "gn:country_code":"NP",
    "gn:dem":1161,
    "gn:feature_class":"P",
    "gn:feature_code":"PPLL",
    "gn:name":"Pathe Bhanjyang",
    "gn:population":0,
    "gn:timezone":"Asia/Kathmandu",
    "iso:country":"NP",
    "wof:name":"Pathe Bhanjyang",
    "wof:placetype":"locality"
},
  "geometry": {"coordinates":[84.36164000000002,28.17004],"type":"Point"}
}