{
  "type": "Feature",
  "properties": {
    "gn:admin1_code":"FR",
    "gn:admin2_code":"9",
    "gn:admin3_code":"75.0",
    "gn:admin4_code":"750033.0",
    "gn:asciiname":"Simal Dhukuri",
    "gn:country_code":"NP",
    "gn:dem":1080,
    "gn:feature_class":"P",
    "gn:feature_code":"PPLL",
    "gn:name":"Simal Dhukuri",
    "gn:population":0,
    "gn:timezone":"Asia/Kathmandu",
    "iso:country":"NP",
    "wof:name":"Simal Dhukuri",
    "wof:placetype":"locality"
},
  "geometry": {"coordinates":[80.43312,29.74866],"type":"Point"}
}