{
  "type": "Feature",
  "properties": {
    "gn:admin1_code":"MR",
    "gn:admin2_code":"6",
    "gn:admin3_code":"64.0",
    "gn:admin4_code":"640011.0",
    "gn:asciiname":"Gharali",
    "gn:country_code":"NP",
    "gn:dem":923,
    "gn:feature_class":"P",
    "gn:feature_code":"PPLL",
    "gn:name":"Gharali",
    "gn:population":0,
    "gn:timezone":"Asia/Kathmandu",
    "iso:country":"NP",
    "wof:name":"Gharali",
    "wof:placetype":"locality"
},
  "geometry": {"coordinates":[81.55886,29.1322],"type":"Point"}
}