{
  "type": "Feature",
  "properties": {
    "gn:admin1_code":"MR",
    "gn:admin2_code":"6",
    "gn:admin3_code":"64.0",
    "gn:admin4_code":"640002.0",
    "gn:asciiname":"Dubi",
    "gn:country_code":"NP",
    "gn:dem":3600,
    "gn:feature_class":"P",
    "gn:feature_code":"PPLL",
    "gn:name":"Dubi",
    "gn:population":0,
    "gn:timezone":"Asia/Kathmandu",
    "iso:country":"NP",
    "wof:name":"Dubi",
    "wof:placetype":"locality"
},
  "geometry": {"coordinates":[81.76354000000001,29.18734000000001],"type":"Point"}
}