{
  "type": "Feature",
  "properties": {
    "gn:admin1_code":"ER",
    "gn:admin2_code":"7",
    "gn:admin3_code":"7.0",
    "gn:admin4_code":"70010.0",
    "gn:asciiname":"Sakrantidanda",
    "gn:country_code":"NP",
    "gn:dem":1286,
    "gn:feature_class":"P",
    "gn:feature_code":"PPLL",
    "gn:name":"Sakrantidanda",
    "gn:population":0,
    "gn:timezone":"Asia/Kathmandu",
    "iso:country":"NP",
    "wof:name":"Sakrantidanda",
    "wof:placetype":"locality"
},
  "geometry": {"coordinates":[87.30911,27.16608],"type":"Point"}
}