{
  "type": "Feature",
  "properties": {
    "gn:admin1_code":"CR",
    "gn:admin2_code":"1",
    "gn:admin3_code":"27.0",
    "gn:admin4_code":"270034.0",
    "gn:asciiname":"Kaule",
    "gn:country_code":"NP",
    "gn:dem":1872,
    "gn:feature_class":"P",
    "gn:feature_code":"PPLL",
    "gn:name":"Kaule",
    "gn:population":0,
    "gn:timezone":"Asia/Kathmandu",
    "iso:country":"NP",
    "name:ceb_x_preferred":[
        "Kaule"
    ],
    "name:deu_x_preferred":[
        "Kaule"
    ],
    "name:pol_x_preferred":[
        "Kaule"
    ],
    "name:swe_x_preferred":[
        "Kaule"
    ],
    "wof:name":"Kaule",
    "wof:placetype":"locality"
},
  "geometry": {"coordinates":[85.49663000000002,27.75685],"type":"Point"}
}