{
  "type": "Feature",
  "properties": {
    "gn:admin1_code":"MR",
    "gn:admin2_code":"12",
    "gn:admin3_code":"55",
    "gn:admin4_code":"550035",
    "gn:asciiname":"Siranchaur",
    "gn:country_code":"NP",
    "gn:dem":1884,
    "gn:feature_class":"P",
    "gn:feature_code":"PPLL",
    "gn:name":"Siranchaur",
    "gn:population":0,
    "gn:timezone":"Asia/Kathmandu",
    "iso:country":"NP",
    "wof:name":"Siranchaur",
    "wof:placetype":"locality"
},
  "geometry": {"coordinates":[82.01141,28.35875],"type":"Point"}
}