{
  "type": "Feature",
  "properties": {
    "gn:admin1_code":"FR",
    "gn:admin2_code":"14.0",
    "gn:admin3_code":"67.0",
    "gn:admin4_code":"670007.0",
    "gn:asciiname":"Payale",
    "gn:country_code":"NP",
    "gn:dem":2394,
    "gn:feature_class":"P",
    "gn:feature_code":"PPLL",
    "gn:name":"Payale",
    "gn:population":0,
    "gn:timezone":"Asia/Kathmandu",
    "iso:country":"NP",
    "wof:name":"Payale",
    "wof:placetype":"locality"
},
  "geometry": {"coordinates":[81.43223,29.39041],"type":"Point"}
}