{
  "type": "Feature",
  "properties": {
    "gn:admin1_code":"FR",
    "gn:admin2_code":"9",
    "gn:admin3_code":"74",
    "gn:admin4_code":"740017",
    "gn:asciiname":"Dungri",
    "gn:country_code":"NP",
    "gn:dem":1438,
    "gn:feature_class":"P",
    "gn:feature_code":"PPLL",
    "gn:name":"Dungri",
    "gn:population":0,
    "gn:timezone":"Asia/Kathmandu",
    "iso:country":"NP",
    "wof:name":"Dungri",
    "wof:placetype":"locality"
},
  "geometry": {"coordinates":[80.46954000000002,29.55921],"type":"Point"}
}