{
  "type": "Feature",
  "properties": {
    "gn:admin1_code":"FR",
    "gn:admin2_code":"14",
    "gn:admin3_code":"68",
    "gn:admin4_code":"680029",
    "gn:asciiname":"Nuwakot",
    "gn:country_code":"NP",
    "gn:dem":1771,
    "gn:feature_class":"P",
    "gn:feature_code":"PPLL",
    "gn:name":"Nuwakot",
    "gn:population":0,
    "gn:timezone":"Asia/Kathmandu",
    "iso:country":"NP",
    "name:pol_x_preferred":[
        "Nuwakot"
    ],
    "wof:name":"Nuwakot",
    "wof:placetype":"locality"
},
  "geometry": {"coordinates":[81.15474,29.44301],"type":"Point"}
}