{
  "type": "Feature",
  "properties": {
    "gn:admin1_code":"WR",
    "gn:admin2_code":"8",
    "gn:admin3_code":"51.0",
    "gn:admin4_code":"510013.0",
    "gn:asciiname":"Tallo Khillu",
    "gn:country_code":"NP",
    "gn:dem":1547,
    "gn:feature_class":"P",
    "gn:feature_code":"PPLL",
    "gn:name":"Tallo Khillu",
    "gn:population":0,
    "gn:timezone":"Asia/Kathmandu",
    "iso:country":"NP",
    "wof:name":"Tallo Khillu",
    "wof:placetype":"locality"
},
  "geometry": {"coordinates":[83.06184,28.03852],"type":"Point"}
}