{
  "type": "Feature",
  "properties": {
    "gn:admin1_code":"MR",
    "gn:admin2_code":"6",
    "gn:admin3_code":"66.0",
    "gn:admin4_code":"660011.0",
    "gn:asciiname":"Chaukan chaur",
    "gn:country_code":"NP",
    "gn:dem":2705,
    "gn:feature_class":"P",
    "gn:feature_code":"PPLL",
    "gn:name":"Chaukan chaur",
    "gn:population":0,
    "gn:timezone":"Asia/Kathmandu",
    "iso:country":"NP",
    "wof:name":"Chaukan chaur",
    "wof:placetype":"locality"
},
  "geometry": {"coordinates":[81.87826,29.93473],"type":"Point"}
}