{
  "type": "Feature",
  "properties": {
    "gn:admin1_code":"MR",
    "gn:admin2_code":"12",
    "gn:admin3_code":"52",
    "gn:admin4_code":"520035",
    "gn:asciiname":"Todke",
    "gn:country_code":"NP",
    "gn:dem":1855,
    "gn:feature_class":"P",
    "gn:feature_code":"PPLL",
    "gn:name":"Todke",
    "gn:population":0,
    "gn:timezone":"Asia/Kathmandu",
    "iso:country":"NP",
    "wof:name":"Todke",
    "wof:placetype":"locality"
},
  "geometry": {"coordinates":[82.97345,28.10672000000001],"type":"Point"}
}