{
  "type": "Feature",
  "properties": {
    "gn:admin1_code":"00",
    "gn:asciiname":"Nalan Khola",
    "gn:country_code":"NP",
    "gn:dem":1042,
    "gn:feature_class":"P",
    "gn:feature_code":"PPL",
    "gn:name":"Nal\u0101\u1e45 Khol\u0101",
    "gn:population":0,
    "gn:timezone":"Asia/Kathmandu",
    "iso:country":"NP",
    "name:nep_x_preferred":[
        "Nal\u0101\u1e45 Khol\u0101"
    ],
    "wof:name":"Nalan Khola",
    "wof:placetype":"locality"
},
  "geometry": {"coordinates":[84.82559000000001,27.86788],"type":"Point"}
}