{
  "type": "Feature",
  "properties": {
    "gn:admin1_code":"WR",
    "gn:admin2_code":"3",
    "gn:admin3_code":"43",
    "gn:admin4_code":"430012.0",
    "gn:asciiname":"Ranbasa",
    "gn:country_code":"NP",
    "gn:dem":1170,
    "gn:feature_class":"P",
    "gn:feature_code":"PPLL",
    "gn:name":"Ranbasa",
    "gn:population":0,
    "gn:timezone":"Asia/Kathmandu",
    "iso:country":"NP",
    "wof:name":"Ranbasa",
    "wof:placetype":"locality"
},
  "geometry": {"coordinates":[83.38405,28.42276],"type":"Point"}
}