{
  "type": "Feature",
  "properties": {
    "gn:admin1_code":"MR",
    "gn:admin2_code":"2.0",
    "gn:admin3_code":"57.0",
    "gn:admin4_code":"570025.0",
    "gn:asciiname":"Jogigaun",
    "gn:country_code":"NP",
    "gn:dem":161,
    "gn:feature_class":"P",
    "gn:feature_code":"PPLL",
    "gn:name":"Jogigaun",
    "gn:population":0,
    "gn:timezone":"Asia/Kathmandu",
    "iso:country":"NP",
    "wof:name":"Jogigaun",
    "wof:placetype":"locality"
},
  "geometry": {"coordinates":[81.70371,28.12711],"type":"Point"}
}