{
  "type": "Feature",
  "properties": {
    "gn:admin1_code":"CR",
    "gn:admin2_code":"1",
    "gn:admin3_code":"30.0",
    "gn:admin4_code":"300043.0",
    "gn:asciiname":"Maur",
    "gn:country_code":"NP",
    "gn:dem":1675,
    "gn:feature_class":"P",
    "gn:feature_code":"PPLL",
    "gn:name":"Maur",
    "gn:population":0,
    "gn:timezone":"Asia/Kathmandu",
    "iso:country":"NP",
    "name:ceb_x_preferred":[
        "Maur"
    ],
    "name:deu_x_preferred":[
        "Maur"
    ],
    "name:eus_x_preferred":[
        "Maur"
    ],
    "name:ita_x_preferred":[
        "Maur"
    ],
    "name:nld_x_preferred":[
        "Maur"
    ],
    "name:pol_x_preferred":[
        "Maur"
    ],
    "name:rus_x_preferred":[
        "\u041c\u0430\u0443\u0440"
    ],
    "name:spa_x_preferred":[
        "Maur"
    ],
    "name:swe_x_preferred":[
        "Maur"
    ],
    "wof:name":"Maur",
    "wof:placetype":"locality"
},
  "geometry": {"coordinates":[85.03792,28.04211],"type":"Point"}
}