{
  "type": "Feature",
  "properties": {
    "gn:admin1_code":"CR",
    "gn:admin2_code":"1",
    "gn:admin3_code":"24.0",
    "gn:admin4_code":"240043.0",
    "gn:asciiname":"Kankare",
    "gn:country_code":"NP",
    "gn:dem":1283,
    "gn:feature_class":"P",
    "gn:feature_code":"PPLL",
    "gn:name":"Kankare",
    "gn:population":0,
    "gn:timezone":"Asia/Kathmandu",
    "iso:country":"NP",
    "wof:name":"Kankare",
    "wof:placetype":"locality"
},
  "geometry": {"coordinates":[85.65098,27.53582],"type":"Point"}
}