{
  "type": "Feature",
  "properties": {
    "gn:admin1_code":"WR",
    "gn:admin2_code":"8",
    "gn:admin3_code":"51.0",
    "gn:admin4_code":"510015.0",
    "gn:asciiname":"Debha",
    "gn:country_code":"NP",
    "gn:dem":1222,
    "gn:feature_class":"P",
    "gn:feature_code":"PPLL",
    "gn:name":"Debha",
    "gn:population":0,
    "gn:timezone":"Asia/Kathmandu",
    "iso:country":"NP",
    "wof:name":"Debha",
    "wof:placetype":"locality"
},
  "geometry": {"coordinates":[83.08790999999999,27.93134],"type":"Point"}
}