{
  "type": "Feature",
  "properties": {
    "gn:admin1_code":"FR",
    "gn:admin2_code":"14",
    "gn:admin3_code":"70.0",
    "gn:admin4_code":"700012.0",
    "gn:asciiname":"Upallogaun",
    "gn:country_code":"NP",
    "gn:dem":1908,
    "gn:feature_class":"P",
    "gn:feature_code":"PPLL",
    "gn:name":"Upallogaun",
    "gn:population":0,
    "gn:timezone":"Asia/Kathmandu",
    "iso:country":"NP",
    "wof:name":"Upallogaun",
    "wof:placetype":"locality"
},
  "geometry": {"coordinates":[80.94511999999997,29.11825],"type":"Point"}
}