{
  "type": "Feature",
  "properties": {
    "gn:admin1_code":"MR",
    "gn:admin2_code":"6",
    "gn:admin3_code":"63.0",
    "gn:admin4_code":"630004.0",
    "gn:asciiname":"Rajikot",
    "gn:country_code":"NP",
    "gn:dem":2666,
    "gn:feature_class":"P",
    "gn:feature_code":"PPLL",
    "gn:name":"Rajikot",
    "gn:population":0,
    "gn:timezone":"Asia/Kathmandu",
    "iso:country":"NP",
    "wof:name":"Rajikot",
    "wof:placetype":"locality"
},
  "geometry": {"coordinates":[82.20440000000001,29.28508],"type":"Point"}
}