{
  "type": "Feature",
  "properties": {
    "gn:admin1_code":"MR",
    "gn:admin2_code":"12",
    "gn:admin3_code":"56.0",
    "gn:admin4_code":"560029.0",
    "gn:asciiname":"Simle",
    "gn:country_code":"NP",
    "gn:dem":1035,
    "gn:feature_class":"P",
    "gn:feature_code":"PPLL",
    "gn:name":"Simle",
    "gn:population":0,
    "gn:timezone":"Asia/Kathmandu",
    "iso:country":"NP",
    "wof:name":"Simle",
    "wof:placetype":"locality"
},
  "geometry": {"coordinates":[82.58256999999998,28.00491],"type":"Point"}
}