{
  "type": "Feature",
  "properties": {
    "gn:admin1_code":"MR",
    "gn:admin2_code":"12",
    "gn:admin3_code":"54",
    "gn:admin4_code":"540006",
    "gn:asciiname":"Samalemare",
    "gn:country_code":"NP",
    "gn:dem":879,
    "gn:feature_class":"P",
    "gn:feature_code":"PPLL",
    "gn:name":"Samalemare",
    "gn:population":0,
    "gn:timezone":"Asia/Kathmandu",
    "iso:country":"NP",
    "wof:name":"Samalemare",
    "wof:placetype":"locality"
},
  "geometry": {"coordinates":[82.20614999999999,28.66746],"type":"Point"}
}