{
  "type": "Feature",
  "properties": {
    "gn:admin1_code":"MR",
    "gn:admin2_code":"12",
    "gn:admin3_code":"53",
    "gn:admin4_code":"530025",
    "gn:asciiname":"Majuwa",
    "gn:country_code":"NP",
    "gn:dem":1494,
    "gn:feature_class":"P",
    "gn:feature_code":"PPLL",
    "gn:name":"Majuwa",
    "gn:population":0,
    "gn:timezone":"Asia/Kathmandu",
    "iso:country":"NP",
    "wof:name":"Majuwa",
    "wof:placetype":"locality"
},
  "geometry": {"coordinates":[82.55034999999999,28.27616],"type":"Point"}
}