{
  "type": "Feature",
  "properties": {
    "gn:admin1_code":"FR",
    "gn:admin2_code":"14",
    "gn:admin3_code":"70.0",
    "gn:admin4_code":"700004.0",
    "gn:asciiname":"Simgaun",
    "gn:country_code":"NP",
    "gn:dem":991,
    "gn:feature_class":"P",
    "gn:feature_code":"PPLL",
    "gn:name":"Simgaun",
    "gn:population":0,
    "gn:timezone":"Asia/Kathmandu",
    "iso:country":"NP",
    "wof:name":"Simgaun",
    "wof:placetype":"locality"
},
  "geometry": {"coordinates":[80.99649000000002,29.18271],"type":"Point"}
}