{
  "type": "Feature",
  "properties": {
    "gn:admin1_code":"CR",
    "gn:admin2_code":"11",
    "gn:admin3_code":"31",
    "gn:admin4_code":"310022",
    "gn:asciiname":"Chilaunedanda",
    "gn:country_code":"NP",
    "gn:dem":1269,
    "gn:feature_class":"P",
    "gn:feature_code":"PPLL",
    "gn:name":"Chilaunedanda",
    "gn:population":0,
    "gn:timezone":"Asia/Kathmandu",
    "iso:country":"NP",
    "wof:name":"Chilaunedanda",
    "wof:placetype":"locality"
},
  "geometry": {"coordinates":[85.23106999999997,27.4756],"type":"Point"}
}