{
  "type": "Feature",
  "properties": {
    "gn:admin1_code":"ER",
    "gn:admin2_code":"10",
    "gn:admin3_code":"2",
    "gn:admin4_code":"20005",
    "gn:asciiname":"Madibung",
    "gn:country_code":"NP",
    "gn:dem":1618,
    "gn:feature_class":"P",
    "gn:feature_code":"PPLL",
    "gn:name":"Madibung",
    "gn:population":0,
    "gn:timezone":"Asia/Kathmandu",
    "iso:country":"NP",
    "wof:name":"Madibung",
    "wof:placetype":"locality"
},
  "geometry": {"coordinates":[87.76618000000001,27.18771],"type":"Point"}
}