{
  "type": "Feature",
  "properties": {
    "gn:admin1_code":"MR",
    "gn:admin2_code":"2.0",
    "gn:admin3_code":"58.0",
    "gn:admin4_code":"580012.0",
    "gn:asciiname":"Sano Danphe",
    "gn:country_code":"NP",
    "gn:dem":143,
    "gn:feature_class":"P",
    "gn:feature_code":"PPLL",
    "gn:name":"Sano Danphe",
    "gn:population":0,
    "gn:timezone":"Asia/Kathmandu",
    "iso:country":"NP",
    "wof:name":"Sano Danphe",
    "wof:placetype":"locality"
},
  "geometry": {"coordinates":[81.48980999999998,28.0872],"type":"Point"}
}