{
  "type": "Feature",
  "properties": {
    "gn:admin1_code":"MR",
    "gn:admin2_code":"2.0",
    "gn:admin3_code":"59.0",
    "gn:admin4_code":"590022.0",
    "gn:asciiname":"Bangetal",
    "gn:country_code":"NP",
    "gn:dem":755,
    "gn:feature_class":"P",
    "gn:feature_code":"PPLL",
    "gn:name":"Bangetal",
    "gn:population":0,
    "gn:timezone":"Asia/Kathmandu",
    "iso:country":"NP",
    "wof:name":"Bangetal",
    "wof:placetype":"locality"
},
  "geometry": {"coordinates":[81.45063,28.59722],"type":"Point"}
}