{
  "type": "Feature",
  "properties": {
    "gn:admin1_code":"CR",
    "gn:admin2_code":"11",
    "gn:admin3_code":"31",
    "gn:admin4_code":"310036",
    "gn:asciiname":"Naukhante",
    "gn:country_code":"NP",
    "gn:dem":339,
    "gn:feature_class":"P",
    "gn:feature_code":"PPLL",
    "gn:name":"Naukhante",
    "gn:population":0,
    "gn:timezone":"Asia/Kathmandu",
    "iso:country":"NP",
    "wof:name":"Naukhante",
    "wof:placetype":"locality"
},
  "geometry": {"coordinates":[85.43044,27.22068],"type":"Point"}
}