{
  "type": "Feature",
  "properties": {
    "gn:admin1_code":"CR",
    "gn:admin2_code":"11",
    "gn:admin3_code":"32",
    "gn:admin4_code":"320074",
    "gn:asciiname":"Kharkitola",
    "gn:country_code":"NP",
    "gn:dem":84,
    "gn:feature_class":"P",
    "gn:feature_code":"PPLL",
    "gn:name":"Kharkitola",
    "gn:population":0,
    "gn:timezone":"Asia/Kathmandu",
    "iso:country":"NP",
    "wof:name":"Kharkitola",
    "wof:placetype":"locality"
},
  "geometry": {"coordinates":[85.33948000000002,26.87485],"type":"Point"}
}