{
  "type": "Feature",
  "properties": {
    "gn:admin1_code":"MR",
    "gn:admin2_code":"2.0",
    "gn:admin3_code":"57.0",
    "gn:admin4_code":"570037.0",
    "gn:asciiname":"Kigariyanpurwa",
    "gn:country_code":"NP",
    "gn:dem":151,
    "gn:feature_class":"P",
    "gn:feature_code":"PPLL",
    "gn:name":"Kigariyanpurwa",
    "gn:population":0,
    "gn:timezone":"Asia/Kathmandu",
    "iso:country":"NP",
    "wof:name":"Kigariyanpurwa",
    "wof:placetype":"locality"
},
  "geometry": {"coordinates":[81.672,28.05775],"type":"Point"}
}