{
  "type": "Feature",
  "properties": {
    "gn:admin1_code":"CR",
    "gn:admin2_code":"1",
    "gn:admin3_code":"23",
    "gn:admin4_code":"230050",
    "gn:asciiname":"Swanrgaun",
    "gn:country_code":"NP",
    "gn:dem":1484,
    "gn:feature_class":"P",
    "gn:feature_code":"PPLL",
    "gn:name":"Swanrgaun",
    "gn:population":0,
    "gn:timezone":"Asia/Kathmandu",
    "iso:country":"NP",
    "wof:name":"Swanrgaun",
    "wof:placetype":"locality"
},
  "geometry": {"coordinates":[85.63894999999999,27.80515],"type":"Point"}
}