{
  "type": "Feature",
  "properties": {
    "gn:admin1_code":"ER",
    "gn:admin2_code":"7",
    "gn:admin3_code":"7.0",
    "gn:admin4_code":"70004.0",
    "gn:asciiname":"Sokropa",
    "gn:country_code":"NP",
    "gn:dem":1472,
    "gn:feature_class":"P",
    "gn:feature_code":"PPLL",
    "gn:name":"Sokropa",
    "gn:population":0,
    "gn:timezone":"Asia/Kathmandu",
    "iso:country":"NP",
    "wof:name":"Sokropa",
    "wof:placetype":"locality"
},
  "geometry": {"coordinates":[87.46332,26.87569],"type":"Point"}
}