{
  "type": "Feature",
  "properties": {
    "gn:admin1_code":"FR",
    "gn:admin2_code":"14",
    "gn:admin3_code":"68",
    "gn:admin4_code":"680036",
    "gn:asciiname":"Machheni Patal",
    "gn:country_code":"NP",
    "gn:dem":1810,
    "gn:feature_class":"P",
    "gn:feature_code":"PPLL",
    "gn:name":"Machheni Patal",
    "gn:population":0,
    "gn:timezone":"Asia/Kathmandu",
    "iso:country":"NP",
    "wof:name":"Machheni Patal",
    "wof:placetype":"locality"
},
  "geometry": {"coordinates":[81.20129,29.43391],"type":"Point"}
}