{
  "type": "Feature",
  "properties": {
    "gn:admin1_code":"WR",
    "gn:admin2_code":"8",
    "gn:admin3_code":"48",
    "gn:admin4_code":"480018",
    "gn:asciiname":"Bahrabise",
    "gn:country_code":"NP",
    "gn:dem":401,
    "gn:feature_class":"P",
    "gn:feature_code":"PPLL",
    "gn:name":"Bahrabise",
    "gn:population":0,
    "gn:timezone":"Asia/Kathmandu",
    "iso:country":"NP",
    "name:deu_x_preferred":[
        "Barhabise"
    ],
    "name:fra_x_preferred":[
        "Bahrabise"
    ],
    "name:msa_x_preferred":[
        "Barhabise"
    ],
    "name:nep_x_preferred":[
        "\u092c\u093e\u0939\u094d\u0930\u092c\u093f\u0938\u0947"
    ],
    "name:pol_x_preferred":[
        "Barhabise"
    ],
    "wof:name":"Bahrabise",
    "wof:placetype":"locality"
},
  "geometry": {"coordinates":[83.73300999999999,27.68644],"type":"Point"}
}