{
  "type": "Feature",
  "properties": {
    "gn:admin1_code":"WR",
    "gn:admin2_code":"8",
    "gn:admin3_code":"48",
    "gn:admin4_code":"480018",
    "gn:asciiname":"Bahrabise",
    "gn:country_code":"NP",
    "gn:dem":401,
    "gn:feature_class":"P",
    "gn:feature_code":"PPLL",
    "gn:name":"Bahrabise",
    "gn:population":0,
    "gn:timezone":"Asia/Kathmandu",
    "iso:country":"NP",
    "wof:name":"Bahrabise",
    "wof:placetype":"locality"
},
  "geometry": {"coordinates":[83.73300999999999,27.68644],"type":"Point"}
}