{
  "type": "Feature",
  "properties": {
    "gn:admin1_code":"CR",
    "gn:admin2_code":"1",
    "gn:admin3_code":"24.0",
    "gn:admin4_code":"240014.0",
    "gn:asciiname":"Sulekot",
    "gn:country_code":"NP",
    "gn:dem":1361,
    "gn:feature_class":"P",
    "gn:feature_code":"PPLL",
    "gn:name":"Sulekot",
    "gn:population":0,
    "gn:timezone":"Asia/Kathmandu",
    "iso:country":"NP",
    "wof:name":"Sulekot",
    "wof:placetype":"locality"
},
  "geometry": {"coordinates":[85.64811999999998,27.69634000000001],"type":"Point"}
}