{
  "type": "Feature",
  "properties": {
    "gn:admin1_code":"00",
    "gn:asciiname":"Kattike",
    "gn:country_code":"NP",
    "gn:dem":1020,
    "gn:feature_class":"P",
    "gn:feature_code":"PPL",
    "gn:name":"K\u0101ttike",
    "gn:population":0,
    "gn:timezone":"Asia/Kathmandu",
    "iso:country":"NP",
    "wof:name":"Kattike",
    "wof:placetype":"locality"
},
  "geometry": {"coordinates":[86.15586,27.71707],"type":"Point"}
}