{
  "type": "Feature",
  "properties": {
    "gn:admin1_code":"ER",
    "gn:admin2_code":"10",
    "gn:admin3_code":"2",
    "gn:admin4_code":"20005",
    "gn:asciiname":"Pipalbote",
    "gn:country_code":"NP",
    "gn:dem":1655,
    "gn:feature_class":"P",
    "gn:feature_code":"PPLL",
    "gn:name":"Pipalbote",
    "gn:population":0,
    "gn:timezone":"Asia/Kathmandu",
    "iso:country":"NP",
    "wof:name":"Pipalbote",
    "wof:placetype":"locality"
},
  "geometry": {"coordinates":[87.80155000000001,27.19596],"type":"Point"}
}