{
  "type": "Feature",
  "properties": {
    "gn:admin1_code":"FR",
    "gn:admin2_code":"14",
    "gn:admin3_code":"70.0",
    "gn:admin4_code":"700010.0",
    "gn:asciiname":"Sunbata",
    "gn:country_code":"NP",
    "gn:dem":1370,
    "gn:feature_class":"P",
    "gn:feature_code":"PPLL",
    "gn:name":"Sunbata",
    "gn:population":0,
    "gn:timezone":"Asia/Kathmandu",
    "iso:country":"NP",
    "wof:name":"Sunbata",
    "wof:placetype":"locality"
},
  "geometry": {"coordinates":[80.96921999999998,29.36527],"type":"Point"}
}