{
  "type": "Feature",
  "properties": {
    "gn:admin1_code":"WR",
    "gn:admin2_code":"8",
    "gn:admin3_code":"50.0",
    "gn:admin4_code":"500026.0",
    "gn:asciiname":"Chamkipur",
    "gn:country_code":"NP",
    "gn:dem":134,
    "gn:feature_class":"P",
    "gn:feature_code":"PPLL",
    "gn:name":"Chamkipur",
    "gn:population":0,
    "gn:timezone":"Asia/Kathmandu",
    "iso:country":"NP",
    "wof:name":"Chamkipur",
    "wof:placetype":"locality"
},
  "geometry": {"coordinates":[83.16554000000002,27.6674],"type":"Point"}
}