{
  "type": "Feature",
  "properties": {
    "gn:admin1_code":"WR",
    "gn:admin2_code":"3",
    "gn:admin3_code":"45.0",
    "gn:admin4_code":"450017.0",
    "gn:asciiname":"Duwar",
    "gn:country_code":"NP",
    "gn:dem":1570,
    "gn:feature_class":"P",
    "gn:feature_code":"PPLL",
    "gn:name":"Duwar",
    "gn:population":0,
    "gn:timezone":"Asia/Kathmandu",
    "iso:country":"NP",
    "wof:name":"Duwar",
    "wof:placetype":"locality"
},
  "geometry": {"coordinates":[83.60899000000001,28.24067],"type":"Point"}
}