{
  "type": "Feature",
  "properties": {
    "gn:admin1_code":"ER",
    "gn:admin2_code":"7",
    "gn:admin3_code":"7.0",
    "gn:admin4_code":"70011.0",
    "gn:asciiname":"Dhap",
    "gn:country_code":"NP",
    "gn:dem":654,
    "gn:feature_class":"P",
    "gn:feature_code":"PPLL",
    "gn:name":"Dhap",
    "gn:population":0,
    "gn:timezone":"Asia/Kathmandu",
    "iso:country":"NP",
    "name:ceb_x_preferred":[
        "Dhap"
    ],
    "name:fra_x_preferred":[
        "Dhap"
    ],
    "name:msa_x_preferred":[
        "Dhap"
    ],
    "name:nep_x_preferred":[
        "\u0927\u093e\u092a"
    ],
    "name:new_x_preferred":[
        "\u0927\u093e\u092a"
    ],
    "name:pol_x_preferred":[
        "Dhap"
    ],
    "wof:name":"Dhap",
    "wof:placetype":"locality"
},
  "geometry": {"coordinates":[87.21472,26.91987],"type":"Point"}
}