{
  "type": "Feature",
  "properties": {
    "gn:admin1_code":"MR",
    "gn:admin2_code":"6",
    "gn:admin3_code":"63.0",
    "gn:admin4_code":"630003.0",
    "gn:asciiname":"Bharbhare",
    "gn:country_code":"NP",
    "gn:dem":2968,
    "gn:feature_class":"P",
    "gn:feature_code":"PPLL",
    "gn:name":"Bharbhare",
    "gn:population":0,
    "gn:timezone":"Asia/Kathmandu",
    "iso:country":"NP",
    "wof:name":"Bharbhare",
    "wof:placetype":"locality"
},
  "geometry": {"coordinates":[82.10927,29.42504000000001],"type":"Point"}
}