{
  "type": "Feature",
  "properties": {
    "gn:admin1_code":"FR",
    "gn:admin2_code":"9",
    "gn:admin3_code":"74",
    "gn:admin4_code":"740032",
    "gn:asciiname":"Mauradi",
    "gn:country_code":"NP",
    "gn:dem":1572,
    "gn:feature_class":"P",
    "gn:feature_code":"PPLL",
    "gn:name":"Mauradi",
    "gn:population":0,
    "gn:timezone":"Asia/Kathmandu",
    "iso:country":"NP",
    "wof:name":"Mauradi",
    "wof:placetype":"locality"
},
  "geometry": {"coordinates":[80.75521999999999,29.60985],"type":"Point"}
}