{
  "type": "Feature",
  "properties": {
    "gn:admin1_code":"ER",
    "gn:admin2_code":"7",
    "gn:admin3_code":"6",
    "gn:admin4_code":"60006",
    "gn:asciiname":"Panchayanjhora",
    "gn:country_code":"NP",
    "gn:dem":127,
    "gn:feature_class":"P",
    "gn:feature_code":"PPLL",
    "gn:name":"Panchayanjhora",
    "gn:population":0,
    "gn:timezone":"Asia/Kathmandu",
    "iso:country":"NP",
    "wof:name":"Panchayanjhora",
    "wof:placetype":"locality"
},
  "geometry": {"coordinates":[87.23371999999998,26.73004],"type":"Point"}
}