{
  "type": "Feature",
  "properties": {
    "gn:admin1_code":"WR",
    "gn:admin2_code":"4",
    "gn:admin3_code":"40.0",
    "gn:admin4_code":"400006.0",
    "gn:asciiname":"Lamakhet",
    "gn:country_code":"NP",
    "gn:dem":870,
    "gn:feature_class":"P",
    "gn:feature_code":"PPLL",
    "gn:name":"Lamakhet",
    "gn:population":0,
    "gn:timezone":"Asia/Kathmandu",
    "iso:country":"NP",
    "wof:name":"Lamakhet",
    "wof:placetype":"locality"
},
  "geometry": {"coordinates":[83.86779,28.23853],"type":"Point"}
}