{
  "type": "Feature",
  "properties": {
    "gn:admin1_code":"WR",
    "gn:admin2_code":"4.0",
    "gn:admin3_code":"39.0",
    "gn:admin4_code":"390043.0",
    "gn:asciiname":"Bharka",
    "gn:country_code":"NP",
    "gn:dem":1350,
    "gn:feature_class":"P",
    "gn:feature_code":"PPLL",
    "gn:name":"Bharka",
    "gn:population":0,
    "gn:timezone":"Asia/Kathmandu",
    "iso:country":"NP",
    "wof:name":"Bharka",
    "wof:placetype":"locality"
},
  "geometry": {"coordinates":[83.63446,27.99024],"type":"Point"}
}