{
  "type": "Feature",
  "properties": {
    "gn:admin1_code":"FR",
    "gn:admin2_code":"14",
    "gn:admin3_code":"71.0",
    "gn:admin4_code":"710006.0",
    "gn:asciiname":"Tigri",
    "gn:country_code":"NP",
    "gn:dem":164,
    "gn:feature_class":"P",
    "gn:feature_code":"PPLL",
    "gn:name":"Tigri",
    "gn:population":0,
    "gn:timezone":"Asia/Kathmandu",
    "iso:country":"NP",
    "name:ben_x_preferred":[
        "\u09a4\u09bf\u0997\u09b0\u09bf"
    ],
    "name:bpy_x_preferred":[
        "\u09a4\u09bf\u0997\u09b0\u09bf"
    ],
    "name:ita_x_preferred":[
        "Tigri"
    ],
    "name:msa_x_preferred":[
        "Tigri"
    ],
    "name:nld_x_preferred":[
        "Tigri"
    ],
    "name:por_x_preferred":[
        "Tigri"
    ],
    "name:tam_x_preferred":[
        "\u0ba4\u0bbf\u0b95\u0bcd\u0bb0\u0bbf"
    ],
    "name:vie_x_preferred":[
        "Tigri"
    ],
    "name:zho_x_preferred":[
        "\u8482\u683c\u91cc"
    ],
    "wof:name":"Tigri",
    "wof:placetype":"locality"
},
  "geometry": {"coordinates":[81.06746,28.63325],"type":"Point"}
}