{
  "type": "Feature",
  "properties": {
    "gn:admin1_code":"FR",
    "gn:admin2_code":"9",
    "gn:admin3_code":"74",
    "gn:admin4_code":"740046",
    "gn:asciiname":"Chaumala",
    "gn:country_code":"NP",
    "gn:dem":1491,
    "gn:feature_class":"P",
    "gn:feature_code":"PPLL",
    "gn:name":"Chaumala",
    "gn:population":0,
    "gn:timezone":"Asia/Kathmandu",
    "iso:country":"NP",
    "wof:name":"Chaumala",
    "wof:placetype":"locality"
},
  "geometry": {"coordinates":[80.57904000000001,29.51053],"type":"Point"}
}