{
  "type": "Feature",
  "properties": {
    "gn:admin1_code":"ER",
    "gn:admin2_code":"13.0",
    "gn:admin3_code":"14.0",
    "gn:admin4_code":"140030.0",
    "gn:asciiname":"Gadhidanda",
    "gn:country_code":"NP",
    "gn:dem":607,
    "gn:feature_class":"P",
    "gn:feature_code":"PPLL",
    "gn:name":"Gadhidanda",
    "gn:population":0,
    "gn:timezone":"Asia/Kathmandu",
    "iso:country":"NP",
    "wof:name":"Gadhidanda",
    "wof:placetype":"locality"
},
  "geometry": {"coordinates":[86.43151999999998,26.99824000000001],"type":"Point"}
}