{
  "type": "Feature",
  "properties": {
    "gn:admin1_code":"FR",
    "gn:admin2_code":"14",
    "gn:admin3_code":"68",
    "gn:admin4_code":"680026",
    "gn:asciiname":"Lamatola",
    "gn:country_code":"NP",
    "gn:dem":1407,
    "gn:feature_class":"P",
    "gn:feature_code":"PPLL",
    "gn:name":"Lamatola",
    "gn:population":0,
    "gn:timezone":"Asia/Kathmandu",
    "iso:country":"NP",
    "name:ceb_x_preferred":[
        "Lamatola"
    ],
    "name:mai_x_preferred":[
        "\u0932\u093e\u092e\u093e\u0924\u094b\u0932\u093e"
    ],
    "name:msa_x_preferred":[
        "Lamatola"
    ],
    "name:nep_x_preferred":[
        "\u0932\u093e\u092e\u093e\u0924\u094b\u0932\u093e"
    ],
    "name:new_x_preferred":[
        "\u0932\u093e\u092e\u093e\u091f\u094b\u0932\u093e"
    ],
    "name:pol_x_preferred":[
        "Lamatola"
    ],
    "name:urd_x_preferred":[
        "\u0644\u0627\u0645\u0627\u0679\u0648\u0644\u0627"
    ],
    "wof:name":"Lamatola",
    "wof:placetype":"locality"
},
  "geometry": {"coordinates":[81.13974,29.46484],"type":"Point"}
}