{
  "type": "Feature",
  "properties": {
    "gn:admin1_code":"ER",
    "gn:admin2_code":"10",
    "gn:admin3_code":"4.0",
    "gn:admin4_code":"40025.0",
    "gn:asciiname":"Gauriyadhargaun",
    "gn:country_code":"NP",
    "gn:dem":88,
    "gn:feature_class":"P",
    "gn:feature_code":"PPLL",
    "gn:name":"Gauriyadhargaun",
    "gn:population":0,
    "gn:timezone":"Asia/Kathmandu",
    "iso:country":"NP",
    "wof:name":"Gauriyadhargaun",
    "wof:placetype":"locality"
},
  "geometry": {"coordinates":[87.69838,26.51024],"type":"Point"}
}