{
  "type": "Feature",
  "properties": {
    "gn:admin1_code":"CR",
    "gn:admin2_code":"11",
    "gn:admin3_code":"31",
    "gn:admin4_code":"310016",
    "gn:asciiname":"Pathibhara Deurali",
    "gn:country_code":"NP",
    "gn:dem":287,
    "gn:feature_class":"P",
    "gn:feature_code":"PPLL",
    "gn:name":"Pathibhara Deurali",
    "gn:population":0,
    "gn:timezone":"Asia/Kathmandu",
    "iso:country":"NP",
    "wof:name":"Pathibhara Deurali",
    "wof:placetype":"locality"
},
  "geometry": {"coordinates":[85.37907,27.34204],"type":"Point"}
}