{
  "type": "Feature",
  "properties": {
    "gn:admin1_code":"FR",
    "gn:admin2_code":"14",
    "gn:admin3_code":"69.0",
    "gn:admin4_code":"690011.0",
    "gn:asciiname":"Bhyakundesain",
    "gn:country_code":"NP",
    "gn:dem":1543,
    "gn:feature_class":"P",
    "gn:feature_code":"PPLL",
    "gn:name":"Bhyakundesain",
    "gn:population":0,
    "gn:timezone":"Asia/Kathmandu",
    "iso:country":"NP",
    "wof:name":"Bhyakundesain",
    "wof:placetype":"locality"
},
  "geometry": {"coordinates":[81.34709000000002,29.04192],"type":"Point"}
}