{
  "type": "Feature",
  "properties": {
    "gn:admin1_code":"WR",
    "gn:admin2_code":"4",
    "gn:admin3_code":"37",
    "gn:admin4_code":"370039",
    "gn:asciiname":"Nayagaun",
    "gn:country_code":"NP",
    "gn:dem":1267,
    "gn:feature_class":"P",
    "gn:feature_code":"PPLL",
    "gn:name":"Nayagaun",
    "gn:population":0,
    "gn:timezone":"Asia/Kathmandu",
    "iso:country":"NP",
    "name:msa_x_preferred":[
        "Nayagaun"
    ],
    "name:nep_x_preferred":[
        "\u0928\u092f\u093e\u0901\u0917\u093e\u0901\u0909"
    ],
    "wof:name":"Nayagaun",
    "wof:placetype":"locality"
},
  "geometry": {"coordinates":[84.30015999999998,28.25277],"type":"Point"}
}