{
  "type": "Feature",
  "properties": {
    "gn:admin1_code":"00",
    "gn:asciiname":"Phalate",
    "gn:country_code":"NP",
    "gn:dem":2521,
    "gn:feature_class":"P",
    "gn:feature_code":"PPL",
    "gn:name":"Phal\u0101\u0303\u1e6de",
    "gn:population":0,
    "gn:timezone":"Asia/Kathmandu",
    "iso:country":"NP",
    "name:und_x_variant":[
        "Phal\u0101\u0303\u1e6de",
        "Phal\u0101n\u1e6de"
    ],
    "wof:name":"Phalate",
    "wof:placetype":"locality"
},
  "geometry": {"coordinates":[85.96605,27.5889],"type":"Point"}
}