{
  "type": "Feature",
  "properties": {
    "gn:admin1_code":"WR",
    "gn:admin2_code":"4.0",
    "gn:admin3_code":"39.0",
    "gn:admin4_code":"390044.0",
    "gn:asciiname":"Batase",
    "gn:country_code":"NP",
    "gn:dem":941,
    "gn:feature_class":"P",
    "gn:feature_code":"PPLL",
    "gn:name":"Batase",
    "gn:population":0,
    "gn:timezone":"Asia/Kathmandu",
    "iso:country":"NP",
    "name:ceb_x_preferred":[
        "Batase"
    ],
    "name:pol_x_preferred":[
        "Batase"
    ],
    "wof:name":"Batase",
    "wof:placetype":"locality"
},
  "geometry": {"coordinates":[83.79829000000002,28.08304],"type":"Point"}
}