{
  "type": "Feature",
  "properties": {
    "gn:admin1_code":"CR",
    "gn:admin2_code":"1",
    "gn:admin3_code":"30.0",
    "gn:admin4_code":"300037.0",
    "gn:asciiname":"Ramche",
    "gn:country_code":"NP",
    "gn:dem":779,
    "gn:feature_class":"P",
    "gn:feature_code":"PPLL",
    "gn:name":"Ramche",
    "gn:population":0,
    "gn:timezone":"Asia/Kathmandu",
    "iso:country":"NP",
    "name:fra_x_preferred":[
        "Ramche"
    ],
    "name:new_x_preferred":[
        "\u0930\u093e\u092e\u094d\u091a\u0947"
    ],
    "name:pol_x_preferred":[
        "Ramche"
    ],
    "wof:name":"Ramche",
    "wof:placetype":"locality"
},
  "geometry": {"coordinates":[84.91502,27.78392],"type":"Point"}
}