{
  "type": "Feature",
  "properties": {
    "gn:admin1_code":"MR",
    "gn:admin2_code":"2.0",
    "gn:admin3_code":"57.0",
    "gn:admin4_code":"570033.0",
    "gn:asciiname":"Thukaila",
    "gn:country_code":"NP",
    "gn:dem":149,
    "gn:feature_class":"P",
    "gn:feature_code":"PPLL",
    "gn:name":"Thukaila",
    "gn:population":0,
    "gn:timezone":"Asia/Kathmandu",
    "iso:country":"NP",
    "wof:name":"Thukaila",
    "wof:placetype":"locality"
},
  "geometry": {"coordinates":[81.60563,28.042],"type":"Point"}
}