{
  "type": "Feature",
  "properties": {
    "gn:admin1_code":"ER",
    "gn:admin2_code":"13",
    "gn:admin3_code":"16",
    "gn:admin4_code":"160046",
    "gn:asciiname":"Itaharwa",
    "gn:country_code":"NP",
    "gn:dem":97,
    "gn:feature_class":"P",
    "gn:feature_code":"PPLL",
    "gn:name":"Itaharwa",
    "gn:population":0,
    "gn:timezone":"Asia/Kathmandu",
    "iso:country":"NP",
    "name:ceb_x_preferred":[
        "Itaharwa"
    ],
    "name:dty_x_preferred":[
        "\u0907\u091f\u0939\u0930\u094d\u0935\u093e"
    ],
    "name:mai_x_preferred":[
        "\u0907\u091f\u0939\u0930\u094d\u0935\u093e"
    ],
    "name:msa_x_preferred":[
        "Itaharwa"
    ],
    "name:nep_x_preferred":[
        "\u0907\u091f\u0939\u0930\u094d\u0935\u093e"
    ],
    "name:new_x_preferred":[
        "\u0907\u091f\u0930\u094d\u0939\u0935\u093e"
    ],
    "name:pol_x_preferred":[
        "Itaharwa"
    ],
    "wof:name":"Itaharwa",
    "wof:placetype":"locality"
},
  "geometry": {"coordinates":[86.50071,26.61815],"type":"Point"}
}