{
  "type": "Feature",
  "properties": {
    "gn:admin1_code":"ER",
    "gn:admin2_code":"10",
    "gn:admin3_code":"3.0",
    "gn:admin4_code":"30002.0",
    "gn:asciiname":"Nunsari Toribari",
    "gn:country_code":"NP",
    "gn:dem":224,
    "gn:feature_class":"P",
    "gn:feature_code":"PPLL",
    "gn:name":"Nunsari Toribari",
    "gn:population":0,
    "gn:timezone":"Asia/Kathmandu",
    "iso:country":"NP",
    "wof:name":"Nunsari Toribari",
    "wof:placetype":"locality"
},
  "geometry": {"coordinates":[87.67081999999998,26.76027],"type":"Point"}
}