{
  "type": "Feature",
  "properties": {
    "gn:admin1_code":"CR",
    "gn:admin2_code":"11",
    "gn:admin3_code":"31",
    "gn:admin4_code":"310018.0",
    "gn:asciiname":"Damar",
    "gn:country_code":"NP",
    "gn:dem":325,
    "gn:feature_class":"P",
    "gn:feature_code":"PPLL",
    "gn:name":"Damar",
    "gn:population":0,
    "gn:timezone":"Asia/Kathmandu",
    "iso:country":"NP",
    "name:aze_x_preferred":[
        "Damar sistemi"
    ],
    "name:ceb_x_preferred":[
        "Damar"
    ],
    "name:deu_x_preferred":[
        "Damar"
    ],
    "name:ind_x_preferred":[
        "Damar"
    ],
    "name:ita_x_preferred":[
        "Damar"
    ],
    "name:jav_x_preferred":[
        "Damar"
    ],
    "name:msa_x_preferred":[
        "Damar"
    ],
    "name:nld_x_preferred":[
        "Damar"
    ],
    "name:por_x_preferred":[
        "Damar"
    ],
    "name:swe_x_preferred":[
        "Damar"
    ],
    "name:tur_x_preferred":[
        "Damar"
    ],
    "wof:name":"Damar",
    "wof:placetype":"locality"
},
  "geometry": {"coordinates":[84.84934,27.49041],"type":"Point"}
}