{
  "type": "Feature",
  "properties": {
    "gn:admin1_code":"ER",
    "gn:admin2_code":"13.0",
    "gn:admin3_code":"14.0",
    "gn:admin4_code":"140040.0",
    "gn:asciiname":"Thamkharka",
    "gn:country_code":"NP",
    "gn:dem":1275,
    "gn:feature_class":"P",
    "gn:feature_code":"PPLL",
    "gn:name":"Thamkharka",
    "gn:population":0,
    "gn:timezone":"Asia/Kathmandu",
    "iso:country":"NP",
    "wof:name":"Thamkharka",
    "wof:placetype":"locality"
},
  "geometry": {"coordinates":[86.56108,27.11932],"type":"Point"}
}