{
  "type": "Feature",
  "properties": {
    "gn:admin1_code":"WR",
    "gn:admin2_code":"4.0",
    "gn:admin3_code":"38.0",
    "gn:admin4_code":"380046.0",
    "gn:asciiname":"Balendi",
    "gn:country_code":"NP",
    "gn:dem":585,
    "gn:feature_class":"P",
    "gn:feature_code":"PPLL",
    "gn:name":"Balendi",
    "gn:population":0,
    "gn:timezone":"Asia/Kathmandu",
    "iso:country":"NP",
    "wof:name":"Balendi",
    "wof:placetype":"locality"
},
  "geometry": {"coordinates":[84.16333,28.06742],"type":"Point"}
}