{
  "type": "Feature",
  "properties": {
    "gn:admin1_code":"MR",
    "gn:admin2_code":"12",
    "gn:admin3_code":"53",
    "gn:admin4_code":"530022",
    "gn:asciiname":"Jhenam",
    "gn:country_code":"NP",
    "gn:dem":1493,
    "gn:feature_class":"P",
    "gn:feature_code":"PPLL",
    "gn:name":"Jhenam",
    "gn:population":0,
    "gn:timezone":"Asia/Kathmandu",
    "iso:country":"NP",
    "name:ceb_x_preferred":[
        "Jhenam"
    ],
    "name:fra_x_preferred":[
        "Jhenam"
    ],
    "name:mai_x_preferred":[
        "\u091d\u0947\u0928\u093e\u092e"
    ],
    "name:msa_x_preferred":[
        "Jhenam"
    ],
    "name:nep_x_preferred":[
        "\u091d\u0947\u0928\u093e\u092e"
    ],
    "name:new_x_preferred":[
        "\u091d\u0947\u0928\u092e"
    ],
    "name:pol_x_preferred":[
        "Jhenam"
    ],
    "wof:name":"Jhenam",
    "wof:placetype":"locality"
},
  "geometry": {"coordinates":[82.45854,28.22861],"type":"Point"}
}