{
  "type": "Feature",
  "properties": {
    "gn:admin1_code":"WR",
    "gn:admin2_code":"4.0",
    "gn:admin3_code":"38.0",
    "gn:admin4_code":"380021.0",
    "gn:asciiname":"Khuimaryan",
    "gn:country_code":"NP",
    "gn:dem":786,
    "gn:feature_class":"P",
    "gn:feature_code":"PPLL",
    "gn:name":"Khuimaryan",
    "gn:population":0,
    "gn:timezone":"Asia/Kathmandu",
    "iso:country":"NP",
    "wof:name":"Khuimaryan",
    "wof:placetype":"locality"
},
  "geometry": {"coordinates":[83.98148,28.09709],"type":"Point"}
}