{
  "type": "Feature",
  "properties": {
    "gn:admin1_code":"WR",
    "gn:admin2_code":"8",
    "gn:admin3_code":"46.0",
    "gn:admin4_code":"460041.0",
    "gn:asciiname":"Bhedi Khalta",
    "gn:country_code":"NP",
    "gn:dem":1632,
    "gn:feature_class":"P",
    "gn:feature_code":"PPLL",
    "gn:name":"Bhedi Khalta",
    "gn:population":0,
    "gn:timezone":"Asia/Kathmandu",
    "iso:country":"NP",
    "wof:name":"Bhedi Khalta",
    "wof:placetype":"locality"
},
  "geometry": {"coordinates":[83.45402,28.1092],"type":"Point"}
}