{
  "type": "Feature",
  "properties": {
    "gn:admin1_code":"CR",
    "gn:admin2_code":"1",
    "gn:admin3_code":"28",
    "gn:admin4_code":"280027",
    "gn:asciiname":"Chhaharegaun",
    "gn:country_code":"NP",
    "gn:dem":1551,
    "gn:feature_class":"P",
    "gn:feature_code":"PPLL",
    "gn:name":"Chhaharegaun",
    "gn:population":0,
    "gn:timezone":"Asia/Kathmandu",
    "iso:country":"NP",
    "wof:name":"Chhaharegaun",
    "wof:placetype":"locality"
},
  "geometry": {"coordinates":[85.23039,27.82987],"type":"Point"}
}