{
  "type": "Feature",
  "properties": {
    "gn:admin1_code":"CR",
    "gn:admin2_code":"1",
    "gn:admin3_code":"24.0",
    "gn:admin4_code":"240072.0",
    "gn:asciiname":"Timilsinagaun",
    "gn:country_code":"NP",
    "gn:dem":1781,
    "gn:feature_class":"P",
    "gn:feature_code":"PPLL",
    "gn:name":"Timilsinagaun",
    "gn:population":0,
    "gn:timezone":"Asia/Kathmandu",
    "iso:country":"NP",
    "wof:name":"Timilsinagaun",
    "wof:placetype":"locality"
},
  "geometry": {"coordinates":[85.43040000000001,27.59373],"type":"Point"}
}