{
  "type": "Feature",
  "properties": {
    "gn:admin1_code":"ER",
    "gn:admin2_code":"13",
    "gn:admin3_code":"12",
    "gn:admin4_code":"120003.0",
    "gn:asciiname":"Jalkeni",
    "gn:country_code":"NP",
    "gn:dem":1173,
    "gn:feature_class":"P",
    "gn:feature_code":"PPLL",
    "gn:name":"Jalkeni",
    "gn:population":0,
    "gn:timezone":"Asia/Kathmandu",
    "iso:country":"NP",
    "wof:name":"Jalkeni",
    "wof:placetype":"locality"
},
  "geometry": {"coordinates":[86.35472,27.22446],"type":"Point"}
}