{
  "type": "Feature",
  "properties": {
    "gn:admin1_code":"ER",
    "gn:admin2_code":"7",
    "gn:admin3_code":"9",
    "gn:admin4_code":"90031",
    "gn:asciiname":"Sibhuwa",
    "gn:country_code":"NP",
    "gn:dem":830,
    "gn:feature_class":"P",
    "gn:feature_code":"PPLL",
    "gn:name":"Sibhuwa",
    "gn:population":0,
    "gn:timezone":"Asia/Kathmandu",
    "iso:country":"NP",
    "wof:name":"Sibhuwa",
    "wof:placetype":"locality"
},
  "geometry": {"coordinates":[87.30019,27.35938],"type":"Point"}
}