{
  "type": "Feature",
  "properties": {
    "gn:admin1_code":"WR",
    "gn:admin2_code":"3",
    "gn:admin3_code":"45.0",
    "gn:admin4_code":"450001.0",
    "gn:asciiname":"Kiri",
    "gn:country_code":"NP",
    "gn:dem":2210,
    "gn:feature_class":"P",
    "gn:feature_code":"PPLL",
    "gn:name":"Kiri",
    "gn:population":0,
    "gn:timezone":"Asia/Kathmandu",
    "iso:country":"NP",
    "name:ceb_x_preferred":[
        "Kiri"
    ],
    "name:deu_x_preferred":[
        "Kiri"
    ],
    "name:est_x_preferred":[
        "Kiri"
    ],
    "name:fas_x_preferred":[
        "\u06a9\u06cc\u0631\u06cc"
    ],
    "name:fin_x_preferred":[
        "Kiri"
    ],
    "name:fra_x_preferred":[
        "Kiri"
    ],
    "name:ind_x_preferred":[
        "Kiri"
    ],
    "name:ron_x_preferred":[
        "Kiri"
    ],
    "name:spa_x_preferred":[
        "Kiri"
    ],
    "name:swe_x_preferred":[
        "Kiri"
    ],
    "name:ukr_x_preferred":[
        "\u041a\u0456\u0440\u0456"
    ],
    "wof:name":"Kiri",
    "wof:placetype":"locality"
},
  "geometry": {"coordinates":[83.22844000000001,28.39442],"type":"Point"}
}