{
  "type": "Feature",
  "properties": {
    "gn:admin1_code":"WR",
    "gn:admin2_code":"3",
    "gn:admin3_code":"45.0",
    "gn:admin4_code":"450001.0",
    "gn:asciiname":"Kiri",
    "gn:country_code":"NP",
    "gn:dem":2210,
    "gn:feature_class":"P",
    "gn:feature_code":"PPLL",
    "gn:name":"Kiri",
    "gn:population":0,
    "gn:timezone":"Asia/Kathmandu",
    "iso:country":"NP",
    "wof:name":"Kiri",
    "wof:placetype":"locality"
},
  "geometry": {"coordinates":[83.22844000000001,28.39442],"type":"Point"}
}