{
  "type": "Feature",
  "properties": {
    "gn:admin1_code":"ER",
    "gn:admin2_code":"13",
    "gn:admin3_code":"13.0",
    "gn:admin4_code":"130014.0",
    "gn:asciiname":"Khiraule",
    "gn:country_code":"NP",
    "gn:dem":1945,
    "gn:feature_class":"P",
    "gn:feature_code":"PPLL",
    "gn:name":"Khiraule",
    "gn:population":0,
    "gn:timezone":"Asia/Kathmandu",
    "iso:country":"NP",
    "wof:name":"Khiraule",
    "wof:placetype":"locality"
},
  "geometry": {"coordinates":[86.84641999999999,27.1221],"type":"Point"}
}