{
  "type": "Feature",
  "properties": {
    "gn:admin1_code":"CR",
    "gn:admin2_code":"1",
    "gn:admin3_code":"23",
    "gn:admin4_code":"230058",
    "gn:asciiname":"Majhigaun",
    "gn:country_code":"NP",
    "gn:dem":756,
    "gn:feature_class":"P",
    "gn:feature_code":"PPLL",
    "gn:name":"Majhigaun",
    "gn:population":0,
    "gn:timezone":"Asia/Kathmandu",
    "iso:country":"NP",
    "wof:name":"Majhigaun",
    "wof:placetype":"locality"
},
  "geometry": {"coordinates":[85.70066,27.66404],"type":"Point"}
}