{
  "type": "Feature",
  "properties": {
    "gn:admin1_code":"WR",
    "gn:admin2_code":"8",
    "gn:admin3_code":"50.0",
    "gn:admin4_code":"500057.0",
    "gn:asciiname":"Amarlonaha",
    "gn:country_code":"NP",
    "gn:dem":96,
    "gn:feature_class":"P",
    "gn:feature_code":"PPLL",
    "gn:name":"Amarlonaha",
    "gn:population":0,
    "gn:timezone":"Asia/Kathmandu",
    "iso:country":"NP",
    "wof:name":"Amarlonaha",
    "wof:placetype":"locality"
},
  "geometry": {"coordinates":[83.04685000000001,27.48772],"type":"Point"}
}