{
  "type": "Feature",
  "properties": {
    "gn:admin1_code":"WR",
    "gn:admin2_code":"3",
    "gn:admin3_code":"44",
    "gn:admin4_code":"440047",
    "gn:asciiname":"Dhubibot",
    "gn:country_code":"NP",
    "gn:dem":1279,
    "gn:feature_class":"P",
    "gn:feature_code":"PPLL",
    "gn:name":"Dhubibot",
    "gn:population":0,
    "gn:timezone":"Asia/Kathmandu",
    "iso:country":"NP",
    "wof:name":"Dhubibot",
    "wof:placetype":"locality"
},
  "geometry": {"coordinates":[83.69918,28.18687000000001],"type":"Point"}
}