{
  "type": "Feature",
  "properties": {
    "gn:admin1_code":"CR",
    "gn:admin2_code":"5",
    "gn:admin3_code":"19",
    "gn:admin4_code":"190076",
    "gn:asciiname":"Bhadaure",
    "gn:country_code":"NP",
    "gn:dem":274,
    "gn:feature_class":"P",
    "gn:feature_code":"PPLL",
    "gn:name":"Bhadaure",
    "gn:population":0,
    "gn:timezone":"Asia/Kathmandu",
    "iso:country":"NP",
    "name:pol_x_preferred":[
        "Bhadaure"
    ],
    "wof:name":"Bhadaure",
    "wof:placetype":"locality"
},
  "geometry": {"coordinates":[85.77424000000001,27.07136],"type":"Point"}
}