{
  "type": "Feature",
  "properties": {
    "gn:admin1_code":"MR",
    "gn:admin2_code":"12",
    "gn:admin3_code":"54",
    "gn:admin4_code":"540025",
    "gn:asciiname":"Daning",
    "gn:country_code":"NP",
    "gn:dem":1872,
    "gn:feature_class":"P",
    "gn:feature_code":"PPLL",
    "gn:name":"Daning",
    "gn:population":0,
    "gn:timezone":"Asia/Kathmandu",
    "iso:country":"NP",
    "name:ceb_x_preferred":[
        "Daning"
    ],
    "wof:name":"Daning",
    "wof:placetype":"locality"
},
  "geometry": {"coordinates":[82.69837,28.55399],"type":"Point"}
}