{
  "type": "Feature",
  "properties": {
    "gn:admin1_code":"ER",
    "gn:admin2_code":"13.0",
    "gn:admin3_code":"14.0",
    "gn:admin4_code":"140008.0",
    "gn:asciiname":"Okhreni",
    "gn:country_code":"NP",
    "gn:dem":1532,
    "gn:feature_class":"P",
    "gn:feature_code":"PPLL",
    "gn:name":"Okhreni",
    "gn:population":0,
    "gn:timezone":"Asia/Kathmandu",
    "iso:country":"NP",
    "wof:name":"Okhreni",
    "wof:placetype":"locality"
},
  "geometry": {"coordinates":[86.62724,26.9886],"type":"Point"}
}