{
  "type": "Feature",
  "properties": {
    "gn:admin1_code":"WR",
    "gn:admin2_code":"4",
    "gn:admin3_code":"40.0",
    "gn:admin4_code":"400032.0",
    "gn:asciiname":"Himalaya Tol",
    "gn:country_code":"NP",
    "gn:dem":831,
    "gn:feature_class":"P",
    "gn:feature_code":"PPLL",
    "gn:name":"Himalaya Tol",
    "gn:population":0,
    "gn:timezone":"Asia/Kathmandu",
    "iso:country":"NP",
    "wof:name":"Himalaya Tol",
    "wof:placetype":"locality"
},
  "geometry": {"coordinates":[83.9817,28.20386],"type":"Point"}
}