{
  "type": "Feature",
  "properties": {
    "gn:admin1_code":"FR",
    "gn:admin2_code":"14",
    "gn:admin3_code":"69.0",
    "gn:admin4_code":"690065.0",
    "gn:asciiname":"Raskanda",
    "gn:country_code":"NP",
    "gn:dem":1116,
    "gn:feature_class":"P",
    "gn:feature_code":"PPLL",
    "gn:name":"Raskanda",
    "gn:population":0,
    "gn:timezone":"Asia/Kathmandu",
    "iso:country":"NP",
    "wof:name":"Raskanda",
    "wof:placetype":"locality"
},
  "geometry": {"coordinates":[81.2015,29.25281],"type":"Point"}
}