{
  "type": "Feature",
  "properties": {
    "gn:admin1_code":"FR",
    "gn:admin2_code":"9",
    "gn:admin3_code":"74",
    "gn:admin4_code":"740038",
    "gn:asciiname":"Bikuli",
    "gn:country_code":"NP",
    "gn:dem":1743,
    "gn:feature_class":"P",
    "gn:feature_code":"PPLL",
    "gn:name":"Bikuli",
    "gn:population":0,
    "gn:timezone":"Asia/Kathmandu",
    "iso:country":"NP",
    "wof:name":"Bikuli",
    "wof:placetype":"locality"
},
  "geometry": {"coordinates":[80.5673,29.54501],"type":"Point"}
}