{
  "type": "Feature",
  "properties": {
    "gn:admin1_code":"FR",
    "gn:admin2_code":"14",
    "gn:admin3_code":"71.0",
    "gn:admin4_code":"710023.0",
    "gn:asciiname":"Chaukidada",
    "gn:country_code":"NP",
    "gn:dem":199,
    "gn:feature_class":"P",
    "gn:feature_code":"PPLL",
    "gn:name":"Chaukidada",
    "gn:population":0,
    "gn:timezone":"Asia/Kathmandu",
    "iso:country":"NP",
    "wof:name":"Chaukidada",
    "wof:placetype":"locality"
},
  "geometry": {"coordinates":[80.53572,28.82305],"type":"Point"}
}