{
  "type": "Feature",
  "properties": {
    "gn:admin1_code":"MR",
    "gn:admin2_code":"2.0",
    "gn:admin3_code":"59.0",
    "gn:admin4_code":"590006.0",
    "gn:asciiname":"Rag",
    "gn:country_code":"NP",
    "gn:dem":292,
    "gn:feature_class":"P",
    "gn:feature_code":"PPLL",
    "gn:name":"Rag",
    "gn:population":0,
    "gn:timezone":"Asia/Kathmandu",
    "iso:country":"NP",
    "name:ceb_x_preferred":[
        "Rag"
    ],
    "name:deu_x_preferred":[
        "Rag"
    ],
    "name:jpn_x_preferred":[
        "\u30e9\u30b0"
    ],
    "name:nld_x_preferred":[
        "Rag"
    ],
    "name:spa_x_preferred":[
        "Rag"
    ],
    "name:swe_x_preferred":[
        "Rag"
    ],
    "wof:name":"Rag",
    "wof:placetype":"locality"
},
  "geometry": {"coordinates":[81.333,28.79577],"type":"Point"}
}