{
  "type": "Feature",
  "properties": {
    "gn:admin1_code":"FR",
    "gn:admin2_code":"9",
    "gn:admin3_code":"75.0",
    "gn:admin4_code":"750019.0",
    "gn:asciiname":"Saneda",
    "gn:country_code":"NP",
    "gn:dem":1460,
    "gn:feature_class":"P",
    "gn:feature_code":"PPLL",
    "gn:name":"Saneda",
    "gn:population":0,
    "gn:timezone":"Asia/Kathmandu",
    "iso:country":"NP",
    "wof:name":"Saneda",
    "wof:placetype":"locality"
},
  "geometry": {"coordinates":[80.43831,29.71927],"type":"Point"}
}