{
  "type": "Feature",
  "properties": {
    "gn:admin1_code":"CR",
    "gn:admin2_code":"1.0",
    "gn:asciiname":"Hari Bdr Tamang House",
    "gn:country_code":"NP",
    "gn:dem":1703,
    "gn:feature_class":"P",
    "gn:feature_code":"PPL",
    "gn:name":"Hari Bdr Tamang House",
    "gn:population":10000,
    "gn:timezone":"Asia/Kathmandu",
    "iso:country":"NP",
    "wof:name":"Hari Bdr Tamang House",
    "wof:placetype":"locality",
    "wof:population":10000
},
  "geometry": {"coordinates":[85.45893000000002,27.6289],"type":"Point"}
}