{
  "type": "Feature",
  "properties": {
    "gn:admin1_code":"00",
    "gn:asciiname":"Angbung",
    "gn:country_code":"NP",
    "gn:dem":915,
    "gn:feature_class":"P",
    "gn:feature_code":"PPL",
    "gn:name":"\u0100ngbung",
    "gn:population":0,
    "gn:timezone":"Asia/Kathmandu",
    "iso:country":"NP",
    "wof:name":"Angbung",
    "wof:placetype":"locality"
},
  "geometry": {"coordinates":[87.70206999999998,27.26333],"type":"Point"}
}