{
  "type": "Feature",
  "properties": {
    "gn:admin1_code":"MR",
    "gn:admin2_code":"2",
    "gn:admin3_code":"60.0",
    "gn:admin4_code":"600036.0",
    "gn:asciiname":"Sajpani",
    "gn:country_code":"NP",
    "gn:dem":1323,
    "gn:feature_class":"P",
    "gn:feature_code":"PPLL",
    "gn:name":"Sajpani",
    "gn:population":0,
    "gn:timezone":"Asia/Kathmandu",
    "iso:country":"NP",
    "wof:name":"Sajpani",
    "wof:placetype":"locality"
},
  "geometry": {"coordinates":[81.58083000000001,28.81875],"type":"Point"}
}