{
  "type": "Feature",
  "properties": {
    "gn:admin1_code":"WR",
    "gn:admin2_code":"4.0",
    "gn:admin3_code":"39.0",
    "gn:admin4_code":"390053.0",
    "gn:asciiname":"Dhanmuda",
    "gn:country_code":"NP",
    "gn:dem":891,
    "gn:feature_class":"P",
    "gn:feature_code":"PPLL",
    "gn:name":"Dhanmuda",
    "gn:population":0,
    "gn:timezone":"Asia/Kathmandu",
    "iso:country":"NP",
    "wof:name":"Dhanmuda",
    "wof:placetype":"locality"
},
  "geometry": {"coordinates":[83.69738000000002,27.99407],"type":"Point"}
}