{
  "type": "Feature",
  "properties": {
    "gn:admin1_code":"WR",
    "gn:admin2_code":"8",
    "gn:admin3_code":"50.0",
    "gn:admin4_code":"500019.0",
    "gn:asciiname":"Kharindrapur",
    "gn:country_code":"NP",
    "gn:dem":118,
    "gn:feature_class":"P",
    "gn:feature_code":"PPLL",
    "gn:name":"Kharindrapur",
    "gn:population":0,
    "gn:timezone":"Asia/Kathmandu",
    "iso:country":"NP",
    "wof:name":"Kharindrapur",
    "wof:placetype":"locality"
},
  "geometry": {"coordinates":[82.90170000000001,27.64605],"type":"Point"}
}