{
  "type": "Feature",
  "properties": {
    "gn:admin1_code":"00",
    "gn:asciiname":"Namai",
    "gn:country_code":"NP",
    "gn:dem":253,
    "gn:feature_class":"P",
    "gn:feature_code":"PPL",
    "gn:name":"Nam\u0101i",
    "gn:population":0,
    "gn:timezone":"Asia/Kathmandu",
    "iso:country":"NP",
    "wof:name":"Namai",
    "wof:placetype":"locality"
},
  "geometry": {"coordinates":[82.51499,27.85997],"type":"Point"}
}