{
  "type": "Feature",
  "properties": {
    "gn:admin1_code":"00",
    "gn:asciiname":"Khorondada",
    "gn:country_code":"NP",
    "gn:dem":1848,
    "gn:feature_class":"P",
    "gn:feature_code":"PPL",
    "gn:name":"Khoro\u1e45\u1e0d\u0101\u0303\u1e0d\u0101",
    "gn:population":0,
    "gn:timezone":"Asia/Kathmandu",
    "iso:country":"NP",
    "name:und_x_variant":[
        "Khoro\u1e45\u1e0d\u0101\u0303\u1e0d\u0101",
        "Khoro\u1e45\u1e0d\u0101n\u1e0d\u0101"
    ],
    "wof:name":"Khorondada",
    "wof:placetype":"locality"
},
  "geometry": {"coordinates":[85.53715,27.52649000000001],"type":"Point"}
}