{
  "type": "Feature",
  "properties": {
    "gn:admin1_code":"FR",
    "gn:admin2_code":"14",
    "gn:admin3_code":"70.0",
    "gn:admin4_code":"700047.0",
    "gn:asciiname":"Sinki Chunna",
    "gn:country_code":"NP",
    "gn:dem":1966,
    "gn:feature_class":"P",
    "gn:feature_code":"PPLL",
    "gn:name":"Sinki Chunna",
    "gn:population":0,
    "gn:timezone":"Asia/Kathmandu",
    "iso:country":"NP",
    "wof:name":"Sinki Chunna",
    "wof:placetype":"locality"
},
  "geometry": {"coordinates":[80.80171999999997,29.21273],"type":"Point"}
}