{
  "type": "Feature",
  "properties": {
    "gn:admin1_code":"MR",
    "gn:admin2_code":"12",
    "gn:admin3_code":"54",
    "gn:admin4_code":"540006",
    "gn:asciiname":"Khutti",
    "gn:country_code":"NP",
    "gn:dem":975,
    "gn:feature_class":"P",
    "gn:feature_code":"PPLL",
    "gn:name":"Khutti",
    "gn:population":0,
    "gn:timezone":"Asia/Kathmandu",
    "iso:country":"NP",
    "wof:name":"Khutti",
    "wof:placetype":"locality"
},
  "geometry": {"coordinates":[82.24861,28.63477],"type":"Point"}
}