{
  "type": "Feature",
  "properties": {
    "gn:admin1_code":"WR",
    "gn:admin2_code":"3",
    "gn:admin3_code":"42",
    "gn:admin4_code":"420015",
    "gn:asciiname":"Selibung",
    "gn:country_code":"NP",
    "gn:dem":6057,
    "gn:feature_class":"P",
    "gn:feature_code":"PPLL",
    "gn:name":"Selibung",
    "gn:population":0,
    "gn:timezone":"Asia/Kathmandu",
    "iso:country":"NP",
    "wof:name":"Selibung",
    "wof:placetype":"locality"
},
  "geometry": {"coordinates":[84.16789,28.88604],"type":"Point"}
}