{
  "type": "Feature",
  "properties": {
    "gn:admin1_code":"WR",
    "gn:admin2_code":"4",
    "gn:admin3_code":"40.0",
    "gn:admin4_code":"400043.0",
    "gn:asciiname":"Udulke",
    "gn:country_code":"NP",
    "gn:dem":1447,
    "gn:feature_class":"P",
    "gn:feature_code":"PPLL",
    "gn:name":"Udulke",
    "gn:population":0,
    "gn:timezone":"Asia/Kathmandu",
    "iso:country":"NP",
    "wof:name":"Udulke",
    "wof:placetype":"locality"
},
  "geometry": {"coordinates":[84.11479,28.2609],"type":"Point"}
}