{
  "type": "Feature",
  "properties": {
    "gn:admin1_code":"WR",
    "gn:admin2_code":"3",
    "gn:admin3_code":"45.0",
    "gn:admin4_code":"450024.0",
    "gn:asciiname":"Jhule",
    "gn:country_code":"NP",
    "gn:dem":1775,
    "gn:feature_class":"P",
    "gn:feature_code":"PPLL",
    "gn:name":"Jhule",
    "gn:population":0,
    "gn:timezone":"Asia/Kathmandu",
    "iso:country":"NP",
    "name:bih_x_preferred":[
        "\u091d\u0941\u0932\u0947"
    ],
    "name:ceb_x_preferred":[
        "Jhule"
    ],
    "name:mai_x_preferred":[
        "\u091d\u0941\u0932\u0947"
    ],
    "name:msa_x_preferred":[
        "Jhule"
    ],
    "name:nep_x_preferred":[
        "\u091d\u0941\u0932\u0947"
    ],
    "name:new_x_preferred":[
        "\u091d\u0941\u0932\u0947"
    ],
    "name:pol_x_preferred":[
        "Jhule"
    ],
    "wof:name":"Jhule",
    "wof:placetype":"locality"
},
  "geometry": {"coordinates":[83.52391999999998,28.15892],"type":"Point"}
}