{
  "type": "Feature",
  "properties": {
    "gn:admin1_code":"WR",
    "gn:admin2_code":"3",
    "gn:admin3_code":"44",
    "gn:admin4_code":"440027",
    "gn:asciiname":"Amphidanda",
    "gn:country_code":"NP",
    "gn:dem":1203,
    "gn:feature_class":"P",
    "gn:feature_code":"PPLL",
    "gn:name":"Amphidanda",
    "gn:population":0,
    "gn:timezone":"Asia/Kathmandu",
    "iso:country":"NP",
    "wof:name":"Amphidanda",
    "wof:placetype":"locality"
},
  "geometry": {"coordinates":[83.76151999999998,28.17285],"type":"Point"}
}