{
  "type": "Feature",
  "properties": {
    "gn:admin1_code":"CR",
    "gn:admin2_code":"1",
    "gn:admin3_code":"28",
    "gn:admin4_code":"280002.0",
    "gn:asciiname":"Kamare",
    "gn:country_code":"NP",
    "gn:dem":1001,
    "gn:feature_class":"P",
    "gn:feature_code":"PPLL",
    "gn:name":"Kamare",
    "gn:population":0,
    "gn:timezone":"Asia/Kathmandu",
    "iso:country":"NP",
    "name:ceb_x_preferred":[
        "Kamare"
    ],
    "name:swe_x_preferred":[
        "Kamare"
    ],
    "wof:name":"Kamare",
    "wof:placetype":"locality"
},
  "geometry": {"coordinates":[85.36993000000002,27.91758],"type":"Point"}
}