{
  "type": "Feature",
  "properties": {
    "gn:admin1_code":"ER",
    "gn:admin2_code":"13",
    "gn:admin3_code":"11",
    "gn:admin4_code":"110024",
    "gn:asciiname":"Lamsumna Goth",
    "gn:country_code":"NP",
    "gn:dem":5386,
    "gn:feature_class":"P",
    "gn:feature_code":"PPLL",
    "gn:name":"Lamsumna Goth",
    "gn:population":0,
    "gn:timezone":"Asia/Kathmandu",
    "iso:country":"NP",
    "wof:name":"Lamsumna Goth",
    "wof:placetype":"locality"
},
  "geometry": {"coordinates":[86.63088,28.02958],"type":"Point"}
}