{
  "type": "Feature",
  "properties": {
    "gn:admin1_code":"WR",
    "gn:admin2_code":"4.0",
    "gn:admin3_code":"39.0",
    "gn:admin4_code":"390001.0",
    "gn:asciiname":"Pipaldanda",
    "gn:country_code":"NP",
    "gn:dem":1022,
    "gn:feature_class":"P",
    "gn:feature_code":"PPLL",
    "gn:name":"Pipaldanda",
    "gn:population":0,
    "gn:timezone":"Asia/Kathmandu",
    "iso:country":"NP",
    "name:msa_x_preferred":[
        "Pipaldanda"
    ],
    "name:nep_x_preferred":[
        "\u092a\u093f\u092a\u0932\u0921\u093e\u0901\u0921\u093e"
    ],
    "name:new_x_preferred":[
        "\u092a\u093f\u092a\u0932\u0921\u093e\u0902\u0921\u093e \u0917\u093e\u0935\u093f\u0938"
    ],
    "name:pol_x_preferred":[
        "Pipaldanda"
    ],
    "wof:name":"Pipaldanda",
    "wof:placetype":"locality"
},
  "geometry": {"coordinates":[83.5046,27.94871],"type":"Point"}
}