{
  "type": "Feature",
  "properties": {
    "gn:admin1_code":"WR",
    "gn:admin2_code":"4",
    "gn:admin3_code":"40.0",
    "gn:admin4_code":"400010.0",
    "gn:asciiname":"Lakurkot",
    "gn:country_code":"NP",
    "gn:dem":1315,
    "gn:feature_class":"P",
    "gn:feature_code":"PPLL",
    "gn:name":"Lakurkot",
    "gn:population":0,
    "gn:timezone":"Asia/Kathmandu",
    "iso:country":"NP",
    "wof:name":"Lakurkot",
    "wof:placetype":"locality"
},
  "geometry": {"coordinates":[83.866,28.27873],"type":"Point"}
}