{
  "type": "Feature",
  "properties": {
    "gn:admin1_code":"CR",
    "gn:admin2_code":"11",
    "gn:admin3_code":"34",
    "gn:admin4_code":"340068",
    "gn:asciiname":"Jhalamahiya",
    "gn:country_code":"NP",
    "gn:dem":87,
    "gn:feature_class":"P",
    "gn:feature_code":"PPLL",
    "gn:name":"Jhalamahiya",
    "gn:population":0,
    "gn:timezone":"Asia/Kathmandu",
    "iso:country":"NP",
    "wof:name":"Jhalamahiya",
    "wof:placetype":"locality"
},
  "geometry": {"coordinates":[84.66129000000002,27.05701],"type":"Point"}
}