{
  "type": "Feature",
  "properties": {
    "gn:admin1_code":"CR",
    "gn:admin2_code":"5",
    "gn:admin3_code":"18",
    "gn:admin4_code":"180022.0",
    "gn:asciiname":"Dhirapur",
    "gn:country_code":"NP",
    "gn:dem":65,
    "gn:feature_class":"P",
    "gn:feature_code":"PPLL",
    "gn:name":"Dhirapur",
    "gn:population":0,
    "gn:timezone":"Asia/Kathmandu",
    "iso:country":"NP",
    "wof:name":"Dhirapur",
    "wof:placetype":"locality"
},
  "geometry": {"coordinates":[85.84209,26.64519],"type":"Point"}
}