{
  "type": "Feature",
  "properties": {
    "gn:admin1_code":"WR",
    "gn:admin2_code":"3",
    "gn:admin3_code":"42",
    "gn:admin4_code":"420010",
    "gn:asciiname":"Kunjo",
    "gn:country_code":"NP",
    "gn:dem":2715,
    "gn:feature_class":"P",
    "gn:feature_code":"PPLL",
    "gn:name":"Kunjo",
    "gn:population":0,
    "gn:timezone":"Asia/Kathmandu",
    "iso:country":"NP",
    "name:ceb_x_preferred":[
        "Kunjo"
    ],
    "name:deu_x_preferred":[
        "Kunjo"
    ],
    "name:dty_x_preferred":[
        "\u0915\u0941\u091e\u094d\u091c\u094b"
    ],
    "name:fra_x_preferred":[
        "Kunjo"
    ],
    "name:msa_x_preferred":[
        "Kunjo"
    ],
    "name:nep_x_preferred":[
        "\u0915\u0941\u091e\u094d\u091c\u094b"
    ],
    "name:new_x_preferred":[
        "\u0915\u0941\u0902\u091c\u094b"
    ],
    "name:pol_x_preferred":[
        "Kunjo"
    ],
    "name:por_x_preferred":[
        "Kunjo"
    ],
    "wof:name":"Kunjo",
    "wof:placetype":"locality"
},
  "geometry": {"coordinates":[83.63558,28.65488],"type":"Point"}
}