{
  "type": "Feature",
  "properties": {
    "gn:admin1_code":"00",
    "gn:asciiname":"Chyachaur",
    "gn:country_code":"NP",
    "gn:dem":1987,
    "gn:feature_class":"P",
    "gn:feature_code":"PPL",
    "gn:name":"Chy\u0101chaur",
    "gn:population":0,
    "gn:timezone":"Asia/Kathmandu",
    "iso:country":"NP",
    "wof:name":"Chyachaur",
    "wof:placetype":"locality"
},
  "geometry": {"coordinates":[85.82096999999997,27.68303],"type":"Point"}
}