{
  "type": "Feature",
  "properties": {
    "gn:admin1_code":"FR",
    "gn:admin2_code":"9",
    "gn:admin3_code":"75.0",
    "gn:admin4_code":"750004.0",
    "gn:asciiname":"Nampa Chuli",
    "gn:country_code":"NP",
    "gn:dem":6445,
    "gn:feature_class":"P",
    "gn:feature_code":"PPLL",
    "gn:name":"Nampa Chuli",
    "gn:population":0,
    "gn:timezone":"Asia/Kathmandu",
    "iso:country":"NP",
    "wof:name":"Nampa Chuli",
    "wof:placetype":"locality"
},
  "geometry": {"coordinates":[81.0167,29.98216],"type":"Point"}
}