{
  "type": "Feature",
  "properties": {
    "gn:admin1_code":"MR",
    "gn:admin2_code":"2",
    "gn:admin3_code":"61.0",
    "gn:admin4_code":"610019.0",
    "gn:asciiname":"Chiplekadh Danda",
    "gn:country_code":"NP",
    "gn:dem":3261,
    "gn:feature_class":"P",
    "gn:feature_code":"PPLL",
    "gn:name":"Chiplekadh Danda",
    "gn:population":0,
    "gn:timezone":"Asia/Kathmandu",
    "iso:country":"NP",
    "wof:name":"Chiplekadh Danda",
    "wof:placetype":"locality"
},
  "geometry": {"coordinates":[82.07987,28.90697],"type":"Point"}
}