{
  "type": "Feature",
  "properties": {
    "gn:admin1_code":"WR",
    "gn:admin2_code":"3",
    "gn:admin3_code":"42",
    "gn:admin4_code":"420008",
    "gn:asciiname":"Lembeebuk",
    "gn:country_code":"NP",
    "gn:dem":3028,
    "gn:feature_class":"P",
    "gn:feature_code":"PPLL",
    "gn:name":"Lembeebuk",
    "gn:population":0,
    "gn:timezone":"Asia/Kathmandu",
    "iso:country":"NP",
    "wof:name":"Lembeebuk",
    "wof:placetype":"locality"
},
  "geometry": {"coordinates":[83.80064,28.83513],"type":"Point"}
}