{
  "type": "Feature",
  "properties": {
    "gn:admin1_code":"ER",
    "gn:admin2_code":"13",
    "gn:admin3_code":"15",
    "gn:admin4_code":"150089",
    "gn:asciiname":"Garuraha",
    "gn:country_code":"NP",
    "gn:dem":128,
    "gn:feature_class":"P",
    "gn:feature_code":"PPLL",
    "gn:name":"Garuraha",
    "gn:population":0,
    "gn:timezone":"Asia/Kathmandu",
    "iso:country":"NP",
    "wof:name":"Garuraha",
    "wof:placetype":"locality"
},
  "geometry": {"coordinates":[86.58723000000001,26.6446],"type":"Point"}
}