{
  "type": "Feature",
  "properties": {
    "gn:admin1_code":"WR",
    "gn:admin2_code":"4",
    "gn:admin3_code":"40.0",
    "gn:admin4_code":"400022.0",
    "gn:asciiname":"Dhakalthar",
    "gn:country_code":"NP",
    "gn:dem":670,
    "gn:feature_class":"P",
    "gn:feature_code":"PPLL",
    "gn:name":"Dhakalthar",
    "gn:population":0,
    "gn:timezone":"Asia/Kathmandu",
    "iso:country":"NP",
    "wof:name":"Dhakalthar",
    "wof:placetype":"locality"
},
  "geometry": {"coordinates":[84.11492,28.13217],"type":"Point"}
}