{
  "type": "Feature",
  "properties": {
    "gn:admin1_code":"WR",
    "gn:admin2_code":"4.0",
    "gn:admin3_code":"39.0",
    "gn:admin4_code":"390052.0",
    "gn:asciiname":"Khoriya",
    "gn:country_code":"NP",
    "gn:dem":885,
    "gn:feature_class":"P",
    "gn:feature_code":"PPLL",
    "gn:name":"Khoriya",
    "gn:population":0,
    "gn:timezone":"Asia/Kathmandu",
    "iso:country":"NP",
    "wof:name":"Khoriya",
    "wof:placetype":"locality"
},
  "geometry": {"coordinates":[83.58896999999997,27.96738],"type":"Point"}
}