{
  "type": "Feature",
  "properties": {
    "gn:admin1_code":"WR",
    "gn:admin2_code":"4",
    "gn:admin3_code":"40.0",
    "gn:admin4_code":"400032.0",
    "gn:asciiname":"Bichari Chok",
    "gn:country_code":"NP",
    "gn:dem":873,
    "gn:feature_class":"P",
    "gn:feature_code":"PPLL",
    "gn:name":"Bichari Chok",
    "gn:population":0,
    "gn:timezone":"Asia/Kathmandu",
    "iso:country":"NP",
    "wof:name":"Bichari Chok",
    "wof:placetype":"locality"
},
  "geometry": {"coordinates":[83.97766999999997,28.22129],"type":"Point"}
}