{
  "type": "Feature",
  "properties": {
    "gn:admin1_code":"ER",
    "gn:admin2_code":"10.0",
    "gn:admin3_code":"1.0",
    "gn:admin4_code":"10015.0",
    "gn:asciiname":"Lorindin",
    "gn:country_code":"NP",
    "gn:dem":846,
    "gn:feature_class":"P",
    "gn:feature_code":"PPLL",
    "gn:name":"Lorindin",
    "gn:population":0,
    "gn:timezone":"Asia/Kathmandu",
    "iso:country":"NP",
    "wof:name":"Lorindin",
    "wof:placetype":"locality"
},
  "geometry": {"coordinates":[87.67855,27.40441],"type":"Point"}
}