{
  "type": "Feature",
  "properties": {
    "gn:admin1_code":"FR",
    "gn:admin2_code":"14",
    "gn:admin3_code":"70.0",
    "gn:admin4_code":"700010.0",
    "gn:asciiname":"Batukar kharka",
    "gn:country_code":"NP",
    "gn:dem":1605,
    "gn:feature_class":"P",
    "gn:feature_code":"PPLL",
    "gn:name":"Batukar kharka",
    "gn:population":0,
    "gn:timezone":"Asia/Kathmandu",
    "iso:country":"NP",
    "wof:name":"Batukar kharka",
    "wof:placetype":"locality"
},
  "geometry": {"coordinates":[80.9563,29.35143],"type":"Point"}
}