{
  "type": "Feature",
  "properties": {
    "gn:admin1_code":"WR",
    "gn:admin2_code":"4",
    "gn:admin3_code":"37",
    "gn:admin4_code":"370027.0",
    "gn:asciiname":"Bhakunde",
    "gn:country_code":"NP",
    "gn:dem":751,
    "gn:feature_class":"P",
    "gn:feature_code":"PPLL",
    "gn:name":"Bhakunde",
    "gn:population":0,
    "gn:timezone":"Asia/Kathmandu",
    "iso:country":"NP",
    "name:ceb_x_preferred":[
        "Bhakunde"
    ],
    "name:fra_x_preferred":[
        "Bhakunde"
    ],
    "name:nep_x_preferred":[
        "\u092d\u0915\u0941\u0923\u094d\u0921\u0947"
    ],
    "name:pol_x_preferred":[
        "Bhakunde"
    ],
    "wof:name":"Bhakunde",
    "wof:placetype":"locality"
},
  "geometry": {"coordinates":[84.39202,28.20506],"type":"Point"}
}