{
  "type": "Feature",
  "properties": {
    "gn:admin1_code":"ER",
    "gn:admin2_code":"7",
    "gn:admin3_code":"6",
    "gn:admin4_code":"60006",
    "gn:asciiname":"Sisuwa",
    "gn:country_code":"NP",
    "gn:dem":112,
    "gn:feature_class":"P",
    "gn:feature_code":"PPLL",
    "gn:name":"Sisuwa",
    "gn:population":0,
    "gn:timezone":"Asia/Kathmandu",
    "iso:country":"NP",
    "wof:name":"Sisuwa",
    "wof:placetype":"locality"
},
  "geometry": {"coordinates":[87.21109,26.71347],"type":"Point"}
}