{
  "type": "Feature",
  "properties": {
    "gn:admin1_code":"MR",
    "gn:admin2_code":"2.0",
    "gn:admin3_code":"59.0",
    "gn:admin4_code":"590015.0",
    "gn:asciiname":"Pakhapani",
    "gn:country_code":"NP",
    "gn:dem":1328,
    "gn:feature_class":"P",
    "gn:feature_code":"PPLL",
    "gn:name":"Pakhapani",
    "gn:population":0,
    "gn:timezone":"Asia/Kathmandu",
    "iso:country":"NP",
    "wof:name":"Pakhapani",
    "wof:placetype":"locality"
},
  "geometry": {"coordinates":[81.60696,28.64623],"type":"Point"}
}