{
  "type": "Feature",
  "properties": {
    "gn:admin1_code":"00",
    "gn:asciiname":"Bhurchaur",
    "gn:country_code":"NP",
    "gn:dem":725,
    "gn:feature_class":"P",
    "gn:feature_code":"PPL",
    "gn:name":"Bhurchaur",
    "gn:population":0,
    "gn:timezone":"Asia/Kathmandu",
    "iso:country":"NP",
    "name:nep_x_preferred":[
        "Bhurchaur"
    ],
    "wof:name":"Bhurchaur",
    "wof:placetype":"locality"
},
  "geometry": {"coordinates":[82.09904,28.62535],"type":"Point"}
}