{
  "type": "Feature",
  "properties": {
    "gn:admin1_code":"ER",
    "gn:admin2_code":"7",
    "gn:admin3_code":"7.0",
    "gn:admin4_code":"70023.0",
    "gn:asciiname":"Andrung",
    "gn:country_code":"NP",
    "gn:dem":514,
    "gn:feature_class":"P",
    "gn:feature_code":"PPLL",
    "gn:name":"Andrung",
    "gn:population":0,
    "gn:timezone":"Asia/Kathmandu",
    "iso:country":"NP",
    "wof:name":"Andrung",
    "wof:placetype":"locality"
},
  "geometry": {"coordinates":[87.31905999999999,27.14029],"type":"Point"}
}