{
  "type": "Feature",
  "properties": {
    "gn:admin1_code":"MR",
    "gn:admin2_code":"6",
    "gn:admin3_code":"66.0",
    "gn:admin4_code":"660020.0",
    "gn:asciiname":"Munkhati Lek",
    "gn:country_code":"NP",
    "gn:dem":4412,
    "gn:feature_class":"P",
    "gn:feature_code":"PPLL",
    "gn:name":"Munkhati Lek",
    "gn:population":0,
    "gn:timezone":"Asia/Kathmandu",
    "iso:country":"NP",
    "wof:name":"Munkhati Lek",
    "wof:placetype":"locality"
},
  "geometry": {"coordinates":[82.03658,29.83684],"type":"Point"}
}