{
  "type": "Feature",
  "properties": {
    "gn:admin1_code":"WR",
    "gn:admin2_code":"4",
    "gn:admin3_code":"37",
    "gn:admin4_code":"370021",
    "gn:asciiname":"Selkyu",
    "gn:country_code":"NP",
    "gn:dem":1315,
    "gn:feature_class":"P",
    "gn:feature_code":"PPLL",
    "gn:name":"Selkyu",
    "gn:population":0,
    "gn:timezone":"Asia/Kathmandu",
    "iso:country":"NP",
    "wof:name":"Selkyu",
    "wof:placetype":"locality"
},
  "geometry": {"coordinates":[84.48299999999998,28.2414],"type":"Point"}
}