{
  "type": "Feature",
  "properties": {
    "gn:admin1_code":"CR",
    "gn:admin2_code":"1",
    "gn:admin3_code":"29",
    "gn:admin4_code":"290009",
    "gn:asciiname":"Jibjibe",
    "gn:country_code":"NP",
    "gn:dem":1491,
    "gn:feature_class":"P",
    "gn:feature_code":"PPLL",
    "gn:name":"Jibjibe",
    "gn:population":0,
    "gn:timezone":"Asia/Kathmandu",
    "iso:country":"NP",
    "wof:name":"Jibjibe",
    "wof:placetype":"locality"
},
  "geometry": {"coordinates":[85.22849000000002,27.99596],"type":"Point"}
}