{
  "type": "Feature",
  "properties": {
    "gn:admin1_code":"CR",
    "gn:admin2_code":"11",
    "gn:admin3_code":"35.0",
    "gn:admin4_code":"350037.0",
    "gn:asciiname":"Kadalghareti",
    "gn:country_code":"NP",
    "gn:dem":422,
    "gn:feature_class":"P",
    "gn:feature_code":"PPLL",
    "gn:name":"Kadalghareti",
    "gn:population":0,
    "gn:timezone":"Asia/Kathmandu",
    "iso:country":"NP",
    "wof:name":"Kadalghareti",
    "wof:placetype":"locality"
},
  "geometry": {"coordinates":[84.62626,27.70791],"type":"Point"}
}