{
  "type": "Feature",
  "properties": {
    "gn:admin1_code":"MR",
    "gn:admin2_code":"2.0",
    "gn:admin3_code":"57.0",
    "gn:admin4_code":"570014.0",
    "gn:asciiname":"Bhajjupurwa",
    "gn:country_code":"NP",
    "gn:dem":143,
    "gn:feature_class":"P",
    "gn:feature_code":"PPLL",
    "gn:name":"Bhajjupurwa",
    "gn:population":0,
    "gn:timezone":"Asia/Kathmandu",
    "iso:country":"NP",
    "wof:name":"Bhajjupurwa",
    "wof:placetype":"locality"
},
  "geometry": {"coordinates":[81.67366,28.00206],"type":"Point"}
}