{
  "type": "Feature",
  "properties": {
    "iso:country":"NP",
    "qs:gn_pop":0,
    "qs:name":"Khudibeni",
    "qs:name_adm0":"Nepal",
    "qs:name_adm1":"Pashchimanchal",
    "qs:photos":135,
    "qs:photos_1k":27,
    "qs:photos_9k":1,
    "qs:photos_9r":3,
    "qs:photos_all":135,
    "qs:photos_sr":3,
    "qs:placetype":"Town",
    "qs:pop_sr":"0",
    "qs:woe_adm0":23424911,
    "wof:name":"Khudibeni",
    "wof:placetype":"locality"
},
  "geometry": {"coordinates":[84.37008299999999,28.290652],"type":"Point"}
}