{
  "type": "Feature",
  "properties": {
    "gn:admin1_code":"MR",
    "gn:admin2_code":"2",
    "gn:admin3_code":"61.0",
    "gn:admin4_code":"610003.0",
    "gn:asciiname":"Khahare",
    "gn:country_code":"NP",
    "gn:dem":1136,
    "gn:feature_class":"P",
    "gn:feature_code":"PPLL",
    "gn:name":"Khahare",
    "gn:population":0,
    "gn:timezone":"Asia/Kathmandu",
    "iso:country":"NP",
    "wof:name":"Khahare",
    "wof:placetype":"locality"
},
  "geometry": {"coordinates":[82.08958,28.65519],"type":"Point"}
}