{
  "type": "Feature",
  "properties": {
    "gn:admin1_code":"00",
    "gn:asciiname":"Apghachhi",
    "gn:country_code":"NP",
    "gn:dem":141,
    "gn:feature_class":"P",
    "gn:feature_code":"PPL",
    "gn:name":"\u0100\u0303pgh\u0101chhi\u0307\u0304",
    "gn:population":0,
    "gn:timezone":"Asia/Kathmandu",
    "iso:country":"NP",
    "name:nep_x_preferred":[
        "\u0100\u0303pgh\u0101chhi\u0307\u0304"
    ],
    "wof:name":"Apghachhi",
    "wof:placetype":"locality"
},
  "geometry": {"coordinates":[88.06341999999999,26.66904000000001],"type":"Point"}
}