{
  "type": "Feature",
  "properties": {
    "gn:admin1_code":"MR",
    "gn:admin2_code":"2.0",
    "gn:admin3_code":"57.0",
    "gn:admin4_code":"570012.0",
    "gn:asciiname":"Piparhawa",
    "gn:country_code":"NP",
    "gn:dem":160,
    "gn:feature_class":"P",
    "gn:feature_code":"PPLL",
    "gn:name":"Piparhawa",
    "gn:population":0,
    "gn:timezone":"Asia/Kathmandu",
    "iso:country":"NP",
    "name:ceb_x_preferred":[
        "Piparhawa"
    ],
    "name:mai_x_preferred":[
        "\u092a\u093f\u092a\u094d\u0930\u0939\u0935\u093e"
    ],
    "name:msa_x_preferred":[
        "Piparhawa"
    ],
    "name:nep_x_preferred":[
        "\u092a\u093f\u092a\u094d\u0930\u0939\u0935\u093e"
    ],
    "name:new_x_preferred":[
        "\u092a\u093f\u092a\u0930\u094d\u0939\u0935\u093e"
    ],
    "name:pol_x_preferred":[
        "Piparhawa"
    ],
    "wof:name":"Piparhawa",
    "wof:placetype":"locality"
},
  "geometry": {"coordinates":[81.65446999999998,28.13724],"type":"Point"}
}