{
  "type": "Feature",
  "properties": {
    "gn:admin1_code":"ER",
    "gn:admin2_code":"13",
    "gn:admin3_code":"16",
    "gn:admin4_code":"160001",
    "gn:asciiname":"Bramhapuri",
    "gn:country_code":"NP",
    "gn:dem":104,
    "gn:feature_class":"P",
    "gn:feature_code":"PPLL",
    "gn:name":"Bramhapuri",
    "gn:population":0,
    "gn:timezone":"Asia/Kathmandu",
    "iso:country":"NP",
    "name:hin_x_preferred":[
        "\u092c\u094d\u0930\u0939\u094d\u092e\u092a\u0941\u0930\u0940"
    ],
    "wof:name":"Bramhapuri",
    "wof:placetype":"locality"
},
  "geometry": {"coordinates":[86.2899,26.72301],"type":"Point"}
}