{
  "type": "Feature",
  "properties": {
    "gn:admin1_code":"ER",
    "gn:admin2_code":"13",
    "gn:admin3_code":"13",
    "gn:admin4_code":"130059",
    "gn:asciiname":"Raigaun",
    "gn:country_code":"NP",
    "gn:dem":1485,
    "gn:feature_class":"P",
    "gn:feature_code":"PPLL",
    "gn:name":"Raigaun",
    "gn:population":0,
    "gn:timezone":"Asia/Kathmandu",
    "iso:country":"NP",
    "name:ceb_x_preferred":[
        "Raigaun"
    ],
    "name:mai_x_preferred":[
        "\u0930\u093e\u0908\u0917\u093e\u0909\u0901"
    ],
    "name:msa_x_preferred":[
        "Raigaun"
    ],
    "name:new_x_preferred":[
        "\u0930\u093e\u0908\u0917\u093e\u0909\u0902"
    ],
    "name:pol_x_preferred":[
        "Raigaun"
    ],
    "wof:name":"Raigaun",
    "wof:placetype":"locality"
},
  "geometry": {"coordinates":[86.72495000000001,27.35944000000001],"type":"Point"}
}