{
  "type": "Feature",
  "properties": {
    "gn:admin1_code":"MR",
    "gn:admin2_code":"12",
    "gn:admin3_code":"56.0",
    "gn:admin4_code":"560037.0",
    "gn:asciiname":"Darma",
    "gn:country_code":"NP",
    "gn:dem":1454,
    "gn:feature_class":"P",
    "gn:feature_code":"PPLL",
    "gn:name":"Darma",
    "gn:population":0,
    "gn:timezone":"Asia/Kathmandu",
    "iso:country":"NP",
    "name:ceb_x_preferred":[
        "Darma"
    ],
    "name:nld_x_preferred":[
        "Darma"
    ],
    "name:swe_x_preferred":[
        "Darma"
    ],
    "wof:name":"Darma",
    "wof:placetype":"locality"
},
  "geometry": {"coordinates":[82.59217,28.04063],"type":"Point"}
}