{
  "type": "Feature",
  "properties": {
    "gn:admin1_code":"WR",
    "gn:admin2_code":"4.0",
    "gn:admin3_code":"39.0",
    "gn:admin4_code":"390043.0",
    "gn:asciiname":"Bhaluthum",
    "gn:country_code":"NP",
    "gn:dem":1520,
    "gn:feature_class":"P",
    "gn:feature_code":"PPLL",
    "gn:name":"Bhaluthum",
    "gn:population":0,
    "gn:timezone":"Asia/Kathmandu",
    "iso:country":"NP",
    "wof:name":"Bhaluthum",
    "wof:placetype":"locality"
},
  "geometry": {"coordinates":[83.63894999999999,27.98044],"type":"Point"}
}