{
  "type": "Feature",
  "properties": {
    "gn:admin1_code":"CR",
    "gn:admin2_code":"11",
    "gn:admin3_code":"31",
    "gn:admin4_code":"310027",
    "gn:asciiname":"Debaltar",
    "gn:country_code":"NP",
    "gn:dem":1382,
    "gn:feature_class":"P",
    "gn:feature_code":"PPLL",
    "gn:name":"Debaltar",
    "gn:population":0,
    "gn:timezone":"Asia/Kathmandu",
    "iso:country":"NP",
    "wof:name":"Debaltar",
    "wof:placetype":"locality"
},
  "geometry": {"coordinates":[85.17945999999998,27.57942],"type":"Point"}
}