{
  "type": "Feature",
  "properties": {
    "gn:admin1_code":"ER",
    "gn:admin2_code":"10.0",
    "gn:admin3_code":"1.0",
    "gn:admin4_code":"10015.0",
    "gn:asciiname":"Hobok",
    "gn:country_code":"NP",
    "gn:dem":2376,
    "gn:feature_class":"P",
    "gn:feature_code":"PPLL",
    "gn:name":"Hobok",
    "gn:population":0,
    "gn:timezone":"Asia/Kathmandu",
    "iso:country":"NP",
    "wof:name":"Hobok",
    "wof:placetype":"locality"
},
  "geometry": {"coordinates":[87.64548000000001,27.41521],"type":"Point"}
}