{
  "type": "Feature",
  "properties": {
    "gn:admin1_code":"CR",
    "gn:admin2_code":"5",
    "gn:admin3_code":"20",
    "gn:admin4_code":"200043",
    "gn:asciiname":"Chisapani",
    "gn:country_code":"NP",
    "gn:dem":1118,
    "gn:feature_class":"P",
    "gn:feature_code":"PPLL",
    "gn:name":"Chisapani",
    "gn:population":0,
    "gn:timezone":"Asia/Kathmandu",
    "iso:country":"NP",
    "name:ceb_x_preferred":[
        "Chisapani"
    ],
    "name:nep_x_preferred":[
        "\u091a\u093f\u0938\u093e\u092a\u093e\u0928\u0940"
    ],
    "name:nld_x_preferred":[
        "Chisapani"
    ],
    "name:pol_x_preferred":[
        "Chisapani"
    ],
    "wof:name":"Chisapani",
    "wof:placetype":"locality"
},
  "geometry": {"coordinates":[85.9966,27.26693],"type":"Point"}
}