{
  "type": "Feature",
  "properties": {
    "gn:admin1_code":"MR",
    "gn:admin2_code":"2.0",
    "gn:admin3_code":"59.0",
    "gn:admin4_code":"590025.0",
    "gn:asciiname":"Raksi",
    "gn:country_code":"NP",
    "gn:dem":2200,
    "gn:feature_class":"P",
    "gn:feature_code":"PPLL",
    "gn:name":"Raksi",
    "gn:population":0,
    "gn:timezone":"Asia/Kathmandu",
    "iso:country":"NP",
    "name:dty_x_preferred":[
        "\u0930\u0915\u094d\u0938\u0940"
    ],
    "name:fra_x_preferred":[
        "Raksi"
    ],
    "name:jpn_x_preferred":[
        "\u30e9\u30ad\u30b7\u30fc"
    ],
    "name:lit_x_preferred":[
        "Rak\u0161i"
    ],
    "name:nep_x_preferred":[
        "\u0930\u0915\u094d\u0938\u0940"
    ],
    "name:nld_x_preferred":[
        "Raksi"
    ],
    "name:spa_x_preferred":[
        "Rakshi"
    ],
    "name:ukr_x_preferred":[
        "\u0420\u0430\u043a\u0441\u0456"
    ],
    "wof:name":"Raksi",
    "wof:placetype":"locality"
},
  "geometry": {"coordinates":[81.88073,28.57408],"type":"Point"}
}