{
  "type": "Feature",
  "properties": {
    "gn:admin1_code":"ER",
    "gn:admin2_code":"7",
    "gn:admin3_code":"5",
    "gn:admin4_code":"50065.0",
    "gn:asciiname":"Tinkateri",
    "gn:country_code":"NP",
    "gn:dem":1307,
    "gn:feature_class":"P",
    "gn:feature_code":"PPLL",
    "gn:name":"Tinkateri",
    "gn:population":0,
    "gn:timezone":"Asia/Kathmandu",
    "iso:country":"NP",
    "wof:name":"Tinkateri",
    "wof:placetype":"locality"
},
  "geometry": {"coordinates":[87.53655000000001,26.83036],"type":"Point"}
}