{
  "type": "Feature",
  "properties": {
    "gn:admin1_code":"00",
    "gn:asciiname":"Ghoddunga",
    "gn:country_code":"NP",
    "gn:dem":990,
    "gn:feature_class":"P",
    "gn:feature_code":"PPL",
    "gn:name":"Gho\u1e0d\u1e0du\u1e45g\u0101",
    "gn:population":0,
    "gn:timezone":"Asia/Kathmandu",
    "iso:country":"NP",
    "wof:name":"Ghoddunga",
    "wof:placetype":"locality"
},
  "geometry": {"coordinates":[85.12021,27.92608],"type":"Point"}
}