{
  "type": "Feature",
  "properties": {
    "gn:admin1_code":"WR",
    "gn:admin2_code":"3",
    "gn:admin3_code":"44",
    "gn:admin4_code":"440020",
    "gn:asciiname":"Phausin",
    "gn:country_code":"NP",
    "gn:dem":1038,
    "gn:feature_class":"P",
    "gn:feature_code":"PPLL",
    "gn:name":"Phausin",
    "gn:population":0,
    "gn:timezone":"Asia/Kathmandu",
    "iso:country":"NP",
    "wof:name":"Phausin",
    "wof:placetype":"locality"
},
  "geometry": {"coordinates":[83.60828000000002,28.30658],"type":"Point"}
}