{
  "type": "Feature",
  "properties": {
    "gn:admin1_code":"WR",
    "gn:admin2_code":"4",
    "gn:admin3_code":"40.0",
    "gn:admin4_code":"400034.0",
    "gn:asciiname":"Takura",
    "gn:country_code":"NP",
    "gn:dem":1265,
    "gn:feature_class":"P",
    "gn:feature_code":"PPLL",
    "gn:name":"Takura",
    "gn:population":0,
    "gn:timezone":"Asia/Kathmandu",
    "iso:country":"NP",
    "name:por_x_preferred":[
        "Takura Tendayi"
    ],
    "name:slk_x_preferred":[
        "Takura"
    ],
    "wof:name":"Takura",
    "wof:placetype":"locality"
},
  "geometry": {"coordinates":[83.96505000000001,28.30439],"type":"Point"}
}