{
  "type": "Feature",
  "properties": {
    "gn:admin1_code":"MR",
    "gn:admin2_code":"12",
    "gn:admin3_code":"53",
    "gn:admin4_code":"530034",
    "gn:asciiname":"Bhorja",
    "gn:country_code":"NP",
    "gn:dem":1571,
    "gn:feature_class":"P",
    "gn:feature_code":"PPLL",
    "gn:name":"Bhorja",
    "gn:population":0,
    "gn:timezone":"Asia/Kathmandu",
    "iso:country":"NP",
    "wof:name":"Bhorja",
    "wof:placetype":"locality"
},
  "geometry": {"coordinates":[82.45624000000002,28.26354000000001],"type":"Point"}
}