{
  "type": "Feature",
  "properties": {
    "gn:admin1_code":"WR",
    "gn:admin2_code":"8",
    "gn:admin3_code":"49",
    "gn:admin4_code":"490033",
    "gn:asciiname":"Asaban",
    "gn:country_code":"NP",
    "gn:dem":133,
    "gn:feature_class":"P",
    "gn:feature_code":"PPLL",
    "gn:name":"Asaban",
    "gn:population":0,
    "gn:timezone":"Asia/Kathmandu",
    "iso:country":"NP",
    "wof:name":"Asaban",
    "wof:placetype":"locality"
},
  "geometry": {"coordinates":[83.49388,27.63031],"type":"Point"}
}