{
  "type": "Feature",
  "properties": {
    "gn:admin1_code":"00",
    "gn:asciiname":"Phijorgaon",
    "gn:country_code":"NP",
    "gn:dem":3884,
    "gn:feature_class":"P",
    "gn:feature_code":"PPL",
    "gn:name":"Phijorgaon",
    "gn:population":0,
    "gn:timezone":"Asia/Kathmandu",
    "iso:country":"NP",
    "wof:name":"Phijorgaon",
    "wof:placetype":"locality"
},
  "geometry": {"coordinates":[82.88214000000001,29.45857],"type":"Point"}
}