{
  "type": "Feature",
  "properties": {
    "gn:admin1_code":"WR",
    "gn:admin2_code":"4.0",
    "gn:admin3_code":"38.0",
    "gn:admin4_code":"380045.0",
    "gn:asciiname":"Sewar",
    "gn:country_code":"NP",
    "gn:dem":456,
    "gn:feature_class":"P",
    "gn:feature_code":"PPLL",
    "gn:name":"Sewar",
    "gn:population":0,
    "gn:timezone":"Asia/Kathmandu",
    "iso:country":"NP",
    "name:ita_x_preferred":[
        "Sewar"
    ],
    "wof:name":"Sewar",
    "wof:placetype":"locality"
},
  "geometry": {"coordinates":[84.27849000000001,27.99958],"type":"Point"}
}