{
  "type": "Feature",
  "properties": {
    "gn:admin1_code":"CR",
    "gn:admin2_code":"5",
    "gn:admin3_code":"20",
    "gn:admin4_code":"200020",
    "gn:asciiname":"Shani",
    "gn:country_code":"NP",
    "gn:dem":588,
    "gn:feature_class":"P",
    "gn:feature_code":"PPLL",
    "gn:name":"Shani",
    "gn:population":0,
    "gn:timezone":"Asia/Kathmandu",
    "iso:country":"NP",
    "name:afr_x_preferred":[
        "Sjani"
    ],
    "name:ben_x_preferred":[
        "\u09b6\u09a8\u09bf"
    ],
    "name:deu_x_preferred":[
        "Shani"
    ],
    "name:fra_x_preferred":[
        "Shani"
    ],
    "name:guj_x_preferred":[
        "\u0ab6\u0aa8\u0abf\u0aa6\u0ac7\u0ab5"
    ],
    "name:hin_x_preferred":[
        "\u0936\u0928\u093f"
    ],
    "name:ind_x_preferred":[
        "Sani"
    ],
    "name:kan_x_preferred":[
        "\u0cb6\u0ca8\u0cbf"
    ],
    "name:mai_x_preferred":[
        "\u0936\u0928\u093f \u0926\u0947\u0935"
    ],
    "name:mal_x_preferred":[
        "\u0d36\u0d28\u0d40\u0d36\u0d4d\u0d35\u0d30\u0d7b"
    ],
    "name:mar_x_preferred":[
        "\u0936\u0928\u093f"
    ],
    "name:nep_x_preferred":[
        "\u0936\u0928\u093f \u0917\u094d\u0930\u0939"
    ],
    "name:nor_x_preferred":[
        "Shani"
    ],
    "name:pol_x_preferred":[
        "\u015aani"
    ],
    "name:por_x_preferred":[
        "Shani"
    ],
    "name:rus_x_preferred":[
        "\u0428\u0430\u043d\u0438"
    ],
    "name:san_x_preferred":[
        "\u0936\u0928\u093f\u0926\u0947\u0935\u0903"
    ],
    "name:spa_x_preferred":[
        "Shani"
    ],
    "name:tam_x_preferred":[
        "\u0b9a\u0ba9\u0bc0\u0bb8\u0bcd\u0bb5\u0bb0\u0ba9\u0bcd"
    ],
    "name:tel_x_preferred":[
        "\u0c36\u0c28\u0c3f"
    ],
    "name:tha_x_preferred":[
        "\u0e1e\u0e23\u0e30\u0e40\u0e2a\u0e32\u0e23\u0e4c"
    ],
    "name:ukr_x_preferred":[
        "\u0428\u0430\u043d\u0456"
    ],
    "wof:name":"Shani",
    "wof:placetype":"locality"
},
  "geometry": {"coordinates":[86.10173,27.12584],"type":"Point"}
}