{
  "type": "Feature",
  "properties": {
    "gn:admin1_code":"FR",
    "gn:admin2_code":"14",
    "gn:admin3_code":"69",
    "gn:admin4_code":"690040",
    "gn:asciiname":"Baddegado",
    "gn:country_code":"NP",
    "gn:dem":2062,
    "gn:feature_class":"P",
    "gn:feature_code":"PPLL",
    "gn:name":"Baddegado",
    "gn:population":0,
    "gn:timezone":"Asia/Kathmandu",
    "iso:country":"NP",
    "wof:name":"Baddegado",
    "wof:placetype":"locality"
},
  "geometry": {"coordinates":[81.32289,29.22823],"type":"Point"}
}