{
  "type": "Feature",
  "properties": {
    "gn:admin1_code":"CR",
    "gn:admin2_code":"11",
    "gn:admin3_code":"35.0",
    "gn:admin4_code":"350026.0",
    "gn:asciiname":"Gopalganj",
    "gn:country_code":"NP",
    "gn:dem":194,
    "gn:feature_class":"P",
    "gn:feature_code":"PPLL",
    "gn:name":"Gopalganj",
    "gn:population":0,
    "gn:timezone":"Asia/Kathmandu",
    "iso:country":"NP",
    "name:ben_x_preferred":[
        "\u0997\u09cb\u09aa\u09be\u09b2\u0997\u099e\u09cd\u099c"
    ],
    "name:ceb_x_preferred":[
        "Gopalganj"
    ],
    "name:deu_x_preferred":[
        "Gopalganj"
    ],
    "name:nld_x_preferred":[
        "Gopalganj"
    ],
    "name:sco_x_preferred":[
        "Gopalganj"
    ],
    "name:swe_x_preferred":[
        "Gopalganj"
    ],
    "wof:name":"Gopalganj",
    "wof:placetype":"locality"
},
  "geometry": {"coordinates":[84.36156,27.64542],"type":"Point"}
}