{
  "type": "Feature",
  "properties": {
    "gn:admin1_code":"ER",
    "gn:admin2_code":"7",
    "gn:admin3_code":"9",
    "gn:admin4_code":"90029.0",
    "gn:asciiname":"Bakaldum",
    "gn:country_code":"NP",
    "gn:dem":1555,
    "gn:feature_class":"P",
    "gn:feature_code":"PPLL",
    "gn:name":"Bakaldum",
    "gn:population":0,
    "gn:timezone":"Asia/Kathmandu",
    "iso:country":"NP",
    "wof:name":"Bakaldum",
    "wof:placetype":"locality"
},
  "geometry": {"coordinates":[87.01751,27.5018],"type":"Point"}
}