{
  "type": "Feature",
  "properties": {
    "gn:admin1_code":"ER",
    "gn:admin2_code":"13",
    "gn:admin3_code":"13",
    "gn:admin4_code":"130072",
    "gn:asciiname":"Jamunatar",
    "gn:country_code":"NP",
    "gn:dem":426,
    "gn:feature_class":"P",
    "gn:feature_code":"PPLL",
    "gn:name":"Jamunatar",
    "gn:population":0,
    "gn:timezone":"Asia/Kathmandu",
    "iso:country":"NP",
    "wof:name":"Jamunatar",
    "wof:placetype":"locality"
},
  "geometry": {"coordinates":[86.78691999999999,26.89113],"type":"Point"}
}