{
  "type": "Feature",
  "properties": {
    "gn:admin1_code":"ER",
    "gn:admin2_code":"13",
    "gn:admin3_code":"13.0",
    "gn:admin4_code":"130022.0",
    "gn:asciiname":"Bajbarnetar",
    "gn:country_code":"NP",
    "gn:dem":969,
    "gn:feature_class":"P",
    "gn:feature_code":"PPLL",
    "gn:name":"Bajbarnetar",
    "gn:population":0,
    "gn:timezone":"Asia/Kathmandu",
    "iso:country":"NP",
    "wof:name":"Bajbarnetar",
    "wof:placetype":"locality"
},
  "geometry": {"coordinates":[86.88112,26.95237],"type":"Point"}
}