{
  "type": "Feature",
  "properties": {
    "gn:admin1_code":"CR",
    "gn:admin2_code":"1",
    "gn:admin3_code":"24.0",
    "gn:admin4_code":"240015.0",
    "gn:asciiname":"Chaubas",
    "gn:country_code":"NP",
    "gn:dem":1882,
    "gn:feature_class":"P",
    "gn:feature_code":"PPLL",
    "gn:name":"Chaubas",
    "gn:population":0,
    "gn:timezone":"Asia/Kathmandu",
    "iso:country":"NP",
    "wof:name":"Chaubas",
    "wof:placetype":"locality"
},
  "geometry": {"coordinates":[85.77965999999998,27.6337],"type":"Point"}
}