{
  "type": "Feature",
  "properties": {
    "gn:admin1_code":"WR",
    "gn:admin2_code":"4",
    "gn:admin3_code":"37",
    "gn:admin4_code":"370015",
    "gn:asciiname":"Tallo Bichaur",
    "gn:country_code":"NP",
    "gn:dem":1197,
    "gn:feature_class":"P",
    "gn:feature_code":"PPLL",
    "gn:name":"Tallo Bichaur",
    "gn:population":0,
    "gn:timezone":"Asia/Kathmandu",
    "iso:country":"NP",
    "wof:name":"Tallo Bichaur",
    "wof:placetype":"locality"
},
  "geometry": {"coordinates":[84.61236,28.18516],"type":"Point"}
}