{
  "type": "Feature",
  "properties": {
    "gn:admin1_code":"MR",
    "gn:admin2_code":"12",
    "gn:admin3_code":"53",
    "gn:admin4_code":"530016",
    "gn:asciiname":"Ratemate",
    "gn:country_code":"NP",
    "gn:dem":1237,
    "gn:feature_class":"P",
    "gn:feature_code":"PPLL",
    "gn:name":"Ratemate",
    "gn:population":0,
    "gn:timezone":"Asia/Kathmandu",
    "iso:country":"NP",
    "wof:name":"Ratemate",
    "wof:placetype":"locality"
},
  "geometry": {"coordinates":[82.78309,28.32674],"type":"Point"}
}