{
  "type": "Feature",
  "properties": {
    "gn:admin1_code":"MR",
    "gn:admin2_code":"12",
    "gn:admin3_code":"52",
    "gn:admin4_code":"520018",
    "gn:asciiname":"Tilkeni",
    "gn:country_code":"NP",
    "gn:dem":1330,
    "gn:feature_class":"P",
    "gn:feature_code":"PPLL",
    "gn:name":"Tilkeni",
    "gn:population":0,
    "gn:timezone":"Asia/Kathmandu",
    "iso:country":"NP",
    "wof:name":"Tilkeni",
    "wof:placetype":"locality"
},
  "geometry": {"coordinates":[82.85243,28.02603],"type":"Point"}
}