{
  "type": "Feature",
  "properties": {
    "gn:admin1_code":"00",
    "gn:asciiname":"Thargumtha",
    "gn:country_code":"NP",
    "gn:dem":2218,
    "gn:feature_class":"P",
    "gn:feature_code":"PPL",
    "gn:name":"Th\u0101rgumtha",
    "gn:population":0,
    "gn:timezone":"Asia/Kathmandu",
    "iso:country":"NP",
    "wof:name":"Thargumtha",
    "wof:placetype":"locality"
},
  "geometry": {"coordinates":[81.90079,29.49799],"type":"Point"}
}