{
  "type": "Feature",
  "properties": {
    "gn:admin1_code":"CR",
    "gn:admin2_code":"5",
    "gn:admin3_code":"20",
    "gn:admin4_code":"200025",
    "gn:asciiname":"Hukse",
    "gn:country_code":"NP",
    "gn:dem":588,
    "gn:feature_class":"P",
    "gn:feature_code":"PPLL",
    "gn:name":"Hukse",
    "gn:population":0,
    "gn:timezone":"Asia/Kathmandu",
    "iso:country":"NP",
    "wof:name":"Hukse",
    "wof:placetype":"locality"
},
  "geometry": {"coordinates":[85.92541999999997,27.22068],"type":"Point"}
}