{
  "type": "Feature",
  "properties": {
    "gn:admin1_code":"WR",
    "gn:admin2_code":"8",
    "gn:admin3_code":"47",
    "gn:admin4_code":"470027",
    "gn:asciiname":"Bhaledhunga",
    "gn:country_code":"NP",
    "gn:dem":953,
    "gn:feature_class":"P",
    "gn:feature_code":"PPLL",
    "gn:name":"Bhaledhunga",
    "gn:population":0,
    "gn:timezone":"Asia/Kathmandu",
    "iso:country":"NP",
    "wof:name":"Bhaledhunga",
    "wof:placetype":"locality"
},
  "geometry": {"coordinates":[83.74024,27.88752],"type":"Point"}
}