{
  "type": "Feature",
  "properties": {
    "gn:admin1_code":"00",
    "gn:asciiname":"Debikot",
    "gn:country_code":"NP",
    "gn:dem":1030,
    "gn:feature_class":"P",
    "gn:feature_code":"PPL",
    "gn:name":"Debikot",
    "gn:population":0,
    "gn:timezone":"Asia/Kathmandu",
    "iso:country":"NP",
    "name:nep_x_preferred":[
        "Devi\u0307\u0304ko\u1e6d"
    ],
    "wof:name":"Debikot",
    "wof:placetype":"locality"
},
  "geometry": {"coordinates":[82.69733000000002,27.8923],"type":"Point"}
}