{
  "type": "Feature",
  "properties": {
    "gn:admin1_code":"ER",
    "gn:admin2_code":"7",
    "gn:admin3_code":"9",
    "gn:admin4_code":"90017",
    "gn:asciiname":"Yangluwa",
    "gn:country_code":"NP",
    "gn:dem":1730,
    "gn:feature_class":"P",
    "gn:feature_code":"PPLL",
    "gn:name":"Yangluwa",
    "gn:population":0,
    "gn:timezone":"Asia/Kathmandu",
    "iso:country":"NP",
    "wof:name":"Yangluwa",
    "wof:placetype":"locality"
},
  "geometry": {"coordinates":[87.22331,27.57324],"type":"Point"}
}