{
  "type": "Feature",
  "properties": {
    "gn:admin1_code":"CR",
    "gn:admin2_code":"1",
    "gn:admin3_code":"23",
    "gn:admin4_code":"230044",
    "gn:asciiname":"Pipse",
    "gn:country_code":"NP",
    "gn:dem":1715,
    "gn:feature_class":"P",
    "gn:feature_code":"PPLL",
    "gn:name":"Pipse",
    "gn:population":0,
    "gn:timezone":"Asia/Kathmandu",
    "iso:country":"NP",
    "wof:name":"Pipse",
    "wof:placetype":"locality"
},
  "geometry": {"coordinates":[85.50388000000002,27.88068],"type":"Point"}
}