{
  "type": "Feature",
  "properties": {
    "gn:admin1_code":"ER",
    "gn:admin2_code":"7.0",
    "gn:admin3_code":"8.0",
    "gn:admin4_code":"80029.0",
    "gn:asciiname":"Lamkateri",
    "gn:country_code":"NP",
    "gn:dem":950,
    "gn:feature_class":"P",
    "gn:feature_code":"PPLL",
    "gn:name":"Lamkateri",
    "gn:population":0,
    "gn:timezone":"Asia/Kathmandu",
    "iso:country":"NP",
    "wof:name":"Lamkateri",
    "wof:placetype":"locality"
},
  "geometry": {"coordinates":[87.49268000000002,27.08501],"type":"Point"}
}