{
  "type": "Feature",
  "properties": {
    "gn:admin1_code":"WR",
    "gn:admin2_code":"4.0",
    "gn:admin3_code":"38.0",
    "gn:admin4_code":"380029.0",
    "gn:asciiname":"Naram",
    "gn:country_code":"NP",
    "gn:dem":1070,
    "gn:feature_class":"P",
    "gn:feature_code":"PPLL",
    "gn:name":"Naram",
    "gn:population":0,
    "gn:timezone":"Asia/Kathmandu",
    "iso:country":"NP",
    "wof:name":"Naram",
    "wof:placetype":"locality"
},
  "geometry": {"coordinates":[84.34599,27.81603],"type":"Point"}
}