{
  "type": "Feature",
  "properties": {
    "gn:admin1_code":"FR",
    "gn:admin2_code":"9",
    "gn:admin3_code":"73.0",
    "gn:admin4_code":"730012.0",
    "gn:asciiname":"Bajilek",
    "gn:country_code":"NP",
    "gn:dem":1550,
    "gn:feature_class":"P",
    "gn:feature_code":"PPLL",
    "gn:name":"Bajilek",
    "gn:population":0,
    "gn:timezone":"Asia/Kathmandu",
    "iso:country":"NP",
    "wof:name":"Bajilek",
    "wof:placetype":"locality"
},
  "geometry": {"coordinates":[80.51561,29.19104],"type":"Point"}
}