{
  "type": "Feature",
  "properties": {
    "gn:admin1_code":"ER",
    "gn:admin2_code":"13",
    "gn:admin3_code":"15",
    "gn:admin4_code":"150004",
    "gn:asciiname":"Potari Balaha",
    "gn:country_code":"NP",
    "gn:dem":82,
    "gn:feature_class":"P",
    "gn:feature_code":"PPLL",
    "gn:name":"Potari Balaha",
    "gn:population":0,
    "gn:timezone":"Asia/Kathmandu",
    "iso:country":"NP",
    "wof:name":"Potari Balaha",
    "wof:placetype":"locality"
},
  "geometry": {"coordinates":[86.91086,26.58991],"type":"Point"}
}