{
  "type": "Feature",
  "properties": {
    "gn:admin1_code":"ER",
    "gn:admin2_code":"7",
    "gn:admin3_code":"7.0",
    "gn:admin4_code":"70032.0",
    "gn:asciiname":"Korna",
    "gn:country_code":"NP",
    "gn:dem":1688,
    "gn:feature_class":"P",
    "gn:feature_code":"PPLL",
    "gn:name":"Korna",
    "gn:population":0,
    "gn:timezone":"Asia/Kathmandu",
    "iso:country":"NP",
    "name:ceb_x_preferred":[
        "Korna"
    ],
    "name:deu_x_preferred":[
        "Korna"
    ],
    "name:swe_x_preferred":[
        "Korna"
    ],
    "wof:name":"Korna",
    "wof:placetype":"locality"
},
  "geometry": {"coordinates":[87.44595,26.86786],"type":"Point"}
}