{
  "type": "Feature",
  "properties": {
    "gn:admin1_code":"FR",
    "gn:admin2_code":"9",
    "gn:admin3_code":"72.0",
    "gn:admin4_code":"720015.0",
    "gn:asciiname":"Gadaniyagaudi",
    "gn:country_code":"NP",
    "gn:dem":176,
    "gn:feature_class":"P",
    "gn:feature_code":"PPLL",
    "gn:name":"Gadaniyagaudi",
    "gn:population":0,
    "gn:timezone":"Asia/Kathmandu",
    "iso:country":"NP",
    "wof:name":"Gadaniyagaudi",
    "wof:placetype":"locality"
},
  "geometry": {"coordinates":[80.30176999999998,28.72685],"type":"Point"}
}