{
  "type": "Feature",
  "properties": {
    "gn:admin1_code":"WR",
    "gn:admin2_code":"4",
    "gn:admin3_code":"40.0",
    "gn:admin4_code":"400008.0",
    "gn:asciiname":"Pokhrel Dihi",
    "gn:country_code":"NP",
    "gn:dem":744,
    "gn:feature_class":"P",
    "gn:feature_code":"PPLL",
    "gn:name":"Pokhrel Dihi",
    "gn:population":0,
    "gn:timezone":"Asia/Kathmandu",
    "iso:country":"NP",
    "wof:name":"Pokhrel Dihi",
    "wof:placetype":"locality"
},
  "geometry": {"coordinates":[84.12697,28.12428],"type":"Point"}
}