{
  "type": "Feature",
  "properties": {
    "gn:admin1_code":"WR",
    "gn:admin2_code":"3",
    "gn:admin3_code":"44",
    "gn:admin4_code":"440009",
    "gn:asciiname":"Bajarmara",
    "gn:country_code":"NP",
    "gn:dem":1832,
    "gn:feature_class":"P",
    "gn:feature_code":"PPLL",
    "gn:name":"Bajarmara",
    "gn:population":0,
    "gn:timezone":"Asia/Kathmandu",
    "iso:country":"NP",
    "wof:name":"Bajarmara",
    "wof:placetype":"locality"
},
  "geometry": {"coordinates":[83.70860999999999,28.13831],"type":"Point"}
}