{
  "type": "Feature",
  "properties": {
    "gn:admin1_code":"CR",
    "gn:admin2_code":"1",
    "gn:admin3_code":"28",
    "gn:admin4_code":"280023",
    "gn:asciiname":"Sankalche",
    "gn:country_code":"NP",
    "gn:dem":2302,
    "gn:feature_class":"P",
    "gn:feature_code":"PPLL",
    "gn:name":"Sankalche",
    "gn:population":0,
    "gn:timezone":"Asia/Kathmandu",
    "iso:country":"NP",
    "wof:name":"Sankalche",
    "wof:placetype":"locality"
},
  "geometry": {"coordinates":[85.46168,28.01442],"type":"Point"}
}