{
  "type": "Feature",
  "properties": {
    "gn:admin1_code":"FR",
    "gn:admin2_code":"9",
    "gn:admin3_code":"74",
    "gn:admin4_code":"740058",
    "gn:asciiname":"Kesekharka",
    "gn:country_code":"NP",
    "gn:dem":1586,
    "gn:feature_class":"P",
    "gn:feature_code":"PPLL",
    "gn:name":"Kesekharka",
    "gn:population":0,
    "gn:timezone":"Asia/Kathmandu",
    "iso:country":"NP",
    "wof:name":"Kesekharka",
    "wof:placetype":"locality"
},
  "geometry": {"coordinates":[80.55998000000002,29.41745],"type":"Point"}
}