{
  "type": "Feature",
  "properties": {
    "gn:admin1_code":"ER",
    "gn:admin2_code":"10",
    "gn:admin3_code":"2",
    "gn:admin4_code":"20020",
    "gn:asciiname":"Janche Bhanjyang",
    "gn:country_code":"NP",
    "gn:dem":3389,
    "gn:feature_class":"P",
    "gn:feature_code":"PPLL",
    "gn:name":"Janche Bhanjyang",
    "gn:population":0,
    "gn:timezone":"Asia/Kathmandu",
    "iso:country":"NP",
    "wof:name":"Janche Bhanjyang",
    "wof:placetype":"locality"
},
  "geometry": {"coordinates":[88.01224000000001,27.2071],"type":"Point"}
}