{
  "type": "Feature",
  "properties": {
    "gn:admin1_code":"CR",
    "gn:admin2_code":"11",
    "gn:admin3_code":"35.0",
    "gn:admin4_code":"350005.0",
    "gn:asciiname":"CancerHospitalArea",
    "gn:country_code":"NP",
    "gn:dem":216,
    "gn:feature_class":"P",
    "gn:feature_code":"PPLL",
    "gn:name":"CancerHospitalArea",
    "gn:population":0,
    "gn:timezone":"Asia/Kathmandu",
    "iso:country":"NP",
    "wof:name":"CancerHospitalArea",
    "wof:placetype":"locality"
},
  "geometry": {"coordinates":[84.4194,27.6674],"type":"Point"}
}