{
  "type": "Feature",
  "properties": {
    "gn:admin1_code":"WR",
    "gn:admin2_code":"8",
    "gn:admin3_code":"51.0",
    "gn:admin4_code":"510022.0",
    "gn:asciiname":"Bhutdanda",
    "gn:country_code":"NP",
    "gn:dem":1060,
    "gn:feature_class":"P",
    "gn:feature_code":"PPLL",
    "gn:name":"Bhutdanda",
    "gn:population":0,
    "gn:timezone":"Asia/Kathmandu",
    "iso:country":"NP",
    "wof:name":"Bhutdanda",
    "wof:placetype":"locality"
},
  "geometry": {"coordinates":[83.23774,27.98952],"type":"Point"}
}