{
  "type": "Feature",
  "properties": {
    "gn:admin1_code":"CR",
    "gn:admin2_code":"1",
    "gn:admin3_code":"24.0",
    "gn:admin4_code":"240072.0",
    "gn:asciiname":"Budhapokhari",
    "gn:country_code":"NP",
    "gn:dem":1896,
    "gn:feature_class":"P",
    "gn:feature_code":"PPLL",
    "gn:name":"Budhapokhari",
    "gn:population":0,
    "gn:timezone":"Asia/Kathmandu",
    "iso:country":"NP",
    "wof:name":"Budhapokhari",
    "wof:placetype":"locality"
},
  "geometry": {"coordinates":[85.45352,27.60986],"type":"Point"}
}