{
  "type": "Feature",
  "properties": {
    "gn:admin1_code":"ER",
    "gn:admin2_code":"13",
    "gn:admin3_code":"11",
    "gn:admin4_code":"110003",
    "gn:asciiname":"Salung",
    "gn:country_code":"NP",
    "gn:dem":2843,
    "gn:feature_class":"P",
    "gn:feature_code":"PPLL",
    "gn:name":"Salung",
    "gn:population":0,
    "gn:timezone":"Asia/Kathmandu",
    "iso:country":"NP",
    "wof:name":"Salung",
    "wof:placetype":"locality"
},
  "geometry": {"coordinates":[86.58809000000002,27.57548],"type":"Point"}
}