{
  "type": "Feature",
  "properties": {
    "gn:admin1_code":"MR",
    "gn:admin2_code":"12",
    "gn:admin3_code":"56.0",
    "gn:admin4_code":"560030.0",
    "gn:asciiname":"Keureni",
    "gn:country_code":"NP",
    "gn:dem":1182,
    "gn:feature_class":"P",
    "gn:feature_code":"PPLL",
    "gn:name":"Keureni",
    "gn:population":0,
    "gn:timezone":"Asia/Kathmandu",
    "iso:country":"NP",
    "wof:name":"Keureni",
    "wof:placetype":"locality"
},
  "geometry": {"coordinates":[82.51429,28.11894],"type":"Point"}
}