{
  "type": "Feature",
  "properties": {
    "gn:admin1_code":"WR",
    "gn:admin2_code":"8",
    "gn:admin3_code":"50.0",
    "gn:admin4_code":"500030.0",
    "gn:asciiname":"Bagaihiya",
    "gn:country_code":"NP",
    "gn:dem":133,
    "gn:feature_class":"P",
    "gn:feature_code":"PPLL",
    "gn:name":"Bagaihiya",
    "gn:population":0,
    "gn:timezone":"Asia/Kathmandu",
    "iso:country":"NP",
    "wof:name":"Bagaihiya",
    "wof:placetype":"locality"
},
  "geometry": {"coordinates":[82.79401999999997,27.64722],"type":"Point"}
}