{
  "type": "Feature",
  "properties": {
    "gn:admin1_code":"FR",
    "gn:admin2_code":"14",
    "gn:admin3_code":"68",
    "gn:admin4_code":"680001",
    "gn:asciiname":"Gurina",
    "gn:country_code":"NP",
    "gn:dem":1371,
    "gn:feature_class":"P",
    "gn:feature_code":"PPLL",
    "gn:name":"Gurina",
    "gn:population":0,
    "gn:timezone":"Asia/Kathmandu",
    "iso:country":"NP",
    "wof:name":"Gurina",
    "wof:placetype":"locality"
},
  "geometry": {"coordinates":[80.86651999999999,29.56082],"type":"Point"}
}