{
  "type": "Feature",
  "properties": {
    "gn:admin1_code":"MR",
    "gn:admin2_code":"6",
    "gn:admin3_code":"63.0",
    "gn:admin4_code":"630002.0",
    "gn:asciiname":"Baduwal Bada",
    "gn:country_code":"NP",
    "gn:dem":2690,
    "gn:feature_class":"P",
    "gn:feature_code":"PPLL",
    "gn:name":"Baduwal Bada",
    "gn:population":0,
    "gn:timezone":"Asia/Kathmandu",
    "iso:country":"NP",
    "wof:name":"Baduwal Bada",
    "wof:placetype":"locality"
},
  "geometry": {"coordinates":[82.00678000000001,29.39336],"type":"Point"}
}