{
  "type": "Feature",
  "properties": {
    "gn:admin1_code":"CR",
    "gn:admin2_code":"5",
    "gn:admin3_code":"22.0",
    "gn:admin4_code":"220037.0",
    "gn:asciiname":"Bwansa",
    "gn:country_code":"NP",
    "gn:dem":1922,
    "gn:feature_class":"P",
    "gn:feature_code":"PPLL",
    "gn:name":"Bwansa",
    "gn:population":0,
    "gn:timezone":"Asia/Kathmandu",
    "iso:country":"NP",
    "wof:name":"Bwansa",
    "wof:placetype":"locality"
},
  "geometry": {"coordinates":[86.24476999999997,27.5983],"type":"Point"}
}