{
  "type": "Feature",
  "properties": {
    "gn:admin1_code":"CR",
    "gn:admin2_code":"1",
    "gn:admin3_code":"25",
    "gn:admin4_code":"250001",
    "gn:asciiname":"Mathillo Asrang",
    "gn:country_code":"NP",
    "gn:dem":1387,
    "gn:feature_class":"P",
    "gn:feature_code":"PPLL",
    "gn:name":"Mathillo Asrang",
    "gn:population":0,
    "gn:timezone":"Asia/Kathmandu",
    "iso:country":"NP",
    "wof:name":"Mathillo Asrang",
    "wof:placetype":"locality"
},
  "geometry": {"coordinates":[85.32484000000002,27.46275],"type":"Point"}
}