{
  "type": "Feature",
  "properties": {
    "gn:admin1_code":"FR",
    "gn:admin2_code":"9",
    "gn:admin3_code":"74",
    "gn:admin4_code":"740044",
    "gn:asciiname":"Tilkuda",
    "gn:country_code":"NP",
    "gn:dem":2067,
    "gn:feature_class":"P",
    "gn:feature_code":"PPLL",
    "gn:name":"Tilkuda",
    "gn:population":0,
    "gn:timezone":"Asia/Kathmandu",
    "iso:country":"NP",
    "wof:name":"Tilkuda",
    "wof:placetype":"locality"
},
  "geometry": {"coordinates":[80.59755,29.46059],"type":"Point"}
}