{
  "type": "Feature",
  "properties": {
    "gn:admin1_code":"FR",
    "gn:admin2_code":"14",
    "gn:admin3_code":"70.0",
    "gn:admin4_code":"700023.0",
    "gn:asciiname":"Mallo Kalena",
    "gn:country_code":"NP",
    "gn:dem":1392,
    "gn:feature_class":"P",
    "gn:feature_code":"PPLL",
    "gn:name":"Mallo Kalena",
    "gn:population":0,
    "gn:timezone":"Asia/Kathmandu",
    "iso:country":"NP",
    "wof:name":"Mallo Kalena",
    "wof:placetype":"locality"
},
  "geometry": {"coordinates":[80.98286,29.28745],"type":"Point"}
}