{
  "type": "Feature",
  "properties": {
    "gn:admin1_code":"CR",
    "gn:admin2_code":"1",
    "gn:admin3_code":"25",
    "gn:admin4_code":"250012",
    "gn:asciiname":"Silinge",
    "gn:country_code":"NP",
    "gn:dem":1784,
    "gn:feature_class":"P",
    "gn:feature_code":"PPLL",
    "gn:name":"Silinge",
    "gn:population":0,
    "gn:timezone":"Asia/Kathmandu",
    "iso:country":"NP",
    "wof:name":"Silinge",
    "wof:placetype":"locality"
},
  "geometry": {"coordinates":[85.33525999999998,27.5339],"type":"Point"}
}