{
  "type": "Feature",
  "properties": {
    "gn:admin1_code":"FR",
    "gn:admin2_code":"14",
    "gn:admin3_code":"71.0",
    "gn:admin4_code":"710040.0",
    "gn:asciiname":"Gunamare",
    "gn:country_code":"NP",
    "gn:dem":437,
    "gn:feature_class":"P",
    "gn:feature_code":"PPLL",
    "gn:name":"Gunamare",
    "gn:population":0,
    "gn:timezone":"Asia/Kathmandu",
    "iso:country":"NP",
    "wof:name":"Gunamare",
    "wof:placetype":"locality"
},
  "geometry": {"coordinates":[81.21575,28.72909000000001],"type":"Point"}
}