{
  "type": "Feature",
  "properties": {
    "gn:admin1_code":"WR",
    "gn:admin2_code":"4.0",
    "gn:admin3_code":"38.0",
    "gn:admin4_code":"380029.0",
    "gn:asciiname":"Chheranga",
    "gn:country_code":"NP",
    "gn:dem":759,
    "gn:feature_class":"P",
    "gn:feature_code":"PPLL",
    "gn:name":"Chheranga",
    "gn:population":0,
    "gn:timezone":"Asia/Kathmandu",
    "iso:country":"NP",
    "wof:name":"Chheranga",
    "wof:placetype":"locality"
},
  "geometry": {"coordinates":[84.31114000000002,27.80298],"type":"Point"}
}