{
  "type": "Feature",
  "properties": {
    "gn:admin1_code":"FR",
    "gn:admin2_code":"9",
    "gn:admin3_code":"74",
    "gn:admin4_code":"740029",
    "gn:asciiname":"Bhawanegaun",
    "gn:country_code":"NP",
    "gn:dem":1455,
    "gn:feature_class":"P",
    "gn:feature_code":"PPLL",
    "gn:name":"Bhawanegaun",
    "gn:population":0,
    "gn:timezone":"Asia/Kathmandu",
    "iso:country":"NP",
    "wof:name":"Bhawanegaun",
    "wof:placetype":"locality"
},
  "geometry": {"coordinates":[80.70650000000001,29.59964],"type":"Point"}
}