{
  "type": "Feature",
  "properties": {
    "gn:admin1_code":"WR",
    "gn:admin2_code":"3",
    "gn:admin3_code":"45.0",
    "gn:admin4_code":"450016.0",
    "gn:asciiname":"Dechha",
    "gn:country_code":"NP",
    "gn:dem":986,
    "gn:feature_class":"P",
    "gn:feature_code":"PPLL",
    "gn:name":"Dechha",
    "gn:population":0,
    "gn:timezone":"Asia/Kathmandu",
    "iso:country":"NP",
    "wof:name":"Dechha",
    "wof:placetype":"locality"
},
  "geometry": {"coordinates":[83.62653,28.13298],"type":"Point"}
}