{
  "type": "Feature",
  "properties": {
    "gn:admin1_code":"FR",
    "gn:admin2_code":"14",
    "gn:admin3_code":"69",
    "gn:admin4_code":"690037",
    "gn:asciiname":"Tamattibada",
    "gn:country_code":"NP",
    "gn:dem":1163,
    "gn:feature_class":"P",
    "gn:feature_code":"PPLL",
    "gn:name":"Tamattibada",
    "gn:population":0,
    "gn:timezone":"Asia/Kathmandu",
    "iso:country":"NP",
    "wof:name":"Tamattibada",
    "wof:placetype":"locality"
},
  "geometry": {"coordinates":[81.30048000000002,29.18036],"type":"Point"}
}