{
  "type": "Feature",
  "properties": {
    "gn:admin1_code":"00",
    "gn:asciiname":"Maulodada",
    "gn:country_code":"NP",
    "gn:dem":1345,
    "gn:feature_class":"P",
    "gn:feature_code":"PPL",
    "gn:name":"Maulo\u1e0d\u0101\u0303\u1e0d\u0101",
    "gn:population":0,
    "gn:timezone":"Asia/Kathmandu",
    "iso:country":"NP",
    "name:nep_x_preferred":[
        "Maulo\u1e0d\u0101\u0303\u1e0d\u0101"
    ],
    "wof:name":"Maulodada",
    "wof:placetype":"locality"
},
  "geometry": {"coordinates":[87.57325,26.95719],"type":"Point"}
}