{
  "type": "Feature",
  "properties": {
    "gn:admin1_code":"MR",
    "gn:admin2_code":"6",
    "gn:admin3_code":"64.0",
    "gn:admin4_code":"640030.0",
    "gn:asciiname":"Kamlechaur",
    "gn:country_code":"NP",
    "gn:dem":1929,
    "gn:feature_class":"P",
    "gn:feature_code":"PPLL",
    "gn:name":"Kamlechaur",
    "gn:population":0,
    "gn:timezone":"Asia/Kathmandu",
    "iso:country":"NP",
    "wof:name":"Kamlechaur",
    "wof:placetype":"locality"
},
  "geometry": {"coordinates":[81.80422,29.30654],"type":"Point"}
}