{
  "type": "Feature",
  "properties": {
    "gn:admin1_code":"FR",
    "gn:admin2_code":"9",
    "gn:admin3_code":"74",
    "gn:admin4_code":"740038",
    "gn:asciiname":"Bangsalla",
    "gn:country_code":"NP",
    "gn:dem":1422,
    "gn:feature_class":"P",
    "gn:feature_code":"PPLL",
    "gn:name":"Bangsalla",
    "gn:population":0,
    "gn:timezone":"Asia/Kathmandu",
    "iso:country":"NP",
    "wof:name":"Bangsalla",
    "wof:placetype":"locality"
},
  "geometry": {"coordinates":[80.56186,29.52202],"type":"Point"}
}