{
  "type": "Feature",
  "properties": {
    "gn:admin1_code":"00",
    "gn:asciiname":"Dadajerun",
    "gn:country_code":"NP",
    "gn:dem":1493,
    "gn:feature_class":"P",
    "gn:feature_code":"PPL",
    "gn:name":"\u1e0c\u0101\u0303\u1e0d\u0101jeru\u1e45",
    "gn:population":0,
    "gn:timezone":"Asia/Kathmandu",
    "iso:country":"NP",
    "name:nep_x_preferred":[
        "\u1e0c\u0101n\u1e0d\u0101jeru\u1e45"
    ],
    "name:und_x_variant":[
        "\u1e0c\u0101\u0303\u1e0d\u0101jeru\u1e45"
    ],
    "wof:name":"Dadajerun",
    "wof:placetype":"locality"
},
  "geometry": {"coordinates":[86.36875000000001,27.22656],"type":"Point"}
}