{
  "type": "Feature",
  "properties": {
    "gn:admin1_code":"00",
    "gn:asciiname":"Yanma",
    "gn:country_code":"NP",
    "gn:dem":1809,
    "gn:feature_class":"P",
    "gn:feature_code":"PPL",
    "gn:name":"Y\u0101\u1e45m\u0101",
    "gn:population":0,
    "gn:timezone":"Asia/Kathmandu",
    "iso:country":"NP",
    "wof:name":"Yanma",
    "wof:placetype":"locality"
},
  "geometry": {"coordinates":[86.97184,27.37017],"type":"Point"}
}