{
  "type": "Feature",
  "properties": {
    "gn:admin1_code":"CR",
    "gn:admin2_code":"5",
    "gn:admin3_code":"19",
    "gn:admin4_code":"190009",
    "gn:asciiname":"Chinimil Tandi",
    "gn:country_code":"NP",
    "gn:dem":96,
    "gn:feature_class":"P",
    "gn:feature_code":"PPLL",
    "gn:name":"Chinimil Tandi",
    "gn:population":0,
    "gn:timezone":"Asia/Kathmandu",
    "iso:country":"NP",
    "wof:name":"Chinimil Tandi",
    "wof:placetype":"locality"
},
  "geometry": {"coordinates":[85.47114999999999,26.96675],"type":"Point"}
}