{
  "type": "Feature",
  "properties": {
    "gn:admin1_code":"MR",
    "gn:admin2_code":"12",
    "gn:admin3_code":"56.0",
    "gn:admin4_code":"560036.0",
    "gn:asciiname":"Tikuligadh",
    "gn:country_code":"NP",
    "gn:dem":262,
    "gn:feature_class":"P",
    "gn:feature_code":"PPLL",
    "gn:name":"Tikuligadh",
    "gn:population":0,
    "gn:timezone":"Asia/Kathmandu",
    "iso:country":"NP",
    "name:ceb_x_preferred":[
        "Tikuligadh"
    ],
    "name:msa_x_preferred":[
        "Tikuligadh"
    ],
    "name:new_x_preferred":[
        "\u0924\u093f\u0915\u0941\u0932\u0940\u0917\u0922"
    ],
    "name:pol_x_preferred":[
        "Tikuligadh"
    ],
    "wof:name":"Tikuligadh",
    "wof:placetype":"locality"
},
  "geometry": {"coordinates":[82.56314999999999,27.86919],"type":"Point"}
}