{
  "type": "Feature",
  "properties": {
    "gn:admin1_code":"CR",
    "gn:admin2_code":"5",
    "gn:admin3_code":"22.0",
    "gn:admin4_code":"220031.0",
    "gn:asciiname":"Chitre",
    "gn:country_code":"NP",
    "gn:dem":2298,
    "gn:feature_class":"P",
    "gn:feature_code":"PPLL",
    "gn:name":"Chitre",
    "gn:population":0,
    "gn:timezone":"Asia/Kathmandu",
    "iso:country":"NP",
    "wof:name":"Chitre",
    "wof:placetype":"locality"
},
  "geometry": {"coordinates":[86.16306999999998,27.78188],"type":"Point"}
}