{
  "type": "Feature",
  "properties": {
    "gn:admin1_code":"WR",
    "gn:admin2_code":"8",
    "gn:admin3_code":"47",
    "gn:admin4_code":"470052",
    "gn:asciiname":"Rangbas",
    "gn:country_code":"NP",
    "gn:dem":938,
    "gn:feature_class":"P",
    "gn:feature_code":"PPLL",
    "gn:name":"Rangbas",
    "gn:population":0,
    "gn:timezone":"Asia/Kathmandu",
    "iso:country":"NP",
    "wof:name":"Rangbas",
    "wof:placetype":"locality"
},
  "geometry": {"coordinates":[83.71753000000002,27.72274],"type":"Point"}
}