{
  "type": "Feature",
  "properties": {
    "gn:admin1_code":"MR",
    "gn:admin2_code":"2",
    "gn:admin3_code":"61.0",
    "gn:admin4_code":"610027.0",
    "gn:asciiname":"Saltara",
    "gn:country_code":"NP",
    "gn:dem":633,
    "gn:feature_class":"P",
    "gn:feature_code":"PPLL",
    "gn:name":"Saltara",
    "gn:population":0,
    "gn:timezone":"Asia/Kathmandu",
    "iso:country":"NP",
    "name:azb_x_preferred":[
        "\u0633\u0627\u0644\u062a\u0627\u0631\u0627"
    ],
    "name:bel_x_preferred":[
        "\u0421\u0430\u043b\u044c\u0442\u0430\u0440\u0430"
    ],
    "name:bul_x_preferred":[
        "\u0421\u0430\u043b\u0442\u0430\u0440\u0430"
    ],
    "name:ceb_x_preferred":[
        "Saltara"
    ],
    "name:deu_x_preferred":[
        "Saltara"
    ],
    "name:epo_x_preferred":[
        "Saltara"
    ],
    "name:eus_x_preferred":[
        "Saltara"
    ],
    "name:fas_x_preferred":[
        "\u0633\u0627\u0644\u062a\u0627\u0631\u0627"
    ],
    "name:fra_x_preferred":[
        "Saltara"
    ],
    "name:hun_x_preferred":[
        "Saltara"
    ],
    "name:hye_x_preferred":[
        "\u054d\u0561\u056c\u057f\u0561\u0580\u0561"
    ],
    "name:ina_x_preferred":[
        "Saltara"
    ],
    "name:ita_x_preferred":[
        "Saltara"
    ],
    "name:jpn_x_preferred":[
        "\u30b5\u30eb\u30bf\u30fc\u30e9"
    ],
    "name:kaz_x_preferred":[
        "\u0421\u0430\u043b\u044c\u0442\u0430\u0440\u0430"
    ],
    "name:lat_x_preferred":[
        "Saltaria"
    ],
    "name:lmo_x_preferred":[
        "Saltara"
    ],
    "name:msa_x_preferred":[
        "Saltara"
    ],
    "name:nap_x_preferred":[
        "Saltara"
    ],
    "name:nld_x_preferred":[
        "Saltara"
    ],
    "name:pms_x_preferred":[
        "Saltara"
    ],
    "name:pol_x_preferred":[
        "Saltara"
    ],
    "name:por_x_preferred":[
        "Saltara"
    ],
    "name:ron_x_preferred":[
        "Saltara"
    ],
    "name:rus_x_preferred":[
        "\u0421\u0430\u043b\u044c\u0442\u0430\u0440\u0430"
    ],
    "name:spa_x_preferred":[
        "Saltara"
    ],
    "name:srp_x_preferred":[
        "\u0421\u0430\u043b\u0442\u0430\u0440\u0430"
    ],
    "name:tgl_x_preferred":[
        "Saltara"
    ],
    "name:ukr_x_preferred":[
        "\u0421\u0430\u043b\u044c\u0442\u0430\u0440\u0430"
    ],
    "name:uzb_x_preferred":[
        "Saltara"
    ],
    "name:vec_x_preferred":[
        "Saltara"
    ],
    "name:vie_x_preferred":[
        "Saltara"
    ],
    "name:vol_x_preferred":[
        "Saltara"
    ],
    "name:war_x_preferred":[
        "Saltara"
    ],
    "name:zho_x_preferred":[
        "\u8428\u5c14\u5854\u62c9"
    ],
    "wof:name":"Saltara",
    "wof:placetype":"locality"
},
  "geometry": {"coordinates":[82.02526,28.65629],"type":"Point"}
}