{
  "type": "Feature",
  "properties": {
    "gn:admin1_code":"MR",
    "gn:admin2_code":"2",
    "gn:admin3_code":"61.0",
    "gn:admin4_code":"610027.0",
    "gn:asciiname":"Saltara",
    "gn:country_code":"NP",
    "gn:dem":633,
    "gn:feature_class":"P",
    "gn:feature_code":"PPLL",
    "gn:name":"Saltara",
    "gn:population":0,
    "gn:timezone":"Asia/Kathmandu",
    "iso:country":"NP",
    "wof:name":"Saltara",
    "wof:placetype":"locality"
},
  "geometry": {"coordinates":[82.02526,28.65629],"type":"Point"}
}