{
  "type": "Feature",
  "properties": {
    "gn:admin1_code":"CR",
    "gn:admin2_code":"5",
    "gn:admin3_code":"20",
    "gn:admin4_code":"200004",
    "gn:asciiname":"Gargare",
    "gn:country_code":"NP",
    "gn:dem":1177,
    "gn:feature_class":"P",
    "gn:feature_code":"PPLL",
    "gn:name":"Gargare",
    "gn:population":0,
    "gn:timezone":"Asia/Kathmandu",
    "iso:country":"NP",
    "wof:name":"Gargare",
    "wof:placetype":"locality"
},
  "geometry": {"coordinates":[86.14069000000001,27.18612000000001],"type":"Point"}
}