{
  "type": "Feature",
  "properties": {
    "gn:admin1_code":"CR",
    "gn:admin2_code":"5",
    "gn:admin3_code":"20",
    "gn:admin4_code":"200049",
    "gn:asciiname":"Kebalpur",
    "gn:country_code":"NP",
    "gn:dem":1097,
    "gn:feature_class":"P",
    "gn:feature_code":"PPLL",
    "gn:name":"Kebalpur",
    "gn:population":0,
    "gn:timezone":"Asia/Kathmandu",
    "iso:country":"NP",
    "name:msa_x_preferred":[
        "Kebalpur"
    ],
    "wof:name":"Kebalpur",
    "wof:placetype":"locality"
},
  "geometry": {"coordinates":[86.22802,27.22324],"type":"Point"}
}