{
  "type": "Feature",
  "properties": {
    "gn:admin1_code":"CR",
    "gn:admin2_code":"11",
    "gn:admin3_code":"35.0",
    "gn:admin4_code":"350007.0",
    "gn:asciiname":"Jyamire",
    "gn:country_code":"NP",
    "gn:dem":202,
    "gn:feature_class":"P",
    "gn:feature_code":"PPLL",
    "gn:name":"Jyamire",
    "gn:population":0,
    "gn:timezone":"Asia/Kathmandu",
    "iso:country":"NP",
    "wof:name":"Jyamire",
    "wof:placetype":"locality"
},
  "geometry": {"coordinates":[84.54949000000001,27.61976],"type":"Point"}
}