{
  "type": "Feature",
  "properties": {
    "gn:admin1_code":"ER",
    "gn:admin2_code":"7",
    "gn:admin3_code":"9",
    "gn:admin4_code":"90011",
    "gn:asciiname":"Arubote",
    "gn:country_code":"NP",
    "gn:dem":1955,
    "gn:feature_class":"P",
    "gn:feature_code":"PPLL",
    "gn:name":"Arubote",
    "gn:population":0,
    "gn:timezone":"Asia/Kathmandu",
    "iso:country":"NP",
    "name:bih_x_preferred":[
        "\u0906\u0930\u0941\u0935\u094b\u091f\u0947"
    ],
    "name:ceb_x_preferred":[
        "Aarubote"
    ],
    "name:mai_x_preferred":[
        "\u0906\u0930\u0941\u0935\u094b\u091f\u0947"
    ],
    "name:msa_x_preferred":[
        "Aarubote"
    ],
    "name:nep_x_preferred":[
        "\u0906\u0930\u0941\u092c\u094b\u091f\u0947"
    ],
    "name:new_x_preferred":[
        "\u0906\u0930\u0941\u092c\u094b\u091f\u0947"
    ],
    "name:pol_x_preferred":[
        "Aarubote"
    ],
    "wof:name":"Arubote",
    "wof:placetype":"locality"
},
  "geometry": {"coordinates":[87.36468000000001,27.37374],"type":"Point"}
}