{
  "type": "Feature",
  "properties": {
    "gn:admin1_code":"WR",
    "gn:admin2_code":"3",
    "gn:admin3_code":"44",
    "gn:admin4_code":"440023",
    "gn:asciiname":"Dadalichaur",
    "gn:country_code":"NP",
    "gn:dem":795,
    "gn:feature_class":"P",
    "gn:feature_code":"PPLL",
    "gn:name":"Dadalichaur",
    "gn:population":0,
    "gn:timezone":"Asia/Kathmandu",
    "iso:country":"NP",
    "wof:name":"Dadalichaur",
    "wof:placetype":"locality"
},
  "geometry": {"coordinates":[83.64694,28.17387],"type":"Point"}
}