{
  "type": "Feature",
  "properties": {
    "gn:admin1_code":"WR",
    "gn:admin2_code":"4.0",
    "gn:admin3_code":"38.0",
    "gn:admin4_code":"380027.0",
    "gn:asciiname":"Khairenitar",
    "gn:country_code":"NP",
    "gn:dem":515,
    "gn:feature_class":"P",
    "gn:feature_code":"PPLL",
    "gn:name":"Khairenitar",
    "gn:population":0,
    "gn:timezone":"Asia/Kathmandu",
    "iso:country":"NP",
    "name:ceb_x_preferred":[
        "Khairenitar"
    ],
    "name:msa_x_preferred":[
        "Khairenitar"
    ],
    "name:new_x_preferred":[
        "\u0916\u0948\u0930\u0947\u0928\u0940\u091f\u093e\u0930"
    ],
    "name:pol_x_preferred":[
        "Khairenitar"
    ],
    "wof:name":"Khairenitar",
    "wof:placetype":"locality"
},
  "geometry": {"coordinates":[84.09510999999998,28.02969],"type":"Point"}
}