{
  "type": "Feature",
  "properties": {
    "gn:admin1_code":"CR",
    "gn:admin2_code":"1",
    "gn:admin3_code":"30.0",
    "gn:admin4_code":"300008.0",
    "gn:asciiname":"Rupakot",
    "gn:country_code":"NP",
    "gn:dem":1059,
    "gn:feature_class":"P",
    "gn:feature_code":"PPLL",
    "gn:name":"Rupakot",
    "gn:population":0,
    "gn:timezone":"Asia/Kathmandu",
    "iso:country":"NP",
    "name:fra_x_preferred":[
        "Rupakot"
    ],
    "name:new_x_preferred":[
        "\u0930\u0941\u092a\u093e\u0915\u094b\u0924 \u0969"
    ],
    "name:pol_x_preferred":[
        "Rupakot"
    ],
    "wof:name":"Rupakot",
    "wof:placetype":"locality"
},
  "geometry": {"coordinates":[85.1934,27.72458],"type":"Point"}
}