{
  "type": "Feature",
  "properties": {
    "gn:admin1_code":"ER",
    "gn:admin2_code":"7",
    "gn:admin3_code":"9",
    "gn:admin4_code":"90001",
    "gn:asciiname":"Huturungbesi",
    "gn:country_code":"NP",
    "gn:dem":516,
    "gn:feature_class":"P",
    "gn:feature_code":"PPLL",
    "gn:name":"Huturungbesi",
    "gn:population":0,
    "gn:timezone":"Asia/Kathmandu",
    "iso:country":"NP",
    "wof:name":"Huturungbesi",
    "wof:placetype":"locality"
},
  "geometry": {"coordinates":[87.2713,27.23725],"type":"Point"}
}