{
  "type": "Feature",
  "properties": {
    "gn:admin1_code":"MR",
    "gn:admin2_code":"2.0",
    "gn:admin3_code":"59.0",
    "gn:admin4_code":"590022.0",
    "gn:asciiname":"Dubichaur",
    "gn:country_code":"NP",
    "gn:dem":369,
    "gn:feature_class":"P",
    "gn:feature_code":"PPLL",
    "gn:name":"Dubichaur",
    "gn:population":0,
    "gn:timezone":"Asia/Kathmandu",
    "iso:country":"NP",
    "wof:name":"Dubichaur",
    "wof:placetype":"locality"
},
  "geometry": {"coordinates":[81.50369000000001,28.60049],"type":"Point"}
}