{
  "type": "Feature",
  "properties": {
    "gn:admin1_code":"MR",
    "gn:admin2_code":"2.0",
    "gn:admin3_code":"58.0",
    "gn:admin4_code":"580001.0",
    "gn:asciiname":"Kalabanjar",
    "gn:country_code":"NP",
    "gn:dem":148,
    "gn:feature_class":"P",
    "gn:feature_code":"PPLL",
    "gn:name":"Kalabanjar",
    "gn:population":0,
    "gn:timezone":"Asia/Kathmandu",
    "iso:country":"NP",
    "wof:name":"Kalabanjar",
    "wof:placetype":"locality"
},
  "geometry": {"coordinates":[81.13519000000002,28.4154],"type":"Point"}
}