{
  "type": "Feature",
  "properties": {
    "gn:admin1_code":"FR",
    "gn:admin2_code":"14",
    "gn:admin3_code":"71.0",
    "gn:admin4_code":"710042.0",
    "gn:asciiname":"Samitipur",
    "gn:country_code":"NP",
    "gn:dem":161,
    "gn:feature_class":"P",
    "gn:feature_code":"PPLL",
    "gn:name":"Samitipur",
    "gn:population":0,
    "gn:timezone":"Asia/Kathmandu",
    "iso:country":"NP",
    "wof:name":"Samitipur",
    "wof:placetype":"locality"
},
  "geometry": {"coordinates":[81.11754000000001,28.54402],"type":"Point"}
}