{
  "type": "Feature",
  "properties": {
    "gn:admin1_code":"WR",
    "gn:admin2_code":"4.0",
    "gn:admin3_code":"39.0",
    "gn:admin4_code":"390041.0",
    "gn:asciiname":"Bardlang",
    "gn:country_code":"NP",
    "gn:dem":1083,
    "gn:feature_class":"P",
    "gn:feature_code":"PPLL",
    "gn:name":"Bardlang",
    "gn:population":0,
    "gn:timezone":"Asia/Kathmandu",
    "iso:country":"NP",
    "wof:name":"Bardlang",
    "wof:placetype":"locality"
},
  "geometry": {"coordinates":[83.67499000000002,27.96168],"type":"Point"}
}