{
  "type": "Feature",
  "properties": {
    "gn:admin1_code":"CR",
    "gn:admin2_code":"1",
    "gn:admin3_code":"30.0",
    "gn:admin4_code":"300002.0",
    "gn:asciiname":"Karkidandagaun",
    "gn:country_code":"NP",
    "gn:dem":866,
    "gn:feature_class":"P",
    "gn:feature_code":"PPLL",
    "gn:name":"Karkidandagaun",
    "gn:population":0,
    "gn:timezone":"Asia/Kathmandu",
    "iso:country":"NP",
    "wof:name":"Karkidandagaun",
    "wof:placetype":"locality"
},
  "geometry": {"coordinates":[84.96488000000002,27.76373],"type":"Point"}
}