{
  "type": "Feature",
  "properties": {
    "gn:admin1_code":"CR",
    "gn:admin2_code":"1",
    "gn:admin3_code":"23",
    "gn:admin4_code":"230011",
    "gn:asciiname":"Bhote Namlang",
    "gn:country_code":"NP",
    "gn:dem":1702,
    "gn:feature_class":"P",
    "gn:feature_code":"PPLL",
    "gn:name":"Bhote Namlang",
    "gn:population":0,
    "gn:timezone":"Asia/Kathmandu",
    "iso:country":"NP",
    "wof:name":"Bhote Namlang",
    "wof:placetype":"locality"
},
  "geometry": {"coordinates":[85.65803000000002,27.88766],"type":"Point"}
}