{
  "type": "Feature",
  "properties": {
    "gn:admin1_code":"CR",
    "gn:admin2_code":"1.0",
    "gn:admin3_code":"26.0",
    "gn:admin4_code":"260001.0",
    "gn:asciiname":"Thakalmath",
    "gn:country_code":"NP",
    "gn:dem":1741,
    "gn:feature_class":"P",
    "gn:feature_code":"PPLL",
    "gn:name":"Thakalmath",
    "gn:population":0,
    "gn:timezone":"Asia/Kathmandu",
    "iso:country":"NP",
    "wof:name":"Thakalmath",
    "wof:placetype":"locality"
},
  "geometry": {"coordinates":[85.49412,27.69133],"type":"Point"}
}