{
  "type": "Feature",
  "properties": {
    "gn:admin1_code":"WR",
    "gn:admin2_code":"3",
    "gn:admin3_code":"43",
    "gn:admin4_code":"430016",
    "gn:asciiname":"Aul",
    "gn:country_code":"NP",
    "gn:dem":1676,
    "gn:feature_class":"P",
    "gn:feature_code":"PPLL",
    "gn:name":"Aul",
    "gn:population":0,
    "gn:timezone":"Asia/Kathmandu",
    "iso:country":"NP",
    "wof:name":"Aul",
    "wof:placetype":"locality"
},
  "geometry": {"coordinates":[83.61968,28.41462000000001],"type":"Point"}
}