{
  "type": "Feature",
  "properties": {
    "gn:admin1_code":"WR",
    "gn:admin2_code":"3",
    "gn:admin3_code":"43",
    "gn:admin4_code":"430016",
    "gn:asciiname":"Aul",
    "gn:country_code":"NP",
    "gn:dem":1676,
    "gn:feature_class":"P",
    "gn:feature_code":"PPLL",
    "gn:name":"Aul",
    "gn:population":0,
    "gn:timezone":"Asia/Kathmandu",
    "iso:country":"NP",
    "name:bul_x_preferred":[
        "\u0410\u0443\u043b"
    ],
    "name:cat_x_preferred":[
        "A\u00fcl"
    ],
    "name:ces_x_preferred":[
        "Aul"
    ],
    "name:deu_x_preferred":[
        "Aul"
    ],
    "name:eus_x_preferred":[
        "Aul"
    ],
    "name:fra_x_preferred":[
        "Aoul"
    ],
    "name:heb_x_preferred":[
        "\u05d0\u05d0\u05d5\u05dc"
    ],
    "name:hun_x_preferred":[
        "Aul"
    ],
    "name:hye_x_preferred":[
        "\u0531\u0578\u0582\u056c"
    ],
    "name:ita_x_preferred":[
        "Aul"
    ],
    "name:lit_x_preferred":[
        "A\u016blas"
    ],
    "name:msa_x_preferred":[
        "Aul"
    ],
    "name:nld_x_preferred":[
        "Aoel"
    ],
    "name:pol_x_preferred":[
        "Au\u0142"
    ],
    "name:por_x_preferred":[
        "Aul"
    ],
    "name:rus_x_preferred":[
        "\u0410\u0443\u043b"
    ],
    "name:slk_x_preferred":[
        "Aul"
    ],
    "name:spa_x_preferred":[
        "A\u00fal"
    ],
    "name:tgk_x_preferred":[
        "\u0410\u0432\u0443\u043b"
    ],
    "name:ukr_x_preferred":[
        "\u0410\u0443\u043b"
    ],
    "name:zho_x_preferred":[
        "\u963f\u70cf\u723e"
    ],
    "wof:name":"Aul",
    "wof:placetype":"locality"
},
  "geometry": {"coordinates":[83.61968,28.41462000000001],"type":"Point"}
}