{
  "type": "Feature",
  "properties": {
    "gn:admin1_code":"00",
    "gn:asciiname":"Digau",
    "gn:country_code":"NP",
    "gn:dem":871,
    "gn:feature_class":"P",
    "gn:feature_code":"PPL",
    "gn:name":"\u1e0cig\u0101\u0169",
    "gn:population":0,
    "gn:timezone":"Asia/Kathmandu",
    "iso:country":"NP",
    "name:nep_x_preferred":[
        "\u1e0cig\u0101\u0169"
    ],
    "wof:name":"Digau",
    "wof:placetype":"locality"
},
  "geometry": {"coordinates":[84.80028,28.01762],"type":"Point"}
}