{
  "type": "Feature",
  "properties": {
    "gn:admin1_code":"WR",
    "gn:admin2_code":"4",
    "gn:admin3_code":"40.0",
    "gn:admin4_code":"400005.0",
    "gn:asciiname":"Thadabari",
    "gn:country_code":"NP",
    "gn:dem":1103,
    "gn:feature_class":"P",
    "gn:feature_code":"PPLL",
    "gn:name":"Thadabari",
    "gn:population":0,
    "gn:timezone":"Asia/Kathmandu",
    "iso:country":"NP",
    "wof:name":"Thadabari",
    "wof:placetype":"locality"
},
  "geometry": {"coordinates":[84.04761999999999,28.12517],"type":"Point"}
}