{
  "type": "Feature",
  "properties": {
    "gn:admin1_code":"WR",
    "gn:admin2_code":"8",
    "gn:admin3_code":"49",
    "gn:admin4_code":"490066",
    "gn:asciiname":"Chhattarpur",
    "gn:country_code":"NP",
    "gn:dem":99,
    "gn:feature_class":"P",
    "gn:feature_code":"PPLL",
    "gn:name":"Chhattarpur",
    "gn:population":0,
    "gn:timezone":"Asia/Kathmandu",
    "iso:country":"NP",
    "wof:name":"Chhattarpur",
    "wof:placetype":"locality"
},
  "geometry": {"coordinates":[83.32708000000002,27.46304],"type":"Point"}
}