{
  "type": "Feature",
  "properties": {
    "gn:admin1_code":"CR",
    "gn:admin2_code":"1",
    "gn:admin3_code":"30.0",
    "gn:admin4_code":"300031.0",
    "gn:asciiname":"Odaregaun",
    "gn:country_code":"NP",
    "gn:dem":1058,
    "gn:feature_class":"P",
    "gn:feature_code":"PPLL",
    "gn:name":"Odaregaun",
    "gn:population":0,
    "gn:timezone":"Asia/Kathmandu",
    "iso:country":"NP",
    "wof:name":"Odaregaun",
    "wof:placetype":"locality"
},
  "geometry": {"coordinates":[84.88538,28.03908],"type":"Point"}
}