{
  "type": "Feature",
  "properties": {
    "gn:admin1_code":"MR",
    "gn:admin2_code":"12",
    "gn:admin3_code":"53",
    "gn:admin4_code":"530043",
    "gn:asciiname":"Milan Chok",
    "gn:country_code":"NP",
    "gn:dem":1715,
    "gn:feature_class":"P",
    "gn:feature_code":"PPLL",
    "gn:name":"Milan Chok",
    "gn:population":0,
    "gn:timezone":"Asia/Kathmandu",
    "iso:country":"NP",
    "wof:name":"Milan Chok",
    "wof:placetype":"locality"
},
  "geometry": {"coordinates":[82.82762,28.24064000000001],"type":"Point"}
}