{
  "type": "Feature",
  "properties": {
    "gn:admin1_code":"ER",
    "gn:admin2_code":"10",
    "gn:admin3_code":"4.0",
    "gn:admin4_code":"40020.0",
    "gn:asciiname":"Laksmipur",
    "gn:country_code":"NP",
    "gn:dem":120,
    "gn:feature_class":"P",
    "gn:feature_code":"PPLL",
    "gn:name":"Laksmipur",
    "gn:population":0,
    "gn:timezone":"Asia/Kathmandu",
    "iso:country":"NP",
    "wof:name":"Laksmipur",
    "wof:placetype":"locality"
},
  "geometry": {"coordinates":[87.95223,26.64014],"type":"Point"}
}