{
  "type": "Feature",
  "properties": {
    "gn:admin1_code":"CR",
    "gn:admin2_code":"5",
    "gn:admin3_code":"18",
    "gn:admin4_code":"180012",
    "gn:asciiname":"Laksmipur (Bhantabari)",
    "gn:country_code":"NP",
    "gn:dem":142,
    "gn:feature_class":"P",
    "gn:feature_code":"PPLL",
    "gn:name":"Laksmipur (Bhantabari)",
    "gn:population":0,
    "gn:timezone":"Asia/Kathmandu",
    "iso:country":"NP",
    "wof:name":"Laksmipur (Bhantabari)",
    "wof:placetype":"locality"
},
  "geometry": {"coordinates":[85.78754000000001,26.9486],"type":"Point"}
}