{
  "type": "Feature",
  "properties": {
    "gn:admin1_code":"ER",
    "gn:admin2_code":"13",
    "gn:admin3_code":"11",
    "gn:admin4_code":"110001",
    "gn:asciiname":"Hakula",
    "gn:country_code":"NP",
    "gn:dem":1904,
    "gn:feature_class":"P",
    "gn:feature_code":"PPLL",
    "gn:name":"Hakula",
    "gn:population":0,
    "gn:timezone":"Asia/Kathmandu",
    "iso:country":"NP",
    "wof:name":"Hakula",
    "wof:placetype":"locality"
},
  "geometry": {"coordinates":[86.74791,27.53395],"type":"Point"}
}