{
  "type": "Feature",
  "properties": {
    "gn:admin1_code":"CR",
    "gn:admin2_code":"1",
    "gn:admin3_code":"24.0",
    "gn:admin4_code":"240037.0",
    "gn:asciiname":"Bahunchaur",
    "gn:country_code":"NP",
    "gn:dem":1524,
    "gn:feature_class":"P",
    "gn:feature_code":"PPLL",
    "gn:name":"Bahunchaur",
    "gn:population":0,
    "gn:timezone":"Asia/Kathmandu",
    "iso:country":"NP",
    "wof:name":"Bahunchaur",
    "wof:placetype":"locality"
},
  "geometry": {"coordinates":[85.48678000000002,27.5707],"type":"Point"}
}