{
  "type": "Feature",
  "properties": {
    "gn:admin1_code":"ER",
    "gn:admin2_code":"10",
    "gn:admin3_code":"3.0",
    "gn:admin4_code":"30037.0",
    "gn:asciiname":"Sombarebesi",
    "gn:country_code":"NP",
    "gn:dem":916,
    "gn:feature_class":"P",
    "gn:feature_code":"PPLL",
    "gn:name":"Sombarebesi",
    "gn:population":0,
    "gn:timezone":"Asia/Kathmandu",
    "iso:country":"NP",
    "wof:name":"Sombarebesi",
    "wof:placetype":"locality"
},
  "geometry": {"coordinates":[87.96773,26.97136],"type":"Point"}
}