{
  "type": "Feature",
  "properties": {
    "gn:admin1_code":"CR",
    "gn:admin2_code":"1",
    "gn:admin3_code":"29",
    "gn:admin4_code":"290011.0",
    "gn:asciiname":"Dragmorpa",
    "gn:country_code":"NP",
    "gn:dem":5802,
    "gn:feature_class":"P",
    "gn:feature_code":"PPLL",
    "gn:name":"Dragmorpa",
    "gn:population":0,
    "gn:timezone":"Asia/Kathmandu",
    "iso:country":"NP",
    "wof:name":"Dragmorpa",
    "wof:placetype":"locality"
},
  "geometry": {"coordinates":[85.66762,28.32732],"type":"Point"}
}