{
  "type": "Feature",
  "properties": {
    "gn:admin1_code":"ER",
    "gn:admin2_code":"10",
    "gn:admin3_code":"3.0",
    "gn:admin4_code":"30048.0",
    "gn:asciiname":"Maipatal",
    "gn:country_code":"NP",
    "gn:dem":1967,
    "gn:feature_class":"P",
    "gn:feature_code":"PPLL",
    "gn:name":"Maipatal",
    "gn:population":0,
    "gn:timezone":"Asia/Kathmandu",
    "iso:country":"NP",
    "wof:name":"Maipatal",
    "wof:placetype":"locality"
},
  "geometry": {"coordinates":[87.93033,27.02873],"type":"Point"}
}