{
  "type": "Feature",
  "properties": {
    "gn:admin1_code":"CR",
    "gn:admin2_code":"1",
    "gn:admin3_code":"28",
    "gn:admin4_code":"280046",
    "gn:asciiname":"Kaphle",
    "gn:country_code":"NP",
    "gn:dem":1149,
    "gn:feature_class":"P",
    "gn:feature_code":"PPLL",
    "gn:name":"Kaphle",
    "gn:population":0,
    "gn:timezone":"Asia/Kathmandu",
    "iso:country":"NP",
    "wof:name":"Kaphle",
    "wof:placetype":"locality"
},
  "geometry": {"coordinates":[85.40467,27.91816],"type":"Point"}
}