{
  "type": "Feature",
  "properties": {
    "gn:admin1_code":"WR",
    "gn:admin2_code":"8",
    "gn:admin3_code":"50.0",
    "gn:admin4_code":"500046.0",
    "gn:asciiname":"Lalpur",
    "gn:country_code":"NP",
    "gn:dem":114,
    "gn:feature_class":"P",
    "gn:feature_code":"PPLL",
    "gn:name":"Lalpur",
    "gn:population":0,
    "gn:timezone":"Asia/Kathmandu",
    "iso:country":"NP",
    "name:ceb_x_preferred":[
        "Lalpur"
    ],
    "name:pol_x_preferred":[
        "Lalpur"
    ],
    "name:swe_x_preferred":[
        "Lalpur"
    ],
    "wof:name":"Lalpur",
    "wof:placetype":"locality"
},
  "geometry": {"coordinates":[82.88878000000003,27.58856],"type":"Point"}
}