{
  "type": "Feature",
  "properties": {
    "gn:admin1_code":"ER",
    "gn:admin2_code":"13.0",
    "gn:admin3_code":"14.0",
    "gn:admin4_code":"140033.0",
    "gn:asciiname":"Beltar",
    "gn:country_code":"NP",
    "gn:dem":858,
    "gn:feature_class":"P",
    "gn:feature_code":"PPLL",
    "gn:name":"Beltar",
    "gn:population":0,
    "gn:timezone":"Asia/Kathmandu",
    "iso:country":"NP",
    "wof:name":"Beltar",
    "wof:placetype":"locality"
},
  "geometry": {"coordinates":[86.41813,27.09731],"type":"Point"}
}