{
  "type": "Feature",
  "properties": {
    "gn:admin1_code":"FR",
    "gn:admin2_code":"14",
    "gn:admin3_code":"68",
    "gn:admin4_code":"680005",
    "gn:asciiname":"Pundhar",
    "gn:country_code":"NP",
    "gn:dem":2053,
    "gn:feature_class":"P",
    "gn:feature_code":"PPLL",
    "gn:name":"Pundhar",
    "gn:population":0,
    "gn:timezone":"Asia/Kathmandu",
    "iso:country":"NP",
    "wof:name":"Pundhar",
    "wof:placetype":"locality"
},
  "geometry": {"coordinates":[81.05677,29.54436],"type":"Point"}
}