{
  "type": "Feature",
  "properties": {
    "gn:admin1_code":"ER",
    "gn:admin2_code":"13",
    "gn:admin3_code":"12",
    "gn:admin4_code":"120014",
    "gn:asciiname":"Bhadaure",
    "gn:country_code":"NP",
    "gn:dem":1243,
    "gn:feature_class":"P",
    "gn:feature_code":"PPLL",
    "gn:name":"Bhadaure",
    "gn:population":0,
    "gn:timezone":"Asia/Kathmandu",
    "iso:country":"NP",
    "name:pol_x_preferred":[
        "Bhadaure"
    ],
    "wof:name":"Bhadaure",
    "wof:placetype":"locality"
},
  "geometry": {"coordinates":[86.28643000000002,27.33937],"type":"Point"}
}