{
  "type": "Feature",
  "properties": {
    "gn:admin1_code":"WR",
    "gn:admin2_code":"4.0",
    "gn:admin3_code":"38.0",
    "gn:admin4_code":"380010.0",
    "gn:asciiname":"Biruwa",
    "gn:country_code":"NP",
    "gn:dem":926,
    "gn:feature_class":"P",
    "gn:feature_code":"PPLL",
    "gn:name":"Biruwa",
    "gn:population":0,
    "gn:timezone":"Asia/Kathmandu",
    "iso:country":"NP",
    "name:mai_x_preferred":[
        "\u092c\u093f\u0930\u0941\u0935\u093e \u0917\u093e\u0909\u0901\u092a\u093e\u0932\u093f\u0915\u093e"
    ],
    "name:nep_x_preferred":[
        "\u092c\u093f\u0930\u0941\u0935\u093e \u0917\u093e\u0909\u0901\u092a\u093e\u0932\u093f\u0915\u093e"
    ],
    "wof:name":"Biruwa",
    "wof:placetype":"locality"
},
  "geometry": {"coordinates":[84.279,27.85607000000001],"type":"Point"}
}