{
  "type": "Feature",
  "properties": {
    "gn:admin1_code":"MR",
    "gn:admin2_code":"12",
    "gn:admin3_code":"52",
    "gn:admin4_code":"520048",
    "gn:asciiname":"Pidalne",
    "gn:country_code":"NP",
    "gn:dem":947,
    "gn:feature_class":"P",
    "gn:feature_code":"PPLL",
    "gn:name":"Pidalne",
    "gn:population":0,
    "gn:timezone":"Asia/Kathmandu",
    "iso:country":"NP",
    "wof:name":"Pidalne",
    "wof:placetype":"locality"
},
  "geometry": {"coordinates":[82.96484,28.14437],"type":"Point"}
}