{
  "type": "Feature",
  "properties": {
    "gn:admin1_code":"FR",
    "gn:admin2_code":"9",
    "gn:admin3_code":"74",
    "gn:admin4_code":"740060",
    "gn:asciiname":"Bethad",
    "gn:country_code":"NP",
    "gn:dem":1897,
    "gn:feature_class":"P",
    "gn:feature_code":"PPLL",
    "gn:name":"Bethad",
    "gn:population":0,
    "gn:timezone":"Asia/Kathmandu",
    "iso:country":"NP",
    "wof:name":"Bethad",
    "wof:placetype":"locality"
},
  "geometry": {"coordinates":[80.53267,29.55375],"type":"Point"}
}