{
  "type": "Feature",
  "properties": {
    "gn:admin1_code":"MR",
    "gn:admin2_code":"2",
    "gn:admin3_code":"61.0",
    "gn:admin4_code":"610004.0",
    "gn:asciiname":"Thali",
    "gn:country_code":"NP",
    "gn:dem":2567,
    "gn:feature_class":"P",
    "gn:feature_code":"PPLL",
    "gn:name":"Thali",
    "gn:population":0,
    "gn:timezone":"Asia/Kathmandu",
    "iso:country":"NP",
    "wof:name":"Thali",
    "wof:placetype":"locality"
},
  "geometry": {"coordinates":[81.98054,28.96703],"type":"Point"}
}