{
  "type": "Feature",
  "properties": {
    "gn:admin1_code":"ER",
    "gn:admin2_code":"10",
    "gn:admin3_code":"2",
    "gn:admin4_code":"20020",
    "gn:asciiname":"Naralang  Narayan",
    "gn:country_code":"NP",
    "gn:dem":2817,
    "gn:feature_class":"P",
    "gn:feature_code":"PPLL",
    "gn:name":"Naralang  Narayan",
    "gn:population":0,
    "gn:timezone":"Asia/Kathmandu",
    "iso:country":"NP",
    "wof:name":"Naralang  Narayan",
    "wof:placetype":"locality"
},
  "geometry": {"coordinates":[87.97511,27.19451],"type":"Point"}
}