{
  "type": "Feature",
  "properties": {
    "gn:admin1_code":"00",
    "gn:asciiname":"Dillikot",
    "gn:country_code":"NP",
    "gn:dem":2035,
    "gn:feature_class":"P",
    "gn:feature_code":"PPL",
    "gn:name":"Dillikot",
    "gn:population":0,
    "gn:timezone":"Asia/Kathmandu",
    "iso:country":"NP",
    "wof:name":"Dillikot",
    "wof:placetype":"locality"
},
  "geometry": {"coordinates":[81.75381,29.06456],"type":"Point"}
}