{
  "type": "Feature",
  "properties": {
    "gn:admin1_code":"FR",
    "gn:admin2_code":"14",
    "gn:admin3_code":"69",
    "gn:admin4_code":"690024",
    "gn:asciiname":"Dewal",
    "gn:country_code":"NP",
    "gn:dem":1614,
    "gn:feature_class":"P",
    "gn:feature_code":"PPLL",
    "gn:name":"Dewal",
    "gn:population":0,
    "gn:timezone":"Asia/Kathmandu",
    "iso:country":"NP",
    "name:fas_x_preferred":[
        "\u062f\u06cc\u0648\u0644"
    ],
    "name:pnb_x_preferred":[
        "\u062f\u06cc\u0648\u0627\u0644"
    ],
    "name:urd_x_preferred":[
        "\u062f\u06cc\u0648\u0644"
    ],
    "wof:name":"Dewal",
    "wof:placetype":"locality"
},
  "geometry": {"coordinates":[81.31806999999998,29.01836],"type":"Point"}
}