{
  "type": "Feature",
  "properties": {
    "gn:admin1_code":"WR",
    "gn:admin2_code":"3",
    "gn:admin3_code":"44",
    "gn:admin4_code":"440014",
    "gn:asciiname":"Chordi",
    "gn:country_code":"NP",
    "gn:dem":750,
    "gn:feature_class":"P",
    "gn:feature_code":"PPLL",
    "gn:name":"Chordi",
    "gn:population":0,
    "gn:timezone":"Asia/Kathmandu",
    "iso:country":"NP",
    "wof:name":"Chordi",
    "wof:placetype":"locality"
},
  "geometry": {"coordinates":[83.5869,28.03547],"type":"Point"}
}