{
  "type": "Feature",
  "properties": {
    "gn:admin1_code":"WR",
    "gn:admin2_code":"4",
    "gn:admin3_code":"37",
    "gn:admin4_code":"370016",
    "gn:asciiname":"Timure",
    "gn:country_code":"NP",
    "gn:dem":618,
    "gn:feature_class":"P",
    "gn:feature_code":"PPLL",
    "gn:name":"Timure",
    "gn:population":0,
    "gn:timezone":"Asia/Kathmandu",
    "iso:country":"NP",
    "wof:name":"Timure",
    "wof:placetype":"locality"
},
  "geometry": {"coordinates":[84.52946,28.10355],"type":"Point"}
}