{
  "type": "Feature",
  "properties": {
    "gn:admin1_code":"00",
    "gn:asciiname":"Sithuntar",
    "gn:country_code":"NP",
    "gn:dem":226,
    "gn:feature_class":"P",
    "gn:feature_code":"PPL",
    "gn:name":"Si\u1e6dhu\u1e45\u1e6d\u0101r",
    "gn:population":0,
    "gn:timezone":"Asia/Kathmandu",
    "iso:country":"NP",
    "name:nep_x_preferred":[
        "Si\u1e6dhu\u1e45\u1e6d\u0101r"
    ],
    "wof:name":"Sithuntar",
    "wof:placetype":"locality"
},
  "geometry": {"coordinates":[86.50588,26.84293],"type":"Point"}
}