{
  "type": "Feature",
  "properties": {
    "gn:admin1_code":"00",
    "gn:asciiname":"Beldagi",
    "gn:country_code":"NP",
    "gn:dem":108,
    "gn:feature_class":"P",
    "gn:feature_code":"PPL",
    "gn:name":"Bel\u1e0d\u0101\u0303gi\u0307\u0304",
    "gn:population":0,
    "gn:timezone":"Asia/Kathmandu",
    "iso:country":"NP",
    "name:nep_x_preferred":[
        "Bel\u1e0d\u0101\u0303gi\u0307\u0304"
    ],
    "wof:name":"Beldagi",
    "wof:placetype":"locality"
},
  "geometry": {"coordinates":[87.32343,26.6285],"type":"Point"}
}