{
  "type": "Feature",
  "properties": {
    "gn:admin1_code":"MR",
    "gn:admin2_code":"6",
    "gn:admin3_code":"63.0",
    "gn:admin4_code":"630030.0",
    "gn:asciiname":"Rakasim",
    "gn:country_code":"NP",
    "gn:dem":3062,
    "gn:feature_class":"P",
    "gn:feature_code":"PPLL",
    "gn:name":"Rakasim",
    "gn:population":0,
    "gn:timezone":"Asia/Kathmandu",
    "iso:country":"NP",
    "wof:name":"Rakasim",
    "wof:placetype":"locality"
},
  "geometry": {"coordinates":[82.04106999999998,29.25852],"type":"Point"}
}