{
  "type": "Feature",
  "properties": {
    "gn:admin1_code":"FR",
    "gn:admin2_code":"9",
    "gn:admin3_code":"74",
    "gn:admin4_code":"740021",
    "gn:asciiname":"Mallo Timilsaini",
    "gn:country_code":"NP",
    "gn:dem":1072,
    "gn:feature_class":"P",
    "gn:feature_code":"PPLL",
    "gn:name":"Mallo Timilsaini",
    "gn:population":0,
    "gn:timezone":"Asia/Kathmandu",
    "iso:country":"NP",
    "wof:name":"Mallo Timilsaini",
    "wof:placetype":"locality"
},
  "geometry": {"coordinates":[80.53466999999998,29.64343],"type":"Point"}
}