{
  "type": "Feature",
  "properties": {
    "gn:admin1_code":"ER",
    "gn:admin2_code":"7.0",
    "gn:admin3_code":"8.0",
    "gn:admin4_code":"80017.0",
    "gn:asciiname":"Kholme",
    "gn:country_code":"NP",
    "gn:dem":1904,
    "gn:feature_class":"P",
    "gn:feature_code":"PPLL",
    "gn:name":"Kholme",
    "gn:population":0,
    "gn:timezone":"Asia/Kathmandu",
    "iso:country":"NP",
    "wof:name":"Kholme",
    "wof:placetype":"locality"
},
  "geometry": {"coordinates":[87.55428000000001,27.20987],"type":"Point"}
}