{
  "type": "Feature",
  "properties": {
    "gn:admin1_code":"WR",
    "gn:admin2_code":"4.0",
    "gn:admin3_code":"39.0",
    "gn:admin4_code":"390041.0",
    "gn:asciiname":"Chok",
    "gn:country_code":"NP",
    "gn:dem":1110,
    "gn:feature_class":"P",
    "gn:feature_code":"PPLL",
    "gn:name":"Chok",
    "gn:population":0,
    "gn:timezone":"Asia/Kathmandu",
    "iso:country":"NP",
    "name:dan_x_preferred":[
        "Chok"
    ],
    "wof:name":"Chok",
    "wof:placetype":"locality"
},
  "geometry": {"coordinates":[83.69605,27.96265],"type":"Point"}
}