{
  "type": "Feature",
  "properties": {
    "gn:admin1_code":"MR",
    "gn:admin2_code":"12",
    "gn:admin3_code":"56.0",
    "gn:admin4_code":"560033.0",
    "gn:asciiname":"Baghkhor",
    "gn:country_code":"NP",
    "gn:dem":1356,
    "gn:feature_class":"P",
    "gn:feature_code":"PPLL",
    "gn:name":"Baghkhor",
    "gn:population":0,
    "gn:timezone":"Asia/Kathmandu",
    "iso:country":"NP",
    "wof:name":"Baghkhor",
    "wof:placetype":"locality"
},
  "geometry": {"coordinates":[82.25136999999999,28.21811],"type":"Point"}
}