{
  "type": "Feature",
  "properties": {
    "gn:admin1_code":"FR",
    "gn:admin2_code":"14",
    "gn:admin3_code":"71.0",
    "gn:admin4_code":"710034.0",
    "gn:asciiname":"Haraiyapur",
    "gn:country_code":"NP",
    "gn:dem":169,
    "gn:feature_class":"P",
    "gn:feature_code":"PPLL",
    "gn:name":"Haraiyapur",
    "gn:population":0,
    "gn:timezone":"Asia/Kathmandu",
    "iso:country":"NP",
    "wof:name":"Haraiyapur",
    "wof:placetype":"locality"
},
  "geometry": {"coordinates":[81.10328,28.60671],"type":"Point"}
}