{
  "type": "Feature",
  "properties": {
    "gn:admin1_code":"MR",
    "gn:admin2_code":"12",
    "gn:admin3_code":"56.0",
    "gn:admin4_code":"560029.0",
    "gn:asciiname":"Tamakhe",
    "gn:country_code":"NP",
    "gn:dem":436,
    "gn:feature_class":"P",
    "gn:feature_code":"PPLL",
    "gn:name":"Tamakhe",
    "gn:population":0,
    "gn:timezone":"Asia/Kathmandu",
    "iso:country":"NP",
    "wof:name":"Tamakhe",
    "wof:placetype":"locality"
},
  "geometry": {"coordinates":[82.59373000000002,27.93262],"type":"Point"}
}