{
  "type": "Feature",
  "properties": {
    "gn:admin1_code":"ER",
    "gn:admin2_code":"7",
    "gn:admin3_code":"5",
    "gn:admin4_code":"50066.0",
    "gn:asciiname":"Nihure satisale",
    "gn:country_code":"NP",
    "gn:dem":419,
    "gn:feature_class":"P",
    "gn:feature_code":"PPLL",
    "gn:name":"Nihure satisale",
    "gn:population":0,
    "gn:timezone":"Asia/Kathmandu",
    "iso:country":"NP",
    "wof:name":"Nihure satisale",
    "wof:placetype":"locality"
},
  "geometry": {"coordinates":[87.36178000000002,26.7774],"type":"Point"}
}