{
  "type": "Feature",
  "properties": {
    "gn:admin1_code":"ER",
    "gn:admin2_code":"13",
    "gn:admin3_code":"13.0",
    "gn:admin4_code":"130020.0",
    "gn:asciiname":"Pilam",
    "gn:country_code":"NP",
    "gn:dem":1792,
    "gn:feature_class":"P",
    "gn:feature_code":"PPLL",
    "gn:name":"Pilam",
    "gn:population":0,
    "gn:timezone":"Asia/Kathmandu",
    "iso:country":"NP",
    "wof:name":"Pilam",
    "wof:placetype":"locality"
},
  "geometry": {"coordinates":[86.91715000000001,27.01279000000001],"type":"Point"}
}