{
  "type": "Feature",
  "properties": {
    "gn:admin1_code":"MR",
    "gn:admin2_code":"12",
    "gn:admin3_code":"55",
    "gn:admin4_code":"550010",
    "gn:asciiname":"Linga",
    "gn:country_code":"NP",
    "gn:dem":1096,
    "gn:feature_class":"P",
    "gn:feature_code":"PPLL",
    "gn:name":"Linga",
    "gn:population":0,
    "gn:timezone":"Asia/Kathmandu",
    "iso:country":"NP",
    "wof:name":"Linga",
    "wof:placetype":"locality"
},
  "geometry": {"coordinates":[82.29668000000002,28.58309],"type":"Point"}
}