{
  "type": "Feature",
  "properties": {
    "gn:admin1_code":"ER",
    "gn:admin2_code":"7",
    "gn:admin3_code":"10.0",
    "gn:admin4_code":"100021.0",
    "gn:asciiname":"Harbu",
    "gn:country_code":"NP",
    "gn:dem":1749,
    "gn:feature_class":"P",
    "gn:feature_code":"PPLL",
    "gn:name":"Harbu",
    "gn:population":0,
    "gn:timezone":"Asia/Kathmandu",
    "iso:country":"NP",
    "wof:name":"Harbu",
    "wof:placetype":"locality"
},
  "geometry": {"coordinates":[86.97237,27.09854],"type":"Point"}
}