{
  "type": "Feature",
  "properties": {
    "gn:admin1_code":"CR",
    "gn:admin2_code":"1",
    "gn:admin3_code":"27.0",
    "gn:admin4_code":"270031.0",
    "gn:asciiname":"Naradevi",
    "gn:country_code":"NP",
    "gn:dem":1316,
    "gn:feature_class":"P",
    "gn:feature_code":"PPLL",
    "gn:name":"Naradevi",
    "gn:population":0,
    "gn:timezone":"Asia/Kathmandu",
    "iso:country":"NP",
    "wof:name":"Naradevi",
    "wof:placetype":"locality"
},
  "geometry": {"coordinates":[85.30959,27.70842],"type":"Point"}
}