{
  "type": "Feature",
  "properties": {
    "gn:admin1_code":"CR",
    "gn:admin2_code":"5",
    "gn:admin3_code":"20",
    "gn:admin4_code":"200005",
    "gn:asciiname":"Haibarbesi",
    "gn:country_code":"NP",
    "gn:dem":457,
    "gn:feature_class":"P",
    "gn:feature_code":"PPLL",
    "gn:name":"Haibarbesi",
    "gn:population":0,
    "gn:timezone":"Asia/Kathmandu",
    "iso:country":"NP",
    "wof:name":"Haibarbesi",
    "wof:placetype":"locality"
},
  "geometry": {"coordinates":[86.03291,27.30633],"type":"Point"}
}