{
  "type": "Feature",
  "properties": {
    "gn:admin1_code":"FR",
    "gn:admin2_code":"9",
    "gn:admin3_code":"74",
    "gn:admin4_code":"740010",
    "gn:asciiname":"Hadasaun",
    "gn:country_code":"NP",
    "gn:dem":1077,
    "gn:feature_class":"P",
    "gn:feature_code":"PPLL",
    "gn:name":"Hadasaun",
    "gn:population":0,
    "gn:timezone":"Asia/Kathmandu",
    "iso:country":"NP",
    "wof:name":"Hadasaun",
    "wof:placetype":"locality"
},
  "geometry": {"coordinates":[80.38183000000002,29.54511],"type":"Point"}
}