{
  "type": "Feature",
  "properties": {
    "gn:admin1_code":"ER",
    "gn:admin2_code":"7",
    "gn:admin3_code":"5",
    "gn:admin4_code":"50016",
    "gn:asciiname":"Majhgama",
    "gn:country_code":"NP",
    "gn:dem":75,
    "gn:feature_class":"P",
    "gn:feature_code":"PPLL",
    "gn:name":"Majhgama",
    "gn:population":0,
    "gn:timezone":"Asia/Kathmandu",
    "iso:country":"NP",
    "wof:name":"Majhgama",
    "wof:placetype":"locality"
},
  "geometry": {"coordinates":[87.54016,26.46223],"type":"Point"}
}