{
  "type": "Feature",
  "properties": {
    "gn:admin1_code":"FR",
    "gn:admin2_code":"14",
    "gn:admin3_code":"68",
    "gn:admin4_code":"680019",
    "gn:asciiname":"Kalukheti",
    "gn:country_code":"NP",
    "gn:dem":1587,
    "gn:feature_class":"P",
    "gn:feature_code":"PPLL",
    "gn:name":"Kalukheti",
    "gn:population":0,
    "gn:timezone":"Asia/Kathmandu",
    "iso:country":"NP",
    "wof:name":"Kalukheti",
    "wof:placetype":"locality"
},
  "geometry": {"coordinates":[81.17121,29.44814],"type":"Point"}
}