{
  "type": "Feature",
  "properties": {
    "gn:admin1_code":"ER",
    "gn:admin2_code":"10",
    "gn:admin3_code":"4.0",
    "gn:admin4_code":"40004.0",
    "gn:asciiname":"Anjani Kamat",
    "gn:country_code":"NP",
    "gn:dem":84,
    "gn:feature_class":"P",
    "gn:feature_code":"PPLL",
    "gn:name":"Anjani Kamat",
    "gn:population":0,
    "gn:timezone":"Asia/Kathmandu",
    "iso:country":"NP",
    "wof:name":"Anjani Kamat",
    "wof:placetype":"locality"
},
  "geometry": {"coordinates":[87.77468,26.49424],"type":"Point"}
}