{
  "type": "Feature",
  "properties": {
    "gn:admin1_code":"MR",
    "gn:admin2_code":"2.0",
    "gn:admin3_code":"59.0",
    "gn:admin4_code":"590043.0",
    "gn:asciiname":"Gaighat",
    "gn:country_code":"NP",
    "gn:dem":443,
    "gn:feature_class":"P",
    "gn:feature_code":"PPLL",
    "gn:name":"Gaighat",
    "gn:population":0,
    "gn:timezone":"Asia/Kathmandu",
    "iso:country":"NP",
    "wof:name":"Gaighat",
    "wof:placetype":"locality"
},
  "geometry": {"coordinates":[81.70219,28.51625],"type":"Point"}
}