{
  "type": "Feature",
  "properties": {
    "gn:admin1_code":"ER",
    "gn:admin2_code":"10",
    "gn:admin3_code":"4.0",
    "gn:admin4_code":"40003.0",
    "gn:asciiname":"Nirganj",
    "gn:country_code":"NP",
    "gn:dem":245,
    "gn:feature_class":"P",
    "gn:feature_code":"PPLL",
    "gn:name":"Nirganj",
    "gn:population":0,
    "gn:timezone":"Asia/Kathmandu",
    "iso:country":"NP",
    "wof:name":"Nirganj",
    "wof:placetype":"locality"
},
  "geometry": {"coordinates":[88.13936,26.74507],"type":"Point"}
}