{
  "type": "Feature",
  "properties": {
    "gn:admin1_code":"MR",
    "gn:admin2_code":"12",
    "gn:admin3_code":"55",
    "gn:admin4_code":"550013",
    "gn:asciiname":"Maidu",
    "gn:country_code":"NP",
    "gn:dem":1338,
    "gn:feature_class":"P",
    "gn:feature_code":"PPLL",
    "gn:name":"Maidu",
    "gn:population":0,
    "gn:timezone":"Asia/Kathmandu",
    "iso:country":"NP",
    "name:bul_x_preferred":[
        "\u041c\u0430\u0438\u0434\u0443"
    ],
    "name:cat_x_preferred":[
        "Maidus"
    ],
    "name:deu_x_preferred":[
        "Maidu"
    ],
    "name:fra_x_preferred":[
        "Maidu"
    ],
    "name:hrv_x_preferred":[
        "Maidu"
    ],
    "name:ita_x_preferred":[
        "Maidu"
    ],
    "name:lit_x_preferred":[
        "Maidai"
    ],
    "name:nld_x_preferred":[
        "Maidu"
    ],
    "name:pol_x_preferred":[
        "Maidu"
    ],
    "name:por_x_preferred":[
        "Maidu"
    ],
    "name:rus_x_preferred":[
        "\u041c\u0430\u0439\u0434\u0443"
    ],
    "name:spa_x_preferred":[
        "Maidu"
    ],
    "wof:name":"Maidu",
    "wof:placetype":"locality"
},
  "geometry": {"coordinates":[82.06393,28.48194],"type":"Point"}
}