{
  "type": "Feature",
  "properties": {
    "gn:admin1_code":"MR",
    "gn:admin2_code":"12",
    "gn:admin3_code":"55",
    "gn:admin4_code":"550013",
    "gn:asciiname":"Maidu",
    "gn:country_code":"NP",
    "gn:dem":1338,
    "gn:feature_class":"P",
    "gn:feature_code":"PPLL",
    "gn:name":"Maidu",
    "gn:population":0,
    "gn:timezone":"Asia/Kathmandu",
    "iso:country":"NP",
    "wof:name":"Maidu",
    "wof:placetype":"locality"
},
  "geometry": {"coordinates":[82.06393,28.48194],"type":"Point"}
}