{
  "type": "Feature",
  "properties": {
    "gn:admin1_code":"MR",
    "gn:admin2_code":"2",
    "gn:admin3_code":"60.0",
    "gn:admin4_code":"600055.0",
    "gn:asciiname":"Aultoli",
    "gn:country_code":"NP",
    "gn:dem":1405,
    "gn:feature_class":"P",
    "gn:feature_code":"PPLL",
    "gn:name":"Aultoli",
    "gn:population":0,
    "gn:timezone":"Asia/Kathmandu",
    "iso:country":"NP",
    "wof:name":"Aultoli",
    "wof:placetype":"locality"
},
  "geometry": {"coordinates":[81.79340000000001,28.90924],"type":"Point"}
}