{
  "type": "Feature",
  "properties": {
    "gn:admin1_code":"MR",
    "gn:admin2_code":"12",
    "gn:admin3_code":"54",
    "gn:admin4_code":"540029",
    "gn:asciiname":"Saunri",
    "gn:country_code":"NP",
    "gn:dem":2211,
    "gn:feature_class":"P",
    "gn:feature_code":"PPLL",
    "gn:name":"Saunri",
    "gn:population":0,
    "gn:timezone":"Asia/Kathmandu",
    "iso:country":"NP",
    "wof:name":"Saunri",
    "wof:placetype":"locality"
},
  "geometry": {"coordinates":[82.58119000000001,28.67751],"type":"Point"}
}