{
  "type": "Feature",
  "properties": {
    "gn:admin1_code":"WR",
    "gn:admin2_code":"8",
    "gn:admin3_code":"46.0",
    "gn:admin4_code":"460062.0",
    "gn:asciiname":"Argalegaun",
    "gn:country_code":"NP",
    "gn:dem":807,
    "gn:feature_class":"P",
    "gn:feature_code":"PPLL",
    "gn:name":"Argalegaun",
    "gn:population":0,
    "gn:timezone":"Asia/Kathmandu",
    "iso:country":"NP",
    "wof:name":"Argalegaun",
    "wof:placetype":"locality"
},
  "geometry": {"coordinates":[83.34966,28.0463],"type":"Point"}
}