{
  "type": "Feature",
  "properties": {
    "gn:admin1_code":"FR",
    "gn:admin2_code":"9",
    "gn:admin3_code":"74",
    "gn:admin4_code":"740014",
    "gn:asciiname":"Jajari",
    "gn:country_code":"NP",
    "gn:dem":1224,
    "gn:feature_class":"P",
    "gn:feature_code":"PPLL",
    "gn:name":"Jajari",
    "gn:population":0,
    "gn:timezone":"Asia/Kathmandu",
    "iso:country":"NP",
    "wof:name":"Jajari",
    "wof:placetype":"locality"
},
  "geometry": {"coordinates":[80.50124,29.61853],"type":"Point"}
}