{
  "type": "Feature",
  "properties": {
    "gn:admin1_code":"ER",
    "gn:admin2_code":"7",
    "gn:admin3_code":"10.0",
    "gn:admin4_code":"100039.0",
    "gn:asciiname":"Sim",
    "gn:country_code":"NP",
    "gn:dem":2119,
    "gn:feature_class":"P",
    "gn:feature_code":"PPLL",
    "gn:name":"Sim",
    "gn:population":0,
    "gn:timezone":"Asia/Kathmandu",
    "iso:country":"NP",
    "wof:name":"Sim",
    "wof:placetype":"locality"
},
  "geometry": {"coordinates":[86.91438000000002,27.10313],"type":"Point"}
}