{
  "type": "Feature",
  "properties": {
    "gn:admin1_code":"WR",
    "gn:admin2_code":"4.0",
    "gn:admin3_code":"39.0",
    "gn:admin4_code":"390050.0",
    "gn:asciiname":"Khasa",
    "gn:country_code":"NP",
    "gn:dem":1070,
    "gn:feature_class":"P",
    "gn:feature_code":"PPLL",
    "gn:name":"Khasa",
    "gn:population":0,
    "gn:timezone":"Asia/Kathmandu",
    "iso:country":"NP",
    "wof:name":"Khasa",
    "wof:placetype":"locality"
},
  "geometry": {"coordinates":[83.89204000000002,27.92132],"type":"Point"}
}