{
  "type": "Feature",
  "properties": {
    "gn:admin1_code":"CR",
    "gn:admin2_code":"5",
    "gn:admin3_code":"21",
    "gn:admin4_code":"210031",
    "gn:asciiname":"Dhade Kamagaun",
    "gn:country_code":"NP",
    "gn:dem":1509,
    "gn:feature_class":"P",
    "gn:feature_code":"PPLL",
    "gn:name":"Dhade Kamagaun",
    "gn:population":0,
    "gn:timezone":"Asia/Kathmandu",
    "iso:country":"NP",
    "wof:name":"Dhade Kamagaun",
    "wof:placetype":"locality"
},
  "geometry": {"coordinates":[85.85377,27.5437],"type":"Point"}
}