{
  "type": "Feature",
  "properties": {
    "gn:admin1_code":"FR",
    "gn:admin2_code":"14.0",
    "gn:admin3_code":"67.0",
    "gn:admin4_code":"670015.0",
    "gn:asciiname":"Ghagar",
    "gn:country_code":"NP",
    "gn:dem":1395,
    "gn:feature_class":"P",
    "gn:feature_code":"PPLL",
    "gn:name":"Ghagar",
    "gn:population":0,
    "gn:timezone":"Asia/Kathmandu",
    "iso:country":"NP",
    "wof:name":"Ghagar",
    "wof:placetype":"locality"
},
  "geometry": {"coordinates":[81.4529,29.44436],"type":"Point"}
}