{
  "type": "Feature",
  "properties": {
    "gn:admin1_code":"WR",
    "gn:admin2_code":"4.0",
    "gn:admin3_code":"39.0",
    "gn:admin4_code":"390031.0",
    "gn:asciiname":"Daregaunda",
    "gn:country_code":"NP",
    "gn:dem":1225,
    "gn:feature_class":"P",
    "gn:feature_code":"PPLL",
    "gn:name":"Daregaunda",
    "gn:population":0,
    "gn:timezone":"Asia/Kathmandu",
    "iso:country":"NP",
    "wof:name":"Daregaunda",
    "wof:placetype":"locality"
},
  "geometry": {"coordinates":[83.94104,27.96037],"type":"Point"}
}