{
  "type": "Feature",
  "properties": {
    "gn:admin1_code":"CR",
    "gn:admin2_code":"5",
    "gn:admin3_code":"17.0",
    "gn:admin4_code":"170007.0",
    "gn:asciiname":"Kumbhakarna",
    "gn:country_code":"NP",
    "gn:dem":89,
    "gn:feature_class":"P",
    "gn:feature_code":"PPLL",
    "gn:name":"Kumbhakarna",
    "gn:population":0,
    "gn:timezone":"Asia/Kathmandu",
    "iso:country":"NP",
    "name:ben_x_preferred":[
        "\u0995\u09c1\u09ae\u09cd\u09ad\u0995\u09b0\u09cd\u09a3"
    ],
    "name:fra_x_preferred":[
        "Kumbhakarna"
    ],
    "name:guj_x_preferred":[
        "\u0a95\u0ac1\u0a82\u0aad\u0a95\u0ab0\u0acd\u0aa3"
    ],
    "name:hin_x_preferred":[
        "\u0915\u0941\u092e\u094d\u092d\u0915\u0930\u094d\u0923"
    ],
    "name:ind_x_preferred":[
        "Kumbakarna"
    ],
    "name:jav_x_preferred":[
        "Kumbakarna"
    ],
    "name:jpn_x_preferred":[
        "\u30af\u30f3\u30d0\u30ab\u30eb\u30ca"
    ],
    "name:kan_x_preferred":[
        "\u0c95\u0cc1\u0c82\u0cad\u0c95\u0cb0\u0ccd\u0ca3"
    ],
    "name:mal_x_preferred":[
        "\u0d15\u0d41\u0d02\u0d2d\u0d15\u0d7c\u0d23\u0d4d\u0d23\u0d7b"
    ],
    "name:mar_x_preferred":[
        "\u0915\u0941\u0902\u092d\u0915\u0930\u094d\u0923"
    ],
    "name:nep_x_preferred":[
        "\u0915\u0941\u092e\u094d\u092d\u0915\u0930\u094d\u0923"
    ],
    "name:nor_x_preferred":[
        "Kumbhakarna"
    ],
    "name:pan_x_preferred":[
        "\u0a15\u0a41\u0a70\u0a2d\u0a15\u0a30\u0a23"
    ],
    "name:rus_x_preferred":[
        "\u041a\u0443\u043c\u0431\u0445\u0430\u043a\u0430\u0440\u043d\u0430"
    ],
    "name:san_x_preferred":[
        "\u0915\u0941\u092e\u094d\u092d\u0915\u0930\u094d\u0923\u0903"
    ],
    "name:spa_x_preferred":[
        "Kumbh\u00e1 Karna"
    ],
    "name:tam_x_preferred":[
        "\u0b95\u0bc1\u0bae\u0bcd\u0baa\u0b95\u0bb0\u0bc1\u0ba3\u0ba9\u0bcd"
    ],
    "name:tel_x_preferred":[
        "\u0c15\u0c41\u0c02\u0c2d\u0c15\u0c30\u0c4d\u0c23\u0c41\u0c21\u0c41"
    ],
    "name:tha_x_preferred":[
        "\u0e01\u0e38\u0e21\u0e20\u0e01\u0e23\u0e23\u0e13"
    ],
    "wof:name":"Kumbhakarna",
    "wof:placetype":"locality"
},
  "geometry": {"coordinates":[86.11006,26.76164],"type":"Point"}
}