{
  "type": "Feature",
  "properties": {
    "gn:admin1_code":"00",
    "gn:asciiname":"Masdada",
    "gn:country_code":"NP",
    "gn:dem":671,
    "gn:feature_class":"P",
    "gn:feature_code":"PPL",
    "gn:name":"M\u0101s\u1e0d\u0101\u0303\u1e0d\u0101",
    "gn:population":0,
    "gn:timezone":"Asia/Kathmandu",
    "iso:country":"NP",
    "name:nep_x_preferred":[
        "M\u0101s\u1e0d\u0101\u0303\u1e0d\u0101"
    ],
    "wof:name":"Masdada",
    "wof:placetype":"locality"
},
  "geometry": {"coordinates":[86.85149,26.86764],"type":"Point"}
}