{
  "type": "Feature",
  "properties": {
    "gn:admin1_code":"MR",
    "gn:admin2_code":"12",
    "gn:admin3_code":"56.0",
    "gn:admin4_code":"560036.0",
    "gn:asciiname":"Dahakholigaun",
    "gn:country_code":"NP",
    "gn:dem":610,
    "gn:feature_class":"P",
    "gn:feature_code":"PPLL",
    "gn:name":"Dahakholigaun",
    "gn:population":0,
    "gn:timezone":"Asia/Kathmandu",
    "iso:country":"NP",
    "wof:name":"Dahakholigaun",
    "wof:placetype":"locality"
},
  "geometry": {"coordinates":[82.57011999999997,27.91487],"type":"Point"}
}