{
  "type": "Feature",
  "properties": {
    "gn:admin1_code":"CR",
    "gn:admin2_code":"11",
    "gn:admin3_code":"34",
    "gn:admin4_code":"340069",
    "gn:asciiname":"Harishankhawaniya",
    "gn:country_code":"NP",
    "gn:dem":118,
    "gn:feature_class":"P",
    "gn:feature_code":"PPLL",
    "gn:name":"Harishankhawaniya",
    "gn:population":0,
    "gn:timezone":"Asia/Kathmandu",
    "iso:country":"NP",
    "wof:name":"Harishankhawaniya",
    "wof:placetype":"locality"
},
  "geometry": {"coordinates":[84.75069999999999,27.19798],"type":"Point"}
}