{
  "type": "Feature",
  "properties": {
    "gn:admin1_code":"ER",
    "gn:admin2_code":"7.0",
    "gn:admin3_code":"8.0",
    "gn:admin4_code":"80019.0",
    "gn:asciiname":"Phakchamara",
    "gn:country_code":"NP",
    "gn:dem":1408,
    "gn:feature_class":"P",
    "gn:feature_code":"PPLL",
    "gn:name":"Phakchamara",
    "gn:population":0,
    "gn:timezone":"Asia/Kathmandu",
    "iso:country":"NP",
    "name:bih_x_preferred":[
        "\u092b\u093e\u0915\u094d\u091a\u093e\u092e\u093e\u0930\u093e"
    ],
    "name:ceb_x_preferred":[
        "Phakchamara"
    ],
    "name:mai_x_preferred":[
        "\u092b\u093e\u0915\u094d\u091a\u093e\u092e\u093e\u0930\u093e"
    ],
    "name:msa_x_preferred":[
        "Phakchamara"
    ],
    "name:nep_x_preferred":[
        "\u092b\u093e\u0915\u094d\u091a\u093e\u092e\u093e\u0930\u093e"
    ],
    "name:new_x_preferred":[
        "\u092b\u093e\u0915\u094d\u091a\u092e\u0930\u093e"
    ],
    "name:pol_x_preferred":[
        "Phakchamara"
    ],
    "wof:name":"Phakchamara",
    "wof:placetype":"locality"
},
  "geometry": {"coordinates":[87.4704,27.04835],"type":"Point"}
}