{
  "type": "Feature",
  "properties": {
    "gn:admin1_code":"FR",
    "gn:admin2_code":"14",
    "gn:admin3_code":"70.0",
    "gn:admin4_code":"700008.0",
    "gn:asciiname":"Gokul",
    "gn:country_code":"NP",
    "gn:dem":1268,
    "gn:feature_class":"P",
    "gn:feature_code":"PPLL",
    "gn:name":"Gokul",
    "gn:population":0,
    "gn:timezone":"Asia/Kathmandu",
    "iso:country":"NP",
    "name:ben_x_preferred":[
        "\u0997\u09cb\u0995\u09c1\u09b2"
    ],
    "name:bih_x_preferred":[
        "\u0917\u094b\u0915\u0941\u0932"
    ],
    "name:bpy_x_preferred":[
        "\u0997\u09cb\u0995\u09c1\u09b2"
    ],
    "name:ceb_x_preferred":[
        "Gokul"
    ],
    "name:guj_x_preferred":[
        "\u0a97\u0acb\u0a95\u0ac1\u0ab3"
    ],
    "name:hin_x_preferred":[
        "\u0917\u094b\u0915\u0941\u0932"
    ],
    "name:ita_x_preferred":[
        "Gokul"
    ],
    "name:mai_x_preferred":[
        "\u0917\u094b\u0915\u0941\u0932"
    ],
    "name:mlg_x_preferred":[
        "Gokul"
    ],
    "name:msa_x_preferred":[
        "Gokul"
    ],
    "name:nep_x_preferred":[
        "\u0917\u094b\u0915\u0941\u0932"
    ],
    "name:new_x_preferred":[
        "\u0917\u094b\u0915\u0941\u0932"
    ],
    "name:nld_x_preferred":[
        "Gokul"
    ],
    "name:ori_x_preferred":[
        "\u0b17\u0b4b\u0b15\u0b41\u0b33"
    ],
    "name:pol_x_preferred":[
        "Gokul"
    ],
    "name:rus_x_preferred":[
        "\u0413\u043e\u043a\u0443\u043b"
    ],
    "name:sin_x_preferred":[
        "\u0d9c\u0ddd\u0d9a\u0dd4\u0dbd\u0dca"
    ],
    "name:swe_x_preferred":[
        "Gokul"
    ],
    "name:tam_x_preferred":[
        "\u0b95\u0bcb\u0b95\u0bc1\u0bb2\u0bae\u0bcd"
    ],
    "name:ukr_x_preferred":[
        "\u0413\u043e\u043a\u0443\u043b"
    ],
    "name:urd_x_preferred":[
        "\u06af\u0648\u06a9\u0644"
    ],
    "name:vie_x_preferred":[
        "Gokul"
    ],
    "name:zho_x_preferred":[
        "\u6208\u5e93\u5c14"
    ],
    "wof:name":"Gokul",
    "wof:placetype":"locality"
},
  "geometry": {"coordinates":[80.55412,29.09663],"type":"Point"}
}