{
  "type": "Feature",
  "properties": {
    "gn:admin1_code":"MR",
    "gn:admin2_code":"2",
    "gn:admin3_code":"61.0",
    "gn:admin4_code":"610016.0",
    "gn:asciiname":"Ratagaragli",
    "gn:country_code":"NP",
    "gn:dem":2022,
    "gn:feature_class":"P",
    "gn:feature_code":"PPLL",
    "gn:name":"Ratagaragli",
    "gn:population":0,
    "gn:timezone":"Asia/Kathmandu",
    "iso:country":"NP",
    "wof:name":"Ratagaragli",
    "wof:placetype":"locality"
},
  "geometry": {"coordinates":[82.2529,28.83787],"type":"Point"}
}