{
  "type": "Feature",
  "properties": {
    "gn:admin1_code":"MR",
    "gn:admin2_code":"2.0",
    "gn:admin3_code":"57.0",
    "gn:admin4_code":"570032.0",
    "gn:asciiname":"Ganeshpur",
    "gn:country_code":"NP",
    "gn:dem":150,
    "gn:feature_class":"P",
    "gn:feature_code":"PPLL",
    "gn:name":"Ganeshpur",
    "gn:population":0,
    "gn:timezone":"Asia/Kathmandu",
    "iso:country":"NP",
    "name:ceb_x_preferred":[
        "Ganeshpur"
    ],
    "name:nep_x_preferred":[
        "\u0917\u0923\u0947\u0936\u092a\u0941\u0930"
    ],
    "name:pol_x_preferred":[
        "Ganeshpur"
    ],
    "wof:name":"Ganeshpur",
    "wof:placetype":"locality"
},
  "geometry": {"coordinates":[81.63540999999999,28.06648],"type":"Point"}
}