{
  "type": "Feature",
  "properties": {
    "gn:admin1_code":"ER",
    "gn:admin2_code":"10",
    "gn:admin3_code":"2",
    "gn:admin4_code":"20033",
    "gn:asciiname":"Ranitar",
    "gn:country_code":"NP",
    "gn:dem":1754,
    "gn:feature_class":"P",
    "gn:feature_code":"PPLL",
    "gn:name":"Ranitar",
    "gn:population":0,
    "gn:timezone":"Asia/Kathmandu",
    "iso:country":"NP",
    "name:bih_x_preferred":[
        "\u0930\u093e\u0928\u0940\u091f\u093e\u0930"
    ],
    "name:ceb_x_preferred":[
        "Ranitar"
    ],
    "name:mai_x_preferred":[
        "\u0930\u093e\u0928\u0940\u091f\u093e\u0930"
    ],
    "name:msa_x_preferred":[
        "Ranitar"
    ],
    "name:nep_x_preferred":[
        "\u0930\u093e\u0928\u0940\u091f\u093e\u0930"
    ],
    "name:new_x_preferred":[
        "\u0930\u093e\u0928\u0940\u091f\u093e\u0930"
    ],
    "name:pol_x_preferred":[
        "Ranitar"
    ],
    "wof:name":"Ranitar",
    "wof:placetype":"locality"
},
  "geometry": {"coordinates":[87.81385999999998,27.11911],"type":"Point"}
}