{
  "type": "Feature",
  "properties": {
    "gn:admin1_code":"MR",
    "gn:admin2_code":"2.0",
    "gn:admin3_code":"59.0",
    "gn:admin4_code":"590038.0",
    "gn:asciiname":"Thakuri Tol",
    "gn:country_code":"NP",
    "gn:dem":1248,
    "gn:feature_class":"P",
    "gn:feature_code":"PPLL",
    "gn:name":"Thakuri Tol",
    "gn:population":0,
    "gn:timezone":"Asia/Kathmandu",
    "iso:country":"NP",
    "wof:name":"Thakuri Tol",
    "wof:placetype":"locality"
},
  "geometry": {"coordinates":[81.81124,28.54774],"type":"Point"}
}