{
  "type": "Feature",
  "properties": {
    "gn:admin1_code":"ER",
    "gn:admin2_code":"10.0",
    "gn:admin3_code":"1.0",
    "gn:admin4_code":"10035.0",
    "gn:asciiname":"Phyaktu",
    "gn:country_code":"NP",
    "gn:dem":1850,
    "gn:feature_class":"P",
    "gn:feature_code":"PPLL",
    "gn:name":"Phyaktu",
    "gn:population":0,
    "gn:timezone":"Asia/Kathmandu",
    "iso:country":"NP",
    "wof:name":"Phyaktu",
    "wof:placetype":"locality"
},
  "geometry": {"coordinates":[87.53944,27.34524],"type":"Point"}
}