{
  "type": "Feature",
  "properties": {
    "gn:admin1_code":"ER",
    "gn:admin2_code":"13",
    "gn:admin3_code":"13.0",
    "gn:admin4_code":"130014.0",
    "gn:asciiname":"Dhikure",
    "gn:country_code":"NP",
    "gn:dem":2133,
    "gn:feature_class":"P",
    "gn:feature_code":"PPLL",
    "gn:name":"Dhikure",
    "gn:population":0,
    "gn:timezone":"Asia/Kathmandu",
    "iso:country":"NP",
    "wof:name":"Dhikure",
    "wof:placetype":"locality"
},
  "geometry": {"coordinates":[86.85983,27.1117],"type":"Point"}
}