{
  "type": "Feature",
  "properties": {
    "gn:admin1_code":"WR",
    "gn:admin2_code":"4.0",
    "gn:admin3_code":"39.0",
    "gn:admin4_code":"390048.0",
    "gn:asciiname":"Ajingare",
    "gn:country_code":"NP",
    "gn:dem":486,
    "gn:feature_class":"P",
    "gn:feature_code":"PPLL",
    "gn:name":"Ajingare",
    "gn:population":0,
    "gn:timezone":"Asia/Kathmandu",
    "iso:country":"NP",
    "name:mai_x_preferred":[
        "\u0905\u091c\u093f\u0902\u0917\u0930\u0947"
    ],
    "name:nep_x_preferred":[
        "\u0905\u091c\u093f\u0902\u0917\u0930\u0947"
    ],
    "wof:name":"Ajingare",
    "wof:placetype":"locality"
},
  "geometry": {"coordinates":[83.95198000000001,27.90367],"type":"Point"}
}