{
  "type": "Feature",
  "properties": {
    "gn:admin1_code":"00",
    "gn:asciiname":"Pankhathala",
    "gn:country_code":"NP",
    "gn:dem":2166,
    "gn:feature_class":"P",
    "gn:feature_code":"PPL",
    "gn:name":"Pa\u1e45khathal\u0101",
    "gn:population":0,
    "gn:timezone":"Asia/Kathmandu",
    "iso:country":"NP",
    "wof:name":"Pankhathala",
    "wof:placetype":"locality"
},
  "geometry": {"coordinates":[86.96679,27.3974],"type":"Point"}
}