{
  "type": "Feature",
  "properties": {
    "gn:admin1_code":"CR",
    "gn:admin2_code":"1",
    "gn:admin3_code":"23",
    "gn:admin4_code":"230070",
    "gn:asciiname":"Betechhap",
    "gn:country_code":"NP",
    "gn:dem":1321,
    "gn:feature_class":"P",
    "gn:feature_code":"PPLL",
    "gn:name":"Betechhap",
    "gn:population":0,
    "gn:timezone":"Asia/Kathmandu",
    "iso:country":"NP",
    "wof:name":"Betechhap",
    "wof:placetype":"locality"
},
  "geometry": {"coordinates":[85.89565999999998,27.74734],"type":"Point"}
}