{
  "type": "Feature",
  "properties": {
    "gn:admin1_code":"ER",
    "gn:admin2_code":"7",
    "gn:admin3_code":"5",
    "gn:admin4_code":"50030",
    "gn:asciiname":"Singhari",
    "gn:country_code":"NP",
    "gn:dem":77,
    "gn:feature_class":"P",
    "gn:feature_code":"PPLL",
    "gn:name":"Singhari",
    "gn:population":0,
    "gn:timezone":"Asia/Kathmandu",
    "iso:country":"NP",
    "wof:name":"Singhari",
    "wof:placetype":"locality"
},
  "geometry": {"coordinates":[87.64353,26.45832],"type":"Point"}
}