{
  "type": "Feature",
  "properties": {
    "gn:admin1_code":"ER",
    "gn:admin2_code":"13",
    "gn:admin3_code":"12",
    "gn:admin4_code":"120003",
    "gn:asciiname":"Dipsimha",
    "gn:country_code":"NP",
    "gn:dem":901,
    "gn:feature_class":"P",
    "gn:feature_code":"PPLL",
    "gn:name":"Dipsimha",
    "gn:population":0,
    "gn:timezone":"Asia/Kathmandu",
    "iso:country":"NP",
    "wof:name":"Dipsimha",
    "wof:placetype":"locality"
},
  "geometry": {"coordinates":[86.32126,27.24853],"type":"Point"}
}