{
  "type": "Feature",
  "properties": {
    "gn:admin1_code":"CR",
    "gn:admin2_code":"5",
    "gn:admin3_code":"18",
    "gn:admin4_code":"180045",
    "gn:asciiname":"Cheru",
    "gn:country_code":"NP",
    "gn:dem":265,
    "gn:feature_class":"P",
    "gn:feature_code":"PPLL",
    "gn:name":"Cheru",
    "gn:population":0,
    "gn:timezone":"Asia/Kathmandu",
    "iso:country":"NP",
    "wof:name":"Cheru",
    "wof:placetype":"locality"
},
  "geometry": {"coordinates":[85.87581999999998,27.03684],"type":"Point"}
}