{
  "type": "Feature",
  "properties": {
    "gn:admin1_code":"CR",
    "gn:admin2_code":"1",
    "gn:admin3_code":"30.0",
    "gn:admin4_code":"300011.0",
    "gn:asciiname":"Palanse",
    "gn:country_code":"NP",
    "gn:dem":480,
    "gn:feature_class":"P",
    "gn:feature_code":"PPLL",
    "gn:name":"Palanse",
    "gn:population":0,
    "gn:timezone":"Asia/Kathmandu",
    "iso:country":"NP",
    "wof:name":"Palanse",
    "wof:placetype":"locality"
},
  "geometry": {"coordinates":[84.75561,27.79089],"type":"Point"}
}