{
  "type": "Feature",
  "properties": {
    "gn:admin1_code":"CR",
    "gn:admin2_code":"11",
    "gn:admin3_code":"35.0",
    "gn:admin4_code":"350033.0",
    "gn:asciiname":"Tikauli",
    "gn:country_code":"NP",
    "gn:dem":200,
    "gn:feature_class":"P",
    "gn:feature_code":"PPLL",
    "gn:name":"Tikauli",
    "gn:population":0,
    "gn:timezone":"Asia/Kathmandu",
    "iso:country":"NP",
    "wof:name":"Tikauli",
    "wof:placetype":"locality"
},
  "geometry": {"coordinates":[84.50142,27.63236],"type":"Point"}
}