{
  "type": "Feature",
  "properties": {
    "gn:admin1_code":"FR",
    "gn:admin2_code":"9",
    "gn:admin3_code":"73.0",
    "gn:admin4_code":"730005.0",
    "gn:asciiname":"Kaphalkhet",
    "gn:country_code":"NP",
    "gn:dem":1535,
    "gn:feature_class":"P",
    "gn:feature_code":"PPLL",
    "gn:name":"Kaphalkhet",
    "gn:population":0,
    "gn:timezone":"Asia/Kathmandu",
    "iso:country":"NP",
    "wof:name":"Kaphalkhet",
    "wof:placetype":"locality"
},
  "geometry": {"coordinates":[80.45211999999999,29.29092],"type":"Point"}
}