{
  "type": "Feature",
  "properties": {
    "gn:admin1_code":"WR",
    "gn:admin2_code":"3",
    "gn:admin3_code":"45.0",
    "gn:admin4_code":"450023.0",
    "gn:asciiname":"Puma",
    "gn:country_code":"NP",
    "gn:dem":1192,
    "gn:feature_class":"P",
    "gn:feature_code":"PPLL",
    "gn:name":"Puma",
    "gn:population":0,
    "gn:timezone":"Asia/Kathmandu",
    "iso:country":"NP",
    "wof:name":"Puma",
    "wof:placetype":"locality"
},
  "geometry": {"coordinates":[83.61750000000001,28.15395],"type":"Point"}
}