{
  "type": "Feature",
  "properties": {
    "gn:admin1_code":"ER",
    "gn:admin2_code":"13",
    "gn:admin3_code":"12",
    "gn:admin4_code":"120053",
    "gn:asciiname":"Harkapur",
    "gn:country_code":"NP",
    "gn:dem":375,
    "gn:feature_class":"P",
    "gn:feature_code":"PPLL",
    "gn:name":"Harkapur",
    "gn:population":0,
    "gn:timezone":"Asia/Kathmandu",
    "iso:country":"NP",
    "name:bih_x_preferred":[
        "\u0939\u0930\u094d\u0915\u092a\u0941\u0930"
    ],
    "name:ceb_x_preferred":[
        "Harkapur"
    ],
    "name:fra_x_preferred":[
        "Harkapur"
    ],
    "name:hin_x_preferred":[
        "\u0939\u0930\u094d\u0915\u092a\u0941\u0930"
    ],
    "name:mai_x_preferred":[
        "\u0939\u0930\u094d\u0915\u092a\u0941\u0930"
    ],
    "name:msa_x_preferred":[
        "Harkapur"
    ],
    "name:nep_x_preferred":[
        "\u0939\u0930\u094d\u0915\u092a\u0941\u0930"
    ],
    "name:new_x_preferred":[
        "\u0939\u0930\u094d\u0915\u092a\u0941\u0930"
    ],
    "name:pol_x_preferred":[
        "Harkapur"
    ],
    "wof:name":"Harkapur",
    "wof:placetype":"locality"
},
  "geometry": {"coordinates":[86.40684,27.17269000000001],"type":"Point"}
}