{
  "type": "Feature",
  "properties": {
    "gn:admin1_code":"CR",
    "gn:admin2_code":"11",
    "gn:admin3_code":"31",
    "gn:admin4_code":"310038",
    "gn:asciiname":"Rairang",
    "gn:country_code":"NP",
    "gn:dem":477,
    "gn:feature_class":"P",
    "gn:feature_code":"PPLL",
    "gn:name":"Rairang",
    "gn:population":0,
    "gn:timezone":"Asia/Kathmandu",
    "iso:country":"NP",
    "wof:name":"Rairang",
    "wof:placetype":"locality"
},
  "geometry": {"coordinates":[84.85153000000003,27.54225],"type":"Point"}
}