{
  "type": "Feature",
  "properties": {
    "gn:admin1_code":"CR",
    "gn:admin2_code":"1",
    "gn:admin3_code":"24.0",
    "gn:admin4_code":"240043.0",
    "gn:asciiname":"Badare",
    "gn:country_code":"NP",
    "gn:dem":940,
    "gn:feature_class":"P",
    "gn:feature_code":"PPLL",
    "gn:name":"Badare",
    "gn:population":0,
    "gn:timezone":"Asia/Kathmandu",
    "iso:country":"NP",
    "wof:name":"Badare",
    "wof:placetype":"locality"
},
  "geometry": {"coordinates":[85.66873000000002,27.5132],"type":"Point"}
}