{
  "type": "Feature",
  "properties": {
    "gn:admin1_code":"CR",
    "gn:admin2_code":"1",
    "gn:admin3_code":"24.0",
    "gn:admin4_code":"240050.0",
    "gn:asciiname":"Lansal",
    "gn:country_code":"NP",
    "gn:dem":1299,
    "gn:feature_class":"P",
    "gn:feature_code":"PPLL",
    "gn:name":"Lansal",
    "gn:population":0,
    "gn:timezone":"Asia/Kathmandu",
    "iso:country":"NP",
    "wof:name":"Lansal",
    "wof:placetype":"locality"
},
  "geometry": {"coordinates":[85.77646999999997,27.46993],"type":"Point"}
}