{
  "type": "Feature",
  "properties": {
    "gn:admin1_code":"CR",
    "gn:admin2_code":"1",
    "gn:admin3_code":"28",
    "gn:admin4_code":"280027",
    "gn:asciiname":"Nigale",
    "gn:country_code":"NP",
    "gn:dem":1678,
    "gn:feature_class":"P",
    "gn:feature_code":"PPLL",
    "gn:name":"Nigale",
    "gn:population":0,
    "gn:timezone":"Asia/Kathmandu",
    "iso:country":"NP",
    "wof:name":"Nigale",
    "wof:placetype":"locality"
},
  "geometry": {"coordinates":[85.22924,27.81982],"type":"Point"}
}