{
  "type": "Feature",
  "properties": {
    "gn:admin1_code":"00",
    "gn:asciiname":"Budhanilkantha",
    "gn:country_code":"NP",
    "gn:dem":1440,
    "gn:feature_class":"P",
    "gn:feature_code":"PPL",
    "gn:name":"Bu\u1e0dh\u0101nilkan\u1e6dha",
    "gn:population":0,
    "gn:timezone":"Asia/Kathmandu",
    "iso:country":"NP",
    "name:und_x_variant":[
        "Budanilkantha",
        "Budha-Nilkantha",
        "Burh\u0101nilkantha",
        "Bu\u1e0dh\u0101nilkan\u1e6dha"
    ],
    "wof:name":"Budhanilkantha",
    "wof:placetype":"locality"
},
  "geometry": {"coordinates":[85.36244000000001,27.77698],"type":"Point"}
}