{
  "type": "Feature",
  "properties": {
    "gn:admin1_code":"MR",
    "gn:admin2_code":"12",
    "gn:admin3_code":"52",
    "gn:admin4_code":"520006",
    "gn:asciiname":"Tapakot",
    "gn:country_code":"NP",
    "gn:dem":1149,
    "gn:feature_class":"P",
    "gn:feature_code":"PPLL",
    "gn:name":"Tapakot",
    "gn:population":0,
    "gn:timezone":"Asia/Kathmandu",
    "iso:country":"NP",
    "wof:name":"Tapakot",
    "wof:placetype":"locality"
},
  "geometry": {"coordinates":[82.73249,28.17152],"type":"Point"}
}