{
  "type": "Feature",
  "properties": {
    "gn:admin1_code":"ER",
    "gn:admin2_code":"13",
    "gn:admin3_code":"12",
    "gn:admin4_code":"120054",
    "gn:asciiname":"Nisangkhe",
    "gn:country_code":"NP",
    "gn:dem":1391,
    "gn:feature_class":"P",
    "gn:feature_code":"PPLL",
    "gn:name":"Nisangkhe",
    "gn:population":0,
    "gn:timezone":"Asia/Kathmandu",
    "iso:country":"NP",
    "wof:name":"Nisangkhe",
    "wof:placetype":"locality"
},
  "geometry": {"coordinates":[86.56851999999998,27.26026],"type":"Point"}
}