{
  "type": "Feature",
  "properties": {
    "gn:admin1_code":"MR",
    "gn:admin2_code":"12",
    "gn:admin3_code":"55",
    "gn:admin4_code":"550022",
    "gn:asciiname":"Gairagithi",
    "gn:country_code":"NP",
    "gn:dem":1164,
    "gn:feature_class":"P",
    "gn:feature_code":"PPLL",
    "gn:name":"Gairagithi",
    "gn:population":0,
    "gn:timezone":"Asia/Kathmandu",
    "iso:country":"NP",
    "wof:name":"Gairagithi",
    "wof:placetype":"locality"
},
  "geometry": {"coordinates":[82.17443,28.30206],"type":"Point"}
}