{
  "type": "Feature",
  "properties": {
    "gn:admin1_code":"WR",
    "gn:admin2_code":"3",
    "gn:admin3_code":"45.0",
    "gn:admin4_code":"450032.0",
    "gn:asciiname":"Chaubise",
    "gn:country_code":"NP",
    "gn:dem":1687,
    "gn:feature_class":"P",
    "gn:feature_code":"PPLL",
    "gn:name":"Chaubise",
    "gn:population":0,
    "gn:timezone":"Asia/Kathmandu",
    "iso:country":"NP",
    "name:bih_x_preferred":[
        "\u091a\u094c\u092c\u093f\u0938\u0947"
    ],
    "name:nep_x_preferred":[
        "\u091a\u094c\u092c\u093f\u0938\u0947 \u0917\u093e\u0909\u0901\u092a\u093e\u0932\u093f\u0915\u093e"
    ],
    "wof:name":"Chaubise",
    "wof:placetype":"locality"
},
  "geometry": {"coordinates":[83.38949000000002,28.18996],"type":"Point"}
}