{
  "type": "Feature",
  "properties": {
    "gn:admin1_code":"CR",
    "gn:admin2_code":"5",
    "gn:admin3_code":"21",
    "gn:admin4_code":"210016",
    "gn:asciiname":"Pakhegaun",
    "gn:country_code":"NP",
    "gn:dem":2249,
    "gn:feature_class":"P",
    "gn:feature_code":"PPLL",
    "gn:name":"Pakhegaun",
    "gn:population":0,
    "gn:timezone":"Asia/Kathmandu",
    "iso:country":"NP",
    "wof:name":"Pakhegaun",
    "wof:placetype":"locality"
},
  "geometry": {"coordinates":[86.22171999999998,27.49305],"type":"Point"}
}