{
  "type": "Feature",
  "properties": {
    "gn:admin1_code":"ER",
    "gn:admin2_code":"7",
    "gn:admin3_code":"5",
    "gn:admin4_code":"50011",
    "gn:asciiname":"Bhathi Bhaudaha",
    "gn:country_code":"NP",
    "gn:dem":76,
    "gn:feature_class":"P",
    "gn:feature_code":"PPLL",
    "gn:name":"Bhathi Bhaudaha",
    "gn:population":0,
    "gn:timezone":"Asia/Kathmandu",
    "iso:country":"NP",
    "wof:name":"Bhathi Bhaudaha",
    "wof:placetype":"locality"
},
  "geometry": {"coordinates":[87.35819000000002,26.48645],"type":"Point"}
}