{
  "type": "Feature",
  "properties": {
    "gn:admin1_code":"FR",
    "gn:admin2_code":"14",
    "gn:admin3_code":"70.0",
    "gn:admin4_code":"700016.0",
    "gn:asciiname":"Chiurana",
    "gn:country_code":"NP",
    "gn:dem":896,
    "gn:feature_class":"P",
    "gn:feature_code":"PPLL",
    "gn:name":"Chiurana",
    "gn:population":0,
    "gn:timezone":"Asia/Kathmandu",
    "iso:country":"NP",
    "wof:name":"Chiurana",
    "wof:placetype":"locality"
},
  "geometry": {"coordinates":[81.03793,29.14619],"type":"Point"}
}