{
  "type": "Feature",
  "properties": {
    "gn:admin1_code":"ER",
    "gn:admin2_code":"7",
    "gn:admin3_code":"10.0",
    "gn:admin4_code":"100023.0",
    "gn:asciiname":"Kinuwa",
    "gn:country_code":"NP",
    "gn:dem":248,
    "gn:feature_class":"P",
    "gn:feature_code":"PPLL",
    "gn:name":"Kinuwa",
    "gn:population":0,
    "gn:timezone":"Asia/Kathmandu",
    "iso:country":"NP",
    "wof:name":"Kinuwa",
    "wof:placetype":"locality"
},
  "geometry": {"coordinates":[87.09139,26.9167],"type":"Point"}
}