{
  "type": "Feature",
  "properties": {
    "gn:admin1_code":"ER",
    "gn:admin2_code":"7",
    "gn:admin3_code":"10.0",
    "gn:admin4_code":"100053.0",
    "gn:asciiname":"Mude",
    "gn:country_code":"NP",
    "gn:dem":2216,
    "gn:feature_class":"P",
    "gn:feature_code":"PPLL",
    "gn:name":"Mude",
    "gn:population":0,
    "gn:timezone":"Asia/Kathmandu",
    "iso:country":"NP",
    "wof:name":"Mude",
    "wof:placetype":"locality"
},
  "geometry": {"coordinates":[87.05216999999998,27.23123],"type":"Point"}
}