{
  "type": "Feature",
  "properties": {
    "gn:admin1_code":"ER",
    "gn:admin2_code":"10.0",
    "gn:admin3_code":"1.0",
    "gn:admin4_code":"10014.0",
    "gn:asciiname":"Dhande",
    "gn:country_code":"NP",
    "gn:dem":1988,
    "gn:feature_class":"P",
    "gn:feature_code":"PPLL",
    "gn:name":"Dhande",
    "gn:population":0,
    "gn:timezone":"Asia/Kathmandu",
    "iso:country":"NP",
    "wof:name":"Dhande",
    "wof:placetype":"locality"
},
  "geometry": {"coordinates":[87.92761999999998,27.40593],"type":"Point"}
}