{
  "type": "Feature",
  "properties": {
    "gn:admin1_code":"FR",
    "gn:admin2_code":"9",
    "gn:admin3_code":"74",
    "gn:admin4_code":"740030",
    "gn:asciiname":"TalloJhaile",
    "gn:country_code":"NP",
    "gn:dem":1947,
    "gn:feature_class":"P",
    "gn:feature_code":"PPLL",
    "gn:name":"TalloJhaile",
    "gn:population":0,
    "gn:timezone":"Asia/Kathmandu",
    "iso:country":"NP",
    "wof:name":"TalloJhaile",
    "wof:placetype":"locality"
},
  "geometry": {"coordinates":[80.76241999999998,29.69086],"type":"Point"}
}