{
  "type": "Feature",
  "properties": {
    "gn:admin1_code":"CR",
    "gn:admin2_code":"5",
    "gn:admin3_code":"20",
    "gn:admin4_code":"200007",
    "gn:asciiname":"Jorsimal",
    "gn:country_code":"NP",
    "gn:dem":519,
    "gn:feature_class":"P",
    "gn:feature_code":"PPLL",
    "gn:name":"Jorsimal",
    "gn:population":0,
    "gn:timezone":"Asia/Kathmandu",
    "iso:country":"NP",
    "wof:name":"Jorsimal",
    "wof:placetype":"locality"
},
  "geometry": {"coordinates":[86.06506999999998,27.11554000000001],"type":"Point"}
}