{
  "type": "Feature",
  "properties": {
    "gn:admin1_code":"CR",
    "gn:admin2_code":"11",
    "gn:admin3_code":"31",
    "gn:admin4_code":"310008",
    "gn:asciiname":"Baragthan",
    "gn:country_code":"NP",
    "gn:dem":1524,
    "gn:feature_class":"P",
    "gn:feature_code":"PPLL",
    "gn:name":"Baragthan",
    "gn:population":0,
    "gn:timezone":"Asia/Kathmandu",
    "iso:country":"NP",
    "wof:name":"Baragthan",
    "wof:placetype":"locality"
},
  "geometry": {"coordinates":[85.15244,27.53695],"type":"Point"}
}