{
  "type": "Feature",
  "properties": {
    "gn:admin1_code":"ER",
    "gn:admin2_code":"7",
    "gn:admin3_code":"5",
    "gn:admin4_code":"50058",
    "gn:asciiname":"Diputol",
    "gn:country_code":"NP",
    "gn:dem":147,
    "gn:feature_class":"P",
    "gn:feature_code":"PPLL",
    "gn:name":"Diputol",
    "gn:population":0,
    "gn:timezone":"Asia/Kathmandu",
    "iso:country":"NP",
    "wof:name":"Diputol",
    "wof:placetype":"locality"
},
  "geometry": {"coordinates":[87.32824000000002,26.69404],"type":"Point"}
}