{
  "type": "Feature",
  "properties": {
    "gn:admin1_code":"MR",
    "gn:admin2_code":"2",
    "gn:admin3_code":"60.0",
    "gn:admin4_code":"600014.0",
    "gn:asciiname":"Kolopuliya",
    "gn:country_code":"NP",
    "gn:dem":1068,
    "gn:feature_class":"P",
    "gn:feature_code":"PPLL",
    "gn:name":"Kolopuliya",
    "gn:population":0,
    "gn:timezone":"Asia/Kathmandu",
    "iso:country":"NP",
    "wof:name":"Kolopuliya",
    "wof:placetype":"locality"
},
  "geometry": {"coordinates":[81.65971999999999,28.73642000000001],"type":"Point"}
}