{
  "type": "Feature",
  "properties": {
    "gn:admin1_code":"CR",
    "gn:admin2_code":"1",
    "gn:admin3_code":"30.0",
    "gn:admin4_code":"300005.0",
    "gn:asciiname":"Khestegaun",
    "gn:country_code":"NP",
    "gn:dem":862,
    "gn:feature_class":"P",
    "gn:feature_code":"PPLL",
    "gn:name":"Khestegaun",
    "gn:population":0,
    "gn:timezone":"Asia/Kathmandu",
    "iso:country":"NP",
    "wof:name":"Khestegaun",
    "wof:placetype":"locality"
},
  "geometry": {"coordinates":[85.01299999999998,27.75533],"type":"Point"}
}