{
  "type": "Feature",
  "properties": {
    "gn:admin1_code":"ER",
    "gn:admin2_code":"13",
    "gn:admin3_code":"11",
    "gn:admin4_code":"110001",
    "gn:asciiname":"Dangki",
    "gn:country_code":"NP",
    "gn:dem":1560,
    "gn:feature_class":"P",
    "gn:feature_code":"PPLL",
    "gn:name":"Dangki",
    "gn:population":0,
    "gn:timezone":"Asia/Kathmandu",
    "iso:country":"NP",
    "wof:name":"Dangki",
    "wof:placetype":"locality"
},
  "geometry": {"coordinates":[86.7538,27.53129],"type":"Point"}
}