{
  "type": "Feature",
  "properties": {
    "gn:admin1_code":"WR",
    "gn:admin2_code":"4",
    "gn:admin3_code":"40.0",
    "gn:admin4_code":"400005.0",
    "gn:asciiname":"Dandagaun",
    "gn:country_code":"NP",
    "gn:dem":1067,
    "gn:feature_class":"P",
    "gn:feature_code":"PPLL",
    "gn:name":"Dandagaun",
    "gn:population":0,
    "gn:timezone":"Asia/Kathmandu",
    "iso:country":"NP",
    "name:pol_x_preferred":[
        "Dandagaun"
    ],
    "wof:name":"Dandagaun",
    "wof:placetype":"locality"
},
  "geometry": {"coordinates":[84.02960999999998,28.13268],"type":"Point"}
}