{
  "type": "Feature",
  "properties": {
    "gn:admin1_code":"WR",
    "gn:admin2_code":"8",
    "gn:admin3_code":"46.0",
    "gn:admin4_code":"460003.0",
    "gn:asciiname":"Chaurasiphant",
    "gn:country_code":"NP",
    "gn:dem":998,
    "gn:feature_class":"P",
    "gn:feature_code":"PPLL",
    "gn:name":"Chaurasiphant",
    "gn:population":0,
    "gn:timezone":"Asia/Kathmandu",
    "iso:country":"NP",
    "wof:name":"Chaurasiphant",
    "wof:placetype":"locality"
},
  "geometry": {"coordinates":[83.15609000000001,28.15275],"type":"Point"}
}