{
  "type": "Feature",
  "properties": {
    "gn:admin1_code":"WR",
    "gn:admin2_code":"4",
    "gn:admin3_code":"40.0",
    "gn:admin4_code":"400015.0",
    "gn:asciiname":"Jamunabot",
    "gn:country_code":"NP",
    "gn:dem":1177,
    "gn:feature_class":"P",
    "gn:feature_code":"PPLL",
    "gn:name":"Jamunabot",
    "gn:population":0,
    "gn:timezone":"Asia/Kathmandu",
    "iso:country":"NP",
    "wof:name":"Jamunabot",
    "wof:placetype":"locality"
},
  "geometry": {"coordinates":[83.96916,28.23655],"type":"Point"}
}