{
  "type": "Feature",
  "properties": {
    "gn:admin1_code":"WR",
    "gn:admin2_code":"8",
    "gn:admin3_code":"50.0",
    "gn:admin4_code":"500018.0",
    "gn:asciiname":"Nayanbasti",
    "gn:country_code":"NP",
    "gn:dem":112,
    "gn:feature_class":"P",
    "gn:feature_code":"PPLL",
    "gn:name":"Nayanbasti",
    "gn:population":0,
    "gn:timezone":"Asia/Kathmandu",
    "iso:country":"NP",
    "wof:name":"Nayanbasti",
    "wof:placetype":"locality"
},
  "geometry": {"coordinates":[83.00559,27.62749],"type":"Point"}
}