{
  "type": "Feature",
  "properties": {
    "gn:admin1_code":"WR",
    "gn:admin2_code":"3",
    "gn:admin3_code":"42",
    "gn:admin4_code":"420002",
    "gn:asciiname":"Yachebu",
    "gn:country_code":"NP",
    "gn:dem":3908,
    "gn:feature_class":"P",
    "gn:feature_code":"PPLL",
    "gn:name":"Yachebu",
    "gn:population":0,
    "gn:timezone":"Asia/Kathmandu",
    "iso:country":"NP",
    "wof:name":"Yachebu",
    "wof:placetype":"locality"
},
  "geometry": {"coordinates":[83.97010999999998,29.2345],"type":"Point"}
}