{
  "type": "Feature",
  "properties": {
    "gn:admin1_code":"ER",
    "gn:admin2_code":"7",
    "gn:admin3_code":"9",
    "gn:admin4_code":"90015",
    "gn:asciiname":"Umling",
    "gn:country_code":"NP",
    "gn:dem":1788,
    "gn:feature_class":"P",
    "gn:feature_code":"PPLL",
    "gn:name":"Umling",
    "gn:population":0,
    "gn:timezone":"Asia/Kathmandu",
    "iso:country":"NP",
    "wof:name":"Umling",
    "wof:placetype":"locality"
},
  "geometry": {"coordinates":[87.42336999999998,27.2251],"type":"Point"}
}