{
  "type": "Feature",
  "properties": {
    "gn:admin1_code":"ER",
    "gn:admin2_code":"7",
    "gn:admin3_code":"7.0",
    "gn:admin4_code":"70021.0",
    "gn:asciiname":"Dumre",
    "gn:country_code":"NP",
    "gn:dem":446,
    "gn:feature_class":"P",
    "gn:feature_code":"PPLL",
    "gn:name":"Dumre",
    "gn:population":0,
    "gn:timezone":"Asia/Kathmandu",
    "iso:country":"NP",
    "wof:name":"Dumre",
    "wof:placetype":"locality"
},
  "geometry": {"coordinates":[87.37269000000001,26.94055],"type":"Point"}
}