{
  "type": "Feature",
  "properties": {
    "gn:admin1_code":"CR",
    "gn:admin2_code":"1",
    "gn:admin3_code":"28",
    "gn:admin4_code":"280028",
    "gn:asciiname":"Besare",
    "gn:country_code":"NP",
    "gn:dem":944,
    "gn:feature_class":"P",
    "gn:feature_code":"PPLL",
    "gn:name":"Besare",
    "gn:population":0,
    "gn:timezone":"Asia/Kathmandu",
    "iso:country":"NP",
    "wof:name":"Besare",
    "wof:placetype":"locality"
},
  "geometry": {"coordinates":[85.23156,27.92808],"type":"Point"}
}