{
  "type": "Feature",
  "properties": {
    "gn:admin1_code":"CR",
    "gn:admin2_code":"11",
    "gn:admin3_code":"35.0",
    "gn:admin4_code":"350003.0",
    "gn:asciiname":"Sidhuwa",
    "gn:country_code":"NP",
    "gn:dem":181,
    "gn:feature_class":"P",
    "gn:feature_code":"PPLL",
    "gn:name":"Sidhuwa",
    "gn:population":0,
    "gn:timezone":"Asia/Kathmandu",
    "iso:country":"NP",
    "wof:name":"Sidhuwa",
    "wof:placetype":"locality"
},
  "geometry": {"coordinates":[84.3028,27.45376],"type":"Point"}
}