{
  "type": "Feature",
  "properties": {
    "gn:admin1_code":"ER",
    "gn:admin2_code":"10.0",
    "gn:admin3_code":"1.0",
    "gn:admin4_code":"10049.0",
    "gn:asciiname":"Arubote",
    "gn:country_code":"NP",
    "gn:dem":1260,
    "gn:feature_class":"P",
    "gn:feature_code":"PPLL",
    "gn:name":"Arubote",
    "gn:population":0,
    "gn:timezone":"Asia/Kathmandu",
    "iso:country":"NP",
    "wof:name":"Arubote",
    "wof:placetype":"locality"
},
  "geometry": {"coordinates":[87.77252,27.33055],"type":"Point"}
}