{
  "type": "Feature",
  "properties": {
    "gn:admin1_code":"WR",
    "gn:admin2_code":"4",
    "gn:admin3_code":"36.0",
    "gn:admin4_code":"360029.0",
    "gn:asciiname":"Sugure",
    "gn:country_code":"NP",
    "gn:dem":1168,
    "gn:feature_class":"P",
    "gn:feature_code":"PPLL",
    "gn:name":"Sugure",
    "gn:population":0,
    "gn:timezone":"Asia/Kathmandu",
    "iso:country":"NP",
    "wof:name":"Sugure",
    "wof:placetype":"locality"
},
  "geometry": {"coordinates":[84.62271,28.16682],"type":"Point"}
}