{
  "type": "Feature",
  "properties": {
    "gn:admin1_code":"WR",
    "gn:admin2_code":"4",
    "gn:admin3_code":"40.0",
    "gn:admin4_code":"400013.0",
    "gn:asciiname":"Kimrongkholagaun",
    "gn:country_code":"NP",
    "gn:dem":2051,
    "gn:feature_class":"P",
    "gn:feature_code":"PPLL",
    "gn:name":"Kimrongkholagaun",
    "gn:population":0,
    "gn:timezone":"Asia/Kathmandu",
    "iso:country":"NP",
    "wof:name":"Kimrongkholagaun",
    "wof:placetype":"locality"
},
  "geometry": {"coordinates":[83.79629,28.40935],"type":"Point"}
}