{
  "type": "Feature",
  "properties": {
    "gn:admin1_code":"ER",
    "gn:admin2_code":"10",
    "gn:admin3_code":"2",
    "gn:admin4_code":"20011",
    "gn:asciiname":"Sunargaun",
    "gn:country_code":"NP",
    "gn:dem":2428,
    "gn:feature_class":"P",
    "gn:feature_code":"PPLL",
    "gn:name":"Sunargaun",
    "gn:population":0,
    "gn:timezone":"Asia/Kathmandu",
    "iso:country":"NP",
    "wof:name":"Sunargaun",
    "wof:placetype":"locality"
},
  "geometry": {"coordinates":[87.77853,27.06903],"type":"Point"}
}