{
  "type": "Feature",
  "properties": {
    "gn:admin1_code":"CR",
    "gn:admin2_code":"1",
    "gn:admin3_code":"24.0",
    "gn:admin4_code":"240060.0",
    "gn:asciiname":"Hattichhera",
    "gn:country_code":"NP",
    "gn:dem":1104,
    "gn:feature_class":"P",
    "gn:feature_code":"PPLL",
    "gn:name":"Hattichhera",
    "gn:population":0,
    "gn:timezone":"Asia/Kathmandu",
    "iso:country":"NP",
    "wof:name":"Hattichhera",
    "wof:placetype":"locality"
},
  "geometry": {"coordinates":[85.42876,27.44299],"type":"Point"}
}