{
  "type": "Feature",
  "properties": {
    "gn:admin1_code":"MR",
    "gn:admin2_code":"2.0",
    "gn:admin3_code":"58.0",
    "gn:admin4_code":"580010.0",
    "gn:asciiname":"Dangpur",
    "gn:country_code":"NP",
    "gn:dem":173,
    "gn:feature_class":"P",
    "gn:feature_code":"PPLL",
    "gn:name":"Dangpur",
    "gn:population":0,
    "gn:timezone":"Asia/Kathmandu",
    "iso:country":"NP",
    "wof:name":"Dangpur",
    "wof:placetype":"locality"
},
  "geometry": {"coordinates":[81.22611999999999,28.52733],"type":"Point"}
}