{
  "type": "Feature",
  "properties": {
    "gn:admin1_code":"FR",
    "gn:admin2_code":"9",
    "gn:admin3_code":"73.0",
    "gn:admin4_code":"730008.0",
    "gn:asciiname":"Baniya",
    "gn:country_code":"NP",
    "gn:dem":598,
    "gn:feature_class":"P",
    "gn:feature_code":"PPLL",
    "gn:name":"Baniya",
    "gn:population":0,
    "gn:timezone":"Asia/Kathmandu",
    "iso:country":"NP",
    "wof:name":"Baniya",
    "wof:placetype":"locality"
},
  "geometry": {"coordinates":[80.39152,29.35662],"type":"Point"}
}