{
  "type": "Feature",
  "properties": {
    "gn:admin1_code":"MR",
    "gn:admin2_code":"12",
    "gn:admin3_code":"52",
    "gn:admin4_code":"520011.0",
    "gn:asciiname":"Salhanna",
    "gn:country_code":"NP",
    "gn:dem":1675,
    "gn:feature_class":"P",
    "gn:feature_code":"PPLL",
    "gn:name":"Salhanna",
    "gn:population":0,
    "gn:timezone":"Asia/Kathmandu",
    "iso:country":"NP",
    "wof:name":"Salhanna",
    "wof:placetype":"locality"
},
  "geometry": {"coordinates":[82.97556999999998,28.10236],"type":"Point"}
}