{
  "type": "Feature",
  "properties": {
    "gn:admin1_code":"CR",
    "gn:admin2_code":"5",
    "gn:admin3_code":"20",
    "gn:admin4_code":"200028",
    "gn:asciiname":"Jhagare",
    "gn:country_code":"NP",
    "gn:dem":1423,
    "gn:feature_class":"P",
    "gn:feature_code":"PPLL",
    "gn:name":"Jhagare",
    "gn:population":0,
    "gn:timezone":"Asia/Kathmandu",
    "iso:country":"NP",
    "wof:name":"Jhagare",
    "wof:placetype":"locality"
},
  "geometry": {"coordinates":[86.22975,27.17274],"type":"Point"}
}