{
  "type": "Feature",
  "properties": {
    "gn:admin1_code":"WR",
    "gn:admin2_code":"3",
    "gn:admin3_code":"45.0",
    "gn:admin4_code":"450024.0",
    "gn:asciiname":"Liuwa",
    "gn:country_code":"NP",
    "gn:dem":1460,
    "gn:feature_class":"P",
    "gn:feature_code":"PPLL",
    "gn:name":"Liuwa",
    "gn:population":0,
    "gn:timezone":"Asia/Kathmandu",
    "iso:country":"NP",
    "wof:name":"Liuwa",
    "wof:placetype":"locality"
},
  "geometry": {"coordinates":[83.52939000000001,28.1418],"type":"Point"}
}