{
  "type": "Feature",
  "properties": {
    "gn:admin1_code":"WR",
    "gn:admin2_code":"3",
    "gn:admin3_code":"44",
    "gn:admin4_code":"440052",
    "gn:asciiname":"Thuli Pokhari",
    "gn:country_code":"NP",
    "gn:dem":1634,
    "gn:feature_class":"P",
    "gn:feature_code":"PPLL",
    "gn:name":"Thuli Pokhari",
    "gn:population":0,
    "gn:timezone":"Asia/Kathmandu",
    "iso:country":"NP",
    "name:mai_x_preferred":[
        "\u0920\u0942\u0932\u0940\u092a\u094b\u0916\u0930\u0940"
    ],
    "name:msa_x_preferred":[
        "Thuli Pokhari"
    ],
    "name:nep_x_preferred":[
        "\u0920\u0942\u0932\u0940\u092a\u094b\u0916\u0930\u0940"
    ],
    "name:new_x_preferred":[
        "\u0920\u0941\u0932\u0940 \u092a\u094b\u0916\u0930\u0940"
    ],
    "name:pol_x_preferred":[
        "Thuli Pokhari"
    ],
    "wof:name":"Thuli Pokhari",
    "wof:placetype":"locality"
},
  "geometry": {"coordinates":[83.73380999999998,28.20528],"type":"Point"}
}