{
  "type": "Feature",
  "properties": {
    "gn:admin1_code":"WR",
    "gn:admin2_code":"3",
    "gn:admin3_code":"44",
    "gn:admin4_code":"440052",
    "gn:asciiname":"Thuli Pokhari",
    "gn:country_code":"NP",
    "gn:dem":1634,
    "gn:feature_class":"P",
    "gn:feature_code":"PPLL",
    "gn:name":"Thuli Pokhari",
    "gn:population":0,
    "gn:timezone":"Asia/Kathmandu",
    "iso:country":"NP",
    "wof:name":"Thuli Pokhari",
    "wof:placetype":"locality"
},
  "geometry": {"coordinates":[83.73380999999998,28.20528],"type":"Point"}
}