{
  "type": "Feature",
  "properties": {
    "gn:admin1_code":"WR",
    "gn:admin2_code":"3",
    "gn:admin3_code":"44",
    "gn:admin4_code":"440022",
    "gn:asciiname":"Nursery",
    "gn:country_code":"NP",
    "gn:dem":1985,
    "gn:feature_class":"P",
    "gn:feature_code":"PPLL",
    "gn:name":"Nursery",
    "gn:population":0,
    "gn:timezone":"Asia/Kathmandu",
    "iso:country":"NP",
    "wof:name":"Nursery",
    "wof:placetype":"locality"
},
  "geometry": {"coordinates":[83.70626,28.12047],"type":"Point"}
}