{
  "type": "Feature",
  "properties": {
    "gn:admin1_code":"CR",
    "gn:admin2_code":"1",
    "gn:admin3_code":"30.0",
    "gn:admin4_code":"300036.0",
    "gn:asciiname":"Painyakharka",
    "gn:country_code":"NP",
    "gn:dem":1815,
    "gn:feature_class":"P",
    "gn:feature_code":"PPLL",
    "gn:name":"Painyakharka",
    "gn:population":0,
    "gn:timezone":"Asia/Kathmandu",
    "iso:country":"NP",
    "wof:name":"Painyakharka",
    "wof:placetype":"locality"
},
  "geometry": {"coordinates":[84.92124,28.07599],"type":"Point"}
}