{
  "type": "Feature",
  "properties": {
    "gn:admin1_code":"MR",
    "gn:admin2_code":"2",
    "gn:admin3_code":"61.0",
    "gn:admin4_code":"610013.0",
    "gn:asciiname":"Kayakhet",
    "gn:country_code":"NP",
    "gn:dem":1317,
    "gn:feature_class":"P",
    "gn:feature_code":"PPLL",
    "gn:name":"Kayakhet",
    "gn:population":0,
    "gn:timezone":"Asia/Kathmandu",
    "iso:country":"NP",
    "wof:name":"Kayakhet",
    "wof:placetype":"locality"
},
  "geometry": {"coordinates":[82.36338000000001,28.80991],"type":"Point"}
}