{
  "type": "Feature",
  "properties": {
    "gn:admin1_code":"WR",
    "gn:admin2_code":"4.0",
    "gn:admin3_code":"39.0",
    "gn:admin4_code":"390031.0",
    "gn:asciiname":"Adhmara",
    "gn:country_code":"NP",
    "gn:dem":519,
    "gn:feature_class":"P",
    "gn:feature_code":"PPLL",
    "gn:name":"Adhmara",
    "gn:population":0,
    "gn:timezone":"Asia/Kathmandu",
    "iso:country":"NP",
    "wof:name":"Adhmara",
    "wof:placetype":"locality"
},
  "geometry": {"coordinates":[83.97589000000001,27.91302],"type":"Point"}
}