{
  "type": "Feature",
  "properties": {
    "gn:admin1_code":"ER",
    "gn:admin2_code":"13",
    "gn:admin3_code":"16",
    "gn:admin4_code":"160024",
    "gn:asciiname":"Chandralalpur",
    "gn:country_code":"NP",
    "gn:dem":150,
    "gn:feature_class":"P",
    "gn:feature_code":"PPLL",
    "gn:name":"Chandralalpur",
    "gn:population":0,
    "gn:timezone":"Asia/Kathmandu",
    "iso:country":"NP",
    "name:bih_x_preferred":[
        "\u091a\u0928\u094d\u0926\u094d\u0930\u0932\u093e\u0932\u092a\u0941\u0930"
    ],
    "name:ceb_x_preferred":[
        "Chandralalpur"
    ],
    "name:msa_x_preferred":[
        "Chandralalpur"
    ],
    "name:nep_x_preferred":[
        "\u091a\u0928\u094d\u0926\u094d\u0930\u0932\u093e\u0932\u092a\u0941\u0930"
    ],
    "name:new_x_preferred":[
        "\u091a\u0928\u094d\u0926\u094d\u0930\u0932\u093e\u0932\u092a\u0941\u0930"
    ],
    "name:pol_x_preferred":[
        "Chandralalpur"
    ],
    "wof:name":"Chandralalpur",
    "wof:placetype":"locality"
},
  "geometry": {"coordinates":[86.31061,26.81204],"type":"Point"}
}