{
  "type": "Feature",
  "properties": {
    "gn:admin1_code":"CR",
    "gn:admin2_code":"1",
    "gn:admin3_code":"23",
    "gn:admin4_code":"230026",
    "gn:asciiname":"Gunsakot",
    "gn:country_code":"NP",
    "gn:dem":1724,
    "gn:feature_class":"P",
    "gn:feature_code":"PPLL",
    "gn:name":"Gunsakot",
    "gn:population":0,
    "gn:timezone":"Asia/Kathmandu",
    "iso:country":"NP",
    "wof:name":"Gunsakot",
    "wof:placetype":"locality"
},
  "geometry": {"coordinates":[85.67067,27.92677],"type":"Point"}
}