{
  "type": "Feature",
  "properties": {
    "gn:admin1_code":"CR",
    "gn:admin2_code":"1",
    "gn:admin3_code":"23",
    "gn:admin4_code":"230060",
    "gn:asciiname":"Phusre",
    "gn:country_code":"NP",
    "gn:dem":2306,
    "gn:feature_class":"P",
    "gn:feature_code":"PPLL",
    "gn:name":"Phusre",
    "gn:population":0,
    "gn:timezone":"Asia/Kathmandu",
    "iso:country":"NP",
    "wof:name":"Phusre",
    "wof:placetype":"locality"
},
  "geometry": {"coordinates":[85.69954,27.85537],"type":"Point"}
}