{
  "type": "Feature",
  "properties": {
    "gn:admin1_code":"WR",
    "gn:admin2_code":"4.0",
    "gn:admin3_code":"38.0",
    "gn:admin4_code":"380037.0",
    "gn:asciiname":"Kirpetar",
    "gn:country_code":"NP",
    "gn:dem":405,
    "gn:feature_class":"P",
    "gn:feature_code":"PPLL",
    "gn:name":"Kirpetar",
    "gn:population":0,
    "gn:timezone":"Asia/Kathmandu",
    "iso:country":"NP",
    "wof:name":"Kirpetar",
    "wof:placetype":"locality"
},
  "geometry": {"coordinates":[84.16322,27.85635],"type":"Point"}
}