{
  "type": "Feature",
  "properties": {
    "gn:admin1_code":"ER",
    "gn:admin2_code":"13",
    "gn:admin3_code":"11",
    "gn:admin4_code":"110022",
    "gn:asciiname":"Kuwapani",
    "gn:country_code":"NP",
    "gn:dem":1294,
    "gn:feature_class":"P",
    "gn:feature_code":"PPLL",
    "gn:name":"Kuwapani",
    "gn:population":0,
    "gn:timezone":"Asia/Kathmandu",
    "iso:country":"NP",
    "wof:name":"Kuwapani",
    "wof:placetype":"locality"
},
  "geometry": {"coordinates":[86.73992,27.46484],"type":"Point"}
}