{
  "type": "Feature",
  "properties": {
    "gn:admin1_code":"MR",
    "gn:admin2_code":"2.0",
    "gn:admin3_code":"58.0",
    "gn:admin4_code":"580029.0",
    "gn:asciiname":"Khaisakala",
    "gn:country_code":"NP",
    "gn:dem":149,
    "gn:feature_class":"P",
    "gn:feature_code":"PPLL",
    "gn:name":"Khaisakala",
    "gn:population":0,
    "gn:timezone":"Asia/Kathmandu",
    "iso:country":"NP",
    "wof:name":"Khaisakala",
    "wof:placetype":"locality"
},
  "geometry": {"coordinates":[81.51111,28.18138],"type":"Point"}
}