{
  "type": "Feature",
  "properties": {
    "gn:admin1_code":"ER",
    "gn:admin2_code":"7.0",
    "gn:admin3_code":"6.0",
    "gn:admin4_code":"60038.0",
    "gn:asciiname":"Rampur",
    "gn:country_code":"NP",
    "gn:dem":110,
    "gn:feature_class":"P",
    "gn:feature_code":"PPLL",
    "gn:name":"Rampur",
    "gn:population":0,
    "gn:timezone":"Asia/Kathmandu",
    "iso:country":"NP",
    "wof:name":"Rampur",
    "wof:placetype":"locality"
},
  "geometry": {"coordinates":[87.21970999999998,26.69354],"type":"Point"}
}