{
  "type": "Feature",
  "properties": {
    "gn:admin1_code":"CR",
    "gn:admin2_code":"1",
    "gn:admin3_code":"23",
    "gn:admin4_code":"230073",
    "gn:asciiname":"Chilaune",
    "gn:country_code":"NP",
    "gn:dem":1806,
    "gn:feature_class":"P",
    "gn:feature_code":"PPLL",
    "gn:name":"Chilaune",
    "gn:population":0,
    "gn:timezone":"Asia/Kathmandu",
    "iso:country":"NP",
    "wof:name":"Chilaune",
    "wof:placetype":"locality"
},
  "geometry": {"coordinates":[85.65191,27.94992],"type":"Point"}
}