{
  "type": "Feature",
  "properties": {
    "gn:admin1_code":"WR",
    "gn:admin2_code":"4",
    "gn:admin3_code":"41",
    "gn:admin4_code":"410012.0",
    "gn:asciiname":"Bojhotang Goth",
    "gn:country_code":"NP",
    "gn:dem":4057,
    "gn:feature_class":"P",
    "gn:feature_code":"PPLL",
    "gn:name":"Bojhotang Goth",
    "gn:population":0,
    "gn:timezone":"Asia/Kathmandu",
    "iso:country":"NP",
    "wof:name":"Bojhotang Goth",
    "wof:placetype":"locality"
},
  "geometry": {"coordinates":[84.04001,28.67491],"type":"Point"}
}