{
  "type": "Feature",
  "properties": {
    "gn:admin1_code":"CR",
    "gn:admin2_code":"1",
    "gn:admin3_code":"25",
    "gn:admin4_code":"250027",
    "gn:asciiname":"Kumbheshwar",
    "gn:country_code":"NP",
    "gn:dem":1288,
    "gn:feature_class":"P",
    "gn:feature_code":"PPLL",
    "gn:name":"Kumbheshwar",
    "gn:population":0,
    "gn:timezone":"Asia/Kathmandu",
    "iso:country":"NP",
    "wof:name":"Kumbheshwar",
    "wof:placetype":"locality"
},
  "geometry": {"coordinates":[85.33304,27.67827],"type":"Point"}
}