{
  "type": "Feature",
  "properties": {
    "gn:admin1_code":"MR",
    "gn:admin2_code":"2",
    "gn:admin3_code":"61.0",
    "gn:admin4_code":"610021.0",
    "gn:asciiname":"Palte",
    "gn:country_code":"NP",
    "gn:dem":2103,
    "gn:feature_class":"P",
    "gn:feature_code":"PPLL",
    "gn:name":"Palte",
    "gn:population":0,
    "gn:timezone":"Asia/Kathmandu",
    "iso:country":"NP",
    "wof:name":"Palte",
    "wof:placetype":"locality"
},
  "geometry": {"coordinates":[82.16424000000001,28.72883],"type":"Point"}
}