{
  "type": "Feature",
  "properties": {
    "gn:admin1_code":"CR",
    "gn:admin2_code":"11",
    "gn:admin3_code":"31",
    "gn:admin4_code":"310004",
    "gn:asciiname":"Basudev",
    "gn:country_code":"NP",
    "gn:dem":434,
    "gn:feature_class":"P",
    "gn:feature_code":"PPLL",
    "gn:name":"Basudev",
    "gn:population":0,
    "gn:timezone":"Asia/Kathmandu",
    "iso:country":"NP",
    "wof:name":"Basudev",
    "wof:placetype":"locality"
},
  "geometry": {"coordinates":[84.93471,27.4654],"type":"Point"}
}