{
  "type": "Feature",
  "properties": {
    "gn:admin1_code":"CR",
    "gn:admin2_code":"11",
    "gn:admin3_code":"35.0",
    "gn:admin4_code":"350022.0",
    "gn:asciiname":"Gothdanda",
    "gn:country_code":"NP",
    "gn:dem":933,
    "gn:feature_class":"P",
    "gn:feature_code":"PPLL",
    "gn:name":"Gothdanda",
    "gn:population":0,
    "gn:timezone":"Asia/Kathmandu",
    "iso:country":"NP",
    "wof:name":"Gothdanda",
    "wof:placetype":"locality"
},
  "geometry": {"coordinates":[84.68607,27.67245],"type":"Point"}
}