{
  "type": "Feature",
  "properties": {
    "gn:admin1_code":"MR",
    "gn:admin2_code":"6",
    "gn:admin3_code":"62.0",
    "gn:admin4_code":"620023.0",
    "gn:asciiname":"Khalrupi",
    "gn:country_code":"NP",
    "gn:dem":2634,
    "gn:feature_class":"P",
    "gn:feature_code":"PPLL",
    "gn:name":"Khalrupi",
    "gn:population":0,
    "gn:timezone":"Asia/Kathmandu",
    "iso:country":"NP",
    "wof:name":"Khalrupi",
    "wof:placetype":"locality"
},
  "geometry": {"coordinates":[82.89275000000001,29.00493],"type":"Point"}
}