{
  "type": "Feature",
  "properties": {
    "gn:admin1_code":"CR",
    "gn:admin2_code":"1",
    "gn:admin3_code":"23",
    "gn:admin4_code":"230037",
    "gn:asciiname":"Simle",
    "gn:country_code":"NP",
    "gn:dem":1242,
    "gn:feature_class":"P",
    "gn:feature_code":"PPLL",
    "gn:name":"Simle",
    "gn:population":0,
    "gn:timezone":"Asia/Kathmandu",
    "iso:country":"NP",
    "name:bih_x_preferred":[
        "\u0938\u093f\u092e\u094d\u0932\u0947"
    ],
    "name:ceb_x_preferred":[
        "Simle"
    ],
    "name:mai_x_preferred":[
        "\u0938\u093f\u092e\u094d\u0932\u0947"
    ],
    "name:msa_x_preferred":[
        "Simle"
    ],
    "name:nep_x_preferred":[
        "\u0938\u093f\u092e\u094d\u0932\u0947"
    ],
    "name:new_x_preferred":[
        "\u0938\u093f\u092e\u094d\u0932\u0947"
    ],
    "name:pol_x_preferred":[
        "Simle"
    ],
    "wof:name":"Simle",
    "wof:placetype":"locality"
},
  "geometry": {"coordinates":[85.91733000000001,27.78659],"type":"Point"}
}