{
  "type": "Feature",
  "properties": {
    "gn:admin1_code":"MR",
    "gn:admin2_code":"12",
    "gn:admin3_code":"54",
    "gn:admin4_code":"540026",
    "gn:asciiname":"Muru",
    "gn:country_code":"NP",
    "gn:dem":1484,
    "gn:feature_class":"P",
    "gn:feature_code":"PPLL",
    "gn:name":"Muru",
    "gn:population":0,
    "gn:timezone":"Asia/Kathmandu",
    "iso:country":"NP",
    "name:nno_x_preferred":[
        "Muru"
    ],
    "name:nor_x_preferred":[
        "Muru"
    ],
    "name:swe_x_preferred":[
        "Muru"
    ],
    "wof:name":"Muru",
    "wof:placetype":"locality"
},
  "geometry": {"coordinates":[82.40078000000003,28.57216],"type":"Point"}
}