{
  "type": "Feature",
  "properties": {
    "gn:admin1_code":"CR",
    "gn:admin2_code":"1",
    "gn:admin3_code":"23",
    "gn:admin4_code":"230020",
    "gn:asciiname":"Bokse",
    "gn:country_code":"NP",
    "gn:dem":837,
    "gn:feature_class":"P",
    "gn:feature_code":"PPLL",
    "gn:name":"Bokse",
    "gn:population":0,
    "gn:timezone":"Asia/Kathmandu",
    "iso:country":"NP",
    "wof:name":"Bokse",
    "wof:placetype":"locality"
},
  "geometry": {"coordinates":[85.77028,27.8091],"type":"Point"}
}