{
  "type": "Feature",
  "properties": {
    "gn:admin1_code":"CR",
    "gn:admin2_code":"1",
    "gn:admin3_code":"27.0",
    "gn:admin4_code":"270016.0",
    "gn:asciiname":"Tilangatar",
    "gn:country_code":"NP",
    "gn:dem":1338,
    "gn:feature_class":"P",
    "gn:feature_code":"PPLL",
    "gn:name":"Tilangatar",
    "gn:population":0,
    "gn:timezone":"Asia/Kathmandu",
    "iso:country":"NP",
    "wof:name":"Tilangatar",
    "wof:placetype":"locality"
},
  "geometry": {"coordinates":[85.32623000000002,27.74182],"type":"Point"}
}