{
  "type": "Feature",
  "properties": {
    "gn:admin1_code":"00",
    "gn:asciiname":"Jhapa",
    "gn:country_code":"NP",
    "gn:dem":90,
    "gn:feature_class":"P",
    "gn:feature_code":"PPL",
    "gn:name":"Jh\u0101p\u0101",
    "gn:population":0,
    "gn:timezone":"Asia/Kathmandu",
    "iso:country":"NP",
    "name:nep_x_preferred":[
        "Jh\u0101p\u0101"
    ],
    "wof:name":"Jhapa",
    "wof:placetype":"locality"
},
  "geometry": {"coordinates":[87.07006,26.62835],"type":"Point"}
}