{
  "type": "Feature",
  "properties": {
    "gn:admin1_code":"ER",
    "gn:admin2_code":"13",
    "gn:admin3_code":"13",
    "gn:admin4_code":"130072",
    "gn:asciiname":"Dhaplang",
    "gn:country_code":"NP",
    "gn:dem":275,
    "gn:feature_class":"P",
    "gn:feature_code":"PPLL",
    "gn:name":"Dhaplang",
    "gn:population":0,
    "gn:timezone":"Asia/Kathmandu",
    "iso:country":"NP",
    "wof:name":"Dhaplang",
    "wof:placetype":"locality"
},
  "geometry": {"coordinates":[86.77982,26.89036],"type":"Point"}
}