{
  "type": "Feature",
  "properties": {
    "gn:admin1_code":"CR",
    "gn:admin2_code":"5",
    "gn:admin3_code":"21",
    "gn:admin4_code":"210052",
    "gn:asciiname":"Bhadaure",
    "gn:country_code":"NP",
    "gn:dem":808,
    "gn:feature_class":"P",
    "gn:feature_code":"PPLL",
    "gn:name":"Bhadaure",
    "gn:population":0,
    "gn:timezone":"Asia/Kathmandu",
    "iso:country":"NP",
    "wof:name":"Bhadaure",
    "wof:placetype":"locality"
},
  "geometry": {"coordinates":[86.08919,27.36677],"type":"Point"}
}