{
  "type": "Feature",
  "properties": {
    "gn:admin1_code":"WR",
    "gn:admin2_code":"4",
    "gn:admin3_code":"40.0",
    "gn:admin4_code":"400028.0",
    "gn:asciiname":"Samle",
    "gn:country_code":"NP",
    "gn:dem":1462,
    "gn:feature_class":"P",
    "gn:feature_code":"PPLL",
    "gn:name":"Samle",
    "gn:population":0,
    "gn:timezone":"Asia/Kathmandu",
    "iso:country":"NP",
    "wof:name":"Samle",
    "wof:placetype":"locality"
},
  "geometry": {"coordinates":[84.18925,28.2803],"type":"Point"}
}