{
  "type": "Feature",
  "properties": {
    "gn:admin1_code":"MR",
    "gn:admin2_code":"12",
    "gn:admin3_code":"55",
    "gn:admin4_code":"550011",
    "gn:asciiname":"Bangiraha",
    "gn:country_code":"NP",
    "gn:dem":537,
    "gn:feature_class":"P",
    "gn:feature_code":"PPLL",
    "gn:name":"Bangiraha",
    "gn:population":0,
    "gn:timezone":"Asia/Kathmandu",
    "iso:country":"NP",
    "wof:name":"Bangiraha",
    "wof:placetype":"locality"
},
  "geometry": {"coordinates":[82.00738,28.46657],"type":"Point"}
}