{
  "type": "Feature",
  "properties": {
    "gn:admin1_code":"CR",
    "gn:admin2_code":"1",
    "gn:admin3_code":"30.0",
    "gn:admin4_code":"300007.0",
    "gn:asciiname":"Chulidanda",
    "gn:country_code":"NP",
    "gn:dem":1137,
    "gn:feature_class":"P",
    "gn:feature_code":"PPLL",
    "gn:name":"Chulidanda",
    "gn:population":0,
    "gn:timezone":"Asia/Kathmandu",
    "iso:country":"NP",
    "wof:name":"Chulidanda",
    "wof:placetype":"locality"
},
  "geometry": {"coordinates":[84.83750999999999,27.94942],"type":"Point"}
}