{
  "type": "Feature",
  "properties": {
    "gn:admin1_code":"FR",
    "gn:admin2_code":"14",
    "gn:admin3_code":"71.0",
    "gn:admin4_code":"710004.0",
    "gn:asciiname":"Kanhaiyapur",
    "gn:country_code":"NP",
    "gn:dem":145,
    "gn:feature_class":"P",
    "gn:feature_code":"PPLL",
    "gn:name":"Kanhaiyapur",
    "gn:population":0,
    "gn:timezone":"Asia/Kathmandu",
    "iso:country":"NP",
    "wof:name":"Kanhaiyapur",
    "wof:placetype":"locality"
},
  "geometry": {"coordinates":[80.99095,28.46273],"type":"Point"}
}