{
  "type": "Feature",
  "properties": {
    "gn:admin1_code":"CR",
    "gn:admin2_code":"11",
    "gn:admin3_code":"35.0",
    "gn:admin4_code":"350006.0",
    "gn:asciiname":"Chitrekot",
    "gn:country_code":"NP",
    "gn:dem":238,
    "gn:feature_class":"P",
    "gn:feature_code":"PPLL",
    "gn:name":"Chitrekot",
    "gn:population":0,
    "gn:timezone":"Asia/Kathmandu",
    "iso:country":"NP",
    "wof:name":"Chitrekot",
    "wof:placetype":"locality"
},
  "geometry": {"coordinates":[84.62585,27.62143],"type":"Point"}
}