{
  "type": "Feature",
  "properties": {
    "gn:admin1_code":"ER",
    "gn:admin2_code":"13.0",
    "gn:admin3_code":"14.0",
    "gn:admin4_code":"140040.0",
    "gn:asciiname":"Kopche",
    "gn:country_code":"NP",
    "gn:dem":856,
    "gn:feature_class":"P",
    "gn:feature_code":"PPLL",
    "gn:name":"Kopche",
    "gn:population":0,
    "gn:timezone":"Asia/Kathmandu",
    "iso:country":"NP",
    "wof:name":"Kopche",
    "wof:placetype":"locality"
},
  "geometry": {"coordinates":[86.59508000000002,27.09377000000001],"type":"Point"}
}