{
  "type": "Feature",
  "properties": {
    "gn:admin1_code":"ER",
    "gn:admin2_code":"7.0",
    "gn:admin3_code":"6.0",
    "gn:admin4_code":"60018.0",
    "gn:asciiname":"Ganeshchok",
    "gn:country_code":"NP",
    "gn:dem":453,
    "gn:feature_class":"P",
    "gn:feature_code":"PPLL",
    "gn:name":"Ganeshchok",
    "gn:population":0,
    "gn:timezone":"Asia/Kathmandu",
    "iso:country":"NP",
    "wof:name":"Ganeshchok",
    "wof:placetype":"locality"
},
  "geometry": {"coordinates":[87.29674,26.81684000000001],"type":"Point"}
}