{
  "type": "Feature",
  "properties": {
    "gn:admin1_code":"MR",
    "gn:admin2_code":"2.0",
    "gn:admin3_code":"59.0",
    "gn:admin4_code":"590032.0",
    "gn:asciiname":"Sanjhgotheri",
    "gn:country_code":"NP",
    "gn:dem":483,
    "gn:feature_class":"P",
    "gn:feature_code":"PPLL",
    "gn:name":"Sanjhgotheri",
    "gn:population":0,
    "gn:timezone":"Asia/Kathmandu",
    "iso:country":"NP",
    "wof:name":"Sanjhgotheri",
    "wof:placetype":"locality"
},
  "geometry": {"coordinates":[81.66586,28.49225],"type":"Point"}
}