{
  "type": "Feature",
  "properties": {
    "gn:admin1_code":"CR",
    "gn:admin2_code":"5",
    "gn:admin3_code":"19",
    "gn:admin4_code":"190068",
    "gn:asciiname":"Motipur",
    "gn:country_code":"NP",
    "gn:dem":86,
    "gn:feature_class":"P",
    "gn:feature_code":"PPLL",
    "gn:name":"Motipur",
    "gn:population":0,
    "gn:timezone":"Asia/Kathmandu",
    "iso:country":"NP",
    "name:ceb_x_preferred":[
        "Motipur"
    ],
    "name:fra_x_preferred":[
        "Motipur"
    ],
    "name:mai_x_preferred":[
        "\u092e\u094b\u0924\u0940\u092a\u0941\u0930 \u0938\u0930\u094d\u0932\u093e\u0939\u0940"
    ],
    "name:nep_x_preferred":[
        "\u092e\u094b\u0924\u0940\u092a\u0941\u0930 \u0938\u0930\u094d\u0932\u093e\u0939\u0940"
    ],
    "name:pol_x_preferred":[
        "Motipur"
    ],
    "wof:name":"Motipur",
    "wof:placetype":"locality"
},
  "geometry": {"coordinates":[85.52266999999998,26.87806],"type":"Point"}
}