{
  "type": "Feature",
  "properties": {
    "gn:admin1_code":"FR",
    "gn:admin2_code":"14",
    "gn:admin3_code":"68",
    "gn:admin4_code":"680012",
    "gn:asciiname":"Tola",
    "gn:country_code":"NP",
    "gn:dem":2008,
    "gn:feature_class":"P",
    "gn:feature_code":"PPLL",
    "gn:name":"Tola",
    "gn:population":0,
    "gn:timezone":"Asia/Kathmandu",
    "iso:country":"NP",
    "wof:name":"Tola",
    "wof:placetype":"locality"
},
  "geometry": {"coordinates":[80.79409,29.5277],"type":"Point"}
}