{
  "type": "Feature",
  "properties": {
    "gn:admin1_code":"MR",
    "gn:admin2_code":"12",
    "gn:admin3_code":"52",
    "gn:admin4_code":"520030",
    "gn:asciiname":"Anpdhara",
    "gn:country_code":"NP",
    "gn:dem":1297,
    "gn:feature_class":"P",
    "gn:feature_code":"PPLL",
    "gn:name":"Anpdhara",
    "gn:population":0,
    "gn:timezone":"Asia/Kathmandu",
    "iso:country":"NP",
    "wof:name":"Anpdhara",
    "wof:placetype":"locality"
},
  "geometry": {"coordinates":[82.82831,28.15443],"type":"Point"}
}