{
  "type": "Feature",
  "properties": {
    "gn:admin1_code":"FR",
    "gn:admin2_code":"9",
    "gn:admin3_code":"74",
    "gn:admin4_code":"740056",
    "gn:asciiname":"Jatarekholagaun",
    "gn:country_code":"NP",
    "gn:dem":1734,
    "gn:feature_class":"P",
    "gn:feature_code":"PPLL",
    "gn:name":"Jatarekholagaun",
    "gn:population":0,
    "gn:timezone":"Asia/Kathmandu",
    "iso:country":"NP",
    "wof:name":"Jatarekholagaun",
    "wof:placetype":"locality"
},
  "geometry": {"coordinates":[80.61757,29.46981],"type":"Point"}
}