{
  "type": "Feature",
  "properties": {
    "gn:admin1_code":"ER",
    "gn:admin2_code":"7.0",
    "gn:admin3_code":"8.0",
    "gn:admin4_code":"80018.0",
    "gn:asciiname":"Laphe",
    "gn:country_code":"NP",
    "gn:dem":821,
    "gn:feature_class":"P",
    "gn:feature_code":"PPLL",
    "gn:name":"Laphe",
    "gn:population":0,
    "gn:timezone":"Asia/Kathmandu",
    "iso:country":"NP",
    "wof:name":"Laphe",
    "wof:placetype":"locality"
},
  "geometry": {"coordinates":[87.45035,26.98545],"type":"Point"}
}