{
  "type": "Feature",
  "properties": {
    "gn:admin1_code":"WR",
    "gn:admin2_code":"4.0",
    "gn:admin3_code":"38.0",
    "gn:admin4_code":"380041.0",
    "gn:asciiname":"Majhgaun",
    "gn:country_code":"NP",
    "gn:dem":972,
    "gn:feature_class":"P",
    "gn:feature_code":"PPLL",
    "gn:name":"Majhgaun",
    "gn:population":0,
    "gn:timezone":"Asia/Kathmandu",
    "iso:country":"NP",
    "wof:name":"Majhgaun",
    "wof:placetype":"locality"
},
  "geometry": {"coordinates":[84.32753000000002,28.0807],"type":"Point"}
}