{
  "type": "Feature",
  "properties": {
    "gn:admin1_code":"ER",
    "gn:admin2_code":"10",
    "gn:admin3_code":"2",
    "gn:admin4_code":"20019",
    "gn:asciiname":"Patighar",
    "gn:country_code":"NP",
    "gn:dem":1125,
    "gn:feature_class":"P",
    "gn:feature_code":"PPLL",
    "gn:name":"Patighar",
    "gn:population":0,
    "gn:timezone":"Asia/Kathmandu",
    "iso:country":"NP",
    "wof:name":"Patighar",
    "wof:placetype":"locality"
},
  "geometry": {"coordinates":[87.53138,26.98033],"type":"Point"}
}