{
  "type": "Feature",
  "properties": {
    "gn:admin1_code":"CR",
    "gn:admin2_code":"11",
    "gn:admin3_code":"31",
    "gn:admin4_code":"310022",
    "gn:asciiname":"Khanidanda",
    "gn:country_code":"NP",
    "gn:dem":1367,
    "gn:feature_class":"P",
    "gn:feature_code":"PPLL",
    "gn:name":"Khanidanda",
    "gn:population":0,
    "gn:timezone":"Asia/Kathmandu",
    "iso:country":"NP",
    "wof:name":"Khanidanda",
    "wof:placetype":"locality"
},
  "geometry": {"coordinates":[85.21486999999998,27.52216],"type":"Point"}
}