{
  "type": "Feature",
  "properties": {
    "gn:admin1_code":"WR",
    "gn:admin2_code":"4",
    "gn:admin3_code":"36.0",
    "gn:admin4_code":"360046.0",
    "gn:asciiname":"Chilaune",
    "gn:country_code":"NP",
    "gn:dem":862,
    "gn:feature_class":"P",
    "gn:feature_code":"PPLL",
    "gn:name":"Chilaune",
    "gn:population":0,
    "gn:timezone":"Asia/Kathmandu",
    "iso:country":"NP",
    "wof:name":"Chilaune",
    "wof:placetype":"locality"
},
  "geometry": {"coordinates":[84.62066999999998,28.02875],"type":"Point"}
}