{
  "type": "Feature",
  "properties": {
    "gn:admin1_code":"FR",
    "gn:admin2_code":"14",
    "gn:admin3_code":"70.0",
    "gn:admin4_code":"700026.0",
    "gn:asciiname":"Kaladhunga",
    "gn:country_code":"NP",
    "gn:dem":1563,
    "gn:feature_class":"P",
    "gn:feature_code":"PPLL",
    "gn:name":"Kaladhunga",
    "gn:population":0,
    "gn:timezone":"Asia/Kathmandu",
    "iso:country":"NP",
    "wof:name":"Kaladhunga",
    "wof:placetype":"locality"
},
  "geometry": {"coordinates":[80.90272,29.19485],"type":"Point"}
}