{
  "type": "Feature",
  "properties": {
    "gn:admin1_code":"WR",
    "gn:admin2_code":"4",
    "gn:admin3_code":"37",
    "gn:admin4_code":"370025",
    "gn:asciiname":"Dailung",
    "gn:country_code":"NP",
    "gn:dem":1155,
    "gn:feature_class":"P",
    "gn:feature_code":"PPLL",
    "gn:name":"Dailung",
    "gn:population":0,
    "gn:timezone":"Asia/Kathmandu",
    "iso:country":"NP",
    "wof:name":"Dailung",
    "wof:placetype":"locality"
},
  "geometry": {"coordinates":[84.50049,28.25946],"type":"Point"}
}