{
  "type": "Feature",
  "properties": {
    "gn:admin1_code":"MR",
    "gn:admin2_code":"12",
    "gn:admin3_code":"53",
    "gn:admin4_code":"530010",
    "gn:asciiname":"Jhyalgung",
    "gn:country_code":"NP",
    "gn:dem":2106,
    "gn:feature_class":"P",
    "gn:feature_code":"PPLL",
    "gn:name":"Jhyalgung",
    "gn:population":0,
    "gn:timezone":"Asia/Kathmandu",
    "iso:country":"NP",
    "wof:name":"Jhyalgung",
    "wof:placetype":"locality"
},
  "geometry": {"coordinates":[82.88979,28.37796],"type":"Point"}
}