{
  "type": "Feature",
  "properties": {
    "gn:admin1_code":"WR",
    "gn:admin2_code":"4.0",
    "gn:admin3_code":"38.0",
    "gn:admin4_code":"380018.0",
    "gn:asciiname":"Putaliswanra",
    "gn:country_code":"NP",
    "gn:dem":491,
    "gn:feature_class":"P",
    "gn:feature_code":"PPLL",
    "gn:name":"Putaliswanra",
    "gn:population":0,
    "gn:timezone":"Asia/Kathmandu",
    "iso:country":"NP",
    "wof:name":"Putaliswanra",
    "wof:placetype":"locality"
},
  "geometry": {"coordinates":[84.37038000000003,27.87339],"type":"Point"}
}