{
  "type": "Feature",
  "properties": {
    "gn:admin1_code":"FR",
    "gn:admin2_code":"9",
    "gn:admin3_code":"74",
    "gn:admin4_code":"740033",
    "gn:asciiname":"Layanti",
    "gn:country_code":"NP",
    "gn:dem":1719,
    "gn:feature_class":"P",
    "gn:feature_code":"PPLL",
    "gn:name":"Layanti",
    "gn:population":0,
    "gn:timezone":"Asia/Kathmandu",
    "iso:country":"NP",
    "wof:name":"Layanti",
    "wof:placetype":"locality"
},
  "geometry": {"coordinates":[80.69771,29.63039],"type":"Point"}
}