{
  "type": "Feature",
  "properties": {
    "gn:admin1_code":"FR",
    "gn:admin2_code":"14",
    "gn:admin3_code":"68",
    "gn:admin4_code":"680014",
    "gn:asciiname":"Niyan Nauli",
    "gn:country_code":"NP",
    "gn:dem":1551,
    "gn:feature_class":"P",
    "gn:feature_code":"PPLL",
    "gn:name":"Niyan Nauli",
    "gn:population":0,
    "gn:timezone":"Asia/Kathmandu",
    "iso:country":"NP",
    "wof:name":"Niyan Nauli",
    "wof:placetype":"locality"
},
  "geometry": {"coordinates":[81.30146999999999,29.63627],"type":"Point"}
}