{
  "type": "Feature",
  "properties": {
    "gn:admin1_code":"CR",
    "gn:admin2_code":"11",
    "gn:admin3_code":"31",
    "gn:admin4_code":"310028",
    "gn:asciiname":"Chhapbesi",
    "gn:country_code":"NP",
    "gn:dem":672,
    "gn:feature_class":"P",
    "gn:feature_code":"PPLL",
    "gn:name":"Chhapbesi",
    "gn:population":0,
    "gn:timezone":"Asia/Kathmandu",
    "iso:country":"NP",
    "wof:name":"Chhapbesi",
    "wof:placetype":"locality"
},
  "geometry": {"coordinates":[85.14088000000002,27.43571],"type":"Point"}
}