{
  "type": "Feature",
  "properties": {
    "gn:admin1_code":"WR",
    "gn:admin2_code":"8",
    "gn:admin3_code":"48",
    "gn:admin4_code":"480033",
    "gn:asciiname":"koldanda",
    "gn:country_code":"NP",
    "gn:dem":773,
    "gn:feature_class":"P",
    "gn:feature_code":"PPLL",
    "gn:name":"koldanda",
    "gn:population":0,
    "gn:timezone":"Asia/Kathmandu",
    "iso:country":"NP",
    "name:ceb_x_preferred":[
        "Koldada"
    ],
    "name:hin_x_preferred":[
        "\u0915\u094b\u0932\u0921\u093e\u0901\u0921\u093e"
    ],
    "name:msa_x_preferred":[
        "Koldada"
    ],
    "name:nep_x_preferred":[
        "\u0915\u094b\u0932\u0921\u093e\u0901\u0921\u093e"
    ],
    "name:new_x_preferred":[
        "\u0915\u094b\u0932\u094d\u0921\u093e\u0902\u0921\u093e"
    ],
    "name:pol_x_preferred":[
        "Koldada"
    ],
    "wof:name":"koldanda",
    "wof:placetype":"locality"
},
  "geometry": {"coordinates":[84.28532,27.80953],"type":"Point"}
}