{
  "type": "Feature",
  "properties": {
    "gn:admin1_code":"FR",
    "gn:admin2_code":"14",
    "gn:admin3_code":"68",
    "gn:admin4_code":"680035",
    "gn:asciiname":"Gwano",
    "gn:country_code":"NP",
    "gn:dem":1925,
    "gn:feature_class":"P",
    "gn:feature_code":"PPLL",
    "gn:name":"Gwano",
    "gn:population":0,
    "gn:timezone":"Asia/Kathmandu",
    "iso:country":"NP",
    "wof:name":"Gwano",
    "wof:placetype":"locality"
},
  "geometry": {"coordinates":[81.01313,29.4407],"type":"Point"}
}