{
  "type": "Feature",
  "properties": {
    "gn:admin1_code":"MR",
    "gn:admin2_code":"2",
    "gn:admin3_code":"60.0",
    "gn:admin4_code":"600006.0",
    "gn:asciiname":"Bahunbanda",
    "gn:country_code":"NP",
    "gn:dem":1250,
    "gn:feature_class":"P",
    "gn:feature_code":"PPLL",
    "gn:name":"Bahunbanda",
    "gn:population":0,
    "gn:timezone":"Asia/Kathmandu",
    "iso:country":"NP",
    "wof:name":"Bahunbanda",
    "wof:placetype":"locality"
},
  "geometry": {"coordinates":[81.67284000000002,28.9077],"type":"Point"}
}