{
  "type": "Feature",
  "properties": {
    "gn:admin1_code":"MR",
    "gn:admin2_code":"2",
    "gn:admin3_code":"60.0",
    "gn:admin4_code":"600007.0",
    "gn:asciiname":"Jaluken",
    "gn:country_code":"NP",
    "gn:dem":1180,
    "gn:feature_class":"P",
    "gn:feature_code":"PPLL",
    "gn:name":"Jaluken",
    "gn:population":0,
    "gn:timezone":"Asia/Kathmandu",
    "iso:country":"NP",
    "wof:name":"Jaluken",
    "wof:placetype":"locality"
},
  "geometry": {"coordinates":[81.63705999999998,28.75298],"type":"Point"}
}