{
  "type": "Feature",
  "properties": {
    "gn:admin1_code":"00",
    "gn:asciiname":"Chilaunekhark",
    "gn:country_code":"NP",
    "gn:dem":1056,
    "gn:feature_class":"P",
    "gn:feature_code":"PPL",
    "gn:name":"Chil\u0101unekhark",
    "gn:population":0,
    "gn:timezone":"Asia/Kathmandu",
    "iso:country":"NP",
    "name:nep_x_preferred":[
        "Chil\u0101unekhark"
    ],
    "wof:name":"Chilaunekhark",
    "wof:placetype":"locality"
},
  "geometry": {"coordinates":[84.87272,27.75035],"type":"Point"}
}