{
  "type": "Feature",
  "properties": {
    "gn:admin1_code":"00",
    "gn:asciiname":"Jhajhpatti",
    "gn:country_code":"NP",
    "gn:dem":89,
    "gn:feature_class":"P",
    "gn:feature_code":"PPL",
    "gn:name":"Jh\u0101\u0303jhpa\u1e6d\u1e6di\u0307\u0304",
    "gn:population":0,
    "gn:timezone":"Asia/Kathmandu",
    "iso:country":"NP",
    "name:nep_x_preferred":[
        "Jh\u0101\u0303jhpa\u1e6d\u1e6di\u0307\u0304"
    ],
    "wof:name":"Jhajhpatti",
    "wof:placetype":"locality"
},
  "geometry": {"coordinates":[86.40384,26.58597],"type":"Point"}
}