{
  "type": "Feature",
  "properties": {
    "gn:admin1_code":"WR",
    "gn:admin2_code":"4",
    "gn:admin3_code":"40.0",
    "gn:admin4_code":"400019.0",
    "gn:asciiname":"Poligaun",
    "gn:country_code":"NP",
    "gn:dem":900,
    "gn:feature_class":"P",
    "gn:feature_code":"PPLL",
    "gn:name":"Poligaun",
    "gn:population":0,
    "gn:timezone":"Asia/Kathmandu",
    "iso:country":"NP",
    "wof:name":"Poligaun",
    "wof:placetype":"locality"
},
  "geometry": {"coordinates":[83.94365999999999,28.14822],"type":"Point"}
}