{
  "type": "Feature",
  "properties": {
    "gn:admin1_code":"ER",
    "gn:admin2_code":"13",
    "gn:admin3_code":"12",
    "gn:admin4_code":"120028",
    "gn:asciiname":"Bhadare",
    "gn:country_code":"NP",
    "gn:dem":1393,
    "gn:feature_class":"P",
    "gn:feature_code":"PPLL",
    "gn:name":"Bhadare",
    "gn:population":0,
    "gn:timezone":"Asia/Kathmandu",
    "iso:country":"NP",
    "wof:name":"Bhadare",
    "wof:placetype":"locality"
},
  "geometry": {"coordinates":[86.56541,27.32269],"type":"Point"}
}