{
  "type": "Feature",
  "properties": {
    "gn:admin1_code":"ER",
    "gn:admin2_code":"13.0",
    "gn:admin3_code":"14.0",
    "gn:admin4_code":"140035.0",
    "gn:asciiname":"Kerabari",
    "gn:country_code":"NP",
    "gn:dem":1038,
    "gn:feature_class":"P",
    "gn:feature_code":"PPLL",
    "gn:name":"Kerabari",
    "gn:population":0,
    "gn:timezone":"Asia/Kathmandu",
    "iso:country":"NP",
    "wof:name":"Kerabari",
    "wof:placetype":"locality"
},
  "geometry": {"coordinates":[86.41539,27.04079],"type":"Point"}
}