{
  "type": "Feature",
  "properties": {
    "gn:admin1_code":"CR",
    "gn:admin2_code":"1",
    "gn:admin3_code":"23",
    "gn:admin4_code":"230058.0",
    "gn:asciiname":"Sangachok",
    "gn:country_code":"NP",
    "gn:dem":1178,
    "gn:feature_class":"P",
    "gn:feature_code":"PPLL",
    "gn:name":"Sangachok",
    "gn:population":0,
    "gn:timezone":"Asia/Kathmandu",
    "iso:country":"NP",
    "name:msa_x_preferred":[
        "Sangachok"
    ],
    "name:nep_x_preferred":[
        "\u0938\u093e\u0901\u0917\u093e\u091a\u094b\u0915"
    ],
    "name:new_x_preferred":[
        "\u0938\u093e\u0902\u0917\u093e\u091a\u094b\u0915"
    ],
    "name:pol_x_preferred":[
        "Sangachok"
    ],
    "wof:name":"Sangachok",
    "wof:placetype":"locality"
},
  "geometry": {"coordinates":[85.71597,27.69027],"type":"Point"}
}