{
  "type": "Feature",
  "properties": {
    "gn:admin1_code":"MR",
    "gn:admin2_code":"12",
    "gn:admin3_code":"56.0",
    "gn:admin4_code":"560035.0",
    "gn:asciiname":"Bhanpur",
    "gn:country_code":"NP",
    "gn:dem":283,
    "gn:feature_class":"P",
    "gn:feature_code":"PPLL",
    "gn:name":"Bhanpur",
    "gn:population":0,
    "gn:timezone":"Asia/Kathmandu",
    "iso:country":"NP",
    "wof:name":"Bhanpur",
    "wof:placetype":"locality"
},
  "geometry": {"coordinates":[82.67983000000002,27.8344],"type":"Point"}
}