{
  "type": "Feature",
  "properties": {
    "gn:admin1_code":"WR",
    "gn:admin2_code":"4",
    "gn:admin3_code":"37",
    "gn:admin4_code":"370002",
    "gn:asciiname":"Sangla",
    "gn:country_code":"NP",
    "gn:dem":1812,
    "gn:feature_class":"P",
    "gn:feature_code":"PPLL",
    "gn:name":"Sangla",
    "gn:population":0,
    "gn:timezone":"Asia/Kathmandu",
    "iso:country":"NP",
    "name:ceb_x_preferred":[
        "Sangla"
    ],
    "name:pol_x_preferred":[
        "Sangla"
    ],
    "name:swe_x_preferred":[
        "Sangla"
    ],
    "wof:name":"Sangla",
    "wof:placetype":"locality"
},
  "geometry": {"coordinates":[84.4366,28.34131],"type":"Point"}
}