{
  "type": "Feature",
  "properties": {
    "gn:admin1_code":"MR",
    "gn:admin2_code":"2.0",
    "gn:admin3_code":"59.0",
    "gn:admin4_code":"590034.0",
    "gn:asciiname":"Sano Natne",
    "gn:country_code":"NP",
    "gn:dem":946,
    "gn:feature_class":"P",
    "gn:feature_code":"PPLL",
    "gn:name":"Sano Natne",
    "gn:population":0,
    "gn:timezone":"Asia/Kathmandu",
    "iso:country":"NP",
    "wof:name":"Sano Natne",
    "wof:placetype":"locality"
},
  "geometry": {"coordinates":[81.76443,28.41176],"type":"Point"}
}