{
  "type": "Feature",
  "properties": {
    "gn:admin1_code":"ER",
    "gn:admin2_code":"7",
    "gn:admin3_code":"5",
    "gn:admin4_code":"50046",
    "gn:asciiname":"Majite",
    "gn:country_code":"NP",
    "gn:dem":1780,
    "gn:feature_class":"P",
    "gn:feature_code":"PPLL",
    "gn:name":"Majite",
    "gn:population":0,
    "gn:timezone":"Asia/Kathmandu",
    "iso:country":"NP",
    "wof:name":"Majite",
    "wof:placetype":"locality"
},
  "geometry": {"coordinates":[87.40588000000002,26.85564],"type":"Point"}
}