{
  "type": "Feature",
  "properties": {
    "gn:admin1_code":"WR",
    "gn:admin2_code":"4.0",
    "gn:admin3_code":"39.0",
    "gn:admin4_code":"390028.0",
    "gn:asciiname":"Satipole",
    "gn:country_code":"NP",
    "gn:dem":1526,
    "gn:feature_class":"P",
    "gn:feature_code":"PPLL",
    "gn:name":"Satipole",
    "gn:population":0,
    "gn:timezone":"Asia/Kathmandu",
    "iso:country":"NP",
    "wof:name":"Satipole",
    "wof:placetype":"locality"
},
  "geometry": {"coordinates":[83.76624,28.05996],"type":"Point"}
}