{
  "type": "Feature",
  "properties": {
    "gn:admin1_code":"FR",
    "gn:admin2_code":"9",
    "gn:admin3_code":"73.0",
    "gn:admin4_code":"730012.0",
    "gn:asciiname":"Tola",
    "gn:country_code":"NP",
    "gn:dem":1438,
    "gn:feature_class":"P",
    "gn:feature_code":"PPLL",
    "gn:name":"Tola",
    "gn:population":0,
    "gn:timezone":"Asia/Kathmandu",
    "iso:country":"NP",
    "name:ceb_x_preferred":[
        "Tola"
    ],
    "name:deu_x_preferred":[
        "Tola"
    ],
    "name:fra_x_preferred":[
        "Tola"
    ],
    "name:ita_x_preferred":[
        "Tola"
    ],
    "name:nld_x_preferred":[
        "Tola"
    ],
    "name:pol_x_preferred":[
        "Tola"
    ],
    "name:por_x_preferred":[
        "Tola"
    ],
    "name:rus_x_preferred":[
        "\u0422\u043e\u043b\u0430"
    ],
    "name:spa_x_preferred":[
        "Tola"
    ],
    "name:swe_x_preferred":[
        "Tola"
    ],
    "name:ukr_x_preferred":[
        "\u0422\u043e\u043b\u0430"
    ],
    "name:vie_x_preferred":[
        "Tola"
    ],
    "wof:name":"Tola",
    "wof:placetype":"locality"
},
  "geometry": {"coordinates":[80.55159999999999,29.1962],"type":"Point"}
}