{
  "type": "Feature",
  "properties": {
    "gn:admin1_code":"ER",
    "gn:admin2_code":"13",
    "gn:admin3_code":"13.0",
    "gn:admin4_code":"130009.0",
    "gn:asciiname":"Jimigaun",
    "gn:country_code":"NP",
    "gn:dem":1075,
    "gn:feature_class":"P",
    "gn:feature_code":"PPLL",
    "gn:name":"Jimigaun",
    "gn:population":0,
    "gn:timezone":"Asia/Kathmandu",
    "iso:country":"NP",
    "wof:name":"Jimigaun",
    "wof:placetype":"locality"
},
  "geometry": {"coordinates":[86.81742,26.99145],"type":"Point"}
}