{
  "type": "Feature",
  "properties": {
    "gn:admin1_code":"FR",
    "gn:admin2_code":"14",
    "gn:admin3_code":"70.0",
    "gn:admin4_code":"700048.0",
    "gn:asciiname":"Khadsain",
    "gn:country_code":"NP",
    "gn:dem":1893,
    "gn:feature_class":"P",
    "gn:feature_code":"PPLL",
    "gn:name":"Khadsain",
    "gn:population":0,
    "gn:timezone":"Asia/Kathmandu",
    "iso:country":"NP",
    "wof:name":"Khadsain",
    "wof:placetype":"locality"
},
  "geometry": {"coordinates":[80.98668000000001,29.12412],"type":"Point"}
}