{
  "type": "Feature",
  "properties": {
    "gn:admin1_code":"CR",
    "gn:admin2_code":"5",
    "gn:admin3_code":"20",
    "gn:admin4_code":"200026",
    "gn:asciiname":"Lamibagar",
    "gn:country_code":"NP",
    "gn:dem":491,
    "gn:feature_class":"P",
    "gn:feature_code":"PPLL",
    "gn:name":"Lamibagar",
    "gn:population":0,
    "gn:timezone":"Asia/Kathmandu",
    "iso:country":"NP",
    "wof:name":"Lamibagar",
    "wof:placetype":"locality"
},
  "geometry": {"coordinates":[85.6024,27.34254],"type":"Point"}
}