{
  "type": "Feature",
  "properties": {
    "gn:admin1_code":"ER",
    "gn:admin2_code":"7",
    "gn:admin3_code":"5",
    "gn:admin4_code":"50010",
    "gn:asciiname":"Jamunabari",
    "gn:country_code":"NP",
    "gn:dem":130,
    "gn:feature_class":"P",
    "gn:feature_code":"PPLL",
    "gn:name":"Jamunabari",
    "gn:population":0,
    "gn:timezone":"Asia/Kathmandu",
    "iso:country":"NP",
    "wof:name":"Jamunabari",
    "wof:placetype":"locality"
},
  "geometry": {"coordinates":[87.43544,26.64368],"type":"Point"}
}