{
  "type": "Feature",
  "properties": {
    "gn:admin1_code":"WR",
    "gn:admin2_code":"3",
    "gn:admin3_code":"45",
    "gn:admin4_code":"450060",
    "gn:asciiname":"Korikholagaun",
    "gn:country_code":"NP",
    "gn:dem":1029,
    "gn:feature_class":"P",
    "gn:feature_code":"PPLL",
    "gn:name":"Korikholagaun",
    "gn:population":0,
    "gn:timezone":"Asia/Kathmandu",
    "iso:country":"NP",
    "wof:name":"Korikholagaun",
    "wof:placetype":"locality"
},
  "geometry": {"coordinates":[83.54895,28.26272],"type":"Point"}
}