{
  "type": "Feature",
  "properties": {
    "gn:admin1_code":"MR",
    "gn:admin2_code":"12",
    "gn:admin3_code":"55",
    "gn:admin4_code":"550015",
    "gn:asciiname":"Ashwa",
    "gn:country_code":"NP",
    "gn:dem":1185,
    "gn:feature_class":"P",
    "gn:feature_code":"PPLL",
    "gn:name":"Ashwa",
    "gn:population":0,
    "gn:timezone":"Asia/Kathmandu",
    "iso:country":"NP",
    "wof:name":"Ashwa",
    "wof:placetype":"locality"
},
  "geometry": {"coordinates":[82.16933,28.33236],"type":"Point"}
}