{
  "type": "Feature",
  "properties": {
    "gn:admin1_code":"ER",
    "gn:admin2_code":"13",
    "gn:admin3_code":"11",
    "gn:admin4_code":"110001",
    "gn:asciiname":"Solaban",
    "gn:country_code":"NP",
    "gn:dem":2066,
    "gn:feature_class":"P",
    "gn:feature_code":"PPLL",
    "gn:name":"Solaban",
    "gn:population":0,
    "gn:timezone":"Asia/Kathmandu",
    "iso:country":"NP",
    "wof:name":"Solaban",
    "wof:placetype":"locality"
},
  "geometry": {"coordinates":[86.7552,27.55084],"type":"Point"}
}