{
  "type": "Feature",
  "properties": {
    "gn:admin1_code":"CR",
    "gn:admin2_code":"1",
    "gn:admin3_code":"28",
    "gn:admin4_code":"280004",
    "gn:asciiname":"Amare",
    "gn:country_code":"NP",
    "gn:dem":933,
    "gn:feature_class":"P",
    "gn:feature_code":"PPLL",
    "gn:name":"Amare",
    "gn:population":0,
    "gn:timezone":"Asia/Kathmandu",
    "iso:country":"NP",
    "name:ita_x_preferred":[
        "Amare"
    ],
    "wof:name":"Amare",
    "wof:placetype":"locality"
},
  "geometry": {"coordinates":[85.15477,27.83148],"type":"Point"}
}