{
  "type": "Feature",
  "properties": {
    "gn:admin1_code":"MR",
    "gn:admin2_code":"6",
    "gn:admin3_code":"65",
    "gn:admin4_code":"650015",
    "gn:asciiname":"Pulu",
    "gn:country_code":"NP",
    "gn:dem":2333,
    "gn:feature_class":"P",
    "gn:feature_code":"PPLL",
    "gn:name":"Pulu",
    "gn:population":0,
    "gn:timezone":"Asia/Kathmandu",
    "iso:country":"NP",
    "name:fra_x_preferred":[
        "Pulu"
    ],
    "name:mai_x_preferred":[
        "\u092a\u0941\u0932\u0942"
    ],
    "name:msa_x_preferred":[
        "Pulu"
    ],
    "name:nep_x_preferred":[
        "\u092a\u0941\u0932\u0942"
    ],
    "name:new_x_preferred":[
        "\u092a\u0941\u0932\u0941"
    ],
    "name:pol_x_preferred":[
        "Pulu"
    ],
    "wof:name":"Pulu",
    "wof:placetype":"locality"
},
  "geometry": {"coordinates":[82.4014,29.58027],"type":"Point"}
}