{
  "type": "Feature",
  "properties": {
    "gn:admin1_code":"WR",
    "gn:admin2_code":"4",
    "gn:admin3_code":"36.0",
    "gn:admin4_code":"360002.0",
    "gn:asciiname":"Ghorpani",
    "gn:country_code":"NP",
    "gn:dem":1114,
    "gn:feature_class":"P",
    "gn:feature_code":"PPLL",
    "gn:name":"Ghorpani",
    "gn:population":0,
    "gn:timezone":"Asia/Kathmandu",
    "iso:country":"NP",
    "wof:name":"Ghorpani",
    "wof:placetype":"locality"
},
  "geometry": {"coordinates":[84.80242,28.10036],"type":"Point"}
}