{
  "type": "Feature",
  "properties": {
    "gn:admin1_code":"WR",
    "gn:admin2_code":"4.0",
    "gn:admin3_code":"39.0",
    "gn:admin4_code":"390027.0",
    "gn:asciiname":"Dhuni",
    "gn:country_code":"NP",
    "gn:dem":1205,
    "gn:feature_class":"P",
    "gn:feature_code":"PPLL",
    "gn:name":"Dhuni",
    "gn:population":0,
    "gn:timezone":"Asia/Kathmandu",
    "iso:country":"NP",
    "wof:name":"Dhuni",
    "wof:placetype":"locality"
},
  "geometry": {"coordinates":[83.78885,27.94288],"type":"Point"}
}