{
  "type": "Feature",
  "properties": {
    "gn:admin1_code":"CR",
    "gn:admin2_code":"5",
    "gn:admin3_code":"22.0",
    "gn:admin4_code":"220022.0",
    "gn:asciiname":"Kagate",
    "gn:country_code":"NP",
    "gn:dem":2332,
    "gn:feature_class":"P",
    "gn:feature_code":"PPLL",
    "gn:name":"Kagate",
    "gn:population":0,
    "gn:timezone":"Asia/Kathmandu",
    "iso:country":"NP",
    "wof:name":"Kagate",
    "wof:placetype":"locality"
},
  "geometry": {"coordinates":[86.13094,27.57588],"type":"Point"}
}