{
  "type": "Feature",
  "properties": {
    "gn:admin1_code":"ER",
    "gn:admin2_code":"7",
    "gn:admin3_code":"10.0",
    "gn:admin4_code":"100031.0",
    "gn:asciiname":"Ambote",
    "gn:country_code":"NP",
    "gn:dem":997,
    "gn:feature_class":"P",
    "gn:feature_code":"PPLL",
    "gn:name":"Ambote",
    "gn:population":0,
    "gn:timezone":"Asia/Kathmandu",
    "iso:country":"NP",
    "wof:name":"Ambote",
    "wof:placetype":"locality"
},
  "geometry": {"coordinates":[87.15204,27.35608],"type":"Point"}
}