{
  "type": "Feature",
  "properties": {
    "gn:admin1_code":"FR",
    "gn:admin2_code":"9",
    "gn:admin3_code":"75.0",
    "gn:admin4_code":"750017.0",
    "gn:asciiname":"Nyaute",
    "gn:country_code":"NP",
    "gn:dem":1970,
    "gn:feature_class":"P",
    "gn:feature_code":"PPLL",
    "gn:name":"Nyaute",
    "gn:population":0,
    "gn:timezone":"Asia/Kathmandu",
    "iso:country":"NP",
    "wof:name":"Nyaute",
    "wof:placetype":"locality"
},
  "geometry": {"coordinates":[80.54935,29.73723],"type":"Point"}
}