{
  "type": "Feature",
  "properties": {
    "gn:admin1_code":"WR",
    "gn:admin2_code":"4",
    "gn:admin3_code":"36.0",
    "gn:admin4_code":"360047.0",
    "gn:asciiname":"Bhangeri",
    "gn:country_code":"NP",
    "gn:dem":574,
    "gn:feature_class":"P",
    "gn:feature_code":"PPLL",
    "gn:name":"Bhangeri",
    "gn:population":0,
    "gn:timezone":"Asia/Kathmandu",
    "iso:country":"NP",
    "wof:name":"Bhangeri",
    "wof:placetype":"locality"
},
  "geometry": {"coordinates":[84.52620999999998,28.02134],"type":"Point"}
}