{
  "type": "Feature",
  "properties": {
    "gn:admin1_code":"ER",
    "gn:admin2_code":"7",
    "gn:admin3_code":"5",
    "gn:admin4_code":"50043.0",
    "gn:asciiname":"Karaibona",
    "gn:country_code":"NP",
    "gn:dem":109,
    "gn:feature_class":"P",
    "gn:feature_code":"PPLL",
    "gn:name":"Karaibona",
    "gn:population":0,
    "gn:timezone":"Asia/Kathmandu",
    "iso:country":"NP",
    "wof:name":"Karaibona",
    "wof:placetype":"locality"
},
  "geometry": {"coordinates":[87.34700000000002,26.61773],"type":"Point"}
}