{
  "type": "Feature",
  "properties": {
    "gn:admin1_code":"00",
    "gn:asciiname":"Rinbutol",
    "gn:country_code":"NP",
    "gn:dem":762,
    "gn:feature_class":"P",
    "gn:feature_code":"PPL",
    "gn:name":"Ri\u1e45bu\u1e6dol",
    "gn:population":0,
    "gn:timezone":"Asia/Kathmandu",
    "iso:country":"NP",
    "name:nep_x_preferred":[
        "Ri\u1e45bu\u1e6dol"
    ],
    "wof:name":"Rinbutol",
    "wof:placetype":"locality"
},
  "geometry": {"coordinates":[87.23352,26.90121],"type":"Point"}
}