{
  "type": "Feature",
  "properties": {
    "gn:admin1_code":"FR",
    "gn:admin2_code":"14.0",
    "gn:admin3_code":"68.0",
    "gn:admin4_code":"680045.0",
    "gn:asciiname":"Suwakot",
    "gn:country_code":"NP",
    "gn:dem":1837,
    "gn:feature_class":"P",
    "gn:feature_code":"PPLL",
    "gn:name":"Suwakot",
    "gn:population":0,
    "gn:timezone":"Asia/Kathmandu",
    "iso:country":"NP",
    "wof:name":"Suwakot",
    "wof:placetype":"locality"
},
  "geometry": {"coordinates":[80.83865,29.50481],"type":"Point"}
}