{
  "type": "Feature",
  "properties": {
    "gn:admin1_code":"FR",
    "gn:admin2_code":"14",
    "gn:admin3_code":"68",
    "gn:admin4_code":"680014",
    "gn:asciiname":"Masta Temple",
    "gn:country_code":"NP",
    "gn:dem":2821,
    "gn:feature_class":"P",
    "gn:feature_code":"PPLL",
    "gn:name":"Masta Temple",
    "gn:population":0,
    "gn:timezone":"Asia/Kathmandu",
    "iso:country":"NP",
    "wof:name":"Masta Temple",
    "wof:placetype":"locality"
},
  "geometry": {"coordinates":[81.26862,29.65768],"type":"Point"}
}