{
  "type": "Feature",
  "properties": {
    "gn:admin1_code":"MR",
    "gn:admin2_code":"12",
    "gn:admin3_code":"55",
    "gn:admin4_code":"550015",
    "gn:asciiname":"Khairabang",
    "gn:country_code":"NP",
    "gn:dem":1585,
    "gn:feature_class":"P",
    "gn:feature_code":"PPLL",
    "gn:name":"Khairabang",
    "gn:population":0,
    "gn:timezone":"Asia/Kathmandu",
    "iso:country":"NP",
    "wof:name":"Khairabang",
    "wof:placetype":"locality"
},
  "geometry": {"coordinates":[82.17076999999998,28.34352],"type":"Point"}
}