{
  "type": "Feature",
  "properties": {
    "gn:admin1_code":"CR",
    "gn:admin2_code":"5",
    "gn:admin3_code":"20",
    "gn:admin4_code":"200040",
    "gn:asciiname":"Bhotekhola",
    "gn:country_code":"NP",
    "gn:dem":939,
    "gn:feature_class":"P",
    "gn:feature_code":"PPLL",
    "gn:name":"Bhotekhola",
    "gn:population":0,
    "gn:timezone":"Asia/Kathmandu",
    "iso:country":"NP",
    "wof:name":"Bhotekhola",
    "wof:placetype":"locality"
},
  "geometry": {"coordinates":[85.89804000000002,27.36668],"type":"Point"}
}