{
  "type": "Feature",
  "properties": {
    "gn:admin1_code":"CR",
    "gn:admin2_code":"1",
    "gn:admin3_code":"27.0",
    "gn:admin4_code":"270008.0",
    "gn:asciiname":"Phedigaun",
    "gn:country_code":"NP",
    "gn:dem":1700,
    "gn:feature_class":"P",
    "gn:feature_code":"PPLL",
    "gn:name":"Phedigaun",
    "gn:population":0,
    "gn:timezone":"Asia/Kathmandu",
    "iso:country":"NP",
    "wof:name":"Phedigaun",
    "wof:placetype":"locality"
},
  "geometry": {"coordinates":[85.37177,27.79309000000001],"type":"Point"}
}