{
  "type": "Feature",
  "properties": {
    "gn:admin1_code":"FR",
    "gn:admin2_code":"14",
    "gn:admin3_code":"71.0",
    "gn:admin4_code":"710010.0",
    "gn:asciiname":"Gauri Katan",
    "gn:country_code":"NP",
    "gn:dem":172,
    "gn:feature_class":"P",
    "gn:feature_code":"PPLL",
    "gn:name":"Gauri Katan",
    "gn:population":0,
    "gn:timezone":"Asia/Kathmandu",
    "iso:country":"NP",
    "wof:name":"Gauri Katan",
    "wof:placetype":"locality"
},
  "geometry": {"coordinates":[80.60833000000002,28.66349],"type":"Point"}
}