{
  "type": "Feature",
  "properties": {
    "gn:admin1_code":"CR",
    "gn:admin2_code":"5",
    "gn:admin3_code":"19",
    "gn:admin4_code":"190071",
    "gn:asciiname":"Mechchherang",
    "gn:country_code":"NP",
    "gn:dem":326,
    "gn:feature_class":"P",
    "gn:feature_code":"PPLL",
    "gn:name":"Mechchherang",
    "gn:population":0,
    "gn:timezone":"Asia/Kathmandu",
    "iso:country":"NP",
    "wof:name":"Mechchherang",
    "wof:placetype":"locality"
},
  "geometry": {"coordinates":[85.66164000000001,27.15328],"type":"Point"}
}