{
  "type": "Feature",
  "properties": {
    "gn:admin1_code":"MR",
    "gn:admin2_code":"6",
    "gn:admin3_code":"63.0",
    "gn:admin4_code":"630022.0",
    "gn:asciiname":"Rapu",
    "gn:country_code":"NP",
    "gn:dem":3370,
    "gn:feature_class":"P",
    "gn:feature_code":"PPLL",
    "gn:name":"Rapu",
    "gn:population":0,
    "gn:timezone":"Asia/Kathmandu",
    "iso:country":"NP",
    "wof:name":"Rapu",
    "wof:placetype":"locality"
},
  "geometry": {"coordinates":[82.00135,29.19167],"type":"Point"}
}