{
  "type": "Feature",
  "properties": {
    "gn:admin1_code":"WR",
    "gn:admin2_code":"8",
    "gn:admin3_code":"47",
    "gn:admin4_code":"470004",
    "gn:asciiname":"Chidipani",
    "gn:country_code":"NP",
    "gn:dem":979,
    "gn:feature_class":"P",
    "gn:feature_code":"PPLL",
    "gn:name":"Chidipani",
    "gn:population":0,
    "gn:timezone":"Asia/Kathmandu",
    "iso:country":"NP",
    "name:ceb_x_preferred":[
        "Chidipani"
    ],
    "name:hin_x_preferred":[
        "\u091a\u093f\u0926\u093f\u092a\u093e\u0928\u0940"
    ],
    "name:msa_x_preferred":[
        "Chidipani"
    ],
    "name:nep_x_preferred":[
        "\u091a\u093f\u0926\u093f\u092a\u093e\u0928\u0940"
    ],
    "name:new_x_preferred":[
        "\u091a\u093f\u0921\u093f\u092a\u093e\u0928\u0940"
    ],
    "name:pol_x_preferred":[
        "Chidipani"
    ],
    "wof:name":"Chidipani",
    "wof:placetype":"locality"
},
  "geometry": {"coordinates":[83.30785,27.77457],"type":"Point"}
}