{
  "type": "Feature",
  "properties": {
    "gn:admin1_code":"MR",
    "gn:admin2_code":"12",
    "gn:admin3_code":"53",
    "gn:admin4_code":"530005",
    "gn:asciiname":"Gapa",
    "gn:country_code":"NP",
    "gn:dem":1713,
    "gn:feature_class":"P",
    "gn:feature_code":"PPLL",
    "gn:name":"Gapa",
    "gn:population":0,
    "gn:timezone":"Asia/Kathmandu",
    "iso:country":"NP",
    "name:bul_x_preferred":[
        "\u0413\u0430\u043f\u0430"
    ],
    "name:ceb_x_preferred":[
        "Gapa"
    ],
    "name:pol_x_preferred":[
        "Gapa"
    ],
    "name:swe_x_preferred":[
        "Gapa"
    ],
    "wof:name":"Gapa",
    "wof:placetype":"locality"
},
  "geometry": {"coordinates":[82.664,28.36824],"type":"Point"}
}