{
  "type": "Feature",
  "properties": {
    "gn:admin1_code":"MR",
    "gn:admin2_code":"2.0",
    "gn:admin3_code":"57.0",
    "gn:admin4_code":"570003.0",
    "gn:asciiname":"Molbipurwa",
    "gn:country_code":"NP",
    "gn:dem":145,
    "gn:feature_class":"P",
    "gn:feature_code":"PPLL",
    "gn:name":"Molbipurwa",
    "gn:population":0,
    "gn:timezone":"Asia/Kathmandu",
    "iso:country":"NP",
    "wof:name":"Molbipurwa",
    "wof:placetype":"locality"
},
  "geometry": {"coordinates":[81.69503,28.0386],"type":"Point"}
}