{
  "type": "Feature",
  "properties": {
    "gn:admin1_code":"MR",
    "gn:admin2_code":"2.0",
    "gn:admin3_code":"59.0",
    "gn:admin4_code":"590042.0",
    "gn:asciiname":"Rithabot",
    "gn:country_code":"NP",
    "gn:dem":1012,
    "gn:feature_class":"P",
    "gn:feature_code":"PPLL",
    "gn:name":"Rithabot",
    "gn:population":0,
    "gn:timezone":"Asia/Kathmandu",
    "iso:country":"NP",
    "wof:name":"Rithabot",
    "wof:placetype":"locality"
},
  "geometry": {"coordinates":[82.00471,28.50572],"type":"Point"}
}