{
  "type": "Feature",
  "properties": {
    "gn:admin1_code":"FR",
    "gn:admin2_code":"14",
    "gn:admin3_code":"71.0",
    "gn:admin4_code":"710040.0",
    "gn:asciiname":"Pateri Banjha",
    "gn:country_code":"NP",
    "gn:dem":342,
    "gn:feature_class":"P",
    "gn:feature_code":"PPLL",
    "gn:name":"Pateri Banjha",
    "gn:population":0,
    "gn:timezone":"Asia/Kathmandu",
    "iso:country":"NP",
    "wof:name":"Pateri Banjha",
    "wof:placetype":"locality"
},
  "geometry": {"coordinates":[81.19062,28.78569],"type":"Point"}
}