{
  "type": "Feature",
  "properties": {
    "gn:admin1_code":"MR",
    "gn:admin2_code":"2.0",
    "gn:admin3_code":"59.0",
    "gn:admin4_code":"590046.0",
    "gn:asciiname":"Majuwa Khet",
    "gn:country_code":"NP",
    "gn:dem":659,
    "gn:feature_class":"P",
    "gn:feature_code":"PPLL",
    "gn:name":"Majuwa Khet",
    "gn:population":0,
    "gn:timezone":"Asia/Kathmandu",
    "iso:country":"NP",
    "wof:name":"Majuwa Khet",
    "wof:placetype":"locality"
},
  "geometry": {"coordinates":[81.90183,28.37723],"type":"Point"}
}