{
  "type": "Feature",
  "properties": {
    "gn:admin1_code":"ER",
    "gn:admin2_code":"13.0",
    "gn:admin3_code":"14.0",
    "gn:admin4_code":"140044.0",
    "gn:asciiname":"Dharapani",
    "gn:country_code":"NP",
    "gn:dem":1351,
    "gn:feature_class":"P",
    "gn:feature_code":"PPLL",
    "gn:name":"Dharapani",
    "gn:population":0,
    "gn:timezone":"Asia/Kathmandu",
    "iso:country":"NP",
    "name:fra_x_preferred":[
        "Dharapani"
    ],
    "name:new_x_preferred":[
        "\u0927\u093e\u0930\u093e\u092a\u093e\u0928\u0940"
    ],
    "name:pol_x_preferred":[
        "Dharapani"
    ],
    "wof:name":"Dharapani",
    "wof:placetype":"locality"
},
  "geometry": {"coordinates":[86.58556999999998,26.95128],"type":"Point"}
}