{
  "type": "Feature",
  "properties": {
    "gn:admin1_code":"WR",
    "gn:admin2_code":"4.0",
    "gn:admin3_code":"39.0",
    "gn:admin4_code":"390061.0",
    "gn:asciiname":"Sahudanda",
    "gn:country_code":"NP",
    "gn:dem":1235,
    "gn:feature_class":"P",
    "gn:feature_code":"PPLL",
    "gn:name":"Sahudanda",
    "gn:population":0,
    "gn:timezone":"Asia/Kathmandu",
    "iso:country":"NP",
    "wof:name":"Sahudanda",
    "wof:placetype":"locality"
},
  "geometry": {"coordinates":[83.77623,28.17501],"type":"Point"}
}