{
  "type": "Feature",
  "properties": {
    "gn:admin1_code":"CR",
    "gn:admin2_code":"5",
    "gn:admin3_code":"20",
    "gn:admin4_code":"200034",
    "gn:asciiname":"Ranmane",
    "gn:country_code":"NP",
    "gn:dem":554,
    "gn:feature_class":"P",
    "gn:feature_code":"PPLL",
    "gn:name":"Ranmane",
    "gn:population":0,
    "gn:timezone":"Asia/Kathmandu",
    "iso:country":"NP",
    "wof:name":"Ranmane",
    "wof:placetype":"locality"
},
  "geometry": {"coordinates":[85.75140999999998,27.28374],"type":"Point"}
}