{
  "type": "Feature",
  "properties": {
    "gn:admin1_code":"WR",
    "gn:admin2_code":"4.0",
    "gn:admin3_code":"39.0",
    "gn:admin4_code":"390034.0",
    "gn:asciiname":"Inaskot",
    "gn:country_code":"NP",
    "gn:dem":1019,
    "gn:feature_class":"P",
    "gn:feature_code":"PPLL",
    "gn:name":"Inaskot",
    "gn:population":0,
    "gn:timezone":"Asia/Kathmandu",
    "iso:country":"NP",
    "wof:name":"Inaskot",
    "wof:placetype":"locality"
},
  "geometry": {"coordinates":[83.83804000000001,27.94263],"type":"Point"}
}