{
  "type": "Feature",
  "properties": {
    "gn:admin1_code":"CR",
    "gn:admin2_code":"1",
    "gn:admin3_code":"25",
    "gn:admin4_code":"250004",
    "gn:asciiname":"Kalche",
    "gn:country_code":"NP",
    "gn:dem":1132,
    "gn:feature_class":"P",
    "gn:feature_code":"PPLL",
    "gn:name":"Kalche",
    "gn:population":0,
    "gn:timezone":"Asia/Kathmandu",
    "iso:country":"NP",
    "wof:name":"Kalche",
    "wof:placetype":"locality"
},
  "geometry": {"coordinates":[85.27901,27.49292],"type":"Point"}
}