{
  "type": "Feature",
  "properties": {
    "gn:admin1_code":"00",
    "gn:asciiname":"Bhandari",
    "gn:country_code":"NP",
    "gn:dem":872,
    "gn:feature_class":"P",
    "gn:feature_code":"PPL",
    "gn:name":"Bhand\u0101ri",
    "gn:population":0,
    "gn:timezone":"Asia/Kathmandu",
    "iso:country":"NP",
    "name:nep_x_preferred":[
        "\u092d\u0923\u094d\u0921\u093e\u0930\u0940"
    ],
    "wof:name":"Bhandari",
    "wof:placetype":"locality"
},
  "geometry": {"coordinates":[80.33178000000002,29.26513],"type":"Point"}
}