{
  "type": "Feature",
  "properties": {
    "gn:admin1_code":"ER",
    "gn:admin2_code":"13",
    "gn:admin3_code":"12",
    "gn:admin4_code":"120022",
    "gn:asciiname":"Devithan",
    "gn:country_code":"NP",
    "gn:dem":1668,
    "gn:feature_class":"P",
    "gn:feature_code":"PPLL",
    "gn:name":"Devithan",
    "gn:population":0,
    "gn:timezone":"Asia/Kathmandu",
    "iso:country":"NP",
    "wof:name":"Devithan",
    "wof:placetype":"locality"
},
  "geometry": {"coordinates":[86.47676,27.24366],"type":"Point"}
}