{
  "type": "Feature",
  "properties": {
    "gn:admin1_code":"FR",
    "gn:admin2_code":"9",
    "gn:admin3_code":"75.0",
    "gn:admin4_code":"750004.0",
    "gn:asciiname":"Sitapul",
    "gn:country_code":"NP",
    "gn:dem":2823,
    "gn:feature_class":"P",
    "gn:feature_code":"PPLL",
    "gn:name":"Sitapul",
    "gn:population":0,
    "gn:timezone":"Asia/Kathmandu",
    "iso:country":"NP",
    "wof:name":"Sitapul",
    "wof:placetype":"locality"
},
  "geometry": {"coordinates":[80.8745,30.12606],"type":"Point"}
}