{
  "type": "Feature",
  "properties": {
    "gn:admin1_code":"MR",
    "gn:admin2_code":"12",
    "gn:admin3_code":"56.0",
    "gn:admin4_code":"560041.0",
    "gn:asciiname":"Jhamariya",
    "gn:country_code":"NP",
    "gn:dem":570,
    "gn:feature_class":"P",
    "gn:feature_code":"PPLL",
    "gn:name":"Jhamariya",
    "gn:population":0,
    "gn:timezone":"Asia/Kathmandu",
    "iso:country":"NP",
    "wof:name":"Jhamariya",
    "wof:placetype":"locality"
},
  "geometry": {"coordinates":[82.23416999999998,28.05907],"type":"Point"}
}