{
  "type": "Feature",
  "properties": {
    "gn:admin1_code":"ER",
    "gn:admin2_code":"7",
    "gn:admin3_code":"5",
    "gn:admin4_code":"50002.0",
    "gn:asciiname":"Baraltol",
    "gn:country_code":"NP",
    "gn:dem":91,
    "gn:feature_class":"P",
    "gn:feature_code":"PPLL",
    "gn:name":"Baraltol",
    "gn:population":0,
    "gn:timezone":"Asia/Kathmandu",
    "iso:country":"NP",
    "wof:name":"Baraltol",
    "wof:placetype":"locality"
},
  "geometry": {"coordinates":[87.57174000000001,26.55288],"type":"Point"}
}