{
  "type": "Feature",
  "properties": {
    "gn:admin1_code":"MR",
    "gn:admin2_code":"6",
    "gn:admin3_code":"64.0",
    "gn:admin4_code":"640022.0",
    "gn:asciiname":"Khote",
    "gn:country_code":"NP",
    "gn:dem":1222,
    "gn:feature_class":"P",
    "gn:feature_code":"PPLL",
    "gn:name":"Khote",
    "gn:population":0,
    "gn:timezone":"Asia/Kathmandu",
    "iso:country":"NP",
    "wof:name":"Khote",
    "wof:placetype":"locality"
},
  "geometry": {"coordinates":[81.62166999999999,29.23811],"type":"Point"}
}