{
  "type": "Feature",
  "properties": {
    "gn:admin1_code":"CR",
    "gn:admin2_code":"5",
    "gn:admin3_code":"20",
    "gn:admin4_code":"200042",
    "gn:asciiname":"Tangsar",
    "gn:country_code":"NP",
    "gn:dem":904,
    "gn:feature_class":"P",
    "gn:feature_code":"PPLL",
    "gn:name":"Tangsar",
    "gn:population":0,
    "gn:timezone":"Asia/Kathmandu",
    "iso:country":"NP",
    "wof:name":"Tangsar",
    "wof:placetype":"locality"
},
  "geometry": {"coordinates":[86.00763000000001,27.20162],"type":"Point"}
}