{
  "type": "Feature",
  "properties": {
    "gn:admin1_code":"FR",
    "gn:admin2_code":"9",
    "gn:admin3_code":"72.0",
    "gn:admin4_code":"720008.0",
    "gn:asciiname":"Dashrathbasti",
    "gn:country_code":"NP",
    "gn:dem":184,
    "gn:feature_class":"P",
    "gn:feature_code":"PPLL",
    "gn:name":"Dashrathbasti",
    "gn:population":0,
    "gn:timezone":"Asia/Kathmandu",
    "iso:country":"NP",
    "wof:name":"Dashrathbasti",
    "wof:placetype":"locality"
},
  "geometry": {"coordinates":[80.44821,28.68062],"type":"Point"}
}