{
  "type": "Feature",
  "properties": {
    "gn:admin1_code":"FR",
    "gn:admin2_code":"9",
    "gn:admin3_code":"74",
    "gn:admin4_code":"740042",
    "gn:asciiname":"Bitkam",
    "gn:country_code":"NP",
    "gn:dem":971,
    "gn:feature_class":"P",
    "gn:feature_code":"PPLL",
    "gn:name":"Bitkam",
    "gn:population":0,
    "gn:timezone":"Asia/Kathmandu",
    "iso:country":"NP",
    "wof:name":"Bitkam",
    "wof:placetype":"locality"
},
  "geometry": {"coordinates":[80.48588000000002,29.61039],"type":"Point"}
}