{
  "type": "Feature",
  "properties": {
    "gn:admin1_code":"FR",
    "gn:admin2_code":"14",
    "gn:admin3_code":"71.0",
    "gn:admin4_code":"710016.0",
    "gn:asciiname":"Manikapur",
    "gn:country_code":"NP",
    "gn:dem":158,
    "gn:feature_class":"P",
    "gn:feature_code":"PPLL",
    "gn:name":"Manikapur",
    "gn:population":0,
    "gn:timezone":"Asia/Kathmandu",
    "iso:country":"NP",
    "wof:name":"Manikapur",
    "wof:placetype":"locality"
},
  "geometry": {"coordinates":[80.82474999999999,28.55834],"type":"Point"}
}