{
  "type": "Feature",
  "properties": {
    "gn:admin1_code":"CR",
    "gn:admin2_code":"11",
    "gn:admin3_code":"35.0",
    "gn:admin4_code":"350031.0",
    "gn:asciiname":"Simara",
    "gn:country_code":"NP",
    "gn:dem":242,
    "gn:feature_class":"P",
    "gn:feature_code":"PPLL",
    "gn:name":"Simara",
    "gn:population":0,
    "gn:timezone":"Asia/Kathmandu",
    "iso:country":"NP",
    "wof:name":"Simara",
    "wof:placetype":"locality"
},
  "geometry": {"coordinates":[84.69653000000002,27.5803],"type":"Point"}
}