{
  "type": "Feature",
  "properties": {
    "gn:admin1_code":"ER",
    "gn:admin2_code":"13",
    "gn:admin3_code":"11",
    "gn:admin4_code":"110018.0",
    "gn:asciiname":"Tabuche Goth",
    "gn:country_code":"NP",
    "gn:dem":4422,
    "gn:feature_class":"P",
    "gn:feature_code":"PPLL",
    "gn:name":"Tabuche Goth",
    "gn:population":0,
    "gn:timezone":"Asia/Kathmandu",
    "iso:country":"NP",
    "wof:name":"Tabuche Goth",
    "wof:placetype":"locality"
},
  "geometry": {"coordinates":[86.78856,27.8687],"type":"Point"}
}