{
  "type": "Feature",
  "properties": {
    "gn:admin1_code":"MR",
    "gn:admin2_code":"6",
    "gn:admin3_code":"62.0",
    "gn:admin4_code":"620015.0",
    "gn:asciiname":"Sanduwa",
    "gn:country_code":"NP",
    "gn:dem":3302,
    "gn:feature_class":"P",
    "gn:feature_code":"PPLL",
    "gn:name":"Sanduwa",
    "gn:population":0,
    "gn:timezone":"Asia/Kathmandu",
    "iso:country":"NP",
    "wof:name":"Sanduwa",
    "wof:placetype":"locality"
},
  "geometry": {"coordinates":[82.8948,29.13839],"type":"Point"}
}