{
  "type": "Feature",
  "properties": {
    "gn:admin1_code":"FR",
    "gn:admin2_code":"9",
    "gn:admin3_code":"72.0",
    "gn:admin4_code":"720009.0",
    "gn:asciiname":"Gunyalphanta",
    "gn:country_code":"NP",
    "gn:dem":206,
    "gn:feature_class":"P",
    "gn:feature_code":"PPLL",
    "gn:name":"Gunyalphanta",
    "gn:population":0,
    "gn:timezone":"Asia/Kathmandu",
    "iso:country":"NP",
    "wof:name":"Gunyalphanta",
    "wof:placetype":"locality"
},
  "geometry": {"coordinates":[80.39926,28.87568],"type":"Point"}
}