{
  "type": "Feature",
  "properties": {
    "gn:admin1_code":"CR",
    "gn:admin2_code":"5",
    "gn:admin3_code":"21",
    "gn:admin4_code":"210009",
    "gn:asciiname":"Tallo Chankhu",
    "gn:country_code":"NP",
    "gn:dem":979,
    "gn:feature_class":"P",
    "gn:feature_code":"PPLL",
    "gn:name":"Tallo Chankhu",
    "gn:population":0,
    "gn:timezone":"Asia/Kathmandu",
    "iso:country":"NP",
    "wof:name":"Tallo Chankhu",
    "wof:placetype":"locality"
},
  "geometry": {"coordinates":[86.05228000000002,27.44311],"type":"Point"}
}