{
  "type": "Feature",
  "properties": {
    "gn:admin1_code":"ER",
    "gn:admin2_code":"13",
    "gn:admin3_code":"11",
    "gn:admin4_code":"110024.0",
    "gn:asciiname":"Singkorab",
    "gn:country_code":"NP",
    "gn:dem":5865,
    "gn:feature_class":"P",
    "gn:feature_code":"PPLL",
    "gn:name":"Singkorab",
    "gn:population":0,
    "gn:timezone":"Asia/Kathmandu",
    "iso:country":"NP",
    "wof:name":"Singkorab",
    "wof:placetype":"locality"
},
  "geometry": {"coordinates":[86.55221999999998,27.92896],"type":"Point"}
}