{
  "type": "Feature",
  "properties": {
    "gn:admin1_code":"ER",
    "gn:admin2_code":"7",
    "gn:admin3_code":"5",
    "gn:admin4_code":"50060",
    "gn:asciiname":"Rachana",
    "gn:country_code":"NP",
    "gn:dem":232,
    "gn:feature_class":"P",
    "gn:feature_code":"PPLL",
    "gn:name":"Rachana",
    "gn:population":0,
    "gn:timezone":"Asia/Kathmandu",
    "iso:country":"NP",
    "wof:name":"Rachana",
    "wof:placetype":"locality"
},
  "geometry": {"coordinates":[87.6605,26.76889000000001],"type":"Point"}
}