{
  "type": "Feature",
  "properties": {
    "gn:admin1_code":"ER",
    "gn:admin2_code":"13",
    "gn:admin3_code":"12",
    "gn:admin4_code":"120047",
    "gn:asciiname":"Dandakharka",
    "gn:country_code":"NP",
    "gn:dem":1600,
    "gn:feature_class":"P",
    "gn:feature_code":"PPLL",
    "gn:name":"Dandakharka",
    "gn:population":0,
    "gn:timezone":"Asia/Kathmandu",
    "iso:country":"NP",
    "name:pol_x_preferred":[
        "Dandakharka"
    ],
    "wof:name":"Dandakharka",
    "wof:placetype":"locality"
},
  "geometry": {"coordinates":[86.43029,27.37872],"type":"Point"}
}