{
  "type": "Feature",
  "properties": {
    "gn:admin1_code":"ER",
    "gn:admin2_code":"13",
    "gn:admin3_code":"15",
    "gn:admin4_code":"150097",
    "gn:asciiname":"Lilajatol",
    "gn:country_code":"NP",
    "gn:dem":86,
    "gn:feature_class":"P",
    "gn:feature_code":"PPLL",
    "gn:name":"Lilajatol",
    "gn:population":0,
    "gn:timezone":"Asia/Kathmandu",
    "iso:country":"NP",
    "wof:name":"Lilajatol",
    "wof:placetype":"locality"
},
  "geometry": {"coordinates":[86.74417,26.53195],"type":"Point"}
}