{
  "type": "Feature",
  "properties": {
    "gn:admin1_code":"CR",
    "gn:admin2_code":"11",
    "gn:admin3_code":"31",
    "gn:admin4_code":"310040",
    "gn:asciiname":"Deutakhola Thali",
    "gn:country_code":"NP",
    "gn:dem":505,
    "gn:feature_class":"P",
    "gn:feature_code":"PPLL",
    "gn:name":"Deutakhola Thali",
    "gn:population":0,
    "gn:timezone":"Asia/Kathmandu",
    "iso:country":"NP",
    "wof:name":"Deutakhola Thali",
    "wof:placetype":"locality"
},
  "geometry": {"coordinates":[85.22001,27.35706],"type":"Point"}
}