{
  "type": "Feature",
  "properties": {
    "gn:admin1_code":"ER",
    "gn:admin2_code":"13",
    "gn:admin3_code":"13.0",
    "gn:admin4_code":"130029.0",
    "gn:asciiname":"Atmara",
    "gn:country_code":"NP",
    "gn:dem":920,
    "gn:feature_class":"P",
    "gn:feature_code":"PPLL",
    "gn:name":"Atmara",
    "gn:population":0,
    "gn:timezone":"Asia/Kathmandu",
    "iso:country":"NP",
    "wof:name":"Atmara",
    "wof:placetype":"locality"
},
  "geometry": {"coordinates":[86.70184,27.29584],"type":"Point"}
}