{
  "type": "Feature",
  "properties": {
    "gn:admin1_code":"WR",
    "gn:admin2_code":"3",
    "gn:admin3_code":"45.0",
    "gn:admin4_code":"450024.0",
    "gn:asciiname":"Thum",
    "gn:country_code":"NP",
    "gn:dem":1319,
    "gn:feature_class":"P",
    "gn:feature_code":"PPLL",
    "gn:name":"Thum",
    "gn:population":0,
    "gn:timezone":"Asia/Kathmandu",
    "iso:country":"NP",
    "wof:name":"Thum",
    "wof:placetype":"locality"
},
  "geometry": {"coordinates":[83.53686999999999,28.13001],"type":"Point"}
}