{
  "type": "Feature",
  "properties": {
    "gn:admin1_code":"ER",
    "gn:admin2_code":"10",
    "gn:admin3_code":"2",
    "gn:admin4_code":"20041",
    "gn:asciiname":"Bhadaure",
    "gn:country_code":"NP",
    "gn:dem":1374,
    "gn:feature_class":"P",
    "gn:feature_code":"PPLL",
    "gn:name":"Bhadaure",
    "gn:population":0,
    "gn:timezone":"Asia/Kathmandu",
    "iso:country":"NP",
    "name:pol_x_preferred":[
        "Bhadaure"
    ],
    "wof:name":"Bhadaure",
    "wof:placetype":"locality"
},
  "geometry": {"coordinates":[87.62679,27.05593],"type":"Point"}
}