{
  "type": "Feature",
  "properties": {
    "gn:admin1_code":"WR",
    "gn:admin2_code":"8",
    "gn:admin3_code":"51.0",
    "gn:admin4_code":"510004.0",
    "gn:asciiname":"Asurkot",
    "gn:country_code":"NP",
    "gn:dem":978,
    "gn:feature_class":"P",
    "gn:feature_code":"PPLL",
    "gn:name":"Asurkot",
    "gn:population":0,
    "gn:timezone":"Asia/Kathmandu",
    "iso:country":"NP",
    "name:ceb_x_preferred":[
        "Asurkot"
    ],
    "name:fra_x_preferred":[
        "Asurkot"
    ],
    "name:mai_x_preferred":[
        "\u0905\u0938\u0941\u0930\u0915\u094b\u091f"
    ],
    "name:msa_x_preferred":[
        "Asurkot"
    ],
    "name:nep_x_preferred":[
        "\u0905\u0938\u0941\u0930\u0915\u094b\u091f"
    ],
    "name:new_x_preferred":[
        "\u0905\u0938\u0941\u0930\u0915\u094b\u091f"
    ],
    "name:pol_x_preferred":[
        "Asurkot"
    ],
    "wof:name":"Asurkot",
    "wof:placetype":"locality"
},
  "geometry": {"coordinates":[82.99339000000001,28.0053],"type":"Point"}
}