{
  "type": "Feature",
  "properties": {
    "gn:admin1_code":"WR",
    "gn:admin2_code":"8",
    "gn:admin3_code":"51.0",
    "gn:admin4_code":"510004.0",
    "gn:asciiname":"Asurkot",
    "gn:country_code":"NP",
    "gn:dem":978,
    "gn:feature_class":"P",
    "gn:feature_code":"PPLL",
    "gn:name":"Asurkot",
    "gn:population":0,
    "gn:timezone":"Asia/Kathmandu",
    "iso:country":"NP",
    "wof:name":"Asurkot",
    "wof:placetype":"locality"
},
  "geometry": {"coordinates":[82.99339000000001,28.0053],"type":"Point"}
}