{
  "type": "Feature",
  "properties": {
    "gn:admin1_code":"CR",
    "gn:admin2_code":"11",
    "gn:admin3_code":"32",
    "gn:admin4_code":"320033",
    "gn:asciiname":"Kudawa",
    "gn:country_code":"NP",
    "gn:dem":77,
    "gn:feature_class":"P",
    "gn:feature_code":"PPLL",
    "gn:name":"Kudawa",
    "gn:population":0,
    "gn:timezone":"Asia/Kathmandu",
    "iso:country":"NP",
    "name:ceb_x_preferred":[
        "Kudawa"
    ],
    "name:fra_x_preferred":[
        "Kudawa"
    ],
    "name:msa_x_preferred":[
        "Kudawa"
    ],
    "name:nep_x_preferred":[
        "\u0915\u0941\u0921\u0935\u093e"
    ],
    "name:new_x_preferred":[
        "\u0915\u0941\u0921\u0935\u093e"
    ],
    "name:pol_x_preferred":[
        "Kudawa"
    ],
    "wof:name":"Kudawa",
    "wof:placetype":"locality"
},
  "geometry": {"coordinates":[85.28579000000001,26.77432],"type":"Point"}
}