{
  "type": "Feature",
  "properties": {
    "gn:admin1_code":"WR",
    "gn:admin2_code":"8",
    "gn:admin3_code":"47",
    "gn:admin4_code":"470034",
    "gn:asciiname":"Singdure",
    "gn:country_code":"NP",
    "gn:dem":468,
    "gn:feature_class":"P",
    "gn:feature_code":"PPLL",
    "gn:name":"Singdure",
    "gn:population":0,
    "gn:timezone":"Asia/Kathmandu",
    "iso:country":"NP",
    "wof:name":"Singdure",
    "wof:placetype":"locality"
},
  "geometry": {"coordinates":[83.84031,27.73422],"type":"Point"}
}