{
  "type": "Feature",
  "properties": {
    "gn:admin1_code":"FR",
    "gn:admin2_code":"14.0",
    "gn:admin3_code":"69.0",
    "gn:admin4_code":"690045.0",
    "gn:asciiname":"Gail (Gandsil)",
    "gn:country_code":"NP",
    "gn:dem":1103,
    "gn:feature_class":"P",
    "gn:feature_code":"PPLL",
    "gn:name":"Gail (Gandsil)",
    "gn:population":0,
    "gn:timezone":"Asia/Kathmandu",
    "iso:country":"NP",
    "wof:name":"Gail (Gandsil)",
    "wof:placetype":"locality"
},
  "geometry": {"coordinates":[81.15034,29.22014],"type":"Point"}
}