{
  "type": "Feature",
  "properties": {
    "gn:admin1_code":"WR",
    "gn:admin2_code":"8",
    "gn:admin3_code":"47",
    "gn:admin4_code":"470049",
    "gn:asciiname":"Talla Bari",
    "gn:country_code":"NP",
    "gn:dem":1146,
    "gn:feature_class":"P",
    "gn:feature_code":"PPLL",
    "gn:name":"Talla Bari",
    "gn:population":0,
    "gn:timezone":"Asia/Kathmandu",
    "iso:country":"NP",
    "wof:name":"Talla Bari",
    "wof:placetype":"locality"
},
  "geometry": {"coordinates":[83.4177,27.87721],"type":"Point"}
}