{
  "type": "Feature",
  "properties": {
    "gn:admin1_code":"FR",
    "gn:admin2_code":"14",
    "gn:admin3_code":"69.0",
    "gn:admin4_code":"690073.0",
    "gn:asciiname":"Turmakhand",
    "gn:country_code":"NP",
    "gn:dem":1393,
    "gn:feature_class":"P",
    "gn:feature_code":"PPLL",
    "gn:name":"Turmakhand",
    "gn:population":0,
    "gn:timezone":"Asia/Kathmandu",
    "iso:country":"NP",
    "wof:name":"Turmakhand",
    "wof:placetype":"locality"
},
  "geometry": {"coordinates":[81.37084,28.94605],"type":"Point"}
}