{
  "type": "Feature",
  "properties": {
    "gn:admin1_code":"MR",
    "gn:admin2_code":"2",
    "gn:admin3_code":"60.0",
    "gn:admin4_code":"600024.0",
    "gn:asciiname":"Pachtola",
    "gn:country_code":"NP",
    "gn:dem":1812,
    "gn:feature_class":"P",
    "gn:feature_code":"PPLL",
    "gn:name":"Pachtola",
    "gn:population":0,
    "gn:timezone":"Asia/Kathmandu",
    "iso:country":"NP",
    "wof:name":"Pachtola",
    "wof:placetype":"locality"
},
  "geometry": {"coordinates":[81.83104,28.76069],"type":"Point"}
}