{
  "type": "Feature",
  "properties": {
    "gn:admin1_code":"ER",
    "gn:admin2_code":"7",
    "gn:admin3_code":"9",
    "gn:admin4_code":"90016",
    "gn:asciiname":"Rambeni",
    "gn:country_code":"NP",
    "gn:dem":699,
    "gn:feature_class":"P",
    "gn:feature_code":"PPLL",
    "gn:name":"Rambeni",
    "gn:population":0,
    "gn:timezone":"Asia/Kathmandu",
    "iso:country":"NP",
    "wof:name":"Rambeni",
    "wof:placetype":"locality"
},
  "geometry": {"coordinates":[87.33618,27.26723],"type":"Point"}
}