{
  "type": "Feature",
  "properties": {
    "gn:admin1_code":"MR",
    "gn:admin2_code":"2",
    "gn:admin3_code":"61.0",
    "gn:admin4_code":"610008.0",
    "gn:asciiname":"Syaltara",
    "gn:country_code":"NP",
    "gn:dem":2011,
    "gn:feature_class":"P",
    "gn:feature_code":"PPLL",
    "gn:name":"Syaltara",
    "gn:population":0,
    "gn:timezone":"Asia/Kathmandu",
    "iso:country":"NP",
    "wof:name":"Syaltara",
    "wof:placetype":"locality"
},
  "geometry": {"coordinates":[82.03196,28.87529],"type":"Point"}
}