{
  "type": "Feature",
  "properties": {
    "gn:admin1_code":"CR",
    "gn:admin2_code":"5",
    "gn:admin3_code":"22.0",
    "gn:admin4_code":"220035.0",
    "gn:asciiname":"Lapilang",
    "gn:country_code":"NP",
    "gn:dem":2007,
    "gn:feature_class":"P",
    "gn:feature_code":"PPLL",
    "gn:name":"Lapilang",
    "gn:population":0,
    "gn:timezone":"Asia/Kathmandu",
    "iso:country":"NP",
    "name:bih_x_preferred":[
        "\u0932\u093e\u092a\u093f\u0932\u093e\u0919"
    ],
    "name:ceb_x_preferred":[
        "Lapilang"
    ],
    "name:mai_x_preferred":[
        "\u0932\u093e\u092a\u093f\u0932\u093e\u0919"
    ],
    "name:msa_x_preferred":[
        "Lapilang"
    ],
    "name:nep_x_preferred":[
        "\u0932\u093e\u092a\u093f\u0932\u093e\u0919"
    ],
    "name:new_x_preferred":[
        "\u0932\u093e\u092a\u093f\u0932\u093e\u0919\u094d\u0917"
    ],
    "name:pol_x_preferred":[
        "Lapilang"
    ],
    "name:urd_x_preferred":[
        "\u0644\u0627\u067e\u06cc\u0644\u0627\u0646\u06af"
    ],
    "wof:name":"Lapilang",
    "wof:placetype":"locality"
},
  "geometry": {"coordinates":[86.1101,27.74951],"type":"Point"}
}