{
  "type": "Feature",
  "properties": {
    "gn:admin1_code":"FR",
    "gn:admin2_code":"14",
    "gn:admin3_code":"70.0",
    "gn:admin4_code":"700028.0",
    "gn:asciiname":"Birkhet Kharka",
    "gn:country_code":"NP",
    "gn:dem":1962,
    "gn:feature_class":"P",
    "gn:feature_code":"PPLL",
    "gn:name":"Birkhet Kharka",
    "gn:population":0,
    "gn:timezone":"Asia/Kathmandu",
    "iso:country":"NP",
    "wof:name":"Birkhet Kharka",
    "wof:placetype":"locality"
},
  "geometry": {"coordinates":[80.95055000000001,29.34637],"type":"Point"}
}