{
  "type": "Feature",
  "properties": {
    "gn:admin1_code":"CR",
    "gn:admin2_code":"1",
    "gn:admin3_code":"28",
    "gn:admin4_code":"280048",
    "gn:asciiname":"Samari Bhanjyang",
    "gn:country_code":"NP",
    "gn:dem":1373,
    "gn:feature_class":"P",
    "gn:feature_code":"PPLL",
    "gn:name":"Samari Bhanjyang",
    "gn:population":0,
    "gn:timezone":"Asia/Kathmandu",
    "iso:country":"NP",
    "wof:name":"Samari Bhanjyang",
    "wof:placetype":"locality"
},
  "geometry": {"coordinates":[85.05060999999998,27.94969],"type":"Point"}
}