{
  "type": "Feature",
  "properties": {
    "gn:admin1_code":"WR",
    "gn:admin2_code":"8",
    "gn:admin3_code":"47",
    "gn:admin4_code":"470032",
    "gn:asciiname":"Thumsardanda",
    "gn:country_code":"NP",
    "gn:dem":1087,
    "gn:feature_class":"P",
    "gn:feature_code":"PPLL",
    "gn:name":"Thumsardanda",
    "gn:population":0,
    "gn:timezone":"Asia/Kathmandu",
    "iso:country":"NP",
    "wof:name":"Thumsardanda",
    "wof:placetype":"locality"
},
  "geometry": {"coordinates":[83.95310000000001,27.7901],"type":"Point"}
}