{
  "type": "Feature",
  "properties": {
    "gn:admin1_code":"ER",
    "gn:admin2_code":"10",
    "gn:admin3_code":"3.0",
    "gn:admin4_code":"30035.0",
    "gn:asciiname":"Kopche",
    "gn:country_code":"NP",
    "gn:dem":1252,
    "gn:feature_class":"P",
    "gn:feature_code":"PPLL",
    "gn:name":"Kopche",
    "gn:population":0,
    "gn:timezone":"Asia/Kathmandu",
    "iso:country":"NP",
    "wof:name":"Kopche",
    "wof:placetype":"locality"
},
  "geometry": {"coordinates":[87.72886,26.94666],"type":"Point"}
}