{
  "type": "Feature",
  "properties": {
    "gn:admin1_code":"FR",
    "gn:admin2_code":"14",
    "gn:admin3_code":"69.0",
    "gn:admin4_code":"690067.0",
    "gn:asciiname":"Patalchaur",
    "gn:country_code":"NP",
    "gn:dem":634,
    "gn:feature_class":"P",
    "gn:feature_code":"PPLL",
    "gn:name":"Patalchaur",
    "gn:population":0,
    "gn:timezone":"Asia/Kathmandu",
    "iso:country":"NP",
    "wof:name":"Patalchaur",
    "wof:placetype":"locality"
},
  "geometry": {"coordinates":[81.05202,29.16786],"type":"Point"}
}