{
  "type": "Feature",
  "properties": {
    "gn:admin1_code":"FR",
    "gn:admin2_code":"9",
    "gn:admin3_code":"73.0",
    "gn:admin4_code":"730004.0",
    "gn:asciiname":"Saukharka",
    "gn:country_code":"NP",
    "gn:dem":2002,
    "gn:feature_class":"P",
    "gn:feature_code":"PPLL",
    "gn:name":"Saukharka",
    "gn:population":0,
    "gn:timezone":"Asia/Kathmandu",
    "iso:country":"NP",
    "wof:name":"Saukharka",
    "wof:placetype":"locality"
},
  "geometry": {"coordinates":[80.62598,29.21274],"type":"Point"}
}