{
  "type": "Feature",
  "properties": {
    "gn:admin1_code":"MR",
    "gn:admin2_code":"12",
    "gn:admin3_code":"53",
    "gn:admin4_code":"530022",
    "gn:asciiname":"Riyale",
    "gn:country_code":"NP",
    "gn:dem":1081,
    "gn:feature_class":"P",
    "gn:feature_code":"PPLL",
    "gn:name":"Riyale",
    "gn:population":0,
    "gn:timezone":"Asia/Kathmandu",
    "iso:country":"NP",
    "wof:name":"Riyale",
    "wof:placetype":"locality"
},
  "geometry": {"coordinates":[82.42231,28.20086],"type":"Point"}
}