{
  "type": "Feature",
  "properties": {
    "gn:admin1_code":"ER",
    "gn:admin2_code":"13",
    "gn:admin3_code":"11",
    "gn:admin4_code":"110026",
    "gn:asciiname":"Necha",
    "gn:country_code":"NP",
    "gn:dem":1382,
    "gn:feature_class":"P",
    "gn:feature_code":"PPLL",
    "gn:name":"Necha",
    "gn:population":0,
    "gn:timezone":"Asia/Kathmandu",
    "iso:country":"NP",
    "name:ceb_x_preferred":[
        "Necha"
    ],
    "name:mai_x_preferred":[
        "\u0928\u0947\u091a\u093e"
    ],
    "name:msa_x_preferred":[
        "Necha"
    ],
    "name:new_x_preferred":[
        "\u0928\u0947\u091a\u093e"
    ],
    "name:pol_x_preferred":[
        "Necha"
    ],
    "wof:name":"Necha",
    "wof:placetype":"locality"
},
  "geometry": {"coordinates":[86.65169,27.35584],"type":"Point"}
}