{
  "type": "Feature",
  "properties": {
    "gn:admin1_code":"ER",
    "gn:admin2_code":"10",
    "gn:admin3_code":"2",
    "gn:admin4_code":"20035",
    "gn:asciiname":"Nakale",
    "gn:country_code":"NP",
    "gn:dem":2056,
    "gn:feature_class":"P",
    "gn:feature_code":"PPLL",
    "gn:name":"Nakale",
    "gn:population":0,
    "gn:timezone":"Asia/Kathmandu",
    "iso:country":"NP",
    "wof:name":"Nakale",
    "wof:placetype":"locality"
},
  "geometry": {"coordinates":[87.88209999999999,27.16452],"type":"Point"}
}