{
  "type": "Feature",
  "properties": {
    "gn:admin1_code":"WR",
    "gn:admin2_code":"4.0",
    "gn:admin3_code":"38.0",
    "gn:admin4_code":"380015.0",
    "gn:asciiname":"Dudhekuna",
    "gn:country_code":"NP",
    "gn:dem":674,
    "gn:feature_class":"P",
    "gn:feature_code":"PPLL",
    "gn:name":"Dudhekuna",
    "gn:population":0,
    "gn:timezone":"Asia/Kathmandu",
    "iso:country":"NP",
    "wof:name":"Dudhekuna",
    "wof:placetype":"locality"
},
  "geometry": {"coordinates":[84.41582,28.11433],"type":"Point"}
}