{
  "type": "Feature",
  "properties": {
    "gn:admin1_code":"00",
    "gn:asciiname":"Kusma",
    "gn:country_code":"NP",
    "gn:dem":985,
    "gn:elevation":"880.0",
    "gn:feature_class":"P",
    "gn:feature_code":"PPL",
    "gn:name":"Kusma",
    "gn:population":0,
    "gn:timezone":"Asia/Kathmandu",
    "iso:country":"NP",
    "wof:name":"Kusma",
    "wof:placetype":"locality"
},
  "geometry": {"coordinates":[83.68259999999999,28.22266],"type":"Point"}
}