{
  "type": "Feature",
  "properties": {
    "gn:admin1_code":"FR",
    "gn:admin2_code":"9",
    "gn:admin3_code":"75.0",
    "gn:admin4_code":"750029.0",
    "gn:asciiname":"Bijaypur",
    "gn:country_code":"NP",
    "gn:dem":1634,
    "gn:feature_class":"P",
    "gn:feature_code":"PPLL",
    "gn:name":"Bijaypur",
    "gn:population":0,
    "gn:timezone":"Asia/Kathmandu",
    "iso:country":"NP",
    "wof:name":"Bijaypur",
    "wof:placetype":"locality"
},
  "geometry": {"coordinates":[80.58292,29.89889],"type":"Point"}
}