{
  "type": "Feature",
  "properties": {
    "gn:admin1_code":"ER",
    "gn:admin2_code":"13.0",
    "gn:admin3_code":"14.0",
    "gn:admin4_code":"140018.0",
    "gn:asciiname":"Bharle",
    "gn:country_code":"NP",
    "gn:dem":682,
    "gn:feature_class":"P",
    "gn:feature_code":"PPLL",
    "gn:name":"Bharle",
    "gn:population":0,
    "gn:timezone":"Asia/Kathmandu",
    "iso:country":"NP",
    "name:ara_x_preferred":[
        "\u0628\u0627\u0631\u0644\u064a"
    ],
    "name:fra_x_preferred":[
        "Bharte"
    ],
    "name:mai_x_preferred":[
        "\u092d\u093e\u0930\u094d\u0924\u0947"
    ],
    "name:nep_x_preferred":[
        "\u092d\u093e\u0930\u094d\u0924\u0947"
    ],
    "name:pol_x_preferred":[
        "Bharte"
    ],
    "wof:name":"Bharle",
    "wof:placetype":"locality"
},
  "geometry": {"coordinates":[87.07469,26.85428],"type":"Point"}
}