{
  "type": "Feature",
  "properties": {
    "gn:admin1_code":"WR",
    "gn:admin2_code":"4",
    "gn:admin3_code":"36.0",
    "gn:admin4_code":"360016.0",
    "gn:asciiname":"Badghere",
    "gn:country_code":"NP",
    "gn:dem":693,
    "gn:feature_class":"P",
    "gn:feature_code":"PPLL",
    "gn:name":"Badghere",
    "gn:population":0,
    "gn:timezone":"Asia/Kathmandu",
    "iso:country":"NP",
    "wof:name":"Badghere",
    "wof:placetype":"locality"
},
  "geometry": {"coordinates":[84.45743,27.98303],"type":"Point"}
}