{
  "type": "Feature",
  "properties": {
    "gn:admin1_code":"CR",
    "gn:admin2_code":"5",
    "gn:admin3_code":"20",
    "gn:admin4_code":"200032",
    "gn:asciiname":"Bajhagaun",
    "gn:country_code":"NP",
    "gn:dem":774,
    "gn:feature_class":"P",
    "gn:feature_code":"PPLL",
    "gn:name":"Bajhagaun",
    "gn:population":0,
    "gn:timezone":"Asia/Kathmandu",
    "iso:country":"NP",
    "wof:name":"Bajhagaun",
    "wof:placetype":"locality"
},
  "geometry": {"coordinates":[86.1627,27.09341],"type":"Point"}
}