{
  "type": "Feature",
  "properties": {
    "gn:admin1_code":"FR",
    "gn:admin2_code":"14",
    "gn:admin3_code":"70.0",
    "gn:admin4_code":"700013.0",
    "gn:asciiname":"Kala Patal",
    "gn:country_code":"NP",
    "gn:dem":573,
    "gn:feature_class":"P",
    "gn:feature_code":"PPLL",
    "gn:name":"Kala Patal",
    "gn:population":0,
    "gn:timezone":"Asia/Kathmandu",
    "iso:country":"NP",
    "wof:name":"Kala Patal",
    "wof:placetype":"locality"
},
  "geometry": {"coordinates":[80.9517,29.26396],"type":"Point"}
}