{
  "type": "Feature",
  "properties": {
    "gn:admin1_code":"MR",
    "gn:admin2_code":"12",
    "gn:admin3_code":"56.0",
    "gn:admin4_code":"560021.0",
    "gn:asciiname":"Bhitreekholagaun",
    "gn:country_code":"NP",
    "gn:dem":897,
    "gn:feature_class":"P",
    "gn:feature_code":"PPLL",
    "gn:name":"Bhitreekholagaun",
    "gn:population":0,
    "gn:timezone":"Asia/Kathmandu",
    "iso:country":"NP",
    "wof:name":"Bhitreekholagaun",
    "wof:placetype":"locality"
},
  "geometry": {"coordinates":[82.64874,27.97601],"type":"Point"}
}