{
  "type": "Feature",
  "properties": {
    "gn:admin1_code":"00",
    "gn:asciiname":"Dalegau",
    "gn:country_code":"NP",
    "gn:dem":315,
    "gn:feature_class":"P",
    "gn:feature_code":"PPL",
    "gn:name":"\u1e0c\u0101leg\u0101\u016b",
    "gn:population":0,
    "gn:timezone":"Asia/Kathmandu",
    "iso:country":"NP",
    "name:nep_x_preferred":[
        "\u1e0c\u0101leg\u0101\u016b"
    ],
    "wof:name":"Dalegau",
    "wof:placetype":"locality"
},
  "geometry": {"coordinates":[87.37770999999999,26.7634],"type":"Point"}
}