{
  "type": "Feature",
  "properties": {
    "gn:admin1_code":"ER",
    "gn:admin2_code":"10",
    "gn:admin3_code":"3.0",
    "gn:admin4_code":"30007.0",
    "gn:asciiname":"Golatar",
    "gn:country_code":"NP",
    "gn:dem":164,
    "gn:feature_class":"P",
    "gn:feature_code":"PPLL",
    "gn:name":"Golatar",
    "gn:population":0,
    "gn:timezone":"Asia/Kathmandu",
    "iso:country":"NP",
    "wof:name":"Golatar",
    "wof:placetype":"locality"
},
  "geometry": {"coordinates":[87.87526,26.7641],"type":"Point"}
}