{
  "type": "Feature",
  "properties": {
    "gn:admin1_code":"ER",
    "gn:admin2_code":"13",
    "gn:admin3_code":"12",
    "gn:admin4_code":"120037",
    "gn:asciiname":"Hilechhap",
    "gn:country_code":"NP",
    "gn:dem":615,
    "gn:feature_class":"P",
    "gn:feature_code":"PPLL",
    "gn:name":"Hilechhap",
    "gn:population":0,
    "gn:timezone":"Asia/Kathmandu",
    "iso:country":"NP",
    "wof:name":"Hilechhap",
    "wof:placetype":"locality"
},
  "geometry": {"coordinates":[86.66986999999997,27.31132],"type":"Point"}
}