{
  "type": "Feature",
  "properties": {
    "gn:admin1_code":"00",
    "gn:asciiname":"Gyalthun",
    "gn:country_code":"NP",
    "gn:dem":1478,
    "gn:feature_class":"P",
    "gn:feature_code":"PPL",
    "gn:name":"Gy\u0101lthu\u1e45",
    "gn:population":0,
    "gn:timezone":"Asia/Kathmandu",
    "iso:country":"NP",
    "name:nep_x_preferred":[
        "Gy\u0101lthu\u1e45"
    ],
    "wof:name":"Gyalthun",
    "wof:placetype":"locality"
},
  "geometry": {"coordinates":[85.52734,27.87633],"type":"Point"}
}