{
  "type": "Feature",
  "properties": {
    "gn:admin1_code":"WR",
    "gn:admin2_code":"4",
    "gn:admin3_code":"37",
    "gn:admin4_code":"370037",
    "gn:asciiname":"Bansarbesi",
    "gn:country_code":"NP",
    "gn:dem":939,
    "gn:feature_class":"P",
    "gn:feature_code":"PPLL",
    "gn:name":"Bansarbesi",
    "gn:population":0,
    "gn:timezone":"Asia/Kathmandu",
    "iso:country":"NP",
    "wof:name":"Bansarbesi",
    "wof:placetype":"locality"
},
  "geometry": {"coordinates":[84.5667,28.13265],"type":"Point"}
}