{
  "type": "Feature",
  "properties": {
    "gn:admin1_code":"00",
    "gn:asciiname":"Dagitola",
    "gn:country_code":"NP",
    "gn:dem":77,
    "gn:feature_class":"P",
    "gn:feature_code":"PPL",
    "gn:name":"\u1e0c\u0101\u0303gi\u0307\u0304\u1e6dol\u0101",
    "gn:population":0,
    "gn:timezone":"Asia/Kathmandu",
    "iso:country":"NP",
    "name:nep_x_preferred":[
        "\u1e0c\u0101\u0303gi\u0307\u0304\u1e6dol\u0101"
    ],
    "wof:name":"Dagitola",
    "wof:placetype":"locality"
},
  "geometry": {"coordinates":[87.69131999999998,26.43877],"type":"Point"}
}