{
  "type": "Feature",
  "properties": {
    "gn:admin1_code":"MR",
    "gn:admin2_code":"6",
    "gn:admin3_code":"62.0",
    "gn:admin4_code":"620016.0",
    "gn:asciiname":"Rahagaun",
    "gn:country_code":"NP",
    "gn:dem":3159,
    "gn:feature_class":"P",
    "gn:feature_code":"PPLL",
    "gn:name":"Rahagaun",
    "gn:population":0,
    "gn:timezone":"Asia/Kathmandu",
    "iso:country":"NP",
    "wof:name":"Rahagaun",
    "wof:placetype":"locality"
},
  "geometry": {"coordinates":[82.92274,29.0083],"type":"Point"}
}