{
  "type": "Feature",
  "properties": {
    "gn:admin1_code":"ER",
    "gn:admin2_code":"7",
    "gn:admin3_code":"10.0",
    "gn:admin4_code":"100019.0",
    "gn:asciiname":"Kolchaur",
    "gn:country_code":"NP",
    "gn:dem":849,
    "gn:feature_class":"P",
    "gn:feature_code":"PPLL",
    "gn:name":"Kolchaur",
    "gn:population":0,
    "gn:timezone":"Asia/Kathmandu",
    "iso:country":"NP",
    "wof:name":"Kolchaur",
    "wof:placetype":"locality"
},
  "geometry": {"coordinates":[87.16208,27.30075],"type":"Point"}
}