{
  "type": "Feature",
  "properties": {
    "gn:admin1_code":"FR",
    "gn:admin2_code":"9",
    "gn:admin3_code":"74",
    "gn:admin4_code":"740051",
    "gn:asciiname":"Rautegaun",
    "gn:country_code":"NP",
    "gn:dem":2198,
    "gn:feature_class":"P",
    "gn:feature_code":"PPLL",
    "gn:name":"Rautegaun",
    "gn:population":0,
    "gn:timezone":"Asia/Kathmandu",
    "iso:country":"NP",
    "wof:name":"Rautegaun",
    "wof:placetype":"locality"
},
  "geometry": {"coordinates":[80.66107,29.49729],"type":"Point"}
}