{
  "type": "Feature",
  "properties": {
    "gn:admin1_code":"WR",
    "gn:admin2_code":"4",
    "gn:admin3_code":"36.0",
    "gn:admin4_code":"360047.0",
    "gn:asciiname":"Kumalgaun",
    "gn:country_code":"NP",
    "gn:dem":587,
    "gn:feature_class":"P",
    "gn:feature_code":"PPLL",
    "gn:name":"Kumalgaun",
    "gn:population":0,
    "gn:timezone":"Asia/Kathmandu",
    "iso:country":"NP",
    "wof:name":"Kumalgaun",
    "wof:placetype":"locality"
},
  "geometry": {"coordinates":[84.4949,28.04679],"type":"Point"}
}