{
  "type": "Feature",
  "properties": {
    "gn:admin1_code":"CR",
    "gn:admin2_code":"5",
    "gn:admin3_code":"19",
    "gn:admin4_code":"190076",
    "gn:asciiname":"Sano Phuljor",
    "gn:country_code":"NP",
    "gn:dem":402,
    "gn:feature_class":"P",
    "gn:feature_code":"PPLL",
    "gn:name":"Sano Phuljor",
    "gn:population":0,
    "gn:timezone":"Asia/Kathmandu",
    "iso:country":"NP",
    "wof:name":"Sano Phuljor",
    "wof:placetype":"locality"
},
  "geometry": {"coordinates":[85.76595999999998,27.12962000000001],"type":"Point"}
}