{
  "type": "Feature",
  "properties": {
    "gn:admin1_code":"ER",
    "gn:admin2_code":"10",
    "gn:admin3_code":"3.0",
    "gn:admin4_code":"30045.0",
    "gn:asciiname":"Panchami Bhanjyang",
    "gn:country_code":"NP",
    "gn:dem":1262,
    "gn:feature_class":"P",
    "gn:feature_code":"PPLL",
    "gn:name":"Panchami Bhanjyang",
    "gn:population":0,
    "gn:timezone":"Asia/Kathmandu",
    "iso:country":"NP",
    "wof:name":"Panchami Bhanjyang",
    "wof:placetype":"locality"
},
  "geometry": {"coordinates":[87.84584,26.87536],"type":"Point"}
}