{
  "type": "Feature",
  "properties": {
    "gn:admin1_code":"MR",
    "gn:admin2_code":"6",
    "gn:admin3_code":"65",
    "gn:admin4_code":"650003",
    "gn:asciiname":"Patrali",
    "gn:country_code":"NP",
    "gn:dem":6198,
    "gn:feature_class":"P",
    "gn:feature_code":"PPLL",
    "gn:name":"Patrali",
    "gn:population":0,
    "gn:timezone":"Asia/Kathmandu",
    "iso:country":"NP",
    "wof:name":"Patrali",
    "wof:placetype":"locality"
},
  "geometry": {"coordinates":[82.59188,29.42362],"type":"Point"}
}