{
  "type": "Feature",
  "properties": {
    "gn:admin1_code":"00",
    "gn:asciiname":"Netadurling",
    "gn:country_code":"NP",
    "gn:dem":1735,
    "gn:feature_class":"P",
    "gn:feature_code":"PPL",
    "gn:name":"Netadurling",
    "gn:population":0,
    "gn:timezone":"Asia/Kathmandu",
    "iso:country":"NP",
    "wof:name":"Netadurling",
    "wof:placetype":"locality"
},
  "geometry": {"coordinates":[83.15598,28.24398],"type":"Point"}
}