{
  "type": "Feature",
  "properties": {
    "gn:admin1_code":"WR",
    "gn:admin2_code":"8",
    "gn:admin3_code":"46.0",
    "gn:admin4_code":"460071.0",
    "gn:asciiname":"Dobanseraphant",
    "gn:country_code":"NP",
    "gn:dem":1180,
    "gn:feature_class":"P",
    "gn:feature_code":"PPLL",
    "gn:name":"Dobanseraphant",
    "gn:population":0,
    "gn:timezone":"Asia/Kathmandu",
    "iso:country":"NP",
    "wof:name":"Dobanseraphant",
    "wof:placetype":"locality"
},
  "geometry": {"coordinates":[83.42326,28.10792],"type":"Point"}
}