{
  "type": "Feature",
  "properties": {
    "gn:admin1_code":"MR",
    "gn:admin2_code":"6",
    "gn:admin3_code":"64.0",
    "gn:admin4_code":"640014.0",
    "gn:asciiname":"Bhitrikholagaun",
    "gn:country_code":"NP",
    "gn:dem":2007,
    "gn:feature_class":"P",
    "gn:feature_code":"PPLL",
    "gn:name":"Bhitrikholagaun",
    "gn:population":0,
    "gn:timezone":"Asia/Kathmandu",
    "iso:country":"NP",
    "wof:name":"Bhitrikholagaun",
    "wof:placetype":"locality"
},
  "geometry": {"coordinates":[81.54524000000001,29.07266],"type":"Point"}
}