{
  "type": "Feature",
  "properties": {
    "gn:admin1_code":"FR",
    "gn:admin2_code":"9",
    "gn:admin3_code":"75.0",
    "gn:admin4_code":"750023.0",
    "gn:asciiname":"Kasauti",
    "gn:country_code":"NP",
    "gn:dem":2660,
    "gn:feature_class":"P",
    "gn:feature_code":"PPLL",
    "gn:name":"Kasauti",
    "gn:population":0,
    "gn:timezone":"Asia/Kathmandu",
    "iso:country":"NP",
    "name:ind_x_preferred":[
        "Kasauti"
    ],
    "name:mar_x_preferred":[
        "\u0915\u0938\u094c\u091f\u0940"
    ],
    "name:new_x_preferred":[
        "\u0915\u0938\u094c\u091f\u0940"
    ],
    "wof:name":"Kasauti",
    "wof:placetype":"locality"
},
  "geometry": {"coordinates":[80.9636,29.79762],"type":"Point"}
}