{
  "type": "Feature",
  "properties": {
    "gn:admin1_code":"MR",
    "gn:admin2_code":"6",
    "gn:admin3_code":"64.0",
    "gn:admin4_code":"640005.0",
    "gn:asciiname":"Rima Jiulo",
    "gn:country_code":"NP",
    "gn:dem":1815,
    "gn:feature_class":"P",
    "gn:feature_code":"PPLL",
    "gn:name":"Rima Jiulo",
    "gn:population":0,
    "gn:timezone":"Asia/Kathmandu",
    "iso:country":"NP",
    "wof:name":"Rima Jiulo",
    "wof:placetype":"locality"
},
  "geometry": {"coordinates":[81.78898000000002,29.34707],"type":"Point"}
}