{
  "type": "Feature",
  "properties": {
    "gn:admin1_code":"MR",
    "gn:admin2_code":"12",
    "gn:admin3_code":"54",
    "gn:admin4_code":"540016",
    "gn:asciiname":"Jhula",
    "gn:country_code":"NP",
    "gn:dem":1053,
    "gn:feature_class":"P",
    "gn:feature_code":"PPLL",
    "gn:name":"Jhula",
    "gn:population":0,
    "gn:timezone":"Asia/Kathmandu",
    "iso:country":"NP",
    "wof:name":"Jhula",
    "wof:placetype":"locality"
},
  "geometry": {"coordinates":[82.45616,28.68293],"type":"Point"}
}