{
  "type": "Feature",
  "properties": {
    "gn:admin1_code":"CR",
    "gn:admin2_code":"5",
    "gn:admin3_code":"20",
    "gn:admin4_code":"200054",
    "gn:asciiname":"Khadkidanda",
    "gn:country_code":"NP",
    "gn:dem":1406,
    "gn:feature_class":"P",
    "gn:feature_code":"PPLL",
    "gn:name":"Khadkidanda",
    "gn:population":0,
    "gn:timezone":"Asia/Kathmandu",
    "iso:country":"NP",
    "wof:name":"Khadkidanda",
    "wof:placetype":"locality"
},
  "geometry": {"coordinates":[86.22957,27.11504],"type":"Point"}
}