{
  "type": "Feature",
  "properties": {
    "gn:admin1_code":"WR",
    "gn:admin2_code":"4",
    "gn:admin3_code":"37",
    "gn:admin4_code":"370022",
    "gn:asciiname":"Upallo Koiralaphat",
    "gn:country_code":"NP",
    "gn:dem":884,
    "gn:feature_class":"P",
    "gn:feature_code":"PPLL",
    "gn:name":"Upallo Koiralaphat",
    "gn:population":0,
    "gn:timezone":"Asia/Kathmandu",
    "iso:country":"NP",
    "wof:name":"Upallo Koiralaphat",
    "wof:placetype":"locality"
},
  "geometry": {"coordinates":[84.32163,28.15442],"type":"Point"}
}