{
  "type": "Feature",
  "properties": {
    "gn:admin1_code":"MR",
    "gn:admin2_code":"12",
    "gn:admin3_code":"55",
    "gn:admin4_code":"550044",
    "gn:asciiname":"Sadanmuda",
    "gn:country_code":"NP",
    "gn:dem":1213,
    "gn:feature_class":"P",
    "gn:feature_code":"PPLL",
    "gn:name":"Sadanmuda",
    "gn:population":0,
    "gn:timezone":"Asia/Kathmandu",
    "iso:country":"NP",
    "wof:name":"Sadanmuda",
    "wof:placetype":"locality"
},
  "geometry": {"coordinates":[82.14303000000002,28.58555],"type":"Point"}
}