{
  "type": "Feature",
  "properties": {
    "gn:admin1_code":"CR",
    "gn:admin2_code":"1",
    "gn:admin3_code":"23",
    "gn:admin4_code":"230050",
    "gn:asciiname":"Kainale",
    "gn:country_code":"NP",
    "gn:dem":1804,
    "gn:feature_class":"P",
    "gn:feature_code":"PPLL",
    "gn:name":"Kainale",
    "gn:population":0,
    "gn:timezone":"Asia/Kathmandu",
    "iso:country":"NP",
    "wof:name":"Kainale",
    "wof:placetype":"locality"
},
  "geometry": {"coordinates":[85.62728,27.8231],"type":"Point"}
}