{
  "type": "Feature",
  "properties": {
    "gn:admin1_code":"CR",
    "gn:admin2_code":"5",
    "gn:admin3_code":"22.0",
    "gn:admin4_code":"220020.0",
    "gn:asciiname":"Lamidanda",
    "gn:country_code":"NP",
    "gn:dem":2030,
    "gn:feature_class":"P",
    "gn:feature_code":"PPLL",
    "gn:name":"Lamidanda",
    "gn:population":0,
    "gn:timezone":"Asia/Kathmandu",
    "iso:country":"NP",
    "name:jpn_x_preferred":[
        "\u30e9\u30df\u30c0\u30f3\u30c0"
    ],
    "name:pol_x_preferred":[
        "Lamidada"
    ],
    "wof:name":"Lamidanda",
    "wof:placetype":"locality"
},
  "geometry": {"coordinates":[86.15574000000002,27.58065],"type":"Point"}
}