{
  "type": "Feature",
  "properties": {
    "gn:admin1_code":"ER",
    "gn:admin2_code":"10",
    "gn:admin3_code":"3.0",
    "gn:admin4_code":"30031.0",
    "gn:asciiname":"Malim",
    "gn:country_code":"NP",
    "gn:dem":1112,
    "gn:feature_class":"P",
    "gn:feature_code":"PPLL",
    "gn:name":"Malim",
    "gn:population":0,
    "gn:timezone":"Asia/Kathmandu",
    "iso:country":"NP",
    "wof:name":"Malim",
    "wof:placetype":"locality"
},
  "geometry": {"coordinates":[88.04756999999999,26.8617],"type":"Point"}
}