{
  "type": "Feature",
  "properties": {
    "gn:admin1_code":"CR",
    "gn:admin2_code":"11.0",
    "gn:admin3_code":"33.0",
    "gn:admin4_code":"330086.0",
    "gn:asciiname":"Rampur",
    "gn:country_code":"NP",
    "gn:dem":98,
    "gn:feature_class":"P",
    "gn:feature_code":"PPLL",
    "gn:name":"Rampur",
    "gn:population":0,
    "gn:timezone":"Asia/Kathmandu",
    "iso:country":"NP",
    "wof:name":"Rampur",
    "wof:placetype":"locality"
},
  "geometry": {"coordinates":[84.94036,27.06858],"type":"Point"}
}