{
  "type": "Feature",
  "properties": {
    "gn:admin1_code":"MR",
    "gn:admin2_code":"12",
    "gn:admin3_code":"54",
    "gn:admin4_code":"540011",
    "gn:asciiname":"Jarachaur",
    "gn:country_code":"NP",
    "gn:dem":1424,
    "gn:feature_class":"P",
    "gn:feature_code":"PPLL",
    "gn:name":"Jarachaur",
    "gn:population":0,
    "gn:timezone":"Asia/Kathmandu",
    "iso:country":"NP",
    "wof:name":"Jarachaur",
    "wof:placetype":"locality"
},
  "geometry": {"coordinates":[82.3978,28.65891],"type":"Point"}
}