{
  "type": "Feature",
  "properties": {
    "gn:admin1_code":"FR",
    "gn:admin2_code":"9",
    "gn:admin3_code":"73.0",
    "gn:admin4_code":"730019.0",
    "gn:asciiname":"Latadeu",
    "gn:country_code":"NP",
    "gn:dem":1404,
    "gn:feature_class":"P",
    "gn:feature_code":"PPLL",
    "gn:name":"Latadeu",
    "gn:population":0,
    "gn:timezone":"Asia/Kathmandu",
    "iso:country":"NP",
    "wof:name":"Latadeu",
    "wof:placetype":"locality"
},
  "geometry": {"coordinates":[80.36256,29.28424],"type":"Point"}
}