{
  "type": "Feature",
  "properties": {
    "gn:admin1_code":"00",
    "gn:asciiname":"Keraswara",
    "gn:country_code":"NP",
    "gn:dem":1288,
    "gn:feature_class":"P",
    "gn:feature_code":"PPL",
    "gn:name":"Ker\u0101sw\u0101\u0303r\u0101",
    "gn:population":0,
    "gn:timezone":"Asia/Kathmandu",
    "iso:country":"NP",
    "wof:name":"Keraswara",
    "wof:placetype":"locality"
},
  "geometry": {"coordinates":[86.52916,27.29918],"type":"Point"}
}