{
  "type": "Feature",
  "properties": {
    "gn:admin1_code":"MR",
    "gn:admin2_code":"12",
    "gn:admin3_code":"56.0",
    "gn:admin4_code":"560014.0",
    "gn:asciiname":"Churetagaun",
    "gn:country_code":"NP",
    "gn:dem":977,
    "gn:feature_class":"P",
    "gn:feature_code":"PPLL",
    "gn:name":"Churetagaun",
    "gn:population":0,
    "gn:timezone":"Asia/Kathmandu",
    "iso:country":"NP",
    "wof:name":"Churetagaun",
    "wof:placetype":"locality"
},
  "geometry": {"coordinates":[82.71179000000002,27.90165],"type":"Point"}
}