{
  "type": "Feature",
  "properties": {
    "gn:admin1_code":"MR",
    "gn:admin2_code":"12",
    "gn:admin3_code":"55",
    "gn:admin4_code":"550022",
    "gn:asciiname":"Jhaprepani",
    "gn:country_code":"NP",
    "gn:dem":1272,
    "gn:feature_class":"P",
    "gn:feature_code":"PPLL",
    "gn:name":"Jhaprepani",
    "gn:population":0,
    "gn:timezone":"Asia/Kathmandu",
    "iso:country":"NP",
    "wof:name":"Jhaprepani",
    "wof:placetype":"locality"
},
  "geometry": {"coordinates":[82.15770999999999,28.31051],"type":"Point"}
}