{
  "type": "Feature",
  "properties": {
    "gn:admin1_code":"FR",
    "gn:admin2_code":"14.0",
    "gn:admin3_code":"69.0",
    "gn:admin4_code":"690054.0",
    "gn:asciiname":"Dudullakopani",
    "gn:country_code":"NP",
    "gn:dem":1801,
    "gn:feature_class":"P",
    "gn:feature_code":"PPLL",
    "gn:name":"Dudullakopani",
    "gn:population":0,
    "gn:timezone":"Asia/Kathmandu",
    "iso:country":"NP",
    "wof:name":"Dudullakopani",
    "wof:placetype":"locality"
},
  "geometry": {"coordinates":[81.29295999999999,29.12477],"type":"Point"}
}