{
  "type": "Feature",
  "properties": {
    "gn:admin1_code":"WR",
    "gn:admin2_code":"4",
    "gn:admin3_code":"36.0",
    "gn:admin4_code":"360013.0",
    "gn:asciiname":"Lamagaun",
    "gn:country_code":"NP",
    "gn:dem":3208,
    "gn:feature_class":"P",
    "gn:feature_code":"PPLL",
    "gn:name":"Lamagaun",
    "gn:population":0,
    "gn:timezone":"Asia/Kathmandu",
    "iso:country":"NP",
    "wof:name":"Lamagaun",
    "wof:placetype":"locality"
},
  "geometry": {"coordinates":[85.07337,28.50588],"type":"Point"}
}