{
  "type": "Feature",
  "properties": {
    "gn:admin1_code":"WR",
    "gn:admin2_code":"8",
    "gn:admin3_code":"49",
    "gn:admin4_code":"490048",
    "gn:asciiname":"Raniganj",
    "gn:country_code":"NP",
    "gn:dem":155,
    "gn:feature_class":"P",
    "gn:feature_code":"PPLL",
    "gn:name":"Raniganj",
    "gn:population":0,
    "gn:timezone":"Asia/Kathmandu",
    "iso:country":"NP",
    "name:ben_x_preferred":[
        "\u09b0\u09be\u09a3\u09c0\u0997\u099e\u09cd\u099c"
    ],
    "name:bih_x_preferred":[
        "\u0930\u093e\u0928\u0940\u0917\u0902\u091c"
    ],
    "name:bpy_x_preferred":[
        "\u09b0\u09be\u09a8\u09bf\u0997\u099e\u09cd\u099c"
    ],
    "name:ceb_x_preferred":[
        "R\u0101n\u012bganj"
    ],
    "name:hif_x_preferred":[
        "Raniganj"
    ],
    "name:hin_x_preferred":[
        "\u0930\u093e\u0928\u0940\u0917\u0902\u091c"
    ],
    "name:ita_x_preferred":[
        "Raniganj"
    ],
    "name:mlg_x_preferred":[
        "Raniganj"
    ],
    "name:msa_x_preferred":[
        "Raniganj"
    ],
    "name:new_x_preferred":[
        "\u0930\u093e\u0928\u0940\u0917\u091e\u094d\u091c"
    ],
    "name:por_x_preferred":[
        "Raniganj"
    ],
    "name:spa_x_preferred":[
        "Raniganj"
    ],
    "name:swe_x_preferred":[
        "Raniganj"
    ],
    "name:tam_x_preferred":[
        "\u0bb0\u0bbe\u0ba3\u0bbf\u0b95\u0b9e\u0bcd\u0b9a\u0bcd"
    ],
    "name:vie_x_preferred":[
        "Raniganj"
    ],
    "name:war_x_preferred":[
        "Raniganj"
    ],
    "name:zho_x_preferred":[
        "\u62c9\u5c3c\u7518\u6770"
    ],
    "wof:name":"Raniganj",
    "wof:placetype":"locality"
},
  "geometry": {"coordinates":[83.44283,27.6692],"type":"Point"}
}