{
  "type": "Feature",
  "properties": {
    "gn:admin1_code":"WR",
    "gn:admin2_code":"8",
    "gn:admin3_code":"49",
    "gn:admin4_code":"490048",
    "gn:asciiname":"Raniganj",
    "gn:country_code":"NP",
    "gn:dem":155,
    "gn:feature_class":"P",
    "gn:feature_code":"PPLL",
    "gn:name":"Raniganj",
    "gn:population":0,
    "gn:timezone":"Asia/Kathmandu",
    "iso:country":"NP",
    "wof:name":"Raniganj",
    "wof:placetype":"locality"
},
  "geometry": {"coordinates":[83.44283,27.6692],"type":"Point"}
}