{
  "type": "Feature",
  "properties": {
    "gn:admin1_code":"MR",
    "gn:admin2_code":"6",
    "gn:admin3_code":"66.0",
    "gn:admin4_code":"660020.0",
    "gn:asciiname":"Purbutta",
    "gn:country_code":"NP",
    "gn:dem":2676,
    "gn:feature_class":"P",
    "gn:feature_code":"PPLL",
    "gn:name":"Purbutta",
    "gn:population":0,
    "gn:timezone":"Asia/Kathmandu",
    "iso:country":"NP",
    "wof:name":"Purbutta",
    "wof:placetype":"locality"
},
  "geometry": {"coordinates":[81.96946,29.84648],"type":"Point"}
}