{
  "type": "Feature",
  "properties": {
    "gn:admin1_code":"ER",
    "gn:admin2_code":"10",
    "gn:admin3_code":"2",
    "gn:admin4_code":"20015",
    "gn:asciiname":"Siruwani",
    "gn:country_code":"NP",
    "gn:dem":1504,
    "gn:feature_class":"P",
    "gn:feature_code":"PPLL",
    "gn:name":"Siruwani",
    "gn:population":0,
    "gn:timezone":"Asia/Kathmandu",
    "iso:country":"NP",
    "wof:name":"Siruwani",
    "wof:placetype":"locality"
},
  "geometry": {"coordinates":[87.58811999999998,26.89163],"type":"Point"}
}