{
  "type": "Feature",
  "properties": {
    "gn:admin1_code":"CR",
    "gn:admin2_code":"1",
    "gn:admin3_code":"24.0",
    "gn:admin4_code":"240065.0",
    "gn:asciiname":"Palang Gawadh",
    "gn:country_code":"NP",
    "gn:dem":1517,
    "gn:feature_class":"P",
    "gn:feature_code":"PPLL",
    "gn:name":"Palang Gawadh",
    "gn:population":0,
    "gn:timezone":"Asia/Kathmandu",
    "iso:country":"NP",
    "wof:name":"Palang Gawadh",
    "wof:placetype":"locality"
},
  "geometry": {"coordinates":[85.53754000000001,27.58356],"type":"Point"}
}