{
  "type": "Feature",
  "properties": {
    "gn:admin1_code":"CR",
    "gn:admin2_code":"11",
    "gn:admin3_code":"35.0",
    "gn:admin4_code":"350028.0",
    "gn:asciiname":"Jitpur",
    "gn:country_code":"NP",
    "gn:dem":198,
    "gn:feature_class":"P",
    "gn:feature_code":"PPLL",
    "gn:name":"Jitpur",
    "gn:population":0,
    "gn:timezone":"Asia/Kathmandu",
    "iso:country":"NP",
    "wof:name":"Jitpur",
    "wof:placetype":"locality"
},
  "geometry": {"coordinates":[84.54503000000003,27.54496],"type":"Point"}
}