{
  "type": "Feature",
  "properties": {
    "gn:admin1_code":"WR",
    "gn:admin2_code":"8",
    "gn:admin3_code":"49",
    "gn:admin4_code":"490036.0",
    "gn:asciiname":"Bangai",
    "gn:country_code":"NP",
    "gn:dem":126,
    "gn:feature_class":"P",
    "gn:feature_code":"PPLL",
    "gn:name":"Bangai",
    "gn:population":0,
    "gn:timezone":"Asia/Kathmandu",
    "iso:country":"NP",
    "wof:name":"Bangai",
    "wof:placetype":"locality"
},
  "geometry": {"coordinates":[83.38329,27.64532],"type":"Point"}
}