{
  "type": "Feature",
  "properties": {
    "gn:admin1_code":"MR",
    "gn:admin2_code":"2.0",
    "gn:admin3_code":"59.0",
    "gn:admin4_code":"590006.0",
    "gn:asciiname":"Sanne",
    "gn:country_code":"NP",
    "gn:dem":740,
    "gn:feature_class":"P",
    "gn:feature_code":"PPLL",
    "gn:name":"Sanne",
    "gn:population":0,
    "gn:timezone":"Asia/Kathmandu",
    "iso:country":"NP",
    "name:ceb_x_preferred":[
        "Sanne"
    ],
    "name:dan_x_preferred":[
        "Sanne"
    ],
    "name:deu_x_preferred":[
        "Sanne"
    ],
    "name:ita_x_preferred":[
        "Sanne"
    ],
    "name:nld_x_preferred":[
        "Sanne"
    ],
    "name:swe_x_preferred":[
        "Sanne"
    ],
    "wof:name":"Sanne",
    "wof:placetype":"locality"
},
  "geometry": {"coordinates":[81.37194000000002,28.84197],"type":"Point"}
}