{
  "type": "Feature",
  "properties": {
    "gn:admin1_code":"MR",
    "gn:admin2_code":"2.0",
    "gn:admin3_code":"57.0",
    "gn:admin4_code":"570011.0",
    "gn:asciiname":"Mulatanti",
    "gn:country_code":"NP",
    "gn:dem":175,
    "gn:feature_class":"P",
    "gn:feature_code":"PPLL",
    "gn:name":"Mulatanti",
    "gn:population":0,
    "gn:timezone":"Asia/Kathmandu",
    "iso:country":"NP",
    "wof:name":"Mulatanti",
    "wof:placetype":"locality"
},
  "geometry": {"coordinates":[81.65869000000001,28.27234],"type":"Point"}
}