{
  "type": "Feature",
  "properties": {
    "gn:admin1_code":"FR",
    "gn:admin2_code":"9",
    "gn:admin3_code":"75.0",
    "gn:admin4_code":"750009.0",
    "gn:asciiname":"Joshigaun",
    "gn:country_code":"NP",
    "gn:dem":1642,
    "gn:feature_class":"P",
    "gn:feature_code":"PPLL",
    "gn:name":"Joshigaun",
    "gn:population":0,
    "gn:timezone":"Asia/Kathmandu",
    "iso:country":"NP",
    "wof:name":"Joshigaun",
    "wof:placetype":"locality"
},
  "geometry": {"coordinates":[80.54788000000001,29.78039],"type":"Point"}
}