{
  "type": "Feature",
  "properties": {
    "gn:admin1_code":"CR",
    "gn:admin2_code":"1",
    "gn:admin3_code":"24.0",
    "gn:admin4_code":"240038.0",
    "gn:asciiname":"Kanpur",
    "gn:country_code":"NP",
    "gn:dem":1562,
    "gn:feature_class":"P",
    "gn:feature_code":"PPLL",
    "gn:name":"Kanpur",
    "gn:population":0,
    "gn:timezone":"Asia/Kathmandu",
    "iso:country":"NP",
    "wof:name":"Kanpur",
    "wof:placetype":"locality"
},
  "geometry": {"coordinates":[85.69948000000002,27.54336],"type":"Point"}
}