{
  "type": "Feature",
  "properties": {
    "gn:admin1_code":"CR",
    "gn:admin2_code":"1",
    "gn:admin3_code":"28",
    "gn:admin4_code":"280035",
    "gn:asciiname":"Gadhiko Thumko",
    "gn:country_code":"NP",
    "gn:dem":1181,
    "gn:feature_class":"P",
    "gn:feature_code":"PPLL",
    "gn:name":"Gadhiko Thumko",
    "gn:population":0,
    "gn:timezone":"Asia/Kathmandu",
    "iso:country":"NP",
    "wof:name":"Gadhiko Thumko",
    "wof:placetype":"locality"
},
  "geometry": {"coordinates":[85.14216999999999,27.7875],"type":"Point"}
}