{
  "type": "Feature",
  "properties": {
    "gn:admin1_code":"WR",
    "gn:admin2_code":"4",
    "gn:admin3_code":"37",
    "gn:admin4_code":"370008",
    "gn:asciiname":"Bhangri",
    "gn:country_code":"NP",
    "gn:dem":876,
    "gn:feature_class":"P",
    "gn:feature_code":"PPLL",
    "gn:name":"Bhangri",
    "gn:population":0,
    "gn:timezone":"Asia/Kathmandu",
    "iso:country":"NP",
    "wof:name":"Bhangri",
    "wof:placetype":"locality"
},
  "geometry": {"coordinates":[84.54699000000002,28.12385],"type":"Point"}
}