{
  "type": "Feature",
  "properties": {
    "gn:admin1_code":"MR",
    "gn:admin2_code":"12",
    "gn:admin3_code":"55",
    "gn:admin4_code":"550043",
    "gn:asciiname":"Koilachaur",
    "gn:country_code":"NP",
    "gn:dem":1745,
    "gn:feature_class":"P",
    "gn:feature_code":"PPLL",
    "gn:name":"Koilachaur",
    "gn:population":0,
    "gn:timezone":"Asia/Kathmandu",
    "iso:country":"NP",
    "wof:name":"Koilachaur",
    "wof:placetype":"locality"
},
  "geometry": {"coordinates":[82.3823,28.2964],"type":"Point"}
}