{
  "type": "Feature",
  "properties": {
    "gn:admin1_code":"WR",
    "gn:admin2_code":"8",
    "gn:admin3_code":"49",
    "gn:admin4_code":"490011",
    "gn:asciiname":"Baragadawa",
    "gn:country_code":"NP",
    "gn:dem":104,
    "gn:feature_class":"P",
    "gn:feature_code":"PPLL",
    "gn:name":"Baragadawa",
    "gn:population":0,
    "gn:timezone":"Asia/Kathmandu",
    "iso:country":"NP",
    "wof:name":"Baragadawa",
    "wof:placetype":"locality"
},
  "geometry": {"coordinates":[83.26753000000002,27.5428],"type":"Point"}
}