{
  "type": "Feature",
  "properties": {
    "gn:admin1_code":"ER",
    "gn:admin2_code":"7",
    "gn:admin3_code":"9",
    "gn:admin4_code":"90026",
    "gn:asciiname":"Sikden",
    "gn:country_code":"NP",
    "gn:dem":1268,
    "gn:feature_class":"P",
    "gn:feature_code":"PPLL",
    "gn:name":"Sikden",
    "gn:population":0,
    "gn:timezone":"Asia/Kathmandu",
    "iso:country":"NP",
    "wof:name":"Sikden",
    "wof:placetype":"locality"
},
  "geometry": {"coordinates":[87.38051,27.43156],"type":"Point"}
}