{
  "type": "Feature",
  "properties": {
    "gn:admin1_code":"MR",
    "gn:admin2_code":"12",
    "gn:admin3_code":"55",
    "gn:admin4_code":"550021",
    "gn:asciiname":"Madanekhuti",
    "gn:country_code":"NP",
    "gn:dem":501,
    "gn:feature_class":"P",
    "gn:feature_code":"PPLL",
    "gn:name":"Madanekhuti",
    "gn:population":0,
    "gn:timezone":"Asia/Kathmandu",
    "iso:country":"NP",
    "wof:name":"Madanekhuti",
    "wof:placetype":"locality"
},
  "geometry": {"coordinates":[81.99542,28.24469],"type":"Point"}
}