{
  "type": "Feature",
  "properties": {
    "gn:admin1_code":"WR",
    "gn:admin2_code":"3",
    "gn:admin3_code":"45",
    "gn:admin4_code":"450057",
    "gn:asciiname":"Boharagaun",
    "gn:country_code":"NP",
    "gn:dem":1570,
    "gn:feature_class":"P",
    "gn:feature_code":"PPLL",
    "gn:name":"Boharagaun",
    "gn:population":0,
    "gn:timezone":"Asia/Kathmandu",
    "iso:country":"NP",
    "name:ceb_x_preferred":[
        "Boharagaun"
    ],
    "name:fra_x_preferred":[
        "Boharagaun"
    ],
    "name:nep_x_preferred":[
        "\u092c\u094b\u0939\u0930\u093e\u0917\u093e\u0909\u0901"
    ],
    "name:new_x_preferred":[
        "\u092c\u094b\u0939\u0930\u093e\u0917\u093e\u0909\u0902"
    ],
    "name:pol_x_preferred":[
        "Boharagaun"
    ],
    "wof:name":"Boharagaun",
    "wof:placetype":"locality"
},
  "geometry": {"coordinates":[83.059,28.37241],"type":"Point"}
}