{
  "type": "Feature",
  "properties": {
    "gn:admin1_code":"ER",
    "gn:admin2_code":"7",
    "gn:admin3_code":"9",
    "gn:admin4_code":"90033",
    "gn:asciiname":"Ghyangkharka",
    "gn:country_code":"NP",
    "gn:dem":1204,
    "gn:feature_class":"P",
    "gn:feature_code":"PPLL",
    "gn:name":"Ghyangkharka",
    "gn:population":0,
    "gn:timezone":"Asia/Kathmandu",
    "iso:country":"NP",
    "wof:name":"Ghyangkharka",
    "wof:placetype":"locality"
},
  "geometry": {"coordinates":[87.10075000000001,27.51529],"type":"Point"}
}