{
  "type": "Feature",
  "properties": {
    "gn:admin1_code":"ER",
    "gn:admin2_code":"13.0",
    "gn:admin3_code":"14.0",
    "gn:admin4_code":"140034.0",
    "gn:asciiname":"Sugachari",
    "gn:country_code":"NP",
    "gn:dem":647,
    "gn:feature_class":"P",
    "gn:feature_code":"PPLL",
    "gn:name":"Sugachari",
    "gn:population":0,
    "gn:timezone":"Asia/Kathmandu",
    "iso:country":"NP",
    "wof:name":"Sugachari",
    "wof:placetype":"locality"
},
  "geometry": {"coordinates":[86.88888,26.87973],"type":"Point"}
}