{
  "type": "Feature",
  "properties": {
    "gn:admin1_code":"MR",
    "gn:admin2_code":"6",
    "gn:admin3_code":"66.0",
    "gn:admin4_code":"660013.0",
    "gn:asciiname":"Yangchu",
    "gn:country_code":"NP",
    "gn:dem":5051,
    "gn:feature_class":"P",
    "gn:feature_code":"PPLL",
    "gn:name":"Yangchu",
    "gn:population":0,
    "gn:timezone":"Asia/Kathmandu",
    "iso:country":"NP",
    "wof:name":"Yangchu",
    "wof:placetype":"locality"
},
  "geometry": {"coordinates":[81.42244000000002,30.22262000000001],"type":"Point"}
}