{
  "type": "Feature",
  "properties": {
    "gn:admin1_code":"CR",
    "gn:admin2_code":"11",
    "gn:admin3_code":"31",
    "gn:admin4_code":"310034",
    "gn:asciiname":"Kamerepani",
    "gn:country_code":"NP",
    "gn:dem":721,
    "gn:feature_class":"P",
    "gn:feature_code":"PPLL",
    "gn:name":"Kamerepani",
    "gn:population":0,
    "gn:timezone":"Asia/Kathmandu",
    "iso:country":"NP",
    "wof:name":"Kamerepani",
    "wof:placetype":"locality"
},
  "geometry": {"coordinates":[84.97474,27.37425],"type":"Point"}
}