{
  "type": "Feature",
  "properties": {
    "gn:admin1_code":"WR",
    "gn:admin2_code":"4.0",
    "gn:admin3_code":"39.0",
    "gn:admin4_code":"390017.0",
    "gn:asciiname":"Dewaldanda",
    "gn:country_code":"NP",
    "gn:dem":597,
    "gn:feature_class":"P",
    "gn:feature_code":"PPLL",
    "gn:name":"Dewaldanda",
    "gn:population":0,
    "gn:timezone":"Asia/Kathmandu",
    "iso:country":"NP",
    "wof:name":"Dewaldanda",
    "wof:placetype":"locality"
},
  "geometry": {"coordinates":[84.00516,28.02832],"type":"Point"}
}