{
  "type": "Feature",
  "properties": {
    "gn:admin1_code":"WR",
    "gn:admin2_code":"3",
    "gn:admin3_code":"45",
    "gn:admin4_code":"450059",
    "gn:asciiname":"Ransing",
    "gn:country_code":"NP",
    "gn:dem":1925,
    "gn:feature_class":"P",
    "gn:feature_code":"PPLL",
    "gn:name":"Ransing",
    "gn:population":0,
    "gn:timezone":"Asia/Kathmandu",
    "iso:country":"NP",
    "wof:name":"Ransing",
    "wof:placetype":"locality"
},
  "geometry": {"coordinates":[83.28605,28.28089000000001],"type":"Point"}
}