{
  "type": "Feature",
  "properties": {
    "gn:admin1_code":"FR",
    "gn:admin2_code":"14",
    "gn:admin3_code":"71.0",
    "gn:admin4_code":"710032.0",
    "gn:asciiname":"Badki Paliya",
    "gn:country_code":"NP",
    "gn:dem":156,
    "gn:feature_class":"P",
    "gn:feature_code":"PPLL",
    "gn:name":"Badki Paliya",
    "gn:population":0,
    "gn:timezone":"Asia/Kathmandu",
    "iso:country":"NP",
    "wof:name":"Badki Paliya",
    "wof:placetype":"locality"
},
  "geometry": {"coordinates":[80.79600000000001,28.54018],"type":"Point"}
}