{
  "type": "Feature",
  "properties": {
    "gn:admin1_code":"ER",
    "gn:admin2_code":"10",
    "gn:admin3_code":"3.0",
    "gn:admin4_code":"30006.0",
    "gn:asciiname":"Hattidhunge",
    "gn:country_code":"NP",
    "gn:dem":239,
    "gn:feature_class":"P",
    "gn:feature_code":"PPLL",
    "gn:name":"Hattidhunge",
    "gn:population":0,
    "gn:timezone":"Asia/Kathmandu",
    "iso:country":"NP",
    "wof:name":"Hattidhunge",
    "wof:placetype":"locality"
},
  "geometry": {"coordinates":[87.77549999999999,26.72399],"type":"Point"}
}