{
  "type": "Feature",
  "properties": {
    "gn:admin1_code":"WR",
    "gn:admin2_code":"8",
    "gn:admin3_code":"47",
    "gn:admin4_code":"470045",
    "gn:asciiname":"Marangkot",
    "gn:country_code":"NP",
    "gn:dem":1298,
    "gn:feature_class":"P",
    "gn:feature_code":"PPLL",
    "gn:name":"Marangkot",
    "gn:population":0,
    "gn:timezone":"Asia/Kathmandu",
    "iso:country":"NP",
    "wof:name":"Marangkot",
    "wof:placetype":"locality"
},
  "geometry": {"coordinates":[83.52427,27.78434],"type":"Point"}
}