{
  "type": "Feature",
  "properties": {
    "gn:admin1_code":"MR",
    "gn:admin2_code":"12",
    "gn:admin3_code":"54",
    "gn:admin4_code":"540004",
    "gn:asciiname":"Bhar",
    "gn:country_code":"NP",
    "gn:dem":2136,
    "gn:feature_class":"P",
    "gn:feature_code":"PPLL",
    "gn:name":"Bhar",
    "gn:population":0,
    "gn:timezone":"Asia/Kathmandu",
    "iso:country":"NP",
    "name:cat_x_preferred":[
        "Bhars"
    ],
    "wof:name":"Bhar",
    "wof:placetype":"locality"
},
  "geometry": {"coordinates":[82.46218,28.72085],"type":"Point"}
}