{
  "type": "Feature",
  "properties": {
    "gn:admin1_code":"00",
    "gn:asciiname":"Sinbandi",
    "gn:country_code":"NP",
    "gn:dem":2165,
    "gn:feature_class":"P",
    "gn:feature_code":"PPL",
    "gn:name":"Si\u1e45bandi\u0307\u0304",
    "gn:population":0,
    "gn:timezone":"Asia/Kathmandu",
    "iso:country":"NP",
    "name:und_x_variant":[
        "Si\u1e45bandi\u0307\u0304",
        "Si\u1e45band\u012b"
    ],
    "wof:name":"Sinbandi",
    "wof:placetype":"locality"
},
  "geometry": {"coordinates":[85.31622,28.0412],"type":"Point"}
}