{
  "type": "Feature",
  "properties": {
    "gn:admin1_code":"ER",
    "gn:admin2_code":"13",
    "gn:admin3_code":"11",
    "gn:admin4_code":"110021",
    "gn:asciiname":"Tulukhop",
    "gn:country_code":"NP",
    "gn:dem":1835,
    "gn:feature_class":"P",
    "gn:feature_code":"PPLL",
    "gn:name":"Tulukhop",
    "gn:population":0,
    "gn:timezone":"Asia/Kathmandu",
    "iso:country":"NP",
    "wof:name":"Tulukhop",
    "wof:placetype":"locality"
},
  "geometry": {"coordinates":[86.74163,27.44656],"type":"Point"}
}