{
  "type": "Feature",
  "properties": {
    "gn:admin1_code":"00",
    "gn:asciiname":"Kumiyahi",
    "gn:country_code":"NP",
    "gn:dem":86,
    "gn:feature_class":"P",
    "gn:feature_code":"PPL",
    "gn:name":"Kumiy\u0101hi\u0307\u0304",
    "gn:population":0,
    "gn:timezone":"Asia/Kathmandu",
    "iso:country":"NP",
    "name:nep_x_preferred":[
        "Kumiy\u0101hi\u0307\u0304"
    ],
    "name:und_x_variant":[
        "Kuiy\u0101hi"
    ],
    "wof:name":"Kumiyahi",
    "wof:placetype":"locality"
},
  "geometry": {"coordinates":[87.03981,26.58025],"type":"Point"}
}