{
  "type": "Feature",
  "properties": {
    "gn:admin1_code":"CR",
    "gn:admin2_code":"5",
    "gn:admin3_code":"21",
    "gn:admin4_code":"210036",
    "gn:asciiname":"Lamagaun",
    "gn:country_code":"NP",
    "gn:dem":1595,
    "gn:feature_class":"P",
    "gn:feature_code":"PPLL",
    "gn:name":"Lamagaun",
    "gn:population":0,
    "gn:timezone":"Asia/Kathmandu",
    "iso:country":"NP",
    "wof:name":"Lamagaun",
    "wof:placetype":"locality"
},
  "geometry": {"coordinates":[86.15554,27.42399],"type":"Point"}
}