{
  "type": "Feature",
  "properties": {
    "gn:admin1_code":"WR",
    "gn:admin2_code":"4.0",
    "gn:admin3_code":"39.0",
    "gn:admin4_code":"390024.0",
    "gn:asciiname":"Bar Pokhara",
    "gn:country_code":"NP",
    "gn:dem":945,
    "gn:feature_class":"P",
    "gn:feature_code":"PPLL",
    "gn:name":"Bar Pokhara",
    "gn:population":0,
    "gn:timezone":"Asia/Kathmandu",
    "iso:country":"NP",
    "wof:name":"Bar Pokhara",
    "wof:placetype":"locality"
},
  "geometry": {"coordinates":[83.62048,27.94454],"type":"Point"}
}