{
  "type": "Feature",
  "properties": {
    "gn:admin1_code":"ER",
    "gn:admin2_code":"7.0",
    "gn:admin3_code":"6.0",
    "gn:admin4_code":"60046.0",
    "gn:asciiname":"Gaderitol",
    "gn:country_code":"NP",
    "gn:dem":69,
    "gn:feature_class":"P",
    "gn:feature_code":"PPLL",
    "gn:name":"Gaderitol",
    "gn:population":0,
    "gn:timezone":"Asia/Kathmandu",
    "iso:country":"NP",
    "wof:name":"Gaderitol",
    "wof:placetype":"locality"
},
  "geometry": {"coordinates":[87.1733,26.40678],"type":"Point"}
}