{
  "type": "Feature",
  "properties": {
    "gn:admin1_code":"WR",
    "gn:admin2_code":"8",
    "gn:admin3_code":"48",
    "gn:admin4_code":"480035",
    "gn:asciiname":"Chisapani",
    "gn:country_code":"NP",
    "gn:dem":157,
    "gn:feature_class":"P",
    "gn:feature_code":"PPLL",
    "gn:name":"Chisapani",
    "gn:population":0,
    "gn:timezone":"Asia/Kathmandu",
    "iso:country":"NP",
    "name:ceb_x_preferred":[
        "Chisapani"
    ],
    "name:nep_x_preferred":[
        "\u091a\u093f\u0938\u093e\u092a\u093e\u0928\u0940"
    ],
    "name:nld_x_preferred":[
        "Chisapani"
    ],
    "name:pol_x_preferred":[
        "Chisapani"
    ],
    "wof:name":"Chisapani",
    "wof:placetype":"locality"
},
  "geometry": {"coordinates":[84.06854,27.60811],"type":"Point"}
}