{
  "type": "Feature",
  "properties": {
    "gn:admin1_code":"MR",
    "gn:admin2_code":"2",
    "gn:admin3_code":"61.0",
    "gn:admin4_code":"610006.0",
    "gn:asciiname":"Gandabba",
    "gn:country_code":"NP",
    "gn:dem":1150,
    "gn:feature_class":"P",
    "gn:feature_code":"PPLL",
    "gn:name":"Gandabba",
    "gn:population":0,
    "gn:timezone":"Asia/Kathmandu",
    "iso:country":"NP",
    "wof:name":"Gandabba",
    "wof:placetype":"locality"
},
  "geometry": {"coordinates":[81.99164,28.73503],"type":"Point"}
}