{
  "type": "Feature",
  "properties": {
    "gn:admin1_code":"CR",
    "gn:admin2_code":"11",
    "gn:admin3_code":"34",
    "gn:admin4_code":"340023",
    "gn:asciiname":"Maruwatandi",
    "gn:country_code":"NP",
    "gn:dem":124,
    "gn:feature_class":"P",
    "gn:feature_code":"PPLL",
    "gn:name":"Maruwatandi",
    "gn:population":0,
    "gn:timezone":"Asia/Kathmandu",
    "iso:country":"NP",
    "wof:name":"Maruwatandi",
    "wof:placetype":"locality"
},
  "geometry": {"coordinates":[84.94929,27.15689],"type":"Point"}
}