{
  "type": "Feature",
  "properties": {
    "gn:admin1_code":"00",
    "gn:asciiname":"Chisanijhora",
    "gn:country_code":"NP",
    "gn:dem":560,
    "gn:feature_class":"P",
    "gn:feature_code":"PPL",
    "gn:name":"Chis\u0101ni\u0307\u0304jhor\u0101",
    "gn:population":0,
    "gn:timezone":"Asia/Kathmandu",
    "iso:country":"NP",
    "name:und_x_variant":[
        "Chis\u0101ni\u0307\u0304jhor\u0101",
        "Chis\u0101n\u012bjhor\u0101"
    ],
    "wof:name":"Chisanijhora",
    "wof:placetype":"locality"
},
  "geometry": {"coordinates":[85.90274000000002,27.21343],"type":"Point"}
}