{
  "type": "Feature",
  "properties": {
    "gn:admin1_code":"MR",
    "gn:admin2_code":"2",
    "gn:admin3_code":"60.0",
    "gn:admin4_code":"600035.0",
    "gn:asciiname":"Kuikana",
    "gn:country_code":"NP",
    "gn:dem":1152,
    "gn:feature_class":"P",
    "gn:feature_code":"PPLL",
    "gn:name":"Kuikana",
    "gn:population":0,
    "gn:timezone":"Asia/Kathmandu",
    "iso:country":"NP",
    "wof:name":"Kuikana",
    "wof:placetype":"locality"
},
  "geometry": {"coordinates":[81.70196,28.83715],"type":"Point"}
}