{
  "type": "Feature",
  "properties": {
    "gn:admin1_code":"MR",
    "gn:admin2_code":"2",
    "gn:admin3_code":"60.0",
    "gn:admin4_code":"600037.0",
    "gn:asciiname":"Pansain",
    "gn:country_code":"NP",
    "gn:dem":1578,
    "gn:feature_class":"P",
    "gn:feature_code":"PPLL",
    "gn:name":"Pansain",
    "gn:population":0,
    "gn:timezone":"Asia/Kathmandu",
    "iso:country":"NP",
    "wof:name":"Pansain",
    "wof:placetype":"locality"
},
  "geometry": {"coordinates":[81.56493,28.85608],"type":"Point"}
}