{
  "type": "Feature",
  "properties": {
    "gn:admin1_code":"ER",
    "gn:admin2_code":"10.0",
    "gn:admin3_code":"1.0",
    "gn:admin4_code":"10008.0",
    "gn:asciiname":"Kheden",
    "gn:country_code":"NP",
    "gn:dem":2394,
    "gn:feature_class":"P",
    "gn:feature_code":"PPLL",
    "gn:name":"Kheden",
    "gn:population":0,
    "gn:timezone":"Asia/Kathmandu",
    "iso:country":"NP",
    "wof:name":"Kheden",
    "wof:placetype":"locality"
},
  "geometry": {"coordinates":[87.76344,27.5092],"type":"Point"}
}