{
  "type": "Feature",
  "properties": {
    "gn:admin1_code":"ER",
    "gn:admin2_code":"7",
    "gn:admin3_code":"5",
    "gn:admin4_code":"50050",
    "gn:asciiname":"Dangitol",
    "gn:country_code":"NP",
    "gn:dem":75,
    "gn:feature_class":"P",
    "gn:feature_code":"PPLL",
    "gn:name":"Dangitol",
    "gn:population":0,
    "gn:timezone":"Asia/Kathmandu",
    "iso:country":"NP",
    "wof:name":"Dangitol",
    "wof:placetype":"locality"
},
  "geometry": {"coordinates":[87.50539000000001,26.4768],"type":"Point"}
}