{
  "type": "Feature",
  "properties": {
    "gn:admin1_code":"ER",
    "gn:admin2_code":"13",
    "gn:admin3_code":"16",
    "gn:admin4_code":"160050",
    "gn:asciiname":"Shripur",
    "gn:country_code":"NP",
    "gn:dem":88,
    "gn:feature_class":"P",
    "gn:feature_code":"PPLL",
    "gn:name":"Shripur",
    "gn:population":0,
    "gn:timezone":"Asia/Kathmandu",
    "iso:country":"NP",
    "wof:name":"Shripur",
    "wof:placetype":"locality"
},
  "geometry": {"coordinates":[86.36309,26.6409],"type":"Point"}
}