{
  "type": "Feature",
  "properties": {
    "gn:admin1_code":"ER",
    "gn:admin2_code":"13.0",
    "gn:admin3_code":"14.0",
    "gn:admin4_code":"140010.0",
    "gn:asciiname":"Paritar",
    "gn:country_code":"NP",
    "gn:dem":1204,
    "gn:feature_class":"P",
    "gn:feature_code":"PPLL",
    "gn:name":"Paritar",
    "gn:population":0,
    "gn:timezone":"Asia/Kathmandu",
    "iso:country":"NP",
    "wof:name":"Paritar",
    "wof:placetype":"locality"
},
  "geometry": {"coordinates":[86.55855,26.95332],"type":"Point"}
}