{
  "type": "Feature",
  "properties": {
    "gn:admin1_code":"MR",
    "gn:admin2_code":"12",
    "gn:admin3_code":"52",
    "gn:admin4_code":"520015",
    "gn:asciiname":"Sarangbesi",
    "gn:country_code":"NP",
    "gn:dem":719,
    "gn:feature_class":"P",
    "gn:feature_code":"PPLL",
    "gn:name":"Sarangbesi",
    "gn:population":0,
    "gn:timezone":"Asia/Kathmandu",
    "iso:country":"NP",
    "wof:name":"Sarangbesi",
    "wof:placetype":"locality"
},
  "geometry": {"coordinates":[82.87154,28.03709000000001],"type":"Point"}
}