{
  "type": "Feature",
  "properties": {
    "gn:admin1_code":"ER",
    "gn:admin2_code":"7.0",
    "gn:admin3_code":"10.0",
    "gn:admin4_code":"100004.0",
    "gn:asciiname":"Dibag",
    "gn:country_code":"NP",
    "gn:dem":1315,
    "gn:feature_class":"P",
    "gn:feature_code":"PPLL",
    "gn:name":"Dibag",
    "gn:population":0,
    "gn:timezone":"Asia/Kathmandu",
    "iso:country":"NP",
    "wof:name":"Dibag",
    "wof:placetype":"locality"
},
  "geometry": {"coordinates":[87.04930999999998,27.03977],"type":"Point"}
}