{
  "type": "Feature",
  "properties": {
    "gn:admin1_code":"WR",
    "gn:admin2_code":"8",
    "gn:admin3_code":"48",
    "gn:admin4_code":"480060.0",
    "gn:asciiname":"Hurjil",
    "gn:country_code":"NP",
    "gn:dem":731,
    "gn:feature_class":"P",
    "gn:feature_code":"PPLL",
    "gn:name":"Hurjil",
    "gn:population":0,
    "gn:timezone":"Asia/Kathmandu",
    "iso:country":"NP",
    "wof:name":"Hurjil",
    "wof:placetype":"locality"
},
  "geometry": {"coordinates":[84.26059000000002,27.72887],"type":"Point"}
}