{
  "type": "Feature",
  "properties": {
    "gn:admin1_code":"ER",
    "gn:admin2_code":"7",
    "gn:admin3_code":"10.0",
    "gn:admin4_code":"100059.0",
    "gn:asciiname":"Talegaun",
    "gn:country_code":"NP",
    "gn:dem":1592,
    "gn:feature_class":"P",
    "gn:feature_code":"PPLL",
    "gn:name":"Talegaun",
    "gn:population":0,
    "gn:timezone":"Asia/Kathmandu",
    "iso:country":"NP",
    "name:ceb_x_preferred":[
        "Talegaun"
    ],
    "name:mai_x_preferred":[
        "\u091f\u093e\u0932\u0947\u0917\u093e\u0909\u0901"
    ],
    "name:msa_x_preferred":[
        "Talegaun"
    ],
    "name:nep_x_preferred":[
        "\u091f\u093e\u0932\u0947\u0917\u093e\u0909\u0901"
    ],
    "name:new_x_preferred":[
        "\u091f\u093e\u0932\u0947\u0917\u093e\u0909\u0901"
    ],
    "name:pol_x_preferred":[
        "Talegaun"
    ],
    "wof:name":"Talegaun",
    "wof:placetype":"locality"
},
  "geometry": {"coordinates":[87.13892,27.17098],"type":"Point"}
}