{
  "type": "Feature",
  "properties": {
    "gn:admin1_code":"WR",
    "gn:admin2_code":"8",
    "gn:admin3_code":"49",
    "gn:admin4_code":"490033",
    "gn:asciiname":"Hararailiya",
    "gn:country_code":"NP",
    "gn:dem":126,
    "gn:feature_class":"P",
    "gn:feature_code":"PPLL",
    "gn:name":"Hararailiya",
    "gn:population":0,
    "gn:timezone":"Asia/Kathmandu",
    "iso:country":"NP",
    "wof:name":"Hararailiya",
    "wof:placetype":"locality"
},
  "geometry": {"coordinates":[83.50136999999999,27.60713],"type":"Point"}
}