{
  "type": "Feature",
  "properties": {
    "gn:admin1_code":"CR",
    "gn:admin2_code":"1",
    "gn:admin3_code":"23",
    "gn:admin4_code":"230078",
    "gn:asciiname":"Polekharka",
    "gn:country_code":"NP",
    "gn:dem":2176,
    "gn:feature_class":"P",
    "gn:feature_code":"PPLL",
    "gn:name":"Polekharka",
    "gn:population":0,
    "gn:timezone":"Asia/Kathmandu",
    "iso:country":"NP",
    "wof:name":"Polekharka",
    "wof:placetype":"locality"
},
  "geometry": {"coordinates":[85.85141,27.6897],"type":"Point"}
}