{
  "type": "Feature",
  "properties": {
    "gn:admin1_code":"MR",
    "gn:admin2_code":"12",
    "gn:admin3_code":"55",
    "gn:admin4_code":"550032",
    "gn:asciiname":"Baghchaur",
    "gn:country_code":"NP",
    "gn:dem":1496,
    "gn:feature_class":"P",
    "gn:feature_code":"PPLL",
    "gn:name":"Baghchaur",
    "gn:population":0,
    "gn:timezone":"Asia/Kathmandu",
    "iso:country":"NP",
    "wof:name":"Baghchaur",
    "wof:placetype":"locality"
},
  "geometry": {"coordinates":[82.09685999999998,28.39617],"type":"Point"}
}