{
  "type": "Feature",
  "properties": {
    "gn:admin1_code":"FR",
    "gn:admin2_code":"14",
    "gn:admin3_code":"69",
    "gn:admin4_code":"690031",
    "gn:asciiname":"Tallo Guyalpani",
    "gn:country_code":"NP",
    "gn:dem":758,
    "gn:feature_class":"P",
    "gn:feature_code":"PPLL",
    "gn:name":"Tallo Guyalpani",
    "gn:population":0,
    "gn:timezone":"Asia/Kathmandu",
    "iso:country":"NP",
    "wof:name":"Tallo Guyalpani",
    "wof:placetype":"locality"
},
  "geometry": {"coordinates":[81.18420999999999,29.2365],"type":"Point"}
}