{
  "type": "Feature",
  "properties": {
    "gn:admin1_code":"WR",
    "gn:admin2_code":"4",
    "gn:admin3_code":"37",
    "gn:admin4_code":"370041",
    "gn:asciiname":"Langdi",
    "gn:country_code":"NP",
    "gn:dem":764,
    "gn:feature_class":"P",
    "gn:feature_code":"PPLL",
    "gn:name":"Langdi",
    "gn:population":0,
    "gn:timezone":"Asia/Kathmandu",
    "iso:country":"NP",
    "wof:name":"Langdi",
    "wof:placetype":"locality"
},
  "geometry": {"coordinates":[84.28662,28.19633],"type":"Point"}
}