{
  "type": "Feature",
  "properties": {
    "gn:admin1_code":"ER",
    "gn:admin2_code":"13",
    "gn:admin3_code":"11",
    "gn:admin4_code":"110004",
    "gn:asciiname":"Bhakangje",
    "gn:country_code":"NP",
    "gn:dem":2386,
    "gn:feature_class":"P",
    "gn:feature_code":"PPLL",
    "gn:name":"Bhakangje",
    "gn:population":0,
    "gn:timezone":"Asia/Kathmandu",
    "iso:country":"NP",
    "wof:name":"Bhakangje",
    "wof:placetype":"locality"
},
  "geometry": {"coordinates":[86.43538000000002,27.59247],"type":"Point"}
}