{
  "type": "Feature",
  "properties": {
    "gn:admin1_code":"MR",
    "gn:admin2_code":"12",
    "gn:admin3_code":"54",
    "gn:admin4_code":"540037",
    "gn:asciiname":"Khadgadanda",
    "gn:country_code":"NP",
    "gn:dem":1810,
    "gn:feature_class":"P",
    "gn:feature_code":"PPLL",
    "gn:name":"Khadgadanda",
    "gn:population":0,
    "gn:timezone":"Asia/Kathmandu",
    "iso:country":"NP",
    "wof:name":"Khadgadanda",
    "wof:placetype":"locality"
},
  "geometry": {"coordinates":[82.50544000000002,28.56192],"type":"Point"}
}