{
  "type": "Feature",
  "properties": {
    "gn:admin1_code":"WR",
    "gn:admin2_code":"3",
    "gn:admin3_code":"45.0",
    "gn:admin4_code":"450016.0",
    "gn:asciiname":"Bao",
    "gn:country_code":"NP",
    "gn:dem":961,
    "gn:feature_class":"P",
    "gn:feature_code":"PPLL",
    "gn:name":"Bao",
    "gn:population":0,
    "gn:timezone":"Asia/Kathmandu",
    "iso:country":"NP",
    "wof:name":"Bao",
    "wof:placetype":"locality"
},
  "geometry": {"coordinates":[83.60063000000002,28.12682],"type":"Point"}
}