{
  "type": "Feature",
  "properties": {
    "gn:admin1_code":"WR",
    "gn:admin2_code":"4.0",
    "gn:admin3_code":"39.0",
    "gn:admin4_code":"390035.0",
    "gn:asciiname":"Fair(Chaitra Dashai&",
    "gn:country_code":"NP",
    "gn:dem":1326,
    "gn:feature_class":"P",
    "gn:feature_code":"PPLL",
    "gn:name":"Fair(Chaitra Dashai&",
    "gn:population":0,
    "gn:timezone":"Asia/Kathmandu",
    "iso:country":"NP",
    "wof:name":"Fair(Chaitra Dashai&",
    "wof:placetype":"locality"
},
  "geometry": {"coordinates":[83.87183,27.99144],"type":"Point"}
}