{
  "type": "Feature",
  "properties": {
    "gn:admin1_code":"CR",
    "gn:admin2_code":"5",
    "gn:admin3_code":"18",
    "gn:admin4_code":"180039",
    "gn:asciiname":"Jamindartol",
    "gn:country_code":"NP",
    "gn:dem":197,
    "gn:feature_class":"P",
    "gn:feature_code":"PPLL",
    "gn:name":"Jamindartol",
    "gn:population":0,
    "gn:timezone":"Asia/Kathmandu",
    "iso:country":"NP",
    "wof:name":"Jamindartol",
    "wof:placetype":"locality"
},
  "geometry": {"coordinates":[85.91431,26.95842],"type":"Point"}
}