{
  "type": "Feature",
  "properties": {
    "gn:admin1_code":"WR",
    "gn:admin2_code":"8",
    "gn:admin3_code":"48",
    "gn:admin4_code":"480051",
    "gn:asciiname":"Pragatinagar",
    "gn:country_code":"NP",
    "gn:dem":176,
    "gn:feature_class":"P",
    "gn:feature_code":"PPLL",
    "gn:name":"Pragatinagar",
    "gn:population":0,
    "gn:timezone":"Asia/Kathmandu",
    "iso:country":"NP",
    "name:ceb_x_preferred":[
        "Pragatinagar"
    ],
    "name:msa_x_preferred":[
        "Pragatinagar"
    ],
    "name:new_x_preferred":[
        "\u092a\u094d\u0930\u0917\u0924\u093f\u0928\u0917\u0930"
    ],
    "name:pol_x_preferred":[
        "Pragatinagar"
    ],
    "wof:name":"Pragatinagar",
    "wof:placetype":"locality"
},
  "geometry": {"coordinates":[84.18427,27.66597],"type":"Point"}
}