{
  "type": "Feature",
  "properties": {
    "gn:admin1_code":"WR",
    "gn:admin2_code":"4",
    "gn:admin3_code":"37",
    "gn:admin4_code":"370012",
    "gn:asciiname":"Kamargaun",
    "gn:country_code":"NP",
    "gn:dem":808,
    "gn:feature_class":"P",
    "gn:feature_code":"PPLL",
    "gn:name":"Kamargaun",
    "gn:population":0,
    "gn:timezone":"Asia/Kathmandu",
    "iso:country":"NP",
    "wof:name":"Kamargaun",
    "wof:placetype":"locality"
},
  "geometry": {"coordinates":[84.42249,28.14032000000001],"type":"Point"}
}