{
  "type": "Feature",
  "properties": {
    "gn:admin1_code":"ER",
    "gn:admin2_code":"13",
    "gn:admin3_code":"13",
    "gn:admin4_code":"130071",
    "gn:asciiname":"Khaju",
    "gn:country_code":"NP",
    "gn:dem":1725,
    "gn:feature_class":"P",
    "gn:feature_code":"PPLL",
    "gn:name":"Khaju",
    "gn:population":0,
    "gn:timezone":"Asia/Kathmandu",
    "iso:country":"NP",
    "wof:name":"Khaju",
    "wof:placetype":"locality"
},
  "geometry": {"coordinates":[86.87605000000001,27.36603],"type":"Point"}
}