{
  "type": "Feature",
  "properties": {
    "gn:admin1_code":"WR",
    "gn:admin2_code":"8",
    "gn:admin3_code":"47",
    "gn:admin4_code":"470032.0",
    "gn:asciiname":"Jhirubas",
    "gn:country_code":"NP",
    "gn:dem":803,
    "gn:feature_class":"P",
    "gn:feature_code":"PPLL",
    "gn:name":"Jhirubas",
    "gn:population":0,
    "gn:timezone":"Asia/Kathmandu",
    "iso:country":"NP",
    "name:ceb_x_preferred":[
        "Jhirubas"
    ],
    "name:hin_x_preferred":[
        "\u091d\u093f\u0930\u0941\u0935\u093e\u0938"
    ],
    "name:msa_x_preferred":[
        "Jhirubas"
    ],
    "name:nep_x_preferred":[
        "\u091d\u093f\u0930\u0941\u0935\u093e\u0938"
    ],
    "name:new_x_preferred":[
        "\u091d\u093f\u0930\u0941\u092c\u093e\u0938"
    ],
    "name:pol_x_preferred":[
        "Jhirubas"
    ],
    "wof:name":"Jhirubas",
    "wof:placetype":"locality"
},
  "geometry": {"coordinates":[83.93611999999997,27.79142],"type":"Point"}
}