{
  "type": "Feature",
  "properties": {
    "gn:admin1_code":"MR",
    "gn:admin2_code":"12",
    "gn:admin3_code":"53",
    "gn:admin4_code":"530039",
    "gn:asciiname":"Simagaun",
    "gn:country_code":"NP",
    "gn:dem":1839,
    "gn:feature_class":"P",
    "gn:feature_code":"PPLL",
    "gn:name":"Simagaun",
    "gn:population":0,
    "gn:timezone":"Asia/Kathmandu",
    "iso:country":"NP",
    "wof:name":"Simagaun",
    "wof:placetype":"locality"
},
  "geometry": {"coordinates":[82.53964999999999,28.43906],"type":"Point"}
}