{
  "type": "Feature",
  "properties": {
    "gn:admin1_code":"ER",
    "gn:admin2_code":"7.0",
    "gn:admin3_code":"8.0",
    "gn:admin4_code":"80028.0",
    "gn:asciiname":"Dhande",
    "gn:country_code":"NP",
    "gn:dem":1345,
    "gn:feature_class":"P",
    "gn:feature_code":"PPLL",
    "gn:name":"Dhande",
    "gn:population":0,
    "gn:timezone":"Asia/Kathmandu",
    "iso:country":"NP",
    "wof:name":"Dhande",
    "wof:placetype":"locality"
},
  "geometry": {"coordinates":[87.47814,27.1521],"type":"Point"}
}