{
  "type": "Feature",
  "properties": {
    "gn:admin1_code":"ER",
    "gn:admin2_code":"13",
    "gn:admin3_code":"12",
    "gn:admin4_code":"120024.0",
    "gn:asciiname":"Khuspu",
    "gn:country_code":"NP",
    "gn:dem":2221,
    "gn:feature_class":"P",
    "gn:feature_code":"PPLL",
    "gn:name":"Khuspu",
    "gn:population":0,
    "gn:timezone":"Asia/Kathmandu",
    "iso:country":"NP",
    "wof:name":"Khuspu",
    "wof:placetype":"locality"
},
  "geometry": {"coordinates":[86.34254,27.45036],"type":"Point"}
}