{
  "type": "Feature",
  "properties": {
    "gn:admin1_code":"CR",
    "gn:admin2_code":"1",
    "gn:admin3_code":"24.0",
    "gn:admin4_code":"240060.0",
    "gn:asciiname":"Khor Bhanjyang",
    "gn:country_code":"NP",
    "gn:dem":491,
    "gn:feature_class":"P",
    "gn:feature_code":"PPLL",
    "gn:name":"Khor Bhanjyang",
    "gn:population":0,
    "gn:timezone":"Asia/Kathmandu",
    "iso:country":"NP",
    "wof:name":"Khor Bhanjyang",
    "wof:placetype":"locality"
},
  "geometry": {"coordinates":[85.45515,27.40185],"type":"Point"}
}