{
  "type": "Feature",
  "properties": {
    "gn:admin1_code":"CR",
    "gn:admin2_code":"11",
    "gn:admin3_code":"35.0",
    "gn:admin4_code":"350028.0",
    "gn:asciiname":"Dherauli",
    "gn:country_code":"NP",
    "gn:dem":196,
    "gn:feature_class":"P",
    "gn:feature_code":"PPLL",
    "gn:name":"Dherauli",
    "gn:population":0,
    "gn:timezone":"Asia/Kathmandu",
    "iso:country":"NP",
    "wof:name":"Dherauli",
    "wof:placetype":"locality"
},
  "geometry": {"coordinates":[84.49415,27.54233],"type":"Point"}
}