{
  "type": "Feature",
  "properties": {
    "gn:admin1_code":"ER",
    "gn:admin2_code":"13",
    "gn:admin3_code":"16",
    "gn:admin4_code":"160010",
    "gn:asciiname":"Raghunathpur",
    "gn:country_code":"NP",
    "gn:dem":133,
    "gn:feature_class":"P",
    "gn:feature_code":"PPLL",
    "gn:name":"Raghunathpur",
    "gn:population":0,
    "gn:timezone":"Asia/Kathmandu",
    "iso:country":"NP",
    "name:bpy_x_preferred":[
        "\u09b0\u0998\u09c1\u09a8\u09be\u09a5\u09aa\u09c1\u09b0"
    ],
    "name:ceb_x_preferred":[
        "Raghunathpur"
    ],
    "name:fra_x_preferred":[
        "Raghunathpur"
    ],
    "name:hif_x_preferred":[
        "Raghunathpur"
    ],
    "name:new_x_preferred":[
        "\u0930\u0918\u0941\u0928\u093e\u0925\u092a\u0941\u0930"
    ],
    "name:nld_x_preferred":[
        "Raghunathpur"
    ],
    "name:pol_x_preferred":[
        "Raghunathpur"
    ],
    "name:swe_x_preferred":[
        "Raghunathpur"
    ],
    "wof:name":"Raghunathpur",
    "wof:placetype":"locality"
},
  "geometry": {"coordinates":[86.45838000000001,26.74672],"type":"Point"}
}