{
  "type": "Feature",
  "properties": {
    "gn:admin1_code":"CR",
    "gn:admin2_code":"1",
    "gn:admin3_code":"23",
    "gn:admin4_code":"230044",
    "gn:asciiname":"Uriyani",
    "gn:country_code":"NP",
    "gn:dem":1521,
    "gn:feature_class":"P",
    "gn:feature_code":"PPLL",
    "gn:name":"Uriyani",
    "gn:population":0,
    "gn:timezone":"Asia/Kathmandu",
    "iso:country":"NP",
    "wof:name":"Uriyani",
    "wof:placetype":"locality"
},
  "geometry": {"coordinates":[85.49879,27.86593],"type":"Point"}
}