{
  "type": "Feature",
  "properties": {
    "gn:admin1_code":"00",
    "gn:asciiname":"Khattar",
    "gn:country_code":"NP",
    "gn:dem":577,
    "gn:feature_class":"P",
    "gn:feature_code":"PPL",
    "gn:name":"Kha\u1e6d\u1e6d\u0101\u0303r",
    "gn:population":0,
    "gn:timezone":"Asia/Kathmandu",
    "iso:country":"NP",
    "name:und_x_variant":[
        "Kha\u1e6d\u1e6d\u0101\u0303r",
        "Kha\u1e6d\u1e6d\u0101nr"
    ],
    "wof:name":"Khattar",
    "wof:placetype":"locality"
},
  "geometry": {"coordinates":[85.88974,27.24914],"type":"Point"}
}