{
  "type": "Feature",
  "properties": {
    "gn:admin1_code":"FR",
    "gn:admin2_code":"9",
    "gn:admin3_code":"74",
    "gn:admin4_code":"740043",
    "gn:asciiname":"Adkatya",
    "gn:country_code":"NP",
    "gn:dem":643,
    "gn:feature_class":"P",
    "gn:feature_code":"PPLL",
    "gn:name":"Adkatya",
    "gn:population":0,
    "gn:timezone":"Asia/Kathmandu",
    "iso:country":"NP",
    "wof:name":"Adkatya",
    "wof:placetype":"locality"
},
  "geometry": {"coordinates":[80.27159,29.39962],"type":"Point"}
}