{
  "type": "Feature",
  "properties": {
    "gn:admin1_code":"CR",
    "gn:admin2_code":"1",
    "gn:admin3_code":"24.0",
    "gn:admin4_code":"240080.0",
    "gn:asciiname":"Maure Bhanjyang",
    "gn:country_code":"NP",
    "gn:dem":1671,
    "gn:feature_class":"P",
    "gn:feature_code":"PPLL",
    "gn:name":"Maure Bhanjyang",
    "gn:population":0,
    "gn:timezone":"Asia/Kathmandu",
    "iso:country":"NP",
    "wof:name":"Maure Bhanjyang",
    "wof:placetype":"locality"
},
  "geometry": {"coordinates":[85.74618000000002,27.53496],"type":"Point"}
}