{
  "type": "Feature",
  "properties": {
    "gn:admin1_code":"WR",
    "gn:admin2_code":"4.0",
    "gn:admin3_code":"38.0",
    "gn:admin4_code":"380032.0",
    "gn:asciiname":"Gijandanda",
    "gn:country_code":"NP",
    "gn:dem":644,
    "gn:feature_class":"P",
    "gn:feature_code":"PPLL",
    "gn:name":"Gijandanda",
    "gn:population":0,
    "gn:timezone":"Asia/Kathmandu",
    "iso:country":"NP",
    "wof:name":"Gijandanda",
    "wof:placetype":"locality"
},
  "geometry": {"coordinates":[84.05488000000003,27.94352],"type":"Point"}
}