{
  "type": "Feature",
  "properties": {
    "gn:admin1_code":"MR",
    "gn:admin2_code":"6",
    "gn:admin3_code":"62.0",
    "gn:admin4_code":"620009.0",
    "gn:asciiname":"Khair",
    "gn:country_code":"NP",
    "gn:dem":2364,
    "gn:feature_class":"P",
    "gn:feature_code":"PPLL",
    "gn:name":"Khair",
    "gn:population":0,
    "gn:timezone":"Asia/Kathmandu",
    "iso:country":"NP",
    "name:bpy_x_preferred":[
        "\u0996\u09be\u0987\u09b0"
    ],
    "name:ceb_x_preferred":[
        "Khair"
    ],
    "name:ita_x_preferred":[
        "Khair"
    ],
    "name:mlg_x_preferred":[
        "Khair"
    ],
    "name:msa_x_preferred":[
        "Khair"
    ],
    "name:new_x_preferred":[
        "\u0916\u0948\u0930"
    ],
    "name:nld_x_preferred":[
        "Khair"
    ],
    "name:ori_x_preferred":[
        "\u0b16\u0b47\u0b30\u0b4d"
    ],
    "name:pnb_x_preferred":[
        "\u06a9\u06be\u06cc\u0631"
    ],
    "name:pol_x_preferred":[
        "Khair"
    ],
    "name:por_x_preferred":[
        "Khair"
    ],
    "name:urd_x_preferred":[
        "\u06a9\u06be\u06cc\u0631"
    ],
    "name:vie_x_preferred":[
        "Khair"
    ],
    "wof:name":"Khair",
    "wof:placetype":"locality"
},
  "geometry": {"coordinates":[82.65266,29.01557],"type":"Point"}
}