{
  "type": "Feature",
  "properties": {
    "gn:admin1_code":"MR",
    "gn:admin2_code":"6",
    "gn:admin3_code":"62.0",
    "gn:admin4_code":"620009.0",
    "gn:asciiname":"Khair",
    "gn:country_code":"NP",
    "gn:dem":2364,
    "gn:feature_class":"P",
    "gn:feature_code":"PPLL",
    "gn:name":"Khair",
    "gn:population":0,
    "gn:timezone":"Asia/Kathmandu",
    "iso:country":"NP",
    "wof:name":"Khair",
    "wof:placetype":"locality"
},
  "geometry": {"coordinates":[82.65266,29.01557],"type":"Point"}
}