{
  "type": "Feature",
  "properties": {
    "gn:admin1_code":"CR",
    "gn:admin2_code":"11",
    "gn:admin3_code":"32",
    "gn:admin4_code":"320074",
    "gn:asciiname":"Rajawara",
    "gn:country_code":"NP",
    "gn:dem":87,
    "gn:feature_class":"P",
    "gn:feature_code":"PPLL",
    "gn:name":"Rajawara",
    "gn:population":0,
    "gn:timezone":"Asia/Kathmandu",
    "iso:country":"NP",
    "wof:name":"Rajawara",
    "wof:placetype":"locality"
},
  "geometry": {"coordinates":[85.35091,26.87966],"type":"Point"}
}