{
  "type": "Feature",
  "properties": {
    "gn:admin1_code":"MR",
    "gn:admin2_code":"12",
    "gn:admin3_code":"53",
    "gn:admin4_code":"530037",
    "gn:asciiname":"Pang",
    "gn:country_code":"NP",
    "gn:dem":1547,
    "gn:feature_class":"P",
    "gn:feature_code":"PPLL",
    "gn:name":"Pang",
    "gn:population":0,
    "gn:timezone":"Asia/Kathmandu",
    "iso:country":"NP",
    "name:ceb_x_preferred":[
        "Pang"
    ],
    "name:deu_x_preferred":[
        "Pang"
    ],
    "name:fra_x_preferred":[
        "Pang"
    ],
    "name:ita_x_preferred":[
        "Pang"
    ],
    "name:pol_x_preferred":[
        "Pang"
    ],
    "name:por_x_preferred":[
        "Pang"
    ],
    "name:rus_x_preferred":[
        "\u041f\u044d\u043d\u0433"
    ],
    "name:swe_x_preferred":[
        "Pang"
    ],
    "wof:name":"Pang",
    "wof:placetype":"locality"
},
  "geometry": {"coordinates":[82.85163,28.28204],"type":"Point"}
}