{
  "type": "Feature",
  "properties": {
    "gn:admin1_code":"MR",
    "gn:admin2_code":"12",
    "gn:admin3_code":"54",
    "gn:admin4_code":"540010",
    "gn:asciiname":"Salleri",
    "gn:country_code":"NP",
    "gn:dem":1487,
    "gn:feature_class":"P",
    "gn:feature_code":"PPLL",
    "gn:name":"Salleri",
    "gn:population":0,
    "gn:timezone":"Asia/Kathmandu",
    "iso:country":"NP",
    "name:ceb_x_preferred":[
        "Salleri"
    ],
    "name:deu_x_preferred":[
        "Salleri"
    ],
    "name:pol_x_preferred":[
        "Salleri"
    ],
    "wof:name":"Salleri",
    "wof:placetype":"locality"
},
  "geometry": {"coordinates":[82.38985,28.68548],"type":"Point"}
}