{
  "type": "Feature",
  "properties": {
    "gn:admin1_code":"MR",
    "gn:admin2_code":"12",
    "gn:admin3_code":"53",
    "gn:admin4_code":"530039",
    "gn:asciiname":"Selachar",
    "gn:country_code":"NP",
    "gn:dem":1993,
    "gn:feature_class":"P",
    "gn:feature_code":"PPLL",
    "gn:name":"Selachar",
    "gn:population":0,
    "gn:timezone":"Asia/Kathmandu",
    "iso:country":"NP",
    "wof:name":"Selachar",
    "wof:placetype":"locality"
},
  "geometry": {"coordinates":[82.55492,28.47084000000001],"type":"Point"}
}