{
  "type": "Feature",
  "properties": {
    "gn:admin1_code":"CR",
    "gn:admin2_code":"11",
    "gn:admin3_code":"31",
    "gn:admin4_code":"310019.0",
    "gn:asciiname":"Pandamar",
    "gn:country_code":"NP",
    "gn:dem":394,
    "gn:feature_class":"P",
    "gn:feature_code":"PPLL",
    "gn:name":"Pandamar",
    "gn:population":0,
    "gn:timezone":"Asia/Kathmandu",
    "iso:country":"NP",
    "wof:name":"Pandamar",
    "wof:placetype":"locality"
},
  "geometry": {"coordinates":[85.1174,27.33334],"type":"Point"}
}