{
  "type": "Feature",
  "properties": {
    "gn:admin1_code":"MR",
    "gn:admin2_code":"12",
    "gn:admin3_code":"55",
    "gn:admin4_code":"550028",
    "gn:asciiname":"Mandanda",
    "gn:country_code":"NP",
    "gn:dem":1265,
    "gn:feature_class":"P",
    "gn:feature_code":"PPLL",
    "gn:name":"Mandanda",
    "gn:population":0,
    "gn:timezone":"Asia/Kathmandu",
    "iso:country":"NP",
    "wof:name":"Mandanda",
    "wof:placetype":"locality"
},
  "geometry": {"coordinates":[82.06834000000001,28.40962],"type":"Point"}
}