{
  "type": "Feature",
  "properties": {
    "gn:admin1_code":"MR",
    "gn:admin2_code":"12",
    "gn:admin3_code":"55",
    "gn:admin4_code":"550006",
    "gn:asciiname":"Surkhala",
    "gn:country_code":"NP",
    "gn:dem":1335,
    "gn:feature_class":"P",
    "gn:feature_code":"PPLL",
    "gn:name":"Surkhala",
    "gn:population":0,
    "gn:timezone":"Asia/Kathmandu",
    "iso:country":"NP",
    "wof:name":"Surkhala",
    "wof:placetype":"locality"
},
  "geometry": {"coordinates":[82.10760000000001,28.45702],"type":"Point"}
}