{
  "type": "Feature",
  "properties": {
    "gn:admin1_code":"WR",
    "gn:admin2_code":"4.0",
    "gn:admin3_code":"39.0",
    "gn:admin4_code":"390022.0",
    "gn:asciiname":"Charghare",
    "gn:country_code":"NP",
    "gn:dem":1415,
    "gn:feature_class":"P",
    "gn:feature_code":"PPLL",
    "gn:name":"Charghare",
    "gn:population":0,
    "gn:timezone":"Asia/Kathmandu",
    "iso:country":"NP",
    "wof:name":"Charghare",
    "wof:placetype":"locality"
},
  "geometry": {"coordinates":[83.91525,28.17147000000001],"type":"Point"}
}