{
  "type": "Feature",
  "properties": {
    "gn:admin1_code":"00",
    "gn:asciiname":"Taulihawa",
    "gn:country_code":"NP",
    "gn:dem":105,
    "gn:feature_class":"P",
    "gn:feature_code":"PPL",
    "gn:name":"Taulihaw\u0101",
    "gn:population":0,
    "gn:timezone":"Asia/Kathmandu",
    "iso:country":"NP",
    "name:und_x_variant":[
        "Piprahwa",
        "Kapilvastu",
        "Taulia",
        "Taulihaw\u0101"
    ],
    "wof:name":"Taulihawa",
    "wof:placetype":"locality"
},
  "geometry": {"coordinates":[83.05356,27.5445],"type":"Point"}
}