{
  "type": "Feature",
  "properties": {
    "gn:admin1_code":"WR",
    "gn:admin2_code":"4",
    "gn:admin3_code":"37",
    "gn:admin4_code":"370053",
    "gn:asciiname":"Sinduredhunga",
    "gn:country_code":"NP",
    "gn:dem":1593,
    "gn:feature_class":"P",
    "gn:feature_code":"PPLL",
    "gn:name":"Sinduredhunga",
    "gn:population":0,
    "gn:timezone":"Asia/Kathmandu",
    "iso:country":"NP",
    "wof:name":"Sinduredhunga",
    "wof:placetype":"locality"
},
  "geometry": {"coordinates":[84.32472,28.17857],"type":"Point"}
}