{
  "type": "Feature",
  "properties": {
    "gn:admin1_code":"00",
    "gn:asciiname":"Nadhitol",
    "gn:country_code":"NP",
    "gn:dem":105,
    "gn:feature_class":"P",
    "gn:feature_code":"PPL",
    "gn:name":"N\u0101\u1e0dhi\u0307\u0304\u1e6dol",
    "gn:population":0,
    "gn:timezone":"Asia/Kathmandu",
    "iso:country":"NP",
    "name:nep_x_preferred":[
        "N\u0101\u1e0dhi\u0307\u0304\u1e6dol"
    ],
    "wof:name":"Nadhitol",
    "wof:placetype":"locality"
},
  "geometry": {"coordinates":[85.62576999999997,26.93794],"type":"Point"}
}