{
  "type": "Feature",
  "properties": {
    "gn:admin1_code":"CR",
    "gn:admin2_code":"5",
    "gn:admin3_code":"21",
    "gn:admin4_code":"210044.0",
    "gn:asciiname":"Kusumbot",
    "gn:country_code":"NP",
    "gn:dem":1201,
    "gn:feature_class":"P",
    "gn:feature_code":"PPLL",
    "gn:name":"Kusumbot",
    "gn:population":0,
    "gn:timezone":"Asia/Kathmandu",
    "iso:country":"NP",
    "wof:name":"Kusumbot",
    "wof:placetype":"locality"
},
  "geometry": {"coordinates":[85.88208,27.43536],"type":"Point"}
}