{
  "type": "Feature",
  "properties": {
    "gn:admin1_code":"WR",
    "gn:admin2_code":"4",
    "gn:admin3_code":"40.0",
    "gn:admin4_code":"400036.0",
    "gn:asciiname":"Barahathok",
    "gn:country_code":"NP",
    "gn:dem":901,
    "gn:feature_class":"P",
    "gn:feature_code":"PPLL",
    "gn:name":"Barahathok",
    "gn:population":0,
    "gn:timezone":"Asia/Kathmandu",
    "iso:country":"NP",
    "wof:name":"Barahathok",
    "wof:placetype":"locality"
},
  "geometry": {"coordinates":[84.13109,28.14551],"type":"Point"}
}