{
  "type": "Feature",
  "properties": {
    "gn:admin1_code":"WR",
    "gn:admin2_code":"8",
    "gn:admin3_code":"47",
    "gn:admin4_code":"470010",
    "gn:asciiname":"Gophek",
    "gn:country_code":"NP",
    "gn:dem":763,
    "gn:feature_class":"P",
    "gn:feature_code":"PPLL",
    "gn:name":"Gophek",
    "gn:population":0,
    "gn:timezone":"Asia/Kathmandu",
    "iso:country":"NP",
    "wof:name":"Gophek",
    "wof:placetype":"locality"
},
  "geometry": {"coordinates":[83.58803,27.84337],"type":"Point"}
}