{
  "type": "Feature",
  "properties": {
    "gn:admin1_code":"00",
    "gn:asciiname":"Gadgau",
    "gn:country_code":"NP",
    "gn:dem":109,
    "gn:feature_class":"P",
    "gn:feature_code":"PPL",
    "gn:name":"Ga\u1e0dg\u0101\u0169",
    "gn:population":0,
    "gn:timezone":"Asia/Kathmandu",
    "iso:country":"NP",
    "name:nep_x_preferred":[
        "Ga\u1e0dg\u0101\u0169"
    ],
    "wof:name":"Gadgau",
    "wof:placetype":"locality"
},
  "geometry": {"coordinates":[87.39928,26.61255],"type":"Point"}
}