{
  "type": "Feature",
  "properties": {
    "gn:admin1_code":"WR",
    "gn:admin2_code":"8",
    "gn:admin3_code":"48",
    "gn:admin4_code":"480020",
    "gn:asciiname":"Gulmigaun",
    "gn:country_code":"NP",
    "gn:dem":168,
    "gn:feature_class":"P",
    "gn:feature_code":"PPLL",
    "gn:name":"Gulmigaun",
    "gn:population":0,
    "gn:timezone":"Asia/Kathmandu",
    "iso:country":"NP",
    "wof:name":"Gulmigaun",
    "wof:placetype":"locality"
},
  "geometry": {"coordinates":[83.89005999999998,27.57434000000001],"type":"Point"}
}