{
  "type": "Feature",
  "properties": {
    "gn:admin1_code":"WR",
    "gn:admin2_code":"4",
    "gn:admin3_code":"36.0",
    "gn:admin4_code":"360062.0",
    "gn:asciiname":"Patiswanra",
    "gn:country_code":"NP",
    "gn:dem":1357,
    "gn:feature_class":"P",
    "gn:feature_code":"PPLL",
    "gn:name":"Patiswanra",
    "gn:population":0,
    "gn:timezone":"Asia/Kathmandu",
    "iso:country":"NP",
    "wof:name":"Patiswanra",
    "wof:placetype":"locality"
},
  "geometry": {"coordinates":[84.6824,27.89589],"type":"Point"}
}