{
  "type": "Feature",
  "properties": {
    "gn:admin1_code":"FR",
    "gn:admin2_code":"14",
    "gn:admin3_code":"71.0",
    "gn:admin4_code":"710015.0",
    "gn:asciiname":"Neta Katan",
    "gn:country_code":"NP",
    "gn:dem":296,
    "gn:feature_class":"P",
    "gn:feature_code":"PPLL",
    "gn:name":"Neta Katan",
    "gn:population":0,
    "gn:timezone":"Asia/Kathmandu",
    "iso:country":"NP",
    "wof:name":"Neta Katan",
    "wof:placetype":"locality"
},
  "geometry": {"coordinates":[80.63859000000002,28.84629],"type":"Point"}
}