{
  "type": "Feature",
  "properties": {
    "gn:admin1_code":"CR",
    "gn:admin2_code":"1",
    "gn:admin3_code":"28",
    "gn:admin4_code":"280003",
    "gn:asciiname":"Muilambra",
    "gn:country_code":"NP",
    "gn:dem":1473,
    "gn:feature_class":"P",
    "gn:feature_code":"PPLL",
    "gn:name":"Muilambra",
    "gn:population":0,
    "gn:timezone":"Asia/Kathmandu",
    "iso:country":"NP",
    "wof:name":"Muilambra",
    "wof:placetype":"locality"
},
  "geometry": {"coordinates":[85.02951,28.00804],"type":"Point"}
}