{
  "type": "Feature",
  "properties": {
    "gn:admin1_code":"WR",
    "gn:admin2_code":"8",
    "gn:admin3_code":"51.0",
    "gn:admin4_code":"510041.0",
    "gn:asciiname":"Amarahi",
    "gn:country_code":"NP",
    "gn:dem":1317,
    "gn:feature_class":"P",
    "gn:feature_code":"PPLL",
    "gn:name":"Amarahi",
    "gn:population":0,
    "gn:timezone":"Asia/Kathmandu",
    "iso:country":"NP",
    "wof:name":"Amarahi",
    "wof:placetype":"locality"
},
  "geometry": {"coordinates":[83.07748000000002,27.86117],"type":"Point"}
}