{
  "type": "Feature",
  "properties": {
    "gn:admin1_code":"MR",
    "gn:admin2_code":"2.0",
    "gn:admin3_code":"58.0",
    "gn:admin4_code":"580017.0",
    "gn:asciiname":"Guptipur",
    "gn:country_code":"NP",
    "gn:dem":154,
    "gn:feature_class":"P",
    "gn:feature_code":"PPLL",
    "gn:name":"Guptipur",
    "gn:population":0,
    "gn:timezone":"Asia/Kathmandu",
    "iso:country":"NP",
    "wof:name":"Guptipur",
    "wof:placetype":"locality"
},
  "geometry": {"coordinates":[81.20585,28.46139],"type":"Point"}
}