{
  "type": "Feature",
  "properties": {
    "gn:admin1_code":"CR",
    "gn:admin2_code":"1",
    "gn:admin3_code":"23",
    "gn:admin4_code":"230045.0",
    "gn:asciiname":"Khiping",
    "gn:country_code":"NP",
    "gn:dem":1274,
    "gn:feature_class":"P",
    "gn:feature_code":"PPLL",
    "gn:name":"Khiping",
    "gn:population":0,
    "gn:timezone":"Asia/Kathmandu",
    "iso:country":"NP",
    "wof:name":"Khiping",
    "wof:placetype":"locality"
},
  "geometry": {"coordinates":[85.86943000000002,27.81562000000001],"type":"Point"}
}