{
  "type": "Feature",
  "properties": {
    "gn:admin1_code":"ER",
    "gn:admin2_code":"13",
    "gn:admin3_code":"12",
    "gn:admin4_code":"120054",
    "gn:asciiname":"Keureni",
    "gn:country_code":"NP",
    "gn:dem":1160,
    "gn:feature_class":"P",
    "gn:feature_code":"PPLL",
    "gn:name":"Keureni",
    "gn:population":0,
    "gn:timezone":"Asia/Kathmandu",
    "iso:country":"NP",
    "wof:name":"Keureni",
    "wof:placetype":"locality"
},
  "geometry": {"coordinates":[86.55158,27.27026],"type":"Point"}
}