{
  "type": "Feature",
  "properties": {
    "gn:admin1_code":"MR",
    "gn:admin2_code":"12",
    "gn:admin3_code":"55",
    "gn:admin4_code":"550017",
    "gn:asciiname":"Rayang",
    "gn:country_code":"NP",
    "gn:dem":358,
    "gn:feature_class":"P",
    "gn:feature_code":"PPLL",
    "gn:name":"Rayang",
    "gn:population":0,
    "gn:timezone":"Asia/Kathmandu",
    "iso:country":"NP",
    "wof:name":"Rayang",
    "wof:placetype":"locality"
},
  "geometry": {"coordinates":[81.81469,28.30839000000001],"type":"Point"}
}