{
  "type": "Feature",
  "properties": {
    "gn:admin1_code":"MR",
    "gn:admin2_code":"2.0",
    "gn:admin3_code":"59.0",
    "gn:admin4_code":"590032.0",
    "gn:asciiname":"Jnawali Khoriya",
    "gn:country_code":"NP",
    "gn:dem":1118,
    "gn:feature_class":"P",
    "gn:feature_code":"PPLL",
    "gn:name":"Jnawali Khoriya",
    "gn:population":0,
    "gn:timezone":"Asia/Kathmandu",
    "iso:country":"NP",
    "wof:name":"Jnawali Khoriya",
    "wof:placetype":"locality"
},
  "geometry": {"coordinates":[81.64896,28.42647],"type":"Point"}
}