{
  "type": "Feature",
  "properties": {
    "gn:admin1_code":"CR",
    "gn:admin2_code":"1",
    "gn:admin3_code":"28",
    "gn:admin4_code":"280045",
    "gn:asciiname":"Mahadevphant",
    "gn:country_code":"NP",
    "gn:dem":447,
    "gn:feature_class":"P",
    "gn:feature_code":"PPLL",
    "gn:name":"Mahadevphant",
    "gn:population":0,
    "gn:timezone":"Asia/Kathmandu",
    "iso:country":"NP",
    "wof:name":"Mahadevphant",
    "wof:placetype":"locality"
},
  "geometry": {"coordinates":[85.06437,27.85725],"type":"Point"}
}