{
  "type": "Feature",
  "properties": {
    "gn:admin1_code":"CR",
    "gn:admin2_code":"1",
    "gn:admin3_code":"23",
    "gn:admin4_code":"230007",
    "gn:asciiname":"Sunchaur",
    "gn:country_code":"NP",
    "gn:dem":1753,
    "gn:feature_class":"P",
    "gn:feature_code":"PPLL",
    "gn:name":"Sunchaur",
    "gn:population":0,
    "gn:timezone":"Asia/Kathmandu",
    "iso:country":"NP",
    "wof:name":"Sunchaur",
    "wof:placetype":"locality"
},
  "geometry": {"coordinates":[85.6156,28.00429],"type":"Point"}
}