{
  "type": "Feature",
  "properties": {
    "gn:admin1_code":"MR",
    "gn:admin2_code":"2.0",
    "gn:admin3_code":"59.0",
    "gn:admin4_code":"590014.0",
    "gn:asciiname":"Dob",
    "gn:country_code":"NP",
    "gn:dem":1109,
    "gn:feature_class":"P",
    "gn:feature_code":"PPLL",
    "gn:name":"Dob",
    "gn:population":0,
    "gn:timezone":"Asia/Kathmandu",
    "iso:country":"NP",
    "name:bos_x_preferred":[
        "Dob"
    ],
    "name:ceb_x_preferred":[
        "Dob"
    ],
    "name:hun_x_preferred":[
        "Dob"
    ],
    "name:slv_x_preferred":[
        "Dob"
    ],
    "name:swe_x_preferred":[
        "Dob"
    ],
    "wof:name":"Dob",
    "wof:placetype":"locality"
},
  "geometry": {"coordinates":[81.96565,28.4091],"type":"Point"}
}