{
  "type": "Feature",
  "properties": {
    "gn:admin1_code":"WR",
    "gn:admin2_code":"4",
    "gn:admin3_code":"40.0",
    "gn:admin4_code":"400024.0",
    "gn:asciiname":"Ghipli",
    "gn:country_code":"NP",
    "gn:dem":2023,
    "gn:feature_class":"P",
    "gn:feature_code":"PPLL",
    "gn:name":"Ghipli",
    "gn:population":0,
    "gn:timezone":"Asia/Kathmandu",
    "iso:country":"NP",
    "wof:name":"Ghipli",
    "wof:placetype":"locality"
},
  "geometry": {"coordinates":[83.87985999999999,28.3963],"type":"Point"}
}