{
  "type": "Feature",
  "properties": {
    "gn:admin1_code":"MR",
    "gn:admin2_code":"12",
    "gn:admin3_code":"55",
    "gn:admin4_code":"550016",
    "gn:asciiname":"Turture",
    "gn:country_code":"NP",
    "gn:dem":1457,
    "gn:feature_class":"P",
    "gn:feature_code":"PPLL",
    "gn:name":"Turture",
    "gn:population":0,
    "gn:timezone":"Asia/Kathmandu",
    "iso:country":"NP",
    "wof:name":"Turture",
    "wof:placetype":"locality"
},
  "geometry": {"coordinates":[82.21838000000002,28.50397],"type":"Point"}
}