{
  "type": "Feature",
  "properties": {
    "gn:admin1_code":"MR",
    "gn:admin2_code":"12",
    "gn:admin3_code":"55",
    "gn:admin4_code":"550045",
    "gn:asciiname":"Rautegaun",
    "gn:country_code":"NP",
    "gn:dem":1673,
    "gn:feature_class":"P",
    "gn:feature_code":"PPLL",
    "gn:name":"Rautegaun",
    "gn:population":0,
    "gn:timezone":"Asia/Kathmandu",
    "iso:country":"NP",
    "wof:name":"Rautegaun",
    "wof:placetype":"locality"
},
  "geometry": {"coordinates":[82.23684,28.40329],"type":"Point"}
}