{
  "type": "Feature",
  "properties": {
    "gn:admin1_code":"WR",
    "gn:admin2_code":"4.0",
    "gn:admin3_code":"39.0",
    "gn:admin4_code":"390021.0",
    "gn:asciiname":"Lamidanda",
    "gn:country_code":"NP",
    "gn:dem":1331,
    "gn:feature_class":"P",
    "gn:feature_code":"PPLL",
    "gn:name":"Lamidanda",
    "gn:population":0,
    "gn:timezone":"Asia/Kathmandu",
    "iso:country":"NP",
    "name:jpn_x_preferred":[
        "\u30e9\u30df\u30c0\u30f3\u30c0"
    ],
    "name:pol_x_preferred":[
        "Lamidada"
    ],
    "wof:name":"Lamidanda",
    "wof:placetype":"locality"
},
  "geometry": {"coordinates":[83.8189,28.13574],"type":"Point"}
}