{
  "type": "Feature",
  "properties": {
    "gn:admin1_code":"MR",
    "gn:admin2_code":"12",
    "gn:admin3_code":"54",
    "gn:admin4_code":"540006",
    "gn:asciiname":"Mangraha",
    "gn:country_code":"NP",
    "gn:dem":856,
    "gn:feature_class":"P",
    "gn:feature_code":"PPLL",
    "gn:name":"Mangraha",
    "gn:population":0,
    "gn:timezone":"Asia/Kathmandu",
    "iso:country":"NP",
    "wof:name":"Mangraha",
    "wof:placetype":"locality"
},
  "geometry": {"coordinates":[82.21408000000002,28.64871],"type":"Point"}
}