{
  "type": "Feature",
  "properties": {
    "gn:admin1_code":"WR",
    "gn:admin2_code":"4",
    "gn:admin3_code":"37",
    "gn:admin4_code":"370034",
    "gn:asciiname":"Shikhara",
    "gn:country_code":"NP",
    "gn:dem":625,
    "gn:feature_class":"P",
    "gn:feature_code":"PPLL",
    "gn:name":"Shikhara",
    "gn:population":0,
    "gn:timezone":"Asia/Kathmandu",
    "iso:country":"NP",
    "wof:name":"Shikhara",
    "wof:placetype":"locality"
},
  "geometry": {"coordinates":[84.30714999999999,28.11326],"type":"Point"}
}