{
  "type": "Feature",
  "properties": {
    "gn:admin1_code":"WR",
    "gn:admin2_code":"4",
    "gn:admin3_code":"37",
    "gn:admin4_code":"370034",
    "gn:asciiname":"Shikhara",
    "gn:country_code":"NP",
    "gn:dem":625,
    "gn:feature_class":"P",
    "gn:feature_code":"PPLL",
    "gn:name":"Shikhara",
    "gn:population":0,
    "gn:timezone":"Asia/Kathmandu",
    "iso:country":"NP",
    "name:deu_x_preferred":[
        "Shikhara"
    ],
    "name:fra_x_preferred":[
        "Shikhara"
    ],
    "name:hun_x_preferred":[
        "Sikhara"
    ],
    "name:ita_x_preferred":[
        "Sikhara"
    ],
    "name:pol_x_preferred":[
        "\u015aikhara"
    ],
    "name:rus_x_preferred":[
        "\u0428\u0438\u043a\u0445\u0430\u0440\u0430"
    ],
    "name:slv_x_preferred":[
        "\u0160ikara"
    ],
    "name:spa_x_preferred":[
        "Sikhara"
    ],
    "name:sqi_x_preferred":[
        "Shihara"
    ],
    "name:swe_x_preferred":[
        "Sikhara"
    ],
    "name:tam_x_preferred":[
        "\u0bb5\u0bbf\u0bae\u0bbe\u0ba9\u0bae\u0bcd"
    ],
    "name:tha_x_preferred":[
        "\u0e28\u0e34\u0e02\u0e23"
    ],
    "name:ukr_x_preferred":[
        "\u0428\u0456\u043a\u0445\u0430\u0440\u0430"
    ],
    "wof:name":"Shikhara",
    "wof:placetype":"locality"
},
  "geometry": {"coordinates":[84.30714999999999,28.11326],"type":"Point"}
}