{
  "type": "Feature",
  "properties": {
    "gn:admin1_code":"ER",
    "gn:admin2_code":"13",
    "gn:admin3_code":"13",
    "gn:admin4_code":"130071",
    "gn:asciiname":"Riska",
    "gn:country_code":"NP",
    "gn:dem":1714,
    "gn:feature_class":"P",
    "gn:feature_code":"PPLL",
    "gn:name":"Riska",
    "gn:population":0,
    "gn:timezone":"Asia/Kathmandu",
    "iso:country":"NP",
    "name:nor_x_preferred":[
        "Riska"
    ],
    "wof:name":"Riska",
    "wof:placetype":"locality"
},
  "geometry": {"coordinates":[86.86934000000002,27.38105],"type":"Point"}
}