{
  "type": "Feature",
  "properties": {
    "gn:admin1_code":"MR",
    "gn:admin2_code":"12",
    "gn:admin3_code":"56.0",
    "gn:admin4_code":"560012.0",
    "gn:asciiname":"Raharpur",
    "gn:country_code":"NP",
    "gn:dem":546,
    "gn:feature_class":"P",
    "gn:feature_code":"PPLL",
    "gn:name":"Raharpur",
    "gn:population":0,
    "gn:timezone":"Asia/Kathmandu",
    "iso:country":"NP",
    "wof:name":"Raharpur",
    "wof:placetype":"locality"
},
  "geometry": {"coordinates":[82.17665,28.07957],"type":"Point"}
}