{
  "type": "Feature",
  "properties": {
    "gn:admin1_code":"FR",
    "gn:admin2_code":"14",
    "gn:admin3_code":"69",
    "gn:admin4_code":"690028",
    "gn:asciiname":"Gajara",
    "gn:country_code":"NP",
    "gn:dem":961,
    "gn:feature_class":"P",
    "gn:feature_code":"PPLL",
    "gn:name":"Gajara",
    "gn:population":0,
    "gn:timezone":"Asia/Kathmandu",
    "iso:country":"NP",
    "wof:name":"Gajara",
    "wof:placetype":"locality"
},
  "geometry": {"coordinates":[81.25951999999999,29.21282],"type":"Point"}
}