{
  "type": "Feature",
  "properties": {
    "gn:admin1_code":"FR",
    "gn:admin2_code":"9",
    "gn:admin3_code":"74",
    "gn:admin4_code":"740015",
    "gn:asciiname":"Haredakhan",
    "gn:country_code":"NP",
    "gn:dem":739,
    "gn:feature_class":"P",
    "gn:feature_code":"PPLL",
    "gn:name":"Haredakhan",
    "gn:population":0,
    "gn:timezone":"Asia/Kathmandu",
    "iso:country":"NP",
    "wof:name":"Haredakhan",
    "wof:placetype":"locality"
},
  "geometry": {"coordinates":[80.82993,29.37803],"type":"Point"}
}