{
  "type": "Feature",
  "properties": {
    "gn:admin1_code":"CR",
    "gn:admin2_code":"5",
    "gn:admin3_code":"19",
    "gn:admin4_code":"190040",
    "gn:asciiname":"Nayarod",
    "gn:country_code":"NP",
    "gn:dem":144,
    "gn:feature_class":"P",
    "gn:feature_code":"PPLL",
    "gn:name":"Nayarod",
    "gn:population":0,
    "gn:timezone":"Asia/Kathmandu",
    "iso:country":"NP",
    "wof:name":"Nayarod",
    "wof:placetype":"locality"
},
  "geometry": {"coordinates":[85.53041,27.09841],"type":"Point"}
}