{
  "type": "Feature",
  "properties": {
    "gn:admin1_code":"MR",
    "gn:admin2_code":"12",
    "gn:admin3_code":"54",
    "gn:admin4_code":"540039",
    "gn:asciiname":"Pakhapani",
    "gn:country_code":"NP",
    "gn:dem":2156,
    "gn:feature_class":"P",
    "gn:feature_code":"PPLL",
    "gn:name":"Pakhapani",
    "gn:population":0,
    "gn:timezone":"Asia/Kathmandu",
    "iso:country":"NP",
    "wof:name":"Pakhapani",
    "wof:placetype":"locality"
},
  "geometry": {"coordinates":[82.67428000000002,28.76863],"type":"Point"}
}