{
  "type": "Feature",
  "properties": {
    "gn:admin1_code":"CR",
    "gn:admin2_code":"1",
    "gn:admin3_code":"28",
    "gn:admin4_code":"280029",
    "gn:asciiname":"Bhyagute Bisan",
    "gn:country_code":"NP",
    "gn:dem":1145,
    "gn:feature_class":"P",
    "gn:feature_code":"PPLL",
    "gn:name":"Bhyagute Bisan",
    "gn:population":0,
    "gn:timezone":"Asia/Kathmandu",
    "iso:country":"NP",
    "wof:name":"Bhyagute Bisan",
    "wof:placetype":"locality"
},
  "geometry": {"coordinates":[85.11866999999999,27.95516],"type":"Point"}
}