{
  "type": "Feature",
  "properties": {
    "gn:admin1_code":"ER",
    "gn:admin2_code":"13",
    "gn:admin3_code":"11",
    "gn:admin4_code":"110024",
    "gn:asciiname":"Chhuphu",
    "gn:country_code":"NP",
    "gn:dem":5344,
    "gn:feature_class":"P",
    "gn:feature_code":"PPLL",
    "gn:name":"Chhuphu",
    "gn:population":0,
    "gn:timezone":"Asia/Kathmandu",
    "iso:country":"NP",
    "wof:name":"Chhuphu",
    "wof:placetype":"locality"
},
  "geometry": {"coordinates":[86.60318000000002,27.92095],"type":"Point"}
}