{
  "type": "Feature",
  "properties": {
    "gn:admin1_code":"CR",
    "gn:admin2_code":"1",
    "gn:admin3_code":"23",
    "gn:admin4_code":"230035.0",
    "gn:asciiname":"Godargaun",
    "gn:country_code":"NP",
    "gn:dem":1307,
    "gn:feature_class":"P",
    "gn:feature_code":"PPLL",
    "gn:name":"Godargaun",
    "gn:population":0,
    "gn:timezone":"Asia/Kathmandu",
    "iso:country":"NP",
    "wof:name":"Godargaun",
    "wof:placetype":"locality"
},
  "geometry": {"coordinates":[85.76636999999999,27.74505],"type":"Point"}
}