{
  "type": "Feature",
  "properties": {
    "gn:admin1_code":"FR",
    "gn:admin2_code":"14.0",
    "gn:admin3_code":"67.0",
    "gn:admin4_code":"670008.0",
    "gn:asciiname":"Sinnekot",
    "gn:country_code":"NP",
    "gn:dem":1909,
    "gn:feature_class":"P",
    "gn:feature_code":"PPLL",
    "gn:name":"Sinnekot",
    "gn:population":0,
    "gn:timezone":"Asia/Kathmandu",
    "iso:country":"NP",
    "wof:name":"Sinnekot",
    "wof:placetype":"locality"
},
  "geometry": {"coordinates":[81.35386,29.29841],"type":"Point"}
}