{
  "type": "Feature",
  "properties": {
    "gn:admin1_code":"WR",
    "gn:admin2_code":"4",
    "gn:admin3_code":"37",
    "gn:admin4_code":"370053",
    "gn:asciiname":"Sindure",
    "gn:country_code":"NP",
    "gn:dem":1387,
    "gn:feature_class":"P",
    "gn:feature_code":"PPLL",
    "gn:name":"Sindure",
    "gn:population":0,
    "gn:timezone":"Asia/Kathmandu",
    "iso:country":"NP",
    "name:ceb_x_preferred":[
        "Sindure"
    ],
    "name:fra_x_preferred":[
        "Sindure"
    ],
    "name:mai_x_preferred":[
        "\u0938\u093f\u0928\u094d\u0926\u0941\u0930\u0947"
    ],
    "name:msa_x_preferred":[
        "Sindure"
    ],
    "name:nep_x_preferred":[
        "\u0938\u093f\u0928\u094d\u0926\u0941\u0930\u0947"
    ],
    "name:new_x_preferred":[
        "\u0938\u093f\u0928\u094d\u0926\u0941\u0930\u0947"
    ],
    "name:pol_x_preferred":[
        "Sindure"
    ],
    "wof:name":"Sindure",
    "wof:placetype":"locality"
},
  "geometry": {"coordinates":[84.32004999999999,28.18199000000001],"type":"Point"}
}