{
  "type": "Feature",
  "properties": {
    "gn:admin1_code":"MR",
    "gn:admin2_code":"2.0",
    "gn:admin3_code":"59.0",
    "gn:admin4_code":"590044.0",
    "gn:asciiname":"Ranibasna",
    "gn:country_code":"NP",
    "gn:dem":1526,
    "gn:feature_class":"P",
    "gn:feature_code":"PPLL",
    "gn:name":"Ranibasna",
    "gn:population":0,
    "gn:timezone":"Asia/Kathmandu",
    "iso:country":"NP",
    "wof:name":"Ranibasna",
    "wof:placetype":"locality"
},
  "geometry": {"coordinates":[81.84435000000001,28.62409],"type":"Point"}
}