{
  "type": "Feature",
  "properties": {
    "gn:admin1_code":"MR",
    "gn:admin2_code":"6",
    "gn:admin3_code":"62.0",
    "gn:admin4_code":"620019.0",
    "gn:asciiname":"Laru Bhanjyang",
    "gn:country_code":"NP",
    "gn:dem":5335,
    "gn:feature_class":"P",
    "gn:feature_code":"PPLL",
    "gn:name":"Laru Bhanjyang",
    "gn:population":0,
    "gn:timezone":"Asia/Kathmandu",
    "iso:country":"NP",
    "wof:name":"Laru Bhanjyang",
    "wof:placetype":"locality"
},
  "geometry": {"coordinates":[83.20600999999998,29.60726],"type":"Point"}
}