{
  "type": "Feature",
  "properties": {
    "gn:admin1_code":"MR",
    "gn:admin2_code":"12",
    "gn:admin3_code":"54",
    "gn:admin4_code":"540039",
    "gn:asciiname":"Tanya Dhara",
    "gn:country_code":"NP",
    "gn:dem":2409,
    "gn:feature_class":"P",
    "gn:feature_code":"PPLL",
    "gn:name":"Tanya Dhara",
    "gn:population":0,
    "gn:timezone":"Asia/Kathmandu",
    "iso:country":"NP",
    "wof:name":"Tanya Dhara",
    "wof:placetype":"locality"
},
  "geometry": {"coordinates":[82.65527,28.76264],"type":"Point"}
}