{
  "type": "Feature",
  "properties": {
    "gn:admin1_code":"WR",
    "gn:admin2_code":"4",
    "gn:admin3_code":"41",
    "gn:admin4_code":"410013.0",
    "gn:asciiname":"Thonche",
    "gn:country_code":"NP",
    "gn:dem":2066,
    "gn:feature_class":"P",
    "gn:feature_code":"PPLL",
    "gn:name":"Thonche",
    "gn:population":0,
    "gn:timezone":"Asia/Kathmandu",
    "iso:country":"NP",
    "wof:name":"Thonche",
    "wof:placetype":"locality"
},
  "geometry": {"coordinates":[84.35639,28.52915],"type":"Point"}
}