{
  "type": "Feature",
  "properties": {
    "gn:admin1_code":"CR",
    "gn:admin2_code":"11",
    "gn:admin3_code":"35.0",
    "gn:admin4_code":"350026.0",
    "gn:asciiname":"Dasharathchok",
    "gn:country_code":"NP",
    "gn:dem":191,
    "gn:feature_class":"P",
    "gn:feature_code":"PPLL",
    "gn:name":"Dasharathchok",
    "gn:population":0,
    "gn:timezone":"Asia/Kathmandu",
    "iso:country":"NP",
    "wof:name":"Dasharathchok",
    "wof:placetype":"locality"
},
  "geometry": {"coordinates":[84.36995,27.66927],"type":"Point"}
}