{
  "type": "Feature",
  "properties": {
    "gn:admin1_code":"ER",
    "gn:admin2_code":"10",
    "gn:admin3_code":"4.0",
    "gn:admin4_code":"40018.0",
    "gn:asciiname":"Gurunchok",
    "gn:country_code":"NP",
    "gn:dem":110,
    "gn:feature_class":"P",
    "gn:feature_code":"PPLL",
    "gn:name":"Gurunchok",
    "gn:population":0,
    "gn:timezone":"Asia/Kathmandu",
    "iso:country":"NP",
    "wof:name":"Gurunchok",
    "wof:placetype":"locality"
},
  "geometry": {"coordinates":[87.7123,26.60067],"type":"Point"}
}