{
  "type": "Feature",
  "properties": {
    "gn:admin1_code":"CR",
    "gn:admin2_code":"11",
    "gn:admin3_code":"31",
    "gn:admin4_code":"310025",
    "gn:asciiname":"Rajarang",
    "gn:country_code":"NP",
    "gn:dem":649,
    "gn:feature_class":"P",
    "gn:feature_code":"PPLL",
    "gn:name":"Rajarang",
    "gn:population":0,
    "gn:timezone":"Asia/Kathmandu",
    "iso:country":"NP",
    "wof:name":"Rajarang",
    "wof:placetype":"locality"
},
  "geometry": {"coordinates":[84.86573,27.63078],"type":"Point"}
}