{
  "type": "Feature",
  "properties": {
    "gn:admin1_code":"CR",
    "gn:admin2_code":"5",
    "gn:admin3_code":"20",
    "gn:admin4_code":"200035",
    "gn:asciiname":"Sinduredobhan",
    "gn:country_code":"NP",
    "gn:dem":272,
    "gn:feature_class":"P",
    "gn:feature_code":"PPLL",
    "gn:name":"Sinduredobhan",
    "gn:population":0,
    "gn:timezone":"Asia/Kathmandu",
    "iso:country":"NP",
    "wof:name":"Sinduredobhan",
    "wof:placetype":"locality"
},
  "geometry": {"coordinates":[85.60024,27.27696],"type":"Point"}
}