{
  "type": "Feature",
  "properties": {
    "gn:admin1_code":"FR",
    "gn:admin2_code":"9",
    "gn:admin3_code":"75.0",
    "gn:admin4_code":"750010.0",
    "gn:asciiname":"Simar",
    "gn:country_code":"NP",
    "gn:dem":2069,
    "gn:feature_class":"P",
    "gn:feature_code":"PPLL",
    "gn:name":"Simar",
    "gn:population":0,
    "gn:timezone":"Asia/Kathmandu",
    "iso:country":"NP",
    "name:ido_x_preferred":[
        "Simaro"
    ],
    "name:nor_x_preferred":[
        "Simar"
    ],
    "name:rus_x_preferred":[
        "\u0414\u0437\u0438\u043c\u0430\u0440\u0440\u0430"
    ],
    "name:ukr_x_preferred":[
        "\u0414\u0437\u0456\u043c\u0430\u0440\u0440\u0430"
    ],
    "wof:name":"Simar",
    "wof:placetype":"locality"
},
  "geometry": {"coordinates":[80.63805000000001,29.88427],"type":"Point"}
}