{
  "type": "Feature",
  "properties": {
    "gn:admin1_code":"MR",
    "gn:admin2_code":"6",
    "gn:admin3_code":"65",
    "gn:admin4_code":"650014",
    "gn:asciiname":"Topla",
    "gn:country_code":"NP",
    "gn:dem":2524,
    "gn:feature_class":"P",
    "gn:feature_code":"PPLL",
    "gn:name":"Topla",
    "gn:population":0,
    "gn:timezone":"Asia/Kathmandu",
    "iso:country":"NP",
    "name:bos_x_preferred":[
        "Topla"
    ],
    "name:ceb_x_preferred":[
        "Topla"
    ],
    "name:deu_x_preferred":[
        "Topla"
    ],
    "name:epo_x_preferred":[
        "Topla"
    ],
    "name:fra_x_preferred":[
        "Topla"
    ],
    "name:pol_x_preferred":[
        "Topla"
    ],
    "name:ron_x_preferred":[
        "Topla"
    ],
    "name:slv_x_preferred":[
        "Topla"
    ],
    "name:srp_x_preferred":[
        "\u0422\u043e\u043f\u043b\u0430"
    ],
    "wof:name":"Topla",
    "wof:placetype":"locality"
},
  "geometry": {"coordinates":[82.13986,29.51125],"type":"Point"}
}