{
  "type": "Feature",
  "properties": {
    "gn:admin1_code":"ER",
    "gn:admin2_code":"7.0",
    "gn:admin3_code":"6.0",
    "gn:admin4_code":"60018.0",
    "gn:asciiname":"Jimichok",
    "gn:country_code":"NP",
    "gn:dem":353,
    "gn:feature_class":"P",
    "gn:feature_code":"PPLL",
    "gn:name":"Jimichok",
    "gn:population":0,
    "gn:timezone":"Asia/Kathmandu",
    "iso:country":"NP",
    "wof:name":"Jimichok",
    "wof:placetype":"locality"
},
  "geometry": {"coordinates":[87.27857,26.80957],"type":"Point"}
}