{
  "type": "Feature",
  "properties": {
    "gn:admin1_code":"WR",
    "gn:admin2_code":"8",
    "gn:admin3_code":"46.0",
    "gn:admin4_code":"460056.0",
    "gn:asciiname":"Limghagaun",
    "gn:country_code":"NP",
    "gn:dem":1403,
    "gn:feature_class":"P",
    "gn:feature_code":"PPLL",
    "gn:name":"Limghagaun",
    "gn:population":0,
    "gn:timezone":"Asia/Kathmandu",
    "iso:country":"NP",
    "wof:name":"Limghagaun",
    "wof:placetype":"locality"
},
  "geometry": {"coordinates":[83.48133,28.01612],"type":"Point"}
}