{
  "type": "Feature",
  "properties": {
    "gn:admin1_code":"ER",
    "gn:admin2_code":"7.0",
    "gn:admin3_code":"6.0",
    "gn:admin4_code":"60041.0",
    "gn:asciiname":"Prakashpur",
    "gn:country_code":"NP",
    "gn:dem":92,
    "gn:feature_class":"P",
    "gn:feature_code":"PPLL",
    "gn:name":"Prakashpur",
    "gn:population":0,
    "gn:timezone":"Asia/Kathmandu",
    "iso:country":"NP",
    "name:bih_x_preferred":[
        "\u092a\u094d\u0930\u0915\u093e\u0936\u092a\u0941\u0930"
    ],
    "name:ceb_x_preferred":[
        "Prakashpur"
    ],
    "name:fra_x_preferred":[
        "Prakashpur"
    ],
    "name:mai_x_preferred":[
        "\u092a\u094d\u0930\u0915\u093e\u0936\u092a\u0941\u0930"
    ],
    "name:msa_x_preferred":[
        "Prakashpur"
    ],
    "name:nep_x_preferred":[
        "\u092a\u094d\u0930\u0915\u093e\u0936\u092a\u0941\u0930"
    ],
    "name:new_x_preferred":[
        "\u092a\u094d\u0930\u0915\u093e\u0936\u092a\u0941\u0930"
    ],
    "name:pol_x_preferred":[
        "Prakashpur"
    ],
    "wof:name":"Prakashpur",
    "wof:placetype":"locality"
},
  "geometry": {"coordinates":[87.09971,26.68815],"type":"Point"}
}