{
  "type": "Feature",
  "properties": {
    "gn:admin1_code":"MR",
    "gn:admin2_code":"12",
    "gn:admin3_code":"53",
    "gn:admin4_code":"530041",
    "gn:asciiname":"Haraldhara",
    "gn:country_code":"NP",
    "gn:dem":1567,
    "gn:feature_class":"P",
    "gn:feature_code":"PPLL",
    "gn:name":"Haraldhara",
    "gn:population":0,
    "gn:timezone":"Asia/Kathmandu",
    "iso:country":"NP",
    "wof:name":"Haraldhara",
    "wof:placetype":"locality"
},
  "geometry": {"coordinates":[82.544,28.24913],"type":"Point"}
}