{
  "type": "Feature",
  "properties": {
    "gn:admin1_code":"ER",
    "gn:admin2_code":"10",
    "gn:admin3_code":"2",
    "gn:admin4_code":"20009",
    "gn:asciiname":"Durdimba",
    "gn:country_code":"NP",
    "gn:dem":1550,
    "gn:feature_class":"P",
    "gn:feature_code":"PPLL",
    "gn:name":"Durdimba",
    "gn:population":0,
    "gn:timezone":"Asia/Kathmandu",
    "iso:country":"NP",
    "name:bih_x_preferred":[
        "\u0926\u0941\u0930\u094d\u0926\u093f\u092e\u094d\u092c\u093e"
    ],
    "name:ceb_x_preferred":[
        "Durdimba"
    ],
    "name:hin_x_preferred":[
        "\u0926\u0941\u0930\u094d\u0926\u093f\u092e\u094d\u092c\u093e"
    ],
    "name:mai_x_preferred":[
        "\u0926\u0941\u0930\u094d\u0926\u093f\u092e\u094d\u092c\u093e"
    ],
    "name:msa_x_preferred":[
        "Durdimba"
    ],
    "name:nep_x_preferred":[
        "\u0926\u0941\u0930\u094d\u0926\u093f\u092e\u094d\u092c\u093e"
    ],
    "name:new_x_preferred":[
        "\u0926\u0941\u0930\u094d\u0926\u093f\u092e\u094d\u092c\u093e"
    ],
    "name:pol_x_preferred":[
        "Durdimba"
    ],
    "wof:name":"Durdimba",
    "wof:placetype":"locality"
},
  "geometry": {"coordinates":[87.54834,26.90253],"type":"Point"}
}