{
  "type": "Feature",
  "properties": {
    "gn:admin1_code":"WR",
    "gn:admin2_code":"4.0",
    "gn:admin3_code":"39.0",
    "gn:admin4_code":"390039.0",
    "gn:asciiname":"Kholegaun",
    "gn:country_code":"NP",
    "gn:dem":946,
    "gn:feature_class":"P",
    "gn:feature_code":"PPLL",
    "gn:name":"Kholegaun",
    "gn:population":0,
    "gn:timezone":"Asia/Kathmandu",
    "iso:country":"NP",
    "wof:name":"Kholegaun",
    "wof:placetype":"locality"
},
  "geometry": {"coordinates":[83.76566,28.11544],"type":"Point"}
}