{
  "type": "Feature",
  "properties": {
    "gn:admin1_code":"CR",
    "gn:admin2_code":"11",
    "gn:admin3_code":"31",
    "gn:admin4_code":"310028",
    "gn:asciiname":"Devidanda",
    "gn:country_code":"NP",
    "gn:dem":595,
    "gn:feature_class":"P",
    "gn:feature_code":"PPLL",
    "gn:name":"Devidanda",
    "gn:population":0,
    "gn:timezone":"Asia/Kathmandu",
    "iso:country":"NP",
    "wof:name":"Devidanda",
    "wof:placetype":"locality"
},
  "geometry": {"coordinates":[85.09728,27.42014],"type":"Point"}
}