{
  "type": "Feature",
  "properties": {
    "gn:admin1_code":"MR",
    "gn:admin2_code":"12",
    "gn:admin3_code":"53",
    "gn:admin4_code":"530015",
    "gn:asciiname":"Amilidanda",
    "gn:country_code":"NP",
    "gn:dem":1394,
    "gn:feature_class":"P",
    "gn:feature_code":"PPLL",
    "gn:name":"Amilidanda",
    "gn:population":0,
    "gn:timezone":"Asia/Kathmandu",
    "iso:country":"NP",
    "wof:name":"Amilidanda",
    "wof:placetype":"locality"
},
  "geometry": {"coordinates":[82.79519000000001,28.3009],"type":"Point"}
}