{
  "type": "Feature",
  "properties": {
    "gn:admin1_code":"CR",
    "gn:admin2_code":"5",
    "gn:admin3_code":"21",
    "gn:admin4_code":"210039",
    "gn:asciiname":"Tribeni",
    "gn:country_code":"NP",
    "gn:dem":523,
    "gn:feature_class":"P",
    "gn:feature_code":"PPLL",
    "gn:name":"Tribeni",
    "gn:population":0,
    "gn:timezone":"Asia/Kathmandu",
    "iso:country":"NP",
    "wof:name":"Tribeni",
    "wof:placetype":"locality"
},
  "geometry": {"coordinates":[85.98439,27.35554],"type":"Point"}
}