{
  "type": "Feature",
  "properties": {
    "gn:admin1_code":"FR",
    "gn:admin2_code":"14",
    "gn:admin3_code":"69.0",
    "gn:admin4_code":"690021.0",
    "gn:asciiname":"Nandapur",
    "gn:country_code":"NP",
    "gn:dem":1405,
    "gn:feature_class":"P",
    "gn:feature_code":"PPLL",
    "gn:name":"Nandapur",
    "gn:population":0,
    "gn:timezone":"Asia/Kathmandu",
    "iso:country":"NP",
    "wof:name":"Nandapur",
    "wof:placetype":"locality"
},
  "geometry": {"coordinates":[81.28671,28.99788],"type":"Point"}
}