{
  "type": "Feature",
  "properties": {
    "gn:admin1_code":"FR",
    "gn:admin2_code":"9",
    "gn:admin3_code":"73.0",
    "gn:admin4_code":"730014.0",
    "gn:asciiname":"Rumayalkharka",
    "gn:country_code":"NP",
    "gn:dem":1485,
    "gn:feature_class":"P",
    "gn:feature_code":"PPLL",
    "gn:name":"Rumayalkharka",
    "gn:population":0,
    "gn:timezone":"Asia/Kathmandu",
    "iso:country":"NP",
    "wof:name":"Rumayalkharka",
    "wof:placetype":"locality"
},
  "geometry": {"coordinates":[80.69367,29.2695],"type":"Point"}
}