{
  "type": "Feature",
  "properties": {
    "gn:admin1_code":"WR",
    "gn:admin2_code":"3",
    "gn:admin3_code":"45.0",
    "gn:admin4_code":"450005.0",
    "gn:asciiname":"Kang",
    "gn:country_code":"NP",
    "gn:dem":2829,
    "gn:feature_class":"P",
    "gn:feature_code":"PPLL",
    "gn:name":"Kang",
    "gn:population":0,
    "gn:timezone":"Asia/Kathmandu",
    "iso:country":"NP",
    "name:ceb_x_preferred":[
        "Kang"
    ],
    "name:deu_x_preferred":[
        "Kang"
    ],
    "name:fin_x_preferred":[
        "Kang"
    ],
    "name:fra_x_preferred":[
        "Kang"
    ],
    "name:ita_x_preferred":[
        "Kang"
    ],
    "name:nor_x_preferred":[
        "Kang"
    ],
    "name:rus_x_preferred":[
        "\u041a\u0430\u043d\u0433"
    ],
    "name:spa_x_preferred":[
        "Kang"
    ],
    "name:swe_x_preferred":[
        "Kang"
    ],
    "name:tha_x_preferred":[
        "\u0e04\u0e31\u0e07"
    ],
    "wof:name":"Kang",
    "wof:placetype":"locality"
},
  "geometry": {"coordinates":[82.99453000000003,28.50653],"type":"Point"}
}