{
  "type": "Feature",
  "properties": {
    "gn:admin1_code":"FR",
    "gn:admin2_code":"9",
    "gn:admin3_code":"73.0",
    "gn:admin4_code":"730006.0",
    "gn:asciiname":"Sunku",
    "gn:country_code":"NP",
    "gn:dem":1343,
    "gn:feature_class":"P",
    "gn:feature_code":"PPLL",
    "gn:name":"Sunku",
    "gn:population":0,
    "gn:timezone":"Asia/Kathmandu",
    "iso:country":"NP",
    "wof:name":"Sunku",
    "wof:placetype":"locality"
},
  "geometry": {"coordinates":[80.71816,29.377],"type":"Point"}
}