{
  "type": "Feature",
  "properties": {
    "gn:admin1_code":"WR",
    "gn:admin2_code":"8",
    "gn:admin3_code":"47",
    "gn:admin4_code":"470038",
    "gn:asciiname":"Palengban",
    "gn:country_code":"NP",
    "gn:dem":738,
    "gn:feature_class":"P",
    "gn:feature_code":"PPLL",
    "gn:name":"Palengban",
    "gn:population":0,
    "gn:timezone":"Asia/Kathmandu",
    "iso:country":"NP",
    "wof:name":"Palengban",
    "wof:placetype":"locality"
},
  "geometry": {"coordinates":[83.63303000000001,27.88277],"type":"Point"}
}