{
  "type": "Feature",
  "properties": {
    "gn:admin1_code":"WR",
    "gn:admin2_code":"4.0",
    "gn:admin3_code":"38.0",
    "gn:admin4_code":"380040.0",
    "gn:asciiname":"Lampata",
    "gn:country_code":"NP",
    "gn:dem":859,
    "gn:feature_class":"P",
    "gn:feature_code":"PPLL",
    "gn:name":"Lampata",
    "gn:population":0,
    "gn:timezone":"Asia/Kathmandu",
    "iso:country":"NP",
    "wof:name":"Lampata",
    "wof:placetype":"locality"
},
  "geometry": {"coordinates":[84.36672,28.11566],"type":"Point"}
}