{
  "type": "Feature",
  "properties": {
    "gn:admin1_code":"CR",
    "gn:admin2_code":"5",
    "gn:admin3_code":"17.0",
    "gn:admin4_code":"170095.0",
    "gn:asciiname":"Thadhi",
    "gn:country_code":"NP",
    "gn:dem":83,
    "gn:feature_class":"P",
    "gn:feature_code":"PPLL",
    "gn:name":"Thadhi",
    "gn:population":0,
    "gn:timezone":"Asia/Kathmandu",
    "iso:country":"NP",
    "wof:name":"Thadhi",
    "wof:placetype":"locality"
},
  "geometry": {"coordinates":[86.07784000000002,26.66653],"type":"Point"}
}