{
  "type": "Feature",
  "properties": {
    "gn:admin1_code":"MR",
    "gn:admin2_code":"6",
    "gn:admin3_code":"64.0",
    "gn:admin4_code":"640025.0",
    "gn:asciiname":"Seri Jyula",
    "gn:country_code":"NP",
    "gn:dem":1165,
    "gn:feature_class":"P",
    "gn:feature_code":"PPLL",
    "gn:name":"Seri Jyula",
    "gn:population":0,
    "gn:timezone":"Asia/Kathmandu",
    "iso:country":"NP",
    "wof:name":"Seri Jyula",
    "wof:placetype":"locality"
},
  "geometry": {"coordinates":[81.60828000000002,29.17943],"type":"Point"}
}