{
  "type": "Feature",
  "properties": {
    "gn:admin1_code":"FR",
    "gn:admin2_code":"14",
    "gn:admin3_code":"71.0",
    "gn:admin4_code":"710031.0",
    "gn:asciiname":"Bokse",
    "gn:country_code":"NP",
    "gn:dem":173,
    "gn:feature_class":"P",
    "gn:feature_code":"PPLL",
    "gn:name":"Bokse",
    "gn:population":0,
    "gn:timezone":"Asia/Kathmandu",
    "iso:country":"NP",
    "wof:name":"Bokse",
    "wof:placetype":"locality"
},
  "geometry": {"coordinates":[81.15272,28.5846],"type":"Point"}
}