{
  "type": "Feature",
  "properties": {
    "gn:admin1_code":"00",
    "gn:asciiname":"Pkhare",
    "gn:country_code":"NP",
    "gn:dem":199,
    "gn:feature_class":"P",
    "gn:feature_code":"PPL",
    "gn:name":"Pkhare",
    "gn:population":0,
    "gn:timezone":"Asia/Kathmandu",
    "iso:country":"NP",
    "name:nep_x_preferred":[
        "Pkhare"
    ],
    "wof:name":"Pkhare",
    "wof:placetype":"locality"
},
  "geometry": {"coordinates":[86.97499000000001,26.82898],"type":"Point"}
}