{
  "type": "Feature",
  "properties": {
    "gn:admin1_code":"ER",
    "gn:admin2_code":"7.0",
    "gn:admin3_code":"8.0",
    "gn:admin4_code":"80016.0",
    "gn:asciiname":"Bhorle",
    "gn:country_code":"NP",
    "gn:dem":1130,
    "gn:feature_class":"P",
    "gn:feature_code":"PPLL",
    "gn:name":"Bhorle",
    "gn:population":0,
    "gn:timezone":"Asia/Kathmandu",
    "iso:country":"NP",
    "name:fra_x_preferred":[
        "Bhorle"
    ],
    "name:pol_x_preferred":[
        "Bhorle"
    ],
    "wof:name":"Bhorle",
    "wof:placetype":"locality"
},
  "geometry": {"coordinates":[87.51554,27.07557000000001],"type":"Point"}
}