{
  "type": "Feature",
  "properties": {
    "gn:admin1_code":"WR",
    "gn:admin2_code":"3",
    "gn:admin3_code":"44",
    "gn:admin4_code":"440019",
    "gn:asciiname":"Ghurunga",
    "gn:country_code":"NP",
    "gn:dem":2334,
    "gn:feature_class":"P",
    "gn:feature_code":"PPLL",
    "gn:name":"Ghurunga",
    "gn:population":0,
    "gn:timezone":"Asia/Kathmandu",
    "iso:country":"NP",
    "wof:name":"Ghurunga",
    "wof:placetype":"locality"
},
  "geometry": {"coordinates":[83.69611,28.31881],"type":"Point"}
}