{
  "type": "Feature",
  "properties": {
    "gn:admin1_code":"ER",
    "gn:admin2_code":"10",
    "gn:admin3_code":"2",
    "gn:admin4_code":"20028",
    "gn:asciiname":"Kolbung",
    "gn:country_code":"NP",
    "gn:dem":1359,
    "gn:feature_class":"P",
    "gn:feature_code":"PPLL",
    "gn:name":"Kolbung",
    "gn:population":0,
    "gn:timezone":"Asia/Kathmandu",
    "iso:country":"NP",
    "wof:name":"Kolbung",
    "wof:placetype":"locality"
},
  "geometry": {"coordinates":[87.72917,27.0444],"type":"Point"}
}