{
  "type": "Feature",
  "properties": {
    "gn:admin1_code":"MR",
    "gn:admin2_code":"6",
    "gn:admin3_code":"64.0",
    "gn:admin4_code":"640006.0",
    "gn:asciiname":"Ramni",
    "gn:country_code":"NP",
    "gn:dem":1713,
    "gn:feature_class":"P",
    "gn:feature_code":"PPLL",
    "gn:name":"Ramni",
    "gn:population":0,
    "gn:timezone":"Asia/Kathmandu",
    "iso:country":"NP",
    "wof:name":"Ramni",
    "wof:placetype":"locality"
},
  "geometry": {"coordinates":[81.74511,29.09833],"type":"Point"}
}