{
  "type": "Feature",
  "properties": {
    "gn:admin1_code":"CR",
    "gn:admin2_code":"1",
    "gn:admin3_code":"24.0",
    "gn:admin4_code":"240063.0",
    "gn:asciiname":"Tamanggaun",
    "gn:country_code":"NP",
    "gn:dem":1672,
    "gn:feature_class":"P",
    "gn:feature_code":"PPLL",
    "gn:name":"Tamanggaun",
    "gn:population":0,
    "gn:timezone":"Asia/Kathmandu",
    "iso:country":"NP",
    "wof:name":"Tamanggaun",
    "wof:placetype":"locality"
},
  "geometry": {"coordinates":[85.47771,27.63149],"type":"Point"}
}