{
  "type": "Feature",
  "properties": {
    "gn:admin1_code":"WR",
    "gn:admin2_code":"8",
    "gn:admin3_code":"46.0",
    "gn:admin4_code":"460039.0",
    "gn:asciiname":"Pamphuka",
    "gn:country_code":"NP",
    "gn:dem":1868,
    "gn:feature_class":"P",
    "gn:feature_code":"PPLL",
    "gn:name":"Pamphuka",
    "gn:population":0,
    "gn:timezone":"Asia/Kathmandu",
    "iso:country":"NP",
    "wof:name":"Pamphuka",
    "wof:placetype":"locality"
},
  "geometry": {"coordinates":[83.47721,28.04171],"type":"Point"}
}