{
  "type": "Feature",
  "properties": {
    "gn:admin1_code":"ER",
    "gn:admin2_code":"10",
    "gn:admin3_code":"2",
    "gn:admin4_code":"20005",
    "gn:asciiname":"Salleri",
    "gn:country_code":"NP",
    "gn:dem":1483,
    "gn:feature_class":"P",
    "gn:feature_code":"PPLL",
    "gn:name":"Salleri",
    "gn:population":0,
    "gn:timezone":"Asia/Kathmandu",
    "iso:country":"NP",
    "name:ceb_x_preferred":[
        "Salleri"
    ],
    "name:deu_x_preferred":[
        "Salleri"
    ],
    "name:pol_x_preferred":[
        "Salleri"
    ],
    "wof:name":"Salleri",
    "wof:placetype":"locality"
},
  "geometry": {"coordinates":[87.79401,27.18896],"type":"Point"}
}