{
  "type": "Feature",
  "properties": {
    "gn:admin1_code":"CR",
    "gn:admin2_code":"11",
    "gn:admin3_code":"35.0",
    "gn:admin4_code":"350006.0",
    "gn:asciiname":"Bajarhatti",
    "gn:country_code":"NP",
    "gn:dem":215,
    "gn:feature_class":"P",
    "gn:feature_code":"PPLL",
    "gn:name":"Bajarhatti",
    "gn:population":0,
    "gn:timezone":"Asia/Kathmandu",
    "iso:country":"NP",
    "wof:name":"Bajarhatti",
    "wof:placetype":"locality"
},
  "geometry": {"coordinates":[84.61266999999999,27.61257],"type":"Point"}
}