{
  "type": "Feature",
  "properties": {
    "gn:admin1_code":"WR",
    "gn:admin2_code":"4",
    "gn:admin3_code":"40.0",
    "gn:admin4_code":"400005.0",
    "gn:asciiname":"Rangedanda",
    "gn:country_code":"NP",
    "gn:dem":730,
    "gn:feature_class":"P",
    "gn:feature_code":"PPLL",
    "gn:name":"Rangedanda",
    "gn:population":0,
    "gn:timezone":"Asia/Kathmandu",
    "iso:country":"NP",
    "wof:name":"Rangedanda",
    "wof:placetype":"locality"
},
  "geometry": {"coordinates":[84.04359000000002,28.10779],"type":"Point"}
}