{
  "type": "Feature",
  "properties": {
    "gn:admin1_code":"ER",
    "gn:admin2_code":"7",
    "gn:admin3_code":"10.0",
    "gn:admin4_code":"100009.0",
    "gn:asciiname":"Chhewa",
    "gn:country_code":"NP",
    "gn:dem":1973,
    "gn:feature_class":"P",
    "gn:feature_code":"PPLL",
    "gn:name":"Chhewa",
    "gn:population":0,
    "gn:timezone":"Asia/Kathmandu",
    "iso:country":"NP",
    "wof:name":"Chhewa",
    "wof:placetype":"locality"
},
  "geometry": {"coordinates":[86.99394000000002,27.01461],"type":"Point"}
}