{
  "type": "Feature",
  "properties": {
    "gn:admin1_code":"ER",
    "gn:admin2_code":"7",
    "gn:admin3_code":"7.0",
    "gn:admin4_code":"70024.0",
    "gn:asciiname":"Pokla",
    "gn:country_code":"NP",
    "gn:dem":524,
    "gn:feature_class":"P",
    "gn:feature_code":"PPLL",
    "gn:name":"Pokla",
    "gn:population":0,
    "gn:timezone":"Asia/Kathmandu",
    "iso:country":"NP",
    "wof:name":"Pokla",
    "wof:placetype":"locality"
},
  "geometry": {"coordinates":[87.24868000000002,26.91457],"type":"Point"}
}