{
  "type": "Feature",
  "properties": {
    "gn:admin1_code":"FR",
    "gn:admin2_code":"9",
    "gn:admin3_code":"74",
    "gn:admin4_code":"740044",
    "gn:asciiname":"Thapla",
    "gn:country_code":"NP",
    "gn:dem":1472,
    "gn:feature_class":"P",
    "gn:feature_code":"PPLL",
    "gn:name":"Thapla",
    "gn:population":0,
    "gn:timezone":"Asia/Kathmandu",
    "iso:country":"NP",
    "wof:name":"Thapla",
    "wof:placetype":"locality"
},
  "geometry": {"coordinates":[80.53457,29.46472],"type":"Point"}
}