{
  "type": "Feature",
  "properties": {
    "gn:admin1_code":"CR",
    "gn:admin2_code":"5",
    "gn:admin3_code":"22.0",
    "gn:admin4_code":"220020.0",
    "gn:asciiname":"Bukuni",
    "gn:country_code":"NP",
    "gn:dem":2263,
    "gn:feature_class":"P",
    "gn:feature_code":"PPLL",
    "gn:name":"Bukuni",
    "gn:population":0,
    "gn:timezone":"Asia/Kathmandu",
    "iso:country":"NP",
    "wof:name":"Bukuni",
    "wof:placetype":"locality"
},
  "geometry": {"coordinates":[86.14618,27.57271],"type":"Point"}
}