{
  "type": "Feature",
  "properties": {
    "gn:admin1_code":"CR",
    "gn:admin2_code":"11",
    "gn:admin3_code":"35.0",
    "gn:admin4_code":"350010.0",
    "gn:asciiname":"Kuchingairha",
    "gn:country_code":"NP",
    "gn:dem":576,
    "gn:feature_class":"P",
    "gn:feature_code":"PPLL",
    "gn:name":"Kuchingairha",
    "gn:population":0,
    "gn:timezone":"Asia/Kathmandu",
    "iso:country":"NP",
    "wof:name":"Kuchingairha",
    "wof:placetype":"locality"
},
  "geometry": {"coordinates":[84.62859,27.85601],"type":"Point"}
}