{
  "type": "Feature",
  "properties": {
    "gn:admin1_code":"WR",
    "gn:admin2_code":"3",
    "gn:admin3_code":"45.0",
    "gn:admin4_code":"450017.0",
    "gn:asciiname":"Okhreni",
    "gn:country_code":"NP",
    "gn:dem":1144,
    "gn:feature_class":"P",
    "gn:feature_code":"PPLL",
    "gn:name":"Okhreni",
    "gn:population":0,
    "gn:timezone":"Asia/Kathmandu",
    "iso:country":"NP",
    "wof:name":"Okhreni",
    "wof:placetype":"locality"
},
  "geometry": {"coordinates":[83.59869,28.25364],"type":"Point"}
}