{
  "type": "Feature",
  "properties": {
    "gn:admin1_code":"ER",
    "gn:admin2_code":"13.0",
    "gn:admin3_code":"14.0",
    "gn:admin4_code":"140025.0",
    "gn:asciiname":"Thamdanda",
    "gn:country_code":"NP",
    "gn:dem":2275,
    "gn:feature_class":"P",
    "gn:feature_code":"PPLL",
    "gn:name":"Thamdanda",
    "gn:population":0,
    "gn:timezone":"Asia/Kathmandu",
    "iso:country":"NP",
    "wof:name":"Thamdanda",
    "wof:placetype":"locality"
},
  "geometry": {"coordinates":[86.61610999999998,27.01915],"type":"Point"}
}