{
  "type": "Feature",
  "properties": {
    "gn:admin1_code":"MR",
    "gn:admin2_code":"12",
    "gn:admin3_code":"56.0",
    "gn:admin4_code":"560015.0",
    "gn:asciiname":"Atuwagaun",
    "gn:country_code":"NP",
    "gn:dem":716,
    "gn:feature_class":"P",
    "gn:feature_code":"PPLL",
    "gn:name":"Atuwagaun",
    "gn:population":0,
    "gn:timezone":"Asia/Kathmandu",
    "iso:country":"NP",
    "wof:name":"Atuwagaun",
    "wof:placetype":"locality"
},
  "geometry": {"coordinates":[82.44511,28.08856],"type":"Point"}
}