{
  "type": "Feature",
  "properties": {
    "gn:admin1_code":"FR",
    "gn:admin2_code":"9",
    "gn:admin3_code":"73.0",
    "gn:admin4_code":"730005.0",
    "gn:asciiname":"Nyalek",
    "gn:country_code":"NP",
    "gn:dem":1469,
    "gn:feature_class":"P",
    "gn:feature_code":"PPLL",
    "gn:name":"Nyalek",
    "gn:population":0,
    "gn:timezone":"Asia/Kathmandu",
    "iso:country":"NP",
    "wof:name":"Nyalek",
    "wof:placetype":"locality"
},
  "geometry": {"coordinates":[80.54267,29.30455],"type":"Point"}
}