{
  "type": "Feature",
  "properties": {
    "gn:admin1_code":"FR",
    "gn:admin2_code":"14",
    "gn:admin3_code":"68",
    "gn:admin4_code":"680008",
    "gn:asciiname":"Satiun",
    "gn:country_code":"NP",
    "gn:dem":2888,
    "gn:feature_class":"P",
    "gn:feature_code":"PPLL",
    "gn:name":"Satiun",
    "gn:population":0,
    "gn:timezone":"Asia/Kathmandu",
    "iso:country":"NP",
    "wof:name":"Satiun",
    "wof:placetype":"locality"
},
  "geometry": {"coordinates":[80.91084000000002,29.6531],"type":"Point"}
}