{
  "type": "Feature",
  "properties": {
    "gn:admin1_code":"MR",
    "gn:admin2_code":"12",
    "gn:admin3_code":"55",
    "gn:admin4_code":"550029",
    "gn:asciiname":"Chanpi Jyula",
    "gn:country_code":"NP",
    "gn:dem":779,
    "gn:feature_class":"P",
    "gn:feature_code":"PPLL",
    "gn:name":"Chanpi Jyula",
    "gn:population":0,
    "gn:timezone":"Asia/Kathmandu",
    "iso:country":"NP",
    "wof:name":"Chanpi Jyula",
    "wof:placetype":"locality"
},
  "geometry": {"coordinates":[82.13337,28.27992],"type":"Point"}
}