{
  "type": "Feature",
  "properties": {
    "gn:admin1_code":"FR",
    "gn:admin2_code":"9",
    "gn:admin3_code":"72.0",
    "gn:admin4_code":"720019.0",
    "gn:asciiname":"Jhajpura",
    "gn:country_code":"NP",
    "gn:dem":225,
    "gn:feature_class":"P",
    "gn:feature_code":"PPLL",
    "gn:name":"Jhajpura",
    "gn:population":0,
    "gn:timezone":"Asia/Kathmandu",
    "iso:country":"NP",
    "wof:name":"Jhajpura",
    "wof:placetype":"locality"
},
  "geometry": {"coordinates":[80.21472,28.97802],"type":"Point"}
}