{
  "type": "Feature",
  "properties": {
    "gn:admin1_code":"CR",
    "gn:admin2_code":"5",
    "gn:admin3_code":"20",
    "gn:admin4_code":"200048",
    "gn:asciiname":"Khanigaun",
    "gn:country_code":"NP",
    "gn:dem":623,
    "gn:feature_class":"P",
    "gn:feature_code":"PPLL",
    "gn:name":"Khanigaun",
    "gn:population":0,
    "gn:timezone":"Asia/Kathmandu",
    "iso:country":"NP",
    "wof:name":"Khanigaun",
    "wof:placetype":"locality"
},
  "geometry": {"coordinates":[86.30974000000001,27.22729],"type":"Point"}
}