{
  "type": "Feature",
  "properties": {
    "gn:admin1_code":"CR",
    "gn:admin2_code":"1",
    "gn:admin3_code":"25",
    "gn:admin4_code":"250038",
    "gn:asciiname":"Satitar",
    "gn:country_code":"NP",
    "gn:dem":1399,
    "gn:feature_class":"P",
    "gn:feature_code":"PPLL",
    "gn:name":"Satitar",
    "gn:population":0,
    "gn:timezone":"Asia/Kathmandu",
    "iso:country":"NP",
    "wof:name":"Satitar",
    "wof:placetype":"locality"
},
  "geometry": {"coordinates":[85.32113000000003,27.62824],"type":"Point"}
}