{
  "type": "Feature",
  "properties": {
    "gn:admin1_code":"WR",
    "gn:admin2_code":"4.0",
    "gn:admin3_code":"38.0",
    "gn:admin4_code":"380047.0",
    "gn:asciiname":"Archale",
    "gn:country_code":"NP",
    "gn:dem":878,
    "gn:feature_class":"P",
    "gn:feature_code":"PPLL",
    "gn:name":"Archale",
    "gn:population":0,
    "gn:timezone":"Asia/Kathmandu",
    "iso:country":"NP",
    "wof:name":"Archale",
    "wof:placetype":"locality"
},
  "geometry": {"coordinates":[84.37915,28.08801],"type":"Point"}
}