{
  "type": "Feature",
  "properties": {
    "gn:admin1_code":"00",
    "gn:asciiname":"Patane - Kholagau",
    "gn:country_code":"NP",
    "gn:dem":2281,
    "gn:feature_class":"P",
    "gn:feature_code":"PPL",
    "gn:name":"P\u0101\u1e6dane - Khol\u0101g\u0101\u0169",
    "gn:population":0,
    "gn:timezone":"Asia/Kathmandu",
    "iso:country":"NP",
    "wof:name":"Patane - Kholagau",
    "wof:placetype":"locality"
},
  "geometry": {"coordinates":[85.46276999999998,27.52937],"type":"Point"}
}