{
  "type": "Feature",
  "properties": {
    "gn:admin1_code":"WR",
    "gn:admin2_code":"8",
    "gn:admin3_code":"51.0",
    "gn:admin4_code":"510018.0",
    "gn:asciiname":"Thada Dhunga",
    "gn:country_code":"NP",
    "gn:dem":1712,
    "gn:feature_class":"P",
    "gn:feature_code":"PPLL",
    "gn:name":"Thada Dhunga",
    "gn:population":0,
    "gn:timezone":"Asia/Kathmandu",
    "iso:country":"NP",
    "wof:name":"Thada Dhunga",
    "wof:placetype":"locality"
},
  "geometry": {"coordinates":[83.04258,28.08205],"type":"Point"}
}