{
  "type": "Feature",
  "properties": {
    "gn:admin1_code":"WR",
    "gn:admin2_code":"8",
    "gn:admin3_code":"47",
    "gn:admin4_code":"470045",
    "gn:asciiname":"Patle",
    "gn:country_code":"NP",
    "gn:dem":925,
    "gn:feature_class":"P",
    "gn:feature_code":"PPLL",
    "gn:name":"Patle",
    "gn:population":0,
    "gn:timezone":"Asia/Kathmandu",
    "iso:country":"NP",
    "name:msa_x_preferred":[
        "Patle"
    ],
    "wof:name":"Patle",
    "wof:placetype":"locality"
},
  "geometry": {"coordinates":[83.53599,27.77492],"type":"Point"}
}