{
  "type": "Feature",
  "properties": {
    "gn:admin1_code":"CR",
    "gn:admin2_code":"5.0",
    "gn:asciiname":"Goswara",
    "gn:country_code":"NP",
    "gn:dem":2456,
    "gn:feature_class":"P",
    "gn:feature_code":"PPLL",
    "gn:name":"Goswara",
    "gn:population":0,
    "gn:timezone":"Asia/Kathmandu",
    "iso:country":"NP",
    "wof:name":"Goswara",
    "wof:placetype":"locality"
},
  "geometry": {"coordinates":[85.91919,27.58442],"type":"Point"}
}