{
  "type": "Feature",
  "properties": {
    "gn:admin1_code":"00",
    "gn:asciiname":"Sawa",
    "gn:country_code":"NP",
    "gn:dem":654,
    "gn:feature_class":"P",
    "gn:feature_code":"PPL",
    "gn:name":"S\u0101\u0303w\u0101",
    "gn:population":0,
    "gn:timezone":"Asia/Kathmandu",
    "iso:country":"NP",
    "name:cat_x_preferred":[
        "Sawa"
    ],
    "name:ceb_x_preferred":[
        "Sawa"
    ],
    "name:deu_x_preferred":[
        "Sawa"
    ],
    "name:fra_x_preferred":[
        "Sawa"
    ],
    "name:ind_x_preferred":[
        "Sawa"
    ],
    "name:ita_x_preferred":[
        "Sawa"
    ],
    "name:nep_x_preferred":[
        "S\u0101\u0303w\u0101"
    ],
    "name:nld_x_preferred":[
        "Sawa"
    ],
    "name:pol_x_preferred":[
        "Sawa"
    ],
    "name:por_x_preferred":[
        "Sawa"
    ],
    "name:swe_x_preferred":[
        "Sawa"
    ],
    "name:tgl_x_preferred":[
        "Sawa"
    ],
    "wof:name":"Sawa",
    "wof:placetype":"locality"
},
  "geometry": {"coordinates":[86.84742,26.87042000000001],"type":"Point"}
}