{
  "type": "Feature",
  "properties": {
    "gn:admin1_code":"FR",
    "gn:admin2_code":"14",
    "gn:admin3_code":"70.0",
    "gn:admin4_code":"700021.0",
    "gn:asciiname":"Chhoya",
    "gn:country_code":"NP",
    "gn:dem":1224,
    "gn:feature_class":"P",
    "gn:feature_code":"PPLL",
    "gn:name":"Chhoya",
    "gn:population":0,
    "gn:timezone":"Asia/Kathmandu",
    "iso:country":"NP",
    "wof:name":"Chhoya",
    "wof:placetype":"locality"
},
  "geometry": {"coordinates":[80.7813,29.26823],"type":"Point"}
}