{
  "type": "Feature",
  "properties": {
    "gn:admin1_code":"WR",
    "gn:admin2_code":"4",
    "gn:admin3_code":"36.0",
    "gn:admin4_code":"360015.0",
    "gn:asciiname":"Gumlung",
    "gn:country_code":"NP",
    "gn:dem":2389,
    "gn:feature_class":"P",
    "gn:feature_code":"PPLL",
    "gn:name":"Gumlung",
    "gn:population":0,
    "gn:timezone":"Asia/Kathmandu",
    "iso:country":"NP",
    "wof:name":"Gumlung",
    "wof:placetype":"locality"
},
  "geometry": {"coordinates":[84.96418,28.46706],"type":"Point"}
}