{
  "type": "Feature",
  "properties": {
    "gn:admin1_code":"ER",
    "gn:admin2_code":"10.0",
    "gn:admin3_code":"1.0",
    "gn:admin4_code":"10005.0",
    "gn:asciiname":"Dhungesanghu",
    "gn:country_code":"NP",
    "gn:dem":1104,
    "gn:feature_class":"P",
    "gn:feature_code":"PPLL",
    "gn:name":"Dhungesanghu",
    "gn:population":0,
    "gn:timezone":"Asia/Kathmandu",
    "iso:country":"NP",
    "wof:name":"Dhungesanghu",
    "wof:placetype":"locality"
},
  "geometry": {"coordinates":[87.59138,27.3649],"type":"Point"}
}