{
  "type": "Feature",
  "properties": {
    "gn:admin1_code":"CR",
    "gn:admin2_code":"1",
    "gn:admin3_code":"30.0",
    "gn:admin4_code":"300020.0",
    "gn:asciiname":"Dalang",
    "gn:country_code":"NP",
    "gn:dem":1058,
    "gn:feature_class":"P",
    "gn:feature_code":"PPLL",
    "gn:name":"Dalang",
    "gn:population":0,
    "gn:timezone":"Asia/Kathmandu",
    "iso:country":"NP",
    "name:ceb_x_preferred":[
        "Dalang"
    ],
    "name:deu_x_preferred":[
        "Dalang"
    ],
    "name:nld_x_preferred":[
        "Dalang"
    ],
    "name:sco_x_preferred":[
        "Dalang"
    ],
    "name:swe_x_preferred":[
        "Dalang"
    ],
    "wof:name":"Dalang",
    "wof:placetype":"locality"
},
  "geometry": {"coordinates":[84.99783000000002,27.83369],"type":"Point"}
}