{
  "type": "Feature",
  "properties": {
    "gn:admin1_code":"ER",
    "gn:admin2_code":"10.0",
    "gn:admin3_code":"1.0",
    "gn:admin4_code":"10048.0",
    "gn:asciiname":"Thokargaun",
    "gn:country_code":"NP",
    "gn:dem":859,
    "gn:feature_class":"P",
    "gn:feature_code":"PPLL",
    "gn:name":"Thokargaun",
    "gn:population":0,
    "gn:timezone":"Asia/Kathmandu",
    "iso:country":"NP",
    "wof:name":"Thokargaun",
    "wof:placetype":"locality"
},
  "geometry": {"coordinates":[87.80224,27.28132],"type":"Point"}
}