{
  "type": "Feature",
  "properties": {
    "gn:admin1_code":"MR",
    "gn:admin2_code":"12",
    "gn:admin3_code":"54",
    "gn:admin4_code":"540040",
    "gn:asciiname":"Ghoralchar",
    "gn:country_code":"NP",
    "gn:dem":1904,
    "gn:feature_class":"P",
    "gn:feature_code":"PPLL",
    "gn:name":"Ghoralchar",
    "gn:population":0,
    "gn:timezone":"Asia/Kathmandu",
    "iso:country":"NP",
    "wof:name":"Ghoralchar",
    "wof:placetype":"locality"
},
  "geometry": {"coordinates":[82.58479,28.58603],"type":"Point"}
}