{
  "type": "Feature",
  "properties": {
    "gn:admin1_code":"WR",
    "gn:admin2_code":"4.0",
    "gn:admin3_code":"38.0",
    "gn:admin4_code":"380020.0",
    "gn:asciiname":"Gachhepani",
    "gn:country_code":"NP",
    "gn:dem":621,
    "gn:feature_class":"P",
    "gn:feature_code":"PPLL",
    "gn:name":"Gachhepani",
    "gn:population":0,
    "gn:timezone":"Asia/Kathmandu",
    "iso:country":"NP",
    "wof:name":"Gachhepani",
    "wof:placetype":"locality"
},
  "geometry": {"coordinates":[84.07427,28.05994],"type":"Point"}
}