{
  "type": "Feature",
  "properties": {
    "gn:admin1_code":"ER",
    "gn:admin2_code":"13",
    "gn:admin3_code":"13.0",
    "gn:admin4_code":"130021.0",
    "gn:asciiname":"Nali",
    "gn:country_code":"NP",
    "gn:dem":1740,
    "gn:feature_class":"P",
    "gn:feature_code":"PPLL",
    "gn:name":"Nali",
    "gn:population":0,
    "gn:timezone":"Asia/Kathmandu",
    "iso:country":"NP",
    "name:ceb_x_preferred":[
        "Nali"
    ],
    "name:swe_x_preferred":[
        "Nali"
    ],
    "wof:name":"Nali",
    "wof:placetype":"locality"
},
  "geometry": {"coordinates":[86.79886999999999,27.10886],"type":"Point"}
}