{
  "type": "Feature",
  "properties": {
    "gn:admin1_code":"WR",
    "gn:admin2_code":"8",
    "gn:admin3_code":"48",
    "gn:admin4_code":"480013.0",
    "gn:asciiname":"Pashchimtar",
    "gn:country_code":"NP",
    "gn:dem":336,
    "gn:feature_class":"P",
    "gn:feature_code":"PPLL",
    "gn:name":"Pashchimtar",
    "gn:population":0,
    "gn:timezone":"Asia/Kathmandu",
    "iso:country":"NP",
    "wof:name":"Pashchimtar",
    "wof:placetype":"locality"
},
  "geometry": {"coordinates":[84.08483000000003,27.86504],"type":"Point"}
}