{
  "type": "Feature",
  "properties": {
    "gn:admin1_code":"ER",
    "gn:admin2_code":"7",
    "gn:admin3_code":"7.0",
    "gn:admin4_code":"70015.0",
    "gn:asciiname":"Bodaredanda",
    "gn:country_code":"NP",
    "gn:dem":832,
    "gn:feature_class":"P",
    "gn:feature_code":"PPLL",
    "gn:name":"Bodaredanda",
    "gn:population":0,
    "gn:timezone":"Asia/Kathmandu",
    "iso:country":"NP",
    "wof:name":"Bodaredanda",
    "wof:placetype":"locality"
},
  "geometry": {"coordinates":[87.35879,26.97433],"type":"Point"}
}