{
  "type": "Feature",
  "properties": {
    "gn:admin1_code":"ER",
    "gn:admin2_code":"10",
    "gn:admin3_code":"4.0",
    "gn:admin4_code":"40021.0",
    "gn:asciiname":"Gherabari",
    "gn:country_code":"NP",
    "gn:dem":76,
    "gn:feature_class":"P",
    "gn:feature_code":"PPLL",
    "gn:name":"Gherabari",
    "gn:population":0,
    "gn:timezone":"Asia/Kathmandu",
    "iso:country":"NP",
    "name:bih_x_preferred":[
        "\u0918\u0947\u0930\u093e\u0935\u093e\u0930\u0940"
    ],
    "name:fra_x_preferred":[
        "Gherabari"
    ],
    "name:hin_x_preferred":[
        "\u0918\u0947\u0930\u093e\u0935\u093e\u0930\u0940"
    ],
    "name:mai_x_preferred":[
        "\u0918\u0947\u0930\u093e\u0935\u093e\u0930\u0940"
    ],
    "name:msa_x_preferred":[
        "Gherabari"
    ],
    "name:nep_x_preferred":[
        "\u0918\u0947\u0930\u093e\u092c\u093e\u0930\u0940"
    ],
    "name:new_x_preferred":[
        "\u0918\u0947\u0930\u093e\u092c\u093e\u0930\u0940"
    ],
    "name:pol_x_preferred":[
        "Gherabari"
    ],
    "wof:name":"Gherabari",
    "wof:placetype":"locality"
},
  "geometry": {"coordinates":[87.94263000000002,26.42579000000001],"type":"Point"}
}