{
  "type": "Feature",
  "properties": {
    "gn:admin1_code":"ER",
    "gn:admin2_code":"10.0",
    "gn:admin3_code":"1.0",
    "gn:admin4_code":"10002.0",
    "gn:asciiname":"Majuwa",
    "gn:country_code":"NP",
    "gn:dem":2096,
    "gn:feature_class":"P",
    "gn:feature_code":"PPLL",
    "gn:name":"Majuwa",
    "gn:population":0,
    "gn:timezone":"Asia/Kathmandu",
    "iso:country":"NP",
    "wof:name":"Majuwa",
    "wof:placetype":"locality"
},
  "geometry": {"coordinates":[87.93013000000001,27.30569],"type":"Point"}
}