{
  "type": "Feature",
  "properties": {
    "gn:admin1_code":"WR",
    "gn:admin2_code":"8",
    "gn:admin3_code":"47",
    "gn:admin4_code":"470058",
    "gn:asciiname":"Mohare",
    "gn:country_code":"NP",
    "gn:dem":911,
    "gn:feature_class":"P",
    "gn:feature_code":"PPLL",
    "gn:name":"Mohare",
    "gn:population":0,
    "gn:timezone":"Asia/Kathmandu",
    "iso:country":"NP",
    "wof:name":"Mohare",
    "wof:placetype":"locality"
},
  "geometry": {"coordinates":[83.38634999999999,27.9447],"type":"Point"}
}