{
  "type": "Feature",
  "properties": {
    "gn:admin1_code":"ER",
    "gn:admin2_code":"7",
    "gn:admin3_code":"9",
    "gn:admin4_code":"90001",
    "gn:asciiname":"Hiletar",
    "gn:country_code":"NP",
    "gn:dem":637,
    "gn:feature_class":"P",
    "gn:feature_code":"PPLL",
    "gn:name":"Hiletar",
    "gn:population":0,
    "gn:timezone":"Asia/Kathmandu",
    "iso:country":"NP",
    "wof:name":"Hiletar",
    "wof:placetype":"locality"
},
  "geometry": {"coordinates":[87.26682,27.19293],"type":"Point"}
}