{
  "type": "Feature",
  "properties": {
    "gn:admin1_code":"WR",
    "gn:admin2_code":"4.0",
    "gn:admin3_code":"38.0",
    "gn:admin4_code":"380019.0",
    "gn:asciiname":"Mustange Bhote Camp",
    "gn:country_code":"NP",
    "gn:dem":466,
    "gn:feature_class":"P",
    "gn:feature_code":"PPLL",
    "gn:name":"Mustange Bhote Camp",
    "gn:population":0,
    "gn:timezone":"Asia/Kathmandu",
    "iso:country":"NP",
    "wof:name":"Mustange Bhote Camp",
    "wof:placetype":"locality"
},
  "geometry": {"coordinates":[84.07420999999999,28.03498],"type":"Point"}
}