{
  "type": "Feature",
  "properties": {
    "gn:admin1_code":"MR",
    "gn:admin2_code":"2",
    "gn:admin3_code":"61.0",
    "gn:admin4_code":"610005.0",
    "gn:asciiname":"Hattisur",
    "gn:country_code":"NP",
    "gn:dem":1953,
    "gn:feature_class":"P",
    "gn:feature_code":"PPLL",
    "gn:name":"Hattisur",
    "gn:population":0,
    "gn:timezone":"Asia/Kathmandu",
    "iso:country":"NP",
    "wof:name":"Hattisur",
    "wof:placetype":"locality"
},
  "geometry": {"coordinates":[82.21963000000002,28.83424],"type":"Point"}
}