{
  "type": "Feature",
  "properties": {
    "gn:admin1_code":"CR",
    "gn:admin2_code":"11",
    "gn:admin3_code":"31",
    "gn:admin4_code":"310017",
    "gn:asciiname":"Thakle",
    "gn:country_code":"NP",
    "gn:dem":1386,
    "gn:feature_class":"P",
    "gn:feature_code":"PPLL",
    "gn:name":"Thakle",
    "gn:population":0,
    "gn:timezone":"Asia/Kathmandu",
    "iso:country":"NP",
    "wof:name":"Thakle",
    "wof:placetype":"locality"
},
  "geometry": {"coordinates":[84.94575999999998,27.61684],"type":"Point"}
}