{
  "type": "Feature",
  "properties": {
    "gn:admin1_code":"CR",
    "gn:admin2_code":"11",
    "gn:admin3_code":"31",
    "gn:admin4_code":"310020",
    "gn:asciiname":"Thanabhareng",
    "gn:country_code":"NP",
    "gn:dem":551,
    "gn:feature_class":"P",
    "gn:feature_code":"PPLL",
    "gn:name":"Thanabhareng",
    "gn:population":0,
    "gn:timezone":"Asia/Kathmandu",
    "iso:country":"NP",
    "wof:name":"Thanabhareng",
    "wof:placetype":"locality"
},
  "geometry": {"coordinates":[85.01519,27.43396],"type":"Point"}
}