{
  "type": "Feature",
  "properties": {
    "gn:admin1_code":"FR",
    "gn:admin2_code":"9",
    "gn:admin3_code":"74",
    "gn:admin4_code":"740038",
    "gn:asciiname":"Noda",
    "gn:country_code":"NP",
    "gn:dem":1586,
    "gn:feature_class":"P",
    "gn:feature_code":"PPLL",
    "gn:name":"Noda",
    "gn:population":0,
    "gn:timezone":"Asia/Kathmandu",
    "iso:country":"NP",
    "name:ceb_x_preferred":[
        "Noda"
    ],
    "name:deu_x_preferred":[
        "Noda"
    ],
    "name:fra_x_preferred":[
        "Noda"
    ],
    "name:lav_x_preferred":[
        "Noda"
    ],
    "name:mlg_x_preferred":[
        "Noda"
    ],
    "name:nld_x_preferred":[
        "Noda"
    ],
    "name:pol_x_preferred":[
        "Noda"
    ],
    "name:por_x_preferred":[
        "Noda"
    ],
    "name:spa_x_preferred":[
        "Noda"
    ],
    "name:swe_x_preferred":[
        "Noda"
    ],
    "wof:name":"Noda",
    "wof:placetype":"locality"
},
  "geometry": {"coordinates":[80.56704999999999,29.53704],"type":"Point"}
}