{
  "type": "Feature",
  "properties": {
    "gn:admin1_code":"WR",
    "gn:admin2_code":"3",
    "gn:admin3_code":"44",
    "gn:admin4_code":"440021",
    "gn:asciiname":"Patle",
    "gn:country_code":"NP",
    "gn:dem":1657,
    "gn:feature_class":"P",
    "gn:feature_code":"PPLL",
    "gn:name":"Patle",
    "gn:population":0,
    "gn:timezone":"Asia/Kathmandu",
    "iso:country":"NP",
    "name:msa_x_preferred":[
        "Patle"
    ],
    "wof:name":"Patle",
    "wof:placetype":"locality"
},
  "geometry": {"coordinates":[83.68467,28.25595],"type":"Point"}
}