{
  "type": "Feature",
  "properties": {
    "gn:admin1_code":"CR",
    "gn:admin2_code":"11",
    "gn:admin3_code":"31",
    "gn:admin4_code":"310001.0",
    "gn:asciiname":"Bahungaun",
    "gn:country_code":"NP",
    "gn:dem":1322,
    "gn:feature_class":"P",
    "gn:feature_code":"PPLL",
    "gn:name":"Bahungaun",
    "gn:population":0,
    "gn:timezone":"Asia/Kathmandu",
    "iso:country":"NP",
    "wof:name":"Bahungaun",
    "wof:placetype":"locality"
},
  "geometry": {"coordinates":[85.01339,27.70131],"type":"Point"}
}