{
  "type": "Feature",
  "properties": {
    "gn:admin1_code":"ER",
    "gn:admin2_code":"13",
    "gn:admin3_code":"11",
    "gn:admin4_code":"110032.0",
    "gn:asciiname":"Salleri",
    "gn:country_code":"NP",
    "gn:dem":3295,
    "gn:feature_class":"P",
    "gn:feature_code":"PPLL",
    "gn:name":"Salleri",
    "gn:population":0,
    "gn:timezone":"Asia/Kathmandu",
    "iso:country":"NP",
    "wof:name":"Salleri",
    "wof:placetype":"locality"
},
  "geometry": {"coordinates":[86.63086,27.56896],"type":"Point"}
}