{
  "type": "Feature",
  "properties": {
    "gn:admin1_code":"FR",
    "gn:admin2_code":"9",
    "gn:admin3_code":"74",
    "gn:admin4_code":"740015",
    "gn:asciiname":"Khairkot",
    "gn:country_code":"NP",
    "gn:dem":1712,
    "gn:feature_class":"P",
    "gn:feature_code":"PPLL",
    "gn:name":"Khairkot",
    "gn:population":0,
    "gn:timezone":"Asia/Kathmandu",
    "iso:country":"NP",
    "wof:name":"Khairkot",
    "wof:placetype":"locality"
},
  "geometry": {"coordinates":[80.78268,29.39675],"type":"Point"}
}