{
  "type": "Feature",
  "properties": {
    "gn:admin1_code":"WR",
    "gn:admin2_code":"4",
    "gn:admin3_code":"37",
    "gn:admin4_code":"370027.0",
    "gn:asciiname":"Khatrigaun",
    "gn:country_code":"NP",
    "gn:dem":894,
    "gn:feature_class":"P",
    "gn:feature_code":"PPLL",
    "gn:name":"Khatrigaun",
    "gn:population":0,
    "gn:timezone":"Asia/Kathmandu",
    "iso:country":"NP",
    "wof:name":"Khatrigaun",
    "wof:placetype":"locality"
},
  "geometry": {"coordinates":[84.38800999999999,28.20551],"type":"Point"}
}