{
  "type": "Feature",
  "properties": {
    "gn:admin1_code":"WR",
    "gn:admin2_code":"4.0",
    "gn:admin3_code":"38.0",
    "gn:admin4_code":"380013.0",
    "gn:asciiname":"Sitan",
    "gn:country_code":"NP",
    "gn:dem":646,
    "gn:feature_class":"P",
    "gn:feature_code":"PPLL",
    "gn:name":"Sitan",
    "gn:population":0,
    "gn:timezone":"Asia/Kathmandu",
    "iso:country":"NP",
    "wof:name":"Sitan",
    "wof:placetype":"locality"
},
  "geometry": {"coordinates":[84.4802,27.82965],"type":"Point"}
}