{
  "type": "Feature",
  "properties": {
    "gn:admin1_code":"CR",
    "gn:admin2_code":"1",
    "gn:admin3_code":"27.0",
    "gn:admin4_code":"270022.0",
    "gn:asciiname":"Siddhitol",
    "gn:country_code":"NP",
    "gn:dem":1310,
    "gn:feature_class":"P",
    "gn:feature_code":"PPLL",
    "gn:name":"Siddhitol",
    "gn:population":0,
    "gn:timezone":"Asia/Kathmandu",
    "iso:country":"NP",
    "wof:name":"Siddhitol",
    "wof:placetype":"locality"
},
  "geometry": {"coordinates":[85.31319000000001,27.73839000000001],"type":"Point"}
}