{
  "type": "Feature",
  "properties": {
    "gn:admin1_code":"ER",
    "gn:admin2_code":"7.0",
    "gn:admin3_code":"8.0",
    "gn:admin4_code":"80003.0",
    "gn:asciiname":"Newang",
    "gn:country_code":"NP",
    "gn:dem":1558,
    "gn:feature_class":"P",
    "gn:feature_code":"PPLL",
    "gn:name":"Newang",
    "gn:population":0,
    "gn:timezone":"Asia/Kathmandu",
    "iso:country":"NP",
    "wof:name":"Newang",
    "wof:placetype":"locality"
},
  "geometry": {"coordinates":[87.43361999999998,27.14653],"type":"Point"}
}