{
  "type": "Feature",
  "properties": {
    "gn:admin1_code":"MR",
    "gn:admin2_code":"2.0",
    "gn:admin3_code":"59.0",
    "gn:admin4_code":"590047.0",
    "gn:asciiname":"Kirmile",
    "gn:country_code":"NP",
    "gn:dem":1523,
    "gn:feature_class":"P",
    "gn:feature_code":"PPLL",
    "gn:name":"Kirmile",
    "gn:population":0,
    "gn:timezone":"Asia/Kathmandu",
    "iso:country":"NP",
    "wof:name":"Kirmile",
    "wof:placetype":"locality"
},
  "geometry": {"coordinates":[81.44960999999998,28.83171],"type":"Point"}
}