{
  "type": "Feature",
  "properties": {
    "gn:admin1_code":"WR",
    "gn:admin2_code":"3",
    "gn:admin3_code":"44",
    "gn:admin4_code":"440006",
    "gn:asciiname":"Banau",
    "gn:country_code":"NP",
    "gn:dem":2010,
    "gn:feature_class":"P",
    "gn:feature_code":"PPLL",
    "gn:name":"Banau",
    "gn:population":0,
    "gn:timezone":"Asia/Kathmandu",
    "iso:country":"NP",
    "name:ceb_x_preferred":[
        "Banaula"
    ],
    "name:mai_x_preferred":[
        "\u092c\u0928\u094c"
    ],
    "name:msa_x_preferred":[
        "Banau"
    ],
    "name:nep_x_preferred":[
        "\u092c\u0928\u094c"
    ],
    "name:pol_x_preferred":[
        "Banou"
    ],
    "wof:name":"Banau",
    "wof:placetype":"locality"
},
  "geometry": {"coordinates":[83.65344,28.28788],"type":"Point"}
}