{
  "type": "Feature",
  "properties": {
    "gn:admin1_code":"WR",
    "gn:admin2_code":"4.0",
    "gn:admin3_code":"38.0",
    "gn:admin4_code":"380025.0",
    "gn:asciiname":"Phal Bhanjyang",
    "gn:country_code":"NP",
    "gn:dem":868,
    "gn:feature_class":"P",
    "gn:feature_code":"PPLL",
    "gn:name":"Phal Bhanjyang",
    "gn:population":0,
    "gn:timezone":"Asia/Kathmandu",
    "iso:country":"NP",
    "wof:name":"Phal Bhanjyang",
    "wof:placetype":"locality"
},
  "geometry": {"coordinates":[84.24359,27.88866],"type":"Point"}
}