{
  "type": "Feature",
  "properties": {
    "gn:admin1_code":"MR",
    "gn:admin2_code":"12",
    "gn:admin3_code":"54",
    "gn:admin4_code":"540029",
    "gn:asciiname":"Thulakhola Danda",
    "gn:country_code":"NP",
    "gn:dem":1427,
    "gn:feature_class":"P",
    "gn:feature_code":"PPLL",
    "gn:name":"Thulakhola Danda",
    "gn:population":0,
    "gn:timezone":"Asia/Kathmandu",
    "iso:country":"NP",
    "wof:name":"Thulakhola Danda",
    "wof:placetype":"locality"
},
  "geometry": {"coordinates":[82.52854000000001,28.66608],"type":"Point"}
}