{
  "type": "Feature",
  "properties": {
    "gn:admin1_code":"FR",
    "gn:admin2_code":"9",
    "gn:admin3_code":"73.0",
    "gn:admin4_code":"730003.0",
    "gn:asciiname":"Litrigaun",
    "gn:country_code":"NP",
    "gn:dem":1242,
    "gn:feature_class":"P",
    "gn:feature_code":"PPLL",
    "gn:name":"Litrigaun",
    "gn:population":0,
    "gn:timezone":"Asia/Kathmandu",
    "iso:country":"NP",
    "wof:name":"Litrigaun",
    "wof:placetype":"locality"
},
  "geometry": {"coordinates":[80.65458000000002,29.30165],"type":"Point"}
}