{
  "type": "Feature",
  "properties": {
    "gn:admin1_code":"CR",
    "gn:admin2_code":"5",
    "gn:admin3_code":"20",
    "gn:admin4_code":"200002",
    "gn:asciiname":"Bhyagure",
    "gn:country_code":"NP",
    "gn:dem":617,
    "gn:feature_class":"P",
    "gn:feature_code":"PPLL",
    "gn:name":"Bhyagure",
    "gn:population":0,
    "gn:timezone":"Asia/Kathmandu",
    "iso:country":"NP",
    "wof:name":"Bhyagure",
    "wof:placetype":"locality"
},
  "geometry": {"coordinates":[86.24615,27.05797],"type":"Point"}
}