{
  "type": "Feature",
  "properties": {
    "gn:admin1_code":"WR",
    "gn:admin2_code":"4",
    "gn:admin3_code":"40.0",
    "gn:admin4_code":"400036.0",
    "gn:asciiname":"Dharamdanda",
    "gn:country_code":"NP",
    "gn:dem":963,
    "gn:feature_class":"P",
    "gn:feature_code":"PPLL",
    "gn:name":"Dharamdanda",
    "gn:population":0,
    "gn:timezone":"Asia/Kathmandu",
    "iso:country":"NP",
    "wof:name":"Dharamdanda",
    "wof:placetype":"locality"
},
  "geometry": {"coordinates":[84.14334000000002,28.14462],"type":"Point"}
}