{
  "type": "Feature",
  "properties": {
    "gn:admin1_code":"CR",
    "gn:admin2_code":"1",
    "gn:admin3_code":"27.0",
    "gn:admin4_code":"270019.0",
    "gn:asciiname":"Bhimsentar",
    "gn:country_code":"NP",
    "gn:dem":1400,
    "gn:feature_class":"P",
    "gn:feature_code":"PPLL",
    "gn:name":"Bhimsentar",
    "gn:population":0,
    "gn:timezone":"Asia/Kathmandu",
    "iso:country":"NP",
    "wof:name":"Bhimsentar",
    "wof:placetype":"locality"
},
  "geometry": {"coordinates":[85.44095,27.74501],"type":"Point"}
}