{
  "type": "Feature",
  "properties": {
    "gn:admin1_code":"WR",
    "gn:admin2_code":"8",
    "gn:admin3_code":"51.0",
    "gn:admin4_code":"510036.0",
    "gn:asciiname":"Tumkot",
    "gn:country_code":"NP",
    "gn:dem":1151,
    "gn:feature_class":"P",
    "gn:feature_code":"PPLL",
    "gn:name":"Tumkot",
    "gn:population":0,
    "gn:timezone":"Asia/Kathmandu",
    "iso:country":"NP",
    "wof:name":"Tumkot",
    "wof:placetype":"locality"
},
  "geometry": {"coordinates":[83.13805000000001,27.99072],"type":"Point"}
}