{
  "type": "Feature",
  "properties": {
    "gn:admin1_code":"MR",
    "gn:admin2_code":"2.0",
    "gn:admin3_code":"59.0",
    "gn:admin4_code":"590019.0",
    "gn:asciiname":"Pokhare",
    "gn:country_code":"NP",
    "gn:dem":522,
    "gn:feature_class":"P",
    "gn:feature_code":"PPLL",
    "gn:name":"Pokhare",
    "gn:population":0,
    "gn:timezone":"Asia/Kathmandu",
    "iso:country":"NP",
    "wof:name":"Pokhare",
    "wof:placetype":"locality"
},
  "geometry": {"coordinates":[81.9252,28.43766],"type":"Point"}
}