{
  "type": "Feature",
  "properties": {
    "gn:admin1_code":"CR",
    "gn:admin2_code":"11",
    "gn:admin3_code":"31",
    "gn:admin4_code":"310021",
    "gn:asciiname":"Bhorle",
    "gn:country_code":"NP",
    "gn:dem":527,
    "gn:feature_class":"P",
    "gn:feature_code":"PPLL",
    "gn:name":"Bhorle",
    "gn:population":0,
    "gn:timezone":"Asia/Kathmandu",
    "iso:country":"NP",
    "name:fra_x_preferred":[
        "Bhorle"
    ],
    "name:pol_x_preferred":[
        "Bhorle"
    ],
    "wof:name":"Bhorle",
    "wof:placetype":"locality"
},
  "geometry": {"coordinates":[85.12799999999999,27.36609],"type":"Point"}
}