{
  "type": "Feature",
  "properties": {
    "gn:admin1_code":"ER",
    "gn:admin2_code":"7.0",
    "gn:admin3_code":"8.0",
    "gn:admin4_code":"80001.0",
    "gn:asciiname":"Phamphewa",
    "gn:country_code":"NP",
    "gn:dem":1620,
    "gn:feature_class":"P",
    "gn:feature_code":"PPLL",
    "gn:name":"Phamphewa",
    "gn:population":0,
    "gn:timezone":"Asia/Kathmandu",
    "iso:country":"NP",
    "wof:name":"Phamphewa",
    "wof:placetype":"locality"
},
  "geometry": {"coordinates":[87.50803000000001,27.19114],"type":"Point"}
}