{
  "type": "Feature",
  "properties": {
    "gn:admin1_code":"CR",
    "gn:admin2_code":"1",
    "gn:admin3_code":"30.0",
    "gn:admin4_code":"300047.0",
    "gn:asciiname":"Thumka",
    "gn:country_code":"NP",
    "gn:dem":830,
    "gn:feature_class":"P",
    "gn:feature_code":"PPLL",
    "gn:name":"Thumka",
    "gn:population":0,
    "gn:timezone":"Asia/Kathmandu",
    "iso:country":"NP",
    "wof:name":"Thumka",
    "wof:placetype":"locality"
},
  "geometry": {"coordinates":[85.05674,27.7228],"type":"Point"}
}