{
  "type": "Feature",
  "properties": {
    "gn:admin1_code":"CR",
    "gn:admin2_code":"11",
    "gn:admin3_code":"34",
    "gn:admin4_code":"340080",
    "gn:asciiname":"Sarswatinagar",
    "gn:country_code":"NP",
    "gn:dem":310,
    "gn:feature_class":"P",
    "gn:feature_code":"PPLL",
    "gn:name":"Sarswatinagar",
    "gn:population":0,
    "gn:timezone":"Asia/Kathmandu",
    "iso:country":"NP",
    "wof:name":"Sarswatinagar",
    "wof:placetype":"locality"
},
  "geometry": {"coordinates":[84.58504000000001,27.37673],"type":"Point"}
}