{
  "type": "Feature",
  "properties": {
    "gn:admin1_code":"ER",
    "gn:admin2_code":"13",
    "gn:admin3_code":"11",
    "gn:admin4_code":"110024",
    "gn:asciiname":"Kholema",
    "gn:country_code":"NP",
    "gn:dem":4666,
    "gn:feature_class":"P",
    "gn:feature_code":"PPLL",
    "gn:name":"Kholema",
    "gn:population":0,
    "gn:timezone":"Asia/Kathmandu",
    "iso:country":"NP",
    "wof:name":"Kholema",
    "wof:placetype":"locality"
},
  "geometry": {"coordinates":[86.59829999999999,27.95024],"type":"Point"}
}