{
  "type": "Feature",
  "properties": {
    "gn:admin1_code":"CR",
    "gn:admin2_code":"5",
    "gn:admin3_code":"20",
    "gn:admin4_code":"200025",
    "gn:asciiname":"Bhumedanda",
    "gn:country_code":"NP",
    "gn:dem":597,
    "gn:feature_class":"P",
    "gn:feature_code":"PPLL",
    "gn:name":"Bhumedanda",
    "gn:population":0,
    "gn:timezone":"Asia/Kathmandu",
    "iso:country":"NP",
    "wof:name":"Bhumedanda",
    "wof:placetype":"locality"
},
  "geometry": {"coordinates":[85.89910999999999,27.22026],"type":"Point"}
}