{
  "type": "Feature",
  "properties": {
    "gn:admin1_code":"WR",
    "gn:admin2_code":"4",
    "gn:admin3_code":"36.0",
    "gn:admin4_code":"360063.0",
    "gn:asciiname":"Thumka",
    "gn:country_code":"NP",
    "gn:dem":675,
    "gn:feature_class":"P",
    "gn:feature_code":"PPLL",
    "gn:name":"Thumka",
    "gn:population":0,
    "gn:timezone":"Asia/Kathmandu",
    "iso:country":"NP",
    "wof:name":"Thumka",
    "wof:placetype":"locality"
},
  "geometry": {"coordinates":[84.68403000000001,28.00176],"type":"Point"}
}