{
  "type": "Feature",
  "properties": {
    "gn:admin1_code":"FR",
    "gn:admin2_code":"9",
    "gn:admin3_code":"74",
    "gn:admin4_code":"740063",
    "gn:asciiname":"Khadik",
    "gn:country_code":"NP",
    "gn:dem":1020,
    "gn:feature_class":"P",
    "gn:feature_code":"PPLL",
    "gn:name":"Khadik",
    "gn:population":0,
    "gn:timezone":"Asia/Kathmandu",
    "iso:country":"NP",
    "wof:name":"Khadik",
    "wof:placetype":"locality"
},
  "geometry": {"coordinates":[80.37238000000001,29.37546],"type":"Point"}
}