{
  "type": "Feature",
  "properties": {
    "gn:admin1_code":"CR",
    "gn:admin2_code":"1",
    "gn:admin3_code":"24.0",
    "gn:admin4_code":"240026.0",
    "gn:asciiname":"Bolde",
    "gn:country_code":"NP",
    "gn:dem":810,
    "gn:feature_class":"P",
    "gn:feature_code":"PPLL",
    "gn:name":"Bolde",
    "gn:population":0,
    "gn:timezone":"Asia/Kathmandu",
    "iso:country":"NP",
    "wof:name":"Bolde",
    "wof:placetype":"locality"
},
  "geometry": {"coordinates":[85.76326,27.53783],"type":"Point"}
}