{
  "type": "Feature",
  "properties": {
    "gn:admin1_code":"CR",
    "gn:admin2_code":"1",
    "gn:admin3_code":"30.0",
    "gn:admin4_code":"300015.0",
    "gn:asciiname":"Indu",
    "gn:country_code":"NP",
    "gn:dem":1130,
    "gn:feature_class":"P",
    "gn:feature_code":"PPLL",
    "gn:name":"Indu",
    "gn:population":0,
    "gn:timezone":"Asia/Kathmandu",
    "iso:country":"NP",
    "wof:name":"Indu",
    "wof:placetype":"locality"
},
  "geometry": {"coordinates":[84.93751,28.04076],"type":"Point"}
}