{
  "type": "Feature",
  "properties": {
    "gn:admin1_code":"MR",
    "gn:admin2_code":"12",
    "gn:admin3_code":"55",
    "gn:admin4_code":"550028",
    "gn:asciiname":"Maitepokhari",
    "gn:country_code":"NP",
    "gn:dem":1618,
    "gn:feature_class":"P",
    "gn:feature_code":"PPLL",
    "gn:name":"Maitepokhari",
    "gn:population":0,
    "gn:timezone":"Asia/Kathmandu",
    "iso:country":"NP",
    "wof:name":"Maitepokhari",
    "wof:placetype":"locality"
},
  "geometry": {"coordinates":[82.09233,28.41635],"type":"Point"}
}