{
  "type": "Feature",
  "properties": {
    "gn:admin1_code":"MR",
    "gn:admin2_code":"6",
    "gn:admin3_code":"63.0",
    "gn:admin4_code":"630005.0",
    "gn:asciiname":"Gahun Dunna",
    "gn:country_code":"NP",
    "gn:dem":3150,
    "gn:feature_class":"P",
    "gn:feature_code":"PPLL",
    "gn:name":"Gahun Dunna",
    "gn:population":0,
    "gn:timezone":"Asia/Kathmandu",
    "iso:country":"NP",
    "wof:name":"Gahun Dunna",
    "wof:placetype":"locality"
},
  "geometry": {"coordinates":[82.34283000000001,29.33284],"type":"Point"}
}