{
  "type": "Feature",
  "properties": {
    "gn:admin1_code":"00",
    "gn:asciiname":"Rubun",
    "gn:country_code":"NP",
    "gn:dem":1266,
    "gn:feature_class":"P",
    "gn:feature_code":"PPL",
    "gn:name":"Rubu\u1e45",
    "gn:population":0,
    "gn:timezone":"Asia/Kathmandu",
    "iso:country":"NP",
    "wof:name":"Rubun",
    "wof:placetype":"locality"
},
  "geometry": {"coordinates":[86.72198,27.26261],"type":"Point"}
}