{
  "type": "Feature",
  "properties": {
    "gn:admin1_code":"WR",
    "gn:admin2_code":"3",
    "gn:admin3_code":"45.0",
    "gn:admin4_code":"450056.0",
    "gn:asciiname":"Garpu",
    "gn:country_code":"NP",
    "gn:dem":1805,
    "gn:feature_class":"P",
    "gn:feature_code":"PPLL",
    "gn:name":"Garpu",
    "gn:population":0,
    "gn:timezone":"Asia/Kathmandu",
    "iso:country":"NP",
    "wof:name":"Garpu",
    "wof:placetype":"locality"
},
  "geometry": {"coordinates":[83.18748000000002,28.42194000000001],"type":"Point"}
}