{
  "type": "Feature",
  "properties": {
    "gn:admin1_code":"ER",
    "gn:admin2_code":"13",
    "gn:admin3_code":"15",
    "gn:admin4_code":"150029",
    "gn:asciiname":"Khoriyatol",
    "gn:country_code":"NP",
    "gn:dem":142,
    "gn:feature_class":"P",
    "gn:feature_code":"PPLL",
    "gn:name":"Khoriyatol",
    "gn:population":0,
    "gn:timezone":"Asia/Kathmandu",
    "iso:country":"NP",
    "wof:name":"Khoriyatol",
    "wof:placetype":"locality"
},
  "geometry": {"coordinates":[86.54734000000001,26.71257],"type":"Point"}
}