{
  "type": "Feature",
  "properties": {
    "gn:admin1_code":"CR",
    "gn:admin2_code":"1",
    "gn:admin3_code":"30.0",
    "gn:admin4_code":"300023.0",
    "gn:asciiname":"Paharechhap",
    "gn:country_code":"NP",
    "gn:dem":614,
    "gn:feature_class":"P",
    "gn:feature_code":"PPLL",
    "gn:name":"Paharechhap",
    "gn:population":0,
    "gn:timezone":"Asia/Kathmandu",
    "iso:country":"NP",
    "wof:name":"Paharechhap",
    "wof:placetype":"locality"
},
  "geometry": {"coordinates":[84.98385,27.86626],"type":"Point"}
}