{
  "type": "Feature",
  "properties": {
    "gn:admin1_code":"ER",
    "gn:admin2_code":"13",
    "gn:admin3_code":"12",
    "gn:admin4_code":"120049.0",
    "gn:asciiname":"Phoksingtar",
    "gn:country_code":"NP",
    "gn:dem":707,
    "gn:feature_class":"P",
    "gn:feature_code":"PPLL",
    "gn:name":"Phoksingtar",
    "gn:population":0,
    "gn:timezone":"Asia/Kathmandu",
    "iso:country":"NP",
    "name:bih_x_preferred":[
        "\u092b\u094b\u0915\u094d\u0938\u093f\u0919\u091f\u093e\u0930"
    ],
    "name:ceb_x_preferred":[
        "Foksingtar"
    ],
    "name:mai_x_preferred":[
        "\u092b\u094b\u0915\u094d\u0938\u093f\u0919\u091f\u093e\u0930"
    ],
    "name:msa_x_preferred":[
        "Foksingtar"
    ],
    "name:nep_x_preferred":[
        "\u092b\u094b\u0915\u094d\u0938\u093f\u0919\u091f\u093e\u0930"
    ],
    "name:new_x_preferred":[
        "\u092b\u094b\u0915\u094d\u0938\u093f\u0919\u091f\u093e\u0930"
    ],
    "name:pol_x_preferred":[
        "Foksingtar"
    ],
    "wof:name":"Phoksingtar",
    "wof:placetype":"locality"
},
  "geometry": {"coordinates":[86.38998000000002,27.24773],"type":"Point"}
}