{
  "type": "Feature",
  "properties": {
    "gn:admin1_code":"FR",
    "gn:admin2_code":"9",
    "gn:admin3_code":"72.0",
    "gn:admin4_code":"720020.0",
    "gn:asciiname":"Sukumbasi Tol",
    "gn:country_code":"NP",
    "gn:dem":179,
    "gn:feature_class":"P",
    "gn:feature_code":"PPLL",
    "gn:name":"Sukumbasi Tol",
    "gn:population":0,
    "gn:timezone":"Asia/Kathmandu",
    "iso:country":"NP",
    "wof:name":"Sukumbasi Tol",
    "wof:placetype":"locality"
},
  "geometry": {"coordinates":[80.4336,28.64391],"type":"Point"}
}