{
  "type": "Feature",
  "properties": {
    "gn:admin1_code":"00",
    "gn:asciiname":"Orandada",
    "gn:country_code":"NP",
    "gn:dem":1955,
    "gn:feature_class":"P",
    "gn:feature_code":"PPL",
    "gn:name":"Or\u0101\u1e45\u1e0d\u0101\u0303\u1e0d\u0101",
    "gn:population":0,
    "gn:timezone":"Asia/Kathmandu",
    "iso:country":"NP",
    "name:und_x_variant":[
        "Or\u0101\u1e45\u1e0d\u0101\u0303\u1e0d\u0101",
        "Or\u0101\u1e45\u1e0d\u0101n\u1e0d\u0101"
    ],
    "wof:name":"Orandada",
    "wof:placetype":"locality"
},
  "geometry": {"coordinates":[86.2008,27.80084],"type":"Point"}
}