{
  "type": "Feature",
  "properties": {
    "gn:admin1_code":"WR",
    "gn:admin2_code":"4",
    "gn:admin3_code":"37",
    "gn:admin4_code":"370030",
    "gn:asciiname":"Kaurani",
    "gn:country_code":"NP",
    "gn:dem":1045,
    "gn:feature_class":"P",
    "gn:feature_code":"PPLL",
    "gn:name":"Kaurani",
    "gn:population":0,
    "gn:timezone":"Asia/Kathmandu",
    "iso:country":"NP",
    "wof:name":"Kaurani",
    "wof:placetype":"locality"
},
  "geometry": {"coordinates":[84.25736999999999,28.20606],"type":"Point"}
}