{
  "type": "Feature",
  "properties": {
    "gn:admin1_code":"WR",
    "gn:admin2_code":"8",
    "gn:admin3_code":"51.0",
    "gn:admin4_code":"510004.0",
    "gn:asciiname":"Khagabesi",
    "gn:country_code":"NP",
    "gn:dem":935,
    "gn:feature_class":"P",
    "gn:feature_code":"PPLL",
    "gn:name":"Khagabesi",
    "gn:population":0,
    "gn:timezone":"Asia/Kathmandu",
    "iso:country":"NP",
    "wof:name":"Khagabesi",
    "wof:placetype":"locality"
},
  "geometry": {"coordinates":[82.9936,28.00827],"type":"Point"}
}