{
  "type": "Feature",
  "properties": {
    "gn:admin1_code":"FR",
    "gn:admin2_code":"14",
    "gn:admin3_code":"70.0",
    "gn:admin4_code":"700014.0",
    "gn:asciiname":"Rambhat",
    "gn:country_code":"NP",
    "gn:dem":984,
    "gn:feature_class":"P",
    "gn:feature_code":"PPLL",
    "gn:name":"Rambhat",
    "gn:population":0,
    "gn:timezone":"Asia/Kathmandu",
    "iso:country":"NP",
    "wof:name":"Rambhat",
    "wof:placetype":"locality"
},
  "geometry": {"coordinates":[80.96823000000001,29.19012],"type":"Point"}
}