{
  "type": "Feature",
  "properties": {
    "gn:admin1_code":"CR",
    "gn:admin2_code":"11",
    "gn:admin3_code":"31",
    "gn:admin4_code":"310019",
    "gn:asciiname":"Girigaun",
    "gn:country_code":"NP",
    "gn:dem":465,
    "gn:feature_class":"P",
    "gn:feature_code":"PPLL",
    "gn:name":"Girigaun",
    "gn:population":0,
    "gn:timezone":"Asia/Kathmandu",
    "iso:country":"NP",
    "wof:name":"Girigaun",
    "wof:placetype":"locality"
},
  "geometry": {"coordinates":[85.09664000000002,27.4013],"type":"Point"}
}