{
  "type": "Feature",
  "properties": {
    "gn:admin1_code":"WR",
    "gn:admin2_code":"3",
    "gn:admin3_code":"44",
    "gn:admin4_code":"440027",
    "gn:asciiname":"Chuderagaun",
    "gn:country_code":"NP",
    "gn:dem":1351,
    "gn:feature_class":"P",
    "gn:feature_code":"PPLL",
    "gn:name":"Chuderagaun",
    "gn:population":0,
    "gn:timezone":"Asia/Kathmandu",
    "iso:country":"NP",
    "wof:name":"Chuderagaun",
    "wof:placetype":"locality"
},
  "geometry": {"coordinates":[83.75749999999999,28.1755],"type":"Point"}
}