{
  "type": "Feature",
  "properties": {
    "gn:admin1_code":"ER",
    "gn:admin2_code":"7",
    "gn:admin3_code":"7.0",
    "gn:admin4_code":"70003.0",
    "gn:asciiname":"Yangpang",
    "gn:country_code":"NP",
    "gn:dem":1538,
    "gn:feature_class":"P",
    "gn:feature_code":"PPLL",
    "gn:name":"Yangpang",
    "gn:population":0,
    "gn:timezone":"Asia/Kathmandu",
    "iso:country":"NP",
    "name:ceb_x_preferred":[
        "Yangpang"
    ],
    "name:mai_x_preferred":[
        "\u092f\u093e\u0919\u092a\u093e\u0919"
    ],
    "name:msa_x_preferred":[
        "Yangpang"
    ],
    "name:new_x_preferred":[
        "\u092f\u093e\u0919\u092a\u093e\u0919"
    ],
    "name:pol_x_preferred":[
        "Yangpang"
    ],
    "name:urd_x_preferred":[
        "\u06cc\u0646\u06af\u067e\u0646\u06af"
    ],
    "wof:name":"Yangpang",
    "wof:placetype":"locality"
},
  "geometry": {"coordinates":[87.33295,27.11071],"type":"Point"}
}