{
  "type": "Feature",
  "properties": {
    "gn:admin1_code":"CR",
    "gn:admin2_code":"1",
    "gn:admin3_code":"30.0",
    "gn:admin4_code":"300037.0",
    "gn:asciiname":"Birabari",
    "gn:country_code":"NP",
    "gn:dem":786,
    "gn:feature_class":"P",
    "gn:feature_code":"PPLL",
    "gn:name":"Birabari",
    "gn:population":0,
    "gn:timezone":"Asia/Kathmandu",
    "iso:country":"NP",
    "wof:name":"Birabari",
    "wof:placetype":"locality"
},
  "geometry": {"coordinates":[84.90955,27.77103],"type":"Point"}
}