{
  "type": "Feature",
  "properties": {
    "gn:admin1_code":"WR",
    "gn:admin2_code":"4.0",
    "gn:admin3_code":"39.0",
    "gn:admin4_code":"390040.0",
    "gn:asciiname":"Pawai (Hatiya)",
    "gn:country_code":"NP",
    "gn:dem":978,
    "gn:feature_class":"P",
    "gn:feature_code":"PPLL",
    "gn:name":"Pawai (Hatiya)",
    "gn:population":0,
    "gn:timezone":"Asia/Kathmandu",
    "iso:country":"NP",
    "wof:name":"Pawai (Hatiya)",
    "wof:placetype":"locality"
},
  "geometry": {"coordinates":[83.92549,28.13185],"type":"Point"}
}