{
  "type": "Feature",
  "properties": {
    "gn:admin1_code":"FR",
    "gn:admin2_code":"9",
    "gn:admin3_code":"73.0",
    "gn:admin4_code":"730019.0",
    "gn:asciiname":"Jakh",
    "gn:country_code":"NP",
    "gn:dem":1063,
    "gn:feature_class":"P",
    "gn:feature_code":"PPLL",
    "gn:name":"Jakh",
    "gn:population":0,
    "gn:timezone":"Asia/Kathmandu",
    "iso:country":"NP",
    "wof:name":"Jakh",
    "wof:placetype":"locality"
},
  "geometry": {"coordinates":[80.33530999999998,29.29827],"type":"Point"}
}