{
  "type": "Feature",
  "properties": {
    "gn:admin1_code":"FR",
    "gn:admin2_code":"14",
    "gn:admin3_code":"68",
    "gn:admin4_code":"680023",
    "gn:asciiname":"Athbis",
    "gn:country_code":"NP",
    "gn:dem":1730,
    "gn:feature_class":"P",
    "gn:feature_code":"PPLL",
    "gn:name":"Athbis",
    "gn:population":0,
    "gn:timezone":"Asia/Kathmandu",
    "iso:country":"NP",
    "wof:name":"Athbis",
    "wof:placetype":"locality"
},
  "geometry": {"coordinates":[81.06583000000001,29.45903],"type":"Point"}
}