{
  "type": "Feature",
  "properties": {
    "gn:admin1_code":"WR",
    "gn:admin2_code":"4",
    "gn:admin3_code":"36.0",
    "gn:admin4_code":"360038.0",
    "gn:asciiname":"Khanibesi",
    "gn:country_code":"NP",
    "gn:dem":1105,
    "gn:feature_class":"P",
    "gn:feature_code":"PPLL",
    "gn:name":"Khanibesi",
    "gn:population":0,
    "gn:timezone":"Asia/Kathmandu",
    "iso:country":"NP",
    "wof:name":"Khanibesi",
    "wof:placetype":"locality"
},
  "geometry": {"coordinates":[84.87109,28.18999],"type":"Point"}
}