{
  "type": "Feature",
  "properties": {
    "gn:admin1_code":"MR",
    "gn:admin2_code":"2.0",
    "gn:admin3_code":"58.0",
    "gn:admin4_code":"580030.0",
    "gn:asciiname":"Ambarpur",
    "gn:country_code":"NP",
    "gn:dem":150,
    "gn:feature_class":"P",
    "gn:feature_code":"PPLL",
    "gn:name":"Ambarpur",
    "gn:population":0,
    "gn:timezone":"Asia/Kathmandu",
    "iso:country":"NP",
    "wof:name":"Ambarpur",
    "wof:placetype":"locality"
},
  "geometry": {"coordinates":[81.24654,28.39738],"type":"Point"}
}