{
  "type": "Feature",
  "properties": {
    "gn:admin1_code":"MR",
    "gn:admin2_code":"2.0",
    "gn:admin3_code":"58.0",
    "gn:admin4_code":"580030.0",
    "gn:asciiname":"Ambarpur",
    "gn:country_code":"NP",
    "gn:dem":150,
    "gn:feature_class":"P",
    "gn:feature_code":"PPLL",
    "gn:name":"Ambarpur",
    "gn:population":0,
    "gn:timezone":"Asia/Kathmandu",
    "iso:country":"NP",
    "name:bih_x_preferred":[
        "\u0905\u092e\u0930\u092a\u0941\u0930"
    ],
    "name:ceb_x_preferred":[
        "Amarpur"
    ],
    "name:fas_x_preferred":[
        "\u0627\u0645\u0628\u0627\u0631\u067e\u0648\u0631"
    ],
    "name:mai_x_preferred":[
        "\u0905\u092e\u092c\u0930\u092a\u0941\u0930"
    ],
    "name:msa_x_preferred":[
        "Ambarpur"
    ],
    "name:nep_x_preferred":[
        "\u0905\u092e\u0930\u092a\u0941\u0930"
    ],
    "name:pol_x_preferred":[
        "Amarpur"
    ],
    "wof:name":"Ambarpur",
    "wof:placetype":"locality"
},
  "geometry": {"coordinates":[81.24654,28.39738],"type":"Point"}
}