{
  "type": "Feature",
  "properties": {
    "gn:admin1_code":"CR",
    "gn:admin2_code":"5",
    "gn:admin3_code":"22.0",
    "gn:admin4_code":"220026.0",
    "gn:asciiname":"Pokhare",
    "gn:country_code":"NP",
    "gn:dem":1856,
    "gn:feature_class":"P",
    "gn:feature_code":"PPLL",
    "gn:name":"Pokhare",
    "gn:population":0,
    "gn:timezone":"Asia/Kathmandu",
    "iso:country":"NP",
    "name:bih_x_preferred":[
        "\u092a\u094b\u0916\u0930\u0947"
    ],
    "name:ceb_x_preferred":[
        "Pokhare"
    ],
    "name:fra_x_preferred":[
        "Pokhare"
    ],
    "name:msa_x_preferred":[
        "Pokhare"
    ],
    "name:nep_x_preferred":[
        "\u092a\u094b\u0916\u0930\u0947"
    ],
    "name:new_x_preferred":[
        "\u092a\u094b\u0916\u0930\u0947"
    ],
    "name:pol_x_preferred":[
        "Pokhare"
    ],
    "wof:name":"Pokhare",
    "wof:placetype":"locality"
},
  "geometry": {"coordinates":[86.15379,27.63736],"type":"Point"}
}