{
  "type": "Feature",
  "properties": {
    "gn:admin1_code":"CR",
    "gn:admin2_code":"1",
    "gn:admin3_code":"27.0",
    "gn:admin4_code":"270050.0",
    "gn:asciiname":"Kalankithan",
    "gn:country_code":"NP",
    "gn:dem":1504,
    "gn:feature_class":"P",
    "gn:feature_code":"PPLL",
    "gn:name":"Kalankithan",
    "gn:population":0,
    "gn:timezone":"Asia/Kathmandu",
    "iso:country":"NP",
    "wof:name":"Kalankithan",
    "wof:placetype":"locality"
},
  "geometry": {"coordinates":[85.25513000000002,27.7079],"type":"Point"}
}