{
  "type": "Feature",
  "properties": {
    "gn:admin1_code":"MR",
    "gn:admin2_code":"2",
    "gn:admin3_code":"61.0",
    "gn:admin4_code":"610008.0",
    "gn:asciiname":"Talguda",
    "gn:country_code":"NP",
    "gn:dem":2515,
    "gn:feature_class":"P",
    "gn:feature_code":"PPLL",
    "gn:name":"Talguda",
    "gn:population":0,
    "gn:timezone":"Asia/Kathmandu",
    "iso:country":"NP",
    "wof:name":"Talguda",
    "wof:placetype":"locality"
},
  "geometry": {"coordinates":[82.04021999999998,28.91312000000001],"type":"Point"}
}