{
  "type": "Feature",
  "properties": {
    "gn:admin1_code":"ER",
    "gn:admin2_code":"13",
    "gn:admin3_code":"11",
    "gn:admin4_code":"110021",
    "gn:asciiname":"Wada",
    "gn:country_code":"NP",
    "gn:dem":1224,
    "gn:feature_class":"P",
    "gn:feature_code":"PPLL",
    "gn:name":"Wada",
    "gn:population":0,
    "gn:timezone":"Asia/Kathmandu",
    "iso:country":"NP",
    "name:ceb_x_preferred":[
        "Wada"
    ],
    "name:deu_x_preferred":[
        "Wada"
    ],
    "name:fra_x_preferred":[
        "Wada"
    ],
    "name:mar_x_preferred":[
        "\u0935\u093e\u0921\u093e"
    ],
    "name:pol_x_preferred":[
        "Wada"
    ],
    "name:rus_x_preferred":[
        "\u0412\u0430\u0434\u0430"
    ],
    "name:swe_x_preferred":[
        "Wada"
    ],
    "wof:name":"Wada",
    "wof:placetype":"locality"
},
  "geometry": {"coordinates":[86.73673000000002,27.45268],"type":"Point"}
}