{
  "type": "Feature",
  "properties": {
    "gn:admin1_code":"CR",
    "gn:admin2_code":"5",
    "gn:admin3_code":"17.0",
    "gn:admin4_code":"170073.0",
    "gn:asciiname":"Bishrampur",
    "gn:country_code":"NP",
    "gn:dem":182,
    "gn:feature_class":"P",
    "gn:feature_code":"PPLL",
    "gn:name":"Bishrampur",
    "gn:population":0,
    "gn:timezone":"Asia/Kathmandu",
    "iso:country":"NP",
    "name:nep_x_preferred":[
        "\u0935\u093f\u0936\u094d\u0930\u093e\u092e\u092a\u0941\u0930"
    ],
    "name:new_x_preferred":[
        "\u0935\u093f\u0936\u094d\u0930\u093e\u092e\u092a\u0941\u0930"
    ],
    "name:pol_x_preferred":[
        "Bishrampur"
    ],
    "wof:name":"Bishrampur",
    "wof:placetype":"locality"
},
  "geometry": {"coordinates":[85.98133,26.93441],"type":"Point"}
}