{
  "type": "Feature",
  "properties": {
    "iso:country":"NP",
    "qs:gn_pop":0,
    "qs:name":"Pashupati Kshetra",
    "qs:name_adm0":"Nepal",
    "qs:name_adm1":"Madhyamanchal",
    "qs:photos":490,
    "qs:photos_1k":99,
    "qs:photos_9k":2,
    "qs:photos_9r":5,
    "qs:photos_all":490,
    "qs:photos_sr":7,
    "qs:placetype":"Town",
    "qs:pop_sr":"0",
    "qs:woe_adm0":23424911,
    "wof:name":"Pashupati Kshetra",
    "wof:placetype":"locality"
},
  "geometry": {"coordinates":[85.347762,27.710411],"type":"Point"}
}