{
  "type": "Feature",
  "properties": {
    "gn:admin1_code":"CR",
    "gn:admin2_code":"5",
    "gn:admin3_code":"19",
    "gn:admin4_code":"190071",
    "gn:asciiname":"Satas",
    "gn:country_code":"NP",
    "gn:dem":316,
    "gn:feature_class":"P",
    "gn:feature_code":"PPLL",
    "gn:name":"Satas",
    "gn:population":0,
    "gn:timezone":"Asia/Kathmandu",
    "iso:country":"NP",
    "wof:name":"Satas",
    "wof:placetype":"locality"
},
  "geometry": {"coordinates":[85.70063,27.14364],"type":"Point"}
}