{
  "type": "Feature",
  "properties": {
    "gn:admin1_code":"MR",
    "gn:admin2_code":"6",
    "gn:admin3_code":"66.0",
    "gn:admin4_code":"660019.0",
    "gn:asciiname":"Siniyan jyula",
    "gn:country_code":"NP",
    "gn:dem":1975,
    "gn:feature_class":"P",
    "gn:feature_code":"PPLL",
    "gn:name":"Siniyan jyula",
    "gn:population":0,
    "gn:timezone":"Asia/Kathmandu",
    "iso:country":"NP",
    "wof:name":"Siniyan jyula",
    "wof:placetype":"locality"
},
  "geometry": {"coordinates":[81.88365999999998,29.83813],"type":"Point"}
}