{
  "type": "Feature",
  "properties": {
    "gn:admin1_code":"ER",
    "gn:admin2_code":"10",
    "gn:admin3_code":"3.0",
    "gn:admin4_code":"30027.0",
    "gn:asciiname":"Dhwanse",
    "gn:country_code":"NP",
    "gn:dem":2170,
    "gn:feature_class":"P",
    "gn:feature_code":"PPLL",
    "gn:name":"Dhwanse",
    "gn:population":0,
    "gn:timezone":"Asia/Kathmandu",
    "iso:country":"NP",
    "wof:name":"Dhwanse",
    "wof:placetype":"locality"
},
  "geometry": {"coordinates":[87.91489,27.02523],"type":"Point"}
}