{
  "type": "Feature",
  "properties": {
    "gn:admin1_code":"MR",
    "gn:admin2_code":"2",
    "gn:admin3_code":"60.0",
    "gn:admin4_code":"600033.0",
    "gn:asciiname":"Panimul",
    "gn:country_code":"NP",
    "gn:dem":1672,
    "gn:feature_class":"P",
    "gn:feature_code":"PPLL",
    "gn:name":"Panimul",
    "gn:population":0,
    "gn:timezone":"Asia/Kathmandu",
    "iso:country":"NP",
    "wof:name":"Panimul",
    "wof:placetype":"locality"
},
  "geometry": {"coordinates":[81.62895999999998,28.79825],"type":"Point"}
}