{
  "type": "Feature",
  "properties": {
    "gn:admin1_code":"CR",
    "gn:admin2_code":"5",
    "gn:admin3_code":"20",
    "gn:admin4_code":"200039",
    "gn:asciiname":"Siureni",
    "gn:country_code":"NP",
    "gn:dem":292,
    "gn:feature_class":"P",
    "gn:feature_code":"PPLL",
    "gn:name":"Siureni",
    "gn:population":0,
    "gn:timezone":"Asia/Kathmandu",
    "iso:country":"NP",
    "wof:name":"Siureni",
    "wof:placetype":"locality"
},
  "geometry": {"coordinates":[85.5181,27.29143],"type":"Point"}
}