{
  "type": "Feature",
  "properties": {
    "gn:admin1_code":"CR",
    "gn:admin2_code":"5",
    "gn:admin3_code":"18",
    "gn:admin4_code":"180040",
    "gn:asciiname":"Kolhuwa",
    "gn:country_code":"NP",
    "gn:dem":73,
    "gn:feature_class":"P",
    "gn:feature_code":"PPLL",
    "gn:name":"Kolhuwa",
    "gn:population":0,
    "gn:timezone":"Asia/Kathmandu",
    "iso:country":"NP",
    "name:ceb_x_preferred":[
        "Kolhuwa"
    ],
    "name:fra_x_preferred":[
        "Kolhuwa"
    ],
    "name:msa_x_preferred":[
        "Kolhuwa"
    ],
    "name:nep_x_preferred":[
        "\u0915\u094b\u0932\u094d\u0939\u0941\u0935\u093e"
    ],
    "name:new_x_preferred":[
        "\u0915\u094b\u0932\u094d\u0939\u0941\u0935\u093e"
    ],
    "name:pol_x_preferred":[
        "Kolhuwa"
    ],
    "wof:name":"Kolhuwa",
    "wof:placetype":"locality"
},
  "geometry": {"coordinates":[85.79143000000001,26.69038],"type":"Point"}
}