{
  "type": "Feature",
  "properties": {
    "gn:admin1_code":"CR",
    "gn:admin2_code":"5",
    "gn:admin3_code":"22.0",
    "gn:admin4_code":"220042.0",
    "gn:asciiname":"Baiti",
    "gn:country_code":"NP",
    "gn:dem":1777,
    "gn:feature_class":"P",
    "gn:feature_code":"PPLL",
    "gn:name":"Baiti",
    "gn:population":0,
    "gn:timezone":"Asia/Kathmandu",
    "iso:country":"NP",
    "wof:name":"Baiti",
    "wof:placetype":"locality"
},
  "geometry": {"coordinates":[86.12308,27.64213],"type":"Point"}
}