{
  "type": "Feature",
  "properties": {
    "gn:admin1_code":"CR",
    "gn:admin2_code":"5",
    "gn:admin3_code":"21",
    "gn:admin4_code":"210055",
    "gn:asciiname":"Laitar",
    "gn:country_code":"NP",
    "gn:dem":2271,
    "gn:feature_class":"P",
    "gn:feature_code":"PPLL",
    "gn:name":"Laitar",
    "gn:population":0,
    "gn:timezone":"Asia/Kathmandu",
    "iso:country":"NP",
    "wof:name":"Laitar",
    "wof:placetype":"locality"
},
  "geometry": {"coordinates":[85.90239,27.56069],"type":"Point"}
}