{
  "type": "Feature",
  "properties": {
    "gn:admin1_code":"00",
    "gn:asciiname":"Mankali",
    "gn:country_code":"NP",
    "gn:dem":1115,
    "gn:feature_class":"P",
    "gn:feature_code":"PPL",
    "gn:name":"Mankali",
    "gn:population":0,
    "gn:timezone":"Asia/Kathmandu",
    "iso:country":"NP",
    "wof:name":"Mankali",
    "wof:placetype":"locality"
},
  "geometry": {"coordinates":[81.26363000000001,29.28685],"type":"Point"}
}