{
  "type": "Feature",
  "properties": {
    "gn:admin1_code":"WR",
    "gn:admin2_code":"8",
    "gn:admin3_code":"48",
    "gn:admin4_code":"480007",
    "gn:asciiname":"Bharta",
    "gn:country_code":"NP",
    "gn:dem":207,
    "gn:feature_class":"P",
    "gn:feature_code":"PPLL",
    "gn:name":"Bharta",
    "gn:population":0,
    "gn:timezone":"Asia/Kathmandu",
    "iso:country":"NP",
    "wof:name":"Bharta",
    "wof:placetype":"locality"
},
  "geometry": {"coordinates":[83.86936999999998,27.65103],"type":"Point"}
}