{
  "type": "Feature",
  "properties": {
    "gn:admin1_code":"ER",
    "gn:admin2_code":"10",
    "gn:admin3_code":"4.0",
    "gn:admin4_code":"40040.0",
    "gn:asciiname":"Danguwajhoda",
    "gn:country_code":"NP",
    "gn:dem":76,
    "gn:feature_class":"P",
    "gn:feature_code":"PPLL",
    "gn:name":"Danguwajhoda",
    "gn:population":0,
    "gn:timezone":"Asia/Kathmandu",
    "iso:country":"NP",
    "wof:name":"Danguwajhoda",
    "wof:placetype":"locality"
},
  "geometry": {"coordinates":[87.99396999999998,26.44401],"type":"Point"}
}