{
  "type": "Feature",
  "properties": {
    "gn:admin1_code":"FR",
    "gn:admin2_code":"14",
    "gn:admin3_code":"68",
    "gn:admin4_code":"680009",
    "gn:asciiname":"Punpati",
    "gn:country_code":"NP",
    "gn:dem":2011,
    "gn:feature_class":"P",
    "gn:feature_code":"PPLL",
    "gn:name":"Punpati",
    "gn:population":0,
    "gn:timezone":"Asia/Kathmandu",
    "iso:country":"NP",
    "wof:name":"Punpati",
    "wof:placetype":"locality"
},
  "geometry": {"coordinates":[80.93648,29.41374],"type":"Point"}
}