{
  "type": "Feature",
  "properties": {
    "gn:admin1_code":"CR",
    "gn:admin2_code":"1",
    "gn:admin3_code":"24.0",
    "gn:admin4_code":"240012.0",
    "gn:asciiname":"Betini",
    "gn:country_code":"NP",
    "gn:dem":1516,
    "gn:feature_class":"P",
    "gn:feature_code":"PPLL",
    "gn:name":"Betini",
    "gn:population":0,
    "gn:timezone":"Asia/Kathmandu",
    "iso:country":"NP",
    "name:fra_x_preferred":[
        "Betini"
    ],
    "name:pol_x_preferred":[
        "Betini"
    ],
    "wof:name":"Betini",
    "wof:placetype":"locality"
},
  "geometry": {"coordinates":[85.68885999999998,27.39175],"type":"Point"}
}