{
  "type": "Feature",
  "properties": {
    "gn:admin1_code":"CR",
    "gn:admin2_code":"1",
    "gn:admin3_code":"27.0",
    "gn:admin4_code":"270027.0",
    "gn:asciiname":"Ghimiregaun",
    "gn:country_code":"NP",
    "gn:dem":1487,
    "gn:feature_class":"P",
    "gn:feature_code":"PPLL",
    "gn:name":"Ghimiregaun",
    "gn:population":0,
    "gn:timezone":"Asia/Kathmandu",
    "iso:country":"NP",
    "wof:name":"Ghimiregaun",
    "wof:placetype":"locality"
},
  "geometry": {"coordinates":[85.28791,27.78667],"type":"Point"}
}