{
  "type": "Feature",
  "properties": {
    "gn:admin1_code":"MR",
    "gn:admin2_code":"2.0",
    "gn:admin3_code":"57.0",
    "gn:admin4_code":"570047.0",
    "gn:asciiname":"Udayapur",
    "gn:country_code":"NP",
    "gn:dem":149,
    "gn:feature_class":"P",
    "gn:feature_code":"PPLL",
    "gn:name":"Udayapur",
    "gn:population":0,
    "gn:timezone":"Asia/Kathmandu",
    "iso:country":"NP",
    "name:ceb_x_preferred":[
        "Udayapur"
    ],
    "name:ita_x_preferred":[
        "Udayapur"
    ],
    "name:nep_x_preferred":[
        "\u0909\u0926\u092f\u092a\u0941\u0930"
    ],
    "name:nld_x_preferred":[
        "Udayapur"
    ],
    "name:pol_x_preferred":[
        "Udayapur"
    ],
    "wof:name":"Udayapur",
    "wof:placetype":"locality"
},
  "geometry": {"coordinates":[81.64950999999998,28.03805],"type":"Point"}
}