{
  "type": "Feature",
  "properties": {
    "gn:admin1_code":"FR",
    "gn:admin2_code":"9",
    "gn:admin3_code":"74",
    "gn:admin4_code":"740016",
    "gn:asciiname":"Dhamali",
    "gn:country_code":"NP",
    "gn:dem":1540,
    "gn:feature_class":"P",
    "gn:feature_code":"PPLL",
    "gn:name":"Dhamali",
    "gn:population":0,
    "gn:timezone":"Asia/Kathmandu",
    "iso:country":"NP",
    "name:ceb_x_preferred":[
        "Dhamali"
    ],
    "name:fra_x_preferred":[
        "Dhamali"
    ],
    "name:mai_x_preferred":[
        "\u0927\u092e\u093e\u0932\u0940"
    ],
    "name:msa_x_preferred":[
        "Dhamali"
    ],
    "name:nep_x_preferred":[
        "\u0927\u092e\u0932\u0940"
    ],
    "name:new_x_preferred":[
        "\u0927\u092e\u0932\u0940"
    ],
    "name:pol_x_preferred":[
        "Dhamali"
    ],
    "wof:name":"Dhamali",
    "wof:placetype":"locality"
},
  "geometry": {"coordinates":[80.59184999999999,29.65769],"type":"Point"}
}