{
  "type": "Feature",
  "properties": {
    "gn:admin1_code":"FR",
    "gn:admin2_code":"14",
    "gn:admin3_code":"70.0",
    "gn:admin4_code":"700022.0",
    "gn:asciiname":"Prithimalla Kharka",
    "gn:country_code":"NP",
    "gn:dem":1832,
    "gn:feature_class":"P",
    "gn:feature_code":"PPLL",
    "gn:name":"Prithimalla Kharka",
    "gn:population":0,
    "gn:timezone":"Asia/Kathmandu",
    "iso:country":"NP",
    "wof:name":"Prithimalla Kharka",
    "wof:placetype":"locality"
},
  "geometry": {"coordinates":[81.10978,29.29852],"type":"Point"}
}