{
  "type": "Feature",
  "properties": {
    "gn:admin1_code":"ER",
    "gn:admin2_code":"13",
    "gn:admin3_code":"13",
    "gn:admin4_code":"130052",
    "gn:asciiname":"Mauwabote",
    "gn:country_code":"NP",
    "gn:dem":1083,
    "gn:feature_class":"P",
    "gn:feature_code":"PPLL",
    "gn:name":"Mauwabote",
    "gn:population":0,
    "gn:timezone":"Asia/Kathmandu",
    "iso:country":"NP",
    "name:ceb_x_preferred":[
        "Mauwabote"
    ],
    "name:mai_x_preferred":[
        "\u092e\u094c\u0935\u093e\u092c\u093e\u091f\u0947"
    ],
    "name:msa_x_preferred":[
        "Mauwabote"
    ],
    "name:new_x_preferred":[
        "\u092e\u094c\u0935\u093e\u092c\u094b\u091f\u0947"
    ],
    "name:pol_x_preferred":[
        "Mauwabote"
    ],
    "wof:name":"Mauwabote",
    "wof:placetype":"locality"
},
  "geometry": {"coordinates":[86.86725,26.95176],"type":"Point"}
}