{
  "type": "Feature",
  "properties": {
    "gn:admin1_code":"ER",
    "gn:admin2_code":"10",
    "gn:admin3_code":"4.0",
    "gn:admin4_code":"40028.0",
    "gn:asciiname":"Harira",
    "gn:country_code":"NP",
    "gn:dem":77,
    "gn:feature_class":"P",
    "gn:feature_code":"PPLL",
    "gn:name":"Harira",
    "gn:population":0,
    "gn:timezone":"Asia/Kathmandu",
    "iso:country":"NP",
    "name:ara_x_preferred":[
        "\u062d\u0631\u064a\u0631\u0629"
    ],
    "name:cat_x_preferred":[
        "Harira"
    ],
    "name:deu_x_preferred":[
        "Harira"
    ],
    "name:epo_x_preferred":[
        "Harira"
    ],
    "name:fra_x_preferred":[
        "Harira"
    ],
    "name:hrv_x_preferred":[
        "Harira"
    ],
    "name:ind_x_preferred":[
        "Harira"
    ],
    "name:ita_x_preferred":[
        "Harira"
    ],
    "name:msa_x_preferred":[
        "Harira"
    ],
    "name:nld_x_preferred":[
        "Harira"
    ],
    "name:pol_x_preferred":[
        "Harira"
    ],
    "name:por_x_preferred":[
        "Harira"
    ],
    "name:spa_x_preferred":[
        "Harira"
    ],
    "name:sqi_x_preferred":[
        "Harira"
    ],
    "wof:name":"Harira",
    "wof:placetype":"locality"
},
  "geometry": {"coordinates":[87.67418000000001,26.47329],"type":"Point"}
}