{
  "type": "Feature",
  "properties": {
    "gn:admin1_code":"ER",
    "gn:admin2_code":"10",
    "gn:admin3_code":"4.0",
    "gn:admin4_code":"40015.0",
    "gn:asciiname":"Kamaljhora",
    "gn:country_code":"NP",
    "gn:dem":95,
    "gn:feature_class":"P",
    "gn:feature_code":"PPLL",
    "gn:name":"Kamaljhora",
    "gn:population":0,
    "gn:timezone":"Asia/Kathmandu",
    "iso:country":"NP",
    "wof:name":"Kamaljhora",
    "wof:placetype":"locality"
},
  "geometry": {"coordinates":[87.79835,26.56402000000001],"type":"Point"}
}