{
  "type": "Feature",
  "properties": {
    "gn:admin1_code":"MR",
    "gn:admin2_code":"12",
    "gn:admin3_code":"55",
    "gn:admin4_code":"550025",
    "gn:asciiname":"Akali",
    "gn:country_code":"NP",
    "gn:dem":1736,
    "gn:feature_class":"P",
    "gn:feature_code":"PPLL",
    "gn:name":"Akali",
    "gn:population":0,
    "gn:timezone":"Asia/Kathmandu",
    "iso:country":"NP",
    "name:mal_x_preferred":[
        "\u0d05\u0d15\u0d3e\u0d32\u0d3f"
    ],
    "wof:name":"Akali",
    "wof:placetype":"locality"
},
  "geometry": {"coordinates":[82.32566,28.33679],"type":"Point"}
}