{
  "type": "Feature",
  "properties": {
    "gn:admin1_code":"00",
    "gn:asciiname":"Chisopani",
    "gn:country_code":"NP",
    "gn:dem":139,
    "gn:feature_class":"P",
    "gn:feature_code":"PPL",
    "gn:name":"Chisopani",
    "gn:population":0,
    "gn:timezone":"Asia/Kathmandu",
    "iso:country":"NP",
    "name:nep_x_preferred":[
        "Chis\u0101p\u0101ni\u0307\u0304"
    ],
    "name:und_x_variant":[
        "Chis\u0101p\u0101ni"
    ],
    "wof:name":"Chisopani",
    "wof:placetype":"locality"
},
  "geometry": {"coordinates":[86.14464,26.93246],"type":"Point"}
}