{
  "type": "Feature",
  "properties": {
    "gn:admin1_code":"FR",
    "gn:admin2_code":"14",
    "gn:admin3_code":"69.0",
    "gn:admin4_code":"690066.0",
    "gn:asciiname":"Basaut",
    "gn:country_code":"NP",
    "gn:dem":1546,
    "gn:feature_class":"P",
    "gn:feature_code":"PPLL",
    "gn:name":"Basaut",
    "gn:population":0,
    "gn:timezone":"Asia/Kathmandu",
    "iso:country":"NP",
    "wof:name":"Basaut",
    "wof:placetype":"locality"
},
  "geometry": {"coordinates":[81.10590999999999,29.19223],"type":"Point"}
}