{
  "type": "Feature",
  "properties": {
    "gn:admin1_code":"ER",
    "gn:admin2_code":"7",
    "gn:admin3_code":"10.0",
    "gn:admin4_code":"100006.0",
    "gn:asciiname":"Baghkhor",
    "gn:country_code":"NP",
    "gn:dem":1344,
    "gn:feature_class":"P",
    "gn:feature_code":"PPL",
    "gn:name":"Baghkhor",
    "gn:population":0,
    "gn:timezone":"Asia/Kathmandu",
    "iso:country":"NP",
    "wof:name":"Baghkhor",
    "wof:placetype":"locality"
},
  "geometry": {"coordinates":[87.12742,27.12133],"type":"Point"}
}