{
  "type": "Feature",
  "properties": {
    "gn:admin1_code":"WR",
    "gn:admin2_code":"4.0",
    "gn:admin3_code":"38.0",
    "gn:admin4_code":"380031.0",
    "gn:asciiname":"Dharampani",
    "gn:country_code":"NP",
    "gn:dem":963,
    "gn:feature_class":"P",
    "gn:feature_code":"PPLL",
    "gn:name":"Dharampani",
    "gn:population":0,
    "gn:timezone":"Asia/Kathmandu",
    "iso:country":"NP",
    "wof:name":"Dharampani",
    "wof:placetype":"locality"
},
  "geometry": {"coordinates":[84.25964,28.07467],"type":"Point"}
}