{
  "type": "Feature",
  "properties": {
    "gn:admin1_code":"WR",
    "gn:admin2_code":"3",
    "gn:admin3_code":"43",
    "gn:admin4_code":"430036",
    "gn:asciiname":"Harpet",
    "gn:country_code":"NP",
    "gn:dem":1817,
    "gn:feature_class":"P",
    "gn:feature_code":"PPLL",
    "gn:name":"Harpet",
    "gn:population":0,
    "gn:timezone":"Asia/Kathmandu",
    "iso:country":"NP",
    "wof:name":"Harpet",
    "wof:placetype":"locality"
},
  "geometry": {"coordinates":[83.3387,28.41252],"type":"Point"}
}