{
  "type": "Feature",
  "properties": {
    "gn:admin1_code":"WR",
    "gn:admin2_code":"3",
    "gn:admin3_code":"44",
    "gn:admin4_code":"440044",
    "gn:asciiname":"Rakse",
    "gn:country_code":"NP",
    "gn:dem":650,
    "gn:feature_class":"P",
    "gn:feature_code":"PPLL",
    "gn:name":"Rakse",
    "gn:population":0,
    "gn:timezone":"Asia/Kathmandu",
    "iso:country":"NP",
    "wof:name":"Rakse",
    "wof:placetype":"locality"
},
  "geometry": {"coordinates":[83.58668,28.02931],"type":"Point"}
}