{
  "type": "Feature",
  "properties": {
    "gn:admin1_code":"ER",
    "gn:admin2_code":"7",
    "gn:admin3_code":"9",
    "gn:admin4_code":"90008",
    "gn:asciiname":"Anptari",
    "gn:country_code":"NP",
    "gn:dem":717,
    "gn:feature_class":"P",
    "gn:feature_code":"PPLL",
    "gn:name":"Anptari",
    "gn:population":0,
    "gn:timezone":"Asia/Kathmandu",
    "iso:country":"NP",
    "wof:name":"Anptari",
    "wof:placetype":"locality"
},
  "geometry": {"coordinates":[87.24589,27.38105],"type":"Point"}
}