{
  "type": "Feature",
  "properties": {
    "gn:admin1_code":"FR",
    "gn:admin2_code":"14",
    "gn:admin3_code":"68",
    "gn:admin4_code":"680036",
    "gn:asciiname":"Bayana",
    "gn:country_code":"NP",
    "gn:dem":2184,
    "gn:feature_class":"P",
    "gn:feature_code":"PPLL",
    "gn:name":"Bayana",
    "gn:population":0,
    "gn:timezone":"Asia/Kathmandu",
    "iso:country":"NP",
    "wof:name":"Bayana",
    "wof:placetype":"locality"
},
  "geometry": {"coordinates":[81.20236,29.46167],"type":"Point"}
}