{
  "type": "Feature",
  "properties": {
    "gn:admin1_code":"CR",
    "gn:admin2_code":"1",
    "gn:admin3_code":"28",
    "gn:admin4_code":"280055",
    "gn:asciiname":"Kattachhap",
    "gn:country_code":"NP",
    "gn:dem":651,
    "gn:feature_class":"P",
    "gn:feature_code":"PPLL",
    "gn:name":"Kattachhap",
    "gn:population":0,
    "gn:timezone":"Asia/Kathmandu",
    "iso:country":"NP",
    "wof:name":"Kattachhap",
    "wof:placetype":"locality"
},
  "geometry": {"coordinates":[85.23276,27.89335],"type":"Point"}
}