{
  "type": "Feature",
  "properties": {
    "gn:admin1_code":"ER",
    "gn:admin2_code":"10",
    "gn:admin3_code":"3.0",
    "gn:admin4_code":"30032.0",
    "gn:asciiname":"Chitre",
    "gn:country_code":"NP",
    "gn:dem":2110,
    "gn:feature_class":"P",
    "gn:feature_code":"PPLL",
    "gn:name":"Chitre",
    "gn:population":0,
    "gn:timezone":"Asia/Kathmandu",
    "iso:country":"NP",
    "wof:name":"Chitre",
    "wof:placetype":"locality"
},
  "geometry": {"coordinates":[88.1262,26.97488],"type":"Point"}
}