{
  "type": "Feature",
  "properties": {
    "gn:admin1_code":"ER",
    "gn:admin2_code":"10.0",
    "gn:asciiname":"Ghuseni",
    "gn:country_code":"NP",
    "gn:dem":1119,
    "gn:feature_class":"P",
    "gn:feature_code":"PPL",
    "gn:name":"Ghuseni",
    "gn:population":0,
    "gn:timezone":"Asia/Kathmandu",
    "iso:country":"NP",
    "name:msa_x_preferred":[
        "Ghuseni"
    ],
    "name:nld_x_preferred":[
        "Ghuseni"
    ],
    "wof:name":"Ghuseni",
    "wof:placetype":"locality"
},
  "geometry": {"coordinates":[87.79753000000002,26.92297],"type":"Point"}
}