{
  "type": "Feature",
  "properties": {
    "gn:admin1_code":"MR",
    "gn:admin2_code":"12",
    "gn:admin3_code":"54",
    "gn:admin4_code":"540035",
    "gn:asciiname":"Jnaarju",
    "gn:country_code":"NP",
    "gn:dem":2053,
    "gn:feature_class":"P",
    "gn:feature_code":"PPLL",
    "gn:name":"Jnaarju",
    "gn:population":0,
    "gn:timezone":"Asia/Kathmandu",
    "iso:country":"NP",
    "wof:name":"Jnaarju",
    "wof:placetype":"locality"
},
  "geometry": {"coordinates":[82.86181999999999,28.69707],"type":"Point"}
}