{
  "type": "Feature",
  "properties": {
    "gn:admin1_code":"ER",
    "gn:admin2_code":"10",
    "gn:admin3_code":"3.0",
    "gn:admin4_code":"30016.0",
    "gn:asciiname":"Majhuwa",
    "gn:country_code":"NP",
    "gn:dem":1833,
    "gn:feature_class":"P",
    "gn:feature_code":"PPLL",
    "gn:name":"Majhuwa",
    "gn:population":0,
    "gn:timezone":"Asia/Kathmandu",
    "iso:country":"NP",
    "wof:name":"Majhuwa",
    "wof:placetype":"locality"
},
  "geometry": {"coordinates":[87.99794,27.0257],"type":"Point"}
}