{
  "type": "Feature",
  "properties": {
    "gn:admin1_code":"MR",
    "gn:admin2_code":"12",
    "gn:admin3_code":"52",
    "gn:admin4_code":"520047",
    "gn:asciiname":"Sripale",
    "gn:country_code":"NP",
    "gn:dem":1341,
    "gn:feature_class":"P",
    "gn:feature_code":"PPLL",
    "gn:name":"Sripale",
    "gn:population":0,
    "gn:timezone":"Asia/Kathmandu",
    "iso:country":"NP",
    "wof:name":"Sripale",
    "wof:placetype":"locality"
},
  "geometry": {"coordinates":[82.93598,28.11502],"type":"Point"}
}