{
  "type": "Feature",
  "properties": {
    "gn:admin1_code":"CR",
    "gn:admin2_code":"1",
    "gn:admin3_code":"23",
    "gn:admin4_code":"230048.0",
    "gn:asciiname":"Bagaicha",
    "gn:country_code":"NP",
    "gn:dem":871,
    "gn:feature_class":"P",
    "gn:feature_code":"PPLL",
    "gn:name":"Bagaicha",
    "gn:population":0,
    "gn:timezone":"Asia/Kathmandu",
    "iso:country":"NP",
    "wof:name":"Bagaicha",
    "wof:placetype":"locality"
},
  "geometry": {"coordinates":[85.57626999999999,27.83802],"type":"Point"}
}