{
  "type": "Feature",
  "properties": {
    "gn:admin1_code":"CR",
    "gn:admin2_code":"1.0",
    "gn:admin3_code":"26.0",
    "gn:admin4_code":"260004.0",
    "gn:asciiname":"Sangdaha",
    "gn:country_code":"NP",
    "gn:dem":1410,
    "gn:feature_class":"P",
    "gn:feature_code":"PPLL",
    "gn:name":"Sangdaha",
    "gn:population":0,
    "gn:timezone":"Asia/Kathmandu",
    "iso:country":"NP",
    "wof:name":"Sangdaha",
    "wof:placetype":"locality"
},
  "geometry": {"coordinates":[85.42905999999998,27.7132],"type":"Point"}
}