{
  "type": "Feature",
  "properties": {
    "gn:admin1_code":"CR",
    "gn:admin2_code":"11",
    "gn:admin3_code":"35.0",
    "gn:admin4_code":"350003.0",
    "gn:asciiname":"Basantapur",
    "gn:country_code":"NP",
    "gn:dem":180,
    "gn:feature_class":"P",
    "gn:feature_code":"PPLL",
    "gn:name":"Basantapur",
    "gn:population":0,
    "gn:timezone":"Asia/Kathmandu",
    "iso:country":"NP",
    "name:fra_x_preferred":[
        "Basantapur"
    ],
    "name:pol_x_preferred":[
        "Basantapur"
    ],
    "wof:name":"Basantapur",
    "wof:placetype":"locality"
},
  "geometry": {"coordinates":[84.31999,27.45728],"type":"Point"}
}