{
  "type": "Feature",
  "properties": {
    "gn:admin1_code":"00",
    "gn:asciiname":"Gopaldada",
    "gn:country_code":"NP",
    "gn:dem":185,
    "gn:feature_class":"P",
    "gn:feature_code":"PPL",
    "gn:name":"Gop\u0101l\u1e0d\u0101\u0303\u1e0d\u0101",
    "gn:population":0,
    "gn:timezone":"Asia/Kathmandu",
    "iso:country":"NP",
    "name:nep_x_preferred":[
        "Gop\u0101l\u1e0d\u0101\u0303\u1e0d\u0101"
    ],
    "wof:name":"Gopaldada",
    "wof:placetype":"locality"
},
  "geometry": {"coordinates":[88.03209,26.71286],"type":"Point"}
}