{
  "type": "Feature",
  "properties": {
    "gn:admin1_code":"CR",
    "gn:admin2_code":"1",
    "gn:admin3_code":"30.0",
    "gn:admin4_code":"300032.0",
    "gn:asciiname":"Nigalpani",
    "gn:country_code":"NP",
    "gn:dem":1259,
    "gn:feature_class":"P",
    "gn:feature_code":"PPLL",
    "gn:name":"Nigalpani",
    "gn:population":0,
    "gn:timezone":"Asia/Kathmandu",
    "iso:country":"NP",
    "wof:name":"Nigalpani",
    "wof:placetype":"locality"
},
  "geometry": {"coordinates":[84.86206999999997,27.95144],"type":"Point"}
}