{
  "type": "Feature",
  "properties": {
    "gn:admin1_code":"FR",
    "gn:admin2_code":"14",
    "gn:admin3_code":"69.0",
    "gn:admin4_code":"690067.0",
    "gn:asciiname":"Parmulli",
    "gn:country_code":"NP",
    "gn:dem":1388,
    "gn:feature_class":"P",
    "gn:feature_code":"PPLL",
    "gn:name":"Parmulli",
    "gn:population":0,
    "gn:timezone":"Asia/Kathmandu",
    "iso:country":"NP",
    "wof:name":"Parmulli",
    "wof:placetype":"locality"
},
  "geometry": {"coordinates":[81.08178000000002,29.18876],"type":"Point"}
}