{
  "type": "Feature",
  "properties": {
    "gn:admin1_code":"FR",
    "gn:admin2_code":"9",
    "gn:admin3_code":"75.0",
    "gn:admin4_code":"750012.0",
    "gn:asciiname":"Khalidanda",
    "gn:country_code":"NP",
    "gn:dem":2231,
    "gn:feature_class":"P",
    "gn:feature_code":"PPLL",
    "gn:name":"Khalidanda",
    "gn:population":0,
    "gn:timezone":"Asia/Kathmandu",
    "iso:country":"NP",
    "wof:name":"Khalidanda",
    "wof:placetype":"locality"
},
  "geometry": {"coordinates":[80.62935999999998,29.75352],"type":"Point"}
}