{
  "type": "Feature",
  "properties": {
    "gn:admin1_code":"MR",
    "gn:admin2_code":"12",
    "gn:admin3_code":"56.0",
    "gn:admin4_code":"560019.0",
    "gn:asciiname":"Maurighat",
    "gn:country_code":"NP",
    "gn:dem":284,
    "gn:feature_class":"P",
    "gn:feature_code":"PPLL",
    "gn:name":"Maurighat",
    "gn:population":0,
    "gn:timezone":"Asia/Kathmandu",
    "iso:country":"NP",
    "wof:name":"Maurighat",
    "wof:placetype":"locality"
},
  "geometry": {"coordinates":[82.69108,27.8496],"type":"Point"}
}