{
  "type": "Feature",
  "properties": {
    "gn:admin1_code":"FR",
    "gn:admin2_code":"9",
    "gn:admin3_code":"74",
    "gn:admin4_code":"740053",
    "gn:asciiname":"Mallo Kathmada",
    "gn:country_code":"NP",
    "gn:dem":2407,
    "gn:feature_class":"P",
    "gn:feature_code":"PPLL",
    "gn:name":"Mallo Kathmada",
    "gn:population":0,
    "gn:timezone":"Asia/Kathmandu",
    "iso:country":"NP",
    "wof:name":"Mallo Kathmada",
    "wof:placetype":"locality"
},
  "geometry": {"coordinates":[80.70147,29.54271],"type":"Point"}
}