{
  "type": "Feature",
  "properties": {
    "gn:admin1_code":"CR",
    "gn:admin2_code":"1",
    "gn:admin3_code":"30.0",
    "gn:admin4_code":"300008.0",
    "gn:asciiname":"Karkigaun",
    "gn:country_code":"NP",
    "gn:dem":1219,
    "gn:feature_class":"P",
    "gn:feature_code":"PPLL",
    "gn:name":"Karkigaun",
    "gn:population":0,
    "gn:timezone":"Asia/Kathmandu",
    "iso:country":"NP",
    "wof:name":"Karkigaun",
    "wof:placetype":"locality"
},
  "geometry": {"coordinates":[85.24166,27.76939],"type":"Point"}
}