{
  "type": "Feature",
  "properties": {
    "gn:admin1_code":"ER",
    "gn:admin2_code":"7.0",
    "gn:admin3_code":"8.0",
    "gn:admin4_code":"80009.0",
    "gn:asciiname":"Sungure",
    "gn:country_code":"NP",
    "gn:dem":1775,
    "gn:feature_class":"P",
    "gn:feature_code":"PPLL",
    "gn:name":"Sungure",
    "gn:population":0,
    "gn:timezone":"Asia/Kathmandu",
    "iso:country":"NP",
    "wof:name":"Sungure",
    "wof:placetype":"locality"
},
  "geometry": {"coordinates":[87.45810999999998,27.03952],"type":"Point"}
}