{
  "type": "Feature",
  "properties": {
    "gn:admin1_code":"ER",
    "gn:admin2_code":"7",
    "gn:admin3_code":"9",
    "gn:admin4_code":"90007.0",
    "gn:asciiname":"Rukma",
    "gn:country_code":"NP",
    "gn:dem":1743,
    "gn:feature_class":"P",
    "gn:feature_code":"PPLL",
    "gn:name":"Rukma",
    "gn:population":0,
    "gn:timezone":"Asia/Kathmandu",
    "iso:country":"NP",
    "wof:name":"Rukma",
    "wof:placetype":"locality"
},
  "geometry": {"coordinates":[87.39834999999999,27.74212],"type":"Point"}
}