{
  "type": "Feature",
  "properties": {
    "gn:admin1_code":"MR",
    "gn:admin2_code":"6",
    "gn:admin3_code":"63.0",
    "gn:admin4_code":"630010.0",
    "gn:asciiname":"Gothi",
    "gn:country_code":"NP",
    "gn:dem":2696,
    "gn:feature_class":"P",
    "gn:feature_code":"PPLL",
    "gn:name":"Gothi",
    "gn:population":0,
    "gn:timezone":"Asia/Kathmandu",
    "iso:country":"NP",
    "name:cat_x_preferred":[
        "Go\u00f0i"
    ],
    "name:dan_x_preferred":[
        "Gode"
    ],
    "name:deu_x_preferred":[
        "Godentum"
    ],
    "name:est_x_preferred":[
        "Goodi"
    ],
    "name:fra_x_preferred":[
        "Go\u00f0i"
    ],
    "name:fry_x_preferred":[
        "Go\u00f0i"
    ],
    "name:hun_x_preferred":[
        "Go\u00f0i"
    ],
    "name:isl_x_preferred":[
        "Go\u00f0or\u00f0sma\u00f0ur"
    ],
    "name:ita_x_preferred":[
        "Go\u00f0i"
    ],
    "name:nld_x_preferred":[
        "Go\u00f0i"
    ],
    "name:nor_x_preferred":[
        "Gode"
    ],
    "name:por_x_preferred":[
        "Godi"
    ],
    "name:rus_x_preferred":[
        "\u0413\u043e\u0434\u0438"
    ],
    "name:spa_x_preferred":[
        "Go\u00f0i"
    ],
    "name:swe_x_preferred":[
        "Gode"
    ],
    "wof:name":"Gothi",
    "wof:placetype":"locality"
},
  "geometry": {"coordinates":[81.91769000000002,29.18246],"type":"Point"}
}