{
  "type": "Feature",
  "properties": {
    "gn:admin1_code":"MR",
    "gn:admin2_code":"12",
    "gn:admin3_code":"54",
    "gn:admin4_code":"540019",
    "gn:asciiname":"Damaju",
    "gn:country_code":"NP",
    "gn:dem":1750,
    "gn:feature_class":"P",
    "gn:feature_code":"PPLL",
    "gn:name":"Damaju",
    "gn:population":0,
    "gn:timezone":"Asia/Kathmandu",
    "iso:country":"NP",
    "wof:name":"Damaju",
    "wof:placetype":"locality"
},
  "geometry": {"coordinates":[82.42478,28.54243],"type":"Point"}
}