{
  "type": "Feature",
  "properties": {
    "gn:admin1_code":"CR",
    "gn:admin2_code":"1",
    "gn:admin3_code":"29",
    "gn:admin4_code":"290016",
    "gn:asciiname":"Nagthali Ghyang",
    "gn:country_code":"NP",
    "gn:dem":3032,
    "gn:feature_class":"P",
    "gn:feature_code":"PPLL",
    "gn:name":"Nagthali Ghyang",
    "gn:population":0,
    "gn:timezone":"Asia/Kathmandu",
    "iso:country":"NP",
    "wof:name":"Nagthali Ghyang",
    "wof:placetype":"locality"
},
  "geometry": {"coordinates":[85.32111,28.21411],"type":"Point"}
}