{
  "type": "Feature",
  "properties": {
    "gn:admin1_code":"WR",
    "gn:admin2_code":"8",
    "gn:admin3_code":"51.0",
    "gn:admin4_code":"510024.0",
    "gn:asciiname":"Dihikateni",
    "gn:country_code":"NP",
    "gn:dem":1109,
    "gn:feature_class":"P",
    "gn:feature_code":"PPLL",
    "gn:name":"Dihikateni",
    "gn:population":0,
    "gn:timezone":"Asia/Kathmandu",
    "iso:country":"NP",
    "wof:name":"Dihikateni",
    "wof:placetype":"locality"
},
  "geometry": {"coordinates":[83.13316,27.94429],"type":"Point"}
}