{
  "type": "Feature",
  "properties": {
    "gn:admin1_code":"ER",
    "gn:admin2_code":"7",
    "gn:admin3_code":"5",
    "gn:admin4_code":"50064",
    "gn:asciiname":"Dumre",
    "gn:country_code":"NP",
    "gn:dem":138,
    "gn:feature_class":"P",
    "gn:feature_code":"PPLL",
    "gn:name":"Dumre",
    "gn:population":0,
    "gn:timezone":"Asia/Kathmandu",
    "iso:country":"NP",
    "wof:name":"Dumre",
    "wof:placetype":"locality"
},
  "geometry": {"coordinates":[87.60438000000001,26.68169],"type":"Point"}
}