{
  "type": "Feature",
  "properties": {
    "gn:admin1_code":"ER",
    "gn:admin2_code":"7",
    "gn:admin3_code":"10.0",
    "gn:admin4_code":"100048.0",
    "gn:asciiname":"Chepangaun",
    "gn:country_code":"NP",
    "gn:dem":1520,
    "gn:feature_class":"P",
    "gn:feature_code":"PPLL",
    "gn:name":"Chepangaun",
    "gn:population":0,
    "gn:timezone":"Asia/Kathmandu",
    "iso:country":"NP",
    "wof:name":"Chepangaun",
    "wof:placetype":"locality"
},
  "geometry": {"coordinates":[87.16914,27.18949000000001],"type":"Point"}
}