{
  "type": "Feature",
  "properties": {
    "gn:admin1_code":"MR",
    "gn:admin2_code":"6",
    "gn:admin3_code":"66.0",
    "gn:admin4_code":"660003.0",
    "gn:asciiname":"Tumlikh",
    "gn:country_code":"NP",
    "gn:dem":2339,
    "gn:feature_class":"P",
    "gn:feature_code":"PPLL",
    "gn:name":"Tumlikh",
    "gn:population":0,
    "gn:timezone":"Asia/Kathmandu",
    "iso:country":"NP",
    "wof:name":"Tumlikh",
    "wof:placetype":"locality"
},
  "geometry": {"coordinates":[81.87083,29.92386],"type":"Point"}
}