{
  "type": "Feature",
  "properties": {
    "gn:admin1_code":"MR",
    "gn:admin2_code":"2",
    "gn:admin3_code":"61.0",
    "gn:admin4_code":"610012.0",
    "gn:asciiname":"Koldanda",
    "gn:country_code":"NP",
    "gn:dem":1854,
    "gn:feature_class":"P",
    "gn:feature_code":"PPLL",
    "gn:name":"Koldanda",
    "gn:population":0,
    "gn:timezone":"Asia/Kathmandu",
    "iso:country":"NP",
    "name:ceb_x_preferred":[
        "Koldada"
    ],
    "name:hin_x_preferred":[
        "\u0915\u094b\u0932\u0921\u093e\u0901\u0921\u093e"
    ],
    "name:msa_x_preferred":[
        "Koldada"
    ],
    "name:nep_x_preferred":[
        "\u0915\u094b\u0932\u0921\u093e\u0901\u0921\u093e"
    ],
    "name:new_x_preferred":[
        "\u0915\u094b\u0932\u094d\u0921\u093e\u0902\u0921\u093e"
    ],
    "name:pol_x_preferred":[
        "Koldada"
    ],
    "wof:name":"Koldanda",
    "wof:placetype":"locality"
},
  "geometry": {"coordinates":[82.06296,28.68898],"type":"Point"}
}