{
  "type": "Feature",
  "properties": {
    "gn:admin1_code":"WR",
    "gn:admin2_code":"4.0",
    "gn:admin3_code":"39.0",
    "gn:admin4_code":"390033.0",
    "gn:asciiname":"Tunibot",
    "gn:country_code":"NP",
    "gn:dem":592,
    "gn:feature_class":"P",
    "gn:feature_code":"PPLL",
    "gn:name":"Tunibot",
    "gn:population":0,
    "gn:timezone":"Asia/Kathmandu",
    "iso:country":"NP",
    "wof:name":"Tunibot",
    "wof:placetype":"locality"
},
  "geometry": {"coordinates":[83.63523000000001,27.92562],"type":"Point"}
}