{
  "type": "Feature",
  "properties": {
    "gn:admin1_code":"WR",
    "gn:admin2_code":"4",
    "gn:admin3_code":"37",
    "gn:admin4_code":"370032",
    "gn:asciiname":"Fair(Chaitra-Astami)",
    "gn:country_code":"NP",
    "gn:dem":971,
    "gn:feature_class":"P",
    "gn:feature_code":"PPLL",
    "gn:name":"Fair(Chaitra-Astami)",
    "gn:population":0,
    "gn:timezone":"Asia/Kathmandu",
    "iso:country":"NP",
    "wof:name":"Fair(Chaitra-Astami)",
    "wof:placetype":"locality"
},
  "geometry": {"coordinates":[84.60894999999999,28.17594],"type":"Point"}
}