{
  "type": "Feature",
  "properties": {
    "gn:admin1_code":"MR",
    "gn:admin2_code":"12",
    "gn:admin3_code":"53",
    "gn:admin4_code":"530005",
    "gn:asciiname":"Udhune",
    "gn:country_code":"NP",
    "gn:dem":1697,
    "gn:feature_class":"P",
    "gn:feature_code":"PPLL",
    "gn:name":"Udhune",
    "gn:population":0,
    "gn:timezone":"Asia/Kathmandu",
    "iso:country":"NP",
    "wof:name":"Udhune",
    "wof:placetype":"locality"
},
  "geometry": {"coordinates":[82.65082,28.35924],"type":"Point"}
}