{
  "type": "Feature",
  "properties": {
    "gn:admin1_code":"CR",
    "gn:admin2_code":"1",
    "gn:admin3_code":"24.0",
    "gn:admin4_code":"240055.0",
    "gn:asciiname":"Airigaun",
    "gn:country_code":"NP",
    "gn:dem":1622,
    "gn:feature_class":"P",
    "gn:feature_code":"PPLL",
    "gn:name":"Airigaun",
    "gn:population":0,
    "gn:timezone":"Asia/Kathmandu",
    "iso:country":"NP",
    "wof:name":"Airigaun",
    "wof:placetype":"locality"
},
  "geometry": {"coordinates":[85.48697,27.61176],"type":"Point"}
}