{
  "type": "Feature",
  "properties": {
    "gn:admin1_code":"FR",
    "gn:admin2_code":"14",
    "gn:admin3_code":"70.0",
    "gn:admin4_code":"700048.0",
    "gn:asciiname":"Loli",
    "gn:country_code":"NP",
    "gn:dem":1521,
    "gn:feature_class":"P",
    "gn:feature_code":"PPLL",
    "gn:name":"Loli",
    "gn:population":0,
    "gn:timezone":"Asia/Kathmandu",
    "iso:country":"NP",
    "wof:name":"Loli",
    "wof:placetype":"locality"
},
  "geometry": {"coordinates":[80.99256,29.14391],"type":"Point"}
}