{
  "type": "Feature",
  "properties": {
    "gn:admin1_code":"WR",
    "gn:admin2_code":"3",
    "gn:admin3_code":"43",
    "gn:admin4_code":"430038",
    "gn:asciiname":"Thamdanda",
    "gn:country_code":"NP",
    "gn:dem":1165,
    "gn:feature_class":"P",
    "gn:feature_code":"PPLL",
    "gn:name":"Thamdanda",
    "gn:population":0,
    "gn:timezone":"Asia/Kathmandu",
    "iso:country":"NP",
    "wof:name":"Thamdanda",
    "wof:placetype":"locality"
},
  "geometry": {"coordinates":[83.50230999999999,28.36092],"type":"Point"}
}