{
  "type": "Feature",
  "properties": {
    "gn:admin1_code":"ER",
    "gn:admin2_code":"13",
    "gn:admin3_code":"16",
    "gn:admin4_code":"160063.0",
    "gn:asciiname":"Lahangoth (Nayangoth)",
    "gn:country_code":"NP",
    "gn:dem":120,
    "gn:feature_class":"P",
    "gn:feature_code":"PPLL",
    "gn:name":"Lahangoth (Nayangoth)",
    "gn:population":0,
    "gn:timezone":"Asia/Kathmandu",
    "iso:country":"NP",
    "wof:name":"Lahangoth (Nayangoth)",
    "wof:placetype":"locality"
},
  "geometry": {"coordinates":[86.49446,26.73692],"type":"Point"}
}