{
  "type": "Feature",
  "properties": {
    "gn:admin1_code":"MR",
    "gn:admin2_code":"2",
    "gn:admin3_code":"61.0",
    "gn:admin4_code":"610005.0",
    "gn:asciiname":"Pali",
    "gn:country_code":"NP",
    "gn:dem":1371,
    "gn:feature_class":"P",
    "gn:feature_code":"PPLL",
    "gn:name":"Pali",
    "gn:population":0,
    "gn:timezone":"Asia/Kathmandu",
    "iso:country":"NP",
    "wof:name":"Pali",
    "wof:placetype":"locality"
},
  "geometry": {"coordinates":[82.27741999999998,28.75157],"type":"Point"}
}