{
  "type": "Feature",
  "properties": {
    "gn:admin1_code":"CR",
    "gn:admin2_code":"11",
    "gn:admin3_code":"31",
    "gn:admin4_code":"310041",
    "gn:asciiname":"Sisneri",
    "gn:country_code":"NP",
    "gn:dem":1479,
    "gn:feature_class":"P",
    "gn:feature_code":"PPLL",
    "gn:name":"Sisneri",
    "gn:population":0,
    "gn:timezone":"Asia/Kathmandu",
    "iso:country":"NP",
    "name:msa_x_preferred":[
        "Sisneri"
    ],
    "name:nep_x_preferred":[
        "\u0938\u093f\u0938\u094d\u0928\u0947\u0930\u0940"
    ],
    "name:new_x_preferred":[
        "\u0938\u093f\u0938\u094d\u0928\u0947\u0930\u0940"
    ],
    "name:pol_x_preferred":[
        "Sisneri"
    ],
    "wof:name":"Sisneri",
    "wof:placetype":"locality"
},
  "geometry": {"coordinates":[85.22841,27.56071],"type":"Point"}
}