{
  "type": "Feature",
  "properties": {
    "gn:admin1_code":"WR",
    "gn:admin2_code":"4.0",
    "gn:admin3_code":"39.0",
    "gn:admin4_code":"390004.0",
    "gn:asciiname":"Baralgaun",
    "gn:country_code":"NP",
    "gn:dem":1085,
    "gn:feature_class":"P",
    "gn:feature_code":"PPLL",
    "gn:name":"Baralgaun",
    "gn:population":0,
    "gn:timezone":"Asia/Kathmandu",
    "iso:country":"NP",
    "wof:name":"Baralgaun",
    "wof:placetype":"locality"
},
  "geometry": {"coordinates":[83.88113,28.16184],"type":"Point"}
}