{
  "type": "Feature",
  "properties": {
    "gn:admin1_code":"CR",
    "gn:admin2_code":"1",
    "gn:admin3_code":"30.0",
    "gn:admin4_code":"300048.0",
    "gn:asciiname":"Ranibari",
    "gn:country_code":"NP",
    "gn:dem":858,
    "gn:feature_class":"P",
    "gn:feature_code":"PPLL",
    "gn:name":"Ranibari",
    "gn:population":0,
    "gn:timezone":"Asia/Kathmandu",
    "iso:country":"NP",
    "wof:name":"Ranibari",
    "wof:placetype":"locality"
},
  "geometry": {"coordinates":[85.07205999999999,27.74128],"type":"Point"}
}