{
  "type": "Feature",
  "properties": {
    "gn:admin1_code":"WR",
    "gn:admin2_code":"4.0",
    "gn:admin3_code":"38.0",
    "gn:admin4_code":"380002.0",
    "gn:asciiname":"Arkhala Bhanjyang",
    "gn:country_code":"NP",
    "gn:dem":677,
    "gn:feature_class":"P",
    "gn:feature_code":"PPLL",
    "gn:name":"Arkhala Bhanjyang",
    "gn:population":0,
    "gn:timezone":"Asia/Kathmandu",
    "iso:country":"NP",
    "wof:name":"Arkhala Bhanjyang",
    "wof:placetype":"locality"
},
  "geometry": {"coordinates":[84.05868000000002,27.97697],"type":"Point"}
}