{
  "type": "Feature",
  "properties": {
    "gn:admin1_code":"FR",
    "gn:admin2_code":"9",
    "gn:admin3_code":"74",
    "gn:admin4_code":"740004",
    "gn:asciiname":"Bhatana",
    "gn:country_code":"NP",
    "gn:dem":1887,
    "gn:feature_class":"P",
    "gn:feature_code":"PPLL",
    "gn:name":"Bhatana",
    "gn:population":0,
    "gn:timezone":"Asia/Kathmandu",
    "iso:country":"NP",
    "name:ceb_x_preferred":[
        "Bhatana"
    ],
    "name:dty_x_preferred":[
        "\u092d\u091f\u0928\u093e \u0917\u093e\u0935\u093f\u0938"
    ],
    "name:mai_x_preferred":[
        "\u092d\u091f\u0928\u093e"
    ],
    "name:msa_x_preferred":[
        "Bhatana"
    ],
    "name:nep_x_preferred":[
        "\u092d\u091f\u0928\u093e"
    ],
    "name:new_x_preferred":[
        "\u092d\u091f\u0928\u093e"
    ],
    "name:pol_x_preferred":[
        "Bhatana"
    ],
    "wof:name":"Bhatana",
    "wof:placetype":"locality"
},
  "geometry": {"coordinates":[80.74218,29.62078],"type":"Point"}
}