{
  "type": "Feature",
  "properties": {
    "gn:admin1_code":"WR",
    "gn:admin2_code":"8",
    "gn:admin3_code":"49",
    "gn:admin4_code":"490022",
    "gn:asciiname":"Bhadachi",
    "gn:country_code":"NP",
    "gn:dem":131,
    "gn:feature_class":"P",
    "gn:feature_code":"PPLL",
    "gn:name":"Bhadachi",
    "gn:population":0,
    "gn:timezone":"Asia/Kathmandu",
    "iso:country":"NP",
    "wof:name":"Bhadachi",
    "wof:placetype":"locality"
},
  "geometry": {"coordinates":[83.29590999999998,27.69617],"type":"Point"}
}