{
  "type": "Feature",
  "properties": {
    "gn:admin1_code":"ER",
    "gn:admin2_code":"13",
    "gn:admin3_code":"12",
    "gn:admin4_code":"120038",
    "gn:asciiname":"Deurali",
    "gn:country_code":"NP",
    "gn:dem":1090,
    "gn:feature_class":"P",
    "gn:feature_code":"PPLL",
    "gn:name":"Deurali",
    "gn:population":0,
    "gn:timezone":"Asia/Kathmandu",
    "iso:country":"NP",
    "name:fra_x_preferred":[
        "Deurali"
    ],
    "name:new_x_preferred":[
        "\u0926\u0947\u0909\u0930\u093e\u0932\u0940 \u0917\u093e\u0935\u093f\u0938"
    ],
    "name:pol_x_preferred":[
        "Deurali"
    ],
    "wof:name":"Deurali",
    "wof:placetype":"locality"
},
  "geometry": {"coordinates":[86.43008,27.36131],"type":"Point"}
}