{
  "type": "Feature",
  "properties": {
    "gn:admin1_code":"MR",
    "gn:admin2_code":"2.0",
    "gn:admin3_code":"58.0",
    "gn:admin4_code":"580030.0",
    "gn:asciiname":"Kothiya",
    "gn:country_code":"NP",
    "gn:dem":147,
    "gn:feature_class":"P",
    "gn:feature_code":"PPLL",
    "gn:name":"Kothiya",
    "gn:population":0,
    "gn:timezone":"Asia/Kathmandu",
    "iso:country":"NP",
    "wof:name":"Kothiya",
    "wof:placetype":"locality"
},
  "geometry": {"coordinates":[81.22882,28.36862],"type":"Point"}
}