{
  "type": "Feature",
  "properties": {
    "gn:admin1_code":"MR",
    "gn:admin2_code":"12",
    "gn:admin3_code":"52",
    "gn:admin4_code":"520039.0",
    "gn:asciiname":"Baddanda",
    "gn:country_code":"NP",
    "gn:dem":970,
    "gn:feature_class":"P",
    "gn:feature_code":"PPLL",
    "gn:name":"Baddanda",
    "gn:population":0,
    "gn:timezone":"Asia/Kathmandu",
    "iso:country":"NP",
    "wof:name":"Baddanda",
    "wof:placetype":"locality"
},
  "geometry": {"coordinates":[82.87094999999999,28.10344000000001],"type":"Point"}
}