{
  "type": "Feature",
  "properties": {
    "gn:admin1_code":"ER",
    "gn:admin2_code":"13",
    "gn:admin3_code":"13.0",
    "gn:admin4_code":"130029.0",
    "gn:asciiname":"Dumre",
    "gn:country_code":"NP",
    "gn:dem":1184,
    "gn:feature_class":"P",
    "gn:feature_code":"PPLL",
    "gn:name":"Dumre",
    "gn:population":0,
    "gn:timezone":"Asia/Kathmandu",
    "iso:country":"NP",
    "name:ceb_x_preferred":[
        "Dumre"
    ],
    "name:fra_x_preferred":[
        "Dumre"
    ],
    "name:ita_x_preferred":[
        "Dumre"
    ],
    "name:mai_x_preferred":[
        "\u0921\u0941\u092e\u094d\u0930\u0947"
    ],
    "name:msa_x_preferred":[
        "Dumre"
    ],
    "name:nep_x_preferred":[
        "\u0926\u0941\u092e\u094d\u0930\u0947"
    ],
    "name:new_x_preferred":[
        "\u0921\u0941\u092e\u094d\u0930\u0947"
    ],
    "name:pol_x_preferred":[
        "Dumre"
    ],
    "wof:name":"Dumre",
    "wof:placetype":"locality"
},
  "geometry": {"coordinates":[86.71095,27.31374000000001],"type":"Point"}
}