{
  "type": "Feature",
  "properties": {
    "gn:admin1_code":"ER",
    "gn:admin2_code":"13",
    "gn:admin3_code":"12",
    "gn:admin4_code":"120020.0",
    "gn:asciiname":"Tosipa",
    "gn:country_code":"NP",
    "gn:dem":1528,
    "gn:feature_class":"P",
    "gn:feature_code":"PPLL",
    "gn:name":"Tosipa",
    "gn:population":0,
    "gn:timezone":"Asia/Kathmandu",
    "iso:country":"NP",
    "wof:name":"Tosipa",
    "wof:placetype":"locality"
},
  "geometry": {"coordinates":[86.31218,27.48563],"type":"Point"}
}