{
  "type": "Feature",
  "properties": {
    "gn:admin1_code":"MR",
    "gn:admin2_code":"2.0",
    "gn:admin3_code":"58.0",
    "gn:admin4_code":"580011.0",
    "gn:asciiname":"Ghumnaha",
    "gn:country_code":"NP",
    "gn:dem":141,
    "gn:feature_class":"P",
    "gn:feature_code":"PPLL",
    "gn:name":"Ghumnaha",
    "gn:population":0,
    "gn:timezone":"Asia/Kathmandu",
    "iso:country":"NP",
    "wof:name":"Ghumnaha",
    "wof:placetype":"locality"
},
  "geometry": {"coordinates":[81.32765999999999,28.15667],"type":"Point"}
}