{
  "type": "Feature",
  "properties": {
    "gn:admin1_code":"CR",
    "gn:admin2_code":"1",
    "gn:admin3_code":"23",
    "gn:admin4_code":"230048",
    "gn:asciiname":"Danuwargaun",
    "gn:country_code":"NP",
    "gn:dem":969,
    "gn:feature_class":"P",
    "gn:feature_code":"PPLL",
    "gn:name":"Danuwargaun",
    "gn:population":0,
    "gn:timezone":"Asia/Kathmandu",
    "iso:country":"NP",
    "wof:name":"Danuwargaun",
    "wof:placetype":"locality"
},
  "geometry": {"coordinates":[85.57373,27.83666],"type":"Point"}
}