{
  "type": "Feature",
  "properties": {
    "gn:admin1_code":"MR",
    "gn:admin2_code":"12",
    "gn:admin3_code":"54",
    "gn:admin4_code":"540026",
    "gn:asciiname":"Ghoredhunga",
    "gn:country_code":"NP",
    "gn:dem":1741,
    "gn:feature_class":"P",
    "gn:feature_code":"PPLL",
    "gn:name":"Ghoredhunga",
    "gn:population":0,
    "gn:timezone":"Asia/Kathmandu",
    "iso:country":"NP",
    "wof:name":"Ghoredhunga",
    "wof:placetype":"locality"
},
  "geometry": {"coordinates":[82.40283000000002,28.5598],"type":"Point"}
}