{
  "type": "Feature",
  "properties": {
    "gn:admin1_code":"FR",
    "gn:admin2_code":"14",
    "gn:admin3_code":"71.0",
    "gn:admin4_code":"710006.0",
    "gn:asciiname":"Dammariya",
    "gn:country_code":"NP",
    "gn:dem":185,
    "gn:feature_class":"P",
    "gn:feature_code":"PPLL",
    "gn:name":"Dammariya",
    "gn:population":0,
    "gn:timezone":"Asia/Kathmandu",
    "iso:country":"NP",
    "wof:name":"Dammariya",
    "wof:placetype":"locality"
},
  "geometry": {"coordinates":[81.09148,28.68397],"type":"Point"}
}