{
  "type": "Feature",
  "properties": {
    "gn:admin1_code":"CR",
    "gn:admin2_code":"1",
    "gn:admin3_code":"28",
    "gn:admin4_code":"280024",
    "gn:asciiname":"Khadga Bhanjyang",
    "gn:country_code":"NP",
    "gn:dem":694,
    "gn:feature_class":"P",
    "gn:feature_code":"PPLL",
    "gn:name":"Khadga Bhanjyang",
    "gn:population":0,
    "gn:timezone":"Asia/Kathmandu",
    "iso:country":"NP",
    "wof:name":"Khadga Bhanjyang",
    "wof:placetype":"locality"
},
  "geometry": {"coordinates":[85.08951,27.88743],"type":"Point"}
}