{
  "type": "Feature",
  "properties": {
    "gn:admin1_code":"CR",
    "gn:admin2_code":"5",
    "gn:admin3_code":"19",
    "gn:admin4_code":"190013",
    "gn:asciiname":"Khoriyatol",
    "gn:country_code":"NP",
    "gn:dem":121,
    "gn:feature_class":"P",
    "gn:feature_code":"PPLL",
    "gn:name":"Khoriyatol",
    "gn:population":0,
    "gn:timezone":"Asia/Kathmandu",
    "iso:country":"NP",
    "wof:name":"Khoriyatol",
    "wof:placetype":"locality"
},
  "geometry": {"coordinates":[85.63247,26.98514],"type":"Point"}
}