{
  "type": "Feature",
  "properties": {
    "gn:admin1_code":"FR",
    "gn:admin2_code":"14.0",
    "gn:admin3_code":"67.0",
    "gn:admin4_code":"670009.0",
    "gn:asciiname":"Turakaro Goth",
    "gn:country_code":"NP",
    "gn:dem":2627,
    "gn:feature_class":"P",
    "gn:feature_code":"PPLL",
    "gn:name":"Turakaro Goth",
    "gn:population":0,
    "gn:timezone":"Asia/Kathmandu",
    "iso:country":"NP",
    "wof:name":"Turakaro Goth",
    "wof:placetype":"locality"
},
  "geometry": {"coordinates":[81.47898000000001,29.54967000000001],"type":"Point"}
}