{
  "type": "Feature",
  "properties": {
    "gn:admin1_code":"CR",
    "gn:admin2_code":"1",
    "gn:admin3_code":"24.0",
    "gn:admin4_code":"240016.0",
    "gn:asciiname":"Kukhrepani",
    "gn:country_code":"NP",
    "gn:dem":1607,
    "gn:feature_class":"P",
    "gn:feature_code":"PPLL",
    "gn:name":"Kukhrepani",
    "gn:population":0,
    "gn:timezone":"Asia/Kathmandu",
    "iso:country":"NP",
    "wof:name":"Kukhrepani",
    "wof:placetype":"locality"
},
  "geometry": {"coordinates":[85.45026,27.49067],"type":"Point"}
}