{
  "type": "Feature",
  "properties": {
    "gn:admin1_code":"MR",
    "gn:admin2_code":"6",
    "gn:admin3_code":"63.0",
    "gn:admin4_code":"630028.0",
    "gn:asciiname":"Dasanta",
    "gn:country_code":"NP",
    "gn:dem":3079,
    "gn:feature_class":"P",
    "gn:feature_code":"PPLL",
    "gn:name":"Dasanta",
    "gn:population":0,
    "gn:timezone":"Asia/Kathmandu",
    "iso:country":"NP",
    "wof:name":"Dasanta",
    "wof:placetype":"locality"
},
  "geometry": {"coordinates":[82.10561,29.29022],"type":"Point"}
}