{
  "type": "Feature",
  "properties": {
    "gn:admin1_code":"00",
    "gn:asciiname":"Gosainkund",
    "gn:country_code":"NP",
    "gn:dem":4337,
    "gn:feature_class":"P",
    "gn:feature_code":"PPL",
    "gn:name":"Gos\u0101inkund",
    "gn:population":0,
    "gn:timezone":"Asia/Kathmandu",
    "iso:country":"NP",
    "wof:name":"Gosainkund",
    "wof:placetype":"locality"
},
  "geometry": {"coordinates":[85.40595999999999,28.08347],"type":"Point"}
}