{
  "type": "Feature",
  "properties": {
    "gn:admin1_code":"MR",
    "gn:admin2_code":"6",
    "gn:admin3_code":"62.0",
    "gn:admin4_code":"620004.0",
    "gn:asciiname":"Thalagaun",
    "gn:country_code":"NP",
    "gn:dem":2630,
    "gn:feature_class":"P",
    "gn:feature_code":"PPLL",
    "gn:name":"Thalagaun",
    "gn:population":0,
    "gn:timezone":"Asia/Kathmandu",
    "iso:country":"NP",
    "wof:name":"Thalagaun",
    "wof:placetype":"locality"
},
  "geometry": {"coordinates":[82.92700000000001,28.9281],"type":"Point"}
}