{
  "type": "Feature",
  "properties": {
    "gn:admin1_code":"FR",
    "gn:admin2_code":"14",
    "gn:admin3_code":"70.0",
    "gn:admin4_code":"700038.0",
    "gn:asciiname":"Ghangada",
    "gn:country_code":"NP",
    "gn:dem":1293,
    "gn:feature_class":"P",
    "gn:feature_code":"PPLL",
    "gn:name":"Ghangada",
    "gn:population":0,
    "gn:timezone":"Asia/Kathmandu",
    "iso:country":"NP",
    "wof:name":"Ghangada",
    "wof:placetype":"locality"
},
  "geometry": {"coordinates":[80.89521999999999,29.2154],"type":"Point"}
}