{
  "type": "Feature",
  "properties": {
    "gn:admin1_code":"WR",
    "gn:admin2_code":"8",
    "gn:admin3_code":"47",
    "gn:admin4_code":"470059",
    "gn:asciiname":"Tamakhani",
    "gn:country_code":"NP",
    "gn:dem":825,
    "gn:feature_class":"P",
    "gn:feature_code":"PPLL",
    "gn:name":"Tamakhani",
    "gn:population":0,
    "gn:timezone":"Asia/Kathmandu",
    "iso:country":"NP",
    "wof:name":"Tamakhani",
    "wof:placetype":"locality"
},
  "geometry": {"coordinates":[83.82586999999999,27.80579],"type":"Point"}
}