{
  "type": "Feature",
  "properties": {
    "gn:admin1_code":"CR",
    "gn:admin2_code":"1",
    "gn:admin3_code":"23",
    "gn:admin4_code":"230029.0",
    "gn:asciiname":"Haldi",
    "gn:country_code":"NP",
    "gn:dem":1336,
    "gn:feature_class":"P",
    "gn:feature_code":"PPLL",
    "gn:name":"Haldi",
    "gn:population":0,
    "gn:timezone":"Asia/Kathmandu",
    "iso:country":"NP",
    "name:ceb_x_preferred":[
        "Haldi"
    ],
    "name:deu_x_preferred":[
        "Haldi"
    ],
    "name:sco_x_preferred":[
        "Haldi"
    ],
    "name:swe_x_preferred":[
        "Haldi"
    ],
    "wof:name":"Haldi",
    "wof:placetype":"locality"
},
  "geometry": {"coordinates":[85.54998000000001,27.94774],"type":"Point"}
}