{
  "type": "Feature",
  "properties": {
    "gn:admin1_code":"FR",
    "gn:admin2_code":"9",
    "gn:admin3_code":"74",
    "gn:admin4_code":"740060",
    "gn:asciiname":"Mungrau",
    "gn:country_code":"NP",
    "gn:dem":1723,
    "gn:feature_class":"P",
    "gn:feature_code":"PPLL",
    "gn:name":"Mungrau",
    "gn:population":0,
    "gn:timezone":"Asia/Kathmandu",
    "iso:country":"NP",
    "wof:name":"Mungrau",
    "wof:placetype":"locality"
},
  "geometry": {"coordinates":[80.52752,29.55771],"type":"Point"}
}