{
  "type": "Feature",
  "properties": {
    "gn:admin1_code":"FR",
    "gn:admin2_code":"9",
    "gn:admin3_code":"75.0",
    "gn:admin4_code":"750026.0",
    "gn:asciiname":"Githapatal",
    "gn:country_code":"NP",
    "gn:dem":1131,
    "gn:feature_class":"P",
    "gn:feature_code":"PPLL",
    "gn:name":"Githapatal",
    "gn:population":0,
    "gn:timezone":"Asia/Kathmandu",
    "iso:country":"NP",
    "wof:name":"Githapatal",
    "wof:placetype":"locality"
},
  "geometry": {"coordinates":[80.44439,29.62708],"type":"Point"}
}