{
  "type": "Feature",
  "properties": {
    "gn:admin1_code":"MR",
    "gn:admin2_code":"12",
    "gn:admin3_code":"56.0",
    "gn:admin4_code":"560032.0",
    "gn:asciiname":"Besahi",
    "gn:country_code":"NP",
    "gn:dem":620,
    "gn:feature_class":"P",
    "gn:feature_code":"PPLL",
    "gn:name":"Besahi",
    "gn:population":0,
    "gn:timezone":"Asia/Kathmandu",
    "iso:country":"NP",
    "wof:name":"Besahi",
    "wof:placetype":"locality"
},
  "geometry": {"coordinates":[82.4378,28.02838],"type":"Point"}
}