{
  "type": "Feature",
  "properties": {
    "gn:admin1_code":"MR",
    "gn:admin2_code":"12",
    "gn:admin3_code":"56.0",
    "gn:admin4_code":"560008.0",
    "gn:asciiname":"Uttar Malawar",
    "gn:country_code":"NP",
    "gn:dem":584,
    "gn:feature_class":"P",
    "gn:feature_code":"PPLL",
    "gn:name":"Uttar Malawar",
    "gn:population":0,
    "gn:timezone":"Asia/Kathmandu",
    "iso:country":"NP",
    "wof:name":"Uttar Malawar",
    "wof:placetype":"locality"
},
  "geometry": {"coordinates":[82.29594,28.05412],"type":"Point"}
}