{
  "type": "Feature",
  "properties": {
    "gn:admin1_code":"CR",
    "gn:admin2_code":"1",
    "gn:admin3_code":"23",
    "gn:admin4_code":"230062",
    "gn:asciiname":"Mehele",
    "gn:country_code":"NP",
    "gn:dem":1087,
    "gn:feature_class":"P",
    "gn:feature_code":"PPLL",
    "gn:name":"Mehele",
    "gn:population":0,
    "gn:timezone":"Asia/Kathmandu",
    "iso:country":"NP",
    "name:pol_x_preferred":[
        "Mehele"
    ],
    "wof:name":"Mehele",
    "wof:placetype":"locality"
},
  "geometry": {"coordinates":[85.5455,27.84435],"type":"Point"}
}