{
  "type": "Feature",
  "properties": {
    "gn:admin1_code":"MR",
    "gn:admin2_code":"12",
    "gn:admin3_code":"56.0",
    "gn:admin4_code":"560040.0",
    "gn:asciiname":"Harrebas",
    "gn:country_code":"NP",
    "gn:dem":875,
    "gn:feature_class":"P",
    "gn:feature_code":"PPLL",
    "gn:name":"Harrebas",
    "gn:population":0,
    "gn:timezone":"Asia/Kathmandu",
    "iso:country":"NP",
    "wof:name":"Harrebas",
    "wof:placetype":"locality"
},
  "geometry": {"coordinates":[82.31199000000002,28.19326],"type":"Point"}
}