{
  "type": "Feature",
  "properties": {
    "gn:admin1_code":"ER",
    "gn:admin2_code":"10",
    "gn:admin3_code":"2",
    "gn:admin4_code":"20014.0",
    "gn:asciiname":"Jaubari",
    "gn:country_code":"NP",
    "gn:dem":1580,
    "gn:feature_class":"P",
    "gn:feature_code":"PPLL",
    "gn:name":"Jaubari",
    "gn:population":0,
    "gn:timezone":"Asia/Kathmandu",
    "iso:country":"NP",
    "wof:name":"Jaubari",
    "wof:placetype":"locality"
},
  "geometry": {"coordinates":[87.68000000000001,26.89396],"type":"Point"}
}