{
  "type": "Feature",
  "properties": {
    "gn:admin1_code":"CR",
    "gn:admin2_code":"11",
    "gn:admin3_code":"31",
    "gn:admin4_code":"310042",
    "gn:asciiname":"Sukaura",
    "gn:country_code":"NP",
    "gn:dem":1085,
    "gn:feature_class":"P",
    "gn:feature_code":"PPLL",
    "gn:name":"Sukaura",
    "gn:population":0,
    "gn:timezone":"Asia/Kathmandu",
    "iso:country":"NP",
    "name:ceb_x_preferred":[
        "Sukaura"
    ],
    "name:msa_x_preferred":[
        "Sukaura"
    ],
    "name:nep_x_preferred":[
        "\u0938\u0941\u0915\u094c\u0930\u093e"
    ],
    "name:new_x_preferred":[
        "\u0938\u0941\u0915\u094c\u0930\u093e"
    ],
    "name:pol_x_preferred":[
        "Sukaura"
    ],
    "wof:name":"Sukaura",
    "wof:placetype":"locality"
},
  "geometry": {"coordinates":[85.18354000000002,27.45331],"type":"Point"}
}