{
  "type": "Feature",
  "properties": {
    "gn:admin1_code":"CR",
    "gn:admin2_code":"5",
    "gn:admin3_code":"22.0",
    "gn:admin4_code":"220016.0",
    "gn:asciiname":"Gurunggaun",
    "gn:country_code":"NP",
    "gn:dem":1032,
    "gn:feature_class":"P",
    "gn:feature_code":"PPLL",
    "gn:name":"Gurunggaun",
    "gn:population":0,
    "gn:timezone":"Asia/Kathmandu",
    "iso:country":"NP",
    "wof:name":"Gurunggaun",
    "wof:placetype":"locality"
},
  "geometry": {"coordinates":[86.06553000000002,27.61506],"type":"Point"}
}