{
  "type": "Feature",
  "properties": {
    "gn:admin1_code":"CR",
    "gn:admin2_code":"11.0",
    "gn:admin3_code":"33.0",
    "gn:admin4_code":"330023.0",
    "gn:asciiname":"Jhitkaiya",
    "gn:country_code":"NP",
    "gn:dem":106,
    "gn:feature_class":"P",
    "gn:feature_code":"PPLL",
    "gn:name":"Jhitkaiya",
    "gn:population":0,
    "gn:timezone":"Asia/Kathmandu",
    "iso:country":"NP",
    "wof:name":"Jhitkaiya",
    "wof:placetype":"locality"
},
  "geometry": {"coordinates":[85.01791999999998,27.06425],"type":"Point"}
}