{
  "type": "Feature",
  "properties": {
    "gn:admin1_code":"WR",
    "gn:admin2_code":"8",
    "gn:admin3_code":"46.0",
    "gn:admin4_code":"460020.0",
    "gn:asciiname":"Chhaphilegaun",
    "gn:country_code":"NP",
    "gn:dem":1857,
    "gn:feature_class":"P",
    "gn:feature_code":"PPLL",
    "gn:name":"Chhaphilegaun",
    "gn:population":0,
    "gn:timezone":"Asia/Kathmandu",
    "iso:country":"NP",
    "wof:name":"Chhaphilegaun",
    "wof:placetype":"locality"
},
  "geometry": {"coordinates":[83.16887,28.22251],"type":"Point"}
}