{
  "type": "Feature",
  "properties": {
    "gn:admin1_code":"WR",
    "gn:admin2_code":"8",
    "gn:admin3_code":"47",
    "gn:admin4_code":"470024",
    "gn:asciiname":"Banskharka",
    "gn:country_code":"NP",
    "gn:dem":847,
    "gn:feature_class":"P",
    "gn:feature_code":"PPLL",
    "gn:name":"Banskharka",
    "gn:population":0,
    "gn:timezone":"Asia/Kathmandu",
    "iso:country":"NP",
    "wof:name":"Banskharka",
    "wof:placetype":"locality"
},
  "geometry": {"coordinates":[83.88766,27.8211],"type":"Point"}
}