{
  "type": "Feature",
  "properties": {
    "gn:admin1_code":"MR",
    "gn:admin2_code":"6",
    "gn:admin3_code":"62.0",
    "gn:admin4_code":"620004.0",
    "gn:asciiname":"Dhupichaur",
    "gn:country_code":"NP",
    "gn:dem":2234,
    "gn:feature_class":"P",
    "gn:feature_code":"PPLL",
    "gn:name":"Dhupichaur",
    "gn:population":0,
    "gn:timezone":"Asia/Kathmandu",
    "iso:country":"NP",
    "wof:name":"Dhupichaur",
    "wof:placetype":"locality"
},
  "geometry": {"coordinates":[82.87340999999998,28.9708],"type":"Point"}
}