{
  "type": "Feature",
  "properties": {
    "gn:admin1_code":"FR",
    "gn:admin2_code":"9",
    "gn:admin3_code":"74",
    "gn:admin4_code":"740007",
    "gn:asciiname":"Harada",
    "gn:country_code":"NP",
    "gn:dem":1485,
    "gn:feature_class":"P",
    "gn:feature_code":"PPLL",
    "gn:name":"Harada",
    "gn:population":0,
    "gn:timezone":"Asia/Kathmandu",
    "iso:country":"NP",
    "wof:name":"Harada",
    "wof:placetype":"locality"
},
  "geometry": {"coordinates":[80.39315999999999,29.39594],"type":"Point"}
}