{
  "type": "Feature",
  "properties": {
    "gn:admin1_code":"00",
    "gn:asciiname":"Sumnara",
    "gn:country_code":"NP",
    "gn:dem":1656,
    "gn:feature_class":"P",
    "gn:feature_code":"PPL",
    "gn:name":"Sumn\u0101r\u0101",
    "gn:population":0,
    "gn:timezone":"Asia/Kathmandu",
    "iso:country":"NP",
    "wof:name":"Sumnara",
    "wof:placetype":"locality"
},
  "geometry": {"coordinates":[85.53231,27.65552000000001],"type":"Point"}
}