{
  "type": "Feature",
  "properties": {
    "gn:admin1_code":"ER",
    "gn:admin2_code":"13.0",
    "gn:admin3_code":"14.0",
    "gn:admin4_code":"140008.0",
    "gn:asciiname":"Bhogteni",
    "gn:country_code":"NP",
    "gn:dem":1265,
    "gn:feature_class":"P",
    "gn:feature_code":"PPLL",
    "gn:name":"Bhogteni",
    "gn:population":0,
    "gn:timezone":"Asia/Kathmandu",
    "iso:country":"NP",
    "wof:name":"Bhogteni",
    "wof:placetype":"locality"
},
  "geometry": {"coordinates":[86.65439000000001,27.01507],"type":"Point"}
}