{
  "type": "Feature",
  "properties": {
    "gn:admin1_code":"ER",
    "gn:admin2_code":"7",
    "gn:admin3_code":"10.0",
    "gn:admin4_code":"100021.0",
    "gn:asciiname":"Sagbala",
    "gn:country_code":"NP",
    "gn:dem":1612,
    "gn:feature_class":"P",
    "gn:feature_code":"PPLL",
    "gn:name":"Sagbala",
    "gn:population":0,
    "gn:timezone":"Asia/Kathmandu",
    "iso:country":"NP",
    "wof:name":"Sagbala",
    "wof:placetype":"locality"
},
  "geometry": {"coordinates":[86.96857,27.08762],"type":"Point"}
}