{
  "type": "Feature",
  "properties": {
    "gn:admin1_code":"WR",
    "gn:admin2_code":"8",
    "gn:admin3_code":"49",
    "gn:admin4_code":"490032",
    "gn:asciiname":"Motipur",
    "gn:country_code":"NP",
    "gn:dem":102,
    "gn:feature_class":"P",
    "gn:feature_code":"PPLL",
    "gn:name":"Motipur",
    "gn:population":0,
    "gn:timezone":"Asia/Kathmandu",
    "iso:country":"NP",
    "name:fra_x_preferred":[
        "Motipur"
    ],
    "name:pol_x_preferred":[
        "Motipur"
    ],
    "wof:name":"Motipur",
    "wof:placetype":"locality"
},
  "geometry": {"coordinates":[83.36194999999999,27.50537000000001],"type":"Point"}
}