{
  "type": "Feature",
  "properties": {
    "gn:admin1_code":"CR",
    "gn:admin2_code":"1",
    "gn:admin3_code":"28",
    "gn:admin4_code":"280054",
    "gn:asciiname":"Biruwatol",
    "gn:country_code":"NP",
    "gn:dem":776,
    "gn:feature_class":"P",
    "gn:feature_code":"PPLL",
    "gn:name":"Biruwatol",
    "gn:population":0,
    "gn:timezone":"Asia/Kathmandu",
    "iso:country":"NP",
    "wof:name":"Biruwatol",
    "wof:placetype":"locality"
},
  "geometry": {"coordinates":[85.32800999999998,27.85867],"type":"Point"}
}