{
  "type": "Feature",
  "properties": {
    "gn:admin1_code":"CR",
    "gn:admin2_code":"1.0",
    "gn:admin3_code":"26.0",
    "gn:admin4_code":"260005.0",
    "gn:asciiname":"Dihigaun",
    "gn:country_code":"NP",
    "gn:dem":1430,
    "gn:feature_class":"P",
    "gn:feature_code":"PPLL",
    "gn:name":"Dihigaun",
    "gn:population":0,
    "gn:timezone":"Asia/Kathmandu",
    "iso:country":"NP",
    "wof:name":"Dihigaun",
    "wof:placetype":"locality"
},
  "geometry": {"coordinates":[85.46156999999999,27.70537],"type":"Point"}
}