{
  "type": "Feature",
  "properties": {
    "gn:admin1_code":"ER",
    "gn:admin2_code":"7",
    "gn:admin3_code":"10.0",
    "gn:admin4_code":"100023.0",
    "gn:asciiname":"Haikharan",
    "gn:country_code":"NP",
    "gn:dem":304,
    "gn:feature_class":"P",
    "gn:feature_code":"PPLL",
    "gn:name":"Haikharan",
    "gn:population":0,
    "gn:timezone":"Asia/Kathmandu",
    "iso:country":"NP",
    "wof:name":"Haikharan",
    "wof:placetype":"locality"
},
  "geometry": {"coordinates":[87.1101,26.92699],"type":"Point"}
}