{
  "type": "Feature",
  "properties": {
    "gn:admin1_code":"ER",
    "gn:admin2_code":"13.0",
    "gn:admin3_code":"14.0",
    "gn:admin4_code":"140024.0",
    "gn:asciiname":"Lemlem",
    "gn:country_code":"NP",
    "gn:dem":857,
    "gn:feature_class":"P",
    "gn:feature_code":"PPLL",
    "gn:name":"Lemlem",
    "gn:population":0,
    "gn:timezone":"Asia/Kathmandu",
    "iso:country":"NP",
    "wof:name":"Lemlem",
    "wof:placetype":"locality"
},
  "geometry": {"coordinates":[87.10961,26.86136],"type":"Point"}
}