{
  "type": "Feature",
  "properties": {
    "gn:admin1_code":"MR",
    "gn:admin2_code":"12",
    "gn:admin3_code":"56.0",
    "gn:admin4_code":"560016.0",
    "gn:asciiname":"Ekali",
    "gn:country_code":"NP",
    "gn:dem":550,
    "gn:feature_class":"P",
    "gn:feature_code":"PPLL",
    "gn:name":"Ekali",
    "gn:population":0,
    "gn:timezone":"Asia/Kathmandu",
    "iso:country":"NP",
    "name:ara_x_preferred":[
        "\u0625\u0643\u0627\u0644\u064a"
    ],
    "name:ceb_x_preferred":[
        "Ek\u00e1li"
    ],
    "name:deu_x_preferred":[
        "Ekali"
    ],
    "name:ell_x_preferred":[
        "\u0395\u03ba\u03ac\u03bb\u03b7 \u039a\u03b7\u03c6\u03b9\u03c3\u03b9\u03ac\u03c2"
    ],
    "name:fin_x_preferred":[
        "Ek\u00e1li"
    ],
    "name:ita_x_preferred":[
        "Ekali"
    ],
    "name:lat_x_preferred":[
        "Hecale"
    ],
    "name:nno_x_preferred":[
        "Ek\u00e1li"
    ],
    "name:pol_x_preferred":[
        "Ekali"
    ],
    "name:ron_x_preferred":[
        "Ekali"
    ],
    "name:rus_x_preferred":[
        "\u042d\u043a\u0430\u043b\u0438"
    ],
    "name:swe_x_preferred":[
        "Ek\u00e1li"
    ],
    "name:tur_x_preferred":[
        "Ekali"
    ],
    "wof:name":"Ekali",
    "wof:placetype":"locality"
},
  "geometry": {"coordinates":[82.17324000000001,28.09685],"type":"Point"}
}