{
  "type": "Feature",
  "properties": {
    "gn:admin1_code":"MR",
    "gn:admin2_code":"12",
    "gn:admin3_code":"52",
    "gn:admin4_code":"520003",
    "gn:asciiname":"Bangesal",
    "gn:country_code":"NP",
    "gn:dem":356,
    "gn:feature_class":"P",
    "gn:feature_code":"PPLL",
    "gn:name":"Bangesal",
    "gn:population":0,
    "gn:timezone":"Asia/Kathmandu",
    "iso:country":"NP",
    "wof:name":"Bangesal",
    "wof:placetype":"locality"
},
  "geometry": {"coordinates":[82.84501,27.90969],"type":"Point"}
}