{
  "type": "Feature",
  "properties": {
    "gn:admin1_code":"MR",
    "gn:admin2_code":"2",
    "gn:admin3_code":"60.0",
    "gn:admin4_code":"600023.0",
    "gn:asciiname":"Chun Takura",
    "gn:country_code":"NP",
    "gn:dem":1335,
    "gn:feature_class":"P",
    "gn:feature_code":"PPLL",
    "gn:name":"Chun Takura",
    "gn:population":0,
    "gn:timezone":"Asia/Kathmandu",
    "iso:country":"NP",
    "wof:name":"Chun Takura",
    "wof:placetype":"locality"
},
  "geometry": {"coordinates":[81.67273,28.96684],"type":"Point"}
}