{
  "type": "Feature",
  "properties": {
    "gn:admin1_code":"MR",
    "gn:admin2_code":"12",
    "gn:admin3_code":"54",
    "gn:admin4_code":"540005",
    "gn:asciiname":"Pachhibang",
    "gn:country_code":"NP",
    "gn:dem":1086,
    "gn:feature_class":"P",
    "gn:feature_code":"PPLL",
    "gn:name":"Pachhibang",
    "gn:population":0,
    "gn:timezone":"Asia/Kathmandu",
    "iso:country":"NP",
    "wof:name":"Pachhibang",
    "wof:placetype":"locality"
},
  "geometry": {"coordinates":[82.47251999999997,28.6046],"type":"Point"}
}