{
  "type": "Feature",
  "properties": {
    "gn:admin1_code":"WR",
    "gn:admin2_code":"8",
    "gn:admin3_code":"47",
    "gn:admin4_code":"470033",
    "gn:asciiname":"Chhahala",
    "gn:country_code":"NP",
    "gn:dem":1150,
    "gn:feature_class":"P",
    "gn:feature_code":"PPLL",
    "gn:name":"Chhahala",
    "gn:population":0,
    "gn:timezone":"Asia/Kathmandu",
    "iso:country":"NP",
    "wof:name":"Chhahala",
    "wof:placetype":"locality"
},
  "geometry": {"coordinates":[83.33591,27.80572],"type":"Point"}
}