{
  "type": "Feature",
  "properties": {
    "gn:admin1_code":"ER",
    "gn:admin2_code":"10",
    "gn:admin3_code":"3.0",
    "gn:admin4_code":"30022.0",
    "gn:asciiname":"Nunthala",
    "gn:country_code":"NP",
    "gn:dem":470,
    "gn:feature_class":"P",
    "gn:feature_code":"PPLL",
    "gn:name":"Nunthala",
    "gn:population":0,
    "gn:timezone":"Asia/Kathmandu",
    "iso:country":"NP",
    "wof:name":"Nunthala",
    "wof:placetype":"locality"
},
  "geometry": {"coordinates":[87.93805,26.80187],"type":"Point"}
}