{
  "type": "Feature",
  "properties": {
    "gn:admin1_code":"MR",
    "gn:admin2_code":"12",
    "gn:admin3_code":"55",
    "gn:admin4_code":"550028",
    "gn:asciiname":"Simleni",
    "gn:country_code":"NP",
    "gn:dem":1448,
    "gn:feature_class":"P",
    "gn:feature_code":"PPLL",
    "gn:name":"Simleni",
    "gn:population":0,
    "gn:timezone":"Asia/Kathmandu",
    "iso:country":"NP",
    "wof:name":"Simleni",
    "wof:placetype":"locality"
},
  "geometry": {"coordinates":[82.06871,28.41957],"type":"Point"}
}