{
  "type": "Feature",
  "properties": {
    "gn:admin1_code":"CR",
    "gn:admin2_code":"11",
    "gn:admin3_code":"32",
    "gn:admin4_code":"320072",
    "gn:asciiname":"Inarwari",
    "gn:country_code":"NP",
    "gn:dem":82,
    "gn:feature_class":"P",
    "gn:feature_code":"PPLL",
    "gn:name":"Inarwari",
    "gn:population":0,
    "gn:timezone":"Asia/Kathmandu",
    "iso:country":"NP",
    "wof:name":"Inarwari",
    "wof:placetype":"locality"
},
  "geometry": {"coordinates":[85.23142,26.88227],"type":"Point"}
}