{
  "type": "Feature",
  "properties": {
    "gn:admin1_code":"MR",
    "gn:admin2_code":"6",
    "gn:admin3_code":"62.0",
    "gn:admin4_code":"620012.0",
    "gn:asciiname":"Chinang",
    "gn:country_code":"NP",
    "gn:dem":4193,
    "gn:feature_class":"P",
    "gn:feature_code":"PPLL",
    "gn:name":"Chinang",
    "gn:population":0,
    "gn:timezone":"Asia/Kathmandu",
    "iso:country":"NP",
    "wof:name":"Chinang",
    "wof:placetype":"locality"
},
  "geometry": {"coordinates":[83.27839,28.88917],"type":"Point"}
}