{
  "type": "Feature",
  "properties": {
    "gn:admin1_code":"MR",
    "gn:admin2_code":"12",
    "gn:admin3_code":"56.0",
    "gn:admin4_code":"560013.0",
    "gn:asciiname":"Halwar",
    "gn:country_code":"NP",
    "gn:dem":672,
    "gn:feature_class":"P",
    "gn:feature_code":"PPLL",
    "gn:name":"Halwar",
    "gn:population":0,
    "gn:timezone":"Asia/Kathmandu",
    "iso:country":"NP",
    "name:ceb_x_preferred":[
        "Halwar"
    ],
    "name:mai_x_preferred":[
        "\u0939\u0932\u0935\u093e\u0930 \u0917\u093e.\u0935\u093f.\u0938."
    ],
    "name:msa_x_preferred":[
        "Halwar"
    ],
    "name:nep_x_preferred":[
        "\u0939\u0932\u0935\u093e\u0930"
    ],
    "name:new_x_preferred":[
        "\u0939\u0932\u094d\u0935\u093e\u0930"
    ],
    "name:pol_x_preferred":[
        "Halwar"
    ],
    "wof:name":"Halwar",
    "wof:placetype":"locality"
},
  "geometry": {"coordinates":[82.34971,28.14015],"type":"Point"}
}