{
  "type": "Feature",
  "properties": {
    "gn:admin1_code":"CR",
    "gn:admin2_code":"5",
    "gn:admin3_code":"22.0",
    "gn:admin4_code":"220049.0",
    "gn:asciiname":"Ibithan",
    "gn:country_code":"NP",
    "gn:dem":1813,
    "gn:feature_class":"P",
    "gn:feature_code":"PPLL",
    "gn:name":"Ibithan",
    "gn:population":0,
    "gn:timezone":"Asia/Kathmandu",
    "iso:country":"NP",
    "wof:name":"Ibithan",
    "wof:placetype":"locality"
},
  "geometry": {"coordinates":[86.23317,27.7335],"type":"Point"}
}