{
  "type": "Feature",
  "properties": {
    "gn:admin1_code":"WR",
    "gn:admin2_code":"4",
    "gn:admin3_code":"41",
    "gn:admin4_code":"410006",
    "gn:asciiname":"Tilicho Peak",
    "gn:country_code":"NP",
    "gn:dem":6728,
    "gn:feature_class":"P",
    "gn:feature_code":"PPLL",
    "gn:name":"Tilicho Peak",
    "gn:population":0,
    "gn:timezone":"Asia/Kathmandu",
    "iso:country":"NP",
    "wof:name":"Tilicho Peak",
    "wof:placetype":"locality"
},
  "geometry": {"coordinates":[83.8163,28.68403],"type":"Point"}
}