{
  "type": "Feature",
  "properties": {
    "gn:admin1_code":"WR",
    "gn:admin2_code":"4",
    "gn:admin3_code":"41",
    "gn:admin4_code":"410006",
    "gn:asciiname":"Tilicho Peak",
    "gn:country_code":"NP",
    "gn:dem":6728,
    "gn:feature_class":"P",
    "gn:feature_code":"PPLL",
    "gn:name":"Tilicho Peak",
    "gn:population":0,
    "gn:timezone":"Asia/Kathmandu",
    "iso:country":"NP",
    "name:ceb_x_preferred":[
        "Tilicho Peak"
    ],
    "name:ces_x_preferred":[
        "Tili\u010do"
    ],
    "name:deu_x_preferred":[
        "Tilicho Peak"
    ],
    "name:fas_x_preferred":[
        "\u062a\u06cc\u0644\u06cc\u0686\u0648 \u067e\u06cc\u06a9"
    ],
    "name:fra_x_preferred":[
        "Pic Tilicho"
    ],
    "name:hin_x_preferred":[
        "\u0924\u093f\u0932\u093f\u091a\u094b \u092a\u0930\u094d\u0935\u0924"
    ],
    "name:ita_x_preferred":[
        "Tilicho Peak"
    ],
    "name:nno_x_preferred":[
        "Tilicho Peak"
    ],
    "name:pnb_x_preferred":[
        "\u062a\u0644\u06cc\u0686\u0648"
    ],
    "name:pol_x_preferred":[
        "Tilicho"
    ],
    "name:por_x_preferred":[
        "Tilicho"
    ],
    "name:rus_x_preferred":[
        "\u0422\u0438\u043b\u0438\u0447\u043e"
    ],
    "name:ukr_x_preferred":[
        "\u041f\u0456\u043a \u0422\u0456\u043b\u0456\u0447\u043e"
    ],
    "name:zho_x_preferred":[
        "\u8482\u5229\u55ac\u5cf0"
    ],
    "wof:name":"Tilicho Peak",
    "wof:placetype":"locality"
},
  "geometry": {"coordinates":[83.8163,28.68403],"type":"Point"}
}