{
  "type": "Feature",
  "properties": {
    "gn:admin1_code":"MR",
    "gn:admin2_code":"12",
    "gn:admin3_code":"53",
    "gn:admin4_code":"530026",
    "gn:asciiname":"Bhainsigaira",
    "gn:country_code":"NP",
    "gn:dem":1892,
    "gn:feature_class":"P",
    "gn:feature_code":"PPLL",
    "gn:name":"Bhainsigaira",
    "gn:population":0,
    "gn:timezone":"Asia/Kathmandu",
    "iso:country":"NP",
    "wof:name":"Bhainsigaira",
    "wof:placetype":"locality"
},
  "geometry": {"coordinates":[82.65743000000001,28.27358],"type":"Point"}
}