{
  "type": "Feature",
  "properties": {
    "gn:admin1_code":"FR",
    "gn:admin2_code":"14",
    "gn:admin3_code":"69.0",
    "gn:admin4_code":"690023.0",
    "gn:asciiname":"Ratimate",
    "gn:country_code":"NP",
    "gn:dem":899,
    "gn:feature_class":"P",
    "gn:feature_code":"PPLL",
    "gn:name":"Ratimate",
    "gn:population":0,
    "gn:timezone":"Asia/Kathmandu",
    "iso:country":"NP",
    "wof:name":"Ratimate",
    "wof:placetype":"locality"
},
  "geometry": {"coordinates":[81.39178000000003,28.99615],"type":"Point"}
}