{
  "type": "Feature",
  "properties": {
    "gn:admin1_code":"ER",
    "gn:admin2_code":"7",
    "gn:admin3_code":"5",
    "gn:admin4_code":"50004",
    "gn:asciiname":"Mangalbari",
    "gn:country_code":"NP",
    "gn:dem":74,
    "gn:feature_class":"P",
    "gn:feature_code":"PPLL",
    "gn:name":"Mangalbari",
    "gn:population":0,
    "gn:timezone":"Asia/Kathmandu",
    "iso:country":"NP",
    "wof:name":"Mangalbari",
    "wof:placetype":"locality"
},
  "geometry": {"coordinates":[87.44197,26.47233],"type":"Point"}
}