{
  "type": "Feature",
  "properties": {
    "gn:admin1_code":"CR",
    "gn:admin2_code":"1",
    "gn:admin3_code":"25",
    "gn:admin4_code":"250015",
    "gn:asciiname":"Machhuya",
    "gn:country_code":"NP",
    "gn:dem":2053,
    "gn:feature_class":"P",
    "gn:feature_code":"PPLL",
    "gn:name":"Machhuya",
    "gn:population":0,
    "gn:timezone":"Asia/Kathmandu",
    "iso:country":"NP",
    "wof:name":"Machhuya",
    "wof:placetype":"locality"
},
  "geometry": {"coordinates":[85.27519000000002,27.54311],"type":"Point"}
}