{
  "type": "Feature",
  "properties": {
    "gn:admin1_code":"WR",
    "gn:admin2_code":"4.0",
    "gn:admin3_code":"39.0",
    "gn:admin4_code":"390046.0",
    "gn:asciiname":"Banpakhe",
    "gn:country_code":"NP",
    "gn:dem":1404,
    "gn:feature_class":"P",
    "gn:feature_code":"PPLL",
    "gn:name":"Banpakhe",
    "gn:population":0,
    "gn:timezone":"Asia/Kathmandu",
    "iso:country":"NP",
    "wof:name":"Banpakhe",
    "wof:placetype":"locality"
},
  "geometry": {"coordinates":[83.74644000000001,28.10787],"type":"Point"}
}