{
  "type": "Feature",
  "properties": {
    "gn:admin1_code":"ER",
    "gn:admin2_code":"13",
    "gn:admin3_code":"16",
    "gn:admin4_code":"160049",
    "gn:asciiname":"Budhiyajamdaha",
    "gn:country_code":"NP",
    "gn:dem":177,
    "gn:feature_class":"P",
    "gn:feature_code":"PPLL",
    "gn:name":"Budhiyajamdaha",
    "gn:population":0,
    "gn:timezone":"Asia/Kathmandu",
    "iso:country":"NP",
    "wof:name":"Budhiyajamdaha",
    "wof:placetype":"locality"
},
  "geometry": {"coordinates":[86.35266999999997,26.83922],"type":"Point"}
}