{
  "type": "Feature",
  "properties": {
    "gn:admin1_code":"FR",
    "gn:admin2_code":"9",
    "gn:admin3_code":"75.0",
    "gn:admin4_code":"750022.0",
    "gn:asciiname":"Masinee Baluwa",
    "gn:country_code":"NP",
    "gn:dem":844,
    "gn:feature_class":"P",
    "gn:feature_code":"PPLL",
    "gn:name":"Masinee Baluwa",
    "gn:population":0,
    "gn:timezone":"Asia/Kathmandu",
    "iso:country":"NP",
    "wof:name":"Masinee Baluwa",
    "wof:placetype":"locality"
},
  "geometry": {"coordinates":[80.49609,29.80194],"type":"Point"}
}