{
  "type": "Feature",
  "properties": {
    "gn:admin1_code":"MR",
    "gn:admin2_code":"12",
    "gn:admin3_code":"53",
    "gn:admin4_code":"530024",
    "gn:asciiname":"Bhurtigaun",
    "gn:country_code":"NP",
    "gn:dem":2029,
    "gn:feature_class":"P",
    "gn:feature_code":"PPLL",
    "gn:name":"Bhurtigaun",
    "gn:population":0,
    "gn:timezone":"Asia/Kathmandu",
    "iso:country":"NP",
    "wof:name":"Bhurtigaun",
    "wof:placetype":"locality"
},
  "geometry": {"coordinates":[82.38689000000002,28.3576],"type":"Point"}
}