{
  "type": "Feature",
  "properties": {
    "gn:admin1_code":"WR",
    "gn:admin2_code":"3",
    "gn:admin3_code":"45.0",
    "gn:admin4_code":"450049.0",
    "gn:asciiname":"Takar",
    "gn:country_code":"NP",
    "gn:dem":2156,
    "gn:feature_class":"P",
    "gn:feature_code":"PPLL",
    "gn:name":"Takar",
    "gn:population":0,
    "gn:timezone":"Asia/Kathmandu",
    "iso:country":"NP",
    "wof:name":"Takar",
    "wof:placetype":"locality"
},
  "geometry": {"coordinates":[83.30263000000002,28.24148],"type":"Point"}
}