{
  "type": "Feature",
  "properties": {
    "gn:admin1_code":"MR",
    "gn:admin2_code":"2",
    "gn:admin3_code":"60.0",
    "gn:admin4_code":"600022.0",
    "gn:asciiname":"Bhutte Daha",
    "gn:country_code":"NP",
    "gn:dem":1720,
    "gn:feature_class":"P",
    "gn:feature_code":"PPLL",
    "gn:name":"Bhutte Daha",
    "gn:population":0,
    "gn:timezone":"Asia/Kathmandu",
    "iso:country":"NP",
    "wof:name":"Bhutte Daha",
    "wof:placetype":"locality"
},
  "geometry": {"coordinates":[81.87834000000002,28.92172],"type":"Point"}
}