{
  "type": "Feature",
  "properties": {
    "gn:admin1_code":"MR",
    "gn:admin2_code":"12",
    "gn:admin3_code":"54",
    "gn:admin4_code":"540022",
    "gn:asciiname":"Taligesma",
    "gn:country_code":"NP",
    "gn:dem":1163,
    "gn:feature_class":"P",
    "gn:feature_code":"PPLL",
    "gn:name":"Taligesma",
    "gn:population":0,
    "gn:timezone":"Asia/Kathmandu",
    "iso:country":"NP",
    "wof:name":"Taligesma",
    "wof:placetype":"locality"
},
  "geometry": {"coordinates":[82.21911999999998,28.66972],"type":"Point"}
}