{
  "type": "Feature",
  "properties": {
    "gn:admin1_code":"CR",
    "gn:admin2_code":"5",
    "gn:admin3_code":"18",
    "gn:admin4_code":"180041.0",
    "gn:asciiname":"Laksminiya",
    "gn:country_code":"NP",
    "gn:dem":149,
    "gn:feature_class":"P",
    "gn:feature_code":"PPLL",
    "gn:name":"Laksminiya",
    "gn:population":0,
    "gn:timezone":"Asia/Kathmandu",
    "iso:country":"NP",
    "wof:name":"Laksminiya",
    "wof:placetype":"locality"
},
  "geometry": {"coordinates":[85.75579999999999,26.96541],"type":"Point"}
}