{
  "type": "Feature",
  "properties": {
    "gn:admin1_code":"MR",
    "gn:admin2_code":"12",
    "gn:admin3_code":"54",
    "gn:admin4_code":"540019",
    "gn:asciiname":"Haibang",
    "gn:country_code":"NP",
    "gn:dem":1899,
    "gn:feature_class":"P",
    "gn:feature_code":"PPLL",
    "gn:name":"Haibang",
    "gn:population":0,
    "gn:timezone":"Asia/Kathmandu",
    "iso:country":"NP",
    "wof:name":"Haibang",
    "wof:placetype":"locality"
},
  "geometry": {"coordinates":[82.39319,28.54938],"type":"Point"}
}