{
  "type": "Feature",
  "properties": {
    "gn:admin1_code":"CR",
    "gn:admin2_code":"11",
    "gn:admin3_code":"31",
    "gn:admin4_code":"310041",
    "gn:asciiname":"Tallogaun",
    "gn:country_code":"NP",
    "gn:dem":1489,
    "gn:feature_class":"P",
    "gn:feature_code":"PPLL",
    "gn:name":"Tallogaun",
    "gn:population":0,
    "gn:timezone":"Asia/Kathmandu",
    "iso:country":"NP",
    "wof:name":"Tallogaun",
    "wof:placetype":"locality"
},
  "geometry": {"coordinates":[85.19745,27.57651],"type":"Point"}
}