{
  "type": "Feature",
  "properties": {
    "gn:admin1_code":"ER",
    "gn:admin2_code":"13",
    "gn:admin3_code":"11",
    "gn:admin4_code":"110006.0",
    "gn:asciiname":"Chaulakharkha",
    "gn:country_code":"NP",
    "gn:dem":1764,
    "gn:feature_class":"P",
    "gn:feature_code":"PPLL",
    "gn:name":"Chaulakharkha",
    "gn:population":0,
    "gn:timezone":"Asia/Kathmandu",
    "iso:country":"NP",
    "wof:name":"Chaulakharkha",
    "wof:placetype":"locality"
},
  "geometry": {"coordinates":[86.38334999999999,27.56663],"type":"Point"}
}