{
  "type": "Feature",
  "properties": {
    "gn:admin1_code":"ER",
    "gn:admin2_code":"13",
    "gn:admin3_code":"11",
    "gn:admin4_code":"110019.0",
    "gn:asciiname":"Chhangetar",
    "gn:country_code":"NP",
    "gn:dem":1990,
    "gn:feature_class":"P",
    "gn:feature_code":"PPLL",
    "gn:name":"Chhangetar",
    "gn:population":0,
    "gn:timezone":"Asia/Kathmandu",
    "iso:country":"NP",
    "wof:name":"Chhangetar",
    "wof:placetype":"locality"
},
  "geometry": {"coordinates":[86.55138000000002,27.44732],"type":"Point"}
}