{
  "type": "Feature",
  "properties": {
    "gn:admin1_code":"CR",
    "gn:admin2_code":"5",
    "gn:admin3_code":"17.0",
    "gn:admin4_code":"170098.0",
    "gn:asciiname":"Belhitol",
    "gn:country_code":"NP",
    "gn:dem":67,
    "gn:feature_class":"P",
    "gn:feature_code":"PPLL",
    "gn:name":"Belhitol",
    "gn:population":0,
    "gn:timezone":"Asia/Kathmandu",
    "iso:country":"NP",
    "wof:name":"Belhitol",
    "wof:placetype":"locality"
},
  "geometry": {"coordinates":[85.86926,26.58393],"type":"Point"}
}