{
  "type": "Feature",
  "properties": {
    "gn:admin1_code":"FR",
    "gn:admin2_code":"9",
    "gn:admin3_code":"74",
    "gn:admin4_code":"740054",
    "gn:asciiname":"Lek Neulali",
    "gn:country_code":"NP",
    "gn:dem":1456,
    "gn:feature_class":"P",
    "gn:feature_code":"PPLL",
    "gn:name":"Lek Neulali",
    "gn:population":0,
    "gn:timezone":"Asia/Kathmandu",
    "iso:country":"NP",
    "wof:name":"Lek Neulali",
    "wof:placetype":"locality"
},
  "geometry": {"coordinates":[80.82155,29.45586],"type":"Point"}
}