{
  "type": "Feature",
  "properties": {
    "gn:admin1_code":"WR",
    "gn:admin2_code":"3",
    "gn:admin3_code":"44",
    "gn:admin4_code":"440017",
    "gn:asciiname":"Harrachaur",
    "gn:country_code":"NP",
    "gn:dem":931,
    "gn:feature_class":"P",
    "gn:feature_code":"PPLL",
    "gn:name":"Harrachaur",
    "gn:population":0,
    "gn:timezone":"Asia/Kathmandu",
    "iso:country":"NP",
    "wof:name":"Harrachaur",
    "wof:placetype":"locality"
},
  "geometry": {"coordinates":[83.70904,28.23211],"type":"Point"}
}