{
  "type": "Feature",
  "properties": {
    "gn:admin1_code":"MR",
    "gn:admin2_code":"12",
    "gn:admin3_code":"53",
    "gn:admin4_code":"530004",
    "gn:asciiname":"Chhap",
    "gn:country_code":"NP",
    "gn:dem":1343,
    "gn:feature_class":"P",
    "gn:feature_code":"PPLL",
    "gn:name":"Chhap",
    "gn:population":0,
    "gn:timezone":"Asia/Kathmandu",
    "iso:country":"NP",
    "wof:name":"Chhap",
    "wof:placetype":"locality"
},
  "geometry": {"coordinates":[82.41082,28.30099],"type":"Point"}
}