{
  "type": "Feature",
  "properties": {
    "gn:admin1_code":"WR",
    "gn:admin2_code":"8",
    "gn:admin3_code":"48",
    "gn:admin4_code":"480038",
    "gn:asciiname":"Dhanewa",
    "gn:country_code":"NP",
    "gn:dem":121,
    "gn:feature_class":"P",
    "gn:feature_code":"PPLL",
    "gn:name":"Dhanewa",
    "gn:population":0,
    "gn:timezone":"Asia/Kathmandu",
    "iso:country":"NP",
    "wof:name":"Dhanewa",
    "wof:placetype":"locality"
},
  "geometry": {"coordinates":[83.78493,27.51104],"type":"Point"}
}