{
  "type": "Feature",
  "properties": {
    "gn:admin1_code":"FR",
    "gn:admin2_code":"9",
    "gn:admin3_code":"74",
    "gn:admin4_code":"740054",
    "gn:asciiname":"Chama",
    "gn:country_code":"NP",
    "gn:dem":1076,
    "gn:feature_class":"P",
    "gn:feature_code":"PPLL",
    "gn:name":"Chama",
    "gn:population":0,
    "gn:timezone":"Asia/Kathmandu",
    "iso:country":"NP",
    "name:ceb_x_preferred":[
        "Chama"
    ],
    "name:deu_x_preferred":[
        "Chama"
    ],
    "name:ita_x_preferred":[
        "Chama"
    ],
    "name:nld_x_preferred":[
        "Chama"
    ],
    "name:pol_x_preferred":[
        "Chama"
    ],
    "name:por_x_preferred":[
        "Chama"
    ],
    "name:spa_x_preferred":[
        "Chama"
    ],
    "name:swa_x_preferred":[
        "Chama"
    ],
    "name:swe_x_preferred":[
        "Chama"
    ],
    "name:vol_x_preferred":[
        "Chama"
    ],
    "wof:name":"Chama",
    "wof:placetype":"locality"
},
  "geometry": {"coordinates":[80.8253,29.46089000000001],"type":"Point"}
}