{
  "type": "Feature",
  "properties": {
    "gn:admin1_code":"MR",
    "gn:admin2_code":"6",
    "gn:admin3_code":"62.0",
    "gn:admin4_code":"620023.0",
    "gn:asciiname":"Gumba",
    "gn:country_code":"NP",
    "gn:dem":3703,
    "gn:feature_class":"P",
    "gn:feature_code":"PPLL",
    "gn:name":"Gumba",
    "gn:population":0,
    "gn:timezone":"Asia/Kathmandu",
    "iso:country":"NP",
    "wof:name":"Gumba",
    "wof:placetype":"locality"
},
  "geometry": {"coordinates":[82.86321,29.00224],"type":"Point"}
}