{
  "type": "Feature",
  "properties": {
    "gn:admin1_code":"MR",
    "gn:admin2_code":"12",
    "gn:admin3_code":"53",
    "gn:admin4_code":"530020",
    "gn:asciiname":"Dhandanda",
    "gn:country_code":"NP",
    "gn:dem":1331,
    "gn:feature_class":"P",
    "gn:feature_code":"PPLL",
    "gn:name":"Dhandanda",
    "gn:population":0,
    "gn:timezone":"Asia/Kathmandu",
    "iso:country":"NP",
    "wof:name":"Dhandanda",
    "wof:placetype":"locality"
},
  "geometry": {"coordinates":[82.60374,28.18081],"type":"Point"}
}