{
  "type": "Feature",
  "properties": {
    "gn:admin1_code":"FR",
    "gn:admin2_code":"14",
    "gn:admin3_code":"69.0",
    "gn:admin4_code":"690059.0",
    "gn:asciiname":"Chauka",
    "gn:country_code":"NP",
    "gn:dem":1856,
    "gn:feature_class":"P",
    "gn:feature_code":"PPLL",
    "gn:name":"Chauka",
    "gn:population":0,
    "gn:timezone":"Asia/Kathmandu",
    "iso:country":"NP",
    "wof:name":"Chauka",
    "wof:placetype":"locality"
},
  "geometry": {"coordinates":[81.44394,29.21317],"type":"Point"}
}