{
  "type": "Feature",
  "properties": {
    "gn:admin1_code":"WR",
    "gn:admin2_code":"8",
    "gn:admin3_code":"48",
    "gn:admin4_code":"480010",
    "gn:asciiname":"Bulingtar",
    "gn:country_code":"NP",
    "gn:dem":371,
    "gn:feature_class":"P",
    "gn:feature_code":"PPLL",
    "gn:name":"Bulingtar",
    "gn:population":0,
    "gn:timezone":"Asia/Kathmandu",
    "iso:country":"NP",
    "name:ceb_x_preferred":[
        "Bulingtar"
    ],
    "name:fra_x_preferred":[
        "Bulingtar"
    ],
    "name:mai_x_preferred":[
        "\u092c\u0941\u0932\u093f\u0919\u091f\u093e\u0930 \u0917\u093e\u0909\u0901\u092a\u093e\u0932\u093f\u0915\u093e"
    ],
    "name:msa_x_preferred":[
        "Bulingtar"
    ],
    "name:nep_x_preferred":[
        "\u092c\u0941\u0932\u093f\u0919\u091f\u093e\u0930 \u0917\u093e\u0909\u0901\u092a\u093e\u0932\u093f\u0915\u093e"
    ],
    "name:new_x_preferred":[
        "\u092c\u0941\u0932\u093f\u0919\u091f\u093e\u0930"
    ],
    "name:pol_x_preferred":[
        "Bulingtar"
    ],
    "wof:name":"Bulingtar",
    "wof:placetype":"locality"
},
  "geometry": {"coordinates":[84.18303,27.83595],"type":"Point"}
}