{
  "type": "Feature",
  "properties": {
    "gn:admin1_code":"FR",
    "gn:admin2_code":"9",
    "gn:admin3_code":"74",
    "gn:admin4_code":"740018",
    "gn:asciiname":"Durgasthan",
    "gn:country_code":"NP",
    "gn:dem":1467,
    "gn:feature_class":"P",
    "gn:feature_code":"PPLL",
    "gn:name":"Durgasthan",
    "gn:population":0,
    "gn:timezone":"Asia/Kathmandu",
    "iso:country":"NP",
    "wof:name":"Durgasthan",
    "wof:placetype":"locality"
},
  "geometry": {"coordinates":[80.47613,29.47962],"type":"Point"}
}