{
  "type": "Feature",
  "properties": {
    "gn:admin1_code":"FR",
    "gn:admin2_code":"9",
    "gn:admin3_code":"74",
    "gn:admin4_code":"740018",
    "gn:asciiname":"Durgasthan",
    "gn:country_code":"NP",
    "gn:dem":1467,
    "gn:feature_class":"P",
    "gn:feature_code":"PPLL",
    "gn:name":"Durgasthan",
    "gn:population":0,
    "gn:timezone":"Asia/Kathmandu",
    "iso:country":"NP",
    "name:ceb_x_preferred":[
        "Durgasthan"
    ],
    "name:dty_x_preferred":[
        "\u0926\u0941\u0930\u094d\u0917\u093e\u0938\u094d\u0925\u093e\u0928 \u0917\u093e\u0935\u093f\u0938"
    ],
    "name:hin_x_preferred":[
        "\u0926\u0941\u0930\u094d\u0917\u093e\u0938\u094d\u0925\u093e\u0928"
    ],
    "name:mai_x_preferred":[
        "\u0926\u0941\u0930\u094d\u0917\u093e\u0938\u094d\u0925\u093e\u0928"
    ],
    "name:msa_x_preferred":[
        "Durgasthan"
    ],
    "name:nep_x_preferred":[
        "\u0926\u0941\u0930\u094d\u0917\u093e\u0938\u094d\u0925\u093e\u0928"
    ],
    "name:new_x_preferred":[
        "\u0926\u0941\u0930\u094d\u0917\u093e\u0938\u094d\u0925\u093e\u0928"
    ],
    "name:pol_x_preferred":[
        "Durgasthan"
    ],
    "wof:name":"Durgasthan",
    "wof:placetype":"locality"
},
  "geometry": {"coordinates":[80.47613,29.47962],"type":"Point"}
}