{
  "type": "Feature",
  "properties": {
    "gn:admin1_code":"CR",
    "gn:admin2_code":"5",
    "gn:admin3_code":"22.0",
    "gn:admin4_code":"220044.0",
    "gn:asciiname":"Deurali",
    "gn:country_code":"NP",
    "gn:dem":1231,
    "gn:feature_class":"P",
    "gn:feature_code":"PPLL",
    "gn:name":"Deurali",
    "gn:population":0,
    "gn:timezone":"Asia/Kathmandu",
    "iso:country":"NP",
    "wof:name":"Deurali",
    "wof:placetype":"locality"
},
  "geometry": {"coordinates":[86.0731,27.58051],"type":"Point"}
}