{
  "type": "Feature",
  "properties": {
    "gn:admin1_code":"CR",
    "gn:admin2_code":"5",
    "gn:admin3_code":"19",
    "gn:admin4_code":"190069",
    "gn:asciiname":"Murtiya",
    "gn:country_code":"NP",
    "gn:dem":98,
    "gn:feature_class":"P",
    "gn:feature_code":"PPLL",
    "gn:name":"Murtiya",
    "gn:population":0,
    "gn:timezone":"Asia/Kathmandu",
    "iso:country":"NP",
    "name:ceb_x_preferred":[
        "Murtiya"
    ],
    "name:fra_x_preferred":[
        "Murtiya"
    ],
    "name:nep_x_preferred":[
        "\u092e\u0941\u0930\u094d\u0924\u093f\u092f\u093e"
    ],
    "name:new_x_preferred":[
        "\u092e\u0941\u0930\u094d\u0924\u093f\u092f\u093e"
    ],
    "name:pol_x_preferred":[
        "Murtiya"
    ],
    "wof:name":"Murtiya",
    "wof:placetype":"locality"
},
  "geometry": {"coordinates":[85.48628000000002,27.00005],"type":"Point"}
}