{
  "type": "Feature",
  "properties": {
    "gn:admin1_code":"WR",
    "gn:admin2_code":"3",
    "gn:admin3_code":"44",
    "gn:admin4_code":"440051",
    "gn:asciiname":"Mulachaur",
    "gn:country_code":"NP",
    "gn:dem":1144,
    "gn:feature_class":"P",
    "gn:feature_code":"PPLL",
    "gn:name":"Mulachaur",
    "gn:population":0,
    "gn:timezone":"Asia/Kathmandu",
    "iso:country":"NP",
    "wof:name":"Mulachaur",
    "wof:placetype":"locality"
},
  "geometry": {"coordinates":[83.72076,28.18269],"type":"Point"}
}