{
  "type": "Feature",
  "properties": {
    "gn:admin1_code":"WR",
    "gn:admin2_code":"4",
    "gn:admin3_code":"40.0",
    "gn:admin4_code":"400022.0",
    "gn:asciiname":"Sakneri",
    "gn:country_code":"NP",
    "gn:dem":769,
    "gn:feature_class":"P",
    "gn:feature_code":"PPLL",
    "gn:name":"Sakneri",
    "gn:population":0,
    "gn:timezone":"Asia/Kathmandu",
    "iso:country":"NP",
    "wof:name":"Sakneri",
    "wof:placetype":"locality"
},
  "geometry": {"coordinates":[84.03733000000003,28.18167],"type":"Point"}
}