{
  "type": "Feature",
  "properties": {
    "gn:admin1_code":"MR",
    "gn:admin2_code":"2",
    "gn:admin3_code":"61.0",
    "gn:admin4_code":"610030.0",
    "gn:asciiname":"Chiuduwa",
    "gn:country_code":"NP",
    "gn:dem":2168,
    "gn:feature_class":"P",
    "gn:feature_code":"PPLL",
    "gn:name":"Chiuduwa",
    "gn:population":0,
    "gn:timezone":"Asia/Kathmandu",
    "iso:country":"NP",
    "wof:name":"Chiuduwa",
    "wof:placetype":"locality"
},
  "geometry": {"coordinates":[81.87008,28.67843],"type":"Point"}
}