{
  "type": "Feature",
  "properties": {
    "gn:admin1_code":"ER",
    "gn:admin2_code":"13",
    "gn:admin3_code":"13",
    "gn:admin4_code":"130051",
    "gn:asciiname":"Bophai",
    "gn:country_code":"NP",
    "gn:dem":849,
    "gn:feature_class":"P",
    "gn:feature_code":"PPLL",
    "gn:name":"Bophai",
    "gn:population":0,
    "gn:timezone":"Asia/Kathmandu",
    "iso:country":"NP",
    "wof:name":"Bophai",
    "wof:placetype":"locality"
},
  "geometry": {"coordinates":[86.82500999999998,27.17135],"type":"Point"}
}