{
  "type": "Feature",
  "properties": {
    "gn:admin1_code":"CR",
    "gn:admin2_code":"1",
    "gn:admin3_code":"25",
    "gn:admin4_code":"250020",
    "gn:asciiname":"Nasurkhel",
    "gn:country_code":"NP",
    "gn:dem":1569,
    "gn:feature_class":"P",
    "gn:feature_code":"PPLL",
    "gn:name":"Nasurkhel",
    "gn:population":0,
    "gn:timezone":"Asia/Kathmandu",
    "iso:country":"NP",
    "wof:name":"Nasurkhel",
    "wof:placetype":"locality"
},
  "geometry": {"coordinates":[85.39021,27.49733],"type":"Point"}
}