{
  "type": "Feature",
  "properties": {
    "gn:admin1_code":"MR",
    "gn:admin2_code":"6",
    "gn:admin3_code":"66.0",
    "gn:admin4_code":"660001.0",
    "gn:asciiname":"Paga",
    "gn:country_code":"NP",
    "gn:dem":2969,
    "gn:feature_class":"P",
    "gn:feature_code":"PPLL",
    "gn:name":"Paga",
    "gn:population":0,
    "gn:timezone":"Asia/Kathmandu",
    "iso:country":"NP",
    "name:ceb_x_preferred":[
        "Paga"
    ],
    "name:pol_x_preferred":[
        "Paga"
    ],
    "name:swe_x_preferred":[
        "Paga"
    ],
    "wof:name":"Paga",
    "wof:placetype":"locality"
},
  "geometry": {"coordinates":[81.94494,29.80276],"type":"Point"}
}