{
  "type": "Feature",
  "properties": {
    "gn:admin1_code":"ER",
    "gn:admin2_code":"7.0",
    "gn:admin3_code":"8.0",
    "gn:admin4_code":"80014.0",
    "gn:asciiname":"Sikdim",
    "gn:country_code":"NP",
    "gn:dem":1988,
    "gn:feature_class":"P",
    "gn:feature_code":"PPLL",
    "gn:name":"Sikdim",
    "gn:population":0,
    "gn:timezone":"Asia/Kathmandu",
    "iso:country":"NP",
    "wof:name":"Sikdim",
    "wof:placetype":"locality"
},
  "geometry": {"coordinates":[87.49174000000002,27.21641],"type":"Point"}
}