{
  "type": "Feature",
  "properties": {
    "gn:admin1_code":"FR",
    "gn:admin2_code":"9",
    "gn:admin3_code":"72.0",
    "gn:admin4_code":"720019.0",
    "gn:asciiname":"Ghorsuwa",
    "gn:country_code":"NP",
    "gn:dem":218,
    "gn:feature_class":"P",
    "gn:feature_code":"PPLL",
    "gn:name":"Ghorsuwa",
    "gn:population":0,
    "gn:timezone":"Asia/Kathmandu",
    "iso:country":"NP",
    "wof:name":"Ghorsuwa",
    "wof:placetype":"locality"
},
  "geometry": {"coordinates":[80.23443,28.96912],"type":"Point"}
}