{
  "type": "Feature",
  "properties": {
    "gn:admin1_code":"MR",
    "gn:admin2_code":"2.0",
    "gn:admin3_code":"57.0",
    "gn:admin4_code":"570003.0",
    "gn:asciiname":"Tewaripurwa",
    "gn:country_code":"NP",
    "gn:dem":147,
    "gn:feature_class":"P",
    "gn:feature_code":"PPLL",
    "gn:name":"Tewaripurwa",
    "gn:population":0,
    "gn:timezone":"Asia/Kathmandu",
    "iso:country":"NP",
    "wof:name":"Tewaripurwa",
    "wof:placetype":"locality"
},
  "geometry": {"coordinates":[81.69213000000001,28.04794],"type":"Point"}
}