{
  "type": "Feature",
  "properties": {
    "gn:admin1_code":"ER",
    "gn:admin2_code":"13",
    "gn:admin3_code":"13.0",
    "gn:admin4_code":"130041.0",
    "gn:asciiname":"Bhangtar",
    "gn:country_code":"NP",
    "gn:dem":1982,
    "gn:feature_class":"P",
    "gn:feature_code":"PPLL",
    "gn:name":"Bhangtar",
    "gn:population":0,
    "gn:timezone":"Asia/Kathmandu",
    "iso:country":"NP",
    "name:ceb_x_preferred":[
        "Bhangtar"
    ],
    "name:swe_x_preferred":[
        "Bhangtar"
    ],
    "wof:name":"Bhangtar",
    "wof:placetype":"locality"
},
  "geometry": {"coordinates":[86.87891999999999,27.14356],"type":"Point"}
}