{
  "type": "Feature",
  "properties": {
    "gn:admin1_code":"ER",
    "gn:admin2_code":"13",
    "gn:admin3_code":"15",
    "gn:admin4_code":"150103.0",
    "gn:asciiname":"Silangetol",
    "gn:country_code":"NP",
    "gn:dem":115,
    "gn:feature_class":"P",
    "gn:feature_code":"PPLL",
    "gn:name":"Silangetol",
    "gn:population":0,
    "gn:timezone":"Asia/Kathmandu",
    "iso:country":"NP",
    "wof:name":"Silangetol",
    "wof:placetype":"locality"
},
  "geometry": {"coordinates":[86.88835,26.6537],"type":"Point"}
}