{
  "type": "Feature",
  "properties": {
    "gn:admin1_code":"WR",
    "gn:admin2_code":"4.0",
    "gn:admin3_code":"39.0",
    "gn:admin4_code":"390030.0",
    "gn:asciiname":"Kholegaun",
    "gn:country_code":"NP",
    "gn:dem":685,
    "gn:feature_class":"P",
    "gn:feature_code":"PPLL",
    "gn:name":"Kholegaun",
    "gn:population":0,
    "gn:timezone":"Asia/Kathmandu",
    "iso:country":"NP",
    "wof:name":"Kholegaun",
    "wof:placetype":"locality"
},
  "geometry": {"coordinates":[83.79978,27.91828],"type":"Point"}
}