{
  "type": "Feature",
  "properties": {
    "gn:admin1_code":"FR",
    "gn:admin2_code":"14",
    "gn:admin3_code":"70.0",
    "gn:admin4_code":"700014.0",
    "gn:asciiname":"Oligaun",
    "gn:country_code":"NP",
    "gn:dem":1367,
    "gn:feature_class":"P",
    "gn:feature_code":"PPLL",
    "gn:name":"Oligaun",
    "gn:population":0,
    "gn:timezone":"Asia/Kathmandu",
    "iso:country":"NP",
    "name:ceb_x_preferred":[
        "Oligau"
    ],
    "name:fra_x_preferred":[
        "Oligau"
    ],
    "name:msa_x_preferred":[
        "Oligau"
    ],
    "name:nep_x_preferred":[
        "\u0913\u0932\u093f\u0917\u093e\u0909\u0901"
    ],
    "name:new_x_preferred":[
        "\u0913\u0932\u093f\u0917\u093e\u0909\u0902"
    ],
    "name:pol_x_preferred":[
        "Oligau"
    ],
    "wof:name":"Oligaun",
    "wof:placetype":"locality"
},
  "geometry": {"coordinates":[80.97187,29.16139],"type":"Point"}
}