{
  "type": "Feature",
  "properties": {
    "gn:admin1_code":"WR",
    "gn:admin2_code":"8",
    "gn:admin3_code":"47",
    "gn:admin4_code":"470001",
    "gn:asciiname":"Archale",
    "gn:country_code":"NP",
    "gn:dem":861,
    "gn:feature_class":"P",
    "gn:feature_code":"PPLL",
    "gn:name":"Archale",
    "gn:population":0,
    "gn:timezone":"Asia/Kathmandu",
    "iso:country":"NP",
    "name:ceb_x_preferred":[
        "Archale"
    ],
    "name:hin_x_preferred":[
        "\u0905\u0930\u094d\u091a\u0932\u0947"
    ],
    "name:msa_x_preferred":[
        "Archale"
    ],
    "name:nep_x_preferred":[
        "\u0905\u0930\u094d\u091a\u0932\u0947"
    ],
    "name:new_x_preferred":[
        "\u0905\u0930\u094d\u091a\u0932\u0947"
    ],
    "name:pol_x_preferred":[
        "Archale"
    ],
    "wof:name":"Archale",
    "wof:placetype":"locality"
},
  "geometry": {"coordinates":[83.86333,27.78633],"type":"Point"}
}