{
  "type": "Feature",
  "properties": {
    "gn:admin1_code":"00",
    "gn:asciiname":"Phubari",
    "gn:country_code":"NP",
    "gn:dem":1340,
    "gn:feature_class":"P",
    "gn:feature_code":"PPL",
    "gn:name":"Ph\u016bb\u0101ri\u0307\u0304",
    "gn:population":0,
    "gn:timezone":"Asia/Kathmandu",
    "iso:country":"NP",
    "name:und_x_variant":[
        "Ph\u016bb\u0101ri\u0307\u0304",
        "Ph\u016bb\u0101r\u012b"
    ],
    "wof:name":"Phubari",
    "wof:placetype":"locality"
},
  "geometry": {"coordinates":[85.36648000000002,27.72452],"type":"Point"}
}