{
  "type": "Feature",
  "properties": {
    "gn:admin1_code":"MR",
    "gn:admin2_code":"12",
    "gn:admin3_code":"53",
    "gn:admin4_code":"530035",
    "gn:asciiname":"Pataledanda",
    "gn:country_code":"NP",
    "gn:dem":1935,
    "gn:feature_class":"P",
    "gn:feature_code":"PPLL",
    "gn:name":"Pataledanda",
    "gn:population":0,
    "gn:timezone":"Asia/Kathmandu",
    "iso:country":"NP",
    "wof:name":"Pataledanda",
    "wof:placetype":"locality"
},
  "geometry": {"coordinates":[82.51116999999998,28.54306],"type":"Point"}
}