{
  "type": "Feature",
  "properties": {
    "gn:admin1_code":"MR",
    "gn:admin2_code":"12",
    "gn:admin3_code":"53",
    "gn:admin4_code":"530027",
    "gn:asciiname":"Goganpani",
    "gn:country_code":"NP",
    "gn:dem":1583,
    "gn:feature_class":"P",
    "gn:feature_code":"PPLL",
    "gn:name":"Goganpani",
    "gn:population":0,
    "gn:timezone":"Asia/Kathmandu",
    "iso:country":"NP",
    "name:pol_x_preferred":[
        "Goganpani"
    ],
    "wof:name":"Goganpani",
    "wof:placetype":"locality"
},
  "geometry": {"coordinates":[82.66849999999999,28.24519],"type":"Point"}
}