{
  "type": "Feature",
  "properties": {
    "gn:admin1_code":"FR",
    "gn:admin2_code":"14",
    "gn:admin3_code":"69.0",
    "gn:admin4_code":"690068.0",
    "gn:asciiname":"Kand",
    "gn:country_code":"NP",
    "gn:dem":1773,
    "gn:feature_class":"P",
    "gn:feature_code":"PPLL",
    "gn:name":"Kand",
    "gn:population":0,
    "gn:timezone":"Asia/Kathmandu",
    "iso:country":"NP",
    "name:ceb_x_preferred":[
        "Kand"
    ],
    "name:swe_x_preferred":[
        "Kand"
    ],
    "wof:name":"Kand",
    "wof:placetype":"locality"
},
  "geometry": {"coordinates":[81.35821,29.20384],"type":"Point"}
}