{
  "type": "Feature",
  "properties": {
    "gn:admin1_code":"CR",
    "gn:admin2_code":"11",
    "gn:admin3_code":"35.0",
    "gn:admin4_code":"350005.0",
    "gn:asciiname":"Adarshachok",
    "gn:country_code":"NP",
    "gn:dem":189,
    "gn:feature_class":"P",
    "gn:feature_code":"PPLL",
    "gn:name":"Adarshachok",
    "gn:population":0,
    "gn:timezone":"Asia/Kathmandu",
    "iso:country":"NP",
    "wof:name":"Adarshachok",
    "wof:placetype":"locality"
},
  "geometry": {"coordinates":[84.37966999999998,27.67251],"type":"Point"}
}