{
  "type": "Feature",
  "properties": {
    "gn:admin1_code":"CR",
    "gn:admin2_code":"5",
    "gn:admin3_code":"20",
    "gn:admin4_code":"200026",
    "gn:asciiname":"Sakhauri",
    "gn:country_code":"NP",
    "gn:dem":270,
    "gn:feature_class":"P",
    "gn:feature_code":"PPLL",
    "gn:name":"Sakhauri",
    "gn:population":0,
    "gn:timezone":"Asia/Kathmandu",
    "iso:country":"NP",
    "wof:name":"Sakhauri",
    "wof:placetype":"locality"
},
  "geometry": {"coordinates":[85.65501999999999,27.2824],"type":"Point"}
}