{
  "type": "Feature",
  "properties": {
    "gn:admin1_code":"WR",
    "gn:admin2_code":"3",
    "gn:admin3_code":"45.0",
    "gn:admin4_code":"450015.0",
    "gn:asciiname":"Argal",
    "gn:country_code":"NP",
    "gn:dem":2184,
    "gn:feature_class":"P",
    "gn:feature_code":"PPLL",
    "gn:name":"Argal",
    "gn:population":0,
    "gn:timezone":"Asia/Kathmandu",
    "iso:country":"NP",
    "wof:name":"Argal",
    "wof:placetype":"locality"
},
  "geometry": {"coordinates":[83.36265,28.34625],"type":"Point"}
}