{
  "type": "Feature",
  "properties": {
    "gn:admin1_code":"FR",
    "gn:admin2_code":"14",
    "gn:admin3_code":"71.0",
    "gn:admin4_code":"710010.0",
    "gn:asciiname":"Devhariya Chok",
    "gn:country_code":"NP",
    "gn:dem":184,
    "gn:feature_class":"P",
    "gn:feature_code":"PPLL",
    "gn:name":"Devhariya Chok",
    "gn:population":0,
    "gn:timezone":"Asia/Kathmandu",
    "iso:country":"NP",
    "wof:name":"Devhariya Chok",
    "wof:placetype":"locality"
},
  "geometry": {"coordinates":[80.61498,28.69826],"type":"Point"}
}