{
  "type": "Feature",
  "properties": {
    "gn:admin1_code":"00",
    "gn:asciiname":"Bhumedada",
    "gn:country_code":"NP",
    "gn:dem":630,
    "gn:feature_class":"P",
    "gn:feature_code":"PPL",
    "gn:name":"Bhume\u1e0d\u0101\u0303\u1e0d\u0101",
    "gn:population":0,
    "gn:timezone":"Asia/Kathmandu",
    "iso:country":"NP",
    "name:nep_x_preferred":[
        "Bhume\u1e0d\u0101\u0303\u1e0d\u0101"
    ],
    "wof:name":"Bhumedada",
    "wof:placetype":"locality"
},
  "geometry": {"coordinates":[84.85600000000002,27.80116],"type":"Point"}
}