{
  "type": "Feature",
  "properties": {
    "gn:admin1_code":"WR",
    "gn:admin2_code":"3",
    "gn:admin3_code":"45.0",
    "gn:admin4_code":"450014.0",
    "gn:asciiname":"Rinubang",
    "gn:country_code":"NP",
    "gn:dem":2240,
    "gn:feature_class":"P",
    "gn:feature_code":"PPLL",
    "gn:name":"Rinubang",
    "gn:population":0,
    "gn:timezone":"Asia/Kathmandu",
    "iso:country":"NP",
    "wof:name":"Rinubang",
    "wof:placetype":"locality"
},
  "geometry": {"coordinates":[82.9525,28.43217000000001],"type":"Point"}
}