{
  "type": "Feature",
  "properties": {
    "gn:admin1_code":"ER",
    "gn:admin2_code":"10",
    "gn:admin3_code":"2",
    "gn:admin4_code":"20030",
    "gn:asciiname":"Surketham",
    "gn:country_code":"NP",
    "gn:dem":3364,
    "gn:feature_class":"P",
    "gn:feature_code":"PPLL",
    "gn:name":"Surketham",
    "gn:population":0,
    "gn:timezone":"Asia/Kathmandu",
    "iso:country":"NP",
    "wof:name":"Surketham",
    "wof:placetype":"locality"
},
  "geometry": {"coordinates":[87.99453000000003,27.13402],"type":"Point"}
}