{
  "type": "Feature",
  "properties": {
    "gn:admin1_code":"FR",
    "gn:admin2_code":"14",
    "gn:admin3_code":"71.0",
    "gn:admin4_code":"710030.0",
    "gn:asciiname":"Narange",
    "gn:country_code":"NP",
    "gn:dem":702,
    "gn:feature_class":"P",
    "gn:feature_code":"PPLL",
    "gn:name":"Narange",
    "gn:population":0,
    "gn:timezone":"Asia/Kathmandu",
    "iso:country":"NP",
    "wof:name":"Narange",
    "wof:placetype":"locality"
},
  "geometry": {"coordinates":[81.00129,28.85458],"type":"Point"}
}