{
  "type": "Feature",
  "properties": {
    "gn:admin1_code":"MR",
    "gn:admin2_code":"12",
    "gn:admin3_code":"56.0",
    "gn:admin4_code":"560039.0",
    "gn:asciiname":"Hattikhaka",
    "gn:country_code":"NP",
    "gn:dem":1015,
    "gn:feature_class":"P",
    "gn:feature_code":"PPLL",
    "gn:name":"Hattikhaka",
    "gn:population":0,
    "gn:timezone":"Asia/Kathmandu",
    "iso:country":"NP",
    "wof:name":"Hattikhaka",
    "wof:placetype":"locality"
},
  "geometry": {"coordinates":[82.52594000000001,28.0701],"type":"Point"}
}