{
  "type": "Feature",
  "properties": {
    "gn:admin1_code":"FR",
    "gn:admin2_code":"9",
    "gn:admin3_code":"72.0",
    "gn:admin4_code":"720003.0",
    "gn:asciiname":"Chadani",
    "gn:country_code":"NP",
    "gn:dem":215,
    "gn:feature_class":"P",
    "gn:feature_code":"PPLL",
    "gn:name":"Chadani",
    "gn:population":0,
    "gn:timezone":"Asia/Kathmandu",
    "iso:country":"NP",
    "wof:name":"Chadani",
    "wof:placetype":"locality"
},
  "geometry": {"coordinates":[80.09040999999998,28.96097],"type":"Point"}
}