{
  "type": "Feature",
  "properties": {
    "gn:admin1_code":"CR",
    "gn:admin2_code":"11",
    "gn:admin3_code":"31",
    "gn:admin4_code":"310024",
    "gn:asciiname":"Kamle",
    "gn:country_code":"NP",
    "gn:dem":1285,
    "gn:feature_class":"P",
    "gn:feature_code":"PPLL",
    "gn:name":"Kamle",
    "gn:population":0,
    "gn:timezone":"Asia/Kathmandu",
    "iso:country":"NP",
    "wof:name":"Kamle",
    "wof:placetype":"locality"
},
  "geometry": {"coordinates":[84.78909,27.62393],"type":"Point"}
}