{
  "type": "Feature",
  "properties": {
    "gn:admin1_code":"ER",
    "gn:admin2_code":"13",
    "gn:admin3_code":"16",
    "gn:admin4_code":"160049",
    "gn:asciiname":"Jamdaha",
    "gn:country_code":"NP",
    "gn:dem":175,
    "gn:feature_class":"P",
    "gn:feature_code":"PPLL",
    "gn:name":"Jamdaha",
    "gn:population":0,
    "gn:timezone":"Asia/Kathmandu",
    "iso:country":"NP",
    "wof:name":"Jamdaha",
    "wof:placetype":"locality"
},
  "geometry": {"coordinates":[86.35041,26.83242000000001],"type":"Point"}
}