{
  "type": "Feature",
  "properties": {
    "gn:admin1_code":"ER",
    "gn:admin2_code":"10",
    "gn:admin3_code":"3.0",
    "gn:admin4_code":"30030.0",
    "gn:asciiname":"Batase",
    "gn:country_code":"NP",
    "gn:dem":1084,
    "gn:feature_class":"P",
    "gn:feature_code":"PPLL",
    "gn:name":"Batase",
    "gn:population":0,
    "gn:timezone":"Asia/Kathmandu",
    "iso:country":"NP",
    "name:ceb_x_preferred":[
        "Batase"
    ],
    "name:pol_x_preferred":[
        "Batase"
    ],
    "wof:name":"Batase",
    "wof:placetype":"locality"
},
  "geometry": {"coordinates":[88.04415999999998,26.9191],"type":"Point"}
}