{
  "type": "Feature",
  "properties": {
    "gn:admin1_code":"MR",
    "gn:admin2_code":"6",
    "gn:admin3_code":"63.0",
    "gn:admin4_code":"630006.0",
    "gn:asciiname":"Mahadev",
    "gn:country_code":"NP",
    "gn:dem":2627,
    "gn:feature_class":"P",
    "gn:feature_code":"PPLL",
    "gn:name":"Mahadev",
    "gn:population":0,
    "gn:timezone":"Asia/Kathmandu",
    "iso:country":"NP",
    "wof:name":"Mahadev",
    "wof:placetype":"locality"
},
  "geometry": {"coordinates":[82.21278000000002,29.25306],"type":"Point"}
}