{
  "type": "Feature",
  "properties": {
    "gn:admin1_code":"ER",
    "gn:admin2_code":"7.0",
    "gn:admin3_code":"8.0",
    "gn:admin4_code":"80017.0",
    "gn:asciiname":"Loguwa",
    "gn:country_code":"NP",
    "gn:dem":1343,
    "gn:feature_class":"P",
    "gn:feature_code":"PPLL",
    "gn:name":"Loguwa",
    "gn:population":0,
    "gn:timezone":"Asia/Kathmandu",
    "iso:country":"NP",
    "wof:name":"Loguwa",
    "wof:placetype":"locality"
},
  "geometry": {"coordinates":[87.54584,27.17741],"type":"Point"}
}