{
  "type": "Feature",
  "properties": {
    "gn:admin1_code":"FR",
    "gn:admin2_code":"14",
    "gn:admin3_code":"71.0",
    "gn:admin4_code":"710033.0",
    "gn:asciiname":"Tulsibari",
    "gn:country_code":"NP",
    "gn:dem":162,
    "gn:feature_class":"P",
    "gn:feature_code":"PPLL",
    "gn:name":"Tulsibari",
    "gn:population":0,
    "gn:timezone":"Asia/Kathmandu",
    "iso:country":"NP",
    "wof:name":"Tulsibari",
    "wof:placetype":"locality"
},
  "geometry": {"coordinates":[80.72368,28.6096],"type":"Point"}
}