{
  "type": "Feature",
  "properties": {
    "gn:admin1_code":"WR",
    "gn:admin2_code":"8",
    "gn:admin3_code":"49",
    "gn:admin4_code":"490017",
    "gn:asciiname":"Chilhiya",
    "gn:country_code":"NP",
    "gn:dem":113,
    "gn:feature_class":"P",
    "gn:feature_code":"PPLL",
    "gn:name":"Chilhiya",
    "gn:population":0,
    "gn:timezone":"Asia/Kathmandu",
    "iso:country":"NP",
    "name:ceb_x_preferred":[
        "Chilhiya"
    ],
    "name:mai_x_preferred":[
        "\u091a\u093f\u0932\u094d\u0939\u093f\u092f\u093e"
    ],
    "name:msa_x_preferred":[
        "Chilhiya"
    ],
    "name:nep_x_preferred":[
        "\u091a\u093f\u0932\u094d\u0939\u093f\u092f\u093e"
    ],
    "name:new_x_preferred":[
        "\u091a\u093f\u0932\u094d\u0939\u093f\u092f\u093e"
    ],
    "name:pol_x_preferred":[
        "Chilhiya"
    ],
    "wof:name":"Chilhiya",
    "wof:placetype":"locality"
},
  "geometry": {"coordinates":[83.44208,27.55757],"type":"Point"}
}