{
  "type": "Feature",
  "properties": {
    "gn:admin1_code":"MR",
    "gn:admin2_code":"2",
    "gn:admin3_code":"61.0",
    "gn:admin4_code":"610007.0",
    "gn:asciiname":"Khurpagaun",
    "gn:country_code":"NP",
    "gn:dem":1891,
    "gn:feature_class":"P",
    "gn:feature_code":"PPLL",
    "gn:name":"Khurpagaun",
    "gn:population":0,
    "gn:timezone":"Asia/Kathmandu",
    "iso:country":"NP",
    "wof:name":"Khurpagaun",
    "wof:placetype":"locality"
},
  "geometry": {"coordinates":[82.16830999999998,28.83804],"type":"Point"}
}