{
  "type": "Feature",
  "properties": {
    "gn:admin1_code":"MR",
    "gn:admin2_code":"2.0",
    "gn:admin3_code":"59.0",
    "gn:admin4_code":"590006.0",
    "gn:asciiname":"Jugepani",
    "gn:country_code":"NP",
    "gn:dem":860,
    "gn:feature_class":"P",
    "gn:feature_code":"PPLL",
    "gn:name":"Jugepani",
    "gn:population":0,
    "gn:timezone":"Asia/Kathmandu",
    "iso:country":"NP",
    "wof:name":"Jugepani",
    "wof:placetype":"locality"
},
  "geometry": {"coordinates":[81.37761,28.84158],"type":"Point"}
}