{
  "type": "Feature",
  "properties": {
    "gn:admin1_code":"WR",
    "gn:admin2_code":"3",
    "gn:admin3_code":"43",
    "gn:admin4_code":"430004",
    "gn:asciiname":"Banskot",
    "gn:country_code":"NP",
    "gn:dem":1530,
    "gn:feature_class":"P",
    "gn:feature_code":"PPLL",
    "gn:name":"Banskot",
    "gn:population":0,
    "gn:timezone":"Asia/Kathmandu",
    "iso:country":"NP",
    "wof:name":"Banskot",
    "wof:placetype":"locality"
},
  "geometry": {"coordinates":[83.57899999999999,28.4537],"type":"Point"}
}