{
  "type": "Feature",
  "properties": {
    "gn:admin1_code":"MR",
    "gn:admin2_code":"2",
    "gn:admin3_code":"60.0",
    "gn:admin4_code":"600030.0",
    "gn:asciiname":"Tankot",
    "gn:country_code":"NP",
    "gn:dem":1601,
    "gn:feature_class":"P",
    "gn:feature_code":"PPLL",
    "gn:name":"Tankot",
    "gn:population":0,
    "gn:timezone":"Asia/Kathmandu",
    "iso:country":"NP",
    "wof:name":"Tankot",
    "wof:placetype":"locality"
},
  "geometry": {"coordinates":[81.77046,28.65345],"type":"Point"}
}