{
  "type": "Feature",
  "properties": {
    "gn:admin1_code":"CR",
    "gn:admin2_code":"1",
    "gn:admin3_code":"28",
    "gn:admin4_code":"280020",
    "gn:asciiname":"Ganeshsthan",
    "gn:country_code":"NP",
    "gn:dem":983,
    "gn:feature_class":"P",
    "gn:feature_code":"PPLL",
    "gn:name":"Ganeshsthan",
    "gn:population":0,
    "gn:timezone":"Asia/Kathmandu",
    "iso:country":"NP",
    "wof:name":"Ganeshsthan",
    "wof:placetype":"locality"
},
  "geometry": {"coordinates":[85.26442,27.92331],"type":"Point"}
}