{
  "type": "Feature",
  "properties": {
    "gn:admin1_code":"ER",
    "gn:admin2_code":"13",
    "gn:admin3_code":"11",
    "gn:admin4_code":"110018",
    "gn:asciiname":"Lola",
    "gn:country_code":"NP",
    "gn:dem":5991,
    "gn:feature_class":"P",
    "gn:feature_code":"PPLL",
    "gn:name":"Lola",
    "gn:population":0,
    "gn:timezone":"Asia/Kathmandu",
    "iso:country":"NP",
    "name:bre_x_preferred":[
        "Lola"
    ],
    "name:ceb_x_preferred":[
        "Lola"
    ],
    "name:deu_x_preferred":[
        "Lola"
    ],
    "name:est_x_preferred":[
        "Lola"
    ],
    "name:fas_x_preferred":[
        "\u0644\u0648\u0644\u0627"
    ],
    "name:fin_x_preferred":[
        "Lola"
    ],
    "name:fra_x_preferred":[
        "Lola"
    ],
    "name:heb_x_preferred":[
        "\u05dc\u05d5\u05dc\u05d4"
    ],
    "name:hun_x_preferred":[
        "Lola"
    ],
    "name:ita_x_preferred":[
        "Lola"
    ],
    "name:nld_x_preferred":[
        "Lola"
    ],
    "name:pol_x_preferred":[
        "Lola"
    ],
    "name:por_x_preferred":[
        "Lola"
    ],
    "name:rus_x_preferred":[
        "\u041b\u043e\u043b\u0430"
    ],
    "name:spa_x_preferred":[
        "Lola"
    ],
    "name:swe_x_preferred":[
        "Lola"
    ],
    "name:tur_x_preferred":[
        "Lola"
    ],
    "name:uzb_x_preferred":[
        "Lola"
    ],
    "wof:name":"Lola",
    "wof:placetype":"locality"
},
  "geometry": {"coordinates":[86.8753,28.0101],"type":"Point"}
}