{
  "type": "Feature",
  "properties": {
    "gn:admin1_code":"MR",
    "gn:admin2_code":"12",
    "gn:admin3_code":"53",
    "gn:admin4_code":"530044",
    "gn:asciiname":"Sunchari",
    "gn:country_code":"NP",
    "gn:dem":1531,
    "gn:feature_class":"P",
    "gn:feature_code":"PPLL",
    "gn:name":"Sunchari",
    "gn:population":0,
    "gn:timezone":"Asia/Kathmandu",
    "iso:country":"NP",
    "wof:name":"Sunchari",
    "wof:placetype":"locality"
},
  "geometry": {"coordinates":[82.80475,28.34555],"type":"Point"}
}