{
  "type": "Feature",
  "properties": {
    "gn:admin1_code":"MR",
    "gn:admin2_code":"2.0",
    "gn:admin3_code":"59.0",
    "gn:admin4_code":"590042.0",
    "gn:asciiname":"Pul Bajar",
    "gn:country_code":"NP",
    "gn:dem":560,
    "gn:feature_class":"P",
    "gn:feature_code":"PPLL",
    "gn:name":"Pul Bajar",
    "gn:population":0,
    "gn:timezone":"Asia/Kathmandu",
    "iso:country":"NP",
    "wof:name":"Pul Bajar",
    "wof:placetype":"locality"
},
  "geometry": {"coordinates":[82.0252,28.52219],"type":"Point"}
}