{
  "type": "Feature",
  "properties": {
    "gn:admin1_code":"ER",
    "gn:admin2_code":"7.0",
    "gn:admin3_code":"8.0",
    "gn:admin4_code":"80014.0",
    "gn:asciiname":"Mangalbare",
    "gn:country_code":"NP",
    "gn:dem":2625,
    "gn:feature_class":"P",
    "gn:feature_code":"PPLL",
    "gn:name":"Mangalbare",
    "gn:population":0,
    "gn:timezone":"Asia/Kathmandu",
    "iso:country":"NP",
    "name:bih_x_preferred":[
        "\u092e\u0902\u0917\u0932\u092c\u093e\u0930\u0947"
    ],
    "name:ceb_x_preferred":[
        "Mangalbare"
    ],
    "name:hin_x_preferred":[
        "\u092e\u0902\u0917\u0932\u092c\u093e\u0930\u0947"
    ],
    "name:msa_x_preferred":[
        "Mangalbare"
    ],
    "name:nep_x_preferred":[
        "\u092e\u0902\u0917\u0932\u092c\u093e\u0930\u0947"
    ],
    "name:new_x_preferred":[
        "\u092e\u0902\u0917\u0932\u092c\u093e\u0930\u0947"
    ],
    "name:nld_x_preferred":[
        "Mangalbare"
    ],
    "name:pol_x_preferred":[
        "Mangalbare"
    ],
    "wof:name":"Mangalbare",
    "wof:placetype":"locality"
},
  "geometry": {"coordinates":[87.47490999999999,27.22663],"type":"Point"}
}