{
  "type": "Feature",
  "properties": {
    "gn:admin1_code":"WR",
    "gn:admin2_code":"8",
    "gn:admin3_code":"47",
    "gn:admin4_code":"470022.0",
    "gn:asciiname":"Dhunge",
    "gn:country_code":"NP",
    "gn:dem":1069,
    "gn:feature_class":"P",
    "gn:feature_code":"PPLL",
    "gn:name":"Dhunge",
    "gn:population":0,
    "gn:timezone":"Asia/Kathmandu",
    "iso:country":"NP",
    "wof:name":"Dhunge",
    "wof:placetype":"locality"
},
  "geometry": {"coordinates":[83.68643,27.89091],"type":"Point"}
}