{
  "type": "Feature",
  "properties": {
    "gn:admin1_code":"CR",
    "gn:admin2_code":"11",
    "gn:admin3_code":"35.0",
    "gn:admin4_code":"350005.0",
    "gn:asciiname":"Kaparphori",
    "gn:country_code":"NP",
    "gn:dem":192,
    "gn:feature_class":"P",
    "gn:feature_code":"PPLL",
    "gn:name":"Kaparphori",
    "gn:population":0,
    "gn:timezone":"Asia/Kathmandu",
    "iso:country":"NP",
    "wof:name":"Kaparphori",
    "wof:placetype":"locality"
},
  "geometry": {"coordinates":[84.48273,27.63368],"type":"Point"}
}