{
  "type": "Feature",
  "properties": {
    "gn:admin1_code":"ER",
    "gn:admin2_code":"10",
    "gn:admin3_code":"2",
    "gn:admin4_code":"20041",
    "gn:asciiname":"Puwa",
    "gn:country_code":"NP",
    "gn:dem":1100,
    "gn:feature_class":"P",
    "gn:feature_code":"PPLL",
    "gn:name":"Puwa",
    "gn:population":0,
    "gn:timezone":"Asia/Kathmandu",
    "iso:country":"NP",
    "wof:name":"Puwa",
    "wof:placetype":"locality"
},
  "geometry": {"coordinates":[87.66696999999998,27.07576],"type":"Point"}
}