{
  "type": "Feature",
  "properties": {
    "gn:admin1_code":"ER",
    "gn:admin2_code":"13",
    "gn:admin3_code":"11",
    "gn:admin4_code":"110005.0",
    "gn:asciiname":"Rukdokharka",
    "gn:country_code":"NP",
    "gn:dem":2673,
    "gn:feature_class":"P",
    "gn:feature_code":"PPLL",
    "gn:name":"Rukdokharka",
    "gn:population":0,
    "gn:timezone":"Asia/Kathmandu",
    "iso:country":"NP",
    "wof:name":"Rukdokharka",
    "wof:placetype":"locality"
},
  "geometry": {"coordinates":[86.84595,27.56205],"type":"Point"}
}