{
  "type": "Feature",
  "properties": {
    "gn:admin1_code":"MR",
    "gn:admin2_code":"12",
    "gn:admin3_code":"52",
    "gn:admin4_code":"520028",
    "gn:asciiname":"Daphle",
    "gn:country_code":"NP",
    "gn:dem":1068,
    "gn:feature_class":"P",
    "gn:feature_code":"PPLL",
    "gn:name":"Daphle",
    "gn:population":0,
    "gn:timezone":"Asia/Kathmandu",
    "iso:country":"NP",
    "wof:name":"Daphle",
    "wof:placetype":"locality"
},
  "geometry": {"coordinates":[82.9772,28.18938],"type":"Point"}
}