{
  "type": "Feature",
  "properties": {
    "gn:admin1_code":"FR",
    "gn:admin2_code":"14.0",
    "gn:admin3_code":"67.0",
    "gn:admin4_code":"670010.0",
    "gn:asciiname":"Anli",
    "gn:country_code":"NP",
    "gn:dem":2321,
    "gn:feature_class":"P",
    "gn:feature_code":"PPLL",
    "gn:name":"Anli",
    "gn:population":0,
    "gn:timezone":"Asia/Kathmandu",
    "iso:country":"NP",
    "wof:name":"Anli",
    "wof:placetype":"locality"
},
  "geometry": {"coordinates":[81.29576999999998,29.4333],"type":"Point"}
}