{
  "type": "Feature",
  "properties": {
    "gn:admin1_code":"ER",
    "gn:admin2_code":"13",
    "gn:admin3_code":"13",
    "gn:admin4_code":"130061",
    "gn:asciiname":"Mulkharka",
    "gn:country_code":"NP",
    "gn:dem":1905,
    "gn:feature_class":"P",
    "gn:feature_code":"PPLL",
    "gn:name":"Mulkharka",
    "gn:population":0,
    "gn:timezone":"Asia/Kathmandu",
    "iso:country":"NP",
    "wof:name":"Mulkharka",
    "wof:placetype":"locality"
},
  "geometry": {"coordinates":[86.81956,27.37447],"type":"Point"}
}