{
  "type": "Feature",
  "properties": {
    "gn:admin1_code":"FR",
    "gn:admin2_code":"9",
    "gn:admin3_code":"72.0",
    "gn:admin4_code":"720012.0",
    "gn:asciiname":"Bichphanta",
    "gn:country_code":"NP",
    "gn:dem":164,
    "gn:feature_class":"P",
    "gn:feature_code":"PPLL",
    "gn:name":"Bichphanta",
    "gn:population":0,
    "gn:timezone":"Asia/Kathmandu",
    "iso:country":"NP",
    "wof:name":"Bichphanta",
    "wof:placetype":"locality"
},
  "geometry": {"coordinates":[80.51980999999998,28.57002],"type":"Point"}
}