{
  "type": "Feature",
  "properties": {
    "gn:admin1_code":"ER",
    "gn:admin2_code":"7",
    "gn:admin3_code":"7.0",
    "gn:admin4_code":"70006.0",
    "gn:asciiname":"Tamanggaun",
    "gn:country_code":"NP",
    "gn:dem":1586,
    "gn:feature_class":"P",
    "gn:feature_code":"PPLL",
    "gn:name":"Tamanggaun",
    "gn:population":0,
    "gn:timezone":"Asia/Kathmandu",
    "iso:country":"NP",
    "wof:name":"Tamanggaun",
    "wof:placetype":"locality"
},
  "geometry": {"coordinates":[87.35432,27.02789000000001],"type":"Point"}
}