{
  "type": "Feature",
  "properties": {
    "gn:admin1_code":"ER",
    "gn:admin2_code":"13",
    "gn:admin3_code":"11",
    "gn:admin4_code":"110026",
    "gn:asciiname":"Ekrate",
    "gn:country_code":"NP",
    "gn:dem":897,
    "gn:feature_class":"P",
    "gn:feature_code":"PPLL",
    "gn:name":"Ekrate",
    "gn:population":0,
    "gn:timezone":"Asia/Kathmandu",
    "iso:country":"NP",
    "wof:name":"Ekrate",
    "wof:placetype":"locality"
},
  "geometry": {"coordinates":[86.66539,27.36451],"type":"Point"}
}