{
  "type": "Feature",
  "properties": {
    "gn:admin1_code":"ER",
    "gn:admin2_code":"7",
    "gn:admin3_code":"5",
    "gn:admin4_code":"50021",
    "gn:asciiname":"Musarbhitta",
    "gn:country_code":"NP",
    "gn:dem":76,
    "gn:feature_class":"P",
    "gn:feature_code":"PPLL",
    "gn:name":"Musarbhitta",
    "gn:population":0,
    "gn:timezone":"Asia/Kathmandu",
    "iso:country":"NP",
    "wof:name":"Musarbhitta",
    "wof:placetype":"locality"
},
  "geometry": {"coordinates":[87.58343000000001,26.47163],"type":"Point"}
}