{
  "type": "Feature",
  "properties": {
    "gn:admin1_code":"WR",
    "gn:admin2_code":"3",
    "gn:admin3_code":"44",
    "gn:admin4_code":"440037",
    "gn:asciiname":"Thumi",
    "gn:country_code":"NP",
    "gn:dem":972,
    "gn:feature_class":"P",
    "gn:feature_code":"PPLL",
    "gn:name":"Thumi",
    "gn:population":0,
    "gn:timezone":"Asia/Kathmandu",
    "iso:country":"NP",
    "name:ceb_x_preferred":[
        "Thumi"
    ],
    "name:mai_x_preferred":[
        "\u0925\u0941\u092e\u0940"
    ],
    "name:msa_x_preferred":[
        "Thumi"
    ],
    "name:nep_x_preferred":[
        "\u0925\u0941\u092e\u0940"
    ],
    "name:new_x_preferred":[
        "\u0925\u0941\u092e\u0940"
    ],
    "name:pol_x_preferred":[
        "Thumi"
    ],
    "wof:name":"Thumi",
    "wof:placetype":"locality"
},
  "geometry": {"coordinates":[83.66462,28.18511],"type":"Point"}
}