{
  "type": "Feature",
  "properties": {
    "gn:admin1_code":"FR",
    "gn:admin2_code":"9",
    "gn:admin3_code":"74",
    "gn:admin4_code":"740060",
    "gn:asciiname":"Kodekhala",
    "gn:country_code":"NP",
    "gn:dem":1605,
    "gn:feature_class":"P",
    "gn:feature_code":"PPLL",
    "gn:name":"Kodekhala",
    "gn:population":0,
    "gn:timezone":"Asia/Kathmandu",
    "iso:country":"NP",
    "wof:name":"Kodekhala",
    "wof:placetype":"locality"
},
  "geometry": {"coordinates":[80.54629,29.56795],"type":"Point"}
}