{
  "type": "Feature",
  "properties": {
    "gn:admin1_code":"00",
    "gn:asciiname":"Gherabani",
    "gn:country_code":"NP",
    "gn:dem":104,
    "gn:feature_class":"P",
    "gn:feature_code":"PPL",
    "gn:name":"Gher\u0101bani\u0307\u0304",
    "gn:population":0,
    "gn:timezone":"Asia/Kathmandu",
    "iso:country":"NP",
    "name:nep_x_preferred":[
        "Gher\u0101bani\u0307\u0304"
    ],
    "wof:name":"Gherabani",
    "wof:placetype":"locality"
},
  "geometry": {"coordinates":[87.30781,26.62288],"type":"Point"}
}