{
  "type": "Feature",
  "properties": {
    "gn:admin1_code":"FR",
    "gn:admin2_code":"14",
    "gn:admin3_code":"69",
    "gn:admin4_code":"690030",
    "gn:asciiname":"Budhakholagaun",
    "gn:country_code":"NP",
    "gn:dem":1237,
    "gn:feature_class":"P",
    "gn:feature_code":"PPLL",
    "gn:name":"Budhakholagaun",
    "gn:population":0,
    "gn:timezone":"Asia/Kathmandu",
    "iso:country":"NP",
    "wof:name":"Budhakholagaun",
    "wof:placetype":"locality"
},
  "geometry": {"coordinates":[81.22235999999999,28.99151],"type":"Point"}
}