{
  "type": "Feature",
  "properties": {
    "gn:admin1_code":"CR",
    "gn:admin2_code":"1",
    "gn:admin3_code":"29",
    "gn:admin4_code":"290003",
    "gn:asciiname":"Simbu",
    "gn:country_code":"NP",
    "gn:dem":2686,
    "gn:feature_class":"P",
    "gn:feature_code":"PPLL",
    "gn:name":"Simbu",
    "gn:population":0,
    "gn:timezone":"Asia/Kathmandu",
    "iso:country":"NP",
    "wof:name":"Simbu",
    "wof:placetype":"locality"
},
  "geometry": {"coordinates":[85.28015000000001,28.22623],"type":"Point"}
}