{
  "type": "Feature",
  "properties": {
    "gn:admin1_code":"FR",
    "gn:admin2_code":"14",
    "gn:admin3_code":"69.0",
    "gn:admin4_code":"690068.0",
    "gn:asciiname":"Kimtola",
    "gn:country_code":"NP",
    "gn:dem":1842,
    "gn:feature_class":"P",
    "gn:feature_code":"PPLL",
    "gn:name":"Kimtola",
    "gn:population":0,
    "gn:timezone":"Asia/Kathmandu",
    "iso:country":"NP",
    "wof:name":"Kimtola",
    "wof:placetype":"locality"
},
  "geometry": {"coordinates":[81.37971999999998,29.21256],"type":"Point"}
}