{
  "type": "Feature",
  "properties": {
    "gn:admin1_code":"MR",
    "gn:admin2_code":"2",
    "gn:admin3_code":"61.0",
    "gn:admin4_code":"610029.0",
    "gn:asciiname":"Dhar",
    "gn:country_code":"NP",
    "gn:dem":1842,
    "gn:feature_class":"P",
    "gn:feature_code":"PPLL",
    "gn:name":"Dhar",
    "gn:population":0,
    "gn:timezone":"Asia/Kathmandu",
    "iso:country":"NP",
    "wof:name":"Dhar",
    "wof:placetype":"locality"
},
  "geometry": {"coordinates":[82.07705,28.85342],"type":"Point"}
}