{
  "type": "Feature",
  "properties": {
    "gn:admin1_code":"CR",
    "gn:admin2_code":"1",
    "gn:admin3_code":"23",
    "gn:admin4_code":"230038.0",
    "gn:asciiname":"Kiulpati",
    "gn:country_code":"NP",
    "gn:dem":1337,
    "gn:feature_class":"P",
    "gn:feature_code":"PPLL",
    "gn:name":"Kiulpati",
    "gn:population":0,
    "gn:timezone":"Asia/Kathmandu",
    "iso:country":"NP",
    "wof:name":"Kiulpati",
    "wof:placetype":"locality"
},
  "geometry": {"coordinates":[85.56010999999999,27.93038],"type":"Point"}
}