{
  "type": "Feature",
  "properties": {
    "gn:admin1_code":"CR",
    "gn:admin2_code":"1",
    "gn:admin3_code":"24.0",
    "gn:admin4_code":"240049.0",
    "gn:asciiname":"Lapsetar",
    "gn:country_code":"NP",
    "gn:dem":1532,
    "gn:feature_class":"P",
    "gn:feature_code":"PPLL",
    "gn:name":"Lapsetar",
    "gn:population":0,
    "gn:timezone":"Asia/Kathmandu",
    "iso:country":"NP",
    "wof:name":"Lapsetar",
    "wof:placetype":"locality"
},
  "geometry": {"coordinates":[85.47979000000002,27.58965],"type":"Point"}
}