{
  "type": "Feature",
  "properties": {
    "gn:admin1_code":"WR",
    "gn:admin2_code":"8",
    "gn:admin3_code":"49",
    "gn:admin4_code":"490052",
    "gn:asciiname":"Lakhanpara",
    "gn:country_code":"NP",
    "gn:dem":124,
    "gn:feature_class":"P",
    "gn:feature_code":"PPLL",
    "gn:name":"Lakhanpara",
    "gn:population":0,
    "gn:timezone":"Asia/Kathmandu",
    "iso:country":"NP",
    "wof:name":"Lakhanpara",
    "wof:placetype":"locality"
},
  "geometry": {"coordinates":[83.34769,27.67227],"type":"Point"}
}