{
  "type": "Feature",
  "properties": {
    "gn:admin1_code":"WR",
    "gn:admin2_code":"8",
    "gn:admin3_code":"49",
    "gn:admin4_code":"490068",
    "gn:asciiname":"Lodpurwa",
    "gn:country_code":"NP",
    "gn:dem":113,
    "gn:feature_class":"P",
    "gn:feature_code":"PPLL",
    "gn:name":"Lodpurwa",
    "gn:population":0,
    "gn:timezone":"Asia/Kathmandu",
    "iso:country":"NP",
    "wof:name":"Lodpurwa",
    "wof:placetype":"locality"
},
  "geometry": {"coordinates":[83.32767,27.57528],"type":"Point"}
}