{
  "type": "Feature",
  "properties": {
    "gn:admin1_code":"CR",
    "gn:admin2_code":"5",
    "gn:admin3_code":"21",
    "gn:admin4_code":"210002",
    "gn:asciiname":"Banchare",
    "gn:country_code":"NP",
    "gn:dem":1354,
    "gn:feature_class":"P",
    "gn:feature_code":"PPLL",
    "gn:name":"Banchare",
    "gn:population":0,
    "gn:timezone":"Asia/Kathmandu",
    "iso:country":"NP",
    "wof:name":"Banchare",
    "wof:placetype":"locality"
},
  "geometry": {"coordinates":[86.16076,27.5182],"type":"Point"}
}