{
  "type": "Feature",
  "properties": {
    "gn:admin1_code":"CR",
    "gn:admin2_code":"1",
    "gn:admin3_code":"24.0",
    "gn:admin4_code":"240084.0",
    "gn:asciiname":"Tallo Bhalukharka",
    "gn:country_code":"NP",
    "gn:dem":1408,
    "gn:feature_class":"P",
    "gn:feature_code":"PPLL",
    "gn:name":"Tallo Bhalukharka",
    "gn:population":0,
    "gn:timezone":"Asia/Kathmandu",
    "iso:country":"NP",
    "wof:name":"Tallo Bhalukharka",
    "wof:placetype":"locality"
},
  "geometry": {"coordinates":[85.58315999999998,27.54261],"type":"Point"}
}