{
  "type": "Feature",
  "properties": {
    "gn:admin1_code":"FR",
    "gn:admin2_code":"9",
    "gn:admin3_code":"74",
    "gn:admin4_code":"740057",
    "gn:asciiname":"Kudi",
    "gn:country_code":"NP",
    "gn:dem":1934,
    "gn:feature_class":"P",
    "gn:feature_code":"PPLL",
    "gn:name":"Kudi",
    "gn:population":0,
    "gn:timezone":"Asia/Kathmandu",
    "iso:country":"NP",
    "wof:name":"Kudi",
    "wof:placetype":"locality"
},
  "geometry": {"coordinates":[80.71893,29.42486],"type":"Point"}
}