{
  "type": "Feature",
  "properties": {
    "gn:admin1_code":"MR",
    "gn:admin2_code":"2",
    "gn:admin3_code":"60.0",
    "gn:admin4_code":"600007.0",
    "gn:asciiname":"Kalmuda",
    "gn:country_code":"NP",
    "gn:dem":1014,
    "gn:feature_class":"P",
    "gn:feature_code":"PPLL",
    "gn:name":"Kalmuda",
    "gn:population":0,
    "gn:timezone":"Asia/Kathmandu",
    "iso:country":"NP",
    "wof:name":"Kalmuda",
    "wof:placetype":"locality"
},
  "geometry": {"coordinates":[81.62954999999999,28.74764],"type":"Point"}
}