{
  "type": "Feature",
  "properties": {
    "gn:admin1_code":"CR",
    "gn:admin2_code":"5",
    "gn:admin3_code":"20",
    "gn:admin4_code":"200010",
    "gn:asciiname":"Kirate",
    "gn:country_code":"NP",
    "gn:dem":733,
    "gn:feature_class":"P",
    "gn:feature_code":"PPLL",
    "gn:name":"Kirate",
    "gn:population":0,
    "gn:timezone":"Asia/Kathmandu",
    "iso:country":"NP",
    "wof:name":"Kirate",
    "wof:placetype":"locality"
},
  "geometry": {"coordinates":[86.05922,27.1701],"type":"Point"}
}