{
  "type": "Feature",
  "properties": {
    "gn:admin1_code":"WR",
    "gn:admin2_code":"8",
    "gn:admin3_code":"46.0",
    "gn:admin4_code":"460011.0",
    "gn:asciiname":"Dan Chaur",
    "gn:country_code":"NP",
    "gn:dem":902,
    "gn:feature_class":"P",
    "gn:feature_code":"PPLL",
    "gn:name":"Dan Chaur",
    "gn:population":0,
    "gn:timezone":"Asia/Kathmandu",
    "iso:country":"NP",
    "wof:name":"Dan Chaur",
    "wof:placetype":"locality"
},
  "geometry": {"coordinates":[83.2937,28.14857],"type":"Point"}
}