{
  "type": "Feature",
  "properties": {
    "gn:admin1_code":"ER",
    "gn:admin2_code":"7",
    "gn:admin3_code":"5",
    "gn:admin4_code":"50049",
    "gn:asciiname":"Sajbote",
    "gn:country_code":"NP",
    "gn:dem":766,
    "gn:feature_class":"P",
    "gn:feature_code":"PPLL",
    "gn:name":"Sajbote",
    "gn:population":0,
    "gn:timezone":"Asia/Kathmandu",
    "iso:country":"NP",
    "wof:name":"Sajbote",
    "wof:placetype":"locality"
},
  "geometry": {"coordinates":[87.64603000000002,26.81711],"type":"Point"}
}