{
  "type": "Feature",
  "properties": {
    "gn:admin1_code":"FR",
    "gn:admin2_code":"14.0",
    "gn:admin3_code":"67.0",
    "gn:admin4_code":"670002.0",
    "gn:asciiname":"Khopi",
    "gn:country_code":"NP",
    "gn:dem":2425,
    "gn:feature_class":"P",
    "gn:feature_code":"PPLL",
    "gn:name":"Khopi",
    "gn:population":0,
    "gn:timezone":"Asia/Kathmandu",
    "iso:country":"NP",
    "name:bih_x_preferred":[
        "\u0916\u094b\u092a\u0940"
    ],
    "name:ceb_x_preferred":[
        "Khopi"
    ],
    "name:fra_x_preferred":[
        "Khopi"
    ],
    "name:mai_x_preferred":[
        "\u0916\u094b\u092a\u0940"
    ],
    "name:msa_x_preferred":[
        "Khopi"
    ],
    "name:nep_x_preferred":[
        "\u0916\u094b\u092a\u0940"
    ],
    "name:new_x_preferred":[
        "\u0916\u094b\u092a\u0940"
    ],
    "name:pol_x_preferred":[
        "Khopi"
    ],
    "wof:name":"Khopi",
    "wof:placetype":"locality"
},
  "geometry": {"coordinates":[81.68924,29.55014000000001],"type":"Point"}
}