{
  "type": "Feature",
  "properties": {
    "gn:admin1_code":"WR",
    "gn:admin2_code":"4.0",
    "gn:admin3_code":"38.0",
    "gn:admin4_code":"380010.0",
    "gn:asciiname":"Ghaderi",
    "gn:country_code":"NP",
    "gn:dem":625,
    "gn:feature_class":"P",
    "gn:feature_code":"PPLL",
    "gn:name":"Ghaderi",
    "gn:population":0,
    "gn:timezone":"Asia/Kathmandu",
    "iso:country":"NP",
    "wof:name":"Ghaderi",
    "wof:placetype":"locality"
},
  "geometry": {"coordinates":[84.24335000000001,27.8549],"type":"Point"}
}