{
  "type": "Feature",
  "properties": {
    "gn:admin1_code":"FR",
    "gn:admin2_code":"14",
    "gn:admin3_code":"68",
    "gn:admin4_code":"680002",
    "gn:asciiname":"Dhami Lek",
    "gn:country_code":"NP",
    "gn:dem":1507,
    "gn:feature_class":"P",
    "gn:feature_code":"PPLL",
    "gn:name":"Dhami Lek",
    "gn:population":0,
    "gn:timezone":"Asia/Kathmandu",
    "iso:country":"NP",
    "wof:name":"Dhami Lek",
    "wof:placetype":"locality"
},
  "geometry": {"coordinates":[80.97660999999999,29.48468],"type":"Point"}
}