{
  "type": "Feature",
  "properties": {
    "gn:admin1_code":"FR",
    "gn:admin2_code":"14",
    "gn:admin3_code":"71.0",
    "gn:admin4_code":"710011.0",
    "gn:asciiname":"Baskoti",
    "gn:country_code":"NP",
    "gn:dem":168,
    "gn:feature_class":"P",
    "gn:feature_code":"PPLL",
    "gn:name":"Baskoti",
    "gn:population":0,
    "gn:timezone":"Asia/Kathmandu",
    "iso:country":"NP",
    "wof:name":"Baskoti",
    "wof:placetype":"locality"
},
  "geometry": {"coordinates":[81.02906999999998,28.6547],"type":"Point"}
}