{
  "type": "Feature",
  "properties": {
    "gn:admin1_code":"CR",
    "gn:admin2_code":"11",
    "gn:admin3_code":"31",
    "gn:admin4_code":"310022",
    "gn:asciiname":"Boldadanda",
    "gn:country_code":"NP",
    "gn:dem":1052,
    "gn:feature_class":"P",
    "gn:feature_code":"PPLL",
    "gn:name":"Boldadanda",
    "gn:population":0,
    "gn:timezone":"Asia/Kathmandu",
    "iso:country":"NP",
    "wof:name":"Boldadanda",
    "wof:placetype":"locality"
},
  "geometry": {"coordinates":[85.2377,27.47787000000001],"type":"Point"}
}