{
  "type": "Feature",
  "properties": {
    "gn:admin1_code":"WR",
    "gn:admin2_code":"4",
    "gn:admin3_code":"36.0",
    "gn:admin4_code":"360008.0",
    "gn:asciiname":"Jogibesi",
    "gn:country_code":"NP",
    "gn:dem":593,
    "gn:feature_class":"P",
    "gn:feature_code":"PPLL",
    "gn:name":"Jogibesi",
    "gn:population":0,
    "gn:timezone":"Asia/Kathmandu",
    "iso:country":"NP",
    "wof:name":"Jogibesi",
    "wof:placetype":"locality"
},
  "geometry": {"coordinates":[84.50331,27.99342],"type":"Point"}
}