{
  "type": "Feature",
  "properties": {
    "gn:admin1_code":"MR",
    "gn:admin2_code":"12",
    "gn:admin3_code":"56.0",
    "gn:admin4_code":"560005.0",
    "gn:asciiname":"Parsaduwa",
    "gn:country_code":"NP",
    "gn:dem":567,
    "gn:feature_class":"P",
    "gn:feature_code":"PPLL",
    "gn:name":"Parsaduwa",
    "gn:population":0,
    "gn:timezone":"Asia/Kathmandu",
    "iso:country":"NP",
    "wof:name":"Parsaduwa",
    "wof:placetype":"locality"
},
  "geometry": {"coordinates":[82.17891,28.10523],"type":"Point"}
}