{
  "type": "Feature",
  "properties": {
    "gn:admin1_code":"WR",
    "gn:admin2_code":"3",
    "gn:admin3_code":"45.0",
    "gn:admin4_code":"450021.0",
    "gn:asciiname":"Khadkachaur",
    "gn:country_code":"NP",
    "gn:dem":1429,
    "gn:feature_class":"P",
    "gn:feature_code":"PPLL",
    "gn:name":"Khadkachaur",
    "gn:population":0,
    "gn:timezone":"Asia/Kathmandu",
    "iso:country":"NP",
    "wof:name":"Khadkachaur",
    "wof:placetype":"locality"
},
  "geometry": {"coordinates":[83.5646,28.31116],"type":"Point"}
}