{
  "type": "Feature",
  "properties": {
    "gn:admin1_code":"ER",
    "gn:admin2_code":"13",
    "gn:admin3_code":"15",
    "gn:admin4_code":"150018",
    "gn:asciiname":"Durgapur",
    "gn:country_code":"NP",
    "gn:dem":80,
    "gn:feature_class":"P",
    "gn:feature_code":"PPLL",
    "gn:name":"Durgapur",
    "gn:population":0,
    "gn:timezone":"Asia/Kathmandu",
    "iso:country":"NP",
    "name:ben_x_preferred":[
        "\u09a6\u09c1\u09b0\u09cd\u0997\u09be\u09aa\u09c1\u09b0"
    ],
    "name:bih_x_preferred":[
        "\u0926\u0941\u0930\u094d\u0917\u093e\u092a\u0941\u0930"
    ],
    "name:bpy_x_preferred":[
        "\u09a6\u09c1\u09b0\u09cd\u0997\u09be\u09aa\u09c1\u09b0"
    ],
    "name:ceb_x_preferred":[
        "Durg\u0101pur"
    ],
    "name:deu_x_preferred":[
        "Durgapur"
    ],
    "name:ell_x_preferred":[
        "\u039d\u03c4\u03bf\u03c5\u03c1\u03b3\u03ba\u03b1\u03c0\u03bf\u03cd\u03c1"
    ],
    "name:epo_x_preferred":[
        "Durgapur"
    ],
    "name:fas_x_preferred":[
        "\u062f\u0648\u0631\u06af\u0627\u067e\u0648\u0631"
    ],
    "name:fra_x_preferred":[
        "Durgapur"
    ],
    "name:hin_x_preferred":[
        "\u0926\u0941\u0930\u094d\u0917\u093e\u092a\u0941\u0930"
    ],
    "name:hun_x_preferred":[
        "Durg\u00e1pur"
    ],
    "name:ita_x_preferred":[
        "Durgapur"
    ],
    "name:jpn_x_preferred":[
        "\u30c9\u30a5\u30eb\u30ac\u30d7\u30eb"
    ],
    "name:kor_x_preferred":[
        "\ub450\ub974\uac00\ud478\ub974"
    ],
    "name:lit_x_preferred":[
        "Durgapuras"
    ],
    "name:mal_x_preferred":[
        "\u0d26\u0d41\u0d7c\u0d17\u0d3e\u0d2a\u0d42\u0d7c"
    ],
    "name:mar_x_preferred":[
        "\u0926\u0941\u0930\u094d\u0917\u093e\u092a\u0942\u0930"
    ],
    "name:mlg_x_preferred":[
        "Durgapur"
    ],
    "name:nep_x_preferred":[
        "\u0926\u0941\u0930\u094d\u0917\u093e\u092a\u0941\u0930"
    ],
    "name:new_x_preferred":[
        "\u0926\u0941\u0930\u094d\u0917\u093e\u092a\u0941\u0930"
    ],
    "name:nor_x_preferred":[
        "Durgapur"
    ],
    "name:pam_x_preferred":[
        "Durgapur"
    ],
    "name:pnb_x_preferred":[
        "\u062f\u0631\u06af\u0627\u067e\u0648\u0631"
    ],
    "name:pol_x_preferred":[
        "Durgapur"
    ],
    "name:pus_x_preferred":[
        "\u062f\u0648\u0631\u06af\u0627\u067e\u0648\u0631"
    ],
    "name:rus_x_preferred":[
        "\u0414\u0443\u0440\u0433\u0430\u043f\u0443\u0440"
    ],
    "name:spa_x_preferred":[
        "Durgapur"
    ],
    "name:srp_x_preferred":[
        "\u0414\u0443\u0440\u0433\u0430\u043f\u0443\u0440"
    ],
    "name:swe_x_preferred":[
        "Durgapur"
    ],
    "name:tam_x_preferred":[
        "\u0ba4\u0bc1\u0bb0\u0bcd\u0b95\u0bbe\u0baa\u0bc2\u0bb0\u0bcd"
    ],
    "name:urd_x_preferred":[
        "\u062f\u0631\u06af\u0627\u067e\u0648\u0631"
    ],
    "name:uzb_x_preferred":[
        "Durgapur"
    ],
    "name:vie_x_preferred":[
        "Durgapur"
    ],
    "name:war_x_preferred":[
        "Durgapur"
    ],
    "name:zho_x_preferred":[
        "\u675c\u723e\u52a0\u5e03\u723e"
    ],
    "wof:name":"Durgapur",
    "wof:placetype":"locality"
},
  "geometry": {"coordinates":[86.84388,26.53957],"type":"Point"}
}