{
  "type": "Feature",
  "properties": {
    "gn:admin1_code":"MR",
    "gn:admin2_code":"2",
    "gn:admin3_code":"60.0",
    "gn:admin4_code":"600049.0",
    "gn:asciiname":"Deuli",
    "gn:country_code":"NP",
    "gn:dem":2146,
    "gn:feature_class":"P",
    "gn:feature_code":"PPLL",
    "gn:name":"Deuli",
    "gn:population":0,
    "gn:timezone":"Asia/Kathmandu",
    "iso:country":"NP",
    "wof:name":"Deuli",
    "wof:placetype":"locality"
},
  "geometry": {"coordinates":[81.84149000000002,28.85384],"type":"Point"}
}