{
  "type": "Feature",
  "properties": {
    "iso:country":"NP",
    "name:ceb_x_preferred":[
        "K\u0101gbeni"
    ],
    "name:deu_x_preferred":[
        "Kagbeni"
    ],
    "name:dty_x_preferred":[
        "\u0915\u093e\u0917\u092c\u0947\u0928\u0940"
    ],
    "name:eng_x_preferred":[
        "Kagbeni"
    ],
    "name:fra_x_preferred":[
        "Kagbeni"
    ],
    "name:nep_x_preferred":[
        "\u0915\u093e\u0917\u092c\u0947\u0928\u0940"
    ],
    "name:new_x_preferred":[
        "\u0915\u093e\u0917\u092c\u0947\u0928\u0940"
    ],
    "name:nld_x_preferred":[
        "Kagbeni"
    ],
    "name:pol_x_preferred":[
        "Kagbeni"
    ],
    "name:por_x_preferred":[
        "Kagbeni"
    ],
    "name:rus_x_preferred":[
        "\u041a\u0430\u0433\u0431\u0435\u043d\u0438"
    ],
    "qs:gn_country":"NP",
    "qs:gn_fcode":"PPL",
    "qs:gn_pop":0,
    "qs:name":"K\u00e5gbeni",
    "qs:name_adm0":"Nepal",
    "qs:name_adm1":"Pashchimanchal",
    "qs:photos":670,
    "qs:photos_1k":136,
    "qs:photos_9k":3,
    "qs:photos_9r":5,
    "qs:photos_all":670,
    "qs:photos_sr":8,
    "qs:placetype":"Town",
    "qs:pop_sr":"0",
    "qs:woe_adm0":23424911,
    "wof:name":"K\u00e5gbeni",
    "wof:placetype":"locality"
},
  "geometry": {"coordinates":[83.79809,28.84485],"type":"Point"}
}