{
  "type": "Feature",
  "properties": {
    "gn:admin1_code":"FR",
    "gn:admin2_code":"14",
    "gn:admin3_code":"71.0",
    "gn:admin4_code":"710038.0",
    "gn:asciiname":"Maitetad",
    "gn:country_code":"NP",
    "gn:dem":691,
    "gn:feature_class":"P",
    "gn:feature_code":"PPLL",
    "gn:name":"Maitetad",
    "gn:population":0,
    "gn:timezone":"Asia/Kathmandu",
    "iso:country":"NP",
    "wof:name":"Maitetad",
    "wof:placetype":"locality"
},
  "geometry": {"coordinates":[80.58988000000002,28.97472],"type":"Point"}
}