{
  "type": "Feature",
  "properties": {
    "gn:admin1_code":"WR",
    "gn:admin2_code":"3",
    "gn:admin3_code":"43",
    "gn:admin4_code":"430040",
    "gn:asciiname":"Nauni Bagar",
    "gn:country_code":"NP",
    "gn:dem":1429,
    "gn:feature_class":"P",
    "gn:feature_code":"PPLL",
    "gn:name":"Nauni Bagar",
    "gn:population":0,
    "gn:timezone":"Asia/Kathmandu",
    "iso:country":"NP",
    "wof:name":"Nauni Bagar",
    "wof:placetype":"locality"
},
  "geometry": {"coordinates":[83.64678000000001,28.48887],"type":"Point"}
}