{
  "type": "Feature",
  "properties": {
    "gn:admin1_code":"MR",
    "gn:admin2_code":"12",
    "gn:admin3_code":"54",
    "gn:admin4_code":"540032",
    "gn:asciiname":"Salli Bisauna",
    "gn:country_code":"NP",
    "gn:dem":1566,
    "gn:feature_class":"P",
    "gn:feature_code":"PPLL",
    "gn:name":"Salli Bisauna",
    "gn:population":0,
    "gn:timezone":"Asia/Kathmandu",
    "iso:country":"NP",
    "wof:name":"Salli Bisauna",
    "wof:placetype":"locality"
},
  "geometry": {"coordinates":[82.69391999999998,28.67906],"type":"Point"}
}