{
  "type": "Feature",
  "properties": {
    "gn:admin1_code":"ER",
    "gn:admin2_code":"10",
    "gn:admin3_code":"4.0",
    "gn:admin4_code":"40018.0",
    "gn:asciiname":"Rangapur",
    "gn:country_code":"NP",
    "gn:dem":107,
    "gn:feature_class":"P",
    "gn:feature_code":"PPLL",
    "gn:name":"Rangapur",
    "gn:population":0,
    "gn:timezone":"Asia/Kathmandu",
    "iso:country":"NP",
    "name:pol_x_preferred":[
        "Rangapur"
    ],
    "wof:name":"Rangapur",
    "wof:placetype":"locality"
},
  "geometry": {"coordinates":[87.70393,26.58915],"type":"Point"}
}