{
  "type": "Feature",
  "properties": {
    "gn:admin1_code":"MR",
    "gn:admin2_code":"12",
    "gn:admin3_code":"52",
    "gn:admin4_code":"520019",
    "gn:asciiname":"Chhabise",
    "gn:country_code":"NP",
    "gn:dem":738,
    "gn:feature_class":"P",
    "gn:feature_code":"PPLL",
    "gn:name":"Chhabise",
    "gn:population":0,
    "gn:timezone":"Asia/Kathmandu",
    "iso:country":"NP",
    "wof:name":"Chhabise",
    "wof:placetype":"locality"
},
  "geometry": {"coordinates":[82.80937,27.94794000000001],"type":"Point"}
}