{
  "type": "Feature",
  "properties": {
    "gn:admin1_code":"MR",
    "gn:admin2_code":"12",
    "gn:admin3_code":"53",
    "gn:admin4_code":"530042",
    "gn:asciiname":"Dokadung",
    "gn:country_code":"NP",
    "gn:dem":1804,
    "gn:feature_class":"P",
    "gn:feature_code":"PPLL",
    "gn:name":"Dokadung",
    "gn:population":0,
    "gn:timezone":"Asia/Kathmandu",
    "iso:country":"NP",
    "wof:name":"Dokadung",
    "wof:placetype":"locality"
},
  "geometry": {"coordinates":[82.79517,28.39187],"type":"Point"}
}