{
  "type": "Feature",
  "properties": {
    "gn:admin1_code":"00",
    "gn:asciiname":"Beteni",
    "gn:country_code":"NP",
    "gn:dem":956,
    "gn:feature_class":"P",
    "gn:feature_code":"PPL",
    "gn:name":"Beteni\u0307\u0304",
    "gn:population":0,
    "gn:timezone":"Asia/Kathmandu",
    "iso:country":"NP",
    "name:mai_x_preferred":[
        "\u092c\u0947\u0924\u093f\u0928\u0940"
    ],
    "name:msa_x_preferred":[
        "Beteni"
    ],
    "name:nep_x_preferred":[
        "Beteni\u0307\u0304"
    ],
    "name:pol_x_preferred":[
        "Beteni"
    ],
    "wof:name":"Beteni",
    "wof:placetype":"locality"
},
  "geometry": {"coordinates":[81.8866,28.36487],"type":"Point"}
}