{
  "type": "Feature",
  "properties": {
    "gn:admin1_code":"00",
    "gn:asciiname":"Kyuola Bhanjyan",
    "gn:country_code":"NP",
    "gn:dem":3472,
    "gn:feature_class":"P",
    "gn:feature_code":"PPL",
    "gn:name":"Kyuol\u0101 Bha\u00f1jy\u0101\u1e45",
    "gn:population":0,
    "gn:timezone":"Asia/Kathmandu",
    "iso:country":"NP",
    "name:nep_x_preferred":[
        "Kyuol\u0101 Bha\u00f1jy\u0101\u1e45"
    ],
    "wof:name":"Kyuola Bhanjyan",
    "wof:placetype":"locality"
},
  "geometry": {"coordinates":[85.49292,27.97258],"type":"Point"}
}