{
  "type": "Feature",
  "properties": {
    "gn:admin1_code":"CR",
    "gn:admin2_code":"5",
    "gn:admin3_code":"19",
    "gn:admin4_code":"190085",
    "gn:asciiname":"Rohuwa",
    "gn:country_code":"NP",
    "gn:dem":81,
    "gn:feature_class":"P",
    "gn:feature_code":"PPLL",
    "gn:name":"Rohuwa",
    "gn:population":0,
    "gn:timezone":"Asia/Kathmandu",
    "iso:country":"NP",
    "name:ceb_x_preferred":[
        "Rohuwa"
    ],
    "name:fra_x_preferred":[
        "Rohuwa"
    ],
    "name:mai_x_preferred":[
        "\u0930\u094b\u0939\u0941\u0935\u093e"
    ],
    "name:nep_x_preferred":[
        "\u0930\u094b\u0939\u0941\u0935\u093e"
    ],
    "name:new_x_preferred":[
        "\u0930\u094b\u0939\u0941\u0935\u093e"
    ],
    "name:pol_x_preferred":[
        "Rohuwa"
    ],
    "wof:name":"Rohuwa",
    "wof:placetype":"locality"
},
  "geometry": {"coordinates":[85.42534999999999,26.8392],"type":"Point"}
}