{
  "type": "Feature",
  "properties": {
    "gn:admin1_code":"WR",
    "gn:admin2_code":"4",
    "gn:admin3_code":"36.0",
    "gn:admin4_code":"360005.0",
    "gn:asciiname":"Magargaun",
    "gn:country_code":"NP",
    "gn:dem":948,
    "gn:feature_class":"P",
    "gn:feature_code":"PPLL",
    "gn:name":"Magargaun",
    "gn:population":0,
    "gn:timezone":"Asia/Kathmandu",
    "iso:country":"NP",
    "wof:name":"Magargaun",
    "wof:placetype":"locality"
},
  "geometry": {"coordinates":[84.71512,28.01479],"type":"Point"}
}