{
  "type": "Feature",
  "properties": {
    "gn:admin1_code":"MR",
    "gn:admin2_code":"2",
    "gn:admin3_code":"61.0",
    "gn:admin4_code":"610023.0",
    "gn:asciiname":"Rungara",
    "gn:country_code":"NP",
    "gn:dem":1921,
    "gn:feature_class":"P",
    "gn:feature_code":"PPLL",
    "gn:name":"Rungara",
    "gn:population":0,
    "gn:timezone":"Asia/Kathmandu",
    "iso:country":"NP",
    "wof:name":"Rungara",
    "wof:placetype":"locality"
},
  "geometry": {"coordinates":[82.25147,28.93099],"type":"Point"}
}