{
  "type": "Feature",
  "properties": {
    "gn:admin1_code":"00",
    "gn:asciiname":"Gojagau",
    "gn:country_code":"NP",
    "gn:dem":142,
    "gn:feature_class":"P",
    "gn:feature_code":"PPL",
    "gn:name":"Goj\u0101g\u0101\u0169",
    "gn:population":0,
    "gn:timezone":"Asia/Kathmandu",
    "iso:country":"NP",
    "name:nep_x_preferred":[
        "Goj\u0101g\u0101\u0169"
    ],
    "wof:name":"Gojagau",
    "wof:placetype":"locality"
},
  "geometry": {"coordinates":[88.09175,26.67373],"type":"Point"}
}