{
  "type": "Feature",
  "properties": {
    "gn:admin1_code":"FR",
    "gn:admin2_code":"9",
    "gn:admin3_code":"74",
    "gn:admin4_code":"740057",
    "gn:asciiname":"Basar",
    "gn:country_code":"NP",
    "gn:dem":1330,
    "gn:feature_class":"P",
    "gn:feature_code":"PPLL",
    "gn:name":"Basar",
    "gn:population":0,
    "gn:timezone":"Asia/Kathmandu",
    "iso:country":"NP",
    "name:ceb_x_preferred":[
        "Basar"
    ],
    "name:deu_x_preferred":[
        "Basar"
    ],
    "name:pol_x_preferred":[
        "Bazar"
    ],
    "name:swe_x_preferred":[
        "Basar"
    ],
    "name:ukr_x_preferred":[
        "\u0411\u0430\u0437\u0430\u0440"
    ],
    "wof:name":"Basar",
    "wof:placetype":"locality"
},
  "geometry": {"coordinates":[80.77346,29.43308],"type":"Point"}
}