{
  "type": "Feature",
  "properties": {
    "gn:admin1_code":"ER",
    "gn:admin2_code":"10",
    "gn:admin3_code":"4.0",
    "gn:admin4_code":"40017.0",
    "gn:asciiname":"Aasiram",
    "gn:country_code":"NP",
    "gn:dem":103,
    "gn:feature_class":"P",
    "gn:feature_code":"PPLL",
    "gn:name":"Aasiram",
    "gn:population":0,
    "gn:timezone":"Asia/Kathmandu",
    "iso:country":"NP",
    "wof:name":"Aasiram",
    "wof:placetype":"locality"
},
  "geometry": {"coordinates":[88.02944000000002,26.58128],"type":"Point"}
}