{
  "type": "Feature",
  "properties": {
    "gn:admin1_code":"CR",
    "gn:admin2_code":"1",
    "gn:admin3_code":"30.0",
    "gn:admin4_code":"300038.0",
    "gn:asciiname":"Managi Bhanjyang",
    "gn:country_code":"NP",
    "gn:dem":2867,
    "gn:feature_class":"P",
    "gn:feature_code":"PPLL",
    "gn:name":"Managi Bhanjyang",
    "gn:population":0,
    "gn:timezone":"Asia/Kathmandu",
    "iso:country":"NP",
    "wof:name":"Managi Bhanjyang",
    "wof:placetype":"locality"
},
  "geometry": {"coordinates":[84.96448000000002,28.1569],"type":"Point"}
}