{
  "type": "Feature",
  "properties": {
    "gn:admin1_code":"WR",
    "gn:admin2_code":"4",
    "gn:admin3_code":"36.0",
    "gn:admin4_code":"360053.0",
    "gn:asciiname":"Kalibote",
    "gn:country_code":"NP",
    "gn:dem":958,
    "gn:feature_class":"P",
    "gn:feature_code":"PPLL",
    "gn:name":"Kalibote",
    "gn:population":0,
    "gn:timezone":"Asia/Kathmandu",
    "iso:country":"NP",
    "wof:name":"Kalibote",
    "wof:placetype":"locality"
},
  "geometry": {"coordinates":[84.70314,28.14252],"type":"Point"}
}