{
  "type": "Feature",
  "properties": {
    "gn:admin1_code":"WR",
    "gn:admin2_code":"3",
    "gn:admin3_code":"45.0",
    "gn:admin4_code":"450046.0",
    "gn:asciiname":"Pallo Kholagaun",
    "gn:country_code":"NP",
    "gn:dem":1479,
    "gn:feature_class":"P",
    "gn:feature_code":"PPLL",
    "gn:name":"Pallo Kholagaun",
    "gn:population":0,
    "gn:timezone":"Asia/Kathmandu",
    "iso:country":"NP",
    "wof:name":"Pallo Kholagaun",
    "wof:placetype":"locality"
},
  "geometry": {"coordinates":[83.34361,28.2459],"type":"Point"}
}