{
  "type": "Feature",
  "properties": {
    "gn:admin1_code":"ER",
    "gn:admin2_code":"10",
    "gn:admin3_code":"3.0",
    "gn:admin4_code":"30040.0",
    "gn:asciiname":"Samalbung",
    "gn:country_code":"NP",
    "gn:dem":1504,
    "gn:feature_class":"P",
    "gn:feature_code":"PPLL",
    "gn:name":"Samalbung",
    "gn:population":0,
    "gn:timezone":"Asia/Kathmandu",
    "iso:country":"NP",
    "name:bih_x_preferred":[
        "\u0938\u092e\u093e\u0932\u092c\u0941\u0919"
    ],
    "name:mai_x_preferred":[
        "\u0938\u092e\u093e\u0932\u092c\u0941\u0919"
    ],
    "name:msa_x_preferred":[
        "Samalpung"
    ],
    "name:nep_x_preferred":[
        "\u0938\u092e\u093e\u0932\u092c\u0941\u0919"
    ],
    "name:nld_x_preferred":[
        "Samalpung"
    ],
    "name:pol_x_preferred":[
        "Samalbung"
    ],
    "wof:name":"Samalbung",
    "wof:placetype":"locality"
},
  "geometry": {"coordinates":[88.1504,26.86984],"type":"Point"}
}