{
  "type": "Feature",
  "properties": {
    "gn:admin1_code":"FR",
    "gn:admin2_code":"14",
    "gn:admin3_code":"70.0",
    "gn:admin4_code":"700031.0",
    "gn:asciiname":"Dokat",
    "gn:country_code":"NP",
    "gn:dem":1777,
    "gn:feature_class":"P",
    "gn:feature_code":"PPLL",
    "gn:name":"Dokat",
    "gn:population":0,
    "gn:timezone":"Asia/Kathmandu",
    "iso:country":"NP",
    "wof:name":"Dokat",
    "wof:placetype":"locality"
},
  "geometry": {"coordinates":[80.85293,29.33563],"type":"Point"}
}