{
  "type": "Feature",
  "properties": {
    "gn:admin1_code":"ER",
    "gn:admin2_code":"13",
    "gn:admin3_code":"11",
    "gn:admin4_code":"110032",
    "gn:asciiname":"Ghhirdi",
    "gn:country_code":"NP",
    "gn:dem":1491,
    "gn:feature_class":"P",
    "gn:feature_code":"PPLL",
    "gn:name":"Ghhirdi",
    "gn:population":0,
    "gn:timezone":"Asia/Kathmandu",
    "iso:country":"NP",
    "wof:name":"Ghhirdi",
    "wof:placetype":"locality"
},
  "geometry": {"coordinates":[86.67726999999999,27.5952],"type":"Point"}
}