{
  "type": "Feature",
  "properties": {
    "gn:admin1_code":"ER",
    "gn:admin2_code":"7.0",
    "gn:admin3_code":"6.0",
    "gn:admin4_code":"60011.0",
    "gn:asciiname":"Dhanpuri",
    "gn:country_code":"NP",
    "gn:dem":107,
    "gn:feature_class":"P",
    "gn:feature_code":"PPLL",
    "gn:name":"Dhanpuri",
    "gn:population":0,
    "gn:timezone":"Asia/Kathmandu",
    "iso:country":"NP",
    "name:ben_x_preferred":[
        "\u09a7\u09a8\u09aa\u09c1\u09b0\u09bf"
    ],
    "name:bpy_x_preferred":[
        "\u09a7\u09a8\u09aa\u09c1\u09b0\u09bf"
    ],
    "name:ind_x_preferred":[
        "Dhanpuri"
    ],
    "name:ita_x_preferred":[
        "Dhanpuri"
    ],
    "name:msa_x_preferred":[
        "Dhanpuri"
    ],
    "name:new_x_preferred":[
        "\u0927\u0928\u092a\u0941\u0930\u0940"
    ],
    "name:por_x_preferred":[
        "Dhanpuri"
    ],
    "name:spa_x_preferred":[
        "Dhanpuri"
    ],
    "name:swe_x_preferred":[
        "Dhanpuri"
    ],
    "name:vie_x_preferred":[
        "Dhanpuri"
    ],
    "name:zho_x_preferred":[
        "\u4e39\u666e\u91cc"
    ],
    "wof:name":"Dhanpuri",
    "wof:placetype":"locality"
},
  "geometry": {"coordinates":[87.18199,26.73529000000001],"type":"Point"}
}