{
  "type": "Feature",
  "properties": {
    "gn:admin1_code":"ER",
    "gn:admin2_code":"7",
    "gn:admin3_code":"7.0",
    "gn:admin4_code":"70036.0",
    "gn:asciiname":"Anpbote",
    "gn:country_code":"NP",
    "gn:dem":625,
    "gn:feature_class":"P",
    "gn:feature_code":"PPLL",
    "gn:name":"Anpbote",
    "gn:population":0,
    "gn:timezone":"Asia/Kathmandu",
    "iso:country":"NP",
    "wof:name":"Anpbote",
    "wof:placetype":"locality"
},
  "geometry": {"coordinates":[87.33575999999999,26.87898],"type":"Point"}
}