{
  "type": "Feature",
  "properties": {
    "gn:admin1_code":"ER",
    "gn:admin2_code":"7",
    "gn:admin3_code":"9",
    "gn:admin4_code":"90011",
    "gn:asciiname":"Terse",
    "gn:country_code":"NP",
    "gn:dem":2011,
    "gn:feature_class":"P",
    "gn:feature_code":"PPLL",
    "gn:name":"Terse",
    "gn:population":0,
    "gn:timezone":"Asia/Kathmandu",
    "iso:country":"NP",
    "wof:name":"Terse",
    "wof:placetype":"locality"
},
  "geometry": {"coordinates":[87.35788000000002,27.37045],"type":"Point"}
}