{
  "type": "Feature",
  "properties": {
    "gn:admin1_code":"00",
    "gn:asciiname":"Madibun",
    "gn:country_code":"NP",
    "gn:dem":1234,
    "gn:feature_class":"P",
    "gn:feature_code":"PPL",
    "gn:name":"M\u0101dibu\u1e45",
    "gn:population":0,
    "gn:timezone":"Asia/Kathmandu",
    "iso:country":"NP",
    "name:nep_x_preferred":[
        "M\u0101dibu\u1e45"
    ],
    "wof:name":"Madibun",
    "wof:placetype":"locality"
},
  "geometry": {"coordinates":[87.58573,26.98],"type":"Point"}
}