{
  "type": "Feature",
  "properties": {
    "gn:admin1_code":"CR",
    "gn:admin2_code":"11",
    "gn:admin3_code":"32",
    "gn:admin4_code":"320069",
    "gn:asciiname":"Bhiman",
    "gn:country_code":"NP",
    "gn:dem":140,
    "gn:feature_class":"P",
    "gn:feature_code":"PPLL",
    "gn:name":"Bhiman",
    "gn:population":0,
    "gn:timezone":"Asia/Kathmandu",
    "iso:country":"NP",
    "wof:name":"Bhiman",
    "wof:placetype":"locality"
},
  "geometry": {"coordinates":[85.5035,27.1655],"type":"Point"}
}