{
  "type": "Feature",
  "properties": {
    "gn:admin1_code":"CR",
    "gn:admin2_code":"1",
    "gn:admin3_code":"28",
    "gn:admin4_code":"280001",
    "gn:asciiname":"Barmedanda",
    "gn:country_code":"NP",
    "gn:dem":1151,
    "gn:feature_class":"P",
    "gn:feature_code":"PPLL",
    "gn:name":"Barmedanda",
    "gn:population":0,
    "gn:timezone":"Asia/Kathmandu",
    "iso:country":"NP",
    "wof:name":"Barmedanda",
    "wof:placetype":"locality"
},
  "geometry": {"coordinates":[85.21095,27.93946],"type":"Point"}
}