{
  "type": "Feature",
  "properties": {
    "gn:admin1_code":"WR",
    "gn:admin2_code":"4",
    "gn:admin3_code":"36.0",
    "gn:admin4_code":"360031.0",
    "gn:asciiname":"Phinamtar",
    "gn:country_code":"NP",
    "gn:dem":917,
    "gn:feature_class":"P",
    "gn:feature_code":"PPLL",
    "gn:name":"Phinamtar",
    "gn:population":0,
    "gn:timezone":"Asia/Kathmandu",
    "iso:country":"NP",
    "wof:name":"Phinamtar",
    "wof:placetype":"locality"
},
  "geometry": {"coordinates":[84.64173000000002,28.11741],"type":"Point"}
}