{
  "type": "Feature",
  "properties": {
    "gn:admin1_code":"ER",
    "gn:admin2_code":"10",
    "gn:admin3_code":"2",
    "gn:admin4_code":"20006",
    "gn:asciiname":"Bardanda",
    "gn:country_code":"NP",
    "gn:dem":1488,
    "gn:feature_class":"P",
    "gn:feature_code":"PPLL",
    "gn:name":"Bardanda",
    "gn:population":0,
    "gn:timezone":"Asia/Kathmandu",
    "iso:country":"NP",
    "wof:name":"Bardanda",
    "wof:placetype":"locality"
},
  "geometry": {"coordinates":[87.76838000000002,27.02925],"type":"Point"}
}