{
  "type": "Feature",
  "properties": {
    "gn:admin1_code":"MR",
    "gn:admin2_code":"2",
    "gn:admin3_code":"60.0",
    "gn:admin4_code":"600039.0",
    "gn:asciiname":"Rapat",
    "gn:country_code":"NP",
    "gn:dem":1381,
    "gn:feature_class":"P",
    "gn:feature_code":"PPLL",
    "gn:name":"Rapat",
    "gn:population":0,
    "gn:timezone":"Asia/Kathmandu",
    "iso:country":"NP",
    "wof:name":"Rapat",
    "wof:placetype":"locality"
},
  "geometry": {"coordinates":[81.8283,28.92698],"type":"Point"}
}