{
  "type": "Feature",
  "properties": {
    "gn:admin1_code":"WR",
    "gn:admin2_code":"8",
    "gn:admin3_code":"51.0",
    "gn:admin4_code":"510028.0",
    "gn:asciiname":"Maidan",
    "gn:country_code":"NP",
    "gn:dem":1140,
    "gn:feature_class":"P",
    "gn:feature_code":"PPLL",
    "gn:name":"Maidan",
    "gn:population":0,
    "gn:timezone":"Asia/Kathmandu",
    "iso:country":"NP",
    "name:ara_x_preferred":[
        "\u0627\u0644\u0645\u064a\u062f\u0627\u0646"
    ],
    "name:ceb_x_preferred":[
        "Maidan"
    ],
    "name:est_x_preferred":[
        "Maidan"
    ],
    "name:fas_x_preferred":[
        "\u0645\u06cc\u062f\u0627\u0646"
    ],
    "name:fra_x_preferred":[
        "Ma\u00efdan"
    ],
    "name:hye_x_preferred":[
        "\u0544\u0561\u0575\u0564\u0561\u0576"
    ],
    "name:ita_x_preferred":[
        "Maidan"
    ],
    "name:por_x_preferred":[
        "Maidan"
    ],
    "name:spa_x_preferred":[
        "Maid\u00e1n"
    ],
    "name:swe_x_preferred":[
        "Maidan"
    ],
    "wof:name":"Maidan",
    "wof:placetype":"locality"
},
  "geometry": {"coordinates":[83.23820000000001,27.90243],"type":"Point"}
}