{
  "type": "Feature",
  "properties": {
    "gn:admin1_code":"CR",
    "gn:admin2_code":"5",
    "gn:admin3_code":"22.0",
    "gn:admin4_code":"220029.0",
    "gn:asciiname":"Lamakari",
    "gn:country_code":"NP",
    "gn:dem":1716,
    "gn:feature_class":"P",
    "gn:feature_code":"PPLL",
    "gn:name":"Lamakari",
    "gn:population":0,
    "gn:timezone":"Asia/Kathmandu",
    "iso:country":"NP",
    "wof:name":"Lamakari",
    "wof:placetype":"locality"
},
  "geometry": {"coordinates":[86.2137,27.7704],"type":"Point"}
}