{
  "type": "Feature",
  "properties": {
    "gn:admin1_code":"CR",
    "gn:admin2_code":"11.0",
    "gn:admin3_code":"33.0",
    "gn:admin4_code":"330075.0",
    "gn:asciiname":"Beheri",
    "gn:country_code":"NP",
    "gn:dem":130,
    "gn:feature_class":"P",
    "gn:feature_code":"PPLL",
    "gn:name":"Beheri",
    "gn:population":0,
    "gn:timezone":"Asia/Kathmandu",
    "iso:country":"NP",
    "wof:name":"Beheri",
    "wof:placetype":"locality"
},
  "geometry": {"coordinates":[84.99776,27.14639],"type":"Point"}
}