{
  "type": "Feature",
  "properties": {
    "gn:admin1_code":"FR",
    "gn:admin2_code":"14.0",
    "gn:admin3_code":"67.0",
    "gn:admin4_code":"670026.0",
    "gn:asciiname":"Bigari",
    "gn:country_code":"NP",
    "gn:dem":2021,
    "gn:feature_class":"P",
    "gn:feature_code":"PPLL",
    "gn:name":"Bigari",
    "gn:population":0,
    "gn:timezone":"Asia/Kathmandu",
    "iso:country":"NP",
    "wof:name":"Bigari",
    "wof:placetype":"locality"
},
  "geometry": {"coordinates":[81.74519000000002,29.37679],"type":"Point"}
}