{
  "type": "Feature",
  "properties": {
    "gn:admin1_code":"00",
    "gn:asciiname":"Bhata",
    "gn:country_code":"NP",
    "gn:dem":206,
    "gn:feature_class":"P",
    "gn:feature_code":"PPL",
    "gn:name":"Bh\u0101\u1e6d\u0101",
    "gn:population":0,
    "gn:timezone":"Asia/Kathmandu",
    "iso:country":"NP",
    "name:fas_x_preferred":[
        "\u0628\u0647\u0627\u062a\u0627"
    ],
    "name:nep_x_preferred":[
        "Bh\u0101\u1e6d\u0101"
    ],
    "name:pnb_x_preferred":[
        "\u0628\u06be\u0627\u0679\u0627"
    ],
    "name:und_x_variant":[
        "Bh\u0101ta"
    ],
    "name:urd_x_preferred":[
        "\u0628\u06be\u0627\u0679\u0627"
    ],
    "wof:name":"Bhata",
    "wof:placetype":"locality"
},
  "geometry": {"coordinates":[84.77682,27.31022],"type":"Point"}
}