{
  "type": "Feature",
  "properties": {
    "gn:admin1_code":"MR",
    "gn:admin2_code":"12",
    "gn:admin3_code":"53",
    "gn:admin4_code":"530002",
    "gn:asciiname":"Garpa",
    "gn:country_code":"NP",
    "gn:dem":1316,
    "gn:feature_class":"P",
    "gn:feature_code":"PPLL",
    "gn:name":"Garpa",
    "gn:population":0,
    "gn:timezone":"Asia/Kathmandu",
    "iso:country":"NP",
    "wof:name":"Garpa",
    "wof:placetype":"locality"
},
  "geometry": {"coordinates":[82.62891,28.3249],"type":"Point"}
}