{
  "type": "Feature",
  "properties": {
    "gn:admin1_code":"CR",
    "gn:admin2_code":"11",
    "gn:admin3_code":"35.0",
    "gn:admin4_code":"350036.0",
    "gn:asciiname":"Hanumannagar",
    "gn:country_code":"NP",
    "gn:dem":186,
    "gn:feature_class":"P",
    "gn:feature_code":"PPLL",
    "gn:name":"Hanumannagar",
    "gn:population":0,
    "gn:timezone":"Asia/Kathmandu",
    "iso:country":"NP",
    "wof:name":"Hanumannagar",
    "wof:placetype":"locality"
},
  "geometry": {"coordinates":[84.35035000000001,27.60547],"type":"Point"}
}