{
  "type": "Feature",
  "properties": {
    "gn:admin1_code":"ER",
    "gn:admin2_code":"7.0",
    "gn:admin3_code":"6.0",
    "gn:admin4_code":"60019.0",
    "gn:asciiname":"Bikrampur",
    "gn:country_code":"NP",
    "gn:dem":73,
    "gn:feature_class":"P",
    "gn:feature_code":"PPLL",
    "gn:name":"Bikrampur",
    "gn:population":0,
    "gn:timezone":"Asia/Kathmandu",
    "iso:country":"NP",
    "name:ben_x_preferred":[
        "\u09ac\u09bf\u0995\u09cd\u09b0\u09ae\u09aa\u09c1\u09b0"
    ],
    "name:cat_x_preferred":[
        "Bikrampur"
    ],
    "name:epo_x_preferred":[
        "Bikrampur"
    ],
    "wof:name":"Bikrampur",
    "wof:placetype":"locality"
},
  "geometry": {"coordinates":[87.10814000000001,26.44667],"type":"Point"}
}