{
  "type": "Feature",
  "properties": {
    "gn:admin1_code":"ER",
    "gn:admin2_code":"10.0",
    "gn:admin3_code":"1.0",
    "gn:admin4_code":"10044.0",
    "gn:asciiname":"Khesewa",
    "gn:country_code":"NP",
    "gn:dem":1666,
    "gn:feature_class":"P",
    "gn:feature_code":"PPLL",
    "gn:name":"Khesewa",
    "gn:population":0,
    "gn:timezone":"Asia/Kathmandu",
    "iso:country":"NP",
    "wof:name":"Khesewa",
    "wof:placetype":"locality"
},
  "geometry": {"coordinates":[87.82731,27.38229],"type":"Point"}
}