{
  "type": "Feature",
  "properties": {
    "gn:admin1_code":"WR",
    "gn:admin2_code":"8",
    "gn:admin3_code":"46.0",
    "gn:admin4_code":"460015.0",
    "gn:asciiname":"Botegaun",
    "gn:country_code":"NP",
    "gn:dem":611,
    "gn:feature_class":"P",
    "gn:feature_code":"PPLL",
    "gn:name":"Botegaun",
    "gn:population":0,
    "gn:timezone":"Asia/Kathmandu",
    "iso:country":"NP",
    "wof:name":"Botegaun",
    "wof:placetype":"locality"
},
  "geometry": {"coordinates":[83.42536,28.02269],"type":"Point"}
}