{
  "type": "Feature",
  "properties": {
    "gn:admin1_code":"WR",
    "gn:admin2_code":"8",
    "gn:admin3_code":"49",
    "gn:admin4_code":"490029",
    "gn:asciiname":"Chhotki Bangai",
    "gn:country_code":"NP",
    "gn:dem":107,
    "gn:feature_class":"P",
    "gn:feature_code":"PPLL",
    "gn:name":"Chhotki Bangai",
    "gn:population":0,
    "gn:timezone":"Asia/Kathmandu",
    "iso:country":"NP",
    "wof:name":"Chhotki Bangai",
    "wof:placetype":"locality"
},
  "geometry": {"coordinates":[83.39731,27.51369],"type":"Point"}
}