{
  "type": "Feature",
  "properties": {
    "gn:admin1_code":"FR",
    "gn:admin2_code":"9",
    "gn:admin3_code":"75.0",
    "gn:admin4_code":"750035.0",
    "gn:asciiname":"Kainoda",
    "gn:country_code":"NP",
    "gn:dem":1423,
    "gn:feature_class":"P",
    "gn:feature_code":"PPLL",
    "gn:name":"Kainoda",
    "gn:population":0,
    "gn:timezone":"Asia/Kathmandu",
    "iso:country":"NP",
    "wof:name":"Kainoda",
    "wof:placetype":"locality"
},
  "geometry": {"coordinates":[80.45480000000001,29.65518],"type":"Point"}
}