{
  "type": "Feature",
  "properties": {
    "gn:admin1_code":"MR",
    "gn:admin2_code":"12",
    "gn:admin3_code":"56.0",
    "gn:admin4_code":"560032.0",
    "gn:asciiname":"Kanariya",
    "gn:country_code":"NP",
    "gn:dem":593,
    "gn:feature_class":"P",
    "gn:feature_code":"PPLL",
    "gn:name":"Kanariya",
    "gn:population":0,
    "gn:timezone":"Asia/Kathmandu",
    "iso:country":"NP",
    "wof:name":"Kanariya",
    "wof:placetype":"locality"
},
  "geometry": {"coordinates":[82.39505,28.00279],"type":"Point"}
}