{
  "type": "Feature",
  "properties": {
    "gn:admin1_code":"ER",
    "gn:admin2_code":"13",
    "gn:admin3_code":"12",
    "gn:admin4_code":"120029",
    "gn:asciiname":"Mathillo Richuwa",
    "gn:country_code":"NP",
    "gn:dem":954,
    "gn:feature_class":"P",
    "gn:feature_code":"PPLL",
    "gn:name":"Mathillo Richuwa",
    "gn:population":0,
    "gn:timezone":"Asia/Kathmandu",
    "iso:country":"NP",
    "wof:name":"Mathillo Richuwa",
    "wof:placetype":"locality"
},
  "geometry": {"coordinates":[86.46139000000002,27.19043],"type":"Point"}
}