{
  "type": "Feature",
  "properties": {
    "gn:admin1_code":"MR",
    "gn:admin2_code":"2",
    "gn:admin3_code":"60.0",
    "gn:admin4_code":"600021.0",
    "gn:asciiname":"Sisne",
    "gn:country_code":"NP",
    "gn:dem":1525,
    "gn:feature_class":"P",
    "gn:feature_code":"PPLL",
    "gn:name":"Sisne",
    "gn:population":0,
    "gn:timezone":"Asia/Kathmandu",
    "iso:country":"NP",
    "wof:name":"Sisne",
    "wof:placetype":"locality"
},
  "geometry": {"coordinates":[81.64149,28.80867000000001],"type":"Point"}
}