{
  "type": "Feature",
  "properties": {
    "gn:admin1_code":"ER",
    "gn:admin2_code":"10",
    "gn:admin3_code":"4.0",
    "gn:admin4_code":"40021.0",
    "gn:asciiname":"Jhantutol",
    "gn:country_code":"NP",
    "gn:dem":76,
    "gn:feature_class":"P",
    "gn:feature_code":"PPLL",
    "gn:name":"Jhantutol",
    "gn:population":0,
    "gn:timezone":"Asia/Kathmandu",
    "iso:country":"NP",
    "wof:name":"Jhantutol",
    "wof:placetype":"locality"
},
  "geometry": {"coordinates":[87.93116999999999,26.42412],"type":"Point"}
}