{
  "type": "Feature",
  "properties": {
    "gn:admin1_code":"CR",
    "gn:admin2_code":"11",
    "gn:admin3_code":"31",
    "gn:admin4_code":"310043",
    "gn:asciiname":"Phirkegaun",
    "gn:country_code":"NP",
    "gn:dem":1050,
    "gn:feature_class":"P",
    "gn:feature_code":"PPLL",
    "gn:name":"Phirkegaun",
    "gn:population":0,
    "gn:timezone":"Asia/Kathmandu",
    "iso:country":"NP",
    "wof:name":"Phirkegaun",
    "wof:placetype":"locality"
},
  "geometry": {"coordinates":[85.2381,27.43465],"type":"Point"}
}