{
  "type": "Feature",
  "properties": {
    "gn:admin1_code":"MR",
    "gn:admin2_code":"12",
    "gn:admin3_code":"52",
    "gn:admin4_code":"520023",
    "gn:asciiname":"Khairakot",
    "gn:country_code":"NP",
    "gn:dem":1357,
    "gn:feature_class":"P",
    "gn:feature_code":"PPLL",
    "gn:name":"Khairakot",
    "gn:population":0,
    "gn:timezone":"Asia/Kathmandu",
    "iso:country":"NP",
    "wof:name":"Khairakot",
    "wof:placetype":"locality"
},
  "geometry": {"coordinates":[82.84702,28.07435],"type":"Point"}
}