{
  "type": "Feature",
  "properties": {
    "gn:admin1_code":"WR",
    "gn:admin2_code":"8",
    "gn:admin3_code":"46.0",
    "gn:admin4_code":"460074.0",
    "gn:asciiname":"Khani Gaun",
    "gn:country_code":"NP",
    "gn:dem":1601,
    "gn:feature_class":"P",
    "gn:feature_code":"PPLL",
    "gn:name":"Khani Gaun",
    "gn:population":0,
    "gn:timezone":"Asia/Kathmandu",
    "iso:country":"NP",
    "wof:name":"Khani Gaun",
    "wof:placetype":"locality"
},
  "geometry": {"coordinates":[83.25353,28.0702],"type":"Point"}
}