{
  "type": "Feature",
  "properties": {
    "gn:admin1_code":"ER",
    "gn:admin2_code":"7",
    "gn:admin3_code":"5",
    "gn:admin4_code":"50045",
    "gn:asciiname":"Deviganjtol",
    "gn:country_code":"NP",
    "gn:dem":131,
    "gn:feature_class":"P",
    "gn:feature_code":"PPLL",
    "gn:name":"Deviganjtol",
    "gn:population":0,
    "gn:timezone":"Asia/Kathmandu",
    "iso:country":"NP",
    "wof:name":"Deviganjtol",
    "wof:placetype":"locality"
},
  "geometry": {"coordinates":[87.57826999999997,26.65157],"type":"Point"}
}