{
  "type": "Feature",
  "properties": {
    "gn:admin1_code":"00",
    "gn:asciiname":"Devigani",
    "gn:country_code":"NP",
    "gn:dem":78,
    "gn:feature_class":"P",
    "gn:feature_code":"PPL",
    "gn:name":"Devi\u0307\u0304ga\u00f1i",
    "gn:population":0,
    "gn:timezone":"Asia/Kathmandu",
    "iso:country":"NP",
    "name:nep_x_preferred":[
        "Devi\u0307\u0304ga\u00f1i"
    ],
    "wof:name":"Devigani",
    "wof:placetype":"locality"
},
  "geometry": {"coordinates":[87.70984,26.4439],"type":"Point"}
}