{
  "type": "Feature",
  "properties": {
    "gn:admin1_code":"MR",
    "gn:admin2_code":"12",
    "gn:admin3_code":"53",
    "gn:admin4_code":"530026",
    "gn:asciiname":"Kaphalpani",
    "gn:country_code":"NP",
    "gn:dem":1931,
    "gn:feature_class":"P",
    "gn:feature_code":"PPLL",
    "gn:name":"Kaphalpani",
    "gn:population":0,
    "gn:timezone":"Asia/Kathmandu",
    "iso:country":"NP",
    "wof:name":"Kaphalpani",
    "wof:placetype":"locality"
},
  "geometry": {"coordinates":[82.65989999999999,28.27631],"type":"Point"}
}