{
  "type": "Feature",
  "properties": {
    "gn:admin1_code":"CR",
    "gn:admin2_code":"5",
    "gn:admin3_code":"20",
    "gn:admin4_code":"200032",
    "gn:asciiname":"Chakmake",
    "gn:country_code":"NP",
    "gn:dem":586,
    "gn:feature_class":"P",
    "gn:feature_code":"PPLL",
    "gn:name":"Chakmake",
    "gn:population":0,
    "gn:timezone":"Asia/Kathmandu",
    "iso:country":"NP",
    "wof:name":"Chakmake",
    "wof:placetype":"locality"
},
  "geometry": {"coordinates":[86.15541999999998,27.11349],"type":"Point"}
}