{
  "type": "Feature",
  "properties": {
    "gn:admin1_code":"MR",
    "gn:admin2_code":"12",
    "gn:admin3_code":"54",
    "gn:admin4_code":"540018",
    "gn:asciiname":"Neta",
    "gn:country_code":"NP",
    "gn:dem":2268,
    "gn:feature_class":"P",
    "gn:feature_code":"PPLL",
    "gn:name":"Neta",
    "gn:population":0,
    "gn:timezone":"Asia/Kathmandu",
    "iso:country":"NP",
    "name:ceb_x_preferred":[
        "Neta"
    ],
    "name:deu_x_preferred":[
        "Neta"
    ],
    "name:fra_x_preferred":[
        "Neta"
    ],
    "name:swe_x_preferred":[
        "Neta"
    ],
    "wof:name":"Neta",
    "wof:placetype":"locality"
},
  "geometry": {"coordinates":[82.70735999999999,28.56456],"type":"Point"}
}