{
  "type": "Feature",
  "properties": {
    "gn:admin1_code":"00",
    "gn:asciiname":"Munge",
    "gn:country_code":"NP",
    "gn:dem":942,
    "gn:feature_class":"P",
    "gn:feature_code":"PPL",
    "gn:name":"Munge",
    "gn:population":0,
    "gn:timezone":"Asia/Kathmandu",
    "iso:country":"NP",
    "wof:name":"Munge",
    "wof:placetype":"locality"
},
  "geometry": {"coordinates":[84.55728000000001,28.10318],"type":"Point"}
}