{
  "type": "Feature",
  "properties": {
    "iso:country":"NP",
    "name:und_x_variant":[
        "Shivaraj"
    ],
    "qs:gn_country":"NP",
    "qs:gn_fcode":"ADM3",
    "qs:gn_pop":530419,
    "qs:name":"Kapilvastu",
    "qs:name_adm0":"Nepal",
    "qs:name_adm1":"Pashchimanchal",
    "qs:photos":5,
    "qs:photos_1k":1,
    "qs:photos_9k":1,
    "qs:photos_9r":3,
    "qs:photos_all":126,
    "qs:photos_sr":1,
    "qs:placetype":"LocalAdmin",
    "qs:pop_sr":"11",
    "qs:woe_adm0":23424911,
    "wof:name":"Kapilvastu",
    "wof:placetype":"localadmin",
    "wof:population":530419
},
  "geometry": {"coordinates":[82.91667,27.66667],"type":"Point"}
}