{
  "type": "Feature",
  "properties": {
    "gn:admin1_code":"MR",
    "gn:admin2_code":"2",
    "gn:admin3_code":"60.0",
    "gn:admin4_code":"600035.0",
    "gn:asciiname":"Thaludanda",
    "gn:country_code":"NP",
    "gn:dem":1302,
    "gn:feature_class":"P",
    "gn:feature_code":"PPLL",
    "gn:name":"Thaludanda",
    "gn:population":0,
    "gn:timezone":"Asia/Kathmandu",
    "iso:country":"NP",
    "wof:name":"Thaludanda",
    "wof:placetype":"locality"
},
  "geometry": {"coordinates":[81.71223000000001,28.82604000000001],"type":"Point"}
}