{
  "type": "Feature",
  "properties": {
    "gn:admin1_code":"CR",
    "gn:admin2_code":"11.0",
    "gn:admin3_code":"33.0",
    "gn:admin4_code":"330073.0",
    "gn:asciiname":"Pathara",
    "gn:country_code":"NP",
    "gn:dem":91,
    "gn:feature_class":"P",
    "gn:feature_code":"PPLL",
    "gn:name":"Pathara",
    "gn:population":0,
    "gn:timezone":"Asia/Kathmandu",
    "iso:country":"NP",
    "wof:name":"Pathara",
    "wof:placetype":"locality"
},
  "geometry": {"coordinates":[85.11993000000002,26.9678],"type":"Point"}
}