{
  "type": "Feature",
  "properties": {
    "gn:admin1_code":"WR",
    "gn:admin2_code":"8",
    "gn:admin3_code":"50.0",
    "gn:admin4_code":"500041.0",
    "gn:asciiname":"Pharena",
    "gn:country_code":"NP",
    "gn:dem":120,
    "gn:feature_class":"P",
    "gn:feature_code":"PPLL",
    "gn:name":"Pharena",
    "gn:population":0,
    "gn:timezone":"Asia/Kathmandu",
    "iso:country":"NP",
    "name:ceb_x_preferred":[
        "Farena"
    ],
    "name:mai_x_preferred":[
        "\u092b\u0930\u0947\u0928\u093e"
    ],
    "name:msa_x_preferred":[
        "Farena"
    ],
    "name:nep_x_preferred":[
        "\u092b\u0930\u0947\u0928\u093e"
    ],
    "name:new_x_preferred":[
        "\u092b\u0930\u0947\u0928\u093e"
    ],
    "name:pol_x_preferred":[
        "Farena"
    ],
    "wof:name":"Pharena",
    "wof:placetype":"locality"
},
  "geometry": {"coordinates":[82.78278,27.61367000000001],"type":"Point"}
}