{
  "type": "Feature",
  "properties": {
    "gn:admin1_code":"CR",
    "gn:admin2_code":"5",
    "gn:admin3_code":"17.0",
    "gn:admin4_code":"170067.0",
    "gn:asciiname":"Belauni",
    "gn:country_code":"NP",
    "gn:dem":82,
    "gn:feature_class":"P",
    "gn:feature_code":"PPLL",
    "gn:name":"Belauni",
    "gn:population":0,
    "gn:timezone":"Asia/Kathmandu",
    "iso:country":"NP",
    "wof:name":"Belauni",
    "wof:placetype":"locality"
},
  "geometry": {"coordinates":[85.9666,26.73598],"type":"Point"}
}