{
  "type": "Feature",
  "properties": {
    "gn:admin1_code":"CR",
    "gn:admin2_code":"5",
    "gn:admin3_code":"22.0",
    "gn:admin4_code":"220030.0",
    "gn:asciiname":"Kutisyau",
    "gn:country_code":"NP",
    "gn:dem":1340,
    "gn:feature_class":"P",
    "gn:feature_code":"PPLL",
    "gn:name":"Kutisyau",
    "gn:population":0,
    "gn:timezone":"Asia/Kathmandu",
    "iso:country":"NP",
    "wof:name":"Kutisyau",
    "wof:placetype":"locality"
},
  "geometry": {"coordinates":[86.1088,27.79281],"type":"Point"}
}