{
  "type": "Feature",
  "properties": {
    "gn:admin1_code":"FR",
    "gn:admin2_code":"9",
    "gn:admin3_code":"73.0",
    "gn:admin4_code":"730002.0",
    "gn:asciiname":"Bhadikholagaun",
    "gn:country_code":"NP",
    "gn:dem":1016,
    "gn:feature_class":"P",
    "gn:feature_code":"PPLL",
    "gn:name":"Bhadikholagaun",
    "gn:population":0,
    "gn:timezone":"Asia/Kathmandu",
    "iso:country":"NP",
    "wof:name":"Bhadikholagaun",
    "wof:placetype":"locality"
},
  "geometry": {"coordinates":[80.50154000000001,29.07206],"type":"Point"}
}