{
  "type": "Feature",
  "properties": {
    "gn:admin1_code":"FR",
    "gn:admin2_code":"9",
    "gn:admin3_code":"73.0",
    "gn:admin4_code":"730013.0",
    "gn:asciiname":"Ghumtigada",
    "gn:country_code":"NP",
    "gn:dem":424,
    "gn:feature_class":"P",
    "gn:feature_code":"PPLL",
    "gn:name":"Ghumtigada",
    "gn:population":0,
    "gn:timezone":"Asia/Kathmandu",
    "iso:country":"NP",
    "wof:name":"Ghumtigada",
    "wof:placetype":"locality"
},
  "geometry": {"coordinates":[80.25176,29.09013],"type":"Point"}
}