{
  "type": "Feature",
  "properties": {
    "gn:admin1_code":"ER",
    "gn:admin2_code":"13",
    "gn:admin3_code":"12",
    "gn:admin4_code":"120003",
    "gn:asciiname":"Debuwaghat",
    "gn:country_code":"NP",
    "gn:dem":553,
    "gn:feature_class":"P",
    "gn:feature_code":"PPLL",
    "gn:name":"Debuwaghat",
    "gn:population":0,
    "gn:timezone":"Asia/Kathmandu",
    "iso:country":"NP",
    "wof:name":"Debuwaghat",
    "wof:placetype":"locality"
},
  "geometry": {"coordinates":[86.35106999999998,27.20493],"type":"Point"}
}