{
  "type": "Feature",
  "properties": {
    "gn:admin1_code":"WR",
    "gn:admin2_code":"4.0",
    "gn:admin3_code":"38.0",
    "gn:admin4_code":"380019.0",
    "gn:asciiname":"Dharapani",
    "gn:country_code":"NP",
    "gn:dem":623,
    "gn:feature_class":"P",
    "gn:feature_code":"PPLL",
    "gn:name":"Dharapani",
    "gn:population":0,
    "gn:timezone":"Asia/Kathmandu",
    "iso:country":"NP",
    "wof:name":"Dharapani",
    "wof:placetype":"locality"
},
  "geometry": {"coordinates":[84.06469,28.02629],"type":"Point"}
}