{
  "type": "Feature",
  "properties": {
    "gn:admin1_code":"FR",
    "gn:admin2_code":"14",
    "gn:admin3_code":"70.0",
    "gn:admin4_code":"700024.0",
    "gn:asciiname":"Kotannjar",
    "gn:country_code":"NP",
    "gn:dem":1431,
    "gn:feature_class":"P",
    "gn:feature_code":"PPLL",
    "gn:name":"Kotannjar",
    "gn:population":0,
    "gn:timezone":"Asia/Kathmandu",
    "iso:country":"NP",
    "wof:name":"Kotannjar",
    "wof:placetype":"locality"
},
  "geometry": {"coordinates":[80.88132,29.31839],"type":"Point"}
}