{
  "type": "Feature",
  "properties": {
    "gn:admin1_code":"MR",
    "gn:admin2_code":"2",
    "gn:admin3_code":"60.0",
    "gn:admin4_code":"600053.0",
    "gn:asciiname":"Baskoti",
    "gn:country_code":"NP",
    "gn:dem":1572,
    "gn:feature_class":"P",
    "gn:feature_code":"PPLL",
    "gn:name":"Baskoti",
    "gn:population":0,
    "gn:timezone":"Asia/Kathmandu",
    "iso:country":"NP",
    "wof:name":"Baskoti",
    "wof:placetype":"locality"
},
  "geometry": {"coordinates":[81.50095999999998,29.04205],"type":"Point"}
}