{
  "type": "Feature",
  "properties": {
    "gn:admin1_code":"WR",
    "gn:admin2_code":"3",
    "gn:admin3_code":"45",
    "gn:admin4_code":"450057",
    "gn:asciiname":"Majh Kateri",
    "gn:country_code":"NP",
    "gn:dem":2458,
    "gn:feature_class":"P",
    "gn:feature_code":"PPLL",
    "gn:name":"Majh Kateri",
    "gn:population":0,
    "gn:timezone":"Asia/Kathmandu",
    "iso:country":"NP",
    "wof:name":"Majh Kateri",
    "wof:placetype":"locality"
},
  "geometry": {"coordinates":[83.08438000000002,28.38248],"type":"Point"}
}