{
  "type": "Feature",
  "properties": {
    "gn:admin1_code":"FR",
    "gn:admin2_code":"14",
    "gn:admin3_code":"69.0",
    "gn:admin4_code":"690003.0",
    "gn:asciiname":"Chhap",
    "gn:country_code":"NP",
    "gn:dem":1223,
    "gn:feature_class":"P",
    "gn:feature_code":"PPLL",
    "gn:name":"Chhap",
    "gn:population":0,
    "gn:timezone":"Asia/Kathmandu",
    "iso:country":"NP",
    "name:ceb_x_preferred":[
        "Chhap"
    ],
    "name:fra_x_preferred":[
        "Chhap"
    ],
    "name:mai_x_preferred":[
        "\u091b\u093e\u092a"
    ],
    "name:msa_x_preferred":[
        "Chhap"
    ],
    "name:nep_x_preferred":[
        "\u091b\u093e\u092a"
    ],
    "name:new_x_preferred":[
        "\u091b\u093e\u092a"
    ],
    "name:pol_x_preferred":[
        "Chhap"
    ],
    "wof:name":"Chhap",
    "wof:placetype":"locality"
},
  "geometry": {"coordinates":[81.32666,29.15139000000001],"type":"Point"}
}