{
  "type": "Feature",
  "properties": {
    "gn:admin1_code":"CR",
    "gn:admin2_code":"1",
    "gn:admin3_code":"30.0",
    "gn:admin4_code":"300014.0",
    "gn:asciiname":"Mankhu Halthum",
    "gn:country_code":"NP",
    "gn:dem":984,
    "gn:feature_class":"P",
    "gn:feature_code":"PPLL",
    "gn:name":"Mankhu Halthum",
    "gn:population":0,
    "gn:timezone":"Asia/Kathmandu",
    "iso:country":"NP",
    "wof:name":"Mankhu Halthum",
    "wof:placetype":"locality"
},
  "geometry": {"coordinates":[85.05767,27.76994],"type":"Point"}
}