{
  "type": "Feature",
  "properties": {
    "gn:admin1_code":"MR",
    "gn:admin2_code":"12",
    "gn:admin3_code":"53",
    "gn:admin4_code":"530010",
    "gn:asciiname":"Jarbang",
    "gn:country_code":"NP",
    "gn:dem":2006,
    "gn:feature_class":"P",
    "gn:feature_code":"PPLL",
    "gn:name":"Jarbang",
    "gn:population":0,
    "gn:timezone":"Asia/Kathmandu",
    "iso:country":"NP",
    "wof:name":"Jarbang",
    "wof:placetype":"locality"
},
  "geometry": {"coordinates":[82.86049,28.36648],"type":"Point"}
}