{
  "type": "Feature",
  "properties": {
    "gn:admin1_code":"ER",
    "gn:admin2_code":"13",
    "gn:admin3_code":"16",
    "gn:admin4_code":"160062.0",
    "gn:asciiname":"Lagadigoth",
    "gn:country_code":"NP",
    "gn:dem":72,
    "gn:feature_class":"P",
    "gn:feature_code":"PPLL",
    "gn:name":"Lagadigoth",
    "gn:population":0,
    "gn:timezone":"Asia/Kathmandu",
    "iso:country":"NP",
    "wof:name":"Lagadigoth",
    "wof:placetype":"locality"
},
  "geometry": {"coordinates":[86.21321,26.60117],"type":"Point"}
}