{
  "type": "Feature",
  "properties": {
    "gn:admin1_code":"ER",
    "gn:admin2_code":"13",
    "gn:admin3_code":"16",
    "gn:admin4_code":"160062.0",
    "gn:asciiname":"Lagadigoth",
    "gn:country_code":"NP",
    "gn:dem":72,
    "gn:feature_class":"P",
    "gn:feature_code":"PPLL",
    "gn:name":"Lagadigoth",
    "gn:population":0,
    "gn:timezone":"Asia/Kathmandu",
    "iso:country":"NP",
    "name:bih_x_preferred":[
        "\u0932\u0917\u0921\u0940 \u0917\u094b\u0920"
    ],
    "name:dty_x_preferred":[
        "\u0932\u0917\u0921\u0940 \u0917\u094b\u0920"
    ],
    "name:mai_x_preferred":[
        "\u0932\u0917\u0921\u0940 \u0917\u094b\u0920"
    ],
    "name:msa_x_preferred":[
        "Lagadigoth"
    ],
    "name:nep_x_preferred":[
        "\u0932\u0917\u0921\u0940 \u0917\u094b\u0920"
    ],
    "name:pol_x_preferred":[
        "Lagadigodh"
    ],
    "name:urd_x_preferred":[
        "\u0644\u0627\u06af\u0627\u0688\u06cc\u06af\u0648\u0679\u06c1"
    ],
    "wof:name":"Lagadigoth",
    "wof:placetype":"locality"
},
  "geometry": {"coordinates":[86.21321,26.60117],"type":"Point"}
}