{
  "type": "Feature",
  "properties": {
    "gn:admin1_code":"MR",
    "gn:admin2_code":"2.0",
    "gn:admin3_code":"58.0",
    "gn:admin4_code":"580022.0",
    "gn:asciiname":"Satgharuwa",
    "gn:country_code":"NP",
    "gn:dem":170,
    "gn:feature_class":"P",
    "gn:feature_code":"PPLL",
    "gn:name":"Satgharuwa",
    "gn:population":0,
    "gn:timezone":"Asia/Kathmandu",
    "iso:country":"NP",
    "wof:name":"Satgharuwa",
    "wof:placetype":"locality"
},
  "geometry": {"coordinates":[81.30911,28.45688],"type":"Point"}
}