{
  "type": "Feature",
  "properties": {
    "gn:admin1_code":"CR",
    "gn:admin2_code":"1",
    "gn:admin3_code":"28",
    "gn:admin4_code":"280044",
    "gn:asciiname":"Chhapthok",
    "gn:country_code":"NP",
    "gn:dem":1062,
    "gn:feature_class":"P",
    "gn:feature_code":"PPLL",
    "gn:name":"Chhapthok",
    "gn:population":0,
    "gn:timezone":"Asia/Kathmandu",
    "iso:country":"NP",
    "wof:name":"Chhapthok",
    "wof:placetype":"locality"
},
  "geometry": {"coordinates":[85.33835999999999,27.93166],"type":"Point"}
}