{
  "type": "Feature",
  "properties": {
    "gn:admin1_code":"CR",
    "gn:admin2_code":"5",
    "gn:admin3_code":"21",
    "gn:admin4_code":"210037",
    "gn:asciiname":"Chitre",
    "gn:country_code":"NP",
    "gn:dem":1999,
    "gn:feature_class":"P",
    "gn:feature_code":"PPLL",
    "gn:name":"Chitre",
    "gn:population":0,
    "gn:timezone":"Asia/Kathmandu",
    "iso:country":"NP",
    "wof:name":"Chitre",
    "wof:placetype":"locality"
},
  "geometry": {"coordinates":[86.17811,27.47125],"type":"Point"}
}