{
  "type": "Feature",
  "properties": {
    "gn:admin1_code":"00",
    "gn:asciiname":"Gidarahi",
    "gn:country_code":"NP",
    "gn:dem":120,
    "gn:feature_class":"P",
    "gn:feature_code":"PPL",
    "gn:name":"Gidar\u0101hi\u0307\u0304",
    "gn:population":0,
    "gn:timezone":"Asia/Kathmandu",
    "iso:country":"NP",
    "name:nep_x_preferred":[
        "Gidar\u0101hi\u0307\u0304"
    ],
    "wof:name":"Gidarahi",
    "wof:placetype":"locality"
},
  "geometry": {"coordinates":[86.59586999999998,26.64106],"type":"Point"}
}