{
  "type": "Feature",
  "properties": {
    "gn:admin1_code":"ER",
    "gn:admin2_code":"7.0",
    "gn:admin3_code":"6.0",
    "gn:admin4_code":"60020.0",
    "gn:asciiname":"Duhabi",
    "gn:country_code":"NP",
    "gn:dem":92,
    "gn:feature_class":"P",
    "gn:feature_code":"PPLL",
    "gn:name":"Duhabi",
    "gn:population":0,
    "gn:timezone":"Asia/Kathmandu",
    "iso:country":"NP",
    "name:nep_x_preferred":[
        "\u0926\u0941\u0939\u093e\u092c\u0940"
    ],
    "name:new_x_preferred":[
        "\u0926\u0941\u0939\u093e\u092c\u0940"
    ],
    "name:pol_x_preferred":[
        "Duhabi"
    ],
    "wof:name":"Duhabi",
    "wof:placetype":"locality"
},
  "geometry": {"coordinates":[87.28567,26.5737],"type":"Point"}
}