{
  "type": "Feature",
  "properties": {
    "gn:admin1_code":"CR",
    "gn:admin2_code":"1",
    "gn:admin3_code":"24.0",
    "gn:admin4_code":"240005.0",
    "gn:asciiname":"Bisaunidanda",
    "gn:country_code":"NP",
    "gn:dem":1387,
    "gn:feature_class":"P",
    "gn:feature_code":"PPLL",
    "gn:name":"Bisaunidanda",
    "gn:population":0,
    "gn:timezone":"Asia/Kathmandu",
    "iso:country":"NP",
    "wof:name":"Bisaunidanda",
    "wof:placetype":"locality"
},
  "geometry": {"coordinates":[85.68131,27.37567],"type":"Point"}
}