{
  "type": "Feature",
  "properties": {
    "gn:admin1_code":"CR",
    "gn:admin2_code":"11",
    "gn:admin3_code":"35.0",
    "gn:admin4_code":"350024.0",
    "gn:asciiname":"Ghaletar",
    "gn:country_code":"NP",
    "gn:dem":830,
    "gn:feature_class":"P",
    "gn:feature_code":"PPLL",
    "gn:name":"Ghaletar",
    "gn:population":0,
    "gn:timezone":"Asia/Kathmandu",
    "iso:country":"NP",
    "wof:name":"Ghaletar",
    "wof:placetype":"locality"
},
  "geometry": {"coordinates":[84.74028,27.67321],"type":"Point"}
}