{
  "type": "Feature",
  "properties": {
    "gn:admin1_code":"MR",
    "gn:admin2_code":"2",
    "gn:admin3_code":"61.0",
    "gn:admin4_code":"610027.0",
    "gn:asciiname":"Takura",
    "gn:country_code":"NP",
    "gn:dem":948,
    "gn:feature_class":"P",
    "gn:feature_code":"PPLL",
    "gn:name":"Takura",
    "gn:population":0,
    "gn:timezone":"Asia/Kathmandu",
    "iso:country":"NP",
    "name:por_x_preferred":[
        "Takura Tendayi"
    ],
    "name:slk_x_preferred":[
        "Takura"
    ],
    "wof:name":"Takura",
    "wof:placetype":"locality"
},
  "geometry": {"coordinates":[81.93178,28.68099],"type":"Point"}
}