{
  "type": "Feature",
  "properties": {
    "gn:admin1_code":"WR",
    "gn:admin2_code":"8",
    "gn:admin3_code":"47",
    "gn:admin4_code":"470050",
    "gn:asciiname":"Sejugaun",
    "gn:country_code":"NP",
    "gn:dem":582,
    "gn:feature_class":"P",
    "gn:feature_code":"PPLL",
    "gn:name":"Sejugaun",
    "gn:population":0,
    "gn:timezone":"Asia/Kathmandu",
    "iso:country":"NP",
    "wof:name":"Sejugaun",
    "wof:placetype":"locality"
},
  "geometry": {"coordinates":[83.66342,27.88774],"type":"Point"}
}