{
  "type": "Feature",
  "properties": {
    "gn:admin1_code":"ER",
    "gn:admin2_code":"7.0",
    "gn:admin3_code":"8.0",
    "gn:admin4_code":"80004.0",
    "gn:asciiname":"Khaireni",
    "gn:country_code":"NP",
    "gn:dem":549,
    "gn:feature_class":"P",
    "gn:feature_code":"PPLL",
    "gn:name":"Khaireni",
    "gn:population":0,
    "gn:timezone":"Asia/Kathmandu",
    "iso:country":"NP",
    "wof:name":"Khaireni",
    "wof:placetype":"locality"
},
  "geometry": {"coordinates":[87.73815999999999,27.19997],"type":"Point"}
}