{
  "type": "Feature",
  "properties": {
    "gn:admin1_code":"FR",
    "gn:admin2_code":"14",
    "gn:admin3_code":"69",
    "gn:admin4_code":"690076",
    "gn:asciiname":"Kuti",
    "gn:country_code":"NP",
    "gn:dem":3148,
    "gn:feature_class":"P",
    "gn:feature_code":"PPLL",
    "gn:name":"Kuti",
    "gn:population":0,
    "gn:timezone":"Asia/Kathmandu",
    "iso:country":"NP",
    "name:bos_x_preferred":[
        "Kuti"
    ],
    "name:ceb_x_preferred":[
        "Kuti"
    ],
    "name:deu_x_preferred":[
        "Kuti"
    ],
    "name:fra_x_preferred":[
        "Kuti"
    ],
    "name:hrv_x_preferred":[
        "Kuti"
    ],
    "name:pol_x_preferred":[
        "Kuti"
    ],
    "name:rus_x_preferred":[
        "\u041a\u0443\u0442\u0438"
    ],
    "name:slv_x_preferred":[
        "Kuti"
    ],
    "name:srp_x_preferred":[
        "\u041a\u0443\u0442\u0438"
    ],
    "name:swe_x_preferred":[
        "Kuti"
    ],
    "wof:name":"Kuti",
    "wof:placetype":"locality"
},
  "geometry": {"coordinates":[81.15719,29.3645],"type":"Point"}
}