{
  "type": "Feature",
  "properties": {
    "gn:admin1_code":"CR",
    "gn:admin2_code":"5",
    "gn:admin3_code":"22.0",
    "gn:admin4_code":"220026.0",
    "gn:asciiname":"Khatrigaun",
    "gn:country_code":"NP",
    "gn:dem":1701,
    "gn:feature_class":"P",
    "gn:feature_code":"PPLL",
    "gn:name":"Khatrigaun",
    "gn:population":0,
    "gn:timezone":"Asia/Kathmandu",
    "iso:country":"NP",
    "wof:name":"Khatrigaun",
    "wof:placetype":"locality"
},
  "geometry": {"coordinates":[86.13755,27.63793],"type":"Point"}
}