{
  "type": "Feature",
  "properties": {
    "gn:admin1_code":"MR",
    "gn:admin2_code":"2",
    "gn:admin3_code":"60.0",
    "gn:admin4_code":"600018.0",
    "gn:asciiname":"Aaltigaira",
    "gn:country_code":"NP",
    "gn:dem":1542,
    "gn:feature_class":"P",
    "gn:feature_code":"PPLL",
    "gn:name":"Aaltigaira",
    "gn:population":0,
    "gn:timezone":"Asia/Kathmandu",
    "iso:country":"NP",
    "wof:name":"Aaltigaira",
    "wof:placetype":"locality"
},
  "geometry": {"coordinates":[81.69870999999998,28.70314],"type":"Point"}
}