{
  "type": "Feature",
  "properties": {
    "gn:admin1_code":"WR",
    "gn:admin2_code":"8",
    "gn:admin3_code":"47",
    "gn:admin4_code":"470045",
    "gn:asciiname":"Jhirbas",
    "gn:country_code":"NP",
    "gn:dem":893,
    "gn:feature_class":"P",
    "gn:feature_code":"PPLL",
    "gn:name":"Jhirbas",
    "gn:population":0,
    "gn:timezone":"Asia/Kathmandu",
    "iso:country":"NP",
    "wof:name":"Jhirbas",
    "wof:placetype":"locality"
},
  "geometry": {"coordinates":[83.47526999999999,27.81452],"type":"Point"}
}