{
  "type": "Feature",
  "properties": {
    "gn:admin1_code":"ER",
    "gn:admin2_code":"7",
    "gn:admin3_code":"7.0",
    "gn:admin4_code":"70018.0",
    "gn:asciiname":"Dhikure",
    "gn:country_code":"NP",
    "gn:dem":1056,
    "gn:feature_class":"P",
    "gn:feature_code":"PPLL",
    "gn:name":"Dhikure",
    "gn:population":0,
    "gn:timezone":"Asia/Kathmandu",
    "iso:country":"NP",
    "wof:name":"Dhikure",
    "wof:placetype":"locality"
},
  "geometry": {"coordinates":[87.27251,27.082],"type":"Point"}
}