{
  "type": "Feature",
  "properties": {
    "gn:admin1_code":"FR",
    "gn:admin2_code":"14",
    "gn:admin3_code":"70.0",
    "gn:admin4_code":"700001.0",
    "gn:asciiname":"Sallikhan",
    "gn:country_code":"NP",
    "gn:dem":1725,
    "gn:feature_class":"P",
    "gn:feature_code":"PPLL",
    "gn:name":"Sallikhan",
    "gn:population":0,
    "gn:timezone":"Asia/Kathmandu",
    "iso:country":"NP",
    "wof:name":"Sallikhan",
    "wof:placetype":"locality"
},
  "geometry": {"coordinates":[80.95862,29.31597],"type":"Point"}
}