{
  "type": "Feature",
  "properties": {
    "gn:admin1_code":"MR",
    "gn:admin2_code":"6",
    "gn:admin3_code":"64.0",
    "gn:admin4_code":"640009.0",
    "gn:asciiname":"Lokhada",
    "gn:country_code":"NP",
    "gn:dem":1641,
    "gn:feature_class":"P",
    "gn:feature_code":"PPLL",
    "gn:name":"Lokhada",
    "gn:population":0,
    "gn:timezone":"Asia/Kathmandu",
    "iso:country":"NP",
    "wof:name":"Lokhada",
    "wof:placetype":"locality"
},
  "geometry": {"coordinates":[81.5639,29.17659],"type":"Point"}
}