{
  "type": "Feature",
  "properties": {
    "gn:admin1_code":"WR",
    "gn:admin2_code":"4",
    "gn:admin3_code":"37",
    "gn:admin4_code":"370050",
    "gn:asciiname":"Kharkabari",
    "gn:country_code":"NP",
    "gn:dem":603,
    "gn:feature_class":"P",
    "gn:feature_code":"PPLL",
    "gn:name":"Kharkabari",
    "gn:population":0,
    "gn:timezone":"Asia/Kathmandu",
    "iso:country":"NP",
    "wof:name":"Kharkabari",
    "wof:placetype":"locality"
},
  "geometry": {"coordinates":[84.23393,28.12944],"type":"Point"}
}