{
  "type": "Feature",
  "properties": {
    "gn:admin1_code":"MR",
    "gn:admin2_code":"12",
    "gn:admin3_code":"55",
    "gn:admin4_code":"550042",
    "gn:asciiname":"Simpak",
    "gn:country_code":"NP",
    "gn:dem":1608,
    "gn:feature_class":"P",
    "gn:feature_code":"PPLL",
    "gn:name":"Simpak",
    "gn:population":0,
    "gn:timezone":"Asia/Kathmandu",
    "iso:country":"NP",
    "wof:name":"Simpak",
    "wof:placetype":"locality"
},
  "geometry": {"coordinates":[82.16838,28.46257],"type":"Point"}
}