{
  "type": "Feature",
  "properties": {
    "gn:admin1_code":"CR",
    "gn:admin2_code":"11",
    "gn:admin3_code":"35.0",
    "gn:admin4_code":"350004.0",
    "gn:asciiname":"Padhariya",
    "gn:country_code":"NP",
    "gn:dem":223,
    "gn:feature_class":"P",
    "gn:feature_code":"PPLL",
    "gn:name":"Padhariya",
    "gn:population":0,
    "gn:timezone":"Asia/Kathmandu",
    "iso:country":"NP",
    "wof:name":"Padhariya",
    "wof:placetype":"locality"
},
  "geometry": {"coordinates":[84.64211999999998,27.58665],"type":"Point"}
}