{
  "type": "Feature",
  "properties": {
    "gn:admin1_code":"CR",
    "gn:admin2_code":"11",
    "gn:admin3_code":"34",
    "gn:admin4_code":"340058",
    "gn:asciiname":"Bahuarwa",
    "gn:country_code":"NP",
    "gn:dem":94,
    "gn:feature_class":"P",
    "gn:feature_code":"PPLL",
    "gn:name":"Bahuarwa",
    "gn:population":0,
    "gn:timezone":"Asia/Kathmandu",
    "iso:country":"NP",
    "name:tam_x_preferred":[
        "\u0baa\u0b95\u0bc1\u0bb5\u0bbe\u0bb0\u0bcd\u0bb5\u0bbe"
    ],
    "wof:name":"Bahuarwa",
    "wof:placetype":"locality"
},
  "geometry": {"coordinates":[84.86999,27.11155],"type":"Point"}
}