{
  "type": "Feature",
  "properties": {
    "gn:admin1_code":"FR",
    "gn:admin2_code":"14",
    "gn:admin3_code":"71.0",
    "gn:admin4_code":"710034.0",
    "gn:asciiname":"Pratappur",
    "gn:country_code":"NP",
    "gn:dem":160,
    "gn:feature_class":"P",
    "gn:feature_code":"PPLL",
    "gn:name":"Pratappur",
    "gn:population":0,
    "gn:timezone":"Asia/Kathmandu",
    "iso:country":"NP",
    "wof:name":"Pratappur",
    "wof:placetype":"locality"
},
  "geometry": {"coordinates":[81.07661999999998,28.60859],"type":"Point"}
}