{
  "type": "Feature",
  "properties": {
    "gn:admin1_code":"MR",
    "gn:admin2_code":"12",
    "gn:admin3_code":"52",
    "gn:admin4_code":"520031",
    "gn:asciiname":"Nepane",
    "gn:country_code":"NP",
    "gn:dem":1386,
    "gn:feature_class":"P",
    "gn:feature_code":"PPLL",
    "gn:name":"Nepane",
    "gn:population":0,
    "gn:timezone":"Asia/Kathmandu",
    "iso:country":"NP",
    "wof:name":"Nepane",
    "wof:placetype":"locality"
},
  "geometry": {"coordinates":[82.8976,28.10698],"type":"Point"}
}