{
  "type": "Feature",
  "properties": {
    "gn:admin1_code":"ER",
    "gn:admin2_code":"7",
    "gn:admin3_code":"10.0",
    "gn:admin4_code":"100048.0",
    "gn:asciiname":"Dhapini",
    "gn:country_code":"NP",
    "gn:dem":770,
    "gn:feature_class":"P",
    "gn:feature_code":"PPLL",
    "gn:name":"Dhapini",
    "gn:population":0,
    "gn:timezone":"Asia/Kathmandu",
    "iso:country":"NP",
    "wof:name":"Dhapini",
    "wof:placetype":"locality"
},
  "geometry": {"coordinates":[87.18231,27.22036],"type":"Point"}
}