{
  "type": "Feature",
  "properties": {
    "gn:admin1_code":"MR",
    "gn:admin2_code":"2",
    "gn:admin3_code":"60.0",
    "gn:admin4_code":"600020.0",
    "gn:asciiname":"Dublegaun",
    "gn:country_code":"NP",
    "gn:dem":884,
    "gn:feature_class":"P",
    "gn:feature_code":"PPLL",
    "gn:name":"Dublegaun",
    "gn:population":0,
    "gn:timezone":"Asia/Kathmandu",
    "iso:country":"NP",
    "wof:name":"Dublegaun",
    "wof:placetype":"locality"
},
  "geometry": {"coordinates":[81.57401,28.91159],"type":"Point"}
}