{
  "type": "Feature",
  "properties": {
    "gn:admin1_code":"00",
    "gn:asciiname":"Hadi Khola",
    "gn:country_code":"NP",
    "gn:dem":604,
    "gn:feature_class":"P",
    "gn:feature_code":"PPL",
    "gn:name":"H\u0101\u0303\u1e0di\u0307\u0304 Khol\u0101",
    "gn:population":0,
    "gn:timezone":"Asia/Kathmandu",
    "iso:country":"NP",
    "name:und_x_variant":[
        "H\u0101\u0303\u1e0di\u0307\u0304 Khol\u0101",
        "H\u0101n\u1e0d\u012b Khol\u0101"
    ],
    "wof:name":"Hadi Khola",
    "wof:placetype":"locality"
},
  "geometry": {"coordinates":[85.73779999999999,27.55836],"type":"Point"}
}