{
  "type": "Feature",
  "properties": {
    "gn:admin1_code":"00",
    "gn:asciiname":"Pandur",
    "gn:country_code":"NP",
    "gn:dem":1170,
    "gn:feature_class":"P",
    "gn:feature_code":"PPL",
    "gn:name":"P\u0101\u1e45dur",
    "gn:population":0,
    "gn:timezone":"Asia/Kathmandu",
    "iso:country":"NP",
    "name:ceb_x_preferred":[
        "Pandur"
    ],
    "name:deu_x_preferred":[
        "Pandur"
    ],
    "name:fra_x_preferred":[
        "Pandur"
    ],
    "name:hrv_x_preferred":[
        "Pandur"
    ],
    "name:pol_x_preferred":[
        "Pandur"
    ],
    "name:slv_x_preferred":[
        "Pandur"
    ],
    "name:swe_x_preferred":[
        "Pandur"
    ],
    "wof:name":"Pandur",
    "wof:placetype":"locality"
},
  "geometry": {"coordinates":[85.29543000000002,27.49713],"type":"Point"}
}