{
  "type": "Feature",
  "properties": {
    "gn:admin1_code":"CR",
    "gn:admin2_code":"1",
    "gn:admin3_code":"28",
    "gn:admin4_code":"280048",
    "gn:asciiname":"Jor Chautara",
    "gn:country_code":"NP",
    "gn:dem":1095,
    "gn:feature_class":"P",
    "gn:feature_code":"PPLL",
    "gn:name":"Jor Chautara",
    "gn:population":0,
    "gn:timezone":"Asia/Kathmandu",
    "iso:country":"NP",
    "wof:name":"Jor Chautara",
    "wof:placetype":"locality"
},
  "geometry": {"coordinates":[85.0232,27.95106],"type":"Point"}
}