{
  "type": "Feature",
  "properties": {
    "gn:admin1_code":"CR",
    "gn:admin2_code":"1",
    "gn:admin3_code":"30.0",
    "gn:admin4_code":"300020.0",
    "gn:asciiname":"Adheri",
    "gn:country_code":"NP",
    "gn:dem":845,
    "gn:feature_class":"P",
    "gn:feature_code":"PPLL",
    "gn:name":"Adheri",
    "gn:population":0,
    "gn:timezone":"Asia/Kathmandu",
    "iso:country":"NP",
    "wof:name":"Adheri",
    "wof:placetype":"locality"
},
  "geometry": {"coordinates":[84.98219,27.8403],"type":"Point"}
}