{
  "type": "Feature",
  "properties": {
    "gn:admin1_code":"ER",
    "gn:admin2_code":"13",
    "gn:admin3_code":"13.0",
    "gn:admin4_code":"130030.0",
    "gn:asciiname":"Sorachun",
    "gn:country_code":"NP",
    "gn:dem":1330,
    "gn:feature_class":"P",
    "gn:feature_code":"PPLL",
    "gn:name":"Sorachun",
    "gn:population":0,
    "gn:timezone":"Asia/Kathmandu",
    "iso:country":"NP",
    "wof:name":"Sorachun",
    "wof:placetype":"locality"
},
  "geometry": {"coordinates":[86.5745,27.19151],"type":"Point"}
}