{
  "type": "Feature",
  "properties": {
    "gn:admin1_code":"WR",
    "gn:admin2_code":"4.0",
    "gn:admin3_code":"39.0",
    "gn:admin4_code":"390034.0",
    "gn:asciiname":"Lagata",
    "gn:country_code":"NP",
    "gn:dem":1028,
    "gn:feature_class":"P",
    "gn:feature_code":"PPLL",
    "gn:name":"Lagata",
    "gn:population":0,
    "gn:timezone":"Asia/Kathmandu",
    "iso:country":"NP",
    "wof:name":"Lagata",
    "wof:placetype":"locality"
},
  "geometry": {"coordinates":[83.8409,27.96504],"type":"Point"}
}