{
  "type": "Feature",
  "properties": {
    "gn:admin1_code":"WR",
    "gn:admin2_code":"4.0",
    "gn:admin3_code":"39.0",
    "gn:admin4_code":"390034.0",
    "gn:asciiname":"Lagata",
    "gn:country_code":"NP",
    "gn:dem":1028,
    "gn:feature_class":"P",
    "gn:feature_code":"PPLL",
    "gn:name":"Lagata",
    "gn:population":0,
    "gn:timezone":"Asia/Kathmandu",
    "iso:country":"NP",
    "name:ara_x_preferred":[
        "\u0644\u0627\u063a\u0627\u062a\u0627"
    ],
    "name:arg_x_preferred":[
        "Lagata"
    ],
    "name:ast_x_preferred":[
        "Lagata"
    ],
    "name:azb_x_preferred":[
        "\u0644\u0627\u0642\u0627\u062a\u0627"
    ],
    "name:cat_x_preferred":[
        "Lagata"
    ],
    "name:ceb_x_preferred":[
        "Lagata"
    ],
    "name:eus_x_preferred":[
        "Lagata"
    ],
    "name:fas_x_preferred":[
        "\u0644\u0627\u06af\u0627\u062a\u0627"
    ],
    "name:fra_x_preferred":[
        "Lagata"
    ],
    "name:hun_x_preferred":[
        "Lagata"
    ],
    "name:ita_x_preferred":[
        "Lagata"
    ],
    "name:kaz_x_preferred":[
        "\u041b\u0430\u0433\u0430\u0442\u0430"
    ],
    "name:msa_x_preferred":[
        "Lagata"
    ],
    "name:nld_x_preferred":[
        "Lagata"
    ],
    "name:oci_x_preferred":[
        "Lagata"
    ],
    "name:pol_x_preferred":[
        "Lagata"
    ],
    "name:por_x_preferred":[
        "Lagata"
    ],
    "name:rus_x_preferred":[
        "\u041b\u0430\u0433\u0430\u0442\u0430"
    ],
    "name:spa_x_preferred":[
        "Lagata"
    ],
    "name:swe_x_preferred":[
        "Lagata"
    ],
    "name:ukr_x_preferred":[
        "\u041b\u0430\u0433\u0430\u0442\u0430"
    ],
    "name:uzb_x_preferred":[
        "Lagata"
    ],
    "name:vie_x_preferred":[
        "Lagata"
    ],
    "name:war_x_preferred":[
        "Lagata"
    ],
    "name:zho_x_preferred":[
        "\u62c9\u52a0\u5854"
    ],
    "wof:name":"Lagata",
    "wof:placetype":"locality"
},
  "geometry": {"coordinates":[83.8409,27.96504],"type":"Point"}
}