{
  "type": "Feature",
  "properties": {
    "gn:admin1_code":"FR",
    "gn:admin2_code":"9",
    "gn:admin3_code":"72.0",
    "gn:admin4_code":"720005.0",
    "gn:asciiname":"Chandeu",
    "gn:country_code":"NP",
    "gn:dem":189,
    "gn:feature_class":"P",
    "gn:feature_code":"PPLL",
    "gn:name":"Chandeu",
    "gn:population":0,
    "gn:timezone":"Asia/Kathmandu",
    "iso:country":"NP",
    "wof:name":"Chandeu",
    "wof:placetype":"locality"
},
  "geometry": {"coordinates":[80.35684000000001,28.7651],"type":"Point"}
}