{
  "type": "Feature",
  "properties": {
    "gn:admin1_code":"MR",
    "gn:admin2_code":"12",
    "gn:admin3_code":"55",
    "gn:admin4_code":"550018",
    "gn:asciiname":"Patyachaur",
    "gn:country_code":"NP",
    "gn:dem":1458,
    "gn:feature_class":"P",
    "gn:feature_code":"PPLL",
    "gn:name":"Patyachaur",
    "gn:population":0,
    "gn:timezone":"Asia/Kathmandu",
    "iso:country":"NP",
    "wof:name":"Patyachaur",
    "wof:placetype":"locality"
},
  "geometry": {"coordinates":[82.15909000000001,28.43424000000001],"type":"Point"}
}