{
  "type": "Feature",
  "properties": {
    "gn:admin1_code":"WR",
    "gn:admin2_code":"8",
    "gn:admin3_code":"46.0",
    "gn:admin4_code":"460037.0",
    "gn:asciiname":"Gobindigaun",
    "gn:country_code":"NP",
    "gn:dem":719,
    "gn:feature_class":"P",
    "gn:feature_code":"PPLL",
    "gn:name":"Gobindigaun",
    "gn:population":0,
    "gn:timezone":"Asia/Kathmandu",
    "iso:country":"NP",
    "wof:name":"Gobindigaun",
    "wof:placetype":"locality"
},
  "geometry": {"coordinates":[83.46502,27.96729],"type":"Point"}
}