{
  "type": "Feature",
  "properties": {
    "gn:admin1_code":"CR",
    "gn:admin2_code":"1",
    "gn:admin3_code":"23",
    "gn:admin4_code":"230034",
    "gn:asciiname":"Dhule",
    "gn:country_code":"NP",
    "gn:dem":1507,
    "gn:feature_class":"P",
    "gn:feature_code":"PPLL",
    "gn:name":"Dhule",
    "gn:population":0,
    "gn:timezone":"Asia/Kathmandu",
    "iso:country":"NP",
    "name:azb_x_preferred":[
        "\u062f\u0648\u0644\u0647"
    ],
    "name:ben_x_preferred":[
        "\u09a7\u09c1\u09b2\u09c7"
    ],
    "name:bih_x_preferred":[
        "\u0927\u0941\u0932\u0947"
    ],
    "name:bpy_x_preferred":[
        "\u09a7\u09c1\u09b2\u09c7"
    ],
    "name:cat_x_preferred":[
        "Dhule"
    ],
    "name:ceb_x_preferred":[
        "Dhule"
    ],
    "name:deu_x_preferred":[
        "Dhule"
    ],
    "name:est_x_preferred":[
        "Dhule"
    ],
    "name:fas_x_preferred":[
        "\u062f\u0648\u0644\u0647"
    ],
    "name:fra_x_preferred":[
        "Dhule"
    ],
    "name:heb_x_preferred":[
        "\u05d3\u05d5\u05dc\u05d4"
    ],
    "name:hif_x_preferred":[
        "Dhule"
    ],
    "name:hin_x_preferred":[
        "\u0927\u0941\u0932\u0947"
    ],
    "name:hun_x_preferred":[
        "Dhule"
    ],
    "name:ita_x_preferred":[
        "Dhule"
    ],
    "name:lit_x_preferred":[
        "Dhul\u0117"
    ],
    "name:mar_x_preferred":[
        "\u0927\u0941\u0933\u0947"
    ],
    "name:mlg_x_preferred":[
        "Dhule"
    ],
    "name:msa_x_preferred":[
        "Dhule"
    ],
    "name:new_x_preferred":[
        "\u0927\u0941\u0932\u0947"
    ],
    "name:nld_x_preferred":[
        "Dhule"
    ],
    "name:nor_x_preferred":[
        "Dhule"
    ],
    "name:ori_x_preferred":[
        "\u0b27\u0b41\u0b32\u0b47"
    ],
    "name:pam_x_preferred":[
        "Dhule"
    ],
    "name:pnb_x_preferred":[
        "\u062f\u06be\u0648\u0644"
    ],
    "name:pol_x_preferred":[
        "Dhule"
    ],
    "name:por_x_preferred":[
        "Dhule"
    ],
    "name:rus_x_preferred":[
        "\u0414\u0445\u0443\u043b\u0438\u044f"
    ],
    "name:san_x_preferred":[
        "\u0927\u0941\u0933\u0947"
    ],
    "name:srp_x_preferred":[
        "\u0414\u0443\u043b\u0435"
    ],
    "name:swe_x_preferred":[
        "Dhule"
    ],
    "name:urd_x_preferred":[
        "\u062f\u06be\u0648\u0644\u06cc\u06c1"
    ],
    "name:vie_x_preferred":[
        "Dhule"
    ],
    "name:war_x_preferred":[
        "Dhule"
    ],
    "wof:name":"Dhule",
    "wof:placetype":"locality"
},
  "geometry": {"coordinates":[85.62321,27.85349],"type":"Point"}
}