{
  "type": "Feature",
  "properties": {
    "gn:admin1_code":"WR",
    "gn:admin2_code":"4.0",
    "gn:admin3_code":"38.0",
    "gn:admin4_code":"380039.0",
    "gn:asciiname":"Gairiswanra",
    "gn:country_code":"NP",
    "gn:dem":1118,
    "gn:feature_class":"P",
    "gn:feature_code":"PPLL",
    "gn:name":"Gairiswanra",
    "gn:population":0,
    "gn:timezone":"Asia/Kathmandu",
    "iso:country":"NP",
    "wof:name":"Gairiswanra",
    "wof:placetype":"locality"
},
  "geometry": {"coordinates":[84.30915,28.08742],"type":"Point"}
}