{
  "type": "Feature",
  "properties": {
    "gn:admin1_code":"MR",
    "gn:admin2_code":"12",
    "gn:admin3_code":"52",
    "gn:admin4_code":"520041",
    "gn:asciiname":"China",
    "gn:country_code":"NP",
    "gn:dem":1319,
    "gn:feature_class":"P",
    "gn:feature_code":"PPLL",
    "gn:name":"China",
    "gn:population":0,
    "gn:timezone":"Asia/Kathmandu",
    "iso:country":"NP",
    "wof:name":"China",
    "wof:placetype":"locality"
},
  "geometry": {"coordinates":[82.81009,28.05083],"type":"Point"}
}