{
  "type": "Feature",
  "properties": {
    "gn:admin1_code":"FR",
    "gn:admin2_code":"9",
    "gn:admin3_code":"75.0",
    "gn:admin4_code":"750033.0",
    "gn:asciiname":"Thaktoli",
    "gn:country_code":"NP",
    "gn:dem":1322,
    "gn:feature_class":"P",
    "gn:feature_code":"PPLL",
    "gn:name":"Thaktoli",
    "gn:population":0,
    "gn:timezone":"Asia/Kathmandu",
    "iso:country":"NP",
    "wof:name":"Thaktoli",
    "wof:placetype":"locality"
},
  "geometry": {"coordinates":[80.42435,29.74864],"type":"Point"}
}