{
  "type": "Feature",
  "properties": {
    "gn:admin1_code":"FR",
    "gn:admin2_code":"14",
    "gn:admin3_code":"68",
    "gn:admin4_code":"680030",
    "gn:asciiname":"Rupedhar",
    "gn:country_code":"NP",
    "gn:dem":1281,
    "gn:feature_class":"P",
    "gn:feature_code":"PPLL",
    "gn:name":"Rupedhar",
    "gn:population":0,
    "gn:timezone":"Asia/Kathmandu",
    "iso:country":"NP",
    "wof:name":"Rupedhar",
    "wof:placetype":"locality"
},
  "geometry": {"coordinates":[81.05816,29.48294000000001],"type":"Point"}
}