{
  "type": "Feature",
  "properties": {
    "gn:admin1_code":"FR",
    "gn:admin2_code":"14",
    "gn:admin3_code":"69",
    "gn:admin4_code":"690036",
    "gn:asciiname":"Kalekanda",
    "gn:country_code":"NP",
    "gn:dem":1352,
    "gn:feature_class":"P",
    "gn:feature_code":"PPLL",
    "gn:name":"Kalekanda",
    "gn:population":0,
    "gn:timezone":"Asia/Kathmandu",
    "iso:country":"NP",
    "name:ceb_x_preferred":[
        "Kalekanda"
    ],
    "name:fra_x_preferred":[
        "Kalekanda"
    ],
    "name:hin_x_preferred":[
        "\u0915\u093e\u0932\u0947\u0917\u093e\u0901\u0921\u093e"
    ],
    "name:mai_x_preferred":[
        "\u0915\u093e\u0932\u0947\u0917\u093e\u0901\u0921\u093e"
    ],
    "name:msa_x_preferred":[
        "Kalekanda"
    ],
    "name:nep_x_preferred":[
        "\u0915\u093e\u0932\u0947\u0917\u093e\u0901\u0921\u093e"
    ],
    "name:new_x_preferred":[
        "\u0915\u093e\u0932\u0947\u0915\u093e\u0902\u0921\u093e"
    ],
    "name:pol_x_preferred":[
        "Kalekanda"
    ],
    "wof:name":"Kalekanda",
    "wof:placetype":"locality"
},
  "geometry": {"coordinates":[81.5078,29.11192],"type":"Point"}
}