{
  "type": "Feature",
  "properties": {
    "gn:admin1_code":"WR",
    "gn:admin2_code":"8",
    "gn:admin3_code":"46.0",
    "gn:admin4_code":"460018.0",
    "gn:asciiname":"Bhattechaur",
    "gn:country_code":"NP",
    "gn:dem":1101,
    "gn:feature_class":"P",
    "gn:feature_code":"PPLL",
    "gn:name":"Bhattechaur",
    "gn:population":0,
    "gn:timezone":"Asia/Kathmandu",
    "iso:country":"NP",
    "wof:name":"Bhattechaur",
    "wof:placetype":"locality"
},
  "geometry": {"coordinates":[83.32523,28.03815],"type":"Point"}
}