{
  "type": "Feature",
  "properties": {
    "gn:admin1_code":"CR",
    "gn:admin2_code":"1",
    "gn:admin3_code":"28",
    "gn:admin4_code":"280025",
    "gn:asciiname":"Archalbot",
    "gn:country_code":"NP",
    "gn:dem":645,
    "gn:feature_class":"P",
    "gn:feature_code":"PPLL",
    "gn:name":"Archalbot",
    "gn:population":0,
    "gn:timezone":"Asia/Kathmandu",
    "iso:country":"NP",
    "name:ara_x_preferred":[
        "\u0623\u0631\u0634\u0627\u0644\u0628\u0648\u062a"
    ],
    "name:ceb_x_preferred":[
        "Archalbot"
    ],
    "name:fra_x_preferred":[
        "Archalbot"
    ],
    "name:mai_x_preferred":[
        "\u0905\u0930\u094d\u091a\u0932\u092c\u094b\u091f"
    ],
    "name:msa_x_preferred":[
        "Archalbot"
    ],
    "name:nep_x_preferred":[
        "\u0905\u0930\u094d\u091a\u0932\u092c\u094b\u091f"
    ],
    "name:new_x_preferred":[
        "\u0905\u0930\u094d\u091a\u0932\u092c\u094b\u091f"
    ],
    "name:pol_x_preferred":[
        "Archalbot"
    ],
    "wof:name":"Archalbot",
    "wof:placetype":"locality"
},
  "geometry": {"coordinates":[85.11279999999999,27.85367],"type":"Point"}
}