{
  "type": "Feature",
  "properties": {
    "gn:admin1_code":"ER",
    "gn:admin2_code":"10",
    "gn:admin3_code":"2",
    "gn:admin4_code":"20008",
    "gn:asciiname":"Biruwa Kopche",
    "gn:country_code":"NP",
    "gn:dem":1988,
    "gn:feature_class":"P",
    "gn:feature_code":"PPLL",
    "gn:name":"Biruwa Kopche",
    "gn:population":0,
    "gn:timezone":"Asia/Kathmandu",
    "iso:country":"NP",
    "wof:name":"Biruwa Kopche",
    "wof:placetype":"locality"
},
  "geometry": {"coordinates":[87.94651,27.25027],"type":"Point"}
}