{
  "type": "Feature",
  "properties": {
    "gn:admin1_code":"FR",
    "gn:admin2_code":"14",
    "gn:admin3_code":"68",
    "gn:admin4_code":"680002",
    "gn:asciiname":"Lasa",
    "gn:country_code":"NP",
    "gn:dem":1884,
    "gn:feature_class":"P",
    "gn:feature_code":"PPLL",
    "gn:name":"Lasa",
    "gn:population":0,
    "gn:timezone":"Asia/Kathmandu",
    "iso:country":"NP",
    "wof:name":"Lasa",
    "wof:placetype":"locality"
},
  "geometry": {"coordinates":[80.99868000000002,29.4914],"type":"Point"}
}