{
  "type": "Feature",
  "properties": {
    "gn:admin1_code":"00",
    "gn:asciiname":"Chainpur",
    "gn:country_code":"NP",
    "gn:dem":1470,
    "gn:feature_class":"P",
    "gn:feature_code":"PPL",
    "gn:name":"Chainpur",
    "gn:population":0,
    "gn:timezone":"Asia/Kathmandu",
    "iso:country":"NP",
    "name:ceb_x_preferred":[
        "Chainpur"
    ],
    "name:deu_x_preferred":[
        "Chainpur"
    ],
    "name:nep_x_preferred":[
        "\u091a\u0948\u0928\u092a\u0941\u0930"
    ],
    "name:new_x_preferred":[
        "\u091a\u0948\u0928\u092a\u0941\u0930"
    ],
    "name:pol_x_preferred":[
        "Chainpur"
    ],
    "wof:name":"Chainpur",
    "wof:placetype":"locality"
},
  "geometry": {"coordinates":[81.19351999999998,29.56228],"type":"Point"}
}