{
  "type": "Feature",
  "properties": {
    "gn:admin1_code":"ER",
    "gn:admin2_code":"10",
    "gn:admin3_code":"3.0",
    "gn:admin4_code":"30043.0",
    "gn:asciiname":"Karele",
    "gn:country_code":"NP",
    "gn:dem":549,
    "gn:feature_class":"P",
    "gn:feature_code":"PPLL",
    "gn:name":"Karele",
    "gn:population":0,
    "gn:timezone":"Asia/Kathmandu",
    "iso:country":"NP",
    "wof:name":"Karele",
    "wof:placetype":"locality"
},
  "geometry": {"coordinates":[88.00624000000001,26.80506],"type":"Point"}
}