{
  "type": "Feature",
  "properties": {
    "gn:admin1_code":"MR",
    "gn:admin2_code":"12",
    "gn:admin3_code":"54",
    "gn:admin4_code":"540032",
    "gn:asciiname":"Kotisimle",
    "gn:country_code":"NP",
    "gn:dem":1513,
    "gn:feature_class":"P",
    "gn:feature_code":"PPLL",
    "gn:name":"Kotisimle",
    "gn:population":0,
    "gn:timezone":"Asia/Kathmandu",
    "iso:country":"NP",
    "wof:name":"Kotisimle",
    "wof:placetype":"locality"
},
  "geometry": {"coordinates":[82.70203000000002,28.69576],"type":"Point"}
}