{
  "type": "Feature",
  "properties": {
    "gn:admin1_code":"ER",
    "gn:admin2_code":"7",
    "gn:admin3_code":"5",
    "gn:admin4_code":"50031",
    "gn:asciiname":"Mathillo Kaseni",
    "gn:country_code":"NP",
    "gn:dem":107,
    "gn:feature_class":"P",
    "gn:feature_code":"PPLL",
    "gn:name":"Mathillo Kaseni",
    "gn:population":0,
    "gn:timezone":"Asia/Kathmandu",
    "iso:country":"NP",
    "wof:name":"Mathillo Kaseni",
    "wof:placetype":"locality"
},
  "geometry": {"coordinates":[87.39530000000001,26.60573],"type":"Point"}
}