{
  "type": "Feature",
  "properties": {
    "gn:admin1_code":"CR",
    "gn:admin2_code":"1",
    "gn:admin3_code":"25",
    "gn:admin4_code":"250018",
    "gn:asciiname":"Karkitar",
    "gn:country_code":"NP",
    "gn:dem":1447,
    "gn:feature_class":"P",
    "gn:feature_code":"PPLL",
    "gn:name":"Karkitar",
    "gn:population":0,
    "gn:timezone":"Asia/Kathmandu",
    "iso:country":"NP",
    "wof:name":"Karkitar",
    "wof:placetype":"locality"
},
  "geometry": {"coordinates":[85.36462,27.62435],"type":"Point"}
}