{
  "type": "Feature",
  "properties": {
    "gn:admin1_code":"MR",
    "gn:admin2_code":"6",
    "gn:admin3_code":"62.0",
    "gn:admin4_code":"620019.0",
    "gn:asciiname":"Chasip",
    "gn:country_code":"NP",
    "gn:dem":4056,
    "gn:feature_class":"P",
    "gn:feature_code":"PPLL",
    "gn:name":"Chasip",
    "gn:population":0,
    "gn:timezone":"Asia/Kathmandu",
    "iso:country":"NP",
    "wof:name":"Chasip",
    "wof:placetype":"locality"
},
  "geometry": {"coordinates":[83.12119,29.37081],"type":"Point"}
}