{
  "type": "Feature",
  "properties": {
    "gn:admin1_code":"WR",
    "gn:admin2_code":"3",
    "gn:admin3_code":"42",
    "gn:admin4_code":"420003",
    "gn:asciiname":"Jhong",
    "gn:country_code":"NP",
    "gn:dem":4050,
    "gn:feature_class":"P",
    "gn:feature_code":"PPLL",
    "gn:name":"Jhong",
    "gn:population":0,
    "gn:timezone":"Asia/Kathmandu",
    "iso:country":"NP",
    "wof:name":"Jhong",
    "wof:placetype":"locality"
},
  "geometry": {"coordinates":[83.9731,29.24432],"type":"Point"}
}