{
  "type": "Feature",
  "properties": {
    "gn:admin1_code":"CR",
    "gn:admin2_code":"5",
    "gn:admin3_code":"20",
    "gn:admin4_code":"200031.0",
    "gn:asciiname":"Devdah",
    "gn:country_code":"NP",
    "gn:dem":183,
    "gn:feature_class":"P",
    "gn:feature_code":"PPLL",
    "gn:name":"Devdah",
    "gn:population":0,
    "gn:timezone":"Asia/Kathmandu",
    "iso:country":"NP",
    "wof:name":"Devdah",
    "wof:placetype":"locality"
},
  "geometry": {"coordinates":[86.29611,26.97198],"type":"Point"}
}