{
  "type": "Feature",
  "properties": {
    "gn:admin1_code":"MR",
    "gn:admin2_code":"2.0",
    "gn:admin3_code":"59.0",
    "gn:admin4_code":"590002.0",
    "gn:asciiname":"Chandreke",
    "gn:country_code":"NP",
    "gn:dem":1340,
    "gn:feature_class":"P",
    "gn:feature_code":"PPLL",
    "gn:name":"Chandreke",
    "gn:population":0,
    "gn:timezone":"Asia/Kathmandu",
    "iso:country":"NP",
    "wof:name":"Chandreke",
    "wof:placetype":"locality"
},
  "geometry": {"coordinates":[81.812,28.64417000000001],"type":"Point"}
}