{
  "type": "Feature",
  "properties": {
    "gn:admin1_code":"FR",
    "gn:admin2_code":"14.0",
    "gn:admin3_code":"67.0",
    "gn:admin4_code":"670027.0",
    "gn:asciiname":"Pipalsain",
    "gn:country_code":"NP",
    "gn:dem":1027,
    "gn:feature_class":"P",
    "gn:feature_code":"PPLL",
    "gn:name":"Pipalsain",
    "gn:population":0,
    "gn:timezone":"Asia/Kathmandu",
    "iso:country":"NP",
    "wof:name":"Pipalsain",
    "wof:placetype":"locality"
},
  "geometry": {"coordinates":[81.32533000000002,29.34551],"type":"Point"}
}