{
  "type": "Feature",
  "properties": {
    "gn:admin1_code":"CR",
    "gn:admin2_code":"11",
    "gn:admin3_code":"34",
    "gn:admin4_code":"340005",
    "gn:asciiname":"Manawa",
    "gn:country_code":"NP",
    "gn:dem":113,
    "gn:feature_class":"P",
    "gn:feature_code":"PPLL",
    "gn:name":"Manawa",
    "gn:population":0,
    "gn:timezone":"Asia/Kathmandu",
    "iso:country":"NP",
    "name:ceb_x_preferred":[
        "Manawa"
    ],
    "name:nld_x_preferred":[
        "Manawa"
    ],
    "wof:name":"Manawa",
    "wof:placetype":"locality"
},
  "geometry": {"coordinates":[84.86556999999998,27.18358],"type":"Point"}
}