{
  "type": "Feature",
  "properties": {
    "gn:admin1_code":"CR",
    "gn:admin2_code":"11.0",
    "gn:admin3_code":"33.0",
    "gn:admin4_code":"330088.0",
    "gn:asciiname":"Ramthaligaun",
    "gn:country_code":"NP",
    "gn:dem":264,
    "gn:feature_class":"P",
    "gn:feature_code":"PPLL",
    "gn:name":"Ramthaligaun",
    "gn:population":0,
    "gn:timezone":"Asia/Kathmandu",
    "iso:country":"NP",
    "wof:name":"Ramthaligaun",
    "wof:placetype":"locality"
},
  "geometry": {"coordinates":[85.12031,27.26867],"type":"Point"}
}