{
  "type": "Feature",
  "properties": {
    "gn:admin1_code":"ER",
    "gn:admin2_code":"7",
    "gn:admin3_code":"5",
    "gn:admin4_code":"50021",
    "gn:asciiname":"Tupiyakhadi",
    "gn:country_code":"NP",
    "gn:dem":79,
    "gn:feature_class":"P",
    "gn:feature_code":"PPLL",
    "gn:name":"Tupiyakhadi",
    "gn:population":0,
    "gn:timezone":"Asia/Kathmandu",
    "iso:country":"NP",
    "wof:name":"Tupiyakhadi",
    "wof:placetype":"locality"
},
  "geometry": {"coordinates":[87.57571,26.46405],"type":"Point"}
}