{
  "type": "Feature",
  "properties": {
    "gn:admin1_code":"CR",
    "gn:admin2_code":"1",
    "gn:admin3_code":"24.0",
    "gn:admin4_code":"240066.0",
    "gn:asciiname":"Bakhreldihi",
    "gn:country_code":"NP",
    "gn:dem":862,
    "gn:feature_class":"P",
    "gn:feature_code":"PPLL",
    "gn:name":"Bakhreldihi",
    "gn:population":0,
    "gn:timezone":"Asia/Kathmandu",
    "iso:country":"NP",
    "wof:name":"Bakhreldihi",
    "wof:placetype":"locality"
},
  "geometry": {"coordinates":[85.6155,27.63654],"type":"Point"}
}