{
  "type": "Feature",
  "properties": {
    "gn:admin1_code":"WR",
    "gn:admin2_code":"3",
    "gn:admin3_code":"45.0",
    "gn:admin4_code":"450026.0",
    "gn:asciiname":"Dale Khoriya",
    "gn:country_code":"NP",
    "gn:dem":1941,
    "gn:feature_class":"P",
    "gn:feature_code":"PPLL",
    "gn:name":"Dale Khoriya",
    "gn:population":0,
    "gn:timezone":"Asia/Kathmandu",
    "iso:country":"NP",
    "wof:name":"Dale Khoriya",
    "wof:placetype":"locality"
},
  "geometry": {"coordinates":[83.48893000000002,28.23799],"type":"Point"}
}