{
  "type": "Feature",
  "properties": {
    "gn:admin1_code":"WR",
    "gn:admin2_code":"8",
    "gn:admin3_code":"47",
    "gn:admin4_code":"470031",
    "gn:asciiname":"Goldihi",
    "gn:country_code":"NP",
    "gn:dem":1331,
    "gn:feature_class":"P",
    "gn:feature_code":"PPLL",
    "gn:name":"Goldihi",
    "gn:population":0,
    "gn:timezone":"Asia/Kathmandu",
    "iso:country":"NP",
    "wof:name":"Goldihi",
    "wof:placetype":"locality"
},
  "geometry": {"coordinates":[83.64272,27.77621],"type":"Point"}
}