{
  "type": "Feature",
  "properties": {
    "gn:admin1_code":"CR",
    "gn:admin2_code":"1",
    "gn:admin3_code":"30.0",
    "gn:admin4_code":"300027.0",
    "gn:asciiname":"Lebengchet",
    "gn:country_code":"NP",
    "gn:dem":1808,
    "gn:feature_class":"P",
    "gn:feature_code":"PPLL",
    "gn:name":"Lebengchet",
    "gn:population":0,
    "gn:timezone":"Asia/Kathmandu",
    "iso:country":"NP",
    "wof:name":"Lebengchet",
    "wof:placetype":"locality"
},
  "geometry": {"coordinates":[85.02188000000002,28.16408],"type":"Point"}
}