{
  "type": "Feature",
  "properties": {
    "gn:admin1_code":"CR",
    "gn:admin2_code":"11",
    "gn:admin3_code":"35.0",
    "gn:admin4_code":"350015.0",
    "gn:asciiname":"Beluwa",
    "gn:country_code":"NP",
    "gn:dem":174,
    "gn:feature_class":"P",
    "gn:feature_code":"PPLL",
    "gn:name":"Beluwa",
    "gn:population":0,
    "gn:timezone":"Asia/Kathmandu",
    "iso:country":"NP",
    "wof:name":"Beluwa",
    "wof:placetype":"locality"
},
  "geometry": {"coordinates":[84.31489000000001,27.65934],"type":"Point"}
}