{
  "type": "Feature",
  "properties": {
    "gn:admin1_code":"FR",
    "gn:admin2_code":"14",
    "gn:admin3_code":"68",
    "gn:admin4_code":"680037",
    "gn:asciiname":"Jukena",
    "gn:country_code":"NP",
    "gn:dem":1937,
    "gn:feature_class":"P",
    "gn:feature_code":"PPLL",
    "gn:name":"Jukena",
    "gn:population":0,
    "gn:timezone":"Asia/Kathmandu",
    "iso:country":"NP",
    "name:bih_x_preferred":[
        "\u091c\u0941\u0915\u0947\u0928\u093e"
    ],
    "name:ceb_x_preferred":[
        "Jukena"
    ],
    "name:fra_x_preferred":[
        "Jukena"
    ],
    "name:mai_x_preferred":[
        "\u091c\u0941\u0915\u0947\u0928\u093e"
    ],
    "name:msa_x_preferred":[
        "Jukena"
    ],
    "name:nep_x_preferred":[
        "\u091c\u0941\u0915\u0947\u0928\u093e"
    ],
    "name:new_x_preferred":[
        "\u091c\u0941\u0915\u0947\u0928\u093e"
    ],
    "name:pol_x_preferred":[
        "Jukena"
    ],
    "wof:name":"Jukena",
    "wof:placetype":"locality"
},
  "geometry": {"coordinates":[81.15371999999998,29.42145],"type":"Point"}
}