{
  "type": "Feature",
  "properties": {
    "gn:admin1_code":"WR",
    "gn:admin2_code":"4.0",
    "gn:admin3_code":"38.0",
    "gn:admin4_code":"380014.0",
    "gn:asciiname":"Dagara",
    "gn:country_code":"NP",
    "gn:dem":861,
    "gn:feature_class":"P",
    "gn:feature_code":"PPLL",
    "gn:name":"Dagara",
    "gn:population":0,
    "gn:timezone":"Asia/Kathmandu",
    "iso:country":"NP",
    "name:cat_x_preferred":[
        "Dagara"
    ],
    "wof:name":"Dagara",
    "wof:placetype":"locality"
},
  "geometry": {"coordinates":[84.35316999999998,27.85688],"type":"Point"}
}