{
  "type": "Feature",
  "properties": {
    "gn:admin1_code":"WR",
    "gn:admin2_code":"4",
    "gn:admin3_code":"36.0",
    "gn:admin4_code":"360020.0",
    "gn:asciiname":"Madanedada",
    "gn:country_code":"NP",
    "gn:dem":466,
    "gn:feature_class":"P",
    "gn:feature_code":"PPLL",
    "gn:name":"Madanedada",
    "gn:population":0,
    "gn:timezone":"Asia/Kathmandu",
    "iso:country":"NP",
    "wof:name":"Madanedada",
    "wof:placetype":"locality"
},
  "geometry": {"coordinates":[84.53192,27.96847],"type":"Point"}
}