{
  "type": "Feature",
  "properties": {
    "gn:admin1_code":"MR",
    "gn:admin2_code":"12",
    "gn:admin3_code":"54",
    "gn:admin4_code":"540006",
    "gn:asciiname":"Kaphalpani",
    "gn:country_code":"NP",
    "gn:dem":1548,
    "gn:feature_class":"P",
    "gn:feature_code":"PPLL",
    "gn:name":"Kaphalpani",
    "gn:population":0,
    "gn:timezone":"Asia/Kathmandu",
    "iso:country":"NP",
    "wof:name":"Kaphalpani",
    "wof:placetype":"locality"
},
  "geometry": {"coordinates":[82.25539000000001,28.60751],"type":"Point"}
}