{
  "type": "Feature",
  "properties": {
    "gn:admin1_code":"ER",
    "gn:admin2_code":"7",
    "gn:admin3_code":"10.0",
    "gn:admin4_code":"100019.0",
    "gn:asciiname":"Archale",
    "gn:country_code":"NP",
    "gn:dem":356,
    "gn:feature_class":"P",
    "gn:feature_code":"PPLL",
    "gn:name":"Archale",
    "gn:population":0,
    "gn:timezone":"Asia/Kathmandu",
    "iso:country":"NP",
    "name:ceb_x_preferred":[
        "Archale"
    ],
    "name:hin_x_preferred":[
        "\u0905\u0930\u094d\u091a\u0932\u0947"
    ],
    "name:msa_x_preferred":[
        "Archale"
    ],
    "name:nep_x_preferred":[
        "\u0905\u0930\u094d\u091a\u0932\u0947"
    ],
    "name:new_x_preferred":[
        "\u0905\u0930\u094d\u091a\u0932\u0947"
    ],
    "name:pol_x_preferred":[
        "Archale"
    ],
    "wof:name":"Archale",
    "wof:placetype":"locality"
},
  "geometry": {"coordinates":[87.17948,27.3222],"type":"Point"}
}