{
  "type": "Feature",
  "properties": {
    "gn:admin1_code":"ER",
    "gn:admin2_code":"7",
    "gn:admin3_code":"5",
    "gn:admin4_code":"50058",
    "gn:asciiname":"Sukunatol",
    "gn:country_code":"NP",
    "gn:dem":148,
    "gn:feature_class":"P",
    "gn:feature_code":"PPLL",
    "gn:name":"Sukunatol",
    "gn:population":0,
    "gn:timezone":"Asia/Kathmandu",
    "iso:country":"NP",
    "wof:name":"Sukunatol",
    "wof:placetype":"locality"
},
  "geometry": {"coordinates":[87.34414,26.69007],"type":"Point"}
}