{
  "type": "Feature",
  "properties": {
    "gn:admin1_code":"CR",
    "gn:admin2_code":"1",
    "gn:admin3_code":"28",
    "gn:admin4_code":"280038",
    "gn:asciiname":"Madanpur",
    "gn:country_code":"NP",
    "gn:dem":570,
    "gn:feature_class":"P",
    "gn:feature_code":"PPLL",
    "gn:name":"Madanpur",
    "gn:population":0,
    "gn:timezone":"Asia/Kathmandu",
    "iso:country":"NP",
    "wof:name":"Madanpur",
    "wof:placetype":"locality"
},
  "geometry": {"coordinates":[85.1752,27.87902],"type":"Point"}
}