{
  "type": "Feature",
  "properties": {
    "gn:admin1_code":"ER",
    "gn:admin2_code":"13",
    "gn:admin3_code":"15",
    "gn:admin4_code":"150080",
    "gn:asciiname":"Shamsherpur",
    "gn:country_code":"NP",
    "gn:dem":107,
    "gn:feature_class":"P",
    "gn:feature_code":"PPLL",
    "gn:name":"Shamsherpur",
    "gn:population":0,
    "gn:timezone":"Asia/Kathmandu",
    "iso:country":"NP",
    "wof:name":"Shamsherpur",
    "wof:placetype":"locality"
},
  "geometry": {"coordinates":[86.53990999999998,26.65704],"type":"Point"}
}