{
  "type": "Feature",
  "properties": {
    "gn:admin1_code":"CR",
    "gn:admin2_code":"1",
    "gn:admin3_code":"23",
    "gn:admin4_code":"230030",
    "gn:asciiname":"Sano Manchet",
    "gn:country_code":"NP",
    "gn:dem":1605,
    "gn:feature_class":"P",
    "gn:feature_code":"PPLL",
    "gn:name":"Sano Manchet",
    "gn:population":0,
    "gn:timezone":"Asia/Kathmandu",
    "iso:country":"NP",
    "wof:name":"Sano Manchet",
    "wof:placetype":"locality"
},
  "geometry": {"coordinates":[85.52445999999998,27.9079],"type":"Point"}
}