{
  "type": "Feature",
  "properties": {
    "gn:admin1_code":"MR",
    "gn:admin2_code":"2",
    "gn:admin3_code":"61.0",
    "gn:admin4_code":"610025.0",
    "gn:asciiname":"Bandala",
    "gn:country_code":"NP",
    "gn:dem":1878,
    "gn:feature_class":"P",
    "gn:feature_code":"PPLL",
    "gn:name":"Bandala",
    "gn:population":0,
    "gn:timezone":"Asia/Kathmandu",
    "iso:country":"NP",
    "wof:name":"Bandala",
    "wof:placetype":"locality"
},
  "geometry": {"coordinates":[82.28463000000001,28.90495],"type":"Point"}
}