{
  "type": "Feature",
  "properties": {
    "gn:admin1_code":"CR",
    "gn:admin2_code":"1",
    "gn:admin3_code":"23",
    "gn:admin4_code":"230071",
    "gn:asciiname":"Urleni",
    "gn:country_code":"NP",
    "gn:dem":1591,
    "gn:feature_class":"P",
    "gn:feature_code":"PPLL",
    "gn:name":"Urleni",
    "gn:population":0,
    "gn:timezone":"Asia/Kathmandu",
    "iso:country":"NP",
    "name:ceb_x_preferred":[
        "Urleni"
    ],
    "name:fra_x_preferred":[
        "Urleni"
    ],
    "name:mai_x_preferred":[
        "\u0909\u0930\u094d\u0932\u0947\u0928\u0940"
    ],
    "name:msa_x_preferred":[
        "Urleni"
    ],
    "name:nep_x_preferred":[
        "\u0909\u0930\u094d\u0932\u0947\u0928\u0940"
    ],
    "name:new_x_preferred":[
        "\u0909\u0930\u094d\u0932\u0947\u0928\u0940"
    ],
    "name:pol_x_preferred":[
        "Urleni"
    ],
    "wof:name":"Urleni",
    "wof:placetype":"locality"
},
  "geometry": {"coordinates":[85.47133000000002,27.85761],"type":"Point"}
}