{
  "type": "Feature",
  "properties": {
    "gn:admin1_code":"CR",
    "gn:admin2_code":"1",
    "gn:admin3_code":"28",
    "gn:admin4_code":"280005",
    "gn:asciiname":"Dibale",
    "gn:country_code":"NP",
    "gn:dem":1752,
    "gn:feature_class":"P",
    "gn:feature_code":"PPLL",
    "gn:name":"Dibale",
    "gn:population":0,
    "gn:timezone":"Asia/Kathmandu",
    "iso:country":"NP",
    "wof:name":"Dibale",
    "wof:placetype":"locality"
},
  "geometry": {"coordinates":[85.46836999999999,27.92533],"type":"Point"}
}