{
  "type": "Feature",
  "properties": {
    "gn:admin1_code":"CR",
    "gn:admin2_code":"1",
    "gn:admin3_code":"28",
    "gn:admin4_code":"280038",
    "gn:asciiname":"Panchmure",
    "gn:country_code":"NP",
    "gn:dem":602,
    "gn:feature_class":"P",
    "gn:feature_code":"PPLL",
    "gn:name":"Panchmure",
    "gn:population":0,
    "gn:timezone":"Asia/Kathmandu",
    "iso:country":"NP",
    "wof:name":"Panchmure",
    "wof:placetype":"locality"
},
  "geometry": {"coordinates":[85.19269,27.88083],"type":"Point"}
}