{
  "type": "Feature",
  "properties": {
    "gn:admin1_code":"WR",
    "gn:admin2_code":"8",
    "gn:admin3_code":"46.0",
    "gn:admin4_code":"460060.0",
    "gn:asciiname":"Gairakharka",
    "gn:country_code":"NP",
    "gn:dem":1415,
    "gn:feature_class":"P",
    "gn:feature_code":"PPLL",
    "gn:name":"Gairakharka",
    "gn:population":0,
    "gn:timezone":"Asia/Kathmandu",
    "iso:country":"NP",
    "wof:name":"Gairakharka",
    "wof:placetype":"locality"
},
  "geometry": {"coordinates":[83.07760999999998,28.16899],"type":"Point"}
}