{
  "type": "Feature",
  "properties": {
    "gn:admin1_code":"FR",
    "gn:admin2_code":"9",
    "gn:admin3_code":"75.0",
    "gn:admin4_code":"750030.0",
    "gn:asciiname":"Mallo Kandapari",
    "gn:country_code":"NP",
    "gn:dem":1678,
    "gn:feature_class":"P",
    "gn:feature_code":"PPLL",
    "gn:name":"Mallo Kandapari",
    "gn:population":0,
    "gn:timezone":"Asia/Kathmandu",
    "iso:country":"NP",
    "wof:name":"Mallo Kandapari",
    "wof:placetype":"locality"
},
  "geometry": {"coordinates":[80.57992,29.70944],"type":"Point"}
}