{
  "type": "Feature",
  "properties": {
    "gn:admin1_code":"MR",
    "gn:admin2_code":"2.0",
    "gn:admin3_code":"58.0",
    "gn:admin4_code":"580015.0",
    "gn:asciiname":"Perhawa",
    "gn:country_code":"NP",
    "gn:dem":160,
    "gn:feature_class":"P",
    "gn:feature_code":"PPLL",
    "gn:name":"Perhawa",
    "gn:population":0,
    "gn:timezone":"Asia/Kathmandu",
    "iso:country":"NP",
    "wof:name":"Perhawa",
    "wof:placetype":"locality"
},
  "geometry": {"coordinates":[81.40876,28.32856],"type":"Point"}
}