{
  "type": "Feature",
  "properties": {
    "gn:admin1_code":"WR",
    "gn:admin2_code":"8",
    "gn:admin3_code":"47",
    "gn:admin4_code":"470057",
    "gn:asciiname":"Dhungri Khola Gaun",
    "gn:country_code":"NP",
    "gn:dem":894,
    "gn:feature_class":"P",
    "gn:feature_code":"PPLL",
    "gn:name":"Dhungri Khola Gaun",
    "gn:population":0,
    "gn:timezone":"Asia/Kathmandu",
    "iso:country":"NP",
    "wof:name":"Dhungri Khola Gaun",
    "wof:placetype":"locality"
},
  "geometry": {"coordinates":[83.26694999999999,27.80417000000001],"type":"Point"}
}