{
  "type": "Feature",
  "properties": {
    "gn:admin1_code":"MR",
    "gn:admin2_code":"2",
    "gn:admin3_code":"60.0",
    "gn:admin4_code":"600022.0",
    "gn:asciiname":"Thinkedanda",
    "gn:country_code":"NP",
    "gn:dem":1853,
    "gn:feature_class":"P",
    "gn:feature_code":"PPLL",
    "gn:name":"Thinkedanda",
    "gn:population":0,
    "gn:timezone":"Asia/Kathmandu",
    "iso:country":"NP",
    "wof:name":"Thinkedanda",
    "wof:placetype":"locality"
},
  "geometry": {"coordinates":[81.88887,28.92845],"type":"Point"}
}