{
  "type": "Feature",
  "properties": {
    "gn:admin1_code":"CR",
    "gn:admin2_code":"1",
    "gn:admin3_code":"23",
    "gn:admin4_code":"230036",
    "gn:asciiname":"Gairatol",
    "gn:country_code":"NP",
    "gn:dem":984,
    "gn:feature_class":"P",
    "gn:feature_code":"PPLL",
    "gn:name":"Gairatol",
    "gn:population":0,
    "gn:timezone":"Asia/Kathmandu",
    "iso:country":"NP",
    "wof:name":"Gairatol",
    "wof:placetype":"locality"
},
  "geometry": {"coordinates":[85.77688000000001,27.71163],"type":"Point"}
}