{
  "type": "Feature",
  "properties": {
    "gn:admin1_code":"FR",
    "gn:admin2_code":"14.0",
    "gn:admin3_code":"67.0",
    "gn:admin4_code":"670005.0",
    "gn:asciiname":"Neta",
    "gn:country_code":"NP",
    "gn:dem":1773,
    "gn:feature_class":"P",
    "gn:feature_code":"PPLL",
    "gn:name":"Neta",
    "gn:population":0,
    "gn:timezone":"Asia/Kathmandu",
    "iso:country":"NP",
    "name:ceb_x_preferred":[
        "Neta"
    ],
    "name:deu_x_preferred":[
        "Neta"
    ],
    "name:fra_x_preferred":[
        "Neta"
    ],
    "name:swe_x_preferred":[
        "Neta"
    ],
    "wof:name":"Neta",
    "wof:placetype":"locality"
},
  "geometry": {"coordinates":[81.69801,29.65584],"type":"Point"}
}