{
  "type": "Feature",
  "properties": {
    "gn:admin1_code":"MR",
    "gn:admin2_code":"2.0",
    "gn:admin3_code":"59.0",
    "gn:admin4_code":"590042.0",
    "gn:asciiname":"Bankikholagaun",
    "gn:country_code":"NP",
    "gn:dem":583,
    "gn:feature_class":"P",
    "gn:feature_code":"PPLL",
    "gn:name":"Bankikholagaun",
    "gn:population":0,
    "gn:timezone":"Asia/Kathmandu",
    "iso:country":"NP",
    "wof:name":"Bankikholagaun",
    "wof:placetype":"locality"
},
  "geometry": {"coordinates":[82.01523,28.52893],"type":"Point"}
}