{
  "type": "Feature",
  "properties": {
    "gn:admin1_code":"ER",
    "gn:admin2_code":"13.0",
    "gn:admin3_code":"14.0",
    "gn:admin4_code":"140002.0",
    "gn:asciiname":"Balamta",
    "gn:country_code":"NP",
    "gn:dem":1076,
    "gn:feature_class":"P",
    "gn:feature_code":"PPLL",
    "gn:name":"Balamta",
    "gn:population":0,
    "gn:timezone":"Asia/Kathmandu",
    "iso:country":"NP",
    "wof:name":"Balamta",
    "wof:placetype":"locality"
},
  "geometry": {"coordinates":[86.67964000000001,27.08558],"type":"Point"}
}