{
  "type": "Feature",
  "properties": {
    "gn:admin1_code":"WR",
    "gn:admin2_code":"8",
    "gn:admin3_code":"48",
    "gn:admin4_code":"480056",
    "gn:asciiname":"Sunwach",
    "gn:country_code":"NP",
    "gn:dem":112,
    "gn:feature_class":"P",
    "gn:feature_code":"PPLL",
    "gn:name":"Sunwach",
    "gn:population":0,
    "gn:timezone":"Asia/Kathmandu",
    "iso:country":"NP",
    "wof:name":"Sunwach",
    "wof:placetype":"locality"
},
  "geometry": {"coordinates":[83.67373000000001,27.51716],"type":"Point"}
}