{
  "type": "Feature",
  "properties": {
    "gn:admin1_code":"00",
    "gn:asciiname":"Phurlun",
    "gn:country_code":"NP",
    "gn:dem":1387,
    "gn:feature_class":"P",
    "gn:feature_code":"PPL",
    "gn:name":"Phurlu\u1e45",
    "gn:population":0,
    "gn:timezone":"Asia/Kathmandu",
    "iso:country":"NP",
    "name:nep_x_preferred":[
        "Phurlu\u1e45"
    ],
    "wof:name":"Phurlun",
    "wof:placetype":"locality"
},
  "geometry": {"coordinates":[86.01392,27.65924],"type":"Point"}
}