{
  "type": "Feature",
  "properties": {
    "gn:admin1_code":"MR",
    "gn:admin2_code":"12",
    "gn:admin3_code":"56.0",
    "gn:admin4_code":"560039.0",
    "gn:asciiname":"Mahadeva",
    "gn:country_code":"NP",
    "gn:dem":671,
    "gn:feature_class":"P",
    "gn:feature_code":"PPLL",
    "gn:name":"Mahadeva",
    "gn:population":0,
    "gn:timezone":"Asia/Kathmandu",
    "iso:country":"NP",
    "name:bih_x_preferred":[
        "\u092e\u0939\u093e\u0926\u0947\u0935\u093e"
    ],
    "name:deu_x_preferred":[
        "Mahadeva"
    ],
    "name:dty_x_preferred":[
        "\u092e\u0939\u093e\u0926\u0947\u0935\u093e \u0917\u093e\u0935\u093f\u0938"
    ],
    "name:ind_x_preferred":[
        "Mahadewa"
    ],
    "name:nep_x_preferred":[
        "\u092e\u0939\u093e\u0926\u0947\u0935\u093e"
    ],
    "name:pol_x_preferred":[
        "Mahadewa"
    ],
    "name:por_x_preferred":[
        "Mahadeva"
    ],
    "wof:name":"Mahadeva",
    "wof:placetype":"locality"
},
  "geometry": {"coordinates":[82.49606999999997,28.03901],"type":"Point"}
}