{
  "type": "Feature",
  "properties": {
    "gn:admin1_code":"CR",
    "gn:admin2_code":"1",
    "gn:admin3_code":"28",
    "gn:admin4_code":"280017",
    "gn:asciiname":"Gutol",
    "gn:country_code":"NP",
    "gn:dem":1474,
    "gn:feature_class":"P",
    "gn:feature_code":"PPLL",
    "gn:name":"Gutol",
    "gn:population":0,
    "gn:timezone":"Asia/Kathmandu",
    "iso:country":"NP",
    "wof:name":"Gutol",
    "wof:placetype":"locality"
},
  "geometry": {"coordinates":[85.09129,27.97298],"type":"Point"}
}