{
  "type": "Feature",
  "properties": {
    "gn:admin1_code":"WR",
    "gn:admin2_code":"4",
    "gn:admin3_code":"36.0",
    "gn:admin4_code":"360016.0",
    "gn:asciiname":"Kaushilatar",
    "gn:country_code":"NP",
    "gn:dem":440,
    "gn:feature_class":"P",
    "gn:feature_code":"PPLL",
    "gn:name":"Kaushilatar",
    "gn:population":0,
    "gn:timezone":"Asia/Kathmandu",
    "iso:country":"NP",
    "wof:name":"Kaushilatar",
    "wof:placetype":"locality"
},
  "geometry": {"coordinates":[84.44051,27.98673],"type":"Point"}
}