{
  "type": "Feature",
  "properties": {
    "gn:admin1_code":"WR",
    "gn:admin2_code":"8",
    "gn:admin3_code":"46.0",
    "gn:admin4_code":"460030.0",
    "gn:asciiname":"Digam",
    "gn:country_code":"NP",
    "gn:dem":1386,
    "gn:feature_class":"P",
    "gn:feature_code":"PPLL",
    "gn:name":"Digam",
    "gn:population":0,
    "gn:timezone":"Asia/Kathmandu",
    "iso:country":"NP",
    "name:ceb_x_preferred":[
        "Digam"
    ],
    "name:fra_x_preferred":[
        "Digam"
    ],
    "name:hin_x_preferred":[
        "\u0926\u093f\u0917\u092e"
    ],
    "name:msa_x_preferred":[
        "Digam"
    ],
    "name:nep_x_preferred":[
        "\u0926\u093f\u0917\u092e"
    ],
    "name:new_x_preferred":[
        "\u0926\u093f\u0917\u092e"
    ],
    "name:pol_x_preferred":[
        "Digam"
    ],
    "wof:name":"Digam",
    "wof:placetype":"locality"
},
  "geometry": {"coordinates":[83.37571,27.99634],"type":"Point"}
}