{
  "type": "Feature",
  "properties": {
    "gn:admin1_code":"WR",
    "gn:admin2_code":"8",
    "gn:admin3_code":"50.0",
    "gn:admin4_code":"500060.0",
    "gn:asciiname":"Dagadauwa",
    "gn:country_code":"NP",
    "gn:dem":121,
    "gn:feature_class":"P",
    "gn:feature_code":"PPLL",
    "gn:name":"Dagadauwa",
    "gn:population":0,
    "gn:timezone":"Asia/Kathmandu",
    "iso:country":"NP",
    "wof:name":"Dagadauwa",
    "wof:placetype":"locality"
},
  "geometry": {"coordinates":[82.81271,27.61172],"type":"Point"}
}