{
  "type": "Feature",
  "properties": {
    "gn:admin1_code":"MR",
    "gn:admin2_code":"2",
    "gn:admin3_code":"60.0",
    "gn:admin4_code":"600012.0",
    "gn:asciiname":"Hadakot",
    "gn:country_code":"NP",
    "gn:dem":1286,
    "gn:feature_class":"P",
    "gn:feature_code":"PPLL",
    "gn:name":"Hadakot",
    "gn:population":0,
    "gn:timezone":"Asia/Kathmandu",
    "iso:country":"NP",
    "wof:name":"Hadakot",
    "wof:placetype":"locality"
},
  "geometry": {"coordinates":[81.56126,28.96531],"type":"Point"}
}