{
  "type": "Feature",
  "properties": {
    "gn:admin1_code":"MR",
    "gn:admin2_code":"2.0",
    "gn:admin3_code":"57.0",
    "gn:admin4_code":"570024.0",
    "gn:asciiname":"Kharche",
    "gn:country_code":"NP",
    "gn:dem":232,
    "gn:feature_class":"P",
    "gn:feature_code":"PPLL",
    "gn:name":"Kharche",
    "gn:population":0,
    "gn:timezone":"Asia/Kathmandu",
    "iso:country":"NP",
    "wof:name":"Kharche",
    "wof:placetype":"locality"
},
  "geometry": {"coordinates":[82.00998,28.00033],"type":"Point"}
}