{
  "type": "Feature",
  "properties": {
    "gn:admin1_code":"CR",
    "gn:admin2_code":"5",
    "gn:admin3_code":"17.0",
    "gn:admin4_code":"170084.0",
    "gn:asciiname":"Sakhuwa",
    "gn:country_code":"NP",
    "gn:dem":119,
    "gn:feature_class":"P",
    "gn:feature_code":"PPLL",
    "gn:name":"Sakhuwa",
    "gn:population":0,
    "gn:timezone":"Asia/Kathmandu",
    "iso:country":"NP",
    "name:ceb_x_preferred":[
        "Sakhuawa"
    ],
    "name:mai_x_preferred":[
        "\u0938\u0916\u0942\u0905\u0935\u093e"
    ],
    "name:msa_x_preferred":[
        "Sakhuwa"
    ],
    "name:nep_x_preferred":[
        "\u0938\u0916\u0942\u0905\u0935\u093e"
    ],
    "name:new_x_preferred":[
        "\u0938\u0916\u0942\u0905\u0935\u093e"
    ],
    "name:pol_x_preferred":[
        "Sakhuawa"
    ],
    "wof:name":"Sakhuwa",
    "wof:placetype":"locality"
},
  "geometry": {"coordinates":[85.97691999999998,26.8563],"type":"Point"}
}