{
  "type": "Feature",
  "properties": {
    "gn:admin1_code":"FR",
    "gn:admin2_code":"14.0",
    "gn:admin3_code":"68.0",
    "gn:admin4_code":"680044.0",
    "gn:asciiname":"Selapakha",
    "gn:country_code":"NP",
    "gn:dem":2196,
    "gn:feature_class":"P",
    "gn:feature_code":"PPLL",
    "gn:name":"Selapakha",
    "gn:population":0,
    "gn:timezone":"Asia/Kathmandu",
    "iso:country":"NP",
    "wof:name":"Selapakha",
    "wof:placetype":"locality"
},
  "geometry": {"coordinates":[81.22665000000001,29.60557],"type":"Point"}
}