{
  "type": "Feature",
  "properties": {
    "gn:admin1_code":"ER",
    "gn:admin2_code":"7.0",
    "gn:admin3_code":"6.0",
    "gn:admin4_code":"60026.0",
    "gn:asciiname":"Magartol",
    "gn:country_code":"NP",
    "gn:dem":93,
    "gn:feature_class":"P",
    "gn:feature_code":"PPLL",
    "gn:name":"Magartol",
    "gn:population":0,
    "gn:timezone":"Asia/Kathmandu",
    "iso:country":"NP",
    "wof:name":"Magartol",
    "wof:placetype":"locality"
},
  "geometry": {"coordinates":[87.15043,26.59357],"type":"Point"}
}