{
  "type": "Feature",
  "properties": {
    "gn:admin1_code":"WR",
    "gn:admin2_code":"4.0",
    "gn:admin3_code":"39.0",
    "gn:admin4_code":"390013.0",
    "gn:asciiname":"Thakurigaun",
    "gn:country_code":"NP",
    "gn:dem":744,
    "gn:feature_class":"P",
    "gn:feature_code":"PPLL",
    "gn:name":"Thakurigaun",
    "gn:population":0,
    "gn:timezone":"Asia/Kathmandu",
    "iso:country":"NP",
    "wof:name":"Thakurigaun",
    "wof:placetype":"locality"
},
  "geometry": {"coordinates":[83.82654000000002,27.90612],"type":"Point"}
}