{
  "type": "Feature",
  "properties": {
    "gn:admin1_code":"00",
    "gn:asciiname":"Salankar",
    "gn:country_code":"NP",
    "gn:dem":1148,
    "gn:feature_class":"P",
    "gn:feature_code":"PPL",
    "gn:name":"Sal\u0101\u1e45kar",
    "gn:population":0,
    "gn:timezone":"Asia/Kathmandu",
    "iso:country":"NP",
    "wof:name":"Salankar",
    "wof:placetype":"locality"
},
  "geometry": {"coordinates":[86.63149,27.36361],"type":"Point"}
}