{
  "type": "Feature",
  "properties": {
    "gn:admin1_code":"FR",
    "gn:admin2_code":"14.0",
    "gn:admin3_code":"67.0",
    "gn:admin4_code":"670026.0",
    "gn:asciiname":"Balu",
    "gn:country_code":"NP",
    "gn:dem":1292,
    "gn:feature_class":"P",
    "gn:feature_code":"PPLL",
    "gn:name":"Balu",
    "gn:population":0,
    "gn:timezone":"Asia/Kathmandu",
    "iso:country":"NP",
    "name:ceb_x_preferred":[
        "Balu"
    ],
    "name:deu_x_preferred":[
        "Balu"
    ],
    "name:rus_x_preferred":[
        "\u0411\u0430\u043b\u0443"
    ],
    "name:swe_x_preferred":[
        "Balu"
    ],
    "wof:name":"Balu",
    "wof:placetype":"locality"
},
  "geometry": {"coordinates":[81.72561,29.39733],"type":"Point"}
}