{
  "type": "Feature",
  "properties": {
    "gn:admin1_code":"MR",
    "gn:admin2_code":"2",
    "gn:admin3_code":"61.0",
    "gn:admin4_code":"610006.0",
    "gn:asciiname":"Ghuskholagaun",
    "gn:country_code":"NP",
    "gn:dem":2399,
    "gn:feature_class":"P",
    "gn:feature_code":"PPLL",
    "gn:name":"Ghuskholagaun",
    "gn:population":0,
    "gn:timezone":"Asia/Kathmandu",
    "iso:country":"NP",
    "wof:name":"Ghuskholagaun",
    "wof:placetype":"locality"
},
  "geometry": {"coordinates":[81.92684,28.76936],"type":"Point"}
}