{
  "type": "Feature",
  "properties": {
    "gn:admin1_code":"CR",
    "gn:admin2_code":"1",
    "gn:admin3_code":"23",
    "gn:admin4_code":"230029",
    "gn:asciiname":"Timbu",
    "gn:country_code":"NP",
    "gn:dem":1637,
    "gn:feature_class":"P",
    "gn:feature_code":"PPLL",
    "gn:name":"Timbu",
    "gn:population":0,
    "gn:timezone":"Asia/Kathmandu",
    "iso:country":"NP",
    "wof:name":"Timbu",
    "wof:placetype":"locality"
},
  "geometry": {"coordinates":[85.55179,27.9585],"type":"Point"}
}