{
  "type": "Feature",
  "properties": {
    "gn:admin1_code":"CR",
    "gn:admin2_code":"1",
    "gn:admin3_code":"24.0",
    "gn:admin4_code":"240034.0",
    "gn:asciiname":"Hokse",
    "gn:country_code":"NP",
    "gn:dem":851,
    "gn:feature_class":"P",
    "gn:feature_code":"PPLL",
    "gn:name":"Hokse",
    "gn:population":0,
    "gn:timezone":"Asia/Kathmandu",
    "iso:country":"NP",
    "wof:name":"Hokse",
    "wof:placetype":"locality"
},
  "geometry": {"coordinates":[85.65895,27.65761],"type":"Point"}
}