{
  "type": "Feature",
  "properties": {
    "gn:admin1_code":"WR",
    "gn:admin2_code":"4",
    "gn:admin3_code":"40.0",
    "gn:admin4_code":"400034.0",
    "gn:asciiname":"Lamdanda",
    "gn:country_code":"NP",
    "gn:dem":1400,
    "gn:feature_class":"P",
    "gn:feature_code":"PPLL",
    "gn:name":"Lamdanda",
    "gn:population":0,
    "gn:timezone":"Asia/Kathmandu",
    "iso:country":"NP",
    "wof:name":"Lamdanda",
    "wof:placetype":"locality"
},
  "geometry": {"coordinates":[83.99089000000002,28.32423],"type":"Point"}
}