{
  "type": "Feature",
  "properties": {
    "gn:admin1_code":"ER",
    "gn:admin2_code":"7",
    "gn:admin3_code":"10.0",
    "gn:admin4_code":"100027.0",
    "gn:asciiname":"Chaurikharka",
    "gn:country_code":"NP",
    "gn:dem":2072,
    "gn:feature_class":"P",
    "gn:feature_code":"PPLL",
    "gn:name":"Chaurikharka",
    "gn:population":0,
    "gn:timezone":"Asia/Kathmandu",
    "iso:country":"NP",
    "name:bih_x_preferred":[
        "\u091a\u094c\u0902\u0930\u0940\u0916\u0930\u094d\u0915"
    ],
    "name:ceb_x_preferred":[
        "Chaurikharka"
    ],
    "name:deu_x_preferred":[
        "Chaurikharka"
    ],
    "name:fra_x_preferred":[
        "Chaurikharka"
    ],
    "name:hin_x_preferred":[
        "\u091a\u094c\u0902\u0930\u0940\u0916\u0930\u094d\u0915"
    ],
    "name:mai_x_preferred":[
        "\u091a\u094c\u0902\u0930\u0940\u0916\u0930\u094d\u0915"
    ],
    "name:msa_x_preferred":[
        "Chaurikharka"
    ],
    "name:nep_x_preferred":[
        "\u091a\u094c\u0902\u0930\u0940\u0916\u0930\u094d\u0915"
    ],
    "name:new_x_preferred":[
        "\u091a\u094c\u0930\u0940\u0916\u0930\u094d\u0915"
    ],
    "name:pol_x_preferred":[
        "Chaurikharka"
    ],
    "wof:name":"Chaurikharka",
    "wof:placetype":"locality"
},
  "geometry": {"coordinates":[87.06044,27.27107],"type":"Point"}
}