{
  "type": "Feature",
  "properties": {
    "gn:admin1_code":"MR",
    "gn:admin2_code":"6",
    "gn:admin3_code":"66.0",
    "gn:admin4_code":"660007.0",
    "gn:asciiname":"Tibuk",
    "gn:country_code":"NP",
    "gn:dem":2397,
    "gn:feature_class":"P",
    "gn:feature_code":"PPLL",
    "gn:name":"Tibuk",
    "gn:population":0,
    "gn:timezone":"Asia/Kathmandu",
    "iso:country":"NP",
    "wof:name":"Tibuk",
    "wof:placetype":"locality"
},
  "geometry": {"coordinates":[81.78714000000002,29.97351],"type":"Point"}
}