{
  "type": "Feature",
  "properties": {
    "gn:admin1_code":"MR",
    "gn:admin2_code":"12",
    "gn:admin3_code":"52",
    "gn:admin4_code":"520049",
    "gn:asciiname":"Sadanthuta",
    "gn:country_code":"NP",
    "gn:dem":1199,
    "gn:feature_class":"P",
    "gn:feature_code":"PPLL",
    "gn:name":"Sadanthuta",
    "gn:population":0,
    "gn:timezone":"Asia/Kathmandu",
    "iso:country":"NP",
    "wof:name":"Sadanthuta",
    "wof:placetype":"locality"
},
  "geometry": {"coordinates":[83.01334,28.12268],"type":"Point"}
}