{
  "type": "Feature",
  "properties": {
    "gn:admin1_code":"WR",
    "gn:admin2_code":"4",
    "gn:admin3_code":"40.0",
    "gn:admin4_code":"400022.0",
    "gn:asciiname":"Talbesi",
    "gn:country_code":"NP",
    "gn:dem":805,
    "gn:feature_class":"P",
    "gn:feature_code":"PPLL",
    "gn:name":"Talbesi",
    "gn:population":0,
    "gn:timezone":"Asia/Kathmandu",
    "iso:country":"NP",
    "wof:name":"Talbesi",
    "wof:placetype":"locality"
},
  "geometry": {"coordinates":[84.03683000000002,28.19274],"type":"Point"}
}