{
  "type": "Feature",
  "properties": {
    "gn:admin1_code":"FR",
    "gn:admin2_code":"9",
    "gn:admin3_code":"74",
    "gn:admin4_code":"740024.0",
    "gn:asciiname":"Lekaijar",
    "gn:country_code":"NP",
    "gn:dem":1775,
    "gn:feature_class":"P",
    "gn:feature_code":"PPLL",
    "gn:name":"Lekaijar",
    "gn:population":0,
    "gn:timezone":"Asia/Kathmandu",
    "iso:country":"NP",
    "wof:name":"Lekaijar",
    "wof:placetype":"locality"
},
  "geometry": {"coordinates":[80.42171999999999,29.50384],"type":"Point"}
}