{
  "type": "Feature",
  "properties": {
    "gn:admin1_code":"MR",
    "gn:admin2_code":"12",
    "gn:admin3_code":"54",
    "gn:admin4_code":"540032",
    "gn:asciiname":"Kida",
    "gn:country_code":"NP",
    "gn:dem":1995,
    "gn:feature_class":"P",
    "gn:feature_code":"PPLL",
    "gn:name":"Kida",
    "gn:population":0,
    "gn:timezone":"Asia/Kathmandu",
    "iso:country":"NP",
    "name:ceb_x_preferred":[
        "Kida"
    ],
    "name:ita_x_preferred":[
        "Kida"
    ],
    "name:swe_x_preferred":[
        "Kida"
    ],
    "wof:name":"Kida",
    "wof:placetype":"locality"
},
  "geometry": {"coordinates":[82.65643,28.67348],"type":"Point"}
}