{
  "type": "Feature",
  "properties": {
    "gn:admin1_code":"MR",
    "gn:admin2_code":"6",
    "gn:admin3_code":"66.0",
    "gn:admin4_code":"660018.0",
    "gn:asciiname":"Tijam",
    "gn:country_code":"NP",
    "gn:dem":5107,
    "gn:feature_class":"P",
    "gn:feature_code":"PPLL",
    "gn:name":"Tijam",
    "gn:population":0,
    "gn:timezone":"Asia/Kathmandu",
    "iso:country":"NP",
    "wof:name":"Tijam",
    "wof:placetype":"locality"
},
  "geometry": {"coordinates":[81.3383,30.11708],"type":"Point"}
}