{
  "type": "Feature",
  "properties": {
    "gn:admin1_code":"00",
    "gn:asciiname":"Ranbagar Bhutaha",
    "gn:country_code":"NP",
    "gn:dem":83,
    "gn:feature_class":"P",
    "gn:feature_code":"PPL",
    "gn:name":"R\u0101nbagar Bhu\u1e6d\u0101h\u0101",
    "gn:population":0,
    "gn:timezone":"Asia/Kathmandu",
    "iso:country":"NP",
    "name:nep_x_preferred":[
        "R\u0101nbagar Bhu\u1e6d\u0101h\u0101"
    ],
    "wof:name":"Ranbagar Bhutaha",
    "wof:placetype":"locality"
},
  "geometry": {"coordinates":[87.11476,26.52742000000001],"type":"Point"}
}