{
  "type": "Feature",
  "properties": {
    "gn:admin1_code":"ER",
    "gn:admin2_code":"13",
    "gn:admin3_code":"13.0",
    "gn:admin4_code":"130014.0",
    "gn:asciiname":"Chhita Pokhari",
    "gn:country_code":"NP",
    "gn:dem":2123,
    "gn:feature_class":"P",
    "gn:feature_code":"PPLL",
    "gn:name":"Chhita Pokhari",
    "gn:population":0,
    "gn:timezone":"Asia/Kathmandu",
    "iso:country":"NP",
    "wof:name":"Chhita Pokhari",
    "wof:placetype":"locality"
},
  "geometry": {"coordinates":[86.83508,27.10304],"type":"Point"}
}