{
  "type": "Feature",
  "properties": {
    "gn:admin1_code":"WR",
    "gn:admin2_code":"4.0",
    "gn:asciiname":"Mirkot",
    "gn:country_code":"NP",
    "gn:dem":664,
    "gn:feature_class":"P",
    "gn:feature_code":"PPL",
    "gn:name":"Mirkot",
    "gn:population":0,
    "gn:timezone":"Asia/Kathmandu",
    "iso:country":"NP",
    "name:ceb_x_preferred":[
        "Mirkot"
    ],
    "name:deu_x_preferred":[
        "Mirkot"
    ],
    "name:mai_x_preferred":[
        "\u092e\u093f\u0930\u0915\u094b\u091f"
    ],
    "name:nep_x_preferred":[
        "\u092e\u093f\u0930\u0915\u094b\u091f"
    ],
    "name:pol_x_preferred":[
        "Bhirkot"
    ],
    "wof:name":"Mirkot",
    "wof:placetype":"locality"
},
  "geometry": {"coordinates":[84.5372,27.99406],"type":"Point"}
}