{
  "type": "Feature",
  "properties": {
    "gn:admin1_code":"CR",
    "gn:admin2_code":"5",
    "gn:admin3_code":"21",
    "gn:admin4_code":"210012",
    "gn:asciiname":"Surke",
    "gn:country_code":"NP",
    "gn:dem":1702,
    "gn:feature_class":"P",
    "gn:feature_code":"PPLL",
    "gn:name":"Surke",
    "gn:population":0,
    "gn:timezone":"Asia/Kathmandu",
    "iso:country":"NP",
    "wof:name":"Surke",
    "wof:placetype":"locality"
},
  "geometry": {"coordinates":[85.98808000000002,27.50566],"type":"Point"}
}