{
  "type": "Feature",
  "properties": {
    "gn:admin1_code":"CR",
    "gn:admin2_code":"11.0",
    "gn:admin3_code":"33.0",
    "gn:admin4_code":"330054.0",
    "gn:asciiname":"Sipure",
    "gn:country_code":"NP",
    "gn:dem":96,
    "gn:feature_class":"P",
    "gn:feature_code":"PPLL",
    "gn:name":"Sipure",
    "gn:population":0,
    "gn:timezone":"Asia/Kathmandu",
    "iso:country":"NP",
    "wof:name":"Sipure",
    "wof:placetype":"locality"
},
  "geometry": {"coordinates":[85.13748000000002,27.0029],"type":"Point"}
}