{
  "type": "Feature",
  "properties": {
    "gn:admin1_code":"CR",
    "gn:admin2_code":"1",
    "gn:admin3_code":"28",
    "gn:admin4_code":"280008",
    "gn:asciiname":"Ashok Batika",
    "gn:country_code":"NP",
    "gn:dem":1020,
    "gn:feature_class":"P",
    "gn:feature_code":"PPLL",
    "gn:name":"Ashok Batika",
    "gn:population":0,
    "gn:timezone":"Asia/Kathmandu",
    "iso:country":"NP",
    "wof:name":"Ashok Batika",
    "wof:placetype":"locality"
},
  "geometry": {"coordinates":[85.17243000000001,27.91909],"type":"Point"}
}