{
  "type": "Feature",
  "properties": {
    "gn:admin1_code":"FR",
    "gn:admin2_code":"14",
    "gn:admin3_code":"68",
    "gn:admin4_code":"680040",
    "gn:asciiname":"Thakunna",
    "gn:country_code":"NP",
    "gn:dem":2537,
    "gn:feature_class":"P",
    "gn:feature_code":"PPLL",
    "gn:name":"Thakunna",
    "gn:population":0,
    "gn:timezone":"Asia/Kathmandu",
    "iso:country":"NP",
    "wof:name":"Thakunna",
    "wof:placetype":"locality"
},
  "geometry": {"coordinates":[81.32198000000002,29.57403],"type":"Point"}
}