{
  "type": "Feature",
  "properties": {
    "gn:admin1_code":"WR",
    "gn:admin2_code":"4.0",
    "gn:admin3_code":"38.0",
    "gn:admin4_code":"380012.0",
    "gn:asciiname":"Mulabari",
    "gn:country_code":"NP",
    "gn:dem":809,
    "gn:feature_class":"P",
    "gn:feature_code":"PPLL",
    "gn:name":"Mulabari",
    "gn:population":0,
    "gn:timezone":"Asia/Kathmandu",
    "iso:country":"NP",
    "wof:name":"Mulabari",
    "wof:placetype":"locality"
},
  "geometry": {"coordinates":[84.11471,27.99774],"type":"Point"}
}