{
  "type": "Feature",
  "properties": {
    "gn:admin1_code":"CR",
    "gn:admin2_code":"11",
    "gn:admin3_code":"34",
    "gn:admin4_code":"340031",
    "gn:asciiname":"Gulariya",
    "gn:country_code":"NP",
    "gn:dem":92,
    "gn:feature_class":"P",
    "gn:feature_code":"PPLL",
    "gn:name":"Gulariya",
    "gn:population":0,
    "gn:timezone":"Asia/Kathmandu",
    "iso:country":"NP",
    "wof:name":"Gulariya",
    "wof:placetype":"locality"
},
  "geometry": {"coordinates":[84.70165,27.10572],"type":"Point"}
}