{
  "type": "Feature",
  "properties": {
    "gn:admin1_code":"MR",
    "gn:admin2_code":"12",
    "gn:admin3_code":"52",
    "gn:admin4_code":"520012",
    "gn:asciiname":"Riman",
    "gn:country_code":"NP",
    "gn:dem":1219,
    "gn:feature_class":"P",
    "gn:feature_code":"PPLL",
    "gn:name":"Riman",
    "gn:population":0,
    "gn:timezone":"Asia/Kathmandu",
    "iso:country":"NP",
    "wof:name":"Riman",
    "wof:placetype":"locality"
},
  "geometry": {"coordinates":[82.81289,28.09921],"type":"Point"}
}