{
  "type": "Feature",
  "properties": {
    "gn:admin1_code":"ER",
    "gn:admin2_code":"7.0",
    "gn:admin3_code":"8.0",
    "gn:admin4_code":"80012.0",
    "gn:asciiname":"Mekchana",
    "gn:country_code":"NP",
    "gn:dem":1795,
    "gn:feature_class":"P",
    "gn:feature_code":"PPLL",
    "gn:name":"Mekchana",
    "gn:population":0,
    "gn:timezone":"Asia/Kathmandu",
    "iso:country":"NP",
    "wof:name":"Mekchana",
    "wof:placetype":"locality"
},
  "geometry": {"coordinates":[87.51374,27.15918],"type":"Point"}
}