{
  "type": "Feature",
  "properties": {
    "gn:admin1_code":"ER",
    "gn:admin2_code":"13",
    "gn:admin3_code":"13.0",
    "gn:admin4_code":"130018.0",
    "gn:asciiname":"Harelodandagaun",
    "gn:country_code":"NP",
    "gn:dem":1544,
    "gn:feature_class":"P",
    "gn:feature_code":"PPLL",
    "gn:name":"Harelodandagaun",
    "gn:population":0,
    "gn:timezone":"Asia/Kathmandu",
    "iso:country":"NP",
    "wof:name":"Harelodandagaun",
    "wof:placetype":"locality"
},
  "geometry": {"coordinates":[86.89286,27.19849],"type":"Point"}
}