{
  "type": "Feature",
  "properties": {
    "gn:admin1_code":"ER",
    "gn:admin2_code":"7",
    "gn:admin3_code":"10.0",
    "gn:admin4_code":"100060.0",
    "gn:asciiname":"Nigure",
    "gn:country_code":"NP",
    "gn:dem":1507,
    "gn:feature_class":"P",
    "gn:feature_code":"PPLL",
    "gn:name":"Nigure",
    "gn:population":0,
    "gn:timezone":"Asia/Kathmandu",
    "iso:country":"NP",
    "wof:name":"Nigure",
    "wof:placetype":"locality"
},
  "geometry": {"coordinates":[87.10600000000002,27.34198],"type":"Point"}
}