{
  "type": "Feature",
  "properties": {
    "gn:admin1_code":"ER",
    "gn:admin2_code":"13.0",
    "gn:admin3_code":"14.0",
    "gn:admin4_code":"140012.0",
    "gn:asciiname":"Ratmate",
    "gn:country_code":"NP",
    "gn:dem":620,
    "gn:feature_class":"P",
    "gn:feature_code":"PPLL",
    "gn:name":"Ratmate",
    "gn:population":0,
    "gn:timezone":"Asia/Kathmandu",
    "iso:country":"NP",
    "name:ceb_x_preferred":[
        "Ratmate"
    ],
    "name:deu_x_preferred":[
        "Ratmate"
    ],
    "name:fra_x_preferred":[
        "Ratmate"
    ],
    "name:mai_x_preferred":[
        "\u0930\u093e\u0924\u092e\u093e\u091f\u0947"
    ],
    "name:msa_x_preferred":[
        "Ratmate"
    ],
    "name:nep_x_preferred":[
        "\u0930\u093e\u0924\u092e\u093e\u091f\u0947"
    ],
    "name:new_x_preferred":[
        "\u0930\u093e\u0924\u094d\u092e\u093e\u091f\u0947"
    ],
    "name:pol_x_preferred":[
        "Ratmate"
    ],
    "wof:name":"Ratmate",
    "wof:placetype":"locality"
},
  "geometry": {"coordinates":[86.35717,27.06398],"type":"Point"}
}