{
  "type": "Feature",
  "properties": {
    "gn:admin1_code":"CR",
    "gn:admin2_code":"11",
    "gn:admin3_code":"31",
    "gn:admin4_code":"310029",
    "gn:asciiname":"Rajrang",
    "gn:country_code":"NP",
    "gn:dem":573,
    "gn:feature_class":"P",
    "gn:feature_code":"PPLL",
    "gn:name":"Rajrang",
    "gn:population":0,
    "gn:timezone":"Asia/Kathmandu",
    "iso:country":"NP",
    "wof:name":"Rajrang",
    "wof:placetype":"locality"
},
  "geometry": {"coordinates":[84.77207,27.59001],"type":"Point"}
}