{
  "type": "Feature",
  "properties": {
    "gn:admin1_code":"CR",
    "gn:admin2_code":"5",
    "gn:admin3_code":"19",
    "gn:admin4_code":"190056",
    "gn:asciiname":"Bastipur",
    "gn:country_code":"NP",
    "gn:dem":151,
    "gn:feature_class":"P",
    "gn:feature_code":"PPLL",
    "gn:name":"Bastipur",
    "gn:population":0,
    "gn:timezone":"Asia/Kathmandu",
    "iso:country":"NP",
    "name:dty_x_preferred":[
        "\u092c\u0938\u094d\u0924\u093f\u092a\u0941\u0930"
    ],
    "name:fra_x_preferred":[
        "Bastipur"
    ],
    "name:nep_x_preferred":[
        "\u092c\u0938\u094d\u0924\u093f\u092a\u0941\u0930"
    ],
    "wof:name":"Bastipur",
    "wof:placetype":"locality"
},
  "geometry": {"coordinates":[85.62553,27.05816],"type":"Point"}
}