{
  "type": "Feature",
  "properties": {
    "gn:admin1_code":"CR",
    "gn:admin2_code":"1",
    "gn:admin3_code":"29",
    "gn:admin4_code":"290003",
    "gn:asciiname":"Brimdang",
    "gn:country_code":"NP",
    "gn:dem":3123,
    "gn:feature_class":"P",
    "gn:feature_code":"PPLL",
    "gn:name":"Brimdang",
    "gn:population":0,
    "gn:timezone":"Asia/Kathmandu",
    "iso:country":"NP",
    "wof:name":"Brimdang",
    "wof:placetype":"locality"
},
  "geometry": {"coordinates":[85.31992,28.20728],"type":"Point"}
}