{
  "type": "Feature",
  "properties": {
    "gn:admin1_code":"WR",
    "gn:admin2_code":"8",
    "gn:admin3_code":"48",
    "gn:admin4_code":"480026",
    "gn:asciiname":"Sugauli",
    "gn:country_code":"NP",
    "gn:dem":108,
    "gn:feature_class":"P",
    "gn:feature_code":"PPLL",
    "gn:name":"Sugauli",
    "gn:population":0,
    "gn:timezone":"Asia/Kathmandu",
    "iso:country":"NP",
    "name:ben_x_preferred":[
        "\u09b8\u09c1\u0997\u09be\u0989\u09b2\u09bf"
    ],
    "name:bih_x_preferred":[
        "\u0938\u0941\u0917\u094c\u0932\u0940"
    ],
    "name:bpy_x_preferred":[
        "\u09b8\u09c1\u0997\u09be\u0989\u09b2\u09bf"
    ],
    "name:cat_x_preferred":[
        "Sugauli"
    ],
    "name:hif_x_preferred":[
        "Sugauli"
    ],
    "name:hin_x_preferred":[
        "\u0938\u0941\u0917\u094c\u0932\u0940"
    ],
    "name:ita_x_preferred":[
        "Sugauli"
    ],
    "name:msa_x_preferred":[
        "Sugauli"
    ],
    "name:nld_x_preferred":[
        "Sugauli"
    ],
    "name:ori_x_preferred":[
        "\u0b38\u0b41\u0b17\u0b3e\u0b09\u0b32\u0b3f"
    ],
    "name:por_x_preferred":[
        "Sugauli"
    ],
    "name:vie_x_preferred":[
        "Sugauli"
    ],
    "name:zho_x_preferred":[
        "\u82cf\u9ad8\u5229"
    ],
    "wof:name":"Sugauli",
    "wof:placetype":"locality"
},
  "geometry": {"coordinates":[83.70729,27.46092],"type":"Point"}
}