{
  "type": "Feature",
  "properties": {
    "gn:admin1_code":"CR",
    "gn:admin2_code":"1",
    "gn:admin3_code":"30.0",
    "gn:admin4_code":"300032.0",
    "gn:asciiname":"Bhalubang",
    "gn:country_code":"NP",
    "gn:dem":704,
    "gn:feature_class":"P",
    "gn:feature_code":"PPLL",
    "gn:name":"Bhalubang",
    "gn:population":0,
    "gn:timezone":"Asia/Kathmandu",
    "iso:country":"NP",
    "wof:name":"Bhalubang",
    "wof:placetype":"locality"
},
  "geometry": {"coordinates":[84.87035999999998,27.92587],"type":"Point"}
}