{
  "type": "Feature",
  "properties": {
    "gn:admin1_code":"WR",
    "gn:admin2_code":"8",
    "gn:admin3_code":"47",
    "gn:admin4_code":"470025.0",
    "gn:asciiname":"Magare Gaun",
    "gn:country_code":"NP",
    "gn:dem":831,
    "gn:feature_class":"P",
    "gn:feature_code":"PPLL",
    "gn:name":"Magare Gaun",
    "gn:population":0,
    "gn:timezone":"Asia/Kathmandu",
    "iso:country":"NP",
    "wof:name":"Magare Gaun",
    "wof:placetype":"locality"
},
  "geometry": {"coordinates":[83.80553,27.8644],"type":"Point"}
}