{
  "type": "Feature",
  "properties": {
    "gn:admin1_code":"ER",
    "gn:admin2_code":"7",
    "gn:admin3_code":"10.0",
    "gn:admin4_code":"100026.0",
    "gn:asciiname":"Jyamire",
    "gn:country_code":"NP",
    "gn:dem":706,
    "gn:feature_class":"P",
    "gn:feature_code":"PPLL",
    "gn:name":"Jyamire",
    "gn:population":0,
    "gn:timezone":"Asia/Kathmandu",
    "iso:country":"NP",
    "wof:name":"Jyamire",
    "wof:placetype":"locality"
},
  "geometry": {"coordinates":[87.11976999999997,26.95141],"type":"Point"}
}