{
  "type": "Feature",
  "properties": {
    "gn:admin1_code":"WR",
    "gn:admin2_code":"4.0",
    "gn:admin3_code":"38.0",
    "gn:admin4_code":"380017.0",
    "gn:asciiname":"Khode",
    "gn:country_code":"NP",
    "gn:dem":630,
    "gn:feature_class":"P",
    "gn:feature_code":"PPLL",
    "gn:name":"Khode",
    "gn:population":0,
    "gn:timezone":"Asia/Kathmandu",
    "iso:country":"NP",
    "wof:name":"Khode",
    "wof:placetype":"locality"
},
  "geometry": {"coordinates":[84.44837,27.82944],"type":"Point"}
}