{
  "type": "Feature",
  "properties": {
    "gn:admin1_code":"MR",
    "gn:admin2_code":"12",
    "gn:admin3_code":"55",
    "gn:admin4_code":"550021",
    "gn:asciiname":"Chaudadi",
    "gn:country_code":"NP",
    "gn:dem":869,
    "gn:feature_class":"P",
    "gn:feature_code":"PPLL",
    "gn:name":"Chaudadi",
    "gn:population":0,
    "gn:timezone":"Asia/Kathmandu",
    "iso:country":"NP",
    "wof:name":"Chaudadi",
    "wof:placetype":"locality"
},
  "geometry": {"coordinates":[82.08126999999998,28.28206],"type":"Point"}
}