{
  "type": "Feature",
  "properties": {
    "gn:admin1_code":"WR",
    "gn:admin2_code":"4",
    "gn:admin3_code":"37",
    "gn:admin4_code":"370026",
    "gn:asciiname":"Hanu",
    "gn:country_code":"NP",
    "gn:dem":1184,
    "gn:feature_class":"P",
    "gn:feature_code":"PPLL",
    "gn:name":"Hanu",
    "gn:population":0,
    "gn:timezone":"Asia/Kathmandu",
    "iso:country":"NP",
    "wof:name":"Hanu",
    "wof:placetype":"locality"
},
  "geometry": {"coordinates":[84.54429,28.15929],"type":"Point"}
}