{
  "type": "Feature",
  "properties": {
    "gn:admin1_code":"WR",
    "gn:admin2_code":"4.0",
    "gn:admin3_code":"39.0",
    "gn:admin4_code":"390024.0",
    "gn:asciiname":"Sunkarne",
    "gn:country_code":"NP",
    "gn:dem":761,
    "gn:feature_class":"P",
    "gn:feature_code":"PPLL",
    "gn:name":"Sunkarne",
    "gn:population":0,
    "gn:timezone":"Asia/Kathmandu",
    "iso:country":"NP",
    "wof:name":"Sunkarne",
    "wof:placetype":"locality"
},
  "geometry": {"coordinates":[83.64100999999999,27.93562],"type":"Point"}
}