{
  "type": "Feature",
  "properties": {
    "gn:admin1_code":"ER",
    "gn:admin2_code":"7",
    "gn:admin3_code":"7.0",
    "gn:admin4_code":"70035.0",
    "gn:asciiname":"Tankhuwa",
    "gn:country_code":"NP",
    "gn:dem":1311,
    "gn:feature_class":"P",
    "gn:feature_code":"PPLL",
    "gn:name":"Tankhuwa",
    "gn:population":0,
    "gn:timezone":"Asia/Kathmandu",
    "iso:country":"NP",
    "name:bih_x_preferred":[
        "\u0924\u093e\u0901\u0916\u0941\u0935\u093e"
    ],
    "name:ceb_x_preferred":[
        "Tankhuwa"
    ],
    "name:mai_x_preferred":[
        "\u0924\u093e\u0901\u0916\u0941\u0935\u093e"
    ],
    "name:nep_x_preferred":[
        "\u0924\u093e\u0901\u0916\u0941\u0935\u093e"
    ],
    "name:new_x_preferred":[
        "\u0924\u0902\u0916\u0941\u0935\u093e"
    ],
    "name:pol_x_preferred":[
        "Tankhuwa"
    ],
    "wof:name":"Tankhuwa",
    "wof:placetype":"locality"
},
  "geometry": {"coordinates":[87.40884,27.01576],"type":"Point"}
}