{
  "type": "Feature",
  "properties": {
    "gn:admin1_code":"WR",
    "gn:admin2_code":"4.0",
    "gn:admin3_code":"39.0",
    "gn:admin4_code":"390051.0",
    "gn:asciiname":"Kambhir",
    "gn:country_code":"NP",
    "gn:dem":1674,
    "gn:feature_class":"P",
    "gn:feature_code":"PPLL",
    "gn:name":"Kambhir",
    "gn:population":0,
    "gn:timezone":"Asia/Kathmandu",
    "iso:country":"NP",
    "wof:name":"Kambhir",
    "wof:placetype":"locality"
},
  "geometry": {"coordinates":[83.82810000000001,28.17527],"type":"Point"}
}