{
  "type": "Feature",
  "properties": {
    "gn:admin1_code":"FR",
    "gn:admin2_code":"14.0",
    "gn:admin3_code":"69.0",
    "gn:admin4_code":"690006.0",
    "gn:asciiname":"Shriban",
    "gn:country_code":"NP",
    "gn:dem":2136,
    "gn:feature_class":"P",
    "gn:feature_code":"PPLL",
    "gn:name":"Shriban",
    "gn:population":0,
    "gn:timezone":"Asia/Kathmandu",
    "iso:country":"NP",
    "wof:name":"Shriban",
    "wof:placetype":"locality"
},
  "geometry": {"coordinates":[81.44981,29.17042],"type":"Point"}
}