{
  "type": "Feature",
  "properties": {
    "gn:admin1_code":"ER",
    "gn:admin2_code":"7",
    "gn:admin3_code":"5",
    "gn:admin4_code":"50018",
    "gn:asciiname":"Dangraha",
    "gn:country_code":"NP",
    "gn:dem":99,
    "gn:feature_class":"P",
    "gn:feature_code":"PPLL",
    "gn:name":"Dangraha",
    "gn:population":0,
    "gn:timezone":"Asia/Kathmandu",
    "iso:country":"NP",
    "name:ceb_x_preferred":[
        "Dangraha"
    ],
    "name:mai_x_preferred":[
        "\u0921\u0902\u0917\u094d\u0930\u093e\u0939\u093e"
    ],
    "name:msa_x_preferred":[
        "Dangraha"
    ],
    "name:nep_x_preferred":[
        "\u0926\u093e\u0902\u0917\u094d\u0930\u0939"
    ],
    "name:new_x_preferred":[
        "\u0926\u093e\u0902\u0917\u094d\u0930\u0939"
    ],
    "name:pol_x_preferred":[
        "Dangraha"
    ],
    "wof:name":"Dangraha",
    "wof:placetype":"locality"
},
  "geometry": {"coordinates":[87.33202,26.58775],"type":"Point"}
}