{
  "type": "Feature",
  "properties": {
    "gn:admin1_code":"CR",
    "gn:admin2_code":"5",
    "gn:admin3_code":"19",
    "gn:admin4_code":"190077",
    "gn:asciiname":"Daphkalitol",
    "gn:country_code":"NP",
    "gn:dem":175,
    "gn:feature_class":"P",
    "gn:feature_code":"PPLL",
    "gn:name":"Daphkalitol",
    "gn:population":0,
    "gn:timezone":"Asia/Kathmandu",
    "iso:country":"NP",
    "wof:name":"Daphkalitol",
    "wof:placetype":"locality"
},
  "geometry": {"coordinates":[85.64143,27.09694],"type":"Point"}
}