{
  "type": "Feature",
  "properties": {
    "gn:admin1_code":"ER",
    "gn:admin2_code":"13.0",
    "gn:admin3_code":"14.0",
    "gn:admin4_code":"140027.0",
    "gn:asciiname":"Ambote",
    "gn:country_code":"NP",
    "gn:dem":950,
    "gn:feature_class":"P",
    "gn:feature_code":"PPLL",
    "gn:name":"Ambote",
    "gn:population":0,
    "gn:timezone":"Asia/Kathmandu",
    "iso:country":"NP",
    "wof:name":"Ambote",
    "wof:placetype":"locality"
},
  "geometry": {"coordinates":[86.52693000000002,26.93015],"type":"Point"}
}