{
  "type": "Feature",
  "properties": {
    "gn:admin1_code":"MR",
    "gn:admin2_code":"12",
    "gn:admin3_code":"53",
    "gn:admin4_code":"530026.0",
    "gn:asciiname":"Satdobato",
    "gn:country_code":"NP",
    "gn:dem":1976,
    "gn:feature_class":"P",
    "gn:feature_code":"PPLL",
    "gn:name":"Satdobato",
    "gn:population":0,
    "gn:timezone":"Asia/Kathmandu",
    "iso:country":"NP",
    "wof:name":"Satdobato",
    "wof:placetype":"locality"
},
  "geometry": {"coordinates":[82.6651,28.27407],"type":"Point"}
}