{
  "type": "Feature",
  "properties": {
    "gn:admin1_code":"CR",
    "gn:admin2_code":"1",
    "gn:admin3_code":"24.0",
    "gn:admin4_code":"240021.0",
    "gn:asciiname":"Thakurigaun",
    "gn:country_code":"NP",
    "gn:dem":1002,
    "gn:feature_class":"P",
    "gn:feature_code":"PPLL",
    "gn:name":"Thakurigaun",
    "gn:population":0,
    "gn:timezone":"Asia/Kathmandu",
    "iso:country":"NP",
    "wof:name":"Thakurigaun",
    "wof:placetype":"locality"
},
  "geometry": {"coordinates":[85.64105000000001,27.59068],"type":"Point"}
}