{
  "type": "Feature",
  "properties": {
    "gn:admin1_code":"MR",
    "gn:admin2_code":"6",
    "gn:admin3_code":"63.0",
    "gn:admin4_code":"630011.0",
    "gn:asciiname":"Kuri Santha",
    "gn:country_code":"NP",
    "gn:dem":2746,
    "gn:feature_class":"P",
    "gn:feature_code":"PPLL",
    "gn:name":"Kuri Santha",
    "gn:population":0,
    "gn:timezone":"Asia/Kathmandu",
    "iso:country":"NP",
    "wof:name":"Kuri Santha",
    "wof:placetype":"locality"
},
  "geometry": {"coordinates":[82.32998000000001,29.21974],"type":"Point"}
}