{
  "type": "Feature",
  "properties": {
    "gn:admin1_code":"WR",
    "gn:admin2_code":"4",
    "gn:admin3_code":"37",
    "gn:admin4_code":"370051",
    "gn:asciiname":"Ramche",
    "gn:country_code":"NP",
    "gn:dem":905,
    "gn:feature_class":"P",
    "gn:feature_code":"PPLL",
    "gn:name":"Ramche",
    "gn:population":0,
    "gn:timezone":"Asia/Kathmandu",
    "iso:country":"NP",
    "wof:name":"Ramche",
    "wof:placetype":"locality"
},
  "geometry": {"coordinates":[84.46565,28.19356],"type":"Point"}
}