{
  "type": "Feature",
  "properties": {
    "gn:admin1_code":"MR",
    "gn:admin2_code":"6",
    "gn:admin3_code":"66.0",
    "gn:admin4_code":"660021.0",
    "gn:asciiname":"Rangherna",
    "gn:country_code":"NP",
    "gn:dem":2646,
    "gn:feature_class":"P",
    "gn:feature_code":"PPLL",
    "gn:name":"Rangherna",
    "gn:population":0,
    "gn:timezone":"Asia/Kathmandu",
    "iso:country":"NP",
    "wof:name":"Rangherna",
    "wof:placetype":"locality"
},
  "geometry": {"coordinates":[81.83445,29.81171],"type":"Point"}
}