{
  "type": "Feature",
  "properties": {
    "gn:admin1_code":"CR",
    "gn:admin2_code":"1",
    "gn:admin3_code":"27.0",
    "gn:admin4_code":"270021.0",
    "gn:asciiname":"Nakhandol",
    "gn:country_code":"NP",
    "gn:dem":1381,
    "gn:feature_class":"P",
    "gn:feature_code":"PPLL",
    "gn:name":"Nakhandol",
    "gn:population":0,
    "gn:timezone":"Asia/Kathmandu",
    "iso:country":"NP",
    "wof:name":"Nakhandol",
    "wof:placetype":"locality"
},
  "geometry": {"coordinates":[85.28206999999998,27.75489],"type":"Point"}
}