{
  "type": "Feature",
  "properties": {
    "gn:admin1_code":"ER",
    "gn:admin2_code":"7",
    "gn:admin3_code":"9",
    "gn:admin4_code":"90021",
    "gn:asciiname":"Wodare",
    "gn:country_code":"NP",
    "gn:dem":2157,
    "gn:feature_class":"P",
    "gn:feature_code":"PPLL",
    "gn:name":"Wodare",
    "gn:population":0,
    "gn:timezone":"Asia/Kathmandu",
    "iso:country":"NP",
    "wof:name":"Wodare",
    "wof:placetype":"locality"
},
  "geometry": {"coordinates":[87.41502,27.27151],"type":"Point"}
}