{
  "type": "Feature",
  "properties": {
    "gn:admin1_code":"CR",
    "gn:admin2_code":"11",
    "gn:admin3_code":"31",
    "gn:admin4_code":"310028",
    "gn:asciiname":"Bhitri Suwara",
    "gn:country_code":"NP",
    "gn:dem":338,
    "gn:feature_class":"P",
    "gn:feature_code":"PPLL",
    "gn:name":"Bhitri Suwara",
    "gn:population":0,
    "gn:timezone":"Asia/Kathmandu",
    "iso:country":"NP",
    "wof:name":"Bhitri Suwara",
    "wof:placetype":"locality"
},
  "geometry": {"coordinates":[85.20874000000001,27.3675],"type":"Point"}
}