{
  "type": "Feature",
  "properties": {
    "gn:admin1_code":"WR",
    "gn:admin2_code":"4.0",
    "gn:admin3_code":"39.0",
    "gn:admin4_code":"390044.0",
    "gn:asciiname":"Lampata",
    "gn:country_code":"NP",
    "gn:dem":866,
    "gn:feature_class":"P",
    "gn:feature_code":"PPLL",
    "gn:name":"Lampata",
    "gn:population":0,
    "gn:timezone":"Asia/Kathmandu",
    "iso:country":"NP",
    "wof:name":"Lampata",
    "wof:placetype":"locality"
},
  "geometry": {"coordinates":[83.82737,28.09165],"type":"Point"}
}