{
  "type": "Feature",
  "properties": {
    "gn:admin1_code":"MR",
    "gn:admin2_code":"2.0",
    "gn:admin3_code":"59.0",
    "gn:admin4_code":"590045.0",
    "gn:asciiname":"Haredanda",
    "gn:country_code":"NP",
    "gn:dem":1356,
    "gn:feature_class":"P",
    "gn:feature_code":"PPLL",
    "gn:name":"Haredanda",
    "gn:population":0,
    "gn:timezone":"Asia/Kathmandu",
    "iso:country":"NP",
    "wof:name":"Haredanda",
    "wof:placetype":"locality"
},
  "geometry": {"coordinates":[81.70109000000002,28.62718],"type":"Point"}
}