{
  "type": "Feature",
  "properties": {
    "gn:admin1_code":"WR",
    "gn:admin2_code":"3",
    "gn:admin3_code":"44",
    "gn:admin4_code":"440011",
    "gn:asciiname":"Chorgauda",
    "gn:country_code":"NP",
    "gn:dem":1284,
    "gn:feature_class":"P",
    "gn:feature_code":"PPLL",
    "gn:name":"Chorgauda",
    "gn:population":0,
    "gn:timezone":"Asia/Kathmandu",
    "iso:country":"NP",
    "wof:name":"Chorgauda",
    "wof:placetype":"locality"
},
  "geometry": {"coordinates":[83.69891,28.05654],"type":"Point"}
}