{
  "type": "Feature",
  "properties": {
    "gn:admin1_code":"FR",
    "gn:admin2_code":"14",
    "gn:admin3_code":"70.0",
    "gn:admin4_code":"700024.0",
    "gn:asciiname":"Rol",
    "gn:country_code":"NP",
    "gn:dem":1220,
    "gn:feature_class":"P",
    "gn:feature_code":"PPLL",
    "gn:name":"Rol",
    "gn:population":0,
    "gn:timezone":"Asia/Kathmandu",
    "iso:country":"NP",
    "wof:name":"Rol",
    "wof:placetype":"locality"
},
  "geometry": {"coordinates":[80.9111,29.30234],"type":"Point"}
}