{
  "type": "Feature",
  "properties": {
    "gn:admin1_code":"ER",
    "gn:admin2_code":"13",
    "gn:admin3_code":"12",
    "gn:admin4_code":"120018",
    "gn:asciiname":"Pahare",
    "gn:country_code":"NP",
    "gn:dem":1545,
    "gn:feature_class":"P",
    "gn:feature_code":"PPLL",
    "gn:name":"Pahare",
    "gn:population":0,
    "gn:timezone":"Asia/Kathmandu",
    "iso:country":"NP",
    "wof:name":"Pahare",
    "wof:placetype":"locality"
},
  "geometry": {"coordinates":[86.49224,27.30154000000001],"type":"Point"}
}