{
  "type": "Feature",
  "properties": {
    "gn:admin1_code":"ER",
    "gn:admin2_code":"10.0",
    "gn:admin3_code":"1.0",
    "gn:admin4_code":"10011.0",
    "gn:asciiname":"Kalikhola",
    "gn:country_code":"NP",
    "gn:dem":2201,
    "gn:feature_class":"P",
    "gn:feature_code":"PPLL",
    "gn:name":"Kalikhola",
    "gn:population":0,
    "gn:timezone":"Asia/Kathmandu",
    "iso:country":"NP",
    "name:bih_x_preferred":[
        "\u0915\u093e\u0932\u0940\u0916\u094b\u0932\u093e"
    ],
    "name:ceb_x_preferred":[
        "Kalikhola"
    ],
    "name:fra_x_preferred":[
        "Kalikhola"
    ],
    "name:mai_x_preferred":[
        "\u0915\u093e\u0932\u0940\u0916\u094b\u0932\u093e"
    ],
    "name:msa_x_preferred":[
        "Kalikhola"
    ],
    "name:nep_x_preferred":[
        "\u0915\u093e\u0932\u0940\u0916\u094b\u0932\u093e"
    ],
    "name:new_x_preferred":[
        "\u0915\u093e\u0932\u0940\u0916\u094b\u0932\u093e"
    ],
    "name:pol_x_preferred":[
        "Kalikhola"
    ],
    "wof:name":"Kalikhola",
    "wof:placetype":"locality"
},
  "geometry": {"coordinates":[87.97749,27.32889],"type":"Point"}
}