{
  "type": "Feature",
  "properties": {
    "gn:admin1_code":"MR",
    "gn:admin2_code":"6",
    "gn:admin3_code":"62.0",
    "gn:admin4_code":"620001.0",
    "gn:asciiname":"Phulak",
    "gn:country_code":"NP",
    "gn:dem":4340,
    "gn:feature_class":"P",
    "gn:feature_code":"PPLL",
    "gn:name":"Phulak",
    "gn:population":0,
    "gn:timezone":"Asia/Kathmandu",
    "iso:country":"NP",
    "wof:name":"Phulak",
    "wof:placetype":"locality"
},
  "geometry": {"coordinates":[82.93818,29.4613],"type":"Point"}
}