{
  "type": "Feature",
  "properties": {
    "gn:admin1_code":"FR",
    "gn:admin2_code":"14",
    "gn:admin3_code":"68",
    "gn:admin4_code":"680038",
    "gn:asciiname":"Dinnu",
    "gn:country_code":"NP",
    "gn:dem":2082,
    "gn:feature_class":"P",
    "gn:feature_code":"PPLL",
    "gn:name":"Dinnu",
    "gn:population":0,
    "gn:timezone":"Asia/Kathmandu",
    "iso:country":"NP",
    "wof:name":"Dinnu",
    "wof:placetype":"locality"
},
  "geometry": {"coordinates":[80.84804,29.64043],"type":"Point"}
}