{
  "type": "Feature",
  "properties": {
    "gn:admin1_code":"CR",
    "gn:admin2_code":"5",
    "gn:admin3_code":"20",
    "gn:admin4_code":"200018",
    "gn:asciiname":"Lahareni",
    "gn:country_code":"NP",
    "gn:dem":702,
    "gn:feature_class":"P",
    "gn:feature_code":"PPLL",
    "gn:name":"Lahareni",
    "gn:population":0,
    "gn:timezone":"Asia/Kathmandu",
    "iso:country":"NP",
    "wof:name":"Lahareni",
    "wof:placetype":"locality"
},
  "geometry": {"coordinates":[86.08726999999998,27.09074],"type":"Point"}
}