{
  "type": "Feature",
  "properties": {
    "gn:admin1_code":"MR",
    "gn:admin2_code":"12",
    "gn:admin3_code":"53",
    "gn:admin4_code":"530029",
    "gn:asciiname":"Misibang",
    "gn:country_code":"NP",
    "gn:dem":1054,
    "gn:feature_class":"P",
    "gn:feature_code":"PPLL",
    "gn:name":"Misibang",
    "gn:population":0,
    "gn:timezone":"Asia/Kathmandu",
    "iso:country":"NP",
    "wof:name":"Misibang",
    "wof:placetype":"locality"
},
  "geometry": {"coordinates":[82.59758000000002,28.33935],"type":"Point"}
}