{
  "type": "Feature",
  "properties": {
    "gn:admin1_code":"WR",
    "gn:admin2_code":"4",
    "gn:admin3_code":"36.0",
    "gn:admin4_code":"360012.0",
    "gn:asciiname":"Hatiya",
    "gn:country_code":"NP",
    "gn:dem":1044,
    "gn:feature_class":"P",
    "gn:feature_code":"PPLL",
    "gn:name":"Hatiya",
    "gn:population":0,
    "gn:timezone":"Asia/Kathmandu",
    "iso:country":"NP",
    "wof:name":"Hatiya",
    "wof:placetype":"locality"
},
  "geometry": {"coordinates":[84.6885,27.97153],"type":"Point"}
}