{
  "type": "Feature",
  "properties": {
    "gn:admin1_code":"FR",
    "gn:admin2_code":"14",
    "gn:admin3_code":"69",
    "gn:admin4_code":"690034",
    "gn:asciiname":"Kotgaun",
    "gn:country_code":"NP",
    "gn:dem":1132,
    "gn:feature_class":"P",
    "gn:feature_code":"PPLL",
    "gn:name":"Kotgaun",
    "gn:population":0,
    "gn:timezone":"Asia/Kathmandu",
    "iso:country":"NP",
    "wof:name":"Kotgaun",
    "wof:placetype":"locality"
},
  "geometry": {"coordinates":[81.30861999999998,29.14924],"type":"Point"}
}