{
  "type": "Feature",
  "properties": {
    "gn:admin1_code":"CR",
    "gn:admin2_code":"11",
    "gn:admin3_code":"32",
    "gn:admin4_code":"320042",
    "gn:asciiname":"Rampur",
    "gn:country_code":"NP",
    "gn:dem":85,
    "gn:feature_class":"P",
    "gn:feature_code":"PPLL",
    "gn:name":"Rampur",
    "gn:population":0,
    "gn:timezone":"Asia/Kathmandu",
    "iso:country":"NP",
    "wof:name":"Rampur",
    "wof:placetype":"locality"
},
  "geometry": {"coordinates":[85.30918,26.86479000000001],"type":"Point"}
}