{
  "type": "Feature",
  "properties": {
    "gn:admin1_code":"WR",
    "gn:admin2_code":"4.0",
    "gn:admin3_code":"39.0",
    "gn:admin4_code":"390025.0",
    "gn:asciiname":"Kapase",
    "gn:country_code":"NP",
    "gn:dem":1342,
    "gn:feature_class":"P",
    "gn:feature_code":"PPLL",
    "gn:name":"Kapase",
    "gn:population":0,
    "gn:timezone":"Asia/Kathmandu",
    "iso:country":"NP",
    "wof:name":"Kapase",
    "wof:placetype":"locality"
},
  "geometry": {"coordinates":[83.70896,28.01755],"type":"Point"}
}