{
  "type": "Feature",
  "properties": {
    "gn:admin1_code":"CR",
    "gn:admin2_code":"1",
    "gn:admin3_code":"30.0",
    "gn:admin4_code":"300022.0",
    "gn:asciiname":"Targaun",
    "gn:country_code":"NP",
    "gn:dem":834,
    "gn:feature_class":"P",
    "gn:feature_code":"PPLL",
    "gn:name":"Targaun",
    "gn:population":0,
    "gn:timezone":"Asia/Kathmandu",
    "iso:country":"NP",
    "wof:name":"Targaun",
    "wof:placetype":"locality"
},
  "geometry": {"coordinates":[85.09532,27.75293],"type":"Point"}
}