{
  "type": "Feature",
  "properties": {
    "gn:admin1_code":"FR",
    "gn:admin2_code":"14",
    "gn:admin3_code":"71.0",
    "gn:admin4_code":"710033.0",
    "gn:asciiname":"Phulbari",
    "gn:country_code":"NP",
    "gn:dem":163,
    "gn:feature_class":"P",
    "gn:feature_code":"PPLL",
    "gn:name":"Phulbari",
    "gn:population":0,
    "gn:timezone":"Asia/Kathmandu",
    "iso:country":"NP",
    "name:nep_x_preferred":[
        "Phulb\u0101ri\u0307\u0304"
    ],
    "name:und_x_variant":[
        "Phulw\u0101ri\u0101"
    ],
    "wof:name":"Phulbari",
    "wof:placetype":"locality"
},
  "geometry": {"coordinates":[80.70932999999999,28.59712],"type":"Point"}
}