{
  "type": "Feature",
  "properties": {
    "gn:admin1_code":"ER",
    "gn:admin2_code":"13",
    "gn:admin3_code":"13.0",
    "gn:admin4_code":"130025.0",
    "gn:asciiname":"Balchung",
    "gn:country_code":"NP",
    "gn:dem":1372,
    "gn:feature_class":"P",
    "gn:feature_code":"PPLL",
    "gn:name":"Balchung",
    "gn:population":0,
    "gn:timezone":"Asia/Kathmandu",
    "iso:country":"NP",
    "wof:name":"Balchung",
    "wof:placetype":"locality"
},
  "geometry": {"coordinates":[86.50790000000001,27.13952],"type":"Point"}
}