{
  "type": "Feature",
  "properties": {
    "iso:country":"NP",
    "name:bho_x_preferred":[
        "\u0927\u0941\u0932\u093f\u0916\u0947\u0932"
    ],
    "name:deu_x_preferred":[
        "Dhulikhel"
    ],
    "name:dty_x_preferred":[
        "\u0927\u0941\u0932\u093f\u0916\u0947\u0932"
    ],
    "name:eng_x_preferred":[
        "Dhulikhel"
    ],
    "name:fin_x_preferred":[
        "Dhulikhel"
    ],
    "name:fra_x_preferred":[
        "Dulikhel"
    ],
    "name:ita_x_preferred":[
        "Dulikhel"
    ],
    "name:jpn_x_preferred":[
        "\u30c9\u30a5\u30ea\u30b1\u30eb"
    ],
    "name:kur_x_preferred":[
        "Dhulikhel"
    ],
    "name:mai_x_preferred":[
        "\u0927\u0941\u0932\u093f\u0916\u0947\u0932 \u0928\u0917\u0930\u092a\u093e\u0932\u093f\u0915\u093e"
    ],
    "name:msa_x_preferred":[
        "Dhulikhel"
    ],
    "name:nep_x_preferred":[
        "\u0927\u0941\u0932\u093f\u0916\u0947\u0932 \u0928\u0917\u0930\u092a\u093e\u0932\u093f\u0915\u093e"
    ],
    "name:nld_x_preferred":[
        "Dulikhel"
    ],
    "name:pol_x_preferred":[
        "Dhulikhel"
    ],
    "name:por_x_preferred":[
        "Dulikhel"
    ],
    "name:spa_x_preferred":[
        "Dhulikhel"
    ],
    "name:urd_x_preferred":[
        "\u062f\u06be\u0644\u06cc \u06a9\u06be\u06cc\u0644"
    ],
    "name:urd_x_variant":[
        "\u062f\u06be\u0644\u06a9\u06be\u06cc\u0644"
    ],
    "name:zho_x_preferred":[
        "\u5716\u5229\u51f1\u723e"
    ],
    "qs:gn_country":"NP",
    "qs:gn_fcode":"PPL",
    "qs:gn_pop":0,
    "qs:name":"Dhulikhel",
    "qs:name_adm0":"Nepal",
    "qs:name_adm1":"Madhyamanchal",
    "qs:photos":657,
    "qs:photos_1k":133,
    "qs:photos_9k":3,
    "qs:photos_9r":5,
    "qs:photos_all":657,
    "qs:photos_sr":8,
    "qs:placetype":"Town",
    "qs:pop_sr":"0",
    "qs:woe_adm0":23424911,
    "wd:wordcount":716,
    "wof:name":"Dhulikhel",
    "wof:placetype":"locality"
},
  "geometry": {"coordinates":[85.54281,27.6221],"type":"Point"}
}