{
  "type": "Feature",
  "properties": {
    "gn:admin1_code":"ER",
    "gn:admin2_code":"13",
    "gn:admin3_code":"16",
    "gn:admin4_code":"160034",
    "gn:asciiname":"Chhaghariya",
    "gn:country_code":"NP",
    "gn:dem":166,
    "gn:feature_class":"P",
    "gn:feature_code":"PPLL",
    "gn:name":"Chhaghariya",
    "gn:population":0,
    "gn:timezone":"Asia/Kathmandu",
    "iso:country":"NP",
    "wof:name":"Chhaghariya",
    "wof:placetype":"locality"
},
  "geometry": {"coordinates":[86.27901,26.85936],"type":"Point"}
}