{
  "type": "Feature",
  "properties": {
    "gn:admin1_code":"CR",
    "gn:admin2_code":"1",
    "gn:admin3_code":"23",
    "gn:admin4_code":"230024",
    "gn:asciiname":"Yarsa",
    "gn:country_code":"NP",
    "gn:dem":1616,
    "gn:feature_class":"P",
    "gn:feature_code":"PPLL",
    "gn:name":"Yarsa",
    "gn:population":0,
    "gn:timezone":"Asia/Kathmandu",
    "iso:country":"NP",
    "name:ceb_x_preferred":[
        "Y\u0101rs\u0101"
    ],
    "name:fra_x_preferred":[
        "Yarsa"
    ],
    "name:msa_x_preferred":[
        "Yarsa"
    ],
    "name:nep_x_preferred":[
        "\u092f\u093e\u0930\u094d\u0938\u093e"
    ],
    "name:new_x_preferred":[
        "\u092f\u093e\u0930\u094d\u0938\u093e"
    ],
    "name:pol_x_preferred":[
        "Yarsa"
    ],
    "name:urd_x_preferred":[
        "\u06cc\u0627\u0631\u0633\u0627"
    ],
    "wof:name":"Yarsa",
    "wof:placetype":"locality"
},
  "geometry": {"coordinates":[85.74851,27.88213],"type":"Point"}
}