{
  "type": "Feature",
  "properties": {
    "gn:admin1_code":"ER",
    "gn:admin2_code":"13",
    "gn:admin3_code":"11",
    "gn:admin4_code":"110010.0",
    "gn:asciiname":"Kangdel",
    "gn:country_code":"NP",
    "gn:dem":2041,
    "gn:feature_class":"P",
    "gn:feature_code":"PPLL",
    "gn:name":"Kangdel",
    "gn:population":0,
    "gn:timezone":"Asia/Kathmandu",
    "iso:country":"NP",
    "wof:name":"Kangdel",
    "wof:placetype":"locality"
},
  "geometry": {"coordinates":[86.61508000000001,27.44324000000001],"type":"Point"}
}