{
  "type": "Feature",
  "properties": {
    "gn:admin1_code":"MR",
    "gn:admin2_code":"2.0",
    "gn:admin3_code":"59.0",
    "gn:admin4_code":"590008.0",
    "gn:asciiname":"Chanabari",
    "gn:country_code":"NP",
    "gn:dem":794,
    "gn:feature_class":"P",
    "gn:feature_code":"PPLL",
    "gn:name":"Chanabari",
    "gn:population":0,
    "gn:timezone":"Asia/Kathmandu",
    "iso:country":"NP",
    "wof:name":"Chanabari",
    "wof:placetype":"locality"
},
  "geometry": {"coordinates":[81.58671,28.61715],"type":"Point"}
}