{
  "type": "Feature",
  "properties": {
    "gn:admin1_code":"WR",
    "gn:admin2_code":"4",
    "gn:admin3_code":"37",
    "gn:admin4_code":"370047",
    "gn:asciiname":"Sariswanra",
    "gn:country_code":"NP",
    "gn:dem":1084,
    "gn:feature_class":"P",
    "gn:feature_code":"PPLL",
    "gn:name":"Sariswanra",
    "gn:population":0,
    "gn:timezone":"Asia/Kathmandu",
    "iso:country":"NP",
    "wof:name":"Sariswanra",
    "wof:placetype":"locality"
},
  "geometry": {"coordinates":[84.37186,28.18873],"type":"Point"}
}