{
  "type": "Feature",
  "properties": {
    "gn:admin1_code":"MR",
    "gn:admin2_code":"2.0",
    "gn:admin3_code":"59.0",
    "gn:admin4_code":"590048.0",
    "gn:asciiname":"Bhanjyang",
    "gn:country_code":"NP",
    "gn:dem":653,
    "gn:feature_class":"P",
    "gn:feature_code":"PPLL",
    "gn:name":"Bhanjyang",
    "gn:population":0,
    "gn:timezone":"Asia/Kathmandu",
    "iso:country":"NP",
    "wof:name":"Bhanjyang",
    "wof:placetype":"locality"
},
  "geometry": {"coordinates":[81.70563,28.56986],"type":"Point"}
}