{
  "type": "Feature",
  "properties": {
    "gn:admin1_code":"FR",
    "gn:admin2_code":"14",
    "gn:admin3_code":"68",
    "gn:admin4_code":"680004",
    "gn:asciiname":"Babangaun",
    "gn:country_code":"NP",
    "gn:dem":1751,
    "gn:feature_class":"P",
    "gn:feature_code":"PPLL",
    "gn:name":"Babangaun",
    "gn:population":0,
    "gn:timezone":"Asia/Kathmandu",
    "iso:country":"NP",
    "wof:name":"Babangaun",
    "wof:placetype":"locality"
},
  "geometry": {"coordinates":[81.25379000000002,29.55279],"type":"Point"}
}