{
  "type": "Feature",
  "properties": {
    "gn:admin1_code":"ER",
    "gn:admin2_code":"13",
    "gn:admin3_code":"16",
    "gn:admin4_code":"160031",
    "gn:asciiname":"Betaha",
    "gn:country_code":"NP",
    "gn:dem":225,
    "gn:feature_class":"P",
    "gn:feature_code":"PPLL",
    "gn:name":"Betaha",
    "gn:population":0,
    "gn:timezone":"Asia/Kathmandu",
    "iso:country":"NP",
    "wof:name":"Betaha",
    "wof:placetype":"locality"
},
  "geometry": {"coordinates":[86.49106,26.8332],"type":"Point"}
}