{
  "type": "Feature",
  "properties": {
    "gn:admin1_code":"MR",
    "gn:admin2_code":"6",
    "gn:admin3_code":"64.0",
    "gn:admin4_code":"640012.0",
    "gn:asciiname":"Durisile",
    "gn:country_code":"NP",
    "gn:dem":2412,
    "gn:feature_class":"P",
    "gn:feature_code":"PPLL",
    "gn:name":"Durisile",
    "gn:population":0,
    "gn:timezone":"Asia/Kathmandu",
    "iso:country":"NP",
    "wof:name":"Durisile",
    "wof:placetype":"locality"
},
  "geometry": {"coordinates":[81.50489,29.1886],"type":"Point"}
}