{
  "type": "Feature",
  "properties": {
    "gn:admin1_code":"MR",
    "gn:admin2_code":"2",
    "gn:admin3_code":"60.0",
    "gn:admin4_code":"600005.0",
    "gn:asciiname":"Gopini",
    "gn:country_code":"NP",
    "gn:dem":1592,
    "gn:feature_class":"P",
    "gn:feature_code":"PPLL",
    "gn:name":"Gopini",
    "gn:population":0,
    "gn:timezone":"Asia/Kathmandu",
    "iso:country":"NP",
    "wof:name":"Gopini",
    "wof:placetype":"locality"
},
  "geometry": {"coordinates":[81.80015999999998,28.9361],"type":"Point"}
}