{
  "type": "Feature",
  "properties": {
    "gn:admin1_code":"CR",
    "gn:admin2_code":"11",
    "gn:admin3_code":"32",
    "gn:admin4_code":"320086.0",
    "gn:asciiname":"Sakhuawa Dhamaura",
    "gn:country_code":"NP",
    "gn:dem":95,
    "gn:feature_class":"P",
    "gn:feature_code":"PPLL",
    "gn:name":"Sakhuawa Dhamaura",
    "gn:population":0,
    "gn:timezone":"Asia/Kathmandu",
    "iso:country":"NP",
    "wof:name":"Sakhuawa Dhamaura",
    "wof:placetype":"locality"
},
  "geometry": {"coordinates":[85.33049,26.99518],"type":"Point"}
}