{
  "type": "Feature",
  "properties": {
    "gn:admin1_code":"CR",
    "gn:admin2_code":"5",
    "gn:admin3_code":"20",
    "gn:admin4_code":"200002",
    "gn:asciiname":"Bimire",
    "gn:country_code":"NP",
    "gn:dem":653,
    "gn:feature_class":"P",
    "gn:feature_code":"PPLL",
    "gn:name":"Bimire",
    "gn:population":0,
    "gn:timezone":"Asia/Kathmandu",
    "iso:country":"NP",
    "wof:name":"Bimire",
    "wof:placetype":"locality"
},
  "geometry": {"coordinates":[86.24848,27.04868],"type":"Point"}
}