{
  "type": "Feature",
  "properties": {
    "gn:admin1_code":"WR",
    "gn:admin2_code":"4",
    "gn:admin3_code":"37",
    "gn:admin4_code":"370020",
    "gn:asciiname":"Anpchaur",
    "gn:country_code":"NP",
    "gn:dem":838,
    "gn:feature_class":"P",
    "gn:feature_code":"PPLL",
    "gn:name":"Anpchaur",
    "gn:population":0,
    "gn:timezone":"Asia/Kathmandu",
    "iso:country":"NP",
    "wof:name":"Anpchaur",
    "wof:placetype":"locality"
},
  "geometry": {"coordinates":[84.48541,28.10534],"type":"Point"}
}