{
  "type": "Feature",
  "properties": {
    "gn:admin1_code":"WR",
    "gn:admin2_code":"8",
    "gn:admin3_code":"49",
    "gn:admin4_code":"490033",
    "gn:asciiname":"Nauwakatti",
    "gn:country_code":"NP",
    "gn:dem":129,
    "gn:feature_class":"P",
    "gn:feature_code":"PPLL",
    "gn:name":"Nauwakatti",
    "gn:population":0,
    "gn:timezone":"Asia/Kathmandu",
    "iso:country":"NP",
    "wof:name":"Nauwakatti",
    "wof:placetype":"locality"
},
  "geometry": {"coordinates":[83.48761,27.62099000000001],"type":"Point"}
}