{
  "type": "Feature",
  "properties": {
    "gn:admin1_code":"00",
    "gn:asciiname":"Phadigau",
    "gn:country_code":"NP",
    "gn:dem":890,
    "gn:feature_class":"P",
    "gn:feature_code":"PPL",
    "gn:name":"Phadi\u0307\u0304g\u0101\u0169",
    "gn:population":0,
    "gn:timezone":"Asia/Kathmandu",
    "iso:country":"NP",
    "name:und_x_variant":[
        "Phadi\u0307\u0304g\u0101\u0169",
        "Phad\u012bg\u0101un"
    ],
    "wof:name":"Phadigau",
    "wof:placetype":"locality"
},
  "geometry": {"coordinates":[86.47006999999998,27.20823],"type":"Point"}
}