{
  "type": "Feature",
  "properties": {
    "gn:admin1_code":"MR",
    "gn:admin2_code":"2.0",
    "gn:admin3_code":"59.0",
    "gn:admin4_code":"590046.0",
    "gn:asciiname":"Pokhari Pata",
    "gn:country_code":"NP",
    "gn:dem":760,
    "gn:feature_class":"P",
    "gn:feature_code":"PPLL",
    "gn:name":"Pokhari Pata",
    "gn:population":0,
    "gn:timezone":"Asia/Kathmandu",
    "iso:country":"NP",
    "wof:name":"Pokhari Pata",
    "wof:placetype":"locality"
},
  "geometry": {"coordinates":[81.88518000000001,28.37962000000001],"type":"Point"}
}