{
  "type": "Feature",
  "properties": {
    "gn:admin1_code":"ER",
    "gn:admin2_code":"7",
    "gn:admin3_code":"9",
    "gn:admin4_code":"90033",
    "gn:asciiname":"Manglung",
    "gn:country_code":"NP",
    "gn:dem":1411,
    "gn:feature_class":"P",
    "gn:feature_code":"PPLL",
    "gn:name":"Manglung",
    "gn:population":0,
    "gn:timezone":"Asia/Kathmandu",
    "iso:country":"NP",
    "wof:name":"Manglung",
    "wof:placetype":"locality"
},
  "geometry": {"coordinates":[87.09805,27.48787],"type":"Point"}
}