{
  "type": "Feature",
  "properties": {
    "gn:admin1_code":"CR",
    "gn:admin2_code":"1",
    "gn:admin3_code":"24.0",
    "gn:admin4_code":"240084.0",
    "gn:asciiname":"Shankheshwari",
    "gn:country_code":"NP",
    "gn:dem":1584,
    "gn:feature_class":"P",
    "gn:feature_code":"PPLL",
    "gn:name":"Shankheshwari",
    "gn:population":0,
    "gn:timezone":"Asia/Kathmandu",
    "iso:country":"NP",
    "wof:name":"Shankheshwari",
    "wof:placetype":"locality"
},
  "geometry": {"coordinates":[85.58001999999998,27.57486],"type":"Point"}
}