{
  "type": "Feature",
  "properties": {
    "gn:admin1_code":"FR",
    "gn:admin2_code":"14.0",
    "gn:admin3_code":"67.0",
    "gn:admin4_code":"670009.0",
    "gn:asciiname":"Dunyalo",
    "gn:country_code":"NP",
    "gn:dem":2449,
    "gn:feature_class":"P",
    "gn:feature_code":"PPLL",
    "gn:name":"Dunyalo",
    "gn:population":0,
    "gn:timezone":"Asia/Kathmandu",
    "iso:country":"NP",
    "wof:name":"Dunyalo",
    "wof:placetype":"locality"
},
  "geometry": {"coordinates":[81.43163,29.57208],"type":"Point"}
}