{
  "type": "Feature",
  "properties": {
    "gn:admin1_code":"WR",
    "gn:admin2_code":"3",
    "gn:admin3_code":"45.0",
    "gn:admin4_code":"450014.0",
    "gn:asciiname":"Gaba",
    "gn:country_code":"NP",
    "gn:dem":2770,
    "gn:feature_class":"P",
    "gn:feature_code":"PPLL",
    "gn:name":"Gaba",
    "gn:population":0,
    "gn:timezone":"Asia/Kathmandu",
    "iso:country":"NP",
    "name:ceb_x_preferred":[
        "Gaba"
    ],
    "name:ita_x_preferred":[
        "Gaba"
    ],
    "name:rus_x_preferred":[
        "\u0413\u0430\u0431\u0430"
    ],
    "name:swe_x_preferred":[
        "Gaba"
    ],
    "wof:name":"Gaba",
    "wof:placetype":"locality"
},
  "geometry": {"coordinates":[82.95464,28.50603],"type":"Point"}
}