{
  "type": "Feature",
  "properties": {
    "gn:admin1_code":"00",
    "gn:asciiname":"Themjen",
    "gn:country_code":"NP",
    "gn:dem":2184,
    "gn:feature_class":"P",
    "gn:feature_code":"PPL",
    "gn:name":"\u1e6chemjen",
    "gn:population":0,
    "gn:timezone":"Asia/Kathmandu",
    "iso:country":"NP",
    "wof:name":"Themjen",
    "wof:placetype":"locality"
},
  "geometry": {"coordinates":[86.4568,27.59286],"type":"Point"}
}