{
  "type": "Feature",
  "properties": {
    "gn:admin1_code":"CR",
    "gn:admin2_code":"11",
    "gn:admin3_code":"31",
    "gn:admin4_code":"310030",
    "gn:asciiname":"Mathillo Sisne",
    "gn:country_code":"NP",
    "gn:dem":1128,
    "gn:feature_class":"P",
    "gn:feature_code":"PPLL",
    "gn:name":"Mathillo Sisne",
    "gn:population":0,
    "gn:timezone":"Asia/Kathmandu",
    "iso:country":"NP",
    "wof:name":"Mathillo Sisne",
    "wof:placetype":"locality"
},
  "geometry": {"coordinates":[85.2938,27.43787],"type":"Point"}
}