{
  "type": "Feature",
  "properties": {
    "gn:admin1_code":"MR",
    "gn:admin2_code":"2.0",
    "gn:admin3_code":"59.0",
    "gn:admin4_code":"590024.0",
    "gn:asciiname":"Kholtepani",
    "gn:country_code":"NP",
    "gn:dem":504,
    "gn:feature_class":"P",
    "gn:feature_code":"PPLL",
    "gn:name":"Kholtepani",
    "gn:population":0,
    "gn:timezone":"Asia/Kathmandu",
    "iso:country":"NP",
    "wof:name":"Kholtepani",
    "wof:placetype":"locality"
},
  "geometry": {"coordinates":[81.7513,28.50101],"type":"Point"}
}