{
  "type": "Feature",
  "properties": {
    "gn:admin1_code":"FR",
    "gn:admin2_code":"14",
    "gn:admin3_code":"69.0",
    "gn:admin4_code":"690012.0",
    "gn:asciiname":"Rimi",
    "gn:country_code":"NP",
    "gn:dem":1826,
    "gn:feature_class":"P",
    "gn:feature_code":"PPLL",
    "gn:name":"Rimi",
    "gn:population":0,
    "gn:timezone":"Asia/Kathmandu",
    "iso:country":"NP",
    "name:ceb_x_preferred":[
        "Rimi"
    ],
    "name:deu_x_preferred":[
        "Rimi"
    ],
    "name:ita_x_preferred":[
        "Rimi"
    ],
    "name:swe_x_preferred":[
        "Rimi"
    ],
    "wof:name":"Rimi",
    "wof:placetype":"locality"
},
  "geometry": {"coordinates":[81.37621999999998,29.11732],"type":"Point"}
}