{
  "type": "Feature",
  "properties": {
    "gn:admin1_code":"WR",
    "gn:admin2_code":"3",
    "gn:admin3_code":"45",
    "gn:admin4_code":"450059",
    "gn:asciiname":"Chharabot",
    "gn:country_code":"NP",
    "gn:dem":2234,
    "gn:feature_class":"P",
    "gn:feature_code":"PPLL",
    "gn:name":"Chharabot",
    "gn:population":0,
    "gn:timezone":"Asia/Kathmandu",
    "iso:country":"NP",
    "wof:name":"Chharabot",
    "wof:placetype":"locality"
},
  "geometry": {"coordinates":[83.25608000000003,28.31734],"type":"Point"}
}