{
  "type": "Feature",
  "properties": {
    "gn:admin1_code":"FR",
    "gn:admin2_code":"14",
    "gn:admin3_code":"71.0",
    "gn:admin4_code":"710024.0",
    "gn:asciiname":"Matkauna",
    "gn:country_code":"NP",
    "gn:dem":187,
    "gn:feature_class":"P",
    "gn:feature_code":"PPLL",
    "gn:name":"Matkauna",
    "gn:population":0,
    "gn:timezone":"Asia/Kathmandu",
    "iso:country":"NP",
    "wof:name":"Matkauna",
    "wof:placetype":"locality"
},
  "geometry": {"coordinates":[80.82428,28.74877],"type":"Point"}
}