{
  "type": "Feature",
  "properties": {
    "gn:admin1_code":"MR",
    "gn:admin2_code":"12",
    "gn:admin3_code":"52",
    "gn:admin4_code":"520024",
    "gn:asciiname":"Bayapakha",
    "gn:country_code":"NP",
    "gn:dem":1436,
    "gn:feature_class":"P",
    "gn:feature_code":"PPLL",
    "gn:name":"Bayapakha",
    "gn:population":0,
    "gn:timezone":"Asia/Kathmandu",
    "iso:country":"NP",
    "wof:name":"Bayapakha",
    "wof:placetype":"locality"
},
  "geometry": {"coordinates":[82.92644,28.21522],"type":"Point"}
}