{
  "type": "Feature",
  "properties": {
    "gn:admin1_code":"MR",
    "gn:admin2_code":"12",
    "gn:admin3_code":"53",
    "gn:admin4_code":"530047",
    "gn:asciiname":"Sansar",
    "gn:country_code":"NP",
    "gn:dem":2187,
    "gn:feature_class":"P",
    "gn:feature_code":"PPLL",
    "gn:name":"Sansar",
    "gn:population":0,
    "gn:timezone":"Asia/Kathmandu",
    "iso:country":"NP",
    "wof:name":"Sansar",
    "wof:placetype":"locality"
},
  "geometry": {"coordinates":[82.68111,28.50565],"type":"Point"}
}