{
  "type": "Feature",
  "properties": {
    "gn:admin1_code":"CR",
    "gn:admin2_code":"1",
    "gn:admin3_code":"30.0",
    "gn:admin4_code":"300002.0",
    "gn:asciiname":"Baghmara",
    "gn:country_code":"NP",
    "gn:dem":893,
    "gn:feature_class":"P",
    "gn:feature_code":"PPLL",
    "gn:name":"Baghmara",
    "gn:population":0,
    "gn:timezone":"Asia/Kathmandu",
    "iso:country":"NP",
    "wof:name":"Baghmara",
    "wof:placetype":"locality"
},
  "geometry": {"coordinates":[84.9646,27.76023],"type":"Point"}
}