{
  "type": "Feature",
  "properties": {
    "gn:admin1_code":"ER",
    "gn:admin2_code":"13",
    "gn:admin3_code":"12",
    "gn:admin4_code":"120004",
    "gn:asciiname":"Lalu",
    "gn:country_code":"NP",
    "gn:dem":1849,
    "gn:feature_class":"P",
    "gn:feature_code":"PPLL",
    "gn:name":"Lalu",
    "gn:population":0,
    "gn:timezone":"Asia/Kathmandu",
    "iso:country":"NP",
    "name:ceb_x_preferred":[
        "Lalu"
    ],
    "name:swe_x_preferred":[
        "Lalu"
    ],
    "wof:name":"Lalu",
    "wof:placetype":"locality"
},
  "geometry": {"coordinates":[86.54745,27.34629],"type":"Point"}
}