{
  "type": "Feature",
  "properties": {
    "gn:admin1_code":"FR",
    "gn:admin2_code":"14",
    "gn:admin3_code":"71.0",
    "gn:admin4_code":"710021.0",
    "gn:asciiname":"Rajipur",
    "gn:country_code":"NP",
    "gn:dem":165,
    "gn:feature_class":"P",
    "gn:feature_code":"PPLL",
    "gn:name":"Rajipur",
    "gn:population":0,
    "gn:timezone":"Asia/Kathmandu",
    "iso:country":"NP",
    "wof:name":"Rajipur",
    "wof:placetype":"locality"
},
  "geometry": {"coordinates":[81.0119,28.63628],"type":"Point"}
}