{
  "type": "Feature",
  "properties": {
    "gn:admin1_code":"FR",
    "gn:admin2_code":"14.0",
    "gn:admin3_code":"69.0",
    "gn:admin4_code":"690045.0",
    "gn:asciiname":"Lungra",
    "gn:country_code":"NP",
    "gn:dem":1050,
    "gn:feature_class":"P",
    "gn:feature_code":"PPLL",
    "gn:name":"Lungra",
    "gn:population":0,
    "gn:timezone":"Asia/Kathmandu",
    "iso:country":"NP",
    "name:bih_x_preferred":[
        "\u0932\u0941\u0902\u0917\u094d\u0930\u093e"
    ],
    "name:ceb_x_preferred":[
        "Lungra"
    ],
    "name:fra_x_preferred":[
        "Lungra"
    ],
    "name:msa_x_preferred":[
        "Lungra"
    ],
    "name:nep_x_preferred":[
        "\u0932\u0941\u0902\u0917\u094d\u0930\u093e"
    ],
    "name:new_x_preferred":[
        "\u0932\u0941\u0919\u0930\u093e"
    ],
    "name:pol_x_preferred":[
        "Lungra"
    ],
    "wof:name":"Lungra",
    "wof:placetype":"locality"
},
  "geometry": {"coordinates":[81.16708,29.21354],"type":"Point"}
}