{
  "type": "Feature",
  "properties": {
    "gn:admin1_code":"CR",
    "gn:admin2_code":"1",
    "gn:admin3_code":"23",
    "gn:admin4_code":"230029",
    "gn:asciiname":"Thuibal",
    "gn:country_code":"NP",
    "gn:dem":2074,
    "gn:feature_class":"P",
    "gn:feature_code":"PPLL",
    "gn:name":"Thuibal",
    "gn:population":0,
    "gn:timezone":"Asia/Kathmandu",
    "iso:country":"NP",
    "wof:name":"Thuibal",
    "wof:placetype":"locality"
},
  "geometry": {"coordinates":[85.54983,27.96651],"type":"Point"}
}