{
  "type": "Feature",
  "properties": {
    "gn:admin1_code":"MR",
    "gn:admin2_code":"12",
    "gn:admin3_code":"52",
    "gn:admin4_code":"520041",
    "gn:asciiname":"Dungdunge",
    "gn:country_code":"NP",
    "gn:dem":1018,
    "gn:feature_class":"P",
    "gn:feature_code":"PPLL",
    "gn:name":"Dungdunge",
    "gn:population":0,
    "gn:timezone":"Asia/Kathmandu",
    "iso:country":"NP",
    "wof:name":"Dungdunge",
    "wof:placetype":"locality"
},
  "geometry": {"coordinates":[82.81905999999999,28.04965],"type":"Point"}
}