{
  "type": "Feature",
  "properties": {
    "gn:admin1_code":"FR",
    "gn:admin2_code":"14",
    "gn:admin3_code":"71.0",
    "gn:admin4_code":"710022.0",
    "gn:asciiname":"Prithipur",
    "gn:country_code":"NP",
    "gn:dem":152,
    "gn:feature_class":"P",
    "gn:feature_code":"PPLL",
    "gn:name":"Prithipur",
    "gn:population":0,
    "gn:timezone":"Asia/Kathmandu",
    "iso:country":"NP",
    "wof:name":"Prithipur",
    "wof:placetype":"locality"
},
  "geometry": {"coordinates":[80.92801999999998,28.47574],"type":"Point"}
}