{
  "type": "Feature",
  "properties": {
    "gn:admin1_code":"WR",
    "gn:admin2_code":"8",
    "gn:admin3_code":"46.0",
    "gn:admin4_code":"460047.0",
    "gn:asciiname":"Lamtar",
    "gn:country_code":"NP",
    "gn:dem":905,
    "gn:feature_class":"P",
    "gn:feature_code":"PPLL",
    "gn:name":"Lamtar",
    "gn:population":0,
    "gn:timezone":"Asia/Kathmandu",
    "iso:country":"NP",
    "name:ara_x_preferred":[
        "\u0644\u0645\u0637\u0627\u0631"
    ],
    "name:azb_x_preferred":[
        "\u0644\u0645\u0637\u0627\u0631"
    ],
    "name:fas_x_preferred":[
        "\u0644\u0645\u0637\u0627\u0631"
    ],
    "name:fra_x_preferred":[
        "Lamtar"
    ],
    "name:ita_x_preferred":[
        "Lamtar"
    ],
    "name:kab_x_preferred":[
        "Lem\u1e6dar"
    ],
    "name:msa_x_preferred":[
        "Lamtar"
    ],
    "name:pol_x_preferred":[
        "Lamtar"
    ],
    "name:por_x_preferred":[
        "Lamtar"
    ],
    "name:ron_x_preferred":[
        "Lamtar"
    ],
    "name:spa_x_preferred":[
        "Lamtar"
    ],
    "name:urd_x_preferred":[
        "\u0644\u0627\u0645\u0679\u0627\u0631"
    ],
    "name:vie_x_preferred":[
        "Lamtar"
    ],
    "wof:name":"Lamtar",
    "wof:placetype":"locality"
},
  "geometry": {"coordinates":[83.19410999999999,28.13431],"type":"Point"}
}