{
  "type": "Feature",
  "properties": {
    "gn:admin1_code":"WR",
    "gn:admin2_code":"8",
    "gn:admin3_code":"46.0",
    "gn:admin4_code":"460047.0",
    "gn:asciiname":"Lamtar",
    "gn:country_code":"NP",
    "gn:dem":905,
    "gn:feature_class":"P",
    "gn:feature_code":"PPLL",
    "gn:name":"Lamtar",
    "gn:population":0,
    "gn:timezone":"Asia/Kathmandu",
    "iso:country":"NP",
    "wof:name":"Lamtar",
    "wof:placetype":"locality"
},
  "geometry": {"coordinates":[83.19410999999999,28.13431],"type":"Point"}
}