{
  "type": "Feature",
  "properties": {
    "gn:admin1_code":"FR",
    "gn:admin2_code":"14",
    "gn:admin3_code":"71.0",
    "gn:admin4_code":"710024.0",
    "gn:asciiname":"Masuriya",
    "gn:country_code":"NP",
    "gn:dem":177,
    "gn:feature_class":"P",
    "gn:feature_code":"PPLL",
    "gn:name":"Masuriya",
    "gn:population":0,
    "gn:timezone":"Asia/Kathmandu",
    "iso:country":"NP",
    "name:ceb_x_preferred":[
        "Masuriya"
    ],
    "name:dty_x_preferred":[
        "\u092e\u0938\u0941\u0930\u093f\u092f\u093e"
    ],
    "name:mai_x_preferred":[
        "\u092e\u0938\u0941\u0930\u093f\u092f\u093e"
    ],
    "name:msa_x_preferred":[
        "Masuriya"
    ],
    "name:nep_x_preferred":[
        "\u092e\u0938\u0941\u0930\u093f\u092f\u093e"
    ],
    "name:new_x_preferred":[
        "\u092e\u0938\u094c\u0930\u093f\u092f\u093e"
    ],
    "name:pol_x_preferred":[
        "Masuriya"
    ],
    "wof:name":"Masuriya",
    "wof:placetype":"locality"
},
  "geometry": {"coordinates":[80.83665000000001,28.70853],"type":"Point"}
}