{
  "type": "Feature",
  "properties": {
    "gn:admin1_code":"ER",
    "gn:admin2_code":"7",
    "gn:admin3_code":"10.0",
    "gn:admin4_code":"100042.0",
    "gn:asciiname":"Lumbuwa",
    "gn:country_code":"NP",
    "gn:dem":1528,
    "gn:feature_class":"P",
    "gn:feature_code":"PPLL",
    "gn:name":"Lumbuwa",
    "gn:population":0,
    "gn:timezone":"Asia/Kathmandu",
    "iso:country":"NP",
    "wof:name":"Lumbuwa",
    "wof:placetype":"locality"
},
  "geometry": {"coordinates":[86.96672,27.19918],"type":"Point"}
}