{
  "type": "Feature",
  "properties": {
    "gn:admin1_code":"CR",
    "gn:admin2_code":"5",
    "gn:admin3_code":"21",
    "gn:admin4_code":"210041",
    "gn:asciiname":"Gogane",
    "gn:country_code":"NP",
    "gn:dem":1686,
    "gn:feature_class":"P",
    "gn:feature_code":"PPLL",
    "gn:name":"Gogane",
    "gn:population":0,
    "gn:timezone":"Asia/Kathmandu",
    "iso:country":"NP",
    "wof:name":"Gogane",
    "wof:placetype":"locality"
},
  "geometry": {"coordinates":[86.00412,27.47766],"type":"Point"}
}