{
  "type": "Feature",
  "properties": {
    "gn:admin1_code":"00",
    "gn:asciiname":"Khadakagau",
    "gn:country_code":"NP",
    "gn:dem":1505,
    "gn:feature_class":"P",
    "gn:feature_code":"PPL",
    "gn:name":"Kha\u1e0dak\u0101g\u0101\u0169",
    "gn:population":0,
    "gn:timezone":"Asia/Kathmandu",
    "iso:country":"NP",
    "name:und_x_variant":[
        "Kha\u1e0dak\u0101g\u0101\u0169",
        "Kha\u1e0dak\u0101g\u0101un"
    ],
    "wof:name":"Khadakagau",
    "wof:placetype":"locality"
},
  "geometry": {"coordinates":[85.4175,27.63528],"type":"Point"}
}