{
  "type": "Feature",
  "properties": {
    "gn:admin1_code":"MR",
    "gn:admin2_code":"12",
    "gn:admin3_code":"53",
    "gn:admin4_code":"530006",
    "gn:asciiname":"Ungaira",
    "gn:country_code":"NP",
    "gn:dem":1450,
    "gn:feature_class":"P",
    "gn:feature_code":"PPLL",
    "gn:name":"Ungaira",
    "gn:population":0,
    "gn:timezone":"Asia/Kathmandu",
    "iso:country":"NP",
    "wof:name":"Ungaira",
    "wof:placetype":"locality"
},
  "geometry": {"coordinates":[82.50166,28.15679],"type":"Point"}
}