{
  "type": "Feature",
  "properties": {
    "gn:admin1_code":"ER",
    "gn:admin2_code":"10.0",
    "gn:admin3_code":"1.0",
    "gn:admin4_code":"10019.0",
    "gn:asciiname":"Thauwa",
    "gn:country_code":"NP",
    "gn:dem":1394,
    "gn:feature_class":"P",
    "gn:feature_code":"PPLL",
    "gn:name":"Thauwa",
    "gn:population":0,
    "gn:timezone":"Asia/Kathmandu",
    "iso:country":"NP",
    "wof:name":"Thauwa",
    "wof:placetype":"locality"
},
  "geometry": {"coordinates":[87.71162,27.43338],"type":"Point"}
}