{
  "type": "Feature",
  "properties": {
    "gn:admin1_code":"WR",
    "gn:admin2_code":"4.0",
    "gn:admin3_code":"38.0",
    "gn:admin4_code":"380004.0",
    "gn:asciiname":"Korikha",
    "gn:country_code":"NP",
    "gn:dem":877,
    "gn:feature_class":"P",
    "gn:feature_code":"PPLL",
    "gn:name":"Korikha",
    "gn:population":0,
    "gn:timezone":"Asia/Kathmandu",
    "iso:country":"NP",
    "wof:name":"Korikha",
    "wof:placetype":"locality"
},
  "geometry": {"coordinates":[84.43619,27.93164],"type":"Point"}
}