{
  "type": "Feature",
  "properties": {
    "gn:admin1_code":"WR",
    "gn:admin2_code":"4",
    "gn:admin3_code":"36.0",
    "gn:admin4_code":"360060.0",
    "gn:asciiname":"Arukharka",
    "gn:country_code":"NP",
    "gn:dem":747,
    "gn:feature_class":"P",
    "gn:feature_code":"PPLL",
    "gn:name":"Arukharka",
    "gn:population":0,
    "gn:timezone":"Asia/Kathmandu",
    "iso:country":"NP",
    "name:ceb_x_preferred":[
        "Arukharka"
    ],
    "name:hin_x_preferred":[
        "\u0906\u0930\u0941\u0916\u0930\u094d\u0915"
    ],
    "name:mai_x_preferred":[
        "\u0906\u0930\u0941\u0916\u0930\u094d\u0915"
    ],
    "name:msa_x_preferred":[
        "Arukharka"
    ],
    "name:nep_x_preferred":[
        "\u0906\u0930\u0941\u0916\u0930\u094d\u0915"
    ],
    "name:new_x_preferred":[
        "\u0906\u0930\u0941\u0916\u0930\u094d\u0915"
    ],
    "name:pol_x_preferred":[
        "Arukharka"
    ],
    "wof:name":"Arukharka",
    "wof:placetype":"locality"
},
  "geometry": {"coordinates":[84.66497,28.09018],"type":"Point"}
}