{
  "type": "Feature",
  "properties": {
    "gn:admin1_code":"ER",
    "gn:admin2_code":"7.0",
    "gn:admin3_code":"8.0",
    "gn:admin4_code":"80023.0",
    "gn:asciiname":"Sampharjan",
    "gn:country_code":"NP",
    "gn:dem":1188,
    "gn:feature_class":"P",
    "gn:feature_code":"PPLL",
    "gn:name":"Sampharjan",
    "gn:population":0,
    "gn:timezone":"Asia/Kathmandu",
    "iso:country":"NP",
    "wof:name":"Sampharjan",
    "wof:placetype":"locality"
},
  "geometry": {"coordinates":[87.54196,27.14529000000001],"type":"Point"}
}