{
  "type": "Feature",
  "properties": {
    "gn:admin1_code":"WR",
    "gn:admin2_code":"8",
    "gn:admin3_code":"46.0",
    "gn:admin4_code":"460051.0",
    "gn:asciiname":"Tallo Tolagaun",
    "gn:country_code":"NP",
    "gn:dem":1611,
    "gn:feature_class":"P",
    "gn:feature_code":"PPLL",
    "gn:name":"Tallo Tolagaun",
    "gn:population":0,
    "gn:timezone":"Asia/Kathmandu",
    "iso:country":"NP",
    "wof:name":"Tallo Tolagaun",
    "wof:placetype":"locality"
},
  "geometry": {"coordinates":[83.41494,28.06605],"type":"Point"}
}