{
  "type": "Feature",
  "properties": {
    "gn:admin1_code":"CR",
    "gn:admin2_code":"5",
    "gn:admin3_code":"19",
    "gn:admin4_code":"190077",
    "gn:asciiname":"Setibhir",
    "gn:country_code":"NP",
    "gn:dem":191,
    "gn:feature_class":"P",
    "gn:feature_code":"PPLL",
    "gn:name":"Setibhir",
    "gn:population":0,
    "gn:timezone":"Asia/Kathmandu",
    "iso:country":"NP",
    "wof:name":"Setibhir",
    "wof:placetype":"locality"
},
  "geometry": {"coordinates":[85.66934999999999,27.09651],"type":"Point"}
}