{
  "type": "Feature",
  "properties": {
    "gn:admin1_code":"WR",
    "gn:admin2_code":"4",
    "gn:admin3_code":"37",
    "gn:admin4_code":"370027",
    "gn:asciiname":"Kokaledanda",
    "gn:country_code":"NP",
    "gn:dem":1017,
    "gn:feature_class":"P",
    "gn:feature_code":"PPLL",
    "gn:name":"Kokaledanda",
    "gn:population":0,
    "gn:timezone":"Asia/Kathmandu",
    "iso:country":"NP",
    "wof:name":"Kokaledanda",
    "wof:placetype":"locality"
},
  "geometry": {"coordinates":[84.37835,28.21115],"type":"Point"}
}