{
  "type": "Feature",
  "properties": {
    "gn:admin1_code":"ER",
    "gn:admin2_code":"7",
    "gn:admin3_code":"10.0",
    "gn:admin4_code":"100020.0",
    "gn:asciiname":"Katahare",
    "gn:country_code":"NP",
    "gn:dem":388,
    "gn:feature_class":"P",
    "gn:feature_code":"PPLL",
    "gn:name":"Katahare",
    "gn:population":0,
    "gn:timezone":"Asia/Kathmandu",
    "iso:country":"NP",
    "wof:name":"Katahare",
    "wof:placetype":"locality"
},
  "geometry": {"coordinates":[87.09151,26.95172],"type":"Point"}
}