{
  "type": "Feature",
  "properties": {
    "gn:admin1_code":"MR",
    "gn:admin2_code":"6",
    "gn:admin3_code":"63.0",
    "gn:admin4_code":"630024.0",
    "gn:asciiname":"Seri",
    "gn:country_code":"NP",
    "gn:dem":3166,
    "gn:feature_class":"P",
    "gn:feature_code":"PPLL",
    "gn:name":"Seri",
    "gn:population":0,
    "gn:timezone":"Asia/Kathmandu",
    "iso:country":"NP",
    "wof:name":"Seri",
    "wof:placetype":"locality"
},
  "geometry": {"coordinates":[81.9558,29.42786],"type":"Point"}
}