{
  "type": "Feature",
  "properties": {
    "gn:admin1_code":"WR",
    "gn:admin2_code":"4.0",
    "gn:admin3_code":"38.0",
    "gn:admin4_code":"380031.0",
    "gn:asciiname":"Dulaipani",
    "gn:country_code":"NP",
    "gn:dem":570,
    "gn:feature_class":"P",
    "gn:feature_code":"PPLL",
    "gn:name":"Dulaipani",
    "gn:population":0,
    "gn:timezone":"Asia/Kathmandu",
    "iso:country":"NP",
    "wof:name":"Dulaipani",
    "wof:placetype":"locality"
},
  "geometry": {"coordinates":[84.23737,28.04841],"type":"Point"}
}