{
  "type": "Feature",
  "properties": {
    "gn:admin1_code":"ER",
    "gn:admin2_code":"10",
    "gn:admin3_code":"4.0",
    "gn:admin4_code":"40043.0",
    "gn:asciiname":"Salbari",
    "gn:country_code":"NP",
    "gn:dem":144,
    "gn:feature_class":"P",
    "gn:feature_code":"PPLL",
    "gn:name":"Salbari",
    "gn:population":0,
    "gn:timezone":"Asia/Kathmandu",
    "iso:country":"NP",
    "wof:name":"Salbari",
    "wof:placetype":"locality"
},
  "geometry": {"coordinates":[88.01505999999998,26.66572],"type":"Point"}
}