{
  "type": "Feature",
  "properties": {
    "gn:admin1_code":"ER",
    "gn:admin2_code":"7",
    "gn:admin3_code":"10.0",
    "gn:admin4_code":"100063.0",
    "gn:asciiname":"Bhaledhunga",
    "gn:country_code":"NP",
    "gn:dem":691,
    "gn:feature_class":"P",
    "gn:feature_code":"PPLL",
    "gn:name":"Bhaledhunga",
    "gn:population":0,
    "gn:timezone":"Asia/Kathmandu",
    "iso:country":"NP",
    "wof:name":"Bhaledhunga",
    "wof:placetype":"locality"
},
  "geometry": {"coordinates":[87.20043000000003,27.23243],"type":"Point"}
}