{
  "type": "Feature",
  "properties": {
    "gn:admin1_code":"CR",
    "gn:admin2_code":"1",
    "gn:admin3_code":"27.0",
    "gn:admin4_code":"270020.0",
    "gn:asciiname":"Talinchok",
    "gn:country_code":"NP",
    "gn:dem":1363,
    "gn:feature_class":"P",
    "gn:feature_code":"PPLL",
    "gn:name":"Talinchok",
    "gn:population":0,
    "gn:timezone":"Asia/Kathmandu",
    "iso:country":"NP",
    "wof:name":"Talinchok",
    "wof:placetype":"locality"
},
  "geometry": {"coordinates":[85.39634000000002,27.74093],"type":"Point"}
}