{
  "type": "Feature",
  "properties": {
    "gn:admin1_code":"MR",
    "gn:admin2_code":"2.0",
    "gn:admin3_code":"59.0",
    "gn:admin4_code":"590045.0",
    "gn:asciiname":"Ratu",
    "gn:country_code":"NP",
    "gn:dem":1629,
    "gn:feature_class":"P",
    "gn:feature_code":"PPLL",
    "gn:name":"Ratu",
    "gn:population":0,
    "gn:timezone":"Asia/Kathmandu",
    "iso:country":"NP",
    "wof:name":"Ratu",
    "wof:placetype":"locality"
},
  "geometry": {"coordinates":[81.70435999999999,28.63658],"type":"Point"}
}