{
  "type": "Feature",
  "properties": {
    "gn:admin1_code":"ER",
    "gn:admin2_code":"10.0",
    "gn:admin3_code":"1.0",
    "gn:admin4_code":"10029.0",
    "gn:asciiname":"Sambhubang",
    "gn:country_code":"NP",
    "gn:dem":1794,
    "gn:feature_class":"P",
    "gn:feature_code":"PPLL",
    "gn:name":"Sambhubang",
    "gn:population":0,
    "gn:timezone":"Asia/Kathmandu",
    "iso:country":"NP",
    "wof:name":"Sambhubang",
    "wof:placetype":"locality"
},
  "geometry": {"coordinates":[87.50713,27.42712],"type":"Point"}
}