{
  "type": "Feature",
  "properties": {
    "gn:admin1_code":"WR",
    "gn:admin2_code":"4.0",
    "gn:admin3_code":"38.0",
    "gn:admin4_code":"380007.0",
    "gn:asciiname":"Dhakalthar",
    "gn:country_code":"NP",
    "gn:dem":620,
    "gn:feature_class":"P",
    "gn:feature_code":"PPLL",
    "gn:name":"Dhakalthar",
    "gn:population":0,
    "gn:timezone":"Asia/Kathmandu",
    "iso:country":"NP",
    "wof:name":"Dhakalthar",
    "wof:placetype":"locality"
},
  "geometry": {"coordinates":[84.37732,28.0475],"type":"Point"}
}