{
  "type": "Feature",
  "properties": {
    "gn:admin1_code":"WR",
    "gn:admin2_code":"4.0",
    "gn:admin3_code":"39.0",
    "gn:admin4_code":"390031.0",
    "gn:asciiname":"Handiban",
    "gn:country_code":"NP",
    "gn:dem":491,
    "gn:feature_class":"P",
    "gn:feature_code":"PPLL",
    "gn:name":"Handiban",
    "gn:population":0,
    "gn:timezone":"Asia/Kathmandu",
    "iso:country":"NP",
    "wof:name":"Handiban",
    "wof:placetype":"locality"
},
  "geometry": {"coordinates":[83.96481,27.90403],"type":"Point"}
}