{
  "type": "Feature",
  "properties": {
    "gn:admin1_code":"MR",
    "gn:admin2_code":"6",
    "gn:admin3_code":"62.0",
    "gn:admin4_code":"620011.0",
    "gn:asciiname":"Lahara",
    "gn:country_code":"NP",
    "gn:dem":3340,
    "gn:feature_class":"P",
    "gn:feature_code":"PPLL",
    "gn:name":"Lahara",
    "gn:population":0,
    "gn:timezone":"Asia/Kathmandu",
    "iso:country":"NP",
    "wof:name":"Lahara",
    "wof:placetype":"locality"
},
  "geometry": {"coordinates":[82.82042,28.9564],"type":"Point"}
}