{
  "type": "Feature",
  "properties": {
    "gn:admin1_code":"00",
    "gn:asciiname":"Sakh",
    "gn:country_code":"NP",
    "gn:dem":1904,
    "gn:feature_class":"P",
    "gn:feature_code":"PPL",
    "gn:name":"S\u0101\u0303kh",
    "gn:population":0,
    "gn:timezone":"Asia/Kathmandu",
    "iso:country":"NP",
    "name:nep_x_preferred":[
        "S\u0101\u0303kh"
    ],
    "name:und_x_variant":[
        "S\u0101kha"
    ],
    "wof:name":"Sakh",
    "wof:placetype":"locality"
},
  "geometry": {"coordinates":[82.51385000000001,28.61293],"type":"Point"}
}