{
  "type": "Feature",
  "properties": {
    "gn:admin1_code":"FR",
    "gn:admin2_code":"9",
    "gn:admin3_code":"74",
    "gn:admin4_code":"740029",
    "gn:asciiname":"Sangaun",
    "gn:country_code":"NP",
    "gn:dem":1773,
    "gn:feature_class":"P",
    "gn:feature_code":"PPLL",
    "gn:name":"Sangaun",
    "gn:population":0,
    "gn:timezone":"Asia/Kathmandu",
    "iso:country":"NP",
    "wof:name":"Sangaun",
    "wof:placetype":"locality"
},
  "geometry": {"coordinates":[80.71289,29.56859],"type":"Point"}
}