{
  "type": "Feature",
  "properties": {
    "gn:admin1_code":"MR",
    "gn:admin2_code":"2",
    "gn:admin3_code":"60.0",
    "gn:admin4_code":"600026.0",
    "gn:asciiname":"Debal",
    "gn:country_code":"NP",
    "gn:dem":1257,
    "gn:feature_class":"P",
    "gn:feature_code":"PPLL",
    "gn:name":"Debal",
    "gn:population":0,
    "gn:timezone":"Asia/Kathmandu",
    "iso:country":"NP",
    "name:ara_x_preferred":[
        "\u0627\u0644\u062f\u064a\u0628\u0644"
    ],
    "name:hin_x_preferred":[
        "\u0926\u0947\u092c\u0932"
    ],
    "name:hun_x_preferred":[
        "Deb\u00e1l"
    ],
    "name:pnb_x_preferred":[
        "\u062f\u06cc\u0628\u0644"
    ],
    "name:rus_x_preferred":[
        "\u0414\u0435\u0431\u0430\u043b"
    ],
    "name:snd_x_preferred":[
        "\u062f\u064a\u0628\u0644"
    ],
    "name:ukr_x_preferred":[
        "\u0414\u0435\u0431\u0430\u043b"
    ],
    "name:urd_x_preferred":[
        "\u062f\u06cc\u0628\u0644"
    ],
    "wof:name":"Debal",
    "wof:placetype":"locality"
},
  "geometry": {"coordinates":[81.71593,28.8926],"type":"Point"}
}