{
  "type": "Feature",
  "properties": {
    "gn:admin1_code":"00",
    "gn:asciiname":"Bhanjyandada",
    "gn:country_code":"NP",
    "gn:dem":908,
    "gn:feature_class":"P",
    "gn:feature_code":"PPL",
    "gn:name":"Bha\u00f1jy\u0101\u1e45\u1e0d\u0101\u0303\u1e0d\u0101",
    "gn:population":0,
    "gn:timezone":"Asia/Kathmandu",
    "iso:country":"NP",
    "name:und_x_variant":[
        "Bha\u00f1jy\u0101\u1e45\u1e0d\u0101\u0303\u1e0d\u0101",
        "Bha\u00f1jy\u0101\u1e45\u1e0d\u0101n\u1e0d\u0101"
    ],
    "wof:name":"Bhanjyandada",
    "wof:placetype":"locality"
},
  "geometry": {"coordinates":[85.9383,27.36866],"type":"Point"}
}