{
  "type": "Feature",
  "properties": {
    "gn:admin1_code":"ER",
    "gn:admin2_code":"7",
    "gn:admin3_code":"5",
    "gn:admin4_code":"50066",
    "gn:asciiname":"Pirre",
    "gn:country_code":"NP",
    "gn:dem":970,
    "gn:feature_class":"P",
    "gn:feature_code":"PPLL",
    "gn:name":"Pirre",
    "gn:population":0,
    "gn:timezone":"Asia/Kathmandu",
    "iso:country":"NP",
    "wof:name":"Pirre",
    "wof:placetype":"locality"
},
  "geometry": {"coordinates":[87.35139000000002,26.80988],"type":"Point"}
}