{
  "type": "Feature",
  "properties": {
    "gn:admin1_code":"MR",
    "gn:admin2_code":"12",
    "gn:admin3_code":"54",
    "gn:admin4_code":"540018",
    "gn:asciiname":"Khabang",
    "gn:country_code":"NP",
    "gn:dem":2057,
    "gn:feature_class":"P",
    "gn:feature_code":"PPLL",
    "gn:name":"Khabang",
    "gn:population":0,
    "gn:timezone":"Asia/Kathmandu",
    "iso:country":"NP",
    "name:mai_x_preferred":[
        "\u0916\u0935\u093e\u0919"
    ],
    "name:msa_x_preferred":[
        "Khabang"
    ],
    "name:nep_x_preferred":[
        "\u0916\u0935\u093e\u0919"
    ],
    "name:new_x_preferred":[
        "\u0916\u0935\u093e\u0921"
    ],
    "name:pol_x_preferred":[
        "Khawang"
    ],
    "wof:name":"Khabang",
    "wof:placetype":"locality"
},
  "geometry": {"coordinates":[82.70922,28.5478],"type":"Point"}
}