{
  "type": "Feature",
  "properties": {
    "gn:admin1_code":"FR",
    "gn:admin2_code":"14.0",
    "gn:admin3_code":"68.0",
    "gn:admin4_code":"680041.0",
    "gn:asciiname":"Chhayala",
    "gn:country_code":"NP",
    "gn:dem":1753,
    "gn:feature_class":"P",
    "gn:feature_code":"PPLL",
    "gn:name":"Chhayala",
    "gn:population":0,
    "gn:timezone":"Asia/Kathmandu",
    "iso:country":"NP",
    "wof:name":"Chhayala",
    "wof:placetype":"locality"
},
  "geometry": {"coordinates":[81.14409999999999,29.53072],"type":"Point"}
}