{
  "type": "Feature",
  "properties": {
    "gn:admin1_code":"CR",
    "gn:admin2_code":"11.0",
    "gn:admin3_code":"33.0",
    "gn:admin4_code":"330036.0",
    "gn:asciiname":"Hegauliya",
    "gn:country_code":"NP",
    "gn:dem":96,
    "gn:feature_class":"P",
    "gn:feature_code":"PPLL",
    "gn:name":"Hegauliya",
    "gn:population":0,
    "gn:timezone":"Asia/Kathmandu",
    "iso:country":"NP",
    "wof:name":"Hegauliya",
    "wof:placetype":"locality"
},
  "geometry": {"coordinates":[85.10245,27.01545],"type":"Point"}
}