{
  "type": "Feature",
  "properties": {
    "gn:admin1_code":"CR",
    "gn:admin2_code":"1",
    "gn:admin3_code":"30.0",
    "gn:admin4_code":"300025.0",
    "gn:asciiname":"Salle",
    "gn:country_code":"NP",
    "gn:dem":1105,
    "gn:feature_class":"P",
    "gn:feature_code":"PPLL",
    "gn:name":"Salle",
    "gn:population":0,
    "gn:timezone":"Asia/Kathmandu",
    "iso:country":"NP",
    "wof:name":"Salle",
    "wof:placetype":"locality"
},
  "geometry": {"coordinates":[84.94386999999998,27.72979],"type":"Point"}
}