{
  "type": "Feature",
  "properties": {
    "gn:admin1_code":"MR",
    "gn:admin2_code":"12",
    "gn:admin3_code":"53",
    "gn:admin4_code":"530022",
    "gn:asciiname":"Magargori",
    "gn:country_code":"NP",
    "gn:dem":1208,
    "gn:feature_class":"P",
    "gn:feature_code":"PPLL",
    "gn:name":"Magargori",
    "gn:population":0,
    "gn:timezone":"Asia/Kathmandu",
    "iso:country":"NP",
    "wof:name":"Magargori",
    "wof:placetype":"locality"
},
  "geometry": {"coordinates":[82.41031,28.20288],"type":"Point"}
}