{
  "type": "Feature",
  "properties": {
    "gn:admin1_code":"CR",
    "gn:admin2_code":"11.0",
    "gn:admin3_code":"33.0",
    "gn:admin4_code":"330034.0",
    "gn:asciiname":"Dumarwana",
    "gn:country_code":"NP",
    "gn:dem":124,
    "gn:feature_class":"P",
    "gn:feature_code":"PPLL",
    "gn:name":"Dumarwana",
    "gn:population":0,
    "gn:timezone":"Asia/Kathmandu",
    "iso:country":"NP",
    "wof:name":"Dumarwana",
    "wof:placetype":"locality"
},
  "geometry": {"coordinates":[85.01904,27.13214],"type":"Point"}
}