{
  "type": "Feature",
  "properties": {
    "gn:admin1_code":"WR",
    "gn:admin2_code":"3",
    "gn:admin3_code":"44",
    "gn:admin4_code":"440031",
    "gn:asciiname":"Chilaunekharka",
    "gn:country_code":"NP",
    "gn:dem":1329,
    "gn:feature_class":"P",
    "gn:feature_code":"PPLL",
    "gn:name":"Chilaunekharka",
    "gn:population":0,
    "gn:timezone":"Asia/Kathmandu",
    "iso:country":"NP",
    "wof:name":"Chilaunekharka",
    "wof:placetype":"locality"
},
  "geometry": {"coordinates":[83.66954,28.12872],"type":"Point"}
}