{
  "type": "Feature",
  "properties": {
    "gn:admin1_code":"FR",
    "gn:admin2_code":"14",
    "gn:admin3_code":"70.0",
    "gn:admin4_code":"700042.0",
    "gn:asciiname":"Gaddigaun",
    "gn:country_code":"NP",
    "gn:dem":918,
    "gn:feature_class":"P",
    "gn:feature_code":"PPLL",
    "gn:name":"Gaddigaun",
    "gn:population":0,
    "gn:timezone":"Asia/Kathmandu",
    "iso:country":"NP",
    "wof:name":"Gaddigaun",
    "wof:placetype":"locality"
},
  "geometry": {"coordinates":[80.97287,29.20548],"type":"Point"}
}