{
  "type": "Feature",
  "properties": {
    "gn:admin1_code":"FR",
    "gn:admin2_code":"9",
    "gn:admin3_code":"74",
    "gn:admin4_code":"740006",
    "gn:asciiname":"Khadkholagaun",
    "gn:country_code":"NP",
    "gn:dem":1914,
    "gn:feature_class":"P",
    "gn:feature_code":"PPLL",
    "gn:name":"Khadkholagaun",
    "gn:population":0,
    "gn:timezone":"Asia/Kathmandu",
    "iso:country":"NP",
    "wof:name":"Khadkholagaun",
    "wof:placetype":"locality"
},
  "geometry": {"coordinates":[80.61264,29.56847],"type":"Point"}
}