{
  "type": "Feature",
  "properties": {
    "gn:admin1_code":"ER",
    "gn:admin2_code":"13",
    "gn:admin3_code":"11",
    "gn:admin4_code":"110019",
    "gn:asciiname":"Phulbari",
    "gn:country_code":"NP",
    "gn:dem":2140,
    "gn:feature_class":"P",
    "gn:feature_code":"PPLL",
    "gn:name":"Phulbari",
    "gn:population":0,
    "gn:timezone":"Asia/Kathmandu",
    "iso:country":"NP",
    "wof:name":"Phulbari",
    "wof:placetype":"locality"
},
  "geometry": {"coordinates":[86.53513000000002,27.44802],"type":"Point"}
}