{
  "type": "Feature",
  "properties": {
    "gn:admin1_code":"ER",
    "gn:admin2_code":"10.0",
    "gn:admin3_code":"1.0",
    "gn:admin4_code":"10001.0",
    "gn:asciiname":"Bunguwa",
    "gn:country_code":"NP",
    "gn:dem":888,
    "gn:feature_class":"P",
    "gn:feature_code":"PPLL",
    "gn:name":"Bunguwa",
    "gn:population":0,
    "gn:timezone":"Asia/Kathmandu",
    "iso:country":"NP",
    "wof:name":"Bunguwa",
    "wof:placetype":"locality"
},
  "geometry": {"coordinates":[87.85686,27.33009],"type":"Point"}
}