{
  "type": "Feature",
  "properties": {
    "gn:admin1_code":"FR",
    "gn:admin2_code":"14",
    "gn:admin3_code":"70.0",
    "gn:admin4_code":"700036.0",
    "gn:asciiname":"Ankhara",
    "gn:country_code":"NP",
    "gn:dem":1245,
    "gn:feature_class":"P",
    "gn:feature_code":"PPLL",
    "gn:name":"Ankhara",
    "gn:population":0,
    "gn:timezone":"Asia/Kathmandu",
    "iso:country":"NP",
    "wof:name":"Ankhara",
    "wof:placetype":"locality"
},
  "geometry": {"coordinates":[80.83811999999998,29.05212],"type":"Point"}
}