{
  "type": "Feature",
  "properties": {
    "gn:admin1_code":"MR",
    "gn:admin2_code":"2.0",
    "gn:admin3_code":"59.0",
    "gn:admin4_code":"590010.0",
    "gn:asciiname":"Sano Harre",
    "gn:country_code":"NP",
    "gn:dem":847,
    "gn:feature_class":"P",
    "gn:feature_code":"PPLL",
    "gn:name":"Sano Harre",
    "gn:population":0,
    "gn:timezone":"Asia/Kathmandu",
    "iso:country":"NP",
    "wof:name":"Sano Harre",
    "wof:placetype":"locality"
},
  "geometry": {"coordinates":[81.70195,28.4137],"type":"Point"}
}