{
  "type": "Feature",
  "properties": {
    "gn:admin1_code":"MR",
    "gn:admin2_code":"12",
    "gn:admin3_code":"54",
    "gn:admin4_code":"540010",
    "gn:asciiname":"Ageri Bisauna",
    "gn:country_code":"NP",
    "gn:dem":1711,
    "gn:feature_class":"P",
    "gn:feature_code":"PPLL",
    "gn:name":"Ageri Bisauna",
    "gn:population":0,
    "gn:timezone":"Asia/Kathmandu",
    "iso:country":"NP",
    "wof:name":"Ageri Bisauna",
    "wof:placetype":"locality"
},
  "geometry": {"coordinates":[82.42152,28.70025],"type":"Point"}
}