{
  "type": "Feature",
  "properties": {
    "gn:admin1_code":"CR",
    "gn:admin2_code":"1",
    "gn:admin3_code":"27.0",
    "gn:admin4_code":"270013.0",
    "gn:asciiname":"Tusalgaun",
    "gn:country_code":"NP",
    "gn:dem":1366,
    "gn:feature_class":"P",
    "gn:feature_code":"PPLL",
    "gn:name":"Tusalgaun",
    "gn:population":0,
    "gn:timezone":"Asia/Kathmandu",
    "iso:country":"NP",
    "wof:name":"Tusalgaun",
    "wof:placetype":"locality"
},
  "geometry": {"coordinates":[85.37114,27.7554],"type":"Point"}
}