{
  "type": "Feature",
  "properties": {
    "gn:admin1_code":"WR",
    "gn:admin2_code":"4",
    "gn:admin3_code":"40.0",
    "gn:admin4_code":"400032.0",
    "gn:asciiname":"Kundahar",
    "gn:country_code":"NP",
    "gn:dem":904,
    "gn:feature_class":"P",
    "gn:feature_code":"PPLL",
    "gn:name":"Kundahar",
    "gn:population":0,
    "gn:timezone":"Asia/Kathmandu",
    "iso:country":"NP",
    "wof:name":"Kundahar",
    "wof:placetype":"locality"
},
  "geometry": {"coordinates":[84.00774,28.21223],"type":"Point"}
}