{
  "type": "Feature",
  "properties": {
    "gn:admin1_code":"ER",
    "gn:admin2_code":"7",
    "gn:admin3_code":"10.0",
    "gn:admin4_code":"100058.0",
    "gn:asciiname":"Sawa",
    "gn:country_code":"NP",
    "gn:dem":1849,
    "gn:feature_class":"P",
    "gn:feature_code":"PPLL",
    "gn:name":"Sawa",
    "gn:population":0,
    "gn:timezone":"Asia/Kathmandu",
    "iso:country":"NP",
    "wof:name":"Sawa",
    "wof:placetype":"locality"
},
  "geometry": {"coordinates":[87.00114000000001,27.2786],"type":"Point"}
}