{
  "type": "Feature",
  "properties": {
    "gn:admin1_code":"WR",
    "gn:admin2_code":"4",
    "gn:admin3_code":"36.0",
    "gn:admin4_code":"360066.0",
    "gn:asciiname":"Khorlabeshi",
    "gn:country_code":"NP",
    "gn:dem":1232,
    "gn:feature_class":"P",
    "gn:feature_code":"PPLL",
    "gn:name":"Khorlabeshi",
    "gn:population":0,
    "gn:timezone":"Asia/Kathmandu",
    "iso:country":"NP",
    "wof:name":"Khorlabeshi",
    "wof:placetype":"locality"
},
  "geometry": {"coordinates":[84.87915,28.2586],"type":"Point"}
}