{
  "type": "Feature",
  "properties": {
    "gn:admin1_code":"CR",
    "gn:admin2_code":"5",
    "gn:admin3_code":"22.0",
    "gn:admin4_code":"220014.0",
    "gn:asciiname":"Dudhile Bhanjyang",
    "gn:country_code":"NP",
    "gn:dem":2278,
    "gn:feature_class":"P",
    "gn:feature_code":"PPLL",
    "gn:name":"Dudhile Bhanjyang",
    "gn:population":0,
    "gn:timezone":"Asia/Kathmandu",
    "iso:country":"NP",
    "wof:name":"Dudhile Bhanjyang",
    "wof:placetype":"locality"
},
  "geometry": {"coordinates":[86.00134,27.53151],"type":"Point"}
}