{
  "type": "Feature",
  "properties": {
    "gn:admin1_code":"ER",
    "gn:admin2_code":"7",
    "gn:admin3_code":"5",
    "gn:admin4_code":"50028",
    "gn:asciiname":"Jate",
    "gn:country_code":"NP",
    "gn:dem":366,
    "gn:feature_class":"P",
    "gn:feature_code":"PPLL",
    "gn:name":"Jate",
    "gn:population":0,
    "gn:timezone":"Asia/Kathmandu",
    "iso:country":"NP",
    "wof:name":"Jate",
    "wof:placetype":"locality"
},
  "geometry": {"coordinates":[87.54770000000001,26.76071],"type":"Point"}
}