{
  "type": "Feature",
  "properties": {
    "gn:admin1_code":"MR",
    "gn:admin2_code":"12",
    "gn:admin3_code":"53",
    "gn:admin4_code":"530038",
    "gn:asciiname":"Daunnebhir",
    "gn:country_code":"NP",
    "gn:dem":1921,
    "gn:feature_class":"P",
    "gn:feature_code":"PPLL",
    "gn:name":"Daunnebhir",
    "gn:population":0,
    "gn:timezone":"Asia/Kathmandu",
    "iso:country":"NP",
    "wof:name":"Daunnebhir",
    "wof:placetype":"locality"
},
  "geometry": {"coordinates":[82.56458000000001,28.49061],"type":"Point"}
}