{
  "type": "Feature",
  "properties": {
    "gn:admin1_code":"MR",
    "gn:admin2_code":"12",
    "gn:admin3_code":"55",
    "gn:admin4_code":"550033",
    "gn:asciiname":"Bharne",
    "gn:country_code":"NP",
    "gn:dem":1714,
    "gn:feature_class":"P",
    "gn:feature_code":"PPLL",
    "gn:name":"Bharne",
    "gn:population":0,
    "gn:timezone":"Asia/Kathmandu",
    "iso:country":"NP",
    "wof:name":"Bharne",
    "wof:placetype":"locality"
},
  "geometry": {"coordinates":[82.2011,28.51599],"type":"Point"}
}