{
  "type": "Feature",
  "properties": {
    "gn:admin1_code":"MR",
    "gn:admin2_code":"12",
    "gn:admin3_code":"52",
    "gn:admin4_code":"520024",
    "gn:asciiname":"Rujim",
    "gn:country_code":"NP",
    "gn:dem":1892,
    "gn:feature_class":"P",
    "gn:feature_code":"PPLL",
    "gn:name":"Rujim",
    "gn:population":0,
    "gn:timezone":"Asia/Kathmandu",
    "iso:country":"NP",
    "wof:name":"Rujim",
    "wof:placetype":"locality"
},
  "geometry": {"coordinates":[82.96071999999999,28.23226],"type":"Point"}
}