{
  "type": "Feature",
  "properties": {
    "gn:admin1_code":"FR",
    "gn:admin2_code":"9",
    "gn:admin3_code":"74",
    "gn:admin4_code":"740002",
    "gn:asciiname":"Dwan",
    "gn:country_code":"NP",
    "gn:dem":1678,
    "gn:feature_class":"P",
    "gn:feature_code":"PPLL",
    "gn:name":"Dwan",
    "gn:population":0,
    "gn:timezone":"Asia/Kathmandu",
    "iso:country":"NP",
    "wof:name":"Dwan",
    "wof:placetype":"locality"
},
  "geometry": {"coordinates":[80.49804,29.4753],"type":"Point"}
}