{
  "type": "Feature",
  "properties": {
    "gn:admin1_code":"WR",
    "gn:admin2_code":"4.0",
    "gn:admin3_code":"38.0",
    "gn:admin4_code":"380003.0",
    "gn:asciiname":"Lek",
    "gn:country_code":"NP",
    "gn:dem":1322,
    "gn:feature_class":"P",
    "gn:feature_code":"PPLL",
    "gn:name":"Lek",
    "gn:population":0,
    "gn:timezone":"Asia/Kathmandu",
    "iso:country":"NP",
    "name:afr_x_preferred":[
        "Lek"
    ],
    "name:als_x_preferred":[
        "Lek"
    ],
    "name:ceb_x_preferred":[
        "Lek"
    ],
    "name:deu_x_preferred":[
        "Lek"
    ],
    "name:epo_x_preferred":[
        "Lek"
    ],
    "name:fra_x_preferred":[
        "Lek"
    ],
    "name:fry_x_preferred":[
        "Lek"
    ],
    "name:kir_x_preferred":[
        "\u041b\u0435\u043a"
    ],
    "name:nld_x_preferred":[
        "Lek"
    ],
    "name:nor_x_preferred":[
        "Lek"
    ],
    "name:pol_x_preferred":[
        "Lek"
    ],
    "name:rus_x_preferred":[
        "\u041b\u0435\u043a"
    ],
    "name:slv_x_preferred":[
        "Lek"
    ],
    "name:spa_x_preferred":[
        "Lek"
    ],
    "name:swe_x_preferred":[
        "Lek"
    ],
    "name:ukr_x_preferred":[
        "\u041b\u0435\u043a"
    ],
    "name:uzb_x_preferred":[
        "Lek"
    ],
    "name:vls_x_preferred":[
        "Lek"
    ],
    "wof:name":"Lek",
    "wof:placetype":"locality"
},
  "geometry": {"coordinates":[84.34799,27.8255],"type":"Point"}
}