{
  "type": "Feature",
  "properties": {
    "gn:admin1_code":"WR",
    "gn:admin2_code":"4",
    "gn:admin3_code":"40.0",
    "gn:admin4_code":"400032.0",
    "gn:asciiname":"Gupteshwar Mahadev",
    "gn:country_code":"NP",
    "gn:dem":793,
    "gn:feature_class":"P",
    "gn:feature_code":"PPLL",
    "gn:name":"Gupteshwar Mahadev",
    "gn:population":0,
    "gn:timezone":"Asia/Kathmandu",
    "iso:country":"NP",
    "wof:name":"Gupteshwar Mahadev",
    "wof:placetype":"locality"
},
  "geometry": {"coordinates":[83.96250000000001,28.18969],"type":"Point"}
}