{
  "type": "Feature",
  "properties": {
    "gn:admin1_code":"CR",
    "gn:admin2_code":"5",
    "gn:admin3_code":"21",
    "gn:admin4_code":"210053",
    "gn:asciiname":"Lapchane Khane",
    "gn:country_code":"NP",
    "gn:dem":2808,
    "gn:feature_class":"P",
    "gn:feature_code":"PPLL",
    "gn:name":"Lapchane Khane",
    "gn:population":0,
    "gn:timezone":"Asia/Kathmandu",
    "iso:country":"NP",
    "wof:name":"Lapchane Khane",
    "wof:placetype":"locality"
},
  "geometry": {"coordinates":[86.28868,27.56227],"type":"Point"}
}