{
  "type": "Feature",
  "properties": {
    "gn:admin1_code":"CR",
    "gn:admin2_code":"5",
    "gn:admin3_code":"18",
    "gn:admin4_code":"180077",
    "gn:asciiname":"Palar",
    "gn:country_code":"NP",
    "gn:dem":114,
    "gn:feature_class":"P",
    "gn:feature_code":"PPLL",
    "gn:name":"Palar",
    "gn:population":0,
    "gn:timezone":"Asia/Kathmandu",
    "iso:country":"NP",
    "name:ara_x_preferred":[
        "\u0628\u0627\u0644\u0627\u0631"
    ],
    "name:ben_x_preferred":[
        "\u09aa\u09be\u09b2\u09be\u09b0"
    ],
    "name:ell_x_preferred":[
        "\u03a0\u03b1\u03bb\u03ac\u03c1"
    ],
    "name:fas_x_preferred":[
        "\u067e\u0627\u0644\u0627\u0631"
    ],
    "name:heb_x_preferred":[
        "\u05e4\u05d0\u05dc\u05d0\u05e8"
    ],
    "name:hun_x_preferred":[
        "Palar"
    ],
    "name:ind_x_preferred":[
        "Palar"
    ],
    "name:ita_x_preferred":[
        "Palar"
    ],
    "name:kor_x_preferred":[
        "\ud314\ub77c\ub974"
    ],
    "name:nld_x_preferred":[
        "Palar"
    ],
    "name:pol_x_preferred":[
        "Palar"
    ],
    "name:por_x_preferred":[
        "Palar"
    ],
    "name:swe_x_preferred":[
        "Palar"
    ],
    "name:tur_x_preferred":[
        "Palar"
    ],
    "name:ukr_x_preferred":[
        "\u041f\u0430\u043b\u0430\u0440"
    ],
    "name:urd_x_preferred":[
        "\u067e\u0627\u0644\u0627\u0631"
    ],
    "name:vie_x_preferred":[
        "S\u00f4ng Palar"
    ],
    "name:zho_cn_x_preferred":[
        "\u5df4\u62c9\u5c14\u6cb3"
    ],
    "name:zho_tw_x_preferred":[
        "\u5e15\u62c9\u6cb3"
    ],
    "wof:name":"Palar",
    "wof:placetype":"locality"
},
  "geometry": {"coordinates":[85.88024,26.875],"type":"Point"}
}