{
  "type": "Feature",
  "properties": {
    "gn:admin1_code":"CR",
    "gn:admin2_code":"5",
    "gn:admin3_code":"18",
    "gn:admin4_code":"180077",
    "gn:asciiname":"Palar",
    "gn:country_code":"NP",
    "gn:dem":114,
    "gn:feature_class":"P",
    "gn:feature_code":"PPLL",
    "gn:name":"Palar",
    "gn:population":0,
    "gn:timezone":"Asia/Kathmandu",
    "iso:country":"NP",
    "wof:name":"Palar",
    "wof:placetype":"locality"
},
  "geometry": {"coordinates":[85.88024,26.875],"type":"Point"}
}