{
  "type": "Feature",
  "properties": {
    "gn:admin1_code":"ER",
    "gn:admin2_code":"7",
    "gn:admin3_code":"5",
    "gn:admin4_code":"50065.0",
    "gn:asciiname":"Hattikharka",
    "gn:country_code":"NP",
    "gn:dem":896,
    "gn:feature_class":"P",
    "gn:feature_code":"PPLL",
    "gn:name":"Hattikharka",
    "gn:population":0,
    "gn:timezone":"Asia/Kathmandu",
    "iso:country":"NP",
    "wof:name":"Hattikharka",
    "wof:placetype":"locality"
},
  "geometry": {"coordinates":[87.52988000000001,26.81551],"type":"Point"}
}