{
  "type": "Feature",
  "properties": {
    "gn:admin1_code":"CR",
    "gn:admin2_code":"1",
    "gn:admin3_code":"30.0",
    "gn:admin4_code":"300026.0",
    "gn:asciiname":"Gobretar",
    "gn:country_code":"NP",
    "gn:dem":418,
    "gn:feature_class":"P",
    "gn:feature_code":"PPLL",
    "gn:name":"Gobretar",
    "gn:population":0,
    "gn:timezone":"Asia/Kathmandu",
    "iso:country":"NP",
    "wof:name":"Gobretar",
    "wof:placetype":"locality"
},
  "geometry": {"coordinates":[84.86868,27.80519],"type":"Point"}
}