{
  "type": "Feature",
  "properties": {
    "gn:admin1_code":"00",
    "gn:asciiname":"Ghilinggaon",
    "gn:country_code":"NP",
    "gn:dem":3607,
    "gn:feature_class":"P",
    "gn:feature_code":"PPL",
    "gn:name":"Ghilinggaon",
    "gn:population":0,
    "gn:timezone":"Asia/Kathmandu",
    "iso:country":"NP",
    "wof:name":"Ghilinggaon",
    "wof:placetype":"locality"
},
  "geometry": {"coordinates":[83.85949000000002,29.0119],"type":"Point"}
}