{
  "type": "Feature",
  "properties": {
    "gn:admin1_code":"WR",
    "gn:admin2_code":"4.0",
    "gn:admin3_code":"39.0",
    "gn:admin4_code":"390045.0",
    "gn:asciiname":"Khali",
    "gn:country_code":"NP",
    "gn:dem":962,
    "gn:feature_class":"P",
    "gn:feature_code":"PPLL",
    "gn:name":"Khali",
    "gn:population":0,
    "gn:timezone":"Asia/Kathmandu",
    "iso:country":"NP",
    "name:ceb_x_preferred":[
        "Khali"
    ],
    "name:por_x_preferred":[
        "Khali"
    ],
    "wof:name":"Khali",
    "wof:placetype":"locality"
},
  "geometry": {"coordinates":[83.89456,28.05226],"type":"Point"}
}