{
  "type": "Feature",
  "properties": {
    "gn:admin1_code":"MR",
    "gn:admin2_code":"12",
    "gn:admin3_code":"56.0",
    "gn:admin4_code":"560029.0",
    "gn:asciiname":"Lungkush",
    "gn:country_code":"NP",
    "gn:dem":1417,
    "gn:feature_class":"P",
    "gn:feature_code":"PPLL",
    "gn:name":"Lungkush",
    "gn:population":0,
    "gn:timezone":"Asia/Kathmandu",
    "iso:country":"NP",
    "wof:name":"Lungkush",
    "wof:placetype":"locality"
},
  "geometry": {"coordinates":[82.59832,28.00301],"type":"Point"}
}