{
  "type": "Feature",
  "properties": {
    "gn:admin1_code":"CR",
    "gn:admin2_code":"11",
    "gn:admin3_code":"31",
    "gn:admin4_code":"310032",
    "gn:asciiname":"Pakanikharka",
    "gn:country_code":"NP",
    "gn:dem":1501,
    "gn:feature_class":"P",
    "gn:feature_code":"PPLL",
    "gn:name":"Pakanikharka",
    "gn:population":0,
    "gn:timezone":"Asia/Kathmandu",
    "iso:country":"NP",
    "wof:name":"Pakanikharka",
    "wof:placetype":"locality"
},
  "geometry": {"coordinates":[85.00305,27.58486],"type":"Point"}
}