{
  "type": "Feature",
  "properties": {
    "gn:admin1_code":"WR",
    "gn:admin2_code":"3",
    "gn:admin3_code":"45.0",
    "gn:admin4_code":"450047.0",
    "gn:asciiname":"Samundra",
    "gn:country_code":"NP",
    "gn:dem":1361,
    "gn:feature_class":"P",
    "gn:feature_code":"PPLL",
    "gn:name":"Samundra",
    "gn:population":0,
    "gn:timezone":"Asia/Kathmandu",
    "iso:country":"NP",
    "wof:name":"Samundra",
    "wof:placetype":"locality"
},
  "geometry": {"coordinates":[83.55077,28.13161],"type":"Point"}
}