{
  "type": "Feature",
  "properties": {
    "gn:admin1_code":"CR",
    "gn:admin2_code":"1",
    "gn:admin3_code":"23",
    "gn:admin4_code":"230043",
    "gn:asciiname":"Paku",
    "gn:country_code":"NP",
    "gn:dem":2215,
    "gn:feature_class":"P",
    "gn:feature_code":"PPLL",
    "gn:name":"Paku",
    "gn:population":0,
    "gn:timezone":"Asia/Kathmandu",
    "iso:country":"NP",
    "wof:name":"Paku",
    "wof:placetype":"locality"
},
  "geometry": {"coordinates":[85.87585,27.89714],"type":"Point"}
}