{
  "type": "Feature",
  "properties": {
    "gn:admin1_code":"WR",
    "gn:admin2_code":"3",
    "gn:admin3_code":"45",
    "gn:admin4_code":"450057",
    "gn:asciiname":"Okhreni",
    "gn:country_code":"NP",
    "gn:dem":1688,
    "gn:feature_class":"P",
    "gn:feature_code":"PPLL",
    "gn:name":"Okhreni",
    "gn:population":0,
    "gn:timezone":"Asia/Kathmandu",
    "iso:country":"NP",
    "name:ceb_x_preferred":[
        "Okhreni"
    ],
    "name:msa_x_preferred":[
        "Okhreni"
    ],
    "name:nep_x_preferred":[
        "\u0913\u0916\u094d\u0930\u0947\u0928\u0940"
    ],
    "name:new_x_preferred":[
        "\u0913\u0916\u094d\u0930\u0947\u0928\u0940"
    ],
    "name:pol_x_preferred":[
        "Okhreni"
    ],
    "wof:name":"Okhreni",
    "wof:placetype":"locality"
},
  "geometry": {"coordinates":[83.03421999999998,28.38479],"type":"Point"}
}