{
  "type": "Feature",
  "properties": {
    "gn:admin1_code":"FR",
    "gn:admin2_code":"14",
    "gn:admin3_code":"70.0",
    "gn:admin4_code":"700003.0",
    "gn:asciiname":"Joena",
    "gn:country_code":"NP",
    "gn:dem":1087,
    "gn:feature_class":"P",
    "gn:feature_code":"PPLL",
    "gn:name":"Joena",
    "gn:population":0,
    "gn:timezone":"Asia/Kathmandu",
    "iso:country":"NP",
    "wof:name":"Joena",
    "wof:placetype":"locality"
},
  "geometry": {"coordinates":[80.78573,29.01678],"type":"Point"}
}