{
  "type": "Feature",
  "properties": {
    "gn:admin1_code":"WR",
    "gn:admin2_code":"8",
    "gn:admin3_code":"46.0",
    "gn:admin4_code":"460071.0",
    "gn:asciiname":"Arjyagaun",
    "gn:country_code":"NP",
    "gn:dem":986,
    "gn:feature_class":"P",
    "gn:feature_code":"PPLL",
    "gn:name":"Arjyagaun",
    "gn:population":0,
    "gn:timezone":"Asia/Kathmandu",
    "iso:country":"NP",
    "wof:name":"Arjyagaun",
    "wof:placetype":"locality"
},
  "geometry": {"coordinates":[83.40961,28.0932],"type":"Point"}
}