{
  "type": "Feature",
  "properties": {
    "gn:admin1_code":"ER",
    "gn:admin2_code":"7",
    "gn:admin3_code":"7.0",
    "gn:admin4_code":"70015.0",
    "gn:asciiname":"Barbote",
    "gn:country_code":"NP",
    "gn:dem":920,
    "gn:feature_class":"P",
    "gn:feature_code":"PPLL",
    "gn:name":"Barbote",
    "gn:population":0,
    "gn:timezone":"Asia/Kathmandu",
    "iso:country":"NP",
    "name:bih_x_preferred":[
        "\u092c\u0930\u092c\u094b\u091f\u0947"
    ],
    "name:ceb_x_preferred":[
        "Barbote"
    ],
    "name:mai_x_preferred":[
        "\u092c\u0930\u092c\u094b\u091f\u0947"
    ],
    "name:msa_x_preferred":[
        "Barbote"
    ],
    "name:nep_x_preferred":[
        "\u092c\u0930\u092c\u094b\u091f\u0947"
    ],
    "name:nld_x_preferred":[
        "Barbote"
    ],
    "name:pol_x_preferred":[
        "Barbote"
    ],
    "wof:name":"Barbote",
    "wof:placetype":"locality"
},
  "geometry": {"coordinates":[87.32092,26.98798],"type":"Point"}
}