{
  "type": "Feature",
  "properties": {
    "gn:admin1_code":"00",
    "gn:asciiname":"Tamantol",
    "gn:country_code":"NP",
    "gn:dem":81,
    "gn:feature_class":"P",
    "gn:feature_code":"PPL",
    "gn:name":"T\u0101m\u0101\u1e45\u1e6dol",
    "gn:population":0,
    "gn:timezone":"Asia/Kathmandu",
    "iso:country":"NP",
    "name:nep_x_preferred":[
        "T\u0101m\u0101\u1e45\u1e6dol"
    ],
    "wof:name":"Tamantol",
    "wof:placetype":"locality"
},
  "geometry": {"coordinates":[87.2289,26.52343],"type":"Point"}
}