{
  "type": "Feature",
  "properties": {
    "gn:admin1_code":"WR",
    "gn:admin2_code":"8",
    "gn:admin3_code":"46.0",
    "gn:admin4_code":"460079.0",
    "gn:asciiname":"Malarani",
    "gn:country_code":"NP",
    "gn:dem":1509,
    "gn:feature_class":"P",
    "gn:feature_code":"PPLL",
    "gn:name":"Malarani",
    "gn:population":0,
    "gn:timezone":"Asia/Kathmandu",
    "iso:country":"NP",
    "name:ceb_x_preferred":[
        "Malarani"
    ],
    "name:fra_x_preferred":[
        "Malarani"
    ],
    "name:mai_x_preferred":[
        "\u092e\u093e\u0932\u093e\u0930\u093e\u0928\u0940"
    ],
    "name:msa_x_preferred":[
        "Malarani"
    ],
    "name:nep_x_preferred":[
        "\u092e\u093e\u0932\u093e\u0930\u093e\u0928\u0940"
    ],
    "name:new_x_preferred":[
        "\u092e\u093e\u0932\u093e\u0930\u093e\u0928\u0940"
    ],
    "name:pol_x_preferred":[
        "Malarani"
    ],
    "wof:name":"Malarani",
    "wof:placetype":"locality"
},
  "geometry": {"coordinates":[83.32559999999999,28.16741],"type":"Point"}
}