{
  "type": "Feature",
  "properties": {
    "gn:admin1_code":"MR",
    "gn:admin2_code":"12",
    "gn:admin3_code":"55",
    "gn:admin4_code":"550030",
    "gn:asciiname":"Pokhara",
    "gn:country_code":"NP",
    "gn:dem":1752,
    "gn:feature_class":"P",
    "gn:feature_code":"PPLL",
    "gn:name":"Pokhara",
    "gn:population":0,
    "gn:timezone":"Asia/Kathmandu",
    "iso:country":"NP",
    "name:ara_x_preferred":[
        "\u0628\u0648\u062e\u0627\u0631\u0627"
    ],
    "name:arg_x_preferred":[
        "Pokhara"
    ],
    "name:ben_x_preferred":[
        "\u09aa\u09cb\u0996\u09b0\u09be"
    ],
    "name:bih_x_preferred":[
        "\u092a\u094b\u0916\u0930\u093e"
    ],
    "name:bul_x_preferred":[
        "\u041f\u043e\u043a\u0445\u0430\u0440\u0430"
    ],
    "name:cat_x_preferred":[
        "Pokhara"
    ],
    "name:ceb_x_preferred":[
        "Pokhara"
    ],
    "name:ces_x_preferred":[
        "P\u00f3khara"
    ],
    "name:dan_x_preferred":[
        "Pokhara"
    ],
    "name:deu_x_preferred":[
        "Pokhara"
    ],
    "name:dty_x_preferred":[
        "\u092a\u094b\u0916\u0930\u093e \u0909\u092a\u092e\u0939\u093e\u0928\u0917\u0930\u092a\u093e\u0932\u093f\u0915\u093e"
    ],
    "name:ell_x_preferred":[
        "\u03a0\u03bf\u03ba\u03ac\u03c1\u03b1"
    ],
    "name:epo_x_preferred":[
        "Pokhara"
    ],
    "name:eus_x_preferred":[
        "Pokhara"
    ],
    "name:fas_x_preferred":[
        "\u067e\u0648\u062e\u0627\u0631\u0627"
    ],
    "name:fij_x_preferred":[
        "Pokhara"
    ],
    "name:fin_x_preferred":[
        "Pokhara"
    ],
    "name:fra_x_preferred":[
        "Pokhara"
    ],
    "name:glg_x_preferred":[
        "Pokhara"
    ],
    "name:heb_x_preferred":[
        "\u05e4\u05d5\u05e7\u05d4\u05e8\u05d4"
    ],
    "name:hin_x_preferred":[
        "\u092a\u094b\u0916\u0930\u093e"
    ],
    "name:hun_x_preferred":[
        "Pokhara"
    ],
    "name:ind_x_preferred":[
        "Pokhara"
    ],
    "name:ita_x_preferred":[
        "Pokhara"
    ],
    "name:jpn_x_preferred":[
        "\u30dd\u30ab\u30e9"
    ],
    "name:kan_x_preferred":[
        "\u0caa\u0cca\u0c96\u0cb0\u0cbe"
    ],
    "name:kor_x_preferred":[
        "\ud3ec\uce74\ub77c"
    ],
    "name:lit_x_preferred":[
        "Pokhara"
    ],
    "name:mal_x_preferred":[
        "\u0d2a\u0d4a\u0d16\u0d3e\u0d31"
    ],
    "name:mon_x_preferred":[
        "\u041f\u043e\u043a\u0445\u0430\u0440\u0430"
    ],
    "name:nld_x_preferred":[
        "Pokhara"
    ],
    "name:nor_x_preferred":[
        "Pokhara"
    ],
    "name:pan_x_preferred":[
        "\u0a2a\u0a4b\u0a16\u0a30\u0a3e"
    ],
    "name:pol_x_preferred":[
        "Pokhara"
    ],
    "name:por_x_preferred":[
        "Pokhara"
    ],
    "name:ron_x_preferred":[
        "Pokhara"
    ],
    "name:rus_x_preferred":[
        "\u041f\u043e\u043a\u0445\u0430\u0440\u0430"
    ],
    "name:slv_x_preferred":[
        "Pokhara"
    ],
    "name:spa_x_preferred":[
        "Pokhara"
    ],
    "name:swe_x_preferred":[
        "Pokhara"
    ],
    "name:tam_x_preferred":[
        "\u0baa\u0bca\u0b95\u0bcd\u0b95\u0bbe\u0bb0\u0bbe"
    ],
    "name:tha_x_preferred":[
        "\u0e42\u0e1b\u0e02\u0e23\u0e32"
    ],
    "name:tur_x_preferred":[
        "Pokhara"
    ],
    "name:ukr_x_preferred":[
        "\u041f\u043e\u043a\u0445\u0430\u0440\u0430"
    ],
    "name:urd_x_preferred":[
        "\u067e\u0648\u06a9\u06be\u0631\u0627"
    ],
    "name:vep_x_preferred":[
        "Pokhar"
    ],
    "name:vie_x_preferred":[
        "Pokhara"
    ],
    "name:zho_x_preferred":[
        "\u535a\u5361\u62c9"
    ],
    "wof:name":"Pokhara",
    "wof:placetype":"locality"
},
  "geometry": {"coordinates":[82.28246999999998,28.37955],"type":"Point"}
}