{
  "type": "Feature",
  "properties": {
    "iso:country":"NP",
    "name:ara_x_preferred":[
        "\u062d\u064a \u0631\u0627\u0645\u064a\u062a\u0634\u0627\u0628"
    ],
    "name:bho_x_preferred":[
        "\u0930\u093e\u092e\u0947\u091b\u093e\u092a \u0917\u093e\u0935\u093f\u0938"
    ],
    "name:chi_x_preferred":[
        "\u62c9\u6885\u6070\u5e03\u5e02"
    ],
    "name:dut_x_preferred":[
        "Ramechhap"
    ],
    "name:eng_x_preferred":[
        "Ramechhap"
    ],
    "name:fre_x_preferred":[
        "Ramechhap"
    ],
    "name:ger_x_preferred":[
        "Ramechhap"
    ],
    "name:nep_x_preferred":[
        "\u0930\u093e\u092e\u0947\u091b\u093e\u092a \u0917\u093e\u0935\u093f\u0938"
    ],
    "name:new_x_preferred":[
        "\u0930\u093e\u092e\u0947\u091b\u093e\u092a \u0917\u093e\u0935\u093f\u0938"
    ],
    "name:pol_x_preferred":[
        "Ramechhap"
    ],
    "name:por_x_preferred":[
        "Ramechhap"
    ],
    "ne:ADM0CAP":0.0,
    "ne:ADM0NAME":"Nepal",
    "ne:ADM0_A3":"NPL",
    "ne:ADM1NAME":"Janakpur",
    "ne:ADMIN1_COD":0,
    "ne:CAPALT":0,
    "ne:CHANGED":4,
    "ne:CHECKME":0,
    "ne:COMPARE":0,
    "ne:DIFFASCII":0,
    "ne:DIFFNOTE":"Added missing admin-1 capital.",
    "ne:ELEVATION":0.0,
    "ne:FEATURECLA":"Admin-1 capital",
    "ne:GEONAMEID":-1,
    "ne:GEONAMESNO":"No GeoNames match due to small population, not in GeoNames, or poor NEV placement.",
    "ne:GN_POP":0,
    "ne:GTOPO30":0.0,
    "ne:ISO_A2":"NP",
    "ne:LABELRANK":6,
    "ne:LATITUDE":27.325998,
    "ne:LONGITUDE":86.086999,
    "ne:LS_MATCH":0,
    "ne:MAX_AREAKM":0.0,
    "ne:MAX_AREAMI":0.0,
    "ne:MAX_BBXMAX":0.0,
    "ne:MAX_BBXMIN":0.0,
    "ne:MAX_BBYMAX":0.0,
    "ne:MAX_BBYMIN":0.0,
    "ne:MAX_NATSCA":0.0,
    "ne:MAX_PERKM":0.0,
    "ne:MAX_PERMI":0.0,
    "ne:MAX_POP10":0,
    "ne:MAX_POP20":0,
    "ne:MAX_POP300":0,
    "ne:MAX_POP310":0,
    "ne:MAX_POP50":0,
    "ne:MEAN_BBXC":0.0,
    "ne:MEAN_BBYC":0.0,
    "ne:MEGACITY":0,
    "ne:MIN_AREAKM":0.0,
    "ne:MIN_AREAMI":0.0,
    "ne:MIN_BBXMAX":0.0,
    "ne:MIN_BBXMIN":0.0,
    "ne:MIN_BBYMAX":0.0,
    "ne:MIN_BBYMIN":0.0,
    "ne:MIN_PERKM":0.0,
    "ne:MIN_PERMI":0.0,
    "ne:NAME":"Ramechhap",
    "ne:NAMEASCII":"Ramechhap",
    "ne:NAMEDIFF":1,
    "ne:NATSCALE":1,
    "ne:POP1950":0,
    "ne:POP1955":0,
    "ne:POP1960":0,
    "ne:POP1965":0,
    "ne:POP1970":0,
    "ne:POP1975":0,
    "ne:POP1980":0,
    "ne:POP1985":0,
    "ne:POP1990":0,
    "ne:POP1995":0,
    "ne:POP2000":0,
    "ne:POP2005":0,
    "ne:POP2010":0,
    "ne:POP2015":0,
    "ne:POP2020":0,
    "ne:POP2025":0,
    "ne:POP2050":0,
    "ne:POP_MAX":15000,
    "ne:POP_MIN":15000,
    "ne:POP_OTHER":0,
    "ne:RANK_MAX":6,
    "ne:RANK_MIN":6,
    "ne:SCALERANK":10,
    "ne:SOV0NAME":"Nepal",
    "ne:SOV_A3":"NPL",
    "ne:UN_FID":0,
    "ne:UN_LAT":0.0,
    "ne:UN_LONG":0.0,
    "ne:WORLDCITY":0,
    "ne:min_zoom":9.0,
    "wof:name":"Ramechhap",
    "wof:placetype":"locality"
},
  "geometry": {"coordinates":[86.08699852858143,27.32599807568982],"type":"Point"}
}