{
  "type": "Feature",
  "properties": {
    "gn:admin1_code":"CR",
    "gn:admin2_code":"5",
    "gn:admin3_code":"20",
    "gn:admin4_code":"200026",
    "gn:asciiname":"Kartike",
    "gn:country_code":"NP",
    "gn:dem":993,
    "gn:feature_class":"P",
    "gn:feature_code":"PPLL",
    "gn:name":"Kartike",
    "gn:population":0,
    "gn:timezone":"Asia/Kathmandu",
    "iso:country":"NP",
    "wof:name":"Kartike",
    "wof:placetype":"locality"
},
  "geometry": {"coordinates":[85.68248,27.32453],"type":"Point"}
}