{
  "type": "Feature",
  "properties": {
    "gn:admin1_code":"FR",
    "gn:admin2_code":"14",
    "gn:admin3_code":"69",
    "gn:admin4_code":"690032",
    "gn:asciiname":"Kuntanko Gado",
    "gn:country_code":"NP",
    "gn:dem":1834,
    "gn:feature_class":"P",
    "gn:feature_code":"PPLL",
    "gn:name":"Kuntanko Gado",
    "gn:population":0,
    "gn:timezone":"Asia/Kathmandu",
    "iso:country":"NP",
    "wof:name":"Kuntanko Gado",
    "wof:placetype":"locality"
},
  "geometry": {"coordinates":[81.29413000000002,29.11112],"type":"Point"}
}