{
  "type": "Feature",
  "properties": {
    "gn:admin1_code":"FR",
    "gn:admin2_code":"14",
    "gn:admin3_code":"71.0",
    "gn:admin4_code":"710031.0",
    "gn:asciiname":"Bhakraiya",
    "gn:country_code":"NP",
    "gn:dem":174,
    "gn:feature_class":"P",
    "gn:feature_code":"PPLL",
    "gn:name":"Bhakraiya",
    "gn:population":0,
    "gn:timezone":"Asia/Kathmandu",
    "iso:country":"NP",
    "wof:name":"Bhakraiya",
    "wof:placetype":"locality"
},
  "geometry": {"coordinates":[81.16401999999999,28.57414],"type":"Point"}
}