{
  "type": "Feature",
  "properties": {
    "gn:admin1_code":"ER",
    "gn:admin2_code":"10",
    "gn:admin3_code":"3.0",
    "gn:admin4_code":"30002.0",
    "gn:asciiname":"Jabbare",
    "gn:country_code":"NP",
    "gn:dem":1484,
    "gn:feature_class":"P",
    "gn:feature_code":"PPLL",
    "gn:name":"Jabbare",
    "gn:population":0,
    "gn:timezone":"Asia/Kathmandu",
    "iso:country":"NP",
    "wof:name":"Jabbare",
    "wof:placetype":"locality"
},
  "geometry": {"coordinates":[87.66171999999997,26.86272],"type":"Point"}
}