{
  "type": "Feature",
  "properties": {
    "gn:admin1_code":"ER",
    "gn:admin2_code":"13",
    "gn:admin3_code":"13.0",
    "gn:admin4_code":"130003.0",
    "gn:asciiname":"Khokseli",
    "gn:country_code":"NP",
    "gn:dem":739,
    "gn:feature_class":"P",
    "gn:feature_code":"PPLL",
    "gn:name":"Khokseli",
    "gn:population":0,
    "gn:timezone":"Asia/Kathmandu",
    "iso:country":"NP",
    "wof:name":"Khokseli",
    "wof:placetype":"locality"
},
  "geometry": {"coordinates":[86.56134,27.21041],"type":"Point"}
}