{
  "type": "Feature",
  "properties": {
    "gn:admin1_code":"FR",
    "gn:admin2_code":"14",
    "gn:admin3_code":"68",
    "gn:admin4_code":"680014",
    "gn:asciiname":"Thulogaro Goth",
    "gn:country_code":"NP",
    "gn:dem":1783,
    "gn:feature_class":"P",
    "gn:feature_code":"PPLL",
    "gn:name":"Thulogaro Goth",
    "gn:population":0,
    "gn:timezone":"Asia/Kathmandu",
    "iso:country":"NP",
    "wof:name":"Thulogaro Goth",
    "wof:placetype":"locality"
},
  "geometry": {"coordinates":[81.25684,29.6258],"type":"Point"}
}