{
  "type": "Feature",
  "properties": {
    "gn:admin1_code":"ER",
    "gn:admin2_code":"7",
    "gn:admin3_code":"9",
    "gn:admin4_code":"90022",
    "gn:asciiname":"Hururu",
    "gn:country_code":"NP",
    "gn:dem":1692,
    "gn:feature_class":"P",
    "gn:feature_code":"PPLL",
    "gn:name":"Hururu",
    "gn:population":0,
    "gn:timezone":"Asia/Kathmandu",
    "iso:country":"NP",
    "wof:name":"Hururu",
    "wof:placetype":"locality"
},
  "geometry": {"coordinates":[87.25321,27.51124],"type":"Point"}
}