{
  "type": "Feature",
  "properties": {
    "gn:admin1_code":"FR",
    "gn:admin2_code":"14.0",
    "gn:admin3_code":"68.0",
    "gn:admin4_code":"680047.0",
    "gn:asciiname":"MallaBhatada",
    "gn:country_code":"NP",
    "gn:dem":1817,
    "gn:feature_class":"P",
    "gn:feature_code":"PPLL",
    "gn:name":"MallaBhatada",
    "gn:population":0,
    "gn:timezone":"Asia/Kathmandu",
    "iso:country":"NP",
    "wof:name":"MallaBhatada",
    "wof:placetype":"locality"
},
  "geometry": {"coordinates":[80.82483000000001,29.52358],"type":"Point"}
}