{
  "type": "Feature",
  "properties": {
    "gn:admin1_code":"WR",
    "gn:admin2_code":"4.0",
    "gn:admin3_code":"38.0",
    "gn:admin4_code":"380012.0",
    "gn:asciiname":"Saunepani",
    "gn:country_code":"NP",
    "gn:dem":512,
    "gn:feature_class":"P",
    "gn:feature_code":"PPLL",
    "gn:name":"Saunepani",
    "gn:population":0,
    "gn:timezone":"Asia/Kathmandu",
    "iso:country":"NP",
    "wof:name":"Saunepani",
    "wof:placetype":"locality"
},
  "geometry": {"coordinates":[84.1264,28.00468],"type":"Point"}
}