{
  "type": "Feature",
  "properties": {
    "gn:admin1_code":"WR",
    "gn:admin2_code":"3",
    "gn:admin3_code":"44",
    "gn:admin4_code":"440017",
    "gn:asciiname":"Chuwa",
    "gn:country_code":"NP",
    "gn:dem":972,
    "gn:feature_class":"P",
    "gn:feature_code":"PPLL",
    "gn:name":"Chuwa",
    "gn:population":0,
    "gn:timezone":"Asia/Kathmandu",
    "iso:country":"NP",
    "name:msa_x_preferred":[
        "Chuwa"
    ],
    "name:nep_x_preferred":[
        "\u091a\u0941\u0935\u093e"
    ],
    "name:new_x_preferred":[
        "\u091a\u0941\u0935\u093e"
    ],
    "name:pol_x_preferred":[
        "Chuwa"
    ],
    "wof:name":"Chuwa",
    "wof:placetype":"locality"
},
  "geometry": {"coordinates":[83.70464,28.23026],"type":"Point"}
}