{
  "type": "Feature",
  "properties": {
    "gn:admin1_code":"FR",
    "gn:admin2_code":"9",
    "gn:admin3_code":"75.0",
    "gn:admin4_code":"750009.0",
    "gn:asciiname":"Dhaukot",
    "gn:country_code":"NP",
    "gn:dem":800,
    "gn:feature_class":"P",
    "gn:feature_code":"PPLL",
    "gn:name":"Dhaukot",
    "gn:population":0,
    "gn:timezone":"Asia/Kathmandu",
    "iso:country":"NP",
    "wof:name":"Dhaukot",
    "wof:placetype":"locality"
},
  "geometry": {"coordinates":[80.45345,29.79711],"type":"Point"}
}