{
  "type": "Feature",
  "properties": {
    "gn:admin1_code":"CR",
    "gn:admin2_code":"1",
    "gn:admin3_code":"25",
    "gn:admin4_code":"250001",
    "gn:asciiname":"Tallo Asrang",
    "gn:country_code":"NP",
    "gn:dem":1028,
    "gn:feature_class":"P",
    "gn:feature_code":"PPLL",
    "gn:name":"Tallo Asrang",
    "gn:population":0,
    "gn:timezone":"Asia/Kathmandu",
    "iso:country":"NP",
    "wof:name":"Tallo Asrang",
    "wof:placetype":"locality"
},
  "geometry": {"coordinates":[85.32388,27.45529],"type":"Point"}
}