{
  "type": "Feature",
  "properties": {
    "gn:admin1_code":"FR",
    "gn:admin2_code":"9",
    "gn:admin3_code":"73.0",
    "gn:admin4_code":"730002.0",
    "gn:asciiname":"Sugmalya",
    "gn:country_code":"NP",
    "gn:dem":1354,
    "gn:feature_class":"P",
    "gn:feature_code":"PPLL",
    "gn:name":"Sugmalya",
    "gn:population":0,
    "gn:timezone":"Asia/Kathmandu",
    "iso:country":"NP",
    "wof:name":"Sugmalya",
    "wof:placetype":"locality"
},
  "geometry": {"coordinates":[80.54982,29.13028],"type":"Point"}
}