{
  "type": "Feature",
  "properties": {
    "gn:admin1_code":"WR",
    "gn:admin2_code":"3",
    "gn:admin3_code":"43",
    "gn:admin4_code":"430028",
    "gn:asciiname":"Asare",
    "gn:country_code":"NP",
    "gn:dem":2023,
    "gn:feature_class":"P",
    "gn:feature_code":"PPLL",
    "gn:name":"Asare",
    "gn:population":0,
    "gn:timezone":"Asia/Kathmandu",
    "iso:country":"NP",
    "wof:name":"Asare",
    "wof:placetype":"locality"
},
  "geometry": {"coordinates":[83.31395000000001,28.41532],"type":"Point"}
}