{
  "type": "Feature",
  "properties": {
    "gn:admin1_code":"ER",
    "gn:admin2_code":"7",
    "gn:admin3_code":"10.0",
    "gn:admin4_code":"100031.0",
    "gn:asciiname":"Devitar",
    "gn:country_code":"NP",
    "gn:dem":695,
    "gn:feature_class":"P",
    "gn:feature_code":"PPLL",
    "gn:name":"Devitar",
    "gn:population":0,
    "gn:timezone":"Asia/Kathmandu",
    "iso:country":"NP",
    "wof:name":"Devitar",
    "wof:placetype":"locality"
},
  "geometry": {"coordinates":[87.1511,27.3727],"type":"Point"}
}