{
  "type": "Feature",
  "properties": {
    "gn:admin1_code":"00",
    "gn:asciiname":"Jhoruntol",
    "gn:country_code":"NP",
    "gn:dem":2256,
    "gn:feature_class":"P",
    "gn:feature_code":"PPL",
    "gn:name":"Jhoru\u1e45\u1e6dol",
    "gn:population":0,
    "gn:timezone":"Asia/Kathmandu",
    "iso:country":"NP",
    "wof:name":"Jhoruntol",
    "wof:placetype":"locality"
},
  "geometry": {"coordinates":[86.15604999999999,27.79387],"type":"Point"}
}