{
  "type": "Feature",
  "properties": {
    "gn:admin1_code":"CR",
    "gn:admin2_code":"1",
    "gn:admin3_code":"24.0",
    "gn:admin4_code":"240071.0",
    "gn:asciiname":"Rabi",
    "gn:country_code":"NP",
    "gn:dem":1294,
    "gn:feature_class":"P",
    "gn:feature_code":"PPLL",
    "gn:name":"Rabi",
    "gn:population":0,
    "gn:timezone":"Asia/Kathmandu",
    "iso:country":"NP",
    "name:ceb_x_preferred":[
        "Rabi"
    ],
    "name:deu_x_preferred":[
        "Rabi"
    ],
    "name:heb_x_preferred":[
        "\u05e8\u05d1\u05d9"
    ],
    "name:jpn_x_preferred":[
        "\u30e9\u30d3"
    ],
    "name:lav_x_preferred":[
        "Rabi"
    ],
    "name:nld_x_preferred":[
        "Rabi"
    ],
    "name:rus_x_preferred":[
        "\u0420\u0430\u0431\u0438"
    ],
    "name:slv_x_preferred":[
        "Rabi"
    ],
    "name:swe_x_preferred":[
        "Rabi"
    ],
    "name:zho_x_preferred":[
        "\u62c9\u6bd4"
    ],
    "wof:name":"Rabi",
    "wof:placetype":"locality"
},
  "geometry": {"coordinates":[85.55833,27.64806],"type":"Point"}
}