{
  "type": "Feature",
  "properties": {
    "gn:admin1_code":"MR",
    "gn:admin2_code":"2",
    "gn:admin3_code":"60.0",
    "gn:admin4_code":"600029.0",
    "gn:asciiname":"Ghodadauna",
    "gn:country_code":"NP",
    "gn:dem":1721,
    "gn:feature_class":"P",
    "gn:feature_code":"PPLL",
    "gn:name":"Ghodadauna",
    "gn:population":0,
    "gn:timezone":"Asia/Kathmandu",
    "iso:country":"NP",
    "wof:name":"Ghodadauna",
    "wof:placetype":"locality"
},
  "geometry": {"coordinates":[81.75206,28.78019],"type":"Point"}
}