{
  "type": "Feature",
  "properties": {
    "gn:admin1_code":"CR",
    "gn:admin2_code":"11.0",
    "gn:admin3_code":"33.0",
    "gn:admin4_code":"330090.0",
    "gn:asciiname":"Tokari",
    "gn:country_code":"NP",
    "gn:dem":120,
    "gn:feature_class":"P",
    "gn:feature_code":"PPLL",
    "gn:name":"Tokari",
    "gn:population":0,
    "gn:timezone":"Asia/Kathmandu",
    "iso:country":"NP",
    "wof:name":"Tokari",
    "wof:placetype":"locality"
},
  "geometry": {"coordinates":[85.17419,27.08957],"type":"Point"}
}