{
  "type": "Feature",
  "properties": {
    "gn:admin1_code":"MR",
    "gn:admin2_code":"2",
    "gn:admin3_code":"60.0",
    "gn:admin4_code":"600032.0",
    "gn:asciiname":"Dhand",
    "gn:country_code":"NP",
    "gn:dem":977,
    "gn:feature_class":"P",
    "gn:feature_code":"PPLL",
    "gn:name":"Dhand",
    "gn:population":0,
    "gn:timezone":"Asia/Kathmandu",
    "iso:country":"NP",
    "wof:name":"Dhand",
    "wof:placetype":"locality"
},
  "geometry": {"coordinates":[81.65881999999998,28.92913],"type":"Point"}
}