{
  "type": "Feature",
  "properties": {
    "gn:admin1_code":"ER",
    "gn:admin2_code":"7",
    "gn:admin3_code":"5",
    "gn:admin4_code":"50035.0",
    "gn:asciiname":"Dumrighat",
    "gn:country_code":"NP",
    "gn:dem":118,
    "gn:feature_class":"P",
    "gn:feature_code":"PPLL",
    "gn:name":"Dumrighat",
    "gn:population":0,
    "gn:timezone":"Asia/Kathmandu",
    "iso:country":"NP",
    "wof:name":"Dumrighat",
    "wof:placetype":"locality"
},
  "geometry": {"coordinates":[87.49422,26.62023],"type":"Point"}
}