{
  "type": "Feature",
  "properties": {
    "gn:admin1_code":"MR",
    "gn:admin2_code":"12",
    "gn:admin3_code":"54",
    "gn:admin4_code":"540015",
    "gn:asciiname":"Challachhode",
    "gn:country_code":"NP",
    "gn:dem":2369,
    "gn:feature_class":"P",
    "gn:feature_code":"PPLL",
    "gn:name":"Challachhode",
    "gn:population":0,
    "gn:timezone":"Asia/Kathmandu",
    "iso:country":"NP",
    "wof:name":"Challachhode",
    "wof:placetype":"locality"
},
  "geometry": {"coordinates":[82.71899999999999,28.67786],"type":"Point"}
}