{
  "type": "Feature",
  "properties": {
    "gn:admin1_code":"MR",
    "gn:admin2_code":"12",
    "gn:admin3_code":"52",
    "gn:admin4_code":"520017",
    "gn:asciiname":"Mukhchaur",
    "gn:country_code":"NP",
    "gn:dem":784,
    "gn:feature_class":"P",
    "gn:feature_code":"PPLL",
    "gn:name":"Mukhchaur",
    "gn:population":0,
    "gn:timezone":"Asia/Kathmandu",
    "iso:country":"NP",
    "wof:name":"Mukhchaur",
    "wof:placetype":"locality"
},
  "geometry": {"coordinates":[82.69734,28.05703],"type":"Point"}
}