{
  "type": "Feature",
  "properties": {
    "gn:admin1_code":"00",
    "gn:asciiname":"Buntan",
    "gn:country_code":"NP",
    "gn:dem":1570,
    "gn:feature_class":"P",
    "gn:feature_code":"PPL",
    "gn:name":"Bu\u1e45t\u0101\u1e45",
    "gn:population":0,
    "gn:timezone":"Asia/Kathmandu",
    "iso:country":"NP",
    "wof:name":"Buntan",
    "wof:placetype":"locality"
},
  "geometry": {"coordinates":[85.10111999999999,27.99254],"type":"Point"}
}