{
  "type": "Feature",
  "properties": {
    "gn:admin1_code":"00",
    "gn:asciiname":"Toli",
    "gn:country_code":"NP",
    "gn:dem":869,
    "gn:feature_class":"P",
    "gn:feature_code":"PPL",
    "gn:name":"Toli",
    "gn:population":0,
    "gn:timezone":"Asia/Kathmandu",
    "iso:country":"NP",
    "name:nep_x_preferred":[
        "Toli\u0307\u0304"
    ],
    "wof:name":"Toli",
    "wof:placetype":"locality"
},
  "geometry": {"coordinates":[81.34222,28.92373],"type":"Point"}
}