{
  "type": "Feature",
  "properties": {
    "gn:admin1_code":"WR",
    "gn:admin2_code":"3",
    "gn:admin3_code":"45.0",
    "gn:admin4_code":"450049.0",
    "gn:asciiname":"Gharedi",
    "gn:country_code":"NP",
    "gn:dem":1292,
    "gn:feature_class":"P",
    "gn:feature_code":"PPLL",
    "gn:name":"Gharedi",
    "gn:population":0,
    "gn:timezone":"Asia/Kathmandu",
    "iso:country":"NP",
    "wof:name":"Gharedi",
    "wof:placetype":"locality"
},
  "geometry": {"coordinates":[83.33396,28.22442],"type":"Point"}
}