{
  "type": "Feature",
  "properties": {
    "gn:admin1_code":"ER",
    "gn:admin2_code":"10.0",
    "gn:admin3_code":"1.0",
    "gn:admin4_code":"10013.0",
    "gn:asciiname":"Hangboreng",
    "gn:country_code":"NP",
    "gn:dem":980,
    "gn:feature_class":"P",
    "gn:feature_code":"PPLL",
    "gn:name":"Hangboreng",
    "gn:population":0,
    "gn:timezone":"Asia/Kathmandu",
    "iso:country":"NP",
    "wof:name":"Hangboreng",
    "wof:placetype":"locality"
},
  "geometry": {"coordinates":[87.70725,27.45261],"type":"Point"}
}