{
  "type": "Feature",
  "properties": {
    "gn:admin1_code":"MR",
    "gn:admin2_code":"2",
    "gn:admin3_code":"60.0",
    "gn:admin4_code":"600034.0",
    "gn:asciiname":"Dharadanda",
    "gn:country_code":"NP",
    "gn:dem":1409,
    "gn:feature_class":"P",
    "gn:feature_code":"PPLL",
    "gn:name":"Dharadanda",
    "gn:population":0,
    "gn:timezone":"Asia/Kathmandu",
    "iso:country":"NP",
    "wof:name":"Dharadanda",
    "wof:placetype":"locality"
},
  "geometry": {"coordinates":[81.86424,28.79525],"type":"Point"}
}