{
  "type": "Feature",
  "properties": {
    "gn:admin1_code":"WR",
    "gn:admin2_code":"4.0",
    "gn:admin3_code":"38.0",
    "gn:admin4_code":"380023.0",
    "gn:asciiname":"Bhanu Memorial Park",
    "gn:country_code":"NP",
    "gn:dem":413,
    "gn:feature_class":"P",
    "gn:feature_code":"PPLL",
    "gn:name":"Bhanu Memorial Park",
    "gn:population":0,
    "gn:timezone":"Asia/Kathmandu",
    "iso:country":"NP",
    "wof:name":"Bhanu Memorial Park",
    "wof:placetype":"locality"
},
  "geometry": {"coordinates":[84.30834,27.98588],"type":"Point"}
}