{
  "type": "Feature",
  "properties": {
    "gn:admin1_code":"CR",
    "gn:admin2_code":"5",
    "gn:admin3_code":"20",
    "gn:admin4_code":"200040",
    "gn:asciiname":"Satbise",
    "gn:country_code":"NP",
    "gn:dem":714,
    "gn:feature_class":"P",
    "gn:feature_code":"PPLL",
    "gn:name":"Satbise",
    "gn:population":0,
    "gn:timezone":"Asia/Kathmandu",
    "iso:country":"NP",
    "wof:name":"Satbise",
    "wof:placetype":"locality"
},
  "geometry": {"coordinates":[85.91378,27.39103],"type":"Point"}
}