{
  "type": "Feature",
  "properties": {
    "gn:admin1_code":"CR",
    "gn:admin2_code":"1",
    "gn:admin3_code":"25",
    "gn:admin4_code":"250027",
    "gn:asciiname":"Patan Hospital",
    "gn:country_code":"NP",
    "gn:dem":1328,
    "gn:feature_class":"P",
    "gn:feature_code":"PPLL",
    "gn:name":"Patan Hospital",
    "gn:population":0,
    "gn:timezone":"Asia/Kathmandu",
    "iso:country":"NP",
    "name:dty_x_preferred":[
        "\u092a\u093e\u091f\u0928 \u0905\u0938\u094d\u092a\u0924\u093e\u0932"
    ],
    "name:nep_x_preferred":[
        "\u092a\u093e\u091f\u0928 \u0905\u0938\u094d\u092a\u0924\u093e\u0932"
    ],
    "wof:name":"Patan Hospital",
    "wof:placetype":"locality"
},
  "geometry": {"coordinates":[85.31961,27.6694],"type":"Point"}
}