{
  "type": "Feature",
  "properties": {
    "gn:admin1_code":"FR",
    "gn:admin2_code":"9",
    "gn:admin3_code":"74",
    "gn:admin4_code":"740057",
    "gn:asciiname":"Rajeijar",
    "gn:country_code":"NP",
    "gn:dem":1641,
    "gn:feature_class":"P",
    "gn:feature_code":"PPLL",
    "gn:name":"Rajeijar",
    "gn:population":0,
    "gn:timezone":"Asia/Kathmandu",
    "iso:country":"NP",
    "wof:name":"Rajeijar",
    "wof:placetype":"locality"
},
  "geometry": {"coordinates":[80.75029000000001,29.43118],"type":"Point"}
}