{
  "type": "Feature",
  "properties": {
    "gn:admin1_code":"CR",
    "gn:admin2_code":"5",
    "gn:admin3_code":"17.0",
    "gn:admin4_code":"170099.0",
    "gn:asciiname":"Tulsiyahi Jabdi",
    "gn:country_code":"NP",
    "gn:dem":65,
    "gn:feature_class":"P",
    "gn:feature_code":"PPLL",
    "gn:name":"Tulsiyahi Jabdi",
    "gn:population":0,
    "gn:timezone":"Asia/Kathmandu",
    "iso:country":"NP",
    "wof:name":"Tulsiyahi Jabdi",
    "wof:placetype":"locality"
},
  "geometry": {"coordinates":[85.85746999999998,26.61277],"type":"Point"}
}