{
  "type": "Feature",
  "properties": {
    "gn:admin1_code":"ER",
    "gn:admin2_code":"7",
    "gn:admin3_code":"10.0",
    "gn:admin4_code":"100017.0",
    "gn:asciiname":"Naulegaun",
    "gn:country_code":"NP",
    "gn:dem":1838,
    "gn:feature_class":"P",
    "gn:feature_code":"PPLL",
    "gn:name":"Naulegaun",
    "gn:population":0,
    "gn:timezone":"Asia/Kathmandu",
    "iso:country":"NP",
    "wof:name":"Naulegaun",
    "wof:placetype":"locality"
},
  "geometry": {"coordinates":[86.95529000000001,27.2198],"type":"Point"}
}