{
  "type": "Feature",
  "properties": {
    "gn:admin1_code":"FR",
    "gn:admin2_code":"9",
    "gn:admin3_code":"75.0",
    "gn:admin4_code":"750023.0",
    "gn:asciiname":"Shivchuli",
    "gn:country_code":"NP",
    "gn:dem":2901,
    "gn:feature_class":"P",
    "gn:feature_code":"PPLL",
    "gn:name":"Shivchuli",
    "gn:population":0,
    "gn:timezone":"Asia/Kathmandu",
    "iso:country":"NP",
    "wof:name":"Shivchuli",
    "wof:placetype":"locality"
},
  "geometry": {"coordinates":[80.96342,29.80616],"type":"Point"}
}