{
  "type": "Feature",
  "properties": {
    "gn:admin1_code":"ER",
    "gn:admin2_code":"13.0",
    "gn:admin3_code":"14.0",
    "gn:admin4_code":"140024.0",
    "gn:asciiname":"Aranga",
    "gn:country_code":"NP",
    "gn:dem":757,
    "gn:feature_class":"P",
    "gn:feature_code":"PPLL",
    "gn:name":"Aranga",
    "gn:population":0,
    "gn:timezone":"Asia/Kathmandu",
    "iso:country":"NP",
    "name:ara_x_preferred":[
        "\u0623\u0631\u0627\u0646\u063a\u0627"
    ],
    "name:ast_x_preferred":[
        "Aranga"
    ],
    "name:azb_x_preferred":[
        "\u0622\u0631\u0627\u0646\u062e\u0627"
    ],
    "name:bre_x_preferred":[
        "Aranga"
    ],
    "name:cat_x_preferred":[
        "Aranga"
    ],
    "name:ceb_x_preferred":[
        "Aranga"
    ],
    "name:deu_x_preferred":[
        "Aranga"
    ],
    "name:eus_x_preferred":[
        "Aranga"
    ],
    "name:fas_x_preferred":[
        "\u0622\u0631\u0627\u0646\u062e\u0627"
    ],
    "name:fra_x_preferred":[
        "Aranga"
    ],
    "name:glg_x_preferred":[
        "Aranga"
    ],
    "name:hun_x_preferred":[
        "Aranga"
    ],
    "name:ita_x_preferred":[
        "Aranga"
    ],
    "name:jpn_x_preferred":[
        "\u30a2\u30e9\u30f3\u30ac"
    ],
    "name:lmo_x_preferred":[
        "Aranga"
    ],
    "name:mkd_x_preferred":[
        "\u0410\u0440\u0430\u043d\u0433\u0430"
    ],
    "name:msa_x_preferred":[
        "Aranga"
    ],
    "name:nld_x_preferred":[
        "Aranga"
    ],
    "name:oci_x_preferred":[
        "Aranga"
    ],
    "name:pam_x_preferred":[
        "Aranga"
    ],
    "name:pol_x_preferred":[
        "Aranga"
    ],
    "name:por_x_preferred":[
        "Aranga"
    ],
    "name:rus_x_preferred":[
        "\u0410\u0440\u0430\u043d\u0433\u0430"
    ],
    "name:sco_x_preferred":[
        "Aranga"
    ],
    "name:spa_x_preferred":[
        "Aranga"
    ],
    "name:swe_x_preferred":[
        "Aranga"
    ],
    "name:tur_x_preferred":[
        "Aranga"
    ],
    "name:ukr_x_preferred":[
        "\u0410\u0440\u0430\u043d\u0433\u0430"
    ],
    "name:uzb_x_preferred":[
        "Aranga"
    ],
    "name:vie_x_preferred":[
        "Aranga"
    ],
    "name:war_x_preferred":[
        "Aranga"
    ],
    "name:zho_x_preferred":[
        "\u963f\u5170\u52a0"
    ],
    "wof:name":"Aranga",
    "wof:placetype":"locality"
},
  "geometry": {"coordinates":[87.11426,26.85989],"type":"Point"}
}