{
  "type": "Feature",
  "properties": {
    "gn:admin1_code":"MR",
    "gn:admin2_code":"12",
    "gn:admin3_code":"55",
    "gn:admin4_code":"550009",
    "gn:asciiname":"Dharkhani",
    "gn:country_code":"NP",
    "gn:dem":1344,
    "gn:feature_class":"P",
    "gn:feature_code":"PPLL",
    "gn:name":"Dharkhani",
    "gn:population":0,
    "gn:timezone":"Asia/Kathmandu",
    "iso:country":"NP",
    "wof:name":"Dharkhani",
    "wof:placetype":"locality"
},
  "geometry": {"coordinates":[82.19808,28.42919],"type":"Point"}
}