{
  "type": "Feature",
  "properties": {
    "gn:admin1_code":"ER",
    "gn:admin2_code":"10",
    "gn:admin3_code":"2",
    "gn:admin4_code":"20012",
    "gn:asciiname":"Laksmi",
    "gn:country_code":"NP",
    "gn:dem":2087,
    "gn:feature_class":"P",
    "gn:feature_code":"PPLL",
    "gn:name":"Laksmi",
    "gn:population":0,
    "gn:timezone":"Asia/Kathmandu",
    "iso:country":"NP",
    "wof:name":"Laksmi",
    "wof:placetype":"locality"
},
  "geometry": {"coordinates":[87.99639999999999,27.3223],"type":"Point"}
}