{
  "type": "Feature",
  "properties": {
    "gn:admin1_code":"CR",
    "gn:admin2_code":"5",
    "gn:admin3_code":"20",
    "gn:admin4_code":"200008",
    "gn:asciiname":"Surmanetar",
    "gn:country_code":"NP",
    "gn:dem":811,
    "gn:feature_class":"P",
    "gn:feature_code":"PPLL",
    "gn:name":"Surmanetar",
    "gn:population":0,
    "gn:timezone":"Asia/Kathmandu",
    "iso:country":"NP",
    "wof:name":"Surmanetar",
    "wof:placetype":"locality"
},
  "geometry": {"coordinates":[85.89986999999998,27.28462],"type":"Point"}
}