{
  "type": "Feature",
  "properties": {
    "gn:admin1_code":"CR",
    "gn:admin2_code":"1",
    "gn:admin3_code":"27.0",
    "gn:admin4_code":"270011.0",
    "gn:asciiname":"Simpani",
    "gn:country_code":"NP",
    "gn:dem":1323,
    "gn:feature_class":"P",
    "gn:feature_code":"PPLL",
    "gn:name":"Simpani",
    "gn:population":0,
    "gn:timezone":"Asia/Kathmandu",
    "iso:country":"NP",
    "wof:name":"Simpani",
    "wof:placetype":"locality"
},
  "geometry": {"coordinates":[85.27370000000001,27.5898],"type":"Point"}
}