{
  "type": "Feature",
  "properties": {
    "gn:admin1_code":"WR",
    "gn:admin2_code":"3",
    "gn:admin3_code":"43",
    "gn:admin4_code":"430024",
    "gn:asciiname":"Jeltung",
    "gn:country_code":"NP",
    "gn:dem":2046,
    "gn:feature_class":"P",
    "gn:feature_code":"PPLL",
    "gn:name":"Jeltung",
    "gn:population":0,
    "gn:timezone":"Asia/Kathmandu",
    "iso:country":"NP",
    "wof:name":"Jeltung",
    "wof:placetype":"locality"
},
  "geometry": {"coordinates":[83.38194,28.5677],"type":"Point"}
}