{
  "type": "Feature",
  "properties": {
    "gn:admin1_code":"MR",
    "gn:admin2_code":"12",
    "gn:admin3_code":"52",
    "gn:admin4_code":"520006",
    "gn:asciiname":"Timile",
    "gn:country_code":"NP",
    "gn:dem":1231,
    "gn:feature_class":"P",
    "gn:feature_code":"PPLL",
    "gn:name":"Timile",
    "gn:population":0,
    "gn:timezone":"Asia/Kathmandu",
    "iso:country":"NP",
    "wof:name":"Timile",
    "wof:placetype":"locality"
},
  "geometry": {"coordinates":[82.77468,28.15937000000001],"type":"Point"}
}