{
  "type": "Feature",
  "properties": {
    "gn:admin1_code":"MR",
    "gn:admin2_code":"2.0",
    "gn:admin3_code":"59.0",
    "gn:admin4_code":"590034.0",
    "gn:asciiname":"Gaun Natne",
    "gn:country_code":"NP",
    "gn:dem":1001,
    "gn:feature_class":"P",
    "gn:feature_code":"PPLL",
    "gn:name":"Gaun Natne",
    "gn:population":0,
    "gn:timezone":"Asia/Kathmandu",
    "iso:country":"NP",
    "wof:name":"Gaun Natne",
    "wof:placetype":"locality"
},
  "geometry": {"coordinates":[81.77134000000002,28.40887],"type":"Point"}
}