{
  "type": "Feature",
  "properties": {
    "gn:admin1_code":"ER",
    "gn:admin2_code":"7",
    "gn:admin3_code":"5",
    "gn:admin4_code":"50029.0",
    "gn:asciiname":"Bhaudha Biharitol",
    "gn:country_code":"NP",
    "gn:dem":80,
    "gn:feature_class":"P",
    "gn:feature_code":"PPLL",
    "gn:name":"Bhaudha Biharitol",
    "gn:population":0,
    "gn:timezone":"Asia/Kathmandu",
    "iso:country":"NP",
    "wof:name":"Bhaudha Biharitol",
    "wof:placetype":"locality"
},
  "geometry": {"coordinates":[87.33176,26.50746],"type":"Point"}
}