{
  "type": "Feature",
  "properties": {
    "gn:admin1_code":"ER",
    "gn:admin2_code":"7",
    "gn:admin3_code":"9",
    "gn:admin4_code":"90030",
    "gn:asciiname":"Magargaun",
    "gn:country_code":"NP",
    "gn:dem":854,
    "gn:feature_class":"P",
    "gn:feature_code":"PPLL",
    "gn:name":"Magargaun",
    "gn:population":0,
    "gn:timezone":"Asia/Kathmandu",
    "iso:country":"NP",
    "wof:name":"Magargaun",
    "wof:placetype":"locality"
},
  "geometry": {"coordinates":[87.15879,27.40962],"type":"Point"}
}