{
  "type": "Feature",
  "properties": {
    "gn:admin1_code":"FR",
    "gn:admin2_code":"9",
    "gn:admin3_code":"74",
    "gn:admin4_code":"740049",
    "gn:asciiname":"Seli",
    "gn:country_code":"NP",
    "gn:dem":1543,
    "gn:feature_class":"P",
    "gn:feature_code":"PPLL",
    "gn:name":"Seli",
    "gn:population":0,
    "gn:timezone":"Asia/Kathmandu",
    "iso:country":"NP",
    "wof:name":"Seli",
    "wof:placetype":"locality"
},
  "geometry": {"coordinates":[80.46592,29.46242],"type":"Point"}
}