{
  "type": "Feature",
  "properties": {
    "gn:admin1_code":"ER",
    "gn:admin2_code":"13",
    "gn:admin3_code":"12",
    "gn:admin4_code":"120046.0",
    "gn:asciiname":"Serna",
    "gn:country_code":"NP",
    "gn:dem":944,
    "gn:feature_class":"P",
    "gn:feature_code":"PPLL",
    "gn:name":"Serna",
    "gn:population":0,
    "gn:timezone":"Asia/Kathmandu",
    "iso:country":"NP",
    "name:bih_x_preferred":[
        "\u0938\u0947\u0930\u094d\u0928\u093e"
    ],
    "name:ceb_x_preferred":[
        "Serna"
    ],
    "name:fra_x_preferred":[
        "Serna"
    ],
    "name:hin_x_preferred":[
        "\u0938\u0947\u0930\u094d\u0928\u093e"
    ],
    "name:mai_x_preferred":[
        "\u0938\u0947\u0930\u094d\u0928\u093e"
    ],
    "name:msa_x_preferred":[
        "Serna"
    ],
    "name:nep_x_preferred":[
        "\u0938\u0947\u0930\u094d\u0928\u093e"
    ],
    "name:new_x_preferred":[
        "\u0938\u0947\u0930\u094d\u0928\u093e"
    ],
    "name:pol_x_preferred":[
        "Serna"
    ],
    "name:spa_x_preferred":[
        "Serna"
    ],
    "wof:name":"Serna",
    "wof:placetype":"locality"
},
  "geometry": {"coordinates":[86.62144000000001,27.31979],"type":"Point"}
}