{
  "type": "Feature",
  "properties": {
    "gn:admin1_code":"CR",
    "gn:admin2_code":"1",
    "gn:admin3_code":"23",
    "gn:admin4_code":"230064",
    "gn:asciiname":"Dhade",
    "gn:country_code":"NP",
    "gn:dem":1303,
    "gn:feature_class":"P",
    "gn:feature_code":"PPLL",
    "gn:name":"Dhade",
    "gn:population":0,
    "gn:timezone":"Asia/Kathmandu",
    "iso:country":"NP",
    "wof:name":"Dhade",
    "wof:placetype":"locality"
},
  "geometry": {"coordinates":[85.65729,27.82333],"type":"Point"}
}