{
  "type": "Feature",
  "properties": {
    "gn:admin1_code":"ER",
    "gn:admin2_code":"10",
    "gn:admin3_code":"3.0",
    "gn:admin4_code":"30015.0",
    "gn:asciiname":"Gewadanda",
    "gn:country_code":"NP",
    "gn:dem":586,
    "gn:feature_class":"P",
    "gn:feature_code":"PPLL",
    "gn:name":"Gewadanda",
    "gn:population":0,
    "gn:timezone":"Asia/Kathmandu",
    "iso:country":"NP",
    "wof:name":"Gewadanda",
    "wof:placetype":"locality"
},
  "geometry": {"coordinates":[87.91298,26.87493],"type":"Point"}
}