{
  "type": "Feature",
  "properties": {
    "gn:admin1_code":"WR",
    "gn:admin2_code":"4",
    "gn:admin3_code":"40.0",
    "gn:admin4_code":"400022.0",
    "gn:asciiname":"Kakare",
    "gn:country_code":"NP",
    "gn:dem":655,
    "gn:feature_class":"P",
    "gn:feature_code":"PPLL",
    "gn:name":"Kakare",
    "gn:population":0,
    "gn:timezone":"Asia/Kathmandu",
    "iso:country":"NP",
    "wof:name":"Kakare",
    "wof:placetype":"locality"
},
  "geometry": {"coordinates":[84.09188,28.14244],"type":"Point"}
}