{
  "type": "Feature",
  "properties": {
    "gn:admin1_code":"FR",
    "gn:admin2_code":"14.0",
    "gn:admin3_code":"67.0",
    "gn:admin4_code":"670002.0",
    "gn:asciiname":"Pipaldali",
    "gn:country_code":"NP",
    "gn:dem":1421,
    "gn:feature_class":"P",
    "gn:feature_code":"PPLL",
    "gn:name":"Pipaldali",
    "gn:population":0,
    "gn:timezone":"Asia/Kathmandu",
    "iso:country":"NP",
    "wof:name":"Pipaldali",
    "wof:placetype":"locality"
},
  "geometry": {"coordinates":[81.68243000000002,29.50673],"type":"Point"}
}