{
  "type": "Feature",
  "properties": {
    "gn:admin1_code":"CR",
    "gn:admin2_code":"1",
    "gn:admin3_code":"30.0",
    "gn:admin4_code":"300025.0",
    "gn:asciiname":"Mahadevkharka",
    "gn:country_code":"NP",
    "gn:dem":1665,
    "gn:feature_class":"P",
    "gn:feature_code":"PPLL",
    "gn:name":"Mahadevkharka",
    "gn:population":0,
    "gn:timezone":"Asia/Kathmandu",
    "iso:country":"NP",
    "wof:name":"Mahadevkharka",
    "wof:placetype":"locality"
},
  "geometry": {"coordinates":[84.97189,27.71947],"type":"Point"}
}