{
  "type": "Feature",
  "properties": {
    "gn:admin1_code":"MR",
    "gn:admin2_code":"2.0",
    "gn:admin3_code":"59.0",
    "gn:admin4_code":"590004.0",
    "gn:asciiname":"Dhanigaun",
    "gn:country_code":"NP",
    "gn:dem":956,
    "gn:feature_class":"P",
    "gn:feature_code":"PPLL",
    "gn:name":"Dhanigaun",
    "gn:population":0,
    "gn:timezone":"Asia/Kathmandu",
    "iso:country":"NP",
    "wof:name":"Dhanigaun",
    "wof:placetype":"locality"
},
  "geometry": {"coordinates":[81.98161,28.56381],"type":"Point"}
}