{
  "type": "Feature",
  "properties": {
    "gn:admin1_code":"MR",
    "gn:admin2_code":"12",
    "gn:admin3_code":"56.0",
    "gn:admin4_code":"560039.0",
    "gn:asciiname":"Tribhuwan Park",
    "gn:country_code":"NP",
    "gn:dem":690,
    "gn:feature_class":"P",
    "gn:feature_code":"PPLL",
    "gn:name":"Tribhuwan Park",
    "gn:population":0,
    "gn:timezone":"Asia/Kathmandu",
    "iso:country":"NP",
    "wof:name":"Tribhuwan Park",
    "wof:placetype":"locality"
},
  "geometry": {"coordinates":[82.4875,28.04742],"type":"Point"}
}