{
  "type": "Feature",
  "properties": {
    "gn:admin1_code":"CR",
    "gn:admin2_code":"1",
    "gn:admin3_code":"24.0",
    "gn:admin4_code":"240073.0",
    "gn:asciiname":"Maitar",
    "gn:country_code":"NP",
    "gn:dem":421,
    "gn:feature_class":"P",
    "gn:feature_code":"PPLL",
    "gn:name":"Maitar",
    "gn:population":0,
    "gn:timezone":"Asia/Kathmandu",
    "iso:country":"NP",
    "wof:name":"Maitar",
    "wof:placetype":"locality"
},
  "geometry": {"coordinates":[85.48026,27.39281],"type":"Point"}
}