{
  "type": "Feature",
  "properties": {
    "gn:admin1_code":"CR",
    "gn:admin2_code":"5",
    "gn:admin3_code":"21",
    "gn:admin4_code":"210003",
    "gn:asciiname":"Muje",
    "gn:country_code":"NP",
    "gn:dem":1508,
    "gn:feature_class":"P",
    "gn:feature_code":"PPLL",
    "gn:name":"Muje",
    "gn:population":0,
    "gn:timezone":"Asia/Kathmandu",
    "iso:country":"NP",
    "wof:name":"Muje",
    "wof:placetype":"locality"
},
  "geometry": {"coordinates":[85.83345,27.48602],"type":"Point"}
}