{
  "type": "Feature",
  "properties": {
    "gn:admin1_code":"CR",
    "gn:admin2_code":"1",
    "gn:admin3_code":"30.0",
    "gn:admin4_code":"300028.0",
    "gn:asciiname":"Chanetar",
    "gn:country_code":"NP",
    "gn:dem":997,
    "gn:feature_class":"P",
    "gn:feature_code":"PPLL",
    "gn:name":"Chanetar",
    "gn:population":0,
    "gn:timezone":"Asia/Kathmandu",
    "iso:country":"NP",
    "wof:name":"Chanetar",
    "wof:placetype":"locality"
},
  "geometry": {"coordinates":[84.78726999999998,27.7285],"type":"Point"}
}