{
  "type": "Feature",
  "properties": {
    "gn:admin1_code":"ER",
    "gn:admin2_code":"13.0",
    "gn:admin3_code":"14.0",
    "gn:admin4_code":"140027.0",
    "gn:asciiname":"Palase",
    "gn:country_code":"NP",
    "gn:dem":376,
    "gn:feature_class":"P",
    "gn:feature_code":"PPLL",
    "gn:name":"Palase",
    "gn:population":0,
    "gn:timezone":"Asia/Kathmandu",
    "iso:country":"NP",
    "name:sco_x_preferred":[
        "Palase"
    ],
    "wof:name":"Palase",
    "wof:placetype":"locality"
},
  "geometry": {"coordinates":[86.48279000000002,26.93431],"type":"Point"}
}