{
  "type": "Feature",
  "properties": {
    "gn:admin1_code":"ER",
    "gn:admin2_code":"10",
    "gn:admin3_code":"2",
    "gn:admin4_code":"20040",
    "gn:asciiname":"Sapnawa",
    "gn:country_code":"NP",
    "gn:dem":1445,
    "gn:feature_class":"P",
    "gn:feature_code":"PPLL",
    "gn:name":"Sapnawa",
    "gn:population":0,
    "gn:timezone":"Asia/Kathmandu",
    "iso:country":"NP",
    "wof:name":"Sapnawa",
    "wof:placetype":"locality"
},
  "geometry": {"coordinates":[87.82934,27.17542000000001],"type":"Point"}
}