{
  "type": "Feature",
  "properties": {
    "gn:admin1_code":"CR",
    "gn:admin2_code":"5",
    "gn:admin3_code":"20",
    "gn:admin4_code":"200023",
    "gn:asciiname":"Khalte",
    "gn:country_code":"NP",
    "gn:dem":720,
    "gn:feature_class":"P",
    "gn:feature_code":"PPLL",
    "gn:name":"Khalte",
    "gn:population":0,
    "gn:timezone":"Asia/Kathmandu",
    "iso:country":"NP",
    "name:msa_x_preferred":[
        "Khalte"
    ],
    "name:nep_x_preferred":[
        "\u0916\u093e\u0932\u094d\u091f\u0947"
    ],
    "name:new_x_preferred":[
        "\u0916\u0932\u094d\u0924\u0947"
    ],
    "name:pol_x_preferred":[
        "Khalte"
    ],
    "wof:name":"Khalte",
    "wof:placetype":"locality"
},
  "geometry": {"coordinates":[86.34815999999999,27.03285],"type":"Point"}
}