{
  "type": "Feature",
  "properties": {
    "gn:admin1_code":"WR",
    "gn:admin2_code":"8",
    "gn:admin3_code":"51.0",
    "gn:admin4_code":"510019.0",
    "gn:asciiname":"Karapu",
    "gn:country_code":"NP",
    "gn:dem":1128,
    "gn:feature_class":"P",
    "gn:feature_code":"PPLL",
    "gn:name":"Karapu",
    "gn:population":0,
    "gn:timezone":"Asia/Kathmandu",
    "iso:country":"NP",
    "wof:name":"Karapu",
    "wof:placetype":"locality"
},
  "geometry": {"coordinates":[83.02383,27.85869000000001],"type":"Point"}
}