{
  "type": "Feature",
  "properties": {
    "gn:admin1_code":"ER",
    "gn:admin2_code":"7",
    "gn:admin3_code":"9",
    "gn:admin4_code":"90013",
    "gn:asciiname":"Bhotebas",
    "gn:country_code":"NP",
    "gn:dem":1840,
    "gn:feature_class":"P",
    "gn:feature_code":"PPLL",
    "gn:name":"Bhotebas",
    "gn:population":0,
    "gn:timezone":"Asia/Kathmandu",
    "iso:country":"NP",
    "wof:name":"Bhotebas",
    "wof:placetype":"locality"
},
  "geometry": {"coordinates":[87.19965000000001,27.44667],"type":"Point"}
}