{
  "type": "Feature",
  "properties": {
    "gn:admin1_code":"WR",
    "gn:admin2_code":"8",
    "gn:admin3_code":"50.0",
    "gn:admin4_code":"500027.0",
    "gn:asciiname":"Manpur",
    "gn:country_code":"NP",
    "gn:dem":119,
    "gn:feature_class":"P",
    "gn:feature_code":"PPLL",
    "gn:name":"Manpur",
    "gn:population":0,
    "gn:timezone":"Asia/Kathmandu",
    "iso:country":"NP",
    "name:ceb_x_preferred":[
        "Manpur"
    ],
    "name:fra_x_preferred":[
        "Manpur"
    ],
    "name:pol_x_preferred":[
        "Manpur"
    ],
    "name:swe_x_preferred":[
        "Manpur"
    ],
    "wof:name":"Manpur",
    "wof:placetype":"locality"
},
  "geometry": {"coordinates":[82.7984,27.60569000000001],"type":"Point"}
}