{
  "type": "Feature",
  "properties": {
    "gn:admin1_code":"ER",
    "gn:admin2_code":"13",
    "gn:admin3_code":"13",
    "gn:admin4_code":"130074",
    "gn:asciiname":"Mukhitang",
    "gn:country_code":"NP",
    "gn:dem":1466,
    "gn:feature_class":"P",
    "gn:feature_code":"PPLL",
    "gn:name":"Mukhitang",
    "gn:population":0,
    "gn:timezone":"Asia/Kathmandu",
    "iso:country":"NP",
    "wof:name":"Mukhitang",
    "wof:placetype":"locality"
},
  "geometry": {"coordinates":[86.91351,27.07082],"type":"Point"}
}