{
  "type": "Feature",
  "properties": {
    "gn:admin1_code":"ER",
    "gn:admin2_code":"13",
    "gn:admin3_code":"16",
    "gn:admin4_code":"160014",
    "gn:asciiname":"Amahi",
    "gn:country_code":"NP",
    "gn:dem":127,
    "gn:feature_class":"P",
    "gn:feature_code":"PPLL",
    "gn:name":"Amahi",
    "gn:population":0,
    "gn:timezone":"Asia/Kathmandu",
    "iso:country":"NP",
    "wof:name":"Amahi",
    "wof:placetype":"locality"
},
  "geometry": {"coordinates":[86.49258,26.75655],"type":"Point"}
}