{
  "type": "Feature",
  "properties": {
    "gn:admin1_code":"MR",
    "gn:admin2_code":"12",
    "gn:admin3_code":"56.0",
    "gn:admin4_code":"560010.0",
    "gn:asciiname":"Pranaha",
    "gn:country_code":"NP",
    "gn:dem":249,
    "gn:feature_class":"P",
    "gn:feature_code":"PPLL",
    "gn:name":"Pranaha",
    "gn:population":0,
    "gn:timezone":"Asia/Kathmandu",
    "iso:country":"NP",
    "wof:name":"Pranaha",
    "wof:placetype":"locality"
},
  "geometry": {"coordinates":[82.55337,27.81514],"type":"Point"}
}