{
  "type": "Feature",
  "properties": {
    "gn:admin1_code":"MR",
    "gn:admin2_code":"6",
    "gn:admin3_code":"64.0",
    "gn:admin4_code":"640002.0",
    "gn:asciiname":"Chhapre",
    "gn:country_code":"NP",
    "gn:dem":2228,
    "gn:feature_class":"P",
    "gn:feature_code":"PPLL",
    "gn:name":"Chhapre",
    "gn:population":0,
    "gn:timezone":"Asia/Kathmandu",
    "iso:country":"NP",
    "name:mai_x_preferred":[
        "\u091b\u093e\u092a\u094d\u0930\u0947"
    ],
    "name:msa_x_preferred":[
        "Chhapre"
    ],
    "name:nep_x_preferred":[
        "\u091b\u093e\u092a\u094d\u0930\u0947"
    ],
    "name:pol_x_preferred":[
        "Chhapre"
    ],
    "wof:name":"Chhapre",
    "wof:placetype":"locality"
},
  "geometry": {"coordinates":[81.78319999999999,29.15858],"type":"Point"}
}