{
  "type": "Feature",
  "properties": {
    "gn:admin1_code":"WR",
    "gn:admin2_code":"8",
    "gn:admin3_code":"46.0",
    "gn:admin4_code":"460034.0",
    "gn:asciiname":"Litungaun",
    "gn:country_code":"NP",
    "gn:dem":1063,
    "gn:feature_class":"P",
    "gn:feature_code":"PPLL",
    "gn:name":"Litungaun",
    "gn:population":0,
    "gn:timezone":"Asia/Kathmandu",
    "iso:country":"NP",
    "wof:name":"Litungaun",
    "wof:placetype":"locality"
},
  "geometry": {"coordinates":[83.52882,28.07274],"type":"Point"}
}