{
  "type": "Feature",
  "properties": {
    "gn:admin1_code":"MR",
    "gn:admin2_code":"6",
    "gn:admin3_code":"66.0",
    "gn:admin4_code":"660014.0",
    "gn:asciiname":"Toli",
    "gn:country_code":"NP",
    "gn:dem":2401,
    "gn:feature_class":"P",
    "gn:feature_code":"PPLL",
    "gn:name":"Toli",
    "gn:population":0,
    "gn:timezone":"Asia/Kathmandu",
    "iso:country":"NP",
    "name:ceb_x_preferred":[
        "Toli"
    ],
    "name:deu_x_preferred":[
        "Toli"
    ],
    "name:fra_x_preferred":[
        "Toli"
    ],
    "name:swe_x_preferred":[
        "Toli"
    ],
    "wof:name":"Toli",
    "wof:placetype":"locality"
},
  "geometry": {"coordinates":[81.74524,29.6423],"type":"Point"}
}