{
  "type": "Feature",
  "properties": {
    "gn:admin1_code":"WR",
    "gn:admin2_code":"8",
    "gn:admin3_code":"47",
    "gn:admin4_code":"470049",
    "gn:asciiname":"Palung",
    "gn:country_code":"NP",
    "gn:dem":1291,
    "gn:feature_class":"P",
    "gn:feature_code":"PPLL",
    "gn:name":"Palung",
    "gn:population":0,
    "gn:timezone":"Asia/Kathmandu",
    "iso:country":"NP",
    "wof:name":"Palung",
    "wof:placetype":"locality"
},
  "geometry": {"coordinates":[83.40437,27.83699],"type":"Point"}
}