{
  "type": "Feature",
  "properties": {
    "gn:admin1_code":"WR",
    "gn:admin2_code":"3",
    "gn:admin3_code":"44",
    "gn:admin4_code":"440002",
    "gn:asciiname":"Kamere",
    "gn:country_code":"NP",
    "gn:dem":747,
    "gn:feature_class":"P",
    "gn:feature_code":"PPLL",
    "gn:name":"Kamere",
    "gn:population":0,
    "gn:timezone":"Asia/Kathmandu",
    "iso:country":"NP",
    "wof:name":"Kamere",
    "wof:placetype":"locality"
},
  "geometry": {"coordinates":[83.60975000000001,28.10952],"type":"Point"}
}