{
  "type": "Feature",
  "properties": {
    "gn:admin1_code":"CR",
    "gn:admin2_code":"1",
    "gn:admin3_code":"23",
    "gn:admin4_code":"230048",
    "gn:asciiname":"Chalisetol",
    "gn:country_code":"NP",
    "gn:dem":1150,
    "gn:feature_class":"P",
    "gn:feature_code":"PPLL",
    "gn:name":"Chalisetol",
    "gn:population":0,
    "gn:timezone":"Asia/Kathmandu",
    "iso:country":"NP",
    "wof:name":"Chalisetol",
    "wof:placetype":"locality"
},
  "geometry": {"coordinates":[85.56355000000001,27.82234],"type":"Point"}
}