{
  "type": "Feature",
  "properties": {
    "gn:admin1_code":"MR",
    "gn:admin2_code":"12",
    "gn:admin3_code":"56.0",
    "gn:admin4_code":"560033.0",
    "gn:asciiname":"Bhyudar",
    "gn:country_code":"NP",
    "gn:dem":913,
    "gn:feature_class":"P",
    "gn:feature_code":"PPLL",
    "gn:name":"Bhyudar",
    "gn:population":0,
    "gn:timezone":"Asia/Kathmandu",
    "iso:country":"NP",
    "wof:name":"Bhyudar",
    "wof:placetype":"locality"
},
  "geometry": {"coordinates":[82.2223,28.19304],"type":"Point"}
}