{
  "type": "Feature",
  "properties": {
    "gn:admin1_code":"CR",
    "gn:admin2_code":"1",
    "gn:admin3_code":"28",
    "gn:admin4_code":"280021",
    "gn:asciiname":"Kache",
    "gn:country_code":"NP",
    "gn:dem":2208,
    "gn:feature_class":"P",
    "gn:feature_code":"PPLL",
    "gn:name":"Kache",
    "gn:population":0,
    "gn:timezone":"Asia/Kathmandu",
    "iso:country":"NP",
    "wof:name":"Kache",
    "wof:placetype":"locality"
},
  "geometry": {"coordinates":[85.47593000000001,27.93111],"type":"Point"}
}