{
  "type": "Feature",
  "properties": {
    "gn:admin1_code":"CR",
    "gn:admin2_code":"11",
    "gn:admin3_code":"31",
    "gn:admin4_code":"310018",
    "gn:asciiname":"Bhiman",
    "gn:country_code":"NP",
    "gn:dem":705,
    "gn:feature_class":"P",
    "gn:feature_code":"PPLL",
    "gn:name":"Bhiman",
    "gn:population":0,
    "gn:timezone":"Asia/Kathmandu",
    "iso:country":"NP",
    "name:msa_x_preferred":[
        "Bhiman"
    ],
    "wof:name":"Bhiman",
    "wof:placetype":"locality"
},
  "geometry": {"coordinates":[84.9037,27.37822],"type":"Point"}
}