{
  "type": "Feature",
  "properties": {
    "gn:admin1_code":"MR",
    "gn:admin2_code":"2.0",
    "gn:admin3_code":"59.0",
    "gn:admin4_code":"590010.0",
    "gn:asciiname":"Hattisunde",
    "gn:country_code":"NP",
    "gn:dem":566,
    "gn:feature_class":"P",
    "gn:feature_code":"PPLL",
    "gn:name":"Hattisunde",
    "gn:population":0,
    "gn:timezone":"Asia/Kathmandu",
    "iso:country":"NP",
    "wof:name":"Hattisunde",
    "wof:placetype":"locality"
},
  "geometry": {"coordinates":[81.71455999999998,28.46043],"type":"Point"}
}