{
  "type": "Feature",
  "properties": {
    "gn:admin1_code":"00",
    "gn:asciiname":"Malbase",
    "gn:country_code":"NP",
    "gn:dem":1404,
    "gn:feature_class":"P",
    "gn:feature_code":"PPL",
    "gn:name":"M\u0101lb\u0101\u0303se",
    "gn:population":0,
    "gn:timezone":"Asia/Kathmandu",
    "iso:country":"NP",
    "name:nep_x_preferred":[
        "M\u0101lb\u0101\u0303se"
    ],
    "wof:name":"Malbase",
    "wof:placetype":"locality"
},
  "geometry": {"coordinates":[86.67149999999999,26.97457],"type":"Point"}
}