{
  "type": "Feature",
  "properties": {
    "gn:admin1_code":"CR",
    "gn:admin2_code":"1",
    "gn:admin3_code":"23",
    "gn:admin4_code":"230024",
    "gn:asciiname":"Sugeli",
    "gn:country_code":"NP",
    "gn:dem":1120,
    "gn:feature_class":"P",
    "gn:feature_code":"PPLL",
    "gn:name":"Sugeli",
    "gn:population":0,
    "gn:timezone":"Asia/Kathmandu",
    "iso:country":"NP",
    "wof:name":"Sugeli",
    "wof:placetype":"locality"
},
  "geometry": {"coordinates":[85.76785,27.90893],"type":"Point"}
}