{
  "type": "Feature",
  "properties": {
    "gn:admin1_code":"WR",
    "gn:admin2_code":"4",
    "gn:admin3_code":"37",
    "gn:admin4_code":"370034",
    "gn:asciiname":"Chindegaun",
    "gn:country_code":"NP",
    "gn:dem":805,
    "gn:feature_class":"P",
    "gn:feature_code":"PPLL",
    "gn:name":"Chindegaun",
    "gn:population":0,
    "gn:timezone":"Asia/Kathmandu",
    "iso:country":"NP",
    "wof:name":"Chindegaun",
    "wof:placetype":"locality"
},
  "geometry": {"coordinates":[84.3014,28.1244],"type":"Point"}
}