{
  "type": "Feature",
  "properties": {
    "gn:admin1_code":"ER",
    "gn:admin2_code":"13.0",
    "gn:admin3_code":"14.0",
    "gn:admin4_code":"140021.0",
    "gn:asciiname":"Kindu",
    "gn:country_code":"NP",
    "gn:dem":850,
    "gn:feature_class":"P",
    "gn:feature_code":"PPLL",
    "gn:name":"Kindu",
    "gn:population":0,
    "gn:timezone":"Asia/Kathmandu",
    "iso:country":"NP",
    "wof:name":"Kindu",
    "wof:placetype":"locality"
},
  "geometry": {"coordinates":[86.39005999999998,27.1687],"type":"Point"}
}