{
  "type": "Feature",
  "properties": {
    "gn:admin1_code":"CR",
    "gn:admin2_code":"1",
    "gn:admin3_code":"30.0",
    "gn:admin4_code":"300023.0",
    "gn:asciiname":"Chhapgaun",
    "gn:country_code":"NP",
    "gn:dem":638,
    "gn:feature_class":"P",
    "gn:feature_code":"PPLL",
    "gn:name":"Chhapgaun",
    "gn:population":0,
    "gn:timezone":"Asia/Kathmandu",
    "iso:country":"NP",
    "wof:name":"Chhapgaun",
    "wof:placetype":"locality"
},
  "geometry": {"coordinates":[84.9969,27.84732],"type":"Point"}
}