{
  "type": "Feature",
  "properties": {
    "gn:admin1_code":"MR",
    "gn:admin2_code":"2.0",
    "gn:admin3_code":"59.0",
    "gn:admin4_code":"590016.0",
    "gn:asciiname":"Bhitrikholagaun",
    "gn:country_code":"NP",
    "gn:dem":1536,
    "gn:feature_class":"P",
    "gn:feature_code":"PPLL",
    "gn:name":"Bhitrikholagaun",
    "gn:population":0,
    "gn:timezone":"Asia/Kathmandu",
    "iso:country":"NP",
    "wof:name":"Bhitrikholagaun",
    "wof:placetype":"locality"
},
  "geometry": {"coordinates":[81.75111,28.63089],"type":"Point"}
}