{
  "type": "Feature",
  "properties": {
    "gn:admin1_code":"00",
    "gn:asciiname":"Sirwani",
    "gn:country_code":"NP",
    "gn:dem":1477,
    "gn:feature_class":"P",
    "gn:feature_code":"PPL",
    "gn:name":"Sirw\u0101ni\u0307\u0304",
    "gn:population":0,
    "gn:timezone":"Asia/Kathmandu",
    "iso:country":"NP",
    "name:nep_x_preferred":[
        "Sirw\u0101ni\u0307\u0304"
    ],
    "wof:name":"Sirwani",
    "wof:placetype":"locality"
},
  "geometry": {"coordinates":[87.5205,26.90457],"type":"Point"}
}