{
  "type": "Feature",
  "properties": {
    "gn:admin1_code":"CR",
    "gn:admin2_code":"5",
    "gn:admin3_code":"21",
    "gn:admin4_code":"210021",
    "gn:asciiname":"Pekarnas",
    "gn:country_code":"NP",
    "gn:dem":1584,
    "gn:feature_class":"P",
    "gn:feature_code":"PPLL",
    "gn:name":"Pekarnas",
    "gn:population":0,
    "gn:timezone":"Asia/Kathmandu",
    "iso:country":"NP",
    "wof:name":"Pekarnas",
    "wof:placetype":"locality"
},
  "geometry": {"coordinates":[86.39269,27.5786],"type":"Point"}
}