{
  "type": "Feature",
  "properties": {
    "gn:admin1_code":"ER",
    "gn:admin2_code":"13",
    "gn:admin3_code":"11",
    "gn:admin4_code":"110034",
    "gn:asciiname":"Khalte",
    "gn:country_code":"NP",
    "gn:dem":2320,
    "gn:feature_class":"P",
    "gn:feature_code":"PPLL",
    "gn:name":"Khalte",
    "gn:population":0,
    "gn:timezone":"Asia/Kathmandu",
    "iso:country":"NP",
    "name:msa_x_preferred":[
        "Khalte"
    ],
    "name:nep_x_preferred":[
        "\u0916\u093e\u0932\u094d\u091f\u0947"
    ],
    "name:new_x_preferred":[
        "\u0916\u0932\u094d\u0924\u0947"
    ],
    "name:pol_x_preferred":[
        "Khalte"
    ],
    "wof:name":"Khalte",
    "wof:placetype":"locality"
},
  "geometry": {"coordinates":[86.57318000000002,27.43401],"type":"Point"}
}