{
  "type": "Feature",
  "properties": {
    "gn:admin1_code":"FR",
    "gn:admin2_code":"9",
    "gn:admin3_code":"74",
    "gn:admin4_code":"740024",
    "gn:asciiname":"Malbela",
    "gn:country_code":"NP",
    "gn:dem":1330,
    "gn:feature_class":"P",
    "gn:feature_code":"PPLL",
    "gn:name":"Malbela",
    "gn:population":0,
    "gn:timezone":"Asia/Kathmandu",
    "iso:country":"NP",
    "wof:name":"Malbela",
    "wof:placetype":"locality"
},
  "geometry": {"coordinates":[80.41766,29.53602],"type":"Point"}
}