{
  "type": "Feature",
  "properties": {
    "gn:admin1_code":"CR",
    "gn:admin2_code":"5",
    "gn:admin3_code":"20",
    "gn:admin4_code":"200026",
    "gn:asciiname":"Siltar",
    "gn:country_code":"NP",
    "gn:dem":502,
    "gn:feature_class":"P",
    "gn:feature_code":"PPLL",
    "gn:name":"Siltar",
    "gn:population":0,
    "gn:timezone":"Asia/Kathmandu",
    "iso:country":"NP",
    "wof:name":"Siltar",
    "wof:placetype":"locality"
},
  "geometry": {"coordinates":[85.71675,27.289],"type":"Point"}
}