{
  "type": "Feature",
  "properties": {
    "gn:admin1_code":"MR",
    "gn:admin2_code":"6",
    "gn:admin3_code":"64.0",
    "gn:admin4_code":"640005.0",
    "gn:asciiname":"Lode",
    "gn:country_code":"NP",
    "gn:dem":1441,
    "gn:feature_class":"P",
    "gn:feature_code":"PPLL",
    "gn:name":"Lode",
    "gn:population":0,
    "gn:timezone":"Asia/Kathmandu",
    "iso:country":"NP",
    "wof:name":"Lode",
    "wof:placetype":"locality"
},
  "geometry": {"coordinates":[81.78624000000001,29.32717],"type":"Point"}
}