{
  "type": "Feature",
  "properties": {
    "gn:admin1_code":"MR",
    "gn:admin2_code":"6",
    "gn:admin3_code":"64.0",
    "gn:admin4_code":"640005.0",
    "gn:asciiname":"Lode",
    "gn:country_code":"NP",
    "gn:dem":1441,
    "gn:feature_class":"P",
    "gn:feature_code":"PPLL",
    "gn:name":"Lode",
    "gn:population":0,
    "gn:timezone":"Asia/Kathmandu",
    "iso:country":"NP",
    "name:deu_x_preferred":[
        "Ganglagerst\u00e4tte"
    ],
    "name:swe_x_preferred":[
        "Malm\u00e5der"
    ],
    "name:ukr_x_preferred":[
        "\u0416\u0438\u043b\u044c\u043d\u0435 \u0440\u043e\u0434\u043e\u0432\u0438\u0449\u0435"
    ],
    "wof:name":"Lode",
    "wof:placetype":"locality"
},
  "geometry": {"coordinates":[81.78624000000001,29.32717],"type":"Point"}
}