{
  "type": "Feature",
  "properties": {
    "gn:admin1_code":"WR",
    "gn:admin2_code":"8",
    "gn:admin3_code":"47",
    "gn:admin4_code":"470059",
    "gn:asciiname":"Dhakre Bas",
    "gn:country_code":"NP",
    "gn:dem":964,
    "gn:feature_class":"P",
    "gn:feature_code":"PPLL",
    "gn:name":"Dhakre Bas",
    "gn:population":0,
    "gn:timezone":"Asia/Kathmandu",
    "iso:country":"NP",
    "wof:name":"Dhakre Bas",
    "wof:placetype":"locality"
},
  "geometry": {"coordinates":[83.83139,27.81975],"type":"Point"}
}