{
  "type": "Feature",
  "properties": {
    "gn:admin1_code":"MR",
    "gn:admin2_code":"12",
    "gn:admin3_code":"56.0",
    "gn:admin4_code":"560016.0",
    "gn:asciiname":"Saraiya",
    "gn:country_code":"NP",
    "gn:dem":574,
    "gn:feature_class":"P",
    "gn:feature_code":"PPLL",
    "gn:name":"Saraiya",
    "gn:population":0,
    "gn:timezone":"Asia/Kathmandu",
    "iso:country":"NP",
    "wof:name":"Saraiya",
    "wof:placetype":"locality"
},
  "geometry": {"coordinates":[82.22748,28.09723],"type":"Point"}
}