{
  "type": "Feature",
  "properties": {
    "gn:admin1_code":"CR",
    "gn:admin2_code":"5",
    "gn:admin3_code":"21",
    "gn:admin4_code":"210039",
    "gn:asciiname":"Pakarwas",
    "gn:country_code":"NP",
    "gn:dem":750,
    "gn:feature_class":"P",
    "gn:feature_code":"PPLL",
    "gn:name":"Pakarwas",
    "gn:population":0,
    "gn:timezone":"Asia/Kathmandu",
    "iso:country":"NP",
    "wof:name":"Pakarwas",
    "wof:placetype":"locality"
},
  "geometry": {"coordinates":[85.99793000000003,27.40558],"type":"Point"}
}