{
  "type": "Feature",
  "properties": {
    "gn:admin1_code":"FR",
    "gn:admin2_code":"14",
    "gn:admin3_code":"71.0",
    "gn:admin4_code":"710025.0",
    "gn:asciiname":"Pammagada",
    "gn:country_code":"NP",
    "gn:dem":430,
    "gn:feature_class":"P",
    "gn:feature_code":"PPLL",
    "gn:name":"Pammagada",
    "gn:population":0,
    "gn:timezone":"Asia/Kathmandu",
    "iso:country":"NP",
    "wof:name":"Pammagada",
    "wof:placetype":"locality"
},
  "geometry": {"coordinates":[80.92429,28.93843],"type":"Point"}
}