{
  "type": "Feature",
  "properties": {
    "gn:admin1_code":"FR",
    "gn:admin2_code":"14.0",
    "gn:admin3_code":"67.0",
    "gn:admin4_code":"670005.0",
    "gn:asciiname":"Kotigaun",
    "gn:country_code":"NP",
    "gn:dem":2113,
    "gn:feature_class":"P",
    "gn:feature_code":"PPLL",
    "gn:name":"Kotigaun",
    "gn:population":0,
    "gn:timezone":"Asia/Kathmandu",
    "iso:country":"NP",
    "wof:name":"Kotigaun",
    "wof:placetype":"locality"
},
  "geometry": {"coordinates":[81.67184,29.61928],"type":"Point"}
}