{
  "type": "Feature",
  "properties": {
    "gn:admin1_code":"FR",
    "gn:admin2_code":"14",
    "gn:admin3_code":"68",
    "gn:admin4_code":"680005",
    "gn:asciiname":"Danna",
    "gn:country_code":"NP",
    "gn:dem":1651,
    "gn:feature_class":"P",
    "gn:feature_code":"PPLL",
    "gn:name":"Danna",
    "gn:population":0,
    "gn:timezone":"Asia/Kathmandu",
    "iso:country":"NP",
    "name:ceb_x_preferred":[
        "Danna"
    ],
    "name:deu_x_preferred":[
        "Danna"
    ],
    "name:fra_x_preferred":[
        "Danna"
    ],
    "name:ita_x_preferred":[
        "Danna"
    ],
    "name:rus_x_preferred":[
        "\u0414\u0430\u043d\u043d\u0430"
    ],
    "name:swe_x_preferred":[
        "Danna"
    ],
    "wof:name":"Danna",
    "wof:placetype":"locality"
},
  "geometry": {"coordinates":[81.08162,29.52872],"type":"Point"}
}