{
  "type": "Feature",
  "properties": {
    "gn:admin1_code":"WR",
    "gn:admin2_code":"8",
    "gn:admin3_code":"47",
    "gn:admin4_code":"470015",
    "gn:asciiname":"Kumal Gaun",
    "gn:country_code":"NP",
    "gn:dem":1120,
    "gn:feature_class":"P",
    "gn:feature_code":"PPLL",
    "gn:name":"Kumal Gaun",
    "gn:population":0,
    "gn:timezone":"Asia/Kathmandu",
    "iso:country":"NP",
    "wof:name":"Kumal Gaun",
    "wof:placetype":"locality"
},
  "geometry": {"coordinates":[83.57184000000002,27.86732],"type":"Point"}
}