{
  "type": "Feature",
  "properties": {
    "gn:admin1_code":"WR",
    "gn:admin2_code":"4",
    "gn:admin3_code":"36.0",
    "gn:admin4_code":"360027.0",
    "gn:asciiname":"Dwarephat",
    "gn:country_code":"NP",
    "gn:dem":418,
    "gn:feature_class":"P",
    "gn:feature_code":"PPLL",
    "gn:name":"Dwarephat",
    "gn:population":0,
    "gn:timezone":"Asia/Kathmandu",
    "iso:country":"NP",
    "wof:name":"Dwarephat",
    "wof:placetype":"locality"
},
  "geometry": {"coordinates":[84.83005,27.78174000000001],"type":"Point"}
}