{
  "type": "Feature",
  "properties": {
    "gn:admin1_code":"FR",
    "gn:admin2_code":"14",
    "gn:admin3_code":"68",
    "gn:admin4_code":"680004",
    "gn:asciiname":"Thana",
    "gn:country_code":"NP",
    "gn:dem":1559,
    "gn:feature_class":"P",
    "gn:feature_code":"PPLL",
    "gn:name":"Thana",
    "gn:population":0,
    "gn:timezone":"Asia/Kathmandu",
    "iso:country":"NP",
    "name:ben_x_preferred":[
        "\u09a5\u09be\u09a8\u09be"
    ],
    "name:deu_x_preferred":[
        "Thana"
    ],
    "name:fra_x_preferred":[
        "Thana"
    ],
    "name:hun_x_preferred":[
        "Thana"
    ],
    "wof:name":"Thana",
    "wof:placetype":"locality"
},
  "geometry": {"coordinates":[81.2458,29.54768],"type":"Point"}
}