{
  "type": "Feature",
  "properties": {
    "gn:admin1_code":"CR",
    "gn:admin2_code":"5",
    "gn:admin3_code":"18",
    "gn:admin4_code":"180055",
    "gn:asciiname":"Pathaliya (Durgatol)",
    "gn:country_code":"NP",
    "gn:dem":138,
    "gn:feature_class":"P",
    "gn:feature_code":"PPLL",
    "gn:name":"Pathaliya (Durgatol)",
    "gn:population":0,
    "gn:timezone":"Asia/Kathmandu",
    "iso:country":"NP",
    "wof:name":"Pathaliya (Durgatol)",
    "wof:placetype":"locality"
},
  "geometry": {"coordinates":[85.8706,26.91265],"type":"Point"}
}