{
  "type": "Feature",
  "properties": {
    "gn:admin1_code":"FR",
    "gn:admin2_code":"9",
    "gn:admin3_code":"73.0",
    "gn:admin4_code":"730017.0",
    "gn:asciiname":"Guyalkhet",
    "gn:country_code":"NP",
    "gn:dem":764,
    "gn:feature_class":"P",
    "gn:feature_code":"PPLL",
    "gn:name":"Guyalkhet",
    "gn:population":0,
    "gn:timezone":"Asia/Kathmandu",
    "iso:country":"NP",
    "wof:name":"Guyalkhet",
    "wof:placetype":"locality"
},
  "geometry": {"coordinates":[80.70477,29.30978],"type":"Point"}
}