{
  "type": "Feature",
  "properties": {
    "gn:admin1_code":"CR",
    "gn:admin2_code":"1",
    "gn:admin3_code":"23",
    "gn:admin4_code":"230040",
    "gn:asciiname":"Khutume",
    "gn:country_code":"NP",
    "gn:dem":1230,
    "gn:feature_class":"P",
    "gn:feature_code":"PPLL",
    "gn:name":"Khutume",
    "gn:population":0,
    "gn:timezone":"Asia/Kathmandu",
    "iso:country":"NP",
    "wof:name":"Khutume",
    "wof:placetype":"locality"
},
  "geometry": {"coordinates":[85.66616999999999,27.77721],"type":"Point"}
}