{
  "type": "Feature",
  "properties": {
    "gn:admin1_code":"CR",
    "gn:admin2_code":"11.0",
    "gn:admin3_code":"33.0",
    "gn:admin4_code":"330074.0",
    "gn:asciiname":"Pheta",
    "gn:country_code":"NP",
    "gn:dem":90,
    "gn:feature_class":"P",
    "gn:feature_code":"PPLL",
    "gn:name":"Pheta",
    "gn:population":0,
    "gn:timezone":"Asia/Kathmandu",
    "iso:country":"NP",
    "wof:name":"Pheta",
    "wof:placetype":"locality"
},
  "geometry": {"coordinates":[84.94731,27.00256],"type":"Point"}
}