{
  "type": "Feature",
  "properties": {
    "gn:admin1_code":"ER",
    "gn:admin2_code":"7",
    "gn:admin3_code":"9",
    "gn:admin4_code":"90009",
    "gn:asciiname":"Kagguwa",
    "gn:country_code":"NP",
    "gn:dem":1801,
    "gn:feature_class":"P",
    "gn:feature_code":"PPLL",
    "gn:name":"Kagguwa",
    "gn:population":0,
    "gn:timezone":"Asia/Kathmandu",
    "iso:country":"NP",
    "wof:name":"Kagguwa",
    "wof:placetype":"locality"
},
  "geometry": {"coordinates":[87.20073000000002,27.45252],"type":"Point"}
}