{
  "type": "Feature",
  "properties": {
    "gn:admin1_code":"MR",
    "gn:admin2_code":"12",
    "gn:admin3_code":"55",
    "gn:admin4_code":"550035",
    "gn:asciiname":"Bhirkuna",
    "gn:country_code":"NP",
    "gn:dem":1701,
    "gn:feature_class":"P",
    "gn:feature_code":"PPLL",
    "gn:name":"Bhirkuna",
    "gn:population":0,
    "gn:timezone":"Asia/Kathmandu",
    "iso:country":"NP",
    "wof:name":"Bhirkuna",
    "wof:placetype":"locality"
},
  "geometry": {"coordinates":[82.02193,28.34535],"type":"Point"}
}