{
  "type": "Feature",
  "properties": {
    "gn:admin1_code":"MR",
    "gn:admin2_code":"6",
    "gn:admin3_code":"64.0",
    "gn:admin4_code":"640001.0",
    "gn:asciiname":"Badalkot",
    "gn:country_code":"NP",
    "gn:dem":1338,
    "gn:feature_class":"P",
    "gn:feature_code":"PPLL",
    "gn:name":"Badalkot",
    "gn:population":0,
    "gn:timezone":"Asia/Kathmandu",
    "iso:country":"NP",
    "name:ceb_x_preferred":[
        "Badalkot"
    ],
    "name:fra_x_preferred":[
        "Badalkot"
    ],
    "name:mai_x_preferred":[
        "\u092c\u0926\u093e\u0932\u0915\u094b\u091f"
    ],
    "name:msa_x_preferred":[
        "Badalkot"
    ],
    "name:nep_x_preferred":[
        "\u092c\u0926\u093e\u0932\u0915\u094b\u091f"
    ],
    "name:pol_x_preferred":[
        "Badalkot"
    ],
    "wof:name":"Badalkot",
    "wof:placetype":"locality"
},
  "geometry": {"coordinates":[81.6404,29.17958],"type":"Point"}
}