{
  "type": "Feature",
  "properties": {
    "gn:admin1_code":"ER",
    "gn:admin2_code":"13",
    "gn:admin3_code":"15",
    "gn:admin4_code":"150032",
    "gn:asciiname":"Dhangadhi",
    "gn:country_code":"NP",
    "gn:dem":100,
    "gn:feature_class":"P",
    "gn:feature_code":"PPLL",
    "gn:name":"Dhangadhi",
    "gn:population":0,
    "gn:timezone":"Asia/Kathmandu",
    "iso:country":"NP",
    "name:ara_x_preferred":[
        "\u062f\u0647\u0627\u0646\u063a\u0627\u062f\u064a"
    ],
    "name:bih_x_preferred":[
        "\u0927\u0928\u0917\u0922\u0940"
    ],
    "name:ceb_x_preferred":[
        "Dhangarhi"
    ],
    "name:deu_x_preferred":[
        "Dhangadhi"
    ],
    "name:dty_x_preferred":[
        "\u0927\u0928\u0917\u0922\u0940 \u0909\u092a\u092e\u0939\u093e\u0928\u0917\u0930\u092a\u093e\u0932\u093f\u0915\u093e"
    ],
    "name:fin_x_preferred":[
        "Dhangadhi"
    ],
    "name:fra_x_preferred":[
        "Dhangadhi"
    ],
    "name:heb_x_preferred":[
        "\u05d3\u05d4\u05d0\u05e0\u05d2\u05d3\u05d9"
    ],
    "name:ita_x_preferred":[
        "Dhangadhi"
    ],
    "name:lit_x_preferred":[
        "Dhangadhis"
    ],
    "name:nep_x_preferred":[
        "\u0927\u0928\u0917\u0922\u0940 \u0909\u092a\u092e\u0939\u093e\u0928\u0917\u0930\u092a\u093e\u0932\u093f\u0915\u093e"
    ],
    "name:new_x_preferred":[
        "\u0927\u0928\u0917\u0922\u0940 \u0928\u0917\u0930\u092a\u093e\u0932\u093f\u0915\u093e"
    ],
    "name:nld_x_preferred":[
        "Dhangadhi"
    ],
    "name:pol_x_preferred":[
        "Dhangadhi"
    ],
    "name:por_x_preferred":[
        "Dhangadhi"
    ],
    "name:rus_x_preferred":[
        "\u0414\u0445\u0430\u043d\u0433\u0430\u0434\u0445\u0438"
    ],
    "name:tam_x_preferred":[
        "\u0ba4\u0b99\u0bcd\u0b95\u0b9f\u0bbf"
    ],
    "name:urd_x_preferred":[
        "\u062f\u06be\u0646\u06af\u0627\u0691\u06c1\u06cc"
    ],
    "name:zho_x_preferred":[
        "\u4e39\u52a0\u5730"
    ],
    "wof:name":"Dhangadhi",
    "wof:placetype":"locality"
},
  "geometry": {"coordinates":[86.57613000000001,26.6039],"type":"Point"}
}