{
  "type": "Feature",
  "properties": {
    "gn:admin1_code":"WR",
    "gn:admin2_code":"3",
    "gn:admin3_code":"45.0",
    "gn:admin4_code":"450040.0",
    "gn:asciiname":"Bhitriban",
    "gn:country_code":"NP",
    "gn:dem":2078,
    "gn:feature_class":"P",
    "gn:feature_code":"PPLL",
    "gn:name":"Bhitriban",
    "gn:population":0,
    "gn:timezone":"Asia/Kathmandu",
    "iso:country":"NP",
    "wof:name":"Bhitriban",
    "wof:placetype":"locality"
},
  "geometry": {"coordinates":[83.2437,28.46824],"type":"Point"}
}