{
  "type": "Feature",
  "properties": {
    "gn:admin1_code":"WR",
    "gn:admin2_code":"8",
    "gn:admin3_code":"51.0",
    "gn:admin4_code":"510006.0",
    "gn:asciiname":"Kabhar Neta",
    "gn:country_code":"NP",
    "gn:dem":1936,
    "gn:feature_class":"P",
    "gn:feature_code":"PPLL",
    "gn:name":"Kabhar Neta",
    "gn:population":0,
    "gn:timezone":"Asia/Kathmandu",
    "iso:country":"NP",
    "wof:name":"Kabhar Neta",
    "wof:placetype":"locality"
},
  "geometry": {"coordinates":[83.1052,28.0603],"type":"Point"}
}