{
  "type": "Feature",
  "properties": {
    "gn:admin1_code":"MR",
    "gn:admin2_code":"2",
    "gn:admin3_code":"60.0",
    "gn:admin4_code":"600006.0",
    "gn:asciiname":"Toleni",
    "gn:country_code":"NP",
    "gn:dem":1103,
    "gn:feature_class":"P",
    "gn:feature_code":"PPLL",
    "gn:name":"Toleni",
    "gn:population":0,
    "gn:timezone":"Asia/Kathmandu",
    "iso:country":"NP",
    "name:ceb_x_preferred":[
        "Toleni"
    ],
    "name:fra_x_preferred":[
        "Toleni"
    ],
    "name:mai_x_preferred":[
        "\u0924\u094b\u0932\u0947\u0928\u0940"
    ],
    "name:msa_x_preferred":[
        "Toleni"
    ],
    "name:nep_x_preferred":[
        "\u0924\u094b\u0932\u0947\u0928\u0940"
    ],
    "name:new_x_preferred":[
        "\u0924\u094b\u0932\u0947\u0928\u0940"
    ],
    "name:pol_x_preferred":[
        "Toleni"
    ],
    "wof:name":"Toleni",
    "wof:placetype":"locality"
},
  "geometry": {"coordinates":[81.66965999999999,28.90233],"type":"Point"}
}