{
  "type": "Feature",
  "properties": {
    "gn:admin1_code":"CR",
    "gn:admin2_code":"1",
    "gn:admin3_code":"30.0",
    "gn:admin4_code":"300010.0",
    "gn:asciiname":"Gairi Purshu",
    "gn:country_code":"NP",
    "gn:dem":1143,
    "gn:feature_class":"P",
    "gn:feature_code":"PPLL",
    "gn:name":"Gairi Purshu",
    "gn:population":0,
    "gn:timezone":"Asia/Kathmandu",
    "iso:country":"NP",
    "wof:name":"Gairi Purshu",
    "wof:placetype":"locality"
},
  "geometry": {"coordinates":[84.83001,27.92416],"type":"Point"}
}