{
  "type": "Feature",
  "properties": {
    "gn:admin1_code":"WR",
    "gn:admin2_code":"4.0",
    "gn:admin3_code":"38.0",
    "gn:admin4_code":"380017.0",
    "gn:asciiname":"Amdandabesi",
    "gn:country_code":"NP",
    "gn:dem":293,
    "gn:feature_class":"P",
    "gn:feature_code":"PPLL",
    "gn:name":"Amdandabesi",
    "gn:population":0,
    "gn:timezone":"Asia/Kathmandu",
    "iso:country":"NP",
    "wof:name":"Amdandabesi",
    "wof:placetype":"locality"
},
  "geometry": {"coordinates":[84.46409,27.83102],"type":"Point"}
}