{
  "type": "Feature",
  "properties": {
    "gn:admin1_code":"WR",
    "gn:admin2_code":"3",
    "gn:admin3_code":"44",
    "gn:admin4_code":"440038.0",
    "gn:asciiname":"Nanlibang",
    "gn:country_code":"NP",
    "gn:dem":1219,
    "gn:feature_class":"P",
    "gn:feature_code":"PPLL",
    "gn:name":"Nanlibang",
    "gn:population":0,
    "gn:timezone":"Asia/Kathmandu",
    "iso:country":"NP",
    "wof:name":"Nanlibang",
    "wof:placetype":"locality"
},
  "geometry": {"coordinates":[83.62803000000002,28.27442000000001],"type":"Point"}
}