{
  "type": "Feature",
  "properties": {
    "gn:admin1_code":"FR",
    "gn:admin2_code":"9",
    "gn:admin3_code":"73.0",
    "gn:admin4_code":"730001.0",
    "gn:asciiname":"Bhalumare(Bhaktapur)",
    "gn:country_code":"NP",
    "gn:dem":2111,
    "gn:feature_class":"P",
    "gn:feature_code":"PPLL",
    "gn:name":"Bhalumare(Bhaktapur)",
    "gn:population":0,
    "gn:timezone":"Asia/Kathmandu",
    "iso:country":"NP",
    "wof:name":"Bhalumare(Bhaktapur)",
    "wof:placetype":"locality"
},
  "geometry": {"coordinates":[80.62049,29.38024],"type":"Point"}
}