{
  "type": "Feature",
  "properties": {
    "gn:admin1_code":"CR",
    "gn:admin2_code":"11",
    "gn:admin3_code":"31",
    "gn:admin4_code":"310015",
    "gn:asciiname":"Balchhi Bhanjyang",
    "gn:country_code":"NP",
    "gn:dem":1862,
    "gn:feature_class":"P",
    "gn:feature_code":"PPLL",
    "gn:name":"Balchhi Bhanjyang",
    "gn:population":0,
    "gn:timezone":"Asia/Kathmandu",
    "iso:country":"NP",
    "wof:name":"Balchhi Bhanjyang",
    "wof:placetype":"locality"
},
  "geometry": {"coordinates":[85.23563,27.57691],"type":"Point"}
}