{
  "type": "Feature",
  "properties": {
    "gn:admin1_code":"ER",
    "gn:admin2_code":"13",
    "gn:admin3_code":"15",
    "gn:admin4_code":"150096",
    "gn:asciiname":"Banauli",
    "gn:country_code":"NP",
    "gn:dem":95,
    "gn:feature_class":"P",
    "gn:feature_code":"PPLL",
    "gn:name":"Banauli",
    "gn:population":0,
    "gn:timezone":"Asia/Kathmandu",
    "iso:country":"NP",
    "name:bih_x_preferred":[
        "\u092c\u0928\u094c\u0932\u0940"
    ],
    "name:ceb_x_preferred":[
        "Banauli"
    ],
    "name:dty_x_preferred":[
        "\u092c\u0928\u094c\u0932\u0940 \u0917\u093e\u0935\u093f\u0938"
    ],
    "name:fra_x_preferred":[
        "Banauli"
    ],
    "name:hin_x_preferred":[
        "\u092c\u0928\u094c\u0932\u0940"
    ],
    "name:mai_x_preferred":[
        "\u092c\u0928\u094c\u0932\u0940"
    ],
    "name:msa_x_preferred":[
        "Banauli"
    ],
    "name:nep_x_preferred":[
        "\u092c\u0928\u094c\u0932\u0940"
    ],
    "name:new_x_preferred":[
        "\u092c\u0928\u094c\u0932\u0940"
    ],
    "name:pol_x_preferred":[
        "Banauli"
    ],
    "wof:name":"Banauli",
    "wof:placetype":"locality"
},
  "geometry": {"coordinates":[86.82108000000002,26.58318],"type":"Point"}
}