{
  "type": "Feature",
  "properties": {
    "gn:admin1_code":"WR",
    "gn:admin2_code":"4.0",
    "gn:admin3_code":"39.0",
    "gn:admin4_code":"390047.0",
    "gn:asciiname":"Krisnapur",
    "gn:country_code":"NP",
    "gn:dem":429,
    "gn:feature_class":"P",
    "gn:feature_code":"PPLL",
    "gn:name":"Krisnapur",
    "gn:population":0,
    "gn:timezone":"Asia/Kathmandu",
    "iso:country":"NP",
    "wof:name":"Krisnapur",
    "wof:placetype":"locality"
},
  "geometry": {"coordinates":[83.83145,27.89038],"type":"Point"}
}