{
  "type": "Feature",
  "properties": {
    "gn:admin1_code":"WR",
    "gn:admin2_code":"8",
    "gn:admin3_code":"50.0",
    "gn:admin4_code":"500024.0",
    "gn:asciiname":"Mungehari",
    "gn:country_code":"NP",
    "gn:dem":102,
    "gn:feature_class":"P",
    "gn:feature_code":"PPLL",
    "gn:name":"Mungehari",
    "gn:population":0,
    "gn:timezone":"Asia/Kathmandu",
    "iso:country":"NP",
    "wof:name":"Mungehari",
    "wof:placetype":"locality"
},
  "geometry": {"coordinates":[83.13791999999999,27.51198],"type":"Point"}
}