{
  "type": "Feature",
  "properties": {
    "gn:admin1_code":"ER",
    "gn:admin2_code":"7",
    "gn:admin3_code":"5",
    "gn:admin4_code":"50066",
    "gn:asciiname":"Dahar",
    "gn:country_code":"NP",
    "gn:dem":988,
    "gn:feature_class":"P",
    "gn:feature_code":"PPLL",
    "gn:name":"Dahar",
    "gn:population":0,
    "gn:timezone":"Asia/Kathmandu",
    "iso:country":"NP",
    "name:ceb_x_preferred":[
        "Dahar"
    ],
    "name:swe_x_preferred":[
        "Dahar"
    ],
    "wof:name":"Dahar",
    "wof:placetype":"locality"
},
  "geometry": {"coordinates":[87.35808,26.80343],"type":"Point"}
}