{
  "type": "Feature",
  "properties": {
    "gn:admin1_code":"ER",
    "gn:admin2_code":"10",
    "gn:admin3_code":"2",
    "gn:admin4_code":"20029",
    "gn:asciiname":"Lalikharka",
    "gn:country_code":"NP",
    "gn:dem":1784,
    "gn:feature_class":"P",
    "gn:feature_code":"PPLL",
    "gn:name":"Lalikharka",
    "gn:population":0,
    "gn:timezone":"Asia/Kathmandu",
    "iso:country":"NP",
    "name:msa_x_preferred":[
        "Lalikharka"
    ],
    "name:urd_x_preferred":[
        "\u0644\u0627\u0644\u06cc\u06a9\u06be\u0627\u0631\u06a9\u0627"
    ],
    "wof:name":"Lalikharka",
    "wof:placetype":"locality"
},
  "geometry": {"coordinates":[87.78331,27.1187],"type":"Point"}
}