{
  "type": "Feature",
  "properties": {
    "gn:admin1_code":"MR",
    "gn:admin2_code":"2.0",
    "gn:admin3_code":"59.0",
    "gn:admin4_code":"590030.0",
    "gn:asciiname":"Kakre Bihar",
    "gn:country_code":"NP",
    "gn:dem":646,
    "gn:feature_class":"P",
    "gn:feature_code":"PPLL",
    "gn:name":"Kakre Bihar",
    "gn:population":0,
    "gn:timezone":"Asia/Kathmandu",
    "iso:country":"NP",
    "wof:name":"Kakre Bihar",
    "wof:placetype":"locality"
},
  "geometry": {"coordinates":[81.62940999999999,28.56894],"type":"Point"}
}