{
  "type": "Feature",
  "properties": {
    "gn:admin1_code":"MR",
    "gn:admin2_code":"12",
    "gn:admin3_code":"53",
    "gn:admin4_code":"530037",
    "gn:asciiname":"Pokhara",
    "gn:country_code":"NP",
    "gn:dem":1667,
    "gn:feature_class":"P",
    "gn:feature_code":"PPLL",
    "gn:name":"Pokhara",
    "gn:population":0,
    "gn:timezone":"Asia/Kathmandu",
    "iso:country":"NP",
    "wof:name":"Pokhara",
    "wof:placetype":"locality"
},
  "geometry": {"coordinates":[82.83709,28.27475],"type":"Point"}
}