{
  "type": "Feature",
  "properties": {
    "gn:admin1_code":"CR",
    "gn:admin2_code":"1",
    "gn:admin3_code":"29",
    "gn:admin4_code":"290011",
    "gn:asciiname":"Yubra",
    "gn:country_code":"NP",
    "gn:dem":5646,
    "gn:feature_class":"P",
    "gn:feature_code":"PPLL",
    "gn:name":"Yubra",
    "gn:population":0,
    "gn:timezone":"Asia/Kathmandu",
    "iso:country":"NP",
    "wof:name":"Yubra",
    "wof:placetype":"locality"
},
  "geometry": {"coordinates":[85.57925,28.26995],"type":"Point"}
}