{
  "type": "Feature",
  "properties": {
    "gn:admin1_code":"ER",
    "gn:admin2_code":"7",
    "gn:admin3_code":"7.0",
    "gn:admin4_code":"70035.0",
    "gn:asciiname":"Okhre",
    "gn:country_code":"NP",
    "gn:dem":1196,
    "gn:feature_class":"P",
    "gn:feature_code":"PPLL",
    "gn:name":"Okhre",
    "gn:population":0,
    "gn:timezone":"Asia/Kathmandu",
    "iso:country":"NP",
    "name:ceb_x_preferred":[
        "Okhre"
    ],
    "name:mai_x_preferred":[
        "\u0913\u0916\u094d\u0930\u0947"
    ],
    "name:msa_x_preferred":[
        "Okhre"
    ],
    "name:nep_x_preferred":[
        "\u0913\u0916\u094d\u0930\u0947"
    ],
    "name:new_x_preferred":[
        "\u0913\u0916\u094d\u0930\u0947"
    ],
    "name:pol_x_preferred":[
        "Okhre"
    ],
    "wof:name":"Okhre",
    "wof:placetype":"locality"
},
  "geometry": {"coordinates":[87.4156,27.02296],"type":"Point"}
}