{
  "type": "Feature",
  "properties": {
    "gn:admin1_code":"CR",
    "gn:admin2_code":"5",
    "gn:admin3_code":"19",
    "gn:admin4_code":"190073",
    "gn:asciiname":"Nawalpur",
    "gn:country_code":"NP",
    "gn:dem":153,
    "gn:feature_class":"P",
    "gn:feature_code":"PPLL",
    "gn:name":"Nawalpur",
    "gn:population":0,
    "gn:timezone":"Asia/Kathmandu",
    "iso:country":"NP",
    "name:ceb_x_preferred":[
        "Nawalpur"
    ],
    "name:msa_x_preferred":[
        "Nawalpur"
    ],
    "name:nep_x_preferred":[
        "\u0928\u0935\u0932\u092a\u0941\u0930"
    ],
    "name:new_x_preferred":[
        "\u0928\u0935\u0932\u092a\u0941\u0930"
    ],
    "name:pol_x_preferred":[
        "Nawalpur"
    ],
    "wof:name":"Nawalpur",
    "wof:placetype":"locality"
},
  "geometry": {"coordinates":[85.60396999999998,27.07336],"type":"Point"}
}