{
  "type": "Feature",
  "properties": {
    "gn:admin1_code":"ER",
    "gn:admin2_code":"7",
    "gn:admin3_code":"10.0",
    "gn:admin4_code":"100019.0",
    "gn:asciiname":"Tarigaun",
    "gn:country_code":"NP",
    "gn:dem":834,
    "gn:feature_class":"P",
    "gn:feature_code":"PPLL",
    "gn:name":"Tarigaun",
    "gn:population":0,
    "gn:timezone":"Asia/Kathmandu",
    "iso:country":"NP",
    "name:ceb_x_preferred":[
        "Tarigaun"
    ],
    "name:mai_x_preferred":[
        "\u091f\u0930\u093f\u0917\u093e\u0901\u0909"
    ],
    "name:msa_x_preferred":[
        "Tarigaun"
    ],
    "name:nep_x_preferred":[
        "\u091f\u0930\u093f\u0917\u093e\u0901\u0909"
    ],
    "name:new_x_preferred":[
        "\u091f\u093e\u0930\u0940\u0917\u093e\u0909\u0902"
    ],
    "name:pol_x_preferred":[
        "Tarigaun"
    ],
    "wof:name":"Tarigaun",
    "wof:placetype":"locality"
},
  "geometry": {"coordinates":[87.17789999999999,27.29829],"type":"Point"}
}