{
  "type": "Feature",
  "properties": {
    "gn:admin1_code":"FR",
    "gn:admin2_code":"9",
    "gn:admin3_code":"74",
    "gn:admin4_code":"740047",
    "gn:asciiname":"Okhaldhunga",
    "gn:country_code":"NP",
    "gn:dem":1906,
    "gn:feature_class":"P",
    "gn:feature_code":"PPLL",
    "gn:name":"Okhaldhunga",
    "gn:population":0,
    "gn:timezone":"Asia/Kathmandu",
    "iso:country":"NP",
    "name:fra_x_preferred":[
        "Okhaldhunga"
    ],
    "name:hin_x_preferred":[
        "\u0913\u0916\u0932\u0922\u0941\u0902\u0917\u093e"
    ],
    "name:msa_x_preferred":[
        "Okhaldhunga"
    ],
    "name:nep_x_preferred":[
        "\u0913\u0916\u0932\u0922\u0941\u0919\u094d\u0917\u093e \u0917\u093e\u0935\u093f\u0938"
    ],
    "name:nld_x_preferred":[
        "Okhaldhunga"
    ],
    "name:pol_x_preferred":[
        "Okhaldhunga"
    ],
    "name:por_x_preferred":[
        "Okhaldhunga"
    ],
    "name:urd_x_preferred":[
        "\u0627\u0648\u06a9\u06be\u0627\u0644\u062f\u06be\u0648\u0646\u06af\u0627"
    ],
    "wof:name":"Okhaldhunga",
    "wof:placetype":"locality"
},
  "geometry": {"coordinates":[80.67900999999998,29.65662],"type":"Point"}
}