{
  "type": "Feature",
  "properties": {
    "gn:admin1_code":"00",
    "gn:asciiname":"Asaina",
    "gn:country_code":"NP",
    "gn:dem":194,
    "gn:feature_class":"P",
    "gn:feature_code":"PPL",
    "gn:name":"Asain\u0101",
    "gn:population":0,
    "gn:timezone":"Asia/Kathmandu",
    "iso:country":"NP",
    "name:nep_x_preferred":[
        "Asain\u0101"
    ],
    "wof:name":"Asaina",
    "wof:placetype":"locality"
},
  "geometry": {"coordinates":[80.33588,28.88857],"type":"Point"}
}