{
  "type": "Feature",
  "properties": {
    "gn:admin1_code":"WR",
    "gn:admin2_code":"3",
    "gn:admin3_code":"44",
    "gn:admin4_code":"440048",
    "gn:asciiname":"Cave",
    "gn:country_code":"NP",
    "gn:dem":936,
    "gn:feature_class":"P",
    "gn:feature_code":"PPLL",
    "gn:name":"Cave",
    "gn:population":0,
    "gn:timezone":"Asia/Kathmandu",
    "iso:country":"NP",
    "wof:name":"Cave",
    "wof:placetype":"locality"
},
  "geometry": {"coordinates":[83.67596,28.22983],"type":"Point"}
}