{
  "type": "Feature",
  "properties": {
    "gn:admin1_code":"WR",
    "gn:admin2_code":"4.0",
    "gn:admin3_code":"38.0",
    "gn:admin4_code":"380019.0",
    "gn:asciiname":"Koldanda",
    "gn:country_code":"NP",
    "gn:dem":708,
    "gn:feature_class":"P",
    "gn:feature_code":"PPLL",
    "gn:name":"Koldanda",
    "gn:population":0,
    "gn:timezone":"Asia/Kathmandu",
    "iso:country":"NP",
    "name:ceb_x_preferred":[
        "Koldada"
    ],
    "name:hin_x_preferred":[
        "\u0915\u094b\u0932\u0921\u093e\u0901\u0921\u093e"
    ],
    "name:msa_x_preferred":[
        "Koldada"
    ],
    "name:nep_x_preferred":[
        "\u0915\u094b\u0932\u0921\u093e\u0901\u0921\u093e"
    ],
    "name:new_x_preferred":[
        "\u0915\u094b\u0932\u094d\u0921\u093e\u0902\u0921\u093e"
    ],
    "name:pol_x_preferred":[
        "Koldada"
    ],
    "wof:name":"Koldanda",
    "wof:placetype":"locality"
},
  "geometry": {"coordinates":[84.05108,28.06192],"type":"Point"}
}