{
  "type": "Feature",
  "properties": {
    "gn:admin1_code":"ER",
    "gn:admin2_code":"10",
    "gn:admin3_code":"4.0",
    "gn:admin4_code":"40044.0",
    "gn:asciiname":"Sainikbasti",
    "gn:country_code":"NP",
    "gn:dem":122,
    "gn:feature_class":"P",
    "gn:feature_code":"PPLL",
    "gn:name":"Sainikbasti",
    "gn:population":0,
    "gn:timezone":"Asia/Kathmandu",
    "iso:country":"NP",
    "wof:name":"Sainikbasti",
    "wof:placetype":"locality"
},
  "geometry": {"coordinates":[87.86031,26.65038],"type":"Point"}
}