{
  "type": "Feature",
  "properties": {
    "gn:admin1_code":"CR",
    "gn:admin2_code":"11",
    "gn:admin3_code":"34",
    "gn:admin4_code":"340078",
    "gn:asciiname":"Supauli",
    "gn:country_code":"NP",
    "gn:dem":107,
    "gn:feature_class":"P",
    "gn:feature_code":"PPLL",
    "gn:name":"Supauli",
    "gn:population":0,
    "gn:timezone":"Asia/Kathmandu",
    "iso:country":"NP",
    "name:fra_x_preferred":[
        "Supauli"
    ],
    "name:mai_x_preferred":[
        "\u0938\u0941\u092a\u094c\u0932\u0940"
    ],
    "name:nep_x_preferred":[
        "\u0938\u0941\u092a\u094c\u0932\u0940"
    ],
    "name:pol_x_preferred":[
        "Supauli"
    ],
    "wof:name":"Supauli",
    "wof:placetype":"locality"
},
  "geometry": {"coordinates":[84.73925,27.1671],"type":"Point"}
}