{
  "type": "Feature",
  "properties": {
    "gn:admin1_code":"FR",
    "gn:admin2_code":"14.0",
    "gn:admin3_code":"67.0",
    "gn:admin4_code":"670026.0",
    "gn:asciiname":"Supana",
    "gn:country_code":"NP",
    "gn:dem":1502,
    "gn:feature_class":"P",
    "gn:feature_code":"PPLL",
    "gn:name":"Supana",
    "gn:population":0,
    "gn:timezone":"Asia/Kathmandu",
    "iso:country":"NP",
    "wof:name":"Supana",
    "wof:placetype":"locality"
},
  "geometry": {"coordinates":[81.73621999999997,29.37283],"type":"Point"}
}