{
  "type": "Feature",
  "properties": {
    "gn:admin1_code":"CR",
    "gn:admin2_code":"5",
    "gn:admin3_code":"21",
    "gn:admin4_code":"210012",
    "gn:asciiname":"Dadhuwa",
    "gn:country_code":"NP",
    "gn:dem":2325,
    "gn:feature_class":"P",
    "gn:feature_code":"PPLL",
    "gn:name":"Dadhuwa",
    "gn:population":0,
    "gn:timezone":"Asia/Kathmandu",
    "iso:country":"NP",
    "wof:name":"Dadhuwa",
    "wof:placetype":"locality"
},
  "geometry": {"coordinates":[85.96095,27.53692],"type":"Point"}
}