{
  "type": "Feature",
  "properties": {
    "gn:admin1_code":"WR",
    "gn:admin2_code":"8",
    "gn:admin3_code":"48",
    "gn:admin4_code":"480013",
    "gn:asciiname":"Singetari",
    "gn:country_code":"NP",
    "gn:dem":321,
    "gn:feature_class":"P",
    "gn:feature_code":"PPLL",
    "gn:name":"Singetari",
    "gn:population":0,
    "gn:timezone":"Asia/Kathmandu",
    "iso:country":"NP",
    "wof:name":"Singetari",
    "wof:placetype":"locality"
},
  "geometry": {"coordinates":[84.07352,27.86111],"type":"Point"}
}