{
  "type": "Feature",
  "properties": {
    "gn:admin1_code":"ER",
    "gn:admin2_code":"10",
    "gn:admin3_code":"2",
    "gn:admin4_code":"20008.0",
    "gn:asciiname":"Perunge",
    "gn:country_code":"NP",
    "gn:dem":1661,
    "gn:feature_class":"P",
    "gn:feature_code":"PPLL",
    "gn:name":"Perunge",
    "gn:population":0,
    "gn:timezone":"Asia/Kathmandu",
    "iso:country":"NP",
    "wof:name":"Perunge",
    "wof:placetype":"locality"
},
  "geometry": {"coordinates":[87.96033,27.25364],"type":"Point"}
}