{
  "type": "Feature",
  "properties": {
    "gn:admin1_code":"MR",
    "gn:admin2_code":"12",
    "gn:admin3_code":"54",
    "gn:admin4_code":"540017",
    "gn:asciiname":"Serabang",
    "gn:country_code":"NP",
    "gn:dem":1849,
    "gn:feature_class":"P",
    "gn:feature_code":"PPLL",
    "gn:name":"Serabang",
    "gn:population":0,
    "gn:timezone":"Asia/Kathmandu",
    "iso:country":"NP",
    "wof:name":"Serabang",
    "wof:placetype":"locality"
},
  "geometry": {"coordinates":[82.66346999999998,28.60628],"type":"Point"}
}