{
  "type": "Feature",
  "properties": {
    "gn:admin1_code":"FR",
    "gn:admin2_code":"9",
    "gn:admin3_code":"74",
    "gn:admin4_code":"740013",
    "gn:asciiname":"Chaudthala",
    "gn:country_code":"NP",
    "gn:dem":1599,
    "gn:feature_class":"P",
    "gn:feature_code":"PPLL",
    "gn:name":"Chaudthala",
    "gn:population":0,
    "gn:timezone":"Asia/Kathmandu",
    "iso:country":"NP",
    "wof:name":"Chaudthala",
    "wof:placetype":"locality"
},
  "geometry": {"coordinates":[80.60243,29.59183],"type":"Point"}
}