{
  "type": "Feature",
  "properties": {
    "gn:admin1_code":"CR",
    "gn:admin2_code":"11",
    "gn:admin3_code":"35.0",
    "gn:admin4_code":"350033.0",
    "gn:asciiname":"Ratnanagar",
    "gn:country_code":"NP",
    "gn:dem":196,
    "gn:feature_class":"P",
    "gn:feature_code":"PPLL",
    "gn:name":"Ratnanagar",
    "gn:population":0,
    "gn:timezone":"Asia/Kathmandu",
    "iso:country":"NP",
    "name:deu_x_preferred":[
        "Ratnanagar"
    ],
    "name:msa_x_preferred":[
        "Ratnanagar"
    ],
    "name:nep_x_preferred":[
        "\u0930\u0924\u094d\u0928\u0928\u0917\u0930 \u0928\u0917\u0930\u092a\u093e\u0932\u093f\u0915\u093e"
    ],
    "name:new_x_preferred":[
        "\u0930\u0924\u094d\u0928\u0928\u0917\u0930 \u0928\u0917\u0930\u092a\u093e\u0932\u093f\u0915\u093e"
    ],
    "name:pol_x_preferred":[
        "Ratnanagar"
    ],
    "name:urd_x_preferred":[
        "\u0631\u062a\u0646 \u0646\u06af\u0631"
    ],
    "name:zho_x_preferred":[
        "\u62c9\u7279\u7d0d\u7d0d\u52a0\u723e"
    ],
    "wof:name":"Ratnanagar",
    "wof:placetype":"locality"
},
  "geometry": {"coordinates":[84.52011,27.61937],"type":"Point"}
}