{
  "type": "Feature",
  "properties": {
    "gn:admin1_code":"CR",
    "gn:admin2_code":"11",
    "gn:admin3_code":"31",
    "gn:admin4_code":"310002",
    "gn:asciiname":"Bharyangdanda",
    "gn:country_code":"NP",
    "gn:dem":1019,
    "gn:feature_class":"P",
    "gn:feature_code":"PPLL",
    "gn:name":"Bharyangdanda",
    "gn:population":0,
    "gn:timezone":"Asia/Kathmandu",
    "iso:country":"NP",
    "wof:name":"Bharyangdanda",
    "wof:placetype":"locality"
},
  "geometry": {"coordinates":[85.11884999999999,27.43912000000001],"type":"Point"}
}