{
  "type": "Feature",
  "properties": {
    "gn:admin1_code":"CR",
    "gn:admin2_code":"5",
    "gn:admin3_code":"19",
    "gn:admin4_code":"190050",
    "gn:asciiname":"Durgatol",
    "gn:country_code":"NP",
    "gn:dem":130,
    "gn:feature_class":"P",
    "gn:feature_code":"PPLL",
    "gn:name":"Durgatol",
    "gn:population":0,
    "gn:timezone":"Asia/Kathmandu",
    "iso:country":"NP",
    "wof:name":"Durgatol",
    "wof:placetype":"locality"
},
  "geometry": {"coordinates":[85.48674,27.11811],"type":"Point"}
}