{
  "type": "Feature",
  "properties": {
    "gn:admin1_code":"ER",
    "gn:admin2_code":"10.0",
    "gn:admin3_code":"1.0",
    "gn:admin4_code":"10032.0",
    "gn:asciiname":"Melung",
    "gn:country_code":"NP",
    "gn:dem":1218,
    "gn:feature_class":"P",
    "gn:feature_code":"PPLL",
    "gn:name":"Melung",
    "gn:population":0,
    "gn:timezone":"Asia/Kathmandu",
    "iso:country":"NP",
    "name:ceb_x_preferred":[
        "Melung"
    ],
    "name:msa_x_preferred":[
        "Melung"
    ],
    "name:new_x_preferred":[
        "\u092e\u0947\u0932\u0941\u0919\u094d\u0917"
    ],
    "name:pol_x_preferred":[
        "Melung"
    ],
    "wof:name":"Melung",
    "wof:placetype":"locality"
},
  "geometry": {"coordinates":[87.65616,27.37017],"type":"Point"}
}