{
  "type": "Feature",
  "properties": {
    "gn:admin1_code":"00",
    "gn:asciiname":"Paltage",
    "gn:country_code":"NP",
    "gn:dem":1564,
    "gn:feature_class":"P",
    "gn:feature_code":"PPL",
    "gn:name":"P\u0101l\u1e6d\u0101\u0303ge",
    "gn:population":0,
    "gn:timezone":"Asia/Kathmandu",
    "iso:country":"NP",
    "name:nep_x_preferred":[
        "P\u0101l\u1e6d\u0101\u0303ge"
    ],
    "wof:name":"Paltage",
    "wof:placetype":"locality"
},
  "geometry": {"coordinates":[88.08054,26.87963],"type":"Point"}
}