{
  "type": "Feature",
  "properties": {
    "gn:admin1_code":"WR",
    "gn:admin2_code":"4.0",
    "gn:admin3_code":"39.0",
    "gn:admin4_code":"390033.0",
    "gn:asciiname":"Malungakot",
    "gn:country_code":"NP",
    "gn:dem":899,
    "gn:feature_class":"P",
    "gn:feature_code":"PPLL",
    "gn:name":"Malungakot",
    "gn:population":0,
    "gn:timezone":"Asia/Kathmandu",
    "iso:country":"NP",
    "wof:name":"Malungakot",
    "wof:placetype":"locality"
},
  "geometry": {"coordinates":[83.64671,27.91421],"type":"Point"}
}