{
  "type": "Feature",
  "properties": {
    "gn:admin1_code":"ER",
    "gn:admin2_code":"13",
    "gn:admin3_code":"11",
    "gn:admin4_code":"110030",
    "gn:asciiname":"Dund",
    "gn:country_code":"NP",
    "gn:dem":1990,
    "gn:feature_class":"P",
    "gn:feature_code":"PPLL",
    "gn:name":"Dund",
    "gn:population":0,
    "gn:timezone":"Asia/Kathmandu",
    "iso:country":"NP",
    "wof:name":"Dund",
    "wof:placetype":"locality"
},
  "geometry": {"coordinates":[86.58443,27.38121],"type":"Point"}
}