{
  "type": "Feature",
  "properties": {
    "gn:admin1_code":"CR",
    "gn:admin2_code":"1",
    "gn:admin3_code":"28",
    "gn:admin4_code":"280042",
    "gn:asciiname":"Lasuntol",
    "gn:country_code":"NP",
    "gn:dem":1549,
    "gn:feature_class":"P",
    "gn:feature_code":"PPLL",
    "gn:name":"Lasuntol",
    "gn:population":0,
    "gn:timezone":"Asia/Kathmandu",
    "iso:country":"NP",
    "wof:name":"Lasuntol",
    "wof:placetype":"locality"
},
  "geometry": {"coordinates":[85.26831,27.80206],"type":"Point"}
}