{
  "type": "Feature",
  "properties": {
    "gn:admin1_code":"WR",
    "gn:admin2_code":"8",
    "gn:admin3_code":"46.0",
    "gn:admin4_code":"460028.0",
    "gn:asciiname":"Nayagaun Maidan",
    "gn:country_code":"NP",
    "gn:dem":1478,
    "gn:feature_class":"P",
    "gn:feature_code":"PPLL",
    "gn:name":"Nayagaun Maidan",
    "gn:population":0,
    "gn:timezone":"Asia/Kathmandu",
    "iso:country":"NP",
    "wof:name":"Nayagaun Maidan",
    "wof:placetype":"locality"
},
  "geometry": {"coordinates":[83.16257,28.07615],"type":"Point"}
}