{
  "type": "Feature",
  "properties": {
    "gn:admin1_code":"WR",
    "gn:admin2_code":"8",
    "gn:admin3_code":"46.0",
    "gn:admin4_code":"460022.0",
    "gn:asciiname":"Bel pokhara",
    "gn:country_code":"NP",
    "gn:dem":915,
    "gn:feature_class":"P",
    "gn:feature_code":"PPLL",
    "gn:name":"Bel pokhara",
    "gn:population":0,
    "gn:timezone":"Asia/Kathmandu",
    "iso:country":"NP",
    "wof:name":"Bel pokhara",
    "wof:placetype":"locality"
},
  "geometry": {"coordinates":[83.27332,27.98583],"type":"Point"}
}