{
  "type": "Feature",
  "properties": {
    "gn:admin1_code":"CR",
    "gn:admin2_code":"1",
    "gn:admin3_code":"28",
    "gn:admin4_code":"280033",
    "gn:asciiname":"Ramche",
    "gn:country_code":"NP",
    "gn:dem":603,
    "gn:feature_class":"P",
    "gn:feature_code":"PPLL",
    "gn:name":"Ramche",
    "gn:population":0,
    "gn:timezone":"Asia/Kathmandu",
    "iso:country":"NP",
    "wof:name":"Ramche",
    "wof:placetype":"locality"
},
  "geometry": {"coordinates":[85.19086999999998,27.9106],"type":"Point"}
}