{
  "type": "Feature",
  "properties": {
    "gn:admin1_code":"ER",
    "gn:admin2_code":"13.0",
    "gn:admin3_code":"14.0",
    "gn:admin4_code":"140023.0",
    "gn:asciiname":"Sirwani",
    "gn:country_code":"NP",
    "gn:dem":645,
    "gn:feature_class":"P",
    "gn:feature_code":"PPLL",
    "gn:name":"Sirwani",
    "gn:population":0,
    "gn:timezone":"Asia/Kathmandu",
    "iso:country":"NP",
    "wof:name":"Sirwani",
    "wof:placetype":"locality"
},
  "geometry": {"coordinates":[86.45675,27.08117],"type":"Point"}
}