{
  "type": "Feature",
  "properties": {
    "gn:admin1_code":"CR",
    "gn:admin2_code":"1",
    "gn:admin3_code":"24.0",
    "gn:admin4_code":"240039.0",
    "gn:asciiname":"Jagate",
    "gn:country_code":"NP",
    "gn:dem":851,
    "gn:feature_class":"P",
    "gn:feature_code":"PPLL",
    "gn:name":"Jagate",
    "gn:population":0,
    "gn:timezone":"Asia/Kathmandu",
    "iso:country":"NP",
    "wof:name":"Jagate",
    "wof:placetype":"locality"
},
  "geometry": {"coordinates":[85.78749999999999,27.54061],"type":"Point"}
}