{
  "type": "Feature",
  "properties": {
    "gn:admin1_code":"FR",
    "gn:admin2_code":"14",
    "gn:admin3_code":"68",
    "gn:admin4_code":"680024",
    "gn:asciiname":"Luyeti",
    "gn:country_code":"NP",
    "gn:dem":1803,
    "gn:feature_class":"P",
    "gn:feature_code":"PPLL",
    "gn:name":"Luyeti",
    "gn:population":0,
    "gn:timezone":"Asia/Kathmandu",
    "iso:country":"NP",
    "wof:name":"Luyeti",
    "wof:placetype":"locality"
},
  "geometry": {"coordinates":[81.02083,29.44749],"type":"Point"}
}