{
  "type": "Feature",
  "properties": {
    "gn:admin1_code":"00",
    "gn:asciiname":"Chaurasitola",
    "gn:country_code":"NP",
    "gn:dem":93,
    "gn:feature_class":"P",
    "gn:feature_code":"PPL",
    "gn:name":"Chaur\u0101si\u0307\u0304\u1e6dol\u0101",
    "gn:population":0,
    "gn:timezone":"Asia/Kathmandu",
    "iso:country":"NP",
    "wof:name":"Chaurasitola",
    "wof:placetype":"locality"
},
  "geometry": {"coordinates":[85.41051999999998,26.97651],"type":"Point"}
}