{
  "type": "Feature",
  "properties": {
    "gn:admin1_code":"MR",
    "gn:admin2_code":"12",
    "gn:admin3_code":"54",
    "gn:admin4_code":"540011",
    "gn:asciiname":"Kamaide",
    "gn:country_code":"NP",
    "gn:dem":1879,
    "gn:feature_class":"P",
    "gn:feature_code":"PPLL",
    "gn:name":"Kamaide",
    "gn:population":0,
    "gn:timezone":"Asia/Kathmandu",
    "iso:country":"NP",
    "wof:name":"Kamaide",
    "wof:placetype":"locality"
},
  "geometry": {"coordinates":[82.34702,28.68259],"type":"Point"}
}