{
  "type": "Feature",
  "properties": {
    "gn:admin1_code":"ER",
    "gn:admin2_code":"7.0",
    "gn:admin3_code":"6.0",
    "gn:admin4_code":"60041.0",
    "gn:asciiname":"Shahi Jangal",
    "gn:country_code":"NP",
    "gn:dem":97,
    "gn:feature_class":"P",
    "gn:feature_code":"PPLL",
    "gn:name":"Shahi Jangal",
    "gn:population":0,
    "gn:timezone":"Asia/Kathmandu",
    "iso:country":"NP",
    "wof:name":"Shahi Jangal",
    "wof:placetype":"locality"
},
  "geometry": {"coordinates":[87.04680999999999,26.71812000000001],"type":"Point"}
}