{
  "type": "Feature",
  "properties": {
    "gn:admin1_code":"WR",
    "gn:admin2_code":"4.0",
    "gn:admin3_code":"39.0",
    "gn:admin4_code":"390005.0",
    "gn:asciiname":"Nakindanda",
    "gn:country_code":"NP",
    "gn:dem":1489,
    "gn:feature_class":"P",
    "gn:feature_code":"PPLL",
    "gn:name":"Nakindanda",
    "gn:population":0,
    "gn:timezone":"Asia/Kathmandu",
    "iso:country":"NP",
    "wof:name":"Nakindanda",
    "wof:placetype":"locality"
},
  "geometry": {"coordinates":[83.82717,28.18861],"type":"Point"}
}