{
  "type": "Feature",
  "properties": {
    "gn:admin1_code":"WR",
    "gn:admin2_code":"4",
    "gn:admin3_code":"37",
    "gn:admin4_code":"370007",
    "gn:asciiname":"Sarkigaun",
    "gn:country_code":"NP",
    "gn:dem":762,
    "gn:feature_class":"P",
    "gn:feature_code":"PPLL",
    "gn:name":"Sarkigaun",
    "gn:population":0,
    "gn:timezone":"Asia/Kathmandu",
    "iso:country":"NP",
    "wof:name":"Sarkigaun",
    "wof:placetype":"locality"
},
  "geometry": {"coordinates":[84.38311999999998,28.22483],"type":"Point"}
}