{
  "type": "Feature",
  "properties": {
    "gn:admin1_code":"ER",
    "gn:admin2_code":"7.0",
    "gn:admin3_code":"8.0",
    "gn:admin4_code":"80025.0",
    "gn:asciiname":"Khelpur",
    "gn:country_code":"NP",
    "gn:dem":1485,
    "gn:feature_class":"P",
    "gn:feature_code":"PPLL",
    "gn:name":"Khelpur",
    "gn:population":0,
    "gn:timezone":"Asia/Kathmandu",
    "iso:country":"NP",
    "wof:name":"Khelpur",
    "wof:placetype":"locality"
},
  "geometry": {"coordinates":[87.62661,27.22144],"type":"Point"}
}