{
  "type": "Feature",
  "properties": {
    "gn:admin1_code":"MR",
    "gn:admin2_code":"2.0",
    "gn:admin3_code":"59.0",
    "gn:admin4_code":"590037.0",
    "gn:asciiname":"Kumaldanda",
    "gn:country_code":"NP",
    "gn:dem":1117,
    "gn:feature_class":"P",
    "gn:feature_code":"PPLL",
    "gn:name":"Kumaldanda",
    "gn:population":0,
    "gn:timezone":"Asia/Kathmandu",
    "iso:country":"NP",
    "wof:name":"Kumaldanda",
    "wof:placetype":"locality"
},
  "geometry": {"coordinates":[81.82274,28.38131],"type":"Point"}
}