{
  "type": "Feature",
  "properties": {
    "gn:admin1_code":"CR",
    "gn:admin2_code":"11.0",
    "gn:admin3_code":"33.0",
    "gn:admin4_code":"330030.0",
    "gn:asciiname":"Nagardaha",
    "gn:country_code":"NP",
    "gn:dem":97,
    "gn:feature_class":"P",
    "gn:feature_code":"PPLL",
    "gn:name":"Nagardaha",
    "gn:population":0,
    "gn:timezone":"Asia/Kathmandu",
    "iso:country":"NP",
    "name:fra_x_preferred":[
        "Nagardaha"
    ],
    "name:mai_x_preferred":[
        "\u0928\u0917\u0930\u0926\u093e\u0939\u093e"
    ],
    "name:msa_x_preferred":[
        "Nagardaha"
    ],
    "name:nep_x_preferred":[
        "\u0928\u0917\u0930\u0926\u093e\u0939\u093e"
    ],
    "name:new_x_preferred":[
        "\u0928\u0917\u0930\u0926\u0939"
    ],
    "name:pol_x_preferred":[
        "Nagardaha"
    ],
    "wof:name":"Nagardaha",
    "wof:placetype":"locality"
},
  "geometry": {"coordinates":[85.07583000000002,27.02141],"type":"Point"}
}