{
  "type": "Feature",
  "properties": {
    "gn:admin1_code":"MR",
    "gn:admin2_code":"2",
    "gn:admin3_code":"60.0",
    "gn:admin4_code":"600046.0",
    "gn:asciiname":"Bahun Tol",
    "gn:country_code":"NP",
    "gn:dem":1313,
    "gn:feature_class":"P",
    "gn:feature_code":"PPLL",
    "gn:name":"Bahun Tol",
    "gn:population":0,
    "gn:timezone":"Asia/Kathmandu",
    "iso:country":"NP",
    "wof:name":"Bahun Tol",
    "wof:placetype":"locality"
},
  "geometry": {"coordinates":[81.69785999999998,28.95892000000001],"type":"Point"}
}