{
  "type": "Feature",
  "properties": {
    "gn:admin1_code":"MR",
    "gn:admin2_code":"2",
    "gn:admin3_code":"60.0",
    "gn:admin4_code":"600048.0",
    "gn:asciiname":"Sidar",
    "gn:country_code":"NP",
    "gn:dem":1345,
    "gn:feature_class":"P",
    "gn:feature_code":"PPLL",
    "gn:name":"Sidar",
    "gn:population":0,
    "gn:timezone":"Asia/Kathmandu",
    "iso:country":"NP",
    "wof:name":"Sidar",
    "wof:placetype":"locality"
},
  "geometry": {"coordinates":[81.84246999999998,28.826],"type":"Point"}
}