{
  "type": "Feature",
  "properties": {
    "gn:admin1_code":"CR",
    "gn:admin2_code":"5",
    "gn:admin3_code":"20",
    "gn:admin4_code":"200013",
    "gn:asciiname":"Kunda",
    "gn:country_code":"NP",
    "gn:dem":381,
    "gn:feature_class":"P",
    "gn:feature_code":"PPLL",
    "gn:name":"Kunda",
    "gn:population":0,
    "gn:timezone":"Asia/Kathmandu",
    "iso:country":"NP",
    "name:ceb_x_preferred":[
        "Kunda"
    ],
    "name:ces_x_preferred":[
        "Kunda"
    ],
    "name:deu_x_preferred":[
        "Kunda"
    ],
    "name:fra_x_preferred":[
        "Kunda"
    ],
    "name:new_x_preferred":[
        "\u0915\u0941\u0928\u094d\u0926\u093e"
    ],
    "name:nld_x_preferred":[
        "Kunda"
    ],
    "name:pol_x_preferred":[
        "Kunda"
    ],
    "name:ron_x_preferred":[
        "Kunda"
    ],
    "name:sco_x_preferred":[
        "Kunda"
    ],
    "name:slk_x_preferred":[
        "Kunda"
    ],
    "name:spa_x_preferred":[
        "Kunda"
    ],
    "name:swe_x_preferred":[
        "Kunda"
    ],
    "name:vie_x_preferred":[
        "Kunda"
    ],
    "wof:name":"Kunda",
    "wof:placetype":"locality"
},
  "geometry": {"coordinates":[85.80068,27.24158],"type":"Point"}
}