{
  "type": "Feature",
  "properties": {
    "gn:admin1_code":"00",
    "gn:asciiname":"Bagaicha",
    "gn:country_code":"NP",
    "gn:dem":248,
    "gn:feature_class":"P",
    "gn:feature_code":"PPL",
    "gn:name":"Bagai\u0307\u0303ch\u0101",
    "gn:population":0,
    "gn:timezone":"Asia/Kathmandu",
    "iso:country":"NP",
    "name:nep_x_preferred":[
        "Bagai\u0307\u0303ch\u0101"
    ],
    "wof:name":"Bagaicha",
    "wof:placetype":"locality"
},
  "geometry": {"coordinates":[86.88981,26.84387000000001],"type":"Point"}
}