{
  "type": "Feature",
  "properties": {
    "gn:admin1_code":"ER",
    "gn:admin2_code":"10.0",
    "gn:admin3_code":"1.0",
    "gn:admin4_code":"10010.0",
    "gn:asciiname":"Hangpang",
    "gn:country_code":"NP",
    "gn:dem":1121,
    "gn:feature_class":"P",
    "gn:feature_code":"PPLL",
    "gn:name":"Hangpang",
    "gn:population":0,
    "gn:timezone":"Asia/Kathmandu",
    "iso:country":"NP",
    "name:bih_x_preferred":[
        "\u0939\u093e\u0919\u094d\u0917\u092a\u093e\u0919\u094d\u0917"
    ],
    "name:fra_x_preferred":[
        "Hangpang"
    ],
    "name:mai_x_preferred":[
        "\u0939\u093e\u0919\u094d\u0917\u092a\u093e\u0919\u094d\u0917"
    ],
    "name:msa_x_preferred":[
        "Hangpang"
    ],
    "name:nep_x_preferred":[
        "\u0939\u093e\u0919\u094d\u0917\u092a\u093e\u0919\u094d\u0917"
    ],
    "name:new_x_preferred":[
        "\u0939\u093e\u0919\u092a\u093e\u0919"
    ],
    "name:pol_x_preferred":[
        "Hangpang"
    ],
    "wof:name":"Hangpang",
    "wof:placetype":"locality"
},
  "geometry": {"coordinates":[87.62409,27.33089],"type":"Point"}
}