{
  "type": "Feature",
  "properties": {
    "gn:admin1_code":"CR",
    "gn:admin2_code":"5",
    "gn:admin3_code":"18",
    "gn:admin4_code":"180045",
    "gn:asciiname":"Dadatol",
    "gn:country_code":"NP",
    "gn:dem":286,
    "gn:feature_class":"P",
    "gn:feature_code":"PPLL",
    "gn:name":"Dadatol",
    "gn:population":0,
    "gn:timezone":"Asia/Kathmandu",
    "iso:country":"NP",
    "wof:name":"Dadatol",
    "wof:placetype":"locality"
},
  "geometry": {"coordinates":[85.82883000000002,27.04556],"type":"Point"}
}