{
  "type": "Feature",
  "properties": {
    "gn:admin1_code":"WR",
    "gn:admin2_code":"4.0",
    "gn:admin3_code":"38.0",
    "gn:admin4_code":"380044.0",
    "gn:asciiname":"Bantar",
    "gn:country_code":"NP",
    "gn:dem":384,
    "gn:feature_class":"P",
    "gn:feature_code":"PPLL",
    "gn:name":"Bantar",
    "gn:population":0,
    "gn:timezone":"Asia/Kathmandu",
    "iso:country":"NP",
    "wof:name":"Bantar",
    "wof:placetype":"locality"
},
  "geometry": {"coordinates":[84.04363000000002,27.86515],"type":"Point"}
}