{
  "type": "Feature",
  "properties": {
    "gn:admin1_code":"ER",
    "gn:admin2_code":"13",
    "gn:admin3_code":"16",
    "gn:admin4_code":"160068",
    "gn:asciiname":"Khairtoka",
    "gn:country_code":"NP",
    "gn:dem":74,
    "gn:feature_class":"P",
    "gn:feature_code":"PPLL",
    "gn:name":"Khairtoka",
    "gn:population":0,
    "gn:timezone":"Asia/Kathmandu",
    "iso:country":"NP",
    "wof:name":"Khairtoka",
    "wof:placetype":"locality"
},
  "geometry": {"coordinates":[86.17998,26.62225],"type":"Point"}
}