{
  "type": "Feature",
  "properties": {
    "gn:admin1_code":"CR",
    "gn:admin2_code":"5",
    "gn:admin3_code":"20",
    "gn:admin4_code":"200025.0",
    "gn:asciiname":"Chisapanijhora",
    "gn:country_code":"NP",
    "gn:dem":546,
    "gn:feature_class":"P",
    "gn:feature_code":"PPLL",
    "gn:name":"Chisapanijhora",
    "gn:population":0,
    "gn:timezone":"Asia/Kathmandu",
    "iso:country":"NP",
    "wof:name":"Chisapanijhora",
    "wof:placetype":"locality"
},
  "geometry": {"coordinates":[85.90523,27.21369],"type":"Point"}
}