{
  "type": "Feature",
  "properties": {
    "gn:admin1_code":"WR",
    "gn:admin2_code":"8",
    "gn:admin3_code":"49",
    "gn:admin4_code":"490057",
    "gn:asciiname":"Byauri",
    "gn:country_code":"NP",
    "gn:dem":122,
    "gn:feature_class":"P",
    "gn:feature_code":"PPLL",
    "gn:name":"Byauri",
    "gn:population":0,
    "gn:timezone":"Asia/Kathmandu",
    "iso:country":"NP",
    "wof:name":"Byauri",
    "wof:placetype":"locality"
},
  "geometry": {"coordinates":[83.2621,27.64673],"type":"Point"}
}