{
  "type": "Feature",
  "properties": {
    "gn:admin1_code":"CR",
    "gn:admin2_code":"1",
    "gn:admin3_code":"28",
    "gn:admin4_code":"280048",
    "gn:asciiname":"Phalante",
    "gn:country_code":"NP",
    "gn:dem":1597,
    "gn:feature_class":"P",
    "gn:feature_code":"PPLL",
    "gn:name":"Phalante",
    "gn:population":0,
    "gn:timezone":"Asia/Kathmandu",
    "iso:country":"NP",
    "wof:name":"Phalante",
    "wof:placetype":"locality"
},
  "geometry": {"coordinates":[85.03398,27.97955],"type":"Point"}
}