{
  "type": "Feature",
  "properties": {
    "gn:admin1_code":"MR",
    "gn:admin2_code":"12",
    "gn:admin3_code":"56.0",
    "gn:admin4_code":"560010.0",
    "gn:asciiname":"Parseni",
    "gn:country_code":"NP",
    "gn:dem":262,
    "gn:feature_class":"P",
    "gn:feature_code":"PPLL",
    "gn:name":"Parseni",
    "gn:population":0,
    "gn:timezone":"Asia/Kathmandu",
    "iso:country":"NP",
    "wof:name":"Parseni",
    "wof:placetype":"locality"
},
  "geometry": {"coordinates":[82.59031999999998,27.81417],"type":"Point"}
}