{
  "type": "Feature",
  "properties": {
    "gn:admin1_code":"CR",
    "gn:admin2_code":"1",
    "gn:admin3_code":"23",
    "gn:admin4_code":"230016",
    "gn:asciiname":"Sungurephant",
    "gn:country_code":"NP",
    "gn:dem":1276,
    "gn:feature_class":"P",
    "gn:feature_code":"PPLL",
    "gn:name":"Sungurephant",
    "gn:population":0,
    "gn:timezone":"Asia/Kathmandu",
    "iso:country":"NP",
    "wof:name":"Sungurephant",
    "wof:placetype":"locality"
},
  "geometry": {"coordinates":[85.55683000000001,27.85841],"type":"Point"}
}