{
  "type": "Feature",
  "properties": {
    "gn:admin1_code":"ER",
    "gn:admin2_code":"13",
    "gn:admin3_code":"16",
    "gn:admin4_code":"160060",
    "gn:asciiname":"Charari",
    "gn:country_code":"NP",
    "gn:dem":101,
    "gn:feature_class":"P",
    "gn:feature_code":"PPLL",
    "gn:name":"Charari",
    "gn:population":0,
    "gn:timezone":"Asia/Kathmandu",
    "iso:country":"NP",
    "wof:name":"Charari",
    "wof:placetype":"locality"
},
  "geometry": {"coordinates":[86.36117,26.68981],"type":"Point"}
}