{
  "type": "Feature",
  "properties": {
    "gn:admin1_code":"MR",
    "gn:admin2_code":"2",
    "gn:admin3_code":"61.0",
    "gn:admin4_code":"610006.0",
    "gn:asciiname":"Changkhil",
    "gn:country_code":"NP",
    "gn:dem":880,
    "gn:feature_class":"P",
    "gn:feature_code":"PPLL",
    "gn:name":"Changkhil",
    "gn:population":0,
    "gn:timezone":"Asia/Kathmandu",
    "iso:country":"NP",
    "wof:name":"Changkhil",
    "wof:placetype":"locality"
},
  "geometry": {"coordinates":[82.03929000000002,28.73496],"type":"Point"}
}