{
  "type": "Feature",
  "properties": {
    "gn:admin1_code":"MR",
    "gn:admin2_code":"12",
    "gn:admin3_code":"53",
    "gn:admin4_code":"530028",
    "gn:asciiname":"Ghiu Pokhara",
    "gn:country_code":"NP",
    "gn:dem":1202,
    "gn:feature_class":"P",
    "gn:feature_code":"PPLL",
    "gn:name":"Ghiu Pokhara",
    "gn:population":0,
    "gn:timezone":"Asia/Kathmandu",
    "iso:country":"NP",
    "wof:name":"Ghiu Pokhara",
    "wof:placetype":"locality"
},
  "geometry": {"coordinates":[82.57294,28.36224],"type":"Point"}
}