{
  "type": "Feature",
  "properties": {
    "gn:admin1_code":"WR",
    "gn:admin2_code":"3",
    "gn:admin3_code":"44",
    "gn:admin4_code":"440008",
    "gn:asciiname":"Maidan",
    "gn:country_code":"NP",
    "gn:dem":989,
    "gn:feature_class":"P",
    "gn:feature_code":"PPLL",
    "gn:name":"Maidan",
    "gn:population":0,
    "gn:timezone":"Asia/Kathmandu",
    "iso:country":"NP",
    "wof:name":"Maidan",
    "wof:placetype":"locality"
},
  "geometry": {"coordinates":[83.64100999999999,28.04457],"type":"Point"}
}