{
  "type": "Feature",
  "properties": {
    "gn:admin1_code":"ER",
    "gn:admin2_code":"10",
    "gn:admin3_code":"3.0",
    "gn:admin4_code":"30046.0",
    "gn:asciiname":"Soyak",
    "gn:country_code":"NP",
    "gn:dem":1012,
    "gn:feature_class":"P",
    "gn:feature_code":"PPLL",
    "gn:name":"Soyak",
    "gn:population":0,
    "gn:timezone":"Asia/Kathmandu",
    "iso:country":"NP",
    "name:bih_x_preferred":[
        "\u0938\u094b\u092f\u093e\u0915"
    ],
    "name:ceb_x_preferred":[
        "Soyak"
    ],
    "name:mai_x_preferred":[
        "\u0938\u094b\u092f\u093e\u0915"
    ],
    "name:msa_x_preferred":[
        "Soyak"
    ],
    "name:nep_x_preferred":[
        "\u0938\u094b\u092f\u093e\u0915"
    ],
    "name:nld_x_preferred":[
        "Soyak"
    ],
    "wof:name":"Soyak",
    "wof:placetype":"locality"
},
  "geometry": {"coordinates":[87.87059000000001,26.84632],"type":"Point"}
}