{
  "type": "Feature",
  "properties": {
    "gn:admin1_code":"ER",
    "gn:admin2_code":"13",
    "gn:admin3_code":"11",
    "gn:admin4_code":"110012",
    "gn:asciiname":"Dharapani",
    "gn:country_code":"NP",
    "gn:dem":2563,
    "gn:feature_class":"P",
    "gn:feature_code":"PPLL",
    "gn:name":"Dharapani",
    "gn:population":0,
    "gn:timezone":"Asia/Kathmandu",
    "iso:country":"NP",
    "wof:name":"Dharapani",
    "wof:placetype":"locality"
},
  "geometry": {"coordinates":[86.50773000000002,27.45879],"type":"Point"}
}