{
  "type": "Feature",
  "properties": {
    "gn:admin1_code":"FR",
    "gn:admin2_code":"14",
    "gn:admin3_code":"69.0",
    "gn:admin4_code":"690003.0",
    "gn:asciiname":"Palakatne",
    "gn:country_code":"NP",
    "gn:dem":1411,
    "gn:feature_class":"P",
    "gn:feature_code":"PPLL",
    "gn:name":"Palakatne",
    "gn:population":0,
    "gn:timezone":"Asia/Kathmandu",
    "iso:country":"NP",
    "wof:name":"Palakatne",
    "wof:placetype":"locality"
},
  "geometry": {"coordinates":[81.33433000000002,29.15034],"type":"Point"}
}