{
  "type": "Feature",
  "properties": {
    "gn:admin1_code":"WR",
    "gn:admin2_code":"4.0",
    "gn:admin3_code":"39.0",
    "gn:admin4_code":"390032.0",
    "gn:asciiname":"Budhakot",
    "gn:country_code":"NP",
    "gn:dem":1619,
    "gn:feature_class":"P",
    "gn:feature_code":"PPLL",
    "gn:name":"Budhakot",
    "gn:population":0,
    "gn:timezone":"Asia/Kathmandu",
    "iso:country":"NP",
    "name:ceb_x_preferred":[
        "Budhakot"
    ],
    "name:fra_x_preferred":[
        "Budhakot"
    ],
    "name:mai_x_preferred":[
        "\u092c\u0941\u0922\u093e\u0915\u094b\u091f"
    ],
    "name:msa_x_preferred":[
        "Budhakot"
    ],
    "name:nep_x_preferred":[
        "\u092c\u0941\u0922\u093e\u0915\u094b\u0924"
    ],
    "name:new_x_preferred":[
        "\u092c\u0941\u0922\u093e\u0915\u094b\u0924"
    ],
    "name:pol_x_preferred":[
        "Budhakot"
    ],
    "wof:name":"Budhakot",
    "wof:placetype":"locality"
},
  "geometry": {"coordinates":[83.84206999999998,28.00046],"type":"Point"}
}