{
  "type": "Feature",
  "properties": {
    "gn:admin1_code":"00",
    "gn:asciiname":"Trisuli Bazar",
    "gn:country_code":"NP",
    "gn:dem":630,
    "gn:feature_class":"P",
    "gn:feature_code":"PPL",
    "gn:name":"Tris\u016bli B\u0101z\u0101r",
    "gn:population":0,
    "gn:timezone":"Asia/Kathmandu",
    "iso:country":"NP",
    "name:und_x_variant":[
        "Khinchit",
        "Trisuli",
        "Tris\u016bli B\u0101z\u0101r"
    ],
    "wof:name":"Trisuli Bazar",
    "wof:placetype":"locality"
},
  "geometry": {"coordinates":[85.14144,27.92751],"type":"Point"}
}