{
  "type": "Feature",
  "properties": {
    "gn:admin1_code":"WR",
    "gn:admin2_code":"4",
    "gn:admin3_code":"36.0",
    "gn:admin4_code":"360009.0",
    "gn:asciiname":"Archanbas",
    "gn:country_code":"NP",
    "gn:dem":1129,
    "gn:feature_class":"P",
    "gn:feature_code":"PPLL",
    "gn:name":"Archanbas",
    "gn:population":0,
    "gn:timezone":"Asia/Kathmandu",
    "iso:country":"NP",
    "wof:name":"Archanbas",
    "wof:placetype":"locality"
},
  "geometry": {"coordinates":[84.68315,27.83616],"type":"Point"}
}