{
  "type": "Feature",
  "properties": {
    "gn:admin1_code":"WR",
    "gn:admin2_code":"8",
    "gn:admin3_code":"46.0",
    "gn:admin4_code":"460054.0",
    "gn:asciiname":"Man Kot",
    "gn:country_code":"NP",
    "gn:dem":954,
    "gn:feature_class":"P",
    "gn:feature_code":"PPLL",
    "gn:name":"Man Kot",
    "gn:population":0,
    "gn:timezone":"Asia/Kathmandu",
    "iso:country":"NP",
    "wof:name":"Man Kot",
    "wof:placetype":"locality"
},
  "geometry": {"coordinates":[83.33136999999998,27.96066],"type":"Point"}
}