{
  "type": "Feature",
  "properties": {
    "gn:admin1_code":"WR",
    "gn:admin2_code":"4",
    "gn:admin3_code":"40.0",
    "gn:admin4_code":"400035.0",
    "gn:asciiname":"Ribhan",
    "gn:country_code":"NP",
    "gn:dem":1521,
    "gn:feature_class":"P",
    "gn:feature_code":"PPLL",
    "gn:name":"Ribhan",
    "gn:population":0,
    "gn:timezone":"Asia/Kathmandu",
    "iso:country":"NP",
    "name:ceb_x_preferred":[
        "Reevan"
    ],
    "name:deu_x_preferred":[
        "Rivan"
    ],
    "name:fra_x_preferred":[
        "Rivan"
    ],
    "name:mai_x_preferred":[
        "\u0930\u093f\u092d\u093e\u0928"
    ],
    "name:msa_x_preferred":[
        "Reevan"
    ],
    "name:nep_x_preferred":[
        "\u0930\u093f\u092d\u093e\u0928"
    ],
    "name:new_x_preferred":[
        "\u0930\u0940\u0935\u0928"
    ],
    "name:pol_x_preferred":[
        "Reevan"
    ],
    "wof:name":"Ribhan",
    "wof:placetype":"locality"
},
  "geometry": {"coordinates":[83.91396,28.32635],"type":"Point"}
}