{
  "type": "Feature",
  "properties": {
    "gn:admin1_code":"FR",
    "gn:admin2_code":"14.0",
    "gn:admin3_code":"69.0",
    "gn:admin4_code":"690041.0",
    "gn:asciiname":"Odale",
    "gn:country_code":"NP",
    "gn:dem":1270,
    "gn:feature_class":"P",
    "gn:feature_code":"PPLL",
    "gn:name":"Odale",
    "gn:population":0,
    "gn:timezone":"Asia/Kathmandu",
    "iso:country":"NP",
    "wof:name":"Odale",
    "wof:placetype":"locality"
},
  "geometry": {"coordinates":[81.36679000000002,29.1056],"type":"Point"}
}