{
  "type": "Feature",
  "properties": {
    "gn:admin1_code":"WR",
    "gn:admin2_code":"8",
    "gn:admin3_code":"47",
    "gn:admin4_code":"470014.0",
    "gn:asciiname":"Pande Khola",
    "gn:country_code":"NP",
    "gn:dem":1228,
    "gn:feature_class":"P",
    "gn:feature_code":"PPLL",
    "gn:name":"Pande Khola",
    "gn:population":0,
    "gn:timezone":"Asia/Kathmandu",
    "iso:country":"NP",
    "wof:name":"Pande Khola",
    "wof:placetype":"locality"
},
  "geometry": {"coordinates":[83.64678000000001,27.82976],"type":"Point"}
}