{
  "type": "Feature",
  "properties": {
    "gn:admin1_code":"CR",
    "gn:admin2_code":"11",
    "gn:admin3_code":"31",
    "gn:admin4_code":"310039",
    "gn:asciiname":"Pattharchok",
    "gn:country_code":"NP",
    "gn:dem":999,
    "gn:feature_class":"P",
    "gn:feature_code":"PPLL",
    "gn:name":"Pattharchok",
    "gn:population":0,
    "gn:timezone":"Asia/Kathmandu",
    "iso:country":"NP",
    "wof:name":"Pattharchok",
    "wof:placetype":"locality"
},
  "geometry": {"coordinates":[85.29550999999999,27.4171],"type":"Point"}
}