{
  "type": "Feature",
  "properties": {
    "gn:admin1_code":"00",
    "gn:asciiname":"Damdawali",
    "gn:country_code":"NP",
    "gn:dem":506,
    "gn:feature_class":"P",
    "gn:feature_code":"PPL",
    "gn:name":"Damdaw\u0101li\u0307\u0304",
    "gn:population":0,
    "gn:timezone":"Asia/Kathmandu",
    "iso:country":"NP",
    "name:nep_x_preferred":[
        "Damdaw\u0101li\u0307\u0304"
    ],
    "name:und_x_variant":[
        "D\u0101mdw\u0101li",
        "W\u0101l\u012b"
    ],
    "wof:name":"Damdawali",
    "wof:placetype":"locality"
},
  "geometry": {"coordinates":[81.91001999999997,28.27081],"type":"Point"}
}