{
  "type": "Feature",
  "properties": {
    "gn:admin1_code":"MR",
    "gn:admin2_code":"2.0",
    "gn:admin3_code":"59.0",
    "gn:admin4_code":"590029.0",
    "gn:asciiname":"Bini",
    "gn:country_code":"NP",
    "gn:dem":319,
    "gn:feature_class":"P",
    "gn:feature_code":"PPLL",
    "gn:name":"Bini",
    "gn:population":0,
    "gn:timezone":"Asia/Kathmandu",
    "iso:country":"NP",
    "name:ceb_x_preferred":[
        "Bini"
    ],
    "name:deu_x_preferred":[
        "Bini"
    ],
    "name:fra_x_preferred":[
        "Bini"
    ],
    "name:ita_x_preferred":[
        "Bini"
    ],
    "name:por_x_preferred":[
        "Bini"
    ],
    "name:rus_x_preferred":[
        "\u0411\u0438\u043d\u0438"
    ],
    "name:swe_x_preferred":[
        "Bini"
    ],
    "name:ukr_x_preferred":[
        "\u0411\u0456\u043d\u0456"
    ],
    "wof:name":"Bini",
    "wof:placetype":"locality"
},
  "geometry": {"coordinates":[81.10897,28.96588],"type":"Point"}
}