{
  "type": "Feature",
  "properties": {
    "gn:admin1_code":"FR",
    "gn:admin2_code":"14",
    "gn:admin3_code":"70.0",
    "gn:admin4_code":"700047.0",
    "gn:asciiname":"Gainigaun",
    "gn:country_code":"NP",
    "gn:dem":1122,
    "gn:feature_class":"P",
    "gn:feature_code":"PPLL",
    "gn:name":"Gainigaun",
    "gn:population":0,
    "gn:timezone":"Asia/Kathmandu",
    "iso:country":"NP",
    "wof:name":"Gainigaun",
    "wof:placetype":"locality"
},
  "geometry": {"coordinates":[80.81607,29.24555],"type":"Point"}
}