{
  "type": "Feature",
  "properties": {
    "gn:admin1_code":"00",
    "gn:asciiname":"Bahagau",
    "gn:country_code":"NP",
    "gn:dem":653,
    "gn:feature_class":"P",
    "gn:feature_code":"PPL",
    "gn:name":"B\u0101\u0303h\u0101g\u0101\u0169",
    "gn:population":0,
    "gn:timezone":"Asia/Kathmandu",
    "iso:country":"NP",
    "name:und_x_variant":[
        "B\u0101\u0303h\u0101g\u0101\u0169",
        "B\u0101nh\u0101g\u0101un"
    ],
    "wof:name":"Bahagau",
    "wof:placetype":"locality"
},
  "geometry": {"coordinates":[85.36949,27.42714],"type":"Point"}
}