{
  "type": "Feature",
  "properties": {
    "gn:admin1_code":"ER",
    "gn:admin2_code":"13",
    "gn:admin3_code":"13.0",
    "gn:admin4_code":"130019.0",
    "gn:asciiname":"Dhaireni",
    "gn:country_code":"NP",
    "gn:dem":807,
    "gn:feature_class":"P",
    "gn:feature_code":"PPLL",
    "gn:name":"Dhaireni",
    "gn:population":0,
    "gn:timezone":"Asia/Kathmandu",
    "iso:country":"NP",
    "wof:name":"Dhaireni",
    "wof:placetype":"locality"
},
  "geometry": {"coordinates":[86.52429000000002,27.18289],"type":"Point"}
}