{
  "type": "Feature",
  "properties": {
    "gn:admin1_code":"FR",
    "gn:admin2_code":"9",
    "gn:admin3_code":"72.0",
    "gn:admin4_code":"720006.0",
    "gn:asciiname":"Sundarnagar",
    "gn:country_code":"NP",
    "gn:dem":186,
    "gn:feature_class":"P",
    "gn:feature_code":"PPLL",
    "gn:name":"Sundarnagar",
    "gn:population":0,
    "gn:timezone":"Asia/Kathmandu",
    "iso:country":"NP",
    "wof:name":"Sundarnagar",
    "wof:placetype":"locality"
},
  "geometry": {"coordinates":[80.07138,28.83767000000001],"type":"Point"}
}