{
  "type": "Feature",
  "properties": {
    "gn:admin1_code":"ER",
    "gn:admin2_code":"13",
    "gn:admin3_code":"12",
    "gn:admin4_code":"120013",
    "gn:asciiname":"Puranagaun",
    "gn:country_code":"NP",
    "gn:dem":1229,
    "gn:feature_class":"P",
    "gn:feature_code":"PPLL",
    "gn:name":"Puranagaun",
    "gn:population":0,
    "gn:timezone":"Asia/Kathmandu",
    "iso:country":"NP",
    "wof:name":"Puranagaun",
    "wof:placetype":"locality"
},
  "geometry": {"coordinates":[86.32422,27.30668],"type":"Point"}
}