{
  "type": "Feature",
  "properties": {
    "gn:admin1_code":"FR",
    "gn:admin2_code":"14",
    "gn:admin3_code":"70.0",
    "gn:admin4_code":"700020.0",
    "gn:asciiname":"Simargad",
    "gn:country_code":"NP",
    "gn:dem":848,
    "gn:feature_class":"P",
    "gn:feature_code":"PPLL",
    "gn:name":"Simargad",
    "gn:population":0,
    "gn:timezone":"Asia/Kathmandu",
    "iso:country":"NP",
    "wof:name":"Simargad",
    "wof:placetype":"locality"
},
  "geometry": {"coordinates":[80.88099,29.41531],"type":"Point"}
}