{
  "type": "Feature",
  "properties": {
    "gn:admin1_code":"ER",
    "gn:admin2_code":"10.0",
    "gn:admin3_code":"1.0",
    "gn:admin4_code":"10031.0",
    "gn:asciiname":"Ambote",
    "gn:country_code":"NP",
    "gn:dem":849,
    "gn:feature_class":"P",
    "gn:feature_code":"PPLL",
    "gn:name":"Ambote",
    "gn:population":0,
    "gn:timezone":"Asia/Kathmandu",
    "iso:country":"NP",
    "wof:name":"Ambote",
    "wof:placetype":"locality"
},
  "geometry": {"coordinates":[87.64504000000002,27.33121],"type":"Point"}
}