{
  "type": "Feature",
  "properties": {
    "gn:admin1_code":"FR",
    "gn:admin2_code":"14",
    "gn:admin3_code":"69.0",
    "gn:admin4_code":"690056.0",
    "gn:asciiname":"Lash",
    "gn:country_code":"NP",
    "gn:dem":561,
    "gn:feature_class":"P",
    "gn:feature_code":"PPLL",
    "gn:name":"Lash",
    "gn:population":0,
    "gn:timezone":"Asia/Kathmandu",
    "iso:country":"NP",
    "wof:name":"Lash",
    "wof:placetype":"locality"
},
  "geometry": {"coordinates":[81.21395,29.16931],"type":"Point"}
}