{
  "type": "Feature",
  "properties": {
    "gn:admin1_code":"ER",
    "gn:admin2_code":"13",
    "gn:admin3_code":"12",
    "gn:admin4_code":"120042",
    "gn:asciiname":"Koiralagaun",
    "gn:country_code":"NP",
    "gn:dem":1037,
    "gn:feature_class":"P",
    "gn:feature_code":"PPLL",
    "gn:name":"Koiralagaun",
    "gn:population":0,
    "gn:timezone":"Asia/Kathmandu",
    "iso:country":"NP",
    "wof:name":"Koiralagaun",
    "wof:placetype":"locality"
},
  "geometry": {"coordinates":[86.61147,27.32327],"type":"Point"}
}