{
  "type": "Feature",
  "properties": {
    "gn:admin1_code":"MR",
    "gn:admin2_code":"2",
    "gn:admin3_code":"61.0",
    "gn:admin4_code":"610014.0",
    "gn:asciiname":"Ude",
    "gn:country_code":"NP",
    "gn:dem":1633,
    "gn:feature_class":"P",
    "gn:feature_code":"PPLL",
    "gn:name":"Ude",
    "gn:population":0,
    "gn:timezone":"Asia/Kathmandu",
    "iso:country":"NP",
    "wof:name":"Ude",
    "wof:placetype":"locality"
},
  "geometry": {"coordinates":[82.22091999999998,28.74818],"type":"Point"}
}