{
  "type": "Feature",
  "properties": {
    "gn:admin1_code":"MR",
    "gn:admin2_code":"6",
    "gn:admin3_code":"63.0",
    "gn:admin4_code":"630008.0",
    "gn:asciiname":"Dhalapa",
    "gn:country_code":"NP",
    "gn:dem":3089,
    "gn:feature_class":"P",
    "gn:feature_code":"PPLL",
    "gn:name":"Dhalapa",
    "gn:population":0,
    "gn:timezone":"Asia/Kathmandu",
    "iso:country":"NP",
    "wof:name":"Dhalapa",
    "wof:placetype":"locality"
},
  "geometry": {"coordinates":[82.30627,29.318],"type":"Point"}
}