{
  "type": "Feature",
  "properties": {
    "gn:admin1_code":"FR",
    "gn:admin2_code":"14",
    "gn:admin3_code":"68",
    "gn:admin4_code":"680002",
    "gn:asciiname":"Deulek",
    "gn:country_code":"NP",
    "gn:dem":2069,
    "gn:feature_class":"P",
    "gn:feature_code":"PPLL",
    "gn:name":"Deulek",
    "gn:population":0,
    "gn:timezone":"Asia/Kathmandu",
    "iso:country":"NP",
    "name:ceb_x_preferred":[
        "Deulek"
    ],
    "name:dty_x_preferred":[
        "\u0926\u0947\u0909\u0932\u0947\u0915 \u0917\u093e\u0935\u093f\u0938"
    ],
    "name:mai_x_preferred":[
        "\u0926\u0947\u0909\u0932\u0947\u0915"
    ],
    "name:msa_x_preferred":[
        "Deulek"
    ],
    "name:nep_x_preferred":[
        "\u0926\u0947\u0909\u0932\u0947\u0915"
    ],
    "name:new_x_preferred":[
        "\u0926\u0947\u0909\u0932\u0947\u0915"
    ],
    "name:pol_x_preferred":[
        "Deulek"
    ],
    "wof:name":"Deulek",
    "wof:placetype":"locality"
},
  "geometry": {"coordinates":[80.99755,29.49669],"type":"Point"}
}