{
  "type": "Feature",
  "properties": {
    "gn:admin1_code":"MR",
    "gn:admin2_code":"12",
    "gn:admin3_code":"55",
    "gn:admin4_code":"550004",
    "gn:asciiname":"Banghkot",
    "gn:country_code":"NP",
    "gn:dem":1642,
    "gn:feature_class":"P",
    "gn:feature_code":"PPLL",
    "gn:name":"Banghkot",
    "gn:population":0,
    "gn:timezone":"Asia/Kathmandu",
    "iso:country":"NP",
    "wof:name":"Banghkot",
    "wof:placetype":"locality"
},
  "geometry": {"coordinates":[82.07498000000002,28.55613],"type":"Point"}
}