{
  "type": "Feature",
  "properties": {
    "gn:admin1_code":"FR",
    "gn:admin2_code":"9",
    "gn:admin3_code":"74",
    "gn:admin4_code":"740051",
    "gn:asciiname":"Khaneta",
    "gn:country_code":"NP",
    "gn:dem":2085,
    "gn:feature_class":"P",
    "gn:feature_code":"PPLL",
    "gn:name":"Khaneta",
    "gn:population":0,
    "gn:timezone":"Asia/Kathmandu",
    "iso:country":"NP",
    "wof:name":"Khaneta",
    "wof:placetype":"locality"
},
  "geometry": {"coordinates":[80.64116999999997,29.49848],"type":"Point"}
}