{
  "type": "Feature",
  "properties": {
    "gn:admin1_code":"CR",
    "gn:admin2_code":"11",
    "gn:admin3_code":"34",
    "gn:admin4_code":"340021",
    "gn:asciiname":"Solakpur",
    "gn:country_code":"NP",
    "gn:dem":118,
    "gn:feature_class":"P",
    "gn:feature_code":"PPLL",
    "gn:name":"Solakpur",
    "gn:population":0,
    "gn:timezone":"Asia/Kathmandu",
    "iso:country":"NP",
    "wof:name":"Solakpur",
    "wof:placetype":"locality"
},
  "geometry": {"coordinates":[84.93831,27.14044],"type":"Point"}
}