{
  "type": "Feature",
  "properties": {
    "gn:admin1_code":"CR",
    "gn:admin2_code":"11",
    "gn:admin3_code":"35.0",
    "gn:admin4_code":"350039.0",
    "gn:asciiname":"Gaidakhasa",
    "gn:country_code":"NP",
    "gn:dem":152,
    "gn:feature_class":"P",
    "gn:feature_code":"PPLL",
    "gn:name":"Gaidakhasa",
    "gn:population":0,
    "gn:timezone":"Asia/Kathmandu",
    "iso:country":"NP",
    "wof:name":"Gaidakhasa",
    "wof:placetype":"locality"
},
  "geometry": {"coordinates":[84.05463,27.53687],"type":"Point"}
}