{
  "type": "Feature",
  "properties": {
    "gn:admin1_code":"MR",
    "gn:admin2_code":"12",
    "gn:admin3_code":"52",
    "gn:admin4_code":"520011",
    "gn:asciiname":"Padime",
    "gn:country_code":"NP",
    "gn:dem":1870,
    "gn:feature_class":"P",
    "gn:feature_code":"PPLL",
    "gn:name":"Padime",
    "gn:population":0,
    "gn:timezone":"Asia/Kathmandu",
    "iso:country":"NP",
    "wof:name":"Padime",
    "wof:placetype":"locality"
},
  "geometry": {"coordinates":[82.98413000000002,28.09807],"type":"Point"}
}