{
  "type": "Feature",
  "properties": {
    "gn:admin1_code":"CR",
    "gn:admin2_code":"1",
    "gn:admin3_code":"24.0",
    "gn:admin4_code":"240057.0",
    "gn:asciiname":"Mangaltar Bajar",
    "gn:country_code":"NP",
    "gn:dem":706,
    "gn:feature_class":"P",
    "gn:feature_code":"PPLL",
    "gn:name":"Mangaltar Bajar",
    "gn:population":0,
    "gn:timezone":"Asia/Kathmandu",
    "iso:country":"NP",
    "wof:name":"Mangaltar Bajar",
    "wof:placetype":"locality"
},
  "geometry": {"coordinates":[85.74512,27.47728],"type":"Point"}
}