{
  "type": "Feature",
  "properties": {
    "gn:admin1_code":"FR",
    "gn:admin2_code":"9",
    "gn:admin3_code":"74",
    "gn:admin4_code":"740036",
    "gn:asciiname":"Upargaun",
    "gn:country_code":"NP",
    "gn:dem":1372,
    "gn:feature_class":"P",
    "gn:feature_code":"PPLL",
    "gn:name":"Upargaun",
    "gn:population":0,
    "gn:timezone":"Asia/Kathmandu",
    "iso:country":"NP",
    "wof:name":"Upargaun",
    "wof:placetype":"locality"
},
  "geometry": {"coordinates":[80.68203000000003,29.60445],"type":"Point"}
}