{
  "type": "Feature",
  "properties": {
    "gn:admin1_code":"WR",
    "gn:admin2_code":"4",
    "gn:admin3_code":"37",
    "gn:admin4_code":"370002",
    "gn:asciiname":"Dahare",
    "gn:country_code":"NP",
    "gn:dem":2053,
    "gn:feature_class":"P",
    "gn:feature_code":"PPLL",
    "gn:name":"Dahare",
    "gn:population":0,
    "gn:timezone":"Asia/Kathmandu",
    "iso:country":"NP",
    "wof:name":"Dahare",
    "wof:placetype":"locality"
},
  "geometry": {"coordinates":[84.47049,28.37518],"type":"Point"}
}