{
  "type": "Feature",
  "properties": {
    "gn:admin1_code":"MR",
    "gn:admin2_code":"6",
    "gn:admin3_code":"66.0",
    "gn:admin4_code":"660018.0",
    "gn:asciiname":"Garsa Lagna",
    "gn:country_code":"NP",
    "gn:dem":3880,
    "gn:feature_class":"P",
    "gn:feature_code":"PPLL",
    "gn:name":"Garsa Lagna",
    "gn:population":0,
    "gn:timezone":"Asia/Kathmandu",
    "iso:country":"NP",
    "wof:name":"Garsa Lagna",
    "wof:placetype":"locality"
},
  "geometry": {"coordinates":[81.58431,30.04237],"type":"Point"}
}