{
  "type": "Feature",
  "properties": {
    "gn:admin1_code":"MR",
    "gn:admin2_code":"12",
    "gn:admin3_code":"54",
    "gn:admin4_code":"540040",
    "gn:asciiname":"Lingribang",
    "gn:country_code":"NP",
    "gn:dem":1808,
    "gn:feature_class":"P",
    "gn:feature_code":"PPLL",
    "gn:name":"Lingribang",
    "gn:population":0,
    "gn:timezone":"Asia/Kathmandu",
    "iso:country":"NP",
    "wof:name":"Lingribang",
    "wof:placetype":"locality"
},
  "geometry": {"coordinates":[82.58383000000001,28.59013],"type":"Point"}
}