{
  "type": "Feature",
  "properties": {
    "gn:admin1_code":"FR",
    "gn:admin2_code":"14",
    "gn:admin3_code":"69",
    "gn:admin4_code":"690024",
    "gn:asciiname":"Hadelu",
    "gn:country_code":"NP",
    "gn:dem":901,
    "gn:feature_class":"P",
    "gn:feature_code":"PPLL",
    "gn:name":"Hadelu",
    "gn:population":0,
    "gn:timezone":"Asia/Kathmandu",
    "iso:country":"NP",
    "wof:name":"Hadelu",
    "wof:placetype":"locality"
},
  "geometry": {"coordinates":[81.28289000000002,29.04245],"type":"Point"}
}