{
  "type": "Feature",
  "properties": {
    "gn:admin1_code":"WR",
    "gn:admin2_code":"4",
    "gn:admin3_code":"37",
    "gn:admin4_code":"370016.0",
    "gn:asciiname":"Lambata",
    "gn:country_code":"NP",
    "gn:dem":826,
    "gn:feature_class":"P",
    "gn:feature_code":"PPLL",
    "gn:name":"Lambata",
    "gn:population":0,
    "gn:timezone":"Asia/Kathmandu",
    "iso:country":"NP",
    "wof:name":"Lambata",
    "wof:placetype":"locality"
},
  "geometry": {"coordinates":[84.51125999999999,28.11307],"type":"Point"}
}