{
  "type": "Feature",
  "properties": {
    "gn:admin1_code":"MR",
    "gn:admin2_code":"2.0",
    "gn:admin3_code":"58.0",
    "gn:admin4_code":"580003.0",
    "gn:asciiname":"Kusumdanda",
    "gn:country_code":"NP",
    "gn:dem":162,
    "gn:feature_class":"P",
    "gn:feature_code":"PPLL",
    "gn:name":"Kusumdanda",
    "gn:population":0,
    "gn:timezone":"Asia/Kathmandu",
    "iso:country":"NP",
    "wof:name":"Kusumdanda",
    "wof:placetype":"locality"
},
  "geometry": {"coordinates":[81.32015,28.36829],"type":"Point"}
}