{
  "type": "Feature",
  "properties": {
    "gn:admin1_code":"WR",
    "gn:admin2_code":"4.0",
    "gn:admin3_code":"39.0",
    "gn:admin4_code":"390002.0",
    "gn:asciiname":"Bhaktikot",
    "gn:country_code":"NP",
    "gn:dem":1421,
    "gn:feature_class":"P",
    "gn:feature_code":"PPLL",
    "gn:name":"Bhaktikot",
    "gn:population":0,
    "gn:timezone":"Asia/Kathmandu",
    "iso:country":"NP",
    "wof:name":"Bhaktikot",
    "wof:placetype":"locality"
},
  "geometry": {"coordinates":[83.75134,28.07266],"type":"Point"}
}