{
  "type": "Feature",
  "properties": {
    "gn:admin1_code":"FR",
    "gn:admin2_code":"14.0",
    "gn:admin3_code":"67.0",
    "gn:admin4_code":"670012.0",
    "gn:asciiname":"Thakgaun",
    "gn:country_code":"NP",
    "gn:dem":1467,
    "gn:feature_class":"P",
    "gn:feature_code":"PPLL",
    "gn:name":"Thakgaun",
    "gn:population":0,
    "gn:timezone":"Asia/Kathmandu",
    "iso:country":"NP",
    "wof:name":"Thakgaun",
    "wof:placetype":"locality"
},
  "geometry": {"coordinates":[81.30596,29.3771],"type":"Point"}
}