{
  "type": "Feature",
  "properties": {
    "gn:admin1_code":"WR",
    "gn:admin2_code":"4.0",
    "gn:admin3_code":"39.0",
    "gn:admin4_code":"390014.0",
    "gn:asciiname":"Singarkholagaun",
    "gn:country_code":"NP",
    "gn:dem":892,
    "gn:feature_class":"P",
    "gn:feature_code":"PPLL",
    "gn:name":"Singarkholagaun",
    "gn:population":0,
    "gn:timezone":"Asia/Kathmandu",
    "iso:country":"NP",
    "wof:name":"Singarkholagaun",
    "wof:placetype":"locality"
},
  "geometry": {"coordinates":[83.78278,28.01348],"type":"Point"}
}