{
  "type": "Feature",
  "properties": {
    "gn:admin1_code":"ER",
    "gn:admin2_code":"10",
    "gn:admin3_code":"4.0",
    "gn:admin4_code":"40048.0",
    "gn:asciiname":"Ghailadubba",
    "gn:country_code":"NP",
    "gn:dem":122,
    "gn:feature_class":"P",
    "gn:feature_code":"PPLL",
    "gn:name":"Ghailadubba",
    "gn:population":0,
    "gn:timezone":"Asia/Kathmandu",
    "iso:country":"NP",
    "name:ceb_x_preferred":[
        "Ghailadubba"
    ],
    "name:msa_x_preferred":[
        "Ghailadubba"
    ],
    "name:nep_x_preferred":[
        "\u0918\u0948\u0932\u093e\u0921\u0941\u092c\u094d\u092c\u093e"
    ],
    "name:new_x_preferred":[
        "\u0918\u0948\u0932\u093e\u0921\u0941\u092c\u094d\u092c\u093e"
    ],
    "name:pol_x_preferred":[
        "Ghailadubba"
    ],
    "wof:name":"Ghailadubba",
    "wof:placetype":"locality"
},
  "geometry": {"coordinates":[87.93241,26.65341],"type":"Point"}
}