{
  "type": "Feature",
  "properties": {
    "gn:admin1_code":"WR",
    "gn:admin2_code":"4",
    "gn:admin3_code":"37",
    "gn:admin4_code":"370020.0",
    "gn:asciiname":"Chepe Sangu",
    "gn:country_code":"NP",
    "gn:dem":526,
    "gn:feature_class":"P",
    "gn:feature_code":"PPLL",
    "gn:name":"Chepe Sangu",
    "gn:population":0,
    "gn:timezone":"Asia/Kathmandu",
    "iso:country":"NP",
    "wof:name":"Chepe Sangu",
    "wof:placetype":"locality"
},
  "geometry": {"coordinates":[84.48433,28.06321],"type":"Point"}
}