{
  "type": "Feature",
  "properties": {
    "gn:admin1_code":"FR",
    "gn:admin2_code":"9",
    "gn:admin3_code":"74",
    "gn:admin4_code":"740012",
    "gn:asciiname":"Silla",
    "gn:country_code":"NP",
    "gn:dem":1486,
    "gn:feature_class":"P",
    "gn:feature_code":"PPLL",
    "gn:name":"Silla",
    "gn:population":0,
    "gn:timezone":"Asia/Kathmandu",
    "iso:country":"NP",
    "wof:name":"Silla",
    "wof:placetype":"locality"
},
  "geometry": {"coordinates":[80.50827,29.58713],"type":"Point"}
}