{
  "type": "Feature",
  "properties": {
    "gn:admin1_code":"MR",
    "gn:admin2_code":"2.0",
    "gn:admin3_code":"59.0",
    "gn:admin4_code":"590011.0",
    "gn:asciiname":"Sano Beteni",
    "gn:country_code":"NP",
    "gn:dem":1403,
    "gn:feature_class":"P",
    "gn:feature_code":"PPLL",
    "gn:name":"Sano Beteni",
    "gn:population":0,
    "gn:timezone":"Asia/Kathmandu",
    "iso:country":"NP",
    "wof:name":"Sano Beteni",
    "wof:placetype":"locality"
},
  "geometry": {"coordinates":[81.88266999999998,28.49835],"type":"Point"}
}