{
  "type": "Feature",
  "properties": {
    "gn:admin1_code":"ER",
    "gn:admin2_code":"13",
    "gn:admin3_code":"16",
    "gn:admin4_code":"160030",
    "gn:asciiname":"Medinipur",
    "gn:country_code":"NP",
    "gn:dem":123,
    "gn:feature_class":"P",
    "gn:feature_code":"PPLL",
    "gn:name":"Medinipur",
    "gn:population":0,
    "gn:timezone":"Asia/Kathmandu",
    "iso:country":"NP",
    "name:ara_x_preferred":[
        "\u0645\u064a\u062f\u064a\u0646\u064a\u0628\u0648\u0631"
    ],
    "name:ell_x_preferred":[
        "\u039c\u03b5\u03bd\u03c4\u03b9\u03bd\u03b9\u03c0\u03bf\u03cd\u03c1"
    ],
    "name:hun_x_preferred":[
        "Medinipur"
    ],
    "name:ind_x_preferred":[
        "Medinipur"
    ],
    "name:tur_x_preferred":[
        "Medinipur"
    ],
    "name:ukr_x_preferred":[
        "\u041c\u0435\u0434\u0456\u043d\u0456\u043f\u0443\u0440"
    ],
    "wof:name":"Medinipur",
    "wof:placetype":"locality"
},
  "geometry": {"coordinates":[86.43279,26.73179],"type":"Point"}
}