{
  "type": "Feature",
  "properties": {
    "gn:admin1_code":"WR",
    "gn:admin2_code":"4",
    "gn:admin3_code":"36.0",
    "gn:admin4_code":"360037.0",
    "gn:asciiname":"Kirunje",
    "gn:country_code":"NP",
    "gn:dem":2147,
    "gn:feature_class":"P",
    "gn:feature_code":"PPLL",
    "gn:name":"Kirunje",
    "gn:population":0,
    "gn:timezone":"Asia/Kathmandu",
    "iso:country":"NP",
    "wof:name":"Kirunje",
    "wof:placetype":"locality"
},
  "geometry": {"coordinates":[84.80953000000002,28.19487],"type":"Point"}
}