{
  "type": "Feature",
  "properties": {
    "gn:admin1_code":"WR",
    "gn:admin2_code":"3",
    "gn:admin3_code":"44",
    "gn:admin4_code":"440035",
    "gn:asciiname":"Dhada",
    "gn:country_code":"NP",
    "gn:dem":1527,
    "gn:feature_class":"P",
    "gn:feature_code":"PPLL",
    "gn:name":"Dhada",
    "gn:population":0,
    "gn:timezone":"Asia/Kathmandu",
    "iso:country":"NP",
    "name:hif_x_preferred":[
        "Dhada"
    ],
    "name:tel_x_preferred":[
        "\u0c26\u0c21"
    ],
    "wof:name":"Dhada",
    "wof:placetype":"locality"
},
  "geometry": {"coordinates":[83.68219999999999,28.1117],"type":"Point"}
}