{
  "type": "Feature",
  "properties": {
    "gn:admin1_code":"MR",
    "gn:admin2_code":"2",
    "gn:admin3_code":"61.0",
    "gn:admin4_code":"610016.0",
    "gn:asciiname":"Porsalli",
    "gn:country_code":"NP",
    "gn:dem":2505,
    "gn:feature_class":"P",
    "gn:feature_code":"PPLL",
    "gn:name":"Porsalli",
    "gn:population":0,
    "gn:timezone":"Asia/Kathmandu",
    "iso:country":"NP",
    "wof:name":"Porsalli",
    "wof:placetype":"locality"
},
  "geometry": {"coordinates":[82.24405,28.88022],"type":"Point"}
}