{
  "type": "Feature",
  "properties": {
    "gn:admin1_code":"MR",
    "gn:admin2_code":"12",
    "gn:admin3_code":"56.0",
    "gn:admin4_code":"560024.0",
    "gn:asciiname":"Mathaura",
    "gn:country_code":"NP",
    "gn:dem":550,
    "gn:feature_class":"P",
    "gn:feature_code":"PPLL",
    "gn:name":"Mathaura",
    "gn:population":0,
    "gn:timezone":"Asia/Kathmandu",
    "iso:country":"NP",
    "wof:name":"Mathaura",
    "wof:placetype":"locality"
},
  "geometry": {"coordinates":[82.12066999999998,28.1339],"type":"Point"}
}