{
  "type": "Feature",
  "properties": {
    "gn:admin1_code":"ER",
    "gn:admin2_code":"13.0",
    "gn:admin3_code":"14.0",
    "gn:admin4_code":"140001.0",
    "gn:asciiname":"Dandagaun",
    "gn:country_code":"NP",
    "gn:dem":828,
    "gn:feature_class":"P",
    "gn:feature_code":"PPLL",
    "gn:name":"Dandagaun",
    "gn:population":0,
    "gn:timezone":"Asia/Kathmandu",
    "iso:country":"NP",
    "name:pol_x_preferred":[
        "Dandagaun"
    ],
    "wof:name":"Dandagaun",
    "wof:placetype":"locality"
},
  "geometry": {"coordinates":[86.72882,26.96695],"type":"Point"}
}