{
  "type": "Feature",
  "properties": {
    "iso:country":"NP",
    "name:ben_x_preferred":[
        "\u09ae\u09a8\u09cb\u0995\u09be\u09ae\u09a8\u09be \u09ae\u09a8\u09cd\u09a6\u09bf\u09b0"
    ],
    "name:dty_x_preferred":[
        "\u092e\u0928\u0915\u093e\u092e\u0928\u093e \u092e\u0928\u094d\u0926\u093f\u0930"
    ],
    "name:eng_x_preferred":[
        "Manakamana"
    ],
    "name:hin_x_preferred":[
        "\u092e\u0928\u094b\u0915\u093e\u092e\u0928\u093e \u092e\u0928\u094d\u0926\u093f\u0930"
    ],
    "name:kan_x_preferred":[
        "\u0cae\u0ca8\u0c95\u0cbe\u0cae\u0ca8\u0cbe\u0ca6\u0cc7\u0cb5\u0cbf"
    ],
    "name:mai_x_preferred":[
        "\u092e\u0928\u0915\u093e\u092e\u0928\u093e \u092e\u0928\u094d\u0926\u093f\u0930"
    ],
    "name:nep_x_preferred":[
        "\u092e\u0928\u0915\u093e\u092e\u0928\u093e \u092e\u0928\u094d\u0926\u093f\u0930"
    ],
    "name:new_x_preferred":[
        "\u092e\u0928\u0915\u093e\u092e\u0928\u093e"
    ],
    "name:rus_x_preferred":[
        "\u041c\u0430\u043d\u0430\u043a\u0430\u043c\u0430\u043d\u0430"
    ],
    "name:zho_x_preferred":[
        "\u739b\u7eb3\u5361\u739b\u7eb3\u5e99"
    ],
    "name:zho_x_variant":[
        "\u739b\u7eb3\u5361\u739b\u7eb3"
    ],
    "qs:gn_pop":0,
    "qs:name":"Manakamana",
    "qs:name_adm0":"Nepal",
    "qs:name_adm1":"Pashchimanchal",
    "qs:photos":619,
    "qs:photos_1k":125,
    "qs:photos_9k":3,
    "qs:photos_9r":5,
    "qs:photos_all":619,
    "qs:photos_sr":8,
    "qs:placetype":"Town",
    "qs:pop_sr":"0",
    "qs:woe_adm0":23424911,
    "wd:wordcount":1276,
    "wof:name":"Manakamana",
    "wof:placetype":"locality"
},
  "geometry": {"coordinates":[84.551811,27.90812],"type":"Point"}
}