{
  "type": "Feature",
  "properties": {
    "iso:country":"NP",
    "name:arz_x_preferred":[
        "\u0645\u0639\u0628\u062f \u0645\u0627\u0646\u0627\u0643\u0627\u0645\u0627\u0646\u0627"
    ],
    "name:ben_x_preferred":[
        "\u09ae\u09a8\u09cb\u0995\u09be\u09ae\u09a8\u09be \u09ae\u09a8\u09cd\u09a6\u09bf\u09b0"
    ],
    "name:dty_x_preferred":[
        "\u092e\u0928\u0915\u093e\u092e\u0928\u093e \u092e\u0928\u094d\u0926\u093f\u0930"
    ],
    "name:eng_x_preferred":[
        "Manakamana"
    ],
    "name:eng_x_variant":[
        "Manakamana Temple"
    ],
    "name:hin_x_preferred":[
        "\u092e\u0928\u094b\u0915\u093e\u092e\u0928\u093e \u092e\u0928\u094d\u0926\u093f\u0930"
    ],
    "name:kan_x_preferred":[
        "\u0cae\u0ca8\u0c95\u0cbe\u0cae\u0ca8\u0cbe\u0ca6\u0cc7\u0cb5\u0cbf"
    ],
    "name:mai_x_preferred":[
        "\u092e\u0928\u0915\u093e\u092e\u0928\u093e \u092e\u0928\u094d\u0926\u093f\u0930"
    ],
    "name:mal_x_preferred":[
        "\u0d2e\u0d28\u0d15\u0d3e\u0d2e\u0d28 \u0d15\u0d4d\u0d37\u0d47\u0d24\u0d4d\u0d30\u0d02"
    ],
    "name:nep_x_preferred":[
        "\u092e\u0928\u0915\u093e\u092e\u0928\u093e \u092e\u0928\u094d\u0926\u093f\u0930"
    ],
    "name:new_x_preferred":[
        "\u092e\u0928\u0915\u093e\u092e\u0928\u093e"
    ],
    "name:ori_x_preferred":[
        "\u0b2e\u200c\u0b28\u200c\u0b15\u0b3e\u0b2e\u0b28\u0b3e \u0b2e\u0b28\u0b4d\u0b26\u0b3f\u0b30"
    ],
    "name:rus_x_preferred":[
        "\u041c\u0430\u043d\u0430\u043a\u0430\u043c\u0430\u043d\u0430"
    ],
    "name:tel_x_preferred":[
        "\u0c2e\u0c28\u0c15\u0c3e\u0c2e\u0c28 \u0c26\u0c47\u0c35\u0c3e\u0c32\u0c2f\u0c02"
    ],
    "name:zho_x_preferred":[
        "\u739b\u7eb3\u5361\u739b\u7eb3\u5e99"
    ],
    "name:zho_x_variant":[
        "\u739b\u7eb3\u5361\u739b\u7eb3"
    ],
    "qs:gn_pop":0,
    "qs:name":"Manakamana",
    "qs:name_adm0":"Nepal",
    "qs:name_adm1":"Pashchimanchal",
    "qs:photos":619,
    "qs:photos_1k":125,
    "qs:photos_9k":3,
    "qs:photos_9r":5,
    "qs:photos_all":619,
    "qs:photos_sr":8,
    "qs:placetype":"Town",
    "qs:pop_sr":"0",
    "qs:woe_adm0":23424911,
    "wd:wordcount":1276,
    "wof:name":"Manakamana",
    "wof:placetype":"locality"
},
  "geometry": {"coordinates":[84.551811,27.90812],"type":"Point"}
}