{
  "type": "Feature",
  "properties": {
    "gn:admin1_code":"MR",
    "gn:admin2_code":"12",
    "gn:admin3_code":"53",
    "gn:admin4_code":"530017",
    "gn:asciiname":"Jumlung",
    "gn:country_code":"NP",
    "gn:dem":2498,
    "gn:feature_class":"P",
    "gn:feature_code":"PPLL",
    "gn:name":"Jumlung",
    "gn:population":0,
    "gn:timezone":"Asia/Kathmandu",
    "iso:country":"NP",
    "wof:name":"Jumlung",
    "wof:placetype":"locality"
},
  "geometry": {"coordinates":[82.76646,28.40074000000001],"type":"Point"}
}