{
  "type": "Feature",
  "properties": {
    "gn:admin1_code":"CR",
    "gn:admin2_code":"11",
    "gn:admin3_code":"31",
    "gn:admin4_code":"310023.0",
    "gn:asciiname":"Chanthai",
    "gn:country_code":"NP",
    "gn:dem":827,
    "gn:feature_class":"P",
    "gn:feature_code":"PPLL",
    "gn:name":"Chanthai",
    "gn:population":0,
    "gn:timezone":"Asia/Kathmandu",
    "iso:country":"NP",
    "wof:name":"Chanthai",
    "wof:placetype":"locality"
},
  "geometry": {"coordinates":[84.93946,27.59606],"type":"Point"}
}