{
  "type": "Feature",
  "properties": {
    "gn:admin1_code":"00",
    "gn:asciiname":"Simtan",
    "gn:country_code":"NP",
    "gn:dem":1471,
    "gn:feature_class":"P",
    "gn:feature_code":"PPL",
    "gn:name":"Sim\u1e6d\u0101\u1e45",
    "gn:population":0,
    "gn:timezone":"Asia/Kathmandu",
    "iso:country":"NP",
    "name:nep_x_preferred":[
        "Sim\u1e6d\u0101\u1e45"
    ],
    "wof:name":"Simtan",
    "wof:placetype":"locality"
},
  "geometry": {"coordinates":[85.38466,27.95407],"type":"Point"}
}