{
  "type": "Feature",
  "properties": {
    "gn:admin1_code":"MR",
    "gn:admin2_code":"12",
    "gn:admin3_code":"55",
    "gn:admin4_code":"550009",
    "gn:asciiname":"Simtara",
    "gn:country_code":"NP",
    "gn:dem":1036,
    "gn:feature_class":"P",
    "gn:feature_code":"PPLL",
    "gn:name":"Simtara",
    "gn:population":0,
    "gn:timezone":"Asia/Kathmandu",
    "iso:country":"NP",
    "wof:name":"Simtara",
    "wof:placetype":"locality"
},
  "geometry": {"coordinates":[82.1939,28.38846],"type":"Point"}
}