{
  "type": "Feature",
  "properties": {
    "gn:admin1_code":"WR",
    "gn:admin2_code":"4",
    "gn:admin3_code":"37",
    "gn:admin4_code":"370004",
    "gn:asciiname":"Bhalamchaur",
    "gn:country_code":"NP",
    "gn:dem":1591,
    "gn:feature_class":"P",
    "gn:feature_code":"PPLL",
    "gn:name":"Bhalamchaur",
    "gn:population":0,
    "gn:timezone":"Asia/Kathmandu",
    "iso:country":"NP",
    "wof:name":"Bhalamchaur",
    "wof:placetype":"locality"
},
  "geometry": {"coordinates":[84.33124000000002,28.26693],"type":"Point"}
}