{
  "type": "Feature",
  "properties": {
    "gn:admin1_code":"ER",
    "gn:admin2_code":"7",
    "gn:admin3_code":"7.0",
    "gn:admin4_code":"70032.0",
    "gn:asciiname":"Hattitar",
    "gn:country_code":"NP",
    "gn:dem":1797,
    "gn:feature_class":"P",
    "gn:feature_code":"PPLL",
    "gn:name":"Hattitar",
    "gn:population":0,
    "gn:timezone":"Asia/Kathmandu",
    "iso:country":"NP",
    "wof:name":"Hattitar",
    "wof:placetype":"locality"
},
  "geometry": {"coordinates":[87.42223,26.87357],"type":"Point"}
}