{
  "type": "Feature",
  "properties": {
    "gn:admin1_code":"FR",
    "gn:admin2_code":"9",
    "gn:admin3_code":"74",
    "gn:admin4_code":"740052",
    "gn:asciiname":"Dawani",
    "gn:country_code":"NP",
    "gn:dem":1701,
    "gn:feature_class":"P",
    "gn:feature_code":"PPLL",
    "gn:name":"Dawani",
    "gn:population":0,
    "gn:timezone":"Asia/Kathmandu",
    "iso:country":"NP",
    "wof:name":"Dawani",
    "wof:placetype":"locality"
},
  "geometry": {"coordinates":[80.39143,29.40829],"type":"Point"}
}