{
  "type": "Feature",
  "properties": {
    "gn:admin1_code":"CR",
    "gn:admin2_code":"1",
    "gn:admin3_code":"29",
    "gn:admin4_code":"290010",
    "gn:asciiname":"Dhunge",
    "gn:country_code":"NP",
    "gn:dem":1515,
    "gn:feature_class":"P",
    "gn:feature_code":"PPLL",
    "gn:name":"Dhunge",
    "gn:population":0,
    "gn:timezone":"Asia/Kathmandu",
    "iso:country":"NP",
    "wof:name":"Dhunge",
    "wof:placetype":"locality"
},
  "geometry": {"coordinates":[85.20685,28.0228],"type":"Point"}
}