{
  "type": "Feature",
  "properties": {
    "gn:admin1_code":"CR",
    "gn:admin2_code":"1",
    "gn:admin3_code":"24.0",
    "gn:admin4_code":"240006.0",
    "gn:asciiname":"Ghokechaur",
    "gn:country_code":"NP",
    "gn:dem":1490,
    "gn:feature_class":"P",
    "gn:feature_code":"PPLL",
    "gn:name":"Ghokechaur",
    "gn:population":0,
    "gn:timezone":"Asia/Kathmandu",
    "iso:country":"NP",
    "wof:name":"Ghokechaur",
    "wof:placetype":"locality"
},
  "geometry": {"coordinates":[85.53161,27.63431],"type":"Point"}
}