{
  "type": "Feature",
  "properties": {
    "gn:admin1_code":"ER",
    "gn:admin2_code":"7",
    "gn:admin3_code":"9",
    "gn:admin4_code":"90033",
    "gn:asciiname":"Siktemtar",
    "gn:country_code":"NP",
    "gn:dem":677,
    "gn:feature_class":"P",
    "gn:feature_code":"PPLL",
    "gn:name":"Siktemtar",
    "gn:population":0,
    "gn:timezone":"Asia/Kathmandu",
    "iso:country":"NP",
    "wof:name":"Siktemtar",
    "wof:placetype":"locality"
},
  "geometry": {"coordinates":[87.09577,27.47176],"type":"Point"}
}