{
  "type": "Feature",
  "properties": {
    "gn:admin1_code":"MR",
    "gn:admin2_code":"12",
    "gn:admin3_code":"55",
    "gn:admin4_code":"550025",
    "gn:asciiname":"Rokchi",
    "gn:country_code":"NP",
    "gn:dem":1866,
    "gn:feature_class":"P",
    "gn:feature_code":"PPLL",
    "gn:name":"Rokchi",
    "gn:population":0,
    "gn:timezone":"Asia/Kathmandu",
    "iso:country":"NP",
    "wof:name":"Rokchi",
    "wof:placetype":"locality"
},
  "geometry": {"coordinates":[82.36024999999999,28.3653],"type":"Point"}
}