{
  "type": "Feature",
  "properties": {
    "gn:admin1_code":"CR",
    "gn:admin2_code":"5",
    "gn:admin3_code":"17.0",
    "gn:admin4_code":"170097.0",
    "gn:asciiname":"Gumastatol",
    "gn:country_code":"NP",
    "gn:dem":289,
    "gn:feature_class":"P",
    "gn:feature_code":"PPLL",
    "gn:name":"Gumastatol",
    "gn:population":0,
    "gn:timezone":"Asia/Kathmandu",
    "iso:country":"NP",
    "wof:name":"Gumastatol",
    "wof:placetype":"locality"
},
  "geometry": {"coordinates":[85.93397,27.01751],"type":"Point"}
}