{
  "type": "Feature",
  "properties": {
    "gn:admin1_code":"ER",
    "gn:admin2_code":"7.0",
    "gn:admin3_code":"8.0",
    "gn:admin4_code":"80026.0",
    "gn:asciiname":"Majuwa",
    "gn:country_code":"NP",
    "gn:dem":1962,
    "gn:feature_class":"P",
    "gn:feature_code":"PPLL",
    "gn:name":"Majuwa",
    "gn:population":0,
    "gn:timezone":"Asia/Kathmandu",
    "iso:country":"NP",
    "wof:name":"Majuwa",
    "wof:placetype":"locality"
},
  "geometry": {"coordinates":[87.52346,27.26586],"type":"Point"}
}