{
  "type": "Feature",
  "properties": {
    "gn:admin1_code":"WR",
    "gn:admin2_code":"8",
    "gn:admin3_code":"51.0",
    "gn:admin4_code":"510005.0",
    "gn:asciiname":"Babihar",
    "gn:country_code":"NP",
    "gn:dem":921,
    "gn:feature_class":"P",
    "gn:feature_code":"PPLL",
    "gn:name":"Babihar",
    "gn:population":0,
    "gn:timezone":"Asia/Kathmandu",
    "iso:country":"NP",
    "wof:name":"Babihar",
    "wof:placetype":"locality"
},
  "geometry": {"coordinates":[83.22613,27.94426],"type":"Point"}
}