{
  "type": "Feature",
  "properties": {
    "gn:admin1_code":"WR",
    "gn:admin2_code":"4",
    "gn:admin3_code":"36.0",
    "gn:admin4_code":"360052.0",
    "gn:asciiname":"Kolchu",
    "gn:country_code":"NP",
    "gn:dem":3693,
    "gn:feature_class":"P",
    "gn:feature_code":"PPLL",
    "gn:name":"Kolchu",
    "gn:population":0,
    "gn:timezone":"Asia/Kathmandu",
    "iso:country":"NP",
    "wof:name":"Kolchu",
    "wof:placetype":"locality"
},
  "geometry": {"coordinates":[84.66152,28.58315],"type":"Point"}
}