{
  "type": "Feature",
  "properties": {
    "gn:admin1_code":"WR",
    "gn:admin2_code":"4",
    "gn:admin3_code":"36.0",
    "gn:admin4_code":"360055.0",
    "gn:asciiname":"Simjung",
    "gn:country_code":"NP",
    "gn:dem":1285,
    "gn:feature_class":"P",
    "gn:feature_code":"PPLL",
    "gn:name":"Simjung",
    "gn:population":0,
    "gn:timezone":"Asia/Kathmandu",
    "iso:country":"NP",
    "wof:name":"Simjung",
    "wof:placetype":"locality"
},
  "geometry": {"coordinates":[84.6897,28.16888],"type":"Point"}
}