{
  "type": "Feature",
  "properties": {
    "gn:admin1_code":"CR",
    "gn:admin2_code":"1",
    "gn:admin3_code":"24.0",
    "gn:admin4_code":"240069.0",
    "gn:asciiname":"Gupti",
    "gn:country_code":"NP",
    "gn:dem":1710,
    "gn:feature_class":"P",
    "gn:feature_code":"PPLL",
    "gn:name":"Gupti",
    "gn:population":0,
    "gn:timezone":"Asia/Kathmandu",
    "iso:country":"NP",
    "name:deu_x_preferred":[
        "Gupti"
    ],
    "name:pol_x_preferred":[
        "Gupti"
    ],
    "wof:name":"Gupti",
    "wof:placetype":"locality"
},
  "geometry": {"coordinates":[85.73715,27.52607],"type":"Point"}
}