{
  "type": "Feature",
  "properties": {
    "gn:admin1_code":"WR",
    "gn:admin2_code":"4.0",
    "gn:admin3_code":"38.0",
    "gn:admin4_code":"380016.0",
    "gn:asciiname":"Jal Bhanjyang",
    "gn:country_code":"NP",
    "gn:dem":1071,
    "gn:feature_class":"P",
    "gn:feature_code":"PPLL",
    "gn:name":"Jal Bhanjyang",
    "gn:population":0,
    "gn:timezone":"Asia/Kathmandu",
    "iso:country":"NP",
    "wof:name":"Jal Bhanjyang",
    "wof:placetype":"locality"
},
  "geometry": {"coordinates":[84.42009,27.87776],"type":"Point"}
}