{
  "type": "Feature",
  "properties": {
    "gn:admin1_code":"WR",
    "gn:admin2_code":"8",
    "gn:admin3_code":"50.0",
    "gn:admin4_code":"500014.0",
    "gn:asciiname":"Jiginihawa",
    "gn:country_code":"NP",
    "gn:dem":100,
    "gn:feature_class":"P",
    "gn:feature_code":"PPLL",
    "gn:name":"Jiginihawa",
    "gn:population":0,
    "gn:timezone":"Asia/Kathmandu",
    "iso:country":"NP",
    "wof:name":"Jiginihawa",
    "wof:placetype":"locality"
},
  "geometry": {"coordinates":[83.16159,27.4734],"type":"Point"}
}