{
  "type": "Feature",
  "properties": {
    "gn:admin1_code":"ER",
    "gn:admin2_code":"10",
    "gn:admin3_code":"3.0",
    "gn:admin4_code":"30019.0",
    "gn:asciiname":"Gharegaun",
    "gn:country_code":"NP",
    "gn:dem":1711,
    "gn:feature_class":"P",
    "gn:feature_code":"PPLL",
    "gn:name":"Gharegaun",
    "gn:population":0,
    "gn:timezone":"Asia/Kathmandu",
    "iso:country":"NP",
    "wof:name":"Gharegaun",
    "wof:placetype":"locality"
},
  "geometry": {"coordinates":[88.04403000000001,26.97877],"type":"Point"}
}