{
  "type": "Feature",
  "properties": {
    "gn:admin1_code":"ER",
    "gn:admin2_code":"10.0",
    "gn:admin3_code":"1.0",
    "gn:admin4_code":"10013.0",
    "gn:asciiname":"Thinga",
    "gn:country_code":"NP",
    "gn:dem":1111,
    "gn:feature_class":"P",
    "gn:feature_code":"PPLL",
    "gn:name":"Thinga",
    "gn:population":0,
    "gn:timezone":"Asia/Kathmandu",
    "iso:country":"NP",
    "wof:name":"Thinga",
    "wof:placetype":"locality"
},
  "geometry": {"coordinates":[87.69896999999997,27.44753],"type":"Point"}
}