{
  "type": "Feature",
  "properties": {
    "gn:admin1_code":"CR",
    "gn:admin2_code":"5",
    "gn:admin3_code":"20",
    "gn:admin4_code":"200034",
    "gn:asciiname":"Bhimsendanda",
    "gn:country_code":"NP",
    "gn:dem":378,
    "gn:feature_class":"P",
    "gn:feature_code":"PPLL",
    "gn:name":"Bhimsendanda",
    "gn:population":0,
    "gn:timezone":"Asia/Kathmandu",
    "iso:country":"NP",
    "wof:name":"Bhimsendanda",
    "wof:placetype":"locality"
},
  "geometry": {"coordinates":[85.76031,27.26427],"type":"Point"}
}