{
  "type": "Feature",
  "properties": {
    "gn:admin1_code":"MR",
    "gn:admin2_code":"12",
    "gn:admin3_code":"55",
    "gn:admin4_code":"550042",
    "gn:asciiname":"Kalimati",
    "gn:country_code":"NP",
    "gn:dem":1281,
    "gn:feature_class":"P",
    "gn:feature_code":"PPLL",
    "gn:name":"Kalimati",
    "gn:population":0,
    "gn:timezone":"Asia/Kathmandu",
    "iso:country":"NP",
    "wof:name":"Kalimati",
    "wof:placetype":"locality"
},
  "geometry": {"coordinates":[82.18630999999998,28.43833],"type":"Point"}
}