{
  "type": "Feature",
  "properties": {
    "gn:admin1_code":"ER",
    "gn:admin2_code":"7",
    "gn:admin3_code":"10.0",
    "gn:admin4_code":"100044.0",
    "gn:asciiname":"Roktawa",
    "gn:country_code":"NP",
    "gn:dem":1714,
    "gn:feature_class":"P",
    "gn:feature_code":"PPLL",
    "gn:name":"Roktawa",
    "gn:population":0,
    "gn:timezone":"Asia/Kathmandu",
    "iso:country":"NP",
    "wof:name":"Roktawa",
    "wof:placetype":"locality"
},
  "geometry": {"coordinates":[86.95759,27.10762],"type":"Point"}
}