{
  "type": "Feature",
  "properties": {
    "gn:admin1_code":"MR",
    "gn:admin2_code":"12",
    "gn:admin3_code":"56.0",
    "gn:admin4_code":"560040.0",
    "gn:asciiname":"Dandakuti",
    "gn:country_code":"NP",
    "gn:dem":834,
    "gn:feature_class":"P",
    "gn:feature_code":"PPLL",
    "gn:name":"Dandakuti",
    "gn:population":0,
    "gn:timezone":"Asia/Kathmandu",
    "iso:country":"NP",
    "wof:name":"Dandakuti",
    "wof:placetype":"locality"
},
  "geometry": {"coordinates":[82.30551,28.17616],"type":"Point"}
}