{
  "type": "Feature",
  "properties": {
    "gn:admin1_code":"CR",
    "gn:admin2_code":"1",
    "gn:admin3_code":"24.0",
    "gn:admin4_code":"240077.0",
    "gn:asciiname":"Godamchaur",
    "gn:country_code":"NP",
    "gn:dem":1866,
    "gn:feature_class":"P",
    "gn:feature_code":"PPLL",
    "gn:name":"Godamchaur",
    "gn:population":0,
    "gn:timezone":"Asia/Kathmandu",
    "iso:country":"NP",
    "name:bih_x_preferred":[
        "\u0917\u094b\u0926\u093e\u092e\u091a\u094c\u0930"
    ],
    "name:ceb_x_preferred":[
        "Godamchaur"
    ],
    "name:msa_x_preferred":[
        "Godamchaur"
    ],
    "name:nep_x_preferred":[
        "\u0917\u094b\u0926\u093e\u092e\u091a\u094c\u0930"
    ],
    "name:new_x_preferred":[
        "\u0917\u094b\u0926\u093e\u092e\u091a\u094c\u0930"
    ],
    "name:pol_x_preferred":[
        "Godamchaur"
    ],
    "wof:name":"Godamchaur",
    "wof:placetype":"locality"
},
  "geometry": {"coordinates":[85.80554000000002,27.61956],"type":"Point"}
}