{
  "type": "Feature",
  "properties": {
    "gn:admin1_code":"FR",
    "gn:admin2_code":"14.0",
    "gn:admin3_code":"67.0",
    "gn:admin4_code":"670006.0",
    "gn:asciiname":"Tanpra",
    "gn:country_code":"NP",
    "gn:dem":1139,
    "gn:feature_class":"P",
    "gn:feature_code":"PPLL",
    "gn:name":"Tanpra",
    "gn:population":0,
    "gn:timezone":"Asia/Kathmandu",
    "iso:country":"NP",
    "wof:name":"Tanpra",
    "wof:placetype":"locality"
},
  "geometry": {"coordinates":[81.3656,29.38987],"type":"Point"}
}