{
  "type": "Feature",
  "properties": {
    "gn:admin1_code":"CR",
    "gn:admin2_code":"1",
    "gn:admin3_code":"28",
    "gn:admin4_code":"280060",
    "gn:asciiname":"Gharti Rumta",
    "gn:country_code":"NP",
    "gn:dem":887,
    "gn:feature_class":"P",
    "gn:feature_code":"PPLL",
    "gn:name":"Gharti Rumta",
    "gn:population":0,
    "gn:timezone":"Asia/Kathmandu",
    "iso:country":"NP",
    "wof:name":"Gharti Rumta",
    "wof:placetype":"locality"
},
  "geometry": {"coordinates":[85.34737,27.91782000000001],"type":"Point"}
}