{
  "type": "Feature",
  "properties": {
    "gn:admin1_code":"FR",
    "gn:admin2_code":"14",
    "gn:admin3_code":"71.0",
    "gn:admin4_code":"710043.0",
    "gn:asciiname":"Bhainsasur",
    "gn:country_code":"NP",
    "gn:dem":177,
    "gn:feature_class":"P",
    "gn:feature_code":"PPLL",
    "gn:name":"Bhainsasur",
    "gn:population":0,
    "gn:timezone":"Asia/Kathmandu",
    "iso:country":"NP",
    "wof:name":"Bhainsasur",
    "wof:placetype":"locality"
},
  "geometry": {"coordinates":[80.82625999999998,28.70256],"type":"Point"}
}