{
  "type": "Feature",
  "properties": {
    "gn:admin1_code":"ER",
    "gn:admin2_code":"13",
    "gn:admin3_code":"13",
    "gn:admin4_code":"130066",
    "gn:asciiname":"Salle",
    "gn:country_code":"NP",
    "gn:dem":893,
    "gn:feature_class":"P",
    "gn:feature_code":"PPLL",
    "gn:name":"Salle",
    "gn:population":0,
    "gn:timezone":"Asia/Kathmandu",
    "iso:country":"NP",
    "wof:name":"Salle",
    "wof:placetype":"locality"
},
  "geometry": {"coordinates":[86.62182,27.22903],"type":"Point"}
}