{
  "type": "Feature",
  "properties": {
    "gn:admin1_code":"ER",
    "gn:admin2_code":"7",
    "gn:admin3_code":"6",
    "gn:admin4_code":"60003",
    "gn:asciiname":"Bahuntol",
    "gn:country_code":"NP",
    "gn:dem":72,
    "gn:feature_class":"P",
    "gn:feature_code":"PPLL",
    "gn:name":"Bahuntol",
    "gn:population":0,
    "gn:timezone":"Asia/Kathmandu",
    "iso:country":"NP",
    "wof:name":"Bahuntol",
    "wof:placetype":"locality"
},
  "geometry": {"coordinates":[87.19976,26.45743],"type":"Point"}
}