{
  "type": "Feature",
  "properties": {
    "gn:admin1_code":"MR",
    "gn:admin2_code":"6",
    "gn:admin3_code":"63.0",
    "gn:admin4_code":"630013.0",
    "gn:asciiname":"Nundina",
    "gn:country_code":"NP",
    "gn:dem":3618,
    "gn:feature_class":"P",
    "gn:feature_code":"PPLL",
    "gn:name":"Nundina",
    "gn:population":0,
    "gn:timezone":"Asia/Kathmandu",
    "iso:country":"NP",
    "wof:name":"Nundina",
    "wof:placetype":"locality"
},
  "geometry": {"coordinates":[81.88569,29.27518],"type":"Point"}
}