{
  "type": "Feature",
  "properties": {
    "gn:admin1_code":"ER",
    "gn:admin2_code":"10",
    "gn:admin3_code":"4.0",
    "gn:admin4_code":"40030.0",
    "gn:asciiname":"Nayagaun",
    "gn:country_code":"NP",
    "gn:dem":88,
    "gn:feature_class":"P",
    "gn:feature_code":"PPLL",
    "gn:name":"Nayagaun",
    "gn:population":0,
    "gn:timezone":"Asia/Kathmandu",
    "iso:country":"NP",
    "name:msa_x_preferred":[
        "Nayagaun"
    ],
    "name:nep_x_preferred":[
        "\u0928\u092f\u093e\u0901\u0917\u093e\u0901\u0909"
    ],
    "wof:name":"Nayagaun",
    "wof:placetype":"locality"
},
  "geometry": {"coordinates":[87.65720999999998,26.52432],"type":"Point"}
}