{
  "type": "Feature",
  "properties": {
    "gn:admin1_code":"MR",
    "gn:admin2_code":"2",
    "gn:admin3_code":"60.0",
    "gn:admin4_code":"600040.0",
    "gn:asciiname":"Pauwa",
    "gn:country_code":"NP",
    "gn:dem":1318,
    "gn:feature_class":"P",
    "gn:feature_code":"PPLL",
    "gn:name":"Pauwa",
    "gn:population":0,
    "gn:timezone":"Asia/Kathmandu",
    "iso:country":"NP",
    "wof:name":"Pauwa",
    "wof:placetype":"locality"
},
  "geometry": {"coordinates":[81.61131,28.8742],"type":"Point"}
}