{
  "type": "Feature",
  "properties": {
    "gn:admin1_code":"MR",
    "gn:admin2_code":"2.0",
    "gn:admin3_code":"57.0",
    "gn:admin4_code":"570005.0",
    "gn:asciiname":"Baijapur",
    "gn:country_code":"NP",
    "gn:dem":165,
    "gn:feature_class":"P",
    "gn:feature_code":"PPLL",
    "gn:name":"Baijapur",
    "gn:population":0,
    "gn:timezone":"Asia/Kathmandu",
    "iso:country":"NP",
    "wof:name":"Baijapur",
    "wof:placetype":"locality"
},
  "geometry": {"coordinates":[81.90051,28.02095],"type":"Point"}
}