{
  "type": "Feature",
  "properties": {
    "gn:admin1_code":"CR",
    "gn:admin2_code":"1",
    "gn:admin3_code":"25",
    "gn:admin4_code":"250031",
    "gn:asciiname":"Shrighari",
    "gn:country_code":"NP",
    "gn:dem":1766,
    "gn:feature_class":"P",
    "gn:feature_code":"PPLL",
    "gn:name":"Shrighari",
    "gn:population":0,
    "gn:timezone":"Asia/Kathmandu",
    "iso:country":"NP",
    "wof:name":"Shrighari",
    "wof:placetype":"locality"
},
  "geometry": {"coordinates":[85.26805999999998,27.52819],"type":"Point"}
}