{
  "type": "Feature",
  "properties": {
    "gn:admin1_code":"CR",
    "gn:admin2_code":"5",
    "gn:admin3_code":"20",
    "gn:admin4_code":"200026",
    "gn:asciiname":"Sungure",
    "gn:country_code":"NP",
    "gn:dem":482,
    "gn:feature_class":"P",
    "gn:feature_code":"PPLL",
    "gn:name":"Sungure",
    "gn:population":0,
    "gn:timezone":"Asia/Kathmandu",
    "iso:country":"NP",
    "wof:name":"Sungure",
    "wof:placetype":"locality"
},
  "geometry": {"coordinates":[85.68841999999999,27.28906],"type":"Point"}
}