{
  "type": "Feature",
  "properties": {
    "gn:admin1_code":"FR",
    "gn:admin2_code":"14",
    "gn:admin3_code":"71.0",
    "gn:admin4_code":"710039.0",
    "gn:asciiname":"Syauli bajar",
    "gn:country_code":"NP",
    "gn:dem":208,
    "gn:feature_class":"P",
    "gn:feature_code":"PPLL",
    "gn:name":"Syauli bajar",
    "gn:population":0,
    "gn:timezone":"Asia/Kathmandu",
    "iso:country":"NP",
    "wof:name":"Syauli bajar",
    "wof:placetype":"locality"
},
  "geometry": {"coordinates":[80.62919000000002,28.79614],"type":"Point"}
}