{
  "type": "Feature",
  "properties": {
    "gn:admin1_code":"FR",
    "gn:admin2_code":"9",
    "gn:admin3_code":"75.0",
    "gn:admin4_code":"750034.0",
    "gn:asciiname":"Melibisan",
    "gn:country_code":"NP",
    "gn:dem":1296,
    "gn:feature_class":"P",
    "gn:feature_code":"PPLL",
    "gn:name":"Melibisan",
    "gn:population":0,
    "gn:timezone":"Asia/Kathmandu",
    "iso:country":"NP",
    "wof:name":"Melibisan",
    "wof:placetype":"locality"
},
  "geometry": {"coordinates":[80.68146999999998,29.71829],"type":"Point"}
}