{
  "type": "Feature",
  "properties": {
    "gn:admin1_code":"WR",
    "gn:admin2_code":"4",
    "gn:admin3_code":"37",
    "gn:admin4_code":"370014",
    "gn:asciiname":"Nandeswara",
    "gn:country_code":"NP",
    "gn:dem":947,
    "gn:feature_class":"P",
    "gn:feature_code":"PPLL",
    "gn:name":"Nandeswara",
    "gn:population":0,
    "gn:timezone":"Asia/Kathmandu",
    "iso:country":"NP",
    "wof:name":"Nandeswara",
    "wof:placetype":"locality"
},
  "geometry": {"coordinates":[84.38472,28.29563],"type":"Point"}
}