{
  "type": "Feature",
  "properties": {
    "gn:admin1_code":"ER",
    "gn:admin2_code":"10",
    "gn:admin3_code":"3.0",
    "gn:admin4_code":"30003.0",
    "gn:asciiname":"Melbote",
    "gn:country_code":"NP",
    "gn:dem":1349,
    "gn:feature_class":"P",
    "gn:feature_code":"PPLL",
    "gn:name":"Melbote",
    "gn:population":0,
    "gn:timezone":"Asia/Kathmandu",
    "iso:country":"NP",
    "wof:name":"Melbote",
    "wof:placetype":"locality"
},
  "geometry": {"coordinates":[87.92313,26.93695],"type":"Point"}
}