{
  "type": "Feature",
  "properties": {
    "gn:admin1_code":"WR",
    "gn:admin2_code":"3",
    "gn:admin3_code":"43",
    "gn:admin4_code":"430005",
    "gn:asciiname":"Arje",
    "gn:country_code":"NP",
    "gn:dem":929,
    "gn:feature_class":"P",
    "gn:feature_code":"PPLL",
    "gn:name":"Arje",
    "gn:population":0,
    "gn:timezone":"Asia/Kathmandu",
    "iso:country":"NP",
    "name:ceb_x_preferred":[
        "Arje"
    ],
    "name:mai_x_preferred":[
        "\u0905\u0930\u094d\u091c\u0947"
    ],
    "name:msa_x_preferred":[
        "Arje"
    ],
    "name:nep_x_preferred":[
        "\u0905\u0930\u094d\u091c\u0947"
    ],
    "name:new_x_preferred":[
        "\u0905\u0930\u094d\u091c\u0947"
    ],
    "name:pol_x_preferred":[
        "Arje"
    ],
    "wof:name":"Arje",
    "wof:placetype":"locality"
},
  "geometry": {"coordinates":[83.50091999999999,28.36868],"type":"Point"}
}