{
  "type": "Feature",
  "properties": {
    "gn:admin1_code":"WR",
    "gn:admin2_code":"3",
    "gn:admin3_code":"43",
    "gn:admin4_code":"430005",
    "gn:asciiname":"Arje",
    "gn:country_code":"NP",
    "gn:dem":929,
    "gn:feature_class":"P",
    "gn:feature_code":"PPLL",
    "gn:name":"Arje",
    "gn:population":0,
    "gn:timezone":"Asia/Kathmandu",
    "iso:country":"NP",
    "wof:name":"Arje",
    "wof:placetype":"locality"
},
  "geometry": {"coordinates":[83.50091999999999,28.36868],"type":"Point"}
}