{
  "type": "Feature",
  "properties": {
    "gn:admin1_code":"CR",
    "gn:admin2_code":"11",
    "gn:admin3_code":"31",
    "gn:admin4_code":"310014",
    "gn:asciiname":"Thorpakhaharegaun",
    "gn:country_code":"NP",
    "gn:dem":454,
    "gn:feature_class":"P",
    "gn:feature_code":"PPLL",
    "gn:name":"Thorpakhaharegaun",
    "gn:population":0,
    "gn:timezone":"Asia/Kathmandu",
    "iso:country":"NP",
    "wof:name":"Thorpakhaharegaun",
    "wof:placetype":"locality"
},
  "geometry": {"coordinates":[85.28126999999998,27.29439],"type":"Point"}
}