{
  "type": "Feature",
  "properties": {
    "gn:admin1_code":"FR",
    "gn:admin2_code":"14",
    "gn:admin3_code":"71.0",
    "gn:admin4_code":"710040.0",
    "gn:asciiname":"Jamunepani",
    "gn:country_code":"NP",
    "gn:dem":795,
    "gn:feature_class":"P",
    "gn:feature_code":"PPLL",
    "gn:name":"Jamunepani",
    "gn:population":0,
    "gn:timezone":"Asia/Kathmandu",
    "iso:country":"NP",
    "wof:name":"Jamunepani",
    "wof:placetype":"locality"
},
  "geometry": {"coordinates":[81.07288,28.81594],"type":"Point"}
}