{
  "type": "Feature",
  "properties": {
    "gn:admin1_code":"ER",
    "gn:admin2_code":"10.0",
    "gn:admin3_code":"1.0",
    "gn:admin4_code":"10015.0",
    "gn:asciiname":"Bagalegaun",
    "gn:country_code":"NP",
    "gn:dem":1264,
    "gn:feature_class":"P",
    "gn:feature_code":"PPLL",
    "gn:name":"Bagalegaun",
    "gn:population":0,
    "gn:timezone":"Asia/Kathmandu",
    "iso:country":"NP",
    "wof:name":"Bagalegaun",
    "wof:placetype":"locality"
},
  "geometry": {"coordinates":[87.63691,27.39682],"type":"Point"}
}