{
  "type": "Feature",
  "properties": {
    "gn:admin1_code":"MR",
    "gn:admin2_code":"12",
    "gn:admin3_code":"52",
    "gn:admin4_code":"520049",
    "gn:asciiname":"Bange",
    "gn:country_code":"NP",
    "gn:dem":1417,
    "gn:feature_class":"P",
    "gn:feature_code":"PPLL",
    "gn:name":"Bange",
    "gn:population":0,
    "gn:timezone":"Asia/Kathmandu",
    "iso:country":"NP",
    "wof:name":"Bange",
    "wof:placetype":"locality"
},
  "geometry": {"coordinates":[82.99839,28.11177],"type":"Point"}
}