{
  "type": "Feature",
  "properties": {
    "gn:admin1_code":"CR",
    "gn:admin2_code":"1",
    "gn:admin3_code":"30.0",
    "gn:admin4_code":"300034.0",
    "gn:asciiname":"Bhandarithok",
    "gn:country_code":"NP",
    "gn:dem":1034,
    "gn:feature_class":"P",
    "gn:feature_code":"PPLL",
    "gn:name":"Bhandarithok",
    "gn:population":0,
    "gn:timezone":"Asia/Kathmandu",
    "iso:country":"NP",
    "wof:name":"Bhandarithok",
    "wof:placetype":"locality"
},
  "geometry": {"coordinates":[85.17108,27.71567000000001],"type":"Point"}
}