{
  "type": "Feature",
  "properties": {
    "gn:admin1_code":"CR",
    "gn:admin2_code":"11",
    "gn:admin3_code":"31",
    "gn:admin4_code":"310011",
    "gn:asciiname":"Panesh",
    "gn:country_code":"NP",
    "gn:dem":568,
    "gn:feature_class":"P",
    "gn:feature_code":"PPLL",
    "gn:name":"Panesh",
    "gn:population":0,
    "gn:timezone":"Asia/Kathmandu",
    "iso:country":"NP",
    "wof:name":"Panesh",
    "wof:placetype":"locality"
},
  "geometry": {"coordinates":[85.04438,27.37606],"type":"Point"}
}