{
  "type": "Feature",
  "properties": {
    "gn:admin1_code":"FR",
    "gn:admin2_code":"14.0",
    "gn:admin3_code":"69.0",
    "gn:admin4_code":"690044.0",
    "gn:asciiname":"Dogade",
    "gn:country_code":"NP",
    "gn:dem":812,
    "gn:feature_class":"P",
    "gn:feature_code":"PPLL",
    "gn:name":"Dogade",
    "gn:population":0,
    "gn:timezone":"Asia/Kathmandu",
    "iso:country":"NP",
    "wof:name":"Dogade",
    "wof:placetype":"locality"
},
  "geometry": {"coordinates":[81.44355999999998,29.08388],"type":"Point"}
}