{
  "type": "Feature",
  "properties": {
    "gn:admin1_code":"CR",
    "gn:admin2_code":"5",
    "gn:admin3_code":"19",
    "gn:admin4_code":"190077.0",
    "gn:asciiname":"Jalkeni",
    "gn:country_code":"NP",
    "gn:dem":371,
    "gn:feature_class":"P",
    "gn:feature_code":"PPLL",
    "gn:name":"Jalkeni",
    "gn:population":0,
    "gn:timezone":"Asia/Kathmandu",
    "iso:country":"NP",
    "wof:name":"Jalkeni",
    "wof:placetype":"locality"
},
  "geometry": {"coordinates":[85.64776999999999,27.12524],"type":"Point"}
}