{
  "type": "Feature",
  "properties": {
    "gn:admin1_code":"CR",
    "gn:admin2_code":"11.0",
    "gn:admin3_code":"33.0",
    "gn:admin4_code":"330005.0",
    "gn:asciiname":"Babuain",
    "gn:country_code":"NP",
    "gn:dem":94,
    "gn:feature_class":"P",
    "gn:feature_code":"PPLL",
    "gn:name":"Babuain",
    "gn:population":0,
    "gn:timezone":"Asia/Kathmandu",
    "iso:country":"NP",
    "name:ceb_x_preferred":[
        "Babuain"
    ],
    "name:msa_x_preferred":[
        "Babuain"
    ],
    "name:new_x_preferred":[
        "\u092c\u092c\u0941\u0906\u0907\u0902"
    ],
    "name:pol_x_preferred":[
        "Babuain"
    ],
    "wof:name":"Babuain",
    "wof:placetype":"locality"
},
  "geometry": {"coordinates":[85.07427,26.98519000000001],"type":"Point"}
}