{
  "type": "Feature",
  "properties": {
    "gn:admin1_code":"MR",
    "gn:admin2_code":"12",
    "gn:admin3_code":"54",
    "gn:admin4_code":"540035",
    "gn:asciiname":"Argawa",
    "gn:country_code":"NP",
    "gn:dem":2473,
    "gn:feature_class":"P",
    "gn:feature_code":"PPLL",
    "gn:name":"Argawa",
    "gn:population":0,
    "gn:timezone":"Asia/Kathmandu",
    "iso:country":"NP",
    "wof:name":"Argawa",
    "wof:placetype":"locality"
},
  "geometry": {"coordinates":[82.88633,28.68448],"type":"Point"}
}