{
  "type": "Feature",
  "properties": {
    "gn:admin1_code":"ER",
    "gn:asciiname":"Chandra Garhi",
    "gn:country_code":"NP",
    "gn:dem":103,
    "gn:feature_class":"P",
    "gn:feature_code":"PPL",
    "gn:name":"Chandra Garhi",
    "gn:population":0,
    "gn:timezone":"Asia/Kathmandu",
    "iso:country":"NP",
    "name:und_x_variant":[
        "Chandragadhi",
        "Chandra Garhi"
    ],
    "wof:name":"Chandra Garhi",
    "wof:placetype":"locality"
},
  "geometry": {"coordinates":[88.06,26.585],"type":"Point"}
}