{
  "type": "Feature",
  "properties": {
    "gn:admin1_code":"WR",
    "gn:admin2_code":"4",
    "gn:admin3_code":"40.0",
    "gn:admin4_code":"400044.0",
    "gn:asciiname":"Phalyankot",
    "gn:country_code":"NP",
    "gn:dem":911,
    "gn:feature_class":"P",
    "gn:feature_code":"PPLL",
    "gn:name":"Phalyankot",
    "gn:population":0,
    "gn:timezone":"Asia/Kathmandu",
    "iso:country":"NP",
    "wof:name":"Phalyankot",
    "wof:placetype":"locality"
},
  "geometry": {"coordinates":[84.20941999999999,28.15181],"type":"Point"}
}