{
  "type": "Feature",
  "properties": {
    "gn:admin1_code":"FR",
    "gn:admin2_code":"9",
    "gn:admin3_code":"75.0",
    "gn:admin4_code":"750016.0",
    "gn:asciiname":"Padathi",
    "gn:country_code":"NP",
    "gn:dem":1705,
    "gn:feature_class":"P",
    "gn:feature_code":"PPLL",
    "gn:name":"Padathi",
    "gn:population":0,
    "gn:timezone":"Asia/Kathmandu",
    "iso:country":"NP",
    "wof:name":"Padathi",
    "wof:placetype":"locality"
},
  "geometry": {"coordinates":[80.83386999999998,29.73097000000001],"type":"Point"}
}