{
  "type": "Feature",
  "properties": {
    "gn:admin1_code":"FR",
    "gn:admin2_code":"14",
    "gn:admin3_code":"71.0",
    "gn:admin4_code":"710020.0",
    "gn:asciiname":"Jagati",
    "gn:country_code":"NP",
    "gn:dem":412,
    "gn:feature_class":"P",
    "gn:feature_code":"PPLL",
    "gn:name":"Jagati",
    "gn:population":0,
    "gn:timezone":"Asia/Kathmandu",
    "iso:country":"NP",
    "name:eus_x_preferred":[
        "Jagati"
    ],
    "wof:name":"Jagati",
    "wof:placetype":"locality"
},
  "geometry": {"coordinates":[80.67527,28.88842],"type":"Point"}
}