{
  "type": "Feature",
  "properties": {
    "gn:admin1_code":"CR",
    "gn:admin2_code":"5",
    "gn:admin3_code":"20",
    "gn:admin4_code":"200021",
    "gn:asciiname":"Mainapur",
    "gn:country_code":"NP",
    "gn:dem":662,
    "gn:feature_class":"P",
    "gn:feature_code":"PPLL",
    "gn:name":"Mainapur",
    "gn:population":0,
    "gn:timezone":"Asia/Kathmandu",
    "iso:country":"NP",
    "wof:name":"Mainapur",
    "wof:placetype":"locality"
},
  "geometry": {"coordinates":[85.87872,27.40259],"type":"Point"}
}