{
  "type": "Feature",
  "properties": {
    "gn:admin1_code":"CR",
    "gn:admin2_code":"5",
    "gn:admin3_code":"20",
    "gn:admin4_code":"200003",
    "gn:asciiname":"Kholagaun",
    "gn:country_code":"NP",
    "gn:dem":1611,
    "gn:feature_class":"P",
    "gn:feature_code":"PPLL",
    "gn:name":"Kholagaun",
    "gn:population":0,
    "gn:timezone":"Asia/Kathmandu",
    "iso:country":"NP",
    "name:fra_x_preferred":[
        "Kholagaun"
    ],
    "name:new_x_preferred":[
        "\u0916\u094b\u0932\u093e\u0917\u093e\u0909\u0902 \u0968"
    ],
    "name:pol_x_preferred":[
        "Kholagaun"
    ],
    "wof:name":"Kholagaun",
    "wof:placetype":"locality"
},
  "geometry": {"coordinates":[86.23101,27.15276],"type":"Point"}
}