{
  "type": "Feature",
  "properties": {
    "gn:admin1_code":"CR",
    "gn:admin2_code":"5",
    "gn:admin3_code":"22.0",
    "gn:admin4_code":"220024.0",
    "gn:asciiname":"Dharapanigaun",
    "gn:country_code":"NP",
    "gn:dem":1970,
    "gn:feature_class":"P",
    "gn:feature_code":"PPLL",
    "gn:name":"Dharapanigaun",
    "gn:population":0,
    "gn:timezone":"Asia/Kathmandu",
    "iso:country":"NP",
    "wof:name":"Dharapanigaun",
    "wof:placetype":"locality"
},
  "geometry": {"coordinates":[86.19705999999999,27.62421],"type":"Point"}
}