{
  "type": "Feature",
  "properties": {
    "gn:admin1_code":"MR",
    "gn:admin2_code":"12",
    "gn:admin3_code":"55",
    "gn:admin4_code":"550029",
    "gn:asciiname":"Chhipchhipe",
    "gn:country_code":"NP",
    "gn:dem":947,
    "gn:feature_class":"P",
    "gn:feature_code":"PPLL",
    "gn:name":"Chhipchhipe",
    "gn:population":0,
    "gn:timezone":"Asia/Kathmandu",
    "iso:country":"NP",
    "name:ceb_x_preferred":[
        "Chhipchhipe"
    ],
    "name:mai_x_preferred":[
        "\u091b\u093f\u092a\u091b\u093f\u092a\u0947"
    ],
    "name:msa_x_preferred":[
        "Chhipchhipe"
    ],
    "name:nep_x_preferred":[
        "\u091b\u093f\u092a\u091b\u093f\u092a\u0947"
    ],
    "name:new_x_preferred":[
        "\u091b\u093f\u092a\u091b\u093f\u092a\u0947"
    ],
    "name:pol_x_preferred":[
        "Chhipchhipe"
    ],
    "wof:name":"Chhipchhipe",
    "wof:placetype":"locality"
},
  "geometry": {"coordinates":[82.14379,28.29069],"type":"Point"}
}