{
  "type": "Feature",
  "properties": {
    "gn:admin1_code":"ER",
    "gn:admin2_code":"13",
    "gn:admin3_code":"12",
    "gn:admin4_code":"120008",
    "gn:asciiname":"Kilkhurading",
    "gn:country_code":"NP",
    "gn:dem":2706,
    "gn:feature_class":"P",
    "gn:feature_code":"PPLL",
    "gn:name":"Kilkhurading",
    "gn:population":0,
    "gn:timezone":"Asia/Kathmandu",
    "iso:country":"NP",
    "wof:name":"Kilkhurading",
    "wof:placetype":"locality"
},
  "geometry": {"coordinates":[86.3824,27.47364],"type":"Point"}
}