{
  "type": "Feature",
  "properties": {
    "gn:admin1_code":"ER",
    "gn:admin2_code":"7",
    "gn:admin3_code":"7.0",
    "gn:admin4_code":"70019.0",
    "gn:asciiname":"Guranse",
    "gn:country_code":"NP",
    "gn:dem":2223,
    "gn:feature_class":"P",
    "gn:feature_code":"PPLL",
    "gn:name":"Guranse",
    "gn:population":0,
    "gn:timezone":"Asia/Kathmandu",
    "iso:country":"NP",
    "wof:name":"Guranse",
    "wof:placetype":"locality"
},
  "geometry": {"coordinates":[87.34891999999998,27.04583],"type":"Point"}
}