{
  "type": "Feature",
  "properties": {
    "gn:admin1_code":"FR",
    "gn:admin2_code":"14.0",
    "gn:admin3_code":"69.0",
    "gn:admin4_code":"690051.0",
    "gn:asciiname":"Dhurgaun",
    "gn:country_code":"NP",
    "gn:dem":1122,
    "gn:feature_class":"P",
    "gn:feature_code":"PPLL",
    "gn:name":"Dhurgaun",
    "gn:population":0,
    "gn:timezone":"Asia/Kathmandu",
    "iso:country":"NP",
    "wof:name":"Dhurgaun",
    "wof:placetype":"locality"
},
  "geometry": {"coordinates":[81.31604,28.94579],"type":"Point"}
}