{
  "type": "Feature",
  "properties": {
    "gn:admin1_code":"CR",
    "gn:admin2_code":"5",
    "gn:admin3_code":"20",
    "gn:admin4_code":"200005",
    "gn:asciiname":"Jhagarpur",
    "gn:country_code":"NP",
    "gn:dem":916,
    "gn:feature_class":"P",
    "gn:feature_code":"PPLL",
    "gn:name":"Jhagarpur",
    "gn:population":0,
    "gn:timezone":"Asia/Kathmandu",
    "iso:country":"NP",
    "wof:name":"Jhagarpur",
    "wof:placetype":"locality"
},
  "geometry": {"coordinates":[86.0475,27.27468],"type":"Point"}
}