{
  "type": "Feature",
  "properties": {
    "gn:admin1_code":"CR",
    "gn:admin2_code":"1",
    "gn:admin3_code":"25",
    "gn:admin4_code":"250017",
    "gn:asciiname":"Syal Bhanjyang",
    "gn:country_code":"NP",
    "gn:dem":978,
    "gn:feature_class":"P",
    "gn:feature_code":"PPLL",
    "gn:name":"Syal Bhanjyang",
    "gn:population":0,
    "gn:timezone":"Asia/Kathmandu",
    "iso:country":"NP",
    "wof:name":"Syal Bhanjyang",
    "wof:placetype":"locality"
},
  "geometry": {"coordinates":[85.36421999999997,27.44018],"type":"Point"}
}