{
  "type": "Feature",
  "properties": {
    "gn:admin1_code":"MR",
    "gn:admin2_code":"6",
    "gn:admin3_code":"62.0",
    "gn:admin4_code":"620020.0",
    "gn:asciiname":"Okta",
    "gn:country_code":"NP",
    "gn:dem":2553,
    "gn:feature_class":"P",
    "gn:feature_code":"PPLL",
    "gn:name":"Okta",
    "gn:population":0,
    "gn:timezone":"Asia/Kathmandu",
    "iso:country":"NP",
    "name:fas_x_preferred":[
        "\u0627\u06a9\u062a\u0627"
    ],
    "name:fra_x_preferred":[
        "Octa"
    ],
    "name:ita_x_preferred":[
        "Okta"
    ],
    "name:spa_x_preferred":[
        "Octa"
    ],
    "wof:name":"Okta",
    "wof:placetype":"locality"
},
  "geometry": {"coordinates":[82.48029,29.08039],"type":"Point"}
}