{
  "type": "Feature",
  "properties": {
    "gn:admin1_code":"ER",
    "gn:admin2_code":"13",
    "gn:admin3_code":"13.0",
    "gn:admin4_code":"130011.0",
    "gn:asciiname":"Batase",
    "gn:country_code":"NP",
    "gn:dem":1066,
    "gn:feature_class":"P",
    "gn:feature_code":"PPLL",
    "gn:name":"Batase",
    "gn:population":0,
    "gn:timezone":"Asia/Kathmandu",
    "iso:country":"NP",
    "wof:name":"Batase",
    "wof:placetype":"locality"
},
  "geometry": {"coordinates":[86.7452,27.08727],"type":"Point"}
}