{
  "type": "Feature",
  "properties": {
    "gn:admin1_code":"CR",
    "gn:admin2_code":"11.0",
    "gn:admin3_code":"33.0",
    "gn:admin4_code":"330052.0",
    "gn:asciiname":"Rampur",
    "gn:country_code":"NP",
    "gn:dem":97,
    "gn:feature_class":"P",
    "gn:feature_code":"PPLL",
    "gn:name":"Rampur",
    "gn:population":0,
    "gn:timezone":"Asia/Kathmandu",
    "iso:country":"NP",
    "wof:name":"Rampur",
    "wof:placetype":"locality"
},
  "geometry": {"coordinates":[85.02195,27.03015],"type":"Point"}
}