{
  "type": "Feature",
  "properties": {
    "gn:admin1_code":"WR",
    "gn:admin2_code":"4.0",
    "gn:admin3_code":"38.0",
    "gn:admin4_code":"380038.0",
    "gn:asciiname":"Naya Risin",
    "gn:country_code":"NP",
    "gn:dem":1099,
    "gn:feature_class":"P",
    "gn:feature_code":"PPLL",
    "gn:name":"Naya Risin",
    "gn:population":0,
    "gn:timezone":"Asia/Kathmandu",
    "iso:country":"NP",
    "wof:name":"Naya Risin",
    "wof:placetype":"locality"
},
  "geometry": {"coordinates":[84.16086,27.92719],"type":"Point"}
}