{
  "type": "Feature",
  "properties": {
    "gn:admin1_code":"ER",
    "gn:admin2_code":"10",
    "gn:admin3_code":"2",
    "gn:admin4_code":"20032",
    "gn:asciiname":"Thumselin",
    "gn:country_code":"NP",
    "gn:dem":1240,
    "gn:feature_class":"P",
    "gn:feature_code":"PPLL",
    "gn:name":"Thumselin",
    "gn:population":0,
    "gn:timezone":"Asia/Kathmandu",
    "iso:country":"NP",
    "wof:name":"Thumselin",
    "wof:placetype":"locality"
},
  "geometry": {"coordinates":[87.65004999999999,27.10185],"type":"Point"}
}