{
  "type": "Feature",
  "properties": {
    "gn:admin1_code":"CR",
    "gn:admin2_code":"1.0",
    "gn:admin3_code":"26.0",
    "gn:admin4_code":"260009.0",
    "gn:asciiname":"Khadkagaun",
    "gn:country_code":"NP",
    "gn:dem":1465,
    "gn:feature_class":"P",
    "gn:feature_code":"PPLL",
    "gn:name":"Khadkagaun",
    "gn:population":0,
    "gn:timezone":"Asia/Kathmandu",
    "iso:country":"NP",
    "wof:name":"Khadkagaun",
    "wof:placetype":"locality"
},
  "geometry": {"coordinates":[85.41949,27.63688],"type":"Point"}
}