{
  "type": "Feature",
  "properties": {
    "gn:admin1_code":"CR",
    "gn:admin2_code":"5",
    "gn:admin3_code":"22.0",
    "gn:admin4_code":"220034.0",
    "gn:asciiname":"Patagaun",
    "gn:country_code":"NP",
    "gn:dem":1320,
    "gn:feature_class":"P",
    "gn:feature_code":"PPLL",
    "gn:name":"Patagaun",
    "gn:population":0,
    "gn:timezone":"Asia/Kathmandu",
    "iso:country":"NP",
    "wof:name":"Patagaun",
    "wof:placetype":"locality"
},
  "geometry": {"coordinates":[86.11843,27.72356],"type":"Point"}
}