{
  "type": "Feature",
  "properties": {
    "gn:admin1_code":"WR",
    "gn:admin2_code":"4",
    "gn:admin3_code":"37",
    "gn:admin4_code":"370021",
    "gn:asciiname":"Saran Chok",
    "gn:country_code":"NP",
    "gn:dem":1102,
    "gn:feature_class":"P",
    "gn:feature_code":"PPLL",
    "gn:name":"Saran Chok",
    "gn:population":0,
    "gn:timezone":"Asia/Kathmandu",
    "iso:country":"NP",
    "wof:name":"Saran Chok",
    "wof:placetype":"locality"
},
  "geometry": {"coordinates":[84.46025,28.22003],"type":"Point"}
}