{
  "type": "Feature",
  "properties": {
    "gn:admin1_code":"WR",
    "gn:admin2_code":"8",
    "gn:admin3_code":"47",
    "gn:admin4_code":"470025",
    "gn:asciiname":"Bardaliya",
    "gn:country_code":"NP",
    "gn:dem":389,
    "gn:feature_class":"P",
    "gn:feature_code":"PPLL",
    "gn:name":"Bardaliya",
    "gn:population":0,
    "gn:timezone":"Asia/Kathmandu",
    "iso:country":"NP",
    "wof:name":"Bardaliya",
    "wof:placetype":"locality"
},
  "geometry": {"coordinates":[83.78609,27.88425],"type":"Point"}
}