{
  "type": "Feature",
  "properties": {
    "gn:admin1_code":"WR",
    "gn:admin2_code":"4.0",
    "gn:admin3_code":"38.0",
    "gn:admin4_code":"380023.0",
    "gn:asciiname":"Golla",
    "gn:country_code":"NP",
    "gn:dem":544,
    "gn:feature_class":"P",
    "gn:feature_code":"PPLL",
    "gn:name":"Golla",
    "gn:population":0,
    "gn:timezone":"Asia/Kathmandu",
    "iso:country":"NP",
    "name:ceb_x_preferred":[
        "Golla"
    ],
    "name:deu_x_preferred":[
        "Golla"
    ],
    "wof:name":"Golla",
    "wof:placetype":"locality"
},
  "geometry": {"coordinates":[84.31689,27.98574],"type":"Point"}
}