{
  "type": "Feature",
  "properties": {
    "gn:admin1_code":"MR",
    "gn:admin2_code":"2",
    "gn:admin3_code":"60.0",
    "gn:admin4_code":"600026.0",
    "gn:asciiname":"Bhabra",
    "gn:country_code":"NP",
    "gn:dem":1620,
    "gn:feature_class":"P",
    "gn:feature_code":"PPLL",
    "gn:name":"Bhabra",
    "gn:population":0,
    "gn:timezone":"Asia/Kathmandu",
    "iso:country":"NP",
    "wof:name":"Bhabra",
    "wof:placetype":"locality"
},
  "geometry": {"coordinates":[81.7186,28.91932000000001],"type":"Point"}
}