{
  "type": "Feature",
  "properties": {
    "gn:admin1_code":"MR",
    "gn:admin2_code":"6",
    "gn:admin3_code":"63.0",
    "gn:admin4_code":"630019.0",
    "gn:asciiname":"Kot",
    "gn:country_code":"NP",
    "gn:dem":2485,
    "gn:feature_class":"P",
    "gn:feature_code":"PPLL",
    "gn:name":"Kot",
    "gn:population":0,
    "gn:timezone":"Asia/Kathmandu",
    "iso:country":"NP",
    "name:pol_x_preferred":[
        "Kot"
    ],
    "wof:name":"Kot",
    "wof:placetype":"locality"
},
  "geometry": {"coordinates":[81.92998,29.22184],"type":"Point"}
}