{
  "type": "Feature",
  "properties": {
    "gn:admin1_code":"WR",
    "gn:admin2_code":"8",
    "gn:admin3_code":"48",
    "gn:admin4_code":"480022",
    "gn:asciiname":"Bisunpura",
    "gn:country_code":"NP",
    "gn:dem":107,
    "gn:feature_class":"P",
    "gn:feature_code":"PPLL",
    "gn:name":"Bisunpura",
    "gn:population":0,
    "gn:timezone":"Asia/Kathmandu",
    "iso:country":"NP",
    "name:ceb_x_preferred":[
        "Bisunpura"
    ],
    "name:msa_x_preferred":[
        "Bisunpura"
    ],
    "name:nep_x_preferred":[
        "\u092c\u093f\u0938\u0941\u0928\u094d\u092a\u0941\u0930\u093e"
    ],
    "name:new_x_preferred":[
        "\u092c\u093f\u0938\u0941\u0928\u094d\u092a\u0941\u0930\u093e"
    ],
    "name:pol_x_preferred":[
        "Bisunpura"
    ],
    "wof:name":"Bisunpura",
    "wof:placetype":"locality"
},
  "geometry": {"coordinates":[83.65469,27.46857],"type":"Point"}
}