{
  "type": "Feature",
  "properties": {
    "gn:admin1_code":"MR",
    "gn:admin2_code":"2.0",
    "gn:admin3_code":"59.0",
    "gn:admin4_code":"590020.0",
    "gn:asciiname":"Shikaribas",
    "gn:country_code":"NP",
    "gn:dem":1677,
    "gn:feature_class":"P",
    "gn:feature_code":"PPLL",
    "gn:name":"Shikaribas",
    "gn:population":0,
    "gn:timezone":"Asia/Kathmandu",
    "iso:country":"NP",
    "wof:name":"Shikaribas",
    "wof:placetype":"locality"
},
  "geometry": {"coordinates":[81.86429,28.51292],"type":"Point"}
}