{
  "type": "Feature",
  "properties": {
    "gn:admin1_code":"CR",
    "gn:admin2_code":"5",
    "gn:admin3_code":"20",
    "gn:admin4_code":"200020",
    "gn:asciiname":"Dhamidanda",
    "gn:country_code":"NP",
    "gn:dem":981,
    "gn:feature_class":"P",
    "gn:feature_code":"PPLL",
    "gn:name":"Dhamidanda",
    "gn:population":0,
    "gn:timezone":"Asia/Kathmandu",
    "iso:country":"NP",
    "wof:name":"Dhamidanda",
    "wof:placetype":"locality"
},
  "geometry": {"coordinates":[86.11736999999999,27.0776],"type":"Point"}
}