{
  "type": "Feature",
  "properties": {
    "gn:admin1_code":"WR",
    "gn:admin2_code":"4.0",
    "gn:admin3_code":"39.0",
    "gn:admin4_code":"390016.0",
    "gn:asciiname":"Dandakhani",
    "gn:country_code":"NP",
    "gn:dem":953,
    "gn:feature_class":"P",
    "gn:feature_code":"PPLL",
    "gn:name":"Dandakhani",
    "gn:population":0,
    "gn:timezone":"Asia/Kathmandu",
    "iso:country":"NP",
    "wof:name":"Dandakhani",
    "wof:placetype":"locality"
},
  "geometry": {"coordinates":[83.91721,27.93623],"type":"Point"}
}