{
  "type": "Feature",
  "properties": {
    "gn:admin1_code":"CR",
    "gn:admin2_code":"1",
    "gn:admin3_code":"30.0",
    "gn:admin4_code":"300021.0",
    "gn:asciiname":"Arukharka",
    "gn:country_code":"NP",
    "gn:dem":1258,
    "gn:feature_class":"P",
    "gn:feature_code":"PPLL",
    "gn:name":"Arukharka",
    "gn:population":0,
    "gn:timezone":"Asia/Kathmandu",
    "iso:country":"NP",
    "name:ceb_x_preferred":[
        "Arukharka"
    ],
    "name:hin_x_preferred":[
        "\u0906\u0930\u0941\u0916\u0930\u094d\u0915"
    ],
    "name:mai_x_preferred":[
        "\u0906\u0930\u0941\u0916\u0930\u094d\u0915"
    ],
    "name:msa_x_preferred":[
        "Arukharka"
    ],
    "name:nep_x_preferred":[
        "\u0906\u0930\u0941\u0916\u0930\u094d\u0915"
    ],
    "name:new_x_preferred":[
        "\u0906\u0930\u0941\u0916\u0930\u094d\u0915"
    ],
    "name:pol_x_preferred":[
        "Arukharka"
    ],
    "wof:name":"Arukharka",
    "wof:placetype":"locality"
},
  "geometry": {"coordinates":[84.98371999999998,27.96576],"type":"Point"}
}