{
  "type": "Feature",
  "properties": {
    "gn:admin1_code":"WR",
    "gn:admin2_code":"4",
    "gn:admin3_code":"40.0",
    "gn:admin4_code":"400005.0",
    "gn:asciiname":"Chhahara",
    "gn:country_code":"NP",
    "gn:dem":658,
    "gn:feature_class":"P",
    "gn:feature_code":"PPLL",
    "gn:name":"Chhahara",
    "gn:population":0,
    "gn:timezone":"Asia/Kathmandu",
    "iso:country":"NP",
    "name:ceb_x_preferred":[
        "Chhahara"
    ],
    "name:hin_x_preferred":[
        "\u091b\u0939\u0930\u093e"
    ],
    "name:msa_x_preferred":[
        "Chhahara"
    ],
    "name:nep_x_preferred":[
        "\u091b\u0939\u0930\u093e"
    ],
    "name:new_x_preferred":[
        "\u091b\u0939\u0930\u093e"
    ],
    "name:pol_x_preferred":[
        "Chhahara"
    ],
    "wof:name":"Chhahara",
    "wof:placetype":"locality"
},
  "geometry": {"coordinates":[84.02611999999998,28.10796],"type":"Point"}
}