{
  "type": "Feature",
  "properties": {
    "gn:admin1_code":"CR",
    "gn:admin2_code":"11",
    "gn:admin3_code":"32",
    "gn:admin4_code":"320020",
    "gn:asciiname":"Dewahi Pokhariyatol",
    "gn:country_code":"NP",
    "gn:dem":87,
    "gn:feature_class":"P",
    "gn:feature_code":"PPLL",
    "gn:name":"Dewahi Pokhariyatol",
    "gn:population":0,
    "gn:timezone":"Asia/Kathmandu",
    "iso:country":"NP",
    "wof:name":"Dewahi Pokhariyatol",
    "wof:placetype":"locality"
},
  "geometry": {"coordinates":[85.25520999999998,26.9267],"type":"Point"}
}