{
  "type": "Feature",
  "properties": {
    "gn:admin1_code":"ER",
    "gn:admin2_code":"13.0",
    "gn:admin3_code":"14.0",
    "gn:admin4_code":"140044.0",
    "gn:asciiname":"Hadegaun",
    "gn:country_code":"NP",
    "gn:dem":274,
    "gn:feature_class":"P",
    "gn:feature_code":"PPLL",
    "gn:name":"Hadegaun",
    "gn:population":0,
    "gn:timezone":"Asia/Kathmandu",
    "iso:country":"NP",
    "wof:name":"Hadegaun",
    "wof:placetype":"locality"
},
  "geometry": {"coordinates":[86.55398000000002,26.84679],"type":"Point"}
}