{
  "type": "Feature",
  "properties": {
    "gn:admin1_code":"CR",
    "gn:admin2_code":"11",
    "gn:admin3_code":"31",
    "gn:admin4_code":"310001",
    "gn:asciiname":"Jhagaredanda",
    "gn:country_code":"NP",
    "gn:dem":1565,
    "gn:feature_class":"P",
    "gn:feature_code":"PPLL",
    "gn:name":"Jhagaredanda",
    "gn:population":0,
    "gn:timezone":"Asia/Kathmandu",
    "iso:country":"NP",
    "wof:name":"Jhagaredanda",
    "wof:placetype":"locality"
},
  "geometry": {"coordinates":[84.98815,27.68484],"type":"Point"}
}