{
  "type": "Feature",
  "properties": {
    "gn:admin1_code":"ER",
    "gn:admin2_code":"13",
    "gn:admin3_code":"11",
    "gn:admin4_code":"110008",
    "gn:asciiname":"Sirumlagoth",
    "gn:country_code":"NP",
    "gn:dem":1975,
    "gn:feature_class":"P",
    "gn:feature_code":"PPLL",
    "gn:name":"Sirumlagoth",
    "gn:population":0,
    "gn:timezone":"Asia/Kathmandu",
    "iso:country":"NP",
    "wof:name":"Sirumlagoth",
    "wof:placetype":"locality"
},
  "geometry": {"coordinates":[86.89393000000003,27.56141],"type":"Point"}
}