{
  "type": "Feature",
  "properties": {
    "gn:admin1_code":"ER",
    "gn:admin2_code":"13",
    "gn:admin3_code":"16",
    "gn:admin4_code":"160063",
    "gn:asciiname":"Singrahi",
    "gn:country_code":"NP",
    "gn:dem":116,
    "gn:feature_class":"P",
    "gn:feature_code":"PPLL",
    "gn:name":"Singrahi",
    "gn:population":0,
    "gn:timezone":"Asia/Kathmandu",
    "iso:country":"NP",
    "wof:name":"Singrahi",
    "wof:placetype":"locality"
},
  "geometry": {"coordinates":[86.48509,26.70587],"type":"Point"}
}