{
  "type": "Feature",
  "properties": {
    "gn:admin1_code":"WR",
    "gn:admin2_code":"3",
    "gn:admin3_code":"43",
    "gn:admin4_code":"430016.0",
    "gn:asciiname":"Sabandre",
    "gn:country_code":"NP",
    "gn:dem":1741,
    "gn:feature_class":"P",
    "gn:feature_code":"PPLL",
    "gn:name":"Sabandre",
    "gn:population":0,
    "gn:timezone":"Asia/Kathmandu",
    "iso:country":"NP",
    "wof:name":"Sabandre",
    "wof:placetype":"locality"
},
  "geometry": {"coordinates":[83.60858,28.41825],"type":"Point"}
}