{
  "type": "Feature",
  "properties": {
    "gn:admin1_code":"MR",
    "gn:admin2_code":"12",
    "gn:admin3_code":"55",
    "gn:admin4_code":"550047",
    "gn:asciiname":"Siyala",
    "gn:country_code":"NP",
    "gn:dem":1087,
    "gn:feature_class":"P",
    "gn:feature_code":"PPLL",
    "gn:name":"Siyala",
    "gn:population":0,
    "gn:timezone":"Asia/Kathmandu",
    "iso:country":"NP",
    "wof:name":"Siyala",
    "wof:placetype":"locality"
},
  "geometry": {"coordinates":[82.28759000000002,28.3043],"type":"Point"}
}