{
  "type": "Feature",
  "properties": {
    "gn:admin1_code":"ER",
    "gn:admin2_code":"13",
    "gn:admin3_code":"12",
    "gn:admin4_code":"120016",
    "gn:asciiname":"Masar",
    "gn:country_code":"NP",
    "gn:dem":969,
    "gn:feature_class":"P",
    "gn:feature_code":"PPLL",
    "gn:name":"Masar",
    "gn:population":0,
    "gn:timezone":"Asia/Kathmandu",
    "iso:country":"NP",
    "wof:name":"Masar",
    "wof:placetype":"locality"
},
  "geometry": {"coordinates":[86.41303000000001,27.33126],"type":"Point"}
}