{
  "type": "Feature",
  "properties": {
    "gn:admin1_code":"FR",
    "gn:admin2_code":"14.0",
    "gn:admin3_code":"67.0",
    "gn:admin4_code":"670017.0",
    "gn:asciiname":"Sarketola",
    "gn:country_code":"NP",
    "gn:dem":2008,
    "gn:feature_class":"P",
    "gn:feature_code":"PPLL",
    "gn:name":"Sarketola",
    "gn:population":0,
    "gn:timezone":"Asia/Kathmandu",
    "iso:country":"NP",
    "wof:name":"Sarketola",
    "wof:placetype":"locality"
},
  "geometry": {"coordinates":[81.38294,29.3575],"type":"Point"}
}