{
  "type": "Feature",
  "properties": {
    "gn:admin1_code":"MR",
    "gn:admin2_code":"12",
    "gn:admin3_code":"56.0",
    "gn:admin4_code":"560019.0",
    "gn:asciiname":"Bagdhadi",
    "gn:country_code":"NP",
    "gn:dem":290,
    "gn:feature_class":"P",
    "gn:feature_code":"PPLL",
    "gn:name":"Bagdhadi",
    "gn:population":0,
    "gn:timezone":"Asia/Kathmandu",
    "iso:country":"NP",
    "wof:name":"Bagdhadi",
    "wof:placetype":"locality"
},
  "geometry": {"coordinates":[82.70208000000002,27.85107],"type":"Point"}
}