{
  "type": "Feature",
  "properties": {
    "gn:admin1_code":"00",
    "gn:asciiname":"Auraha",
    "gn:country_code":"NP",
    "gn:dem":81,
    "gn:feature_class":"P",
    "gn:feature_code":"PPL",
    "gn:name":"Aurah\u0101",
    "gn:population":0,
    "gn:timezone":"Asia/Kathmandu",
    "iso:country":"NP",
    "name:nep_x_preferred":[
        "Aurah\u0101"
    ],
    "name:nep_x_variant":[
        "Shri\u0307\u0304pur"
    ],
    "wof:name":"Auraha",
    "wof:placetype":"locality"
},
  "geometry": {"coordinates":[86.24235,26.65222],"type":"Point"}
}