{
  "type": "Feature",
  "properties": {
    "gn:admin1_code":"ER",
    "gn:admin2_code":"7",
    "gn:admin3_code":"5",
    "gn:admin4_code":"50005",
    "gn:asciiname":"Matikhuwa",
    "gn:country_code":"NP",
    "gn:dem":100,
    "gn:feature_class":"P",
    "gn:feature_code":"PPLL",
    "gn:name":"Matikhuwa",
    "gn:population":0,
    "gn:timezone":"Asia/Kathmandu",
    "iso:country":"NP",
    "wof:name":"Matikhuwa",
    "wof:placetype":"locality"
},
  "geometry": {"coordinates":[87.46961,26.58496],"type":"Point"}
}