{
  "type": "Feature",
  "properties": {
    "gn:admin1_code":"FR",
    "gn:admin2_code":"9",
    "gn:admin3_code":"75.0",
    "gn:admin4_code":"750016.0",
    "gn:asciiname":"Jude",
    "gn:country_code":"NP",
    "gn:dem":1581,
    "gn:feature_class":"P",
    "gn:feature_code":"PPLL",
    "gn:name":"Jude",
    "gn:population":0,
    "gn:timezone":"Asia/Kathmandu",
    "iso:country":"NP",
    "name:bar_x_preferred":[
        "Jude"
    ],
    "name:deu_x_preferred":[
        "Jude"
    ],
    "name:fra_x_preferred":[
        "Jude"
    ],
    "name:glg_x_preferred":[
        "Jude"
    ],
    "name:heb_x_preferred":[
        "\u05d2'\u05d5\u05d3"
    ],
    "name:jpn_x_preferred":[
        "Jude"
    ],
    "name:kat_x_preferred":[
        "\u10d8\u10e3\u10d3\u10d0"
    ],
    "name:mlg_x_preferred":[
        "Joda"
    ],
    "name:pol_x_preferred":[
        "Jude"
    ],
    "name:zho_x_preferred":[
        "Jude"
    ],
    "wof:name":"Jude",
    "wof:placetype":"locality"
},
  "geometry": {"coordinates":[80.81403,29.7495],"type":"Point"}
}