{
  "type": "Feature",
  "properties": {
    "gn:admin1_code":"WR",
    "gn:admin2_code":"4",
    "gn:admin3_code":"36.0",
    "gn:admin4_code":"360067.0",
    "gn:asciiname":"Pitadanda",
    "gn:country_code":"NP",
    "gn:dem":1713,
    "gn:feature_class":"P",
    "gn:feature_code":"PPLL",
    "gn:name":"Pitadanda",
    "gn:population":0,
    "gn:timezone":"Asia/Kathmandu",
    "iso:country":"NP",
    "wof:name":"Pitadanda",
    "wof:placetype":"locality"
},
  "geometry": {"coordinates":[84.74507,28.19511],"type":"Point"}
}