{
  "type": "Feature",
  "properties": {
    "gn:admin1_code":"WR",
    "gn:admin2_code":"4",
    "gn:admin3_code":"37",
    "gn:admin4_code":"370044",
    "gn:asciiname":"Jamtudanda",
    "gn:country_code":"NP",
    "gn:dem":1066,
    "gn:feature_class":"P",
    "gn:feature_code":"PPLL",
    "gn:name":"Jamtudanda",
    "gn:population":0,
    "gn:timezone":"Asia/Kathmandu",
    "iso:country":"NP",
    "wof:name":"Jamtudanda",
    "wof:placetype":"locality"
},
  "geometry": {"coordinates":[84.5076,28.19913],"type":"Point"}
}