{
  "type": "Feature",
  "properties": {
    "gn:admin1_code":"WR",
    "gn:admin2_code":"8",
    "gn:admin3_code":"46.0",
    "gn:admin4_code":"460021.0",
    "gn:asciiname":"Beltar",
    "gn:country_code":"NP",
    "gn:dem":1062,
    "gn:feature_class":"P",
    "gn:feature_code":"PPLL",
    "gn:name":"Beltar",
    "gn:population":0,
    "gn:timezone":"Asia/Kathmandu",
    "iso:country":"NP",
    "wof:name":"Beltar",
    "wof:placetype":"locality"
},
  "geometry": {"coordinates":[83.19917,28.15125],"type":"Point"}
}