{
  "type": "Feature",
  "properties": {
    "gn:admin1_code":"CR",
    "gn:admin2_code":"1",
    "gn:admin3_code":"25",
    "gn:admin4_code":"250030",
    "gn:asciiname":"Arubot",
    "gn:country_code":"NP",
    "gn:dem":1589,
    "gn:feature_class":"P",
    "gn:feature_code":"PPLL",
    "gn:name":"Arubot",
    "gn:population":0,
    "gn:timezone":"Asia/Kathmandu",
    "iso:country":"NP",
    "wof:name":"Arubot",
    "wof:placetype":"locality"
},
  "geometry": {"coordinates":[85.37851999999999,27.62603],"type":"Point"}
}