{
  "type": "Feature",
  "properties": {
    "gn:admin1_code":"ER",
    "gn:admin2_code":"13",
    "gn:admin3_code":"15",
    "gn:admin4_code":"150094",
    "gn:asciiname":"Dhobikhar",
    "gn:country_code":"NP",
    "gn:dem":148,
    "gn:feature_class":"P",
    "gn:feature_code":"PPLL",
    "gn:name":"Dhobikhar",
    "gn:population":0,
    "gn:timezone":"Asia/Kathmandu",
    "iso:country":"NP",
    "wof:name":"Dhobikhar",
    "wof:placetype":"locality"
},
  "geometry": {"coordinates":[86.56933000000002,26.7707],"type":"Point"}
}