{
  "type": "Feature",
  "properties": {
    "gn:admin1_code":"MR",
    "gn:admin2_code":"2.0",
    "gn:admin3_code":"59.0",
    "gn:admin4_code":"590025.0",
    "gn:asciiname":"Mathillo Nahagaun (kada)",
    "gn:country_code":"NP",
    "gn:dem":1402,
    "gn:feature_class":"P",
    "gn:feature_code":"PPLL",
    "gn:name":"Mathillo Nahagaun (kada)",
    "gn:population":0,
    "gn:timezone":"Asia/Kathmandu",
    "iso:country":"NP",
    "wof:name":"Mathillo Nahagaun (kada)",
    "wof:placetype":"locality"
},
  "geometry": {"coordinates":[81.89704,28.59638],"type":"Point"}
}