{
  "type": "Feature",
  "properties": {
    "gn:admin1_code":"MR",
    "gn:admin2_code":"2.0",
    "gn:admin3_code":"59.0",
    "gn:admin4_code":"590031.0",
    "gn:asciiname":"Tusara",
    "gn:country_code":"NP",
    "gn:dem":1500,
    "gn:feature_class":"P",
    "gn:feature_code":"PPLL",
    "gn:name":"Tusara",
    "gn:population":0,
    "gn:timezone":"Asia/Kathmandu",
    "iso:country":"NP",
    "name:ceb_x_preferred":[
        "Tusara"
    ],
    "name:fas_x_preferred":[
        "\u062a\u0648\u0633\u0627\u0631\u0627"
    ],
    "name:mai_x_preferred":[
        "\u0924\u0941\u0938\u093e\u0930\u093e"
    ],
    "name:msa_x_preferred":[
        "Tusara"
    ],
    "name:nep_x_preferred":[
        "\u0924\u0941\u0938\u093e\u0930\u093e"
    ],
    "name:new_x_preferred":[
        "\u0924\u0941\u0938\u0930\u093e"
    ],
    "name:pol_x_preferred":[
        "Tusara"
    ],
    "name:urd_x_preferred":[
        "\u062a\u0648\u0633\u0627\u0631\u0627"
    ],
    "wof:name":"Tusara",
    "wof:placetype":"locality"
},
  "geometry": {"coordinates":[81.59786,28.68978],"type":"Point"}
}