{
  "type": "Feature",
  "properties": {
    "gn:admin1_code":"FR",
    "gn:admin2_code":"9",
    "gn:admin3_code":"75.0",
    "gn:admin4_code":"750025.0",
    "gn:asciiname":"Parilek",
    "gn:country_code":"NP",
    "gn:dem":1537,
    "gn:feature_class":"P",
    "gn:feature_code":"PPLL",
    "gn:name":"Parilek",
    "gn:population":0,
    "gn:timezone":"Asia/Kathmandu",
    "iso:country":"NP",
    "wof:name":"Parilek",
    "wof:placetype":"locality"
},
  "geometry": {"coordinates":[80.4564,29.70223],"type":"Point"}
}