{
  "type": "Feature",
  "properties": {
    "gn:admin1_code":"00",
    "gn:asciiname":"Jondanda",
    "gn:country_code":"NP",
    "gn:dem":1426,
    "gn:feature_class":"P",
    "gn:feature_code":"PPL",
    "gn:name":"Jo\u1e45\u1e0d\u0101n\u1e0d\u0101",
    "gn:population":0,
    "gn:timezone":"Asia/Kathmandu",
    "iso:country":"NP",
    "wof:name":"Jondanda",
    "wof:placetype":"locality"
},
  "geometry": {"coordinates":[85.29303,27.96202000000001],"type":"Point"}
}