{
  "type": "Feature",
  "properties": {
    "gn:admin1_code":"ER",
    "gn:admin2_code":"10",
    "gn:admin3_code":"4.0",
    "gn:admin4_code":"40016.0",
    "gn:asciiname":"Miyanbari",
    "gn:country_code":"NP",
    "gn:dem":116,
    "gn:feature_class":"P",
    "gn:feature_code":"PPLL",
    "gn:name":"Miyanbari",
    "gn:population":0,
    "gn:timezone":"Asia/Kathmandu",
    "iso:country":"NP",
    "wof:name":"Miyanbari",
    "wof:placetype":"locality"
},
  "geometry": {"coordinates":[88.08493,26.62677],"type":"Point"}
}