{
  "type": "Feature",
  "properties": {
    "gn:admin1_code":"WR",
    "gn:admin2_code":"3",
    "gn:admin3_code":"45.0",
    "gn:admin4_code":"450015.0",
    "gn:asciiname":"Ratmata",
    "gn:country_code":"NP",
    "gn:dem":2099,
    "gn:feature_class":"P",
    "gn:feature_code":"PPLL",
    "gn:name":"Ratmata",
    "gn:population":0,
    "gn:timezone":"Asia/Kathmandu",
    "iso:country":"NP",
    "wof:name":"Ratmata",
    "wof:placetype":"locality"
},
  "geometry": {"coordinates":[83.37899,28.32719],"type":"Point"}
}