{
  "type": "Feature",
  "properties": {
    "gn:admin1_code":"FR",
    "gn:admin2_code":"14.0",
    "gn:admin3_code":"67.0",
    "gn:admin4_code":"670021.0",
    "gn:asciiname":"Thoknu",
    "gn:country_code":"NP",
    "gn:dem":1617,
    "gn:feature_class":"P",
    "gn:feature_code":"PPLL",
    "gn:name":"Thoknu",
    "gn:population":0,
    "gn:timezone":"Asia/Kathmandu",
    "iso:country":"NP",
    "wof:name":"Thoknu",
    "wof:placetype":"locality"
},
  "geometry": {"coordinates":[81.33394,29.38998],"type":"Point"}
}