{
  "type": "Feature",
  "properties": {
    "gn:admin1_code":"MR",
    "gn:admin2_code":"12",
    "gn:admin3_code":"54",
    "gn:admin4_code":"540004",
    "gn:asciiname":"Bhotanigare",
    "gn:country_code":"NP",
    "gn:dem":1949,
    "gn:feature_class":"P",
    "gn:feature_code":"PPLL",
    "gn:name":"Bhotanigare",
    "gn:population":0,
    "gn:timezone":"Asia/Kathmandu",
    "iso:country":"NP",
    "wof:name":"Bhotanigare",
    "wof:placetype":"locality"
},
  "geometry": {"coordinates":[82.49799999999998,28.68564000000001],"type":"Point"}
}