{
  "type": "Feature",
  "properties": {
    "gn:admin1_code":"FR",
    "gn:admin2_code":"9",
    "gn:admin3_code":"72.0",
    "gn:admin4_code":"720007.0",
    "gn:asciiname":"Kalapani",
    "gn:country_code":"NP",
    "gn:dem":232,
    "gn:feature_class":"P",
    "gn:feature_code":"PPLL",
    "gn:name":"Kalapani",
    "gn:population":0,
    "gn:timezone":"Asia/Kathmandu",
    "iso:country":"NP",
    "name:ceb_x_preferred":[
        "Kalapani"
    ],
    "name:fra_x_preferred":[
        "Kala Pani"
    ],
    "name:swe_x_preferred":[
        "Kalapani"
    ],
    "wof:name":"Kalapani",
    "wof:placetype":"locality"
},
  "geometry": {"coordinates":[80.36046,28.95664],"type":"Point"}
}