{
  "type": "Feature",
  "properties": {
    "gn:admin1_code":"ER",
    "gn:admin2_code":"13.0",
    "gn:admin3_code":"14.0",
    "gn:admin4_code":"140030.0",
    "gn:asciiname":"Bhasuwa",
    "gn:country_code":"NP",
    "gn:dem":359,
    "gn:feature_class":"P",
    "gn:feature_code":"PPLL",
    "gn:name":"Bhasuwa",
    "gn:population":0,
    "gn:timezone":"Asia/Kathmandu",
    "iso:country":"NP",
    "wof:name":"Bhasuwa",
    "wof:placetype":"locality"
},
  "geometry": {"coordinates":[86.45659000000001,26.90526],"type":"Point"}
}