{
  "type": "Feature",
  "properties": {
    "gn:admin1_code":"FR",
    "gn:admin2_code":"9",
    "gn:admin3_code":"75.0",
    "gn:admin4_code":"750035.0",
    "gn:asciiname":"Binkhali",
    "gn:country_code":"NP",
    "gn:dem":905,
    "gn:feature_class":"P",
    "gn:feature_code":"PPLL",
    "gn:name":"Binkhali",
    "gn:population":0,
    "gn:timezone":"Asia/Kathmandu",
    "iso:country":"NP",
    "wof:name":"Binkhali",
    "wof:placetype":"locality"
},
  "geometry": {"coordinates":[80.47024999999999,29.62821],"type":"Point"}
}