{
  "type": "Feature",
  "properties": {
    "gn:admin1_code":"MR",
    "gn:admin2_code":"12",
    "gn:admin3_code":"55",
    "gn:admin4_code":"550003",
    "gn:asciiname":"Makhula",
    "gn:country_code":"NP",
    "gn:dem":1231,
    "gn:feature_class":"P",
    "gn:feature_code":"PPLL",
    "gn:name":"Makhula",
    "gn:population":0,
    "gn:timezone":"Asia/Kathmandu",
    "iso:country":"NP",
    "wof:name":"Makhula",
    "wof:placetype":"locality"
},
  "geometry": {"coordinates":[82.26698,28.4207],"type":"Point"}
}