{
  "type": "Feature",
  "properties": {
    "gn:admin1_code":"WR",
    "gn:admin2_code":"4",
    "gn:admin3_code":"40.0",
    "gn:admin4_code":"400006.0",
    "gn:asciiname":"Hurkane",
    "gn:country_code":"NP",
    "gn:dem":1645,
    "gn:feature_class":"P",
    "gn:feature_code":"PPLL",
    "gn:name":"Hurkane",
    "gn:population":0,
    "gn:timezone":"Asia/Kathmandu",
    "iso:country":"NP",
    "wof:name":"Hurkane",
    "wof:placetype":"locality"
},
  "geometry": {"coordinates":[83.84913,28.21613],"type":"Point"}
}