{
  "type": "Feature",
  "properties": {
    "gn:admin1_code":"FR",
    "gn:admin2_code":"9",
    "gn:admin3_code":"74",
    "gn:admin4_code":"740013",
    "gn:asciiname":"Patauji",
    "gn:country_code":"NP",
    "gn:dem":1034,
    "gn:feature_class":"P",
    "gn:feature_code":"PPLL",
    "gn:name":"Patauji",
    "gn:population":0,
    "gn:timezone":"Asia/Kathmandu",
    "iso:country":"NP",
    "wof:name":"Patauji",
    "wof:placetype":"locality"
},
  "geometry": {"coordinates":[80.59103,29.63274],"type":"Point"}
}