{
  "type": "Feature",
  "properties": {
    "gn:admin1_code":"WR",
    "gn:admin2_code":"8",
    "gn:admin3_code":"51.0",
    "gn:admin4_code":"510008.0",
    "gn:asciiname":"Madelchaur",
    "gn:country_code":"NP",
    "gn:dem":1255,
    "gn:feature_class":"P",
    "gn:feature_code":"PPLL",
    "gn:name":"Madelchaur",
    "gn:population":0,
    "gn:timezone":"Asia/Kathmandu",
    "iso:country":"NP",
    "wof:name":"Madelchaur",
    "wof:placetype":"locality"
},
  "geometry": {"coordinates":[83.21623000000002,28.03245],"type":"Point"}
}