{
  "type": "Feature",
  "properties": {
    "gn:admin1_code":"CR",
    "gn:admin2_code":"11",
    "gn:admin3_code":"31",
    "gn:admin4_code":"310032",
    "gn:asciiname":"Nange",
    "gn:country_code":"NP",
    "gn:dem":1890,
    "gn:feature_class":"P",
    "gn:feature_code":"PPLL",
    "gn:name":"Nange",
    "gn:population":0,
    "gn:timezone":"Asia/Kathmandu",
    "iso:country":"NP",
    "name:fra_x_preferred":[
        "Nange"
    ],
    "name:ron_x_preferred":[
        "Nange"
    ],
    "name:slv_x_preferred":[
        "Nange"
    ],
    "name:srp_x_preferred":[
        "\u041d\u0430\u043d\u0433\u0435"
    ],
    "wof:name":"Nange",
    "wof:placetype":"locality"
},
  "geometry": {"coordinates":[85.03933000000001,27.59255],"type":"Point"}
}