{
  "type": "Feature",
  "properties": {
    "gn:admin1_code":"CR",
    "gn:admin2_code":"1",
    "gn:admin3_code":"28",
    "gn:admin4_code":"280018",
    "gn:asciiname":"Jhilkeshwar Mahadevdanda",
    "gn:country_code":"NP",
    "gn:dem":915,
    "gn:feature_class":"P",
    "gn:feature_code":"PPLL",
    "gn:name":"Jhilkeshwar Mahadevdanda",
    "gn:population":0,
    "gn:timezone":"Asia/Kathmandu",
    "iso:country":"NP",
    "wof:name":"Jhilkeshwar Mahadevdanda",
    "wof:placetype":"locality"
},
  "geometry": {"coordinates":[85.0498,27.83096],"type":"Point"}
}