{
  "type": "Feature",
  "properties": {
    "gn:admin1_code":"CR",
    "gn:admin2_code":"1",
    "gn:admin3_code":"30.0",
    "gn:admin4_code":"300008.0",
    "gn:asciiname":"Gairabari",
    "gn:country_code":"NP",
    "gn:dem":1296,
    "gn:feature_class":"P",
    "gn:feature_code":"PPLL",
    "gn:name":"Gairabari",
    "gn:population":0,
    "gn:timezone":"Asia/Kathmandu",
    "iso:country":"NP",
    "wof:name":"Gairabari",
    "wof:placetype":"locality"
},
  "geometry": {"coordinates":[85.21913000000001,27.73011],"type":"Point"}
}