{
  "type": "Feature",
  "properties": {
    "gn:admin1_code":"MR",
    "gn:admin2_code":"12",
    "gn:admin3_code":"55",
    "gn:admin4_code":"550038",
    "gn:asciiname":"Dayakot",
    "gn:country_code":"NP",
    "gn:dem":1730,
    "gn:feature_class":"P",
    "gn:feature_code":"PPLL",
    "gn:name":"Dayakot",
    "gn:population":0,
    "gn:timezone":"Asia/Kathmandu",
    "iso:country":"NP",
    "wof:name":"Dayakot",
    "wof:placetype":"locality"
},
  "geometry": {"coordinates":[82.37316,28.26286],"type":"Point"}
}