{
  "type": "Feature",
  "properties": {
    "gn:admin1_code":"WR",
    "gn:admin2_code":"3",
    "gn:admin3_code":"45",
    "gn:admin4_code":"450060",
    "gn:asciiname":"Sigana",
    "gn:country_code":"NP",
    "gn:dem":1398,
    "gn:feature_class":"P",
    "gn:feature_code":"PPLL",
    "gn:name":"Sigana",
    "gn:population":0,
    "gn:timezone":"Asia/Kathmandu",
    "iso:country":"NP",
    "wof:name":"Sigana",
    "wof:placetype":"locality"
},
  "geometry": {"coordinates":[83.56022,28.24925],"type":"Point"}
}