{
  "type": "Feature",
  "properties": {
    "gn:admin1_code":"WR",
    "gn:admin2_code":"3",
    "gn:admin3_code":"45.0",
    "gn:admin4_code":"450029.0",
    "gn:asciiname":"Bhumara",
    "gn:country_code":"NP",
    "gn:dem":1538,
    "gn:feature_class":"P",
    "gn:feature_code":"PPLL",
    "gn:name":"Bhumara",
    "gn:population":0,
    "gn:timezone":"Asia/Kathmandu",
    "iso:country":"NP",
    "wof:name":"Bhumara",
    "wof:placetype":"locality"
},
  "geometry": {"coordinates":[83.48787,28.1318],"type":"Point"}
}