{
  "type": "Feature",
  "properties": {
    "gn:admin1_code":"WR",
    "gn:admin2_code":"8",
    "gn:admin3_code":"50.0",
    "gn:admin4_code":"500023.0",
    "gn:asciiname":"Dhanchaura",
    "gn:country_code":"NP",
    "gn:dem":126,
    "gn:feature_class":"P",
    "gn:feature_code":"PPLL",
    "gn:name":"Dhanchaura",
    "gn:population":0,
    "gn:timezone":"Asia/Kathmandu",
    "iso:country":"NP",
    "wof:name":"Dhanchaura",
    "wof:placetype":"locality"
},
  "geometry": {"coordinates":[83.02506,27.69412],"type":"Point"}
}