{
  "type": "Feature",
  "properties": {
    "gn:admin1_code":"CR",
    "gn:admin2_code":"1",
    "gn:admin3_code":"23",
    "gn:admin4_code":"230029",
    "gn:asciiname":"Kusangpal",
    "gn:country_code":"NP",
    "gn:dem":1885,
    "gn:feature_class":"P",
    "gn:feature_code":"PPLL",
    "gn:name":"Kusangpal",
    "gn:population":0,
    "gn:timezone":"Asia/Kathmandu",
    "iso:country":"NP",
    "wof:name":"Kusangpal",
    "wof:placetype":"locality"
},
  "geometry": {"coordinates":[85.53366,28.00732],"type":"Point"}
}