{
  "type": "Feature",
  "properties": {
    "gn:admin1_code":"CR",
    "gn:admin2_code":"5",
    "gn:admin3_code":"19",
    "gn:admin4_code":"190077",
    "gn:asciiname":"Chihandandagaun",
    "gn:country_code":"NP",
    "gn:dem":276,
    "gn:feature_class":"P",
    "gn:feature_code":"PPLL",
    "gn:name":"Chihandandagaun",
    "gn:population":0,
    "gn:timezone":"Asia/Kathmandu",
    "iso:country":"NP",
    "wof:name":"Chihandandagaun",
    "wof:placetype":"locality"
},
  "geometry": {"coordinates":[85.65274000000002,27.11835],"type":"Point"}
}