{
  "type": "Feature",
  "properties": {
    "gn:admin1_code":"WR",
    "gn:admin2_code":"8",
    "gn:admin3_code":"50.0",
    "gn:admin4_code":"500015.0",
    "gn:asciiname":"Katahaniya",
    "gn:country_code":"NP",
    "gn:dem":123,
    "gn:feature_class":"P",
    "gn:feature_code":"PPLL",
    "gn:name":"Katahaniya",
    "gn:population":0,
    "gn:timezone":"Asia/Kathmandu",
    "iso:country":"NP",
    "wof:name":"Katahaniya",
    "wof:placetype":"locality"
},
  "geometry": {"coordinates":[82.86435,27.63229],"type":"Point"}
}