{
  "type": "Feature",
  "properties": {
    "gn:admin1_code":"MR",
    "gn:admin2_code":"2",
    "gn:admin3_code":"61.0",
    "gn:admin4_code":"610011.0",
    "gn:asciiname":"Adanda",
    "gn:country_code":"NP",
    "gn:dem":1808,
    "gn:feature_class":"P",
    "gn:feature_code":"PPLL",
    "gn:name":"Adanda",
    "gn:population":0,
    "gn:timezone":"Asia/Kathmandu",
    "iso:country":"NP",
    "wof:name":"Adanda",
    "wof:placetype":"locality"
},
  "geometry": {"coordinates":[81.91074,28.71563],"type":"Point"}
}