{
  "type": "Feature",
  "properties": {
    "gn:admin1_code":"WR",
    "gn:admin2_code":"4.0",
    "gn:admin3_code":"38.0",
    "gn:admin4_code":"380024.0",
    "gn:asciiname":"Haledi",
    "gn:country_code":"NP",
    "gn:dem":386,
    "gn:feature_class":"P",
    "gn:feature_code":"PPLL",
    "gn:name":"Haledi",
    "gn:population":0,
    "gn:timezone":"Asia/Kathmandu",
    "iso:country":"NP",
    "wof:name":"Haledi",
    "wof:placetype":"locality"
},
  "geometry": {"coordinates":[84.20981999999999,28.01011],"type":"Point"}
}