{
  "type": "Feature",
  "properties": {
    "gn:admin1_code":"MR",
    "gn:admin2_code":"6",
    "gn:admin3_code":"64.0",
    "gn:admin4_code":"640018.0",
    "gn:asciiname":"Nanikot",
    "gn:country_code":"NP",
    "gn:dem":2113,
    "gn:feature_class":"P",
    "gn:feature_code":"PPLL",
    "gn:name":"Nanikot",
    "gn:population":0,
    "gn:timezone":"Asia/Kathmandu",
    "iso:country":"NP",
    "wof:name":"Nanikot",
    "wof:placetype":"locality"
},
  "geometry": {"coordinates":[81.72462,29.3021],"type":"Point"}
}