{
  "type": "Feature",
  "properties": {
    "gn:admin1_code":"MR",
    "gn:admin2_code":"6",
    "gn:admin3_code":"63.0",
    "gn:admin4_code":"630011.0",
    "gn:asciiname":"Ratamata",
    "gn:country_code":"NP",
    "gn:dem":3606,
    "gn:feature_class":"P",
    "gn:feature_code":"PPLL",
    "gn:name":"Ratamata",
    "gn:population":0,
    "gn:timezone":"Asia/Kathmandu",
    "iso:country":"NP",
    "wof:name":"Ratamata",
    "wof:placetype":"locality"
},
  "geometry": {"coordinates":[82.37374,29.14274],"type":"Point"}
}