{
  "type": "Feature",
  "properties": {
    "gn:admin1_code":"ER",
    "gn:admin2_code":"13",
    "gn:admin3_code":"13.0",
    "gn:admin4_code":"130033.0",
    "gn:asciiname":"Shikarithumka",
    "gn:country_code":"NP",
    "gn:dem":1680,
    "gn:feature_class":"P",
    "gn:feature_code":"PPLL",
    "gn:name":"Shikarithumka",
    "gn:population":0,
    "gn:timezone":"Asia/Kathmandu",
    "iso:country":"NP",
    "wof:name":"Shikarithumka",
    "wof:placetype":"locality"
},
  "geometry": {"coordinates":[86.81959000000001,27.05321],"type":"Point"}
}