{
  "type": "Feature",
  "properties": {
    "gn:admin1_code":"MR",
    "gn:admin2_code":"2",
    "gn:admin3_code":"61.0",
    "gn:admin4_code":"610026.0",
    "gn:asciiname":"Dedkula",
    "gn:country_code":"NP",
    "gn:dem":1979,
    "gn:feature_class":"P",
    "gn:feature_code":"PPLL",
    "gn:name":"Dedkula",
    "gn:population":0,
    "gn:timezone":"Asia/Kathmandu",
    "iso:country":"NP",
    "wof:name":"Dedkula",
    "wof:placetype":"locality"
},
  "geometry": {"coordinates":[81.90425999999999,28.76765],"type":"Point"}
}