{
  "type": "Feature",
  "properties": {
    "gn:admin1_code":"MR",
    "gn:admin2_code":"6",
    "gn:admin3_code":"63.0",
    "gn:admin4_code":"630016.0",
    "gn:asciiname":"Simkholakhet",
    "gn:country_code":"NP",
    "gn:dem":2750,
    "gn:feature_class":"P",
    "gn:feature_code":"PPLL",
    "gn:name":"Simkholakhet",
    "gn:population":0,
    "gn:timezone":"Asia/Kathmandu",
    "iso:country":"NP",
    "wof:name":"Simkholakhet",
    "wof:placetype":"locality"
},
  "geometry": {"coordinates":[82.00569,29.25535],"type":"Point"}
}