{
  "type": "Feature",
  "properties": {
    "gn:admin1_code":"FR",
    "gn:admin2_code":"14",
    "gn:admin3_code":"68",
    "gn:admin4_code":"680008",
    "gn:asciiname":"ThulDhunga",
    "gn:country_code":"NP",
    "gn:dem":2209,
    "gn:feature_class":"P",
    "gn:feature_code":"PPLL",
    "gn:name":"ThulDhunga",
    "gn:population":0,
    "gn:timezone":"Asia/Kathmandu",
    "iso:country":"NP",
    "wof:name":"ThulDhunga",
    "wof:placetype":"locality"
},
  "geometry": {"coordinates":[80.98484000000001,29.65554],"type":"Point"}
}