{
  "type": "Feature",
  "properties": {
    "gn:admin1_code":"ER",
    "gn:admin2_code":"13",
    "gn:admin3_code":"12",
    "gn:admin4_code":"120017.0",
    "gn:asciiname":"Damar",
    "gn:country_code":"NP",
    "gn:dem":2604,
    "gn:feature_class":"P",
    "gn:feature_code":"PPLL",
    "gn:name":"Damar",
    "gn:population":0,
    "gn:timezone":"Asia/Kathmandu",
    "iso:country":"NP",
    "name:aze_x_preferred":[
        "Damar sistemi"
    ],
    "name:ceb_x_preferred":[
        "Damar"
    ],
    "name:deu_x_preferred":[
        "Damar"
    ],
    "name:ind_x_preferred":[
        "Damar"
    ],
    "name:ita_x_preferred":[
        "Damar"
    ],
    "name:jav_x_preferred":[
        "Damar"
    ],
    "name:msa_x_preferred":[
        "Damar"
    ],
    "name:nld_x_preferred":[
        "Damar"
    ],
    "name:por_x_preferred":[
        "Damar"
    ],
    "name:swe_x_preferred":[
        "Damar"
    ],
    "name:tur_x_preferred":[
        "Damar"
    ],
    "wof:name":"Damar",
    "wof:placetype":"locality"
},
  "geometry": {"coordinates":[86.45943,27.42705],"type":"Point"}
}