{
  "type": "Feature",
  "properties": {
    "gn:admin1_code":"ER",
    "gn:admin2_code":"10",
    "gn:admin3_code":"2",
    "gn:admin4_code":"20033",
    "gn:asciiname":"Devithan",
    "gn:country_code":"NP",
    "gn:dem":1921,
    "gn:feature_class":"P",
    "gn:feature_code":"PPLL",
    "gn:name":"Devithan",
    "gn:population":0,
    "gn:timezone":"Asia/Kathmandu",
    "iso:country":"NP",
    "wof:name":"Devithan",
    "wof:placetype":"locality"
},
  "geometry": {"coordinates":[87.79770000000001,27.11854000000001],"type":"Point"}
}