{
  "type": "Feature",
  "properties": {
    "gn:admin1_code":"MR",
    "gn:admin2_code":"12",
    "gn:admin3_code":"55",
    "gn:admin4_code":"550034",
    "gn:asciiname":"Kaphleni",
    "gn:country_code":"NP",
    "gn:dem":1482,
    "gn:feature_class":"P",
    "gn:feature_code":"PPLL",
    "gn:name":"Kaphleni",
    "gn:population":0,
    "gn:timezone":"Asia/Kathmandu",
    "iso:country":"NP",
    "wof:name":"Kaphleni",
    "wof:placetype":"locality"
},
  "geometry": {"coordinates":[82.14306999999999,28.5422],"type":"Point"}
}