{
  "type": "Feature",
  "properties": {
    "gn:admin1_code":"MR",
    "gn:admin2_code":"12",
    "gn:admin3_code":"55",
    "gn:admin4_code":"550021",
    "gn:asciiname":"Bhagar",
    "gn:country_code":"NP",
    "gn:dem":764,
    "gn:feature_class":"P",
    "gn:feature_code":"PPLL",
    "gn:name":"Bhagar",
    "gn:population":0,
    "gn:timezone":"Asia/Kathmandu",
    "iso:country":"NP",
    "wof:name":"Bhagar",
    "wof:placetype":"locality"
},
  "geometry": {"coordinates":[82.11863000000002,28.22393],"type":"Point"}
}