{
  "type": "Feature",
  "properties": {
    "gn:admin1_code":"CR",
    "gn:admin2_code":"11",
    "gn:admin3_code":"35.0",
    "gn:admin4_code":"350020.0",
    "gn:asciiname":"Maites",
    "gn:country_code":"NP",
    "gn:dem":1354,
    "gn:feature_class":"P",
    "gn:feature_code":"PPLL",
    "gn:name":"Maites",
    "gn:population":0,
    "gn:timezone":"Asia/Kathmandu",
    "iso:country":"NP",
    "wof:name":"Maites",
    "wof:placetype":"locality"
},
  "geometry": {"coordinates":[84.60514000000001,27.79122000000001],"type":"Point"}
}