{
  "type": "Feature",
  "properties": {
    "gn:admin1_code":"WR",
    "gn:admin2_code":"3",
    "gn:admin3_code":"45.0",
    "gn:admin4_code":"450040.0",
    "gn:asciiname":"Dip",
    "gn:country_code":"NP",
    "gn:dem":2169,
    "gn:feature_class":"P",
    "gn:feature_code":"PPLL",
    "gn:name":"Dip",
    "gn:population":0,
    "gn:timezone":"Asia/Kathmandu",
    "iso:country":"NP",
    "name:cat_x_preferred":[
        "DIP"
    ],
    "name:ceb_x_preferred":[
        "Dip"
    ],
    "name:hrv_x_preferred":[
        "DIP"
    ],
    "name:spa_x_preferred":[
        "Dip"
    ],
    "wof:name":"Dip",
    "wof:placetype":"locality"
},
  "geometry": {"coordinates":[83.2114,28.44001],"type":"Point"}
}