{
  "type": "Feature",
  "properties": {
    "gn:admin1_code":"MR",
    "gn:admin2_code":"2.0",
    "gn:admin3_code":"58.0",
    "gn:admin4_code":"580005.0",
    "gn:asciiname":"Ishwariganj",
    "gn:country_code":"NP",
    "gn:dem":142,
    "gn:feature_class":"P",
    "gn:feature_code":"PPLL",
    "gn:name":"Ishwariganj",
    "gn:population":0,
    "gn:timezone":"Asia/Kathmandu",
    "iso:country":"NP",
    "wof:name":"Ishwariganj",
    "wof:placetype":"locality"
},
  "geometry": {"coordinates":[81.14686,28.37706],"type":"Point"}
}