{
  "type": "Feature",
  "properties": {
    "gn:admin1_code":"ER",
    "gn:admin2_code":"7",
    "gn:admin3_code":"9",
    "gn:admin4_code":"90009",
    "gn:asciiname":"Dharane",
    "gn:country_code":"NP",
    "gn:dem":1485,
    "gn:feature_class":"P",
    "gn:feature_code":"PPLL",
    "gn:name":"Dharane",
    "gn:population":0,
    "gn:timezone":"Asia/Kathmandu",
    "iso:country":"NP",
    "wof:name":"Dharane",
    "wof:placetype":"locality"
},
  "geometry": {"coordinates":[87.2075,27.46269],"type":"Point"}
}