{
  "type": "Feature",
  "properties": {
    "gn:admin1_code":"MR",
    "gn:admin2_code":"2.0",
    "gn:admin3_code":"59.0",
    "gn:admin4_code":"590047.0",
    "gn:asciiname":"Kota",
    "gn:country_code":"NP",
    "gn:dem":458,
    "gn:feature_class":"P",
    "gn:feature_code":"PPLL",
    "gn:name":"Kota",
    "gn:population":0,
    "gn:timezone":"Asia/Kathmandu",
    "iso:country":"NP",
    "name:bih_x_preferred":[
        "\u0915\u094b\u091f\u093e"
    ],
    "name:bpy_x_preferred":[
        "\u0995\u09cb\u09a4\u09be"
    ],
    "name:cat_x_preferred":[
        "Kota"
    ],
    "name:ceb_x_preferred":[
        "Kota"
    ],
    "name:deu_x_preferred":[
        "Kota"
    ],
    "name:fas_x_preferred":[
        "\u06a9\u0648\u062a\u0627"
    ],
    "name:fra_x_preferred":[
        "Kota"
    ],
    "name:hun_x_preferred":[
        "Kota"
    ],
    "name:ind_x_preferred":[
        "Kota"
    ],
    "name:ita_x_preferred":[
        "Kota"
    ],
    "name:lav_x_preferred":[
        "Kota"
    ],
    "name:msa_x_preferred":[
        "Kota"
    ],
    "name:new_x_preferred":[
        "\u0915\u094b\u0924\u093e"
    ],
    "name:nld_x_preferred":[
        "Kota"
    ],
    "name:pol_x_preferred":[
        "Kota"
    ],
    "name:pus_x_preferred":[
        "\u06a9\u0648\u062a\u0627"
    ],
    "name:rus_x_preferred":[
        "\u041a\u043e\u0442\u0430"
    ],
    "name:spa_x_preferred":[
        "Kota"
    ],
    "name:swe_x_preferred":[
        "Kota"
    ],
    "name:ukr_x_preferred":[
        "\u041a\u043e\u0442\u0430"
    ],
    "name:vie_x_preferred":[
        "Kota"
    ],
    "wof:name":"Kota",
    "wof:placetype":"locality"
},
  "geometry": {"coordinates":[81.43677,28.78896],"type":"Point"}
}