{
  "type": "Feature",
  "properties": {
    "gn:admin1_code":"MR",
    "gn:admin2_code":"2.0",
    "gn:admin3_code":"59.0",
    "gn:admin4_code":"590047.0",
    "gn:asciiname":"Kota",
    "gn:country_code":"NP",
    "gn:dem":458,
    "gn:feature_class":"P",
    "gn:feature_code":"PPLL",
    "gn:name":"Kota",
    "gn:population":0,
    "gn:timezone":"Asia/Kathmandu",
    "iso:country":"NP",
    "wof:name":"Kota",
    "wof:placetype":"locality"
},
  "geometry": {"coordinates":[81.43677,28.78896],"type":"Point"}
}