{
  "type": "Feature",
  "properties": {
    "gn:admin1_code":"ER",
    "gn:admin2_code":"7",
    "gn:admin3_code":"7.0",
    "gn:admin4_code":"70029.0",
    "gn:asciiname":"Kolchaur",
    "gn:country_code":"NP",
    "gn:dem":1405,
    "gn:feature_class":"P",
    "gn:feature_code":"PPLL",
    "gn:name":"Kolchaur",
    "gn:population":0,
    "gn:timezone":"Asia/Kathmandu",
    "iso:country":"NP",
    "wof:name":"Kolchaur",
    "wof:placetype":"locality"
},
  "geometry": {"coordinates":[87.34583000000001,27.09492],"type":"Point"}
}