{
  "type": "Feature",
  "properties": {
    "gn:admin1_code":"FR",
    "gn:admin2_code":"9",
    "gn:admin3_code":"73.0",
    "gn:admin4_code":"730019.0",
    "gn:asciiname":"Makarkudi",
    "gn:country_code":"NP",
    "gn:dem":1211,
    "gn:feature_class":"P",
    "gn:feature_code":"PPLL",
    "gn:name":"Makarkudi",
    "gn:population":0,
    "gn:timezone":"Asia/Kathmandu",
    "iso:country":"NP",
    "wof:name":"Makarkudi",
    "wof:placetype":"locality"
},
  "geometry": {"coordinates":[80.34676,29.28362000000001],"type":"Point"}
}