{
  "type": "Feature",
  "properties": {
    "gn:admin1_code":"CR",
    "gn:admin2_code":"1",
    "gn:admin3_code":"24.0",
    "gn:admin4_code":"240010.0",
    "gn:asciiname":"Pachuwarghat",
    "gn:country_code":"NP",
    "gn:dem":601,
    "gn:feature_class":"P",
    "gn:feature_code":"PPLL",
    "gn:name":"Pachuwarghat",
    "gn:population":0,
    "gn:timezone":"Asia/Kathmandu",
    "iso:country":"NP",
    "wof:name":"Pachuwarghat",
    "wof:placetype":"locality"
},
  "geometry": {"coordinates":[85.74947,27.55505],"type":"Point"}
}