{
  "type": "Feature",
  "properties": {
    "gn:admin1_code":"FR",
    "gn:admin2_code":"14",
    "gn:admin3_code":"68",
    "gn:admin4_code":"680029",
    "gn:asciiname":"Lamdhunga",
    "gn:country_code":"NP",
    "gn:dem":1890,
    "gn:feature_class":"P",
    "gn:feature_code":"PPLL",
    "gn:name":"Lamdhunga",
    "gn:population":0,
    "gn:timezone":"Asia/Kathmandu",
    "iso:country":"NP",
    "wof:name":"Lamdhunga",
    "wof:placetype":"locality"
},
  "geometry": {"coordinates":[81.17123000000002,29.46014000000001],"type":"Point"}
}