{
  "type": "Feature",
  "properties": {
    "gn:admin1_code":"CR",
    "gn:admin2_code":"1",
    "gn:admin3_code":"28",
    "gn:admin4_code":"280031",
    "gn:asciiname":"Mairitar",
    "gn:country_code":"NP",
    "gn:dem":509,
    "gn:feature_class":"P",
    "gn:feature_code":"PPLL",
    "gn:name":"Mairitar",
    "gn:population":0,
    "gn:timezone":"Asia/Kathmandu",
    "iso:country":"NP",
    "wof:name":"Mairitar",
    "wof:placetype":"locality"
},
  "geometry": {"coordinates":[85.08105,27.85999],"type":"Point"}
}