{
  "type": "Feature",
  "properties": {
    "gn:admin1_code":"ER",
    "gn:admin2_code":"7",
    "gn:admin3_code":"7.0",
    "gn:admin4_code":"70035.0",
    "gn:asciiname":"Guthgaun",
    "gn:country_code":"NP",
    "gn:dem":1167,
    "gn:feature_class":"P",
    "gn:feature_code":"PPLL",
    "gn:name":"Guthgaun",
    "gn:population":0,
    "gn:timezone":"Asia/Kathmandu",
    "iso:country":"NP",
    "wof:name":"Guthgaun",
    "wof:placetype":"locality"
},
  "geometry": {"coordinates":[87.41064,26.98973],"type":"Point"}
}