{
  "type": "Feature",
  "properties": {
    "gn:admin1_code":"CR",
    "gn:admin2_code":"11",
    "gn:admin3_code":"31",
    "gn:admin4_code":"310024",
    "gn:asciiname":"Chamanti",
    "gn:country_code":"NP",
    "gn:dem":732,
    "gn:feature_class":"P",
    "gn:feature_code":"PPLL",
    "gn:name":"Chamanti",
    "gn:population":0,
    "gn:timezone":"Asia/Kathmandu",
    "iso:country":"NP",
    "wof:name":"Chamanti",
    "wof:placetype":"locality"
},
  "geometry": {"coordinates":[84.81137,27.58931],"type":"Point"}
}