{
  "type": "Feature",
  "properties": {
    "gn:admin1_code":"MR",
    "gn:admin2_code":"12",
    "gn:admin3_code":"54",
    "gn:admin4_code":"540042",
    "gn:asciiname":"Sunkhana Lek",
    "gn:country_code":"NP",
    "gn:dem":1799,
    "gn:feature_class":"P",
    "gn:feature_code":"PPLL",
    "gn:name":"Sunkhana Lek",
    "gn:population":0,
    "gn:timezone":"Asia/Kathmandu",
    "iso:country":"NP",
    "wof:name":"Sunkhana Lek",
    "wof:placetype":"locality"
},
  "geometry": {"coordinates":[82.52996,28.63628],"type":"Point"}
}