{
  "type": "Feature",
  "properties": {
    "gn:admin1_code":"MR",
    "gn:admin2_code":"12",
    "gn:admin3_code":"53",
    "gn:admin4_code":"530021",
    "gn:asciiname":"Sarpal",
    "gn:country_code":"NP",
    "gn:dem":1557,
    "gn:feature_class":"P",
    "gn:feature_code":"PPLL",
    "gn:name":"Sarpal",
    "gn:population":0,
    "gn:timezone":"Asia/Kathmandu",
    "iso:country":"NP",
    "wof:name":"Sarpal",
    "wof:placetype":"locality"
},
  "geometry": {"coordinates":[82.55724000000002,28.25933],"type":"Point"}
}