{
  "type": "Feature",
  "properties": {
    "gn:admin1_code":"MR",
    "gn:admin2_code":"6",
    "gn:admin3_code":"64.0",
    "gn:admin4_code":"640026.0",
    "gn:asciiname":"Majh Angan",
    "gn:country_code":"NP",
    "gn:dem":2005,
    "gn:feature_class":"P",
    "gn:feature_code":"PPLL",
    "gn:name":"Majh Angan",
    "gn:population":0,
    "gn:timezone":"Asia/Kathmandu",
    "iso:country":"NP",
    "wof:name":"Majh Angan",
    "wof:placetype":"locality"
},
  "geometry": {"coordinates":[81.54599,29.22558],"type":"Point"}
}