{
  "type": "Feature",
  "properties": {
    "gn:admin1_code":"CR",
    "gn:admin2_code":"11",
    "gn:admin3_code":"31",
    "gn:admin4_code":"310004",
    "gn:asciiname":"Lekhpani",
    "gn:country_code":"NP",
    "gn:dem":926,
    "gn:feature_class":"P",
    "gn:feature_code":"PPLL",
    "gn:name":"Lekhpani",
    "gn:population":0,
    "gn:timezone":"Asia/Kathmandu",
    "iso:country":"NP",
    "wof:name":"Lekhpani",
    "wof:placetype":"locality"
},
  "geometry": {"coordinates":[84.96185,27.48479],"type":"Point"}
}