{
  "type": "Feature",
  "properties": {
    "gn:admin1_code":"CR",
    "gn:admin2_code":"11",
    "gn:admin3_code":"35.0",
    "gn:admin4_code":"350011.0",
    "gn:asciiname":"Dibyanagar",
    "gn:country_code":"NP",
    "gn:dem":167,
    "gn:feature_class":"P",
    "gn:feature_code":"PPLL",
    "gn:name":"Dibyanagar",
    "gn:population":0,
    "gn:timezone":"Asia/Kathmandu",
    "iso:country":"NP",
    "name:hin_x_preferred":[
        "\u0926\u093f\u0935\u094d\u092f\u0928\u0917\u0930"
    ],
    "name:msa_x_preferred":[
        "Dibyanagar"
    ],
    "name:nep_x_preferred":[
        "\u0926\u093f\u0935\u094d\u092f\u0928\u0917\u0930"
    ],
    "name:new_x_preferred":[
        "\u0926\u093f\u0935\u094d\u092f\u0928\u0917\u0930"
    ],
    "wof:name":"Dibyanagar",
    "wof:placetype":"locality"
},
  "geometry": {"coordinates":[84.25747,27.59448],"type":"Point"}
}