{
  "type": "Feature",
  "properties": {
    "gn:admin1_code":"00",
    "gn:asciiname":"Sisaiya",
    "gn:country_code":"NP",
    "gn:dem":164,
    "gn:feature_class":"P",
    "gn:feature_code":"PPL",
    "gn:name":"Sisaiy\u0101",
    "gn:population":0,
    "gn:timezone":"Asia/Kathmandu",
    "iso:country":"NP",
    "name:nep_x_preferred":[
        "Sisaiy\u0101"
    ],
    "name:und_x_variant":[
        "Sasaiya",
        "Sisaria"
    ],
    "wof:name":"Sisaiya",
    "wof:placetype":"locality"
},
  "geometry": {"coordinates":[80.88150999999998,28.67987],"type":"Point"}
}