{
  "type": "Feature",
  "properties": {
    "gn:admin1_code":"WR",
    "gn:admin2_code":"3",
    "gn:admin3_code":"44",
    "gn:admin4_code":"440039",
    "gn:asciiname":"Ganabang",
    "gn:country_code":"NP",
    "gn:dem":1739,
    "gn:feature_class":"P",
    "gn:feature_code":"PPLL",
    "gn:name":"Ganabang",
    "gn:population":0,
    "gn:timezone":"Asia/Kathmandu",
    "iso:country":"NP",
    "wof:name":"Ganabang",
    "wof:placetype":"locality"
},
  "geometry": {"coordinates":[83.70589,28.11107],"type":"Point"}
}