{
  "type": "Feature",
  "properties": {
    "gn:admin1_code":"CR",
    "gn:admin2_code":"11",
    "gn:admin3_code":"35.0",
    "gn:admin4_code":"350014.0",
    "gn:asciiname":"Kesharbag",
    "gn:country_code":"NP",
    "gn:dem":194,
    "gn:feature_class":"P",
    "gn:feature_code":"PPLL",
    "gn:name":"Kesharbag",
    "gn:population":0,
    "gn:timezone":"Asia/Kathmandu",
    "iso:country":"NP",
    "wof:name":"Kesharbag",
    "wof:placetype":"locality"
},
  "geometry": {"coordinates":[84.41110999999999,27.61808],"type":"Point"}
}