{
  "type": "Feature",
  "properties": {
    "gn:admin1_code":"WR",
    "gn:admin2_code":"4",
    "gn:admin3_code":"37",
    "gn:admin4_code":"370001",
    "gn:asciiname":"Agrapakha",
    "gn:country_code":"NP",
    "gn:dem":1019,
    "gn:feature_class":"P",
    "gn:feature_code":"PPLL",
    "gn:name":"Agrapakha",
    "gn:population":0,
    "gn:timezone":"Asia/Kathmandu",
    "iso:country":"NP",
    "wof:name":"Agrapakha",
    "wof:placetype":"locality"
},
  "geometry": {"coordinates":[84.4791,28.17411],"type":"Point"}
}