{
  "type": "Feature",
  "properties": {
    "gn:admin1_code":"ER",
    "gn:admin2_code":"13.0",
    "gn:admin3_code":"14.0",
    "gn:admin4_code":"140005.0",
    "gn:asciiname":"Karambote",
    "gn:country_code":"NP",
    "gn:dem":398,
    "gn:feature_class":"P",
    "gn:feature_code":"PPLL",
    "gn:name":"Karambote",
    "gn:population":0,
    "gn:timezone":"Asia/Kathmandu",
    "iso:country":"NP",
    "wof:name":"Karambote",
    "wof:placetype":"locality"
},
  "geometry": {"coordinates":[86.62184999999999,27.13392],"type":"Point"}
}