{
  "type": "Feature",
  "properties": {
    "iso:country":"NP",
    "name:ara_x_preferred":[
        "\u0628\u064a\u0633\u064a\u0633\u0627\u0647\u0627\u0631"
    ],
    "name:deu_x_preferred":[
        "Besisahar"
    ],
    "name:dut_x_preferred":[
        "Besisahar"
    ],
    "name:eng_x_preferred":[
        "Besisahar"
    ],
    "name:fra_x_preferred":[
        "Besisahar"
    ],
    "name:fre_x_preferred":[
        "Besisahar"
    ],
    "name:ger_x_preferred":[
        "Besisahar"
    ],
    "name:ita_x_preferred":[
        "Besisahar"
    ],
    "name:jpn_x_preferred":[
        "\u30d9\u30b7\u30b5\u30cf\u30eb"
    ],
    "name:nep_x_preferred":[
        "\u092c\u0947\u0938\u0940\u0938\u0939\u0930 \u0928\u0917\u0930\u092a\u093e\u0932\u093f\u0915\u093e"
    ],
    "name:pol_x_preferred":[
        "Besishahar"
    ],
    "name:por_x_preferred":[
        "Besisahar"
    ],
    "name:rus_x_preferred":[
        "\u0411\u0435\u0441\u0438\u0441\u0430\u0445\u0430\u0440"
    ],
    "name:urd_x_preferred":[
        "\u0628\u06cc\u0633\u06cc\u0633 \u06c1\u0631"
    ],
    "qs:gn_pop":0,
    "qs:name":"Besisahar",
    "qs:name_adm0":"Nepal",
    "qs:name_adm1":"Pashchimanchal",
    "qs:photos":68,
    "qs:photos_1k":14,
    "qs:photos_9k":1,
    "qs:photos_9r":2,
    "qs:photos_all":68,
    "qs:photos_sr":2,
    "qs:placetype":"Town",
    "qs:pop_sr":"0",
    "qs:woe_adm0":23424911,
    "wd:wordcount":1714,
    "wof:name":"Besisahar",
    "wof:placetype":"locality"
},
  "geometry": {"coordinates":[84.43014549999999,28.125],"type":"Point"}
}