{
  "type": "Feature",
  "properties": {
    "gn:admin1_code":"WR",
    "gn:admin2_code":"4",
    "gn:admin3_code":"36.0",
    "gn:admin4_code":"360048.0",
    "gn:asciiname":"Amle",
    "gn:country_code":"NP",
    "gn:dem":1192,
    "gn:feature_class":"P",
    "gn:feature_code":"PPLL",
    "gn:name":"Amle",
    "gn:population":0,
    "gn:timezone":"Asia/Kathmandu",
    "iso:country":"NP",
    "wof:name":"Amle",
    "wof:placetype":"locality"
},
  "geometry": {"coordinates":[84.74415,28.08176],"type":"Point"}
}