{
  "type": "Feature",
  "properties": {
    "gn:admin1_code":"CR",
    "gn:admin2_code":"1",
    "gn:admin3_code":"24.0",
    "gn:admin4_code":"240065.0",
    "gn:asciiname":"Chamkharka",
    "gn:country_code":"NP",
    "gn:dem":1536,
    "gn:feature_class":"P",
    "gn:feature_code":"PPLL",
    "gn:name":"Chamkharka",
    "gn:population":0,
    "gn:timezone":"Asia/Kathmandu",
    "iso:country":"NP",
    "wof:name":"Chamkharka",
    "wof:placetype":"locality"
},
  "geometry": {"coordinates":[85.50196,27.59828],"type":"Point"}
}