{
  "type": "Feature",
  "properties": {
    "gn:admin1_code":"FR",
    "gn:admin2_code":"14",
    "gn:admin3_code":"71.0",
    "gn:admin4_code":"710040.0",
    "gn:asciiname":"Badikathai",
    "gn:country_code":"NP",
    "gn:dem":393,
    "gn:feature_class":"P",
    "gn:feature_code":"PPLL",
    "gn:name":"Badikathai",
    "gn:population":0,
    "gn:timezone":"Asia/Kathmandu",
    "iso:country":"NP",
    "wof:name":"Badikathai",
    "wof:placetype":"locality"
},
  "geometry": {"coordinates":[81.03586999999997,28.75666],"type":"Point"}
}