{
  "type": "Feature",
  "properties": {
    "gn:admin1_code":"ER",
    "gn:admin2_code":"7",
    "gn:admin3_code":"10.0",
    "gn:admin4_code":"100061.0",
    "gn:asciiname":"Chhungkha",
    "gn:country_code":"NP",
    "gn:dem":1513,
    "gn:feature_class":"P",
    "gn:feature_code":"PPLL",
    "gn:name":"Chhungkha",
    "gn:population":0,
    "gn:timezone":"Asia/Kathmandu",
    "iso:country":"NP",
    "wof:name":"Chhungkha",
    "wof:placetype":"locality"
},
  "geometry": {"coordinates":[86.99016999999998,26.98162],"type":"Point"}
}