{
  "type": "Feature",
  "properties": {
    "gn:admin1_code":"WR",
    "gn:admin2_code":"8",
    "gn:admin3_code":"47",
    "gn:admin4_code":"470059",
    "gn:asciiname":"Kali Ban",
    "gn:country_code":"NP",
    "gn:dem":757,
    "gn:feature_class":"P",
    "gn:feature_code":"PPLL",
    "gn:name":"Kali Ban",
    "gn:population":0,
    "gn:timezone":"Asia/Kathmandu",
    "iso:country":"NP",
    "wof:name":"Kali Ban",
    "wof:placetype":"locality"
},
  "geometry": {"coordinates":[83.88667,27.82914],"type":"Point"}
}