{
  "type": "Feature",
  "properties": {
    "gn:admin1_code":"FR",
    "gn:admin2_code":"14.0",
    "gn:admin3_code":"67.0",
    "gn:admin4_code":"670019.0",
    "gn:asciiname":"Kolti",
    "gn:country_code":"NP",
    "gn:dem":1425,
    "gn:feature_class":"P",
    "gn:feature_code":"PPLL",
    "gn:name":"Kolti",
    "gn:population":0,
    "gn:timezone":"Asia/Kathmandu",
    "iso:country":"NP",
    "name:ceb_x_preferred":[
        "Kolti"
    ],
    "name:fra_x_preferred":[
        "Kolti"
    ],
    "name:mai_x_preferred":[
        "\u0915\u094b\u0932\u094d\u091f\u0940"
    ],
    "name:msa_x_preferred":[
        "Kolti"
    ],
    "name:nep_x_preferred":[
        "\u0915\u094b\u0932\u094d\u091f\u0940"
    ],
    "name:new_x_preferred":[
        "\u0915\u094b\u0932\u094d\u091f\u0940"
    ],
    "name:nor_x_preferred":[
        "Kolti"
    ],
    "name:pol_x_preferred":[
        "Kolti"
    ],
    "wof:name":"Kolti",
    "wof:placetype":"locality"
},
  "geometry": {"coordinates":[81.66193,29.50571],"type":"Point"}
}