{
  "type": "Feature",
  "properties": {
    "gn:admin1_code":"ER",
    "gn:admin2_code":"7.0",
    "gn:admin3_code":"10.0",
    "gn:admin4_code":"100005.0",
    "gn:asciiname":"Gairigaun",
    "gn:country_code":"NP",
    "gn:dem":1861,
    "gn:feature_class":"P",
    "gn:feature_code":"PPLL",
    "gn:name":"Gairigaun",
    "gn:population":0,
    "gn:timezone":"Asia/Kathmandu",
    "iso:country":"NP",
    "wof:name":"Gairigaun",
    "wof:placetype":"locality"
},
  "geometry": {"coordinates":[86.96368000000002,27.02428],"type":"Point"}
}