{
  "type": "Feature",
  "properties": {
    "gn:admin1_code":"MR",
    "gn:admin2_code":"6",
    "gn:admin3_code":"63.0",
    "gn:admin4_code":"630030.0",
    "gn:asciiname":"Laghu",
    "gn:country_code":"NP",
    "gn:dem":2375,
    "gn:feature_class":"P",
    "gn:feature_code":"PPLL",
    "gn:name":"Laghu",
    "gn:population":0,
    "gn:timezone":"Asia/Kathmandu",
    "iso:country":"NP",
    "wof:name":"Laghu",
    "wof:placetype":"locality"
},
  "geometry": {"coordinates":[82.05658000000003,29.23676],"type":"Point"}
}