{
  "type": "Feature",
  "properties": {
    "gn:admin1_code":"MR",
    "gn:admin2_code":"2",
    "gn:admin3_code":"60.0",
    "gn:admin4_code":"600008.0",
    "gn:asciiname":"Kaphalsaini",
    "gn:country_code":"NP",
    "gn:dem":1387,
    "gn:feature_class":"P",
    "gn:feature_code":"PPLL",
    "gn:name":"Kaphalsaini",
    "gn:population":0,
    "gn:timezone":"Asia/Kathmandu",
    "iso:country":"NP",
    "wof:name":"Kaphalsaini",
    "wof:placetype":"locality"
},
  "geometry": {"coordinates":[81.70435999999999,28.78343],"type":"Point"}
}