{
  "type": "Feature",
  "properties": {
    "gn:admin1_code":"WR",
    "gn:admin2_code":"3",
    "gn:admin3_code":"45.0",
    "gn:admin4_code":"450005.0",
    "gn:asciiname":"Nabi",
    "gn:country_code":"NP",
    "gn:dem":2861,
    "gn:feature_class":"P",
    "gn:feature_code":"PPLL",
    "gn:name":"Nabi",
    "gn:population":0,
    "gn:timezone":"Asia/Kathmandu",
    "iso:country":"NP",
    "name:ceb_x_preferred":[
        "Nabi"
    ],
    "name:deu_x_preferred":[
        "Nabi"
    ],
    "name:epo_x_preferred":[
        "Nabi"
    ],
    "name:fra_x_preferred":[
        "Nabi"
    ],
    "name:kaz_x_preferred":[
        "\u041d\u04d9\u0431\u0438"
    ],
    "name:kor_x_preferred":[
        "\ub098\ube44"
    ],
    "name:nds_x_preferred":[
        "Nabi"
    ],
    "name:rus_x_preferred":[
        "\u041d\u0430\u0431\u0438"
    ],
    "name:swe_x_preferred":[
        "Nabi"
    ],
    "wof:name":"Nabi",
    "wof:placetype":"locality"
},
  "geometry": {"coordinates":[83.02998000000002,28.49871],"type":"Point"}
}