{
  "type": "Feature",
  "properties": {
    "gn:admin1_code":"00",
    "gn:asciiname":"Gudel",
    "gn:country_code":"NP",
    "gn:dem":2145,
    "gn:feature_class":"P",
    "gn:feature_code":"PPL",
    "gn:name":"Gudel",
    "gn:population":0,
    "gn:timezone":"Asia/Kathmandu",
    "iso:country":"NP",
    "name:bih_x_preferred":[
        "\u0917\u0941\u0926\u0947\u0932"
    ],
    "name:ceb_x_preferred":[
        "Gudel"
    ],
    "name:deu_x_preferred":[
        "Gudel"
    ],
    "name:fra_x_preferred":[
        "Gudel"
    ],
    "name:hin_x_preferred":[
        "\u0917\u0941\u0926\u0947\u0932"
    ],
    "name:mai_x_preferred":[
        "\u0917\u0941\u0926\u0947\u0932"
    ],
    "name:msa_x_preferred":[
        "Gudel"
    ],
    "name:nep_x_preferred":[
        "\u0917\u0941\u0926\u0947\u0932"
    ],
    "name:new_x_preferred":[
        "\u0917\u0941\u0921\u0947\u0932"
    ],
    "name:pol_x_preferred":[
        "Gudel"
    ],
    "wof:name":"Gudel",
    "wof:placetype":"locality"
},
  "geometry": {"coordinates":[86.86388000000002,27.50436],"type":"Point"}
}