{
  "type": "Feature",
  "properties": {
    "gn:admin1_code":"WR",
    "gn:admin2_code":"4.0",
    "gn:admin3_code":"38.0",
    "gn:admin4_code":"380019.0",
    "gn:asciiname":"Pulchok",
    "gn:country_code":"NP",
    "gn:dem":493,
    "gn:feature_class":"P",
    "gn:feature_code":"PPLL",
    "gn:name":"Pulchok",
    "gn:population":0,
    "gn:timezone":"Asia/Kathmandu",
    "iso:country":"NP",
    "wof:name":"Pulchok",
    "wof:placetype":"locality"
},
  "geometry": {"coordinates":[84.06647,28.05586],"type":"Point"}
}