{
  "type": "Feature",
  "properties": {
    "gn:admin1_code":"WR",
    "gn:admin2_code":"8",
    "gn:admin3_code":"51.0",
    "gn:admin4_code":"510028.0",
    "gn:asciiname":"Bhartapur",
    "gn:country_code":"NP",
    "gn:dem":1298,
    "gn:feature_class":"P",
    "gn:feature_code":"PPLL",
    "gn:name":"Bhartapur",
    "gn:population":0,
    "gn:timezone":"Asia/Kathmandu",
    "iso:country":"NP",
    "wof:name":"Bhartapur",
    "wof:placetype":"locality"
},
  "geometry": {"coordinates":[83.22229,27.84666],"type":"Point"}
}