{
  "type": "Feature",
  "properties": {
    "gn:admin1_code":"WR",
    "gn:admin2_code":"8",
    "gn:admin3_code":"50.0",
    "gn:admin4_code":"500058.0",
    "gn:asciiname":"Shiwaratanpur",
    "gn:country_code":"NP",
    "gn:dem":108,
    "gn:feature_class":"P",
    "gn:feature_code":"PPLL",
    "gn:name":"Shiwaratanpur",
    "gn:population":0,
    "gn:timezone":"Asia/Kathmandu",
    "iso:country":"NP",
    "wof:name":"Shiwaratanpur",
    "wof:placetype":"locality"
},
  "geometry": {"coordinates":[83.16354,27.57214],"type":"Point"}
}