{
  "type": "Feature",
  "properties": {
    "gn:admin1_code":"CR",
    "gn:admin2_code":"5",
    "gn:admin3_code":"18",
    "gn:admin4_code":"180015.0",
    "gn:asciiname":"Koiritol",
    "gn:country_code":"NP",
    "gn:dem":127,
    "gn:feature_class":"P",
    "gn:feature_code":"PPLL",
    "gn:name":"Koiritol",
    "gn:population":0,
    "gn:timezone":"Asia/Kathmandu",
    "iso:country":"NP",
    "wof:name":"Koiritol",
    "wof:placetype":"locality"
},
  "geometry": {"coordinates":[85.85285,26.90297],"type":"Point"}
}