{
  "type": "Feature",
  "properties": {
    "gn:admin1_code":"ER",
    "gn:admin2_code":"7",
    "gn:admin3_code":"7.0",
    "gn:admin4_code":"70007.0",
    "gn:asciiname":"Sadamtar",
    "gn:country_code":"NP",
    "gn:dem":343,
    "gn:feature_class":"P",
    "gn:feature_code":"PPLL",
    "gn:name":"Sadamtar",
    "gn:population":0,
    "gn:timezone":"Asia/Kathmandu",
    "iso:country":"NP",
    "wof:name":"Sadamtar",
    "wof:placetype":"locality"
},
  "geometry": {"coordinates":[87.42626,26.95303],"type":"Point"}
}