{
  "type": "Feature",
  "properties": {
    "gn:admin1_code":"MR",
    "gn:admin2_code":"12",
    "gn:admin3_code":"56.0",
    "gn:admin4_code":"560030.0",
    "gn:asciiname":"Diukot",
    "gn:country_code":"NP",
    "gn:dem":1359,
    "gn:feature_class":"P",
    "gn:feature_code":"PPLL",
    "gn:name":"Diukot",
    "gn:population":0,
    "gn:timezone":"Asia/Kathmandu",
    "iso:country":"NP",
    "wof:name":"Diukot",
    "wof:placetype":"locality"
},
  "geometry": {"coordinates":[82.57485,28.07861],"type":"Point"}
}