{
  "type": "Feature",
  "properties": {
    "gn:admin1_code":"WR",
    "gn:admin2_code":"4",
    "gn:admin3_code":"41",
    "gn:admin4_code":"410010",
    "gn:asciiname":"Dhikur Pokhari",
    "gn:country_code":"NP",
    "gn:dem":3178,
    "gn:feature_class":"P",
    "gn:feature_code":"PPLL",
    "gn:name":"Dhikur Pokhari",
    "gn:population":0,
    "gn:timezone":"Asia/Kathmandu",
    "iso:country":"NP",
    "name:deu_x_preferred":[
        "Dhikur Pokhari"
    ],
    "name:hin_x_preferred":[
        "\u0922\u093f\u0915\u0941\u0930\u0947 \u092a\u094b\u0916\u0930\u0940"
    ],
    "name:mai_x_preferred":[
        "\u0922\u093f\u0915\u0941\u0930\u092a\u094b\u0916\u0930\u0940"
    ],
    "name:msa_x_preferred":[
        "Dhikure Pokhari"
    ],
    "name:nep_x_preferred":[
        "\u0922\u093f\u0915\u0941\u0930\u092a\u094b\u0916\u0930\u0940"
    ],
    "name:new_x_preferred":[
        "\u0922\u093f\u0915\u0941\u0930\u0947 \u092a\u094b\u0916\u0930\u0940"
    ],
    "name:pol_x_preferred":[
        "Dhikure Pokhari"
    ],
    "wof:name":"Dhikur Pokhari",
    "wof:placetype":"locality"
},
  "geometry": {"coordinates":[84.17551,28.60235],"type":"Point"}
}