{
  "type": "Feature",
  "properties": {
    "gn:admin1_code":"CR",
    "gn:admin2_code":"1",
    "gn:admin3_code":"24.0",
    "gn:admin4_code":"240036.0",
    "gn:asciiname":"Sandi",
    "gn:country_code":"NP",
    "gn:dem":678,
    "gn:feature_class":"P",
    "gn:feature_code":"PPLL",
    "gn:name":"Sandi",
    "gn:population":0,
    "gn:timezone":"Asia/Kathmandu",
    "iso:country":"NP",
    "wof:name":"Sandi",
    "wof:placetype":"locality"
},
  "geometry": {"coordinates":[85.69114,27.67247],"type":"Point"}
}