{
  "type": "Feature",
  "properties": {
    "gn:admin1_code":"ER",
    "gn:admin2_code":"7",
    "gn:admin3_code":"7.0",
    "gn:admin4_code":"70015.0",
    "gn:asciiname":"Santang",
    "gn:country_code":"NP",
    "gn:dem":507,
    "gn:feature_class":"P",
    "gn:feature_code":"PPLL",
    "gn:name":"Santang",
    "gn:population":0,
    "gn:timezone":"Asia/Kathmandu",
    "iso:country":"NP",
    "name:ceb_x_preferred":[
        "Santang"
    ],
    "name:swe_x_preferred":[
        "Santang"
    ],
    "wof:name":"Santang",
    "wof:placetype":"locality"
},
  "geometry": {"coordinates":[87.37661999999997,26.95744],"type":"Point"}
}