{
  "type": "Feature",
  "properties": {
    "gn:admin1_code":"ER",
    "gn:admin2_code":"10",
    "gn:admin3_code":"2",
    "gn:admin4_code":"20005",
    "gn:asciiname":"Maleni",
    "gn:country_code":"NP",
    "gn:dem":1009,
    "gn:feature_class":"P",
    "gn:feature_code":"PPLL",
    "gn:name":"Maleni",
    "gn:population":0,
    "gn:timezone":"Asia/Kathmandu",
    "iso:country":"NP",
    "wof:name":"Maleni",
    "wof:placetype":"locality"
},
  "geometry": {"coordinates":[87.73965,27.16902],"type":"Point"}
}