{
  "type": "Feature",
  "properties": {
    "gn:admin1_code":"CR",
    "gn:admin2_code":"5",
    "gn:admin3_code":"22.0",
    "gn:admin4_code":"220004.0",
    "gn:asciiname":"Nayanpul",
    "gn:country_code":"NP",
    "gn:dem":862,
    "gn:feature_class":"P",
    "gn:feature_code":"PPLL",
    "gn:name":"Nayanpul",
    "gn:population":0,
    "gn:timezone":"Asia/Kathmandu",
    "iso:country":"NP",
    "wof:name":"Nayanpul",
    "wof:placetype":"locality"
},
  "geometry": {"coordinates":[86.08014,27.62333],"type":"Point"}
}