{
  "type": "Feature",
  "properties": {
    "gn:admin1_code":"CR",
    "gn:admin2_code":"5",
    "gn:admin3_code":"20",
    "gn:admin4_code":"200054",
    "gn:asciiname":"Dumredanda",
    "gn:country_code":"NP",
    "gn:dem":1100,
    "gn:feature_class":"P",
    "gn:feature_code":"PPLL",
    "gn:name":"Dumredanda",
    "gn:population":0,
    "gn:timezone":"Asia/Kathmandu",
    "iso:country":"NP",
    "wof:name":"Dumredanda",
    "wof:placetype":"locality"
},
  "geometry": {"coordinates":[86.20432,27.11904],"type":"Point"}
}