{
  "type": "Feature",
  "properties": {
    "gn:admin1_code":"FR",
    "gn:admin2_code":"9",
    "gn:admin3_code":"74",
    "gn:admin4_code":"740058",
    "gn:asciiname":"Saj",
    "gn:country_code":"NP",
    "gn:dem":1317,
    "gn:feature_class":"P",
    "gn:feature_code":"PPLL",
    "gn:name":"Saj",
    "gn:population":0,
    "gn:timezone":"Asia/Kathmandu",
    "iso:country":"NP",
    "name:rus_x_preferred":[
        "\u0421\u0430\u0439"
    ],
    "wof:name":"Saj",
    "wof:placetype":"locality"
},
  "geometry": {"coordinates":[80.56896,29.42918],"type":"Point"}
}