{
  "type": "Feature",
  "properties": {
    "gn:admin1_code":"CR",
    "gn:admin2_code":"1",
    "gn:admin3_code":"30.0",
    "gn:admin4_code":"300015.0",
    "gn:asciiname":"Bardhang",
    "gn:country_code":"NP",
    "gn:dem":1346,
    "gn:feature_class":"P",
    "gn:feature_code":"PPLL",
    "gn:name":"Bardhang",
    "gn:population":0,
    "gn:timezone":"Asia/Kathmandu",
    "iso:country":"NP",
    "wof:name":"Bardhang",
    "wof:placetype":"locality"
},
  "geometry": {"coordinates":[84.96766,28.06355],"type":"Point"}
}