{
  "type": "Feature",
  "properties": {
    "gn:admin1_code":"ER",
    "gn:admin2_code":"7",
    "gn:admin3_code":"10.0",
    "gn:admin4_code":"100043.0",
    "gn:asciiname":"Gahate",
    "gn:country_code":"NP",
    "gn:dem":539,
    "gn:feature_class":"P",
    "gn:feature_code":"PPLL",
    "gn:name":"Gahate",
    "gn:population":0,
    "gn:timezone":"Asia/Kathmandu",
    "iso:country":"NP",
    "wof:name":"Gahate",
    "wof:placetype":"locality"
},
  "geometry": {"coordinates":[87.12049,27.41669000000001],"type":"Point"}
}