{
  "type": "Feature",
  "properties": {
    "gn:admin1_code":"ER",
    "gn:admin2_code":"10",
    "gn:admin3_code":"3.0",
    "gn:admin4_code":"30029.0",
    "gn:asciiname":"Gopeni",
    "gn:country_code":"NP",
    "gn:dem":1850,
    "gn:feature_class":"P",
    "gn:feature_code":"PPLL",
    "gn:name":"Gopeni",
    "gn:population":0,
    "gn:timezone":"Asia/Kathmandu",
    "iso:country":"NP",
    "wof:name":"Gopeni",
    "wof:placetype":"locality"
},
  "geometry": {"coordinates":[88.01526,26.94086],"type":"Point"}
}