{
  "type": "Feature",
  "properties": {
    "gn:admin1_code":"MR",
    "gn:admin2_code":"2",
    "gn:admin3_code":"60.0",
    "gn:admin4_code":"600033.0",
    "gn:asciiname":"Kosedhungga",
    "gn:country_code":"NP",
    "gn:dem":1632,
    "gn:feature_class":"P",
    "gn:feature_code":"PPLL",
    "gn:name":"Kosedhungga",
    "gn:population":0,
    "gn:timezone":"Asia/Kathmandu",
    "iso:country":"NP",
    "wof:name":"Kosedhungga",
    "wof:placetype":"locality"
},
  "geometry": {"coordinates":[81.63904000000002,28.79431],"type":"Point"}
}