{
  "type": "Feature",
  "properties": {
    "gn:admin1_code":"FR",
    "gn:admin2_code":"9",
    "gn:admin3_code":"74",
    "gn:admin4_code":"740019",
    "gn:asciiname":"Hajiri Dhara",
    "gn:country_code":"NP",
    "gn:dem":1902,
    "gn:feature_class":"P",
    "gn:feature_code":"PPLL",
    "gn:name":"Hajiri Dhara",
    "gn:population":0,
    "gn:timezone":"Asia/Kathmandu",
    "iso:country":"NP",
    "wof:name":"Hajiri Dhara",
    "wof:placetype":"locality"
},
  "geometry": {"coordinates":[80.71141,29.47252000000001],"type":"Point"}
}