{
  "type": "Feature",
  "properties": {
    "gn:admin1_code":"ER",
    "gn:admin2_code":"13.0",
    "gn:admin3_code":"14.0",
    "gn:admin4_code":"140001.0",
    "gn:asciiname":"Dhapeni",
    "gn:country_code":"NP",
    "gn:dem":354,
    "gn:feature_class":"P",
    "gn:feature_code":"PPLL",
    "gn:name":"Dhapeni",
    "gn:population":0,
    "gn:timezone":"Asia/Kathmandu",
    "iso:country":"NP",
    "wof:name":"Dhapeni",
    "wof:placetype":"locality"
},
  "geometry": {"coordinates":[86.72668,27.00201],"type":"Point"}
}