{
  "type": "Feature",
  "properties": {
    "gn:admin1_code":"FR",
    "gn:admin2_code":"14",
    "gn:admin3_code":"68",
    "gn:admin4_code":"680021",
    "gn:asciiname":"Kaphalseri",
    "gn:country_code":"NP",
    "gn:dem":1585,
    "gn:feature_class":"P",
    "gn:feature_code":"PPLL",
    "gn:name":"Kaphalseri",
    "gn:population":0,
    "gn:timezone":"Asia/Kathmandu",
    "iso:country":"NP",
    "wof:name":"Kaphalseri",
    "wof:placetype":"locality"
},
  "geometry": {"coordinates":[80.81435999999999,29.64388],"type":"Point"}
}