{
  "type": "Feature",
  "properties": {
    "gn:admin1_code":"WR",
    "gn:admin2_code":"8",
    "gn:admin3_code":"46.0",
    "gn:admin4_code":"460005.0",
    "gn:asciiname":"Kahung",
    "gn:country_code":"NP",
    "gn:dem":1461,
    "gn:feature_class":"P",
    "gn:feature_code":"PPLL",
    "gn:name":"Kahung",
    "gn:population":0,
    "gn:timezone":"Asia/Kathmandu",
    "iso:country":"NP",
    "wof:name":"Kahung",
    "wof:placetype":"locality"
},
  "geometry": {"coordinates":[83.58667,27.99967],"type":"Point"}
}