{
  "type": "Feature",
  "properties": {
    "gn:admin1_code":"CR",
    "gn:admin2_code":"11",
    "gn:admin3_code":"31",
    "gn:admin4_code":"310040",
    "gn:asciiname":"Goth Kholagaun",
    "gn:country_code":"NP",
    "gn:dem":362,
    "gn:feature_class":"P",
    "gn:feature_code":"PPLL",
    "gn:name":"Goth Kholagaun",
    "gn:population":0,
    "gn:timezone":"Asia/Kathmandu",
    "iso:country":"NP",
    "wof:name":"Goth Kholagaun",
    "wof:placetype":"locality"
},
  "geometry": {"coordinates":[85.22140999999998,27.34668],"type":"Point"}
}