{
  "type": "Feature",
  "properties": {
    "gn:admin1_code":"WR",
    "gn:admin2_code":"3",
    "gn:admin3_code":"44",
    "gn:admin4_code":"440037",
    "gn:asciiname":"Pallabari",
    "gn:country_code":"NP",
    "gn:dem":1056,
    "gn:feature_class":"P",
    "gn:feature_code":"PPLL",
    "gn:name":"Pallabari",
    "gn:population":0,
    "gn:timezone":"Asia/Kathmandu",
    "iso:country":"NP",
    "wof:name":"Pallabari",
    "wof:placetype":"locality"
},
  "geometry": {"coordinates":[83.6798,28.19378],"type":"Point"}
}