{
  "type": "Feature",
  "properties": {
    "gn:admin1_code":"CR",
    "gn:admin2_code":"5",
    "gn:admin3_code":"22.0",
    "gn:admin4_code":"220038.0",
    "gn:asciiname":"Keureni",
    "gn:country_code":"NP",
    "gn:dem":1898,
    "gn:feature_class":"P",
    "gn:feature_code":"PPLL",
    "gn:name":"Keureni",
    "gn:population":0,
    "gn:timezone":"Asia/Kathmandu",
    "iso:country":"NP",
    "wof:name":"Keureni",
    "wof:placetype":"locality"
},
  "geometry": {"coordinates":[86.12016,27.53203],"type":"Point"}
}