{
  "type": "Feature",
  "properties": {
    "gn:admin1_code":"CR",
    "gn:admin2_code":"5",
    "gn:admin3_code":"21",
    "gn:admin4_code":"210047",
    "gn:asciiname":"Darkha Dudhile",
    "gn:country_code":"NP",
    "gn:dem":1899,
    "gn:feature_class":"P",
    "gn:feature_code":"PPLL",
    "gn:name":"Darkha Dudhile",
    "gn:population":0,
    "gn:timezone":"Asia/Kathmandu",
    "iso:country":"NP",
    "wof:name":"Darkha Dudhile",
    "wof:placetype":"locality"
},
  "geometry": {"coordinates":[86.19689,27.55138],"type":"Point"}
}