{
  "type": "Feature",
  "properties": {
    "gn:admin1_code":"ER",
    "gn:admin2_code":"13",
    "gn:admin3_code":"12",
    "gn:admin4_code":"120039.0",
    "gn:asciiname":"Sakhare",
    "gn:country_code":"NP",
    "gn:dem":2092,
    "gn:feature_class":"P",
    "gn:feature_code":"PPLL",
    "gn:name":"Sakhare",
    "gn:population":0,
    "gn:timezone":"Asia/Kathmandu",
    "iso:country":"NP",
    "wof:name":"Sakhare",
    "wof:placetype":"locality"
},
  "geometry": {"coordinates":[86.46753000000002,27.3982],"type":"Point"}
}