{
  "type": "Feature",
  "properties": {
    "gn:admin1_code":"MR",
    "gn:admin2_code":"2.0",
    "gn:admin3_code":"57.0",
    "gn:admin4_code":"570042.0",
    "gn:asciiname":"Hawaldarpur",
    "gn:country_code":"NP",
    "gn:dem":156,
    "gn:feature_class":"P",
    "gn:feature_code":"PPLL",
    "gn:name":"Hawaldarpur",
    "gn:population":0,
    "gn:timezone":"Asia/Kathmandu",
    "iso:country":"NP",
    "wof:name":"Hawaldarpur",
    "wof:placetype":"locality"
},
  "geometry": {"coordinates":[81.66364,28.15404],"type":"Point"}
}