{
  "type": "Feature",
  "properties": {
    "gn:admin1_code":"ER",
    "gn:admin2_code":"10",
    "gn:admin3_code":"3.0",
    "gn:admin4_code":"30019.0",
    "gn:asciiname":"Nagdaha",
    "gn:country_code":"NP",
    "gn:dem":1668,
    "gn:feature_class":"P",
    "gn:feature_code":"PPLL",
    "gn:name":"Nagdaha",
    "gn:population":0,
    "gn:timezone":"Asia/Kathmandu",
    "iso:country":"NP",
    "name:nep_x_preferred":[
        "\u0928\u093e\u0917\u0926\u0939"
    ],
    "wof:name":"Nagdaha",
    "wof:placetype":"locality"
},
  "geometry": {"coordinates":[88.05839,26.98589],"type":"Point"}
}