{
  "type": "Feature",
  "properties": {
    "gn:admin1_code":"MR",
    "gn:admin2_code":"12",
    "gn:admin3_code":"55",
    "gn:admin4_code":"550045",
    "gn:asciiname":"Chalaunepani",
    "gn:country_code":"NP",
    "gn:dem":1755,
    "gn:feature_class":"P",
    "gn:feature_code":"PPLL",
    "gn:name":"Chalaunepani",
    "gn:population":0,
    "gn:timezone":"Asia/Kathmandu",
    "iso:country":"NP",
    "wof:name":"Chalaunepani",
    "wof:placetype":"locality"
},
  "geometry": {"coordinates":[82.25256,28.40034],"type":"Point"}
}