{
  "type": "Feature",
  "properties": {
    "gn:admin1_code":"CR",
    "gn:admin2_code":"5",
    "gn:admin3_code":"17.0",
    "gn:admin4_code":"170079.0",
    "gn:asciiname":"Jhitkahiya",
    "gn:country_code":"NP",
    "gn:dem":81,
    "gn:feature_class":"P",
    "gn:feature_code":"PPLL",
    "gn:name":"Jhitkahiya",
    "gn:population":0,
    "gn:timezone":"Asia/Kathmandu",
    "iso:country":"NP",
    "wof:name":"Jhitkahiya",
    "wof:placetype":"locality"
},
  "geometry": {"coordinates":[86.0204,26.73108],"type":"Point"}
}