{
  "type": "Feature",
  "properties": {
    "gn:admin1_code":"WR",
    "gn:admin2_code":"4",
    "gn:admin3_code":"40.0",
    "gn:admin4_code":"400032.0",
    "gn:asciiname":"Phulbari",
    "gn:country_code":"NP",
    "gn:dem":786,
    "gn:feature_class":"P",
    "gn:feature_code":"PPLL",
    "gn:name":"Phulbari",
    "gn:population":0,
    "gn:timezone":"Asia/Kathmandu",
    "iso:country":"NP",
    "wof:name":"Phulbari",
    "wof:placetype":"locality"
},
  "geometry": {"coordinates":[84.00057,28.17752],"type":"Point"}
}