{
  "type": "Feature",
  "properties": {
    "gn:admin1_code":"CR",
    "gn:admin2_code":"5",
    "gn:admin3_code":"22.0",
    "gn:admin4_code":"220014.0",
    "gn:asciiname":"Dandakharka",
    "gn:country_code":"NP",
    "gn:dem":1798,
    "gn:feature_class":"P",
    "gn:feature_code":"PPLL",
    "gn:name":"Dandakharka",
    "gn:population":0,
    "gn:timezone":"Asia/Kathmandu",
    "iso:country":"NP",
    "name:pol_x_preferred":[
        "Dandakharka"
    ],
    "wof:name":"Dandakharka",
    "wof:placetype":"locality"
},
  "geometry": {"coordinates":[86.03803000000001,27.51638],"type":"Point"}
}