{
  "type": "Feature",
  "properties": {
    "gn:admin1_code":"FR",
    "gn:admin2_code":"14",
    "gn:admin3_code":"69",
    "gn:admin4_code":"690024",
    "gn:asciiname":"Mantoli",
    "gn:country_code":"NP",
    "gn:dem":1606,
    "gn:feature_class":"P",
    "gn:feature_code":"PPLL",
    "gn:name":"Mantoli",
    "gn:population":0,
    "gn:timezone":"Asia/Kathmandu",
    "iso:country":"NP",
    "wof:name":"Mantoli",
    "wof:placetype":"locality"
},
  "geometry": {"coordinates":[81.32122,29.00576],"type":"Point"}
}