{
  "type": "Feature",
  "properties": {
    "gn:admin1_code":"ER",
    "gn:admin2_code":"7",
    "gn:admin3_code":"6",
    "gn:admin4_code":"60003",
    "gn:asciiname":"Dhanuktol",
    "gn:country_code":"NP",
    "gn:dem":70,
    "gn:feature_class":"P",
    "gn:feature_code":"PPLL",
    "gn:name":"Dhanuktol",
    "gn:population":0,
    "gn:timezone":"Asia/Kathmandu",
    "iso:country":"NP",
    "wof:name":"Dhanuktol",
    "wof:placetype":"locality"
},
  "geometry": {"coordinates":[87.17434,26.45585],"type":"Point"}
}