{
  "type": "Feature",
  "properties": {
    "gn:admin1_code":"MR",
    "gn:admin2_code":"2.0",
    "gn:admin3_code":"58.0",
    "gn:admin4_code":"580025.0",
    "gn:asciiname":"Bankhet",
    "gn:country_code":"NP",
    "gn:dem":178,
    "gn:feature_class":"P",
    "gn:feature_code":"PPLL",
    "gn:name":"Bankhet",
    "gn:population":0,
    "gn:timezone":"Asia/Kathmandu",
    "iso:country":"NP",
    "wof:name":"Bankhet",
    "wof:placetype":"locality"
},
  "geometry": {"coordinates":[81.23602,28.56538],"type":"Point"}
}