{
  "type": "Feature",
  "properties": {
    "gn:admin1_code":"00",
    "gn:asciiname":"Bhotekate Khola",
    "gn:country_code":"NP",
    "gn:dem":821,
    "gn:feature_class":"P",
    "gn:feature_code":"PPL",
    "gn:name":"Bho\u1e6dek\u0101\u1e6de Khol\u0101",
    "gn:population":0,
    "gn:timezone":"Asia/Kathmandu",
    "iso:country":"NP",
    "wof:name":"Bhotekate Khola",
    "wof:placetype":"locality"
},
  "geometry": {"coordinates":[85.65838000000002,27.60659],"type":"Point"}
}