{
  "type": "Feature",
  "properties": {
    "gn:admin1_code":"ER",
    "gn:admin2_code":"10",
    "gn:admin3_code":"4.0",
    "gn:admin4_code":"40017.0",
    "gn:asciiname":"Toribari",
    "gn:country_code":"NP",
    "gn:dem":104,
    "gn:feature_class":"P",
    "gn:feature_code":"PPLL",
    "gn:name":"Toribari",
    "gn:population":0,
    "gn:timezone":"Asia/Kathmandu",
    "iso:country":"NP",
    "wof:name":"Toribari",
    "wof:placetype":"locality"
},
  "geometry": {"coordinates":[87.96148000000002,26.57865],"type":"Point"}
}