{
  "type": "Feature",
  "properties": {
    "gn:admin1_code":"ER",
    "gn:admin2_code":"10",
    "gn:admin3_code":"3.0",
    "gn:admin4_code":"30002.0",
    "gn:asciiname":"Jhilke",
    "gn:country_code":"NP",
    "gn:dem":289,
    "gn:feature_class":"P",
    "gn:feature_code":"PPLL",
    "gn:name":"Jhilke",
    "gn:population":0,
    "gn:timezone":"Asia/Kathmandu",
    "iso:country":"NP",
    "wof:name":"Jhilke",
    "wof:placetype":"locality"
},
  "geometry": {"coordinates":[87.76275,26.75402],"type":"Point"}
}