{
  "type": "Feature",
  "properties": {
    "gn:admin1_code":"CR",
    "gn:admin2_code":"1",
    "gn:admin3_code":"27.0",
    "gn:admin4_code":"270038.0",
    "gn:asciiname":"Gairigaun",
    "gn:country_code":"NP",
    "gn:dem":1356,
    "gn:feature_class":"P",
    "gn:feature_code":"PPLL",
    "gn:name":"Gairigaun",
    "gn:population":0,
    "gn:timezone":"Asia/Kathmandu",
    "iso:country":"NP",
    "wof:name":"Gairigaun",
    "wof:placetype":"locality"
},
  "geometry": {"coordinates":[85.30775,27.75577],"type":"Point"}
}