{
  "type": "Feature",
  "properties": {
    "gn:admin1_code":"ER",
    "gn:admin2_code":"13",
    "gn:admin3_code":"13",
    "gn:admin4_code":"130052",
    "gn:asciiname":"Rangbhange",
    "gn:country_code":"NP",
    "gn:dem":1078,
    "gn:feature_class":"P",
    "gn:feature_code":"PPLL",
    "gn:name":"Rangbhange",
    "gn:population":0,
    "gn:timezone":"Asia/Kathmandu",
    "iso:country":"NP",
    "wof:name":"Rangbhange",
    "wof:placetype":"locality"
},
  "geometry": {"coordinates":[86.87116,26.93857],"type":"Point"}
}