{
  "type": "Feature",
  "properties": {
    "gn:admin1_code":"ER",
    "gn:admin2_code":"7.0",
    "gn:admin3_code":"8.0",
    "gn:admin4_code":"80015.0",
    "gn:asciiname":"Khurkute",
    "gn:country_code":"NP",
    "gn:dem":1478,
    "gn:feature_class":"P",
    "gn:feature_code":"PPLL",
    "gn:name":"Khurkute",
    "gn:population":0,
    "gn:timezone":"Asia/Kathmandu",
    "iso:country":"NP",
    "wof:name":"Khurkute",
    "wof:placetype":"locality"
},
  "geometry": {"coordinates":[87.54879,27.11949000000001],"type":"Point"}
}