{
  "type": "Feature",
  "properties": {
    "gn:admin1_code":"WR",
    "gn:admin2_code":"4",
    "gn:admin3_code":"36.0",
    "gn:admin4_code":"360045.0",
    "gn:asciiname":"Seprak",
    "gn:country_code":"NP",
    "gn:dem":1096,
    "gn:feature_class":"P",
    "gn:feature_code":"PPLL",
    "gn:name":"Seprak",
    "gn:population":0,
    "gn:timezone":"Asia/Kathmandu",
    "iso:country":"NP",
    "wof:name":"Seprak",
    "wof:placetype":"locality"
},
  "geometry": {"coordinates":[84.69315999999998,27.93405],"type":"Point"}
}