{
  "type": "Feature",
  "properties": {
    "gn:admin1_code":"CR",
    "gn:admin2_code":"1",
    "gn:admin3_code":"23",
    "gn:admin4_code":"230012",
    "gn:asciiname":"Rokatol",
    "gn:country_code":"NP",
    "gn:dem":1421,
    "gn:feature_class":"P",
    "gn:feature_code":"PPLL",
    "gn:name":"Rokatol",
    "gn:population":0,
    "gn:timezone":"Asia/Kathmandu",
    "iso:country":"NP",
    "wof:name":"Rokatol",
    "wof:placetype":"locality"
},
  "geometry": {"coordinates":[85.51319000000002,27.79619000000001],"type":"Point"}
}