{
  "type": "Feature",
  "properties": {
    "gn:admin1_code":"FR",
    "gn:admin2_code":"9",
    "gn:admin3_code":"73.0",
    "gn:admin4_code":"730010.0",
    "gn:asciiname":"Dudh pokhari",
    "gn:country_code":"NP",
    "gn:dem":1581,
    "gn:feature_class":"P",
    "gn:feature_code":"PPLL",
    "gn:name":"Dudh pokhari",
    "gn:population":0,
    "gn:timezone":"Asia/Kathmandu",
    "iso:country":"NP",
    "wof:name":"Dudh pokhari",
    "wof:placetype":"locality"
},
  "geometry": {"coordinates":[80.48793000000001,29.38448],"type":"Point"}
}