{
  "type": "Feature",
  "properties": {
    "gn:admin1_code":"ER",
    "gn:admin2_code":"13",
    "gn:admin3_code":"13.0",
    "gn:admin4_code":"130013.0",
    "gn:asciiname":"Mahabir",
    "gn:country_code":"NP",
    "gn:dem":1448,
    "gn:feature_class":"P",
    "gn:feature_code":"PPLL",
    "gn:name":"Mahabir",
    "gn:population":0,
    "gn:timezone":"Asia/Kathmandu",
    "iso:country":"NP",
    "wof:name":"Mahabir",
    "wof:placetype":"locality"
},
  "geometry": {"coordinates":[86.71850000000001,27.19633],"type":"Point"}
}