{
  "type": "Feature",
  "properties": {
    "gn:admin1_code":"ER",
    "gn:admin2_code":"7",
    "gn:admin3_code":"5",
    "gn:admin4_code":"50055",
    "gn:asciiname":"Banarjhula",
    "gn:country_code":"NP",
    "gn:dem":100,
    "gn:feature_class":"P",
    "gn:feature_code":"PPLL",
    "gn:name":"Banarjhula",
    "gn:population":0,
    "gn:timezone":"Asia/Kathmandu",
    "iso:country":"NP",
    "name:bih_x_preferred":[
        "\u092c\u0928\u0930\u091d\u0941\u0932\u093e"
    ],
    "name:ceb_x_preferred":[
        "Banarjhula"
    ],
    "name:fra_x_preferred":[
        "Banarjhula"
    ],
    "name:mai_x_preferred":[
        "\u092c\u0928\u0930\u091d\u0941\u0932\u093e"
    ],
    "name:msa_x_preferred":[
        "Banarjhula"
    ],
    "name:nep_x_preferred":[
        "\u092c\u0928\u0930\u091d\u0941\u0932\u093e"
    ],
    "name:new_x_preferred":[
        "\u092c\u0928\u0930\u091d\u0941\u0932\u093e"
    ],
    "name:pol_x_preferred":[
        "Banarjhula"
    ],
    "wof:name":"Banarjhula",
    "wof:placetype":"locality"
},
  "geometry": {"coordinates":[87.29698,26.6013],"type":"Point"}
}