{
  "type": "Feature",
  "properties": {
    "gn:admin1_code":"WR",
    "gn:admin2_code":"8",
    "gn:admin3_code":"51.0",
    "gn:admin4_code":"510001.0",
    "gn:asciiname":"Kur Dewichaur",
    "gn:country_code":"NP",
    "gn:dem":1502,
    "gn:feature_class":"P",
    "gn:feature_code":"PPLL",
    "gn:name":"Kur Dewichaur",
    "gn:population":0,
    "gn:timezone":"Asia/Kathmandu",
    "iso:country":"NP",
    "wof:name":"Kur Dewichaur",
    "wof:placetype":"locality"
},
  "geometry": {"coordinates":[83.19320999999999,27.91714],"type":"Point"}
}