{
  "type": "Feature",
  "properties": {
    "gn:admin1_code":"ER",
    "gn:admin2_code":"13.0",
    "gn:admin3_code":"14.0",
    "gn:admin4_code":"140033.0",
    "gn:asciiname":"Barrebari",
    "gn:country_code":"NP",
    "gn:dem":404,
    "gn:feature_class":"P",
    "gn:feature_code":"PPLL",
    "gn:name":"Barrebari",
    "gn:population":0,
    "gn:timezone":"Asia/Kathmandu",
    "iso:country":"NP",
    "wof:name":"Barrebari",
    "wof:placetype":"locality"
},
  "geometry": {"coordinates":[86.44407,27.12047],"type":"Point"}
}