{
  "type": "Feature",
  "properties": {
    "gn:admin1_code":"ER",
    "gn:admin2_code":"13",
    "gn:admin3_code":"15",
    "gn:admin4_code":"150101",
    "gn:asciiname":"Sehara",
    "gn:country_code":"NP",
    "gn:dem":92,
    "gn:feature_class":"P",
    "gn:feature_code":"PPLL",
    "gn:name":"Sehara",
    "gn:population":0,
    "gn:timezone":"Asia/Kathmandu",
    "iso:country":"NP",
    "wof:name":"Sehara",
    "wof:placetype":"locality"
},
  "geometry": {"coordinates":[86.52866,26.58157000000001],"type":"Point"}
}