{
  "type": "Feature",
  "properties": {
    "gn:admin1_code":"WR",
    "gn:admin2_code":"4",
    "gn:admin3_code":"41",
    "gn:admin4_code":"410008",
    "gn:asciiname":"Jomsong Himal",
    "gn:country_code":"NP",
    "gn:dem":5485,
    "gn:feature_class":"P",
    "gn:feature_code":"PPLL",
    "gn:name":"Jomsong Himal",
    "gn:population":0,
    "gn:timezone":"Asia/Kathmandu",
    "iso:country":"NP",
    "wof:name":"Jomsong Himal",
    "wof:placetype":"locality"
},
  "geometry": {"coordinates":[84.13861999999997,28.84434000000001],"type":"Point"}
}