{
  "type": "Feature",
  "properties": {
    "gn:admin1_code":"WR",
    "gn:admin2_code":"8",
    "gn:admin3_code":"47",
    "gn:admin4_code":"470004",
    "gn:asciiname":"Sukha Dhamar",
    "gn:country_code":"NP",
    "gn:dem":1000,
    "gn:feature_class":"P",
    "gn:feature_code":"PPLL",
    "gn:name":"Sukha Dhamar",
    "gn:population":0,
    "gn:timezone":"Asia/Kathmandu",
    "iso:country":"NP",
    "wof:name":"Sukha Dhamar",
    "wof:placetype":"locality"
},
  "geometry": {"coordinates":[83.29635,27.79533],"type":"Point"}
}