{
  "type": "Feature",
  "properties": {
    "gn:admin1_code":"WR",
    "gn:admin2_code":"3",
    "gn:admin3_code":"44",
    "gn:admin4_code":"440047.0",
    "gn:asciiname":"Tiure",
    "gn:country_code":"NP",
    "gn:dem":1241,
    "gn:feature_class":"P",
    "gn:feature_code":"PPLL",
    "gn:name":"Tiure",
    "gn:population":0,
    "gn:timezone":"Asia/Kathmandu",
    "iso:country":"NP",
    "wof:name":"Tiure",
    "wof:placetype":"locality"
},
  "geometry": {"coordinates":[83.69011999999999,28.17185],"type":"Point"}
}