{
  "type": "Feature",
  "properties": {
    "iso:country":"NP",
    "qs:gn_country":"NP",
    "qs:gn_fcode":"ADM3",
    "qs:gn_pop":217498,
    "qs:name":"Rolpa",
    "qs:name_adm0":"Nepal",
    "qs:name_adm1":"Madhya Pashchimanchal",
    "qs:photos":0,
    "qs:photos_1k":0,
    "qs:photos_9k":0,
    "qs:photos_9r":0,
    "qs:photos_all":0,
    "qs:photos_sr":0,
    "qs:placetype":"LocalAdmin",
    "qs:pop_sr":"10",
    "qs:woe_adm0":23424911,
    "wof:name":"Rolpa",
    "wof:placetype":"localadmin",
    "wof:population":217498
},
  "geometry": {"coordinates":[82.75,28.41667],"type":"Point"}
}