{
  "type": "Feature",
  "properties": {
    "gn:admin1_code":"ER",
    "gn:admin2_code":"7.0",
    "gn:admin3_code":"8.0",
    "gn:admin4_code":"80017.0",
    "gn:asciiname":"Bhainse",
    "gn:country_code":"NP",
    "gn:dem":2129,
    "gn:feature_class":"P",
    "gn:feature_code":"PPLL",
    "gn:name":"Bhainse",
    "gn:population":0,
    "gn:timezone":"Asia/Kathmandu",
    "iso:country":"NP",
    "wof:name":"Bhainse",
    "wof:placetype":"locality"
},
  "geometry": {"coordinates":[87.56744,27.20206],"type":"Point"}
}