{
  "type": "Feature",
  "properties": {
    "gn:admin1_code":"WR",
    "gn:admin2_code":"4.0",
    "gn:admin3_code":"38.0",
    "gn:admin4_code":"380031.0",
    "gn:asciiname":"Baniya Dihi",
    "gn:country_code":"NP",
    "gn:dem":457,
    "gn:feature_class":"P",
    "gn:feature_code":"PPLL",
    "gn:name":"Baniya Dihi",
    "gn:population":0,
    "gn:timezone":"Asia/Kathmandu",
    "iso:country":"NP",
    "wof:name":"Baniya Dihi",
    "wof:placetype":"locality"
},
  "geometry": {"coordinates":[84.2445,28.08208],"type":"Point"}
}