{
  "type": "Feature",
  "properties": {
    "gn:admin1_code":"CR",
    "gn:admin2_code":"1",
    "gn:admin3_code":"28",
    "gn:admin4_code":"280038",
    "gn:asciiname":"Simpani",
    "gn:country_code":"NP",
    "gn:dem":684,
    "gn:feature_class":"P",
    "gn:feature_code":"PPLL",
    "gn:name":"Simpani",
    "gn:population":0,
    "gn:timezone":"Asia/Kathmandu",
    "iso:country":"NP",
    "name:fra_x_preferred":[
        "Simpani"
    ],
    "name:new_x_preferred":[
        "\u0938\u093f\u092e\u094d\u092a\u093e\u0928\u0940"
    ],
    "name:pol_x_preferred":[
        "Simpani"
    ],
    "wof:name":"Simpani",
    "wof:placetype":"locality"
},
  "geometry": {"coordinates":[85.16545000000001,27.87877000000001],"type":"Point"}
}