{
  "type": "Feature",
  "properties": {
    "gn:admin1_code":"CR",
    "gn:admin2_code":"5",
    "gn:admin3_code":"22.0",
    "gn:admin4_code":"220002.0",
    "gn:asciiname":"Babare",
    "gn:country_code":"NP",
    "gn:dem":1618,
    "gn:feature_class":"P",
    "gn:feature_code":"PPLL",
    "gn:name":"Babare",
    "gn:population":0,
    "gn:timezone":"Asia/Kathmandu",
    "iso:country":"NP",
    "name:bih_x_preferred":[
        "\u092c\u093e\u092c\u0930\u0947"
    ],
    "name:ceb_x_preferred":[
        "Babare"
    ],
    "name:mai_x_preferred":[
        "\u092c\u093e\u092c\u0930\u0947"
    ],
    "name:msa_x_preferred":[
        "Babare"
    ],
    "name:nep_x_preferred":[
        "\u092c\u093e\u092c\u0930\u0947"
    ],
    "name:new_x_preferred":[
        "\u092c\u093e\u092c\u0930\u0947"
    ],
    "name:pol_x_preferred":[
        "Babare"
    ],
    "wof:name":"Babare",
    "wof:placetype":"locality"
},
  "geometry": {"coordinates":[86.12151,27.77647],"type":"Point"}
}