{
  "type": "Feature",
  "properties": {
    "gn:admin1_code":"ER",
    "gn:admin2_code":"7",
    "gn:admin3_code":"10.0",
    "gn:admin4_code":"100035.0",
    "gn:asciiname":"Wadumla",
    "gn:country_code":"NP",
    "gn:dem":1631,
    "gn:feature_class":"P",
    "gn:feature_code":"PPLL",
    "gn:name":"Wadumla",
    "gn:population":0,
    "gn:timezone":"Asia/Kathmandu",
    "iso:country":"NP",
    "wof:name":"Wadumla",
    "wof:placetype":"locality"
},
  "geometry": {"coordinates":[86.98033000000002,27.18269],"type":"Point"}
}