{
  "type": "Feature",
  "properties": {
    "gn:admin1_code":"CR",
    "gn:admin2_code":"5",
    "gn:admin3_code":"22.0",
    "gn:admin4_code":"220006.0",
    "gn:asciiname":"Pata",
    "gn:country_code":"NP",
    "gn:dem":1923,
    "gn:feature_class":"P",
    "gn:feature_code":"PPLL",
    "gn:name":"Pata",
    "gn:population":0,
    "gn:timezone":"Asia/Kathmandu",
    "iso:country":"NP",
    "wof:name":"Pata",
    "wof:placetype":"locality"
},
  "geometry": {"coordinates":[85.93751999999998,27.65278],"type":"Point"}
}