{
  "type": "Feature",
  "properties": {
    "gn:admin1_code":"WR",
    "gn:admin2_code":"4.0",
    "gn:admin3_code":"38.0",
    "gn:admin4_code":"380002.0",
    "gn:asciiname":"Phulumthan",
    "gn:country_code":"NP",
    "gn:dem":1000,
    "gn:feature_class":"P",
    "gn:feature_code":"PPLL",
    "gn:name":"Phulumthan",
    "gn:population":0,
    "gn:timezone":"Asia/Kathmandu",
    "iso:country":"NP",
    "wof:name":"Phulumthan",
    "wof:placetype":"locality"
},
  "geometry": {"coordinates":[84.01345000000001,27.97804],"type":"Point"}
}