{
  "type": "Feature",
  "properties": {
    "gn:admin1_code":"ER",
    "gn:admin2_code":"7",
    "gn:admin3_code":"5",
    "gn:admin4_code":"50060.0",
    "gn:asciiname":"Kalidaha",
    "gn:country_code":"NP",
    "gn:dem":219,
    "gn:feature_class":"P",
    "gn:feature_code":"PPLL",
    "gn:name":"Kalidaha",
    "gn:population":0,
    "gn:timezone":"Asia/Kathmandu",
    "iso:country":"NP",
    "wof:name":"Kalidaha",
    "wof:placetype":"locality"
},
  "geometry": {"coordinates":[87.63191999999999,26.75445],"type":"Point"}
}