{
  "type": "Feature",
  "properties": {
    "gn:admin1_code":"WR",
    "gn:admin2_code":"8",
    "gn:admin3_code":"49",
    "gn:admin4_code":"490019",
    "gn:asciiname":"Purana Pani",
    "gn:country_code":"NP",
    "gn:dem":510,
    "gn:feature_class":"P",
    "gn:feature_code":"PPLL",
    "gn:name":"Purana Pani",
    "gn:population":0,
    "gn:timezone":"Asia/Kathmandu",
    "iso:country":"NP",
    "wof:name":"Purana Pani",
    "wof:placetype":"locality"
},
  "geometry": {"coordinates":[83.55945,27.69965],"type":"Point"}
}