{
  "type": "Feature",
  "properties": {
    "gn:admin1_code":"00",
    "gn:asciiname":"Ikchun",
    "gn:country_code":"NP",
    "gn:dem":1168,
    "gn:feature_class":"P",
    "gn:feature_code":"PPL",
    "gn:name":"Ikchu\u1e45",
    "gn:population":0,
    "gn:timezone":"Asia/Kathmandu",
    "iso:country":"NP",
    "name:nep_x_preferred":[
        "Ikchu\u1e45"
    ],
    "wof:name":"Ikchun",
    "wof:placetype":"locality"
},
  "geometry": {"coordinates":[85.09756999999998,27.49849],"type":"Point"}
}