{
  "type": "Feature",
  "properties": {
    "gn:admin1_code":"ER",
    "gn:admin2_code":"10.0",
    "gn:admin3_code":"1.0",
    "gn:admin4_code":"10025.0",
    "gn:asciiname":"Bhirgaun",
    "gn:country_code":"NP",
    "gn:dem":1587,
    "gn:feature_class":"P",
    "gn:feature_code":"PPLL",
    "gn:name":"Bhirgaun",
    "gn:population":0,
    "gn:timezone":"Asia/Kathmandu",
    "iso:country":"NP",
    "wof:name":"Bhirgaun",
    "wof:placetype":"locality"
},
  "geometry": {"coordinates":[87.65276,27.28352000000001],"type":"Point"}
}