{
  "type": "Feature",
  "properties": {
    "gn:admin1_code":"MR",
    "gn:admin2_code":"12",
    "gn:admin3_code":"53",
    "gn:admin4_code":"530033",
    "gn:asciiname":"Pharsachaur",
    "gn:country_code":"NP",
    "gn:dem":1001,
    "gn:feature_class":"P",
    "gn:feature_code":"PPLL",
    "gn:name":"Pharsachaur",
    "gn:population":0,
    "gn:timezone":"Asia/Kathmandu",
    "iso:country":"NP",
    "wof:name":"Pharsachaur",
    "wof:placetype":"locality"
},
  "geometry": {"coordinates":[82.73246999999998,28.26075],"type":"Point"}
}