{
  "type": "Feature",
  "properties": {
    "gn:admin1_code":"CR",
    "gn:admin2_code":"1",
    "gn:admin3_code":"25",
    "gn:admin4_code":"250024",
    "gn:asciiname":"Dandagaun",
    "gn:country_code":"NP",
    "gn:dem":1399,
    "gn:feature_class":"P",
    "gn:feature_code":"PPLL",
    "gn:name":"Dandagaun",
    "gn:population":0,
    "gn:timezone":"Asia/Kathmandu",
    "iso:country":"NP",
    "wof:name":"Dandagaun",
    "wof:placetype":"locality"
},
  "geometry": {"coordinates":[85.34115,27.602],"type":"Point"}
}