{
  "type": "Feature",
  "properties": {
    "gn:admin1_code":"WR",
    "gn:admin2_code":"3",
    "gn:admin3_code":"44",
    "gn:admin4_code":"440014.0",
    "gn:asciiname":"Ranipani",
    "gn:country_code":"NP",
    "gn:dem":866,
    "gn:feature_class":"P",
    "gn:feature_code":"PPLL",
    "gn:name":"Ranipani",
    "gn:population":0,
    "gn:timezone":"Asia/Kathmandu",
    "iso:country":"NP",
    "wof:name":"Ranipani",
    "wof:placetype":"locality"
},
  "geometry": {"coordinates":[83.57571,28.05069],"type":"Point"}
}