{
  "type": "Feature",
  "properties": {
    "gn:admin1_code":"WR",
    "gn:admin2_code":"4",
    "gn:admin3_code":"40.0",
    "gn:admin4_code":"400032.0",
    "gn:asciiname":"Bhadrakali temple",
    "gn:country_code":"NP",
    "gn:dem":854,
    "gn:feature_class":"P",
    "gn:feature_code":"PPLL",
    "gn:name":"Bhadrakali temple",
    "gn:population":0,
    "gn:timezone":"Asia/Kathmandu",
    "iso:country":"NP",
    "wof:name":"Bhadrakali temple",
    "wof:placetype":"locality"
},
  "geometry": {"coordinates":[84.00981,28.21423],"type":"Point"}
}