{
  "type": "Feature",
  "properties": {
    "gn:admin1_code":"CR",
    "gn:admin2_code":"11.0",
    "gn:admin3_code":"33.0",
    "gn:admin4_code":"330091.0",
    "gn:asciiname":"Bairiya",
    "gn:country_code":"NP",
    "gn:dem":83,
    "gn:feature_class":"P",
    "gn:feature_code":"PPLL",
    "gn:name":"Bairiya",
    "gn:population":0,
    "gn:timezone":"Asia/Kathmandu",
    "iso:country":"NP",
    "name:ceb_x_preferred":[
        "Bairiya"
    ],
    "name:hin_x_preferred":[
        "\u092c\u0948\u0930\u093f\u092f\u093e"
    ],
    "name:mai_x_preferred":[
        "\u092c\u0948\u0930\u093f\u092f\u093e"
    ],
    "name:msa_x_preferred":[
        "Bairiya"
    ],
    "name:new_x_preferred":[
        "\u092c\u0948\u0930\u093f\u092f\u093e"
    ],
    "name:pol_x_preferred":[
        "Bairiya"
    ],
    "wof:name":"Bairiya",
    "wof:placetype":"locality"
},
  "geometry": {"coordinates":[85.09354999999999,26.87812],"type":"Point"}
}