{
  "type": "Feature",
  "properties": {
    "gn:admin1_code":"MR",
    "gn:admin2_code":"2.0",
    "gn:admin3_code":"59.0",
    "gn:admin4_code":"590049.0",
    "gn:asciiname":"Kuta",
    "gn:country_code":"NP",
    "gn:dem":336,
    "gn:feature_class":"P",
    "gn:feature_code":"PPLL",
    "gn:name":"Kuta",
    "gn:population":0,
    "gn:timezone":"Asia/Kathmandu",
    "iso:country":"NP",
    "name:ace_x_preferred":[
        "Kuta"
    ],
    "name:bos_x_preferred":[
        "Kuta"
    ],
    "name:ceb_x_preferred":[
        "Kuta"
    ],
    "name:ces_x_preferred":[
        "Kuta"
    ],
    "name:dan_x_preferred":[
        "Kuta"
    ],
    "name:deu_x_preferred":[
        "Kuta"
    ],
    "name:fin_x_preferred":[
        "Kuta"
    ],
    "name:fra_x_preferred":[
        "Kuta"
    ],
    "name:hin_x_preferred":[
        "\u0915\u0942\u091f\u093e"
    ],
    "name:ind_x_preferred":[
        "Kuta"
    ],
    "name:ita_x_preferred":[
        "Kuta"
    ],
    "name:jav_x_preferred":[
        "Kuta"
    ],
    "name:kan_x_preferred":[
        "\u0c95\u0cc1\u0ca4"
    ],
    "name:mlg_x_preferred":[
        "Kuta"
    ],
    "name:msa_x_preferred":[
        "Kuta"
    ],
    "name:nld_x_preferred":[
        "Kuta"
    ],
    "name:nor_x_preferred":[
        "Kuta"
    ],
    "name:pol_x_preferred":[
        "Kuta"
    ],
    "name:por_x_preferred":[
        "Kuta"
    ],
    "name:rus_x_preferred":[
        "\u041a\u0443\u0442\u0430"
    ],
    "name:swe_x_preferred":[
        "Kuta"
    ],
    "wof:name":"Kuta",
    "wof:placetype":"locality"
},
  "geometry": {"coordinates":[81.40300000000001,28.69156],"type":"Point"}
}