{
  "type": "Feature",
  "properties": {
    "gn:admin1_code":"MR",
    "gn:admin2_code":"2.0",
    "gn:admin3_code":"59.0",
    "gn:admin4_code":"590049.0",
    "gn:asciiname":"Kuta",
    "gn:country_code":"NP",
    "gn:dem":336,
    "gn:feature_class":"P",
    "gn:feature_code":"PPLL",
    "gn:name":"Kuta",
    "gn:population":0,
    "gn:timezone":"Asia/Kathmandu",
    "iso:country":"NP",
    "wof:name":"Kuta",
    "wof:placetype":"locality"
},
  "geometry": {"coordinates":[81.40300000000001,28.69156],"type":"Point"}
}