{
  "type": "Feature",
  "properties": {
    "gn:admin1_code":"CR",
    "gn:admin2_code":"1",
    "gn:admin3_code":"23",
    "gn:admin4_code":"230024",
    "gn:asciiname":"Kipiche",
    "gn:country_code":"NP",
    "gn:dem":952,
    "gn:feature_class":"P",
    "gn:feature_code":"PPLL",
    "gn:name":"Kipiche",
    "gn:population":0,
    "gn:timezone":"Asia/Kathmandu",
    "iso:country":"NP",
    "wof:name":"Kipiche",
    "wof:placetype":"locality"
},
  "geometry": {"coordinates":[85.75431,27.87099000000001],"type":"Point"}
}