{
  "type": "Feature",
  "properties": {
    "gn:admin1_code":"FR",
    "gn:admin2_code":"14",
    "gn:admin3_code":"70.0",
    "gn:admin4_code":"700044.0",
    "gn:asciiname":"Airoda",
    "gn:country_code":"NP",
    "gn:dem":1396,
    "gn:feature_class":"P",
    "gn:feature_code":"PPLL",
    "gn:name":"Airoda",
    "gn:population":0,
    "gn:timezone":"Asia/Kathmandu",
    "iso:country":"NP",
    "wof:name":"Airoda",
    "wof:placetype":"locality"
},
  "geometry": {"coordinates":[80.70515999999998,29.13558],"type":"Point"}
}