{
  "type": "Feature",
  "properties": {
    "gn:admin1_code":"ER",
    "gn:admin2_code":"10",
    "gn:admin3_code":"2",
    "gn:admin4_code":"20004",
    "gn:asciiname":"Anpchok",
    "gn:country_code":"NP",
    "gn:dem":1408,
    "gn:feature_class":"P",
    "gn:feature_code":"PPLL",
    "gn:name":"Anpchok",
    "gn:population":0,
    "gn:timezone":"Asia/Kathmandu",
    "iso:country":"NP",
    "wof:name":"Anpchok",
    "wof:placetype":"locality"
},
  "geometry": {"coordinates":[87.76775000000001,27.25994],"type":"Point"}
}