{
  "type": "Feature",
  "properties": {
    "gn:admin1_code":"WR",
    "gn:admin2_code":"4",
    "gn:admin3_code":"36.0",
    "gn:admin4_code":"360033.0",
    "gn:asciiname":"Kupregaun",
    "gn:country_code":"NP",
    "gn:dem":1068,
    "gn:feature_class":"P",
    "gn:feature_code":"PPLL",
    "gn:name":"Kupregaun",
    "gn:population":0,
    "gn:timezone":"Asia/Kathmandu",
    "iso:country":"NP",
    "wof:name":"Kupregaun",
    "wof:placetype":"locality"
},
  "geometry": {"coordinates":[84.59026999999998,28.13707],"type":"Point"}
}