{
  "type": "Feature",
  "properties": {
    "gn:admin1_code":"CR",
    "gn:admin2_code":"1",
    "gn:admin3_code":"28",
    "gn:admin4_code":"280061",
    "gn:asciiname":"Sole Bajar",
    "gn:country_code":"NP",
    "gn:dem":628,
    "gn:feature_class":"P",
    "gn:feature_code":"PPLL",
    "gn:name":"Sole Bajar",
    "gn:population":0,
    "gn:timezone":"Asia/Kathmandu",
    "iso:country":"NP",
    "wof:name":"Sole Bajar",
    "wof:placetype":"locality"
},
  "geometry": {"coordinates":[85.18109,27.98232],"type":"Point"}
}