{
  "type": "Feature",
  "properties": {
    "gn:admin1_code":"CR",
    "gn:admin2_code":"5",
    "gn:admin3_code":"19",
    "gn:admin4_code":"190035",
    "gn:asciiname":"Harkatwa",
    "gn:country_code":"NP",
    "gn:dem":128,
    "gn:feature_class":"P",
    "gn:feature_code":"PPLL",
    "gn:name":"Harkatwa",
    "gn:population":0,
    "gn:timezone":"Asia/Kathmandu",
    "iso:country":"NP",
    "wof:name":"Harkatwa",
    "wof:placetype":"locality"
},
  "geometry": {"coordinates":[85.70169,26.96789],"type":"Point"}
}