{
  "type": "Feature",
  "properties": {
    "gn:admin1_code":"MR",
    "gn:admin2_code":"12",
    "gn:admin3_code":"56.0",
    "gn:admin4_code":"560001.0",
    "gn:asciiname":"Uttar Khilatpur",
    "gn:country_code":"NP",
    "gn:dem":713,
    "gn:feature_class":"P",
    "gn:feature_code":"PPLL",
    "gn:name":"Uttar Khilatpur",
    "gn:population":0,
    "gn:timezone":"Asia/Kathmandu",
    "iso:country":"NP",
    "wof:name":"Uttar Khilatpur",
    "wof:placetype":"locality"
},
  "geometry": {"coordinates":[82.15895999999999,28.19536],"type":"Point"}
}