{
  "type": "Feature",
  "properties": {
    "gn:admin1_code":"WR",
    "gn:admin2_code":"4",
    "gn:admin3_code":"36.0",
    "gn:admin4_code":"360059.0",
    "gn:asciiname":"Mathillo Masar",
    "gn:country_code":"NP",
    "gn:dem":831,
    "gn:feature_class":"P",
    "gn:feature_code":"PPLL",
    "gn:name":"Mathillo Masar",
    "gn:population":0,
    "gn:timezone":"Asia/Kathmandu",
    "iso:country":"NP",
    "wof:name":"Mathillo Masar",
    "wof:placetype":"locality"
},
  "geometry": {"coordinates":[84.66916999999999,28.07794],"type":"Point"}
}