{
  "type": "Feature",
  "properties": {
    "gn:admin1_code":"WR",
    "gn:admin2_code":"3",
    "gn:admin3_code":"44",
    "gn:admin4_code":"440006",
    "gn:asciiname":"Phata",
    "gn:country_code":"NP",
    "gn:dem":1730,
    "gn:feature_class":"P",
    "gn:feature_code":"PPLL",
    "gn:name":"Phata",
    "gn:population":0,
    "gn:timezone":"Asia/Kathmandu",
    "iso:country":"NP",
    "wof:name":"Phata",
    "wof:placetype":"locality"
},
  "geometry": {"coordinates":[83.63654,28.2923],"type":"Point"}
}