{
  "type": "Feature",
  "properties": {
    "gn:admin1_code":"WR",
    "gn:admin2_code":"3",
    "gn:admin3_code":"45.0",
    "gn:admin4_code":"450008.0",
    "gn:asciiname":"Manu",
    "gn:country_code":"NP",
    "gn:dem":1752,
    "gn:feature_class":"P",
    "gn:feature_code":"PPLL",
    "gn:name":"Manu",
    "gn:population":0,
    "gn:timezone":"Asia/Kathmandu",
    "iso:country":"NP",
    "wof:name":"Manu",
    "wof:placetype":"locality"
},
  "geometry": {"coordinates":[83.45119,28.2622],"type":"Point"}
}