{
  "type": "Feature",
  "properties": {
    "gn:admin1_code":"CR",
    "gn:admin2_code":"1",
    "gn:admin3_code":"25",
    "gn:admin4_code":"250038",
    "gn:asciiname":"Chokhel",
    "gn:country_code":"NP",
    "gn:dem":1365,
    "gn:feature_class":"P",
    "gn:feature_code":"PPLL",
    "gn:name":"Chokhel",
    "gn:population":0,
    "gn:timezone":"Asia/Kathmandu",
    "iso:country":"NP",
    "wof:name":"Chokhel",
    "wof:placetype":"locality"
},
  "geometry": {"coordinates":[85.32101,27.64061],"type":"Point"}
}