{
  "type": "Feature",
  "properties": {
    "gn:admin1_code":"FR",
    "gn:admin2_code":"9",
    "gn:admin3_code":"75.0",
    "gn:admin4_code":"750015.0",
    "gn:asciiname":"Dhanakheti",
    "gn:country_code":"NP",
    "gn:dem":804,
    "gn:feature_class":"P",
    "gn:feature_code":"PPLL",
    "gn:name":"Dhanakheti",
    "gn:population":0,
    "gn:timezone":"Asia/Kathmandu",
    "iso:country":"NP",
    "wof:name":"Dhanakheti",
    "wof:placetype":"locality"
},
  "geometry": {"coordinates":[80.54347,29.6714],"type":"Point"}
}