{
  "type": "Feature",
  "properties": {
    "gn:admin1_code":"FR",
    "gn:admin2_code":"14.0",
    "gn:admin3_code":"69.0",
    "gn:admin4_code":"690047.0",
    "gn:asciiname":"Chimeshal",
    "gn:country_code":"NP",
    "gn:dem":1207,
    "gn:feature_class":"P",
    "gn:feature_code":"PPLL",
    "gn:name":"Chimeshal",
    "gn:population":0,
    "gn:timezone":"Asia/Kathmandu",
    "iso:country":"NP",
    "wof:name":"Chimeshal",
    "wof:placetype":"locality"
},
  "geometry": {"coordinates":[81.23413000000002,29.13149],"type":"Point"}
}