{
  "type": "Feature",
  "properties": {
    "gn:admin1_code":"CR",
    "gn:admin2_code":"11",
    "gn:admin3_code":"32",
    "gn:admin4_code":"320084",
    "gn:asciiname":"Nathunitol",
    "gn:country_code":"NP",
    "gn:dem":98,
    "gn:feature_class":"P",
    "gn:feature_code":"PPLL",
    "gn:name":"Nathunitol",
    "gn:population":0,
    "gn:timezone":"Asia/Kathmandu",
    "iso:country":"NP",
    "wof:name":"Nathunitol",
    "wof:placetype":"locality"
},
  "geometry": {"coordinates":[85.29741999999997,27.02855],"type":"Point"}
}