{
  "type": "Feature",
  "properties": {
    "gn:admin1_code":"FR",
    "gn:admin2_code":"9",
    "gn:admin3_code":"74",
    "gn:admin4_code":"740019",
    "gn:asciiname":"Rodigadh",
    "gn:country_code":"NP",
    "gn:dem":2005,
    "gn:feature_class":"P",
    "gn:feature_code":"PPLL",
    "gn:name":"Rodigadh",
    "gn:population":0,
    "gn:timezone":"Asia/Kathmandu",
    "iso:country":"NP",
    "wof:name":"Rodigadh",
    "wof:placetype":"locality"
},
  "geometry": {"coordinates":[80.72596,29.47784],"type":"Point"}
}