{
  "type": "Feature",
  "properties": {
    "gn:admin1_code":"FR",
    "gn:admin2_code":"14.0",
    "gn:admin3_code":"68.0",
    "gn:admin4_code":"680047.0",
    "gn:asciiname":"Tolyan",
    "gn:country_code":"NP",
    "gn:dem":1805,
    "gn:feature_class":"P",
    "gn:feature_code":"PPLL",
    "gn:name":"Tolyan",
    "gn:population":0,
    "gn:timezone":"Asia/Kathmandu",
    "iso:country":"NP",
    "wof:name":"Tolyan",
    "wof:placetype":"locality"
},
  "geometry": {"coordinates":[80.81489000000001,29.53082],"type":"Point"}
}