{
  "type": "Feature",
  "properties": {
    "gn:admin1_code":"WR",
    "gn:admin2_code":"4.0",
    "gn:admin3_code":"38.0",
    "gn:admin4_code":"380033.0",
    "gn:asciiname":"Swanra",
    "gn:country_code":"NP",
    "gn:dem":694,
    "gn:feature_class":"P",
    "gn:feature_code":"PPLL",
    "gn:name":"Swanra",
    "gn:population":0,
    "gn:timezone":"Asia/Kathmandu",
    "iso:country":"NP",
    "wof:name":"Swanra",
    "wof:placetype":"locality"
},
  "geometry": {"coordinates":[84.13240999999999,28.01929],"type":"Point"}
}