{
  "type": "Feature",
  "properties": {
    "gn:admin1_code":"ER",
    "gn:admin2_code":"7",
    "gn:admin3_code":"10.0",
    "gn:admin4_code":"100010.0",
    "gn:asciiname":"Surke",
    "gn:country_code":"NP",
    "gn:dem":1661,
    "gn:feature_class":"P",
    "gn:feature_code":"PPLL",
    "gn:name":"Surke",
    "gn:population":0,
    "gn:timezone":"Asia/Kathmandu",
    "iso:country":"NP",
    "wof:name":"Surke",
    "wof:placetype":"locality"
},
  "geometry": {"coordinates":[87.00877,27.12249000000001],"type":"Point"}
}