{
  "type": "Feature",
  "properties": {
    "gn:admin1_code":"FR",
    "gn:admin2_code":"14",
    "gn:admin3_code":"70.0",
    "gn:admin4_code":"700025.0",
    "gn:asciiname":"Palchaur",
    "gn:country_code":"NP",
    "gn:dem":991,
    "gn:feature_class":"P",
    "gn:feature_code":"PPLL",
    "gn:name":"Palchaur",
    "gn:population":0,
    "gn:timezone":"Asia/Kathmandu",
    "iso:country":"NP",
    "wof:name":"Palchaur",
    "wof:placetype":"locality"
},
  "geometry": {"coordinates":[81.12098,29.0263],"type":"Point"}
}