{
  "type": "Feature",
  "properties": {
    "gn:admin1_code":"CR",
    "gn:admin2_code":"11",
    "gn:admin3_code":"35.0",
    "gn:admin4_code":"350008.0",
    "gn:asciiname":"Bharle",
    "gn:country_code":"NP",
    "gn:dem":1095,
    "gn:feature_class":"P",
    "gn:feature_code":"PPLL",
    "gn:name":"Bharle",
    "gn:population":0,
    "gn:timezone":"Asia/Kathmandu",
    "iso:country":"NP",
    "name:ara_x_preferred":[
        "\u0628\u0627\u0631\u0644\u064a"
    ],
    "name:fra_x_preferred":[
        "Bharte"
    ],
    "name:mai_x_preferred":[
        "\u092d\u093e\u0930\u094d\u0924\u0947"
    ],
    "name:nep_x_preferred":[
        "\u092d\u093e\u0930\u094d\u0924\u0947"
    ],
    "name:pol_x_preferred":[
        "Bharte"
    ],
    "wof:name":"Bharle",
    "wof:placetype":"locality"
},
  "geometry": {"coordinates":[84.58363,27.79619000000001],"type":"Point"}
}