{
  "type": "Feature",
  "properties": {
    "gn:admin1_code":"MR",
    "gn:admin2_code":"12",
    "gn:admin3_code":"54",
    "gn:admin4_code":"540040",
    "gn:asciiname":"Bhata Ladaune",
    "gn:country_code":"NP",
    "gn:dem":1884,
    "gn:feature_class":"P",
    "gn:feature_code":"PPLL",
    "gn:name":"Bhata Ladaune",
    "gn:population":0,
    "gn:timezone":"Asia/Kathmandu",
    "iso:country":"NP",
    "wof:name":"Bhata Ladaune",
    "wof:placetype":"locality"
},
  "geometry": {"coordinates":[82.60724,28.60007],"type":"Point"}
}