{
  "type": "Feature",
  "properties": {
    "gn:admin1_code":"ER",
    "gn:admin2_code":"7.0",
    "gn:admin3_code":"8.0",
    "gn:admin4_code":"80007.0",
    "gn:asciiname":"Panchami",
    "gn:country_code":"NP",
    "gn:dem":1422,
    "gn:feature_class":"P",
    "gn:feature_code":"PPLL",
    "gn:name":"Panchami",
    "gn:population":0,
    "gn:timezone":"Asia/Kathmandu",
    "iso:country":"NP",
    "name:guj_x_preferred":[
        "\u0aaa\u0abe\u0a82\u0a9a\u0aae"
    ],
    "name:hin_x_preferred":[
        "\u092a\u0902\u091a\u092e\u0940"
    ],
    "name:mar_x_preferred":[
        "\u092a\u0902\u091a\u092e\u0940"
    ],
    "name:new_x_preferred":[
        "\u092a\u091e\u094d\u091a\u092e\u0940"
    ],
    "name:ori_x_preferred":[
        "\u0b2a\u0b1e\u0b4d\u0b1a\u0b2e\u0b40"
    ],
    "name:san_x_preferred":[
        "\u092a\u091e\u094d\u091a\u092e\u0940"
    ],
    "name:tam_x_preferred":[
        "\u0baa\u0b9e\u0bcd\u0b9a\u0bae\u0bbf"
    ],
    "name:tel_x_preferred":[
        "\u0c2a\u0c02\u0c1a\u0c2e\u0c3f"
    ],
    "wof:name":"Panchami",
    "wof:placetype":"locality"
},
  "geometry": {"coordinates":[87.59823,27.19905],"type":"Point"}
}