{
  "type": "Feature",
  "properties": {
    "gn:admin1_code":"MR",
    "gn:admin2_code":"12",
    "gn:admin3_code":"54",
    "gn:admin4_code":"540003",
    "gn:asciiname":"Chintu",
    "gn:country_code":"NP",
    "gn:dem":1567,
    "gn:feature_class":"P",
    "gn:feature_code":"PPLL",
    "gn:name":"Chintu",
    "gn:population":0,
    "gn:timezone":"Asia/Kathmandu",
    "iso:country":"NP",
    "wof:name":"Chintu",
    "wof:placetype":"locality"
},
  "geometry": {"coordinates":[82.33029000000001,28.6336],"type":"Point"}
}