{
  "type": "Feature",
  "properties": {
    "gn:admin1_code":"ER",
    "gn:admin2_code":"7",
    "gn:admin3_code":"5",
    "gn:admin4_code":"50044",
    "gn:asciiname":"Customs Office",
    "gn:country_code":"NP",
    "gn:dem":68,
    "gn:feature_class":"P",
    "gn:feature_code":"PPLL",
    "gn:name":"Customs Office",
    "gn:population":0,
    "gn:timezone":"Asia/Kathmandu",
    "iso:country":"NP",
    "wof:name":"Customs Office",
    "wof:placetype":"locality"
},
  "geometry": {"coordinates":[87.38378,26.4209],"type":"Point"}
}