{
  "type": "Feature",
  "properties": {
    "gn:admin1_code":"MR",
    "gn:admin2_code":"2.0",
    "gn:admin3_code":"59.0",
    "gn:admin4_code":"590031.0",
    "gn:asciiname":"Gaujeni",
    "gn:country_code":"NP",
    "gn:dem":1263,
    "gn:feature_class":"P",
    "gn:feature_code":"PPLL",
    "gn:name":"Gaujeni",
    "gn:population":0,
    "gn:timezone":"Asia/Kathmandu",
    "iso:country":"NP",
    "wof:name":"Gaujeni",
    "wof:placetype":"locality"
},
  "geometry": {"coordinates":[81.55421,28.65831],"type":"Point"}
}