{
  "type": "Feature",
  "properties": {
    "gn:admin1_code":"WR",
    "gn:admin2_code":"4.0",
    "gn:admin3_code":"39.0",
    "gn:admin4_code":"390019.0",
    "gn:asciiname":"Thulogaun",
    "gn:country_code":"NP",
    "gn:dem":1154,
    "gn:feature_class":"P",
    "gn:feature_code":"PPLL",
    "gn:name":"Thulogaun",
    "gn:population":0,
    "gn:timezone":"Asia/Kathmandu",
    "iso:country":"NP",
    "name:mai_x_preferred":[
        "\u0920\u0942\u0932\u094b\u0917\u093e\u0909\u0901"
    ],
    "name:msa_x_preferred":[
        "Thulogaun"
    ],
    "name:nep_x_preferred":[
        "\u0920\u0942\u0932\u094b\u0917\u093e\u0909\u0901"
    ],
    "name:pol_x_preferred":[
        "Thulogoun"
    ],
    "wof:name":"Thulogaun",
    "wof:placetype":"locality"
},
  "geometry": {"coordinates":[83.80889000000001,28.03509],"type":"Point"}
}