{
  "type": "Feature",
  "properties": {
    "gn:admin1_code":"FR",
    "gn:admin2_code":"14",
    "gn:admin3_code":"69",
    "gn:admin4_code":"690037",
    "gn:asciiname":"Bandegadi",
    "gn:country_code":"NP",
    "gn:dem":939,
    "gn:feature_class":"P",
    "gn:feature_code":"PPLL",
    "gn:name":"Bandegadi",
    "gn:population":0,
    "gn:timezone":"Asia/Kathmandu",
    "iso:country":"NP",
    "wof:name":"Bandegadi",
    "wof:placetype":"locality"
},
  "geometry": {"coordinates":[81.2949,29.17101],"type":"Point"}
}