{
  "type": "Feature",
  "properties": {
    "gn:admin1_code":"FR",
    "gn:admin2_code":"9",
    "gn:admin3_code":"73.0",
    "gn:admin4_code":"730003.0",
    "gn:asciiname":"Kalpokhari",
    "gn:country_code":"NP",
    "gn:dem":1764,
    "gn:feature_class":"P",
    "gn:feature_code":"PPLL",
    "gn:name":"Kalpokhari",
    "gn:population":0,
    "gn:timezone":"Asia/Kathmandu",
    "iso:country":"NP",
    "wof:name":"Kalpokhari",
    "wof:placetype":"locality"
},
  "geometry": {"coordinates":[80.62569000000001,29.27561],"type":"Point"}
}