{
  "type": "Feature",
  "properties": {
    "gn:admin1_code":"MR",
    "gn:admin2_code":"2.0",
    "gn:admin3_code":"59.0",
    "gn:admin4_code":"590046.0",
    "gn:asciiname":"Sisneta",
    "gn:country_code":"NP",
    "gn:dem":1454,
    "gn:feature_class":"P",
    "gn:feature_code":"PPLL",
    "gn:name":"Sisneta",
    "gn:population":0,
    "gn:timezone":"Asia/Kathmandu",
    "iso:country":"NP",
    "wof:name":"Sisneta",
    "wof:placetype":"locality"
},
  "geometry": {"coordinates":[81.93751,28.41851],"type":"Point"}
}