{
  "type": "Feature",
  "properties": {
    "gn:admin1_code":"FR",
    "gn:admin2_code":"14",
    "gn:admin3_code":"71.0",
    "gn:admin4_code":"710020.0",
    "gn:asciiname":"Tuni goth",
    "gn:country_code":"NP",
    "gn:dem":1317,
    "gn:feature_class":"P",
    "gn:feature_code":"PPLL",
    "gn:name":"Tuni goth",
    "gn:population":0,
    "gn:timezone":"Asia/Kathmandu",
    "iso:country":"NP",
    "wof:name":"Tuni goth",
    "wof:placetype":"locality"
},
  "geometry": {"coordinates":[80.70225000000001,28.90168],"type":"Point"}
}