{
  "type": "Feature",
  "properties": {
    "gn:admin1_code":"FR",
    "gn:admin2_code":"14",
    "gn:admin3_code":"68",
    "gn:admin4_code":"680032",
    "gn:asciiname":"Gurelthum",
    "gn:country_code":"NP",
    "gn:dem":1725,
    "gn:feature_class":"P",
    "gn:feature_code":"PPLL",
    "gn:name":"Gurelthum",
    "gn:population":0,
    "gn:timezone":"Asia/Kathmandu",
    "iso:country":"NP",
    "wof:name":"Gurelthum",
    "wof:placetype":"locality"
},
  "geometry": {"coordinates":[81.08894000000002,29.51117],"type":"Point"}
}