{
  "type": "Feature",
  "properties": {
    "gn:admin1_code":"MR",
    "gn:admin2_code":"12",
    "gn:admin3_code":"52",
    "gn:admin4_code":"520038",
    "gn:asciiname":"Kalle",
    "gn:country_code":"NP",
    "gn:dem":1238,
    "gn:feature_class":"P",
    "gn:feature_code":"PPLL",
    "gn:name":"Kalle",
    "gn:population":0,
    "gn:timezone":"Asia/Kathmandu",
    "iso:country":"NP",
    "wof:name":"Kalle",
    "wof:placetype":"locality"
},
  "geometry": {"coordinates":[83.01958,28.23432],"type":"Point"}
}