{
  "type": "Feature",
  "properties": {
    "gn:admin1_code":"CR",
    "gn:admin2_code":"5",
    "gn:admin3_code":"17.0",
    "gn:admin4_code":"170016.0",
    "gn:asciiname":"Lalgadh",
    "gn:country_code":"NP",
    "gn:dem":218,
    "gn:feature_class":"P",
    "gn:feature_code":"PPLL",
    "gn:name":"Lalgadh",
    "gn:population":0,
    "gn:timezone":"Asia/Kathmandu",
    "iso:country":"NP",
    "wof:name":"Lalgadh",
    "wof:placetype":"locality"
},
  "geometry": {"coordinates":[85.92764,26.97893],"type":"Point"}
}