{
  "type": "Feature",
  "properties": {
    "gn:admin1_code":"WR",
    "gn:admin2_code":"8",
    "gn:admin3_code":"49",
    "gn:admin4_code":"490051.0",
    "gn:asciiname":"Gulariya",
    "gn:country_code":"NP",
    "gn:dem":97,
    "gn:feature_class":"P",
    "gn:feature_code":"PPLL",
    "gn:name":"Gulariya",
    "gn:population":0,
    "gn:timezone":"Asia/Kathmandu",
    "iso:country":"NP",
    "name:ceb_x_preferred":[
        "Gulariy\u0101"
    ],
    "name:deu_x_preferred":[
        "Gulariya"
    ],
    "name:dty_x_preferred":[
        "\u0917\u0941\u0932\u0930\u093f\u092f\u093e \u0928\u0917\u0930\u092a\u093e\u0932\u093f\u0915\u093e"
    ],
    "name:fra_x_preferred":[
        "Gularia"
    ],
    "name:ita_x_preferred":[
        "Gularia"
    ],
    "name:mai_x_preferred":[
        "\u0917\u0941\u0932\u0930\u093f\u092f\u093e \u0928\u0917\u0930\u092a\u093e\u0932\u093f\u0915\u093e"
    ],
    "name:msa_x_preferred":[
        "Gularia"
    ],
    "name:nep_x_preferred":[
        "\u0917\u0941\u0932\u0930\u093f\u092f\u093e \u0928\u0917\u0930\u092a\u093e\u0932\u093f\u0915\u093e"
    ],
    "name:nld_x_preferred":[
        "Gularia"
    ],
    "name:pol_x_preferred":[
        "Gularia"
    ],
    "name:por_x_preferred":[
        "Gularia"
    ],
    "name:rus_x_preferred":[
        "\u0413\u0443\u043b\u0430\u0440\u0438\u044f"
    ],
    "name:urd_x_preferred":[
        "\u06af\u0648\u0644\u0627\u0631\u06cc\u0627"
    ],
    "name:zho_x_preferred":[
        "\u53e4\u62c9\u91cc\u4e9e"
    ],
    "wof:name":"Gulariya",
    "wof:placetype":"locality"
},
  "geometry": {"coordinates":[83.32182,27.45161],"type":"Point"}
}