{
  "type": "Feature",
  "properties": {
    "gn:admin1_code":"ER",
    "gn:admin2_code":"13",
    "gn:admin3_code":"11",
    "gn:admin4_code":"110024",
    "gn:asciiname":"Thesiyo",
    "gn:country_code":"NP",
    "gn:dem":3482,
    "gn:feature_class":"P",
    "gn:feature_code":"PPLL",
    "gn:name":"Thesiyo",
    "gn:population":0,
    "gn:timezone":"Asia/Kathmandu",
    "iso:country":"NP",
    "wof:name":"Thesiyo",
    "wof:placetype":"locality"
},
  "geometry": {"coordinates":[86.68895999999999,27.81979],"type":"Point"}
}