{
  "type": "Feature",
  "properties": {
    "gn:admin1_code":"CR",
    "gn:admin2_code":"1",
    "gn:admin3_code":"30.0",
    "gn:admin4_code":"300038.0",
    "gn:asciiname":"Ladap",
    "gn:country_code":"NP",
    "gn:dem":1938,
    "gn:feature_class":"P",
    "gn:feature_code":"PPLL",
    "gn:name":"Ladap",
    "gn:population":0,
    "gn:timezone":"Asia/Kathmandu",
    "iso:country":"NP",
    "wof:name":"Ladap",
    "wof:placetype":"locality"
},
  "geometry": {"coordinates":[84.95283000000001,28.09382],"type":"Point"}
}