{
  "type": "Feature",
  "properties": {
    "gn:admin1_code":"CR",
    "gn:admin2_code":"1",
    "gn:admin3_code":"24.0",
    "gn:admin4_code":"240033.0",
    "gn:asciiname":"Keurenitar",
    "gn:country_code":"NP",
    "gn:dem":1266,
    "gn:feature_class":"P",
    "gn:feature_code":"PPLL",
    "gn:name":"Keurenitar",
    "gn:population":0,
    "gn:timezone":"Asia/Kathmandu",
    "iso:country":"NP",
    "wof:name":"Keurenitar",
    "wof:placetype":"locality"
},
  "geometry": {"coordinates":[85.77209999999999,27.57077],"type":"Point"}
}