{
  "type": "Feature",
  "properties": {
    "gn:admin1_code":"FR",
    "gn:admin2_code":"14.0",
    "gn:admin3_code":"68.0",
    "gn:admin4_code":"680042.0",
    "gn:asciiname":"Mangrapani",
    "gn:country_code":"NP",
    "gn:dem":2899,
    "gn:feature_class":"P",
    "gn:feature_code":"PPLL",
    "gn:name":"Mangrapani",
    "gn:population":0,
    "gn:timezone":"Asia/Kathmandu",
    "iso:country":"NP",
    "wof:name":"Mangrapani",
    "wof:placetype":"locality"
},
  "geometry": {"coordinates":[81.00227,29.56543],"type":"Point"}
}