{
  "type": "Feature",
  "properties": {
    "gn:admin1_code":"ER",
    "gn:admin2_code":"13",
    "gn:admin3_code":"15",
    "gn:admin4_code":"150027",
    "gn:asciiname":"Mahuwa",
    "gn:country_code":"NP",
    "gn:dem":69,
    "gn:feature_class":"P",
    "gn:feature_code":"PPLL",
    "gn:name":"Mahuwa",
    "gn:population":0,
    "gn:timezone":"Asia/Kathmandu",
    "iso:country":"NP",
    "name:ceb_x_preferred":[
        "Mahuwa"
    ],
    "wof:name":"Mahuwa",
    "wof:placetype":"locality"
},
  "geometry": {"coordinates":[86.72176,26.44807],"type":"Point"}
}