{
  "type": "Feature",
  "properties": {
    "gn:admin1_code":"CR",
    "gn:admin2_code":"1.0",
    "gn:asciiname":"Nakkhu",
    "gn:country_code":"NP",
    "gn:dem":1287,
    "gn:feature_class":"P",
    "gn:feature_code":"PPL",
    "gn:name":"Nakkhu",
    "gn:population":0,
    "gn:timezone":"Asia/Kathmandu",
    "iso:country":"NP",
    "wof:name":"Nakkhu",
    "wof:placetype":"locality"
},
  "geometry": {"coordinates":[85.30726999999997,27.66211],"type":"Point"}
}