{
  "type": "Feature",
  "properties": {
    "gn:admin1_code":"CR",
    "gn:admin2_code":"1.0",
    "gn:admin3_code":"26.0",
    "gn:admin4_code":"260018.0",
    "gn:asciiname":"Saudol",
    "gn:country_code":"NP",
    "gn:dem":1374,
    "gn:feature_class":"P",
    "gn:feature_code":"PPLL",
    "gn:name":"Saudol",
    "gn:population":0,
    "gn:timezone":"Asia/Kathmandu",
    "iso:country":"NP",
    "wof:name":"Saudol",
    "wof:placetype":"locality"
},
  "geometry": {"coordinates":[85.47969999999999,27.66648],"type":"Point"}
}