{
  "type": "Feature",
  "properties": {
    "gn:admin1_code":"FR",
    "gn:admin2_code":"9",
    "gn:admin3_code":"72.0",
    "gn:admin4_code":"720018.0",
    "gn:asciiname":"Thulo Singapur",
    "gn:country_code":"NP",
    "gn:dem":184,
    "gn:feature_class":"P",
    "gn:feature_code":"PPLL",
    "gn:name":"Thulo Singapur",
    "gn:population":0,
    "gn:timezone":"Asia/Kathmandu",
    "iso:country":"NP",
    "wof:name":"Thulo Singapur",
    "wof:placetype":"locality"
},
  "geometry": {"coordinates":[80.35511,28.70902],"type":"Point"}
}