{
  "type": "Feature",
  "properties": {
    "gn:admin1_code":"MR",
    "gn:admin2_code":"12",
    "gn:admin3_code":"53",
    "gn:admin4_code":"530015",
    "gn:asciiname":"Tallo Gumchal",
    "gn:country_code":"NP",
    "gn:dem":1351,
    "gn:feature_class":"P",
    "gn:feature_code":"PPLL",
    "gn:name":"Tallo Gumchal",
    "gn:population":0,
    "gn:timezone":"Asia/Kathmandu",
    "iso:country":"NP",
    "wof:name":"Tallo Gumchal",
    "wof:placetype":"locality"
},
  "geometry": {"coordinates":[82.78701,28.30182000000001],"type":"Point"}
}