{
  "type": "Feature",
  "properties": {
    "gn:admin1_code":"FR",
    "gn:admin2_code":"9",
    "gn:admin3_code":"74",
    "gn:admin4_code":"740050",
    "gn:asciiname":"Ganwagada",
    "gn:country_code":"NP",
    "gn:dem":864,
    "gn:feature_class":"P",
    "gn:feature_code":"PPLL",
    "gn:name":"Ganwagada",
    "gn:population":0,
    "gn:timezone":"Asia/Kathmandu",
    "iso:country":"NP",
    "wof:name":"Ganwagada",
    "wof:placetype":"locality"
},
  "geometry": {"coordinates":[80.31958,29.32686],"type":"Point"}
}