{
  "type": "Feature",
  "properties": {
    "gn:admin1_code":"WR",
    "gn:admin2_code":"8",
    "gn:admin3_code":"46.0",
    "gn:admin4_code":"460017.0",
    "gn:asciiname":"Sadhankharka",
    "gn:country_code":"NP",
    "gn:dem":1532,
    "gn:feature_class":"P",
    "gn:feature_code":"PPLL",
    "gn:name":"Sadhankharka",
    "gn:population":0,
    "gn:timezone":"Asia/Kathmandu",
    "iso:country":"NP",
    "wof:name":"Sadhankharka",
    "wof:placetype":"locality"
},
  "geometry": {"coordinates":[83.51895999999998,28.11257],"type":"Point"}
}