{
  "type": "Feature",
  "properties": {
    "gn:admin1_code":"MR",
    "gn:admin2_code":"12",
    "gn:admin3_code":"54",
    "gn:admin4_code":"540037",
    "gn:asciiname":"Garpadhuri",
    "gn:country_code":"NP",
    "gn:dem":2448,
    "gn:feature_class":"P",
    "gn:feature_code":"PPLL",
    "gn:name":"Garpadhuri",
    "gn:population":0,
    "gn:timezone":"Asia/Kathmandu",
    "iso:country":"NP",
    "wof:name":"Garpadhuri",
    "wof:placetype":"locality"
},
  "geometry": {"coordinates":[82.55478000000002,28.59303],"type":"Point"}
}