{
  "type": "Feature",
  "properties": {
    "gn:admin1_code":"CR",
    "gn:admin2_code":"1",
    "gn:admin3_code":"24.0",
    "gn:admin4_code":"240041.0",
    "gn:asciiname":"Kartike",
    "gn:country_code":"NP",
    "gn:dem":1291,
    "gn:feature_class":"P",
    "gn:feature_code":"PPLL",
    "gn:name":"Kartike",
    "gn:population":0,
    "gn:timezone":"Asia/Kathmandu",
    "iso:country":"NP",
    "wof:name":"Kartike",
    "wof:placetype":"locality"
},
  "geometry": {"coordinates":[85.58119000000001,27.61396],"type":"Point"}
}