{
  "type": "Feature",
  "properties": {
    "gn:admin1_code":"ER",
    "gn:admin2_code":"7",
    "gn:admin3_code":"9",
    "gn:admin4_code":"90007",
    "gn:asciiname":"Dangok",
    "gn:country_code":"NP",
    "gn:dem":2470,
    "gn:feature_class":"P",
    "gn:feature_code":"PPLL",
    "gn:name":"Dangok",
    "gn:population":0,
    "gn:timezone":"Asia/Kathmandu",
    "iso:country":"NP",
    "wof:name":"Dangok",
    "wof:placetype":"locality"
},
  "geometry": {"coordinates":[87.38046,27.78102],"type":"Point"}
}