{
  "type": "Feature",
  "properties": {
    "gn:admin1_code":"FR",
    "gn:admin2_code":"14",
    "gn:admin3_code":"71.0",
    "gn:admin4_code":"710020.0",
    "gn:asciiname":"Garbha Darbar",
    "gn:country_code":"NP",
    "gn:dem":1227,
    "gn:feature_class":"P",
    "gn:feature_code":"PPLL",
    "gn:name":"Garbha Darbar",
    "gn:population":0,
    "gn:timezone":"Asia/Kathmandu",
    "iso:country":"NP",
    "wof:name":"Garbha Darbar",
    "wof:placetype":"locality"
},
  "geometry": {"coordinates":[80.76956,28.89769],"type":"Point"}
}