{
  "type": "Feature",
  "properties": {
    "gn:admin1_code":"WR",
    "gn:admin2_code":"4",
    "gn:admin3_code":"41",
    "gn:admin4_code":"410009",
    "gn:asciiname":"Nawal",
    "gn:country_code":"NP",
    "gn:dem":3662,
    "gn:feature_class":"P",
    "gn:feature_code":"PPLA4",
    "gn:name":"Nawal",
    "gn:population":0,
    "gn:timezone":"Asia/Kathmandu",
    "iso:country":"NP",
    "name:ara_x_preferred":[
        "\u0646\u0648\u0627\u0644"
    ],
    "name:deu_x_preferred":[
        "Nawal"
    ],
    "name:swe_x_preferred":[
        "Nawal"
    ],
    "wof:name":"Nawal",
    "wof:placetype":"locality"
},
  "geometry": {"coordinates":[84.10279,28.64831],"type":"Point"}
}