{
  "type": "Feature",
  "properties": {
    "gn:admin1_code":"FR",
    "gn:admin2_code":"9",
    "gn:admin3_code":"75.0",
    "gn:admin4_code":"750034.0",
    "gn:asciiname":"Jwaithalo",
    "gn:country_code":"NP",
    "gn:dem":1094,
    "gn:feature_class":"P",
    "gn:feature_code":"PPLL",
    "gn:name":"Jwaithalo",
    "gn:population":0,
    "gn:timezone":"Asia/Kathmandu",
    "iso:country":"NP",
    "wof:name":"Jwaithalo",
    "wof:placetype":"locality"
},
  "geometry": {"coordinates":[80.73613,29.73247000000001],"type":"Point"}
}