{
  "type": "Feature",
  "properties": {
    "gn:admin1_code":"FR",
    "gn:admin2_code":"9",
    "gn:admin3_code":"74",
    "gn:admin4_code":"740026",
    "gn:asciiname":"Santadi",
    "gn:country_code":"NP",
    "gn:dem":1559,
    "gn:feature_class":"P",
    "gn:feature_code":"PPLL",
    "gn:name":"Santadi",
    "gn:population":0,
    "gn:timezone":"Asia/Kathmandu",
    "iso:country":"NP",
    "wof:name":"Santadi",
    "wof:placetype":"locality"
},
  "geometry": {"coordinates":[80.49524,29.54909],"type":"Point"}
}