{
  "type": "Feature",
  "properties": {
    "gn:admin1_code":"FR",
    "gn:admin2_code":"9",
    "gn:admin3_code":"74",
    "gn:admin4_code":"740026",
    "gn:asciiname":"Santadi",
    "gn:country_code":"NP",
    "gn:dem":1559,
    "gn:feature_class":"P",
    "gn:feature_code":"PPLL",
    "gn:name":"Santadi",
    "gn:population":0,
    "gn:timezone":"Asia/Kathmandu",
    "iso:country":"NP",
    "name:arg_x_preferred":[
        "Santadi"
    ],
    "name:ast_x_preferred":[
        "Santadi"
    ],
    "name:azb_x_preferred":[
        "\u0633\u0627\u0646\u062a\u0627\u062f\u06cc"
    ],
    "name:bul_x_preferred":[
        "\u0421\u0430\u043d\u0442\u0430\u0434\u0438"
    ],
    "name:cat_x_preferred":[
        "Santadi"
    ],
    "name:ceb_x_preferred":[
        "Santadi"
    ],
    "name:ces_x_preferred":[
        "Santadi"
    ],
    "name:dan_x_preferred":[
        "Santadi"
    ],
    "name:deu_x_preferred":[
        "Santadi"
    ],
    "name:epo_x_preferred":[
        "Santadi"
    ],
    "name:eus_x_preferred":[
        "Santadi"
    ],
    "name:fas_x_preferred":[
        "\u0633\u0627\u0646\u062a\u0627\u062f\u06cc"
    ],
    "name:fin_x_preferred":[
        "Santadi"
    ],
    "name:fra_x_preferred":[
        "Santadi"
    ],
    "name:hrv_x_preferred":[
        "Santadi"
    ],
    "name:hun_x_preferred":[
        "Santadi"
    ],
    "name:hye_x_preferred":[
        "\u054d\u0561\u0576\u057f\u0561\u0564\u056b"
    ],
    "name:ind_x_preferred":[
        "Santadi"
    ],
    "name:ita_x_preferred":[
        "Santadi"
    ],
    "name:jpn_x_preferred":[
        "\u30b5\u30f3\u30bf\u30c7\u30a3"
    ],
    "name:kaz_x_preferred":[
        "\u0421\u0430\u043d\u0442\u0430\u0434\u0438"
    ],
    "name:lmo_x_preferred":[
        "Santadi"
    ],
    "name:msa_x_preferred":[
        "Santadi"
    ],
    "name:nap_x_preferred":[
        "Santadi"
    ],
    "name:nld_x_preferred":[
        "Santadi"
    ],
    "name:nno_x_preferred":[
        "Santadi"
    ],
    "name:nor_x_preferred":[
        "Santadi"
    ],
    "name:pms_x_preferred":[
        "Santadi"
    ],
    "name:pol_x_preferred":[
        "Santadi"
    ],
    "name:por_x_preferred":[
        "Santadi"
    ],
    "name:ron_x_preferred":[
        "Santadi"
    ],
    "name:rus_x_preferred":[
        "\u0421\u0430\u043d\u0442\u0430\u0434\u0438"
    ],
    "name:scn_x_preferred":[
        "Santadi"
    ],
    "name:spa_x_preferred":[
        "Santadi"
    ],
    "name:sqi_x_preferred":[
        "Santadi"
    ],
    "name:srd_x_preferred":[
        "Santadi"
    ],
    "name:srp_x_preferred":[
        "\u0421\u0430\u043d\u0442\u0430\u0434\u0438"
    ],
    "name:tgl_x_preferred":[
        "Santadi"
    ],
    "name:tur_x_preferred":[
        "Santadi"
    ],
    "name:ukr_x_preferred":[
        "\u0421\u0430\u043d\u0442\u0430\u0434\u0456"
    ],
    "name:uzb_x_preferred":[
        "Santadi"
    ],
    "name:vec_x_preferred":[
        "Santadi"
    ],
    "name:vie_x_preferred":[
        "Santadi"
    ],
    "name:vol_x_preferred":[
        "Santadi"
    ],
    "name:war_x_preferred":[
        "Santadi"
    ],
    "name:zho_x_preferred":[
        "\u6851\u5854\u8fea"
    ],
    "wof:name":"Santadi",
    "wof:placetype":"locality"
},
  "geometry": {"coordinates":[80.49524,29.54909],"type":"Point"}
}