{
  "type": "Feature",
  "properties": {
    "gn:admin1_code":"CR",
    "gn:admin2_code":"1",
    "gn:admin3_code":"25",
    "gn:admin4_code":"250041",
    "gn:asciiname":"Bhairthum",
    "gn:country_code":"NP",
    "gn:dem":1181,
    "gn:feature_class":"P",
    "gn:feature_code":"PPLL",
    "gn:name":"Bhairthum",
    "gn:population":0,
    "gn:timezone":"Asia/Kathmandu",
    "iso:country":"NP",
    "wof:name":"Bhairthum",
    "wof:placetype":"locality"
},
  "geometry": {"coordinates":[85.39248000000001,27.43586],"type":"Point"}
}