{
  "type": "Feature",
  "properties": {
    "gn:admin1_code":"ER",
    "gn:admin2_code":"13",
    "gn:admin3_code":"11",
    "gn:admin4_code":"110026",
    "gn:asciiname":"Puranokhani",
    "gn:country_code":"NP",
    "gn:dem":1144,
    "gn:feature_class":"P",
    "gn:feature_code":"PPLL",
    "gn:name":"Puranokhani",
    "gn:population":0,
    "gn:timezone":"Asia/Kathmandu",
    "iso:country":"NP",
    "wof:name":"Puranokhani",
    "wof:placetype":"locality"
},
  "geometry": {"coordinates":[86.67066,27.35508],"type":"Point"}
}