{
  "type": "Feature",
  "properties": {
    "gn:admin1_code":"WR",
    "gn:admin2_code":"4",
    "gn:admin3_code":"41",
    "gn:admin4_code":"410012",
    "gn:asciiname":"Tallo Humde",
    "gn:country_code":"NP",
    "gn:dem":3475,
    "gn:feature_class":"P",
    "gn:feature_code":"PPLL",
    "gn:name":"Tallo Humde",
    "gn:population":0,
    "gn:timezone":"Asia/Kathmandu",
    "iso:country":"NP",
    "wof:name":"Tallo Humde",
    "wof:placetype":"locality"
},
  "geometry": {"coordinates":[84.09918,28.63336],"type":"Point"}
}