{
  "type": "Feature",
  "properties": {
    "gn:admin1_code":"MR",
    "gn:admin2_code":"12",
    "gn:admin3_code":"55",
    "gn:admin4_code":"550013",
    "gn:asciiname":"Kimuchaur",
    "gn:country_code":"NP",
    "gn:dem":1035,
    "gn:feature_class":"P",
    "gn:feature_code":"PPLL",
    "gn:name":"Kimuchaur",
    "gn:population":0,
    "gn:timezone":"Asia/Kathmandu",
    "iso:country":"NP",
    "wof:name":"Kimuchaur",
    "wof:placetype":"locality"
},
  "geometry": {"coordinates":[82.09405,28.48286],"type":"Point"}
}