{
  "type": "Feature",
  "properties": {
    "gn:admin1_code":"FR",
    "gn:admin2_code":"14.0",
    "gn:admin3_code":"67.0",
    "gn:admin4_code":"670022.0",
    "gn:asciiname":"Phurka Chadhauna",
    "gn:country_code":"NP",
    "gn:dem":1682,
    "gn:feature_class":"P",
    "gn:feature_code":"PPLL",
    "gn:name":"Phurka Chadhauna",
    "gn:population":0,
    "gn:timezone":"Asia/Kathmandu",
    "iso:country":"NP",
    "wof:name":"Phurka Chadhauna",
    "wof:placetype":"locality"
},
  "geometry": {"coordinates":[81.39737,29.47139],"type":"Point"}
}