{
  "type": "Feature",
  "properties": {
    "gn:admin1_code":"CR",
    "gn:admin2_code":"5",
    "gn:admin3_code":"19",
    "gn:admin4_code":"190076",
    "gn:asciiname":"Mathillo Chisapani",
    "gn:country_code":"NP",
    "gn:dem":315,
    "gn:feature_class":"P",
    "gn:feature_code":"PPLL",
    "gn:name":"Mathillo Chisapani",
    "gn:population":0,
    "gn:timezone":"Asia/Kathmandu",
    "iso:country":"NP",
    "wof:name":"Mathillo Chisapani",
    "wof:placetype":"locality"
},
  "geometry": {"coordinates":[85.71838000000002,27.09881],"type":"Point"}
}