{
  "type": "Feature",
  "properties": {
    "gn:admin1_code":"CR",
    "gn:admin2_code":"1",
    "gn:admin3_code":"23",
    "gn:admin4_code":"230014.0",
    "gn:asciiname":"Laksmandanda",
    "gn:country_code":"NP",
    "gn:dem":1397,
    "gn:feature_class":"P",
    "gn:feature_code":"PPLL",
    "gn:name":"Laksmandanda",
    "gn:population":0,
    "gn:timezone":"Asia/Kathmandu",
    "iso:country":"NP",
    "wof:name":"Laksmandanda",
    "wof:placetype":"locality"
},
  "geometry": {"coordinates":[85.72136,27.76712],"type":"Point"}
}