{
  "type": "Feature",
  "properties": {
    "gn:country":"NP",
    "gn:fcode":"PPL",
    "gn:population":10000,
    "iso:country":"NP",
    "qs:name":"kankrabari Dovan",
    "qs:photos_9r":0,
    "qs:photos_sr":0,
    "qs:pop_sr":"5",
    "wof:name":"kankrabari Dovan",
    "wof:placetype":"locality",
    "wof:population":10000
},
  "geometry": {"coordinates":[85.45934,27.62881],"type":"Point"}
}