{
  "type": "Feature",
  "properties": {
    "gn:admin1_code":"00",
    "gn:asciiname":"Bhrihuti Bajar",
    "gn:country_code":"NP",
    "gn:dem":209,
    "gn:feature_class":"P",
    "gn:feature_code":"PPL",
    "gn:name":"Bhri\u0307\u0304huti\u0307\u0304 Baj\u0101r",
    "gn:population":0,
    "gn:timezone":"Asia/Kathmandu",
    "iso:country":"NP",
    "name:nep_x_preferred":[
        "Bhri\u0307\u0304huti\u0307\u0304 Baj\u0101r"
    ],
    "wof:name":"Bhrihuti Bajar",
    "wof:placetype":"locality"
},
  "geometry": {"coordinates":[88.14449999999999,26.72749],"type":"Point"}
}