{
  "type": "Feature",
  "properties": {
    "gn:admin1_code":"CR",
    "gn:admin2_code":"5",
    "gn:admin3_code":"22.0",
    "gn:admin4_code":"220023.0",
    "gn:asciiname":"Serakapti",
    "gn:country_code":"NP",
    "gn:dem":2509,
    "gn:feature_class":"P",
    "gn:feature_code":"PPLL",
    "gn:name":"Serakapti",
    "gn:population":0,
    "gn:timezone":"Asia/Kathmandu",
    "iso:country":"NP",
    "wof:name":"Serakapti",
    "wof:placetype":"locality"
},
  "geometry": {"coordinates":[86.22113,27.68658],"type":"Point"}
}