{
  "type": "Feature",
  "properties": {
    "gn:admin1_code":"CR",
    "gn:admin2_code":"5",
    "gn:admin3_code":"21",
    "gn:admin4_code":"210034",
    "gn:asciiname":"Kunauri",
    "gn:country_code":"NP",
    "gn:dem":521,
    "gn:feature_class":"P",
    "gn:feature_code":"PPLL",
    "gn:name":"Kunauri",
    "gn:population":0,
    "gn:timezone":"Asia/Kathmandu",
    "iso:country":"NP",
    "wof:name":"Kunauri",
    "wof:placetype":"locality"
},
  "geometry": {"coordinates":[86.03598000000002,27.37524],"type":"Point"}
}