{
  "type": "Feature",
  "properties": {
    "gn:admin1_code":"00",
    "gn:asciiname":"Barigau",
    "gn:country_code":"NP",
    "gn:dem":1009,
    "gn:feature_class":"P",
    "gn:feature_code":"PPL",
    "gn:name":"B\u0101ri\u0307\u0304g\u0101\u0169",
    "gn:population":0,
    "gn:timezone":"Asia/Kathmandu",
    "iso:country":"NP",
    "name:nep_x_preferred":[
        "B\u0101ri\u0307\u0304g\u0101\u0169"
    ],
    "wof:name":"Barigau",
    "wof:placetype":"locality"
},
  "geometry": {"coordinates":[87.13490999999998,26.96336],"type":"Point"}
}