{
  "type": "Feature",
  "properties": {
    "gn:admin1_code":"CR",
    "gn:admin2_code":"1",
    "gn:admin3_code":"30.0",
    "gn:admin4_code":"300037.0",
    "gn:asciiname":"Dhad",
    "gn:country_code":"NP",
    "gn:dem":1860,
    "gn:feature_class":"P",
    "gn:feature_code":"PPLL",
    "gn:name":"Dhad",
    "gn:population":0,
    "gn:timezone":"Asia/Kathmandu",
    "iso:country":"NP",
    "wof:name":"Dhad",
    "wof:placetype":"locality"
},
  "geometry": {"coordinates":[84.93136,27.70863],"type":"Point"}
}