{
  "type": "Feature",
  "properties": {
    "gn:admin1_code":"WR",
    "gn:admin2_code":"8",
    "gn:admin3_code":"47",
    "gn:admin4_code":"470006",
    "gn:asciiname":"Barangdi",
    "gn:country_code":"NP",
    "gn:dem":1043,
    "gn:feature_class":"P",
    "gn:feature_code":"PPLL",
    "gn:name":"Barangdi",
    "gn:population":0,
    "gn:timezone":"Asia/Kathmandu",
    "iso:country":"NP",
    "wof:name":"Barangdi",
    "wof:placetype":"locality"
},
  "geometry": {"coordinates":[83.54675999999998,27.88599],"type":"Point"}
}