{
  "type": "Feature",
  "properties": {
    "gn:admin1_code":"FR",
    "gn:admin2_code":"9",
    "gn:admin3_code":"74",
    "gn:admin4_code":"740019",
    "gn:asciiname":"Dhura",
    "gn:country_code":"NP",
    "gn:dem":1861,
    "gn:feature_class":"P",
    "gn:feature_code":"PPLL",
    "gn:name":"Dhura",
    "gn:population":0,
    "gn:timezone":"Asia/Kathmandu",
    "iso:country":"NP",
    "wof:name":"Dhura",
    "wof:placetype":"locality"
},
  "geometry": {"coordinates":[80.70622,29.45797],"type":"Point"}
}