{
  "type": "Feature",
  "properties": {
    "gn:admin1_code":"MR",
    "gn:admin2_code":"12",
    "gn:admin3_code":"54",
    "gn:admin4_code":"540003",
    "gn:asciiname":"Tang",
    "gn:country_code":"NP",
    "gn:dem":1437,
    "gn:feature_class":"P",
    "gn:feature_code":"PPLL",
    "gn:name":"Tang",
    "gn:population":0,
    "gn:timezone":"Asia/Kathmandu",
    "iso:country":"NP",
    "name:ceb_x_preferred":[
        "Tang"
    ],
    "name:dan_x_preferred":[
        "Tang"
    ],
    "name:deu_x_preferred":[
        "Tang"
    ],
    "name:est_x_preferred":[
        "Tang"
    ],
    "name:fin_x_preferred":[
        "Tang"
    ],
    "name:fra_x_preferred":[
        "Tang"
    ],
    "name:hun_x_preferred":[
        "Tang"
    ],
    "name:nld_x_preferred":[
        "Tang"
    ],
    "name:nor_x_preferred":[
        "Tang"
    ],
    "name:pol_x_preferred":[
        "Tang"
    ],
    "name:rus_x_preferred":[
        "\u0422\u0430\u043d\u0433"
    ],
    "name:spa_x_preferred":[
        "Tang"
    ],
    "name:swe_x_preferred":[
        "Tang"
    ],
    "name:ukr_x_preferred":[
        "\u0422\u0430\u043d\u0433"
    ],
    "wof:name":"Tang",
    "wof:placetype":"locality"
},
  "geometry": {"coordinates":[82.37054999999999,28.6339],"type":"Point"}
}