{
  "type": "Feature",
  "properties": {
    "gn:admin1_code":"ER",
    "gn:admin2_code":"7.0",
    "gn:admin3_code":"8.0",
    "gn:admin4_code":"80004.0",
    "gn:asciiname":"Nageshwari",
    "gn:country_code":"NP",
    "gn:dem":900,
    "gn:feature_class":"P",
    "gn:feature_code":"PPLL",
    "gn:name":"Nageshwari",
    "gn:population":0,
    "gn:timezone":"Asia/Kathmandu",
    "iso:country":"NP",
    "wof:name":"Nageshwari",
    "wof:placetype":"locality"
},
  "geometry": {"coordinates":[87.73877,27.20788],"type":"Point"}
}