{
  "type": "Feature",
  "properties": {
    "gn:admin1_code":"CR",
    "gn:admin2_code":"1",
    "gn:admin3_code":"30.0",
    "gn:admin4_code":"300027.0",
    "gn:asciiname":"Kachet",
    "gn:country_code":"NP",
    "gn:dem":2386,
    "gn:feature_class":"P",
    "gn:feature_code":"PPLL",
    "gn:name":"Kachet",
    "gn:population":0,
    "gn:timezone":"Asia/Kathmandu",
    "iso:country":"NP",
    "wof:name":"Kachet",
    "wof:placetype":"locality"
},
  "geometry": {"coordinates":[85.00368,28.14222],"type":"Point"}
}