{
  "type": "Feature",
  "properties": {
    "gn:admin1_code":"WR",
    "gn:admin2_code":"4",
    "gn:admin3_code":"40.0",
    "gn:admin4_code":"400010.0",
    "gn:asciiname":"Bhaerchaur",
    "gn:country_code":"NP",
    "gn:dem":1056,
    "gn:feature_class":"P",
    "gn:feature_code":"PPLL",
    "gn:name":"Bhaerchaur",
    "gn:population":0,
    "gn:timezone":"Asia/Kathmandu",
    "iso:country":"NP",
    "wof:name":"Bhaerchaur",
    "wof:placetype":"locality"
},
  "geometry": {"coordinates":[83.84491,28.26342],"type":"Point"}
}