{
  "type": "Feature",
  "properties": {
    "gn:admin1_code":"ER",
    "gn:admin2_code":"13",
    "gn:admin3_code":"16",
    "gn:admin4_code":"160041",
    "gn:asciiname":"Auraha (Shripur)",
    "gn:country_code":"NP",
    "gn:dem":79,
    "gn:feature_class":"P",
    "gn:feature_code":"PPLL",
    "gn:name":"Auraha (Shripur)",
    "gn:population":0,
    "gn:timezone":"Asia/Kathmandu",
    "iso:country":"NP",
    "wof:name":"Auraha (Shripur)",
    "wof:placetype":"locality"
},
  "geometry": {"coordinates":[86.24545000000001,26.6531],"type":"Point"}
}