{
  "type": "Feature",
  "properties": {
    "gn:admin1_code":"WR",
    "gn:admin2_code":"8",
    "gn:admin3_code":"49",
    "gn:admin4_code":"490019",
    "gn:asciiname":"Budhar Gaun",
    "gn:country_code":"NP",
    "gn:dem":503,
    "gn:feature_class":"P",
    "gn:feature_code":"PPLL",
    "gn:name":"Budhar Gaun",
    "gn:population":0,
    "gn:timezone":"Asia/Kathmandu",
    "iso:country":"NP",
    "wof:name":"Budhar Gaun",
    "wof:placetype":"locality"
},
  "geometry": {"coordinates":[83.52768,27.71527],"type":"Point"}
}