{
  "type": "Feature",
  "properties": {
    "gn:admin1_code":"ER",
    "gn:admin2_code":"10",
    "gn:admin3_code":"4.0",
    "gn:admin4_code":"40044.0",
    "gn:asciiname":"Laljhoda",
    "gn:country_code":"NP",
    "gn:dem":128,
    "gn:feature_class":"P",
    "gn:feature_code":"PPLL",
    "gn:name":"Laljhoda",
    "gn:population":0,
    "gn:timezone":"Asia/Kathmandu",
    "iso:country":"NP",
    "wof:name":"Laljhoda",
    "wof:placetype":"locality"
},
  "geometry": {"coordinates":[87.81692,26.6347],"type":"Point"}
}