{
  "type": "Feature",
  "properties": {
    "gn:admin1_code":"ER",
    "gn:admin2_code":"7.0",
    "gn:admin3_code":"8.0",
    "gn:admin4_code":"80001.0",
    "gn:asciiname":"Dhunge Sangu",
    "gn:country_code":"NP",
    "gn:dem":1180,
    "gn:feature_class":"P",
    "gn:feature_code":"PPLL",
    "gn:name":"Dhunge Sangu",
    "gn:population":0,
    "gn:timezone":"Asia/Kathmandu",
    "iso:country":"NP",
    "wof:name":"Dhunge Sangu",
    "wof:placetype":"locality"
},
  "geometry": {"coordinates":[87.52837,27.17098],"type":"Point"}
}