{
  "type": "Feature",
  "properties": {
    "gn:admin1_code":"MR",
    "gn:admin2_code":"2.0",
    "gn:admin3_code":"59.0",
    "gn:admin4_code":"590023.0",
    "gn:asciiname":"Dahaldanda",
    "gn:country_code":"NP",
    "gn:dem":1027,
    "gn:feature_class":"P",
    "gn:feature_code":"PPLL",
    "gn:name":"Dahaldanda",
    "gn:population":0,
    "gn:timezone":"Asia/Kathmandu",
    "iso:country":"NP",
    "wof:name":"Dahaldanda",
    "wof:placetype":"locality"
},
  "geometry": {"coordinates":[81.65201999999999,28.61872],"type":"Point"}
}