{
  "type": "Feature",
  "properties": {
    "gn:admin1_code":"ER",
    "gn:admin2_code":"7",
    "gn:admin3_code":"7.0",
    "gn:admin4_code":"70029.0",
    "gn:asciiname":"Sirise",
    "gn:country_code":"NP",
    "gn:dem":1760,
    "gn:feature_class":"P",
    "gn:feature_code":"PPLL",
    "gn:name":"Sirise",
    "gn:population":0,
    "gn:timezone":"Asia/Kathmandu",
    "iso:country":"NP",
    "name:ceb_x_preferred":[
        "Sirise"
    ],
    "name:fra_x_preferred":[
        "Sirise"
    ],
    "name:ita_x_preferred":[
        "Sirise"
    ],
    "name:mai_x_preferred":[
        "\u0938\u093f\u0930\u093f\u0938\u0947"
    ],
    "name:msa_x_preferred":[
        "Sirise"
    ],
    "name:new_x_preferred":[
        "\u0938\u093f\u0930\u093f\u0938\u0947"
    ],
    "name:pol_x_preferred":[
        "Sirise"
    ],
    "wof:name":"Sirise",
    "wof:placetype":"locality"
},
  "geometry": {"coordinates":[87.37921999999998,27.08956],"type":"Point"}
}