{
  "type": "Feature",
  "properties": {
    "gn:admin1_code":"FR",
    "gn:admin2_code":"9",
    "gn:admin3_code":"73.0",
    "gn:admin4_code":"730021.0",
    "gn:asciiname":"Kalena",
    "gn:country_code":"NP",
    "gn:dem":650,
    "gn:feature_class":"P",
    "gn:feature_code":"PPLL",
    "gn:name":"Kalena",
    "gn:population":0,
    "gn:timezone":"Asia/Kathmandu",
    "iso:country":"NP",
    "name:ceb_x_preferred":[
        "Kalena"
    ],
    "name:fra_x_preferred":[
        "Kalena"
    ],
    "name:mai_x_preferred":[
        "\u0915\u0932\u0947\u0928\u093e"
    ],
    "name:msa_x_preferred":[
        "Kalena"
    ],
    "name:nep_x_preferred":[
        "\u0915\u0932\u0947\u0928\u093e"
    ],
    "name:new_x_preferred":[
        "\u0915\u0932\u0947\u0928\u093e"
    ],
    "name:pol_x_preferred":[
        "Kalena"
    ],
    "wof:name":"Kalena",
    "wof:placetype":"locality"
},
  "geometry": {"coordinates":[80.39877,29.17139],"type":"Point"}
}