{
  "type": "Feature",
  "properties": {
    "gn:admin1_code":"MR",
    "gn:admin2_code":"12",
    "gn:admin3_code":"52",
    "gn:admin4_code":"520007",
    "gn:asciiname":"Upallo Bhingri",
    "gn:country_code":"NP",
    "gn:dem":718,
    "gn:feature_class":"P",
    "gn:feature_code":"PPLL",
    "gn:name":"Upallo Bhingri",
    "gn:population":0,
    "gn:timezone":"Asia/Kathmandu",
    "iso:country":"NP",
    "wof:name":"Upallo Bhingri",
    "wof:placetype":"locality"
},
  "geometry": {"coordinates":[82.70352,28.15353],"type":"Point"}
}