{
  "type": "Feature",
  "properties": {
    "gn:admin1_code":"CR",
    "gn:admin2_code":"1",
    "gn:admin3_code":"23",
    "gn:admin4_code":"230008.0",
    "gn:asciiname":"Bhotephulping",
    "gn:country_code":"NP",
    "gn:dem":1414,
    "gn:feature_class":"P",
    "gn:feature_code":"PPLL",
    "gn:name":"Bhotephulping",
    "gn:population":0,
    "gn:timezone":"Asia/Kathmandu",
    "iso:country":"NP",
    "wof:name":"Bhotephulping",
    "wof:placetype":"locality"
},
  "geometry": {"coordinates":[85.75360999999999,27.80873],"type":"Point"}
}