{
  "type": "Feature",
  "properties": {
    "gn:admin1_code":"ER",
    "gn:admin2_code":"10",
    "gn:admin3_code":"3.0",
    "gn:admin4_code":"30043.0",
    "gn:asciiname":"Jure",
    "gn:country_code":"NP",
    "gn:dem":1289,
    "gn:feature_class":"P",
    "gn:feature_code":"PPLL",
    "gn:name":"Jure",
    "gn:population":0,
    "gn:timezone":"Asia/Kathmandu",
    "iso:country":"NP",
    "wof:name":"Jure",
    "wof:placetype":"locality"
},
  "geometry": {"coordinates":[88.02849000000001,26.84702],"type":"Point"}
}