{
  "type": "Feature",
  "properties": {
    "gn:admin1_code":"ER",
    "gn:admin2_code":"10",
    "gn:admin3_code":"3.0",
    "gn:admin4_code":"30006.0",
    "gn:asciiname":"Arnakhadi",
    "gn:country_code":"NP",
    "gn:dem":153,
    "gn:feature_class":"P",
    "gn:feature_code":"PPLL",
    "gn:name":"Arnakhadi",
    "gn:population":0,
    "gn:timezone":"Asia/Kathmandu",
    "iso:country":"NP",
    "wof:name":"Arnakhadi",
    "wof:placetype":"locality"
},
  "geometry": {"coordinates":[87.76418000000002,26.6766],"type":"Point"}
}