{
  "type": "Feature",
  "properties": {
    "gn:admin1_code":"ER",
    "gn:admin2_code":"10",
    "gn:admin3_code":"2",
    "gn:admin4_code":"20031",
    "gn:asciiname":"Thamthum Jukte",
    "gn:country_code":"NP",
    "gn:dem":1835,
    "gn:feature_class":"P",
    "gn:feature_code":"PPLL",
    "gn:name":"Thamthum Jukte",
    "gn:population":0,
    "gn:timezone":"Asia/Kathmandu",
    "iso:country":"NP",
    "wof:name":"Thamthum Jukte",
    "wof:placetype":"locality"
},
  "geometry": {"coordinates":[87.66878,26.92377],"type":"Point"}
}