{
  "type": "Feature",
  "properties": {
    "gn:admin1_code":"MR",
    "gn:admin2_code":"12",
    "gn:admin3_code":"52",
    "gn:admin4_code":"520002",
    "gn:asciiname":"Bakhrikhor",
    "gn:country_code":"NP",
    "gn:dem":1248,
    "gn:feature_class":"P",
    "gn:feature_code":"PPLL",
    "gn:name":"Bakhrikhor",
    "gn:population":0,
    "gn:timezone":"Asia/Kathmandu",
    "iso:country":"NP",
    "wof:name":"Bakhrikhor",
    "wof:placetype":"locality"
},
  "geometry": {"coordinates":[83.00803000000001,28.15072],"type":"Point"}
}