{
  "type": "Feature",
  "properties": {
    "gn:admin1_code":"WR",
    "gn:admin2_code":"4.0",
    "gn:admin3_code":"39.0",
    "gn:admin4_code":"390012.0",
    "gn:asciiname":"Khalduwa",
    "gn:country_code":"NP",
    "gn:dem":1093,
    "gn:feature_class":"P",
    "gn:feature_code":"PPLL",
    "gn:name":"Khalduwa",
    "gn:population":0,
    "gn:timezone":"Asia/Kathmandu",
    "iso:country":"NP",
    "wof:name":"Khalduwa",
    "wof:placetype":"locality"
},
  "geometry": {"coordinates":[83.48155,27.94252],"type":"Point"}
}