{
  "type": "Feature",
  "properties": {
    "gn:admin1_code":"MR",
    "gn:admin2_code":"12",
    "gn:admin3_code":"52",
    "gn:admin4_code":"520031",
    "gn:asciiname":"Jahane Pokhara",
    "gn:country_code":"NP",
    "gn:dem":1154,
    "gn:feature_class":"P",
    "gn:feature_code":"PPLL",
    "gn:name":"Jahane Pokhara",
    "gn:population":0,
    "gn:timezone":"Asia/Kathmandu",
    "iso:country":"NP",
    "wof:name":"Jahane Pokhara",
    "wof:placetype":"locality"
},
  "geometry": {"coordinates":[82.91273000000002,28.13483],"type":"Point"}
}