{
  "type": "Feature",
  "properties": {
    "gn:admin1_code":"WR",
    "gn:admin2_code":"4.0",
    "gn:admin3_code":"39.0",
    "gn:admin4_code":"390057.0",
    "gn:asciiname":"Tamadi",
    "gn:country_code":"NP",
    "gn:dem":881,
    "gn:feature_class":"P",
    "gn:feature_code":"PPLL",
    "gn:name":"Tamadi",
    "gn:population":0,
    "gn:timezone":"Asia/Kathmandu",
    "iso:country":"NP",
    "wof:name":"Tamadi",
    "wof:placetype":"locality"
},
  "geometry": {"coordinates":[83.70538000000001,28.00761],"type":"Point"}
}