{
  "type": "Feature",
  "properties": {
    "gn:admin1_code":"CR",
    "gn:admin2_code":"1",
    "gn:admin3_code":"28",
    "gn:admin4_code":"280041",
    "gn:asciiname":"Bahunbesi Anpra",
    "gn:country_code":"NP",
    "gn:dem":719,
    "gn:feature_class":"P",
    "gn:feature_code":"PPLL",
    "gn:name":"Bahunbesi Anpra",
    "gn:population":0,
    "gn:timezone":"Asia/Kathmandu",
    "iso:country":"NP",
    "wof:name":"Bahunbesi Anpra",
    "wof:placetype":"locality"
},
  "geometry": {"coordinates":[85.29477,27.92079],"type":"Point"}
}