{
  "type": "Feature",
  "properties": {
    "gn:admin1_code":"WR",
    "gn:admin2_code":"4.0",
    "gn:admin3_code":"37.0",
    "gn:admin4_code":"370036.0",
    "gn:asciiname":"Khudi",
    "gn:country_code":"NP",
    "gn:dem":860,
    "gn:elevation":"823.0",
    "gn:feature_class":"P",
    "gn:feature_code":"PPLA4",
    "gn:name":"Khudi",
    "gn:population":0,
    "gn:timezone":"Asia/Kathmandu",
    "iso:country":"NP",
    "wof:name":"Khudi",
    "wof:placetype":"locality"
},
  "geometry": {"coordinates":[84.35911999999998,28.28216],"type":"Point"}
}