{
  "type": "Feature",
  "properties": {
    "gn:admin1_code":"FR",
    "gn:admin2_code":"14",
    "gn:admin3_code":"68",
    "gn:admin4_code":"680022",
    "gn:asciiname":"Kumaichaur",
    "gn:country_code":"NP",
    "gn:dem":1912,
    "gn:feature_class":"P",
    "gn:feature_code":"PPLL",
    "gn:name":"Kumaichaur",
    "gn:population":0,
    "gn:timezone":"Asia/Kathmandu",
    "iso:country":"NP",
    "wof:name":"Kumaichaur",
    "wof:placetype":"locality"
},
  "geometry": {"coordinates":[80.90428,29.56725],"type":"Point"}
}