{
  "type": "Feature",
  "properties": {
    "gn:admin1_code":"CR",
    "gn:admin2_code":"11.0",
    "gn:admin3_code":"33.0",
    "gn:admin4_code":"330067.0",
    "gn:asciiname":"Narahi",
    "gn:country_code":"NP",
    "gn:dem":96,
    "gn:feature_class":"P",
    "gn:feature_code":"PPLL",
    "gn:name":"Narahi",
    "gn:population":0,
    "gn:timezone":"Asia/Kathmandu",
    "iso:country":"NP",
    "name:ceb_x_preferred":[
        "Narahi"
    ],
    "name:fra_x_preferred":[
        "Narahi"
    ],
    "name:hin_x_preferred":[
        "\u0928\u0930\u0939\u0940"
    ],
    "name:mai_x_preferred":[
        "\u0928\u0930\u0939\u0940"
    ],
    "name:msa_x_preferred":[
        "Narahi"
    ],
    "name:nep_x_preferred":[
        "\u0928\u0930\u0939\u0940"
    ],
    "name:new_x_preferred":[
        "\u0928\u0930\u0939\u0940"
    ],
    "name:pol_x_preferred":[
        "Narahi"
    ],
    "wof:name":"Narahi",
    "wof:placetype":"locality"
},
  "geometry": {"coordinates":[85.10439000000002,27.00971],"type":"Point"}
}