{
  "type": "Feature",
  "properties": {
    "gn:admin1_code":"ER",
    "gn:admin2_code":"10.0",
    "gn:admin3_code":"1.0",
    "gn:admin4_code":"10027.0",
    "gn:asciiname":"Lapsing",
    "gn:country_code":"NP",
    "gn:dem":2515,
    "gn:feature_class":"P",
    "gn:feature_code":"PPLL",
    "gn:name":"Lapsing",
    "gn:population":0,
    "gn:timezone":"Asia/Kathmandu",
    "iso:country":"NP",
    "wof:name":"Lapsing",
    "wof:placetype":"locality"
},
  "geometry": {"coordinates":[87.63941,27.57841],"type":"Point"}
}