{
  "type": "Feature",
  "properties": {
    "gn:admin1_code":"WR",
    "gn:admin2_code":"4",
    "gn:admin3_code":"37",
    "gn:admin4_code":"370004",
    "gn:asciiname":"Bimda",
    "gn:country_code":"NP",
    "gn:dem":1375,
    "gn:feature_class":"P",
    "gn:feature_code":"PPLL",
    "gn:name":"Bimda",
    "gn:population":0,
    "gn:timezone":"Asia/Kathmandu",
    "iso:country":"NP",
    "wof:name":"Bimda",
    "wof:placetype":"locality"
},
  "geometry": {"coordinates":[84.33945,28.2244],"type":"Point"}
}