{
  "type": "Feature",
  "properties": {
    "gn:admin1_code":"CR",
    "gn:admin2_code":"11",
    "gn:admin3_code":"31",
    "gn:admin4_code":"310036",
    "gn:asciiname":"Gairikhop",
    "gn:country_code":"NP",
    "gn:dem":524,
    "gn:feature_class":"P",
    "gn:feature_code":"PPLL",
    "gn:name":"Gairikhop",
    "gn:population":0,
    "gn:timezone":"Asia/Kathmandu",
    "iso:country":"NP",
    "wof:name":"Gairikhop",
    "wof:placetype":"locality"
},
  "geometry": {"coordinates":[85.40491999999998,27.20337],"type":"Point"}
}