{
  "type": "Feature",
  "properties": {
    "gn:admin1_code":"ER",
    "gn:admin2_code":"13",
    "gn:admin3_code":"12",
    "gn:admin4_code":"120041",
    "gn:asciiname":"Thulo Bhainse",
    "gn:country_code":"NP",
    "gn:dem":1889,
    "gn:feature_class":"P",
    "gn:feature_code":"PPLL",
    "gn:name":"Thulo Bhainse",
    "gn:population":0,
    "gn:timezone":"Asia/Kathmandu",
    "iso:country":"NP",
    "wof:name":"Thulo Bhainse",
    "wof:placetype":"locality"
},
  "geometry": {"coordinates":[86.2677,27.36229],"type":"Point"}
}