{
  "type": "Feature",
  "properties": {
    "gn:admin1_code":"WR",
    "gn:admin2_code":"4",
    "gn:admin3_code":"40.0",
    "gn:admin4_code":"400017.0",
    "gn:asciiname":"Thulaswanra",
    "gn:country_code":"NP",
    "gn:dem":1032,
    "gn:feature_class":"P",
    "gn:feature_code":"PPLL",
    "gn:name":"Thulaswanra",
    "gn:population":0,
    "gn:timezone":"Asia/Kathmandu",
    "iso:country":"NP",
    "wof:name":"Thulaswanra",
    "wof:placetype":"locality"
},
  "geometry": {"coordinates":[84.07417,28.22925],"type":"Point"}
}