{
  "type": "Feature",
  "properties": {
    "gn:admin1_code":"ER",
    "gn:admin2_code":"10",
    "gn:admin3_code":"2",
    "gn:admin4_code":"20027",
    "gn:asciiname":"Pauwadanda",
    "gn:country_code":"NP",
    "gn:dem":2017,
    "gn:feature_class":"P",
    "gn:feature_code":"PPLL",
    "gn:name":"Pauwadanda",
    "gn:population":0,
    "gn:timezone":"Asia/Kathmandu",
    "iso:country":"NP",
    "wof:name":"Pauwadanda",
    "wof:placetype":"locality"
},
  "geometry": {"coordinates":[87.79823,27.04573],"type":"Point"}
}