{
  "type": "Feature",
  "properties": {
    "gn:admin1_code":"ER",
    "gn:admin2_code":"13",
    "gn:admin3_code":"13",
    "gn:admin4_code":"130073",
    "gn:asciiname":"Phalate",
    "gn:country_code":"NP",
    "gn:dem":1895,
    "gn:feature_class":"P",
    "gn:feature_code":"PPLL",
    "gn:name":"Phalate",
    "gn:population":0,
    "gn:timezone":"Asia/Kathmandu",
    "iso:country":"NP",
    "wof:name":"Phalate",
    "wof:placetype":"locality"
},
  "geometry": {"coordinates":[86.82984999999999,27.12447],"type":"Point"}
}