{
  "type": "Feature",
  "properties": {
    "gn:admin1_code":"MR",
    "gn:admin2_code":"6",
    "gn:admin3_code":"62.0",
    "gn:admin4_code":"620013.0",
    "gn:asciiname":"Danda",
    "gn:country_code":"NP",
    "gn:dem":2605,
    "gn:feature_class":"P",
    "gn:feature_code":"PPLL",
    "gn:name":"Danda",
    "gn:population":0,
    "gn:timezone":"Asia/Kathmandu",
    "iso:country":"NP",
    "wof:name":"Danda",
    "wof:placetype":"locality"
},
  "geometry": {"coordinates":[82.52769000000001,29.05573],"type":"Point"}
}