{
  "type": "Feature",
  "properties": {
    "gn:admin1_code":"CR",
    "gn:admin2_code":"1",
    "gn:admin3_code":"24.0",
    "gn:admin4_code":"240075.0",
    "gn:asciiname":"Basghari",
    "gn:country_code":"NP",
    "gn:dem":1216,
    "gn:feature_class":"P",
    "gn:feature_code":"PPLL",
    "gn:name":"Basghari",
    "gn:population":0,
    "gn:timezone":"Asia/Kathmandu",
    "iso:country":"NP",
    "wof:name":"Basghari",
    "wof:placetype":"locality"
},
  "geometry": {"coordinates":[85.52986,27.39739],"type":"Point"}
}