{
  "type": "Feature",
  "properties": {
    "gn:admin1_code":"MR",
    "gn:admin2_code":"12",
    "gn:admin3_code":"53",
    "gn:admin4_code":"530009",
    "gn:asciiname":"Ghoshang",
    "gn:country_code":"NP",
    "gn:dem":1452,
    "gn:feature_class":"P",
    "gn:feature_code":"PPLL",
    "gn:name":"Ghoshang",
    "gn:population":0,
    "gn:timezone":"Asia/Kathmandu",
    "iso:country":"NP",
    "wof:name":"Ghoshang",
    "wof:placetype":"locality"
},
  "geometry": {"coordinates":[82.75926,28.36254000000001],"type":"Point"}
}