{
  "type": "Feature",
  "properties": {
    "gn:admin1_code":"FR",
    "gn:admin2_code":"14",
    "gn:admin3_code":"68",
    "gn:admin4_code":"680002",
    "gn:asciiname":"Gadagaun",
    "gn:country_code":"NP",
    "gn:dem":1509,
    "gn:feature_class":"P",
    "gn:feature_code":"PPLL",
    "gn:name":"Gadagaun",
    "gn:population":0,
    "gn:timezone":"Asia/Kathmandu",
    "iso:country":"NP",
    "wof:name":"Gadagaun",
    "wof:placetype":"locality"
},
  "geometry": {"coordinates":[80.9905,29.4922],"type":"Point"}
}