{
  "type": "Feature",
  "properties": {
    "gn:admin1_code":"CR",
    "gn:admin2_code":"5",
    "gn:admin3_code":"19",
    "gn:admin4_code":"190100",
    "gn:asciiname":"Sekhtol",
    "gn:country_code":"NP",
    "gn:dem":86,
    "gn:feature_class":"P",
    "gn:feature_code":"PPLL",
    "gn:name":"Sekhtol",
    "gn:population":0,
    "gn:timezone":"Asia/Kathmandu",
    "iso:country":"NP",
    "wof:name":"Sekhtol",
    "wof:placetype":"locality"
},
  "geometry": {"coordinates":[85.59024000000002,26.85352],"type":"Point"}
}