{
  "type": "Feature",
  "properties": {
    "gn:admin1_code":"CR",
    "gn:admin2_code":"5",
    "gn:admin3_code":"20",
    "gn:admin4_code":"200010",
    "gn:asciiname":"Duduwa",
    "gn:country_code":"NP",
    "gn:dem":540,
    "gn:feature_class":"P",
    "gn:feature_code":"PPLL",
    "gn:name":"Duduwa",
    "gn:population":0,
    "gn:timezone":"Asia/Kathmandu",
    "iso:country":"NP",
    "wof:name":"Duduwa",
    "wof:placetype":"locality"
},
  "geometry": {"coordinates":[86.08207,27.13815],"type":"Point"}
}