{
  "type": "Feature",
  "properties": {
    "gn:admin1_code":"MR",
    "gn:admin2_code":"12",
    "gn:admin3_code":"52",
    "gn:admin4_code":"520016",
    "gn:asciiname":"Bagdula",
    "gn:country_code":"NP",
    "gn:dem":826,
    "gn:feature_class":"P",
    "gn:feature_code":"PPLL",
    "gn:name":"Bagdula",
    "gn:population":0,
    "gn:timezone":"Asia/Kathmandu",
    "iso:country":"NP",
    "wof:name":"Bagdula",
    "wof:placetype":"locality"
},
  "geometry": {"coordinates":[82.88695,28.12765],"type":"Point"}
}