{
  "type": "Feature",
  "properties": {
    "gn:admin1_code":"FR",
    "gn:admin2_code":"9",
    "gn:admin3_code":"73.0",
    "gn:admin4_code":"730007.0",
    "gn:asciiname":"Chanali",
    "gn:country_code":"NP",
    "gn:dem":1341,
    "gn:feature_class":"P",
    "gn:feature_code":"PPLL",
    "gn:name":"Chanali",
    "gn:population":0,
    "gn:timezone":"Asia/Kathmandu",
    "iso:country":"NP",
    "wof:name":"Chanali",
    "wof:placetype":"locality"
},
  "geometry": {"coordinates":[80.51859,29.32926],"type":"Point"}
}