{
  "type": "Feature",
  "properties": {
    "gn:admin1_code":"ER",
    "gn:admin2_code":"13",
    "gn:admin3_code":"13",
    "gn:admin4_code":"130058",
    "gn:asciiname":"Chokhane",
    "gn:country_code":"NP",
    "gn:dem":1553,
    "gn:feature_class":"P",
    "gn:feature_code":"PPLL",
    "gn:name":"Chokhane",
    "gn:population":0,
    "gn:timezone":"Asia/Kathmandu",
    "iso:country":"NP",
    "wof:name":"Chokhane",
    "wof:placetype":"locality"
},
  "geometry": {"coordinates":[86.88776999999997,27.30155],"type":"Point"}
}