{
  "type": "Feature",
  "properties": {
    "gn:admin1_code":"FR",
    "gn:admin2_code":"14",
    "gn:admin3_code":"71.0",
    "gn:admin4_code":"710001.0",
    "gn:asciiname":"Baliya",
    "gn:country_code":"NP",
    "gn:dem":175,
    "gn:feature_class":"P",
    "gn:feature_code":"PPLL",
    "gn:name":"Baliya",
    "gn:population":0,
    "gn:timezone":"Asia/Kathmandu",
    "iso:country":"NP",
    "name:ceb_x_preferred":[
        "Baliya"
    ],
    "name:mar_x_preferred":[
        "\u092c\u0932\u093f\u092f\u093e"
    ],
    "name:msa_x_preferred":[
        "Baliya"
    ],
    "name:nep_x_preferred":[
        "\u092c\u0932\u093f\u092f\u093e"
    ],
    "name:new_x_preferred":[
        "\u092c\u0932\u093f\u092f\u093e"
    ],
    "name:pol_x_preferred":[
        "Baliya"
    ],
    "wof:name":"Baliya",
    "wof:placetype":"locality"
},
  "geometry": {"coordinates":[81.11603000000002,28.63871],"type":"Point"}
}