{
  "type": "Feature",
  "properties": {
    "gn:admin1_code":"WR",
    "gn:admin2_code":"8",
    "gn:admin3_code":"48",
    "gn:admin4_code":"480033",
    "gn:asciiname":"Kaphaldanda",
    "gn:country_code":"NP",
    "gn:dem":1176,
    "gn:feature_class":"P",
    "gn:feature_code":"PPLL",
    "gn:name":"Kaphaldanda",
    "gn:population":0,
    "gn:timezone":"Asia/Kathmandu",
    "iso:country":"NP",
    "wof:name":"Kaphaldanda",
    "wof:placetype":"locality"
},
  "geometry": {"coordinates":[84.24491,27.79691],"type":"Point"}
}