{
  "type": "Feature",
  "properties": {
    "gn:admin1_code":"CR",
    "gn:admin2_code":"11.0",
    "gn:admin3_code":"33.0",
    "gn:admin4_code":"330041.0",
    "gn:asciiname":"Janakinagar",
    "gn:country_code":"NP",
    "gn:dem":81,
    "gn:feature_class":"P",
    "gn:feature_code":"PPLL",
    "gn:name":"Janakinagar",
    "gn:population":0,
    "gn:timezone":"Asia/Kathmandu",
    "iso:country":"NP",
    "name:pol_x_preferred":[
        "Janakinagar"
    ],
    "wof:name":"Janakinagar",
    "wof:placetype":"locality"
},
  "geometry": {"coordinates":[85.12555,26.89038],"type":"Point"}
}