{
  "type": "Feature",
  "properties": {
    "gn:admin1_code":"CR",
    "gn:admin2_code":"1",
    "gn:admin3_code":"24.0",
    "gn:admin4_code":"240013.0",
    "gn:asciiname":"Dharamshala",
    "gn:country_code":"NP",
    "gn:dem":1647,
    "gn:feature_class":"P",
    "gn:feature_code":"PPLL",
    "gn:name":"Dharamshala",
    "gn:population":0,
    "gn:timezone":"Asia/Kathmandu",
    "iso:country":"NP",
    "wof:name":"Dharamshala",
    "wof:placetype":"locality"
},
  "geometry": {"coordinates":[85.52469000000001,27.55155],"type":"Point"}
}