{
  "type": "Feature",
  "properties": {
    "gn:admin1_code":"CR",
    "gn:admin2_code":"11",
    "gn:admin3_code":"31",
    "gn:admin4_code":"310026",
    "gn:asciiname":"Purano Damar",
    "gn:country_code":"NP",
    "gn:dem":1768,
    "gn:feature_class":"P",
    "gn:feature_code":"PPLL",
    "gn:name":"Purano Damar",
    "gn:population":0,
    "gn:timezone":"Asia/Kathmandu",
    "iso:country":"NP",
    "wof:name":"Purano Damar",
    "wof:placetype":"locality"
},
  "geometry": {"coordinates":[85.16388000000001,27.53418],"type":"Point"}
}