{
  "type": "Feature",
  "properties": {
    "gn:admin1_code":"WR",
    "gn:admin2_code":"3",
    "gn:admin3_code":"45.0",
    "gn:admin4_code":"450039.0",
    "gn:asciiname":"Sirbare",
    "gn:country_code":"NP",
    "gn:dem":1271,
    "gn:feature_class":"P",
    "gn:feature_code":"PPLL",
    "gn:name":"Sirbare",
    "gn:population":0,
    "gn:timezone":"Asia/Kathmandu",
    "iso:country":"NP",
    "wof:name":"Sirbare",
    "wof:placetype":"locality"
},
  "geometry": {"coordinates":[83.40189000000002,28.21905],"type":"Point"}
}