{
  "type": "Feature",
  "properties": {
    "gn:admin1_code":"MR",
    "gn:admin2_code":"2.0",
    "gn:admin3_code":"58.0",
    "gn:admin4_code":"580030.0",
    "gn:asciiname":"Sundarpur",
    "gn:country_code":"NP",
    "gn:dem":149,
    "gn:feature_class":"P",
    "gn:feature_code":"PPLL",
    "gn:name":"Sundarpur",
    "gn:population":0,
    "gn:timezone":"Asia/Kathmandu",
    "iso:country":"NP",
    "name:ceb_x_preferred":[
        "Sundarpur"
    ],
    "name:fra_x_preferred":[
        "Sundarpur"
    ],
    "name:ita_x_preferred":[
        "Sundarpur"
    ],
    "name:mai_x_preferred":[
        "\u0938\u0941\u0928\u094d\u0926\u0930\u092a\u0941\u0930"
    ],
    "name:new_x_preferred":[
        "\u0938\u0941\u0928\u094d\u0926\u0930\u092a\u0941\u0930"
    ],
    "name:pol_x_preferred":[
        "Sundarpur"
    ],
    "wof:name":"Sundarpur",
    "wof:placetype":"locality"
},
  "geometry": {"coordinates":[81.253,28.39036],"type":"Point"}
}