{
  "type": "Feature",
  "properties": {
    "gn:admin1_code":"CR",
    "gn:admin2_code":"11",
    "gn:admin3_code":"31",
    "gn:admin4_code":"310005",
    "gn:asciiname":"Beteni",
    "gn:country_code":"NP",
    "gn:dem":885,
    "gn:feature_class":"P",
    "gn:feature_code":"PPLL",
    "gn:name":"Beteni",
    "gn:population":0,
    "gn:timezone":"Asia/Kathmandu",
    "iso:country":"NP",
    "name:mai_x_preferred":[
        "\u092c\u0947\u0924\u093f\u0928\u0940"
    ],
    "name:msa_x_preferred":[
        "Beteni"
    ],
    "name:pol_x_preferred":[
        "Beteni"
    ],
    "wof:name":"Beteni",
    "wof:placetype":"locality"
},
  "geometry": {"coordinates":[85.39716999999997,27.39678],"type":"Point"}
}