{
  "type": "Feature",
  "properties": {
    "gn:admin1_code":"CR",
    "gn:admin2_code":"1",
    "gn:admin3_code":"28",
    "gn:admin4_code":"280034",
    "gn:asciiname":"Kimtang Tallogaun",
    "gn:country_code":"NP",
    "gn:dem":1763,
    "gn:feature_class":"P",
    "gn:feature_code":"PPLL",
    "gn:name":"Kimtang Tallogaun",
    "gn:population":0,
    "gn:timezone":"Asia/Kathmandu",
    "iso:country":"NP",
    "wof:name":"Kimtang Tallogaun",
    "wof:placetype":"locality"
},
  "geometry": {"coordinates":[85.03323,28.02044],"type":"Point"}
}