{
  "type": "Feature",
  "properties": {
    "gn:admin1_code":"WR",
    "gn:admin2_code":"4",
    "gn:admin3_code":"37",
    "gn:admin4_code":"370009",
    "gn:asciiname":"Bikharka",
    "gn:country_code":"NP",
    "gn:dem":859,
    "gn:feature_class":"P",
    "gn:feature_code":"PPLL",
    "gn:name":"Bikharka",
    "gn:population":0,
    "gn:timezone":"Asia/Kathmandu",
    "iso:country":"NP",
    "wof:name":"Bikharka",
    "wof:placetype":"locality"
},
  "geometry": {"coordinates":[84.47910999999998,28.14207],"type":"Point"}
}