{
  "type": "Feature",
  "properties": {
    "gn:admin1_code":"CR",
    "gn:admin2_code":"5",
    "gn:admin3_code":"19",
    "gn:admin4_code":"190093",
    "gn:asciiname":"Phenhara",
    "gn:country_code":"NP",
    "gn:dem":79,
    "gn:feature_class":"P",
    "gn:feature_code":"PPLL",
    "gn:name":"Phenhara",
    "gn:population":0,
    "gn:timezone":"Asia/Kathmandu",
    "iso:country":"NP",
    "wof:name":"Phenhara",
    "wof:placetype":"locality"
},
  "geometry": {"coordinates":[85.48595,26.80558],"type":"Point"}
}