{
  "type": "Feature",
  "properties": {
    "gn:admin1_code":"ER",
    "gn:admin2_code":"13",
    "gn:admin3_code":"16",
    "gn:admin4_code":"160088",
    "gn:asciiname":"Baluwatol",
    "gn:country_code":"NP",
    "gn:dem":109,
    "gn:feature_class":"P",
    "gn:feature_code":"PPLL",
    "gn:name":"Baluwatol",
    "gn:population":0,
    "gn:timezone":"Asia/Kathmandu",
    "iso:country":"NP",
    "wof:name":"Baluwatol",
    "wof:placetype":"locality"
},
  "geometry": {"coordinates":[86.2159,26.81904],"type":"Point"}
}