{
  "type": "Feature",
  "properties": {
    "gn:admin1_code":"FR",
    "gn:admin2_code":"9",
    "gn:admin3_code":"74",
    "gn:admin4_code":"740018",
    "gn:asciiname":"Maikharka",
    "gn:country_code":"NP",
    "gn:dem":1927,
    "gn:feature_class":"P",
    "gn:feature_code":"PPLL",
    "gn:name":"Maikharka",
    "gn:population":0,
    "gn:timezone":"Asia/Kathmandu",
    "iso:country":"NP",
    "wof:name":"Maikharka",
    "wof:placetype":"locality"
},
  "geometry": {"coordinates":[80.45482,29.47536],"type":"Point"}
}