{
  "type": "Feature",
  "properties": {
    "gn:admin1_code":"CR",
    "gn:admin2_code":"5",
    "gn:admin3_code":"20",
    "gn:admin4_code":"200027",
    "gn:asciiname":"Khangsangbesi",
    "gn:country_code":"NP",
    "gn:dem":390,
    "gn:feature_class":"P",
    "gn:feature_code":"PPLL",
    "gn:name":"Khangsangbesi",
    "gn:population":0,
    "gn:timezone":"Asia/Kathmandu",
    "iso:country":"NP",
    "wof:name":"Khangsangbesi",
    "wof:placetype":"locality"
},
  "geometry": {"coordinates":[86.28185999999999,27.24542000000001],"type":"Point"}
}