{
  "type": "Feature",
  "properties": {
    "gn:admin1_code":"FR",
    "gn:admin2_code":"9",
    "gn:admin3_code":"74",
    "gn:admin4_code":"740038",
    "gn:asciiname":"Paligada",
    "gn:country_code":"NP",
    "gn:dem":1483,
    "gn:feature_class":"P",
    "gn:feature_code":"PPLL",
    "gn:name":"Paligada",
    "gn:population":0,
    "gn:timezone":"Asia/Kathmandu",
    "iso:country":"NP",
    "wof:name":"Paligada",
    "wof:placetype":"locality"
},
  "geometry": {"coordinates":[80.56381999999998,29.52736],"type":"Point"}
}