{
  "type": "Feature",
  "properties": {
    "gn:admin1_code":"CR",
    "gn:admin2_code":"11",
    "gn:admin3_code":"35.0",
    "gn:admin4_code":"350027.0",
    "gn:asciiname":"Sajapur",
    "gn:country_code":"NP",
    "gn:dem":157,
    "gn:feature_class":"P",
    "gn:feature_code":"PPLL",
    "gn:name":"Sajapur",
    "gn:population":0,
    "gn:timezone":"Asia/Kathmandu",
    "iso:country":"NP",
    "wof:name":"Sajapur",
    "wof:placetype":"locality"
},
  "geometry": {"coordinates":[84.21766,27.593],"type":"Point"}
}