{
  "type": "Feature",
  "properties": {
    "gn:admin1_code":"00",
    "gn:asciiname":"Badeldhap",
    "gn:country_code":"NP",
    "gn:dem":526,
    "gn:feature_class":"P",
    "gn:feature_code":"PPL",
    "gn:name":"B\u00e3deldh\u0101p",
    "gn:population":0,
    "gn:timezone":"Asia/Kathmandu",
    "iso:country":"NP",
    "name:nep_x_preferred":[
        "B\u00e3deldh\u0101p"
    ],
    "wof:name":"Badeldhap",
    "wof:placetype":"locality"
},
  "geometry": {"coordinates":[85.00305,27.39006],"type":"Point"}
}