{
  "type": "Feature",
  "properties": {
    "gn:admin1_code":"CR",
    "gn:admin2_code":"1",
    "gn:admin3_code":"27.0",
    "gn:admin4_code":"270046.0",
    "gn:asciiname":"Purigaun",
    "gn:country_code":"NP",
    "gn:dem":1374,
    "gn:feature_class":"P",
    "gn:feature_code":"PPLL",
    "gn:name":"Purigaun",
    "gn:population":0,
    "gn:timezone":"Asia/Kathmandu",
    "iso:country":"NP",
    "wof:name":"Purigaun",
    "wof:placetype":"locality"
},
  "geometry": {"coordinates":[85.24986,27.72216],"type":"Point"}
}