{
  "type": "Feature",
  "properties": {
    "gn:admin1_code":"WR",
    "gn:admin2_code":"4.0",
    "gn:admin3_code":"39.0",
    "gn:admin4_code":"390017.0",
    "gn:asciiname":"Lalai",
    "gn:country_code":"NP",
    "gn:dem":1016,
    "gn:feature_class":"P",
    "gn:feature_code":"PPLL",
    "gn:name":"Lalai",
    "gn:population":0,
    "gn:timezone":"Asia/Kathmandu",
    "iso:country":"NP",
    "wof:name":"Lalai",
    "wof:placetype":"locality"
},
  "geometry": {"coordinates":[83.98604,28.01019],"type":"Point"}
}