{
  "type": "Feature",
  "properties": {
    "gn:admin1_code":"FR",
    "gn:admin2_code":"14",
    "gn:admin3_code":"69",
    "gn:admin4_code":"690025",
    "gn:asciiname":"Hitbado",
    "gn:country_code":"NP",
    "gn:dem":1106,
    "gn:feature_class":"P",
    "gn:feature_code":"PPLL",
    "gn:name":"Hitbado",
    "gn:population":0,
    "gn:timezone":"Asia/Kathmandu",
    "iso:country":"NP",
    "wof:name":"Hitbado",
    "wof:placetype":"locality"
},
  "geometry": {"coordinates":[81.23550999999998,29.28368],"type":"Point"}
}