{
  "type": "Feature",
  "properties": {
    "gn:admin1_code":"MR",
    "gn:admin2_code":"6",
    "gn:admin3_code":"64.0",
    "gn:admin4_code":"640030.0",
    "gn:asciiname":"Salli",
    "gn:country_code":"NP",
    "gn:dem":3012,
    "gn:feature_class":"P",
    "gn:feature_code":"PPLL",
    "gn:name":"Salli",
    "gn:population":0,
    "gn:timezone":"Asia/Kathmandu",
    "iso:country":"NP",
    "wof:name":"Salli",
    "wof:placetype":"locality"
},
  "geometry": {"coordinates":[81.81943000000003,29.27995],"type":"Point"}
}