{
  "type": "Feature",
  "properties": {
    "gn:admin1_code":"CR",
    "gn:admin2_code":"11",
    "gn:admin3_code":"35.0",
    "gn:admin4_code":"350030.0",
    "gn:asciiname":"Ganganagar",
    "gn:country_code":"NP",
    "gn:dem":179,
    "gn:feature_class":"P",
    "gn:feature_code":"PPLL",
    "gn:name":"Ganganagar",
    "gn:population":0,
    "gn:timezone":"Asia/Kathmandu",
    "iso:country":"NP",
    "wof:name":"Ganganagar",
    "wof:placetype":"locality"
},
  "geometry": {"coordinates":[84.36951999999999,27.57854],"type":"Point"}
}