{
  "type": "Feature",
  "properties": {
    "gn:admin1_code":"CR",
    "gn:admin2_code":"5",
    "gn:admin3_code":"20",
    "gn:admin4_code":"200018",
    "gn:asciiname":"Chitali",
    "gn:country_code":"NP",
    "gn:dem":351,
    "gn:feature_class":"P",
    "gn:feature_code":"PPLL",
    "gn:name":"Chitali",
    "gn:population":0,
    "gn:timezone":"Asia/Kathmandu",
    "iso:country":"NP",
    "name:mar_x_preferred":[
        "\u091a\u093f\u0924\u0933\u0940"
    ],
    "wof:name":"Chitali",
    "wof:placetype":"locality"
},
  "geometry": {"coordinates":[86.10518,27.04749],"type":"Point"}
}