{
  "type": "Feature",
  "properties": {
    "gn:admin1_code":"CR",
    "gn:admin2_code":"5",
    "gn:admin3_code":"20",
    "gn:admin4_code":"200039",
    "gn:asciiname":"Banauli",
    "gn:country_code":"NP",
    "gn:dem":215,
    "gn:feature_class":"P",
    "gn:feature_code":"PPLL",
    "gn:name":"Banauli",
    "gn:population":0,
    "gn:timezone":"Asia/Kathmandu",
    "iso:country":"NP",
    "wof:name":"Banauli",
    "wof:placetype":"locality"
},
  "geometry": {"coordinates":[85.48281999999998,27.28069],"type":"Point"}
}