{
  "type": "Feature",
  "properties": {
    "gn:admin1_code":"CR",
    "gn:admin2_code":"11",
    "gn:admin3_code":"31",
    "gn:admin4_code":"310022.0",
    "gn:asciiname":"Kicholpa",
    "gn:country_code":"NP",
    "gn:dem":1283,
    "gn:feature_class":"P",
    "gn:feature_code":"PPLL",
    "gn:name":"Kicholpa",
    "gn:population":0,
    "gn:timezone":"Asia/Kathmandu",
    "iso:country":"NP",
    "wof:name":"Kicholpa",
    "wof:placetype":"locality"
},
  "geometry": {"coordinates":[85.22781999999999,27.48194],"type":"Point"}
}