{
  "type": "Feature",
  "properties": {
    "gn:admin1_code":"FR",
    "gn:admin2_code":"14",
    "gn:admin3_code":"70.0",
    "gn:admin4_code":"700003.0",
    "gn:asciiname":"Binesau",
    "gn:country_code":"NP",
    "gn:dem":716,
    "gn:feature_class":"P",
    "gn:feature_code":"PPLL",
    "gn:name":"Binesau",
    "gn:population":0,
    "gn:timezone":"Asia/Kathmandu",
    "iso:country":"NP",
    "wof:name":"Binesau",
    "wof:placetype":"locality"
},
  "geometry": {"coordinates":[80.83565,28.98214],"type":"Point"}
}