{
  "type": "Feature",
  "properties": {
    "gn:admin1_code":"ER",
    "gn:admin2_code":"13",
    "gn:admin3_code":"12",
    "gn:admin4_code":"120040",
    "gn:asciiname":"Pulai",
    "gn:country_code":"NP",
    "gn:dem":1662,
    "gn:feature_class":"P",
    "gn:feature_code":"PPLL",
    "gn:name":"Pulai",
    "gn:population":0,
    "gn:timezone":"Asia/Kathmandu",
    "iso:country":"NP",
    "wof:name":"Pulai",
    "wof:placetype":"locality"
},
  "geometry": {"coordinates":[86.29823,27.46885],"type":"Point"}
}