{
  "type": "Feature",
  "properties": {
    "gn:admin1_code":"WR",
    "gn:admin2_code":"3",
    "gn:admin3_code":"45.0",
    "gn:admin4_code":"450007.0",
    "gn:asciiname":"Kaphaldanda",
    "gn:country_code":"NP",
    "gn:dem":1410,
    "gn:feature_class":"P",
    "gn:feature_code":"PPLL",
    "gn:name":"Kaphaldanda",
    "gn:population":0,
    "gn:timezone":"Asia/Kathmandu",
    "iso:country":"NP",
    "wof:name":"Kaphaldanda",
    "wof:placetype":"locality"
},
  "geometry": {"coordinates":[83.5038,28.24584],"type":"Point"}
}