{
  "type": "Feature",
  "properties": {
    "gn:admin1_code":"ER",
    "gn:admin2_code":"7",
    "gn:admin3_code":"5",
    "gn:admin4_code":"50003",
    "gn:asciiname":"Jainpur Bahuwan",
    "gn:country_code":"NP",
    "gn:dem":70,
    "gn:feature_class":"P",
    "gn:feature_code":"PPLL",
    "gn:name":"Jainpur Bahuwan",
    "gn:population":0,
    "gn:timezone":"Asia/Kathmandu",
    "iso:country":"NP",
    "wof:name":"Jainpur Bahuwan",
    "wof:placetype":"locality"
},
  "geometry": {"coordinates":[87.50905999999998,26.44307],"type":"Point"}
}