{
  "type": "Feature",
  "properties": {
    "gn:admin1_code":"WR",
    "gn:admin2_code":"3",
    "gn:admin3_code":"45.0",
    "gn:admin4_code":"450002.0",
    "gn:asciiname":"Bhadar",
    "gn:country_code":"NP",
    "gn:dem":1358,
    "gn:feature_class":"P",
    "gn:feature_code":"PPLL",
    "gn:name":"Bhadar",
    "gn:population":0,
    "gn:timezone":"Asia/Kathmandu",
    "iso:country":"NP",
    "wof:name":"Bhadar",
    "wof:placetype":"locality"
},
  "geometry": {"coordinates":[83.61309,28.19797],"type":"Point"}
}