{
  "type": "Feature",
  "properties": {
    "gn:admin1_code":"MR",
    "gn:admin2_code":"6",
    "gn:admin3_code":"66.0",
    "gn:admin4_code":"660013.0",
    "gn:asciiname":"Tankchhe",
    "gn:country_code":"NP",
    "gn:dem":4224,
    "gn:feature_class":"P",
    "gn:feature_code":"PPLL",
    "gn:name":"Tankchhe",
    "gn:population":0,
    "gn:timezone":"Asia/Kathmandu",
    "iso:country":"NP",
    "wof:name":"Tankchhe",
    "wof:placetype":"locality"
},
  "geometry": {"coordinates":[81.67610999999999,30.27635],"type":"Point"}
}