{
  "type": "Feature",
  "properties": {
    "gn:admin1_code":"CR",
    "gn:admin2_code":"1",
    "gn:admin3_code":"28",
    "gn:admin4_code":"280008.0",
    "gn:asciiname":"Tallo Pipaltar",
    "gn:country_code":"NP",
    "gn:dem":555,
    "gn:feature_class":"P",
    "gn:feature_code":"PPLL",
    "gn:name":"Tallo Pipaltar",
    "gn:population":0,
    "gn:timezone":"Asia/Kathmandu",
    "iso:country":"NP",
    "wof:name":"Tallo Pipaltar",
    "wof:placetype":"locality"
},
  "geometry": {"coordinates":[85.12288000000002,27.86405],"type":"Point"}
}