{
  "type": "Feature",
  "properties": {
    "gn:admin1_code":"FR",
    "gn:admin2_code":"14.0",
    "gn:admin3_code":"67.0",
    "gn:admin4_code":"670001.0",
    "gn:asciiname":"Naina",
    "gn:country_code":"NP",
    "gn:dem":1685,
    "gn:feature_class":"P",
    "gn:feature_code":"PPLL",
    "gn:name":"Naina",
    "gn:population":0,
    "gn:timezone":"Asia/Kathmandu",
    "iso:country":"NP",
    "wof:name":"Naina",
    "wof:placetype":"locality"
},
  "geometry": {"coordinates":[81.38731,29.44319],"type":"Point"}
}