{
  "type": "Feature",
  "properties": {
    "gn:admin1_code":"FR",
    "gn:admin2_code":"14",
    "gn:admin3_code":"70.0",
    "gn:admin4_code":"700003.0",
    "gn:asciiname":"Berpati",
    "gn:country_code":"NP",
    "gn:dem":1028,
    "gn:feature_class":"P",
    "gn:feature_code":"PPLL",
    "gn:name":"Berpati",
    "gn:population":0,
    "gn:timezone":"Asia/Kathmandu",
    "iso:country":"NP",
    "wof:name":"Berpati",
    "wof:placetype":"locality"
},
  "geometry": {"coordinates":[80.81039,29.01664],"type":"Point"}
}