{
  "type": "Feature",
  "properties": {
    "gn:admin1_code":"CR",
    "gn:admin2_code":"11",
    "gn:admin3_code":"31",
    "gn:admin4_code":"310016.0",
    "gn:asciiname":"Katusepani",
    "gn:country_code":"NP",
    "gn:dem":355,
    "gn:feature_class":"P",
    "gn:feature_code":"PPLL",
    "gn:name":"Katusepani",
    "gn:population":0,
    "gn:timezone":"Asia/Kathmandu",
    "iso:country":"NP",
    "wof:name":"Katusepani",
    "wof:placetype":"locality"
},
  "geometry": {"coordinates":[85.37663000000001,27.29766],"type":"Point"}
}