{
  "type": "Feature",
  "properties": {
    "gn:admin1_code":"CR",
    "gn:admin2_code":"1",
    "gn:admin3_code":"28",
    "gn:admin4_code":"280006",
    "gn:asciiname":"Budhisera",
    "gn:country_code":"NP",
    "gn:dem":715,
    "gn:feature_class":"P",
    "gn:feature_code":"PPLL",
    "gn:name":"Budhisera",
    "gn:population":0,
    "gn:timezone":"Asia/Kathmandu",
    "iso:country":"NP",
    "wof:name":"Budhisera",
    "wof:placetype":"locality"
},
  "geometry": {"coordinates":[85.31976999999998,27.8603],"type":"Point"}
}