{
  "type": "Feature",
  "properties": {
    "gn:admin1_code":"WR",
    "gn:admin2_code":"8",
    "gn:admin3_code":"46.0",
    "gn:admin4_code":"460022.0",
    "gn:asciiname":"Thulachaur",
    "gn:country_code":"NP",
    "gn:dem":1276,
    "gn:feature_class":"P",
    "gn:feature_code":"PPLL",
    "gn:name":"Thulachaur",
    "gn:population":0,
    "gn:timezone":"Asia/Kathmandu",
    "iso:country":"NP",
    "wof:name":"Thulachaur",
    "wof:placetype":"locality"
},
  "geometry": {"coordinates":[83.28959,28.02717],"type":"Point"}
}