{
  "type": "Feature",
  "properties": {
    "gn:admin1_code":"WR",
    "gn:admin2_code":"3",
    "gn:admin3_code":"45.0",
    "gn:admin4_code":"450005.0",
    "gn:asciiname":"Salathan",
    "gn:country_code":"NP",
    "gn:dem":2875,
    "gn:feature_class":"P",
    "gn:feature_code":"PPLL",
    "gn:name":"Salathan",
    "gn:population":0,
    "gn:timezone":"Asia/Kathmandu",
    "iso:country":"NP",
    "wof:name":"Salathan",
    "wof:placetype":"locality"
},
  "geometry": {"coordinates":[83.06389,28.48243],"type":"Point"}
}