{
  "type": "Feature",
  "properties": {
    "gn:admin1_code":"WR",
    "gn:admin2_code":"4",
    "gn:admin3_code":"37",
    "gn:admin4_code":"370037",
    "gn:asciiname":"Chharnas",
    "gn:country_code":"NP",
    "gn:dem":1426,
    "gn:feature_class":"P",
    "gn:feature_code":"PPLL",
    "gn:name":"Chharnas",
    "gn:population":0,
    "gn:timezone":"Asia/Kathmandu",
    "iso:country":"NP",
    "wof:name":"Chharnas",
    "wof:placetype":"locality"
},
  "geometry": {"coordinates":[84.55134,28.15966],"type":"Point"}
}