{
  "type": "Feature",
  "properties": {
    "gn:admin1_code":"CR",
    "gn:admin2_code":"5",
    "gn:admin3_code":"19",
    "gn:admin4_code":"190005",
    "gn:asciiname":"Gadahatol",
    "gn:country_code":"NP",
    "gn:dem":106,
    "gn:feature_class":"P",
    "gn:feature_code":"PPLL",
    "gn:name":"Gadahatol",
    "gn:population":0,
    "gn:timezone":"Asia/Kathmandu",
    "iso:country":"NP",
    "wof:name":"Gadahatol",
    "wof:placetype":"locality"
},
  "geometry": {"coordinates":[85.6097,26.94976],"type":"Point"}
}