{
  "type": "Feature",
  "properties": {
    "gn:admin1_code":"ER",
    "gn:admin2_code":"7.0",
    "gn:admin3_code":"6.0",
    "gn:admin4_code":"60037.0",
    "gn:asciiname":"Ulti Teliyaritol",
    "gn:country_code":"NP",
    "gn:dem":83,
    "gn:feature_class":"P",
    "gn:feature_code":"PPLL",
    "gn:name":"Ulti Teliyaritol",
    "gn:population":0,
    "gn:timezone":"Asia/Kathmandu",
    "iso:country":"NP",
    "wof:name":"Ulti Teliyaritol",
    "wof:placetype":"locality"
},
  "geometry": {"coordinates":[87.08826999999999,26.55314000000001],"type":"Point"}
}