{
  "type": "Feature",
  "properties": {
    "gn:admin1_code":"WR",
    "gn:admin2_code":"4",
    "gn:admin3_code":"36.0",
    "gn:admin4_code":"360024.0",
    "gn:asciiname":"Khaireni Pakho",
    "gn:country_code":"NP",
    "gn:dem":539,
    "gn:feature_class":"P",
    "gn:feature_code":"PPLL",
    "gn:name":"Khaireni Pakho",
    "gn:population":0,
    "gn:timezone":"Asia/Kathmandu",
    "iso:country":"NP",
    "wof:name":"Khaireni Pakho",
    "wof:placetype":"locality"
},
  "geometry": {"coordinates":[84.6255,28.04685],"type":"Point"}
}