{
  "type": "Feature",
  "properties": {
    "gn:admin1_code":"MR",
    "gn:admin2_code":"12",
    "gn:admin3_code":"56.0",
    "gn:admin4_code":"560009.0",
    "gn:asciiname":"Syamari",
    "gn:country_code":"NP",
    "gn:dem":251,
    "gn:feature_class":"P",
    "gn:feature_code":"PPLL",
    "gn:name":"Syamari",
    "gn:population":0,
    "gn:timezone":"Asia/Kathmandu",
    "iso:country":"NP",
    "wof:name":"Syamari",
    "wof:placetype":"locality"
},
  "geometry": {"coordinates":[82.52979000000001,27.82703],"type":"Point"}
}