{
  "type": "Feature",
  "properties": {
    "gn:admin1_code":"CR",
    "gn:admin2_code":"11",
    "gn:admin3_code":"34",
    "gn:admin4_code":"340075",
    "gn:asciiname":"Subarnapur",
    "gn:country_code":"NP",
    "gn:dem":130,
    "gn:feature_class":"P",
    "gn:feature_code":"PPLL",
    "gn:name":"Subarnapur",
    "gn:population":0,
    "gn:timezone":"Asia/Kathmandu",
    "iso:country":"NP",
    "name:ceb_x_preferred":[
        "Subarnapur"
    ],
    "name:deu_x_preferred":[
        "Subarnapur"
    ],
    "name:swe_x_preferred":[
        "Subarnapur"
    ],
    "wof:name":"Subarnapur",
    "wof:placetype":"locality"
},
  "geometry": {"coordinates":[84.71042,27.22765],"type":"Point"}
}