{
  "type": "Feature",
  "properties": {
    "gn:admin1_code":"CR",
    "gn:admin2_code":"5",
    "gn:admin3_code":"19",
    "gn:admin4_code":"190071",
    "gn:asciiname":"Lopchandihi",
    "gn:country_code":"NP",
    "gn:dem":283,
    "gn:feature_class":"P",
    "gn:feature_code":"PPLL",
    "gn:name":"Lopchandihi",
    "gn:population":0,
    "gn:timezone":"Asia/Kathmandu",
    "iso:country":"NP",
    "wof:name":"Lopchandihi",
    "wof:placetype":"locality"
},
  "geometry": {"coordinates":[85.68484000000002,27.16228],"type":"Point"}
}