{
  "type": "Feature",
  "properties": {
    "gn:admin1_code":"MR",
    "gn:admin2_code":"12",
    "gn:admin3_code":"55",
    "gn:admin4_code":"550026",
    "gn:asciiname":"Badakholagaun",
    "gn:country_code":"NP",
    "gn:dem":1541,
    "gn:feature_class":"P",
    "gn:feature_code":"PPLL",
    "gn:name":"Badakholagaun",
    "gn:population":0,
    "gn:timezone":"Asia/Kathmandu",
    "iso:country":"NP",
    "wof:name":"Badakholagaun",
    "wof:placetype":"locality"
},
  "geometry": {"coordinates":[82.35056,28.46667],"type":"Point"}
}