{
  "type": "Feature",
  "properties": {
    "gn:admin1_code":"CR",
    "gn:admin2_code":"1",
    "gn:admin3_code":"27.0",
    "gn:admin4_code":"270029.0",
    "gn:asciiname":"Karkithok",
    "gn:country_code":"NP",
    "gn:dem":1379,
    "gn:feature_class":"P",
    "gn:feature_code":"PPLL",
    "gn:name":"Karkithok",
    "gn:population":0,
    "gn:timezone":"Asia/Kathmandu",
    "iso:country":"NP",
    "wof:name":"Karkithok",
    "wof:placetype":"locality"
},
  "geometry": {"coordinates":[85.31576,27.78385],"type":"Point"}
}