{
  "type": "Feature",
  "properties": {
    "gn:admin1_code":"00",
    "gn:asciiname":"Jogedada",
    "gn:country_code":"NP",
    "gn:dem":337,
    "gn:feature_class":"P",
    "gn:feature_code":"PPL",
    "gn:name":"Joge\u1e0d\u0101\u0303\u1e0d\u0101",
    "gn:population":0,
    "gn:timezone":"Asia/Kathmandu",
    "iso:country":"NP",
    "name:nep_x_preferred":[
        "Joge\u1e0d\u0101\u0303\u1e0d\u0101"
    ],
    "wof:name":"Jogedada",
    "wof:placetype":"locality"
},
  "geometry": {"coordinates":[86.45756,26.92386],"type":"Point"}
}