{
  "type": "Feature",
  "properties": {
    "gn:admin1_code":"FR",
    "gn:admin2_code":"14",
    "gn:admin3_code":"71.0",
    "gn:admin4_code":"710037.0",
    "gn:asciiname":"Belar",
    "gn:country_code":"NP",
    "gn:dem":184,
    "gn:feature_class":"P",
    "gn:feature_code":"PPLL",
    "gn:name":"Belar",
    "gn:population":0,
    "gn:timezone":"Asia/Kathmandu",
    "iso:country":"NP",
    "wof:name":"Belar",
    "wof:placetype":"locality"
},
  "geometry": {"coordinates":[80.97476,28.69857],"type":"Point"}
}