{
  "type": "Feature",
  "properties": {
    "gn:admin1_code":"ER",
    "gn:admin2_code":"10",
    "gn:admin3_code":"2",
    "gn:admin4_code":"20034",
    "gn:asciiname":"Oyakmatar",
    "gn:country_code":"NP",
    "gn:dem":1354,
    "gn:feature_class":"P",
    "gn:feature_code":"PPLL",
    "gn:name":"Oyakmatar",
    "gn:population":0,
    "gn:timezone":"Asia/Kathmandu",
    "iso:country":"NP",
    "wof:name":"Oyakmatar",
    "wof:placetype":"locality"
},
  "geometry": {"coordinates":[87.65204,26.98427],"type":"Point"}
}