{
  "type": "Feature",
  "properties": {
    "gn:admin1_code":"00",
    "gn:asciiname":"Dhadin Besi",
    "gn:country_code":"NP",
    "gn:dem":648,
    "gn:feature_class":"P",
    "gn:feature_code":"PPL",
    "gn:name":"Dh\u0101di\u1e45 Besi\u0307\u0304",
    "gn:population":0,
    "gn:timezone":"Asia/Kathmandu",
    "iso:country":"NP",
    "name:nep_x_preferred":[
        "Dh\u0101di\u1e45 Besi\u0307\u0304"
    ],
    "name:und_x_variant":[
        "Dhadinbesi"
    ],
    "wof:name":"Dhadin Besi",
    "wof:placetype":"locality"
},
  "geometry": {"coordinates":[84.89626,27.91281],"type":"Point"}
}