{
  "type": "Feature",
  "properties": {
    "gn:admin1_code":"FR",
    "gn:admin2_code":"14",
    "gn:admin3_code":"70.0",
    "gn:admin4_code":"700006.0",
    "gn:asciiname":"Sabala",
    "gn:country_code":"NP",
    "gn:dem":497,
    "gn:feature_class":"P",
    "gn:feature_code":"PPLL",
    "gn:name":"Sabala",
    "gn:population":0,
    "gn:timezone":"Asia/Kathmandu",
    "iso:country":"NP",
    "wof:name":"Sabala",
    "wof:placetype":"locality"
},
  "geometry": {"coordinates":[81.12268,29.07792],"type":"Point"}
}