{
  "type": "Feature",
  "properties": {
    "gn:admin1_code":"ER",
    "gn:admin2_code":"7",
    "gn:admin3_code":"9",
    "gn:admin4_code":"90009.0",
    "gn:asciiname":"Tomuwabesi",
    "gn:country_code":"NP",
    "gn:dem":1026,
    "gn:feature_class":"P",
    "gn:feature_code":"PPLL",
    "gn:name":"Tomuwabesi",
    "gn:population":0,
    "gn:timezone":"Asia/Kathmandu",
    "iso:country":"NP",
    "wof:name":"Tomuwabesi",
    "wof:placetype":"locality"
},
  "geometry": {"coordinates":[87.20177,27.51316],"type":"Point"}
}