{
  "type": "Feature",
  "properties": {
    "gn:admin1_code":"WR",
    "gn:admin2_code":"8",
    "gn:admin3_code":"48",
    "gn:admin4_code":"480054",
    "gn:asciiname":"Rakachuli",
    "gn:country_code":"NP",
    "gn:dem":1022,
    "gn:feature_class":"P",
    "gn:feature_code":"PPLL",
    "gn:name":"Rakachuli",
    "gn:population":0,
    "gn:timezone":"Asia/Kathmandu",
    "iso:country":"NP",
    "name:ceb_x_preferred":[
        "Rakachuli"
    ],
    "name:fra_x_preferred":[
        "Rakachuli"
    ],
    "name:mai_x_preferred":[
        "\u0930\u093e\u0915\u093e\u091a\u0941\u0932\u0940"
    ],
    "name:msa_x_preferred":[
        "Rakachuli"
    ],
    "name:nep_x_preferred":[
        "\u0930\u093e\u0915\u093e\u091a\u0941\u0932\u0940"
    ],
    "name:new_x_preferred":[
        "\u0930\u093e\u0915\u093e\u091a\u0941\u0932\u0940"
    ],
    "name:pol_x_preferred":[
        "Rakachuli"
    ],
    "wof:name":"Rakachuli",
    "wof:placetype":"locality"
},
  "geometry": {"coordinates":[83.85736,27.71631],"type":"Point"}
}