{
  "type": "Feature",
  "properties": {
    "gn:admin1_code":"WR",
    "gn:admin2_code":"8",
    "gn:admin3_code":"47",
    "gn:admin4_code":"470033",
    "gn:asciiname":"Chahala",
    "gn:country_code":"NP",
    "gn:dem":851,
    "gn:feature_class":"P",
    "gn:feature_code":"PPLL",
    "gn:name":"Chahala",
    "gn:population":0,
    "gn:timezone":"Asia/Kathmandu",
    "iso:country":"NP",
    "wof:name":"Chahala",
    "wof:placetype":"locality"
},
  "geometry": {"coordinates":[83.33563000000002,27.79129],"type":"Point"}
}