{
  "type": "Feature",
  "properties": {
    "gn:admin1_code":"MR",
    "gn:admin2_code":"2",
    "gn:admin3_code":"61.0",
    "gn:admin4_code":"610009.0",
    "gn:asciiname":"Bajikamata",
    "gn:country_code":"NP",
    "gn:dem":784,
    "gn:feature_class":"P",
    "gn:feature_code":"PPLL",
    "gn:name":"Bajikamata",
    "gn:population":0,
    "gn:timezone":"Asia/Kathmandu",
    "iso:country":"NP",
    "wof:name":"Bajikamata",
    "wof:placetype":"locality"
},
  "geometry": {"coordinates":[82.17508000000002,28.63093],"type":"Point"}
}