{
  "type": "Feature",
  "properties": {
    "gn:admin1_code":"MR",
    "gn:admin2_code":"2",
    "gn:admin3_code":"61.0",
    "gn:admin4_code":"610008.0",
    "gn:asciiname":"Ghuskholagaun",
    "gn:country_code":"NP",
    "gn:dem":1960,
    "gn:feature_class":"P",
    "gn:feature_code":"PPLL",
    "gn:name":"Ghuskholagaun",
    "gn:population":0,
    "gn:timezone":"Asia/Kathmandu",
    "iso:country":"NP",
    "wof:name":"Ghuskholagaun",
    "wof:placetype":"locality"
},
  "geometry": {"coordinates":[82.00118000000001,28.81314],"type":"Point"}
}