{
  "type": "Feature",
  "properties": {
    "gn:admin1_code":"CR",
    "gn:admin2_code":"11",
    "gn:admin3_code":"34",
    "gn:admin4_code":"340003",
    "gn:asciiname":"Sisiai Bahuari",
    "gn:country_code":"NP",
    "gn:dem":95,
    "gn:feature_class":"P",
    "gn:feature_code":"PPLL",
    "gn:name":"Sisiai Bahuari",
    "gn:population":0,
    "gn:timezone":"Asia/Kathmandu",
    "iso:country":"NP",
    "wof:name":"Sisiai Bahuari",
    "wof:placetype":"locality"
},
  "geometry": {"coordinates":[84.77083,27.11601],"type":"Point"}
}