{
  "type": "Feature",
  "properties": {
    "gn:admin1_code":"CR",
    "gn:admin2_code":"1",
    "gn:admin3_code":"24.0",
    "gn:admin4_code":"240086.0",
    "gn:asciiname":"Gagalate",
    "gn:country_code":"NP",
    "gn:dem":1715,
    "gn:feature_class":"P",
    "gn:feature_code":"PPLL",
    "gn:name":"Gagalate",
    "gn:population":0,
    "gn:timezone":"Asia/Kathmandu",
    "iso:country":"NP",
    "wof:name":"Gagalate",
    "wof:placetype":"locality"
},
  "geometry": {"coordinates":[85.65768,27.45816],"type":"Point"}
}