{
  "type": "Feature",
  "properties": {
    "gn:admin1_code":"CR",
    "gn:admin2_code":"5",
    "gn:admin3_code":"21",
    "gn:admin4_code":"210013",
    "gn:asciiname":"Gothgaun",
    "gn:country_code":"NP",
    "gn:dem":1262,
    "gn:feature_class":"P",
    "gn:feature_code":"PPLL",
    "gn:name":"Gothgaun",
    "gn:population":0,
    "gn:timezone":"Asia/Kathmandu",
    "iso:country":"NP",
    "wof:name":"Gothgaun",
    "wof:placetype":"locality"
},
  "geometry": {"coordinates":[86.18365,27.37658],"type":"Point"}
}