{
  "type": "Feature",
  "properties": {
    "gn:admin1_code":"MR",
    "gn:admin2_code":"12",
    "gn:admin3_code":"55",
    "gn:admin4_code":"550002",
    "gn:asciiname":"Bajer",
    "gn:country_code":"NP",
    "gn:dem":1883,
    "gn:feature_class":"P",
    "gn:feature_code":"PPLL",
    "gn:name":"Bajer",
    "gn:population":0,
    "gn:timezone":"Asia/Kathmandu",
    "iso:country":"NP",
    "name:ces_x_preferred":[
        "Bajer"
    ],
    "name:dan_x_preferred":[
        "Bajer"
    ],
    "name:deu_x_preferred":[
        "Bajer"
    ],
    "name:srp_x_preferred":[
        "\u0411\u0430\u0458\u0435\u0440"
    ],
    "wof:name":"Bajer",
    "wof:placetype":"locality"
},
  "geometry": {"coordinates":[82.40181,28.48254],"type":"Point"}
}