{
  "type": "Feature",
  "properties": {
    "gn:admin1_code":"00",
    "gn:asciiname":"Munchu",
    "gn:country_code":"NP",
    "gn:dem":3110,
    "gn:feature_class":"P",
    "gn:feature_code":"PPL",
    "gn:name":"Munch\u016b",
    "gn:population":0,
    "gn:timezone":"Asia/Kathmandu",
    "iso:country":"NP",
    "name:und_x_variant":[
        "Munchi",
        "Munch\u016b"
    ],
    "wof:name":"Munchu",
    "wof:placetype":"locality"
},
  "geometry": {"coordinates":[81.54375,30.06849],"type":"Point"}
}