{
  "type": "Feature",
  "properties": {
    "gn:admin1_code":"WR",
    "gn:admin2_code":"4",
    "gn:admin3_code":"36.0",
    "gn:admin4_code":"360001.0",
    "gn:asciiname":"Maiwal",
    "gn:country_code":"NP",
    "gn:dem":1240,
    "gn:feature_class":"P",
    "gn:feature_code":"PPLL",
    "gn:name":"Maiwal",
    "gn:population":0,
    "gn:timezone":"Asia/Kathmandu",
    "iso:country":"NP",
    "wof:name":"Maiwal",
    "wof:placetype":"locality"
},
  "geometry": {"coordinates":[84.53171999999998,28.06152],"type":"Point"}
}