{
  "type": "Feature",
  "properties": {
    "gn:admin1_code":"WR",
    "gn:admin2_code":"4.0",
    "gn:admin3_code":"38.0",
    "gn:admin4_code":"380021.0",
    "gn:asciiname":"Kamitari Narpate",
    "gn:country_code":"NP",
    "gn:dem":543,
    "gn:feature_class":"P",
    "gn:feature_code":"PPLL",
    "gn:name":"Kamitari Narpate",
    "gn:population":0,
    "gn:timezone":"Asia/Kathmandu",
    "iso:country":"NP",
    "wof:name":"Kamitari Narpate",
    "wof:placetype":"locality"
},
  "geometry": {"coordinates":[84.01692,28.10382],"type":"Point"}
}