{
  "type": "Feature",
  "properties": {
    "gn:admin1_code":"FR",
    "gn:admin2_code":"9",
    "gn:admin3_code":"74",
    "gn:admin4_code":"740056",
    "gn:asciiname":"Kartekot",
    "gn:country_code":"NP",
    "gn:dem":1945,
    "gn:feature_class":"P",
    "gn:feature_code":"PPLL",
    "gn:name":"Kartekot",
    "gn:population":0,
    "gn:timezone":"Asia/Kathmandu",
    "iso:country":"NP",
    "wof:name":"Kartekot",
    "wof:placetype":"locality"
},
  "geometry": {"coordinates":[80.62109,29.46282],"type":"Point"}
}