{
  "type": "Feature",
  "properties": {
    "gn:admin1_code":"WR",
    "gn:admin2_code":"4.0",
    "gn:admin3_code":"39.0",
    "gn:admin4_code":"390013.0",
    "gn:asciiname":"Dhurkot",
    "gn:country_code":"NP",
    "gn:dem":857,
    "gn:feature_class":"P",
    "gn:feature_code":"PPLL",
    "gn:name":"Dhurkot",
    "gn:population":0,
    "gn:timezone":"Asia/Kathmandu",
    "iso:country":"NP",
    "name:ceb_x_preferred":[
        "Dhurkot"
    ],
    "name:fra_x_preferred":[
        "Dhurkot"
    ],
    "name:hin_x_preferred":[
        "\u0927\u0941\u0930\u0915\u094b\u0924"
    ],
    "name:msa_x_preferred":[
        "Dhurkot"
    ],
    "name:nep_x_preferred":[
        "\u0927\u0941\u0930\u0915\u094b\u0924"
    ],
    "name:new_x_preferred":[
        "\u0927\u0941\u0930\u0915\u094b\u0924"
    ],
    "name:pol_x_preferred":[
        "Dhurkot"
    ],
    "wof:name":"Dhurkot",
    "wof:placetype":"locality"
},
  "geometry": {"coordinates":[83.82822,27.92122],"type":"Point"}
}