{
  "type": "Feature",
  "properties": {
    "gn:admin1_code":"WR",
    "gn:admin2_code":"3",
    "gn:admin3_code":"43",
    "gn:admin4_code":"430036",
    "gn:asciiname":"Darkha",
    "gn:country_code":"NP",
    "gn:dem":1664,
    "gn:feature_class":"P",
    "gn:feature_code":"PPLL",
    "gn:name":"Darkha",
    "gn:population":0,
    "gn:timezone":"Asia/Kathmandu",
    "iso:country":"NP",
    "wof:name":"Darkha",
    "wof:placetype":"locality"
},
  "geometry": {"coordinates":[83.35198000000003,28.40195],"type":"Point"}
}