{
  "type": "Feature",
  "properties": {
    "gn:admin1_code":"WR",
    "gn:admin2_code":"8",
    "gn:admin3_code":"50.0",
    "gn:admin4_code":"500023.0",
    "gn:asciiname":"Taku",
    "gn:country_code":"NP",
    "gn:dem":130,
    "gn:feature_class":"P",
    "gn:feature_code":"PPLL",
    "gn:name":"Taku",
    "gn:population":0,
    "gn:timezone":"Asia/Kathmandu",
    "iso:country":"NP",
    "name:ceb_x_preferred":[
        "Taku"
    ],
    "name:deu_x_preferred":[
        "Taku"
    ],
    "name:fin_x_preferred":[
        "Taku"
    ],
    "name:fra_x_preferred":[
        "Taku"
    ],
    "name:jpn_x_preferred":[
        "Taku"
    ],
    "name:nld_x_preferred":[
        "Taku"
    ],
    "name:swe_x_preferred":[
        "Taku"
    ],
    "wof:name":"Taku",
    "wof:placetype":"locality"
},
  "geometry": {"coordinates":[82.98097,27.72294],"type":"Point"}
}