{
  "type": "Feature",
  "properties": {
    "gn:admin1_code":"FR",
    "gn:admin2_code":"14",
    "gn:admin3_code":"69.0",
    "gn:admin4_code":"690009.0",
    "gn:asciiname":"Siruban",
    "gn:country_code":"NP",
    "gn:dem":819,
    "gn:feature_class":"P",
    "gn:feature_code":"PPLL",
    "gn:name":"Siruban",
    "gn:population":0,
    "gn:timezone":"Asia/Kathmandu",
    "iso:country":"NP",
    "wof:name":"Siruban",
    "wof:placetype":"locality"
},
  "geometry": {"coordinates":[81.39865999999998,28.96383],"type":"Point"}
}