{
  "type": "Feature",
  "properties": {
    "gn:admin1_code":"MR",
    "gn:admin2_code":"2.0",
    "gn:admin3_code":"57.0",
    "gn:admin4_code":"570042.0",
    "gn:asciiname":"Nayanbasti",
    "gn:country_code":"NP",
    "gn:dem":159,
    "gn:feature_class":"P",
    "gn:feature_code":"PPLL",
    "gn:name":"Nayanbasti",
    "gn:population":0,
    "gn:timezone":"Asia/Kathmandu",
    "iso:country":"NP",
    "wof:name":"Nayanbasti",
    "wof:placetype":"locality"
},
  "geometry": {"coordinates":[81.67737,28.1446],"type":"Point"}
}