{
  "type": "Feature",
  "properties": {
    "gn:admin1_code":"CR",
    "gn:admin2_code":"5",
    "gn:admin3_code":"20",
    "gn:admin4_code":"200002",
    "gn:asciiname":"Gujarat",
    "gn:country_code":"NP",
    "gn:dem":732,
    "gn:feature_class":"P",
    "gn:feature_code":"PPLL",
    "gn:name":"Gujarat",
    "gn:population":0,
    "gn:timezone":"Asia/Kathmandu",
    "iso:country":"NP",
    "wof:name":"Gujarat",
    "wof:placetype":"locality"
},
  "geometry": {"coordinates":[86.25235000000001,27.04554000000001],"type":"Point"}
}