{
  "type": "Feature",
  "properties": {
    "gn:admin1_code":"MR",
    "gn:admin2_code":"2.0",
    "gn:admin3_code":"59.0",
    "gn:admin4_code":"590049.0",
    "gn:asciiname":"Kaseni",
    "gn:country_code":"NP",
    "gn:dem":342,
    "gn:feature_class":"P",
    "gn:feature_code":"PPLL",
    "gn:name":"Kaseni",
    "gn:population":0,
    "gn:timezone":"Asia/Kathmandu",
    "iso:country":"NP",
    "name:pol_x_preferred":[
        "Kaseni"
    ],
    "wof:name":"Kaseni",
    "wof:placetype":"locality"
},
  "geometry": {"coordinates":[81.41209000000001,28.68303],"type":"Point"}
}