{
  "type": "Feature",
  "properties": {
    "gn:admin1_code":"CR",
    "gn:admin2_code":"1",
    "gn:admin3_code":"23",
    "gn:admin4_code":"230053",
    "gn:asciiname":"Pantang",
    "gn:country_code":"NP",
    "gn:dem":1986,
    "gn:feature_class":"P",
    "gn:feature_code":"PPLL",
    "gn:name":"Pantang",
    "gn:population":0,
    "gn:timezone":"Asia/Kathmandu",
    "iso:country":"NP",
    "wof:name":"Pantang",
    "wof:placetype":"locality"
},
  "geometry": {"coordinates":[85.79889,27.8997],"type":"Point"}
}