{
  "type": "Feature",
  "properties": {
    "gn:admin1_code":"FR",
    "gn:admin2_code":"14",
    "gn:admin3_code":"71.0",
    "gn:admin4_code":"710006.0",
    "gn:asciiname":"Choripur",
    "gn:country_code":"NP",
    "gn:dem":170,
    "gn:feature_class":"P",
    "gn:feature_code":"PPLL",
    "gn:name":"Choripur",
    "gn:population":0,
    "gn:timezone":"Asia/Kathmandu",
    "iso:country":"NP",
    "wof:name":"Choripur",
    "wof:placetype":"locality"
},
  "geometry": {"coordinates":[81.12105,28.64923],"type":"Point"}
}