{
  "type": "Feature",
  "properties": {
    "gn:admin1_code":"MR",
    "gn:admin2_code":"12",
    "gn:admin3_code":"53",
    "gn:admin4_code":"530045",
    "gn:asciiname":"Bidbang",
    "gn:country_code":"NP",
    "gn:dem":1700,
    "gn:feature_class":"P",
    "gn:feature_code":"PPLL",
    "gn:name":"Bidbang",
    "gn:population":0,
    "gn:timezone":"Asia/Kathmandu",
    "iso:country":"NP",
    "wof:name":"Bidbang",
    "wof:placetype":"locality"
},
  "geometry": {"coordinates":[82.50541,28.45191],"type":"Point"}
}