{
  "type": "Feature",
  "properties": {
    "gn:admin1_code":"WR",
    "gn:admin2_code":"4.0",
    "gn:admin3_code":"38.0",
    "gn:admin4_code":"380008.0",
    "gn:asciiname":"Gahate",
    "gn:country_code":"NP",
    "gn:dem":562,
    "gn:feature_class":"P",
    "gn:feature_code":"PPLL",
    "gn:name":"Gahate",
    "gn:population":0,
    "gn:timezone":"Asia/Kathmandu",
    "iso:country":"NP",
    "wof:name":"Gahate",
    "wof:placetype":"locality"
},
  "geometry": {"coordinates":[84.03832,28.0127],"type":"Point"}
}