{
  "type": "Feature",
  "properties": {
    "gn:admin1_code":"WR",
    "gn:admin2_code":"8",
    "gn:admin3_code":"46.0",
    "gn:admin4_code":"460046.0",
    "gn:asciiname":"Thulapokharagaun",
    "gn:country_code":"NP",
    "gn:dem":1384,
    "gn:feature_class":"P",
    "gn:feature_code":"PPLL",
    "gn:name":"Thulapokharagaun",
    "gn:population":0,
    "gn:timezone":"Asia/Kathmandu",
    "iso:country":"NP",
    "wof:name":"Thulapokharagaun",
    "wof:placetype":"locality"
},
  "geometry": {"coordinates":[83.36259,28.02567],"type":"Point"}
}