{
  "type": "Feature",
  "properties": {
    "gn:admin1_code":"ER",
    "gn:admin2_code":"13",
    "gn:admin3_code":"13",
    "gn:admin4_code":"130068",
    "gn:asciiname":"Bojheni",
    "gn:country_code":"NP",
    "gn:dem":1478,
    "gn:feature_class":"P",
    "gn:feature_code":"PPLL",
    "gn:name":"Bojheni",
    "gn:population":0,
    "gn:timezone":"Asia/Kathmandu",
    "iso:country":"NP",
    "wof:name":"Bojheni",
    "wof:placetype":"locality"
},
  "geometry": {"coordinates":[86.83029999999999,26.95545],"type":"Point"}
}