{
  "type": "Feature",
  "properties": {
    "gn:admin1_code":"CR",
    "gn:admin2_code":"5",
    "gn:admin3_code":"20",
    "gn:admin4_code":"200023",
    "gn:asciiname":"Kamitar",
    "gn:country_code":"NP",
    "gn:dem":1135,
    "gn:feature_class":"P",
    "gn:feature_code":"PPLL",
    "gn:name":"Kamitar",
    "gn:population":0,
    "gn:timezone":"Asia/Kathmandu",
    "iso:country":"NP",
    "wof:name":"Kamitar",
    "wof:placetype":"locality"
},
  "geometry": {"coordinates":[86.32384999999999,27.05067],"type":"Point"}
}