{
  "type": "Feature",
  "properties": {
    "gn:admin1_code":"MR",
    "gn:admin2_code":"6",
    "gn:admin3_code":"66.0",
    "gn:admin4_code":"660014.0",
    "gn:asciiname":"Tanja Maila",
    "gn:country_code":"NP",
    "gn:dem":1921,
    "gn:feature_class":"P",
    "gn:feature_code":"PPLL",
    "gn:name":"Tanja Maila",
    "gn:population":0,
    "gn:timezone":"Asia/Kathmandu",
    "iso:country":"NP",
    "wof:name":"Tanja Maila",
    "wof:placetype":"locality"
},
  "geometry": {"coordinates":[81.75638000000002,29.63519],"type":"Point"}
}