{
  "type": "Feature",
  "properties": {
    "gn:admin1_code":"WR",
    "gn:admin2_code":"8",
    "gn:admin3_code":"47",
    "gn:admin4_code":"470034",
    "gn:asciiname":"Huksepakha",
    "gn:country_code":"NP",
    "gn:dem":810,
    "gn:feature_class":"P",
    "gn:feature_code":"PPLL",
    "gn:name":"Huksepakha",
    "gn:population":0,
    "gn:timezone":"Asia/Kathmandu",
    "iso:country":"NP",
    "wof:name":"Huksepakha",
    "wof:placetype":"locality"
},
  "geometry": {"coordinates":[83.78046999999999,27.72965],"type":"Point"}
}