{
  "type": "Feature",
  "properties": {
    "gn:admin1_code":"ER",
    "gn:admin2_code":"13",
    "gn:admin3_code":"12",
    "gn:admin4_code":"120013.0",
    "gn:asciiname":"Saniduwa",
    "gn:country_code":"NP",
    "gn:dem":1634,
    "gn:feature_class":"P",
    "gn:feature_code":"PPLL",
    "gn:name":"Saniduwa",
    "gn:population":0,
    "gn:timezone":"Asia/Kathmandu",
    "iso:country":"NP",
    "wof:name":"Saniduwa",
    "wof:placetype":"locality"
},
  "geometry": {"coordinates":[86.34838000000001,27.3159],"type":"Point"}
}