{
  "type": "Feature",
  "properties": {
    "gn:admin1_code":"MR",
    "gn:admin2_code":"12",
    "gn:admin3_code":"54",
    "gn:admin4_code":"540013",
    "gn:asciiname":"Banke Jyula",
    "gn:country_code":"NP",
    "gn:dem":1190,
    "gn:feature_class":"P",
    "gn:feature_code":"PPLL",
    "gn:name":"Banke Jyula",
    "gn:population":0,
    "gn:timezone":"Asia/Kathmandu",
    "iso:country":"NP",
    "wof:name":"Banke Jyula",
    "wof:placetype":"locality"
},
  "geometry": {"coordinates":[82.29689,28.736],"type":"Point"}
}