{
  "type": "Feature",
  "properties": {
    "gn:admin1_code":"MR",
    "gn:admin2_code":"2.0",
    "gn:admin3_code":"59.0",
    "gn:admin4_code":"590010.0",
    "gn:asciiname":"Maintada",
    "gn:country_code":"NP",
    "gn:dem":698,
    "gn:feature_class":"P",
    "gn:feature_code":"PPLL",
    "gn:name":"Maintada",
    "gn:population":0,
    "gn:timezone":"Asia/Kathmandu",
    "iso:country":"NP",
    "name:fra_x_preferred":[
        "Maintada"
    ],
    "name:msa_x_preferred":[
        "Maintada"
    ],
    "name:nep_x_preferred":[
        "\u092e\u0948\u0928\u0924\u0921\u093e"
    ],
    "name:new_x_preferred":[
        "\u092e\u0948\u0928\u094d\u0924\u093e\u0921\u093e"
    ],
    "name:pol_x_preferred":[
        "Maintada"
    ],
    "wof:name":"Maintada",
    "wof:placetype":"locality"
},
  "geometry": {"coordinates":[81.70418000000002,28.42963],"type":"Point"}
}