{
  "type": "Feature",
  "properties": {
    "gn:admin1_code":"CR",
    "gn:admin2_code":"5",
    "gn:admin3_code":"17.0",
    "gn:admin4_code":"170061.0",
    "gn:asciiname":"Nirajpur",
    "gn:country_code":"NP",
    "gn:dem":154,
    "gn:feature_class":"P",
    "gn:feature_code":"PPLL",
    "gn:name":"Nirajpur",
    "gn:population":0,
    "gn:timezone":"Asia/Kathmandu",
    "iso:country":"NP",
    "wof:name":"Nirajpur",
    "wof:placetype":"locality"
},
  "geometry": {"coordinates":[85.91542,26.91666],"type":"Point"}
}