{
  "type": "Feature",
  "properties": {
    "gn:admin1_code":"FR",
    "gn:admin2_code":"9",
    "gn:admin3_code":"74",
    "gn:admin4_code":"740036",
    "gn:asciiname":"Rikhoda",
    "gn:country_code":"NP",
    "gn:dem":1916,
    "gn:feature_class":"P",
    "gn:feature_code":"PPLL",
    "gn:name":"Rikhoda",
    "gn:population":0,
    "gn:timezone":"Asia/Kathmandu",
    "iso:country":"NP",
    "wof:name":"Rikhoda",
    "wof:placetype":"locality"
},
  "geometry": {"coordinates":[80.65003,29.58602],"type":"Point"}
}