{
  "type": "Feature",
  "properties": {
    "gn:admin1_code":"MR",
    "gn:admin2_code":"12",
    "gn:admin3_code":"53",
    "gn:admin4_code":"530042",
    "gn:asciiname":"Sajar",
    "gn:country_code":"NP",
    "gn:dem":1909,
    "gn:feature_class":"P",
    "gn:feature_code":"PPLL",
    "gn:name":"Sajar",
    "gn:population":0,
    "gn:timezone":"Asia/Kathmandu",
    "iso:country":"NP",
    "name:fas_x_preferred":[
        "\u0633\u062c\u0627\u0631"
    ],
    "wof:name":"Sajar",
    "wof:placetype":"locality"
},
  "geometry": {"coordinates":[82.83511,28.4031],"type":"Point"}
}