{
  "type": "Feature",
  "properties": {
    "gn:admin1_code":"WR",
    "gn:admin2_code":"4.0",
    "gn:admin3_code":"39.0",
    "gn:admin4_code":"390017.0",
    "gn:asciiname":"Jarebar",
    "gn:country_code":"NP",
    "gn:dem":485,
    "gn:feature_class":"P",
    "gn:feature_code":"PPLL",
    "gn:name":"Jarebar",
    "gn:population":0,
    "gn:timezone":"Asia/Kathmandu",
    "iso:country":"NP",
    "wof:name":"Jarebar",
    "wof:placetype":"locality"
},
  "geometry": {"coordinates":[84.03100000000001,28.01997],"type":"Point"}
}