{
  "type": "Feature",
  "properties": {
    "gn:admin1_code":"FR",
    "gn:admin2_code":"9",
    "gn:admin3_code":"73.0",
    "gn:admin4_code":"730001.0",
    "gn:asciiname":"Deugada",
    "gn:country_code":"NP",
    "gn:dem":1539,
    "gn:feature_class":"P",
    "gn:feature_code":"PPLL",
    "gn:name":"Deugada",
    "gn:population":0,
    "gn:timezone":"Asia/Kathmandu",
    "iso:country":"NP",
    "wof:name":"Deugada",
    "wof:placetype":"locality"
},
  "geometry": {"coordinates":[80.59668000000001,29.36387],"type":"Point"}
}