{
  "type": "Feature",
  "properties": {
    "gn:admin1_code":"CR",
    "gn:admin2_code":"11",
    "gn:admin3_code":"32",
    "gn:admin4_code":"320061",
    "gn:asciiname":"Mahuliya",
    "gn:country_code":"NP",
    "gn:dem":76,
    "gn:feature_class":"P",
    "gn:feature_code":"PPLL",
    "gn:name":"Mahuliya",
    "gn:population":0,
    "gn:timezone":"Asia/Kathmandu",
    "iso:country":"NP",
    "wof:name":"Mahuliya",
    "wof:placetype":"locality"
},
  "geometry": {"coordinates":[85.20314999999999,26.77387],"type":"Point"}
}