{
  "type": "Feature",
  "properties": {
    "gn:admin1_code":"CR",
    "gn:admin2_code":"5",
    "gn:admin3_code":"20",
    "gn:admin4_code":"200047",
    "gn:asciiname":"Neupanetar",
    "gn:country_code":"NP",
    "gn:dem":520,
    "gn:feature_class":"P",
    "gn:feature_code":"PPLL",
    "gn:name":"Neupanetar",
    "gn:population":0,
    "gn:timezone":"Asia/Kathmandu",
    "iso:country":"NP",
    "wof:name":"Neupanetar",
    "wof:placetype":"locality"
},
  "geometry": {"coordinates":[85.97416,27.36149],"type":"Point"}
}