{
  "type": "Feature",
  "properties": {
    "gn:admin1_code":"FR",
    "gn:admin2_code":"9",
    "gn:admin3_code":"74",
    "gn:admin4_code":"740005",
    "gn:asciiname":"Annari",
    "gn:country_code":"NP",
    "gn:dem":1438,
    "gn:feature_class":"P",
    "gn:feature_code":"PPLL",
    "gn:name":"Annari",
    "gn:population":0,
    "gn:timezone":"Asia/Kathmandu",
    "iso:country":"NP",
    "wof:name":"Annari",
    "wof:placetype":"locality"
},
  "geometry": {"coordinates":[80.5518,29.47745],"type":"Point"}
}