{
  "type": "Feature",
  "properties": {
    "gn:admin1_code":"00",
    "gn:asciiname":"Sansange",
    "gn:country_code":"NP",
    "gn:dem":546,
    "gn:feature_class":"P",
    "gn:feature_code":"PPL",
    "gn:name":"S\u0101\u1e45s\u0101\u1e45ge",
    "gn:population":0,
    "gn:timezone":"Asia/Kathmandu",
    "iso:country":"NP",
    "name:nep_x_preferred":[
        "S\u0101\u1e45s\u0101\u1e45ge"
    ],
    "wof:name":"Sansange",
    "wof:placetype":"locality"
},
  "geometry": {"coordinates":[88.14293000000001,26.78353],"type":"Point"}
}