{
  "type": "Feature",
  "properties": {
    "gn:admin1_code":"ER",
    "gn:admin2_code":"7",
    "gn:admin3_code":"5",
    "gn:admin4_code":"50065.0",
    "gn:asciiname":"Pitlumba",
    "gn:country_code":"NP",
    "gn:dem":1178,
    "gn:feature_class":"P",
    "gn:feature_code":"PPLL",
    "gn:name":"Pitlumba",
    "gn:population":0,
    "gn:timezone":"Asia/Kathmandu",
    "iso:country":"NP",
    "wof:name":"Pitlumba",
    "wof:placetype":"locality"
},
  "geometry": {"coordinates":[87.50641999999998,26.82826],"type":"Point"}
}