{
  "type": "Feature",
  "properties": {
    "gn:admin1_code":"CR",
    "gn:admin2_code":"5",
    "gn:admin3_code":"22.0",
    "gn:admin4_code":"220023.0",
    "gn:asciiname":"Mahatara",
    "gn:country_code":"NP",
    "gn:dem":1460,
    "gn:feature_class":"P",
    "gn:feature_code":"PPLL",
    "gn:name":"Mahatara",
    "gn:population":0,
    "gn:timezone":"Asia/Kathmandu",
    "iso:country":"NP",
    "wof:name":"Mahatara",
    "wof:placetype":"locality"
},
  "geometry": {"coordinates":[86.16630000000001,27.71942],"type":"Point"}
}