{
  "type": "Feature",
  "properties": {
    "gn:admin1_code":"ER",
    "gn:admin2_code":"7",
    "gn:admin3_code":"7.0",
    "gn:admin4_code":"70029.0",
    "gn:asciiname":"Ganeshtar",
    "gn:country_code":"NP",
    "gn:dem":1805,
    "gn:feature_class":"P",
    "gn:feature_code":"PPLL",
    "gn:name":"Ganeshtar",
    "gn:population":0,
    "gn:timezone":"Asia/Kathmandu",
    "iso:country":"NP",
    "wof:name":"Ganeshtar",
    "wof:placetype":"locality"
},
  "geometry": {"coordinates":[87.36731,27.09227000000001],"type":"Point"}
}