{
  "type": "Feature",
  "properties": {
    "gn:admin1_code":"MR",
    "gn:admin2_code":"12",
    "gn:admin3_code":"53",
    "gn:admin4_code":"530011",
    "gn:asciiname":"Bhirkharka",
    "gn:country_code":"NP",
    "gn:dem":1675,
    "gn:feature_class":"P",
    "gn:feature_code":"PPLL",
    "gn:name":"Bhirkharka",
    "gn:population":0,
    "gn:timezone":"Asia/Kathmandu",
    "iso:country":"NP",
    "wof:name":"Bhirkharka",
    "wof:placetype":"locality"
},
  "geometry": {"coordinates":[82.49401,28.32742],"type":"Point"}
}