{
  "type": "Feature",
  "properties": {
    "gn:admin1_code":"CR",
    "gn:admin2_code":"1",
    "gn:admin3_code":"24.0",
    "gn:admin4_code":"240022.0",
    "gn:asciiname":"Kaphalbot",
    "gn:country_code":"NP",
    "gn:dem":1522,
    "gn:feature_class":"P",
    "gn:feature_code":"PPLL",
    "gn:name":"Kaphalbot",
    "gn:population":0,
    "gn:timezone":"Asia/Kathmandu",
    "iso:country":"NP",
    "wof:name":"Kaphalbot",
    "wof:placetype":"locality"
},
  "geometry": {"coordinates":[85.55789,27.68386],"type":"Point"}
}