{
  "type": "Feature",
  "properties": {
    "gn:admin1_code":"CR",
    "gn:admin2_code":"1",
    "gn:admin3_code":"25",
    "gn:admin4_code":"250026",
    "gn:asciiname":"Wakhat",
    "gn:country_code":"NP",
    "gn:dem":1291,
    "gn:feature_class":"P",
    "gn:feature_code":"PPLL",
    "gn:name":"Wakhat",
    "gn:population":0,
    "gn:timezone":"Asia/Kathmandu",
    "iso:country":"NP",
    "wof:name":"Wakhat",
    "wof:placetype":"locality"
},
  "geometry": {"coordinates":[85.29640000000001,27.63853],"type":"Point"}
}