{
  "type": "Feature",
  "properties": {
    "gn:admin1_code":"ER",
    "gn:admin2_code":"10.0",
    "gn:admin3_code":"1.0",
    "gn:admin4_code":"10036.0",
    "gn:asciiname":"Hangjamma",
    "gn:country_code":"NP",
    "gn:dem":1304,
    "gn:feature_class":"P",
    "gn:feature_code":"PPLL",
    "gn:name":"Hangjamma",
    "gn:population":0,
    "gn:timezone":"Asia/Kathmandu",
    "iso:country":"NP",
    "wof:name":"Hangjamma",
    "wof:placetype":"locality"
},
  "geometry": {"coordinates":[87.6028,27.38507],"type":"Point"}
}