{
  "type": "Feature",
  "properties": {
    "gn:admin1_code":"ER",
    "gn:admin2_code":"7",
    "gn:admin3_code":"5",
    "gn:admin4_code":"50043",
    "gn:asciiname":"Chandranagar",
    "gn:country_code":"NP",
    "gn:dem":137,
    "gn:feature_class":"P",
    "gn:feature_code":"PPLL",
    "gn:name":"Chandranagar",
    "gn:population":0,
    "gn:timezone":"Asia/Kathmandu",
    "iso:country":"NP",
    "wof:name":"Chandranagar",
    "wof:placetype":"locality"
},
  "geometry": {"coordinates":[87.35963000000002,26.66762],"type":"Point"}
}