{
  "type": "Feature",
  "properties": {
    "gn:admin1_code":"FR",
    "gn:admin2_code":"14",
    "gn:admin3_code":"68",
    "gn:admin4_code":"680039",
    "gn:asciiname":"Chaudam",
    "gn:country_code":"NP",
    "gn:dem":1042,
    "gn:feature_class":"P",
    "gn:feature_code":"PPLL",
    "gn:name":"Chaudam",
    "gn:population":0,
    "gn:timezone":"Asia/Kathmandu",
    "iso:country":"NP",
    "wof:name":"Chaudam",
    "wof:placetype":"locality"
},
  "geometry": {"coordinates":[80.92095999999999,29.46577000000001],"type":"Point"}
}