{
  "type": "Feature",
  "properties": {
    "gn:admin1_code":"ER",
    "gn:admin2_code":"13",
    "gn:admin3_code":"13.0",
    "gn:admin4_code":"130001.0",
    "gn:asciiname":"Ainselukharka",
    "gn:country_code":"NP",
    "gn:dem":2215,
    "gn:feature_class":"P",
    "gn:feature_code":"PPLL",
    "gn:name":"Ainselukharka",
    "gn:population":0,
    "gn:timezone":"Asia/Kathmandu",
    "iso:country":"NP",
    "wof:name":"Ainselukharka",
    "wof:placetype":"locality"
},
  "geometry": {"coordinates":[86.75299999999999,27.367],"type":"Point"}
}