{
  "type": "Feature",
  "properties": {
    "gn:admin1_code":"CR",
    "gn:admin2_code":"1",
    "gn:admin3_code":"30.0",
    "gn:admin4_code":"300024.0",
    "gn:asciiname":"Chhaghare",
    "gn:country_code":"NP",
    "gn:dem":829,
    "gn:feature_class":"P",
    "gn:feature_code":"PPLL",
    "gn:name":"Chhaghare",
    "gn:population":0,
    "gn:timezone":"Asia/Kathmandu",
    "iso:country":"NP",
    "wof:name":"Chhaghare",
    "wof:placetype":"locality"
},
  "geometry": {"coordinates":[84.78084,27.93082],"type":"Point"}
}