{
  "type": "Feature",
  "properties": {
    "gn:admin1_code":"WR",
    "gn:admin2_code":"4.0",
    "gn:admin3_code":"38.0",
    "gn:admin4_code":"380029.0",
    "gn:asciiname":"Manudanda",
    "gn:country_code":"NP",
    "gn:dem":1067,
    "gn:feature_class":"P",
    "gn:feature_code":"PPLL",
    "gn:name":"Manudanda",
    "gn:population":0,
    "gn:timezone":"Asia/Kathmandu",
    "iso:country":"NP",
    "wof:name":"Manudanda",
    "wof:placetype":"locality"
},
  "geometry": {"coordinates":[84.3506,27.77475],"type":"Point"}
}