{
  "type": "Feature",
  "properties": {
    "gn:admin1_code":"FR",
    "gn:admin2_code":"14",
    "gn:admin3_code":"70.0",
    "gn:admin4_code":"700003.0",
    "gn:asciiname":"Tari",
    "gn:country_code":"NP",
    "gn:dem":853,
    "gn:feature_class":"P",
    "gn:feature_code":"PPLL",
    "gn:name":"Tari",
    "gn:population":0,
    "gn:timezone":"Asia/Kathmandu",
    "iso:country":"NP",
    "name:ceb_x_preferred":[
        "Tari"
    ],
    "name:deu_x_preferred":[
        "Tari"
    ],
    "name:fra_x_preferred":[
        "Tari"
    ],
    "name:ita_x_preferred":[
        "Tari"
    ],
    "name:nds_x_preferred":[
        "Tari"
    ],
    "name:rus_x_preferred":[
        "\u0422\u0430\u0440\u0438"
    ],
    "name:swe_x_preferred":[
        "Tari"
    ],
    "wof:name":"Tari",
    "wof:placetype":"locality"
},
  "geometry": {"coordinates":[80.89577,28.97202],"type":"Point"}
}