{
  "type": "Feature",
  "properties": {
    "gn:admin1_code":"WR",
    "gn:admin2_code":"4",
    "gn:admin3_code":"36.0",
    "gn:admin4_code":"360039.0",
    "gn:asciiname":"Rani Peak (Lidanai Peak)",
    "gn:country_code":"NP",
    "gn:dem":6407,
    "gn:feature_class":"P",
    "gn:feature_code":"PPLL",
    "gn:name":"Rani Peak (Lidanai Peak)",
    "gn:population":0,
    "gn:timezone":"Asia/Kathmandu",
    "iso:country":"NP",
    "wof:name":"Rani Peak (Lidanai Peak)",
    "wof:placetype":"locality"
},
  "geometry": {"coordinates":[84.6896,28.46624000000001],"type":"Point"}
}