{
  "type": "Feature",
  "properties": {
    "gn:admin1_code":"CR",
    "gn:admin2_code":"1",
    "gn:admin3_code":"28",
    "gn:admin4_code":"280044",
    "gn:asciiname":"Barhabise",
    "gn:country_code":"NP",
    "gn:dem":816,
    "gn:feature_class":"P",
    "gn:feature_code":"PPLL",
    "gn:name":"Barhabise",
    "gn:population":0,
    "gn:timezone":"Asia/Kathmandu",
    "iso:country":"NP",
    "name:pol_x_preferred":[
        "Barhabise"
    ],
    "wof:name":"Barhabise",
    "wof:placetype":"locality"
},
  "geometry": {"coordinates":[85.34031999999998,27.92507],"type":"Point"}
}