{
  "type": "Feature",
  "properties": {
    "gn:admin1_code":"MR",
    "gn:admin2_code":"2.0",
    "gn:admin3_code":"59.0",
    "gn:admin4_code":"590046.0",
    "gn:asciiname":"Tallo  Kanda",
    "gn:country_code":"NP",
    "gn:dem":1170,
    "gn:feature_class":"P",
    "gn:feature_code":"PPLL",
    "gn:name":"Tallo  Kanda",
    "gn:population":0,
    "gn:timezone":"Asia/Kathmandu",
    "iso:country":"NP",
    "wof:name":"Tallo Kanda",
    "wof:placetype":"locality"
},
  "geometry": {"coordinates":[81.91763,28.39517],"type":"Point"}
}