{
  "type": "Feature",
  "properties": {
    "gn:admin1_code":"WR",
    "gn:admin2_code":"4.0",
    "gn:admin3_code":"39.0",
    "gn:admin4_code":"390062.0",
    "gn:asciiname":"Jyamire",
    "gn:country_code":"NP",
    "gn:dem":1092,
    "gn:feature_class":"P",
    "gn:feature_code":"PPLL",
    "gn:name":"Jyamire",
    "gn:population":0,
    "gn:timezone":"Asia/Kathmandu",
    "iso:country":"NP",
    "name:fra_x_preferred":[
        "Jyamire"
    ],
    "name:new_x_preferred":[
        "\u091c\u094d\u092f\u093e\u092e\u093f\u0930\u0947"
    ],
    "name:pol_x_preferred":[
        "Jyamire"
    ],
    "wof:name":"Jyamire",
    "wof:placetype":"locality"
},
  "geometry": {"coordinates":[83.83538,27.99166],"type":"Point"}
}