{
  "type": "Feature",
  "properties": {
    "gn:admin1_code":"WR",
    "gn:admin2_code":"3",
    "gn:admin3_code":"44",
    "gn:admin4_code":"440046.0",
    "gn:asciiname":"Darsu",
    "gn:country_code":"NP",
    "gn:dem":989,
    "gn:feature_class":"P",
    "gn:feature_code":"PPLL",
    "gn:name":"Darsu",
    "gn:population":0,
    "gn:timezone":"Asia/Kathmandu",
    "iso:country":"NP",
    "wof:name":"Darsu",
    "wof:placetype":"locality"
},
  "geometry": {"coordinates":[83.68595999999999,28.05251],"type":"Point"}
}