{
  "type": "Feature",
  "properties": {
    "gn:admin1_code":"ER",
    "gn:admin2_code":"7.0",
    "gn:admin3_code":"6.0",
    "gn:admin4_code":"60025.0",
    "gn:asciiname":"Haripur",
    "gn:country_code":"NP",
    "gn:dem":84,
    "gn:feature_class":"P",
    "gn:feature_code":"PPLL",
    "gn:name":"Haripur",
    "gn:population":0,
    "gn:timezone":"Asia/Kathmandu",
    "iso:country":"NP",
    "wof:name":"Haripur",
    "wof:placetype":"locality"
},
  "geometry": {"coordinates":[86.99618000000002,26.55406],"type":"Point"}
}