{
  "type": "Feature",
  "properties": {
    "gn:admin1_code":"ER",
    "gn:admin2_code":"13",
    "gn:admin3_code":"16",
    "gn:admin4_code":"160022",
    "gn:asciiname":"Nimdanda",
    "gn:country_code":"NP",
    "gn:dem":198,
    "gn:feature_class":"P",
    "gn:feature_code":"PPLL",
    "gn:name":"Nimdanda",
    "gn:population":0,
    "gn:timezone":"Asia/Kathmandu",
    "iso:country":"NP",
    "wof:name":"Nimdanda",
    "wof:placetype":"locality"
},
  "geometry": {"coordinates":[86.44444,26.80765],"type":"Point"}
}