{
  "type": "Feature",
  "properties": {
    "gn:admin1_code":"CR",
    "gn:admin2_code":"1",
    "gn:admin3_code":"25",
    "gn:admin4_code":"250017.0",
    "gn:asciiname":"Baluwadanda",
    "gn:country_code":"NP",
    "gn:dem":1531,
    "gn:feature_class":"P",
    "gn:feature_code":"PPLL",
    "gn:name":"Baluwadanda",
    "gn:population":0,
    "gn:timezone":"Asia/Kathmandu",
    "iso:country":"NP",
    "wof:name":"Baluwadanda",
    "wof:placetype":"locality"
},
  "geometry": {"coordinates":[85.36754000000001,27.4488],"type":"Point"}
}