{
  "type": "Feature",
  "properties": {
    "gn:admin1_code":"ER",
    "gn:admin2_code":"7.0",
    "gn:admin3_code":"6.0",
    "gn:admin4_code":"60030.0",
    "gn:asciiname":"Simarbona Uttartol",
    "gn:country_code":"NP",
    "gn:dem":100,
    "gn:feature_class":"P",
    "gn:feature_code":"PPLL",
    "gn:name":"Simarbona Uttartol",
    "gn:population":0,
    "gn:timezone":"Asia/Kathmandu",
    "iso:country":"NP",
    "wof:name":"Simarbona Uttartol",
    "wof:placetype":"locality"
},
  "geometry": {"coordinates":[87.29715,26.62181],"type":"Point"}
}