{
  "type": "Feature",
  "properties": {
    "gn:admin1_code":"FR",
    "gn:admin2_code":"9",
    "gn:admin3_code":"74",
    "gn:admin4_code":"740050",
    "gn:asciiname":"Tunigado",
    "gn:country_code":"NP",
    "gn:dem":763,
    "gn:feature_class":"P",
    "gn:feature_code":"PPLL",
    "gn:name":"Tunigado",
    "gn:population":0,
    "gn:timezone":"Asia/Kathmandu",
    "iso:country":"NP",
    "wof:name":"Tunigado",
    "wof:placetype":"locality"
},
  "geometry": {"coordinates":[80.34784999999999,29.3438],"type":"Point"}
}