{
  "type": "Feature",
  "properties": {
    "gn:admin1_code":"WR",
    "gn:admin2_code":"8",
    "gn:admin3_code":"47",
    "gn:admin4_code":"470066",
    "gn:asciiname":"Yamgha",
    "gn:country_code":"NP",
    "gn:dem":915,
    "gn:feature_class":"P",
    "gn:feature_code":"PPLL",
    "gn:name":"Yamgha",
    "gn:population":0,
    "gn:timezone":"Asia/Kathmandu",
    "iso:country":"NP",
    "wof:name":"Yamgha",
    "wof:placetype":"locality"
},
  "geometry": {"coordinates":[83.58013000000003,27.91394],"type":"Point"}
}