{
  "type": "Feature",
  "properties": {
    "gn:admin1_code":"WR",
    "gn:admin2_code":"4",
    "gn:admin3_code":"37",
    "gn:admin4_code":"370055",
    "gn:asciiname":"Bahare Dihi",
    "gn:country_code":"NP",
    "gn:dem":455,
    "gn:feature_class":"P",
    "gn:feature_code":"PPLL",
    "gn:name":"Bahare Dihi",
    "gn:population":0,
    "gn:timezone":"Asia/Kathmandu",
    "iso:country":"NP",
    "wof:name":"Bahare Dihi",
    "wof:placetype":"locality"
},
  "geometry": {"coordinates":[84.2705,28.0971],"type":"Point"}
}