{
  "type": "Feature",
  "properties": {
    "gn:admin1_code":"ER",
    "gn:admin2_code":"13.0",
    "gn:admin3_code":"14.0",
    "gn:admin4_code":"140009.0",
    "gn:asciiname":"Banthuwa",
    "gn:country_code":"NP",
    "gn:dem":679,
    "gn:feature_class":"P",
    "gn:feature_code":"PPLL",
    "gn:name":"Banthuwa",
    "gn:population":0,
    "gn:timezone":"Asia/Kathmandu",
    "iso:country":"NP",
    "wof:name":"Banthuwa",
    "wof:placetype":"locality"
},
  "geometry": {"coordinates":[86.97093000000002,26.8746],"type":"Point"}
}