{
  "type": "Feature",
  "properties": {
    "gn:admin1_code":"ER",
    "gn:admin2_code":"10",
    "gn:admin3_code":"4.0",
    "gn:admin4_code":"40039.0",
    "gn:asciiname":"Nayanbasti",
    "gn:country_code":"NP",
    "gn:dem":67,
    "gn:feature_class":"P",
    "gn:feature_code":"PPLL",
    "gn:name":"Nayanbasti",
    "gn:population":0,
    "gn:timezone":"Asia/Kathmandu",
    "iso:country":"NP",
    "wof:name":"Nayanbasti",
    "wof:placetype":"locality"
},
  "geometry": {"coordinates":[88.05351999999998,26.4098],"type":"Point"}
}