{
  "type": "Feature",
  "properties": {
    "gn:admin1_code":"ER",
    "gn:admin2_code":"13",
    "gn:admin3_code":"13.0",
    "gn:admin4_code":"130021.0",
    "gn:asciiname":"Khutumbu",
    "gn:country_code":"NP",
    "gn:dem":1093,
    "gn:feature_class":"P",
    "gn:feature_code":"PPLL",
    "gn:name":"Khutumbu",
    "gn:population":0,
    "gn:timezone":"Asia/Kathmandu",
    "iso:country":"NP",
    "wof:name":"Khutumbu",
    "wof:placetype":"locality"
},
  "geometry": {"coordinates":[86.76813,27.11139],"type":"Point"}
}