{
  "type": "Feature",
  "properties": {
    "gn:admin1_code":"FR",
    "gn:admin2_code":"14",
    "gn:admin3_code":"69.0",
    "gn:admin4_code":"690075.0",
    "gn:asciiname":"Sarpadanda",
    "gn:country_code":"NP",
    "gn:dem":1205,
    "gn:feature_class":"P",
    "gn:feature_code":"PPLL",
    "gn:name":"Sarpadanda",
    "gn:population":0,
    "gn:timezone":"Asia/Kathmandu",
    "iso:country":"NP",
    "wof:name":"Sarpadanda",
    "wof:placetype":"locality"
},
  "geometry": {"coordinates":[81.45777,29.1075],"type":"Point"}
}