{
  "type": "Feature",
  "properties": {
    "gn:admin1_code":"MR",
    "gn:admin2_code":"12",
    "gn:admin3_code":"52",
    "gn:admin4_code":"520020",
    "gn:asciiname":"Dandathar",
    "gn:country_code":"NP",
    "gn:dem":896,
    "gn:feature_class":"P",
    "gn:feature_code":"PPLL",
    "gn:name":"Dandathar",
    "gn:population":0,
    "gn:timezone":"Asia/Kathmandu",
    "iso:country":"NP",
    "wof:name":"Dandathar",
    "wof:placetype":"locality"
},
  "geometry": {"coordinates":[82.72063,28.10024],"type":"Point"}
}