{
  "type": "Feature",
  "properties": {
    "gn:admin1_code":"FR",
    "gn:admin2_code":"9",
    "gn:admin3_code":"72.0",
    "gn:admin4_code":"720008.0",
    "gn:asciiname":"Puraina (Shivabasti)",
    "gn:country_code":"NP",
    "gn:dem":182,
    "gn:feature_class":"P",
    "gn:feature_code":"PPLL",
    "gn:name":"Puraina (Shivabasti)",
    "gn:population":0,
    "gn:timezone":"Asia/Kathmandu",
    "iso:country":"NP",
    "wof:name":"Puraina (Shivabasti)",
    "wof:placetype":"locality"
},
  "geometry": {"coordinates":[80.42152,28.69212000000001],"type":"Point"}
}