{
  "type": "Feature",
  "properties": {
    "gn:admin1_code":"ER",
    "gn:admin2_code":"10",
    "gn:admin3_code":"4.0",
    "gn:admin4_code":"40010.0",
    "gn:asciiname":"Bisubari",
    "gn:country_code":"NP",
    "gn:dem":101,
    "gn:feature_class":"P",
    "gn:feature_code":"PPLL",
    "gn:name":"Bisubari",
    "gn:population":0,
    "gn:timezone":"Asia/Kathmandu",
    "iso:country":"NP",
    "wof:name":"Bisubari",
    "wof:placetype":"locality"
},
  "geometry": {"coordinates":[88.05747,26.57639],"type":"Point"}
}