{
  "type": "Feature",
  "properties": {
    "gn:admin1_code":"FR",
    "gn:admin2_code":"14",
    "gn:admin3_code":"70.0",
    "gn:admin4_code":"700046.0",
    "gn:asciiname":"Jaula Amkhet",
    "gn:country_code":"NP",
    "gn:dem":995,
    "gn:feature_class":"P",
    "gn:feature_code":"PPLL",
    "gn:name":"Jaula Amkhet",
    "gn:population":0,
    "gn:timezone":"Asia/Kathmandu",
    "iso:country":"NP",
    "wof:name":"Jaula Amkhet",
    "wof:placetype":"locality"
},
  "geometry": {"coordinates":[81.02133000000001,28.99726],"type":"Point"}
}