{
  "type": "Feature",
  "properties": {
    "gn:admin1_code":"FR",
    "gn:admin2_code":"14",
    "gn:admin3_code":"70.0",
    "gn:admin4_code":"700027.0",
    "gn:asciiname":"Borbada",
    "gn:country_code":"NP",
    "gn:dem":1198,
    "gn:feature_class":"P",
    "gn:feature_code":"PPLL",
    "gn:name":"Borbada",
    "gn:population":0,
    "gn:timezone":"Asia/Kathmandu",
    "iso:country":"NP",
    "wof:name":"Borbada",
    "wof:placetype":"locality"
},
  "geometry": {"coordinates":[81.04461999999999,29.03944000000001],"type":"Point"}
}