{
  "type": "Feature",
  "properties": {
    "gn:admin1_code":"CR",
    "gn:admin2_code":"1",
    "gn:admin3_code":"24.0",
    "gn:admin4_code":"240054.0",
    "gn:asciiname":"Bhanjyang Kharka",
    "gn:country_code":"NP",
    "gn:dem":1575,
    "gn:feature_class":"P",
    "gn:feature_code":"PPLL",
    "gn:name":"Bhanjyang Kharka",
    "gn:population":0,
    "gn:timezone":"Asia/Kathmandu",
    "iso:country":"NP",
    "wof:name":"Bhanjyang Kharka",
    "wof:placetype":"locality"
},
  "geometry": {"coordinates":[85.5628,27.53758],"type":"Point"}
}