{
  "type": "Feature",
  "properties": {
    "gn:admin1_code":"WR",
    "gn:admin2_code":"4.0",
    "gn:admin3_code":"38.0",
    "gn:admin4_code":"380028.0",
    "gn:asciiname":"Kudadi",
    "gn:country_code":"NP",
    "gn:dem":825,
    "gn:feature_class":"P",
    "gn:feature_code":"PPLL",
    "gn:name":"Kudadi",
    "gn:population":0,
    "gn:timezone":"Asia/Kathmandu",
    "iso:country":"NP",
    "wof:name":"Kudadi",
    "wof:placetype":"locality"
},
  "geometry": {"coordinates":[83.98226,27.93352],"type":"Point"}
}