{
  "type": "Feature",
  "properties": {
    "gn:admin1_code":"ER",
    "gn:admin2_code":"10",
    "gn:admin3_code":"3.0",
    "gn:admin4_code":"30030.0",
    "gn:asciiname":"Lapsibote",
    "gn:country_code":"NP",
    "gn:dem":1539,
    "gn:feature_class":"P",
    "gn:feature_code":"PPLL",
    "gn:name":"Lapsibote",
    "gn:population":0,
    "gn:timezone":"Asia/Kathmandu",
    "iso:country":"NP",
    "wof:name":"Lapsibote",
    "wof:placetype":"locality"
},
  "geometry": {"coordinates":[88.0425,26.94493],"type":"Point"}
}