{
  "type": "Feature",
  "properties": {
    "gn:admin1_code":"CR",
    "gn:admin2_code":"11",
    "gn:admin3_code":"31",
    "gn:admin4_code":"310032",
    "gn:asciiname":"Ukhubari",
    "gn:country_code":"NP",
    "gn:dem":986,
    "gn:feature_class":"P",
    "gn:feature_code":"PPLL",
    "gn:name":"Ukhubari",
    "gn:population":0,
    "gn:timezone":"Asia/Kathmandu",
    "iso:country":"NP",
    "wof:name":"Ukhubari",
    "wof:placetype":"locality"
},
  "geometry": {"coordinates":[85.02795,27.55658],"type":"Point"}
}