{
  "type": "Feature",
  "properties": {
    "gn:admin1_code":"ER",
    "gn:admin2_code":"7.0",
    "gn:admin3_code":"6.0",
    "gn:admin4_code":"60050.0",
    "gn:asciiname":"Bengari",
    "gn:country_code":"NP",
    "gn:dem":94,
    "gn:feature_class":"P",
    "gn:feature_code":"PPLL",
    "gn:name":"Bengari",
    "gn:population":0,
    "gn:timezone":"Asia/Kathmandu",
    "iso:country":"NP",
    "wof:name":"Bengari",
    "wof:placetype":"locality"
},
  "geometry": {"coordinates":[87.27037,26.58951],"type":"Point"}
}