{
  "type": "Feature",
  "properties": {
    "gn:admin1_code":"CR",
    "gn:admin2_code":"5",
    "gn:admin3_code":"20",
    "gn:admin4_code":"200035",
    "gn:asciiname":"Bhutare",
    "gn:country_code":"NP",
    "gn:dem":193,
    "gn:feature_class":"P",
    "gn:feature_code":"PPLL",
    "gn:name":"Bhutare",
    "gn:population":0,
    "gn:timezone":"Asia/Kathmandu",
    "iso:country":"NP",
    "wof:name":"Bhutare",
    "wof:placetype":"locality"
},
  "geometry": {"coordinates":[85.51730999999999,27.24288],"type":"Point"}
}