{
  "type": "Feature",
  "properties": {
    "gn:admin1_code":"FR",
    "gn:admin2_code":"9",
    "gn:admin3_code":"72.0",
    "gn:admin4_code":"720004.0",
    "gn:asciiname":"Hattithala",
    "gn:country_code":"NP",
    "gn:dem":228,
    "gn:feature_class":"P",
    "gn:feature_code":"PPLL",
    "gn:name":"Hattithala",
    "gn:population":0,
    "gn:timezone":"Asia/Kathmandu",
    "iso:country":"NP",
    "wof:name":"Hattithala",
    "wof:placetype":"locality"
},
  "geometry": {"coordinates":[80.3103,28.96578],"type":"Point"}
}