{
  "type": "Feature",
  "properties": {
    "gn:admin1_code":"MR",
    "gn:admin2_code":"2.0",
    "gn:admin3_code":"59.0",
    "gn:admin4_code":"590034.0",
    "gn:asciiname":"Khallugaira",
    "gn:country_code":"NP",
    "gn:dem":768,
    "gn:feature_class":"P",
    "gn:feature_code":"PPLL",
    "gn:name":"Khallugaira",
    "gn:population":0,
    "gn:timezone":"Asia/Kathmandu",
    "iso:country":"NP",
    "wof:name":"Khallugaira",
    "wof:placetype":"locality"
},
  "geometry": {"coordinates":[81.78891999999998,28.40032],"type":"Point"}
}