{
  "type": "Feature",
  "properties": {
    "gn:admin1_code":"WR",
    "gn:admin2_code":"4.0",
    "gn:admin3_code":"39.0",
    "gn:admin4_code":"390016.0",
    "gn:asciiname":"Bahundi",
    "gn:country_code":"NP",
    "gn:dem":1049,
    "gn:feature_class":"P",
    "gn:feature_code":"PPLL",
    "gn:name":"Bahundi",
    "gn:population":0,
    "gn:timezone":"Asia/Kathmandu",
    "iso:country":"NP",
    "wof:name":"Bahundi",
    "wof:placetype":"locality"
},
  "geometry": {"coordinates":[83.91755000000001,27.94703],"type":"Point"}
}