{
  "type": "Feature",
  "properties": {
    "gn:admin1_code":"CR",
    "gn:admin2_code":"5",
    "gn:admin3_code":"22.0",
    "gn:admin4_code":"220004.0",
    "gn:asciiname":"Jilu",
    "gn:country_code":"NP",
    "gn:dem":1397,
    "gn:feature_class":"P",
    "gn:feature_code":"PPLL",
    "gn:name":"Jilu",
    "gn:population":0,
    "gn:timezone":"Asia/Kathmandu",
    "iso:country":"NP",
    "name:fas_x_preferred":[
        "\u062c\u0644\u0648"
    ],
    "wof:name":"Jilu",
    "wof:placetype":"locality"
},
  "geometry": {"coordinates":[86.07093,27.65292],"type":"Point"}
}