{
  "type": "Feature",
  "properties": {
    "gn:admin1_code":"ER",
    "gn:admin2_code":"13.0",
    "gn:admin3_code":"14.0",
    "gn:admin4_code":"140011.0",
    "gn:asciiname":"Bakainiya",
    "gn:country_code":"NP",
    "gn:dem":126,
    "gn:feature_class":"P",
    "gn:feature_code":"PPLL",
    "gn:name":"Bakainiya",
    "gn:population":0,
    "gn:timezone":"Asia/Kathmandu",
    "iso:country":"NP",
    "wof:name":"Bakainiya",
    "wof:placetype":"locality"
},
  "geometry": {"coordinates":[86.82393,26.78261],"type":"Point"}
}