{
  "type": "Feature",
  "properties": {
    "gn:admin1_code":"MR",
    "gn:admin2_code":"12",
    "gn:admin3_code":"55",
    "gn:admin4_code":"550042",
    "gn:asciiname":"Baragaun",
    "gn:country_code":"NP",
    "gn:dem":1287,
    "gn:feature_class":"P",
    "gn:feature_code":"PPLL",
    "gn:name":"Baragaun",
    "gn:population":0,
    "gn:timezone":"Asia/Kathmandu",
    "iso:country":"NP",
    "wof:name":"Baragaun",
    "wof:placetype":"locality"
},
  "geometry": {"coordinates":[82.21949000000002,28.4561],"type":"Point"}
}