{
  "type": "Feature",
  "properties": {
    "gn:admin1_code":"FR",
    "gn:admin2_code":"14",
    "gn:admin3_code":"68",
    "gn:admin4_code":"680002",
    "gn:asciiname":"Suganaulo",
    "gn:country_code":"NP",
    "gn:dem":1827,
    "gn:feature_class":"P",
    "gn:feature_code":"PPLL",
    "gn:name":"Suganaulo",
    "gn:population":0,
    "gn:timezone":"Asia/Kathmandu",
    "iso:country":"NP",
    "wof:name":"Suganaulo",
    "wof:placetype":"locality"
},
  "geometry": {"coordinates":[80.95905999999999,29.51689],"type":"Point"}
}