{
  "type": "Feature",
  "properties": {
    "gn:admin1_code":"CR",
    "gn:admin2_code":"1",
    "gn:admin3_code":"25",
    "gn:admin4_code":"250001",
    "gn:asciiname":"Syauri",
    "gn:country_code":"NP",
    "gn:dem":1082,
    "gn:feature_class":"P",
    "gn:feature_code":"PPLL",
    "gn:name":"Syauri",
    "gn:population":0,
    "gn:timezone":"Asia/Kathmandu",
    "iso:country":"NP",
    "wof:name":"Syauri",
    "wof:placetype":"locality"
},
  "geometry": {"coordinates":[85.33623,27.45486],"type":"Point"}
}