{
  "type": "Feature",
  "properties": {
    "gn:admin1_code":"ER",
    "gn:admin2_code":"13",
    "gn:admin3_code":"13.0",
    "gn:admin4_code":"130019.0",
    "gn:asciiname":"Bakhapu",
    "gn:country_code":"NP",
    "gn:dem":1283,
    "gn:feature_class":"P",
    "gn:feature_code":"PPLL",
    "gn:name":"Bakhapu",
    "gn:population":0,
    "gn:timezone":"Asia/Kathmandu",
    "iso:country":"NP",
    "wof:name":"Bakhapu",
    "wof:placetype":"locality"
},
  "geometry": {"coordinates":[86.52668,27.16533],"type":"Point"}
}