{
  "type": "Feature",
  "properties": {
    "gn:admin1_code":"CR",
    "gn:admin2_code":"5",
    "gn:admin3_code":"22.0",
    "gn:admin4_code":"220037.0",
    "gn:asciiname":"Yelung",
    "gn:country_code":"NP",
    "gn:dem":2153,
    "gn:feature_class":"P",
    "gn:feature_code":"PPLL",
    "gn:name":"Yelung",
    "gn:population":0,
    "gn:timezone":"Asia/Kathmandu",
    "iso:country":"NP",
    "wof:name":"Yelung",
    "wof:placetype":"locality"
},
  "geometry": {"coordinates":[86.26246,27.64075],"type":"Point"}
}