{
  "type": "Feature",
  "properties": {
    "gn:admin1_code":"WR",
    "gn:admin2_code":"3",
    "gn:admin3_code":"45.0",
    "gn:admin4_code":"450048.0",
    "gn:asciiname":"Bhagar",
    "gn:country_code":"NP",
    "gn:dem":1258,
    "gn:feature_class":"P",
    "gn:feature_code":"PPLL",
    "gn:name":"Bhagar",
    "gn:population":0,
    "gn:timezone":"Asia/Kathmandu",
    "iso:country":"NP",
    "wof:name":"Bhagar",
    "wof:placetype":"locality"
},
  "geometry": {"coordinates":[83.57593,28.20705],"type":"Point"}
}