{
  "type": "Feature",
  "properties": {
    "gn:admin1_code":"FR",
    "gn:admin2_code":"14",
    "gn:admin3_code":"69.0",
    "gn:admin4_code":"690022.0",
    "gn:asciiname":"Pitargada",
    "gn:country_code":"NP",
    "gn:dem":1903,
    "gn:feature_class":"P",
    "gn:feature_code":"PPLL",
    "gn:name":"Pitargada",
    "gn:population":0,
    "gn:timezone":"Asia/Kathmandu",
    "iso:country":"NP",
    "wof:name":"Pitargada",
    "wof:placetype":"locality"
},
  "geometry": {"coordinates":[81.33856999999998,29.04951],"type":"Point"}
}