{
  "type": "Feature",
  "properties": {
    "gn:admin1_code":"MR",
    "gn:admin2_code":"2.0",
    "gn:admin3_code":"59.0",
    "gn:admin4_code":"590041.0",
    "gn:asciiname":"Kotilagaun",
    "gn:country_code":"NP",
    "gn:dem":1188,
    "gn:feature_class":"P",
    "gn:feature_code":"PPLL",
    "gn:name":"Kotilagaun",
    "gn:population":0,
    "gn:timezone":"Asia/Kathmandu",
    "iso:country":"NP",
    "wof:name":"Kotilagaun",
    "wof:placetype":"locality"
},
  "geometry": {"coordinates":[81.82245,28.61843],"type":"Point"}
}