{
  "type": "Feature",
  "properties": {
    "gn:admin1_code":"WR",
    "gn:admin2_code":"4.0",
    "gn:admin3_code":"38.0",
    "gn:admin4_code":"380038.0",
    "gn:asciiname":"Gurunggaun",
    "gn:country_code":"NP",
    "gn:dem":924,
    "gn:feature_class":"P",
    "gn:feature_code":"PPLL",
    "gn:name":"Gurunggaun",
    "gn:population":0,
    "gn:timezone":"Asia/Kathmandu",
    "iso:country":"NP",
    "wof:name":"Gurunggaun",
    "wof:placetype":"locality"
},
  "geometry": {"coordinates":[84.14834999999999,27.94716],"type":"Point"}
}