{
  "type": "Feature",
  "properties": {
    "gn:admin1_code":"MR",
    "gn:admin2_code":"12",
    "gn:admin3_code":"55",
    "gn:admin4_code":"550011",
    "gn:asciiname":"Basneura",
    "gn:country_code":"NP",
    "gn:dem":878,
    "gn:feature_class":"P",
    "gn:feature_code":"PPLL",
    "gn:name":"Basneura",
    "gn:population":0,
    "gn:timezone":"Asia/Kathmandu",
    "iso:country":"NP",
    "wof:name":"Basneura",
    "wof:placetype":"locality"
},
  "geometry": {"coordinates":[82.0386,28.50061],"type":"Point"}
}