{
  "type": "Feature",
  "properties": {
    "gn:admin1_code":"WR",
    "gn:admin2_code":"4.0",
    "gn:admin3_code":"38.0",
    "gn:admin4_code":"380025.0",
    "gn:asciiname":"Thaprek Bhanjyang",
    "gn:country_code":"NP",
    "gn:dem":690,
    "gn:feature_class":"P",
    "gn:feature_code":"PPLL",
    "gn:name":"Thaprek Bhanjyang",
    "gn:population":0,
    "gn:timezone":"Asia/Kathmandu",
    "iso:country":"NP",
    "wof:name":"Thaprek Bhanjyang",
    "wof:placetype":"locality"
},
  "geometry": {"coordinates":[84.23173,27.8854],"type":"Point"}
}