{
  "type": "Feature",
  "properties": {
    "gn:admin1_code":"CR",
    "gn:admin2_code":"11",
    "gn:admin3_code":"35.0",
    "gn:admin4_code":"350005.0",
    "gn:asciiname":"Kathsikri",
    "gn:country_code":"NP",
    "gn:dem":209,
    "gn:feature_class":"P",
    "gn:feature_code":"PPLL",
    "gn:name":"Kathsikri",
    "gn:population":0,
    "gn:timezone":"Asia/Kathmandu",
    "iso:country":"NP",
    "wof:name":"Kathsikri",
    "wof:placetype":"locality"
},
  "geometry": {"coordinates":[84.44473000000001,27.65671],"type":"Point"}
}