{
  "type": "Feature",
  "properties": {
    "gn:admin1_code":"MR",
    "gn:admin2_code":"12",
    "gn:admin3_code":"52",
    "gn:admin4_code":"520018",
    "gn:asciiname":"Dhubang",
    "gn:country_code":"NP",
    "gn:dem":693,
    "gn:feature_class":"P",
    "gn:feature_code":"PPLL",
    "gn:name":"Dhubang",
    "gn:population":0,
    "gn:timezone":"Asia/Kathmandu",
    "iso:country":"NP",
    "name:hin_x_preferred":[
        "\u0927\u0941\u0935\u093e\u0919"
    ],
    "name:mai_x_preferred":[
        "\u0927\u0941\u0935\u093e\u0919"
    ],
    "name:msa_x_preferred":[
        "Dhubang"
    ],
    "name:nep_x_preferred":[
        "\u0927\u0941\u0935\u093e\u0919"
    ],
    "name:new_x_preferred":[
        "\u0927\u0941\u0935\u093e\u0919"
    ],
    "name:pol_x_preferred":[
        "Dhuwang"
    ],
    "wof:name":"Dhubang",
    "wof:placetype":"locality"
},
  "geometry": {"coordinates":[82.85218,28.04032],"type":"Point"}
}