{
  "type": "Feature",
  "properties": {
    "gn:admin1_code":"MR",
    "gn:admin2_code":"6",
    "gn:admin3_code":"62.0",
    "gn:admin4_code":"620013.0",
    "gn:asciiname":"Khadu",
    "gn:country_code":"NP",
    "gn:dem":2115,
    "gn:feature_class":"P",
    "gn:feature_code":"PPLL",
    "gn:name":"Khadu",
    "gn:population":0,
    "gn:timezone":"Asia/Kathmandu",
    "iso:country":"NP",
    "wof:name":"Khadu",
    "wof:placetype":"locality"
},
  "geometry": {"coordinates":[82.53338000000002,29.06528],"type":"Point"}
}