{
  "type": "Feature",
  "properties": {
    "gn:admin1_code":"ER",
    "gn:admin2_code":"7",
    "gn:admin3_code":"10.0",
    "gn:admin4_code":"100007.0",
    "gn:asciiname":"Asine",
    "gn:country_code":"NP",
    "gn:dem":1914,
    "gn:feature_class":"P",
    "gn:feature_code":"PPLL",
    "gn:name":"Asine",
    "gn:population":0,
    "gn:timezone":"Asia/Kathmandu",
    "iso:country":"NP",
    "wof:name":"Asine",
    "wof:placetype":"locality"
},
  "geometry": {"coordinates":[87.09191,27.20689],"type":"Point"}
}