{
  "type": "Feature",
  "properties": {
    "gn:admin1_code":"ER",
    "gn:admin2_code":"7",
    "gn:admin3_code":"10.0",
    "gn:admin4_code":"100007.0",
    "gn:asciiname":"Asine",
    "gn:country_code":"NP",
    "gn:dem":1914,
    "gn:feature_class":"P",
    "gn:feature_code":"PPLL",
    "gn:name":"Asine",
    "gn:population":0,
    "gn:timezone":"Asia/Kathmandu",
    "iso:country":"NP",
    "name:als_x_preferred":[
        "Asine"
    ],
    "name:ara_x_preferred":[
        "\u0623\u0633\u064a\u0646\u064a"
    ],
    "name:cat_x_preferred":[
        "\u00c0sine"
    ],
    "name:deu_x_preferred":[
        "Asine"
    ],
    "name:ell_x_preferred":[
        "\u0391\u03c3\u03af\u03bd\u03b7"
    ],
    "name:fin_x_preferred":[
        "Asine"
    ],
    "name:fra_x_preferred":[
        "Asin\u00e8"
    ],
    "name:ita_x_preferred":[
        "Asine"
    ],
    "name:lat_x_preferred":[
        "Asine"
    ],
    "name:rus_x_preferred":[
        "\u0410\u0441\u0438\u043d\u0430"
    ],
    "name:spa_x_preferred":[
        "\u00c1sine"
    ],
    "name:swe_x_preferred":[
        "Asine"
    ],
    "wof:name":"Asine",
    "wof:placetype":"locality"
},
  "geometry": {"coordinates":[87.09191,27.20689],"type":"Point"}
}