{
  "type": "Feature",
  "properties": {
    "gn:admin1_code":"MR",
    "gn:admin2_code":"12",
    "gn:admin3_code":"53",
    "gn:admin4_code":"530044",
    "gn:asciiname":"Arkhale",
    "gn:country_code":"NP",
    "gn:dem":1852,
    "gn:feature_class":"P",
    "gn:feature_code":"PPLL",
    "gn:name":"Arkhale",
    "gn:population":0,
    "gn:timezone":"Asia/Kathmandu",
    "iso:country":"NP",
    "wof:name":"Arkhale",
    "wof:placetype":"locality"
},
  "geometry": {"coordinates":[82.81004,28.3385],"type":"Point"}
}