{
  "type": "Feature",
  "properties": {
    "gn:admin1_code":"MR",
    "gn:admin2_code":"2",
    "gn:admin3_code":"61.0",
    "gn:admin4_code":"610009.0",
    "gn:asciiname":"Kattigaun",
    "gn:country_code":"NP",
    "gn:dem":1211,
    "gn:feature_class":"P",
    "gn:feature_code":"PPLL",
    "gn:name":"Kattigaun",
    "gn:population":0,
    "gn:timezone":"Asia/Kathmandu",
    "iso:country":"NP",
    "wof:name":"Kattigaun",
    "wof:placetype":"locality"
},
  "geometry": {"coordinates":[82.14654,28.65426],"type":"Point"}
}