{
  "type": "Feature",
  "properties": {
    "gn:admin1_code":"MR",
    "gn:admin2_code":"12",
    "gn:admin3_code":"53",
    "gn:admin4_code":"530031",
    "gn:asciiname":"Karegaun",
    "gn:country_code":"NP",
    "gn:dem":1442,
    "gn:feature_class":"P",
    "gn:feature_code":"PPLL",
    "gn:name":"Karegaun",
    "gn:population":0,
    "gn:timezone":"Asia/Kathmandu",
    "iso:country":"NP",
    "wof:name":"Karegaun",
    "wof:placetype":"locality"
},
  "geometry": {"coordinates":[82.59813,28.29376],"type":"Point"}
}