{
  "type": "Feature",
  "properties": {
    "gn:admin1_code":"WR",
    "gn:admin2_code":"4",
    "gn:admin3_code":"36.0",
    "gn:admin4_code":"360059.0",
    "gn:asciiname":"Dhape",
    "gn:country_code":"NP",
    "gn:dem":1127,
    "gn:feature_class":"P",
    "gn:feature_code":"PPLL",
    "gn:name":"Dhape",
    "gn:population":0,
    "gn:timezone":"Asia/Kathmandu",
    "iso:country":"NP",
    "wof:name":"Dhape",
    "wof:placetype":"locality"
},
  "geometry": {"coordinates":[84.6897,28.09283],"type":"Point"}
}