{
  "type": "Feature",
  "properties": {
    "gn:admin1_code":"CR",
    "gn:admin2_code":"1",
    "gn:admin3_code":"30.0",
    "gn:admin4_code":"300028.0",
    "gn:asciiname":"kattike",
    "gn:country_code":"NP",
    "gn:dem":1212,
    "gn:feature_class":"P",
    "gn:feature_code":"PPLL",
    "gn:name":"kattike",
    "gn:population":0,
    "gn:timezone":"Asia/Kathmandu",
    "iso:country":"NP",
    "wof:name":"kattike",
    "wof:placetype":"locality"
},
  "geometry": {"coordinates":[84.77271999999998,27.7351],"type":"Point"}
}