{
  "type": "Feature",
  "properties": {
    "gn:admin1_code":"WR",
    "gn:admin2_code":"8",
    "gn:admin3_code":"47",
    "gn:admin4_code":"470037",
    "gn:asciiname":"Khaliban",
    "gn:country_code":"NP",
    "gn:dem":913,
    "gn:feature_class":"P",
    "gn:feature_code":"PPLL",
    "gn:name":"Khaliban",
    "gn:population":0,
    "gn:timezone":"Asia/Kathmandu",
    "iso:country":"NP",
    "name:ceb_x_preferred":[
        "Khaliban"
    ],
    "name:msa_x_preferred":[
        "Khaliban"
    ],
    "name:nep_x_preferred":[
        "\u0916\u093e\u0932\u0940\u0935\u0928"
    ],
    "name:new_x_preferred":[
        "\u0916\u093e\u0932\u0940\u092c\u0928"
    ],
    "name:pol_x_preferred":[
        "Khaliban"
    ],
    "wof:name":"Khaliban",
    "wof:placetype":"locality"
},
  "geometry": {"coordinates":[83.84206999999998,27.85524],"type":"Point"}
}