{
  "type": "Feature",
  "properties": {
    "gn:admin1_code":"FR",
    "gn:admin2_code":"14",
    "gn:admin3_code":"68",
    "gn:admin4_code":"680027",
    "gn:asciiname":"Chyakot",
    "gn:country_code":"NP",
    "gn:dem":2340,
    "gn:feature_class":"P",
    "gn:feature_code":"PPLL",
    "gn:name":"Chyakot",
    "gn:population":0,
    "gn:timezone":"Asia/Kathmandu",
    "iso:country":"NP",
    "wof:name":"Chyakot",
    "wof:placetype":"locality"
},
  "geometry": {"coordinates":[81.01203000000002,29.56404],"type":"Point"}
}