{
  "type": "Feature",
  "properties": {
    "gn:admin1_code":"MR",
    "gn:admin2_code":"6",
    "gn:admin3_code":"64.0",
    "gn:admin4_code":"640018.0",
    "gn:asciiname":"Nawaghar Beshi",
    "gn:country_code":"NP",
    "gn:dem":1033,
    "gn:feature_class":"P",
    "gn:feature_code":"PPLL",
    "gn:name":"Nawaghar Beshi",
    "gn:population":0,
    "gn:timezone":"Asia/Kathmandu",
    "iso:country":"NP",
    "wof:name":"Nawaghar Beshi",
    "wof:placetype":"locality"
},
  "geometry": {"coordinates":[81.75104,29.32269],"type":"Point"}
}