{
  "type": "Feature",
  "properties": {
    "gn:admin1_code":"CR",
    "gn:admin2_code":"5",
    "gn:admin3_code":"20",
    "gn:admin4_code":"200009",
    "gn:asciiname":"Dandakateteri",
    "gn:country_code":"NP",
    "gn:dem":600,
    "gn:feature_class":"P",
    "gn:feature_code":"PPLL",
    "gn:name":"Dandakateteri",
    "gn:population":0,
    "gn:timezone":"Asia/Kathmandu",
    "iso:country":"NP",
    "wof:name":"Dandakateteri",
    "wof:placetype":"locality"
},
  "geometry": {"coordinates":[85.98624000000002,27.33311],"type":"Point"}
}