{
  "type": "Feature",
  "properties": {
    "gn:admin1_code":"MR",
    "gn:admin2_code":"12",
    "gn:admin3_code":"55",
    "gn:admin4_code":"550012",
    "gn:asciiname":"Pajakholagaun",
    "gn:country_code":"NP",
    "gn:dem":1450,
    "gn:feature_class":"P",
    "gn:feature_code":"PPLL",
    "gn:name":"Pajakholagaun",
    "gn:population":0,
    "gn:timezone":"Asia/Kathmandu",
    "iso:country":"NP",
    "wof:name":"Pajakholagaun",
    "wof:placetype":"locality"
},
  "geometry": {"coordinates":[82.34425,28.56698],"type":"Point"}
}