{
  "type": "Feature",
  "properties": {
    "gn:admin1_code":"ER",
    "gn:admin2_code":"13",
    "gn:admin3_code":"11",
    "gn:admin4_code":"110020",
    "gn:asciiname":"Phalamkhani",
    "gn:country_code":"NP",
    "gn:dem":2662,
    "gn:feature_class":"P",
    "gn:feature_code":"PPLL",
    "gn:name":"Phalamkhani",
    "gn:population":0,
    "gn:timezone":"Asia/Kathmandu",
    "iso:country":"NP",
    "name:ceb_x_preferred":[
        "Falamkhani"
    ],
    "name:mai_x_preferred":[
        "\u092b\u0932\u093e\u092e\u0916\u093e\u0928\u0940 \u0917\u093e\u0935\u093f\u0938"
    ],
    "name:msa_x_preferred":[
        "Falamkhani"
    ],
    "name:nep_x_preferred":[
        "\u092b\u0932\u093e\u092e\u0916\u093e\u0928\u0940 \u0917\u093e\u0935\u093f\u0938"
    ],
    "name:new_x_preferred":[
        "\u092b\u0932\u093e\u092e\u0916\u093e\u0928\u0940"
    ],
    "name:pol_x_preferred":[
        "Falamkhani"
    ],
    "name:urd_x_preferred":[
        "\u0641\u0627\u0644\u0627\u0645\u062e\u0627\u0646\u06cc"
    ],
    "wof:name":"Phalamkhani",
    "wof:placetype":"locality"
},
  "geometry": {"coordinates":[86.54259,27.53078],"type":"Point"}
}