{
  "type": "Feature",
  "properties": {
    "gn:admin1_code":"CR",
    "gn:admin2_code":"1",
    "gn:admin3_code":"23",
    "gn:admin4_code":"230023",
    "gn:asciiname":"Dhuskun",
    "gn:country_code":"NP",
    "gn:dem":1226,
    "gn:feature_class":"P",
    "gn:feature_code":"PPLL",
    "gn:name":"Dhuskun",
    "gn:population":0,
    "gn:timezone":"Asia/Kathmandu",
    "iso:country":"NP",
    "name:ceb_x_preferred":[
        "Dhuskun"
    ],
    "name:msa_x_preferred":[
        "Ghuskun"
    ],
    "name:nep_x_preferred":[
        "\u0927\u0941\u0938\u094d\u0915\u0941\u0928"
    ],
    "name:new_x_preferred":[
        "\u0918\u0941\u0938\u094d\u0915\u0941\u0928"
    ],
    "name:pol_x_preferred":[
        "Ghuskun"
    ],
    "wof:name":"Dhuskun",
    "wof:placetype":"locality"
},
  "geometry": {"coordinates":[85.90516,27.772],"type":"Point"}
}