{
  "type": "Feature",
  "properties": {
    "gn:admin1_code":"CR",
    "gn:admin2_code":"5",
    "gn:admin3_code":"17.0",
    "gn:admin4_code":"170079.0",
    "gn:asciiname":"Paudeshwar",
    "gn:country_code":"NP",
    "gn:dem":78,
    "gn:feature_class":"P",
    "gn:feature_code":"PPLL",
    "gn:name":"Paudeshwar",
    "gn:population":0,
    "gn:timezone":"Asia/Kathmandu",
    "iso:country":"NP",
    "name:ceb_x_preferred":[
        "Paudeswor"
    ],
    "name:mai_x_preferred":[
        "\u092a\u094c\u0921\u0947\u0936\u094d\u0935\u0930"
    ],
    "name:msa_x_preferred":[
        "Paudeswor"
    ],
    "name:nep_x_preferred":[
        "\u092a\u094c\u0921\u0947\u0936\u094d\u0935\u0930"
    ],
    "name:new_x_preferred":[
        "\u092a\u094c\u0921\u0947\u0936\u094d\u0935\u0930"
    ],
    "name:pol_x_preferred":[
        "Paudeswor"
    ],
    "wof:name":"Paudeshwar",
    "wof:placetype":"locality"
},
  "geometry": {"coordinates":[86.00466,26.72785],"type":"Point"}
}