{
  "type": "Feature",
  "properties": {
    "gn:admin1_code":"ER",
    "gn:admin2_code":"10",
    "gn:admin3_code":"2",
    "gn:admin4_code":"20035",
    "gn:asciiname":"Chande",
    "gn:country_code":"NP",
    "gn:dem":2010,
    "gn:feature_class":"P",
    "gn:feature_code":"PPLL",
    "gn:name":"Chande",
    "gn:population":0,
    "gn:timezone":"Asia/Kathmandu",
    "iso:country":"NP",
    "name:deu_x_preferred":[
        "Chande"
    ],
    "name:spa_x_preferred":[
        "Chande"
    ],
    "name:tel_x_preferred":[
        "\u0c1a\u0c02\u0c26\u0c47(\u0c35\u0c3e\u0c26\u0c4d\u0c2f \u0c2a\u0c30\u0c3f\u0c15\u0c30\u0c02)"
    ],
    "wof:name":"Chande",
    "wof:placetype":"locality"
},
  "geometry": {"coordinates":[87.93221,27.13821],"type":"Point"}
}