{
  "type": "Feature",
  "properties": {
    "gn:admin1_code":"ER",
    "gn:admin2_code":"10",
    "gn:admin3_code":"2",
    "gn:admin4_code":"20035",
    "gn:asciiname":"Chande",
    "gn:country_code":"NP",
    "gn:dem":2010,
    "gn:feature_class":"P",
    "gn:feature_code":"PPLL",
    "gn:name":"Chande",
    "gn:population":0,
    "gn:timezone":"Asia/Kathmandu",
    "iso:country":"NP",
    "wof:name":"Chande",
    "wof:placetype":"locality"
},
  "geometry": {"coordinates":[87.93221,27.13821],"type":"Point"}
}