{
  "type": "Feature",
  "properties": {
    "gn:admin1_code":"ER",
    "gn:admin2_code":"7",
    "gn:admin3_code":"10.0",
    "gn:admin4_code":"100059.0",
    "gn:asciiname":"Chhokimala",
    "gn:country_code":"NP",
    "gn:dem":1303,
    "gn:feature_class":"P",
    "gn:feature_code":"PPLL",
    "gn:name":"Chhokimala",
    "gn:population":0,
    "gn:timezone":"Asia/Kathmandu",
    "iso:country":"NP",
    "wof:name":"Chhokimala",
    "wof:placetype":"locality"
},
  "geometry": {"coordinates":[87.15371,27.18268],"type":"Point"}
}