{
  "type": "Feature",
  "properties": {
    "gn:admin1_code":"WR",
    "gn:admin2_code":"3",
    "gn:admin3_code":"43",
    "gn:admin4_code":"430006",
    "gn:asciiname":"Baur",
    "gn:country_code":"NP",
    "gn:dem":853,
    "gn:feature_class":"P",
    "gn:feature_code":"PPLL",
    "gn:name":"Baur",
    "gn:population":0,
    "gn:timezone":"Asia/Kathmandu",
    "iso:country":"NP",
    "name:ceb_x_preferred":[
        "Baur"
    ],
    "name:ces_x_preferred":[
        "Baur"
    ],
    "name:deu_x_preferred":[
        "Baur"
    ],
    "name:fra_x_preferred":[
        "Baur"
    ],
    "name:rus_x_preferred":[
        "\u0411\u0430\u0443\u0440"
    ],
    "name:swe_x_preferred":[
        "Baur"
    ],
    "wof:name":"Baur",
    "wof:placetype":"locality"
},
  "geometry": {"coordinates":[83.54640000000001,28.33854],"type":"Point"}
}