{
  "type": "Feature",
  "properties": {
    "gn:admin1_code":"MR",
    "gn:admin2_code":"6",
    "gn:admin3_code":"65",
    "gn:admin4_code":"650021",
    "gn:asciiname":"Nigalbot",
    "gn:country_code":"NP",
    "gn:dem":2627,
    "gn:feature_class":"P",
    "gn:feature_code":"PPLL",
    "gn:name":"Nigalbot",
    "gn:population":0,
    "gn:timezone":"Asia/Kathmandu",
    "iso:country":"NP",
    "wof:name":"Nigalbot",
    "wof:placetype":"locality"
},
  "geometry": {"coordinates":[81.97889000000001,29.53641],"type":"Point"}
}