{
  "type": "Feature",
  "properties": {
    "gn:admin1_code":"CR",
    "gn:admin2_code":"5",
    "gn:admin3_code":"22.0",
    "gn:admin4_code":"220043.0",
    "gn:asciiname":"Chisapni",
    "gn:country_code":"NP",
    "gn:dem":1726,
    "gn:feature_class":"P",
    "gn:feature_code":"PPLL",
    "gn:name":"Chisapni",
    "gn:population":0,
    "gn:timezone":"Asia/Kathmandu",
    "iso:country":"NP",
    "wof:name":"Chisapni",
    "wof:placetype":"locality"
},
  "geometry": {"coordinates":[86.19086999999998,27.78021],"type":"Point"}
}