{
  "type": "Feature",
  "properties": {
    "gn:admin1_code":"CR",
    "gn:admin2_code":"5",
    "gn:admin3_code":"17.0",
    "gn:admin4_code":"170102.0",
    "gn:asciiname":"Kesharkuti",
    "gn:country_code":"NP",
    "gn:dem":136,
    "gn:feature_class":"P",
    "gn:feature_code":"PPLL",
    "gn:name":"Kesharkuti",
    "gn:population":0,
    "gn:timezone":"Asia/Kathmandu",
    "iso:country":"NP",
    "wof:name":"Kesharkuti",
    "wof:placetype":"locality"
},
  "geometry": {"coordinates":[86.06186,26.88427],"type":"Point"}
}