{
  "type": "Feature",
  "properties": {
    "gn:admin1_code":"MR",
    "gn:admin2_code":"12",
    "gn:admin3_code":"52",
    "gn:admin4_code":"520029",
    "gn:asciiname":"Jairikanda",
    "gn:country_code":"NP",
    "gn:dem":1849,
    "gn:feature_class":"P",
    "gn:feature_code":"PPLL",
    "gn:name":"Jairikanda",
    "gn:population":0,
    "gn:timezone":"Asia/Kathmandu",
    "iso:country":"NP",
    "wof:name":"Jairikanda",
    "wof:placetype":"locality"
},
  "geometry": {"coordinates":[82.92256999999999,28.18077000000001],"type":"Point"}
}