{
  "type": "Feature",
  "properties": {
    "gn:admin1_code":"FR",
    "gn:admin2_code":"9",
    "gn:admin3_code":"74",
    "gn:admin4_code":"740036",
    "gn:asciiname":"Malla Dahi",
    "gn:country_code":"NP",
    "gn:dem":1617,
    "gn:feature_class":"P",
    "gn:feature_code":"PPLL",
    "gn:name":"Malla Dahi",
    "gn:population":0,
    "gn:timezone":"Asia/Kathmandu",
    "iso:country":"NP",
    "wof:name":"Malla Dahi",
    "wof:placetype":"locality"
},
  "geometry": {"coordinates":[80.68656,29.59609],"type":"Point"}
}