{
  "type": "Feature",
  "properties": {
    "gn:admin1_code":"WR",
    "gn:admin2_code":"4",
    "gn:admin3_code":"40.0",
    "gn:admin4_code":"400007.0",
    "gn:asciiname":"Tikhedhunga",
    "gn:country_code":"NP",
    "gn:dem":1623,
    "gn:feature_class":"P",
    "gn:feature_code":"PPLL",
    "gn:name":"Tikhedhunga",
    "gn:population":200,
    "gn:timezone":"Asia/Kathmandu",
    "iso:country":"NP",
    "wof:name":"Tikhedhunga",
    "wof:placetype":"locality",
    "wof:population":200
},
  "geometry": {"coordinates":[83.7457,28.34964],"type":"Point"}
}