{
  "type": "Feature",
  "properties": {
    "gn:admin1_code":"CR",
    "gn:admin2_code":"5",
    "gn:admin3_code":"19",
    "gn:admin4_code":"190048",
    "gn:asciiname":"Gair",
    "gn:country_code":"NP",
    "gn:dem":109,
    "gn:feature_class":"P",
    "gn:feature_code":"PPLL",
    "gn:name":"Gair",
    "gn:population":0,
    "gn:timezone":"Asia/Kathmandu",
    "iso:country":"NP",
    "wof:name":"Gair",
    "wof:placetype":"locality"
},
  "geometry": {"coordinates":[85.56026999999997,26.96554],"type":"Point"}
}