{
  "type": "Feature",
  "properties": {
    "gn:admin1_code":"WR",
    "gn:admin2_code":"8",
    "gn:admin3_code":"48",
    "gn:admin4_code":"480041",
    "gn:asciiname":"DholBajar",
    "gn:country_code":"NP",
    "gn:dem":180,
    "gn:feature_class":"P",
    "gn:feature_code":"PPLL",
    "gn:name":"DholBajar",
    "gn:population":0,
    "gn:timezone":"Asia/Kathmandu",
    "iso:country":"NP",
    "wof:name":"DholBajar",
    "wof:placetype":"locality"
},
  "geometry": {"coordinates":[84.29011,27.68658],"type":"Point"}
}