{
  "type": "Feature",
  "properties": {
    "gn:admin1_code":"MR",
    "gn:admin2_code":"12",
    "gn:admin3_code":"54",
    "gn:admin4_code":"540014",
    "gn:asciiname":"Tamagar",
    "gn:country_code":"NP",
    "gn:dem":2342,
    "gn:feature_class":"P",
    "gn:feature_code":"PPLL",
    "gn:name":"Tamagar",
    "gn:population":0,
    "gn:timezone":"Asia/Kathmandu",
    "iso:country":"NP",
    "wof:name":"Tamagar",
    "wof:placetype":"locality"
},
  "geometry": {"coordinates":[82.89891,28.64592],"type":"Point"}
}