{
  "type": "Feature",
  "properties": {
    "gn:admin1_code":"ER",
    "gn:admin2_code":"7",
    "gn:admin3_code":"9",
    "gn:admin4_code":"90014",
    "gn:asciiname":"Nigure",
    "gn:country_code":"NP",
    "gn:dem":417,
    "gn:feature_class":"P",
    "gn:feature_code":"PPLL",
    "gn:name":"Nigure",
    "gn:population":0,
    "gn:timezone":"Asia/Kathmandu",
    "iso:country":"NP",
    "wof:name":"Nigure",
    "wof:placetype":"locality"
},
  "geometry": {"coordinates":[87.23609,27.30005],"type":"Point"}
}