{
  "type": "Feature",
  "properties": {
    "gn:admin1_code":"FR",
    "gn:admin2_code":"9",
    "gn:admin3_code":"75.0",
    "gn:admin4_code":"750032.0",
    "gn:asciiname":"Nachane",
    "gn:country_code":"NP",
    "gn:dem":1065,
    "gn:feature_class":"P",
    "gn:feature_code":"PPLL",
    "gn:name":"Nachane",
    "gn:population":0,
    "gn:timezone":"Asia/Kathmandu",
    "iso:country":"NP",
    "name:ben_x_preferred":[
        "\u09a8\u09be\u099a\u09be\u09a8\u09c7"
    ],
    "name:bpy_x_preferred":[
        "\u09a8\u09be\u099a\u09be\u09a8\u09c7"
    ],
    "name:ita_x_preferred":[
        "Nachane"
    ],
    "name:msa_x_preferred":[
        "Nachane"
    ],
    "name:new_x_preferred":[
        "\u0928\u091a\u093e\u0928\u0947"
    ],
    "name:nld_x_preferred":[
        "Nachane"
    ],
    "name:por_x_preferred":[
        "Nachane"
    ],
    "name:urd_x_preferred":[
        "\u0646\u0686\u0627\u0646\u06d2"
    ],
    "name:vie_x_preferred":[
        "Nachane"
    ],
    "name:zho_x_preferred":[
        "\u7eb3\u6070\u5185"
    ],
    "wof:name":"Nachane",
    "wof:placetype":"locality"
},
  "geometry": {"coordinates":[80.49764,29.68342],"type":"Point"}
}