{
  "type": "Feature",
  "properties": {
    "gn:admin1_code":"CR",
    "gn:admin2_code":"1",
    "gn:admin3_code":"23",
    "gn:admin4_code":"230035",
    "gn:asciiname":"Sukute",
    "gn:country_code":"NP",
    "gn:dem":700,
    "gn:feature_class":"P",
    "gn:feature_code":"PPLL",
    "gn:name":"Sukute",
    "gn:population":0,
    "gn:timezone":"Asia/Kathmandu",
    "iso:country":"NP",
    "wof:name":"Sukute",
    "wof:placetype":"locality"
},
  "geometry": {"coordinates":[85.75695999999998,27.70056],"type":"Point"}
}