{
  "type": "Feature",
  "properties": {
    "gn:admin1_code":"WR",
    "gn:admin2_code":"8",
    "gn:admin3_code":"46.0",
    "gn:admin4_code":"460063.0",
    "gn:asciiname":"Danda Pokhari",
    "gn:country_code":"NP",
    "gn:dem":1212,
    "gn:feature_class":"P",
    "gn:feature_code":"PPLL",
    "gn:name":"Danda Pokhari",
    "gn:population":0,
    "gn:timezone":"Asia/Kathmandu",
    "iso:country":"NP",
    "wof:name":"Danda Pokhari",
    "wof:placetype":"locality"
},
  "geometry": {"coordinates":[83.31582,28.11174],"type":"Point"}
}