{
  "type": "Feature",
  "properties": {
    "gn:admin1_code":"WR",
    "gn:admin2_code":"4",
    "gn:admin3_code":"36.0",
    "gn:admin4_code":"360065.0",
    "gn:asciiname":"Swanragaun",
    "gn:country_code":"NP",
    "gn:dem":988,
    "gn:feature_class":"P",
    "gn:feature_code":"PPLL",
    "gn:name":"Swanragaun",
    "gn:population":0,
    "gn:timezone":"Asia/Kathmandu",
    "iso:country":"NP",
    "wof:name":"Swanragaun",
    "wof:placetype":"locality"
},
  "geometry": {"coordinates":[84.81711999999997,28.10577],"type":"Point"}
}