{
  "type": "Feature",
  "properties": {
    "gn:admin1_code":"00",
    "gn:asciiname":"Gairakhuti",
    "gn:country_code":"NP",
    "gn:dem":627,
    "gn:feature_class":"P",
    "gn:feature_code":"PPL",
    "gn:name":"Gair\u0101khu\u1e6di\u0307\u0304",
    "gn:population":0,
    "gn:timezone":"Asia/Kathmandu",
    "iso:country":"NP",
    "name:nep_x_preferred":[
        "Gair\u0101khu\u1e6di\u0307\u0304"
    ],
    "name:und_x_variant":[
        "Garenkhuti"
    ],
    "wof:name":"Gairakhuti",
    "wof:placetype":"locality"
},
  "geometry": {"coordinates":[82.48475000000001,27.96855],"type":"Point"}
}