{
  "type": "Feature",
  "properties": {
    "gn:admin1_code":"CR",
    "gn:admin2_code":"1",
    "gn:admin3_code":"30.0",
    "gn:admin4_code":"300046.0",
    "gn:asciiname":"Chilaunebot",
    "gn:country_code":"NP",
    "gn:dem":658,
    "gn:feature_class":"P",
    "gn:feature_code":"PPLL",
    "gn:name":"Chilaunebot",
    "gn:population":0,
    "gn:timezone":"Asia/Kathmandu",
    "iso:country":"NP",
    "wof:name":"Chilaunebot",
    "wof:placetype":"locality"
},
  "geometry": {"coordinates":[84.88648000000001,27.89246],"type":"Point"}
}