{
  "type": "Feature",
  "properties": {
    "gn:admin1_code":"CR",
    "gn:admin2_code":"11",
    "gn:admin3_code":"35.0",
    "gn:admin4_code":"350034.0",
    "gn:asciiname":"Bangai",
    "gn:country_code":"NP",
    "gn:dem":174,
    "gn:feature_class":"P",
    "gn:feature_code":"PPLL",
    "gn:name":"Bangai",
    "gn:population":0,
    "gn:timezone":"Asia/Kathmandu",
    "iso:country":"NP",
    "name:ceb_x_preferred":[
        "Bangai"
    ],
    "name:swe_x_preferred":[
        "Bangai"
    ],
    "wof:name":"Bangai",
    "wof:placetype":"locality"
},
  "geometry": {"coordinates":[84.3265,27.66496],"type":"Point"}
}