{
  "type": "Feature",
  "properties": {
    "gn:admin1_code":"FR",
    "gn:admin2_code":"14",
    "gn:admin3_code":"68",
    "gn:admin4_code":"680011",
    "gn:asciiname":"Gotanna",
    "gn:country_code":"NP",
    "gn:dem":2427,
    "gn:feature_class":"P",
    "gn:feature_code":"PPLL",
    "gn:name":"Gotanna",
    "gn:population":0,
    "gn:timezone":"Asia/Kathmandu",
    "iso:country":"NP",
    "wof:name":"Gotanna",
    "wof:placetype":"locality"
},
  "geometry": {"coordinates":[81.11428000000002,29.60657],"type":"Point"}
}