{
  "type": "Feature",
  "properties": {
    "gn:admin1_code":"MR",
    "gn:admin2_code":"12",
    "gn:admin3_code":"52",
    "gn:admin4_code":"520045",
    "gn:asciiname":"Chhepte Odar",
    "gn:country_code":"NP",
    "gn:dem":1990,
    "gn:feature_class":"P",
    "gn:feature_code":"PPLL",
    "gn:name":"Chhepte Odar",
    "gn:population":0,
    "gn:timezone":"Asia/Kathmandu",
    "iso:country":"NP",
    "wof:name":"Chhepte Odar",
    "wof:placetype":"locality"
},
  "geometry": {"coordinates":[82.93977,28.30882],"type":"Point"}
}