{
  "type": "Feature",
  "properties": {
    "gn:admin1_code":"WR",
    "gn:admin2_code":"4.0",
    "gn:admin3_code":"39.0",
    "gn:admin4_code":"390003.0",
    "gn:asciiname":"Chihandanda",
    "gn:country_code":"NP",
    "gn:dem":1645,
    "gn:feature_class":"P",
    "gn:feature_code":"PPLL",
    "gn:name":"Chihandanda",
    "gn:population":0,
    "gn:timezone":"Asia/Kathmandu",
    "iso:country":"NP",
    "wof:name":"Chihandanda",
    "wof:placetype":"locality"
},
  "geometry": {"coordinates":[83.72675,28.13611],"type":"Point"}
}