{
  "type": "Feature",
  "properties": {
    "gn:admin1_code":"WR",
    "gn:admin2_code":"4.0",
    "gn:admin3_code":"38.0",
    "gn:admin4_code":"380030.0",
    "gn:asciiname":"Mugurdanda",
    "gn:country_code":"NP",
    "gn:dem":931,
    "gn:feature_class":"P",
    "gn:feature_code":"PPLL",
    "gn:name":"Mugurdanda",
    "gn:population":0,
    "gn:timezone":"Asia/Kathmandu",
    "iso:country":"NP",
    "wof:name":"Mugurdanda",
    "wof:placetype":"locality"
},
  "geometry": {"coordinates":[84.19424000000002,27.93769],"type":"Point"}
}