{
  "type": "Feature",
  "properties": {
    "gn:admin1_code":"ER",
    "gn:admin2_code":"7",
    "gn:admin3_code":"9",
    "gn:admin4_code":"90009",
    "gn:asciiname":"Diding",
    "gn:country_code":"NP",
    "gn:dem":1719,
    "gn:feature_class":"P",
    "gn:feature_code":"PPLL",
    "gn:name":"Diding",
    "gn:population":0,
    "gn:timezone":"Asia/Kathmandu",
    "iso:country":"NP",
    "name:bih_x_preferred":[
        "\u0926\u093f\u0926\u093f\u0919"
    ],
    "name:ceb_x_preferred":[
        "Diding"
    ],
    "name:hin_x_preferred":[
        "\u0926\u093f\u0926\u093f\u0919"
    ],
    "name:mai_x_preferred":[
        "\u0926\u093f\u0926\u093f\u0919"
    ],
    "name:msa_x_preferred":[
        "Diding"
    ],
    "name:nep_x_preferred":[
        "\u0926\u093f\u0926\u093f\u0919"
    ],
    "name:new_x_preferred":[
        "\u0926\u093f\u0926\u093f\u0919"
    ],
    "name:pol_x_preferred":[
        "Diding"
    ],
    "wof:name":"Diding",
    "wof:placetype":"locality"
},
  "geometry": {"coordinates":[87.22015,27.50305],"type":"Point"}
}