{
  "type": "Feature",
  "properties": {
    "gn:admin1_code":"FR",
    "gn:admin2_code":"14",
    "gn:admin3_code":"69",
    "gn:admin4_code":"690030",
    "gn:asciiname":"Patan",
    "gn:country_code":"NP",
    "gn:dem":937,
    "gn:feature_class":"P",
    "gn:feature_code":"PPLL",
    "gn:name":"Patan",
    "gn:population":0,
    "gn:timezone":"Asia/Kathmandu",
    "iso:country":"NP",
    "wof:name":"Patan",
    "wof:placetype":"locality"
},
  "geometry": {"coordinates":[81.25149,29.03911],"type":"Point"}
}