{
  "type": "Feature",
  "properties": {
    "gn:admin1_code":"CR",
    "gn:admin2_code":"1",
    "gn:admin3_code":"24.0",
    "gn:admin4_code":"240036.0",
    "gn:asciiname":"Dhaireni",
    "gn:country_code":"NP",
    "gn:dem":1115,
    "gn:feature_class":"P",
    "gn:feature_code":"PPLL",
    "gn:name":"Dhaireni",
    "gn:population":0,
    "gn:timezone":"Asia/Kathmandu",
    "iso:country":"NP",
    "wof:name":"Dhaireni",
    "wof:placetype":"locality"
},
  "geometry": {"coordinates":[85.67388000000003,27.66147],"type":"Point"}
}