{
  "type": "Feature",
  "properties": {
    "gn:admin1_code":"FR",
    "gn:admin2_code":"14",
    "gn:admin3_code":"70.0",
    "gn:admin4_code":"700007.0",
    "gn:asciiname":"Chorki",
    "gn:country_code":"NP",
    "gn:dem":2233,
    "gn:feature_class":"P",
    "gn:feature_code":"PPLL",
    "gn:name":"Chorki",
    "gn:population":0,
    "gn:timezone":"Asia/Kathmandu",
    "iso:country":"NP",
    "name:azb_x_preferred":[
        "\u062e\u0648\u0631\u06a9\u06cc"
    ],
    "name:fas_x_preferred":[
        "\u062e\u0648\u0631\u06a9\u06cc"
    ],
    "name:fra_x_preferred":[
        "Chorki"
    ],
    "name:nld_x_preferred":[
        "Chorki"
    ],
    "name:pol_x_preferred":[
        "Chorki"
    ],
    "name:ukr_x_preferred":[
        "\u0425\u043e\u0440\u043a\u0456"
    ],
    "wof:name":"Chorki",
    "wof:placetype":"locality"
},
  "geometry": {"coordinates":[80.90965,29.39558],"type":"Point"}
}