{
  "type": "Feature",
  "properties": {
    "gn:admin1_code":"WR",
    "gn:admin2_code":"4",
    "gn:admin3_code":"36.0",
    "gn:admin4_code":"360022.0",
    "gn:asciiname":"Alaiche",
    "gn:country_code":"NP",
    "gn:dem":559,
    "gn:feature_class":"P",
    "gn:feature_code":"PPLL",
    "gn:name":"Alaiche",
    "gn:population":0,
    "gn:timezone":"Asia/Kathmandu",
    "iso:country":"NP",
    "wof:name":"Alaiche",
    "wof:placetype":"locality"
},
  "geometry": {"coordinates":[84.72673,27.9015],"type":"Point"}
}