{
  "type": "Feature",
  "properties": {
    "gn:admin1_code":"MR",
    "gn:admin2_code":"12",
    "gn:admin3_code":"53",
    "gn:admin4_code":"530016",
    "gn:asciiname":"Bhadaurethan",
    "gn:country_code":"NP",
    "gn:dem":1577,
    "gn:feature_class":"P",
    "gn:feature_code":"PPLL",
    "gn:name":"Bhadaurethan",
    "gn:population":0,
    "gn:timezone":"Asia/Kathmandu",
    "iso:country":"NP",
    "wof:name":"Bhadaurethan",
    "wof:placetype":"locality"
},
  "geometry": {"coordinates":[82.84564,28.30302],"type":"Point"}
}