{
  "type": "Feature",
  "properties": {
    "gn:admin1_code":"FR",
    "gn:admin2_code":"9",
    "gn:admin3_code":"74",
    "gn:admin4_code":"740056",
    "gn:asciiname":"Sugarkhal",
    "gn:country_code":"NP",
    "gn:dem":2098,
    "gn:feature_class":"P",
    "gn:feature_code":"PPLL",
    "gn:name":"Sugarkhal",
    "gn:population":0,
    "gn:timezone":"Asia/Kathmandu",
    "iso:country":"NP",
    "name:ceb_x_preferred":[
        "Sugarkhal"
    ],
    "name:mai_x_preferred":[
        "\u0938\u0941\u0901\u0917\u0941\u0930\u0916\u093e\u0932"
    ],
    "name:msa_x_preferred":[
        "Sugarkhal"
    ],
    "name:nep_x_preferred":[
        "\u0938\u0941\u0901\u0917\u0941\u0930\u0916\u093e\u0932"
    ],
    "name:new_x_preferred":[
        "\u0938\u0941\u0901\u0917\u0930\u0916\u093e\u0932"
    ],
    "name:pol_x_preferred":[
        "Sugarkhal"
    ],
    "wof:name":"Sugarkhal",
    "wof:placetype":"locality"
},
  "geometry": {"coordinates":[80.63039999999999,29.45871],"type":"Point"}
}