{
  "type": "Feature",
  "properties": {
    "gn:admin1_code":"MR",
    "gn:admin2_code":"2",
    "gn:admin3_code":"60.0",
    "gn:admin4_code":"600005.0",
    "gn:asciiname":"Alegau",
    "gn:country_code":"NP",
    "gn:dem":1422,
    "gn:feature_class":"P",
    "gn:feature_code":"PPLL",
    "gn:name":"Alegau",
    "gn:population":0,
    "gn:timezone":"Asia/Kathmandu",
    "iso:country":"NP",
    "wof:name":"Alegau",
    "wof:placetype":"locality"
},
  "geometry": {"coordinates":[81.80778000000002,28.9273],"type":"Point"}
}