{
  "type": "Feature",
  "properties": {
    "gn:admin1_code":"ER",
    "gn:admin2_code":"10",
    "gn:admin3_code":"4.0",
    "gn:admin4_code":"40017.0",
    "gn:asciiname":"Baraghare",
    "gn:country_code":"NP",
    "gn:dem":108,
    "gn:feature_class":"P",
    "gn:feature_code":"PPLL",
    "gn:name":"Baraghare",
    "gn:population":0,
    "gn:timezone":"Asia/Kathmandu",
    "iso:country":"NP",
    "wof:name":"Baraghare",
    "wof:placetype":"locality"
},
  "geometry": {"coordinates":[88.04514,26.6007],"type":"Point"}
}