{
  "type": "Feature",
  "properties": {
    "gn:admin1_code":"MR",
    "gn:admin2_code":"6",
    "gn:admin3_code":"62.0",
    "gn:admin4_code":"620011.0",
    "gn:asciiname":"Hangaun",
    "gn:country_code":"NP",
    "gn:dem":2628,
    "gn:feature_class":"P",
    "gn:feature_code":"PPLL",
    "gn:name":"Hangaun",
    "gn:population":0,
    "gn:timezone":"Asia/Kathmandu",
    "iso:country":"NP",
    "wof:name":"Hangaun",
    "wof:placetype":"locality"
},
  "geometry": {"coordinates":[82.83717,28.95288],"type":"Point"}
}