{
  "type": "Feature",
  "properties": {
    "gn:admin1_code":"CR",
    "gn:admin2_code":"1",
    "gn:admin3_code":"24.0",
    "gn:admin4_code":"240052.0",
    "gn:asciiname":"Thadokol",
    "gn:country_code":"NP",
    "gn:dem":722,
    "gn:feature_class":"P",
    "gn:feature_code":"PPLL",
    "gn:name":"Thadokol",
    "gn:population":0,
    "gn:timezone":"Asia/Kathmandu",
    "iso:country":"NP",
    "wof:name":"Thadokol",
    "wof:placetype":"locality"
},
  "geometry": {"coordinates":[85.60363000000002,27.74519],"type":"Point"}
}