{
  "type": "Feature",
  "properties": {
    "gn:admin1_code":"ER",
    "gn:admin2_code":"7",
    "gn:admin3_code":"10.0",
    "gn:admin4_code":"100049.0",
    "gn:asciiname":"Hangkangla",
    "gn:country_code":"NP",
    "gn:dem":1446,
    "gn:feature_class":"P",
    "gn:feature_code":"PPLL",
    "gn:name":"Hangkangla",
    "gn:population":0,
    "gn:timezone":"Asia/Kathmandu",
    "iso:country":"NP",
    "wof:name":"Hangkangla",
    "wof:placetype":"locality"
},
  "geometry": {"coordinates":[87.08069999999999,27.02115],"type":"Point"}
}