{
  "type": "Feature",
  "properties": {
    "gn:admin1_code":"CR",
    "gn:admin2_code":"5",
    "gn:admin3_code":"21",
    "gn:admin4_code":"210046",
    "gn:asciiname":"Linaha",
    "gn:country_code":"NP",
    "gn:dem":1211,
    "gn:feature_class":"P",
    "gn:feature_code":"PPLL",
    "gn:name":"Linaha",
    "gn:population":0,
    "gn:timezone":"Asia/Kathmandu",
    "iso:country":"NP",
    "wof:name":"Linaha",
    "wof:placetype":"locality"
},
  "geometry": {"coordinates":[86.17582,27.28351],"type":"Point"}
}