{
  "type": "Feature",
  "properties": {
    "gn:admin1_code":"CR",
    "gn:admin2_code":"11",
    "gn:admin3_code":"31",
    "gn:admin4_code":"310001",
    "gn:asciiname":"Kabhrechhap",
    "gn:country_code":"NP",
    "gn:dem":1081,
    "gn:feature_class":"P",
    "gn:feature_code":"PPLL",
    "gn:name":"Kabhrechhap",
    "gn:population":0,
    "gn:timezone":"Asia/Kathmandu",
    "iso:country":"NP",
    "wof:name":"Kabhrechhap",
    "wof:placetype":"locality"
},
  "geometry": {"coordinates":[85.04045000000001,27.70107],"type":"Point"}
}