{
  "type": "Feature",
  "properties": {
    "gn:admin1_code":"00",
    "gn:asciiname":"Dadagau",
    "gn:country_code":"NP",
    "gn:dem":992,
    "gn:feature_class":"P",
    "gn:feature_code":"PPL",
    "gn:name":"\u1e0c\u0101\u0303\u1e0d\u0101g\u0101\u0169",
    "gn:population":0,
    "gn:timezone":"Asia/Kathmandu",
    "iso:country":"NP",
    "name:nep_x_preferred":[
        "\u1e0c\u0101\u0303\u1e0d\u0101g\u0101\u0169"
    ],
    "wof:name":"Dadagau",
    "wof:placetype":"locality"
},
  "geometry": {"coordinates":[84.80211,28.08373],"type":"Point"}
}