{
  "type": "Feature",
  "properties": {
    "gn:admin1_code":"MR",
    "gn:admin2_code":"12",
    "gn:admin3_code":"54",
    "gn:admin4_code":"540037",
    "gn:asciiname":"Debas tal",
    "gn:country_code":"NP",
    "gn:dem":2157,
    "gn:feature_class":"P",
    "gn:feature_code":"PPLL",
    "gn:name":"Debas tal",
    "gn:population":0,
    "gn:timezone":"Asia/Kathmandu",
    "iso:country":"NP",
    "wof:name":"Debas tal",
    "wof:placetype":"locality"
},
  "geometry": {"coordinates":[82.52651,28.56744],"type":"Point"}
}