{
  "type": "Feature",
  "properties": {
    "gn:admin1_code":"MR",
    "gn:admin2_code":"12",
    "gn:admin3_code":"54",
    "gn:admin4_code":"540031",
    "gn:asciiname":"Malika",
    "gn:country_code":"NP",
    "gn:dem":1648,
    "gn:feature_class":"P",
    "gn:feature_code":"PPLL",
    "gn:name":"Malika",
    "gn:population":0,
    "gn:timezone":"Asia/Kathmandu",
    "iso:country":"NP",
    "name:ceb_x_preferred":[
        "Malika"
    ],
    "name:deu_x_preferred":[
        "Malika"
    ],
    "name:fra_x_preferred":[
        "Malika"
    ],
    "name:nep_x_preferred":[
        "\u092e\u093e\u0932\u093f\u0915\u093e"
    ],
    "name:pol_x_preferred":[
        "Malika"
    ],
    "wof:name":"Malika",
    "wof:placetype":"locality"
},
  "geometry": {"coordinates":[82.26668000000002,28.67875],"type":"Point"}
}