{
  "type": "Feature",
  "properties": {
    "gn:admin1_code":"ER",
    "gn:admin2_code":"7",
    "gn:admin3_code":"9",
    "gn:admin4_code":"90027",
    "gn:asciiname":"Dubeni",
    "gn:country_code":"NP",
    "gn:dem":2269,
    "gn:feature_class":"P",
    "gn:feature_code":"PPLL",
    "gn:name":"Dubeni",
    "gn:population":0,
    "gn:timezone":"Asia/Kathmandu",
    "iso:country":"NP",
    "wof:name":"Dubeni",
    "wof:placetype":"locality"
},
  "geometry": {"coordinates":[87.41802,27.32287],"type":"Point"}
}