{
  "type": "Feature",
  "properties": {
    "gn:admin1_code":"CR",
    "gn:admin2_code":"5",
    "gn:admin3_code":"20",
    "gn:admin4_code":"200035",
    "gn:asciiname":"Uchaldhunga",
    "gn:country_code":"NP",
    "gn:dem":332,
    "gn:feature_class":"P",
    "gn:feature_code":"PPLL",
    "gn:name":"Uchaldhunga",
    "gn:population":0,
    "gn:timezone":"Asia/Kathmandu",
    "iso:country":"NP",
    "wof:name":"Uchaldhunga",
    "wof:placetype":"locality"
},
  "geometry": {"coordinates":[85.57030999999998,27.29541],"type":"Point"}
}