{
  "type": "Feature",
  "properties": {
    "gn:admin1_code":"MR",
    "gn:admin2_code":"6",
    "gn:admin3_code":"62.0",
    "gn:admin4_code":"620004.0",
    "gn:asciiname":"Lochakholagaun",
    "gn:country_code":"NP",
    "gn:dem":2417,
    "gn:feature_class":"P",
    "gn:feature_code":"PPLL",
    "gn:name":"Lochakholagaun",
    "gn:population":0,
    "gn:timezone":"Asia/Kathmandu",
    "iso:country":"NP",
    "wof:name":"Lochakholagaun",
    "wof:placetype":"locality"
},
  "geometry": {"coordinates":[82.90052,28.93378],"type":"Point"}
}