{
  "type": "Feature",
  "properties": {
    "gn:admin1_code":"CR",
    "gn:admin2_code":"1",
    "gn:admin3_code":"23",
    "gn:admin4_code":"230042",
    "gn:asciiname":"Nargang",
    "gn:country_code":"NP",
    "gn:dem":1729,
    "gn:feature_class":"P",
    "gn:feature_code":"PPLL",
    "gn:name":"Nargang",
    "gn:population":0,
    "gn:timezone":"Asia/Kathmandu",
    "iso:country":"NP",
    "wof:name":"Nargang",
    "wof:placetype":"locality"
},
  "geometry": {"coordinates":[85.84057,27.65156],"type":"Point"}
}