{
  "type": "Feature",
  "properties": {
    "iso:country":"NP",
    "name:ceb_x_preferred":[
        "Bhojpur"
    ],
    "name:deu_x_preferred":[
        "Bhojpur"
    ],
    "name:eng_x_preferred":[
        "Bhojpur"
    ],
    "name:fra_x_preferred":[
        "Bhojpur"
    ],
    "name:heb_x_preferred":[
        "\u05d1\u05d5\u05d2'\u05e4\u05d5\u05e8"
    ],
    "name:hun_x_preferred":[
        "Bhojpur"
    ],
    "name:jpn_x_preferred":[
        "\u30dc\u30b8\u30d7\u30eb"
    ],
    "name:lit_x_preferred":[
        "Bhod\u017epuras"
    ],
    "name:lit_x_variant":[
        "Bod\u017epuras"
    ],
    "name:mai_x_preferred":[
        "\u092d\u094b\u091c\u092a\u0941\u0930 \u0928\u0917\u0930\u092a\u093e\u0932\u093f\u0915\u093e"
    ],
    "name:msa_x_preferred":[
        "Bhojpur"
    ],
    "name:nep_x_preferred":[
        "\u092d\u094b\u091c\u092a\u0941\u0930 \u0928\u0917\u0930\u092a\u093e\u0932\u093f\u0915\u093e"
    ],
    "name:nld_x_preferred":[
        "Bhojpur"
    ],
    "name:pol_x_preferred":[
        "Bhojpur"
    ],
    "name:por_x_preferred":[
        "Bhojpur"
    ],
    "name:urd_x_preferred":[
        "\u0628\u06be\u0648\u062c\u067e\u0648\u0631\u060c \u0646\u06cc\u067e\u0627\u0644"
    ],
    "name:urd_x_variant":[
        "\u0628\u06be\u0648\u062c\u067e\u0648\u0631"
    ],
    "name:zho_x_preferred":[
        "\u535a\u5091\u666e\u723e"
    ],
    "qs:gn_country":"NP",
    "qs:gn_fcode":"PPLA3",
    "qs:gn_pop":3250,
    "qs:name":"Bhojpur",
    "qs:name_adm0":"Nepal",
    "qs:name_adm1":"Purwanchal",
    "qs:photos":0,
    "qs:photos_1k":0,
    "qs:photos_9k":1,
    "qs:photos_9r":1,
    "qs:photos_all":1,
    "qs:photos_sr":0,
    "qs:placetype":"Town",
    "qs:pop_sr":"4",
    "qs:woe_adm0":23424911,
    "wd:wordcount":461,
    "wof:name":"Bhojpur",
    "wof:placetype":"locality",
    "wof:population":3250
},
  "geometry": {"coordinates":[87.04607,27.1715],"type":"Point"}
}