{
  "type": "Feature",
  "properties": {
    "gn:admin1_code":"WR",
    "gn:admin2_code":"8",
    "gn:admin3_code":"49",
    "gn:admin4_code":"490014",
    "gn:asciiname":"Shrawan Chok",
    "gn:country_code":"NP",
    "gn:dem":303,
    "gn:feature_class":"P",
    "gn:feature_code":"PPLL",
    "gn:name":"Shrawan Chok",
    "gn:population":0,
    "gn:timezone":"Asia/Kathmandu",
    "iso:country":"NP",
    "wof:name":"Shrawan Chok",
    "wof:placetype":"locality"
},
  "geometry": {"coordinates":[83.47094,27.71461],"type":"Point"}
}