{
  "type": "Feature",
  "properties": {
    "gn:admin1_code":"ER",
    "gn:admin2_code":"10",
    "gn:admin3_code":"4.0",
    "gn:admin4_code":"40035.0",
    "gn:asciiname":"Jatruchaun",
    "gn:country_code":"NP",
    "gn:dem":102,
    "gn:feature_class":"P",
    "gn:feature_code":"PPLL",
    "gn:name":"Jatruchaun",
    "gn:population":0,
    "gn:timezone":"Asia/Kathmandu",
    "iso:country":"NP",
    "wof:name":"Jatruchaun",
    "wof:placetype":"locality"
},
  "geometry": {"coordinates":[87.68810999999999,26.5751],"type":"Point"}
}