{
  "type": "Feature",
  "properties": {
    "gn:admin1_code":"MR",
    "gn:admin2_code":"12",
    "gn:admin3_code":"53",
    "gn:admin4_code":"530017",
    "gn:asciiname":"Lungdun",
    "gn:country_code":"NP",
    "gn:dem":2384,
    "gn:feature_class":"P",
    "gn:feature_code":"PPLL",
    "gn:name":"Lungdun",
    "gn:population":0,
    "gn:timezone":"Asia/Kathmandu",
    "iso:country":"NP",
    "wof:name":"Lungdun",
    "wof:placetype":"locality"
},
  "geometry": {"coordinates":[82.73594,28.36167],"type":"Point"}
}