{
  "type": "Feature",
  "properties": {
    "gn:admin1_code":"MR",
    "gn:admin2_code":"12",
    "gn:admin3_code":"55",
    "gn:admin4_code":"550033",
    "gn:asciiname":"Syani  Panyari",
    "gn:country_code":"NP",
    "gn:dem":1253,
    "gn:feature_class":"P",
    "gn:feature_code":"PPLL",
    "gn:name":"Syani  Panyari",
    "gn:population":0,
    "gn:timezone":"Asia/Kathmandu",
    "iso:country":"NP",
    "wof:name":"Syani  Panyari",
    "wof:placetype":"locality"
},
  "geometry": {"coordinates":[82.20595,28.5426],"type":"Point"}
}