{
  "type": "Feature",
  "properties": {
    "gn:admin1_code":"CR",
    "gn:admin2_code":"11",
    "gn:admin3_code":"34",
    "gn:admin4_code":"340034",
    "gn:asciiname":"Ramauli",
    "gn:country_code":"NP",
    "gn:dem":103,
    "gn:feature_class":"P",
    "gn:feature_code":"PPLL",
    "gn:name":"Ramauli",
    "gn:population":0,
    "gn:timezone":"Asia/Kathmandu",
    "iso:country":"NP",
    "wof:name":"Ramauli",
    "wof:placetype":"locality"
},
  "geometry": {"coordinates":[84.86889000000002,27.1511],"type":"Point"}
}