{
  "type": "Feature",
  "properties": {
    "gn:admin1_code":"ER",
    "gn:admin2_code":"13.0",
    "gn:admin3_code":"14.0",
    "gn:admin4_code":"140014.0",
    "gn:asciiname":"Sukaura",
    "gn:country_code":"NP",
    "gn:dem":507,
    "gn:feature_class":"P",
    "gn:feature_code":"PPLL",
    "gn:name":"Sukaura",
    "gn:population":0,
    "gn:timezone":"Asia/Kathmandu",
    "iso:country":"NP",
    "name:ceb_x_preferred":[
        "Sukaura"
    ],
    "name:msa_x_preferred":[
        "Sukaura"
    ],
    "name:nep_x_preferred":[
        "\u0938\u0941\u0915\u094c\u0930\u093e"
    ],
    "name:new_x_preferred":[
        "\u0938\u0941\u0915\u094c\u0930\u093e"
    ],
    "name:pol_x_preferred":[
        "Sukaura"
    ],
    "wof:name":"Sukaura",
    "wof:placetype":"locality"
},
  "geometry": {"coordinates":[86.64784,26.89735],"type":"Point"}
}