{
  "type": "Feature",
  "properties": {
    "gn:admin1_code":"WR",
    "gn:admin2_code":"8",
    "gn:admin3_code":"48",
    "gn:admin4_code":"480027.0",
    "gn:asciiname":"Sadha Bhanjyang",
    "gn:country_code":"NP",
    "gn:dem":1038,
    "gn:feature_class":"P",
    "gn:feature_code":"PPLL",
    "gn:name":"Sadha Bhanjyang",
    "gn:population":0,
    "gn:timezone":"Asia/Kathmandu",
    "iso:country":"NP",
    "wof:name":"Sadha Bhanjyang",
    "wof:placetype":"locality"
},
  "geometry": {"coordinates":[83.97088000000002,27.73569],"type":"Point"}
}