{
  "type": "Feature",
  "properties": {
    "gn:admin1_code":"WR",
    "gn:admin2_code":"3",
    "gn:admin3_code":"45.0",
    "gn:admin4_code":"450013.0",
    "gn:asciiname":"Pakhapani",
    "gn:country_code":"NP",
    "gn:dem":1392,
    "gn:feature_class":"P",
    "gn:feature_code":"PPLL",
    "gn:name":"Pakhapani",
    "gn:population":0,
    "gn:timezone":"Asia/Kathmandu",
    "iso:country":"NP",
    "name:fra_x_preferred":[
        "Pakhapani"
    ],
    "name:nep_x_preferred":[
        "\u092a\u093e\u0916\u093e\u092a\u093e\u0928\u0940"
    ],
    "name:pol_x_preferred":[
        "Pakhapani"
    ],
    "wof:name":"Pakhapani",
    "wof:placetype":"locality"
},
  "geometry": {"coordinates":[83.12984,28.36606],"type":"Point"}
}