{
  "type": "Feature",
  "properties": {
    "gn:admin1_code":"CR",
    "gn:admin2_code":"5",
    "gn:admin3_code":"20",
    "gn:admin4_code":"200033",
    "gn:asciiname":"Damarchauki",
    "gn:country_code":"NP",
    "gn:dem":1799,
    "gn:feature_class":"P",
    "gn:feature_code":"PPLL",
    "gn:name":"Damarchauki",
    "gn:population":0,
    "gn:timezone":"Asia/Kathmandu",
    "iso:country":"NP",
    "wof:name":"Damarchauki",
    "wof:placetype":"locality"
},
  "geometry": {"coordinates":[86.2671,27.13601],"type":"Point"}
}