{
  "type": "Feature",
  "properties": {
    "gn:admin1_code":"WR",
    "gn:admin2_code":"8",
    "gn:admin3_code":"49",
    "gn:admin4_code":"490064",
    "gn:asciiname":"Dhanchhi",
    "gn:country_code":"NP",
    "gn:dem":116,
    "gn:feature_class":"P",
    "gn:feature_code":"PPLL",
    "gn:name":"Dhanchhi",
    "gn:population":0,
    "gn:timezone":"Asia/Kathmandu",
    "iso:country":"NP",
    "wof:name":"Dhanchhi",
    "wof:placetype":"locality"
},
  "geometry": {"coordinates":[83.54810000000001,27.54456],"type":"Point"}
}