{
  "type": "Feature",
  "properties": {
    "gn:admin1_code":"WR",
    "gn:admin2_code":"8",
    "gn:admin3_code":"47",
    "gn:admin4_code":"470065",
    "gn:asciiname":"Geja",
    "gn:country_code":"NP",
    "gn:dem":702,
    "gn:feature_class":"P",
    "gn:feature_code":"PPLL",
    "gn:name":"Geja",
    "gn:population":0,
    "gn:timezone":"Asia/Kathmandu",
    "iso:country":"NP",
    "wof:name":"Geja",
    "wof:placetype":"locality"
},
  "geometry": {"coordinates":[84.01075,27.81199],"type":"Point"}
}