{
  "type": "Feature",
  "properties": {
    "gn:admin1_code":"FR",
    "gn:admin2_code":"14",
    "gn:admin3_code":"71.0",
    "gn:admin4_code":"710012.0",
    "gn:asciiname":"Subarnapur",
    "gn:country_code":"NP",
    "gn:dem":168,
    "gn:feature_class":"P",
    "gn:feature_code":"PPLL",
    "gn:name":"Subarnapur",
    "gn:population":0,
    "gn:timezone":"Asia/Kathmandu",
    "iso:country":"NP",
    "name:ceb_x_preferred":[
        "Subarnapur"
    ],
    "name:deu_x_preferred":[
        "Subarnapur"
    ],
    "name:swe_x_preferred":[
        "Subarnapur"
    ],
    "wof:name":"Subarnapur",
    "wof:placetype":"locality"
},
  "geometry": {"coordinates":[81.1544,28.55918],"type":"Point"}
}