{
  "type": "Feature",
  "properties": {
    "gn:admin1_code":"ER",
    "gn:admin2_code":"13.0",
    "gn:admin3_code":"14.0",
    "gn:admin4_code":"140037.0",
    "gn:asciiname":"Tamlichha",
    "gn:country_code":"NP",
    "gn:dem":1226,
    "gn:feature_class":"P",
    "gn:feature_code":"PPLL",
    "gn:name":"Tamlichha",
    "gn:population":0,
    "gn:timezone":"Asia/Kathmandu",
    "iso:country":"NP",
    "name:bih_x_preferred":[
        "\u0924\u093e\u092e\u094d\u0932\u0940\u091b\u093e"
    ],
    "name:ita_x_preferred":[
        "Tamlichha"
    ],
    "name:mai_x_preferred":[
        "\u0924\u093e\u092e\u094d\u0932\u0940\u091b\u093e"
    ],
    "name:msa_x_preferred":[
        "Tamlichha"
    ],
    "name:nep_x_preferred":[
        "\u0924\u093e\u092e\u094d\u0932\u0940\u091b\u093e"
    ],
    "name:pol_x_preferred":[
        "Tamlida"
    ],
    "wof:name":"Tamlichha",
    "wof:placetype":"locality"
},
  "geometry": {"coordinates":[86.65173,27.10586],"type":"Point"}
}