{
  "type": "Feature",
  "properties": {
    "gn:admin1_code":"WR",
    "gn:admin2_code":"4.0",
    "gn:admin3_code":"39.0",
    "gn:admin4_code":"390039.0",
    "gn:asciiname":"Tribeni",
    "gn:country_code":"NP",
    "gn:dem":1989,
    "gn:feature_class":"P",
    "gn:feature_code":"PPLL",
    "gn:name":"Tribeni",
    "gn:population":0,
    "gn:timezone":"Asia/Kathmandu",
    "iso:country":"NP",
    "name:fra_x_preferred":[
        "Tribeni"
    ],
    "name:pol_x_preferred":[
        "Tribeni"
    ],
    "wof:name":"Tribeni",
    "wof:placetype":"locality"
},
  "geometry": {"coordinates":[83.74753,28.14283],"type":"Point"}
}