{
  "type": "Feature",
  "properties": {
    "gn:admin1_code":"CR",
    "gn:admin2_code":"1.0",
    "gn:asciiname":"Jyamaruk",
    "gn:country_code":"NP",
    "gn:dem":1233,
    "gn:feature_class":"P",
    "gn:feature_code":"PPL",
    "gn:name":"Jyamaruk",
    "gn:population":0,
    "gn:timezone":"Asia/Kathmandu",
    "iso:country":"NP",
    "name:msa_x_preferred":[
        "Jyamaruk"
    ],
    "wof:name":"Jyamaruk",
    "wof:placetype":"locality"
},
  "geometry": {"coordinates":[84.87361999999997,27.97602],"type":"Point"}
}