{
  "type": "Feature",
  "properties": {
    "gn:admin1_code":"CR",
    "gn:admin2_code":"1",
    "gn:admin3_code":"23",
    "gn:admin4_code":"230020",
    "gn:asciiname":"Dhuskot Banche",
    "gn:country_code":"NP",
    "gn:dem":1361,
    "gn:feature_class":"P",
    "gn:feature_code":"PPLL",
    "gn:name":"Dhuskot Banche",
    "gn:population":0,
    "gn:timezone":"Asia/Kathmandu",
    "iso:country":"NP",
    "wof:name":"Dhuskot Banche",
    "wof:placetype":"locality"
},
  "geometry": {"coordinates":[85.79947,27.80232],"type":"Point"}
}