{
  "type": "Feature",
  "properties": {
    "gn:admin1_code":"CR",
    "gn:admin2_code":"1",
    "gn:admin3_code":"23",
    "gn:admin4_code":"230003",
    "gn:asciiname":"Dhikurebesi",
    "gn:country_code":"NP",
    "gn:dem":758,
    "gn:feature_class":"P",
    "gn:feature_code":"PPLL",
    "gn:name":"Dhikurebesi",
    "gn:population":0,
    "gn:timezone":"Asia/Kathmandu",
    "iso:country":"NP",
    "wof:name":"Dhikurebesi",
    "wof:placetype":"locality"
},
  "geometry": {"coordinates":[85.57208,27.78752],"type":"Point"}
}