{
  "type": "Feature",
  "properties": {
    "gn:admin1_code":"CR",
    "gn:admin2_code":"11.0",
    "gn:admin3_code":"33.0",
    "gn:admin4_code":"330017.0",
    "gn:asciiname":"Beldari",
    "gn:country_code":"NP",
    "gn:dem":77,
    "gn:feature_class":"P",
    "gn:feature_code":"PPLL",
    "gn:name":"Beldari",
    "gn:population":0,
    "gn:timezone":"Asia/Kathmandu",
    "iso:country":"NP",
    "name:ceb_x_preferred":[
        "Beldari"
    ],
    "name:fra_x_preferred":[
        "Beldari"
    ],
    "name:mai_x_preferred":[
        "\u092c\u0947\u0932\u094d\u0926\u093e\u0930\u0940"
    ],
    "name:msa_x_preferred":[
        "Beldari"
    ],
    "name:nep_x_preferred":[
        "\u092c\u0947\u0932\u094d\u0926\u093e\u0930\u0940"
    ],
    "name:pol_x_preferred":[
        "Beldari"
    ],
    "wof:name":"Beldari",
    "wof:placetype":"locality"
},
  "geometry": {"coordinates":[85.05051999999998,26.8602],"type":"Point"}
}