{
  "type": "Feature",
  "properties": {
    "gn:admin1_code":"WR",
    "gn:admin2_code":"8",
    "gn:admin3_code":"46.0",
    "gn:admin4_code":"460039.0",
    "gn:asciiname":"Dhandgairagaun",
    "gn:country_code":"NP",
    "gn:dem":773,
    "gn:feature_class":"P",
    "gn:feature_code":"PPLL",
    "gn:name":"Dhandgairagaun",
    "gn:population":0,
    "gn:timezone":"Asia/Kathmandu",
    "iso:country":"NP",
    "wof:name":"Dhandgairagaun",
    "wof:placetype":"locality"
},
  "geometry": {"coordinates":[83.45568,28.01409],"type":"Point"}
}