{
  "type": "Feature",
  "properties": {
    "gn:admin1_code":"MR",
    "gn:admin2_code":"12",
    "gn:admin3_code":"56.0",
    "gn:admin4_code":"560040.0",
    "gn:asciiname":"Gothikholagaun",
    "gn:country_code":"NP",
    "gn:dem":828,
    "gn:feature_class":"P",
    "gn:feature_code":"PPLL",
    "gn:name":"Gothikholagaun",
    "gn:population":0,
    "gn:timezone":"Asia/Kathmandu",
    "iso:country":"NP",
    "wof:name":"Gothikholagaun",
    "wof:placetype":"locality"
},
  "geometry": {"coordinates":[82.31573,28.18062],"type":"Point"}
}