{
  "type": "Feature",
  "properties": {
    "gn:admin1_code":"ER",
    "gn:admin2_code":"7.0",
    "gn:admin3_code":"8.0",
    "gn:admin4_code":"80007.0",
    "gn:asciiname":"Layamba",
    "gn:country_code":"NP",
    "gn:dem":1266,
    "gn:feature_class":"P",
    "gn:feature_code":"PPLL",
    "gn:name":"Layamba",
    "gn:population":0,
    "gn:timezone":"Asia/Kathmandu",
    "iso:country":"NP",
    "wof:name":"Layamba",
    "wof:placetype":"locality"
},
  "geometry": {"coordinates":[87.60178000000001,27.19194],"type":"Point"}
}