{
  "type": "Feature",
  "properties": {
    "gn:admin1_code":"FR",
    "gn:admin2_code":"9",
    "gn:admin3_code":"73.0",
    "gn:admin4_code":"730003.0",
    "gn:asciiname":"Salyadi",
    "gn:country_code":"NP",
    "gn:dem":1520,
    "gn:feature_class":"P",
    "gn:feature_code":"PPLL",
    "gn:name":"Salyadi",
    "gn:population":0,
    "gn:timezone":"Asia/Kathmandu",
    "iso:country":"NP",
    "wof:name":"Salyadi",
    "wof:placetype":"locality"
},
  "geometry": {"coordinates":[80.59560999999999,29.33642],"type":"Point"}
}