{
  "type": "Feature",
  "properties": {
    "gn:admin1_code":"WR",
    "gn:admin2_code":"3",
    "gn:admin3_code":"44",
    "gn:admin4_code":"440012",
    "gn:asciiname":"Jhilibrang",
    "gn:country_code":"NP",
    "gn:dem":1624,
    "gn:feature_class":"P",
    "gn:feature_code":"PPLL",
    "gn:name":"Jhilibrang",
    "gn:population":0,
    "gn:timezone":"Asia/Kathmandu",
    "iso:country":"NP",
    "wof:name":"Jhilibrang",
    "wof:placetype":"locality"
},
  "geometry": {"coordinates":[83.73314999999999,28.34114000000001],"type":"Point"}
}