{
  "type": "Feature",
  "properties": {
    "gn:admin1_code":"WR",
    "gn:admin2_code":"4.0",
    "gn:admin3_code":"39.0",
    "gn:admin4_code":"390052.0",
    "gn:asciiname":"Balam Jaipate",
    "gn:country_code":"NP",
    "gn:dem":796,
    "gn:feature_class":"P",
    "gn:feature_code":"PPLL",
    "gn:name":"Balam Jaipate",
    "gn:population":0,
    "gn:timezone":"Asia/Kathmandu",
    "iso:country":"NP",
    "wof:name":"Balam Jaipate",
    "wof:placetype":"locality"
},
  "geometry": {"coordinates":[83.61098,27.94902],"type":"Point"}
}