{
  "type": "Feature",
  "properties": {
    "gn:admin1_code":"ER",
    "gn:admin2_code":"10.0",
    "gn:admin3_code":"1.0",
    "gn:admin4_code":"10038.0",
    "gn:asciiname":"Sawandin",
    "gn:country_code":"NP",
    "gn:dem":1505,
    "gn:feature_class":"P",
    "gn:feature_code":"PPLL",
    "gn:name":"Sawandin",
    "gn:population":0,
    "gn:timezone":"Asia/Kathmandu",
    "iso:country":"NP",
    "wof:name":"Sawandin",
    "wof:placetype":"locality"
},
  "geometry": {"coordinates":[87.68809,27.43226],"type":"Point"}
}