{
  "type": "Feature",
  "properties": {
    "gn:admin1_code":"WR",
    "gn:admin2_code":"3",
    "gn:admin3_code":"45",
    "gn:admin4_code":"450059",
    "gn:asciiname":"Kholakharka",
    "gn:country_code":"NP",
    "gn:dem":2702,
    "gn:feature_class":"P",
    "gn:feature_code":"PPLL",
    "gn:name":"Kholakharka",
    "gn:population":0,
    "gn:timezone":"Asia/Kathmandu",
    "iso:country":"NP",
    "wof:name":"Kholakharka",
    "wof:placetype":"locality"
},
  "geometry": {"coordinates":[83.29330999999998,28.33129000000001],"type":"Point"}
}