{
  "type": "Feature",
  "properties": {
    "gn:admin1_code":"WR",
    "gn:admin2_code":"3",
    "gn:admin3_code":"44",
    "gn:admin4_code":"440039",
    "gn:asciiname":"Nalekharka",
    "gn:country_code":"NP",
    "gn:dem":1347,
    "gn:feature_class":"P",
    "gn:feature_code":"PPLL",
    "gn:name":"Nalekharka",
    "gn:population":0,
    "gn:timezone":"Asia/Kathmandu",
    "iso:country":"NP",
    "wof:name":"Nalekharka",
    "wof:placetype":"locality"
},
  "geometry": {"coordinates":[83.6999,28.09792],"type":"Point"}
}