{
  "type": "Feature",
  "properties": {
    "gn:admin1_code":"WR",
    "gn:admin2_code":"8",
    "gn:admin3_code":"48",
    "gn:admin4_code":"480038",
    "gn:asciiname":"Chisapni",
    "gn:country_code":"NP",
    "gn:dem":120,
    "gn:feature_class":"P",
    "gn:feature_code":"PPLL",
    "gn:name":"Chisapni",
    "gn:population":0,
    "gn:timezone":"Asia/Kathmandu",
    "iso:country":"NP",
    "wof:name":"Chisapni",
    "wof:placetype":"locality"
},
  "geometry": {"coordinates":[83.77353000000002,27.55037],"type":"Point"}
}