{
  "type": "Feature",
  "properties": {
    "gn:admin1_code":"FR",
    "gn:admin2_code":"9",
    "gn:admin3_code":"72.0",
    "gn:admin4_code":"720011.0",
    "gn:asciiname":"Lamsar",
    "gn:country_code":"NP",
    "gn:dem":224,
    "gn:feature_class":"P",
    "gn:feature_code":"PPLL",
    "gn:name":"Lamsar",
    "gn:population":0,
    "gn:timezone":"Asia/Kathmandu",
    "iso:country":"NP",
    "wof:name":"Lamsar",
    "wof:placetype":"locality"
},
  "geometry": {"coordinates":[80.12621999999998,28.98972],"type":"Point"}
}