{
  "type": "Feature",
  "properties": {
    "gn:admin1_code":"MR",
    "gn:admin2_code":"2.0",
    "gn:admin3_code":"57.0",
    "gn:admin4_code":"570037.0",
    "gn:asciiname":"Jodhapurwa",
    "gn:country_code":"NP",
    "gn:dem":153,
    "gn:feature_class":"P",
    "gn:feature_code":"PPLL",
    "gn:name":"Jodhapurwa",
    "gn:population":0,
    "gn:timezone":"Asia/Kathmandu",
    "iso:country":"NP",
    "wof:name":"Jodhapurwa",
    "wof:placetype":"locality"
},
  "geometry": {"coordinates":[81.67585,28.05916],"type":"Point"}
}