{
  "type": "Feature",
  "properties": {
    "gn:admin1_code":"MR",
    "gn:admin2_code":"12",
    "gn:admin3_code":"52",
    "gn:admin4_code":"520045",
    "gn:asciiname":"Totke",
    "gn:country_code":"NP",
    "gn:dem":2104,
    "gn:feature_class":"P",
    "gn:feature_code":"PPLL",
    "gn:name":"Totke",
    "gn:population":0,
    "gn:timezone":"Asia/Kathmandu",
    "iso:country":"NP",
    "wof:name":"Totke",
    "wof:placetype":"locality"
},
  "geometry": {"coordinates":[82.93664,28.32489],"type":"Point"}
}