{
  "type": "Feature",
  "properties": {
    "gn:admin1_code":"WR",
    "gn:admin2_code":"4",
    "gn:admin3_code":"40.0",
    "gn:admin4_code":"400023.0",
    "gn:asciiname":"Tirlung",
    "gn:country_code":"NP",
    "gn:dem":1662,
    "gn:feature_class":"P",
    "gn:feature_code":"PPLL",
    "gn:name":"Tirlung",
    "gn:population":0,
    "gn:timezone":"Asia/Kathmandu",
    "iso:country":"NP",
    "wof:name":"Tirlung",
    "wof:placetype":"locality"
},
  "geometry": {"coordinates":[83.82106999999998,28.35351],"type":"Point"}
}