{
  "type": "Feature",
  "properties": {
    "gn:admin1_code":"FR",
    "gn:admin2_code":"9",
    "gn:admin3_code":"74",
    "gn:admin4_code":"740026",
    "gn:asciiname":"Kalauna",
    "gn:country_code":"NP",
    "gn:dem":1370,
    "gn:feature_class":"P",
    "gn:feature_code":"PPLL",
    "gn:name":"Kalauna",
    "gn:population":0,
    "gn:timezone":"Asia/Kathmandu",
    "iso:country":"NP",
    "wof:name":"Kalauna",
    "wof:placetype":"locality"
},
  "geometry": {"coordinates":[80.49476,29.57113],"type":"Point"}
}