{
  "type": "Feature",
  "properties": {
    "gn:admin1_code":"WR",
    "gn:admin2_code":"3",
    "gn:admin3_code":"43",
    "gn:admin4_code":"430003",
    "gn:asciiname":"Simalchaur",
    "gn:country_code":"NP",
    "gn:dem":1173,
    "gn:feature_class":"P",
    "gn:feature_code":"PPLL",
    "gn:name":"Simalchaur",
    "gn:population":0,
    "gn:timezone":"Asia/Kathmandu",
    "iso:country":"NP",
    "wof:name":"Simalchaur",
    "wof:placetype":"locality"
},
  "geometry": {"coordinates":[83.49144,28.38054],"type":"Point"}
}