{
  "type": "Feature",
  "properties": {
    "gn:admin1_code":"MR",
    "gn:admin2_code":"6",
    "gn:admin3_code":"65",
    "gn:admin4_code":"650022",
    "gn:asciiname":"Jogi Lek",
    "gn:country_code":"NP",
    "gn:dem":2334,
    "gn:feature_class":"P",
    "gn:feature_code":"PPLL",
    "gn:name":"Jogi Lek",
    "gn:population":0,
    "gn:timezone":"Asia/Kathmandu",
    "iso:country":"NP",
    "wof:name":"Jogi Lek",
    "wof:placetype":"locality"
},
  "geometry": {"coordinates":[81.92912,29.53398],"type":"Point"}
}