{
  "type": "Feature",
  "properties": {
    "gn:admin1_code":"ER",
    "gn:admin2_code":"13",
    "gn:admin3_code":"11",
    "gn:admin4_code":"110029",
    "gn:asciiname":"Dansi",
    "gn:country_code":"NP",
    "gn:dem":2093,
    "gn:feature_class":"P",
    "gn:feature_code":"PPLL",
    "gn:name":"Dansi",
    "gn:population":0,
    "gn:timezone":"Asia/Kathmandu",
    "iso:country":"NP",
    "wof:name":"Dansi",
    "wof:placetype":"locality"
},
  "geometry": {"coordinates":[86.57817,27.49702000000001],"type":"Point"}
}