{
  "type": "Feature",
  "properties": {
    "gn:admin1_code":"WR",
    "gn:admin2_code":"4",
    "gn:admin3_code":"36.0",
    "gn:admin4_code":"360027.0",
    "gn:asciiname":"Baltar",
    "gn:country_code":"NP",
    "gn:dem":389,
    "gn:feature_class":"P",
    "gn:feature_code":"PPLL",
    "gn:name":"Baltar",
    "gn:population":0,
    "gn:timezone":"Asia/Kathmandu",
    "iso:country":"NP",
    "name:ceb_x_preferred":[
        "Baltar"
    ],
    "name:deu_x_preferred":[
        "Baltar"
    ],
    "name:epo_x_preferred":[
        "Baltar"
    ],
    "name:fra_x_preferred":[
        "Baltar"
    ],
    "name:glg_x_preferred":[
        "Baltar"
    ],
    "name:por_x_preferred":[
        "Baltar"
    ],
    "name:rus_x_preferred":[
        "\u0411\u0430\u043b\u0442\u0430\u0440"
    ],
    "name:spa_x_preferred":[
        "Baltar"
    ],
    "name:swe_x_preferred":[
        "Baltar"
    ],
    "wof:name":"Baltar",
    "wof:placetype":"locality"
},
  "geometry": {"coordinates":[84.73459,27.80677],"type":"Point"}
}