{
  "type": "Feature",
  "properties": {
    "gn:admin1_code":"CR",
    "gn:admin2_code":"1",
    "gn:admin3_code":"30.0",
    "gn:admin4_code":"300018.0",
    "gn:asciiname":"Takthali",
    "gn:country_code":"NP",
    "gn:dem":874,
    "gn:feature_class":"P",
    "gn:feature_code":"PPLL",
    "gn:name":"Takthali",
    "gn:population":0,
    "gn:timezone":"Asia/Kathmandu",
    "iso:country":"NP",
    "wof:name":"Takthali",
    "wof:placetype":"locality"
},
  "geometry": {"coordinates":[84.66322,27.80347],"type":"Point"}
}