{
  "type": "Feature",
  "properties": {
    "gn:admin1_code":"FR",
    "gn:admin2_code":"14",
    "gn:admin3_code":"71.0",
    "gn:admin4_code":"710038.0",
    "gn:asciiname":"Bayala",
    "gn:country_code":"NP",
    "gn:dem":1231,
    "gn:feature_class":"P",
    "gn:feature_code":"PPLL",
    "gn:name":"Bayala",
    "gn:population":0,
    "gn:timezone":"Asia/Kathmandu",
    "iso:country":"NP",
    "name:bih_x_preferred":[
        "\u092c\u092f\u093e\u0932\u093e"
    ],
    "name:ceb_x_preferred":[
        "Bayala"
    ],
    "name:fra_x_preferred":[
        "Bayala"
    ],
    "name:mai_x_preferred":[
        "\u092c\u092f\u093e\u0932\u093e"
    ],
    "name:msa_x_preferred":[
        "Bayala"
    ],
    "name:nep_x_preferred":[
        "\u092c\u092f\u093e\u0932\u093e"
    ],
    "name:pol_x_preferred":[
        "Bayala"
    ],
    "wof:name":"Bayala",
    "wof:placetype":"locality"
},
  "geometry": {"coordinates":[80.60164,29.0418],"type":"Point"}
}