{
  "type": "Feature",
  "properties": {
    "gn:admin1_code":"ER",
    "gn:admin2_code":"13",
    "gn:admin3_code":"13.0",
    "gn:admin4_code":"130038.0",
    "gn:asciiname":"Sabru",
    "gn:country_code":"NP",
    "gn:dem":1443,
    "gn:feature_class":"P",
    "gn:feature_code":"PPLL",
    "gn:name":"Sabru",
    "gn:population":0,
    "gn:timezone":"Asia/Kathmandu",
    "iso:country":"NP",
    "wof:name":"Sabru",
    "wof:placetype":"locality"
},
  "geometry": {"coordinates":[86.79685000000001,27.30351],"type":"Point"}
}