{
  "type": "Feature",
  "properties": {
    "gn:admin1_code":"MR",
    "gn:admin2_code":"12",
    "gn:admin3_code":"55",
    "gn:admin4_code":"550009",
    "gn:asciiname":"Amalapani",
    "gn:country_code":"NP",
    "gn:dem":1385,
    "gn:feature_class":"P",
    "gn:feature_code":"PPLL",
    "gn:name":"Amalapani",
    "gn:population":0,
    "gn:timezone":"Asia/Kathmandu",
    "iso:country":"NP",
    "wof:name":"Amalapani",
    "wof:placetype":"locality"
},
  "geometry": {"coordinates":[82.19983000000001,28.41711],"type":"Point"}
}