{
  "type": "Feature",
  "properties": {
    "gn:admin1_code":"WR",
    "gn:admin2_code":"4",
    "gn:admin3_code":"36.0",
    "gn:admin4_code":"360010.0",
    "gn:asciiname":"Ranagaun",
    "gn:country_code":"NP",
    "gn:dem":2344,
    "gn:feature_class":"P",
    "gn:feature_code":"PPLL",
    "gn:name":"Ranagaun",
    "gn:population":0,
    "gn:timezone":"Asia/Kathmandu",
    "iso:country":"NP",
    "name:msa_x_preferred":[
        "Ranagau"
    ],
    "name:new_x_preferred":[
        "\u0930\u093e\u0928\u093e\u0917\u093e\u0909\u0902"
    ],
    "name:pol_x_preferred":[
        "Ranagau"
    ],
    "wof:name":"Ranagaun",
    "wof:placetype":"locality"
},
  "geometry": {"coordinates":[84.87299999999998,28.49978],"type":"Point"}
}