{
  "type": "Feature",
  "properties": {
    "gn:admin1_code":"WR",
    "gn:admin2_code":"4",
    "gn:admin3_code":"37",
    "gn:admin4_code":"370035",
    "gn:asciiname":"Kalyanbesi",
    "gn:country_code":"NP",
    "gn:dem":717,
    "gn:feature_class":"P",
    "gn:feature_code":"PPLL",
    "gn:name":"Kalyanbesi",
    "gn:population":0,
    "gn:timezone":"Asia/Kathmandu",
    "iso:country":"NP",
    "wof:name":"Kalyanbesi",
    "wof:placetype":"locality"
},
  "geometry": {"coordinates":[84.21549,28.18773],"type":"Point"}
}