{
  "type": "Feature",
  "properties": {
    "gn:admin1_code":"WR",
    "gn:admin2_code":"4",
    "gn:admin3_code":"37",
    "gn:admin4_code":"370027",
    "gn:asciiname":"Bohoragaun",
    "gn:country_code":"NP",
    "gn:dem":852,
    "gn:feature_class":"P",
    "gn:feature_code":"PPLL",
    "gn:name":"Bohoragaun",
    "gn:population":0,
    "gn:timezone":"Asia/Kathmandu",
    "iso:country":"NP",
    "wof:name":"Bohoragaun",
    "wof:placetype":"locality"
},
  "geometry": {"coordinates":[84.38835,28.21254],"type":"Point"}
}