{
  "type": "Feature",
  "properties": {
    "gn:admin1_code":"CR",
    "gn:admin2_code":"5",
    "gn:admin3_code":"20",
    "gn:admin4_code":"200002.0",
    "gn:asciiname":"Pipale Bhanjyang",
    "gn:country_code":"NP",
    "gn:dem":988,
    "gn:feature_class":"P",
    "gn:feature_code":"PPLL",
    "gn:name":"Pipale Bhanjyang",
    "gn:population":0,
    "gn:timezone":"Asia/Kathmandu",
    "iso:country":"NP",
    "wof:name":"Pipale Bhanjyang",
    "wof:placetype":"locality"
},
  "geometry": {"coordinates":[86.30358000000003,27.03832],"type":"Point"}
}