{
  "type": "Feature",
  "properties": {
    "gn:admin1_code":"FR",
    "gn:admin2_code":"14",
    "gn:admin3_code":"71.0",
    "gn:admin4_code":"710015.0",
    "gn:asciiname":"Tudela",
    "gn:country_code":"NP",
    "gn:dem":249,
    "gn:feature_class":"P",
    "gn:feature_code":"PPLL",
    "gn:name":"Tudela",
    "gn:population":0,
    "gn:timezone":"Asia/Kathmandu",
    "iso:country":"NP",
    "name:cat_x_preferred":[
        "Tudela"
    ],
    "name:ceb_x_preferred":[
        "Tudela"
    ],
    "name:deu_x_preferred":[
        "Tudela"
    ],
    "name:eus_x_preferred":[
        "Tudela"
    ],
    "name:fra_x_preferred":[
        "Tudela"
    ],
    "name:hrv_x_preferred":[
        "Tudela"
    ],
    "name:ita_x_preferred":[
        "Tudela"
    ],
    "name:mlg_x_preferred":[
        "Tudela"
    ],
    "name:nld_x_preferred":[
        "Tudela"
    ],
    "name:spa_x_preferred":[
        "Tudela"
    ],
    "name:war_x_preferred":[
        "Tudela"
    ],
    "wof:name":"Tudela",
    "wof:placetype":"locality"
},
  "geometry": {"coordinates":[80.52378,28.88885],"type":"Point"}
}