{
  "type": "Feature",
  "properties": {
    "gn:admin1_code":"MR",
    "gn:admin2_code":"12",
    "gn:admin3_code":"55",
    "gn:admin4_code":"550032",
    "gn:asciiname":"Sanigade",
    "gn:country_code":"NP",
    "gn:dem":1806,
    "gn:feature_class":"P",
    "gn:feature_code":"PPLL",
    "gn:name":"Sanigade",
    "gn:population":0,
    "gn:timezone":"Asia/Kathmandu",
    "iso:country":"NP",
    "wof:name":"Sanigade",
    "wof:placetype":"locality"
},
  "geometry": {"coordinates":[82.07545,28.38003],"type":"Point"}
}