{
  "type": "Feature",
  "properties": {
    "gn:admin1_code":"WR",
    "gn:admin2_code":"4.0",
    "gn:admin3_code":"38.0",
    "gn:admin4_code":"380039.0",
    "gn:asciiname":"Dal Bhanjyang",
    "gn:country_code":"NP",
    "gn:dem":953,
    "gn:feature_class":"P",
    "gn:feature_code":"PPLL",
    "gn:name":"Dal Bhanjyang",
    "gn:population":0,
    "gn:timezone":"Asia/Kathmandu",
    "iso:country":"NP",
    "wof:name":"Dal Bhanjyang",
    "wof:placetype":"locality"
},
  "geometry": {"coordinates":[84.29709,28.07879],"type":"Point"}
}