{
  "type": "Feature",
  "properties": {
    "gn:admin1_code":"WR",
    "gn:admin2_code":"3",
    "gn:admin3_code":"44",
    "gn:admin4_code":"440034",
    "gn:asciiname":"Sahela",
    "gn:country_code":"NP",
    "gn:dem":815,
    "gn:feature_class":"P",
    "gn:feature_code":"PPLL",
    "gn:name":"Sahela",
    "gn:population":0,
    "gn:timezone":"Asia/Kathmandu",
    "iso:country":"NP",
    "wof:name":"Sahela",
    "wof:placetype":"locality"
},
  "geometry": {"coordinates":[83.67608,28.1646],"type":"Point"}
}