{
  "type": "Feature",
  "properties": {
    "gn:admin1_code":"CR",
    "gn:admin2_code":"1",
    "gn:admin3_code":"24.0",
    "gn:admin4_code":"240029.0",
    "gn:asciiname":"Sirudanda",
    "gn:country_code":"NP",
    "gn:dem":839,
    "gn:feature_class":"P",
    "gn:feature_code":"PPLL",
    "gn:name":"Sirudanda",
    "gn:population":0,
    "gn:timezone":"Asia/Kathmandu",
    "iso:country":"NP",
    "wof:name":"Sirudanda",
    "wof:placetype":"locality"
},
  "geometry": {"coordinates":[85.64034000000002,27.39602],"type":"Point"}
}