{
  "type": "Feature",
  "properties": {
    "gn:admin1_code":"WR",
    "gn:admin2_code":"3",
    "gn:admin3_code":"43",
    "gn:admin4_code":"430032",
    "gn:asciiname":"Rakhu",
    "gn:country_code":"NP",
    "gn:dem":1574,
    "gn:feature_class":"P",
    "gn:feature_code":"PPLL",
    "gn:name":"Rakhu",
    "gn:population":0,
    "gn:timezone":"Asia/Kathmandu",
    "iso:country":"NP",
    "wof:name":"Rakhu",
    "wof:placetype":"locality"
},
  "geometry": {"coordinates":[83.58096999999999,28.39844],"type":"Point"}
}