{
  "type": "Feature",
  "properties": {
    "gn:admin1_code":"CR",
    "gn:admin2_code":"1",
    "gn:admin3_code":"28",
    "gn:admin4_code":"280038",
    "gn:asciiname":"Chihandanda",
    "gn:country_code":"NP",
    "gn:dem":921,
    "gn:feature_class":"P",
    "gn:feature_code":"PPLL",
    "gn:name":"Chihandanda",
    "gn:population":0,
    "gn:timezone":"Asia/Kathmandu",
    "iso:country":"NP",
    "wof:name":"Chihandanda",
    "wof:placetype":"locality"
},
  "geometry": {"coordinates":[85.21375999999999,27.84163],"type":"Point"}
}