{
  "type": "Feature",
  "properties": {
    "gn:admin1_code":"CR",
    "gn:admin2_code":"11.0",
    "gn:admin3_code":"33.0",
    "gn:admin4_code":"330064.0",
    "gn:asciiname":"Badaharuwa",
    "gn:country_code":"NP",
    "gn:dem":127,
    "gn:feature_class":"P",
    "gn:feature_code":"PPLL",
    "gn:name":"Badaharuwa",
    "gn:population":0,
    "gn:timezone":"Asia/Kathmandu",
    "iso:country":"NP",
    "wof:name":"Badaharuwa",
    "wof:placetype":"locality"
},
  "geometry": {"coordinates":[85.05155000000001,27.12764],"type":"Point"}
}