{
  "type": "Feature",
  "properties": {
    "gn:admin1_code":"CR",
    "gn:admin2_code":"1",
    "gn:admin3_code":"25",
    "gn:admin4_code":"250006",
    "gn:asciiname":"Todkedanda",
    "gn:country_code":"NP",
    "gn:dem":1735,
    "gn:feature_class":"P",
    "gn:feature_code":"PPLL",
    "gn:name":"Todkedanda",
    "gn:population":0,
    "gn:timezone":"Asia/Kathmandu",
    "iso:country":"NP",
    "wof:name":"Todkedanda",
    "wof:placetype":"locality"
},
  "geometry": {"coordinates":[85.34984,27.4853],"type":"Point"}
}