{
  "type": "Feature",
  "properties": {
    "gn:admin1_code":"FR",
    "gn:admin2_code":"14",
    "gn:admin3_code":"71.0",
    "gn:admin4_code":"710008.0",
    "gn:asciiname":"Khakraula",
    "gn:country_code":"NP",
    "gn:dem":145,
    "gn:feature_class":"P",
    "gn:feature_code":"PPLL",
    "gn:name":"Khakraula",
    "gn:population":0,
    "gn:timezone":"Asia/Kathmandu",
    "iso:country":"NP",
    "wof:name":"Khakraula",
    "wof:placetype":"locality"
},
  "geometry": {"coordinates":[81.03676,28.43979],"type":"Point"}
}