{
  "type": "Feature",
  "properties": {
    "gn:admin1_code":"MR",
    "gn:admin2_code":"12",
    "gn:admin3_code":"52",
    "gn:admin4_code":"520018",
    "gn:asciiname":"Hapurkholagaun",
    "gn:country_code":"NP",
    "gn:dem":960,
    "gn:feature_class":"P",
    "gn:feature_code":"PPLL",
    "gn:name":"Hapurkholagaun",
    "gn:population":0,
    "gn:timezone":"Asia/Kathmandu",
    "iso:country":"NP",
    "wof:name":"Hapurkholagaun",
    "wof:placetype":"locality"
},
  "geometry": {"coordinates":[82.85069,27.99601],"type":"Point"}
}