{
  "type": "Feature",
  "properties": {
    "gn:admin1_code":"CR",
    "gn:admin2_code":"1",
    "gn:admin3_code":"28",
    "gn:admin4_code":"280008",
    "gn:asciiname":"Devighat Koloni",
    "gn:country_code":"NP",
    "gn:dem":539,
    "gn:feature_class":"P",
    "gn:feature_code":"PPLL",
    "gn:name":"Devighat Koloni",
    "gn:population":0,
    "gn:timezone":"Asia/Kathmandu",
    "iso:country":"NP",
    "wof:name":"Devighat Koloni",
    "wof:placetype":"locality"
},
  "geometry": {"coordinates":[85.13919,27.89778],"type":"Point"}
}