{
  "type": "Feature",
  "properties": {
    "gn:admin1_code":"FR",
    "gn:admin2_code":"14.0",
    "gn:admin3_code":"67.0",
    "gn:admin4_code":"670019.0",
    "gn:asciiname":"Chamdayo",
    "gn:country_code":"NP",
    "gn:dem":2436,
    "gn:feature_class":"P",
    "gn:feature_code":"PPLL",
    "gn:name":"Chamdayo",
    "gn:population":0,
    "gn:timezone":"Asia/Kathmandu",
    "iso:country":"NP",
    "wof:name":"Chamdayo",
    "wof:placetype":"locality"
},
  "geometry": {"coordinates":[81.58484,29.51893],"type":"Point"}
}