{
  "type": "Feature",
  "properties": {
    "gn:admin1_code":"WR",
    "gn:admin2_code":"8",
    "gn:admin3_code":"48",
    "gn:admin4_code":"480056",
    "gn:asciiname":"Kunawar",
    "gn:country_code":"NP",
    "gn:dem":114,
    "gn:feature_class":"P",
    "gn:feature_code":"PPLL",
    "gn:name":"Kunawar",
    "gn:population":0,
    "gn:timezone":"Asia/Kathmandu",
    "iso:country":"NP",
    "wof:name":"Kunawar",
    "wof:placetype":"locality"
},
  "geometry": {"coordinates":[83.69466,27.53132],"type":"Point"}
}