{
  "type": "Feature",
  "properties": {
    "gn:admin1_code":"MR",
    "gn:admin2_code":"6",
    "gn:admin3_code":"64.0",
    "gn:admin4_code":"640023.0",
    "gn:asciiname":"Bhanka",
    "gn:country_code":"NP",
    "gn:dem":1569,
    "gn:feature_class":"P",
    "gn:feature_code":"PPLL",
    "gn:name":"Bhanka",
    "gn:population":0,
    "gn:timezone":"Asia/Kathmandu",
    "iso:country":"NP",
    "wof:name":"Bhanka",
    "wof:placetype":"locality"
},
  "geometry": {"coordinates":[81.71469999999999,29.24866],"type":"Point"}
}