{
  "type": "Feature",
  "properties": {
    "gn:admin1_code":"MR",
    "gn:admin2_code":"6",
    "gn:admin3_code":"66.0",
    "gn:admin4_code":"660014.0",
    "gn:asciiname":"Tamra",
    "gn:country_code":"NP",
    "gn:dem":1211,
    "gn:feature_class":"P",
    "gn:feature_code":"PPLL",
    "gn:name":"Tamra",
    "gn:population":0,
    "gn:timezone":"Asia/Kathmandu",
    "iso:country":"NP",
    "name:ara_x_preferred":[
        "\u0637\u0645\u0631\u0629"
    ],
    "name:cat_x_preferred":[
        "Tamra"
    ],
    "name:ceb_x_preferred":[
        "Tamra"
    ],
    "name:ces_x_preferred":[
        "Tamra"
    ],
    "name:deu_x_preferred":[
        "Tamra"
    ],
    "name:fas_x_preferred":[
        "\u0637\u0645\u0631\u0647"
    ],
    "name:fra_x_preferred":[
        "Tamra"
    ],
    "name:heb_x_preferred":[
        "\u05d8\u05de\u05e8\u05d4"
    ],
    "name:ind_x_preferred":[
        "Tamra"
    ],
    "name:ita_x_preferred":[
        "Tamra"
    ],
    "name:kat_x_preferred":[
        "\u10e2\u10d0\u10db\u10e0\u10d0"
    ],
    "name:nld_x_preferred":[
        "Tamra"
    ],
    "name:nno_x_preferred":[
        "Tamra"
    ],
    "name:nor_x_preferred":[
        "Tamra"
    ],
    "name:pol_x_preferred":[
        "Tamra"
    ],
    "name:por_x_preferred":[
        "Tamra"
    ],
    "name:ron_x_preferred":[
        "Tamra"
    ],
    "name:rus_x_preferred":[
        "\u0422\u0430\u043c\u0440\u0430"
    ],
    "name:sco_x_preferred":[
        "Tamra"
    ],
    "name:spa_x_preferred":[
        "Tamra"
    ],
    "name:swe_x_preferred":[
        "Tamra"
    ],
    "name:tam_x_preferred":[
        "\u0ba4\u0bae\u0bcd\u0bb0\u0bbe"
    ],
    "name:tgl_x_preferred":[
        "Tamra"
    ],
    "name:urd_x_preferred":[
        "\u0637\u0645\u0631\u06c1"
    ],
    "name:vie_x_preferred":[
        "Tamra"
    ],
    "name:yid_x_preferred":[
        "\u05d8\u05de\u05e8\u05d4"
    ],
    "name:zho_x_preferred":[
        "\u5854\u59c6\u62c9"
    ],
    "wof:name":"Tamra",
    "wof:placetype":"locality"
},
  "geometry": {"coordinates":[81.78959999999999,29.62652000000001],"type":"Point"}
}