{
  "type": "Feature",
  "properties": {
    "gn:admin1_code":"MR",
    "gn:admin2_code":"6",
    "gn:admin3_code":"66.0",
    "gn:admin4_code":"660014.0",
    "gn:asciiname":"Tamra",
    "gn:country_code":"NP",
    "gn:dem":1211,
    "gn:feature_class":"P",
    "gn:feature_code":"PPLL",
    "gn:name":"Tamra",
    "gn:population":0,
    "gn:timezone":"Asia/Kathmandu",
    "iso:country":"NP",
    "wof:name":"Tamra",
    "wof:placetype":"locality"
},
  "geometry": {"coordinates":[81.78959999999999,29.62652000000001],"type":"Point"}
}