{
  "type": "Feature",
  "properties": {
    "gn:admin1_code":"FR",
    "gn:admin2_code":"14.0",
    "gn:admin3_code":"69.0",
    "gn:admin4_code":"690044.0",
    "gn:asciiname":"Patane",
    "gn:country_code":"NP",
    "gn:dem":794,
    "gn:feature_class":"P",
    "gn:feature_code":"PPLL",
    "gn:name":"Patane",
    "gn:population":0,
    "gn:timezone":"Asia/Kathmandu",
    "iso:country":"NP",
    "wof:name":"Patane",
    "wof:placetype":"locality"
},
  "geometry": {"coordinates":[81.4482,29.08336],"type":"Point"}
}