{
  "type": "Feature",
  "properties": {
    "gn:admin1_code":"CR",
    "gn:admin2_code":"5",
    "gn:admin3_code":"17.0",
    "gn:admin4_code":"170080.0",
    "gn:asciiname":"Chaukitol",
    "gn:country_code":"NP",
    "gn:dem":133,
    "gn:feature_class":"P",
    "gn:feature_code":"PPLL",
    "gn:name":"Chaukitol",
    "gn:population":0,
    "gn:timezone":"Asia/Kathmandu",
    "iso:country":"NP",
    "wof:name":"Chaukitol",
    "wof:placetype":"locality"
},
  "geometry": {"coordinates":[85.97277,26.87837],"type":"Point"}
}