{
  "type": "Feature",
  "properties": {
    "gn:admin1_code":"FR",
    "gn:admin2_code":"9",
    "gn:admin3_code":"75.0",
    "gn:admin4_code":"750026.0",
    "gn:asciiname":"Bitaura",
    "gn:country_code":"NP",
    "gn:dem":1239,
    "gn:feature_class":"P",
    "gn:feature_code":"PPLL",
    "gn:name":"Bitaura",
    "gn:population":0,
    "gn:timezone":"Asia/Kathmandu",
    "iso:country":"NP",
    "wof:name":"Bitaura",
    "wof:placetype":"locality"
},
  "geometry": {"coordinates":[80.45693,29.63731],"type":"Point"}
}