{
  "type": "Feature",
  "properties": {
    "gn:admin1_code":"WR",
    "gn:admin2_code":"3",
    "gn:admin3_code":"45.0",
    "gn:admin4_code":"450030.0",
    "gn:asciiname":"Charaundi",
    "gn:country_code":"NP",
    "gn:dem":1301,
    "gn:feature_class":"P",
    "gn:feature_code":"PPLL",
    "gn:name":"Charaundi",
    "gn:population":0,
    "gn:timezone":"Asia/Kathmandu",
    "iso:country":"NP",
    "name:pol_x_preferred":[
        "Charaundi"
    ],
    "wof:name":"Charaundi",
    "wof:placetype":"locality"
},
  "geometry": {"coordinates":[83.43281,28.22628],"type":"Point"}
}