{
  "type": "Feature",
  "properties": {
    "gn:admin1_code":"ER",
    "gn:admin2_code":"10.0",
    "gn:admin3_code":"1.0",
    "gn:admin4_code":"10018.0",
    "gn:asciiname":"Pawa",
    "gn:country_code":"NP",
    "gn:dem":1690,
    "gn:feature_class":"P",
    "gn:feature_code":"PPLL",
    "gn:name":"Pawa",
    "gn:population":0,
    "gn:timezone":"Asia/Kathmandu",
    "iso:country":"NP",
    "name:ceb_x_preferred":[
        "Pawa"
    ],
    "name:deu_x_preferred":[
        "Pawa"
    ],
    "wof:name":"Pawa",
    "wof:placetype":"locality"
},
  "geometry": {"coordinates":[87.59804,27.40058],"type":"Point"}
}