{
  "type": "Feature",
  "properties": {
    "gn:admin1_code":"CR",
    "gn:admin2_code":"5",
    "gn:admin3_code":"22.0",
    "gn:admin4_code":"220036.0",
    "gn:asciiname":"Aunse",
    "gn:country_code":"NP",
    "gn:dem":1372,
    "gn:feature_class":"P",
    "gn:feature_code":"PPLL",
    "gn:name":"Aunse",
    "gn:population":0,
    "gn:timezone":"Asia/Kathmandu",
    "iso:country":"NP",
    "wof:name":"Aunse",
    "wof:placetype":"locality"
},
  "geometry": {"coordinates":[86.00163000000001,27.66646],"type":"Point"}
}