{
  "type": "Feature",
  "properties": {
    "gn:admin1_code":"FR",
    "gn:admin2_code":"14",
    "gn:admin3_code":"71.0",
    "gn:admin4_code":"710030.0",
    "gn:asciiname":"Kapra",
    "gn:country_code":"NP",
    "gn:dem":990,
    "gn:feature_class":"P",
    "gn:feature_code":"PPLL",
    "gn:name":"Kapra",
    "gn:population":0,
    "gn:timezone":"Asia/Kathmandu",
    "iso:country":"NP",
    "wof:name":"Kapra",
    "wof:placetype":"locality"
},
  "geometry": {"coordinates":[80.98721999999999,28.91255],"type":"Point"}
}