{
  "type": "Feature",
  "properties": {
    "gn:admin1_code":"WR",
    "gn:admin2_code":"4.0",
    "gn:admin3_code":"39.0",
    "gn:admin4_code":"390038.0",
    "gn:asciiname":"Gejha",
    "gn:country_code":"NP",
    "gn:dem":765,
    "gn:feature_class":"P",
    "gn:feature_code":"PPLL",
    "gn:name":"Gejha",
    "gn:population":0,
    "gn:timezone":"Asia/Kathmandu",
    "iso:country":"NP",
    "name:ceb_x_preferred":[
        "Gejha"
    ],
    "name:msa_x_preferred":[
        "Gegha"
    ],
    "name:pol_x_preferred":[
        "Gejha"
    ],
    "wof:name":"Gejha",
    "wof:placetype":"locality"
},
  "geometry": {"coordinates":[83.73254,27.92579000000001],"type":"Point"}
}