{
  "type": "Feature",
  "properties": {
    "gn:admin1_code":"00",
    "gn:asciiname":"Lamabagar",
    "gn:country_code":"NP",
    "gn:dem":2004,
    "gn:feature_class":"P",
    "gn:feature_code":"PPL",
    "gn:name":"L\u0101m\u0101bagar",
    "gn:population":0,
    "gn:timezone":"Asia/Kathmandu",
    "iso:country":"NP",
    "name:und_x_variant":[
        "L\u0101mobagar",
        "L\u0101m\u0101bagar"
    ],
    "wof:name":"Lamabagar",
    "wof:placetype":"locality"
},
  "geometry": {"coordinates":[86.21104,27.9131],"type":"Point"}
}