{
  "type": "Feature",
  "properties": {
    "gn:admin1_code":"MR",
    "gn:admin2_code":"2",
    "gn:admin3_code":"61.0",
    "gn:admin4_code":"610021.0",
    "gn:asciiname":"Goganpani",
    "gn:country_code":"NP",
    "gn:dem":1003,
    "gn:feature_class":"P",
    "gn:feature_code":"PPLL",
    "gn:name":"Goganpani",
    "gn:population":0,
    "gn:timezone":"Asia/Kathmandu",
    "iso:country":"NP",
    "name:pol_x_preferred":[
        "Goganpani"
    ],
    "wof:name":"Goganpani",
    "wof:placetype":"locality"
},
  "geometry": {"coordinates":[82.12133,28.68967],"type":"Point"}
}