{
  "type": "Feature",
  "properties": {
    "gn:admin1_code":"CR",
    "gn:admin2_code":"5",
    "gn:admin3_code":"21",
    "gn:admin4_code":"210023",
    "gn:asciiname":"Dangdunge",
    "gn:country_code":"NP",
    "gn:dem":2216,
    "gn:feature_class":"P",
    "gn:feature_code":"PPLL",
    "gn:name":"Dangdunge",
    "gn:population":0,
    "gn:timezone":"Asia/Kathmandu",
    "iso:country":"NP",
    "wof:name":"Dangdunge",
    "wof:placetype":"locality"
},
  "geometry": {"coordinates":[86.26478,27.51225],"type":"Point"}
}