{
  "type": "Feature",
  "properties": {
    "gn:admin1_code":"FR",
    "gn:admin2_code":"14",
    "gn:admin3_code":"69.0",
    "gn:admin4_code":"690061.0",
    "gn:asciiname":"Kakarsand",
    "gn:country_code":"NP",
    "gn:dem":688,
    "gn:feature_class":"P",
    "gn:feature_code":"PPLL",
    "gn:name":"Kakarsand",
    "gn:population":0,
    "gn:timezone":"Asia/Kathmandu",
    "iso:country":"NP",
    "wof:name":"Kakarsand",
    "wof:placetype":"locality"
},
  "geometry": {"coordinates":[81.21118,29.20778],"type":"Point"}
}