{
  "type": "Feature",
  "properties": {
    "gn:admin1_code":"CR",
    "gn:admin2_code":"5",
    "gn:admin3_code":"19",
    "gn:admin4_code":"190019",
    "gn:asciiname":"Mandilawatol",
    "gn:country_code":"NP",
    "gn:dem":88,
    "gn:feature_class":"P",
    "gn:feature_code":"PPLL",
    "gn:name":"Mandilawatol",
    "gn:population":0,
    "gn:timezone":"Asia/Kathmandu",
    "iso:country":"NP",
    "wof:name":"Mandilawatol",
    "wof:placetype":"locality"
},
  "geometry": {"coordinates":[85.43818,26.92809],"type":"Point"}
}