{
  "type": "Feature",
  "properties": {
    "gn:admin1_code":"CR",
    "gn:admin2_code":"5",
    "gn:admin3_code":"22.0",
    "gn:admin4_code":"220024.0",
    "gn:asciiname":"Kuthame",
    "gn:country_code":"NP",
    "gn:dem":2333,
    "gn:feature_class":"P",
    "gn:feature_code":"PPLL",
    "gn:name":"Kuthame",
    "gn:population":0,
    "gn:timezone":"Asia/Kathmandu",
    "iso:country":"NP",
    "wof:name":"Kuthame",
    "wof:placetype":"locality"
},
  "geometry": {"coordinates":[86.25444,27.61548],"type":"Point"}
}