{
  "type": "Feature",
  "properties": {
    "gn:admin1_code":"WR",
    "gn:admin2_code":"4",
    "gn:admin3_code":"37",
    "gn:admin4_code":"370039",
    "gn:asciiname":"Kalaichi",
    "gn:country_code":"NP",
    "gn:dem":1258,
    "gn:feature_class":"P",
    "gn:feature_code":"PPLL",
    "gn:name":"Kalaichi",
    "gn:population":0,
    "gn:timezone":"Asia/Kathmandu",
    "iso:country":"NP",
    "wof:name":"Kalaichi",
    "wof:placetype":"locality"
},
  "geometry": {"coordinates":[84.28626,28.24855],"type":"Point"}
}