{
  "type": "Feature",
  "properties": {
    "gn:admin1_code":"ER",
    "gn:admin2_code":"7",
    "gn:admin3_code":"5",
    "gn:admin4_code":"50012",
    "gn:asciiname":"Arubotte",
    "gn:country_code":"NP",
    "gn:dem":1411,
    "gn:feature_class":"P",
    "gn:feature_code":"PPLL",
    "gn:name":"Arubotte",
    "gn:population":0,
    "gn:timezone":"Asia/Kathmandu",
    "iso:country":"NP",
    "wof:name":"Arubotte",
    "wof:placetype":"locality"
},
  "geometry": {"coordinates":[87.4573,26.81274],"type":"Point"}
}