{
  "type": "Feature",
  "properties": {
    "gn:admin1_code":"MR",
    "gn:admin2_code":"12",
    "gn:admin3_code":"55",
    "gn:admin4_code":"550012",
    "gn:asciiname":"Bholteka",
    "gn:country_code":"NP",
    "gn:dem":1628,
    "gn:feature_class":"P",
    "gn:feature_code":"PPLL",
    "gn:name":"Bholteka",
    "gn:population":0,
    "gn:timezone":"Asia/Kathmandu",
    "iso:country":"NP",
    "wof:name":"Bholteka",
    "wof:placetype":"locality"
},
  "geometry": {"coordinates":[82.37156,28.54953],"type":"Point"}
}