{
  "type": "Feature",
  "properties": {
    "gn:admin1_code":"WR",
    "gn:admin2_code":"8",
    "gn:admin3_code":"49",
    "gn:admin4_code":"490034",
    "gn:asciiname":"Uttarchauridih",
    "gn:country_code":"NP",
    "gn:dem":93,
    "gn:feature_class":"P",
    "gn:feature_code":"PPLL",
    "gn:name":"Uttarchauridih",
    "gn:population":0,
    "gn:timezone":"Asia/Kathmandu",
    "iso:country":"NP",
    "wof:name":"Uttarchauridih",
    "wof:placetype":"locality"
},
  "geometry": {"coordinates":[83.30079000000001,27.37363],"type":"Point"}
}