{
  "type": "Feature",
  "properties": {
    "gn:admin1_code":"00",
    "gn:asciiname":"Bagar",
    "gn:country_code":"NP",
    "gn:dem":1357,
    "gn:feature_class":"P",
    "gn:feature_code":"PPL",
    "gn:name":"Bagar",
    "gn:population":0,
    "gn:timezone":"Asia/Kathmandu",
    "iso:country":"NP",
    "wof:name":"Bagar",
    "wof:placetype":"locality"
},
  "geometry": {"coordinates":[80.56667,29.83333],"type":"Point"}
}