{
  "type": "Feature",
  "properties": {
    "gn:admin1_code":"WR",
    "gn:admin2_code":"3",
    "gn:admin3_code":"44",
    "gn:admin4_code":"440055",
    "gn:asciiname":"Gorang",
    "gn:country_code":"NP",
    "gn:dem":924,
    "gn:feature_class":"P",
    "gn:feature_code":"PPLL",
    "gn:name":"Gorang",
    "gn:population":0,
    "gn:timezone":"Asia/Kathmandu",
    "iso:country":"NP",
    "wof:name":"Gorang",
    "wof:placetype":"locality"
},
  "geometry": {"coordinates":[83.62709,28.05018],"type":"Point"}
}