{
  "type": "Feature",
  "properties": {
    "gn:admin1_code":"CR",
    "gn:admin2_code":"1",
    "gn:admin3_code":"25",
    "gn:admin4_code":"250027.0",
    "gn:asciiname":"Chakupat",
    "gn:country_code":"NP",
    "gn:dem":1295,
    "gn:feature_class":"P",
    "gn:feature_code":"PPLL",
    "gn:name":"Chakupat",
    "gn:population":0,
    "gn:timezone":"Asia/Kathmandu",
    "iso:country":"NP",
    "wof:name":"Chakupat",
    "wof:placetype":"locality"
},
  "geometry": {"coordinates":[85.32496,27.68261],"type":"Point"}
}