{
  "type": "Feature",
  "properties": {
    "gn:admin1_code":"MR",
    "gn:admin2_code":"2.0",
    "gn:admin3_code":"59.0",
    "gn:admin4_code":"590006.0",
    "gn:asciiname":"Kalosota",
    "gn:country_code":"NP",
    "gn:dem":356,
    "gn:feature_class":"P",
    "gn:feature_code":"PPLL",
    "gn:name":"Kalosota",
    "gn:population":0,
    "gn:timezone":"Asia/Kathmandu",
    "iso:country":"NP",
    "wof:name":"Kalosota",
    "wof:placetype":"locality"
},
  "geometry": {"coordinates":[81.37130000000001,28.8213],"type":"Point"}
}