{
  "type": "Feature",
  "properties": {
    "gn:admin1_code":"CR",
    "gn:admin2_code":"1",
    "gn:admin3_code":"23",
    "gn:admin4_code":"230012",
    "gn:asciiname":"Bhotechaur",
    "gn:country_code":"NP",
    "gn:dem":1651,
    "gn:feature_class":"P",
    "gn:feature_code":"PPLL",
    "gn:name":"Bhotechaur",
    "gn:population":0,
    "gn:timezone":"Asia/Kathmandu",
    "iso:country":"NP",
    "name:ceb_x_preferred":[
        "Bhotechaur"
    ],
    "name:msa_x_preferred":[
        "Bhotechaur"
    ],
    "name:nep_x_preferred":[
        "\u092d\u094b\u091f\u0947\u091a\u094c\u0930"
    ],
    "name:new_x_preferred":[
        "\u092d\u094b\u091f\u0947\u091a\u094c\u0930"
    ],
    "name:pol_x_preferred":[
        "Bhotechaur"
    ],
    "wof:name":"Bhotechaur",
    "wof:placetype":"locality"
},
  "geometry": {"coordinates":[85.49918000000002,27.79002],"type":"Point"}
}