{
  "type": "Feature",
  "properties": {
    "gn:admin1_code":"FR",
    "gn:admin2_code":"9",
    "gn:admin3_code":"74",
    "gn:admin4_code":"740052",
    "gn:asciiname":"Dosara",
    "gn:country_code":"NP",
    "gn:dem":1276,
    "gn:feature_class":"P",
    "gn:feature_code":"PPLL",
    "gn:name":"Dosara",
    "gn:population":0,
    "gn:timezone":"Asia/Kathmandu",
    "iso:country":"NP",
    "wof:name":"Dosara",
    "wof:placetype":"locality"
},
  "geometry": {"coordinates":[80.37005000000001,29.42082000000001],"type":"Point"}
}