{
  "type": "Feature",
  "properties": {
    "gn:admin1_code":"WR",
    "gn:admin2_code":"4.0",
    "gn:admin3_code":"39.0",
    "gn:admin4_code":"390038.0",
    "gn:asciiname":"Dumindanda",
    "gn:country_code":"NP",
    "gn:dem":703,
    "gn:feature_class":"P",
    "gn:feature_code":"PPLL",
    "gn:name":"Dumindanda",
    "gn:population":0,
    "gn:timezone":"Asia/Kathmandu",
    "iso:country":"NP",
    "wof:name":"Dumindanda",
    "wof:placetype":"locality"
},
  "geometry": {"coordinates":[83.75641999999998,27.93925],"type":"Point"}
}