{
  "type": "Feature",
  "properties": {
    "gn:admin1_code":"WR",
    "gn:admin2_code":"4",
    "gn:admin3_code":"40.0",
    "gn:admin4_code":"400042.0",
    "gn:asciiname":"Nauledanda",
    "gn:country_code":"NP",
    "gn:dem":1255,
    "gn:feature_class":"P",
    "gn:feature_code":"PPLL",
    "gn:name":"Nauledanda",
    "gn:population":0,
    "gn:timezone":"Asia/Kathmandu",
    "iso:country":"NP",
    "wof:name":"Nauledanda",
    "wof:placetype":"locality"
},
  "geometry": {"coordinates":[84.06429,28.27126],"type":"Point"}
}