{
  "type": "Feature",
  "properties": {
    "gn:admin1_code":"CR",
    "gn:admin2_code":"5",
    "gn:admin3_code":"21",
    "gn:admin4_code":"210041",
    "gn:asciiname":"Adbari",
    "gn:country_code":"NP",
    "gn:dem":1345,
    "gn:feature_class":"P",
    "gn:feature_code":"PPLL",
    "gn:name":"Adbari",
    "gn:population":0,
    "gn:timezone":"Asia/Kathmandu",
    "iso:country":"NP",
    "wof:name":"Adbari",
    "wof:placetype":"locality"
},
  "geometry": {"coordinates":[86.01034,27.45425],"type":"Point"}
}