{
  "type": "Feature",
  "properties": {
    "gn:admin1_code":"CR",
    "gn:admin2_code":"1",
    "gn:admin3_code":"25",
    "gn:admin4_code":"250019",
    "gn:asciiname":"Khaharegaun",
    "gn:country_code":"NP",
    "gn:dem":1483,
    "gn:feature_class":"P",
    "gn:feature_code":"PPLL",
    "gn:name":"Khaharegaun",
    "gn:population":0,
    "gn:timezone":"Asia/Kathmandu",
    "iso:country":"NP",
    "wof:name":"Khaharegaun",
    "wof:placetype":"locality"
},
  "geometry": {"coordinates":[85.37698,27.59898],"type":"Point"}
}