{
  "type": "Feature",
  "properties": {
    "gn:admin1_code":"ER",
    "gn:admin2_code":"7.0",
    "gn:admin3_code":"6.0",
    "gn:admin4_code":"60044.0",
    "gn:asciiname":"Chaudharitol",
    "gn:country_code":"NP",
    "gn:dem":75,
    "gn:feature_class":"P",
    "gn:feature_code":"PPLL",
    "gn:name":"Chaudharitol",
    "gn:population":0,
    "gn:timezone":"Asia/Kathmandu",
    "iso:country":"NP",
    "wof:name":"Chaudharitol",
    "wof:placetype":"locality"
},
  "geometry": {"coordinates":[87.17359999999999,26.44207],"type":"Point"}
}