{
  "type": "Feature",
  "properties": {
    "gn:admin1_code":"CR",
    "gn:admin2_code":"1",
    "gn:admin3_code":"28",
    "gn:admin4_code":"280049.0",
    "gn:asciiname":"Bistathok",
    "gn:country_code":"NP",
    "gn:dem":1138,
    "gn:feature_class":"P",
    "gn:feature_code":"PPLL",
    "gn:name":"Bistathok",
    "gn:population":0,
    "gn:timezone":"Asia/Kathmandu",
    "iso:country":"NP",
    "wof:name":"Bistathok",
    "wof:placetype":"locality"
},
  "geometry": {"coordinates":[85.35916999999998,27.85472],"type":"Point"}
}