{
  "type": "Feature",
  "properties": {
    "gn:admin1_code":"MR",
    "gn:admin2_code":"12",
    "gn:admin3_code":"54",
    "gn:admin4_code":"540037",
    "gn:asciiname":"Kiteni",
    "gn:country_code":"NP",
    "gn:dem":2230,
    "gn:feature_class":"P",
    "gn:feature_code":"PPLL",
    "gn:name":"Kiteni",
    "gn:population":0,
    "gn:timezone":"Asia/Kathmandu",
    "iso:country":"NP",
    "wof:name":"Kiteni",
    "wof:placetype":"locality"
},
  "geometry": {"coordinates":[82.56560999999998,28.6094],"type":"Point"}
}