{
  "type": "Feature",
  "properties": {
    "gn:admin1_code":"MR",
    "gn:admin2_code":"12",
    "gn:admin3_code":"56.0",
    "gn:admin4_code":"560007.0",
    "gn:asciiname":"Dhikpur",
    "gn:country_code":"NP",
    "gn:dem":609,
    "gn:feature_class":"P",
    "gn:feature_code":"PPLL",
    "gn:name":"Dhikpur",
    "gn:population":0,
    "gn:timezone":"Asia/Kathmandu",
    "iso:country":"NP",
    "name:ceb_x_preferred":[
        "Dhikpur"
    ],
    "name:hin_x_preferred":[
        "\u0927\u093f\u0915\u092a\u0941\u0930"
    ],
    "name:msa_x_preferred":[
        "Dhikpur"
    ],
    "name:nep_x_preferred":[
        "\u0922\u093f\u0915\u092a\u0941\u0930"
    ],
    "name:new_x_preferred":[
        "\u0922\u093f\u0915\u092a\u0941\u0930"
    ],
    "name:pol_x_preferred":[
        "Dhikpur"
    ],
    "wof:name":"Dhikpur",
    "wof:placetype":"locality"
},
  "geometry": {"coordinates":[82.38279,28.05014000000001],"type":"Point"}
}