{
  "type": "Feature",
  "properties": {
    "gn:admin1_code":"WR",
    "gn:admin2_code":"8",
    "gn:admin3_code":"47",
    "gn:admin4_code":"470027",
    "gn:asciiname":"Pokharathok",
    "gn:country_code":"NP",
    "gn:dem":1059,
    "gn:feature_class":"P",
    "gn:feature_code":"PPLL",
    "gn:name":"Pokharathok",
    "gn:population":0,
    "gn:timezone":"Asia/Kathmandu",
    "iso:country":"NP",
    "name:fra_x_preferred":[
        "Pokharathok"
    ],
    "name:nep_x_preferred":[
        "\u092a\u094b\u0916\u0930\u093e\u0925\u094b\u0915"
    ],
    "name:pol_x_preferred":[
        "Pokharathok"
    ],
    "wof:name":"Pokharathok",
    "wof:placetype":"locality"
},
  "geometry": {"coordinates":[83.73751999999998,27.87712],"type":"Point"}
}