{
  "type": "Feature",
  "properties": {
    "gn:admin1_code":"MR",
    "gn:admin2_code":"12",
    "gn:admin3_code":"55",
    "gn:admin4_code":"550020",
    "gn:asciiname":"Malwani",
    "gn:country_code":"NP",
    "gn:dem":606,
    "gn:feature_class":"P",
    "gn:feature_code":"PPLL",
    "gn:name":"Malwani",
    "gn:population":0,
    "gn:timezone":"Asia/Kathmandu",
    "iso:country":"NP",
    "wof:name":"Malwani",
    "wof:placetype":"locality"
},
  "geometry": {"coordinates":[81.90853,28.32939],"type":"Point"}
}