{
  "type": "Feature",
  "properties": {
    "gn:admin1_code":"ER",
    "gn:admin2_code":"7",
    "gn:admin3_code":"9",
    "gn:admin4_code":"90022",
    "gn:asciiname":"Sabang",
    "gn:country_code":"NP",
    "gn:dem":1702,
    "gn:feature_class":"P",
    "gn:feature_code":"PPLL",
    "gn:name":"Sabang",
    "gn:population":0,
    "gn:timezone":"Asia/Kathmandu",
    "iso:country":"NP",
    "wof:name":"Sabang",
    "wof:placetype":"locality"
},
  "geometry": {"coordinates":[87.33629000000001,27.54949],"type":"Point"}
}