{
  "type": "Feature",
  "properties": {
    "gn:admin1_code":"MR",
    "gn:admin2_code":"2.0",
    "gn:admin3_code":"59.0",
    "gn:admin4_code":"590040.0",
    "gn:asciiname":"Phagune",
    "gn:country_code":"NP",
    "gn:dem":669,
    "gn:feature_class":"P",
    "gn:feature_code":"PPLL",
    "gn:name":"Phagune",
    "gn:population":0,
    "gn:timezone":"Asia/Kathmandu",
    "iso:country":"NP",
    "wof:name":"Phagune",
    "wof:placetype":"locality"
},
  "geometry": {"coordinates":[81.53108,28.75945],"type":"Point"}
}