{
  "type": "Feature",
  "properties": {
    "gn:admin1_code":"WR",
    "gn:admin2_code":"8",
    "gn:admin3_code":"46.0",
    "gn:admin4_code":"460002.0",
    "gn:asciiname":"Arwathok",
    "gn:country_code":"NP",
    "gn:dem":853,
    "gn:feature_class":"P",
    "gn:feature_code":"PPLL",
    "gn:name":"Arwathok",
    "gn:population":0,
    "gn:timezone":"Asia/Kathmandu",
    "iso:country":"NP",
    "wof:name":"Arwathok",
    "wof:placetype":"locality"
},
  "geometry": {"coordinates":[83.30501,27.97587],"type":"Point"}
}