{
  "type": "Feature",
  "properties": {
    "gn:admin1_code":"ER",
    "gn:admin2_code":"10",
    "gn:admin3_code":"3.0",
    "gn:admin4_code":"30044.0",
    "gn:asciiname":"Chhiruwa",
    "gn:country_code":"NP",
    "gn:dem":1578,
    "gn:feature_class":"P",
    "gn:feature_code":"PPLL",
    "gn:name":"Chhiruwa",
    "gn:population":0,
    "gn:timezone":"Asia/Kathmandu",
    "iso:country":"NP",
    "wof:name":"Chhiruwa",
    "wof:placetype":"locality"
},
  "geometry": {"coordinates":[88.13215,26.88826],"type":"Point"}
}