{
  "type": "Feature",
  "properties": {
    "gn:admin1_code":"ER",
    "gn:admin2_code":"13",
    "gn:admin3_code":"16",
    "gn:admin4_code":"160022",
    "gn:asciiname":"Bhotetar",
    "gn:country_code":"NP",
    "gn:dem":234,
    "gn:feature_class":"P",
    "gn:feature_code":"PPLL",
    "gn:name":"Bhotetar",
    "gn:population":0,
    "gn:timezone":"Asia/Kathmandu",
    "iso:country":"NP",
    "wof:name":"Bhotetar",
    "wof:placetype":"locality"
},
  "geometry": {"coordinates":[86.42215999999998,26.82066],"type":"Point"}
}