{
  "type": "Feature",
  "properties": {
    "gn:admin1_code":"MR",
    "gn:admin2_code":"12",
    "gn:admin3_code":"52",
    "gn:admin4_code":"520006",
    "gn:asciiname":"Belbas",
    "gn:country_code":"NP",
    "gn:dem":1142,
    "gn:feature_class":"P",
    "gn:feature_code":"PPLL",
    "gn:name":"Belbas",
    "gn:population":0,
    "gn:timezone":"Asia/Kathmandu",
    "iso:country":"NP",
    "name:mai_x_preferred":[
        "\u0935\u0947\u0932\u092c\u093e\u0938"
    ],
    "name:msa_x_preferred":[
        "Belbas"
    ],
    "name:nep_x_preferred":[
        "\u0935\u0947\u0932\u092c\u093e\u0938"
    ],
    "name:pol_x_preferred":[
        "Belwaspur"
    ],
    "wof:name":"Belbas",
    "wof:placetype":"locality"
},
  "geometry": {"coordinates":[82.75034000000002,28.15343],"type":"Point"}
}