{
  "type": "Feature",
  "properties": {
    "gn:admin1_code":"CR",
    "gn:admin2_code":"1",
    "gn:admin3_code":"23",
    "gn:admin4_code":"230051",
    "gn:asciiname":"Tallo Chhap",
    "gn:country_code":"NP",
    "gn:dem":1069,
    "gn:feature_class":"P",
    "gn:feature_code":"PPLL",
    "gn:name":"Tallo Chhap",
    "gn:population":0,
    "gn:timezone":"Asia/Kathmandu",
    "iso:country":"NP",
    "wof:name":"Tallo Chhap",
    "wof:placetype":"locality"
},
  "geometry": {"coordinates":[85.84035,27.74668],"type":"Point"}
}