{
  "type": "Feature",
  "properties": {
    "gn:admin1_code":"FR",
    "gn:admin2_code":"14",
    "gn:admin3_code":"69",
    "gn:admin4_code":"690027",
    "gn:asciiname":"Ratmate",
    "gn:country_code":"NP",
    "gn:dem":1626,
    "gn:feature_class":"P",
    "gn:feature_code":"PPLL",
    "gn:name":"Ratmate",
    "gn:population":0,
    "gn:timezone":"Asia/Kathmandu",
    "iso:country":"NP",
    "name:ceb_x_preferred":[
        "Ratmate"
    ],
    "name:deu_x_preferred":[
        "Ratmate"
    ],
    "name:fra_x_preferred":[
        "Ratmate"
    ],
    "name:mai_x_preferred":[
        "\u0930\u093e\u0924\u092e\u093e\u091f\u0947"
    ],
    "name:msa_x_preferred":[
        "Ratmate"
    ],
    "name:nep_x_preferred":[
        "\u0930\u093e\u0924\u092e\u093e\u091f\u0947"
    ],
    "name:new_x_preferred":[
        "\u0930\u093e\u0924\u094d\u092e\u093e\u091f\u0947"
    ],
    "name:pol_x_preferred":[
        "Ratmate"
    ],
    "wof:name":"Ratmate",
    "wof:placetype":"locality"
},
  "geometry": {"coordinates":[81.11205,29.25477],"type":"Point"}
}