{
  "type": "Feature",
  "properties": {
    "gn:admin1_code":"00",
    "gn:asciiname":"Harrebarre",
    "gn:country_code":"NP",
    "gn:dem":1173,
    "gn:feature_class":"P",
    "gn:feature_code":"PPL",
    "gn:name":"Harrebarre",
    "gn:population":0,
    "gn:timezone":"Asia/Kathmandu",
    "iso:country":"NP",
    "wof:name":"Harrebarre",
    "wof:placetype":"locality"
},
  "geometry": {"coordinates":[82.97906999999999,27.83647],"type":"Point"}
}