{
  "type": "Feature",
  "properties": {
    "gn:admin1_code":"WR",
    "gn:admin2_code":"3",
    "gn:admin3_code":"44",
    "gn:admin4_code":"440024",
    "gn:asciiname":"Rahalchaur",
    "gn:country_code":"NP",
    "gn:dem":1003,
    "gn:feature_class":"P",
    "gn:feature_code":"PPLL",
    "gn:name":"Rahalchaur",
    "gn:population":0,
    "gn:timezone":"Asia/Kathmandu",
    "iso:country":"NP",
    "wof:name":"Rahalchaur",
    "wof:placetype":"locality"
},
  "geometry": {"coordinates":[83.66243,28.17548],"type":"Point"}
}