{
  "type": "Feature",
  "properties": {
    "gn:admin1_code":"CR",
    "gn:admin2_code":"1",
    "gn:admin3_code":"28",
    "gn:admin4_code":"280025",
    "gn:asciiname":"Bageshwari",
    "gn:country_code":"NP",
    "gn:dem":1118,
    "gn:feature_class":"P",
    "gn:feature_code":"PPLL",
    "gn:name":"Bageshwari",
    "gn:population":0,
    "gn:timezone":"Asia/Kathmandu",
    "iso:country":"NP",
    "wof:name":"Bageshwari",
    "wof:placetype":"locality"
},
  "geometry": {"coordinates":[85.09744999999999,27.84055],"type":"Point"}
}