{
  "type": "Feature",
  "properties": {
    "gn:admin1_code":"00",
    "gn:asciiname":"Rajnaji",
    "gn:country_code":"NP",
    "gn:dem":131,
    "gn:feature_class":"P",
    "gn:feature_code":"PPL",
    "gn:name":"R\u0101jn\u0101ji\u0307\u0304",
    "gn:population":0,
    "gn:timezone":"Asia/Kathmandu",
    "iso:country":"NP",
    "name:nep_x_preferred":[
        "R\u0101jn\u0101ji\u0307\u0304"
    ],
    "wof:name":"Rajnaji",
    "wof:placetype":"locality"
},
  "geometry": {"coordinates":[86.93913000000001,26.79106],"type":"Point"}
}