{
  "type": "Feature",
  "properties": {
    "gn:admin1_code":"MR",
    "gn:admin2_code":"12",
    "gn:admin3_code":"53",
    "gn:admin4_code":"530047",
    "gn:asciiname":"Jajarkot",
    "gn:country_code":"NP",
    "gn:dem":2515,
    "gn:feature_class":"P",
    "gn:feature_code":"PPLL",
    "gn:name":"Jajarkot",
    "gn:population":0,
    "gn:timezone":"Asia/Kathmandu",
    "iso:country":"NP",
    "name:bpy_x_preferred":[
        "\u099c\u09be\u099c\u09b0\u0995\u09cb\u099f"
    ],
    "name:por_x_preferred":[
        "Jajarkot"
    ],
    "name:urd_x_preferred":[
        "\u062c\u062c\u0631\u06a9\u0648\u0679"
    ],
    "wof:name":"Jajarkot",
    "wof:placetype":"locality"
},
  "geometry": {"coordinates":[82.66504999999999,28.49356],"type":"Point"}
}