{
  "type": "Feature",
  "properties": {
    "gn:admin1_code":"WR",
    "gn:admin2_code":"4",
    "gn:admin3_code":"36.0",
    "gn:admin4_code":"360034.0",
    "gn:asciiname":"Rumchet",
    "gn:country_code":"NP",
    "gn:dem":1790,
    "gn:feature_class":"P",
    "gn:feature_code":"PPLL",
    "gn:name":"Rumchet",
    "gn:population":0,
    "gn:timezone":"Asia/Kathmandu",
    "iso:country":"NP",
    "wof:name":"Rumchet",
    "wof:placetype":"locality"
},
  "geometry": {"coordinates":[84.90883000000002,28.24726],"type":"Point"}
}