{
  "type": "Feature",
  "properties": {
    "gn:admin1_code":"WR",
    "gn:admin2_code":"4",
    "gn:admin3_code":"40.0",
    "gn:admin4_code":"400002.0",
    "gn:asciiname":"Tipyani",
    "gn:country_code":"NP",
    "gn:dem":1687,
    "gn:feature_class":"P",
    "gn:feature_code":"PPLL",
    "gn:name":"Tipyani",
    "gn:population":0,
    "gn:timezone":"Asia/Kathmandu",
    "iso:country":"NP",
    "wof:name":"Tipyani",
    "wof:placetype":"locality"
},
  "geometry": {"coordinates":[84.02204999999999,28.28072],"type":"Point"}
}