{
  "type": "Feature",
  "properties": {
    "gn:admin1_code":"CR",
    "gn:admin2_code":"11",
    "gn:admin3_code":"31",
    "gn:admin4_code":"310017",
    "gn:asciiname":"Dhudedanda",
    "gn:country_code":"NP",
    "gn:dem":1283,
    "gn:feature_class":"P",
    "gn:feature_code":"PPLL",
    "gn:name":"Dhudedanda",
    "gn:population":0,
    "gn:timezone":"Asia/Kathmandu",
    "iso:country":"NP",
    "wof:name":"Dhudedanda",
    "wof:placetype":"locality"
},
  "geometry": {"coordinates":[84.97854,27.63300000000001],"type":"Point"}
}