{
  "type": "Feature",
  "properties": {
    "gn:admin1_code":"FR",
    "gn:admin2_code":"9",
    "gn:admin3_code":"73.0",
    "gn:admin4_code":"730015.0",
    "gn:asciiname":"Nintola",
    "gn:country_code":"NP",
    "gn:dem":1284,
    "gn:feature_class":"P",
    "gn:feature_code":"PPLL",
    "gn:name":"Nintola",
    "gn:population":0,
    "gn:timezone":"Asia/Kathmandu",
    "iso:country":"NP",
    "wof:name":"Nintola",
    "wof:placetype":"locality"
},
  "geometry": {"coordinates":[80.65158000000002,29.33949],"type":"Point"}
}