{
  "type": "Feature",
  "properties": {
    "gn:admin1_code":"ER",
    "gn:admin2_code":"7",
    "gn:admin3_code":"7.0",
    "gn:admin4_code":"70006.0",
    "gn:asciiname":"Khawagaun",
    "gn:country_code":"NP",
    "gn:dem":1845,
    "gn:feature_class":"P",
    "gn:feature_code":"PPLL",
    "gn:name":"Khawagaun",
    "gn:population":0,
    "gn:timezone":"Asia/Kathmandu",
    "iso:country":"NP",
    "wof:name":"Khawagaun",
    "wof:placetype":"locality"
},
  "geometry": {"coordinates":[87.36060000000001,27.03984],"type":"Point"}
}