{
  "type": "Feature",
  "properties": {
    "gn:admin1_code":"MR",
    "gn:admin2_code":"6",
    "gn:admin3_code":"66.0",
    "gn:admin4_code":"660024.0",
    "gn:asciiname":"Phaderagaun Chanphetadi",
    "gn:country_code":"NP",
    "gn:dem":1705,
    "gn:feature_class":"P",
    "gn:feature_code":"PPLL",
    "gn:name":"Phaderagaun Chanphetadi",
    "gn:population":0,
    "gn:timezone":"Asia/Kathmandu",
    "iso:country":"NP",
    "wof:name":"Phaderagaun Chanphetadi",
    "wof:placetype":"locality"
},
  "geometry": {"coordinates":[81.86945,29.6618],"type":"Point"}
}