{
  "type": "Feature",
  "properties": {
    "gn:admin1_code":"CR",
    "gn:admin2_code":"1",
    "gn:admin3_code":"30.0",
    "gn:admin4_code":"300009.0",
    "gn:asciiname":"Singang",
    "gn:country_code":"NP",
    "gn:dem":802,
    "gn:feature_class":"P",
    "gn:feature_code":"PPLL",
    "gn:name":"Singang",
    "gn:population":0,
    "gn:timezone":"Asia/Kathmandu",
    "iso:country":"NP",
    "wof:name":"Singang",
    "wof:placetype":"locality"
},
  "geometry": {"coordinates":[84.99665999999998,28.07764],"type":"Point"}
}