{
  "type": "Feature",
  "properties": {
    "gn:admin1_code":"ER",
    "gn:admin2_code":"13",
    "gn:admin3_code":"13",
    "gn:admin4_code":"130046",
    "gn:asciiname":"Mathillo Mabe",
    "gn:country_code":"NP",
    "gn:dem":1058,
    "gn:feature_class":"P",
    "gn:feature_code":"PPLL",
    "gn:name":"Mathillo Mabe",
    "gn:population":0,
    "gn:timezone":"Asia/Kathmandu",
    "iso:country":"NP",
    "wof:name":"Mathillo Mabe",
    "wof:placetype":"locality"
},
  "geometry": {"coordinates":[86.77646999999997,27.03019],"type":"Point"}
}