{
  "type": "Feature",
  "properties": {
    "gn:admin1_code":"ER",
    "gn:admin2_code":"7",
    "gn:admin3_code":"5",
    "gn:admin4_code":"50051",
    "gn:asciiname":"Dohulu",
    "gn:country_code":"NP",
    "gn:dem":103,
    "gn:feature_class":"P",
    "gn:feature_code":"PPLL",
    "gn:name":"Dohulu",
    "gn:population":0,
    "gn:timezone":"Asia/Kathmandu",
    "iso:country":"NP",
    "wof:name":"Dohulu",
    "wof:placetype":"locality"
},
  "geometry": {"coordinates":[87.54274000000002,26.58828],"type":"Point"}
}