{
  "type": "Feature",
  "properties": {
    "gn:admin1_code":"CR",
    "gn:admin2_code":"1",
    "gn:admin3_code":"30.0",
    "gn:admin4_code":"300017.0",
    "gn:asciiname":"Chyamthali",
    "gn:country_code":"NP",
    "gn:dem":1614,
    "gn:feature_class":"P",
    "gn:feature_code":"PPLL",
    "gn:name":"Chyamthali",
    "gn:population":0,
    "gn:timezone":"Asia/Kathmandu",
    "iso:country":"NP",
    "wof:name":"Chyamthali",
    "wof:placetype":"locality"
},
  "geometry": {"coordinates":[85.03268,28.12322],"type":"Point"}
}