{
  "type": "Feature",
  "properties": {
    "gn:admin1_code":"FR",
    "gn:admin2_code":"14",
    "gn:admin3_code":"70.0",
    "gn:admin4_code":"700004.0",
    "gn:asciiname":"Botado",
    "gn:country_code":"NP",
    "gn:dem":553,
    "gn:feature_class":"P",
    "gn:feature_code":"PPLL",
    "gn:name":"Botado",
    "gn:population":0,
    "gn:timezone":"Asia/Kathmandu",
    "iso:country":"NP",
    "wof:name":"Botado",
    "wof:placetype":"locality"
},
  "geometry": {"coordinates":[81.00612,29.19834],"type":"Point"}
}