{
  "type": "Feature",
  "properties": {
    "gn:admin1_code":"00",
    "gn:asciiname":"Arnegau",
    "gn:country_code":"NP",
    "gn:dem":342,
    "gn:feature_class":"P",
    "gn:feature_code":"PPL",
    "gn:name":"Arneg\u0101\u0169",
    "gn:population":0,
    "gn:timezone":"Asia/Kathmandu",
    "iso:country":"NP",
    "name:nep_x_preferred":[
        "Arneg\u0101\u0169"
    ],
    "wof:name":"Arnegau",
    "wof:placetype":"locality"
},
  "geometry": {"coordinates":[86.45733,26.91044],"type":"Point"}
}