{
  "type": "Feature",
  "properties": {
    "gn:admin1_code":"ER",
    "gn:admin2_code":"7",
    "gn:admin3_code":"5",
    "gn:admin4_code":"50028",
    "gn:asciiname":"Hokse",
    "gn:country_code":"NP",
    "gn:dem":896,
    "gn:feature_class":"P",
    "gn:feature_code":"PPLL",
    "gn:name":"Hokse",
    "gn:population":0,
    "gn:timezone":"Asia/Kathmandu",
    "iso:country":"NP",
    "wof:name":"Hokse",
    "wof:placetype":"locality"
},
  "geometry": {"coordinates":[87.55951,26.8063],"type":"Point"}
}