{
  "type": "Feature",
  "properties": {
    "gn:admin1_code":"WR",
    "gn:admin2_code":"8",
    "gn:admin3_code":"48",
    "gn:admin4_code":"480007",
    "gn:asciiname":"Ghumaure",
    "gn:country_code":"NP",
    "gn:dem":189,
    "gn:feature_class":"P",
    "gn:feature_code":"PPLL",
    "gn:name":"Ghumaure",
    "gn:population":0,
    "gn:timezone":"Asia/Kathmandu",
    "iso:country":"NP",
    "wof:name":"Ghumaure",
    "wof:placetype":"locality"
},
  "geometry": {"coordinates":[83.81992,27.65693],"type":"Point"}
}