{
  "type": "Feature",
  "properties": {
    "gn:admin1_code":"MR",
    "gn:admin2_code":"6",
    "gn:admin3_code":"64.0",
    "gn:admin4_code":"640014.0",
    "gn:asciiname":"Siradi",
    "gn:country_code":"NP",
    "gn:dem":998,
    "gn:feature_class":"P",
    "gn:feature_code":"PPLL",
    "gn:name":"Siradi",
    "gn:population":0,
    "gn:timezone":"Asia/Kathmandu",
    "iso:country":"NP",
    "wof:name":"Siradi",
    "wof:placetype":"locality"
},
  "geometry": {"coordinates":[81.54666,29.10923],"type":"Point"}
}