{
  "type": "Feature",
  "properties": {
    "gn:admin1_code":"WR",
    "gn:admin2_code":"4",
    "gn:admin3_code":"37",
    "gn:admin4_code":"370019",
    "gn:asciiname":"Tiwaridanda",
    "gn:country_code":"NP",
    "gn:dem":922,
    "gn:feature_class":"P",
    "gn:feature_code":"PPLL",
    "gn:name":"Tiwaridanda",
    "gn:population":0,
    "gn:timezone":"Asia/Kathmandu",
    "iso:country":"NP",
    "wof:name":"Tiwaridanda",
    "wof:placetype":"locality"
},
  "geometry": {"coordinates":[84.44086,28.19515],"type":"Point"}
}