{
  "type": "Feature",
  "properties": {
    "gn:admin1_code":"ER",
    "gn:admin2_code":"7",
    "gn:admin3_code":"7.0",
    "gn:admin4_code":"70028.0",
    "gn:asciiname":"Muga",
    "gn:country_code":"NP",
    "gn:dem":1239,
    "gn:feature_class":"P",
    "gn:feature_code":"PPLL",
    "gn:name":"Muga",
    "gn:population":0,
    "gn:timezone":"Asia/Kathmandu",
    "iso:country":"NP",
    "name:cat_x_preferred":[
        "La Muga"
    ],
    "name:ceb_x_preferred":[
        "Muga"
    ],
    "name:eus_x_preferred":[
        "Muga"
    ],
    "name:spa_x_preferred":[
        "Muga"
    ],
    "name:swe_x_preferred":[
        "Muga"
    ],
    "wof:name":"Muga",
    "wof:placetype":"locality"
},
  "geometry": {"coordinates":[87.22638000000001,27.03816],"type":"Point"}
}