{
  "type": "Feature",
  "properties": {
    "gn:admin1_code":"WR",
    "gn:admin2_code":"8",
    "gn:admin3_code":"49",
    "gn:admin4_code":"490047",
    "gn:asciiname":"Manikapur",
    "gn:country_code":"NP",
    "gn:dem":104,
    "gn:feature_class":"P",
    "gn:feature_code":"PPLL",
    "gn:name":"Manikapur",
    "gn:population":0,
    "gn:timezone":"Asia/Kathmandu",
    "iso:country":"NP",
    "name:mai_x_preferred":[
        "\u092e\u0928\u093f\u0915\u093e\u092a\u0941\u0930"
    ],
    "name:msa_x_preferred":[
        "Manikapur"
    ],
    "name:nep_x_preferred":[
        "\u092e\u0928\u093f\u0915\u093e\u092a\u0941\u0930"
    ],
    "name:new_x_preferred":[
        "\u092e\u0923\u093f\u0915\u093e\u092a\u0941\u0930"
    ],
    "name:pol_x_preferred":[
        "Manikapur"
    ],
    "wof:name":"Manikapur",
    "wof:placetype":"locality"
},
  "geometry": {"coordinates":[83.24403000000002,27.52314],"type":"Point"}
}