{
  "type": "Feature",
  "properties": {
    "gn:country":"NP",
    "gn:fcode":"PPL",
    "gn:pop":230,
    "iso:country":"NP",
    "name:ast_x_preferred":[
        "Lukla"
    ],
    "name:bul_x_preferred":[
        "\u041b\u0443\u043a\u043b\u0430"
    ],
    "name:chi_x_preferred":[
        "\u5362\u514b\u62c9"
    ],
    "name:cze_x_preferred":[
        "Lukla"
    ],
    "name:dan_x_preferred":[
        "Lukla"
    ],
    "name:dut_x_preferred":[
        "Lukla"
    ],
    "name:eng_x_preferred":[
        "Lukla"
    ],
    "name:epo_x_preferred":[
        "Lukla"
    ],
    "name:fin_x_preferred":[
        "Lukla"
    ],
    "name:fra_x_preferred":[
        "Lukla"
    ],
    "name:fre_x_preferred":[
        "Lukla"
    ],
    "name:ger_x_preferred":[
        "Lukla"
    ],
    "name:heb_x_preferred":[
        "\u05dc\u05d5\u05e7\u05dc\u05d4"
    ],
    "name:ina_x_preferred":[
        "Lukla"
    ],
    "name:ita_x_preferred":[
        "Lukla"
    ],
    "name:jpn_x_preferred":[
        "\u30eb\u30af\u30e9"
    ],
    "name:kor_x_preferred":[
        "\ub8e8\ud074\ub77c"
    ],
    "name:lit_x_preferred":[
        "Lukla"
    ],
    "name:lmo_x_preferred":[
        "Lukla"
    ],
    "name:nep_x_preferred":[
        "\u0932\u0941\u0915\u094d\u0932\u093e"
    ],
    "name:nob_x_preferred":[
        "Lukla"
    ],
    "name:por_x_preferred":[
        "Lukla"
    ],
    "name:rus_x_preferred":[
        "\u041b\u0443\u043a\u043b\u0430"
    ],
    "name:spa_x_preferred":[
        "Lukla"
    ],
    "name:zho_x_preferred":[
        "\u5362\u514b\u62c9"
    ],
    "qs:name":"Lukla",
    "qs:photos_9r":0,
    "qs:photos_sr":0,
    "qs:pop_sr":"2",
    "wd:wordcount":293,
    "wof:name":"Lukla",
    "wof:placetype":"locality",
    "wof:population":230
},
  "geometry": {"coordinates":[86.73139999999999,27.68664],"type":"Point"}
}