{
  "type": "Feature",
  "properties": {
    "gn:admin1_code":"WR",
    "gn:admin2_code":"8",
    "gn:admin3_code":"51.0",
    "gn:admin4_code":"510023.0",
    "gn:asciiname":"Deurali",
    "gn:country_code":"NP",
    "gn:dem":1697,
    "gn:feature_class":"P",
    "gn:feature_code":"PPLL",
    "gn:name":"Deurali",
    "gn:population":0,
    "gn:timezone":"Asia/Kathmandu",
    "iso:country":"NP",
    "wof:name":"Deurali",
    "wof:placetype":"locality"
},
  "geometry": {"coordinates":[83.12146,28.0494],"type":"Point"}
}