{
  "type": "Feature",
  "properties": {
    "gn:admin1_code":"CR",
    "gn:admin2_code":"1",
    "gn:admin3_code":"24.0",
    "gn:admin4_code":"240067.0",
    "gn:asciiname":"Hanumankharka",
    "gn:country_code":"NP",
    "gn:dem":1347,
    "gn:feature_class":"P",
    "gn:feature_code":"PPLL",
    "gn:name":"Hanumankharka",
    "gn:population":0,
    "gn:timezone":"Asia/Kathmandu",
    "iso:country":"NP",
    "wof:name":"Hanumankharka",
    "wof:placetype":"locality"
},
  "geometry": {"coordinates":[85.59211999999999,27.59694],"type":"Point"}
}