{
  "type": "Feature",
  "properties": {
    "gn:admin1_code":"ER",
    "gn:admin2_code":"13",
    "gn:admin3_code":"16",
    "gn:admin4_code":"160008",
    "gn:asciiname":"Musaharitol",
    "gn:country_code":"NP",
    "gn:dem":109,
    "gn:feature_class":"P",
    "gn:feature_code":"PPLL",
    "gn:name":"Musaharitol",
    "gn:population":0,
    "gn:timezone":"Asia/Kathmandu",
    "iso:country":"NP",
    "wof:name":"Musaharitol",
    "wof:placetype":"locality"
},
  "geometry": {"coordinates":[86.25745999999999,26.76808],"type":"Point"}
}