{
  "type": "Feature",
  "properties": {
    "gn:admin1_code":"CR",
    "gn:admin2_code":"11.0",
    "gn:admin3_code":"33.0",
    "gn:admin4_code":"330002.0",
    "gn:asciiname":"Chakarigaun",
    "gn:country_code":"NP",
    "gn:dem":288,
    "gn:feature_class":"P",
    "gn:feature_code":"PPLL",
    "gn:name":"Chakarigaun",
    "gn:population":0,
    "gn:timezone":"Asia/Kathmandu",
    "iso:country":"NP",
    "wof:name":"Chakarigaun",
    "wof:placetype":"locality"
},
  "geometry": {"coordinates":[85.01931,27.28845],"type":"Point"}
}