{
  "type": "Feature",
  "properties": {
    "gn:admin1_code":"FR",
    "gn:admin2_code":"14.0",
    "gn:admin3_code":"67.0",
    "gn:admin4_code":"670014.0",
    "gn:asciiname":"Matesagru",
    "gn:country_code":"NP",
    "gn:dem":2383,
    "gn:feature_class":"P",
    "gn:feature_code":"PPLL",
    "gn:name":"Matesagru",
    "gn:population":0,
    "gn:timezone":"Asia/Kathmandu",
    "iso:country":"NP",
    "wof:name":"Matesagru",
    "wof:placetype":"locality"
},
  "geometry": {"coordinates":[81.25213000000002,29.39992],"type":"Point"}
}