{
  "type": "Feature",
  "properties": {
    "gn:admin1_code":"ER",
    "gn:admin2_code":"10",
    "gn:admin3_code":"2",
    "gn:admin4_code":"20005",
    "gn:asciiname":"Nagi",
    "gn:country_code":"NP",
    "gn:dem":1857,
    "gn:feature_class":"P",
    "gn:feature_code":"PPLL",
    "gn:name":"Nagi",
    "gn:population":0,
    "gn:timezone":"Asia/Kathmandu",
    "iso:country":"NP",
    "wof:name":"Nagi",
    "wof:placetype":"locality"
},
  "geometry": {"coordinates":[87.79528000000001,27.19736],"type":"Point"}
}