{
  "type": "Feature",
  "properties": {
    "gn:admin1_code":"WR",
    "gn:admin2_code":"4",
    "gn:admin3_code":"36.0",
    "gn:admin4_code":"360053.0",
    "gn:asciiname":"Mahabhirswanra",
    "gn:country_code":"NP",
    "gn:dem":1986,
    "gn:feature_class":"P",
    "gn:feature_code":"PPLL",
    "gn:name":"Mahabhirswanra",
    "gn:population":0,
    "gn:timezone":"Asia/Kathmandu",
    "iso:country":"NP",
    "wof:name":"Mahabhirswanra",
    "wof:placetype":"locality"
},
  "geometry": {"coordinates":[84.74014,28.15008],"type":"Point"}
}