{
  "type": "Feature",
  "properties": {
    "gn:admin1_code":"00",
    "gn:asciiname":"Nagiyan",
    "gn:country_code":"NP",
    "gn:dem":1520,
    "gn:feature_class":"P",
    "gn:feature_code":"PPL",
    "gn:name":"N\u0101giy\u0101n",
    "gn:population":0,
    "gn:timezone":"Asia/Kathmandu",
    "iso:country":"NP",
    "wof:name":"Nagiyan",
    "wof:placetype":"locality"
},
  "geometry": {"coordinates":[86.66703000000003,27.48661],"type":"Point"}
}