{
  "type": "Feature",
  "properties": {
    "gn:admin1_code":"MR",
    "gn:admin2_code":"12",
    "gn:admin3_code":"55",
    "gn:admin4_code":"550046",
    "gn:asciiname":"Childhale",
    "gn:country_code":"NP",
    "gn:dem":1396,
    "gn:feature_class":"P",
    "gn:feature_code":"PPLL",
    "gn:name":"Childhale",
    "gn:population":0,
    "gn:timezone":"Asia/Kathmandu",
    "iso:country":"NP",
    "wof:name":"Childhale",
    "wof:placetype":"locality"
},
  "geometry": {"coordinates":[82.3155,28.4679],"type":"Point"}
}