{
  "type": "Feature",
  "properties": {
    "gn:admin1_code":"WR",
    "gn:admin2_code":"8",
    "gn:admin3_code":"46.0",
    "gn:admin4_code":"460066.0",
    "gn:asciiname":"Purkot Daha",
    "gn:country_code":"NP",
    "gn:dem":1598,
    "gn:feature_class":"P",
    "gn:feature_code":"PPLL",
    "gn:name":"Purkot Daha",
    "gn:population":0,
    "gn:timezone":"Asia/Kathmandu",
    "iso:country":"NP",
    "wof:name":"Purkot Daha",
    "wof:placetype":"locality"
},
  "geometry": {"coordinates":[83.07528000000001,28.14674],"type":"Point"}
}