{
  "type": "Feature",
  "properties": {
    "gn:admin1_code":"CR",
    "gn:admin2_code":"1",
    "gn:admin3_code":"28",
    "gn:admin4_code":"280051",
    "gn:asciiname":"Buldunche",
    "gn:country_code":"NP",
    "gn:dem":1897,
    "gn:feature_class":"P",
    "gn:feature_code":"PPLL",
    "gn:name":"Buldunche",
    "gn:population":0,
    "gn:timezone":"Asia/Kathmandu",
    "iso:country":"NP",
    "wof:name":"Buldunche",
    "wof:placetype":"locality"
},
  "geometry": {"coordinates":[85.39369000000001,27.97408],"type":"Point"}
}