{
  "type": "Feature",
  "properties": {
    "gn:admin1_code":"ER",
    "gn:admin2_code":"10.0",
    "gn:admin3_code":"1.0",
    "gn:admin4_code":"10011.0",
    "gn:asciiname":"Chawa",
    "gn:country_code":"NP",
    "gn:dem":2230,
    "gn:feature_class":"P",
    "gn:feature_code":"PPLL",
    "gn:name":"Chawa",
    "gn:population":0,
    "gn:timezone":"Asia/Kathmandu",
    "iso:country":"NP",
    "name:fas_x_preferred":[
        "\u0686\u0627\u0648\u0627"
    ],
    "name:urd_x_preferred":[
        "\u0686\u0627\u0648\u0627"
    ],
    "wof:name":"Chawa",
    "wof:placetype":"locality"
},
  "geometry": {"coordinates":[87.97468000000001,27.31586],"type":"Point"}
}