{
  "type": "Feature",
  "properties": {
    "gn:admin1_code":"FR",
    "gn:admin2_code":"14",
    "gn:admin3_code":"69.0",
    "gn:admin4_code":"690011.0",
    "gn:asciiname":"Thalepata",
    "gn:country_code":"NP",
    "gn:dem":1665,
    "gn:feature_class":"P",
    "gn:feature_code":"PPLL",
    "gn:name":"Thalepata",
    "gn:population":0,
    "gn:timezone":"Asia/Kathmandu",
    "iso:country":"NP",
    "wof:name":"Thalepata",
    "wof:placetype":"locality"
},
  "geometry": {"coordinates":[81.35061999999998,29.04723],"type":"Point"}
}