{
  "type": "Feature",
  "properties": {
    "gn:admin1_code":"CR",
    "gn:admin2_code":"1",
    "gn:admin3_code":"23",
    "gn:admin4_code":"230061.0",
    "gn:asciiname":"Badahare",
    "gn:country_code":"NP",
    "gn:dem":854,
    "gn:feature_class":"P",
    "gn:feature_code":"PPLL",
    "gn:name":"Badahare",
    "gn:population":0,
    "gn:timezone":"Asia/Kathmandu",
    "iso:country":"NP",
    "wof:name":"Badahare",
    "wof:placetype":"locality"
},
  "geometry": {"coordinates":[85.58521999999998,27.80698],"type":"Point"}
}