{
  "type": "Feature",
  "properties": {
    "gn:admin1_code":"WR",
    "gn:admin2_code":"8",
    "gn:admin3_code":"47",
    "gn:admin4_code":"470012",
    "gn:asciiname":"Phulung",
    "gn:country_code":"NP",
    "gn:dem":1190,
    "gn:feature_class":"P",
    "gn:feature_code":"PPLL",
    "gn:name":"Phulung",
    "gn:population":0,
    "gn:timezone":"Asia/Kathmandu",
    "iso:country":"NP",
    "wof:name":"Phulung",
    "wof:placetype":"locality"
},
  "geometry": {"coordinates":[83.58071,27.88899],"type":"Point"}
}