{
  "type": "Feature",
  "properties": {
    "gn:admin1_code":"WR",
    "gn:admin2_code":"4.0",
    "gn:admin3_code":"38.0",
    "gn:admin4_code":"380001.0",
    "gn:asciiname":"Kaphadanda",
    "gn:country_code":"NP",
    "gn:dem":1205,
    "gn:feature_class":"P",
    "gn:feature_code":"PPLL",
    "gn:name":"Kaphadanda",
    "gn:population":0,
    "gn:timezone":"Asia/Kathmandu",
    "iso:country":"NP",
    "wof:name":"Kaphadanda",
    "wof:placetype":"locality"
},
  "geometry": {"coordinates":[84.51952,27.8585],"type":"Point"}
}