{
  "type": "Feature",
  "properties": {
    "gn:admin1_code":"WR",
    "gn:admin2_code":"8",
    "gn:admin3_code":"48",
    "gn:admin4_code":"480049",
    "gn:asciiname":"Harihar",
    "gn:country_code":"NP",
    "gn:dem":201,
    "gn:feature_class":"P",
    "gn:feature_code":"PPLL",
    "gn:name":"Harihar",
    "gn:population":0,
    "gn:timezone":"Asia/Kathmandu",
    "iso:country":"NP",
    "name:bar_x_preferred":[
        "Harihar"
    ],
    "name:ben_x_preferred":[
        "\u09b9\u09b0\u09bf\u09b9\u09b0"
    ],
    "name:bpy_x_preferred":[
        "\u09b9\u09b0\u09bf\u09b9\u09b0"
    ],
    "name:ceb_x_preferred":[
        "Harihar"
    ],
    "name:deu_x_preferred":[
        "Harihar"
    ],
    "name:hin_x_preferred":[
        "\u0939\u0930\u093f\u0939\u0930"
    ],
    "name:ita_x_preferred":[
        "Harihar"
    ],
    "name:kan_x_preferred":[
        "\u0cb9\u0cb0\u0cbf\u0cb9\u0cb0"
    ],
    "name:mlg_x_preferred":[
        "Harihar"
    ],
    "name:msa_x_preferred":[
        "Harihar"
    ],
    "name:new_x_preferred":[
        "\u0939\u0930\u093f\u0939\u0930"
    ],
    "name:nld_x_preferred":[
        "Harihar"
    ],
    "name:spa_x_preferred":[
        "Harihar"
    ],
    "name:swe_x_preferred":[
        "Harihar"
    ],
    "name:vie_x_preferred":[
        "Harihar"
    ],
    "name:zho_x_preferred":[
        "\u54c8\u91cc\u54c8\u5c14"
    ],
    "wof:name":"Harihar",
    "wof:placetype":"locality"
},
  "geometry": {"coordinates":[83.97225,27.58854],"type":"Point"}
}