{
  "type": "Feature",
  "properties": {
    "gn:admin1_code":"FR",
    "gn:admin2_code":"14",
    "gn:admin3_code":"70.0",
    "gn:admin4_code":"700003.0",
    "gn:asciiname":"Asura",
    "gn:country_code":"NP",
    "gn:dem":1586,
    "gn:feature_class":"P",
    "gn:feature_code":"PPLL",
    "gn:name":"Asura",
    "gn:population":0,
    "gn:timezone":"Asia/Kathmandu",
    "iso:country":"NP",
    "name:afr_x_preferred":[
        "Asura"
    ],
    "name:bul_x_preferred":[
        "\u0410\u0448\u0443\u0440\u0430"
    ],
    "name:bxr_x_preferred":[
        "\u0410\u0441\u0443\u0443\u0440\u0438"
    ],
    "name:cat_x_preferred":[
        "Asura"
    ],
    "name:ces_x_preferred":[
        "Asura"
    ],
    "name:dan_x_preferred":[
        "Asura"
    ],
    "name:deu_x_preferred":[
        "Asura"
    ],
    "name:epo_x_preferred":[
        "Asuro"
    ],
    "name:est_x_preferred":[
        "Asura"
    ],
    "name:fas_x_preferred":[
        "\u0627\u0633\u0648\u0631\u0627\u0647\u0627"
    ],
    "name:fin_x_preferred":[
        "Asurat"
    ],
    "name:fra_x_preferred":[
        "Asura"
    ],
    "name:gom_x_preferred":[
        "Asura"
    ],
    "name:hin_x_preferred":[
        "\u0905\u0938\u0941\u0930"
    ],
    "name:hun_x_preferred":[
        "Aszura"
    ],
    "name:ind_x_preferred":[
        "Asura"
    ],
    "name:ita_x_preferred":[
        "Asura"
    ],
    "name:jpn_x_preferred":[
        "\u30a2\u30b9\u30e9"
    ],
    "name:kan_x_preferred":[
        "\u0c85\u0cb8\u0cc1\u0cb0"
    ],
    "name:kor_x_preferred":[
        "\uc544\uc218\ub77c"
    ],
    "name:lit_x_preferred":[
        "Asura"
    ],
    "name:mal_x_preferred":[
        "\u0d05\u0d38\u0d41\u0d30\u0d7b"
    ],
    "name:mar_x_preferred":[
        "\u0905\u0938\u0941\u0930"
    ],
    "name:nep_x_preferred":[
        "\u0905\u0938\u0941\u0930"
    ],
    "name:new_x_preferred":[
        "\u0905\u0938\u0941\u0930"
    ],
    "name:nld_x_preferred":[
        "Asura"
    ],
    "name:nor_x_preferred":[
        "Asura"
    ],
    "name:pol_x_preferred":[
        "Asura"
    ],
    "name:por_x_preferred":[
        "Asuras"
    ],
    "name:ron_x_preferred":[
        "Asura"
    ],
    "name:rus_x_preferred":[
        "\u0410\u0441\u0443\u0440\u044b"
    ],
    "name:slk_x_preferred":[
        "Asura"
    ],
    "name:slv_x_preferred":[
        "Asure"
    ],
    "name:spa_x_preferred":[
        "Asura"
    ],
    "name:swe_x_preferred":[
        "Asura"
    ],
    "name:tam_x_preferred":[
        "\u0b85\u0b9a\u0bc1\u0bb0\u0bb0\u0bcd"
    ],
    "name:tha_x_preferred":[
        "\u0e2d\u0e2a\u0e39\u0e23"
    ],
    "name:ukr_x_preferred":[
        "\u0410\u0441\u0443\u0440\u0430"
    ],
    "name:urd_x_preferred":[
        "\u0627\u0633\u0631"
    ],
    "name:vie_x_preferred":[
        "A-tu-la"
    ],
    "name:zho_x_preferred":[
        "\u963f\u4fee\u7f57"
    ],
    "wof:name":"Asura",
    "wof:placetype":"locality"
},
  "geometry": {"coordinates":[80.84135000000001,29.00872],"type":"Point"}
}