{
  "type": "Feature",
  "properties": {
    "gn:admin1_code":"MR",
    "gn:admin2_code":"12",
    "gn:admin3_code":"55",
    "gn:admin4_code":"550023",
    "gn:asciiname":"Gairi Kateri",
    "gn:country_code":"NP",
    "gn:dem":1779,
    "gn:feature_class":"P",
    "gn:feature_code":"PPLL",
    "gn:name":"Gairi Kateri",
    "gn:population":0,
    "gn:timezone":"Asia/Kathmandu",
    "iso:country":"NP",
    "wof:name":"Gairi Kateri",
    "wof:placetype":"locality"
},
  "geometry": {"coordinates":[82.21321999999998,28.25036],"type":"Point"}
}