{
  "type": "Feature",
  "properties": {
    "gn:admin1_code":"00",
    "gn:asciiname":"Libanggaon",
    "gn:country_code":"NP",
    "gn:dem":1301,
    "gn:feature_class":"P",
    "gn:feature_code":"PPL",
    "gn:name":"Lib\u0101nggaon",
    "gn:population":0,
    "gn:timezone":"Asia/Kathmandu",
    "iso:country":"NP",
    "name:und_x_variant":[
        "Liwang",
        "Liwangaon",
        "Lib\u0101nggaon"
    ],
    "wof:name":"Libanggaon",
    "wof:placetype":"locality"
},
  "geometry": {"coordinates":[82.63531,28.30447],"type":"Point"}
}