{
  "type": "Feature",
  "properties": {
    "gn:admin1_code":"ER",
    "gn:admin2_code":"7",
    "gn:admin3_code":"10.0",
    "gn:admin4_code":"100018.0",
    "gn:asciiname":"Khewa Bhanjyang",
    "gn:country_code":"NP",
    "gn:dem":1066,
    "gn:feature_class":"P",
    "gn:feature_code":"PPLL",
    "gn:name":"Khewa Bhanjyang",
    "gn:population":0,
    "gn:timezone":"Asia/Kathmandu",
    "iso:country":"NP",
    "wof:name":"Khewa Bhanjyang",
    "wof:placetype":"locality"
},
  "geometry": {"coordinates":[87.01021,27.13761],"type":"Point"}
}