{
  "type": "Feature",
  "properties": {
    "gn:admin1_code":"CR",
    "gn:admin2_code":"1",
    "gn:admin3_code":"24.0",
    "gn:admin4_code":"240060.0",
    "gn:asciiname":"Khajuli",
    "gn:country_code":"NP",
    "gn:dem":1299,
    "gn:feature_class":"P",
    "gn:feature_code":"PPLL",
    "gn:name":"Khajuli",
    "gn:population":0,
    "gn:timezone":"Asia/Kathmandu",
    "iso:country":"NP",
    "wof:name":"Khajuli",
    "wof:placetype":"locality"
},
  "geometry": {"coordinates":[85.43989999999999,27.43482],"type":"Point"}
}