{
  "type": "Feature",
  "properties": {
    "gn:admin1_code":"MR",
    "gn:admin2_code":"6",
    "gn:admin3_code":"63.0",
    "gn:admin4_code":"630001.0",
    "gn:asciiname":"Dhandkharka",
    "gn:country_code":"NP",
    "gn:dem":3067,
    "gn:feature_class":"P",
    "gn:feature_code":"PPLL",
    "gn:name":"Dhandkharka",
    "gn:population":0,
    "gn:timezone":"Asia/Kathmandu",
    "iso:country":"NP",
    "wof:name":"Dhandkharka",
    "wof:placetype":"locality"
},
  "geometry": {"coordinates":[81.95823,29.33316],"type":"Point"}
}