{
  "type": "Feature",
  "properties": {
    "gn:admin1_code":"ER",
    "gn:admin2_code":"7",
    "gn:admin3_code":"5",
    "gn:admin4_code":"50002",
    "gn:asciiname":"Kechana",
    "gn:country_code":"NP",
    "gn:dem":95,
    "gn:feature_class":"P",
    "gn:feature_code":"PPLL",
    "gn:name":"Kechana",
    "gn:population":0,
    "gn:timezone":"Asia/Kathmandu",
    "iso:country":"NP",
    "name:bih_x_preferred":[
        "\u0915\u0947\u091a\u0928\u093e"
    ],
    "name:ceb_x_preferred":[
        "Kechana"
    ],
    "name:dty_x_preferred":[
        "\u0915\u0947\u091a\u0928\u093e"
    ],
    "name:fra_x_preferred":[
        "Kechana"
    ],
    "name:hin_x_preferred":[
        "\u0915\u0947\u091a\u0928\u093e"
    ],
    "name:mai_x_preferred":[
        "\u0915\u0947\u091a\u0928\u093e"
    ],
    "name:msa_x_preferred":[
        "Kechana"
    ],
    "name:nep_x_preferred":[
        "\u0915\u0947\u091a\u0928\u093e"
    ],
    "name:new_x_preferred":[
        "\u0915\u0947\u091a\u0928\u093e"
    ],
    "name:pol_x_preferred":[
        "Kechana"
    ],
    "wof:name":"Kechana",
    "wof:placetype":"locality"
},
  "geometry": {"coordinates":[87.52929,26.57219000000001],"type":"Point"}
}