{
  "type": "Feature",
  "properties": {
    "gn:admin1_code":"FR",
    "gn:admin2_code":"14.0",
    "gn:admin3_code":"67.0",
    "gn:admin4_code":"670004.0",
    "gn:asciiname":"Kapritola",
    "gn:country_code":"NP",
    "gn:dem":1716,
    "gn:feature_class":"P",
    "gn:feature_code":"PPLL",
    "gn:name":"Kapritola",
    "gn:population":0,
    "gn:timezone":"Asia/Kathmandu",
    "iso:country":"NP",
    "wof:name":"Kapritola",
    "wof:placetype":"locality"
},
  "geometry": {"coordinates":[81.29348,29.34573],"type":"Point"}
}