{
  "type": "Feature",
  "properties": {
    "gn:admin1_code":"CR",
    "gn:admin2_code":"1",
    "gn:admin3_code":"23",
    "gn:admin4_code":"230078",
    "gn:asciiname":"Pakhar Dobhang",
    "gn:country_code":"NP",
    "gn:dem":1025,
    "gn:feature_class":"P",
    "gn:feature_code":"PPLL",
    "gn:name":"Pakhar Dobhang",
    "gn:population":0,
    "gn:timezone":"Asia/Kathmandu",
    "iso:country":"NP",
    "wof:name":"Pakhar Dobhang",
    "wof:placetype":"locality"
},
  "geometry": {"coordinates":[85.80416,27.73845],"type":"Point"}
}