{
  "type": "Feature",
  "properties": {
    "gn:admin1_code":"ER",
    "gn:admin2_code":"13",
    "gn:admin3_code":"13.0",
    "gn:admin4_code":"130015.0",
    "gn:asciiname":"Khila",
    "gn:country_code":"NP",
    "gn:dem":855,
    "gn:feature_class":"P",
    "gn:feature_code":"PPLL",
    "gn:name":"Khila",
    "gn:population":0,
    "gn:timezone":"Asia/Kathmandu",
    "iso:country":"NP",
    "wof:name":"Khila",
    "wof:placetype":"locality"
},
  "geometry": {"coordinates":[86.74799999999998,27.10697],"type":"Point"}
}