{
  "type": "Feature",
  "properties": {
    "gn:admin1_code":"CR",
    "gn:admin2_code":"11.0",
    "gn:admin3_code":"33.0",
    "gn:admin4_code":"330007.0",
    "gn:asciiname":"Gachhiyatola",
    "gn:country_code":"NP",
    "gn:dem":81,
    "gn:feature_class":"P",
    "gn:feature_code":"PPLL",
    "gn:name":"Gachhiyatola",
    "gn:population":0,
    "gn:timezone":"Asia/Kathmandu",
    "iso:country":"NP",
    "wof:name":"Gachhiyatola",
    "wof:placetype":"locality"
},
  "geometry": {"coordinates":[84.98241999999998,26.91618],"type":"Point"}
}