{
  "type": "Feature",
  "properties": {
    "gn:admin1_code":"ER",
    "gn:admin2_code":"13.0",
    "gn:admin3_code":"14.0",
    "gn:admin4_code":"140039.0",
    "gn:asciiname":"Majhkharka",
    "gn:country_code":"NP",
    "gn:dem":878,
    "gn:feature_class":"P",
    "gn:feature_code":"PPLL",
    "gn:name":"Majhkharka",
    "gn:population":0,
    "gn:timezone":"Asia/Kathmandu",
    "iso:country":"NP",
    "wof:name":"Majhkharka",
    "wof:placetype":"locality"
},
  "geometry": {"coordinates":[86.49594999999999,27.02312],"type":"Point"}
}