{
  "type": "Feature",
  "properties": {
    "gn:admin1_code":"ER",
    "gn:admin2_code":"7",
    "gn:admin3_code":"5",
    "gn:admin4_code":"50013",
    "gn:asciiname":"Rajbangshitol",
    "gn:country_code":"NP",
    "gn:dem":69,
    "gn:feature_class":"P",
    "gn:feature_code":"PPLL",
    "gn:name":"Rajbangshitol",
    "gn:population":0,
    "gn:timezone":"Asia/Kathmandu",
    "iso:country":"NP",
    "wof:name":"Rajbangshitol",
    "wof:placetype":"locality"
},
  "geometry": {"coordinates":[87.29673000000003,26.42595],"type":"Point"}
}