{
  "type": "Feature",
  "properties": {
    "gn:admin1_code":"ER",
    "gn:admin2_code":"7",
    "gn:admin3_code":"5",
    "gn:admin4_code":"50004",
    "gn:asciiname":"Jirayat",
    "gn:country_code":"NP",
    "gn:dem":86,
    "gn:feature_class":"P",
    "gn:feature_code":"PPLL",
    "gn:name":"Jirayat",
    "gn:population":0,
    "gn:timezone":"Asia/Kathmandu",
    "iso:country":"NP",
    "wof:name":"Jirayat",
    "wof:placetype":"locality"
},
  "geometry": {"coordinates":[87.43301,26.5482],"type":"Point"}
}