{
  "type": "Feature",
  "properties": {
    "gn:admin1_code":"WR",
    "gn:admin2_code":"8",
    "gn:admin3_code":"48",
    "gn:admin4_code":"480053",
    "gn:asciiname":"Belswara",
    "gn:country_code":"NP",
    "gn:dem":676,
    "gn:feature_class":"P",
    "gn:feature_code":"PPLL",
    "gn:name":"Belswara",
    "gn:population":0,
    "gn:timezone":"Asia/Kathmandu",
    "iso:country":"NP",
    "wof:name":"Belswara",
    "wof:placetype":"locality"
},
  "geometry": {"coordinates":[84.24427,27.75173],"type":"Point"}
}