{
  "type": "Feature",
  "properties": {
    "gn:admin1_code":"FR",
    "gn:admin2_code":"9",
    "gn:admin3_code":"74",
    "gn:admin4_code":"740003",
    "gn:asciiname":"Basain",
    "gn:country_code":"NP",
    "gn:dem":1940,
    "gn:feature_class":"P",
    "gn:feature_code":"PPLL",
    "gn:name":"Basain",
    "gn:population":0,
    "gn:timezone":"Asia/Kathmandu",
    "iso:country":"NP",
    "wof:name":"Basain",
    "wof:placetype":"locality"
},
  "geometry": {"coordinates":[80.52641,29.51104],"type":"Point"}
}