{
  "type": "Feature",
  "properties": {
    "gn:admin1_code":"ER",
    "gn:admin2_code":"13",
    "gn:admin3_code":"11",
    "gn:admin4_code":"110030.0",
    "gn:asciiname":"Nemle",
    "gn:country_code":"NP",
    "gn:dem":1437,
    "gn:feature_class":"P",
    "gn:feature_code":"PPLL",
    "gn:name":"Nemle",
    "gn:population":0,
    "gn:timezone":"Asia/Kathmandu",
    "iso:country":"NP",
    "wof:name":"Nemle",
    "wof:placetype":"locality"
},
  "geometry": {"coordinates":[86.60155999999998,27.38172],"type":"Point"}
}