{
  "type": "Feature",
  "properties": {
    "gn:admin1_code":"WR",
    "gn:admin2_code":"4.0",
    "gn:admin3_code":"39.0",
    "gn:admin4_code":"390061.0",
    "gn:asciiname":"Chilaunebas",
    "gn:country_code":"NP",
    "gn:dem":1026,
    "gn:feature_class":"P",
    "gn:feature_code":"PPLL",
    "gn:name":"Chilaunebas",
    "gn:population":0,
    "gn:timezone":"Asia/Kathmandu",
    "iso:country":"NP",
    "name:ceb_x_preferred":[
        "Chilaunebas"
    ],
    "name:hin_x_preferred":[
        "\u091a\u093f\u0932\u093e\u0909\u0928\u0947\u092c\u093e\u0938"
    ],
    "name:mai_x_preferred":[
        "\u091a\u093f\u0932\u093e\u0909\u0928\u0947\u092c\u093e\u0938"
    ],
    "name:msa_x_preferred":[
        "Chilaunebas"
    ],
    "name:nep_x_preferred":[
        "\u091a\u093f\u0932\u093e\u0909\u0928\u0947\u092c\u093e\u0938"
    ],
    "name:new_x_preferred":[
        "\u091a\u093f\u0932\u093e\u0909\u0928\u0947\u092c\u093e\u0938"
    ],
    "name:pol_x_preferred":[
        "Chilaunebas"
    ],
    "wof:name":"Chilaunebas",
    "wof:placetype":"locality"
},
  "geometry": {"coordinates":[83.78706,28.16944],"type":"Point"}
}