{
  "type": "Feature",
  "properties": {
    "gn:admin1_code":"ER",
    "gn:admin2_code":"7",
    "gn:admin3_code":"10.0",
    "gn:admin4_code":"100032.0",
    "gn:asciiname":"Phalamdhunga",
    "gn:country_code":"NP",
    "gn:dem":1415,
    "gn:feature_class":"P",
    "gn:feature_code":"PPLL",
    "gn:name":"Phalamdhunga",
    "gn:population":0,
    "gn:timezone":"Asia/Kathmandu",
    "iso:country":"NP",
    "wof:name":"Phalamdhunga",
    "wof:placetype":"locality"
},
  "geometry": {"coordinates":[87.11633,27.01283],"type":"Point"}
}