{
  "type": "Feature",
  "properties": {
    "gn:admin1_code":"WR",
    "gn:admin2_code":"4",
    "gn:admin3_code":"40.0",
    "gn:admin4_code":"400022.0",
    "gn:asciiname":"Ghatok Pakho Ban",
    "gn:country_code":"NP",
    "gn:dem":716,
    "gn:feature_class":"P",
    "gn:feature_code":"PPLL",
    "gn:name":"Ghatok Pakho Ban",
    "gn:population":0,
    "gn:timezone":"Asia/Kathmandu",
    "iso:country":"NP",
    "wof:name":"Ghatok Pakho Ban",
    "wof:placetype":"locality"
},
  "geometry": {"coordinates":[84.10375999999999,28.18042],"type":"Point"}
}