{
  "type": "Feature",
  "properties": {
    "gn:admin1_code":"ER",
    "gn:admin2_code":"10",
    "gn:admin3_code":"3.0",
    "gn:admin4_code":"30011.0",
    "gn:asciiname":"Kharkholagaun",
    "gn:country_code":"NP",
    "gn:dem":725,
    "gn:feature_class":"P",
    "gn:feature_code":"PPLL",
    "gn:name":"Kharkholagaun",
    "gn:population":0,
    "gn:timezone":"Asia/Kathmandu",
    "iso:country":"NP",
    "wof:name":"Kharkholagaun",
    "wof:placetype":"locality"
},
  "geometry": {"coordinates":[88.08096,26.79379],"type":"Point"}
}