{
  "type": "Feature",
  "properties": {
    "gn:admin1_code":"WR",
    "gn:admin2_code":"4",
    "gn:admin3_code":"36.0",
    "gn:admin4_code":"360009.0",
    "gn:asciiname":"Aidanda",
    "gn:country_code":"NP",
    "gn:dem":720,
    "gn:feature_class":"P",
    "gn:feature_code":"PPLL",
    "gn:name":"Aidanda",
    "gn:population":0,
    "gn:timezone":"Asia/Kathmandu",
    "iso:country":"NP",
    "wof:name":"Aidanda",
    "wof:placetype":"locality"
},
  "geometry": {"coordinates":[84.68106999999998,27.85127],"type":"Point"}
}