{
  "type": "Feature",
  "properties": {
    "gn:admin1_code":"WR",
    "gn:admin2_code":"4",
    "gn:admin3_code":"40.0",
    "gn:admin4_code":"400031.0",
    "gn:asciiname":"Hog Goth",
    "gn:country_code":"NP",
    "gn:dem":2165,
    "gn:feature_class":"P",
    "gn:feature_code":"PPLL",
    "gn:name":"Hog Goth",
    "gn:population":0,
    "gn:timezone":"Asia/Kathmandu",
    "iso:country":"NP",
    "wof:name":"Hog Goth",
    "wof:placetype":"locality"
},
  "geometry": {"coordinates":[84.1126,28.42602],"type":"Point"}
}