{
  "type": "Feature",
  "properties": {
    "gn:admin1_code":"ER",
    "gn:admin2_code":"7.0",
    "gn:admin3_code":"8.0",
    "gn:admin4_code":"80019.0",
    "gn:asciiname":"Damaigaun",
    "gn:country_code":"NP",
    "gn:dem":1303,
    "gn:feature_class":"P",
    "gn:feature_code":"PPLL",
    "gn:name":"Damaigaun",
    "gn:population":0,
    "gn:timezone":"Asia/Kathmandu",
    "iso:country":"NP",
    "wof:name":"Damaigaun",
    "wof:placetype":"locality"
},
  "geometry": {"coordinates":[87.47889000000001,27.03053],"type":"Point"}
}