{
  "type": "Feature",
  "properties": {
    "gn:admin1_code":"CR",
    "gn:admin2_code":"11",
    "gn:admin3_code":"31",
    "gn:admin4_code":"310010",
    "gn:asciiname":"Bhandarkharka",
    "gn:country_code":"NP",
    "gn:dem":1924,
    "gn:feature_class":"P",
    "gn:feature_code":"PPLL",
    "gn:name":"Bhandarkharka",
    "gn:population":0,
    "gn:timezone":"Asia/Kathmandu",
    "iso:country":"NP",
    "wof:name":"Bhandarkharka",
    "wof:placetype":"locality"
},
  "geometry": {"coordinates":[85.18964,27.66547000000001],"type":"Point"}
}