{
  "type": "Feature",
  "properties": {
    "gn:admin1_code":"WR",
    "gn:admin2_code":"4.0",
    "gn:admin3_code":"38.0",
    "gn:admin4_code":"380003.0",
    "gn:asciiname":"Jhadup",
    "gn:country_code":"NP",
    "gn:dem":635,
    "gn:feature_class":"P",
    "gn:feature_code":"PPLL",
    "gn:name":"Jhadup",
    "gn:population":0,
    "gn:timezone":"Asia/Kathmandu",
    "iso:country":"NP",
    "wof:name":"Jhadup",
    "wof:placetype":"locality"
},
  "geometry": {"coordinates":[84.31764,27.89768],"type":"Point"}
}