{
  "type": "Feature",
  "properties": {
    "gn:gn_country":"NP",
    "gn:gn_fcode":"ADM3",
    "gn:gn_pop":426489,
    "iso:country":"NP",
    "name:unk_x_variant":[
        "Bard\u012ba"
    ],
    "qs:gn_country":"NP",
    "qs:gn_fcode":"ADM3",
    "qs:gn_pop":426489,
    "qs:name":"Bardiya",
    "qs:name_adm0":"Nepal",
    "qs:name_adm1":"Madhya Pashchimanchal",
    "qs:photos":1,
    "qs:photos_1k":1,
    "qs:photos_9k":1,
    "qs:photos_9r":1,
    "qs:photos_all":1,
    "qs:photos_sr":1,
    "qs:placetype":"LocalAdmin",
    "qs:pop_sr":"10",
    "qs:woe_adm0":23424911,
    "qs_pg:aaroncc":"NP",
    "qs_pg:gn_country":"NP",
    "qs_pg:gn_fcode":"ADM3",
    "qs_pg:gn_pop":426489,
    "qs_pg:name":"Bardiya",
    "qs_pg:name_adm0":"Nepal",
    "qs_pg:name_adm1":"Madhya Pashchimanchal",
    "qs_pg:photos":1,
    "qs_pg:photos_1k":1,
    "qs_pg:photos_9k":1,
    "qs_pg:photos_9r":1,
    "qs_pg:photos_all":1,
    "qs_pg:photos_sr":1,
    "qs_pg:pop_sr":10,
    "qs_pg:qs_pg_placetype":"localadmin",
    "qs_pg:qs_pg_placetype_gp":"LocalAdmin",
    "qs_pg:woe_adm0":23424911,
    "wof:name":"Bardiya",
    "wof:placetype":"localadmin",
    "wof:population":426489
},
  "geometry": {"coordinates":[81.41667,28.33333],"type":"Point"}
}