{
  "type": "Feature",
  "properties": {
    "gn:admin1_code":"FR",
    "gn:admin2_code":"14",
    "gn:admin3_code":"71.0",
    "gn:admin4_code":"710028.0",
    "gn:asciiname":"Sayal",
    "gn:country_code":"NP",
    "gn:dem":964,
    "gn:feature_class":"P",
    "gn:feature_code":"PPLL",
    "gn:name":"Sayal",
    "gn:population":0,
    "gn:timezone":"Asia/Kathmandu",
    "iso:country":"NP",
    "wof:name":"Sayal",
    "wof:placetype":"locality"
},
  "geometry": {"coordinates":[80.68901,28.95152],"type":"Point"}
}