{
  "type": "Feature",
  "properties": {
    "gn:admin1_code":"FR",
    "gn:admin2_code":"9",
    "gn:admin3_code":"73.0",
    "gn:admin4_code":"730005.0",
    "gn:asciiname":"Pokhari",
    "gn:country_code":"NP",
    "gn:dem":1606,
    "gn:feature_class":"P",
    "gn:feature_code":"PPLL",
    "gn:name":"Pokhari",
    "gn:population":0,
    "gn:timezone":"Asia/Kathmandu",
    "iso:country":"NP",
    "name:ceb_x_preferred":[
        "Pokhari"
    ],
    "name:fra_x_preferred":[
        "Pokhari"
    ],
    "name:ita_x_preferred":[
        "Pokhari"
    ],
    "name:new_x_preferred":[
        "\u092a\u094b\u0916\u0930\u0940"
    ],
    "name:pol_x_preferred":[
        "Pokhari"
    ],
    "wof:name":"Pokhari",
    "wof:placetype":"locality"
},
  "geometry": {"coordinates":[80.44548,29.28385],"type":"Point"}
}