{
  "type": "Feature",
  "properties": {
    "gn:admin1_code":"FR",
    "gn:admin2_code":"9",
    "gn:admin3_code":"72.0",
    "gn:admin4_code":"720005.0",
    "gn:asciiname":"Jai",
    "gn:country_code":"NP",
    "gn:dem":193,
    "gn:feature_class":"P",
    "gn:feature_code":"PPLL",
    "gn:name":"Jai",
    "gn:population":0,
    "gn:timezone":"Asia/Kathmandu",
    "iso:country":"NP",
    "name:ceb_x_preferred":[
        "Jai"
    ],
    "name:eus_x_preferred":[
        "Jai"
    ],
    "name:swe_x_preferred":[
        "Jai"
    ],
    "wof:name":"Jai",
    "wof:placetype":"locality"
},
  "geometry": {"coordinates":[80.37114,28.80555],"type":"Point"}
}