{
  "type": "Feature",
  "properties": {
    "gn:admin1_code":"MR",
    "gn:admin2_code":"12",
    "gn:admin3_code":"53",
    "gn:admin4_code":"530006",
    "gn:asciiname":"Khara",
    "gn:country_code":"NP",
    "gn:dem":1368,
    "gn:feature_class":"P",
    "gn:feature_code":"PPLL",
    "gn:name":"Khara",
    "gn:population":0,
    "gn:timezone":"Asia/Kathmandu",
    "iso:country":"NP",
    "wof:name":"Khara",
    "wof:placetype":"locality"
},
  "geometry": {"coordinates":[82.50079000000002,28.15145],"type":"Point"}
}