{
  "type": "Feature",
  "properties": {
    "gn:admin1_code":"ER",
    "gn:admin2_code":"10",
    "gn:admin3_code":"2",
    "gn:admin4_code":"20037",
    "gn:asciiname":"Pakhagaun",
    "gn:country_code":"NP",
    "gn:dem":1327,
    "gn:feature_class":"P",
    "gn:feature_code":"PPLL",
    "gn:name":"Pakhagaun",
    "gn:population":0,
    "gn:timezone":"Asia/Kathmandu",
    "iso:country":"NP",
    "wof:name":"Pakhagaun",
    "wof:placetype":"locality"
},
  "geometry": {"coordinates":[87.75697,27.19014],"type":"Point"}
}