{
  "type": "Feature",
  "properties": {
    "gn:admin1_code":"MR",
    "gn:admin2_code":"12",
    "gn:admin3_code":"53",
    "gn:admin4_code":"530026",
    "gn:asciiname":"Gothmare",
    "gn:country_code":"NP",
    "gn:dem":1783,
    "gn:feature_class":"P",
    "gn:feature_code":"PPLL",
    "gn:name":"Gothmare",
    "gn:population":0,
    "gn:timezone":"Asia/Kathmandu",
    "iso:country":"NP",
    "wof:name":"Gothmare",
    "wof:placetype":"locality"
},
  "geometry": {"coordinates":[82.68069,28.28385],"type":"Point"}
}