{
  "type": "Feature",
  "properties": {
    "gn:admin1_code":"CR",
    "gn:admin2_code":"1",
    "gn:admin3_code":"30.0",
    "gn:admin4_code":"300019.0",
    "gn:asciiname":"Ratomate",
    "gn:country_code":"NP",
    "gn:dem":908,
    "gn:feature_class":"P",
    "gn:feature_code":"PPLL",
    "gn:name":"Ratomate",
    "gn:population":0,
    "gn:timezone":"Asia/Kathmandu",
    "iso:country":"NP",
    "wof:name":"Ratomate",
    "wof:placetype":"locality"
},
  "geometry": {"coordinates":[84.8317,27.98319],"type":"Point"}
}