{
  "type": "Feature",
  "properties": {
    "gn:admin1_code":"CR",
    "gn:admin2_code":"1",
    "gn:admin3_code":"24.0",
    "gn:admin4_code":"240045.0",
    "gn:asciiname":"Kirdas",
    "gn:country_code":"NP",
    "gn:dem":843,
    "gn:feature_class":"P",
    "gn:feature_code":"PPLL",
    "gn:name":"Kirdas",
    "gn:population":0,
    "gn:timezone":"Asia/Kathmandu",
    "iso:country":"NP",
    "wof:name":"Kirdas",
    "wof:placetype":"locality"
},
  "geometry": {"coordinates":[85.71621,27.50593],"type":"Point"}
}