{
  "type": "Feature",
  "properties": {
    "gn:admin1_code":"WR",
    "gn:admin2_code":"8",
    "gn:admin3_code":"49",
    "gn:admin4_code":"490053",
    "gn:asciiname":"Sisahaniya",
    "gn:country_code":"NP",
    "gn:dem":111,
    "gn:feature_class":"P",
    "gn:feature_code":"PPLL",
    "gn:name":"Sisahaniya",
    "gn:population":0,
    "gn:timezone":"Asia/Kathmandu",
    "iso:country":"NP",
    "name:fra_x_preferred":[
        "Sisahaniya"
    ],
    "name:new_x_preferred":[
        "\u0938\u093f\u0938\u093e\u0939\u093e\u0928\u093f\u092f\u093e"
    ],
    "name:pol_x_preferred":[
        "Sisahaniya"
    ],
    "wof:name":"Sisahaniya",
    "wof:placetype":"locality"
},
  "geometry": {"coordinates":[83.51434,27.52072],"type":"Point"}
}