{
  "type": "Feature",
  "properties": {
    "gn:admin1_code":"WR",
    "gn:admin2_code":"3",
    "gn:admin3_code":"42",
    "gn:admin4_code":"420014",
    "gn:asciiname":"Tongga",
    "gn:country_code":"NP",
    "gn:dem":3311,
    "gn:feature_class":"P",
    "gn:feature_code":"PPLL",
    "gn:name":"Tongga",
    "gn:population":0,
    "gn:timezone":"Asia/Kathmandu",
    "iso:country":"NP",
    "wof:name":"Tongga",
    "wof:placetype":"locality"
},
  "geometry": {"coordinates":[83.84009,28.82546],"type":"Point"}
}