{
  "type": "Feature",
  "properties": {
    "gn:admin1_code":"MR",
    "gn:admin2_code":"6",
    "gn:admin3_code":"64.0",
    "gn:admin4_code":"640007.0",
    "gn:asciiname":"Panetoli",
    "gn:country_code":"NP",
    "gn:dem":2945,
    "gn:feature_class":"P",
    "gn:feature_code":"PPLL",
    "gn:name":"Panetoli",
    "gn:population":0,
    "gn:timezone":"Asia/Kathmandu",
    "iso:country":"NP",
    "wof:name":"Panetoli",
    "wof:placetype":"locality"
},
  "geometry": {"coordinates":[81.82191999999998,29.18391],"type":"Point"}
}