{
  "type": "Feature",
  "properties": {
    "gn:admin1_code":"ER",
    "gn:admin2_code":"13",
    "gn:admin3_code":"15",
    "gn:admin4_code":"150095",
    "gn:asciiname":"Portaha",
    "gn:country_code":"NP",
    "gn:dem":82,
    "gn:feature_class":"P",
    "gn:feature_code":"PPLL",
    "gn:name":"Portaha",
    "gn:population":0,
    "gn:timezone":"Asia/Kathmandu",
    "iso:country":"NP",
    "name:bih_x_preferred":[
        "\u092a\u094b\u0930\u094d\u0924\u093e\u0939\u093e"
    ],
    "name:ceb_x_preferred":[
        "Portaha"
    ],
    "name:fra_x_preferred":[
        "Portaha"
    ],
    "name:mai_x_preferred":[
        "\u092a\u094b\u0930\u094d\u0924\u093e\u0939\u093e"
    ],
    "name:msa_x_preferred":[
        "Portaha"
    ],
    "name:nep_x_preferred":[
        "\u092a\u094b\u0930\u094d\u0924\u093e\u0939\u093e"
    ],
    "name:new_x_preferred":[
        "\u092a\u094b\u0930\u094d\u0924\u0939\u093e"
    ],
    "name:pol_x_preferred":[
        "Portaha"
    ],
    "wof:name":"Portaha",
    "wof:placetype":"locality"
},
  "geometry": {"coordinates":[86.88849,26.55771],"type":"Point"}
}