{
  "type": "Feature",
  "properties": {
    "gn:admin1_code":"CR",
    "gn:admin2_code":"1",
    "gn:admin3_code":"23",
    "gn:admin4_code":"230008",
    "gn:asciiname":"Mahabhir",
    "gn:country_code":"NP",
    "gn:dem":1862,
    "gn:feature_class":"P",
    "gn:feature_code":"PPLL",
    "gn:name":"Mahabhir",
    "gn:population":0,
    "gn:timezone":"Asia/Kathmandu",
    "iso:country":"NP",
    "wof:name":"Mahabhir",
    "wof:placetype":"locality"
},
  "geometry": {"coordinates":[85.72778000000002,27.83029],"type":"Point"}
}