{
  "type": "Feature",
  "properties": {
    "gn:admin1_code":"ER",
    "gn:admin2_code":"10",
    "gn:admin3_code":"4.0",
    "gn:admin4_code":"40004.0",
    "gn:asciiname":"Chaklachaun",
    "gn:country_code":"NP",
    "gn:dem":89,
    "gn:feature_class":"P",
    "gn:feature_code":"PPLL",
    "gn:name":"Chaklachaun",
    "gn:population":0,
    "gn:timezone":"Asia/Kathmandu",
    "iso:country":"NP",
    "wof:name":"Chaklachaun",
    "wof:placetype":"locality"
},
  "geometry": {"coordinates":[87.74540999999998,26.52193],"type":"Point"}
}