{
  "type": "Feature",
  "properties": {
    "gn:admin1_code":"00",
    "gn:asciiname":"Munigaun",
    "gn:country_code":"NP",
    "gn:dem":3584,
    "gn:feature_class":"P",
    "gn:feature_code":"PPL",
    "gn:name":"Munig\u0101un",
    "gn:population":0,
    "gn:timezone":"Asia/Kathmandu",
    "iso:country":"NP",
    "name:und_x_variant":[
        "Munigaon",
        "Munig\u0101un"
    ],
    "wof:name":"Munigaun",
    "wof:placetype":"locality"
},
  "geometry": {"coordinates":[82.36703,29.21485],"type":"Point"}
}