{
  "type": "Feature",
  "properties": {
    "gn:admin1_code":"CR",
    "gn:admin2_code":"1",
    "gn:admin3_code":"28",
    "gn:admin4_code":"280018",
    "gn:asciiname":"Dadhuwa",
    "gn:country_code":"NP",
    "gn:dem":1409,
    "gn:feature_class":"P",
    "gn:feature_code":"PPLL",
    "gn:name":"Dadhuwa",
    "gn:population":0,
    "gn:timezone":"Asia/Kathmandu",
    "iso:country":"NP",
    "name:bih_x_preferred":[
        "\u0921\u0921\u0941\u0935\u093e"
    ],
    "name:ceb_x_preferred":[
        "Dadhuwa"
    ],
    "name:mai_x_preferred":[
        "\u0921\u0921\u0941\u0935\u093e"
    ],
    "name:msa_x_preferred":[
        "Dadhuwa"
    ],
    "name:nep_x_preferred":[
        "\u0921\u0921\u0941\u0935\u093e"
    ],
    "name:new_x_preferred":[
        "\u0926\u0927\u0941\u0935\u093e"
    ],
    "name:pol_x_preferred":[
        "Dadhuwa"
    ],
    "wof:name":"Dadhuwa",
    "wof:placetype":"locality"
},
  "geometry": {"coordinates":[85.08367,27.81454],"type":"Point"}
}