{
  "type": "Feature",
  "properties": {
    "gn:admin1_code":"FR",
    "gn:admin2_code":"9",
    "gn:admin3_code":"74",
    "gn:admin4_code":"740007",
    "gn:asciiname":"Melghat",
    "gn:country_code":"NP",
    "gn:dem":641,
    "gn:feature_class":"P",
    "gn:feature_code":"PPLL",
    "gn:name":"Melghat",
    "gn:population":0,
    "gn:timezone":"Asia/Kathmandu",
    "iso:country":"NP",
    "name:cat_x_preferred":[
        "Melghat"
    ],
    "name:mar_x_preferred":[
        "\u092e\u0947\u0933\u0918\u093e\u091f \u0905\u092d\u092f\u093e\u0930\u0923\u094d\u092f"
    ],
    "name:urd_x_preferred":[
        "\u0645\u0644\u06af\u06be\u0627\u0679"
    ],
    "wof:name":"Melghat",
    "wof:placetype":"locality"
},
  "geometry": {"coordinates":[80.39881,29.36062],"type":"Point"}
}