{
  "type": "Feature",
  "properties": {
    "gn:admin1_code":"00",
    "gn:asciiname":"Tilpunbesi",
    "gn:country_code":"NP",
    "gn:dem":1091,
    "gn:feature_class":"P",
    "gn:feature_code":"PPL",
    "gn:name":"Tilpu\u1e45besi\u0307\u0304",
    "gn:population":0,
    "gn:timezone":"Asia/Kathmandu",
    "iso:country":"NP",
    "name:nep_x_preferred":[
        "Tilpu\u1e45besi\u0307\u0304"
    ],
    "name:nep_x_variant":[
        "Tilpu\u1e45bes\u012b"
    ],
    "wof:name":"Tilpunbesi",
    "wof:placetype":"locality"
},
  "geometry": {"coordinates":[86.19941999999998,27.17214],"type":"Point"}
}