{
  "type": "Feature",
  "properties": {
    "gn:admin1_code":"ER",
    "gn:admin2_code":"10",
    "gn:admin3_code":"4.0",
    "gn:admin4_code":"40035.0",
    "gn:asciiname":"Gauriyadhargau",
    "gn:country_code":"NP",
    "gn:dem":92,
    "gn:feature_class":"P",
    "gn:feature_code":"PPLL",
    "gn:name":"Gauriyadhargau",
    "gn:population":0,
    "gn:timezone":"Asia/Kathmandu",
    "iso:country":"NP",
    "wof:name":"Gauriyadhargau",
    "wof:placetype":"locality"
},
  "geometry": {"coordinates":[87.69801,26.52324],"type":"Point"}
}