{
  "type": "Feature",
  "properties": {
    "gn:admin1_code":"00",
    "gn:asciiname":"Wapsa Khani",
    "gn:country_code":"NP",
    "gn:dem":1966,
    "gn:feature_class":"P",
    "gn:feature_code":"PPL",
    "gn:name":"W\u0101psa Kh\u0101ni",
    "gn:population":0,
    "gn:timezone":"Asia/Kathmandu",
    "iso:country":"NP",
    "wof:name":"Wapsa Khani",
    "wof:placetype":"locality"
},
  "geometry": {"coordinates":[86.71904000000001,27.51861],"type":"Point"}
}