{
  "type": "Feature",
  "properties": {
    "gn:admin1_code":"ER",
    "gn:admin2_code":"13",
    "gn:admin3_code":"13.0",
    "gn:admin4_code":"130027.0",
    "gn:asciiname":"Buwalung",
    "gn:country_code":"NP",
    "gn:dem":1669,
    "gn:feature_class":"P",
    "gn:feature_code":"PPLL",
    "gn:name":"Buwalung",
    "gn:population":0,
    "gn:timezone":"Asia/Kathmandu",
    "iso:country":"NP",
    "wof:name":"Buwalung",
    "wof:placetype":"locality"
},
  "geometry": {"coordinates":[86.85543,27.22491],"type":"Point"}
}