{
  "type": "Feature",
  "properties": {
    "gn:admin1_code":"CR",
    "gn:admin2_code":"1",
    "gn:admin3_code":"23",
    "gn:admin4_code":"230019",
    "gn:asciiname":"Tinchalnedanda",
    "gn:country_code":"NP",
    "gn:dem":4251,
    "gn:feature_class":"P",
    "gn:feature_code":"PPLL",
    "gn:name":"Tinchalnedanda",
    "gn:population":0,
    "gn:timezone":"Asia/Kathmandu",
    "iso:country":"NP",
    "wof:name":"Tinchalnedanda",
    "wof:placetype":"locality"
},
  "geometry": {"coordinates":[86.05539,27.90231],"type":"Point"}
}