{
  "type": "Feature",
  "properties": {
    "gn:admin1_code":"FR",
    "gn:admin2_code":"14",
    "gn:admin3_code":"71.0",
    "gn:admin4_code":"710032.0",
    "gn:asciiname":"Sadakpur",
    "gn:country_code":"NP",
    "gn:dem":159,
    "gn:feature_class":"P",
    "gn:feature_code":"PPLL",
    "gn:name":"Sadakpur",
    "gn:population":0,
    "gn:timezone":"Asia/Kathmandu",
    "iso:country":"NP",
    "name:urd_x_preferred":[
        "\u0635\u062f\u0627\u06a9\u067e\u0648\u0631"
    ],
    "wof:name":"Sadakpur",
    "wof:placetype":"locality"
},
  "geometry": {"coordinates":[80.80835999999999,28.56339],"type":"Point"}
}