{
  "type": "Feature",
  "properties": {
    "gn:admin1_code":"WR",
    "gn:admin2_code":"4",
    "gn:admin3_code":"37",
    "gn:admin4_code":"370006",
    "gn:asciiname":"Khaliswara",
    "gn:country_code":"NP",
    "gn:dem":1855,
    "gn:feature_class":"P",
    "gn:feature_code":"PPLL",
    "gn:name":"Khaliswara",
    "gn:population":0,
    "gn:timezone":"Asia/Kathmandu",
    "iso:country":"NP",
    "wof:name":"Khaliswara",
    "wof:placetype":"locality"
},
  "geometry": {"coordinates":[84.43084,28.25278],"type":"Point"}
}