{
  "type": "Feature",
  "properties": {
    "gn:admin1_code":"CR",
    "gn:admin2_code":"1",
    "gn:admin3_code":"28",
    "gn:admin4_code":"280020",
    "gn:asciiname":"Bakhre",
    "gn:country_code":"NP",
    "gn:dem":682,
    "gn:feature_class":"P",
    "gn:feature_code":"PPLL",
    "gn:name":"Bakhre",
    "gn:population":0,
    "gn:timezone":"Asia/Kathmandu",
    "iso:country":"NP",
    "wof:name":"Bakhre",
    "wof:placetype":"locality"
},
  "geometry": {"coordinates":[85.26054999999999,27.91535],"type":"Point"}
}