{
  "type": "Feature",
  "properties": {
    "gn:admin1_code":"CR",
    "gn:admin2_code":"1",
    "gn:admin3_code":"23",
    "gn:admin4_code":"230041",
    "gn:asciiname":"Nangedanda",
    "gn:country_code":"NP",
    "gn:dem":1616,
    "gn:feature_class":"P",
    "gn:feature_code":"PPLL",
    "gn:name":"Nangedanda",
    "gn:population":0,
    "gn:timezone":"Asia/Kathmandu",
    "iso:country":"NP",
    "wof:name":"Nangedanda",
    "wof:placetype":"locality"
},
  "geometry": {"coordinates":[85.62734,27.86877],"type":"Point"}
}