{
  "type": "Feature",
  "properties": {
    "gn:admin1_code":"MR",
    "gn:admin2_code":"12",
    "gn:admin3_code":"53",
    "gn:admin4_code":"530018",
    "gn:asciiname":"Titepani",
    "gn:country_code":"NP",
    "gn:dem":1933,
    "gn:feature_class":"P",
    "gn:feature_code":"PPLL",
    "gn:name":"Titepani",
    "gn:population":0,
    "gn:timezone":"Asia/Kathmandu",
    "iso:country":"NP",
    "wof:name":"Titepani",
    "wof:placetype":"locality"
},
  "geometry": {"coordinates":[82.76640999999999,28.34812],"type":"Point"}
}