{
  "type": "Feature",
  "properties": {
    "gn:admin1_code":"CR",
    "gn:admin2_code":"5",
    "gn:admin3_code":"20",
    "gn:admin4_code":"200048",
    "gn:asciiname":"Thuldhunga",
    "gn:country_code":"NP",
    "gn:dem":953,
    "gn:feature_class":"P",
    "gn:feature_code":"PPLL",
    "gn:name":"Thuldhunga",
    "gn:population":0,
    "gn:timezone":"Asia/Kathmandu",
    "iso:country":"NP",
    "wof:name":"Thuldhunga",
    "wof:placetype":"locality"
},
  "geometry": {"coordinates":[86.33481999999999,27.19918],"type":"Point"}
}