{
  "type": "Feature",
  "properties": {
    "gn:admin1_code":"CR",
    "gn:admin2_code":"1",
    "gn:admin3_code":"25",
    "gn:admin4_code":"250001",
    "gn:asciiname":"Lukni",
    "gn:country_code":"NP",
    "gn:dem":823,
    "gn:feature_class":"P",
    "gn:feature_code":"PPLL",
    "gn:name":"Lukni",
    "gn:population":0,
    "gn:timezone":"Asia/Kathmandu",
    "iso:country":"NP",
    "wof:name":"Lukni",
    "wof:placetype":"locality"
},
  "geometry": {"coordinates":[85.31480000000001,27.45136],"type":"Point"}
}