{
  "type": "Feature",
  "properties": {
    "gn:admin1_code":"MR",
    "gn:admin2_code":"2.0",
    "gn:admin3_code":"58.0",
    "gn:admin4_code":"580015.0",
    "gn:asciiname":"Bhagatpurwa",
    "gn:country_code":"NP",
    "gn:dem":166,
    "gn:feature_class":"P",
    "gn:feature_code":"PPLL",
    "gn:name":"Bhagatpurwa",
    "gn:population":0,
    "gn:timezone":"Asia/Kathmandu",
    "iso:country":"NP",
    "wof:name":"Bhagatpurwa",
    "wof:placetype":"locality"
},
  "geometry": {"coordinates":[81.43301,28.34267],"type":"Point"}
}