{
  "type": "Feature",
  "properties": {
    "gn:admin1_code":"WR",
    "gn:admin2_code":"3",
    "gn:admin3_code":"44",
    "gn:admin4_code":"440024",
    "gn:asciiname":"Manmela",
    "gn:country_code":"NP",
    "gn:dem":974,
    "gn:feature_class":"P",
    "gn:feature_code":"PPLL",
    "gn:name":"Manmela",
    "gn:population":0,
    "gn:timezone":"Asia/Kathmandu",
    "iso:country":"NP",
    "wof:name":"Manmela",
    "wof:placetype":"locality"
},
  "geometry": {"coordinates":[83.66764000000001,28.18653],"type":"Point"}
}