{
  "type": "Feature",
  "properties": {
    "gn:admin1_code":"WR",
    "gn:admin2_code":"3",
    "gn:admin3_code":"45.0",
    "gn:admin4_code":"450037.0",
    "gn:asciiname":"Tutiphed",
    "gn:country_code":"NP",
    "gn:dem":1323,
    "gn:feature_class":"P",
    "gn:feature_code":"PPLL",
    "gn:name":"Tutiphed",
    "gn:population":0,
    "gn:timezone":"Asia/Kathmandu",
    "iso:country":"NP",
    "wof:name":"Tutiphed",
    "wof:placetype":"locality"
},
  "geometry": {"coordinates":[83.26026999999998,28.22183],"type":"Point"}
}