{
  "type": "Feature",
  "properties": {
    "gn:admin1_code":"ER",
    "gn:admin2_code":"13",
    "gn:admin3_code":"12",
    "gn:admin4_code":"120024",
    "gn:asciiname":"Mehele",
    "gn:country_code":"NP",
    "gn:dem":2533,
    "gn:feature_class":"P",
    "gn:feature_code":"PPLL",
    "gn:name":"Mehele",
    "gn:population":0,
    "gn:timezone":"Asia/Kathmandu",
    "iso:country":"NP",
    "wof:name":"Mehele",
    "wof:placetype":"locality"
},
  "geometry": {"coordinates":[86.34965,27.42873],"type":"Point"}
}