{
  "type": "Feature",
  "properties": {
    "gn:admin1_code":"MR",
    "gn:admin2_code":"6",
    "gn:admin3_code":"66.0",
    "gn:admin4_code":"660003.0",
    "gn:asciiname":"Narthala",
    "gn:country_code":"NP",
    "gn:dem":3521,
    "gn:feature_class":"P",
    "gn:feature_code":"PPLL",
    "gn:name":"Narthala",
    "gn:population":0,
    "gn:timezone":"Asia/Kathmandu",
    "iso:country":"NP",
    "wof:name":"Narthala",
    "wof:placetype":"locality"
},
  "geometry": {"coordinates":[81.85173,29.90733],"type":"Point"}
}