{
  "type": "Feature",
  "properties": {
    "gn:admin1_code":"WR",
    "gn:admin2_code":"4",
    "gn:admin3_code":"40.0",
    "gn:admin4_code":"400014.0",
    "gn:asciiname":"Sisneghari",
    "gn:country_code":"NP",
    "gn:dem":671,
    "gn:feature_class":"P",
    "gn:feature_code":"PPLL",
    "gn:name":"Sisneghari",
    "gn:population":0,
    "gn:timezone":"Asia/Kathmandu",
    "iso:country":"NP",
    "wof:name":"Sisneghari",
    "wof:placetype":"locality"
},
  "geometry": {"coordinates":[84.19892,28.17078],"type":"Point"}
}