{
  "type": "Feature",
  "properties": {
    "gn:admin1_code":"CR",
    "gn:admin2_code":"11",
    "gn:admin3_code":"31",
    "gn:admin4_code":"310002",
    "gn:asciiname":"Thulo Salle",
    "gn:country_code":"NP",
    "gn:dem":822,
    "gn:feature_class":"P",
    "gn:feature_code":"PPLL",
    "gn:name":"Thulo Salle",
    "gn:population":0,
    "gn:timezone":"Asia/Kathmandu",
    "iso:country":"NP",
    "wof:name":"Thulo Salle",
    "wof:placetype":"locality"
},
  "geometry": {"coordinates":[85.12638000000003,27.4405],"type":"Point"}
}