{
  "type": "Feature",
  "properties": {
    "gn:admin1_code":"ER",
    "gn:admin2_code":"10",
    "gn:admin3_code":"4.0",
    "gn:admin4_code":"40035.0",
    "gn:asciiname":"Maidanghopa",
    "gn:country_code":"NP",
    "gn:dem":105,
    "gn:feature_class":"P",
    "gn:feature_code":"PPLL",
    "gn:name":"Maidanghopa",
    "gn:population":0,
    "gn:timezone":"Asia/Kathmandu",
    "iso:country":"NP",
    "wof:name":"Maidanghopa",
    "wof:placetype":"locality"
},
  "geometry": {"coordinates":[87.69471999999998,26.57808],"type":"Point"}
}