{
  "type": "Feature",
  "properties": {
    "gn:admin1_code":"FR",
    "gn:admin2_code":"9",
    "gn:admin3_code":"75.0",
    "gn:admin4_code":"750028.0",
    "gn:asciiname":"Dhibdiya",
    "gn:country_code":"NP",
    "gn:dem":1670,
    "gn:feature_class":"P",
    "gn:feature_code":"PPLL",
    "gn:name":"Dhibdiya",
    "gn:population":0,
    "gn:timezone":"Asia/Kathmandu",
    "iso:country":"NP",
    "wof:name":"Dhibdiya",
    "wof:placetype":"locality"
},
  "geometry": {"coordinates":[80.48626999999998,29.73091],"type":"Point"}
}