{
  "type": "Feature",
  "properties": {
    "gn:admin1_code":"WR",
    "gn:admin2_code":"3",
    "gn:admin3_code":"45.0",
    "gn:admin4_code":"450029.0",
    "gn:asciiname":"Daleng",
    "gn:country_code":"NP",
    "gn:dem":1648,
    "gn:feature_class":"P",
    "gn:feature_code":"PPLL",
    "gn:name":"Daleng",
    "gn:population":0,
    "gn:timezone":"Asia/Kathmandu",
    "iso:country":"NP",
    "wof:name":"Daleng",
    "wof:placetype":"locality"
},
  "geometry": {"coordinates":[83.49741,28.12545],"type":"Point"}
}