{
  "type": "Feature",
  "properties": {
    "gn:admin1_code":"ER",
    "gn:admin2_code":"7",
    "gn:admin3_code":"9",
    "gn:admin4_code":"90010",
    "gn:asciiname":"Thang Thumbuk",
    "gn:country_code":"NP",
    "gn:dem":1952,
    "gn:feature_class":"P",
    "gn:feature_code":"PPLL",
    "gn:name":"Thang Thumbuk",
    "gn:population":0,
    "gn:timezone":"Asia/Kathmandu",
    "iso:country":"NP",
    "wof:name":"Thang Thumbuk",
    "wof:placetype":"locality"
},
  "geometry": {"coordinates":[87.366,27.75356],"type":"Point"}
}