{
  "type": "Feature",
  "properties": {
    "gn:admin1_code":"ER",
    "gn:admin2_code":"7.0",
    "gn:admin3_code":"6.0",
    "gn:admin4_code":"60023.0",
    "gn:asciiname":"Shantitol",
    "gn:country_code":"NP",
    "gn:dem":135,
    "gn:feature_class":"P",
    "gn:feature_code":"PPLL",
    "gn:name":"Shantitol",
    "gn:population":0,
    "gn:timezone":"Asia/Kathmandu",
    "iso:country":"NP",
    "wof:name":"Shantitol",
    "wof:placetype":"locality"
},
  "geometry": {"coordinates":[87.27264,26.70286],"type":"Point"}
}