{
  "type": "Feature",
  "properties": {
    "gn:admin1_code":"ER",
    "gn:admin2_code":"13",
    "gn:admin3_code":"11",
    "gn:admin4_code":"110034",
    "gn:asciiname":"Rampa",
    "gn:country_code":"NP",
    "gn:dem":1791,
    "gn:feature_class":"P",
    "gn:feature_code":"PPLL",
    "gn:name":"Rampa",
    "gn:population":0,
    "gn:timezone":"Asia/Kathmandu",
    "iso:country":"NP",
    "name:cat_x_preferred":[
        "Rampa"
    ],
    "name:ces_x_preferred":[
        "Rampa"
    ],
    "name:deu_x_preferred":[
        "Rampa"
    ],
    "name:kaz_x_preferred":[
        "\u0420\u0430\u043c\u043f\u0430"
    ],
    "name:pol_x_preferred":[
        "Rampa"
    ],
    "name:por_x_preferred":[
        "Rampa"
    ],
    "name:rus_x_preferred":[
        "\u0420\u0430\u043c\u043f\u0430"
    ],
    "name:srp_x_preferred":[
        "Rampa"
    ],
    "name:ukr_x_preferred":[
        "\u0420\u0430\u043c\u043f\u0430"
    ],
    "wof:name":"Rampa",
    "wof:placetype":"locality"
},
  "geometry": {"coordinates":[86.60643,27.41438],"type":"Point"}
}