{
  "type": "Feature",
  "properties": {
    "gn:admin1_code":"WR",
    "gn:admin2_code":"3",
    "gn:admin3_code":"42",
    "gn:admin4_code":"420016.0",
    "gn:asciiname":"Dhorenjhan",
    "gn:country_code":"NP",
    "gn:dem":2802,
    "gn:feature_class":"P",
    "gn:feature_code":"PPLL",
    "gn:name":"Dhorenjhan",
    "gn:population":0,
    "gn:timezone":"Asia/Kathmandu",
    "iso:country":"NP",
    "wof:name":"Dhorenjhan",
    "wof:placetype":"locality"
},
  "geometry": {"coordinates":[83.67537,28.71608],"type":"Point"}
}