{
  "type": "Feature",
  "properties": {
    "gn:admin1_code":"WR",
    "gn:admin2_code":"8",
    "gn:admin3_code":"47",
    "gn:admin4_code":"470024",
    "gn:asciiname":"Pataksar",
    "gn:country_code":"NP",
    "gn:dem":1183,
    "gn:feature_class":"P",
    "gn:feature_code":"PPLL",
    "gn:name":"Pataksar",
    "gn:population":0,
    "gn:timezone":"Asia/Kathmandu",
    "iso:country":"NP",
    "wof:name":"Pataksar",
    "wof:placetype":"locality"
},
  "geometry": {"coordinates":[83.89955,27.78305],"type":"Point"}
}