{
  "type": "Feature",
  "properties": {
    "gn:admin1_code":"ER",
    "gn:admin2_code":"13",
    "gn:admin3_code":"13",
    "gn:admin4_code":"130060",
    "gn:asciiname":"Kaule",
    "gn:country_code":"NP",
    "gn:dem":1245,
    "gn:feature_class":"P",
    "gn:feature_code":"PPLL",
    "gn:name":"Kaule",
    "gn:population":0,
    "gn:timezone":"Asia/Kathmandu",
    "iso:country":"NP",
    "name:ceb_x_preferred":[
        "Kaule"
    ],
    "name:deu_x_preferred":[
        "Kaule"
    ],
    "name:pol_x_preferred":[
        "Kaule"
    ],
    "name:swe_x_preferred":[
        "Kaule"
    ],
    "wof:name":"Kaule",
    "wof:placetype":"locality"
},
  "geometry": {"coordinates":[86.72787,27.15853],"type":"Point"}
}