{
  "type": "Feature",
  "properties": {
    "gn:admin1_code":"00",
    "gn:asciiname":"Selghat",
    "gn:country_code":"NP",
    "gn:dem":541,
    "gn:feature_class":"P",
    "gn:feature_code":"PPL",
    "gn:name":"Selgh\u0101t",
    "gn:population":0,
    "gn:timezone":"Asia/Kathmandu",
    "iso:country":"NP",
    "name:nep_x_preferred":[
        "Selgh\u0101t"
    ],
    "wof:name":"Selghat",
    "wof:placetype":"locality"
},
  "geometry": {"coordinates":[85.98544,27.34049000000001],"type":"Point"}
}