{
  "type": "Feature",
  "properties": {
    "gn:admin1_code":"ER",
    "gn:admin2_code":"13",
    "gn:admin3_code":"13",
    "gn:admin4_code":"130075.0",
    "gn:asciiname":"Kharbani",
    "gn:country_code":"NP",
    "gn:dem":629,
    "gn:feature_class":"P",
    "gn:feature_code":"PPLL",
    "gn:name":"Kharbani",
    "gn:population":0,
    "gn:timezone":"Asia/Kathmandu",
    "iso:country":"NP",
    "wof:name":"Kharbani",
    "wof:placetype":"locality"
},
  "geometry": {"coordinates":[86.93106999999998,26.92331],"type":"Point"}
}