{
  "type": "Feature",
  "properties": {
    "gn:admin1_code":"ER",
    "gn:admin2_code":"10",
    "gn:admin3_code":"3.0",
    "gn:admin4_code":"30004.0",
    "gn:asciiname":"Chamaita",
    "gn:country_code":"NP",
    "gn:dem":1723,
    "gn:feature_class":"P",
    "gn:feature_code":"PPLL",
    "gn:name":"Chamaita",
    "gn:population":0,
    "gn:timezone":"Asia/Kathmandu",
    "iso:country":"NP",
    "name:bih_x_preferred":[
        "\u091a\u092e\u0948\u0924\u093e"
    ],
    "name:ceb_x_preferred":[
        "Chamaita"
    ],
    "name:mai_x_preferred":[
        "\u091a\u092e\u0948\u0924\u093e"
    ],
    "name:msa_x_preferred":[
        "Chameta"
    ],
    "name:nep_x_preferred":[
        "\u091a\u092e\u0948\u0924\u093e"
    ],
    "name:new_x_preferred":[
        "\u091a\u092e\u0948\u0924\u093e"
    ],
    "name:nld_x_preferred":[
        "Chameta"
    ],
    "name:pol_x_preferred":[
        "Chameta"
    ],
    "wof:name":"Chamaita",
    "wof:placetype":"locality"
},
  "geometry": {"coordinates":[87.83166999999997,27.01331],"type":"Point"}
}