{
  "type": "Feature",
  "properties": {
    "gn:admin1_code":"WR",
    "gn:admin2_code":"4.0",
    "gn:admin3_code":"38.0",
    "gn:admin4_code":"380012.0",
    "gn:asciiname":"Bisaunedanda",
    "gn:country_code":"NP",
    "gn:dem":530,
    "gn:feature_class":"P",
    "gn:feature_code":"PPLL",
    "gn:name":"Bisaunedanda",
    "gn:population":0,
    "gn:timezone":"Asia/Kathmandu",
    "iso:country":"NP",
    "wof:name":"Bisaunedanda",
    "wof:placetype":"locality"
},
  "geometry": {"coordinates":[84.15391,28.00168],"type":"Point"}
}