{
  "type": "Feature",
  "properties": {
    "gn:admin1_code":"FR",
    "gn:admin2_code":"9",
    "gn:admin3_code":"75.0",
    "gn:admin4_code":"750035.0",
    "gn:asciiname":"Bandoli",
    "gn:country_code":"NP",
    "gn:dem":816,
    "gn:feature_class":"P",
    "gn:feature_code":"PPLL",
    "gn:name":"Bandoli",
    "gn:population":0,
    "gn:timezone":"Asia/Kathmandu",
    "iso:country":"NP",
    "wof:name":"Bandoli",
    "wof:placetype":"locality"
},
  "geometry": {"coordinates":[80.50995999999998,29.6623],"type":"Point"}
}