{
  "type": "Feature",
  "properties": {
    "gn:admin1_code":"CR",
    "gn:admin2_code":"1",
    "gn:admin3_code":"28",
    "gn:admin4_code":"280005",
    "gn:asciiname":"Bangesalla",
    "gn:country_code":"NP",
    "gn:dem":1465,
    "gn:feature_class":"P",
    "gn:feature_code":"PPLL",
    "gn:name":"Bangesalla",
    "gn:population":0,
    "gn:timezone":"Asia/Kathmandu",
    "iso:country":"NP",
    "wof:name":"Bangesalla",
    "wof:placetype":"locality"
},
  "geometry": {"coordinates":[85.42319999999999,27.90915],"type":"Point"}
}