{
  "type": "Feature",
  "properties": {
    "gn:admin1_code":"MR",
    "gn:admin2_code":"12",
    "gn:admin3_code":"52",
    "gn:admin4_code":"520020",
    "gn:asciiname":"Dharampa",
    "gn:country_code":"NP",
    "gn:dem":1634,
    "gn:feature_class":"P",
    "gn:feature_code":"PPLL",
    "gn:name":"Dharampa",
    "gn:population":0,
    "gn:timezone":"Asia/Kathmandu",
    "iso:country":"NP",
    "wof:name":"Dharampa",
    "wof:placetype":"locality"
},
  "geometry": {"coordinates":[82.71079,28.07991],"type":"Point"}
}