{
  "type": "Feature",
  "properties": {
    "gn:admin1_code":"CR",
    "gn:admin2_code":"1",
    "gn:admin3_code":"29",
    "gn:admin4_code":"290001",
    "gn:asciiname":"Sarsyu",
    "gn:country_code":"NP",
    "gn:dem":1919,
    "gn:feature_class":"P",
    "gn:feature_code":"PPLL",
    "gn:name":"Sarsyu",
    "gn:population":0,
    "gn:timezone":"Asia/Kathmandu",
    "iso:country":"NP",
    "wof:name":"Sarsyu",
    "wof:placetype":"locality"
},
  "geometry": {"coordinates":[85.24776,28.00938],"type":"Point"}
}