{
  "type": "Feature",
  "properties": {
    "gn:admin1_code":"MR",
    "gn:admin2_code":"12",
    "gn:admin3_code":"53",
    "gn:admin4_code":"530006",
    "gn:asciiname":"Okharpata",
    "gn:country_code":"NP",
    "gn:dem":1409,
    "gn:feature_class":"P",
    "gn:feature_code":"PPLL",
    "gn:name":"Okharpata",
    "gn:population":0,
    "gn:timezone":"Asia/Kathmandu",
    "iso:country":"NP",
    "wof:name":"Okharpata",
    "wof:placetype":"locality"
},
  "geometry": {"coordinates":[82.47244000000001,28.17691],"type":"Point"}
}