{
  "type": "Feature",
  "properties": {
    "gn:admin1_code":"ER",
    "gn:admin2_code":"7.0",
    "gn:admin3_code":"8.0",
    "gn:admin4_code":"80010.0",
    "gn:asciiname":"Chilaunebesi",
    "gn:country_code":"NP",
    "gn:dem":1061,
    "gn:feature_class":"P",
    "gn:feature_code":"PPLL",
    "gn:name":"Chilaunebesi",
    "gn:population":0,
    "gn:timezone":"Asia/Kathmandu",
    "iso:country":"NP",
    "wof:name":"Chilaunebesi",
    "wof:placetype":"locality"
},
  "geometry": {"coordinates":[87.66494,27.26442],"type":"Point"}
}