{
  "type": "Feature",
  "properties": {
    "gn:admin1_code":"CR",
    "gn:admin2_code":"5",
    "gn:admin3_code":"22.0",
    "gn:admin4_code":"220035.0",
    "gn:asciiname":"Gujarpa",
    "gn:country_code":"NP",
    "gn:dem":1713,
    "gn:feature_class":"P",
    "gn:feature_code":"PPLL",
    "gn:name":"Gujarpa",
    "gn:population":0,
    "gn:timezone":"Asia/Kathmandu",
    "iso:country":"NP",
    "wof:name":"Gujarpa",
    "wof:placetype":"locality"
},
  "geometry": {"coordinates":[86.08856999999998,27.74499],"type":"Point"}
}