{
  "type": "Feature",
  "properties": {
    "gn:admin1_code":"CR",
    "gn:admin2_code":"5",
    "gn:admin3_code":"19",
    "gn:admin4_code":"190061.0",
    "gn:asciiname":"Madhubani",
    "gn:country_code":"NP",
    "gn:dem":77,
    "gn:feature_class":"P",
    "gn:feature_code":"PPLL",
    "gn:name":"Madhubani",
    "gn:population":0,
    "gn:timezone":"Asia/Kathmandu",
    "iso:country":"NP",
    "name:fra_x_preferred":[
        "Madhubani"
    ],
    "name:mai_x_preferred":[
        "\u092e\u0927\u0941\u092c\u0928\u0940"
    ],
    "name:nep_x_preferred":[
        "\u092e\u0927\u0941\u092c\u0928\u0940"
    ],
    "name:pol_x_preferred":[
        "Madhubani"
    ],
    "name:urd_x_preferred":[
        "\u0645\u062f\u06be\u0648\u0628\u0627\u0646\u06cc"
    ],
    "wof:name":"Madhubani",
    "wof:placetype":"locality"
},
  "geometry": {"coordinates":[85.4081,26.79908],"type":"Point"}
}