{
  "type": "Feature",
  "properties": {
    "gn:admin1_code":"FR",
    "gn:admin2_code":"9",
    "gn:admin3_code":"72.0",
    "gn:admin4_code":"720013.0",
    "gn:asciiname":"Ranipur",
    "gn:country_code":"NP",
    "gn:dem":195,
    "gn:feature_class":"P",
    "gn:feature_code":"PPLL",
    "gn:name":"Ranipur",
    "gn:population":0,
    "gn:timezone":"Asia/Kathmandu",
    "iso:country":"NP",
    "name:pol_x_preferred":[
        "Ranipur"
    ],
    "name:snd_x_preferred":[
        "\u0631\u0627\u06bb\u064a \u067e\u0648\u0631"
    ],
    "name:urd_x_preferred":[
        "\u0631\u0627\u0646\u06cc \u067e\u0648\u0631"
    ],
    "wof:name":"Ranipur",
    "wof:placetype":"locality"
},
  "geometry": {"coordinates":[80.34338000000002,28.8469],"type":"Point"}
}