{
  "type": "Feature",
  "properties": {
    "gn:admin1_code":"ER",
    "gn:admin2_code":"10",
    "gn:admin3_code":"2",
    "gn:admin4_code":"20041",
    "gn:asciiname":"Hoklumba",
    "gn:country_code":"NP",
    "gn:dem":910,
    "gn:feature_class":"P",
    "gn:feature_code":"PPLL",
    "gn:name":"Hoklumba",
    "gn:population":0,
    "gn:timezone":"Asia/Kathmandu",
    "iso:country":"NP",
    "wof:name":"Hoklumba",
    "wof:placetype":"locality"
},
  "geometry": {"coordinates":[87.59024000000002,27.04135],"type":"Point"}
}