{
  "type": "Feature",
  "properties": {
    "gn:admin1_code":"WR",
    "gn:admin2_code":"4",
    "gn:admin3_code":"36.0",
    "gn:admin4_code":"360014.0",
    "gn:asciiname":"Majhgaun",
    "gn:country_code":"NP",
    "gn:dem":947,
    "gn:feature_class":"P",
    "gn:feature_code":"PPLL",
    "gn:name":"Majhgaun",
    "gn:population":0,
    "gn:timezone":"Asia/Kathmandu",
    "iso:country":"NP",
    "wof:name":"Majhgaun",
    "wof:placetype":"locality"
},
  "geometry": {"coordinates":[84.58497,28.0483],"type":"Point"}
}