{
  "type": "Feature",
  "properties": {
    "gn:admin1_code":"MR",
    "gn:admin2_code":"6",
    "gn:admin3_code":"66.0",
    "gn:admin4_code":"660023.0",
    "gn:asciiname":"Talima",
    "gn:country_code":"NP",
    "gn:dem":2840,
    "gn:feature_class":"P",
    "gn:feature_code":"PPLL",
    "gn:name":"Talima",
    "gn:population":0,
    "gn:timezone":"Asia/Kathmandu",
    "iso:country":"NP",
    "wof:name":"Talima",
    "wof:placetype":"locality"
},
  "geometry": {"coordinates":[82.06085,29.7719],"type":"Point"}
}