{
  "type": "Feature",
  "properties": {
    "gn:admin1_code":"WR",
    "gn:admin2_code":"4",
    "gn:admin3_code":"36.0",
    "gn:admin4_code":"360025.0",
    "gn:asciiname":"Gairichhap",
    "gn:country_code":"NP",
    "gn:dem":1265,
    "gn:feature_class":"P",
    "gn:feature_code":"PPLL",
    "gn:name":"Gairichhap",
    "gn:population":0,
    "gn:timezone":"Asia/Kathmandu",
    "iso:country":"NP",
    "wof:name":"Gairichhap",
    "wof:placetype":"locality"
},
  "geometry": {"coordinates":[84.66334000000001,27.9275],"type":"Point"}
}