{
  "type": "Feature",
  "properties": {
    "gn:admin1_code":"MR",
    "gn:admin2_code":"2.0",
    "gn:admin3_code":"57.0",
    "gn:admin4_code":"570004.0",
    "gn:asciiname":"Phutaha",
    "gn:country_code":"NP",
    "gn:dem":153,
    "gn:feature_class":"P",
    "gn:feature_code":"PPLL",
    "gn:name":"Phutaha",
    "gn:population":0,
    "gn:timezone":"Asia/Kathmandu",
    "iso:country":"NP",
    "wof:name":"Phutaha",
    "wof:placetype":"locality"
},
  "geometry": {"coordinates":[81.66164999999999,28.07388],"type":"Point"}
}