{
  "type": "Feature",
  "properties": {
    "gn:admin1_code":"MR",
    "gn:admin2_code":"2.0",
    "gn:admin3_code":"59.0",
    "gn:admin4_code":"590028.0",
    "gn:asciiname":"Baddichaur",
    "gn:country_code":"NP",
    "gn:dem":555,
    "gn:feature_class":"P",
    "gn:feature_code":"PPLL",
    "gn:name":"Baddichaur",
    "gn:population":0,
    "gn:timezone":"Asia/Kathmandu",
    "iso:country":"NP",
    "wof:name":"Baddichaur",
    "wof:placetype":"locality"
},
  "geometry": {"coordinates":[81.50174,28.71713],"type":"Point"}
}