{
  "type": "Feature",
  "properties": {
    "gn:admin1_code":"WR",
    "gn:admin2_code":"4",
    "gn:admin3_code":"36.0",
    "gn:admin4_code":"360018.0",
    "gn:asciiname":"Dhap",
    "gn:country_code":"NP",
    "gn:dem":331,
    "gn:feature_class":"P",
    "gn:feature_code":"PPLL",
    "gn:name":"Dhap",
    "gn:population":0,
    "gn:timezone":"Asia/Kathmandu",
    "iso:country":"NP",
    "name:ceb_x_preferred":[
        "Dhap"
    ],
    "name:fra_x_preferred":[
        "Dhap"
    ],
    "name:msa_x_preferred":[
        "Dhap"
    ],
    "name:nep_x_preferred":[
        "\u0927\u093e\u092a"
    ],
    "name:new_x_preferred":[
        "\u0927\u093e\u092a"
    ],
    "name:pol_x_preferred":[
        "Dhap"
    ],
    "wof:name":"Dhap",
    "wof:placetype":"locality"
},
  "geometry": {"coordinates":[84.53288000000001,27.91934],"type":"Point"}
}