{
  "type": "Feature",
  "properties": {
    "gn:admin1_code":"FR",
    "gn:admin2_code":"14.0",
    "gn:admin3_code":"67.0",
    "gn:admin4_code":"670027.0",
    "gn:asciiname":"Bachkane",
    "gn:country_code":"NP",
    "gn:dem":1931,
    "gn:feature_class":"P",
    "gn:feature_code":"PPLL",
    "gn:name":"Bachkane",
    "gn:population":0,
    "gn:timezone":"Asia/Kathmandu",
    "iso:country":"NP",
    "wof:name":"Bachkane",
    "wof:placetype":"locality"
},
  "geometry": {"coordinates":[81.37059000000001,29.32163],"type":"Point"}
}