{
  "type": "Feature",
  "properties": {
    "gn:admin1_code":"MR",
    "gn:admin2_code":"12",
    "gn:admin3_code":"56.0",
    "gn:admin4_code":"560035.0",
    "gn:asciiname":"Bagarapur",
    "gn:country_code":"NP",
    "gn:dem":269,
    "gn:feature_class":"P",
    "gn:feature_code":"PPLL",
    "gn:name":"Bagarapur",
    "gn:population":0,
    "gn:timezone":"Asia/Kathmandu",
    "iso:country":"NP",
    "wof:name":"Bagarapur",
    "wof:placetype":"locality"
},
  "geometry": {"coordinates":[82.63639999999999,27.83057],"type":"Point"}
}