{
  "type": "Feature",
  "properties": {
    "gn:admin1_code":"WR",
    "gn:admin2_code":"3",
    "gn:admin3_code":"43",
    "gn:admin4_code":"430026",
    "gn:asciiname":"Thanku",
    "gn:country_code":"NP",
    "gn:dem":2185,
    "gn:feature_class":"P",
    "gn:feature_code":"PPLL",
    "gn:name":"Thanku",
    "gn:population":0,
    "gn:timezone":"Asia/Kathmandu",
    "iso:country":"NP",
    "wof:name":"Thanku",
    "wof:placetype":"locality"
},
  "geometry": {"coordinates":[83.67853000000002,28.51252],"type":"Point"}
}