{
  "type": "Feature",
  "properties": {
    "gn:admin1_code":"MR",
    "gn:admin2_code":"6",
    "gn:admin3_code":"63.0",
    "gn:admin4_code":"630023.0",
    "gn:asciiname":"Banne Bada",
    "gn:country_code":"NP",
    "gn:dem":2668,
    "gn:feature_class":"P",
    "gn:feature_code":"PPLL",
    "gn:name":"Banne Bada",
    "gn:population":0,
    "gn:timezone":"Asia/Kathmandu",
    "iso:country":"NP",
    "wof:name":"Banne Bada",
    "wof:placetype":"locality"
},
  "geometry": {"coordinates":[81.99158,29.34063],"type":"Point"}
}