{
  "type": "Feature",
  "properties": {
    "gn:admin1_code":"FR",
    "gn:admin2_code":"14",
    "gn:admin3_code":"68",
    "gn:admin4_code":"680022",
    "gn:asciiname":"Midi",
    "gn:country_code":"NP",
    "gn:dem":1513,
    "gn:feature_class":"P",
    "gn:feature_code":"PPLL",
    "gn:name":"Midi",
    "gn:population":0,
    "gn:timezone":"Asia/Kathmandu",
    "iso:country":"NP",
    "name:cat_x_preferred":[
        "Midi"
    ],
    "name:ceb_x_preferred":[
        "Midi"
    ],
    "name:deu_x_preferred":[
        "Midi"
    ],
    "name:fra_x_preferred":[
        "Midi"
    ],
    "name:ita_x_preferred":[
        "Midi"
    ],
    "name:nld_x_preferred":[
        "Midi"
    ],
    "name:por_x_preferred":[
        "Midi"
    ],
    "name:spa_x_preferred":[
        "Midi"
    ],
    "name:swe_x_preferred":[
        "Midi"
    ],
    "wof:name":"Midi",
    "wof:placetype":"locality"
},
  "geometry": {"coordinates":[80.86714000000001,29.58678],"type":"Point"}
}