{
  "type": "Feature",
  "properties": {
    "gn:admin1_code":"CR",
    "gn:admin2_code":"1",
    "gn:admin3_code":"28",
    "gn:admin4_code":"280050",
    "gn:asciiname":"Salledanda",
    "gn:country_code":"NP",
    "gn:dem":1261,
    "gn:feature_class":"P",
    "gn:feature_code":"PPLL",
    "gn:name":"Salledanda",
    "gn:population":0,
    "gn:timezone":"Asia/Kathmandu",
    "iso:country":"NP",
    "wof:name":"Salledanda",
    "wof:placetype":"locality"
},
  "geometry": {"coordinates":[85.38183000000002,27.9386],"type":"Point"}
}