{
  "type": "Feature",
  "properties": {
    "gn:admin1_code":"MR",
    "gn:admin2_code":"2",
    "gn:admin3_code":"61.0",
    "gn:admin4_code":"610004.0",
    "gn:asciiname":"Suyara",
    "gn:country_code":"NP",
    "gn:dem":2325,
    "gn:feature_class":"P",
    "gn:feature_code":"PPLL",
    "gn:name":"Suyara",
    "gn:population":0,
    "gn:timezone":"Asia/Kathmandu",
    "iso:country":"NP",
    "wof:name":"Suyara",
    "wof:placetype":"locality"
},
  "geometry": {"coordinates":[81.98085999999998,28.91382],"type":"Point"}
}