{
  "type": "Feature",
  "properties": {
    "gn:admin1_code":"FR",
    "gn:admin2_code":"9",
    "gn:admin3_code":"75.0",
    "gn:admin4_code":"750008.0",
    "gn:asciiname":"Taukhi",
    "gn:country_code":"NP",
    "gn:dem":1291,
    "gn:feature_class":"P",
    "gn:feature_code":"PPLL",
    "gn:name":"Taukhi",
    "gn:population":0,
    "gn:timezone":"Asia/Kathmandu",
    "iso:country":"NP",
    "wof:name":"Taukhi",
    "wof:placetype":"locality"
},
  "geometry": {"coordinates":[80.62189000000002,29.69975],"type":"Point"}
}