{
  "type": "Feature",
  "properties": {
    "gn:admin1_code":"CR",
    "gn:admin2_code":"5",
    "gn:admin3_code":"17.0",
    "gn:admin4_code":"170039.0",
    "gn:asciiname":"Mahjigaun",
    "gn:country_code":"NP",
    "gn:dem":188,
    "gn:feature_class":"P",
    "gn:feature_code":"PPLL",
    "gn:name":"Mahjigaun",
    "gn:population":0,
    "gn:timezone":"Asia/Kathmandu",
    "iso:country":"NP",
    "wof:name":"Mahjigaun",
    "wof:placetype":"locality"
},
  "geometry": {"coordinates":[86.26799,26.91751],"type":"Point"}
}