{
  "type": "Feature",
  "properties": {
    "gn:admin1_code":"FR",
    "gn:admin2_code":"14",
    "gn:admin3_code":"68",
    "gn:admin4_code":"680013",
    "gn:asciiname":"Deulikot",
    "gn:country_code":"NP",
    "gn:dem":1593,
    "gn:feature_class":"P",
    "gn:feature_code":"PPLL",
    "gn:name":"Deulikot",
    "gn:population":0,
    "gn:timezone":"Asia/Kathmandu",
    "iso:country":"NP",
    "wof:name":"Deulikot",
    "wof:placetype":"locality"
},
  "geometry": {"coordinates":[80.81503000000002,29.59526],"type":"Point"}
}