{
  "type": "Feature",
  "properties": {
    "gn:admin1_code":"FR",
    "gn:admin2_code":"14",
    "gn:admin3_code":"68",
    "gn:admin4_code":"680013",
    "gn:asciiname":"Deulikot",
    "gn:country_code":"NP",
    "gn:dem":1593,
    "gn:feature_class":"P",
    "gn:feature_code":"PPLL",
    "gn:name":"Deulikot",
    "gn:population":0,
    "gn:timezone":"Asia/Kathmandu",
    "iso:country":"NP",
    "name:ceb_x_preferred":[
        "Deulikot"
    ],
    "name:mai_x_preferred":[
        "\u0926\u0947\u0909\u0932\u0940\u0915\u094b\u091f"
    ],
    "name:msa_x_preferred":[
        "Deulikot"
    ],
    "name:nep_x_preferred":[
        "\u0926\u0947\u0909\u0932\u0940\u0915\u094b\u091f"
    ],
    "name:new_x_preferred":[
        "\u0926\u0947\u0909\u0932\u0940\u0915\u094b\u0924"
    ],
    "name:pol_x_preferred":[
        "Deulikot"
    ],
    "wof:name":"Deulikot",
    "wof:placetype":"locality"
},
  "geometry": {"coordinates":[80.81503000000002,29.59526],"type":"Point"}
}