{
  "type": "Feature",
  "properties": {
    "gn:admin1_code":"CR",
    "gn:admin2_code":"5",
    "gn:admin3_code":"17.0",
    "gn:admin4_code":"170010.0",
    "gn:asciiname":"Labtoli",
    "gn:country_code":"NP",
    "gn:dem":73,
    "gn:feature_class":"P",
    "gn:feature_code":"PPLL",
    "gn:name":"Labtoli",
    "gn:population":0,
    "gn:timezone":"Asia/Kathmandu",
    "iso:country":"NP",
    "wof:name":"Labtoli",
    "wof:placetype":"locality"
},
  "geometry": {"coordinates":[86.12074,26.63554],"type":"Point"}
}