{
  "type": "Feature",
  "properties": {
    "gn:admin1_code":"MR",
    "gn:admin2_code":"12",
    "gn:admin3_code":"56.0",
    "gn:admin4_code":"560003.0",
    "gn:asciiname":"Dodhariya",
    "gn:country_code":"NP",
    "gn:dem":657,
    "gn:feature_class":"P",
    "gn:feature_code":"PPLL",
    "gn:name":"Dodhariya",
    "gn:population":0,
    "gn:timezone":"Asia/Kathmandu",
    "iso:country":"NP",
    "wof:name":"Dodhariya",
    "wof:placetype":"locality"
},
  "geometry": {"coordinates":[82.34482,28.11848],"type":"Point"}
}