{
  "type": "Feature",
  "properties": {
    "gn:admin1_code":"MR",
    "gn:admin2_code":"2.0",
    "gn:admin3_code":"59.0",
    "gn:admin4_code":"590048.0",
    "gn:asciiname":"Arantura",
    "gn:country_code":"NP",
    "gn:dem":618,
    "gn:feature_class":"P",
    "gn:feature_code":"PPLL",
    "gn:name":"Arantura",
    "gn:population":0,
    "gn:timezone":"Asia/Kathmandu",
    "iso:country":"NP",
    "wof:name":"Arantura",
    "wof:placetype":"locality"
},
  "geometry": {"coordinates":[81.75301,28.56171],"type":"Point"}
}