{
  "type": "Feature",
  "properties": {
    "gn:admin1_code":"WR",
    "gn:admin2_code":"8",
    "gn:admin3_code":"51.0",
    "gn:admin4_code":"510037.0",
    "gn:asciiname":"Laurikot",
    "gn:country_code":"NP",
    "gn:dem":933,
    "gn:feature_class":"P",
    "gn:feature_code":"PPLL",
    "gn:name":"Laurikot",
    "gn:population":0,
    "gn:timezone":"Asia/Kathmandu",
    "iso:country":"NP",
    "wof:name":"Laurikot",
    "wof:placetype":"locality"
},
  "geometry": {"coordinates":[82.90064,27.87154],"type":"Point"}
}