{
  "type": "Feature",
  "properties": {
    "gn:admin1_code":"MR",
    "gn:admin2_code":"12",
    "gn:admin3_code":"54",
    "gn:admin4_code":"540020",
    "gn:asciiname":"Neptikanda",
    "gn:country_code":"NP",
    "gn:dem":1776,
    "gn:feature_class":"P",
    "gn:feature_code":"PPLL",
    "gn:name":"Neptikanda",
    "gn:population":0,
    "gn:timezone":"Asia/Kathmandu",
    "iso:country":"NP",
    "wof:name":"Neptikanda",
    "wof:placetype":"locality"
},
  "geometry": {"coordinates":[82.30949,28.62835],"type":"Point"}
}