{
  "type": "Feature",
  "properties": {
    "gn:admin1_code":"CR",
    "gn:admin2_code":"1",
    "gn:admin3_code":"25",
    "gn:admin4_code":"250010",
    "gn:asciiname":"Khatrigaun",
    "gn:country_code":"NP",
    "gn:dem":1384,
    "gn:feature_class":"P",
    "gn:feature_code":"PPLL",
    "gn:name":"Khatrigaun",
    "gn:population":0,
    "gn:timezone":"Asia/Kathmandu",
    "iso:country":"NP",
    "wof:name":"Khatrigaun",
    "wof:placetype":"locality"
},
  "geometry": {"coordinates":[85.31255,27.60803],"type":"Point"}
}