{
  "type": "Feature",
  "properties": {
    "gn:admin1_code":"MR",
    "gn:admin2_code":"2",
    "gn:admin3_code":"61.0",
    "gn:admin4_code":"610005.0",
    "gn:asciiname":"Chhadi",
    "gn:country_code":"NP",
    "gn:dem":986,
    "gn:feature_class":"P",
    "gn:feature_code":"PPLL",
    "gn:name":"Chhadi",
    "gn:population":0,
    "gn:timezone":"Asia/Kathmandu",
    "iso:country":"NP",
    "wof:name":"Chhadi",
    "wof:placetype":"locality"
},
  "geometry": {"coordinates":[82.28035,28.76178],"type":"Point"}
}