{
  "type": "Feature",
  "properties": {
    "gn:admin1_code":"CR",
    "gn:admin2_code":"5",
    "gn:admin3_code":"20",
    "gn:admin4_code":"200035",
    "gn:asciiname":"Bhalkhada",
    "gn:country_code":"NP",
    "gn:dem":364,
    "gn:feature_class":"P",
    "gn:feature_code":"PPLL",
    "gn:name":"Bhalkhada",
    "gn:population":0,
    "gn:timezone":"Asia/Kathmandu",
    "iso:country":"NP",
    "wof:name":"Bhalkhada",
    "wof:placetype":"locality"
},
  "geometry": {"coordinates":[85.56939,27.273],"type":"Point"}
}