{
  "type": "Feature",
  "properties": {
    "gn:admin1_code":"MR",
    "gn:admin2_code":"12",
    "gn:admin3_code":"54",
    "gn:admin4_code":"540009",
    "gn:asciiname":"Sungurkhal",
    "gn:country_code":"NP",
    "gn:dem":2273,
    "gn:feature_class":"P",
    "gn:feature_code":"PPLL",
    "gn:name":"Sungurkhal",
    "gn:population":0,
    "gn:timezone":"Asia/Kathmandu",
    "iso:country":"NP",
    "wof:name":"Sungurkhal",
    "wof:placetype":"locality"
},
  "geometry": {"coordinates":[82.59104000000001,28.52467],"type":"Point"}
}