{
  "type": "Feature",
  "properties": {
    "gn:admin1_code":"WR",
    "gn:admin2_code":"4",
    "gn:admin3_code":"36.0",
    "gn:admin4_code":"360066.0",
    "gn:asciiname":"Bhinchet",
    "gn:country_code":"NP",
    "gn:dem":1571,
    "gn:feature_class":"P",
    "gn:feature_code":"PPLL",
    "gn:name":"Bhinchet",
    "gn:population":0,
    "gn:timezone":"Asia/Kathmandu",
    "iso:country":"NP",
    "wof:name":"Bhinchet",
    "wof:placetype":"locality"
},
  "geometry": {"coordinates":[84.89083000000002,28.29346],"type":"Point"}
}