{
  "type": "Feature",
  "properties": {
    "gn:admin1_code":"MR",
    "gn:admin2_code":"6",
    "gn:admin3_code":"63.0",
    "gn:admin4_code":"630018.0",
    "gn:asciiname":"Rara",
    "gn:country_code":"NP",
    "gn:dem":2340,
    "gn:feature_class":"P",
    "gn:feature_code":"PPLL",
    "gn:name":"Rara",
    "gn:population":0,
    "gn:timezone":"Asia/Kathmandu",
    "iso:country":"NP",
    "name:deu_x_preferred":[
        "Rara"
    ],
    "name:fra_x_preferred":[
        "Rara"
    ],
    "name:hat_x_preferred":[
        "Rara"
    ],
    "name:rus_x_preferred":[
        "\u0420\u0430\u0440\u0430"
    ],
    "wof:name":"Rara",
    "wof:placetype":"locality"
},
  "geometry": {"coordinates":[81.94513000000001,29.22777],"type":"Point"}
}