{
  "type": "Feature",
  "properties": {
    "gn:admin1_code":"WR",
    "gn:admin2_code":"4",
    "gn:admin3_code":"37",
    "gn:admin4_code":"370027",
    "gn:asciiname":"Khari Bhanjyang",
    "gn:country_code":"NP",
    "gn:dem":1291,
    "gn:feature_class":"P",
    "gn:feature_code":"PPLL",
    "gn:name":"Khari Bhanjyang",
    "gn:population":0,
    "gn:timezone":"Asia/Kathmandu",
    "iso:country":"NP",
    "wof:name":"Khari Bhanjyang",
    "wof:placetype":"locality"
},
  "geometry": {"coordinates":[84.39031999999997,28.17798],"type":"Point"}
}