{
  "type": "Feature",
  "properties": {
    "gn:admin1_code":"CR",
    "gn:admin2_code":"1",
    "gn:admin3_code":"28",
    "gn:admin4_code":"280055",
    "gn:asciiname":"Sep",
    "gn:country_code":"NP",
    "gn:dem":557,
    "gn:feature_class":"P",
    "gn:feature_code":"PPLL",
    "gn:name":"Sep",
    "gn:population":0,
    "gn:timezone":"Asia/Kathmandu",
    "iso:country":"NP",
    "wof:name":"Sep",
    "wof:placetype":"locality"
},
  "geometry": {"coordinates":[85.19074000000001,27.89485],"type":"Point"}
}