{
  "type": "Feature",
  "properties": {
    "gn:admin1_code":"MR",
    "gn:admin2_code":"12",
    "gn:admin3_code":"53",
    "gn:admin4_code":"530038",
    "gn:asciiname":"Rangkot",
    "gn:country_code":"NP",
    "gn:dem":1985,
    "gn:feature_class":"P",
    "gn:feature_code":"PPLL",
    "gn:name":"Rangkot",
    "gn:population":0,
    "gn:timezone":"Asia/Kathmandu",
    "iso:country":"NP",
    "name:ceb_x_preferred":[
        "Rangkot"
    ],
    "name:fra_x_preferred":[
        "Rangkot"
    ],
    "name:mai_x_preferred":[
        "\u0930\u093e\u0919\u094d\u0915\u094b\u091f"
    ],
    "name:msa_x_preferred":[
        "Rangkot"
    ],
    "name:nep_x_preferred":[
        "\u0930\u093e\u0919\u094d\u0915\u094b\u091f"
    ],
    "name:new_x_preferred":[
        "\u0930\u0902\u0917\u0915\u094b\u0924"
    ],
    "name:pol_x_preferred":[
        "Rangkot"
    ],
    "wof:name":"Rangkot",
    "wof:placetype":"locality"
},
  "geometry": {"coordinates":[82.54356999999997,28.48831],"type":"Point"}
}