{
  "type": "Feature",
  "properties": {
    "gn:admin1_code":"ER",
    "gn:admin2_code":"7",
    "gn:admin3_code":"5",
    "gn:admin4_code":"50054",
    "gn:asciiname":"Kalimati",
    "gn:country_code":"NP",
    "gn:dem":1764,
    "gn:feature_class":"P",
    "gn:feature_code":"PPLL",
    "gn:name":"Kalimati",
    "gn:population":0,
    "gn:timezone":"Asia/Kathmandu",
    "iso:country":"NP",
    "wof:name":"Kalimati",
    "wof:placetype":"locality"
},
  "geometry": {"coordinates":[87.47102,26.84533],"type":"Point"}
}