{
  "type": "Feature",
  "properties": {
    "gn:admin1_code":"MR",
    "gn:admin2_code":"6",
    "gn:admin3_code":"64.0",
    "gn:admin4_code":"640008.0",
    "gn:asciiname":"Gaira Kapsadi",
    "gn:country_code":"NP",
    "gn:dem":2121,
    "gn:feature_class":"P",
    "gn:feature_code":"PPLL",
    "gn:name":"Gaira Kapsadi",
    "gn:population":0,
    "gn:timezone":"Asia/Kathmandu",
    "iso:country":"NP",
    "wof:name":"Gaira Kapsadi",
    "wof:placetype":"locality"
},
  "geometry": {"coordinates":[81.84617,29.34604],"type":"Point"}
}