{
  "type": "Feature",
  "properties": {
    "gn:admin1_code":"ER",
    "gn:admin2_code":"7",
    "gn:admin3_code":"7.0",
    "gn:admin4_code":"70022.0",
    "gn:asciiname":"Adheri",
    "gn:country_code":"NP",
    "gn:dem":1295,
    "gn:feature_class":"P",
    "gn:feature_code":"PPLL",
    "gn:name":"Adheri",
    "gn:population":0,
    "gn:timezone":"Asia/Kathmandu",
    "iso:country":"NP",
    "wof:name":"Adheri",
    "wof:placetype":"locality"
},
  "geometry": {"coordinates":[87.50875000000001,26.93574000000001],"type":"Point"}
}