{
  "type": "Feature",
  "properties": {
    "gn:admin1_code":"ER",
    "gn:admin2_code":"13.0",
    "gn:admin3_code":"14.0",
    "gn:admin4_code":"140020.0",
    "gn:asciiname":"Lapha Bhanjyang",
    "gn:country_code":"NP",
    "gn:dem":1299,
    "gn:feature_class":"P",
    "gn:feature_code":"PPLL",
    "gn:name":"Lapha Bhanjyang",
    "gn:population":0,
    "gn:timezone":"Asia/Kathmandu",
    "iso:country":"NP",
    "wof:name":"Lapha Bhanjyang",
    "wof:placetype":"locality"
},
  "geometry": {"coordinates":[86.69449,27.04162],"type":"Point"}
}