{
  "type": "Feature",
  "properties": {
    "gn:admin1_code":"FR",
    "gn:admin2_code":"14.0",
    "gn:admin3_code":"67.0",
    "gn:admin4_code":"670014.0",
    "gn:asciiname":"Ganjra",
    "gn:country_code":"NP",
    "gn:dem":1940,
    "gn:feature_class":"P",
    "gn:feature_code":"PPLL",
    "gn:name":"Ganjra",
    "gn:population":0,
    "gn:timezone":"Asia/Kathmandu",
    "iso:country":"NP",
    "wof:name":"Ganjra",
    "wof:placetype":"locality"
},
  "geometry": {"coordinates":[81.25381,29.36601],"type":"Point"}
}