{
  "type": "Feature",
  "properties": {
    "gn:admin1_code":"WR",
    "gn:admin2_code":"3",
    "gn:admin3_code":"45.0",
    "gn:admin4_code":"450005.0",
    "gn:asciiname":"Syal pakha",
    "gn:country_code":"NP",
    "gn:dem":3028,
    "gn:feature_class":"P",
    "gn:feature_code":"PPLL",
    "gn:name":"Syal pakha",
    "gn:population":0,
    "gn:timezone":"Asia/Kathmandu",
    "iso:country":"NP",
    "wof:name":"Syal pakha",
    "wof:placetype":"locality"
},
  "geometry": {"coordinates":[83.04318000000001,28.5036],"type":"Point"}
}