{
  "type": "Feature",
  "properties": {
    "gn:admin1_code":"ER",
    "gn:admin2_code":"10",
    "gn:admin3_code":"4.0",
    "gn:admin4_code":"40021.0",
    "gn:asciiname":"Buwalmadi",
    "gn:country_code":"NP",
    "gn:dem":71,
    "gn:feature_class":"P",
    "gn:feature_code":"PPLL",
    "gn:name":"Buwalmadi",
    "gn:population":0,
    "gn:timezone":"Asia/Kathmandu",
    "iso:country":"NP",
    "wof:name":"Buwalmadi",
    "wof:placetype":"locality"
},
  "geometry": {"coordinates":[87.95865999999999,26.42403],"type":"Point"}
}