{
  "type": "Feature",
  "properties": {
    "gn:admin1_code":"FR",
    "gn:admin2_code":"9",
    "gn:admin3_code":"74",
    "gn:admin4_code":"740013",
    "gn:asciiname":"Kaphalda",
    "gn:country_code":"NP",
    "gn:dem":1237,
    "gn:feature_class":"P",
    "gn:feature_code":"PPLL",
    "gn:name":"Kaphalda",
    "gn:population":0,
    "gn:timezone":"Asia/Kathmandu",
    "iso:country":"NP",
    "wof:name":"Kaphalda",
    "wof:placetype":"locality"
},
  "geometry": {"coordinates":[80.54167,29.6179],"type":"Point"}
}