{
  "type": "Feature",
  "properties": {
    "gn:admin1_code":"CR",
    "gn:admin2_code":"5",
    "gn:admin3_code":"22.0",
    "gn:admin4_code":"220040.0",
    "gn:asciiname":"Nausayabigha",
    "gn:country_code":"NP",
    "gn:dem":839,
    "gn:feature_class":"P",
    "gn:feature_code":"PPLL",
    "gn:name":"Nausayabigha",
    "gn:population":0,
    "gn:timezone":"Asia/Kathmandu",
    "iso:country":"NP",
    "wof:name":"Nausayabigha",
    "wof:placetype":"locality"
},
  "geometry": {"coordinates":[86.08181999999999,27.52404000000001],"type":"Point"}
}