{
  "type": "Feature",
  "properties": {
    "gn:admin1_code":"WR",
    "gn:admin2_code":"8",
    "gn:admin3_code":"47",
    "gn:admin4_code":"470015",
    "gn:asciiname":"Ghorbanda",
    "gn:country_code":"NP",
    "gn:dem":1185,
    "gn:feature_class":"P",
    "gn:feature_code":"PPLL",
    "gn:name":"Ghorbanda",
    "gn:population":0,
    "gn:timezone":"Asia/Kathmandu",
    "iso:country":"NP",
    "wof:name":"Ghorbanda",
    "wof:placetype":"locality"
},
  "geometry": {"coordinates":[83.57388,27.87038],"type":"Point"}
}