{
  "type": "Feature",
  "properties": {
    "gn:admin1_code":"CR",
    "gn:admin2_code":"11.0",
    "gn:admin3_code":"33.0",
    "gn:admin4_code":"330060.0",
    "gn:asciiname":"Madhurijabdi",
    "gn:country_code":"NP",
    "gn:dem":96,
    "gn:feature_class":"P",
    "gn:feature_code":"PPLL",
    "gn:name":"Madhurijabdi",
    "gn:population":0,
    "gn:timezone":"Asia/Kathmandu",
    "iso:country":"NP",
    "name:ceb_x_preferred":[
        "Madhurijabdi"
    ],
    "name:fra_x_preferred":[
        "Madhurijabdi"
    ],
    "name:mai_x_preferred":[
        "\u092e\u0927\u0941\u0930\u0940\u091c\u092c\u094d\u0926\u0940"
    ],
    "name:msa_x_preferred":[
        "Madhurijabdi"
    ],
    "name:nep_x_preferred":[
        "\u092e\u0927\u0941\u0930\u0940\u091c\u092c\u094d\u0926\u0940"
    ],
    "name:new_x_preferred":[
        "\u092e\u0927\u0941\u0930\u093f\u091c\u092c\u094d\u0926\u0940"
    ],
    "name:pol_x_preferred":[
        "Madhurijabdi"
    ],
    "name:urd_x_preferred":[
        "\u0645\u062f\u06be\u0648\u0631\u06cc\u062c\u0627\u0628\u0688\u06cc"
    ],
    "wof:name":"Madhurijabdi",
    "wof:placetype":"locality"
},
  "geometry": {"coordinates":[85.07848,26.9922],"type":"Point"}
}