{
  "type": "Feature",
  "properties": {
    "gn:admin1_code":"CR",
    "gn:admin2_code":"5",
    "gn:admin3_code":"17.0",
    "gn:admin4_code":"170048.0",
    "gn:asciiname":"Rampur",
    "gn:country_code":"NP",
    "gn:dem":74,
    "gn:feature_class":"P",
    "gn:feature_code":"PPLL",
    "gn:name":"Rampur",
    "gn:population":0,
    "gn:timezone":"Asia/Kathmandu",
    "iso:country":"NP",
    "name:ben_x_preferred":[
        "\u09b0\u09be\u09ae\u09aa\u09c1\u09b0"
    ],
    "name:bih_x_preferred":[
        "\u0930\u093e\u092e\u092a\u0941\u0930"
    ],
    "name:bpy_x_preferred":[
        "\u09b0\u09be\u09ae\u09aa\u09c1\u09b0"
    ],
    "name:cat_x_preferred":[
        "Rampur"
    ],
    "name:ceb_x_preferred":[
        "Rampur"
    ],
    "name:deu_x_preferred":[
        "Rampur"
    ],
    "name:ell_x_preferred":[
        "\u03a1\u03b1\u03bc\u03c0\u03bf\u03cd\u03c1"
    ],
    "name:fra_x_preferred":[
        "Rampur"
    ],
    "name:heb_x_preferred":[
        "\u05e8\u05de\u05e4\u05d5\u05e8"
    ],
    "name:hun_x_preferred":[
        "Rampur"
    ],
    "name:ind_x_preferred":[
        "Rampur"
    ],
    "name:ita_x_preferred":[
        "Rampur"
    ],
    "name:new_x_preferred":[
        "\u0930\u093e\u092e\u092a\u0941\u0930"
    ],
    "name:nld_x_preferred":[
        "Rampur"
    ],
    "name:pnb_x_preferred":[
        "\u0631\u0627\u0645 \u067e\u0648\u0631"
    ],
    "name:pol_x_preferred":[
        "Rampur"
    ],
    "name:rus_x_preferred":[
        "\u0420\u0430\u043c\u043f\u0443\u0440"
    ],
    "name:snd_x_preferred":[
        "\u0631\u0627\u0645 \u067e\u0648\u0631"
    ],
    "name:swe_x_preferred":[
        "Rampur"
    ],
    "name:tur_x_preferred":[
        "Rampur"
    ],
    "name:ukr_x_preferred":[
        "\u0420\u0430\u043c\u043f\u0443\u0440"
    ],
    "name:urd_x_preferred":[
        "\u0631\u0627\u0645 \u067e\u0648\u0631"
    ],
    "name:vie_x_preferred":[
        "Rampur"
    ],
    "wof:name":"Rampur",
    "wof:placetype":"locality"
},
  "geometry": {"coordinates":[85.93922000000001,26.7042],"type":"Point"}
}