{
  "type": "Feature",
  "properties": {
    "gn:admin1_code":"CR",
    "gn:admin2_code":"11",
    "gn:admin3_code":"31",
    "gn:admin4_code":"310016",
    "gn:asciiname":"Simaldhop",
    "gn:country_code":"NP",
    "gn:dem":418,
    "gn:feature_class":"P",
    "gn:feature_code":"PPLL",
    "gn:name":"Simaldhop",
    "gn:population":0,
    "gn:timezone":"Asia/Kathmandu",
    "iso:country":"NP",
    "wof:name":"Simaldhop",
    "wof:placetype":"locality"
},
  "geometry": {"coordinates":[85.33532,27.36687],"type":"Point"}
}