{
  "type": "Feature",
  "properties": {
    "gn:admin1_code":"CR",
    "gn:admin2_code":"1",
    "gn:admin3_code":"28",
    "gn:admin4_code":"280026",
    "gn:asciiname":"Besikateri",
    "gn:country_code":"NP",
    "gn:dem":619,
    "gn:feature_class":"P",
    "gn:feature_code":"PPLL",
    "gn:name":"Besikateri",
    "gn:population":0,
    "gn:timezone":"Asia/Kathmandu",
    "iso:country":"NP",
    "wof:name":"Besikateri",
    "wof:placetype":"locality"
},
  "geometry": {"coordinates":[85.28913,27.91722],"type":"Point"}
}