{
  "type": "Feature",
  "properties": {
    "gn:admin1_code":"ER",
    "gn:admin2_code":"7",
    "gn:admin3_code":"10.0",
    "gn:admin4_code":"100017.0",
    "gn:asciiname":"Sangpabuk",
    "gn:country_code":"NP",
    "gn:dem":2051,
    "gn:feature_class":"P",
    "gn:feature_code":"PPLL",
    "gn:name":"Sangpabuk",
    "gn:population":0,
    "gn:timezone":"Asia/Kathmandu",
    "iso:country":"NP",
    "wof:name":"Sangpabuk",
    "wof:placetype":"locality"
},
  "geometry": {"coordinates":[86.93398000000001,27.23229000000001],"type":"Point"}
}