{
  "type": "Feature",
  "properties": {
    "gn:admin1_code":"WR",
    "gn:admin2_code":"8",
    "gn:admin3_code":"50.0",
    "gn:admin4_code":"500063.0",
    "gn:asciiname":"Pakreti",
    "gn:country_code":"NP",
    "gn:dem":108,
    "gn:feature_class":"P",
    "gn:feature_code":"PPLL",
    "gn:name":"Pakreti",
    "gn:population":0,
    "gn:timezone":"Asia/Kathmandu",
    "iso:country":"NP",
    "wof:name":"Pakreti",
    "wof:placetype":"locality"
},
  "geometry": {"coordinates":[83.00386,27.60592],"type":"Point"}
}