{
  "type": "Feature",
  "properties": {
    "gn:admin1_code":"CR",
    "gn:admin2_code":"11.0",
    "gn:admin3_code":"33.0",
    "gn:admin4_code":"330041.0",
    "gn:asciiname":"Golgonj",
    "gn:country_code":"NP",
    "gn:dem":85,
    "gn:feature_class":"P",
    "gn:feature_code":"PPLL",
    "gn:name":"Golgonj",
    "gn:population":0,
    "gn:timezone":"Asia/Kathmandu",
    "iso:country":"NP",
    "wof:name":"Golgonj",
    "wof:placetype":"locality"
},
  "geometry": {"coordinates":[85.13113,26.88637],"type":"Point"}
}