{
  "type": "Feature",
  "properties": {
    "gn:admin1_code":"CR",
    "gn:admin2_code":"1",
    "gn:admin3_code":"29",
    "gn:admin4_code":"290014",
    "gn:asciiname":"Chandanbari",
    "gn:country_code":"NP",
    "gn:dem":3433,
    "gn:feature_class":"P",
    "gn:feature_code":"PPLL",
    "gn:name":"Chandanbari",
    "gn:population":0,
    "gn:timezone":"Asia/Kathmandu",
    "iso:country":"NP",
    "wof:name":"Chandanbari",
    "wof:placetype":"locality"
},
  "geometry": {"coordinates":[85.34344,28.11154],"type":"Point"}
}