{
  "type": "Feature",
  "properties": {
    "gn:admin1_code":"FR",
    "gn:admin2_code":"9",
    "gn:admin3_code":"75.0",
    "gn:admin4_code":"750040.0",
    "gn:asciiname":"Lataun",
    "gn:country_code":"NP",
    "gn:dem":1806,
    "gn:feature_class":"P",
    "gn:feature_code":"PPLL",
    "gn:name":"Lataun",
    "gn:population":0,
    "gn:timezone":"Asia/Kathmandu",
    "iso:country":"NP",
    "wof:name":"Lataun",
    "wof:placetype":"locality"
},
  "geometry": {"coordinates":[80.78355000000001,29.75742],"type":"Point"}
}