{
  "type": "Feature",
  "properties": {
    "gn:admin1_code":"CR",
    "gn:admin2_code":"1",
    "gn:admin3_code":"30.0",
    "gn:admin4_code":"300007.0",
    "gn:asciiname":"Rampurtar",
    "gn:country_code":"NP",
    "gn:dem":508,
    "gn:feature_class":"P",
    "gn:feature_code":"PPLL",
    "gn:name":"Rampurtar",
    "gn:population":0,
    "gn:timezone":"Asia/Kathmandu",
    "iso:country":"NP",
    "wof:name":"Rampurtar",
    "wof:placetype":"locality"
},
  "geometry": {"coordinates":[84.74592,27.94783],"type":"Point"}
}