{
  "type": "Feature",
  "properties": {
    "gn:admin1_code":"FR",
    "gn:admin2_code":"14",
    "gn:admin3_code":"69",
    "gn:admin4_code":"690036",
    "gn:asciiname":"Ranku",
    "gn:country_code":"NP",
    "gn:dem":1218,
    "gn:feature_class":"P",
    "gn:feature_code":"PPLL",
    "gn:name":"Ranku",
    "gn:population":0,
    "gn:timezone":"Asia/Kathmandu",
    "iso:country":"NP",
    "wof:name":"Ranku",
    "wof:placetype":"locality"
},
  "geometry": {"coordinates":[81.48917,29.11539],"type":"Point"}
}