{
  "type": "Feature",
  "properties": {
    "gn:admin1_code":"WR",
    "gn:admin2_code":"8",
    "gn:admin3_code":"47",
    "gn:admin4_code":"470040.0",
    "gn:asciiname":"Tallo Khadsyauli",
    "gn:country_code":"NP",
    "gn:dem":1239,
    "gn:feature_class":"P",
    "gn:feature_code":"PPLL",
    "gn:name":"Tallo Khadsyauli",
    "gn:population":0,
    "gn:timezone":"Asia/Kathmandu",
    "iso:country":"NP",
    "wof:name":"Tallo Khadsyauli",
    "wof:placetype":"locality"
},
  "geometry": {"coordinates":[83.46475,27.86729],"type":"Point"}
}