{
  "type": "Feature",
  "properties": {
    "gn:admin1_code":"FR",
    "gn:admin2_code":"14",
    "gn:admin3_code":"70.0",
    "gn:admin4_code":"700005.0",
    "gn:asciiname":"Kotigaun",
    "gn:country_code":"NP",
    "gn:dem":1178,
    "gn:feature_class":"P",
    "gn:feature_code":"PPLL",
    "gn:name":"Kotigaun",
    "gn:population":0,
    "gn:timezone":"Asia/Kathmandu",
    "iso:country":"NP",
    "wof:name":"Kotigaun",
    "wof:placetype":"locality"
},
  "geometry": {"coordinates":[80.92508000000002,29.19662000000001],"type":"Point"}
}