{
  "type": "Feature",
  "properties": {
    "gn:admin1_code":"MR",
    "gn:admin2_code":"2",
    "gn:admin3_code":"60.0",
    "gn:admin4_code":"600039.0",
    "gn:asciiname":"Ramche",
    "gn:country_code":"NP",
    "gn:dem":1365,
    "gn:feature_class":"P",
    "gn:feature_code":"PPLL",
    "gn:name":"Ramche",
    "gn:population":0,
    "gn:timezone":"Asia/Kathmandu",
    "iso:country":"NP",
    "wof:name":"Ramche",
    "wof:placetype":"locality"
},
  "geometry": {"coordinates":[81.82038,28.92065],"type":"Point"}
}