{
  "type": "Feature",
  "properties": {
    "gn:admin1_code":"CR",
    "gn:admin2_code":"5",
    "gn:admin3_code":"20",
    "gn:admin4_code":"200030",
    "gn:asciiname":"Banjhankri",
    "gn:country_code":"NP",
    "gn:dem":295,
    "gn:feature_class":"P",
    "gn:feature_code":"PPLL",
    "gn:name":"Banjhankri",
    "gn:population":0,
    "gn:timezone":"Asia/Kathmandu",
    "iso:country":"NP",
    "wof:name":"Banjhankri",
    "wof:placetype":"locality"
},
  "geometry": {"coordinates":[85.56278,27.19809],"type":"Point"}
}