{
  "type": "Feature",
  "properties": {
    "gn:admin1_code":"CR",
    "gn:admin2_code":"11",
    "gn:admin3_code":"32",
    "gn:admin4_code":"320043",
    "gn:asciiname":"Piparatola",
    "gn:country_code":"NP",
    "gn:dem":79,
    "gn:feature_class":"P",
    "gn:feature_code":"PPLL",
    "gn:name":"Piparatola",
    "gn:population":0,
    "gn:timezone":"Asia/Kathmandu",
    "iso:country":"NP",
    "wof:name":"Piparatola",
    "wof:placetype":"locality"
},
  "geometry": {"coordinates":[85.29233000000001,26.81088],"type":"Point"}
}