{
  "type": "Feature",
  "properties": {
    "gn:admin1_code":"MR",
    "gn:admin2_code":"2.0",
    "gn:admin3_code":"59.0",
    "gn:admin4_code":"590045.0",
    "gn:asciiname":"Chautara",
    "gn:country_code":"NP",
    "gn:dem":1274,
    "gn:feature_class":"P",
    "gn:feature_code":"PPLL",
    "gn:name":"Chautara",
    "gn:population":0,
    "gn:timezone":"Asia/Kathmandu",
    "iso:country":"NP",
    "name:deu_x_preferred":[
        "Chautara"
    ],
    "name:fin_x_preferred":[
        "Chautara"
    ],
    "name:fra_x_preferred":[
        "Chautara"
    ],
    "name:mai_x_preferred":[
        "\u091a\u094c\u0924\u093e\u0930\u093e \u0928\u0917\u0930\u092a\u093e\u0932\u093f\u0915\u093e"
    ],
    "name:nld_x_preferred":[
        "Chautara"
    ],
    "name:por_x_preferred":[
        "Chautara"
    ],
    "name:urd_x_preferred":[
        "\u0686\u0627\u0648\u062a\u0627\u0631\u0627"
    ],
    "wof:name":"Chautara",
    "wof:placetype":"locality"
},
  "geometry": {"coordinates":[81.69672,28.62384],"type":"Point"}
}