{
  "type": "Feature",
  "properties": {
    "gn:admin1_code":"00",
    "gn:asciiname":"Dhamite",
    "gn:country_code":"NP",
    "gn:dem":316,
    "gn:feature_class":"P",
    "gn:feature_code":"PPL",
    "gn:name":"Dhamite",
    "gn:population":0,
    "gn:timezone":"Asia/Kathmandu",
    "iso:country":"NP",
    "wof:name":"Dhamite",
    "wof:placetype":"locality"
},
  "geometry": {"coordinates":[85.72011999999999,27.26719000000001],"type":"Point"}
}