{
  "type": "Feature",
  "properties": {
    "gn:admin1_code":"WR",
    "gn:admin2_code":"8",
    "gn:admin3_code":"48",
    "gn:admin4_code":"480022",
    "gn:asciiname":"Haldi",
    "gn:country_code":"NP",
    "gn:dem":111,
    "gn:feature_class":"P",
    "gn:feature_code":"PPLL",
    "gn:name":"Haldi",
    "gn:population":0,
    "gn:timezone":"Asia/Kathmandu",
    "iso:country":"NP",
    "name:ceb_x_preferred":[
        "Haldi"
    ],
    "name:deu_x_preferred":[
        "Haldi"
    ],
    "name:sco_x_preferred":[
        "Haldi"
    ],
    "name:swe_x_preferred":[
        "Haldi"
    ],
    "wof:name":"Haldi",
    "wof:placetype":"locality"
},
  "geometry": {"coordinates":[83.64887,27.46847],"type":"Point"}
}