{
  "type": "Feature",
  "properties": {
    "gn:admin1_code":"MR",
    "gn:admin2_code":"12",
    "gn:admin3_code":"54",
    "gn:admin4_code":"540009",
    "gn:asciiname":"Simkholagaun",
    "gn:country_code":"NP",
    "gn:dem":2112,
    "gn:feature_class":"P",
    "gn:feature_code":"PPLL",
    "gn:name":"Simkholagaun",
    "gn:population":0,
    "gn:timezone":"Asia/Kathmandu",
    "iso:country":"NP",
    "wof:name":"Simkholagaun",
    "wof:placetype":"locality"
},
  "geometry": {"coordinates":[82.53869,28.55958],"type":"Point"}
}