{
  "type": "Feature",
  "properties": {
    "gn:admin1_code":"FR",
    "gn:admin2_code":"9",
    "gn:admin3_code":"75.0",
    "gn:admin4_code":"750024.0",
    "gn:asciiname":"Pari Jamir",
    "gn:country_code":"NP",
    "gn:dem":1901,
    "gn:feature_class":"P",
    "gn:feature_code":"PPLL",
    "gn:name":"Pari Jamir",
    "gn:population":0,
    "gn:timezone":"Asia/Kathmandu",
    "iso:country":"NP",
    "wof:name":"Pari Jamir",
    "wof:placetype":"locality"
},
  "geometry": {"coordinates":[80.66421,29.78256],"type":"Point"}
}