{
  "type": "Feature",
  "properties": {
    "gn:admin1_code":"00",
    "gn:asciiname":"Basbote",
    "gn:country_code":"NP",
    "gn:dem":965,
    "gn:feature_class":"P",
    "gn:feature_code":"PPL",
    "gn:name":"B\u0101\u0303sbo\u1e6de",
    "gn:population":0,
    "gn:timezone":"Asia/Kathmandu",
    "iso:country":"NP",
    "name:nep_x_preferred":[
        "B\u0101\u0303sbo\u1e6de"
    ],
    "wof:name":"Basbote",
    "wof:placetype":"locality"
},
  "geometry": {"coordinates":[86.70863,26.96971],"type":"Point"}
}