{
  "type": "Feature",
  "properties": {
    "gn:admin1_code":"CR",
    "gn:admin2_code":"1",
    "gn:admin3_code":"23",
    "gn:admin4_code":"230049.0",
    "gn:asciiname":"Paragang",
    "gn:country_code":"NP",
    "gn:dem":1994,
    "gn:feature_class":"P",
    "gn:feature_code":"PPLL",
    "gn:name":"Paragang",
    "gn:population":0,
    "gn:timezone":"Asia/Kathmandu",
    "iso:country":"NP",
    "wof:name":"Paragang",
    "wof:placetype":"locality"
},
  "geometry": {"coordinates":[85.65553,27.96327],"type":"Point"}
}