{
  "type": "Feature",
  "properties": {
    "gn:admin1_code":"WR",
    "gn:admin2_code":"4.0",
    "gn:admin3_code":"38.0",
    "gn:admin4_code":"380043.0",
    "gn:asciiname":"Tallosyamgha",
    "gn:country_code":"NP",
    "gn:dem":638,
    "gn:feature_class":"P",
    "gn:feature_code":"PPLL",
    "gn:name":"Tallosyamgha",
    "gn:population":0,
    "gn:timezone":"Asia/Kathmandu",
    "iso:country":"NP",
    "wof:name":"Tallosyamgha",
    "wof:placetype":"locality"
},
  "geometry": {"coordinates":[84.21911,28.04972],"type":"Point"}
}