{
  "type": "Feature",
  "properties": {
    "gn:admin1_code":"CR",
    "gn:admin2_code":"11",
    "gn:admin3_code":"35.0",
    "gn:admin4_code":"350013.0",
    "gn:asciiname":"Chainpur",
    "gn:country_code":"NP",
    "gn:dem":174,
    "gn:feature_class":"P",
    "gn:feature_code":"PPLL",
    "gn:name":"Chainpur",
    "gn:population":0,
    "gn:timezone":"Asia/Kathmandu",
    "iso:country":"NP",
    "name:ceb_x_preferred":[
        "Chainpur"
    ],
    "name:deu_x_preferred":[
        "Chainpur"
    ],
    "name:nep_x_preferred":[
        "\u091a\u0948\u0928\u092a\u0941\u0930"
    ],
    "name:new_x_preferred":[
        "\u091a\u0948\u0928\u092a\u0941\u0930"
    ],
    "name:pol_x_preferred":[
        "Chainpur"
    ],
    "wof:name":"Chainpur",
    "wof:placetype":"locality"
},
  "geometry": {"coordinates":[84.27741999999998,27.47461],"type":"Point"}
}