{
  "type": "Feature",
  "properties": {
    "gn:admin1_code":"ER",
    "gn:admin2_code":"7",
    "gn:admin3_code":"5",
    "gn:admin4_code":"50037.0",
    "gn:asciiname":"Tallo Kheruwa",
    "gn:country_code":"NP",
    "gn:dem":266,
    "gn:feature_class":"P",
    "gn:feature_code":"PPLL",
    "gn:name":"Tallo Kheruwa",
    "gn:population":0,
    "gn:timezone":"Asia/Kathmandu",
    "iso:country":"NP",
    "wof:name":"Tallo Kheruwa",
    "wof:placetype":"locality"
},
  "geometry": {"coordinates":[87.52020999999998,26.73554],"type":"Point"}
}