{
  "type": "Feature",
  "properties": {
    "gn:admin1_code":"CR",
    "gn:admin2_code":"5",
    "gn:admin3_code":"17.0",
    "gn:admin4_code":"170005.0",
    "gn:asciiname":"Navatoli",
    "gn:country_code":"NP",
    "gn:dem":68,
    "gn:feature_class":"P",
    "gn:feature_code":"PPLL",
    "gn:name":"Navatoli",
    "gn:population":0,
    "gn:timezone":"Asia/Kathmandu",
    "iso:country":"NP",
    "wof:name":"Navatoli",
    "wof:placetype":"locality"
},
  "geometry": {"coordinates":[85.89206999999998,26.62012],"type":"Point"}
}