{
  "type": "Feature",
  "properties": {
    "gn:admin1_code":"MR",
    "gn:admin2_code":"12",
    "gn:admin3_code":"54",
    "gn:admin4_code":"540042",
    "gn:asciiname":"Thuto Chiuri",
    "gn:country_code":"NP",
    "gn:dem":1060,
    "gn:feature_class":"P",
    "gn:feature_code":"PPLL",
    "gn:name":"Thuto Chiuri",
    "gn:population":0,
    "gn:timezone":"Asia/Kathmandu",
    "iso:country":"NP",
    "wof:name":"Thuto Chiuri",
    "wof:placetype":"locality"
},
  "geometry": {"coordinates":[82.53846,28.64684],"type":"Point"}
}