{
  "type": "Feature",
  "properties": {
    "gn:admin1_code":"WR",
    "gn:admin2_code":"3",
    "gn:admin3_code":"45",
    "gn:admin4_code":"450056",
    "gn:asciiname":"Chekhani",
    "gn:country_code":"NP",
    "gn:dem":2446,
    "gn:feature_class":"P",
    "gn:feature_code":"PPLL",
    "gn:name":"Chekhani",
    "gn:population":0,
    "gn:timezone":"Asia/Kathmandu",
    "iso:country":"NP",
    "wof:name":"Chekhani",
    "wof:placetype":"locality"
},
  "geometry": {"coordinates":[83.16767,28.43388],"type":"Point"}
}