{
  "type": "Feature",
  "properties": {
    "gn:admin1_code":"MR",
    "gn:admin2_code":"2.0",
    "gn:admin3_code":"57.0",
    "gn:admin4_code":"570025.0",
    "gn:asciiname":"Nibuwa",
    "gn:country_code":"NP",
    "gn:dem":172,
    "gn:feature_class":"P",
    "gn:feature_code":"PPLL",
    "gn:name":"Nibuwa",
    "gn:population":0,
    "gn:timezone":"Asia/Kathmandu",
    "iso:country":"NP",
    "wof:name":"Nibuwa",
    "wof:placetype":"locality"
},
  "geometry": {"coordinates":[81.71106999999998,28.20789000000001],"type":"Point"}
}