{
  "type": "Feature",
  "properties": {
    "gn:admin1_code":"MR",
    "gn:admin2_code":"12",
    "gn:admin3_code":"53",
    "gn:admin4_code":"530029",
    "gn:asciiname":"Rimsak",
    "gn:country_code":"NP",
    "gn:dem":1411,
    "gn:feature_class":"P",
    "gn:feature_code":"PPLL",
    "gn:name":"Rimsak",
    "gn:population":0,
    "gn:timezone":"Asia/Kathmandu",
    "iso:country":"NP",
    "wof:name":"Rimsak",
    "wof:placetype":"locality"
},
  "geometry": {"coordinates":[82.5759,28.33526],"type":"Point"}
}