{
  "type": "Feature",
  "properties": {
    "gn:admin1_code":"CR",
    "gn:admin2_code":"1",
    "gn:admin3_code":"28",
    "gn:admin4_code":"280018",
    "gn:asciiname":"Kiriyapani",
    "gn:country_code":"NP",
    "gn:dem":814,
    "gn:feature_class":"P",
    "gn:feature_code":"PPLL",
    "gn:name":"Kiriyapani",
    "gn:population":0,
    "gn:timezone":"Asia/Kathmandu",
    "iso:country":"NP",
    "wof:name":"Kiriyapani",
    "wof:placetype":"locality"
},
  "geometry": {"coordinates":[85.06148,27.83104],"type":"Point"}
}