{
  "type": "Feature",
  "properties": {
    "gn:admin1_code":"ER",
    "gn:admin2_code":"13",
    "gn:admin3_code":"15",
    "gn:admin4_code":"150109",
    "gn:asciiname":"Sitapur",
    "gn:country_code":"NP",
    "gn:dem":124,
    "gn:feature_class":"P",
    "gn:feature_code":"PPLL",
    "gn:name":"Sitapur",
    "gn:population":0,
    "gn:timezone":"Asia/Kathmandu",
    "iso:country":"NP",
    "wof:name":"Sitapur",
    "wof:placetype":"locality"
},
  "geometry": {"coordinates":[86.76631,26.61796],"type":"Point"}
}