{
  "type": "Feature",
  "properties": {
    "gn:admin1_code":"CR",
    "gn:admin2_code":"1",
    "gn:admin3_code":"28",
    "gn:admin4_code":"280049",
    "gn:asciiname":"Bhanjyangthok",
    "gn:country_code":"NP",
    "gn:dem":1092,
    "gn:feature_class":"P",
    "gn:feature_code":"PPLL",
    "gn:name":"Bhanjyangthok",
    "gn:population":0,
    "gn:timezone":"Asia/Kathmandu",
    "iso:country":"NP",
    "wof:name":"Bhanjyangthok",
    "wof:placetype":"locality"
},
  "geometry": {"coordinates":[85.34634,27.85018],"type":"Point"}
}