{
  "type": "Feature",
  "properties": {
    "gn:admin1_code":"CR",
    "gn:admin2_code":"1",
    "gn:admin3_code":"30.0",
    "gn:admin4_code":"300049.0",
    "gn:asciiname":"Somdang",
    "gn:country_code":"NP",
    "gn:dem":3335,
    "gn:feature_class":"P",
    "gn:feature_code":"PPLL",
    "gn:name":"Somdang",
    "gn:population":0,
    "gn:timezone":"Asia/Kathmandu",
    "iso:country":"NP",
    "wof:name":"Somdang",
    "wof:placetype":"locality"
},
  "geometry": {"coordinates":[85.20443,28.19436],"type":"Point"}
}