{
  "type": "Feature",
  "properties": {
    "gn:admin1_code":"CR",
    "gn:admin2_code":"11",
    "gn:admin3_code":"35.0",
    "gn:admin4_code":"350005.0",
    "gn:asciiname":"Bishwashantichok",
    "gn:country_code":"NP",
    "gn:dem":198,
    "gn:feature_class":"P",
    "gn:feature_code":"PPLL",
    "gn:name":"Bishwashantichok",
    "gn:population":0,
    "gn:timezone":"Asia/Kathmandu",
    "iso:country":"NP",
    "wof:name":"Bishwashantichok",
    "wof:placetype":"locality"
},
  "geometry": {"coordinates":[84.41065999999999,27.64246],"type":"Point"}
}