{
  "type": "Feature",
  "properties": {
    "gn:admin1_code":"MR",
    "gn:admin2_code":"12",
    "gn:admin3_code":"55",
    "gn:admin4_code":"550024",
    "gn:asciiname":"Melghari",
    "gn:country_code":"NP",
    "gn:dem":1371,
    "gn:feature_class":"P",
    "gn:feature_code":"PPLL",
    "gn:name":"Melghari",
    "gn:population":0,
    "gn:timezone":"Asia/Kathmandu",
    "iso:country":"NP",
    "wof:name":"Melghari",
    "wof:placetype":"locality"
},
  "geometry": {"coordinates":[82.17295,28.38701],"type":"Point"}
}