{
  "type": "Feature",
  "properties": {
    "gn:admin1_code":"MR",
    "gn:admin2_code":"2",
    "gn:admin3_code":"60.0",
    "gn:admin4_code":"600033.0",
    "gn:asciiname":"Bayalkot",
    "gn:country_code":"NP",
    "gn:dem":1535,
    "gn:feature_class":"P",
    "gn:feature_code":"PPLL",
    "gn:name":"Bayalkot",
    "gn:population":0,
    "gn:timezone":"Asia/Kathmandu",
    "iso:country":"NP",
    "wof:name":"Bayalkot",
    "wof:placetype":"locality"
},
  "geometry": {"coordinates":[81.64010999999998,28.7903],"type":"Point"}
}