{
  "type": "Feature",
  "properties": {
    "gn:admin1_code":"ER",
    "gn:admin2_code":"10",
    "gn:admin3_code":"3.0",
    "gn:admin4_code":"30020.0",
    "gn:asciiname":"Siddhigaun",
    "gn:country_code":"NP",
    "gn:dem":1250,
    "gn:feature_class":"P",
    "gn:feature_code":"PPLL",
    "gn:name":"Siddhigaun",
    "gn:population":0,
    "gn:timezone":"Asia/Kathmandu",
    "iso:country":"NP",
    "wof:name":"Siddhigaun",
    "wof:placetype":"locality"
},
  "geometry": {"coordinates":[88.09914000000001,26.87985],"type":"Point"}
}