{
  "type": "Feature",
  "properties": {
    "gn:admin1_code":"CR",
    "gn:admin2_code":"5",
    "gn:admin3_code":"22.0",
    "gn:admin4_code":"220001.0",
    "gn:asciiname":"Khartal",
    "gn:country_code":"NP",
    "gn:dem":1824,
    "gn:feature_class":"P",
    "gn:feature_code":"PPLL",
    "gn:name":"Khartal",
    "gn:population":0,
    "gn:timezone":"Asia/Kathmandu",
    "iso:country":"NP",
    "name:aze_x_preferred":[
        "Xartal"
    ],
    "name:deu_x_preferred":[
        "Kartal"
    ],
    "name:fra_x_preferred":[
        "Kartal"
    ],
    "name:lad_x_preferred":[
        "Khartal"
    ],
    "name:pan_x_preferred":[
        "\u0a16\u0a5c\u0a24\u0a3e\u0a32"
    ],
    "name:pnb_x_preferred":[
        "\u06a9\u06be\u0691\u062a\u0627\u0644"
    ],
    "name:pol_x_preferred":[
        "Khartal"
    ],
    "name:spa_x_preferred":[
        "Khartal"
    ],
    "wof:name":"Khartal",
    "wof:placetype":"locality"
},
  "geometry": {"coordinates":[86.10301,27.84865],"type":"Point"}
}