{
  "type": "Feature",
  "properties": {
    "gn:admin1_code":"CR",
    "gn:admin2_code":"5",
    "gn:admin3_code":"22.0",
    "gn:admin4_code":"220001.0",
    "gn:asciiname":"Khartal",
    "gn:country_code":"NP",
    "gn:dem":1824,
    "gn:feature_class":"P",
    "gn:feature_code":"PPLL",
    "gn:name":"Khartal",
    "gn:population":0,
    "gn:timezone":"Asia/Kathmandu",
    "iso:country":"NP",
    "wof:name":"Khartal",
    "wof:placetype":"locality"
},
  "geometry": {"coordinates":[86.10301,27.84865],"type":"Point"}
}