{
  "type": "Feature",
  "properties": {
    "gn:admin1_code":"ER",
    "gn:admin2_code":"7",
    "gn:admin3_code":"5",
    "gn:admin4_code":"50060",
    "gn:asciiname":"Chhatrapur",
    "gn:country_code":"NP",
    "gn:dem":668,
    "gn:feature_class":"P",
    "gn:feature_code":"PPLL",
    "gn:name":"Chhatrapur",
    "gn:population":0,
    "gn:timezone":"Asia/Kathmandu",
    "iso:country":"NP",
    "name:bpy_x_preferred":[
        "\u099b\u09a4\u09cd\u09b0\u09aa\u09c1\u09b0"
    ],
    "name:cat_x_preferred":[
        "Chhatrapur"
    ],
    "name:ceb_x_preferred":[
        "Chatrapur"
    ],
    "name:fas_x_preferred":[
        "\u0686\u0627\u062a\u0631\u0627\u067e\u0648\u0631"
    ],
    "name:fin_x_preferred":[
        "Chhatrapur"
    ],
    "name:fra_x_preferred":[
        "Chhatrapur"
    ],
    "name:guj_x_preferred":[
        "\u0a9b\u0aa4\u0acd\u0ab0\u0aaa\u0ac1\u0ab0"
    ],
    "name:hin_x_preferred":[
        "\u091b\u0924\u094d\u0930\u092a\u0941\u0930"
    ],
    "name:ita_x_preferred":[
        "Chhatrapur"
    ],
    "name:lat_x_preferred":[
        "Chatrapura"
    ],
    "name:mar_x_preferred":[
        "\u091b\u0924\u094d\u0930\u092a\u0941\u0930"
    ],
    "name:mlg_x_preferred":[
        "Chhatrapur"
    ],
    "name:msa_x_preferred":[
        "Chhatrapur"
    ],
    "name:new_x_preferred":[
        "\u091b\u0924\u094d\u0930\u092a\u0941\u0930"
    ],
    "name:nld_x_preferred":[
        "Chhatrapur"
    ],
    "name:ori_x_preferred":[
        "\u0b1b\u0b24\u0b4d\u0b30\u0b2a\u0b41\u0b30"
    ],
    "name:pol_x_preferred":[
        "Chatrapur"
    ],
    "name:rus_x_preferred":[
        "\u0427\u0445\u0430\u0442\u0440\u0430\u043f\u0443\u0440"
    ],
    "name:swe_x_preferred":[
        "Chhatrapur"
    ],
    "name:urd_x_preferred":[
        "\u0686\u06be\u062a\u0631\u067e\u0648\u0631"
    ],
    "name:vie_x_preferred":[
        "Chhatrapur"
    ],
    "name:zho_x_preferred":[
        "\u6070\u7279\u62c9\u666e\u5c14"
    ],
    "wof:name":"Chhatrapur",
    "wof:placetype":"locality"
},
  "geometry": {"coordinates":[87.57845,26.78317],"type":"Point"}
}