{
  "type": "Feature",
  "properties": {
    "gn:admin1_code":"ER",
    "gn:admin2_code":"7",
    "gn:admin3_code":"10.0",
    "gn:admin4_code":"100054.0",
    "gn:asciiname":"Balangkhim",
    "gn:country_code":"NP",
    "gn:dem":1296,
    "gn:feature_class":"P",
    "gn:feature_code":"PPLL",
    "gn:name":"Balangkhim",
    "gn:population":0,
    "gn:timezone":"Asia/Kathmandu",
    "iso:country":"NP",
    "wof:name":"Balangkhim",
    "wof:placetype":"locality"
},
  "geometry": {"coordinates":[87.09087,27.00253],"type":"Point"}
}