{
  "type": "Feature",
  "properties": {
    "gn:admin1_code":"WR",
    "gn:admin2_code":"3",
    "gn:admin3_code":"44",
    "gn:admin4_code":"440053",
    "gn:asciiname":"Puranogaun",
    "gn:country_code":"NP",
    "gn:dem":1698,
    "gn:feature_class":"P",
    "gn:feature_code":"PPLL",
    "gn:name":"Puranogaun",
    "gn:population":0,
    "gn:timezone":"Asia/Kathmandu",
    "iso:country":"NP",
    "wof:name":"Puranogaun",
    "wof:placetype":"locality"
},
  "geometry": {"coordinates":[83.77601,28.28461],"type":"Point"}
}