{
  "type": "Feature",
  "properties": {
    "gn:admin1_code":"WR",
    "gn:admin2_code":"8",
    "gn:admin3_code":"50.0",
    "gn:admin4_code":"500069.0",
    "gn:asciiname":"Madarhawa",
    "gn:country_code":"NP",
    "gn:dem":135,
    "gn:feature_class":"P",
    "gn:feature_code":"PPLL",
    "gn:name":"Madarhawa",
    "gn:population":0,
    "gn:timezone":"Asia/Kathmandu",
    "iso:country":"NP",
    "wof:name":"Madarhawa",
    "wof:placetype":"locality"
},
  "geometry": {"coordinates":[82.82814,27.66072],"type":"Point"}
}