{
  "type": "Feature",
  "properties": {
    "gn:admin1_code":"WR",
    "gn:admin2_code":"8",
    "gn:admin3_code":"47",
    "gn:admin4_code":"470049",
    "gn:asciiname":"Palung",
    "gn:country_code":"NP",
    "gn:dem":1376,
    "gn:feature_class":"P",
    "gn:feature_code":"PPLL",
    "gn:name":"Palung",
    "gn:population":0,
    "gn:timezone":"Asia/Kathmandu",
    "iso:country":"NP",
    "name:ceb_x_preferred":[
        "Palung"
    ],
    "name:msa_x_preferred":[
        "Palung"
    ],
    "name:new_x_preferred":[
        "\u092a\u093e\u0932\u0941\u0919"
    ],
    "name:pol_x_preferred":[
        "Palung"
    ],
    "wof:name":"Palung",
    "wof:placetype":"locality"
},
  "geometry": {"coordinates":[83.41169000000002,27.84274000000001],"type":"Point"}
}