{
  "type": "Feature",
  "properties": {
    "gn:admin1_code":"ER",
    "gn:admin2_code":"10.0",
    "gn:admin3_code":"1.0",
    "gn:admin4_code":"10010.0",
    "gn:asciiname":"Khopikharka",
    "gn:country_code":"NP",
    "gn:dem":1989,
    "gn:feature_class":"P",
    "gn:feature_code":"PPLL",
    "gn:name":"Khopikharka",
    "gn:population":0,
    "gn:timezone":"Asia/Kathmandu",
    "iso:country":"NP",
    "wof:name":"Khopikharka",
    "wof:placetype":"locality"
},
  "geometry": {"coordinates":[87.60542,27.29893],"type":"Point"}
}