{
  "type": "Feature",
  "properties": {
    "gn:admin1_code":"CR",
    "gn:admin2_code":"1",
    "gn:admin3_code":"24.0",
    "gn:admin4_code":"240030.0",
    "gn:asciiname":"Dakalthok",
    "gn:country_code":"NP",
    "gn:dem":832,
    "gn:feature_class":"P",
    "gn:feature_code":"PPLL",
    "gn:name":"Dakalthok",
    "gn:population":0,
    "gn:timezone":"Asia/Kathmandu",
    "iso:country":"NP",
    "wof:name":"Dakalthok",
    "wof:placetype":"locality"
},
  "geometry": {"coordinates":[85.59125999999998,27.74254],"type":"Point"}
}