{
  "type": "Feature",
  "properties": {
    "gn:admin1_code":"00",
    "gn:asciiname":"Jhawani",
    "gn:country_code":"NP",
    "gn:dem":85,
    "gn:feature_class":"P",
    "gn:feature_code":"PPL",
    "gn:name":"Jhaw\u0101ni\u0307\u0304",
    "gn:population":0,
    "gn:timezone":"Asia/Kathmandu",
    "iso:country":"NP",
    "wof:name":"Jhawani",
    "wof:placetype":"locality"
},
  "geometry": {"coordinates":[85.12169,26.87966],"type":"Point"}
}