{
  "type": "Feature",
  "properties": {
    "gn:admin1_code":"FR",
    "gn:admin2_code":"14",
    "gn:admin3_code":"70.0",
    "gn:admin4_code":"700010.0",
    "gn:asciiname":"Thapagaun",
    "gn:country_code":"NP",
    "gn:dem":1676,
    "gn:feature_class":"P",
    "gn:feature_code":"PPLL",
    "gn:name":"Thapagaun",
    "gn:population":0,
    "gn:timezone":"Asia/Kathmandu",
    "iso:country":"NP",
    "wof:name":"Thapagaun",
    "wof:placetype":"locality"
},
  "geometry": {"coordinates":[80.98768000000003,29.35729000000001],"type":"Point"}
}