{
  "type": "Feature",
  "properties": {
    "gn:admin1_code":"00",
    "gn:asciiname":"Atigau",
    "gn:country_code":"NP",
    "gn:dem":1204,
    "gn:feature_class":"P",
    "gn:feature_code":"PPL",
    "gn:name":"\u0100\u1e6di\u0307\u0304g\u0101\u0169",
    "gn:population":0,
    "gn:timezone":"Asia/Kathmandu",
    "iso:country":"NP",
    "name:nep_x_preferred":[
        "\u0100\u1e6di\u0307\u0304g\u0101\u0169"
    ],
    "wof:name":"Atigau",
    "wof:placetype":"locality"
},
  "geometry": {"coordinates":[84.89704,28.03108],"type":"Point"}
}