{
  "type": "Feature",
  "properties": {
    "gn:admin1_code":"WR",
    "gn:admin2_code":"4.0",
    "gn:admin3_code":"39.0",
    "gn:admin4_code":"390040.0",
    "gn:asciiname":"Chaur",
    "gn:country_code":"NP",
    "gn:dem":978,
    "gn:feature_class":"P",
    "gn:feature_code":"PPLL",
    "gn:name":"Chaur",
    "gn:population":0,
    "gn:timezone":"Asia/Kathmandu",
    "iso:country":"NP",
    "wof:name":"Chaur",
    "wof:placetype":"locality"
},
  "geometry": {"coordinates":[83.90760999999998,28.10588],"type":"Point"}
}