{
  "type": "Feature",
  "properties": {
    "gn:admin1_code":"WR",
    "gn:admin2_code":"4.0",
    "gn:admin3_code":"38.0",
    "gn:admin4_code":"380025.0",
    "gn:asciiname":"Ramche",
    "gn:country_code":"NP",
    "gn:dem":966,
    "gn:feature_class":"P",
    "gn:feature_code":"PPLL",
    "gn:name":"Ramche",
    "gn:population":0,
    "gn:timezone":"Asia/Kathmandu",
    "iso:country":"NP",
    "wof:name":"Ramche",
    "wof:placetype":"locality"
},
  "geometry": {"coordinates":[84.23628000000002,27.92471],"type":"Point"}
}