{
  "type": "Feature",
  "properties": {
    "gn:admin1_code":"WR",
    "gn:admin2_code":"4.0",
    "gn:admin3_code":"39.0",
    "gn:admin4_code":"390043.0",
    "gn:asciiname":"Dunde",
    "gn:country_code":"NP",
    "gn:dem":846,
    "gn:feature_class":"P",
    "gn:feature_code":"PPLL",
    "gn:name":"Dunde",
    "gn:population":0,
    "gn:timezone":"Asia/Kathmandu",
    "iso:country":"NP",
    "wof:name":"Dunde",
    "wof:placetype":"locality"
},
  "geometry": {"coordinates":[83.64686999999998,27.99993],"type":"Point"}
}