{
  "type": "Feature",
  "properties": {
    "gn:admin1_code":"CR",
    "gn:admin2_code":"11",
    "gn:admin3_code":"31",
    "gn:admin4_code":"310013.0",
    "gn:asciiname":"Jaluke",
    "gn:country_code":"NP",
    "gn:dem":1509,
    "gn:feature_class":"P",
    "gn:feature_code":"PPLL",
    "gn:name":"Jaluke",
    "gn:population":0,
    "gn:timezone":"Asia/Kathmandu",
    "iso:country":"NP",
    "wof:name":"Jaluke",
    "wof:placetype":"locality"
},
  "geometry": {"coordinates":[84.92331999999998,27.66912],"type":"Point"}
}