{
  "type": "Feature",
  "properties": {
    "gn:admin1_code":"ER",
    "gn:admin2_code":"13",
    "gn:admin3_code":"11",
    "gn:admin4_code":"110020",
    "gn:asciiname":"Bhirtala",
    "gn:country_code":"NP",
    "gn:dem":2937,
    "gn:feature_class":"P",
    "gn:feature_code":"PPLL",
    "gn:name":"Bhirtala",
    "gn:population":0,
    "gn:timezone":"Asia/Kathmandu",
    "iso:country":"NP",
    "wof:name":"Bhirtala",
    "wof:placetype":"locality"
},
  "geometry": {"coordinates":[86.52975000000001,27.54685],"type":"Point"}
}