{
  "type": "Feature",
  "properties": {
    "gn:admin1_code":"00",
    "gn:asciiname":"Shitalpur",
    "gn:country_code":"NP",
    "gn:dem":94,
    "gn:feature_class":"P",
    "gn:feature_code":"PPL",
    "gn:name":"Shitalpur",
    "gn:population":0,
    "gn:timezone":"Asia/Kathmandu",
    "iso:country":"NP",
    "name:nep_x_preferred":[
        "Shitalpur"
    ],
    "wof:name":"Shitalpur",
    "wof:placetype":"locality"
},
  "geometry": {"coordinates":[85.19580000000001,26.95622],"type":"Point"}
}