{
  "type": "Feature",
  "properties": {
    "gn:admin1_code":"FR",
    "gn:admin2_code":"14",
    "gn:admin3_code":"68",
    "gn:admin4_code":"680021",
    "gn:asciiname":"DungriBagad",
    "gn:country_code":"NP",
    "gn:dem":1686,
    "gn:feature_class":"P",
    "gn:feature_code":"PPLL",
    "gn:name":"DungriBagad",
    "gn:population":0,
    "gn:timezone":"Asia/Kathmandu",
    "iso:country":"NP",
    "wof:name":"DungriBagad",
    "wof:placetype":"locality"
},
  "geometry": {"coordinates":[80.81153,29.64895],"type":"Point"}
}