{
  "type": "Feature",
  "properties": {
    "gn:admin1_code":"CR",
    "gn:admin2_code":"5",
    "gn:admin3_code":"19",
    "gn:admin4_code":"190010",
    "gn:asciiname":"Bara Uddhoran",
    "gn:country_code":"NP",
    "gn:dem":76,
    "gn:feature_class":"P",
    "gn:feature_code":"PPLL",
    "gn:name":"Bara Uddhoran",
    "gn:population":0,
    "gn:timezone":"Asia/Kathmandu",
    "iso:country":"NP",
    "wof:name":"Bara Uddhoran",
    "wof:placetype":"locality"
},
  "geometry": {"coordinates":[85.4537,26.79049],"type":"Point"}
}