{
  "type": "Feature",
  "properties": {
    "gn:admin1_code":"MR",
    "gn:admin2_code":"2",
    "gn:admin3_code":"60.0",
    "gn:admin4_code":"600040.0",
    "gn:asciiname":"Khetgaun",
    "gn:country_code":"NP",
    "gn:dem":1155,
    "gn:feature_class":"P",
    "gn:feature_code":"PPLL",
    "gn:name":"Khetgaun",
    "gn:population":0,
    "gn:timezone":"Asia/Kathmandu",
    "iso:country":"NP",
    "wof:name":"Khetgaun",
    "wof:placetype":"locality"
},
  "geometry": {"coordinates":[81.59756,28.87874],"type":"Point"}
}