{
  "type": "Feature",
  "properties": {
    "gn:admin1_code":"CR",
    "gn:admin2_code":"1",
    "gn:admin3_code":"29",
    "gn:admin4_code":"290013",
    "gn:asciiname":"Guisa",
    "gn:country_code":"NP",
    "gn:dem":1903,
    "gn:feature_class":"P",
    "gn:feature_code":"PPLL",
    "gn:name":"Guisa",
    "gn:population":0,
    "gn:timezone":"Asia/Kathmandu",
    "iso:country":"NP",
    "name:ceb_x_preferred":[
        "Guisa"
    ],
    "name:fra_x_preferred":[
        "Guisa"
    ],
    "name:ita_x_preferred":[
        "Guisa"
    ],
    "name:kat_x_preferred":[
        "\u10d2\u10e3\u10d8\u10e1\u10d0"
    ],
    "name:nld_x_preferred":[
        "Guisa"
    ],
    "name:pol_x_preferred":[
        "Guisa"
    ],
    "name:spa_x_preferred":[
        "Guisa"
    ],
    "name:swe_x_preferred":[
        "Guisa"
    ],
    "name:vie_x_preferred":[
        "Guisa"
    ],
    "name:zho_x_preferred":[
        "\u5409\u85a9"
    ],
    "wof:name":"Guisa",
    "wof:placetype":"locality"
},
  "geometry": {"coordinates":[85.3001,28.01328],"type":"Point"}
}