{
  "type": "Feature",
  "properties": {
    "gn:admin1_code":"ER",
    "gn:admin2_code":"13.0",
    "gn:asciiname":"Triyuga",
    "gn:country_code":"NP",
    "gn:dem":165,
    "gn:feature_class":"P",
    "gn:feature_code":"PPLL",
    "gn:name":"Triyuga",
    "gn:population":71405,
    "gn:timezone":"Asia/Kathmandu",
    "iso:country":"NP",
    "wof:name":"Triyuga",
    "wof:placetype":"locality",
    "wof:population":71405
},
  "geometry": {"coordinates":[86.699,26.7919],"type":"Point"}
}