{
  "type": "Feature",
  "properties": {
    "gn:admin1_code":"ER",
    "gn:admin2_code":"13.0",
    "gn:asciiname":"Triyuga",
    "gn:country_code":"NP",
    "gn:dem":165,
    "gn:feature_class":"P",
    "gn:feature_code":"PPLL",
    "gn:name":"Triyuga",
    "gn:population":71405,
    "gn:timezone":"Asia/Kathmandu",
    "iso:country":"NP",
    "name:bih_x_preferred":[
        "\u0924\u094d\u0930\u093f\u092f\u0941\u0917\u093e"
    ],
    "name:deu_x_preferred":[
        "Triyuga"
    ],
    "name:fin_x_preferred":[
        "Triyuga"
    ],
    "name:fra_x_preferred":[
        "Triyuga"
    ],
    "name:hin_x_preferred":[
        "\u0924\u094d\u0930\u093f\u092f\u0941\u0917\u093e"
    ],
    "name:ita_x_preferred":[
        "Triyuga"
    ],
    "name:lit_x_preferred":[
        "Trijuga"
    ],
    "name:mai_x_preferred":[
        "\u0924\u094d\u0930\u093f\u092f\u0941\u0917\u093e \u0928\u0917\u0930\u092a\u093e\u0932\u093f\u0915\u093e"
    ],
    "name:msa_x_preferred":[
        "Triyuga"
    ],
    "name:nep_x_preferred":[
        "\u0924\u094d\u0930\u093f\u092f\u0941\u0917\u093e \u0928\u0917\u0930\u092a\u093e\u0932\u093f\u0915\u093e"
    ],
    "name:new_x_preferred":[
        "\u0924\u094d\u0930\u093f\u092f\u0941\u0917\u093e \u0928\u0917\u0930\u092a\u093e\u0932\u093f\u0915\u093e"
    ],
    "name:nld_x_preferred":[
        "Triyuga"
    ],
    "name:pol_x_preferred":[
        "Triyuga"
    ],
    "name:rus_x_preferred":[
        "\u0422\u0440\u0438\u044e\u0433\u0430"
    ],
    "name:urd_x_preferred":[
        "\u062a\u0631\u06cc\u0648\u06af\u0627"
    ],
    "name:zho_x_preferred":[
        "\u7279\u91cc\u5c24\u52a0"
    ],
    "wof:name":"Triyuga",
    "wof:placetype":"locality",
    "wof:population":71405
},
  "geometry": {"coordinates":[86.699,26.7919],"type":"Point"}
}