{
  "type": "Feature",
  "properties": {
    "gn:admin1_code":"WR",
    "gn:admin2_code":"8",
    "gn:admin3_code":"49",
    "gn:admin4_code":"490048",
    "gn:asciiname":"Bhadakaiya",
    "gn:country_code":"NP",
    "gn:dem":143,
    "gn:feature_class":"P",
    "gn:feature_code":"PPLL",
    "gn:name":"Bhadakaiya",
    "gn:population":0,
    "gn:timezone":"Asia/Kathmandu",
    "iso:country":"NP",
    "wof:name":"Bhadakaiya",
    "wof:placetype":"locality"
},
  "geometry": {"coordinates":[83.43089000000001,27.66085],"type":"Point"}
}