{
  "type": "Feature",
  "properties": {
    "gn:admin1_code":"ER",
    "gn:admin2_code":"7",
    "gn:admin3_code":"10.0",
    "gn:admin4_code":"100027.0",
    "gn:asciiname":"Ghiukholagaun",
    "gn:country_code":"NP",
    "gn:dem":2074,
    "gn:feature_class":"P",
    "gn:feature_code":"PPLL",
    "gn:name":"Ghiukholagaun",
    "gn:population":0,
    "gn:timezone":"Asia/Kathmandu",
    "iso:country":"NP",
    "wof:name":"Ghiukholagaun",
    "wof:placetype":"locality"
},
  "geometry": {"coordinates":[87.04767,27.249],"type":"Point"}
}