{
  "type": "Feature",
  "properties": {
    "gn:admin1_code":"ER",
    "gn:admin2_code":"7",
    "gn:admin3_code":"9",
    "gn:admin4_code":"90015",
    "gn:asciiname":"Thulo Oirang",
    "gn:country_code":"NP",
    "gn:dem":2126,
    "gn:feature_class":"P",
    "gn:feature_code":"PPLL",
    "gn:name":"Thulo Oirang",
    "gn:population":0,
    "gn:timezone":"Asia/Kathmandu",
    "iso:country":"NP",
    "wof:name":"Thulo Oirang",
    "wof:placetype":"locality"
},
  "geometry": {"coordinates":[87.45671,27.23568],"type":"Point"}
}