{
  "type": "Feature",
  "properties": {
    "gn:admin1_code":"CR",
    "gn:admin2_code":"1",
    "gn:admin3_code":"23",
    "gn:admin4_code":"230042",
    "gn:asciiname":"Nainimarang",
    "gn:country_code":"NP",
    "gn:dem":1630,
    "gn:feature_class":"P",
    "gn:feature_code":"PPLL",
    "gn:name":"Nainimarang",
    "gn:population":0,
    "gn:timezone":"Asia/Kathmandu",
    "iso:country":"NP",
    "wof:name":"Nainimarang",
    "wof:placetype":"locality"
},
  "geometry": {"coordinates":[85.84416999999998,27.64238],"type":"Point"}
}