{
  "type": "Feature",
  "properties": {
    "gn:admin1_code":"CR",
    "gn:admin2_code":"1",
    "gn:admin3_code":"23",
    "gn:admin4_code":"230069",
    "gn:asciiname":"Bapta",
    "gn:country_code":"NP",
    "gn:dem":1348,
    "gn:feature_class":"P",
    "gn:feature_code":"PPLL",
    "gn:name":"Bapta",
    "gn:population":0,
    "gn:timezone":"Asia/Kathmandu",
    "iso:country":"NP",
    "wof:name":"Bapta",
    "wof:placetype":"locality"
},
  "geometry": {"coordinates":[85.87819,27.74981],"type":"Point"}
}