{
  "type": "Feature",
  "properties": {
    "gn:admin1_code":"WR",
    "gn:admin2_code":"8",
    "gn:admin3_code":"51.0",
    "gn:admin4_code":"510012.0",
    "gn:asciiname":"Todke",
    "gn:country_code":"NP",
    "gn:dem":1309,
    "gn:feature_class":"P",
    "gn:feature_code":"PPLL",
    "gn:name":"Todke",
    "gn:population":0,
    "gn:timezone":"Asia/Kathmandu",
    "iso:country":"NP",
    "wof:name":"Todke",
    "wof:placetype":"locality"
},
  "geometry": {"coordinates":[83.04746999999998,27.92032],"type":"Point"}
}