{
  "type": "Feature",
  "properties": {
    "gn:admin1_code":"ER",
    "gn:admin2_code":"10",
    "gn:admin3_code":"4.0",
    "gn:admin4_code":"40003.0",
    "gn:asciiname":"Khombutar",
    "gn:country_code":"NP",
    "gn:dem":349,
    "gn:feature_class":"P",
    "gn:feature_code":"PPLL",
    "gn:name":"Khombutar",
    "gn:population":0,
    "gn:timezone":"Asia/Kathmandu",
    "iso:country":"NP",
    "wof:name":"Khombutar",
    "wof:placetype":"locality"
},
  "geometry": {"coordinates":[88.13110999999998,26.76524],"type":"Point"}
}