{
  "type": "Feature",
  "properties": {
    "gn:admin1_code":"WR",
    "gn:admin2_code":"4.0",
    "gn:admin3_code":"39.0",
    "gn:admin4_code":"390060.0",
    "gn:asciiname":"Dhansare",
    "gn:country_code":"NP",
    "gn:dem":1127,
    "gn:feature_class":"P",
    "gn:feature_code":"PPLL",
    "gn:name":"Dhansare",
    "gn:population":0,
    "gn:timezone":"Asia/Kathmandu",
    "iso:country":"NP",
    "wof:name":"Dhansare",
    "wof:placetype":"locality"
},
  "geometry": {"coordinates":[83.75635,27.96532],"type":"Point"}
}