{
  "type": "Feature",
  "properties": {
    "iso:country":"NP",
    "name:bho_x_preferred":[
        "\u0920\u094b\u0938\u0947"
    ],
    "name:ceb_x_preferred":[
        "Those"
    ],
    "name:deu_x_preferred":[
        "Those"
    ],
    "name:eng_x_preferred":[
        "Those"
    ],
    "name:msa_x_preferred":[
        "Those"
    ],
    "name:nep_x_preferred":[
        "\u0920\u094b\u0938\u0947"
    ],
    "name:pol_x_preferred":[
        "Those"
    ],
    "name:unk_x_variant":[
        "\u1e6chose"
    ],
    "qs:gn_country":"NP",
    "qs:gn_fcode":"PPL",
    "qs:gn_pop":0,
    "qs:name":"Those",
    "qs:name_adm0":"Nepal",
    "qs:name_adm1":"Madhyamanchal",
    "qs:photos":37,
    "qs:photos_1k":7,
    "qs:photos_9k":1,
    "qs:photos_9r":2,
    "qs:photos_all":37,
    "qs:photos_sr":2,
    "qs:placetype":"Town",
    "qs:pop_sr":"0",
    "qs:woe_adm0":23424911,
    "wd:wordcount":17,
    "wof:name":"Those",
    "wof:placetype":"locality"
},
  "geometry": {"coordinates":[86.25843999999999,27.59048],"type":"Point"}
}