{
  "type": "Feature",
  "properties": {
    "gn:admin1_code":"ER",
    "gn:admin2_code":"7",
    "gn:admin3_code":"10.0",
    "gn:admin4_code":"100030.0",
    "gn:asciiname":"Ekumma",
    "gn:country_code":"NP",
    "gn:dem":1333,
    "gn:feature_class":"P",
    "gn:feature_code":"PPLL",
    "gn:name":"Ekumma",
    "gn:population":0,
    "gn:timezone":"Asia/Kathmandu",
    "iso:country":"NP",
    "wof:name":"Ekumma",
    "wof:placetype":"locality"
},
  "geometry": {"coordinates":[87.07727,27.33628],"type":"Point"}
}