{
  "type": "Feature",
  "properties": {
    "gn:admin1_code":"WR",
    "gn:admin2_code":"8",
    "gn:admin3_code":"51.0",
    "gn:admin4_code":"510036.0",
    "gn:asciiname":"Myal Pokhari",
    "gn:country_code":"NP",
    "gn:dem":1184,
    "gn:feature_class":"P",
    "gn:feature_code":"PPLL",
    "gn:name":"Myal Pokhari",
    "gn:population":0,
    "gn:timezone":"Asia/Kathmandu",
    "iso:country":"NP",
    "wof:name":"Myal Pokhari",
    "wof:placetype":"locality"
},
  "geometry": {"coordinates":[83.14036,27.98278],"type":"Point"}
}