{
  "type": "Feature",
  "properties": {
    "gn:admin1_code":"MR",
    "gn:admin2_code":"12",
    "gn:admin3_code":"55",
    "gn:admin4_code":"550035",
    "gn:asciiname":"Chakleneta",
    "gn:country_code":"NP",
    "gn:dem":1611,
    "gn:feature_class":"P",
    "gn:feature_code":"PPLL",
    "gn:name":"Chakleneta",
    "gn:population":0,
    "gn:timezone":"Asia/Kathmandu",
    "iso:country":"NP",
    "wof:name":"Chakleneta",
    "wof:placetype":"locality"
},
  "geometry": {"coordinates":[82.05121,28.39084],"type":"Point"}
}