{
  "type": "Feature",
  "properties": {
    "gn:admin1_code":"FR",
    "gn:admin2_code":"14",
    "gn:admin3_code":"70.0",
    "gn:admin4_code":"700017.0",
    "gn:asciiname":"Radikhelne",
    "gn:country_code":"NP",
    "gn:dem":1163,
    "gn:feature_class":"P",
    "gn:feature_code":"PPLL",
    "gn:name":"Radikhelne",
    "gn:population":0,
    "gn:timezone":"Asia/Kathmandu",
    "iso:country":"NP",
    "wof:name":"Radikhelne",
    "wof:placetype":"locality"
},
  "geometry": {"coordinates":[81.07223,29.29382],"type":"Point"}
}