{
  "type": "Feature",
  "properties": {
    "gn:admin1_code":"CR",
    "gn:admin2_code":"1",
    "gn:admin3_code":"24.0",
    "gn:admin4_code":"240038.0",
    "gn:asciiname":"Kalapani",
    "gn:country_code":"NP",
    "gn:dem":1547,
    "gn:feature_class":"P",
    "gn:feature_code":"PPLL",
    "gn:name":"Kalapani",
    "gn:population":0,
    "gn:timezone":"Asia/Kathmandu",
    "iso:country":"NP",
    "name:ceb_x_preferred":[
        "Kalapani"
    ],
    "name:fra_x_preferred":[
        "Kala Pani"
    ],
    "name:swe_x_preferred":[
        "Kalapani"
    ],
    "wof:name":"Kalapani",
    "wof:placetype":"locality"
},
  "geometry": {"coordinates":[85.70326999999997,27.54475],"type":"Point"}
}