{
  "type": "Feature",
  "properties": {
    "gn:admin1_code":"FR",
    "gn:admin2_code":"14",
    "gn:admin3_code":"71.0",
    "gn:admin4_code":"710007.0",
    "gn:asciiname":"Mangalpur",
    "gn:country_code":"NP",
    "gn:dem":200,
    "gn:feature_class":"P",
    "gn:feature_code":"PPLL",
    "gn:name":"Mangalpur",
    "gn:population":0,
    "gn:timezone":"Asia/Kathmandu",
    "iso:country":"NP",
    "wof:name":"Mangalpur",
    "wof:placetype":"locality"
},
  "geometry": {"coordinates":[80.74581999999999,28.75611],"type":"Point"}
}