{
  "type": "Feature",
  "properties": {
    "gn:admin1_code":"MR",
    "gn:admin2_code":"6",
    "gn:admin3_code":"66.0",
    "gn:admin4_code":"660026.0",
    "gn:asciiname":"Kantha chaur",
    "gn:country_code":"NP",
    "gn:dem":3030,
    "gn:feature_class":"P",
    "gn:feature_code":"PPLL",
    "gn:name":"Kantha chaur",
    "gn:population":0,
    "gn:timezone":"Asia/Kathmandu",
    "iso:country":"NP",
    "wof:name":"Kantha chaur",
    "wof:placetype":"locality"
},
  "geometry": {"coordinates":[81.77649,29.95683],"type":"Point"}
}