{
  "type": "Feature",
  "properties": {
    "gn:admin1_code":"MR",
    "gn:admin2_code":"12",
    "gn:admin3_code":"53",
    "gn:admin4_code":"530040",
    "gn:asciiname":"Balle",
    "gn:country_code":"NP",
    "gn:dem":2372,
    "gn:feature_class":"P",
    "gn:feature_code":"PPLL",
    "gn:name":"Balle",
    "gn:population":0,
    "gn:timezone":"Asia/Kathmandu",
    "iso:country":"NP",
    "name:ceb_x_preferred":[
        "Balle"
    ],
    "name:dan_x_preferred":[
        "Balle"
    ],
    "name:deu_x_preferred":[
        "Balle"
    ],
    "name:fra_x_preferred":[
        "Balle"
    ],
    "name:hye_x_preferred":[
        "\u0532\u0561\u056c"
    ],
    "name:ind_x_preferred":[
        "Balle"
    ],
    "name:nld_x_preferred":[
        "Balle"
    ],
    "name:nrm_x_preferred":[
        "Balle"
    ],
    "name:por_x_preferred":[
        "Balle"
    ],
    "name:swe_x_preferred":[
        "Balle"
    ],
    "wof:name":"Balle",
    "wof:placetype":"locality"
},
  "geometry": {"coordinates":[82.47261999999998,28.49997],"type":"Point"}
}