{
  "type": "Feature",
  "properties": {
    "gn:admin1_code":"CR",
    "gn:admin2_code":"1",
    "gn:admin3_code":"30.0",
    "gn:admin4_code":"300029.0",
    "gn:asciiname":"Duwarthok",
    "gn:country_code":"NP",
    "gn:dem":1113,
    "gn:feature_class":"P",
    "gn:feature_code":"PPLL",
    "gn:name":"Duwarthok",
    "gn:population":0,
    "gn:timezone":"Asia/Kathmandu",
    "iso:country":"NP",
    "wof:name":"Duwarthok",
    "wof:placetype":"locality"
},
  "geometry": {"coordinates":[84.77351999999998,27.90169],"type":"Point"}
}