{
  "type": "Feature",
  "properties": {
    "gn:admin1_code":"FR",
    "gn:admin2_code":"9",
    "gn:admin3_code":"74",
    "gn:admin4_code":"740042",
    "gn:asciiname":"Doli",
    "gn:country_code":"NP",
    "gn:dem":1298,
    "gn:feature_class":"P",
    "gn:feature_code":"PPLL",
    "gn:name":"Doli",
    "gn:population":0,
    "gn:timezone":"Asia/Kathmandu",
    "iso:country":"NP",
    "name:bos_x_preferred":[
        "Doli"
    ],
    "name:ceb_x_preferred":[
        "Doli"
    ],
    "name:deu_x_preferred":[
        "Doli"
    ],
    "name:fra_x_preferred":[
        "Doli"
    ],
    "name:swe_x_preferred":[
        "Doli"
    ],
    "wof:name":"Doli",
    "wof:placetype":"locality"
},
  "geometry": {"coordinates":[80.47085,29.60774],"type":"Point"}
}