{
  "type": "Feature",
  "properties": {
    "gn:admin1_code":"MR",
    "gn:admin2_code":"2",
    "gn:admin3_code":"60.0",
    "gn:admin4_code":"600012.0",
    "gn:asciiname":"Latipani",
    "gn:country_code":"NP",
    "gn:dem":1061,
    "gn:feature_class":"P",
    "gn:feature_code":"PPLL",
    "gn:name":"Latipani",
    "gn:population":0,
    "gn:timezone":"Asia/Kathmandu",
    "iso:country":"NP",
    "wof:name":"Latipani",
    "wof:placetype":"locality"
},
  "geometry": {"coordinates":[81.55303000000001,28.962],"type":"Point"}
}