{
  "type": "Feature",
  "properties": {
    "gn:admin1_code":"WR",
    "gn:admin2_code":"8",
    "gn:admin3_code":"50.0",
    "gn:admin4_code":"500033.0",
    "gn:asciiname":"Amahawa",
    "gn:country_code":"NP",
    "gn:dem":113,
    "gn:feature_class":"P",
    "gn:feature_code":"PPLL",
    "gn:name":"Amahawa",
    "gn:population":0,
    "gn:timezone":"Asia/Kathmandu",
    "iso:country":"NP",
    "wof:name":"Amahawa",
    "wof:placetype":"locality"
},
  "geometry": {"coordinates":[82.99200999999999,27.63923],"type":"Point"}
}