{
  "type": "Feature",
  "properties": {
    "gn:admin1_code":"WR",
    "gn:admin2_code":"4.0",
    "gn:admin3_code":"38.0",
    "gn:admin4_code":"380031.0",
    "gn:asciiname":"Simle",
    "gn:country_code":"NP",
    "gn:dem":1002,
    "gn:feature_class":"P",
    "gn:feature_code":"PPLL",
    "gn:name":"Simle",
    "gn:population":0,
    "gn:timezone":"Asia/Kathmandu",
    "iso:country":"NP",
    "name:bih_x_preferred":[
        "\u0938\u093f\u092e\u094d\u0932\u0947"
    ],
    "name:ceb_x_preferred":[
        "Simle"
    ],
    "name:mai_x_preferred":[
        "\u0938\u093f\u092e\u094d\u0932\u0947"
    ],
    "name:msa_x_preferred":[
        "Simle"
    ],
    "name:nep_x_preferred":[
        "\u0938\u093f\u092e\u094d\u0932\u0947"
    ],
    "name:new_x_preferred":[
        "\u0938\u093f\u092e\u094d\u0932\u0947"
    ],
    "name:pol_x_preferred":[
        "Simle"
    ],
    "wof:name":"Simle",
    "wof:placetype":"locality"
},
  "geometry": {"coordinates":[84.28305,28.07213],"type":"Point"}
}