{
  "type": "Feature",
  "properties": {
    "gn:admin1_code":"00",
    "gn:asciiname":"Kangabagau",
    "gn:country_code":"NP",
    "gn:dem":1853,
    "gn:feature_class":"P",
    "gn:feature_code":"PPL",
    "gn:name":"K\u0101\u1e45gab\u0101g\u0101\u0169",
    "gn:population":0,
    "gn:timezone":"Asia/Kathmandu",
    "iso:country":"NP",
    "name:und_x_variant":[
        "K\u0101\u1e45gab\u0101g\u0101\u0169",
        "K\u0101\u1e45gab\u0101g\u0101un"
    ],
    "wof:name":"Kangabagau",
    "wof:placetype":"locality"
},
  "geometry": {"coordinates":[86.16202,27.40657],"type":"Point"}
}