{
  "type": "Feature",
  "properties": {
    "gn:admin1_code":"WR",
    "gn:admin2_code":"4",
    "gn:admin3_code":"36.0",
    "gn:admin4_code":"360057.0",
    "gn:asciiname":"Swanra",
    "gn:country_code":"NP",
    "gn:dem":1351,
    "gn:feature_class":"P",
    "gn:feature_code":"PPLL",
    "gn:name":"Swanra",
    "gn:population":0,
    "gn:timezone":"Asia/Kathmandu",
    "iso:country":"NP",
    "wof:name":"Swanra",
    "wof:placetype":"locality"
},
  "geometry": {"coordinates":[84.72681999999998,28.10912],"type":"Point"}
}