{
  "type": "Feature",
  "properties": {
    "gn:admin1_code":"WR",
    "gn:admin2_code":"3",
    "gn:admin3_code":"45.0",
    "gn:admin4_code":"450026.0",
    "gn:asciiname":"Dobilla",
    "gn:country_code":"NP",
    "gn:dem":1071,
    "gn:feature_class":"P",
    "gn:feature_code":"PPLL",
    "gn:name":"Dobilla",
    "gn:population":0,
    "gn:timezone":"Asia/Kathmandu",
    "iso:country":"NP",
    "wof:name":"Dobilla",
    "wof:placetype":"locality"
},
  "geometry": {"coordinates":[83.54314000000002,28.26377],"type":"Point"}
}