{
  "type": "Feature",
  "properties": {
    "gn:admin1_code":"FR",
    "gn:admin2_code":"14.0",
    "gn:admin3_code":"67.0",
    "gn:admin4_code":"670011.0",
    "gn:asciiname":"Gotri",
    "gn:country_code":"NP",
    "gn:dem":1484,
    "gn:feature_class":"P",
    "gn:feature_code":"PPLL",
    "gn:name":"Gotri",
    "gn:population":0,
    "gn:timezone":"Asia/Kathmandu",
    "iso:country":"NP",
    "name:ceb_x_preferred":[
        "Gotree"
    ],
    "name:fra_x_preferred":[
        "Gotree"
    ],
    "name:mai_x_preferred":[
        "\u0917\u094b\u0924\u094d\u0930\u0940"
    ],
    "name:msa_x_preferred":[
        "Gotree"
    ],
    "name:nep_x_preferred":[
        "\u0917\u094b\u0924\u094d\u0930\u0940"
    ],
    "name:new_x_preferred":[
        "\u0917\u094b\u0924\u094d\u0930\u0940"
    ],
    "name:pol_x_preferred":[
        "Gotree"
    ],
    "wof:name":"Gotri",
    "wof:placetype":"locality"
},
  "geometry": {"coordinates":[81.71434000000001,29.36185],"type":"Point"}
}