{
  "type": "Feature",
  "properties": {
    "gn:admin1_code":"MR",
    "gn:admin2_code":"12",
    "gn:admin3_code":"53",
    "gn:admin4_code":"530010",
    "gn:asciiname":"Dhuri",
    "gn:country_code":"NP",
    "gn:dem":2391,
    "gn:feature_class":"P",
    "gn:feature_code":"PPLL",
    "gn:name":"Dhuri",
    "gn:population":0,
    "gn:timezone":"Asia/Kathmandu",
    "iso:country":"NP",
    "name:ben_x_preferred":[
        "\u09a7\u09c1\u09b0\u09bf"
    ],
    "name:bpy_x_preferred":[
        "\u09a7\u09c1\u09b0\u09bf"
    ],
    "name:hin_x_preferred":[
        "\u0927\u0942\u0930\u0940"
    ],
    "name:ita_x_preferred":[
        "Dhuri"
    ],
    "name:msa_x_preferred":[
        "Dhuri"
    ],
    "name:new_x_preferred":[
        "\u0927\u0941\u0930\u0940"
    ],
    "name:nld_x_preferred":[
        "Dhuri"
    ],
    "name:ori_x_preferred":[
        "\u0b27\u0b41\u0b30\u0b3f"
    ],
    "name:pan_x_preferred":[
        "\u0a27\u0a42\u0a30\u0a40"
    ],
    "name:spa_x_preferred":[
        "Dhuri"
    ],
    "name:urd_x_preferred":[
        "\u062f\u06be\u0648\u0631\u06cc"
    ],
    "name:vie_x_preferred":[
        "Dhuri"
    ],
    "wof:name":"Dhuri",
    "wof:placetype":"locality"
},
  "geometry": {"coordinates":[82.84958,28.39384],"type":"Point"}
}