{
  "type": "Feature",
  "properties": {
    "gn:admin1_code":"WR",
    "gn:admin2_code":"8",
    "gn:admin3_code":"48",
    "gn:admin4_code":"480018",
    "gn:asciiname":"Admara",
    "gn:country_code":"NP",
    "gn:dem":253,
    "gn:feature_class":"P",
    "gn:feature_code":"PPLL",
    "gn:name":"Admara",
    "gn:population":0,
    "gn:timezone":"Asia/Kathmandu",
    "iso:country":"NP",
    "wof:name":"Admara",
    "wof:placetype":"locality"
},
  "geometry": {"coordinates":[83.79056,27.67898],"type":"Point"}
}