{
  "type": "Feature",
  "properties": {
    "gn:admin1_code":"MR",
    "gn:admin2_code":"12",
    "gn:admin3_code":"55",
    "gn:admin4_code":"550010",
    "gn:asciiname":"Basnetgaun",
    "gn:country_code":"NP",
    "gn:dem":1261,
    "gn:feature_class":"P",
    "gn:feature_code":"PPLL",
    "gn:name":"Basnetgaun",
    "gn:population":0,
    "gn:timezone":"Asia/Kathmandu",
    "iso:country":"NP",
    "wof:name":"Basnetgaun",
    "wof:placetype":"locality"
},
  "geometry": {"coordinates":[82.31585,28.56648],"type":"Point"}
}