{
  "type": "Feature",
  "properties": {
    "gn:admin1_code":"MR",
    "gn:admin2_code":"12",
    "gn:admin3_code":"53",
    "gn:admin4_code":"530010",
    "gn:asciiname":"Churbangdanda",
    "gn:country_code":"NP",
    "gn:dem":2564,
    "gn:feature_class":"P",
    "gn:feature_code":"PPLL",
    "gn:name":"Churbangdanda",
    "gn:population":0,
    "gn:timezone":"Asia/Kathmandu",
    "iso:country":"NP",
    "wof:name":"Churbangdanda",
    "wof:placetype":"locality"
},
  "geometry": {"coordinates":[82.86705000000001,28.32735],"type":"Point"}
}