{
  "type": "Feature",
  "properties": {
    "gn:admin1_code":"CR",
    "gn:admin2_code":"1",
    "gn:admin3_code":"24.0",
    "gn:admin4_code":"240004.0",
    "gn:asciiname":"Sallebas",
    "gn:country_code":"NP",
    "gn:dem":1228,
    "gn:feature_class":"P",
    "gn:feature_code":"PPLL",
    "gn:name":"Sallebas",
    "gn:population":0,
    "gn:timezone":"Asia/Kathmandu",
    "iso:country":"NP",
    "wof:name":"Sallebas",
    "wof:placetype":"locality"
},
  "geometry": {"coordinates":[85.56524,27.72788],"type":"Point"}
}