{
  "type": "Feature",
  "properties": {
    "gn:admin1_code":"FR",
    "gn:admin2_code":"14",
    "gn:admin3_code":"70.0",
    "gn:admin4_code":"700034.0",
    "gn:asciiname":"Thali",
    "gn:country_code":"NP",
    "gn:dem":1489,
    "gn:feature_class":"P",
    "gn:feature_code":"PPLL",
    "gn:name":"Thali",
    "gn:population":0,
    "gn:timezone":"Asia/Kathmandu",
    "iso:country":"NP",
    "name:deu_x_preferred":[
        "Thali"
    ],
    "name:fin_x_preferred":[
        "Thali"
    ],
    "name:fra_x_preferred":[
        "Thali"
    ],
    "name:guj_x_preferred":[
        "\u0aa5\u0abe\u0ab3\u0ac0"
    ],
    "name:heb_x_preferred":[
        "\u05d8\u05d0\u05dc\u05d9"
    ],
    "name:hin_x_preferred":[
        "\u0925\u093e\u0932\u0940"
    ],
    "name:hye_x_preferred":[
        "\u054f\u0570\u0561\u056c\u056b"
    ],
    "name:ind_x_preferred":[
        "Thali"
    ],
    "name:jpn_x_preferred":[
        "\u30bf\u30fc\u30ea\u30fc"
    ],
    "name:nld_x_preferred":[
        "Thalis"
    ],
    "name:pol_x_preferred":[
        "Thali"
    ],
    "name:rus_x_preferred":[
        "\u0422\u0445\u0430\u043b\u0438"
    ],
    "name:spa_x_preferred":[
        "Thali"
    ],
    "name:ukr_x_preferred":[
        "\u0422\u0445\u0430\u043b\u0456"
    ],
    "wof:name":"Thali",
    "wof:placetype":"locality"
},
  "geometry": {"coordinates":[80.66076,29.05305],"type":"Point"}
}