{
  "type": "Feature",
  "properties": {
    "gn:admin1_code":"ER",
    "gn:admin2_code":"7",
    "gn:admin3_code":"9",
    "gn:admin4_code":"90032.0",
    "gn:asciiname":"Samsa",
    "gn:country_code":"NP",
    "gn:dem":2523,
    "gn:feature_class":"P",
    "gn:feature_code":"PPLL",
    "gn:name":"Samsa",
    "gn:population":0,
    "gn:timezone":"Asia/Kathmandu",
    "iso:country":"NP",
    "name:hin_x_preferred":[
        "\u0938\u092e\u0938\u093e"
    ],
    "wof:name":"Samsa",
    "wof:placetype":"locality"
},
  "geometry": {"coordinates":[87.38261,27.1819],"type":"Point"}
}