{
  "type": "Feature",
  "properties": {
    "gn:admin1_code":"FR",
    "gn:admin2_code":"9",
    "gn:admin3_code":"74",
    "gn:admin4_code":"740057",
    "gn:asciiname":"Ukhakot",
    "gn:country_code":"NP",
    "gn:dem":1299,
    "gn:feature_class":"P",
    "gn:feature_code":"PPLL",
    "gn:name":"Ukhakot",
    "gn:population":0,
    "gn:timezone":"Asia/Kathmandu",
    "iso:country":"NP",
    "wof:name":"Ukhakot",
    "wof:placetype":"locality"
},
  "geometry": {"coordinates":[80.76779999999999,29.42936],"type":"Point"}
}