{
  "type": "Feature",
  "properties": {
    "gn:admin1_code":"ER",
    "gn:admin2_code":"10",
    "gn:admin3_code":"2",
    "gn:admin4_code":"20032",
    "gn:asciiname":"Bohoratal",
    "gn:country_code":"NP",
    "gn:dem":813,
    "gn:feature_class":"P",
    "gn:feature_code":"PPLL",
    "gn:name":"Bohoratal",
    "gn:population":0,
    "gn:timezone":"Asia/Kathmandu",
    "iso:country":"NP",
    "wof:name":"Bohoratal",
    "wof:placetype":"locality"
},
  "geometry": {"coordinates":[87.59919000000002,27.09461],"type":"Point"}
}