{
  "type": "Feature",
  "properties": {
    "gn:admin1_code":"WR",
    "gn:admin2_code":"4",
    "gn:admin3_code":"36.0",
    "gn:admin4_code":"360015.0",
    "gn:asciiname":"Taule",
    "gn:country_code":"NP",
    "gn:dem":2914,
    "gn:feature_class":"P",
    "gn:feature_code":"PPLL",
    "gn:name":"Taule",
    "gn:population":0,
    "gn:timezone":"Asia/Kathmandu",
    "iso:country":"NP",
    "wof:name":"Taule",
    "wof:placetype":"locality"
},
  "geometry": {"coordinates":[84.93143000000001,28.48762],"type":"Point"}
}