{
  "type": "Feature",
  "properties": {
    "gn:admin1_code":"00",
    "gn:asciiname":"Jamu",
    "gn:country_code":"NP",
    "gn:dem":269,
    "gn:feature_class":"P",
    "gn:feature_code":"PPL",
    "gn:name":"J\u0101m\u016b",
    "gn:population":0,
    "gn:timezone":"Asia/Kathmandu",
    "iso:country":"NP",
    "name:deu_x_preferred":[
        "Jamu"
    ],
    "name:ind_x_preferred":[
        "Jamu"
    ],
    "name:jav_x_preferred":[
        "Jamu"
    ],
    "name:msa_x_preferred":[
        "Jamu"
    ],
    "name:tur_x_preferred":[
        "Jamu"
    ],
    "wof:name":"Jamu",
    "wof:placetype":"locality"
},
  "geometry": {"coordinates":[81.33333,28.78333],"type":"Point"}
}