{
  "type": "Feature",
  "properties": {
    "gn:admin1_code":"MR",
    "gn:admin2_code":"6",
    "gn:admin3_code":"66.0",
    "gn:admin4_code":"660010.0",
    "gn:asciiname":"Gumba",
    "gn:country_code":"NP",
    "gn:dem":2840,
    "gn:feature_class":"P",
    "gn:feature_code":"PPLL",
    "gn:name":"Gumba",
    "gn:population":0,
    "gn:timezone":"Asia/Kathmandu",
    "iso:country":"NP",
    "name:ceb_x_preferred":[
        "Gumba"
    ],
    "name:deu_x_preferred":[
        "Gumba"
    ],
    "name:fra_x_preferred":[
        "Gumba"
    ],
    "name:pol_x_preferred":[
        "Gumba"
    ],
    "name:swe_x_preferred":[
        "Gumba"
    ],
    "wof:name":"Gumba",
    "wof:placetype":"locality"
},
  "geometry": {"coordinates":[81.73119,30.0366],"type":"Point"}
}