{
  "type": "Feature",
  "properties": {
    "gn:admin1_code":"CR",
    "gn:admin2_code":"5",
    "gn:admin3_code":"20",
    "gn:admin4_code":"200032",
    "gn:asciiname":"Kastar",
    "gn:country_code":"NP",
    "gn:dem":907,
    "gn:feature_class":"P",
    "gn:feature_code":"PPLL",
    "gn:name":"Kastar",
    "gn:population":0,
    "gn:timezone":"Asia/Kathmandu",
    "iso:country":"NP",
    "wof:name":"Kastar",
    "wof:placetype":"locality"
},
  "geometry": {"coordinates":[86.17541,27.12549000000001],"type":"Point"}
}