{
  "type": "Feature",
  "properties": {
    "gn:admin1_code":"WR",
    "gn:admin2_code":"4",
    "gn:admin3_code":"36.0",
    "gn:admin4_code":"360049.0",
    "gn:asciiname":"Tallo Jarang",
    "gn:country_code":"NP",
    "gn:dem":990,
    "gn:feature_class":"P",
    "gn:feature_code":"PPLL",
    "gn:name":"Tallo Jarang",
    "gn:population":0,
    "gn:timezone":"Asia/Kathmandu",
    "iso:country":"NP",
    "wof:name":"Tallo Jarang",
    "wof:placetype":"locality"
},
  "geometry": {"coordinates":[84.70238000000001,28.06196],"type":"Point"}
}