{
  "type": "Feature",
  "properties": {
    "gn:admin1_code":"CR",
    "gn:admin2_code":"11",
    "gn:admin3_code":"35.0",
    "gn:admin4_code":"350014.0",
    "gn:asciiname":"Narayanchock",
    "gn:country_code":"NP",
    "gn:dem":196,
    "gn:feature_class":"P",
    "gn:feature_code":"PPLL",
    "gn:name":"Narayanchock",
    "gn:population":0,
    "gn:timezone":"Asia/Kathmandu",
    "iso:country":"NP",
    "wof:name":"Narayanchock",
    "wof:placetype":"locality"
},
  "geometry": {"coordinates":[84.40572,27.63073],"type":"Point"}
}