{
  "type": "Feature",
  "properties": {
    "gn:admin1_code":"ER",
    "gn:admin2_code":"7",
    "gn:admin3_code":"10.0",
    "gn:admin4_code":"100031.0",
    "gn:asciiname":"Lamsuwa Bitalab",
    "gn:country_code":"NP",
    "gn:dem":729,
    "gn:feature_class":"P",
    "gn:feature_code":"PPLL",
    "gn:name":"Lamsuwa Bitalab",
    "gn:population":0,
    "gn:timezone":"Asia/Kathmandu",
    "iso:country":"NP",
    "wof:name":"Lamsuwa Bitalab",
    "wof:placetype":"locality"
},
  "geometry": {"coordinates":[87.16788000000003,27.35511],"type":"Point"}
}