{
  "type": "Feature",
  "properties": {
    "gn:admin1_code":"CR",
    "gn:admin2_code":"5",
    "gn:admin3_code":"18",
    "gn:admin4_code":"180034",
    "gn:asciiname":"Malibara",
    "gn:country_code":"NP",
    "gn:dem":67,
    "gn:feature_class":"P",
    "gn:feature_code":"PPLL",
    "gn:name":"Malibara",
    "gn:population":0,
    "gn:timezone":"Asia/Kathmandu",
    "iso:country":"NP",
    "wof:name":"Malibara",
    "wof:placetype":"locality"
},
  "geometry": {"coordinates":[85.78034,26.63382],"type":"Point"}
}