{
  "type": "Feature",
  "properties": {
    "gn:admin1_code":"FR",
    "gn:admin2_code":"14",
    "gn:admin3_code":"68",
    "gn:admin4_code":"680035",
    "gn:asciiname":"Kalapani",
    "gn:country_code":"NP",
    "gn:dem":2344,
    "gn:feature_class":"P",
    "gn:feature_code":"PPLL",
    "gn:name":"Kalapani",
    "gn:population":0,
    "gn:timezone":"Asia/Kathmandu",
    "iso:country":"NP",
    "wof:name":"Kalapani",
    "wof:placetype":"locality"
},
  "geometry": {"coordinates":[80.97726,29.42562],"type":"Point"}
}