{
  "type": "Feature",
  "properties": {
    "gn:admin1_code":"WR",
    "gn:admin2_code":"4.0",
    "gn:admin3_code":"39.0",
    "gn:admin4_code":"390036.0",
    "gn:asciiname":"Chharak",
    "gn:country_code":"NP",
    "gn:dem":734,
    "gn:feature_class":"P",
    "gn:feature_code":"PPLL",
    "gn:name":"Chharak",
    "gn:population":0,
    "gn:timezone":"Asia/Kathmandu",
    "iso:country":"NP",
    "wof:name":"Chharak",
    "wof:placetype":"locality"
},
  "geometry": {"coordinates":[83.61448,27.95701],"type":"Point"}
}