{
  "type": "Feature",
  "properties": {
    "gn:admin1_code":"WR",
    "gn:admin2_code":"4.0",
    "gn:admin3_code":"39.0",
    "gn:admin4_code":"390017.0",
    "gn:asciiname":"Palpali Chhap",
    "gn:country_code":"NP",
    "gn:dem":864,
    "gn:feature_class":"P",
    "gn:feature_code":"PPLL",
    "gn:name":"Palpali Chhap",
    "gn:population":0,
    "gn:timezone":"Asia/Kathmandu",
    "iso:country":"NP",
    "wof:name":"Palpali Chhap",
    "wof:placetype":"locality"
},
  "geometry": {"coordinates":[84.00362,28.02088],"type":"Point"}
}