{
  "type": "Feature",
  "properties": {
    "gn:admin1_code":"CR",
    "gn:admin2_code":"1",
    "gn:admin3_code":"24.0",
    "gn:admin4_code":"240063.0",
    "gn:asciiname":"Sanga",
    "gn:country_code":"NP",
    "gn:dem":1504,
    "gn:feature_class":"P",
    "gn:feature_code":"PPLL",
    "gn:name":"Sanga",
    "gn:population":0,
    "gn:timezone":"Asia/Kathmandu",
    "iso:country":"NP",
    "name:ceb_x_preferred":[
        "Sanga"
    ],
    "name:deu_x_preferred":[
        "Sanga"
    ],
    "name:fra_x_preferred":[
        "Sanga"
    ],
    "name:ita_x_preferred":[
        "Sanga"
    ],
    "name:por_x_preferred":[
        "Sanga"
    ],
    "name:swe_x_preferred":[
        "Sanga"
    ],
    "wof:name":"Sanga",
    "wof:placetype":"locality"
},
  "geometry": {"coordinates":[85.48069,27.645],"type":"Point"}
}