{
  "type": "Feature",
  "properties": {
    "gn:admin1_code":"WR",
    "gn:admin2_code":"4.0",
    "gn:admin3_code":"39.0",
    "gn:admin4_code":"390022.0",
    "gn:asciiname":"Tallo Kudule",
    "gn:country_code":"NP",
    "gn:dem":1251,
    "gn:feature_class":"P",
    "gn:feature_code":"PPLL",
    "gn:name":"Tallo Kudule",
    "gn:population":0,
    "gn:timezone":"Asia/Kathmandu",
    "iso:country":"NP",
    "wof:name":"Tallo Kudule",
    "wof:placetype":"locality"
},
  "geometry": {"coordinates":[83.89846999999997,28.16922000000001],"type":"Point"}
}