{
  "type": "Feature",
  "properties": {
    "gn:admin1_code":"ER",
    "gn:admin2_code":"13",
    "gn:admin3_code":"11",
    "gn:admin4_code":"110022",
    "gn:asciiname":"Pawai",
    "gn:country_code":"NP",
    "gn:dem":1695,
    "gn:feature_class":"P",
    "gn:feature_code":"PPLL",
    "gn:name":"Pawai",
    "gn:population":0,
    "gn:timezone":"Asia/Kathmandu",
    "iso:country":"NP",
    "name:ben_x_preferred":[
        "\u09aa\u09be\u0993\u09af\u09bc\u09be\u0987"
    ],
    "name:bpy_x_preferred":[
        "\u09aa\u09be\u09f1\u09be\u0987"
    ],
    "name:ceb_x_preferred":[
        "Pawai"
    ],
    "name:ita_x_preferred":[
        "Pawai"
    ],
    "name:msa_x_preferred":[
        "Pawai"
    ],
    "name:nld_x_preferred":[
        "Pawai"
    ],
    "name:por_x_preferred":[
        "Pawai"
    ],
    "name:swe_x_preferred":[
        "Pawai"
    ],
    "name:vie_x_preferred":[
        "Pawai"
    ],
    "name:zho_x_preferred":[
        "\u5e15\u74e6\u4f0a"
    ],
    "wof:name":"Pawai",
    "wof:placetype":"locality"
},
  "geometry": {"coordinates":[86.75960000000001,27.5084],"type":"Point"}
}