{
  "type": "Feature",
  "properties": {
    "gn:admin1_code":"MR",
    "gn:admin2_code":"12",
    "gn:admin3_code":"55",
    "gn:admin4_code":"550036",
    "gn:asciiname":"Dhunge Bagar",
    "gn:country_code":"NP",
    "gn:dem":865,
    "gn:feature_class":"P",
    "gn:feature_code":"PPLL",
    "gn:name":"Dhunge Bagar",
    "gn:population":0,
    "gn:timezone":"Asia/Kathmandu",
    "iso:country":"NP",
    "wof:name":"Dhunge Bagar",
    "wof:placetype":"locality"
},
  "geometry": {"coordinates":[82.23220999999999,28.28697],"type":"Point"}
}