{
  "type": "Feature",
  "properties": {
    "gn:admin1_code":"MR",
    "gn:admin2_code":"12",
    "gn:admin3_code":"54",
    "gn:admin4_code":"540034",
    "gn:asciiname":"Jamachaur",
    "gn:country_code":"NP",
    "gn:dem":1376,
    "gn:feature_class":"P",
    "gn:feature_code":"PPLL",
    "gn:name":"Jamachaur",
    "gn:population":0,
    "gn:timezone":"Asia/Kathmandu",
    "iso:country":"NP",
    "wof:name":"Jamachaur",
    "wof:placetype":"locality"
},
  "geometry": {"coordinates":[82.70340999999998,28.65713],"type":"Point"}
}