{
  "type": "Feature",
  "properties": {
    "gn:admin1_code":"ER",
    "gn:admin2_code":"7",
    "gn:admin3_code":"10.0",
    "gn:admin4_code":"100043.0",
    "gn:asciiname":"Papunga",
    "gn:country_code":"NP",
    "gn:dem":534,
    "gn:feature_class":"P",
    "gn:feature_code":"PPLL",
    "gn:name":"Papunga",
    "gn:population":0,
    "gn:timezone":"Asia/Kathmandu",
    "iso:country":"NP",
    "wof:name":"Papunga",
    "wof:placetype":"locality"
},
  "geometry": {"coordinates":[87.11163000000001,27.38546],"type":"Point"}
}