{
  "type": "Feature",
  "properties": {
    "gn:admin1_code":"WR",
    "gn:admin2_code":"4",
    "gn:admin3_code":"37",
    "gn:admin4_code":"370049",
    "gn:asciiname":"Shikharabesi",
    "gn:country_code":"NP",
    "gn:dem":577,
    "gn:feature_class":"P",
    "gn:feature_code":"PPLL",
    "gn:name":"Shikharabesi",
    "gn:population":0,
    "gn:timezone":"Asia/Kathmandu",
    "iso:country":"NP",
    "wof:name":"Shikharabesi",
    "wof:placetype":"locality"
},
  "geometry": {"coordinates":[84.25359,28.10632],"type":"Point"}
}