{
  "type": "Feature",
  "properties": {
    "gn:admin1_code":"MR",
    "gn:admin2_code":"12",
    "gn:admin3_code":"56.0",
    "gn:admin4_code":"560004.0",
    "gn:asciiname":"Arnahawa",
    "gn:country_code":"NP",
    "gn:dem":253,
    "gn:feature_class":"P",
    "gn:feature_code":"PPLL",
    "gn:name":"Arnahawa",
    "gn:population":0,
    "gn:timezone":"Asia/Kathmandu",
    "iso:country":"NP",
    "wof:name":"Arnahawa",
    "wof:placetype":"locality"
},
  "geometry": {"coordinates":[82.53109000000001,27.86905],"type":"Point"}
}