{
  "type": "Feature",
  "properties": {
    "gn:admin1_code":"WR",
    "gn:admin2_code":"4.0",
    "gn:admin3_code":"38.0",
    "gn:admin4_code":"380018.0",
    "gn:asciiname":"Gyajatar",
    "gn:country_code":"NP",
    "gn:dem":651,
    "gn:feature_class":"P",
    "gn:feature_code":"PPLL",
    "gn:name":"Gyajatar",
    "gn:population":0,
    "gn:timezone":"Asia/Kathmandu",
    "iso:country":"NP",
    "wof:name":"Gyajatar",
    "wof:placetype":"locality"
},
  "geometry": {"coordinates":[84.41161,27.86126],"type":"Point"}
}