{
  "type": "Feature",
  "properties": {
    "gn:admin1_code":"WR",
    "gn:admin2_code":"8",
    "gn:admin3_code":"47",
    "gn:admin4_code":"470062",
    "gn:asciiname":"Bhutte Danda",
    "gn:country_code":"NP",
    "gn:dem":1099,
    "gn:feature_class":"P",
    "gn:feature_code":"PPLL",
    "gn:name":"Bhutte Danda",
    "gn:population":0,
    "gn:timezone":"Asia/Kathmandu",
    "iso:country":"NP",
    "wof:name":"Bhutte Danda",
    "wof:placetype":"locality"
},
  "geometry": {"coordinates":[83.52445,27.85178],"type":"Point"}
}