{
  "type": "Feature",
  "properties": {
    "gn:admin1_code":"FR",
    "gn:admin2_code":"9",
    "gn:admin3_code":"74",
    "gn:admin4_code":"740035",
    "gn:asciiname":"Lakhulla",
    "gn:country_code":"NP",
    "gn:dem":1623,
    "gn:feature_class":"P",
    "gn:feature_code":"PPLL",
    "gn:name":"Lakhulla",
    "gn:population":0,
    "gn:timezone":"Asia/Kathmandu",
    "iso:country":"NP",
    "wof:name":"Lakhulla",
    "wof:placetype":"locality"
},
  "geometry": {"coordinates":[80.4057,29.44976],"type":"Point"}
}