{
  "type": "Feature",
  "properties": {
    "gn:admin1_code":"MR",
    "gn:admin2_code":"2.0",
    "gn:admin3_code":"58.0",
    "gn:admin4_code":"580007.0",
    "gn:asciiname":"Chikengaudi",
    "gn:country_code":"NP",
    "gn:dem":155,
    "gn:feature_class":"P",
    "gn:feature_code":"PPLL",
    "gn:name":"Chikengaudi",
    "gn:population":0,
    "gn:timezone":"Asia/Kathmandu",
    "iso:country":"NP",
    "wof:name":"Chikengaudi",
    "wof:placetype":"locality"
},
  "geometry": {"coordinates":[81.45997,28.23908],"type":"Point"}
}