{
  "type": "Feature",
  "properties": {
    "gn:admin1_code":"CR",
    "gn:admin2_code":"5",
    "gn:admin3_code":"17.0",
    "gn:admin4_code":"170080.0",
    "gn:asciiname":"Birpur",
    "gn:country_code":"NP",
    "gn:dem":126,
    "gn:feature_class":"P",
    "gn:feature_code":"PPLL",
    "gn:name":"Birpur",
    "gn:population":0,
    "gn:timezone":"Asia/Kathmandu",
    "iso:country":"NP",
    "name:ben_x_preferred":[
        "\u09ac\u09c0\u09b0\u09aa\u09c1\u09b0"
    ],
    "name:bpy_x_preferred":[
        "\u09ac\u09bf\u09b0\u09aa\u09c1\u09b0"
    ],
    "name:ita_x_preferred":[
        "Birpur"
    ],
    "name:mlg_x_preferred":[
        "Birpur"
    ],
    "name:msa_x_preferred":[
        "Birpur"
    ],
    "name:nep_x_preferred":[
        "\u0935\u0940\u0930\u092a\u0941\u0930"
    ],
    "name:new_x_preferred":[
        "\u0935\u0940\u0930\u092a\u0941\u0930"
    ],
    "name:nld_x_preferred":[
        "Birpur"
    ],
    "name:por_x_preferred":[
        "Birpur"
    ],
    "name:vie_x_preferred":[
        "Birpur"
    ],
    "name:zho_x_preferred":[
        "\u6bd4\u5c14\u666e\u5c14"
    ],
    "wof:name":"Birpur",
    "wof:placetype":"locality"
},
  "geometry": {"coordinates":[85.98214,26.87086],"type":"Point"}
}