{
  "type": "Feature",
  "properties": {
    "gn:admin1_code":"MR",
    "gn:admin2_code":"2",
    "gn:admin3_code":"60.0",
    "gn:admin4_code":"600050.0",
    "gn:asciiname":"Bistagaun",
    "gn:country_code":"NP",
    "gn:dem":1142,
    "gn:feature_class":"P",
    "gn:feature_code":"PPLL",
    "gn:name":"Bistagaun",
    "gn:population":0,
    "gn:timezone":"Asia/Kathmandu",
    "iso:country":"NP",
    "wof:name":"Bistagaun",
    "wof:placetype":"locality"
},
  "geometry": {"coordinates":[81.47936999999997,28.95009000000001],"type":"Point"}
}