{
  "type": "Feature",
  "properties": {
    "gn:admin1_code":"CR",
    "gn:admin2_code":"1",
    "gn:admin3_code":"24.0",
    "gn:admin4_code":"240044.0",
    "gn:asciiname":"Thapaliyathok",
    "gn:country_code":"NP",
    "gn:dem":1122,
    "gn:feature_class":"P",
    "gn:feature_code":"PPLL",
    "gn:name":"Thapaliyathok",
    "gn:population":0,
    "gn:timezone":"Asia/Kathmandu",
    "iso:country":"NP",
    "wof:name":"Thapaliyathok",
    "wof:placetype":"locality"
},
  "geometry": {"coordinates":[85.69622,27.59976],"type":"Point"}
}