{
  "type": "Feature",
  "properties": {
    "gn:admin1_code":"ER",
    "gn:admin2_code":"7",
    "gn:admin3_code":"10.0",
    "gn:admin4_code":"100010.0",
    "gn:asciiname":"Deule",
    "gn:country_code":"NP",
    "gn:dem":992,
    "gn:feature_class":"P",
    "gn:feature_code":"PPLL",
    "gn:name":"Deule",
    "gn:population":0,
    "gn:timezone":"Asia/Kathmandu",
    "iso:country":"NP",
    "wof:name":"Deule",
    "wof:placetype":"locality"
},
  "geometry": {"coordinates":[87.02585000000001,27.10345],"type":"Point"}
}