{
  "type": "Feature",
  "properties": {
    "gn:admin1_code":"CR",
    "gn:admin2_code":"1",
    "gn:admin3_code":"29",
    "gn:admin4_code":"290017",
    "gn:asciiname":"Chodhor",
    "gn:country_code":"NP",
    "gn:dem":2498,
    "gn:feature_class":"P",
    "gn:feature_code":"PPLL",
    "gn:name":"Chodhor",
    "gn:population":0,
    "gn:timezone":"Asia/Kathmandu",
    "iso:country":"NP",
    "wof:name":"Chodhor",
    "wof:placetype":"locality"
},
  "geometry": {"coordinates":[85.41764999999999,28.31469],"type":"Point"}
}