{
  "type": "Feature",
  "properties": {
    "gn:admin1_code":"ER",
    "gn:admin2_code":"10.0",
    "gn:admin3_code":"1.0",
    "gn:admin4_code":"10049.0",
    "gn:asciiname":"Odile",
    "gn:country_code":"NP",
    "gn:dem":1333,
    "gn:feature_class":"P",
    "gn:feature_code":"PPLL",
    "gn:name":"Odile",
    "gn:population":0,
    "gn:timezone":"Asia/Kathmandu",
    "iso:country":"NP",
    "wof:name":"Odile",
    "wof:placetype":"locality"
},
  "geometry": {"coordinates":[87.77138000000002,27.3426],"type":"Point"}
}