{
  "type": "Feature",
  "properties": {
    "gn:admin1_code":"CR",
    "gn:admin2_code":"11",
    "gn:admin3_code":"32",
    "gn:admin4_code":"320016",
    "gn:asciiname":"Bairiya",
    "gn:country_code":"NP",
    "gn:dem":100,
    "gn:feature_class":"P",
    "gn:feature_code":"PPLL",
    "gn:name":"Bairiya",
    "gn:population":0,
    "gn:timezone":"Asia/Kathmandu",
    "iso:country":"NP",
    "wof:name":"Bairiya",
    "wof:placetype":"locality"
},
  "geometry": {"coordinates":[85.38455,27.01686],"type":"Point"}
}