{
  "type": "Feature",
  "properties": {
    "gn:admin1_code":"00",
    "gn:asciiname":"Tersehaun",
    "gn:country_code":"NP",
    "gn:dem":418,
    "gn:feature_class":"P",
    "gn:feature_code":"PPL",
    "gn:name":"\u1e6cerseh\u0101un",
    "gn:population":0,
    "gn:timezone":"Asia/Kathmandu",
    "iso:country":"NP",
    "wof:name":"Tersehaun",
    "wof:placetype":"locality"
},
  "geometry": {"coordinates":[85.66773000000001,27.29944],"type":"Point"}
}