{
  "type": "Feature",
  "properties": {
    "gn:admin1_code":"00",
    "gn:asciiname":"Phitingau",
    "gn:country_code":"NP",
    "gn:dem":674,
    "gn:feature_class":"P",
    "gn:feature_code":"PPL",
    "gn:name":"Phi\u1e6di\u1e45g\u0101\u0169",
    "gn:population":0,
    "gn:timezone":"Asia/Kathmandu",
    "iso:country":"NP",
    "name:und_x_variant":[
        "Phi\u1e6di\u1e45g\u0101\u0169",
        "Phi\u1e6di\u1e45g\u0101un"
    ],
    "wof:name":"Phitingau",
    "wof:placetype":"locality"
},
  "geometry": {"coordinates":[85.93675,27.17174],"type":"Point"}
}