{
  "type": "Feature",
  "properties": {
    "gn:admin1_code":"CR",
    "gn:admin2_code":"1",
    "gn:admin3_code":"23",
    "gn:admin4_code":"230058.0",
    "gn:asciiname":"Bhimtar",
    "gn:country_code":"NP",
    "gn:dem":836,
    "gn:feature_class":"P",
    "gn:feature_code":"PPLL",
    "gn:name":"Bhimtar",
    "gn:population":0,
    "gn:timezone":"Asia/Kathmandu",
    "iso:country":"NP",
    "name:ceb_x_preferred":[
        "Bhimtar"
    ],
    "name:deu_x_preferred":[
        "Bhimtar"
    ],
    "name:fra_x_preferred":[
        "Bhimtar"
    ],
    "name:msa_x_preferred":[
        "Bhimtar"
    ],
    "name:nep_x_preferred":[
        "\u092d\u0940\u092e\u091f\u093e\u0930"
    ],
    "name:new_x_preferred":[
        "\u092d\u0940\u092e\u091f\u093e\u0930"
    ],
    "name:pol_x_preferred":[
        "Bhimtar"
    ],
    "wof:name":"Bhimtar",
    "wof:placetype":"locality"
},
  "geometry": {"coordinates":[85.69058000000003,27.69104],"type":"Point"}
}