{
  "type": "Feature",
  "properties": {
    "gn:admin1_code":"MR",
    "gn:admin2_code":"12",
    "gn:admin3_code":"56.0",
    "gn:admin4_code":"560032.0",
    "gn:asciiname":"Jajaragaun",
    "gn:country_code":"NP",
    "gn:dem":615,
    "gn:feature_class":"P",
    "gn:feature_code":"PPLL",
    "gn:name":"Jajaragaun",
    "gn:population":0,
    "gn:timezone":"Asia/Kathmandu",
    "iso:country":"NP",
    "wof:name":"Jajaragaun",
    "wof:placetype":"locality"
},
  "geometry": {"coordinates":[82.45761999999998,27.99102],"type":"Point"}
}