{
  "type": "Feature",
  "properties": {
    "gn:admin1_code":"ER",
    "gn:admin2_code":"7",
    "gn:admin3_code":"5",
    "gn:admin4_code":"50032.0",
    "gn:asciiname":"Chamaru Patawaritol",
    "gn:country_code":"NP",
    "gn:dem":75,
    "gn:feature_class":"P",
    "gn:feature_code":"PPLL",
    "gn:name":"Chamaru Patawaritol",
    "gn:population":0,
    "gn:timezone":"Asia/Kathmandu",
    "iso:country":"NP",
    "wof:name":"Chamaru Patawaritol",
    "wof:placetype":"locality"
},
  "geometry": {"coordinates":[87.32635999999999,26.4827],"type":"Point"}
}