{
  "type": "Feature",
  "properties": {
    "gn:admin1_code":"ER",
    "gn:admin2_code":"13",
    "gn:admin3_code":"13",
    "gn:admin4_code":"130057",
    "gn:asciiname":"Muktung",
    "gn:country_code":"NP",
    "gn:dem":414,
    "gn:feature_class":"P",
    "gn:feature_code":"PPLL",
    "gn:name":"Muktung",
    "gn:population":0,
    "gn:timezone":"Asia/Kathmandu",
    "iso:country":"NP",
    "wof:name":"Muktung",
    "wof:placetype":"locality"
},
  "geometry": {"coordinates":[86.86774,26.90189],"type":"Point"}
}