{
  "type": "Feature",
  "properties": {
    "gn:admin1_code":"MR",
    "gn:admin2_code":"2.0",
    "gn:admin3_code":"59.0",
    "gn:admin4_code":"590021.0",
    "gn:asciiname":"Salle Takura",
    "gn:country_code":"NP",
    "gn:dem":1422,
    "gn:feature_class":"P",
    "gn:feature_code":"PPLL",
    "gn:name":"Salle Takura",
    "gn:population":0,
    "gn:timezone":"Asia/Kathmandu",
    "iso:country":"NP",
    "wof:name":"Salle Takura",
    "wof:placetype":"locality"
},
  "geometry": {"coordinates":[81.30528000000002,28.90513],"type":"Point"}
}