{
  "type": "Feature",
  "properties": {
    "gn:admin1_code":"WR",
    "gn:admin2_code":"3",
    "gn:admin3_code":"45.0",
    "gn:admin4_code":"450038.0",
    "gn:asciiname":"Kaiya",
    "gn:country_code":"NP",
    "gn:dem":877,
    "gn:feature_class":"P",
    "gn:feature_code":"PPLL",
    "gn:name":"Kaiya",
    "gn:population":0,
    "gn:timezone":"Asia/Kathmandu",
    "iso:country":"NP",
    "wof:name":"Kaiya",
    "wof:placetype":"locality"
},
  "geometry": {"coordinates":[83.66436999999998,28.20751],"type":"Point"}
}