{
  "type": "Feature",
  "properties": {
    "gn:admin1_code":"WR",
    "gn:admin2_code":"8",
    "gn:admin3_code":"47",
    "gn:admin4_code":"470020",
    "gn:asciiname":"Bote Gaun",
    "gn:country_code":"NP",
    "gn:dem":481,
    "gn:feature_class":"P",
    "gn:feature_code":"PPLL",
    "gn:name":"Bote Gaun",
    "gn:population":0,
    "gn:timezone":"Asia/Kathmandu",
    "iso:country":"NP",
    "wof:name":"Bote Gaun",
    "wof:placetype":"locality"
},
  "geometry": {"coordinates":[83.47301999999998,27.75376],"type":"Point"}
}