{
  "type": "Feature",
  "properties": {
    "gn:admin1_code":"CR",
    "gn:admin2_code":"11",
    "gn:admin3_code":"31",
    "gn:admin4_code":"310001.0",
    "gn:asciiname":"Chisapani",
    "gn:country_code":"NP",
    "gn:dem":1684,
    "gn:feature_class":"P",
    "gn:feature_code":"PPLL",
    "gn:name":"Chisapani",
    "gn:population":0,
    "gn:timezone":"Asia/Kathmandu",
    "iso:country":"NP",
    "name:ceb_x_preferred":[
        "Chisapani"
    ],
    "name:nep_x_preferred":[
        "\u091a\u093f\u0938\u093e\u092a\u093e\u0928\u0940"
    ],
    "name:nld_x_preferred":[
        "Chisapani"
    ],
    "name:pol_x_preferred":[
        "Chisapani"
    ],
    "wof:name":"Chisapani",
    "wof:placetype":"locality"
},
  "geometry": {"coordinates":[85.03712,27.65351],"type":"Point"}
}