{
  "type": "Feature",
  "properties": {
    "gn:admin1_code":"MR",
    "gn:admin2_code":"12",
    "gn:admin3_code":"53",
    "gn:admin4_code":"530048",
    "gn:asciiname":"Maimundanda",
    "gn:country_code":"NP",
    "gn:dem":2656,
    "gn:feature_class":"P",
    "gn:feature_code":"PPLL",
    "gn:name":"Maimundanda",
    "gn:population":0,
    "gn:timezone":"Asia/Kathmandu",
    "iso:country":"NP",
    "wof:name":"Maimundanda",
    "wof:placetype":"locality"
},
  "geometry": {"coordinates":[82.82696,28.42925],"type":"Point"}
}