{
  "type": "Feature",
  "properties": {
    "gn:admin1_code":"CR",
    "gn:admin2_code":"1",
    "gn:admin3_code":"23",
    "gn:admin4_code":"230039",
    "gn:asciiname":"Banspani",
    "gn:country_code":"NP",
    "gn:dem":922,
    "gn:feature_class":"P",
    "gn:feature_code":"PPLL",
    "gn:name":"Banspani",
    "gn:population":0,
    "gn:timezone":"Asia/Kathmandu",
    "iso:country":"NP",
    "wof:name":"Banspani",
    "wof:placetype":"locality"
},
  "geometry": {"coordinates":[85.7443,27.78767],"type":"Point"}
}