{
  "type": "Feature",
  "properties": {
    "gn:admin1_code":"WR",
    "gn:admin2_code":"4",
    "gn:admin3_code":"37",
    "gn:admin4_code":"370013",
    "gn:asciiname":"Ghiuje",
    "gn:country_code":"NP",
    "gn:dem":1477,
    "gn:feature_class":"P",
    "gn:feature_code":"PPLL",
    "gn:name":"Ghiuje",
    "gn:population":0,
    "gn:timezone":"Asia/Kathmandu",
    "iso:country":"NP",
    "wof:name":"Ghiuje",
    "wof:placetype":"locality"
},
  "geometry": {"coordinates":[84.25936,28.31923],"type":"Point"}
}