{
  "type": "Feature",
  "properties": {
    "gn:admin1_code":"CR",
    "gn:admin2_code":"11",
    "gn:admin3_code":"35.0",
    "gn:admin4_code":"350022.0",
    "gn:asciiname":"Surkandi",
    "gn:country_code":"NP",
    "gn:dem":688,
    "gn:feature_class":"P",
    "gn:feature_code":"PPLL",
    "gn:name":"Surkandi",
    "gn:population":0,
    "gn:timezone":"Asia/Kathmandu",
    "iso:country":"NP",
    "wof:name":"Surkandi",
    "wof:placetype":"locality"
},
  "geometry": {"coordinates":[84.71885,27.66745],"type":"Point"}
}