{
  "type": "Feature",
  "properties": {
    "gn:admin1_code":"MR",
    "gn:admin2_code":"2",
    "gn:admin3_code":"60.0",
    "gn:admin4_code":"600051.0",
    "gn:asciiname":"Khame",
    "gn:country_code":"NP",
    "gn:dem":1794,
    "gn:feature_class":"P",
    "gn:feature_code":"PPLL",
    "gn:name":"Khame",
    "gn:population":0,
    "gn:timezone":"Asia/Kathmandu",
    "iso:country":"NP",
    "wof:name":"Khame",
    "wof:placetype":"locality"
},
  "geometry": {"coordinates":[81.60455999999998,28.7296],"type":"Point"}
}