{
  "type": "Feature",
  "properties": {
    "gn:admin1_code":"ER",
    "gn:admin2_code":"7.0",
    "gn:admin3_code":"8.0",
    "gn:admin4_code":"80016.0",
    "gn:asciiname":"Khalde",
    "gn:country_code":"NP",
    "gn:dem":937,
    "gn:feature_class":"P",
    "gn:feature_code":"PPLL",
    "gn:name":"Khalde",
    "gn:population":0,
    "gn:timezone":"Asia/Kathmandu",
    "iso:country":"NP",
    "wof:name":"Khalde",
    "wof:placetype":"locality"
},
  "geometry": {"coordinates":[87.51512,27.08192],"type":"Point"}
}