{
  "type": "Feature",
  "properties": {
    "gn:admin1_code":"WR",
    "gn:admin2_code":"8",
    "gn:admin3_code":"47",
    "gn:admin4_code":"470046",
    "gn:asciiname":"Ghyangsingdanda",
    "gn:country_code":"NP",
    "gn:dem":997,
    "gn:feature_class":"P",
    "gn:feature_code":"PPLL",
    "gn:name":"Ghyangsingdanda",
    "gn:population":0,
    "gn:timezone":"Asia/Kathmandu",
    "iso:country":"NP",
    "wof:name":"Ghyangsingdanda",
    "wof:placetype":"locality"
},
  "geometry": {"coordinates":[83.87671999999998,27.76787],"type":"Point"}
}