{
  "type": "Feature",
  "properties": {
    "gn:admin1_code":"00",
    "gn:asciiname":"Manpur",
    "gn:country_code":"NP",
    "gn:dem":245,
    "gn:feature_class":"P",
    "gn:feature_code":"PPL",
    "gn:name":"M\u0101npur",
    "gn:population":0,
    "gn:timezone":"Asia/Kathmandu",
    "iso:country":"NP",
    "name:ceb_x_preferred":[
        "Manpur"
    ],
    "name:fra_x_preferred":[
        "Manpur"
    ],
    "name:nep_x_preferred":[
        "M\u0101npur"
    ],
    "name:pol_x_preferred":[
        "Manpur"
    ],
    "name:swe_x_preferred":[
        "Manpur"
    ],
    "wof:name":"Manpur",
    "wof:placetype":"locality"
},
  "geometry": {"coordinates":[81.32409,28.42156],"type":"Point"}
}