{
  "type": "Feature",
  "properties": {
    "gn:admin1_code":"MR",
    "gn:admin2_code":"12",
    "gn:admin3_code":"53",
    "gn:admin4_code":"530037",
    "gn:asciiname":"Parchung",
    "gn:country_code":"NP",
    "gn:dem":1845,
    "gn:feature_class":"P",
    "gn:feature_code":"PPLL",
    "gn:name":"Parchung",
    "gn:population":0,
    "gn:timezone":"Asia/Kathmandu",
    "iso:country":"NP",
    "wof:name":"Parchung",
    "wof:placetype":"locality"
},
  "geometry": {"coordinates":[82.86096999999999,28.28258],"type":"Point"}
}