{
  "type": "Feature",
  "properties": {
    "gn:admin1_code":"ER",
    "gn:admin2_code":"7.0",
    "gn:admin3_code":"10.0",
    "gn:admin4_code":"100003.0",
    "gn:asciiname":"Kholakharka",
    "gn:country_code":"NP",
    "gn:dem":1625,
    "gn:feature_class":"P",
    "gn:feature_code":"PPLL",
    "gn:name":"Kholakharka",
    "gn:population":0,
    "gn:timezone":"Asia/Kathmandu",
    "iso:country":"NP",
    "wof:name":"Kholakharka",
    "wof:placetype":"locality"
},
  "geometry": {"coordinates":[87.00465,27.06255],"type":"Point"}
}