{
  "type": "Feature",
  "properties": {
    "gn:admin1_code":"CR",
    "gn:admin2_code":"1",
    "gn:admin3_code":"30.0",
    "gn:admin4_code":"300046.0",
    "gn:asciiname":"Gorkhaligaun",
    "gn:country_code":"NP",
    "gn:dem":1507,
    "gn:feature_class":"P",
    "gn:feature_code":"PPLL",
    "gn:name":"Gorkhaligaun",
    "gn:population":0,
    "gn:timezone":"Asia/Kathmandu",
    "iso:country":"NP",
    "wof:name":"Gorkhaligaun",
    "wof:placetype":"locality"
},
  "geometry": {"coordinates":[84.93437,27.8641],"type":"Point"}
}