{
  "type": "Feature",
  "properties": {
    "gn:admin1_code":"ER",
    "gn:admin2_code":"7",
    "gn:admin3_code":"10.0",
    "gn:admin4_code":"100049.0",
    "gn:asciiname":"Hatuwa Garahi",
    "gn:country_code":"NP",
    "gn:dem":1426,
    "gn:feature_class":"P",
    "gn:feature_code":"PPLL",
    "gn:name":"Hatuwa Garahi",
    "gn:population":0,
    "gn:timezone":"Asia/Kathmandu",
    "iso:country":"NP",
    "wof:name":"Hatuwa Garahi",
    "wof:placetype":"locality"
},
  "geometry": {"coordinates":[87.11835000000001,27.02828],"type":"Point"}
}