{
  "type": "Feature",
  "properties": {
    "gn:admin1_code":"MR",
    "gn:admin2_code":"2",
    "gn:admin3_code":"60.0",
    "gn:admin4_code":"600048.0",
    "gn:asciiname":"Rumgaun",
    "gn:country_code":"NP",
    "gn:dem":1379,
    "gn:feature_class":"P",
    "gn:feature_code":"PPLL",
    "gn:name":"Rumgaun",
    "gn:population":0,
    "gn:timezone":"Asia/Kathmandu",
    "iso:country":"NP",
    "wof:name":"Rumgaun",
    "wof:placetype":"locality"
},
  "geometry": {"coordinates":[81.84133,28.80344],"type":"Point"}
}