{
  "type": "Feature",
  "properties": {
    "gn:admin1_code":"ER",
    "gn:admin2_code":"13.0",
    "gn:admin3_code":"14.0",
    "gn:admin4_code":"140029.0",
    "gn:asciiname":"Gogane",
    "gn:country_code":"NP",
    "gn:dem":1445,
    "gn:feature_class":"P",
    "gn:feature_code":"PPLL",
    "gn:name":"Gogane",
    "gn:population":0,
    "gn:timezone":"Asia/Kathmandu",
    "iso:country":"NP",
    "wof:name":"Gogane",
    "wof:placetype":"locality"
},
  "geometry": {"coordinates":[86.61934000000002,26.94933],"type":"Point"}
}