{
  "type": "Feature",
  "properties": {
    "gn:admin1_code":"WR",
    "gn:admin2_code":"8",
    "gn:admin3_code":"50.0",
    "gn:admin4_code":"500019.0",
    "gn:asciiname":"Pipara",
    "gn:country_code":"NP",
    "gn:dem":125,
    "gn:feature_class":"P",
    "gn:feature_code":"PPLL",
    "gn:name":"Pipara",
    "gn:population":0,
    "gn:timezone":"Asia/Kathmandu",
    "iso:country":"NP",
    "wof:name":"Pipara",
    "wof:placetype":"locality"
},
  "geometry": {"coordinates":[82.88064,27.62978],"type":"Point"}
}