{
  "type": "Feature",
  "properties": {
    "gn:admin1_code":"WR",
    "gn:admin2_code":"8",
    "gn:admin3_code":"46.0",
    "gn:admin4_code":"460062.0",
    "gn:asciiname":"Butil Gaun",
    "gn:country_code":"NP",
    "gn:dem":881,
    "gn:feature_class":"P",
    "gn:feature_code":"PPLL",
    "gn:name":"Butil Gaun",
    "gn:population":0,
    "gn:timezone":"Asia/Kathmandu",
    "iso:country":"NP",
    "wof:name":"Butil Gaun",
    "wof:placetype":"locality"
},
  "geometry": {"coordinates":[83.36514,28.0435],"type":"Point"}
}