{
  "type": "Feature",
  "properties": {
    "gn:admin1_code":"WR",
    "gn:admin2_code":"4",
    "gn:admin3_code":"41",
    "gn:admin4_code":"410009",
    "gn:asciiname":"Kangla Bhanjyang",
    "gn:country_code":"NP",
    "gn:dem":5334,
    "gn:feature_class":"P",
    "gn:feature_code":"PPLL",
    "gn:name":"Kangla Bhanjyang",
    "gn:population":0,
    "gn:timezone":"Asia/Kathmandu",
    "iso:country":"NP",
    "wof:name":"Kangla Bhanjyang",
    "wof:placetype":"locality"
},
  "geometry": {"coordinates":[84.12756999999998,28.68752000000001],"type":"Point"}
}