{
  "type": "Feature",
  "properties": {
    "gn:admin1_code":"FR",
    "gn:admin2_code":"14",
    "gn:admin3_code":"69.0",
    "gn:admin4_code":"690070.0",
    "gn:asciiname":"Tundegada",
    "gn:country_code":"NP",
    "gn:dem":1043,
    "gn:feature_class":"P",
    "gn:feature_code":"PPLL",
    "gn:name":"Tundegada",
    "gn:population":0,
    "gn:timezone":"Asia/Kathmandu",
    "iso:country":"NP",
    "wof:name":"Tundegada",
    "wof:placetype":"locality"
},
  "geometry": {"coordinates":[81.27611999999998,29.1808],"type":"Point"}
}