{
  "type": "Feature",
  "properties": {
    "gn:admin1_code":"WR",
    "gn:admin2_code":"3",
    "gn:admin3_code":"44",
    "gn:admin4_code":"440011",
    "gn:asciiname":"Kholakharka",
    "gn:country_code":"NP",
    "gn:dem":1060,
    "gn:feature_class":"P",
    "gn:feature_code":"PPLL",
    "gn:name":"Kholakharka",
    "gn:population":0,
    "gn:timezone":"Asia/Kathmandu",
    "iso:country":"NP",
    "wof:name":"Kholakharka",
    "wof:placetype":"locality"
},
  "geometry": {"coordinates":[83.70135000000001,28.08359],"type":"Point"}
}