{
  "type": "Feature",
  "properties": {
    "gn:admin1_code":"FR",
    "gn:admin2_code":"14",
    "gn:admin3_code":"68",
    "gn:admin4_code":"680037",
    "gn:asciiname":"Maikathan",
    "gn:country_code":"NP",
    "gn:dem":2950,
    "gn:feature_class":"P",
    "gn:feature_code":"PPLL",
    "gn:name":"Maikathan",
    "gn:population":0,
    "gn:timezone":"Asia/Kathmandu",
    "iso:country":"NP",
    "wof:name":"Maikathan",
    "wof:placetype":"locality"
},
  "geometry": {"coordinates":[81.10173,29.41552],"type":"Point"}
}