{
  "type": "Feature",
  "properties": {
    "gn:admin1_code":"MR",
    "gn:admin2_code":"2",
    "gn:admin3_code":"60.0",
    "gn:admin4_code":"600014.0",
    "gn:asciiname":"Gothpanda",
    "gn:country_code":"NP",
    "gn:dem":1082,
    "gn:feature_class":"P",
    "gn:feature_code":"PPLL",
    "gn:name":"Gothpanda",
    "gn:population":0,
    "gn:timezone":"Asia/Kathmandu",
    "iso:country":"NP",
    "wof:name":"Gothpanda",
    "wof:placetype":"locality"
},
  "geometry": {"coordinates":[81.675,28.75241],"type":"Point"}
}