{
  "type": "Feature",
  "properties": {
    "gn:admin1_code":"MR",
    "gn:admin2_code":"2",
    "gn:admin3_code":"60.0",
    "gn:admin4_code":"600018.0",
    "gn:asciiname":"Gadigaun",
    "gn:country_code":"NP",
    "gn:dem":1017,
    "gn:feature_class":"P",
    "gn:feature_code":"PPLL",
    "gn:name":"Gadigaun",
    "gn:population":0,
    "gn:timezone":"Asia/Kathmandu",
    "iso:country":"NP",
    "wof:name":"Gadigaun",
    "wof:placetype":"locality"
},
  "geometry": {"coordinates":[81.68703000000002,28.71005],"type":"Point"}
}