{
  "type": "Feature",
  "properties": {
    "gn:admin1_code":"MR",
    "gn:admin2_code":"12",
    "gn:admin3_code":"56.0",
    "gn:admin4_code":"560025.0",
    "gn:asciiname":"Bayale",
    "gn:country_code":"NP",
    "gn:dem":1013,
    "gn:feature_class":"P",
    "gn:feature_code":"PPLL",
    "gn:name":"Bayale",
    "gn:population":0,
    "gn:timezone":"Asia/Kathmandu",
    "iso:country":"NP",
    "wof:name":"Bayale",
    "wof:placetype":"locality"
},
  "geometry": {"coordinates":[82.24776999999997,28.18869],"type":"Point"}
}