{
  "type": "Feature",
  "properties": {
    "gn:admin1_code":"MR",
    "gn:admin2_code":"6",
    "gn:admin3_code":"64.0",
    "gn:admin4_code":"640001.0",
    "gn:asciiname":"Siku",
    "gn:country_code":"NP",
    "gn:dem":1255,
    "gn:feature_class":"P",
    "gn:feature_code":"PPLL",
    "gn:name":"Siku",
    "gn:population":0,
    "gn:timezone":"Asia/Kathmandu",
    "iso:country":"NP",
    "name:deu_x_preferred":[
        "Siku"
    ],
    "name:fra_x_preferred":[
        "Siku"
    ],
    "name:hun_x_preferred":[
        "Siku"
    ],
    "name:ita_x_preferred":[
        "Siku"
    ],
    "wof:name":"Siku",
    "wof:placetype":"locality"
},
  "geometry": {"coordinates":[81.67175999999998,29.22921],"type":"Point"}
}