{
  "type": "Feature",
  "properties": {
    "gn:admin1_code":"CR",
    "gn:admin2_code":"11",
    "gn:admin3_code":"35.0",
    "gn:admin4_code":"350033.0",
    "gn:asciiname":"Mohana",
    "gn:country_code":"NP",
    "gn:dem":190,
    "gn:feature_class":"P",
    "gn:feature_code":"PPLL",
    "gn:name":"Mohana",
    "gn:population":0,
    "gn:timezone":"Asia/Kathmandu",
    "iso:country":"NP",
    "wof:name":"Mohana",
    "wof:placetype":"locality"
},
  "geometry": {"coordinates":[84.49545000000001,27.61029000000001],"type":"Point"}
}