{
  "type": "Feature",
  "properties": {
    "gn:admin1_code":"WR",
    "gn:admin2_code":"3",
    "gn:admin3_code":"45.0",
    "gn:admin4_code":"450035.0",
    "gn:asciiname":"Damuk",
    "gn:country_code":"NP",
    "gn:dem":864,
    "gn:feature_class":"P",
    "gn:feature_code":"PPLL",
    "gn:name":"Damuk",
    "gn:population":0,
    "gn:timezone":"Asia/Kathmandu",
    "iso:country":"NP",
    "wof:name":"Damuk",
    "wof:placetype":"locality"
},
  "geometry": {"coordinates":[83.65805999999998,28.23031],"type":"Point"}
}