{
  "type": "Feature",
  "properties": {
    "gn:admin1_code":"FR",
    "gn:admin2_code":"9",
    "gn:admin3_code":"74",
    "gn:admin4_code":"740010",
    "gn:asciiname":"Maunigaun",
    "gn:country_code":"NP",
    "gn:dem":1265,
    "gn:feature_class":"P",
    "gn:feature_code":"PPLL",
    "gn:name":"Maunigaun",
    "gn:population":0,
    "gn:timezone":"Asia/Kathmandu",
    "iso:country":"NP",
    "wof:name":"Maunigaun",
    "wof:placetype":"locality"
},
  "geometry": {"coordinates":[80.40411,29.56635],"type":"Point"}
}