{
  "type": "Feature",
  "properties": {
    "gn:admin1_code":"FR",
    "gn:admin2_code":"14",
    "gn:admin3_code":"69.0",
    "gn:admin4_code":"690074.0",
    "gn:asciiname":"Thaplakhal",
    "gn:country_code":"NP",
    "gn:dem":1798,
    "gn:feature_class":"P",
    "gn:feature_code":"PPLL",
    "gn:name":"Thaplakhal",
    "gn:population":0,
    "gn:timezone":"Asia/Kathmandu",
    "iso:country":"NP",
    "wof:name":"Thaplakhal",
    "wof:placetype":"locality"
},
  "geometry": {"coordinates":[81.20137,28.98068],"type":"Point"}
}