{
  "type": "Feature",
  "properties": {
    "gn:admin1_code":"ER",
    "gn:admin2_code":"7",
    "gn:admin3_code":"7.0",
    "gn:admin4_code":"70009.0",
    "gn:asciiname":"Chindribon",
    "gn:country_code":"NP",
    "gn:dem":1146,
    "gn:feature_class":"P",
    "gn:feature_code":"PPLL",
    "gn:name":"Chindribon",
    "gn:population":0,
    "gn:timezone":"Asia/Kathmandu",
    "iso:country":"NP",
    "wof:name":"Chindribon",
    "wof:placetype":"locality"
},
  "geometry": {"coordinates":[87.35821,26.9085],"type":"Point"}
}