{
  "type": "Feature",
  "properties": {
    "gn:admin1_code":"MR",
    "gn:admin2_code":"6",
    "gn:admin3_code":"66.0",
    "gn:admin4_code":"660009.0",
    "gn:asciiname":"Khalsera",
    "gn:country_code":"NP",
    "gn:dem":2623,
    "gn:feature_class":"P",
    "gn:feature_code":"PPLL",
    "gn:name":"Khalsera",
    "gn:population":0,
    "gn:timezone":"Asia/Kathmandu",
    "iso:country":"NP",
    "wof:name":"Khalsera",
    "wof:placetype":"locality"
},
  "geometry": {"coordinates":[81.84144999999999,29.66669000000001],"type":"Point"}
}