{
  "type": "Feature",
  "properties": {
    "gn:admin1_code":"ER",
    "gn:admin2_code":"13",
    "gn:admin3_code":"13.0",
    "gn:admin4_code":"130014.0",
    "gn:asciiname":"Chiplengitol",
    "gn:country_code":"NP",
    "gn:dem":1955,
    "gn:feature_class":"P",
    "gn:feature_code":"PPLL",
    "gn:name":"Chiplengitol",
    "gn:population":0,
    "gn:timezone":"Asia/Kathmandu",
    "iso:country":"NP",
    "wof:name":"Chiplengitol",
    "wof:placetype":"locality"
},
  "geometry": {"coordinates":[86.84889,27.12884],"type":"Point"}
}