{
  "type": "Feature",
  "properties": {
    "gn:admin1_code":"MR",
    "gn:admin2_code":"12",
    "gn:admin3_code":"56.0",
    "gn:admin4_code":"560039.0",
    "gn:asciiname":"Thulo Bahundanda",
    "gn:country_code":"NP",
    "gn:dem":669,
    "gn:feature_class":"P",
    "gn:feature_code":"PPLL",
    "gn:name":"Thulo Bahundanda",
    "gn:population":0,
    "gn:timezone":"Asia/Kathmandu",
    "iso:country":"NP",
    "wof:name":"Thulo Bahundanda",
    "wof:placetype":"locality"
},
  "geometry": {"coordinates":[82.46318000000002,28.05357],"type":"Point"}
}