{
  "type": "Feature",
  "properties": {
    "gn:admin1_code":"CR",
    "gn:admin2_code":"1",
    "gn:admin3_code":"23",
    "gn:admin4_code":"230020.0",
    "gn:asciiname":"Karangaira",
    "gn:country_code":"NP",
    "gn:dem":1400,
    "gn:feature_class":"P",
    "gn:feature_code":"PPLL",
    "gn:name":"Karangaira",
    "gn:population":0,
    "gn:timezone":"Asia/Kathmandu",
    "iso:country":"NP",
    "wof:name":"Karangaira",
    "wof:placetype":"locality"
},
  "geometry": {"coordinates":[85.80658000000003,27.77439],"type":"Point"}
}