{
  "type": "Feature",
  "properties": {
    "gn:admin1_code":"FR",
    "gn:admin2_code":"14",
    "gn:admin3_code":"69.0",
    "gn:admin4_code":"690021.0",
    "gn:asciiname":"Dupha",
    "gn:country_code":"NP",
    "gn:dem":1241,
    "gn:feature_class":"P",
    "gn:feature_code":"PPLL",
    "gn:name":"Dupha",
    "gn:population":0,
    "gn:timezone":"Asia/Kathmandu",
    "iso:country":"NP",
    "wof:name":"Dupha",
    "wof:placetype":"locality"
},
  "geometry": {"coordinates":[81.27364,29.00999],"type":"Point"}
}