{
  "type": "Feature",
  "properties": {
    "gn:admin1_code":"MR",
    "gn:admin2_code":"12",
    "gn:admin3_code":"56.0",
    "gn:admin4_code":"560032.0",
    "gn:asciiname":"Kamda",
    "gn:country_code":"NP",
    "gn:dem":622,
    "gn:feature_class":"P",
    "gn:feature_code":"PPLL",
    "gn:name":"Kamda",
    "gn:population":0,
    "gn:timezone":"Asia/Kathmandu",
    "iso:country":"NP",
    "wof:name":"Kamda",
    "wof:placetype":"locality"
},
  "geometry": {"coordinates":[82.44503,28.01603],"type":"Point"}
}