{
  "type": "Feature",
  "properties": {
    "gn:admin1_code":"WR",
    "gn:admin2_code":"4",
    "gn:admin3_code":"41",
    "gn:admin4_code":"410013",
    "gn:asciiname":"Rentuphant",
    "gn:country_code":"NP",
    "gn:dem":2460,
    "gn:feature_class":"P",
    "gn:feature_code":"PPLL",
    "gn:name":"Rentuphant",
    "gn:population":0,
    "gn:timezone":"Asia/Kathmandu",
    "iso:country":"NP",
    "wof:name":"Rentuphant",
    "wof:placetype":"locality"
},
  "geometry": {"coordinates":[84.32556,28.54104],"type":"Point"}
}