{
  "type": "Feature",
  "properties": {
    "gn:admin1_code":"ER",
    "gn:admin2_code":"10",
    "gn:admin3_code":"2",
    "gn:admin4_code":"20040",
    "gn:asciiname":"Akase",
    "gn:country_code":"NP",
    "gn:dem":1912,
    "gn:feature_class":"P",
    "gn:feature_code":"PPLL",
    "gn:name":"Akase",
    "gn:population":0,
    "gn:timezone":"Asia/Kathmandu",
    "iso:country":"NP",
    "wof:name":"Akase",
    "wof:placetype":"locality"
},
  "geometry": {"coordinates":[87.85597,27.16939],"type":"Point"}
}