{
  "type": "Feature",
  "properties": {
    "gn:admin1_code":"FR",
    "gn:admin2_code":"9",
    "gn:admin3_code":"73.0",
    "gn:admin4_code":"730018.0",
    "gn:asciiname":"Daul",
    "gn:country_code":"NP",
    "gn:dem":992,
    "gn:feature_class":"P",
    "gn:feature_code":"PPLL",
    "gn:name":"Daul",
    "gn:population":0,
    "gn:timezone":"Asia/Kathmandu",
    "iso:country":"NP",
    "wof:name":"Daul",
    "wof:placetype":"locality"
},
  "geometry": {"coordinates":[80.69046,29.31756],"type":"Point"}
}