{
  "type": "Feature",
  "properties": {
    "gn:admin1_code":"MR",
    "gn:admin2_code":"6",
    "gn:admin3_code":"64.0",
    "gn:admin4_code":"640011.0",
    "gn:asciiname":"Balde",
    "gn:country_code":"NP",
    "gn:dem":1053,
    "gn:feature_class":"P",
    "gn:feature_code":"PPLL",
    "gn:name":"Balde",
    "gn:population":0,
    "gn:timezone":"Asia/Kathmandu",
    "iso:country":"NP",
    "wof:name":"Balde",
    "wof:placetype":"locality"
},
  "geometry": {"coordinates":[81.56007,29.12795],"type":"Point"}
}