{
  "type": "Feature",
  "properties": {
    "gn:admin1_code":"FR",
    "gn:admin2_code":"14",
    "gn:admin3_code":"70.0",
    "gn:admin4_code":"700051.0",
    "gn:asciiname":"Amdora",
    "gn:country_code":"NP",
    "gn:dem":842,
    "gn:feature_class":"P",
    "gn:feature_code":"PPLL",
    "gn:name":"Amdora",
    "gn:population":0,
    "gn:timezone":"Asia/Kathmandu",
    "iso:country":"NP",
    "wof:name":"Amdora",
    "wof:placetype":"locality"
},
  "geometry": {"coordinates":[80.82958000000001,29.30767],"type":"Point"}
}