{
  "type": "Feature",
  "properties": {
    "gn:admin1_code":"WR",
    "gn:admin2_code":"8",
    "gn:admin3_code":"47",
    "gn:admin4_code":"470045",
    "gn:asciiname":"Chidibas",
    "gn:country_code":"NP",
    "gn:dem":1162,
    "gn:feature_class":"P",
    "gn:feature_code":"PPLL",
    "gn:name":"Chidibas",
    "gn:population":0,
    "gn:timezone":"Asia/Kathmandu",
    "iso:country":"NP",
    "wof:name":"Chidibas",
    "wof:placetype":"locality"
},
  "geometry": {"coordinates":[83.48846999999998,27.81985],"type":"Point"}
}