{
  "type": "Feature",
  "properties": {
    "gn:admin1_code":"CR",
    "gn:admin2_code":"11",
    "gn:admin3_code":"32",
    "gn:admin4_code":"320026",
    "gn:asciiname":"Dighatol",
    "gn:country_code":"NP",
    "gn:dem":78,
    "gn:feature_class":"P",
    "gn:feature_code":"PPLL",
    "gn:name":"Dighatol",
    "gn:population":0,
    "gn:timezone":"Asia/Kathmandu",
    "iso:country":"NP",
    "wof:name":"Dighatol",
    "wof:placetype":"locality"
},
  "geometry": {"coordinates":[85.28301,26.83361],"type":"Point"}
}