{
  "type": "Feature",
  "properties": {
    "gn:admin1_code":"FR",
    "gn:admin2_code":"9",
    "gn:admin3_code":"74",
    "gn:admin4_code":"740048",
    "gn:asciiname":"Jarauli",
    "gn:country_code":"NP",
    "gn:dem":1310,
    "gn:feature_class":"P",
    "gn:feature_code":"PPLL",
    "gn:name":"Jarauli",
    "gn:population":0,
    "gn:timezone":"Asia/Kathmandu",
    "iso:country":"NP",
    "wof:name":"Jarauli",
    "wof:placetype":"locality"
},
  "geometry": {"coordinates":[80.5322,29.44834],"type":"Point"}
}