{
  "type": "Feature",
  "properties": {
    "gn:admin1_code":"ER",
    "gn:admin2_code":"7",
    "gn:admin3_code":"5",
    "gn:admin4_code":"50037",
    "gn:asciiname":"Patapur",
    "gn:country_code":"NP",
    "gn:dem":597,
    "gn:feature_class":"P",
    "gn:feature_code":"PPLL",
    "gn:name":"Patapur",
    "gn:population":0,
    "gn:timezone":"Asia/Kathmandu",
    "iso:country":"NP",
    "wof:name":"Patapur",
    "wof:placetype":"locality"
},
  "geometry": {"coordinates":[87.51309999999999,26.77106],"type":"Point"}
}