{
  "type": "Feature",
  "properties": {
    "gn:admin1_code":"MR",
    "gn:admin2_code":"12",
    "gn:admin3_code":"53",
    "gn:admin4_code":"530041",
    "gn:asciiname":"Sakhi",
    "gn:country_code":"NP",
    "gn:dem":1499,
    "gn:feature_class":"P",
    "gn:feature_code":"PPLL",
    "gn:name":"Sakhi",
    "gn:population":0,
    "gn:timezone":"Asia/Kathmandu",
    "iso:country":"NP",
    "name:cat_x_preferred":[
        "Sakhi"
    ],
    "name:hin_x_preferred":[
        "\u0938\u0916\u0940 \u0938\u0902\u092a\u094d\u0930\u0926\u093e\u092f"
    ],
    "wof:name":"Sakhi",
    "wof:placetype":"locality"
},
  "geometry": {"coordinates":[82.52842,28.19931],"type":"Point"}
}