{
  "type": "Feature",
  "properties": {
    "gn:admin1_code":"ER",
    "gn:admin2_code":"10",
    "gn:admin3_code":"3.0",
    "gn:admin4_code":"30021.0",
    "gn:asciiname":"Bhalujhoda",
    "gn:country_code":"NP",
    "gn:dem":767,
    "gn:feature_class":"P",
    "gn:feature_code":"PPLL",
    "gn:name":"Bhalujhoda",
    "gn:population":0,
    "gn:timezone":"Asia/Kathmandu",
    "iso:country":"NP",
    "wof:name":"Bhalujhoda",
    "wof:placetype":"locality"
},
  "geometry": {"coordinates":[88.0673,26.80407],"type":"Point"}
}