{
  "type": "Feature",
  "properties": {
    "gn:admin1_code":"ER",
    "gn:admin2_code":"7",
    "gn:admin3_code":"7.0",
    "gn:admin4_code":"70017.0",
    "gn:asciiname":"Tilkekulo",
    "gn:country_code":"NP",
    "gn:dem":842,
    "gn:feature_class":"P",
    "gn:feature_code":"PPLL",
    "gn:name":"Tilkekulo",
    "gn:population":0,
    "gn:timezone":"Asia/Kathmandu",
    "iso:country":"NP",
    "wof:name":"Tilkekulo",
    "wof:placetype":"locality"
},
  "geometry": {"coordinates":[87.23052,27.08838],"type":"Point"}
}