{
  "type": "Feature",
  "properties": {
    "gn:admin1_code":"CR",
    "gn:admin2_code":"1",
    "gn:admin3_code":"29",
    "gn:admin4_code":"290014.0",
    "gn:asciiname":"Thulo Shyaphru",
    "gn:country_code":"NP",
    "gn:dem":2124,
    "gn:feature_class":"P",
    "gn:feature_code":"PPLL",
    "gn:name":"Thulo Shyaphru",
    "gn:population":0,
    "gn:timezone":"Asia/Kathmandu",
    "iso:country":"NP",
    "wof:name":"Thulo Shyaphru",
    "wof:placetype":"locality"
},
  "geometry": {"coordinates":[85.36359,28.14503],"type":"Point"}
}