{
  "type": "Feature",
  "properties": {
    "gn:admin1_code":"MR",
    "gn:admin2_code":"2",
    "gn:admin3_code":"61.0",
    "gn:admin4_code":"610009.0",
    "gn:asciiname":"Bara Baluwa",
    "gn:country_code":"NP",
    "gn:dem":697,
    "gn:feature_class":"P",
    "gn:feature_code":"PPLL",
    "gn:name":"Bara Baluwa",
    "gn:population":0,
    "gn:timezone":"Asia/Kathmandu",
    "iso:country":"NP",
    "wof:name":"Bara Baluwa",
    "wof:placetype":"locality"
},
  "geometry": {"coordinates":[82.16819,28.61936],"type":"Point"}
}