{
  "type": "Feature",
  "properties": {
    "gn:admin1_code":"ER",
    "gn:admin2_code":"7",
    "gn:admin3_code":"9",
    "gn:admin4_code":"90014",
    "gn:asciiname":"Palung",
    "gn:country_code":"NP",
    "gn:dem":1018,
    "gn:feature_class":"P",
    "gn:feature_code":"PPLL",
    "gn:name":"Palung",
    "gn:population":0,
    "gn:timezone":"Asia/Kathmandu",
    "iso:country":"NP",
    "wof:name":"Palung",
    "wof:placetype":"locality"
},
  "geometry": {"coordinates":[87.23401,27.26453],"type":"Point"}
}