{
  "type": "Feature",
  "properties": {
    "gn:admin1_code":"CR",
    "gn:admin2_code":"5",
    "gn:admin3_code":"22.0",
    "gn:admin4_code":"220020.0",
    "gn:asciiname":"Tuspe",
    "gn:country_code":"NP",
    "gn:dem":1658,
    "gn:feature_class":"P",
    "gn:feature_code":"PPLL",
    "gn:name":"Tuspe",
    "gn:population":0,
    "gn:timezone":"Asia/Kathmandu",
    "iso:country":"NP",
    "wof:name":"Tuspe",
    "wof:placetype":"locality"
},
  "geometry": {"coordinates":[86.18169,27.56153],"type":"Point"}
}