{
  "type": "Feature",
  "properties": {
    "gn:admin1_code":"WR",
    "gn:admin2_code":"4.0",
    "gn:admin3_code":"39.0",
    "gn:admin4_code":"390014.0",
    "gn:asciiname":"Mansyankot",
    "gn:country_code":"NP",
    "gn:dem":1123,
    "gn:feature_class":"P",
    "gn:feature_code":"PPLL",
    "gn:name":"Mansyankot",
    "gn:population":0,
    "gn:timezone":"Asia/Kathmandu",
    "iso:country":"NP",
    "wof:name":"Mansyankot",
    "wof:placetype":"locality"
},
  "geometry": {"coordinates":[83.79914000000002,28.00312000000001],"type":"Point"}
}