{
  "type": "Feature",
  "properties": {
    "gn:admin1_code":"WR",
    "gn:admin2_code":"4.0",
    "gn:admin3_code":"38.0",
    "gn:admin4_code":"380012.0",
    "gn:asciiname":"Pipal Chhang",
    "gn:country_code":"NP",
    "gn:dem":867,
    "gn:feature_class":"P",
    "gn:feature_code":"PPLL",
    "gn:name":"Pipal Chhang",
    "gn:population":0,
    "gn:timezone":"Asia/Kathmandu",
    "iso:country":"NP",
    "wof:name":"Pipal Chhang",
    "wof:placetype":"locality"
},
  "geometry": {"coordinates":[84.12614000000001,27.99084],"type":"Point"}
}