{
  "type": "Feature",
  "properties": {
    "gn:admin1_code":"ER",
    "gn:admin2_code":"10",
    "gn:admin3_code":"3.0",
    "gn:admin4_code":"30043.0",
    "gn:asciiname":"Dubletar",
    "gn:country_code":"NP",
    "gn:dem":490,
    "gn:feature_class":"P",
    "gn:feature_code":"PPLL",
    "gn:name":"Dubletar",
    "gn:population":0,
    "gn:timezone":"Asia/Kathmandu",
    "iso:country":"NP",
    "wof:name":"Dubletar",
    "wof:placetype":"locality"
},
  "geometry": {"coordinates":[88.03224,26.82027],"type":"Point"}
}