{
  "type": "Feature",
  "properties": {
    "gn:admin1_code":"ER",
    "gn:admin2_code":"7",
    "gn:admin3_code":"9",
    "gn:admin4_code":"90020",
    "gn:asciiname":"Satbaini",
    "gn:country_code":"NP",
    "gn:dem":1856,
    "gn:feature_class":"P",
    "gn:feature_code":"PPLL",
    "gn:name":"Satbaini",
    "gn:population":0,
    "gn:timezone":"Asia/Kathmandu",
    "iso:country":"NP",
    "wof:name":"Satbaini",
    "wof:placetype":"locality"
},
  "geometry": {"coordinates":[87.24590000000001,27.4859],"type":"Point"}
}