{
  "type": "Feature",
  "properties": {
    "gn:admin1_code":"WR",
    "gn:admin2_code":"8",
    "gn:admin3_code":"46.0",
    "gn:admin4_code":"460012.0",
    "gn:asciiname":"Dagar",
    "gn:country_code":"NP",
    "gn:dem":1638,
    "gn:feature_class":"P",
    "gn:feature_code":"PPLL",
    "gn:name":"Dagar",
    "gn:population":0,
    "gn:timezone":"Asia/Kathmandu",
    "iso:country":"NP",
    "wof:name":"Dagar",
    "wof:placetype":"locality"
},
  "geometry": {"coordinates":[83.0727,28.20096],"type":"Point"}
}