{
  "type": "Feature",
  "properties": {
    "gn:admin1_code":"CR",
    "gn:admin2_code":"5",
    "gn:admin3_code":"21",
    "gn:admin4_code":"210042",
    "gn:asciiname":"Sano Pirati",
    "gn:country_code":"NP",
    "gn:dem":1371,
    "gn:feature_class":"P",
    "gn:feature_code":"PPLL",
    "gn:name":"Sano Pirati",
    "gn:population":0,
    "gn:timezone":"Asia/Kathmandu",
    "iso:country":"NP",
    "wof:name":"Sano Pirati",
    "wof:placetype":"locality"
},
  "geometry": {"coordinates":[86.31241999999997,27.49663],"type":"Point"}
}