{
  "type": "Feature",
  "properties": {
    "gn:admin1_code":"CR",
    "gn:admin2_code":"11",
    "gn:admin3_code":"31",
    "gn:admin4_code":"310026",
    "gn:asciiname":"Ekledamar",
    "gn:country_code":"NP",
    "gn:dem":2068,
    "gn:feature_class":"P",
    "gn:feature_code":"PPLL",
    "gn:name":"Ekledamar",
    "gn:population":0,
    "gn:timezone":"Asia/Kathmandu",
    "iso:country":"NP",
    "wof:name":"Ekledamar",
    "wof:placetype":"locality"
},
  "geometry": {"coordinates":[85.1763,27.54268],"type":"Point"}
}