{
  "type": "Feature",
  "properties": {
    "gn:admin1_code":"ER",
    "gn:admin2_code":"10",
    "gn:admin3_code":"2",
    "gn:admin4_code":"20018",
    "gn:asciiname":"Dhuping",
    "gn:country_code":"NP",
    "gn:dem":1144,
    "gn:feature_class":"P",
    "gn:feature_code":"PPLL",
    "gn:name":"Dhuping",
    "gn:population":0,
    "gn:timezone":"Asia/Kathmandu",
    "iso:country":"NP",
    "wof:name":"Dhuping",
    "wof:placetype":"locality"
},
  "geometry": {"coordinates":[87.62257,27.01578],"type":"Point"}
}