{
  "type": "Feature",
  "properties": {
    "gn:admin1_code":"ER",
    "gn:admin2_code":"13",
    "gn:admin3_code":"12",
    "gn:admin4_code":"120010",
    "gn:asciiname":"Khanigaun",
    "gn:country_code":"NP",
    "gn:dem":1918,
    "gn:feature_class":"P",
    "gn:feature_code":"PPLL",
    "gn:name":"Khanigaun",
    "gn:population":0,
    "gn:timezone":"Asia/Kathmandu",
    "iso:country":"NP",
    "wof:name":"Khanigaun",
    "wof:placetype":"locality"
},
  "geometry": {"coordinates":[86.34065,27.34932],"type":"Point"}
}