{
  "type": "Feature",
  "properties": {
    "gn:admin1_code":"WR",
    "gn:admin2_code":"4.0",
    "gn:admin3_code":"39.0",
    "gn:admin4_code":"390050.0",
    "gn:asciiname":"Gillan",
    "gn:country_code":"NP",
    "gn:dem":551,
    "gn:feature_class":"P",
    "gn:feature_code":"PPLL",
    "gn:name":"Gillan",
    "gn:population":0,
    "gn:timezone":"Asia/Kathmandu",
    "iso:country":"NP",
    "wof:name":"Gillan",
    "wof:placetype":"locality"
},
  "geometry": {"coordinates":[83.866,27.92639],"type":"Point"}
}