{
  "type": "Feature",
  "properties": {
    "gn:admin1_code":"CR",
    "gn:admin2_code":"1",
    "gn:admin3_code":"23",
    "gn:admin4_code":"230024.0",
    "gn:asciiname":"Tarke",
    "gn:country_code":"NP",
    "gn:dem":1014,
    "gn:feature_class":"P",
    "gn:feature_code":"PPLL",
    "gn:name":"Tarke",
    "gn:population":0,
    "gn:timezone":"Asia/Kathmandu",
    "iso:country":"NP",
    "wof:name":"Tarke",
    "wof:placetype":"locality"
},
  "geometry": {"coordinates":[85.7591,27.88975],"type":"Point"}
}