{
  "type": "Feature",
  "properties": {
    "gn:admin1_code":"WR",
    "gn:admin2_code":"4",
    "gn:admin3_code":"36.0",
    "gn:admin4_code":"360043.0",
    "gn:asciiname":"Kayapani",
    "gn:country_code":"NP",
    "gn:dem":968,
    "gn:feature_class":"P",
    "gn:feature_code":"PPLL",
    "gn:name":"Kayapani",
    "gn:population":0,
    "gn:timezone":"Asia/Kathmandu",
    "iso:country":"NP",
    "wof:name":"Kayapani",
    "wof:placetype":"locality"
},
  "geometry": {"coordinates":[84.7371,28.03938],"type":"Point"}
}