{
  "type": "Feature",
  "properties": {
    "gn:admin1_code":"WR",
    "gn:admin2_code":"8",
    "gn:admin3_code":"50.0",
    "gn:admin4_code":"500035.0",
    "gn:asciiname":"Shiwalaya",
    "gn:country_code":"NP",
    "gn:dem":98,
    "gn:feature_class":"P",
    "gn:feature_code":"PPLL",
    "gn:name":"Shiwalaya",
    "gn:population":0,
    "gn:timezone":"Asia/Kathmandu",
    "iso:country":"NP",
    "wof:name":"Shiwalaya",
    "wof:placetype":"locality"
},
  "geometry": {"coordinates":[83.19495999999999,27.45564],"type":"Point"}
}