{
  "type": "Feature",
  "properties": {
    "gn:admin1_code":"00",
    "gn:asciiname":"Komran",
    "gn:country_code":"NP",
    "gn:dem":1785,
    "gn:feature_class":"P",
    "gn:feature_code":"PPL",
    "gn:name":"Komr\u0101\u1e45",
    "gn:population":0,
    "gn:timezone":"Asia/Kathmandu",
    "iso:country":"NP",
    "wof:name":"Komran",
    "wof:placetype":"locality"
},
  "geometry": {"coordinates":[85.63049000000002,27.94778],"type":"Point"}
}