{
  "type": "Feature",
  "properties": {
    "gn:admin1_code":"FR",
    "gn:admin2_code":"14",
    "gn:admin3_code":"70.0",
    "gn:admin4_code":"700029.0",
    "gn:asciiname":"Gadbata",
    "gn:country_code":"NP",
    "gn:dem":1609,
    "gn:feature_class":"P",
    "gn:feature_code":"PPLL",
    "gn:name":"Gadbata",
    "gn:population":0,
    "gn:timezone":"Asia/Kathmandu",
    "iso:country":"NP",
    "wof:name":"Gadbata",
    "wof:placetype":"locality"
},
  "geometry": {"coordinates":[81.03106,29.29948],"type":"Point"}
}