{
  "type": "Feature",
  "properties": {
    "gn:admin1_code":"CR",
    "gn:admin2_code":"5",
    "gn:admin3_code":"21",
    "gn:admin4_code":"210003",
    "gn:asciiname":"Dabu",
    "gn:country_code":"NP",
    "gn:dem":1164,
    "gn:feature_class":"P",
    "gn:feature_code":"PPLL",
    "gn:name":"Dabu",
    "gn:population":0,
    "gn:timezone":"Asia/Kathmandu",
    "iso:country":"NP",
    "name:ceb_x_preferred":[
        "Dabu"
    ],
    "name:deu_x_preferred":[
        "Dabu"
    ],
    "name:fra_x_preferred":[
        "Dabu"
    ],
    "name:ita_x_preferred":[
        "Dabu"
    ],
    "wof:name":"Dabu",
    "wof:placetype":"locality"
},
  "geometry": {"coordinates":[85.82476,27.5035],"type":"Point"}
}