{
  "type": "Feature",
  "properties": {
    "gn:admin1_code":"CR",
    "gn:admin2_code":"1",
    "gn:admin3_code":"28",
    "gn:admin4_code":"280017",
    "gn:asciiname":"Polchet",
    "gn:country_code":"NP",
    "gn:dem":1637,
    "gn:feature_class":"P",
    "gn:feature_code":"PPLL",
    "gn:name":"Polchet",
    "gn:population":0,
    "gn:timezone":"Asia/Kathmandu",
    "iso:country":"NP",
    "wof:name":"Polchet",
    "wof:placetype":"locality"
},
  "geometry": {"coordinates":[85.05645,27.97598],"type":"Point"}
}