{
  "type": "Feature",
  "properties": {
    "gn:admin1_code":"MR",
    "gn:admin2_code":"12",
    "gn:admin3_code":"56.0",
    "gn:admin4_code":"560005.0",
    "gn:asciiname":"Devipur",
    "gn:country_code":"NP",
    "gn:dem":552,
    "gn:feature_class":"P",
    "gn:feature_code":"PPLL",
    "gn:name":"Devipur",
    "gn:population":0,
    "gn:timezone":"Asia/Kathmandu",
    "iso:country":"NP",
    "wof:name":"Devipur",
    "wof:placetype":"locality"
},
  "geometry": {"coordinates":[82.13302,28.12683],"type":"Point"}
}