{
  "type": "Feature",
  "properties": {
    "gn:admin1_code":"MR",
    "gn:admin2_code":"12",
    "gn:admin3_code":"55",
    "gn:admin4_code":"550005",
    "gn:asciiname":"Maineri",
    "gn:country_code":"NP",
    "gn:dem":1247,
    "gn:feature_class":"P",
    "gn:feature_code":"PPLL",
    "gn:name":"Maineri",
    "gn:population":0,
    "gn:timezone":"Asia/Kathmandu",
    "iso:country":"NP",
    "wof:name":"Maineri",
    "wof:placetype":"locality"
},
  "geometry": {"coordinates":[82.28139,28.58621],"type":"Point"}
}