{
  "type": "Feature",
  "properties": {
    "gn:admin1_code":"WR",
    "gn:admin2_code":"8",
    "gn:admin3_code":"50.0",
    "gn:admin4_code":"500015.0",
    "gn:asciiname":"Dharmanagar",
    "gn:country_code":"NP",
    "gn:dem":125,
    "gn:feature_class":"P",
    "gn:feature_code":"PPLL",
    "gn:name":"Dharmanagar",
    "gn:population":0,
    "gn:timezone":"Asia/Kathmandu",
    "iso:country":"NP",
    "name:ben_x_preferred":[
        "\u09a7\u09b0\u09cd\u09ae\u09a8\u0997\u09b0"
    ],
    "name:bpy_x_preferred":[
        "\u09a7\u09b0\u09cd\u09ae\u09a8\u0997\u09b0"
    ],
    "name:ceb_x_preferred":[
        "Dharmanagar"
    ],
    "name:fra_x_preferred":[
        "Dharmanagar"
    ],
    "name:hin_x_preferred":[
        "\u0927\u0930\u094d\u092e\u0928\u0917\u0930"
    ],
    "name:ita_x_preferred":[
        "Dharmanagar"
    ],
    "name:mlg_x_preferred":[
        "Dharmanagar"
    ],
    "name:msa_x_preferred":[
        "Dharmanagar"
    ],
    "name:new_x_preferred":[
        "\u0927\u0930\u094d\u092e\u0928\u0917\u0930"
    ],
    "name:nld_x_preferred":[
        "Dharmanagar"
    ],
    "name:ori_x_preferred":[
        "\u0b27\u0b30\u0b4d\u0b2e\u0b28\u0b17\u0b30"
    ],
    "name:pol_x_preferred":[
        "Dharmanagar"
    ],
    "name:por_x_preferred":[
        "Dharmanagar"
    ],
    "name:swe_x_preferred":[
        "Dharmanagar"
    ],
    "name:tam_x_preferred":[
        "\u0ba4\u0bb0\u0bcd\u0bae\u0ba8\u0b95\u0bb0\u0bcd"
    ],
    "name:urd_x_preferred":[
        "\u062f\u06be\u0631\u0645\u0627\u0646\u06af\u0631"
    ],
    "name:vie_x_preferred":[
        "Dharmanagar"
    ],
    "name:zho_x_preferred":[
        "\u8fbe\u5c14\u9a6c\u7eb3\u52a0\u5c14"
    ],
    "wof:name":"Dharmanagar",
    "wof:placetype":"locality"
},
  "geometry": {"coordinates":[82.85599000000001,27.62346],"type":"Point"}
}