{
  "type": "Feature",
  "properties": {
    "gn:admin1_code":"CR",
    "gn:admin2_code":"1",
    "gn:admin3_code":"30.0",
    "gn:admin4_code":"300024.0",
    "gn:asciiname":"Dhuseni",
    "gn:country_code":"NP",
    "gn:dem":952,
    "gn:feature_class":"P",
    "gn:feature_code":"PPLL",
    "gn:name":"Dhuseni",
    "gn:population":0,
    "gn:timezone":"Asia/Kathmandu",
    "iso:country":"NP",
    "name:fra_x_preferred":[
        "Dhuseni"
    ],
    "name:pol_x_preferred":[
        "Dhuseni"
    ],
    "wof:name":"Dhuseni",
    "wof:placetype":"locality"
},
  "geometry": {"coordinates":[84.76503000000002,27.93148],"type":"Point"}
}