{
  "type": "Feature",
  "properties": {
    "gn:admin1_code":"WR",
    "gn:admin2_code":"3",
    "gn:admin3_code":"44",
    "gn:admin4_code":"440010",
    "gn:asciiname":"Deurali",
    "gn:country_code":"NP",
    "gn:dem":1563,
    "gn:feature_class":"P",
    "gn:feature_code":"PPLL",
    "gn:name":"Deurali",
    "gn:population":0,
    "gn:timezone":"Asia/Kathmandu",
    "iso:country":"NP",
    "wof:name":"Deurali",
    "wof:placetype":"locality"
},
  "geometry": {"coordinates":[83.63238,28.08964000000001],"type":"Point"}
}