{
  "type": "Feature",
  "properties": {
    "gn:admin1_code":"MR",
    "gn:admin2_code":"6",
    "gn:admin3_code":"65",
    "gn:admin4_code":"650023",
    "gn:asciiname":"Harnikandh",
    "gn:country_code":"NP",
    "gn:dem":1779,
    "gn:feature_class":"P",
    "gn:feature_code":"PPLL",
    "gn:name":"Harnikandh",
    "gn:population":0,
    "gn:timezone":"Asia/Kathmandu",
    "iso:country":"NP",
    "wof:name":"Harnikandh",
    "wof:placetype":"locality"
},
  "geometry": {"coordinates":[82.15591999999999,29.56067],"type":"Point"}
}