{
  "type": "Feature",
  "properties": {
    "gn:admin1_code":"CR",
    "gn:admin2_code":"5",
    "gn:admin3_code":"19",
    "gn:admin4_code":"190076",
    "gn:asciiname":"Tinghare",
    "gn:country_code":"NP",
    "gn:dem":217,
    "gn:feature_class":"P",
    "gn:feature_code":"PPLL",
    "gn:name":"Tinghare",
    "gn:population":0,
    "gn:timezone":"Asia/Kathmandu",
    "iso:country":"NP",
    "wof:name":"Tinghare",
    "wof:placetype":"locality"
},
  "geometry": {"coordinates":[85.72435,27.06864],"type":"Point"}
}