{
  "type": "Feature",
  "properties": {
    "gn:admin1_code":"WR",
    "gn:admin2_code":"3",
    "gn:admin3_code":"44",
    "gn:admin4_code":"440038",
    "gn:asciiname":"Daha",
    "gn:country_code":"NP",
    "gn:dem":1048,
    "gn:feature_class":"P",
    "gn:feature_code":"PPLL",
    "gn:name":"Daha",
    "gn:population":0,
    "gn:timezone":"Asia/Kathmandu",
    "iso:country":"NP",
    "name:ceb_x_preferred":[
        "Daha"
    ],
    "name:fra_x_preferred":[
        "Daha"
    ],
    "name:ind_x_preferred":[
        "Daha"
    ],
    "name:ita_x_preferred":[
        "Daha"
    ],
    "name:swe_x_preferred":[
        "Daha"
    ],
    "name:uzb_x_preferred":[
        "Daha"
    ],
    "wof:name":"Daha",
    "wof:placetype":"locality"
},
  "geometry": {"coordinates":[83.60641,28.29158],"type":"Point"}
}