{
  "type": "Feature",
  "properties": {
    "gn:admin1_code":"CR",
    "gn:admin2_code":"5",
    "gn:admin3_code":"20",
    "gn:admin4_code":"200022.0",
    "gn:asciiname":"Kattike",
    "gn:country_code":"NP",
    "gn:dem":1134,
    "gn:feature_class":"P",
    "gn:feature_code":"PPLL",
    "gn:name":"Kattike",
    "gn:population":0,
    "gn:timezone":"Asia/Kathmandu",
    "iso:country":"NP",
    "wof:name":"Kattike",
    "wof:placetype":"locality"
},
  "geometry": {"coordinates":[86.2491,27.10535],"type":"Point"}
}