{
  "type": "Feature",
  "properties": {
    "gn:admin1_code":"FR",
    "gn:admin2_code":"14",
    "gn:admin3_code":"71.0",
    "gn:admin4_code":"710031.0",
    "gn:asciiname":"Pal Bajar",
    "gn:country_code":"NP",
    "gn:dem":180,
    "gn:feature_class":"P",
    "gn:feature_code":"PPLL",
    "gn:name":"Pal Bajar",
    "gn:population":0,
    "gn:timezone":"Asia/Kathmandu",
    "iso:country":"NP",
    "wof:name":"Pal Bajar",
    "wof:placetype":"locality"
},
  "geometry": {"coordinates":[81.17015000000001,28.59238],"type":"Point"}
}