{
  "type": "Feature",
  "properties": {
    "gn:admin1_code":"ER",
    "gn:admin2_code":"13.0",
    "gn:admin3_code":"14.0",
    "gn:admin4_code":"140043.0",
    "gn:asciiname":"Damauti",
    "gn:country_code":"NP",
    "gn:dem":176,
    "gn:feature_class":"P",
    "gn:feature_code":"PPLL",
    "gn:name":"Damauti",
    "gn:population":0,
    "gn:timezone":"Asia/Kathmandu",
    "iso:country":"NP",
    "wof:name":"Damauti",
    "wof:placetype":"locality"
},
  "geometry": {"coordinates":[86.62553,26.7402],"type":"Point"}
}