{
  "type": "Feature",
  "properties": {
    "gn:admin1_code":"CR",
    "gn:admin2_code":"1.0",
    "gn:admin3_code":"26.0",
    "gn:admin4_code":"260005.0",
    "gn:asciiname":"Bhajubhairav",
    "gn:country_code":"NP",
    "gn:dem":1356,
    "gn:feature_class":"P",
    "gn:feature_code":"PPLL",
    "gn:name":"Bhajubhairav",
    "gn:population":0,
    "gn:timezone":"Asia/Kathmandu",
    "iso:country":"NP",
    "wof:name":"Bhajubhairav",
    "wof:placetype":"locality"
},
  "geometry": {"coordinates":[85.4619,27.70074],"type":"Point"}
}