{
  "type": "Feature",
  "properties": {
    "gn:admin1_code":"00",
    "gn:asciiname":"Bajartol",
    "gn:country_code":"NP",
    "gn:dem":99,
    "gn:feature_class":"P",
    "gn:feature_code":"PPL",
    "gn:name":"Baj\u0101r\u1e6dol",
    "gn:population":0,
    "gn:timezone":"Asia/Kathmandu",
    "iso:country":"NP",
    "wof:name":"Bajartol",
    "wof:placetype":"locality"
},
  "geometry": {"coordinates":[85.43231999999998,26.99791],"type":"Point"}
}