{
  "type": "Feature",
  "properties": {
    "gn:admin1_code":"CR",
    "gn:admin2_code":"5.0",
    "gn:asciiname":"Manthali",
    "gn:country_code":"NP",
    "gn:dem":585,
    "gn:feature_class":"P",
    "gn:feature_code":"PPL",
    "gn:name":"Manthali",
    "gn:population":0,
    "gn:timezone":"Asia/Kathmandu",
    "iso:country":"NP",
    "name:new_x_preferred":[
        "\u092e\u0928\u094d\u0925\u0932\u0940"
    ],
    "wof:name":"Manthali",
    "wof:placetype":"locality"
},
  "geometry": {"coordinates":[86.06899,27.37776],"type":"Point"}
}