{
  "type": "Feature",
  "properties": {
    "gn:admin1_code":"ER",
    "gn:admin2_code":"13",
    "gn:admin3_code":"12",
    "gn:admin4_code":"120003",
    "gn:asciiname":"Balkhu",
    "gn:country_code":"NP",
    "gn:dem":963,
    "gn:feature_class":"P",
    "gn:feature_code":"PPLL",
    "gn:name":"Balkhu",
    "gn:population":0,
    "gn:timezone":"Asia/Kathmandu",
    "iso:country":"NP",
    "wof:name":"Balkhu",
    "wof:placetype":"locality"
},
  "geometry": {"coordinates":[86.34104000000001,27.24138],"type":"Point"}
}