{
  "type": "Feature",
  "properties": {
    "gn:admin1_code":"WR",
    "gn:admin2_code":"4",
    "gn:admin3_code":"36.0",
    "gn:admin4_code":"360002.0",
    "gn:asciiname":"Arbang",
    "gn:country_code":"NP",
    "gn:dem":1229,
    "gn:feature_class":"P",
    "gn:feature_code":"PPLL",
    "gn:name":"Arbang",
    "gn:population":0,
    "gn:timezone":"Asia/Kathmandu",
    "iso:country":"NP",
    "wof:name":"Arbang",
    "wof:placetype":"locality"
},
  "geometry": {"coordinates":[84.80488000000003,28.09475],"type":"Point"}
}