{
  "type": "Feature",
  "properties": {
    "gn:admin1_code":"WR",
    "gn:admin2_code":"4",
    "gn:admin3_code":"40.0",
    "gn:admin4_code":"400043.0",
    "gn:asciiname":"Thulo Besi",
    "gn:country_code":"NP",
    "gn:dem":916,
    "gn:feature_class":"P",
    "gn:feature_code":"PPLL",
    "gn:name":"Thulo Besi",
    "gn:population":0,
    "gn:timezone":"Asia/Kathmandu",
    "iso:country":"NP",
    "wof:name":"Thulo Besi",
    "wof:placetype":"locality"
},
  "geometry": {"coordinates":[84.08310999999998,28.25905],"type":"Point"}
}