{
  "type": "Feature",
  "properties": {
    "gn:admin1_code":"ER",
    "gn:admin2_code":"13",
    "gn:admin3_code":"11",
    "gn:admin4_code":"110018",
    "gn:asciiname":"Lobuche",
    "gn:country_code":"NP",
    "gn:dem":5951,
    "gn:feature_class":"P",
    "gn:feature_code":"PPLL",
    "gn:name":"Lobuche",
    "gn:population":0,
    "gn:timezone":"Asia/Kathmandu",
    "iso:country":"NP",
    "name:deu_x_preferred":[
        "Lobuche"
    ],
    "name:fin_x_preferred":[
        "Lobuche"
    ],
    "name:fra_x_preferred":[
        "Lobuche"
    ],
    "name:ita_x_preferred":[
        "Lobuche"
    ],
    "name:pol_x_preferred":[
        "Lobuche"
    ],
    "name:rus_x_preferred":[
        "\u041b\u043e\u0431\u0443\u0447\u0435"
    ],
    "name:ukr_x_preferred":[
        "\u041b\u043e\u0431\u0443\u0447\u0435"
    ],
    "name:zho_x_preferred":[
        "\u7f85\u5e03\u5d0e\u5cf0"
    ],
    "wof:name":"Lobuche",
    "wof:placetype":"locality"
},
  "geometry": {"coordinates":[86.78453,27.97018],"type":"Point"}
}