{
  "type": "Feature",
  "properties": {
    "gn:admin1_code":"MR",
    "gn:admin2_code":"2.0",
    "gn:admin3_code":"59.0",
    "gn:admin4_code":"590036.0",
    "gn:asciiname":"Tule",
    "gn:country_code":"NP",
    "gn:dem":1525,
    "gn:feature_class":"P",
    "gn:feature_code":"PPLL",
    "gn:name":"Tule",
    "gn:population":0,
    "gn:timezone":"Asia/Kathmandu",
    "iso:country":"NP",
    "wof:name":"Tule",
    "wof:placetype":"locality"
},
  "geometry": {"coordinates":[81.83256999999998,28.64679000000001],"type":"Point"}
}