{
  "type": "Feature",
  "properties": {
    "gn:admin1_code":"MR",
    "gn:admin2_code":"12",
    "gn:admin3_code":"53",
    "gn:admin4_code":"530002",
    "gn:asciiname":"Naima",
    "gn:country_code":"NP",
    "gn:dem":1655,
    "gn:feature_class":"P",
    "gn:feature_code":"PPLL",
    "gn:name":"Naima",
    "gn:population":0,
    "gn:timezone":"Asia/Kathmandu",
    "iso:country":"NP",
    "name:deu_x_preferred":[
        "Naima"
    ],
    "name:fra_x_preferred":[
        "Naima"
    ],
    "name:ita_x_preferred":[
        "Naima"
    ],
    "wof:name":"Naima",
    "wof:placetype":"locality"
},
  "geometry": {"coordinates":[82.60654,28.38724],"type":"Point"}
}