{
  "type": "Feature",
  "properties": {
    "gn:admin1_code":"FR",
    "gn:admin2_code":"14",
    "gn:admin3_code":"71.0",
    "gn:admin4_code":"710044.0",
    "gn:asciiname":"Byushah",
    "gn:country_code":"NP",
    "gn:dem":181,
    "gn:feature_class":"P",
    "gn:feature_code":"PPLL",
    "gn:name":"Byushah",
    "gn:population":0,
    "gn:timezone":"Asia/Kathmandu",
    "iso:country":"NP",
    "wof:name":"Byushah",
    "wof:placetype":"locality"
},
  "geometry": {"coordinates":[80.71471,28.73503],"type":"Point"}
}