{
  "type": "Feature",
  "properties": {
    "gn:admin1_code":"00",
    "gn:asciiname":"Pokhari",
    "gn:country_code":"NP",
    "gn:dem":1903,
    "gn:feature_class":"P",
    "gn:feature_code":"PPL",
    "gn:name":"Pokhari\u0307\u0304",
    "gn:population":0,
    "gn:timezone":"Asia/Kathmandu",
    "iso:country":"NP",
    "name:ceb_x_preferred":[
        "Pokhari"
    ],
    "name:fra_x_preferred":[
        "Pokhari"
    ],
    "name:ita_x_preferred":[
        "Pokhari"
    ],
    "name:nep_x_preferred":[
        "Pokhari\u0307\u0304"
    ],
    "name:new_x_preferred":[
        "\u092a\u094b\u0916\u0930\u0940"
    ],
    "name:pol_x_preferred":[
        "Pokhari"
    ],
    "wof:name":"Pokhari",
    "wof:placetype":"locality"
},
  "geometry": {"coordinates":[87.63987,26.96823],"type":"Point"}
}