{
  "type": "Feature",
  "properties": {
    "gn:admin1_code":"ER",
    "gn:admin2_code":"7.0",
    "gn:admin3_code":"8.0",
    "gn:admin4_code":"80001.0",
    "gn:asciiname":"Ambun",
    "gn:country_code":"NP",
    "gn:dem":1537,
    "gn:feature_class":"P",
    "gn:feature_code":"PPLL",
    "gn:name":"Ambun",
    "gn:population":0,
    "gn:timezone":"Asia/Kathmandu",
    "iso:country":"NP",
    "wof:name":"Ambun",
    "wof:placetype":"locality"
},
  "geometry": {"coordinates":[87.52009,27.18199000000001],"type":"Point"}
}