{
  "type": "Feature",
  "properties": {
    "gn:admin1_code":"MR",
    "gn:admin2_code":"12",
    "gn:admin3_code":"53",
    "gn:admin4_code":"530010",
    "gn:asciiname":"Charipani Kharka",
    "gn:country_code":"NP",
    "gn:dem":2935,
    "gn:feature_class":"P",
    "gn:feature_code":"PPLL",
    "gn:name":"Charipani Kharka",
    "gn:population":0,
    "gn:timezone":"Asia/Kathmandu",
    "iso:country":"NP",
    "wof:name":"Charipani Kharka",
    "wof:placetype":"locality"
},
  "geometry": {"coordinates":[82.94335,28.37699000000001],"type":"Point"}
}