{
  "type": "Feature",
  "properties": {
    "gn:admin1_code":"WR",
    "gn:admin2_code":"4.0",
    "gn:admin3_code":"39.0",
    "gn:admin4_code":"390043.0",
    "gn:asciiname":"Tallo Salyan",
    "gn:country_code":"NP",
    "gn:dem":1011,
    "gn:feature_class":"P",
    "gn:feature_code":"PPLL",
    "gn:name":"Tallo Salyan",
    "gn:population":0,
    "gn:timezone":"Asia/Kathmandu",
    "iso:country":"NP",
    "wof:name":"Tallo Salyan",
    "wof:placetype":"locality"
},
  "geometry": {"coordinates":[83.62791,27.99759],"type":"Point"}
}