{
  "type": "Feature",
  "properties": {
    "gn:admin1_code":"WR",
    "gn:admin2_code":"3",
    "gn:admin3_code":"45.0",
    "gn:admin4_code":"450047.0",
    "gn:asciiname":"Phalate",
    "gn:country_code":"NP",
    "gn:dem":1257,
    "gn:feature_class":"P",
    "gn:feature_code":"PPLL",
    "gn:name":"Phalate",
    "gn:population":0,
    "gn:timezone":"Asia/Kathmandu",
    "iso:country":"NP",
    "name:bih_x_preferred":[
        "\u092b\u0932\u093e\u0901\u091f\u0947"
    ],
    "name:nep_x_preferred":[
        "\u092b\u0932\u093e\u0901\u091f\u0947"
    ],
    "name:new_x_preferred":[
        "\u092b\u0932\u093e\u0924\u0947"
    ],
    "name:pol_x_preferred":[
        "Falate"
    ],
    "name:urd_x_preferred":[
        "\u0641\u0627\u0644\u0627\u0679\u06cc"
    ],
    "wof:name":"Phalate",
    "wof:placetype":"locality"
},
  "geometry": {"coordinates":[83.54822,28.1341],"type":"Point"}
}