{
  "type": "Feature",
  "properties": {
    "gn:admin1_code":"WR",
    "gn:admin2_code":"3",
    "gn:admin3_code":"43",
    "gn:admin4_code":"430012",
    "gn:asciiname":"Devisthan",
    "gn:country_code":"NP",
    "gn:dem":1873,
    "gn:feature_class":"P",
    "gn:feature_code":"PPLL",
    "gn:name":"Devisthan",
    "gn:population":0,
    "gn:timezone":"Asia/Kathmandu",
    "iso:country":"NP",
    "name:fra_x_preferred":[
        "Devisthan"
    ],
    "name:new_x_preferred":[
        "\u0926\u0947\u0935\u0940\u0938\u094d\u0925\u093e\u0928 \u0968"
    ],
    "name:pol_x_preferred":[
        "Devisthan"
    ],
    "wof:name":"Devisthan",
    "wof:placetype":"locality"
},
  "geometry": {"coordinates":[83.33363,28.46042000000001],"type":"Point"}
}