{
  "type": "Feature",
  "properties": {
    "gn:admin1_code":"CR",
    "gn:admin2_code":"1",
    "gn:admin3_code":"23",
    "gn:admin4_code":"230044",
    "gn:asciiname":"Tinailung",
    "gn:country_code":"NP",
    "gn:dem":1959,
    "gn:feature_class":"P",
    "gn:feature_code":"PPLL",
    "gn:name":"Tinailung",
    "gn:population":0,
    "gn:timezone":"Asia/Kathmandu",
    "iso:country":"NP",
    "wof:name":"Tinailung",
    "wof:placetype":"locality"
},
  "geometry": {"coordinates":[85.48663000000001,27.90213],"type":"Point"}
}