{
  "type": "Feature",
  "properties": {
    "gn:admin1_code":"MR",
    "gn:admin2_code":"2",
    "gn:admin3_code":"61.0",
    "gn:admin4_code":"610001.0",
    "gn:asciiname":"Barkhale",
    "gn:country_code":"NP",
    "gn:dem":1571,
    "gn:feature_class":"P",
    "gn:feature_code":"PPLL",
    "gn:name":"Barkhale",
    "gn:population":0,
    "gn:timezone":"Asia/Kathmandu",
    "iso:country":"NP",
    "wof:name":"Barkhale",
    "wof:placetype":"locality"
},
  "geometry": {"coordinates":[82.12491,28.82587],"type":"Point"}
}