{
  "type": "Feature",
  "properties": {
    "gn:admin1_code":"ER",
    "gn:admin2_code":"13",
    "gn:admin3_code":"13.0",
    "gn:admin4_code":"130039.0",
    "gn:asciiname":"Thade",
    "gn:country_code":"NP",
    "gn:dem":2110,
    "gn:feature_class":"P",
    "gn:feature_code":"PPLL",
    "gn:name":"Thade",
    "gn:population":0,
    "gn:timezone":"Asia/Kathmandu",
    "iso:country":"NP",
    "wof:name":"Thade",
    "wof:placetype":"locality"
},
  "geometry": {"coordinates":[86.74821,27.25985],"type":"Point"}
}