{
  "type": "Feature",
  "properties": {
    "gn:admin1_code":"MR",
    "gn:admin2_code":"12",
    "gn:admin3_code":"56.0",
    "gn:admin4_code":"560003.0",
    "gn:asciiname":"Haspurwa",
    "gn:country_code":"NP",
    "gn:dem":665,
    "gn:feature_class":"P",
    "gn:feature_code":"PPLL",
    "gn:name":"Haspurwa",
    "gn:population":0,
    "gn:timezone":"Asia/Kathmandu",
    "iso:country":"NP",
    "wof:name":"Haspurwa",
    "wof:placetype":"locality"
},
  "geometry": {"coordinates":[82.37850999999998,28.10299],"type":"Point"}
}