{
  "type": "Feature",
  "properties": {
    "gn:admin1_code":"00",
    "gn:asciiname":"Kalinchok",
    "gn:country_code":"NP",
    "gn:dem":1666,
    "gn:feature_class":"P",
    "gn:feature_code":"PPL",
    "gn:name":"K\u0101li\u1e45chok",
    "gn:population":0,
    "gn:timezone":"Asia/Kathmandu",
    "iso:country":"NP",
    "name:ceb_x_preferred":[
        "Kalingchok"
    ],
    "name:mai_x_preferred":[
        "\u0915\u093e\u0932\u093f\u091e\u094d\u091a\u094b\u0915"
    ],
    "name:nep_x_preferred":[
        "\u0915\u093e\u0932\u093f\u091e\u094d\u091a\u094b\u0915"
    ],
    "wof:name":"Kalinchok",
    "wof:placetype":"locality"
},
  "geometry": {"coordinates":[85.68118,27.49922],"type":"Point"}
}