{
  "type": "Feature",
  "properties": {
    "gn:admin1_code":"00",
    "gn:asciiname":"Bhanjyan",
    "gn:country_code":"NP",
    "gn:dem":1489,
    "gn:feature_class":"P",
    "gn:feature_code":"PPL",
    "gn:name":"Bha\u00f1jy\u0101\u1e45",
    "gn:population":0,
    "gn:timezone":"Asia/Kathmandu",
    "iso:country":"NP",
    "wof:name":"Bhanjyan",
    "wof:placetype":"locality"
},
  "geometry": {"coordinates":[85.28278,27.76806],"type":"Point"}
}