{
  "type": "Feature",
  "properties": {
    "gn:admin1_code":"CR",
    "gn:admin2_code":"11",
    "gn:admin3_code":"31",
    "gn:admin4_code":"310018",
    "gn:asciiname":"Mulkhola Dobhan",
    "gn:country_code":"NP",
    "gn:dem":525,
    "gn:feature_class":"P",
    "gn:feature_code":"PPLL",
    "gn:name":"Mulkhola Dobhan",
    "gn:population":0,
    "gn:timezone":"Asia/Kathmandu",
    "iso:country":"NP",
    "wof:name":"Mulkhola Dobhan",
    "wof:placetype":"locality"
},
  "geometry": {"coordinates":[84.91113,27.41381],"type":"Point"}
}