{
  "type": "Feature",
  "properties": {
    "gn:admin1_code":"00",
    "gn:asciiname":"Sakhui",
    "gn:country_code":"NP",
    "gn:dem":118,
    "gn:feature_class":"P",
    "gn:feature_code":"PPL",
    "gn:name":"Sakhui\u0307\u0304",
    "gn:population":0,
    "gn:timezone":"Asia/Kathmandu",
    "iso:country":"NP",
    "name:und_x_variant":[
        "Sakhui\u0307\u0304",
        "Sakhu\u012b"
    ],
    "wof:name":"Sakhui",
    "wof:placetype":"locality"
},
  "geometry": {"coordinates":[85.03394,27.10061],"type":"Point"}
}