{
  "type": "Feature",
  "properties": {
    "gn:admin1_code":"ER",
    "gn:admin2_code":"10.0",
    "gn:admin3_code":"1.0",
    "gn:admin4_code":"10016.0",
    "gn:asciiname":"Lepchung",
    "gn:country_code":"NP",
    "gn:dem":1790,
    "gn:feature_class":"P",
    "gn:feature_code":"PPLL",
    "gn:name":"Lepchung",
    "gn:population":0,
    "gn:timezone":"Asia/Kathmandu",
    "iso:country":"NP",
    "wof:name":"Lepchung",
    "wof:placetype":"locality"
},
  "geometry": {"coordinates":[87.79281999999998,27.51807],"type":"Point"}
}