{
  "type": "Feature",
  "properties": {
    "gn:admin1_code":"WR",
    "gn:admin2_code":"3",
    "gn:admin3_code":"45.0",
    "gn:admin4_code":"450041.0",
    "gn:asciiname":"Bayali",
    "gn:country_code":"NP",
    "gn:dem":1508,
    "gn:feature_class":"P",
    "gn:feature_code":"PPLL",
    "gn:name":"Bayali",
    "gn:population":0,
    "gn:timezone":"Asia/Kathmandu",
    "iso:country":"NP",
    "wof:name":"Bayali",
    "wof:placetype":"locality"
},
  "geometry": {"coordinates":[83.45845,28.2294],"type":"Point"}
}