{
  "type": "Feature",
  "properties": {
    "gn:admin1_code":"00",
    "gn:asciiname":"Mukubun",
    "gn:country_code":"NP",
    "gn:dem":258,
    "gn:feature_class":"P",
    "gn:feature_code":"PPL",
    "gn:name":"Mukubu\u1e45",
    "gn:population":0,
    "gn:timezone":"Asia/Kathmandu",
    "iso:country":"NP",
    "name:nep_x_preferred":[
        "Mukubu\u1e45"
    ],
    "wof:name":"Mukubun",
    "wof:placetype":"locality"
},
  "geometry": {"coordinates":[87.78778,26.82557000000001],"type":"Point"}
}