{
  "type": "Feature",
  "properties": {
    "gn:admin1_code":"FR",
    "gn:admin2_code":"9",
    "gn:admin3_code":"72.0",
    "gn:admin4_code":"720021.0",
    "gn:asciiname":"Sunaphata",
    "gn:country_code":"NP",
    "gn:dem":217,
    "gn:feature_class":"P",
    "gn:feature_code":"PPLL",
    "gn:name":"Sunaphata",
    "gn:population":0,
    "gn:timezone":"Asia/Kathmandu",
    "iso:country":"NP",
    "wof:name":"Sunaphata",
    "wof:placetype":"locality"
},
  "geometry": {"coordinates":[80.32581999999999,28.94406],"type":"Point"}
}