{
  "type": "Feature",
  "properties": {
    "gn:admin1_code":"WR",
    "gn:admin2_code":"4.0",
    "gn:admin3_code":"39.0",
    "gn:admin4_code":"390048.0",
    "gn:asciiname":"Jaitar",
    "gn:country_code":"NP",
    "gn:dem":397,
    "gn:feature_class":"P",
    "gn:feature_code":"PPLL",
    "gn:name":"Jaitar",
    "gn:population":0,
    "gn:timezone":"Asia/Kathmandu",
    "iso:country":"NP",
    "wof:name":"Jaitar",
    "wof:placetype":"locality"
},
  "geometry": {"coordinates":[83.9324,27.87966],"type":"Point"}
}