{
  "type": "Feature",
  "properties": {
    "gn:admin1_code":"ER",
    "gn:admin2_code":"7",
    "gn:admin3_code":"5",
    "gn:admin4_code":"50012",
    "gn:asciiname":"Rajarani",
    "gn:country_code":"NP",
    "gn:dem":381,
    "gn:feature_class":"P",
    "gn:feature_code":"PPLL",
    "gn:name":"Rajarani",
    "gn:population":0,
    "gn:timezone":"Asia/Kathmandu",
    "iso:country":"NP",
    "wof:name":"Rajarani",
    "wof:placetype":"locality"
},
  "geometry": {"coordinates":[87.48954000000001,26.74603],"type":"Point"}
}