{
  "type": "Feature",
  "properties": {
    "gn:admin1_code":"WR",
    "gn:admin2_code":"3",
    "gn:admin3_code":"44",
    "gn:admin4_code":"440046",
    "gn:asciiname":"Thapathar",
    "gn:country_code":"NP",
    "gn:dem":1037,
    "gn:feature_class":"P",
    "gn:feature_code":"PPLL",
    "gn:name":"Thapathar",
    "gn:population":0,
    "gn:timezone":"Asia/Kathmandu",
    "iso:country":"NP",
    "wof:name":"Thapathar",
    "wof:placetype":"locality"
},
  "geometry": {"coordinates":[83.67993,28.05767],"type":"Point"}
}