{
  "type": "Feature",
  "properties": {
    "gn:admin1_code":"CR",
    "gn:admin2_code":"1",
    "gn:admin3_code":"28",
    "gn:admin4_code":"280011",
    "gn:asciiname":"Khanigaun",
    "gn:country_code":"NP",
    "gn:dem":683,
    "gn:feature_class":"P",
    "gn:feature_code":"PPLL",
    "gn:name":"Khanigaun",
    "gn:population":0,
    "gn:timezone":"Asia/Kathmandu",
    "iso:country":"NP",
    "wof:name":"Khanigaun",
    "wof:placetype":"locality"
},
  "geometry": {"coordinates":[85.13004000000002,27.89961],"type":"Point"}
}