{
  "type": "Feature",
  "properties": {
    "gn:admin1_code":"MR",
    "gn:admin2_code":"12",
    "gn:admin3_code":"53",
    "gn:admin4_code":"530032",
    "gn:asciiname":"Pakhapani",
    "gn:country_code":"NP",
    "gn:dem":1781,
    "gn:feature_class":"P",
    "gn:feature_code":"PPLL",
    "gn:name":"Pakhapani",
    "gn:population":0,
    "gn:timezone":"Asia/Kathmandu",
    "iso:country":"NP",
    "name:fra_x_preferred":[
        "Pakhapani"
    ],
    "name:nep_x_preferred":[
        "\u092a\u093e\u0916\u093e\u092a\u093e\u0928\u0940"
    ],
    "name:pol_x_preferred":[
        "Pakhapani"
    ],
    "wof:name":"Pakhapani",
    "wof:placetype":"locality"
},
  "geometry": {"coordinates":[82.58830999999998,28.14106],"type":"Point"}
}