{
  "type": "Feature",
  "properties": {
    "gn:admin1_code":"WR",
    "gn:admin2_code":"4.0",
    "gn:admin3_code":"38.0",
    "gn:admin4_code":"380027.0",
    "gn:asciiname":"Chyandanda",
    "gn:country_code":"NP",
    "gn:dem":502,
    "gn:feature_class":"P",
    "gn:feature_code":"PPLL",
    "gn:name":"Chyandanda",
    "gn:population":0,
    "gn:timezone":"Asia/Kathmandu",
    "iso:country":"NP",
    "name:ceb_x_preferred":[
        "Chyandada"
    ],
    "name:mai_x_preferred":[
        "\u091a\u093f\u0939\u093e\u0928\u0921\u093e\u0901\u0921\u093e"
    ],
    "name:msa_x_preferred":[
        "Chyandada"
    ],
    "name:nep_x_preferred":[
        "\u091a\u094d\u092f\u093e\u0928\u0921\u093e\u0902\u0921\u093e"
    ],
    "name:new_x_preferred":[
        "\u091a\u094d\u092f\u093e\u0928\u0921\u093e\u0902\u0921\u093e"
    ],
    "name:pol_x_preferred":[
        "Chyandada"
    ],
    "wof:name":"Chyandanda",
    "wof:placetype":"locality"
},
  "geometry": {"coordinates":[84.09340999999998,28.0132],"type":"Point"}
}