{
  "type": "Feature",
  "properties": {
    "gn:admin1_code":"FR",
    "gn:admin2_code":"14",
    "gn:admin3_code":"70.0",
    "gn:admin4_code":"700045.0",
    "gn:asciiname":"Dauda",
    "gn:country_code":"NP",
    "gn:dem":1882,
    "gn:feature_class":"P",
    "gn:feature_code":"PPLL",
    "gn:name":"Dauda",
    "gn:population":0,
    "gn:timezone":"Asia/Kathmandu",
    "iso:country":"NP",
    "wof:name":"Dauda",
    "wof:placetype":"locality"
},
  "geometry": {"coordinates":[80.99722,29.07769],"type":"Point"}
}