{
  "type": "Feature",
  "properties": {
    "gn:admin1_code":"ER",
    "gn:admin2_code":"10.0",
    "gn:admin3_code":"1.0",
    "gn:admin4_code":"10016.0",
    "gn:asciiname":"Ramdang",
    "gn:country_code":"NP",
    "gn:dem":4845,
    "gn:feature_class":"P",
    "gn:feature_code":"PPLL",
    "gn:name":"Ramdang",
    "gn:population":0,
    "gn:timezone":"Asia/Kathmandu",
    "iso:country":"NP",
    "wof:name":"Ramdang",
    "wof:placetype":"locality"
},
  "geometry": {"coordinates":[88.00349,27.7738],"type":"Point"}
}