{
  "type": "Feature",
  "properties": {
    "gn:admin1_code":"ER",
    "gn:admin2_code":"7",
    "gn:admin3_code":"9",
    "gn:admin4_code":"90005",
    "gn:asciiname":"Chapabhui",
    "gn:country_code":"NP",
    "gn:dem":557,
    "gn:feature_class":"P",
    "gn:feature_code":"PPLL",
    "gn:name":"Chapabhui",
    "gn:population":0,
    "gn:timezone":"Asia/Kathmandu",
    "iso:country":"NP",
    "wof:name":"Chapabhui",
    "wof:placetype":"locality"
},
  "geometry": {"coordinates":[87.26605000000001,27.2996],"type":"Point"}
}