{
  "type": "Feature",
  "properties": {
    "gn:admin1_code":"00",
    "gn:asciiname":"Maweshi Hatiya",
    "gn:country_code":"NP",
    "gn:dem":77,
    "gn:feature_class":"P",
    "gn:feature_code":"PPL",
    "gn:name":"Maweshi\u0307\u0304 Ha\u1e6di\u0307\u0304y\u0101",
    "gn:population":0,
    "gn:timezone":"Asia/Kathmandu",
    "iso:country":"NP",
    "name:nep_x_preferred":[
        "Maweshi\u0307\u0304 Ha\u1e6di\u0307\u0304y\u0101"
    ],
    "wof:name":"Maweshi Hatiya",
    "wof:placetype":"locality"
},
  "geometry": {"coordinates":[87.35999,26.47236],"type":"Point"}
}