{
  "type": "Feature",
  "properties": {
    "gn:admin1_code":"CR",
    "gn:admin2_code":"1",
    "gn:admin3_code":"29",
    "gn:admin4_code":"290001",
    "gn:asciiname":"Sarsin",
    "gn:country_code":"NP",
    "gn:dem":1647,
    "gn:feature_class":"P",
    "gn:feature_code":"PPLL",
    "gn:name":"Sarsin",
    "gn:population":0,
    "gn:timezone":"Asia/Kathmandu",
    "iso:country":"NP",
    "wof:name":"Sarsin",
    "wof:placetype":"locality"
},
  "geometry": {"coordinates":[85.24441999999998,28.00031],"type":"Point"}
}