{
  "type": "Feature",
  "properties": {
    "gn:admin1_code":"ER",
    "gn:admin2_code":"10.0",
    "gn:admin3_code":"1.0",
    "gn:admin4_code":"10050.0",
    "gn:asciiname":"Tawanagi",
    "gn:country_code":"NP",
    "gn:dem":4072,
    "gn:feature_class":"P",
    "gn:feature_code":"PPLL",
    "gn:name":"Tawanagi",
    "gn:population":0,
    "gn:timezone":"Asia/Kathmandu",
    "iso:country":"NP",
    "wof:name":"Tawanagi",
    "wof:placetype":"locality"
},
  "geometry": {"coordinates":[88.00856999999998,27.42646],"type":"Point"}
}