{
  "type": "Feature",
  "properties": {
    "gn:admin1_code":"CR",
    "gn:admin2_code":"5",
    "gn:admin3_code":"20",
    "gn:admin4_code":"200031",
    "gn:asciiname":"Bataha",
    "gn:country_code":"NP",
    "gn:dem":207,
    "gn:feature_class":"P",
    "gn:feature_code":"PPLL",
    "gn:name":"Bataha",
    "gn:population":0,
    "gn:timezone":"Asia/Kathmandu",
    "iso:country":"NP",
    "wof:name":"Bataha",
    "wof:placetype":"locality"
},
  "geometry": {"coordinates":[86.30511,26.97104],"type":"Point"}
}