{
  "type": "Feature",
  "properties": {
    "gn:admin1_code":"WR",
    "gn:admin2_code":"4.0",
    "gn:admin3_code":"38.0",
    "gn:admin4_code":"380024.0",
    "gn:asciiname":"Dalalidanda",
    "gn:country_code":"NP",
    "gn:dem":579,
    "gn:feature_class":"P",
    "gn:feature_code":"PPLL",
    "gn:name":"Dalalidanda",
    "gn:population":0,
    "gn:timezone":"Asia/Kathmandu",
    "iso:country":"NP",
    "wof:name":"Dalalidanda",
    "wof:placetype":"locality"
},
  "geometry": {"coordinates":[84.19919,27.98911],"type":"Point"}
}