{
  "type": "Feature",
  "properties": {
    "gn:admin1_code":"CR",
    "gn:admin2_code":"5",
    "gn:admin3_code":"20",
    "gn:admin4_code":"200047",
    "gn:asciiname":"Riththe",
    "gn:country_code":"NP",
    "gn:dem":598,
    "gn:feature_class":"P",
    "gn:feature_code":"PPLL",
    "gn:name":"Riththe",
    "gn:population":0,
    "gn:timezone":"Asia/Kathmandu",
    "iso:country":"NP",
    "wof:name":"Riththe",
    "wof:placetype":"locality"
},
  "geometry": {"coordinates":[85.94306,27.38517],"type":"Point"}
}