{
  "type": "Feature",
  "properties": {
    "gn:admin1_code":"CR",
    "gn:admin2_code":"1",
    "gn:admin3_code":"23",
    "gn:admin4_code":"230007",
    "gn:asciiname":"Ribarma",
    "gn:country_code":"NP",
    "gn:dem":2061,
    "gn:feature_class":"P",
    "gn:feature_code":"PPLL",
    "gn:name":"Ribarma",
    "gn:population":0,
    "gn:timezone":"Asia/Kathmandu",
    "iso:country":"NP",
    "wof:name":"Ribarma",
    "wof:placetype":"locality"
},
  "geometry": {"coordinates":[85.62623000000001,28.00343],"type":"Point"}
}