{
  "type": "Feature",
  "properties": {
    "gn:admin1_code":"ER",
    "gn:admin2_code":"10",
    "gn:admin3_code":"2",
    "gn:admin4_code":"20002",
    "gn:asciiname":"Uttane",
    "gn:country_code":"NP",
    "gn:dem":1770,
    "gn:feature_class":"P",
    "gn:feature_code":"PPLL",
    "gn:name":"Uttane",
    "gn:population":0,
    "gn:timezone":"Asia/Kathmandu",
    "iso:country":"NP",
    "wof:name":"Uttane",
    "wof:placetype":"locality"
},
  "geometry": {"coordinates":[87.70408,27.02833],"type":"Point"}
}