{
  "type": "Feature",
  "properties": {
    "gn:admin1_code":"ER",
    "gn:admin2_code":"13",
    "gn:admin3_code":"15",
    "gn:admin4_code":"150074",
    "gn:asciiname":"Madhupatti",
    "gn:country_code":"NP",
    "gn:dem":144,
    "gn:feature_class":"P",
    "gn:feature_code":"PPLL",
    "gn:name":"Madhupatti",
    "gn:population":0,
    "gn:timezone":"Asia/Kathmandu",
    "iso:country":"NP",
    "wof:name":"Madhupatti",
    "wof:placetype":"locality"
},
  "geometry": {"coordinates":[86.55204000000001,26.70783],"type":"Point"}
}