{
  "type": "Feature",
  "properties": {
    "gn:admin1_code":"CR",
    "gn:admin2_code":"1",
    "gn:admin3_code":"24.0",
    "gn:admin4_code":"240064.0",
    "gn:asciiname":"Thulichaur",
    "gn:country_code":"NP",
    "gn:dem":1461,
    "gn:feature_class":"P",
    "gn:feature_code":"PPLL",
    "gn:name":"Thulichaur",
    "gn:population":0,
    "gn:timezone":"Asia/Kathmandu",
    "iso:country":"NP",
    "wof:name":"Thulichaur",
    "wof:placetype":"locality"
},
  "geometry": {"coordinates":[85.56007,27.6939],"type":"Point"}
}