{
  "type": "Feature",
  "properties": {
    "gn:admin1_code":"ER",
    "gn:admin2_code":"10.0",
    "gn:admin3_code":"1.0",
    "gn:admin4_code":"10022.0",
    "gn:asciiname":"Kheklebung",
    "gn:country_code":"NP",
    "gn:dem":1152,
    "gn:feature_class":"P",
    "gn:feature_code":"PPLL",
    "gn:name":"Kheklebung",
    "gn:population":0,
    "gn:timezone":"Asia/Kathmandu",
    "iso:country":"NP",
    "wof:name":"Kheklebung",
    "wof:placetype":"locality"
},
  "geometry": {"coordinates":[87.86915,27.33719],"type":"Point"}
}