{
  "type": "Feature",
  "properties": {
    "gn:admin1_code":"MR",
    "gn:admin2_code":"12",
    "gn:admin3_code":"55",
    "gn:admin4_code":"550046",
    "gn:asciiname":"Sherachaur",
    "gn:country_code":"NP",
    "gn:dem":1383,
    "gn:feature_class":"P",
    "gn:feature_code":"PPLL",
    "gn:name":"Sherachaur",
    "gn:population":0,
    "gn:timezone":"Asia/Kathmandu",
    "iso:country":"NP",
    "wof:name":"Sherachaur",
    "wof:placetype":"locality"
},
  "geometry": {"coordinates":[82.32548,28.47004],"type":"Point"}
}