{
  "type": "Feature",
  "properties": {
    "gn:admin1_code":"CR",
    "gn:admin2_code":"1",
    "gn:admin3_code":"24.0",
    "gn:admin4_code":"240008.0",
    "gn:asciiname":"Sore",
    "gn:country_code":"NP",
    "gn:dem":1893,
    "gn:feature_class":"P",
    "gn:feature_code":"PPLL",
    "gn:name":"Sore",
    "gn:population":0,
    "gn:timezone":"Asia/Kathmandu",
    "iso:country":"NP",
    "wof:name":"Sore",
    "wof:placetype":"locality"
},
  "geometry": {"coordinates":[85.72076,27.41572],"type":"Point"}
}