{
  "type": "Feature",
  "properties": {
    "gn:admin1_code":"FR",
    "gn:admin2_code":"9",
    "gn:admin3_code":"75.0",
    "gn:admin4_code":"750004.0",
    "gn:asciiname":"Buleenatee",
    "gn:country_code":"NP",
    "gn:dem":2932,
    "gn:feature_class":"P",
    "gn:feature_code":"PPLL",
    "gn:name":"Buleenatee",
    "gn:population":0,
    "gn:timezone":"Asia/Kathmandu",
    "iso:country":"NP",
    "wof:name":"Buleenatee",
    "wof:placetype":"locality"
},
  "geometry": {"coordinates":[80.89465,30.11264000000001],"type":"Point"}
}