{
  "type": "Feature",
  "properties": {
    "gn:admin1_code":"MR",
    "gn:admin2_code":"12",
    "gn:admin3_code":"54",
    "gn:admin4_code":"540040",
    "gn:asciiname":"Khorsalle",
    "gn:country_code":"NP",
    "gn:dem":1795,
    "gn:feature_class":"P",
    "gn:feature_code":"PPLL",
    "gn:name":"Khorsalle",
    "gn:population":0,
    "gn:timezone":"Asia/Kathmandu",
    "iso:country":"NP",
    "wof:name":"Khorsalle",
    "wof:placetype":"locality"
},
  "geometry": {"coordinates":[82.60271999999998,28.61419],"type":"Point"}
}