{
  "type": "Feature",
  "properties": {
    "gn:admin1_code":"MR",
    "gn:admin2_code":"6",
    "gn:admin3_code":"63.0",
    "gn:admin4_code":"630020.0",
    "gn:asciiname":"Khalachaur",
    "gn:country_code":"NP",
    "gn:dem":2315,
    "gn:feature_class":"P",
    "gn:feature_code":"PPLL",
    "gn:name":"Khalachaur",
    "gn:population":0,
    "gn:timezone":"Asia/Kathmandu",
    "iso:country":"NP",
    "wof:name":"Khalachaur",
    "wof:placetype":"locality"
},
  "geometry": {"coordinates":[82.15609000000001,29.26587],"type":"Point"}
}