{
  "type": "Feature",
  "properties": {
    "gn:admin1_code":"00",
    "gn:asciiname":"Phansuwa",
    "gn:country_code":"NP",
    "gn:dem":751,
    "gn:feature_class":"P",
    "gn:feature_code":"PPL",
    "gn:name":"Pha\u1e45suw\u0101",
    "gn:population":0,
    "gn:timezone":"Asia/Kathmandu",
    "iso:country":"NP",
    "name:nep_x_preferred":[
        "Pha\u1e45suw\u0101"
    ],
    "wof:name":"Phansuwa",
    "wof:placetype":"locality"
},
  "geometry": {"coordinates":[87.33866999999999,26.95686],"type":"Point"}
}