{
  "type": "Feature",
  "properties": {
    "gn:admin1_code":"CR",
    "gn:admin2_code":"5",
    "gn:admin3_code":"22.0",
    "gn:admin4_code":"220052.0",
    "gn:asciiname":"Thalahari",
    "gn:country_code":"NP",
    "gn:dem":2265,
    "gn:feature_class":"P",
    "gn:feature_code":"PPLL",
    "gn:name":"Thalahari",
    "gn:population":0,
    "gn:timezone":"Asia/Kathmandu",
    "iso:country":"NP",
    "wof:name":"Thalahari",
    "wof:placetype":"locality"
},
  "geometry": {"coordinates":[86.21025,27.59938],"type":"Point"}
}