{
  "type": "Feature",
  "properties": {
    "gn:admin1_code":"CR",
    "gn:admin2_code":"5",
    "gn:admin3_code":"20",
    "gn:admin4_code":"200054",
    "gn:asciiname":"Batase",
    "gn:country_code":"NP",
    "gn:dem":1173,
    "gn:feature_class":"P",
    "gn:feature_code":"PPLL",
    "gn:name":"Batase",
    "gn:population":0,
    "gn:timezone":"Asia/Kathmandu",
    "iso:country":"NP",
    "name:ceb_x_preferred":[
        "Batase"
    ],
    "name:pol_x_preferred":[
        "Batase"
    ],
    "wof:name":"Batase",
    "wof:placetype":"locality"
},
  "geometry": {"coordinates":[86.21207,27.13394000000001],"type":"Point"}
}