{
  "type": "Feature",
  "properties": {
    "gn:admin1_code":"CR",
    "gn:admin2_code":"11",
    "gn:admin3_code":"35.0",
    "gn:admin4_code":"350010.0",
    "gn:asciiname":"Nayan Basti",
    "gn:country_code":"NP",
    "gn:dem":310,
    "gn:feature_class":"P",
    "gn:feature_code":"PPLL",
    "gn:name":"Nayan Basti",
    "gn:population":0,
    "gn:timezone":"Asia/Kathmandu",
    "iso:country":"NP",
    "wof:name":"Nayan Basti",
    "wof:placetype":"locality"
},
  "geometry": {"coordinates":[84.62857,27.86774],"type":"Point"}
}