{
  "type": "Feature",
  "properties": {
    "gn:admin1_code":"WR",
    "gn:admin2_code":"8",
    "gn:admin3_code":"46.0",
    "gn:admin4_code":"460016.0",
    "gn:asciiname":"Dabhungaun",
    "gn:country_code":"NP",
    "gn:dem":1750,
    "gn:feature_class":"P",
    "gn:feature_code":"PPLL",
    "gn:name":"Dabhungaun",
    "gn:population":0,
    "gn:timezone":"Asia/Kathmandu",
    "iso:country":"NP",
    "wof:name":"Dabhungaun",
    "wof:placetype":"locality"
},
  "geometry": {"coordinates":[83.434,28.07716],"type":"Point"}
}