{
  "type": "Feature",
  "properties": {
    "gn:admin1_code":"WR",
    "gn:admin2_code":"3",
    "gn:admin3_code":"45.0",
    "gn:admin4_code":"450034.0",
    "gn:asciiname":"Kusigaun",
    "gn:country_code":"NP",
    "gn:dem":1097,
    "gn:feature_class":"P",
    "gn:feature_code":"PPLL",
    "gn:name":"Kusigaun",
    "gn:population":0,
    "gn:timezone":"Asia/Kathmandu",
    "iso:country":"NP",
    "wof:name":"Kusigaun",
    "wof:placetype":"locality"
},
  "geometry": {"coordinates":[83.59877,28.20303],"type":"Point"}
}