{
  "type": "Feature",
  "properties": {
    "gn:admin1_code":"ER",
    "gn:admin2_code":"7",
    "gn:admin3_code":"5",
    "gn:admin4_code":"50012",
    "gn:asciiname":"Lokhara",
    "gn:country_code":"NP",
    "gn:dem":273,
    "gn:feature_class":"P",
    "gn:feature_code":"PPLL",
    "gn:name":"Lokhara",
    "gn:population":0,
    "gn:timezone":"Asia/Kathmandu",
    "iso:country":"NP",
    "wof:name":"Lokhara",
    "wof:placetype":"locality"
},
  "geometry": {"coordinates":[87.4958,26.74706],"type":"Point"}
}