{
  "type": "Feature",
  "properties": {
    "gn:admin1_code":"00",
    "gn:asciiname":"Sanla",
    "gn:country_code":"NP",
    "gn:dem":1517,
    "gn:feature_class":"P",
    "gn:feature_code":"PPL",
    "gn:name":"S\u0101nl\u0101",
    "gn:population":0,
    "gn:timezone":"Asia/Kathmandu",
    "iso:country":"NP",
    "wof:name":"Sanla",
    "wof:placetype":"locality"
},
  "geometry": {"coordinates":[85.31471999999999,27.79139],"type":"Point"}
}