{
  "type": "Feature",
  "properties": {
    "gn:admin1_code":"ER",
    "gn:admin2_code":"7",
    "gn:admin3_code":"10.0",
    "gn:admin4_code":"100013.0",
    "gn:asciiname":"Champe",
    "gn:country_code":"NP",
    "gn:dem":1268,
    "gn:feature_class":"P",
    "gn:feature_code":"PPLL",
    "gn:name":"Champe",
    "gn:population":0,
    "gn:timezone":"Asia/Kathmandu",
    "iso:country":"NP",
    "name:bih_x_preferred":[
        "\u091a\u092e\u094d\u092a\u0947"
    ],
    "name:ceb_x_preferred":[
        "Champe"
    ],
    "name:mai_x_preferred":[
        "\u091a\u092e\u094d\u092a\u0947"
    ],
    "name:msa_x_preferred":[
        "Champe"
    ],
    "name:nep_x_preferred":[
        "\u091a\u092e\u094d\u092a\u0947"
    ],
    "name:new_x_preferred":[
        "\u091a\u092e\u094d\u092a\u0947"
    ],
    "name:pol_x_preferred":[
        "Champe"
    ],
    "wof:name":"Champe",
    "wof:placetype":"locality"
},
  "geometry": {"coordinates":[87.13713,27.23204],"type":"Point"}
}