{
  "type": "Feature",
  "properties": {
    "gn:admin1_code":"CR",
    "gn:admin2_code":"1",
    "gn:admin3_code":"28",
    "gn:admin4_code":"280029",
    "gn:asciiname":"Khahare",
    "gn:country_code":"NP",
    "gn:dem":964,
    "gn:feature_class":"P",
    "gn:feature_code":"PPLL",
    "gn:name":"Khahare",
    "gn:population":0,
    "gn:timezone":"Asia/Kathmandu",
    "iso:country":"NP",
    "wof:name":"Khahare",
    "wof:placetype":"locality"
},
  "geometry": {"coordinates":[85.09105,27.94802],"type":"Point"}
}