{
  "type": "Feature",
  "properties": {
    "gn:admin1_code":"MR",
    "gn:admin2_code":"12",
    "gn:admin3_code":"54",
    "gn:admin4_code":"540020",
    "gn:asciiname":"Mandanda",
    "gn:country_code":"NP",
    "gn:dem":1131,
    "gn:feature_class":"P",
    "gn:feature_code":"PPLL",
    "gn:name":"Mandanda",
    "gn:population":0,
    "gn:timezone":"Asia/Kathmandu",
    "iso:country":"NP",
    "wof:name":"Mandanda",
    "wof:placetype":"locality"
},
  "geometry": {"coordinates":[82.27091,28.60958],"type":"Point"}
}