{
  "type": "Feature",
  "properties": {
    "gn:admin1_code":"MR",
    "gn:admin2_code":"12",
    "gn:admin3_code":"54",
    "gn:admin4_code":"540040",
    "gn:asciiname":"Liga",
    "gn:country_code":"NP",
    "gn:dem":1814,
    "gn:feature_class":"P",
    "gn:feature_code":"PPLL",
    "gn:name":"Liga",
    "gn:population":0,
    "gn:timezone":"Asia/Kathmandu",
    "iso:country":"NP",
    "name:bel_x_preferred":[
        "\u041b\u0456\u0433\u0430"
    ],
    "name:ceb_x_preferred":[
        "Liga"
    ],
    "name:ces_x_preferred":[
        "Liga"
    ],
    "name:dan_x_preferred":[
        "Liga"
    ],
    "name:deu_x_preferred":[
        "Liga"
    ],
    "name:epo_x_preferred":[
        "Ligo"
    ],
    "name:fra_x_preferred":[
        "Liga"
    ],
    "name:glg_x_preferred":[
        "Liga"
    ],
    "name:hrv_x_preferred":[
        "Liga"
    ],
    "name:hun_x_preferred":[
        "Liga"
    ],
    "name:hye_x_preferred":[
        "\u053c\u056b\u0563\u0561"
    ],
    "name:jpn_x_preferred":[
        "\u30ea\u30fc\u30b0"
    ],
    "name:lmo_x_preferred":[
        "Liga"
    ],
    "name:nld_x_preferred":[
        "Liga"
    ],
    "name:nor_x_preferred":[
        "Liga"
    ],
    "name:pol_x_preferred":[
        "Liga"
    ],
    "name:por_x_preferred":[
        "Liga"
    ],
    "name:rus_x_preferred":[
        "\u041b\u0438\u0433\u0430"
    ],
    "name:scn_x_preferred":[
        "Cunzuciazzioni"
    ],
    "name:sco_x_preferred":[
        "Liga"
    ],
    "name:slk_x_preferred":[
        "Liga"
    ],
    "name:spa_x_preferred":[
        "Liga"
    ],
    "name:swe_x_preferred":[
        "Liga"
    ],
    "name:tel_x_preferred":[
        "\u0c32\u0c40\u0c17\u0c4d"
    ],
    "name:ukr_x_preferred":[
        "\u041b\u0456\u0433\u0430"
    ],
    "wof:name":"Liga",
    "wof:placetype":"locality"
},
  "geometry": {"coordinates":[82.62893000000003,28.57277],"type":"Point"}
}