{
  "type": "Feature",
  "properties": {
    "gn:admin1_code":"WR",
    "gn:admin2_code":"3",
    "gn:admin3_code":"42",
    "gn:admin4_code":"420001",
    "gn:asciiname":"Saukre",
    "gn:country_code":"NP",
    "gn:dem":3797,
    "gn:feature_class":"P",
    "gn:feature_code":"PPLL",
    "gn:name":"Saukre",
    "gn:population":0,
    "gn:timezone":"Asia/Kathmandu",
    "iso:country":"NP",
    "wof:name":"Saukre",
    "wof:placetype":"locality"
},
  "geometry": {"coordinates":[83.89713,29.12031],"type":"Point"}
}