{
  "type": "Feature",
  "properties": {
    "gn:admin1_code":"CR",
    "gn:admin2_code":"11",
    "gn:admin3_code":"35.0",
    "gn:admin4_code":"350006.0",
    "gn:asciiname":"Sainikgaun",
    "gn:country_code":"NP",
    "gn:dem":242,
    "gn:feature_class":"P",
    "gn:feature_code":"PPLL",
    "gn:name":"Sainikgaun",
    "gn:population":0,
    "gn:timezone":"Asia/Kathmandu",
    "iso:country":"NP",
    "wof:name":"Sainikgaun",
    "wof:placetype":"locality"
},
  "geometry": {"coordinates":[84.63378,27.61838],"type":"Point"}
}