{
  "type": "Feature",
  "properties": {
    "gn:admin1_code":"ER",
    "gn:admin2_code":"7",
    "gn:admin3_code":"7.0",
    "gn:admin4_code":"70019.0",
    "gn:asciiname":"Jaubari",
    "gn:country_code":"NP",
    "gn:dem":1873,
    "gn:feature_class":"P",
    "gn:feature_code":"PPLL",
    "gn:name":"Jaubari",
    "gn:population":0,
    "gn:timezone":"Asia/Kathmandu",
    "iso:country":"NP",
    "wof:name":"Jaubari",
    "wof:placetype":"locality"
},
  "geometry": {"coordinates":[87.35518,27.05802000000001],"type":"Point"}
}