{
  "type": "Feature",
  "properties": {
    "gn:admin1_code":"CR",
    "gn:admin2_code":"1",
    "gn:admin3_code":"28",
    "gn:admin4_code":"280001.0",
    "gn:asciiname":"Simle",
    "gn:country_code":"NP",
    "gn:dem":1175,
    "gn:feature_class":"P",
    "gn:feature_code":"PPLL",
    "gn:name":"Simle",
    "gn:population":0,
    "gn:timezone":"Asia/Kathmandu",
    "iso:country":"NP",
    "wof:name":"Simle",
    "wof:placetype":"locality"
},
  "geometry": {"coordinates":[85.22452,27.93986],"type":"Point"}
}