{
  "type": "Feature",
  "properties": {
    "gn:admin1_code":"CR",
    "gn:admin2_code":"5",
    "gn:admin3_code":"20",
    "gn:admin4_code":"200004",
    "gn:asciiname":"Toritar",
    "gn:country_code":"NP",
    "gn:dem":1405,
    "gn:feature_class":"P",
    "gn:feature_code":"PPLL",
    "gn:name":"Toritar",
    "gn:population":0,
    "gn:timezone":"Asia/Kathmandu",
    "iso:country":"NP",
    "wof:name":"Toritar",
    "wof:placetype":"locality"
},
  "geometry": {"coordinates":[86.14681999999998,27.18812],"type":"Point"}
}