{
  "type": "Feature",
  "properties": {
    "gn:admin1_code":"MR",
    "gn:admin2_code":"12",
    "gn:admin3_code":"54",
    "gn:admin4_code":"540020",
    "gn:asciiname":"Pokhari",
    "gn:country_code":"NP",
    "gn:dem":1387,
    "gn:feature_class":"P",
    "gn:feature_code":"PPLL",
    "gn:name":"Pokhari",
    "gn:population":0,
    "gn:timezone":"Asia/Kathmandu",
    "iso:country":"NP",
    "name:ceb_x_preferred":[
        "Pokhari"
    ],
    "name:fra_x_preferred":[
        "Pokhari"
    ],
    "name:ita_x_preferred":[
        "Pokhari"
    ],
    "name:new_x_preferred":[
        "\u092a\u094b\u0916\u0930\u0940"
    ],
    "name:pol_x_preferred":[
        "Pokhari"
    ],
    "wof:name":"Pokhari",
    "wof:placetype":"locality"
},
  "geometry": {"coordinates":[82.28766,28.65525],"type":"Point"}
}