{
  "type": "Feature",
  "properties": {
    "gn:admin1_code":"MR",
    "gn:admin2_code":"12",
    "gn:admin3_code":"53",
    "gn:admin4_code":"530034",
    "gn:asciiname":"Dwarpani",
    "gn:country_code":"NP",
    "gn:dem":1694,
    "gn:feature_class":"P",
    "gn:feature_code":"PPLL",
    "gn:name":"Dwarpani",
    "gn:population":0,
    "gn:timezone":"Asia/Kathmandu",
    "iso:country":"NP",
    "wof:name":"Dwarpani",
    "wof:placetype":"locality"
},
  "geometry": {"coordinates":[82.44428000000001,28.24556],"type":"Point"}
}