{
  "type": "Feature",
  "properties": {
    "gn:admin1_code":"WR",
    "gn:admin2_code":"8",
    "gn:admin3_code":"51.0",
    "gn:admin4_code":"510023.0",
    "gn:asciiname":"Jaljale",
    "gn:country_code":"NP",
    "gn:dem":1534,
    "gn:feature_class":"P",
    "gn:feature_code":"PPLL",
    "gn:name":"Jaljale",
    "gn:population":0,
    "gn:timezone":"Asia/Kathmandu",
    "iso:country":"NP",
    "wof:name":"Jaljale",
    "wof:placetype":"locality"
},
  "geometry": {"coordinates":[83.12017,28.0392],"type":"Point"}
}