{
  "type": "Feature",
  "properties": {
    "gn:admin1_code":"WR",
    "gn:admin2_code":"3",
    "gn:admin3_code":"45.0",
    "gn:admin4_code":"450005.0",
    "gn:asciiname":"Uttar Ganga",
    "gn:country_code":"NP",
    "gn:dem":2875,
    "gn:feature_class":"P",
    "gn:feature_code":"PPLL",
    "gn:name":"Uttar Ganga",
    "gn:population":0,
    "gn:timezone":"Asia/Kathmandu",
    "iso:country":"NP",
    "wof:name":"Uttar Ganga",
    "wof:placetype":"locality"
},
  "geometry": {"coordinates":[83.0376,28.48477],"type":"Point"}
}