{
  "type": "Feature",
  "properties": {
    "gn:admin1_code":"WR",
    "gn:admin2_code":"8",
    "gn:admin3_code":"46.0",
    "gn:admin4_code":"460017.0",
    "gn:asciiname":"Nayagaun",
    "gn:country_code":"NP",
    "gn:dem":1343,
    "gn:feature_class":"P",
    "gn:feature_code":"PPLL",
    "gn:name":"Nayagaun",
    "gn:population":0,
    "gn:timezone":"Asia/Kathmandu",
    "iso:country":"NP",
    "name:msa_x_preferred":[
        "Nayagaun"
    ],
    "name:nep_x_preferred":[
        "\u0928\u092f\u093e\u0901\u0917\u093e\u0901\u0909"
    ],
    "wof:name":"Nayagaun",
    "wof:placetype":"locality"
},
  "geometry": {"coordinates":[83.51971999999998,28.09522],"type":"Point"}
}