{
  "type": "Feature",
  "properties": {
    "gn:admin1_code":"WR",
    "gn:admin2_code":"4",
    "gn:admin3_code":"40.0",
    "gn:admin4_code":"400042.0",
    "gn:asciiname":"Thak",
    "gn:country_code":"NP",
    "gn:dem":1451,
    "gn:feature_class":"P",
    "gn:feature_code":"PPLL",
    "gn:name":"Thak",
    "gn:population":0,
    "gn:timezone":"Asia/Kathmandu",
    "iso:country":"NP",
    "wof:name":"Thak",
    "wof:placetype":"locality"
},
  "geometry": {"coordinates":[84.07382,28.28836],"type":"Point"}
}