{
  "type": "Feature",
  "properties": {
    "gn:admin1_code":"MR",
    "gn:admin2_code":"12",
    "gn:admin3_code":"52",
    "gn:admin4_code":"520035",
    "gn:asciiname":"Swanbota",
    "gn:country_code":"NP",
    "gn:dem":1023,
    "gn:feature_class":"P",
    "gn:feature_code":"PPLL",
    "gn:name":"Swanbota",
    "gn:population":0,
    "gn:timezone":"Asia/Kathmandu",
    "iso:country":"NP",
    "wof:name":"Swanbota",
    "wof:placetype":"locality"
},
  "geometry": {"coordinates":[82.96706,28.13856],"type":"Point"}
}