{
  "type": "Feature",
  "properties": {
    "gn:admin1_code":"00",
    "gn:asciiname":"Bakanghyan",
    "gn:country_code":"NP",
    "gn:dem":2599,
    "gn:feature_class":"P",
    "gn:feature_code":"PPL",
    "gn:name":"Bak\u0101\u1e45ghy\u0101n",
    "gn:population":0,
    "gn:timezone":"Asia/Kathmandu",
    "iso:country":"NP",
    "wof:name":"Bakanghyan",
    "wof:placetype":"locality"
},
  "geometry": {"coordinates":[85.60673,28.02601],"type":"Point"}
}