{
  "type": "Feature",
  "properties": {
    "gn:admin1_code":"ER",
    "gn:admin2_code":"13",
    "gn:admin3_code":"11",
    "gn:admin4_code":"110008",
    "gn:asciiname":"Muddikharka",
    "gn:country_code":"NP",
    "gn:dem":2506,
    "gn:feature_class":"P",
    "gn:feature_code":"PPLL",
    "gn:name":"Muddikharka",
    "gn:population":0,
    "gn:timezone":"Asia/Kathmandu",
    "iso:country":"NP",
    "wof:name":"Muddikharka",
    "wof:placetype":"locality"
},
  "geometry": {"coordinates":[86.88738000000002,27.57202],"type":"Point"}
}