{
  "type": "Feature",
  "properties": {
    "gn:admin1_code":"FR",
    "gn:admin2_code":"14",
    "gn:admin3_code":"70.0",
    "gn:admin4_code":"700039.0",
    "gn:asciiname":"Madera",
    "gn:country_code":"NP",
    "gn:dem":1089,
    "gn:feature_class":"P",
    "gn:feature_code":"PPLL",
    "gn:name":"Madera",
    "gn:population":0,
    "gn:timezone":"Asia/Kathmandu",
    "iso:country":"NP",
    "name:bar_x_preferred":[
        "Madera"
    ],
    "name:ceb_x_preferred":[
        "Madera"
    ],
    "name:deu_x_preferred":[
        "Madera"
    ],
    "name:fra_x_preferred":[
        "Madera"
    ],
    "name:ita_x_preferred":[
        "Madera"
    ],
    "name:nld_x_preferred":[
        "Madera"
    ],
    "name:pol_x_preferred":[
        "Madera"
    ],
    "name:por_x_preferred":[
        "Madera"
    ],
    "name:rus_x_preferred":[
        "\u041c\u0430\u0434\u0435\u0440\u0430"
    ],
    "name:spa_x_preferred":[
        "Madera"
    ],
    "name:srp_x_preferred":[
        "\u041c\u0430\u0434\u0435\u0440\u0430"
    ],
    "name:swe_x_preferred":[
        "Madera"
    ],
    "name:ukr_x_preferred":[
        "\u041c\u0430\u0434\u0435\u0440\u0430"
    ],
    "wof:name":"Madera",
    "wof:placetype":"locality"
},
  "geometry": {"coordinates":[80.76224000000001,29.08887],"type":"Point"}
}