{
  "type": "Feature",
  "properties": {
    "gn:admin1_code":"ER",
    "gn:admin2_code":"7.0",
    "gn:admin3_code":"10.0",
    "gn:admin4_code":"100004.0",
    "gn:asciiname":"Pamakh",
    "gn:country_code":"NP",
    "gn:dem":1218,
    "gn:feature_class":"P",
    "gn:feature_code":"PPLL",
    "gn:name":"Pamakh",
    "gn:population":0,
    "gn:timezone":"Asia/Kathmandu",
    "iso:country":"NP",
    "wof:name":"Pamakh",
    "wof:placetype":"locality"
},
  "geometry": {"coordinates":[87.05353000000002,27.04465],"type":"Point"}
}