{
  "type": "Feature",
  "properties": {
    "gn:admin1_code":"WR",
    "gn:admin2_code":"8",
    "gn:admin3_code":"49",
    "gn:admin4_code":"490006.0",
    "gn:asciiname":"Ramanagar",
    "gn:country_code":"NP",
    "gn:dem":97,
    "gn:feature_class":"P",
    "gn:feature_code":"PPLL",
    "gn:name":"Ramanagar",
    "gn:population":0,
    "gn:timezone":"Asia/Kathmandu",
    "iso:country":"NP",
    "wof:name":"Ramanagar",
    "wof:placetype":"locality"
},
  "geometry": {"coordinates":[83.38625,27.37864],"type":"Point"}
}