{
  "type": "Feature",
  "properties": {
    "gn:admin1_code":"ER",
    "gn:admin2_code":"7",
    "gn:admin3_code":"10.0",
    "gn:admin4_code":"100044.0",
    "gn:asciiname":"Batang",
    "gn:country_code":"NP",
    "gn:dem":1958,
    "gn:feature_class":"P",
    "gn:feature_code":"PPLL",
    "gn:name":"Batang",
    "gn:population":0,
    "gn:timezone":"Asia/Kathmandu",
    "iso:country":"NP",
    "name:ceb_x_preferred":[
        "Batang"
    ],
    "name:deu_x_preferred":[
        "Batang"
    ],
    "name:fra_x_preferred":[
        "Batang"
    ],
    "name:jpn_x_preferred":[
        "\u30d0\u30bf\u30f3"
    ],
    "name:mlg_x_preferred":[
        "Batang"
    ],
    "name:nld_x_preferred":[
        "Batang"
    ],
    "name:nor_x_preferred":[
        "Batang"
    ],
    "name:sun_x_preferred":[
        "Batang"
    ],
    "name:swe_x_preferred":[
        "Batang"
    ],
    "wof:name":"Batang",
    "wof:placetype":"locality"
},
  "geometry": {"coordinates":[86.93557,27.10368],"type":"Point"}
}