{
  "type": "Feature",
  "properties": {
    "gn:admin1_code":"MR",
    "gn:admin2_code":"2",
    "gn:admin3_code":"60.0",
    "gn:admin4_code":"600021.0",
    "gn:asciiname":"Bhantu",
    "gn:country_code":"NP",
    "gn:dem":757,
    "gn:feature_class":"P",
    "gn:feature_code":"PPLL",
    "gn:name":"Bhantu",
    "gn:population":0,
    "gn:timezone":"Asia/Kathmandu",
    "iso:country":"NP",
    "wof:name":"Bhantu",
    "wof:placetype":"locality"
},
  "geometry": {"coordinates":[81.67737,28.81943],"type":"Point"}
}