{
  "type": "Feature",
  "properties": {
    "gn:admin1_code":"ER",
    "gn:admin2_code":"13",
    "gn:admin3_code":"13.0",
    "gn:admin4_code":"130032.0",
    "gn:asciiname":"Nepalgaun",
    "gn:country_code":"NP",
    "gn:dem":729,
    "gn:feature_class":"P",
    "gn:feature_code":"PPLL",
    "gn:name":"Nepalgaun",
    "gn:population":0,
    "gn:timezone":"Asia/Kathmandu",
    "iso:country":"NP",
    "wof:name":"Nepalgaun",
    "wof:placetype":"locality"
},
  "geometry": {"coordinates":[86.73815,27.30148],"type":"Point"}
}