{
  "type": "Feature",
  "properties": {
    "gn:admin1_code":"WR",
    "gn:admin2_code":"3",
    "gn:admin3_code":"44",
    "gn:admin4_code":"440039",
    "gn:asciiname":"Siththani",
    "gn:country_code":"NP",
    "gn:dem":1660,
    "gn:feature_class":"P",
    "gn:feature_code":"PPLL",
    "gn:name":"Siththani",
    "gn:population":0,
    "gn:timezone":"Asia/Kathmandu",
    "iso:country":"NP",
    "wof:name":"Siththani",
    "wof:placetype":"locality"
},
  "geometry": {"coordinates":[83.71128,28.10839],"type":"Point"}
}