{
  "type": "Feature",
  "properties": {
    "gn:admin1_code":"ER",
    "gn:admin2_code":"7",
    "gn:admin3_code":"5",
    "gn:admin4_code":"50063",
    "gn:asciiname":"Hurhuriyatol",
    "gn:country_code":"NP",
    "gn:dem":83,
    "gn:feature_class":"P",
    "gn:feature_code":"PPLL",
    "gn:name":"Hurhuriyatol",
    "gn:population":0,
    "gn:timezone":"Asia/Kathmandu",
    "iso:country":"NP",
    "wof:name":"Hurhuriyatol",
    "wof:placetype":"locality"
},
  "geometry": {"coordinates":[87.38729000000002,26.51959],"type":"Point"}
}