{
  "type": "Feature",
  "properties": {
    "gn:admin1_code":"00",
    "gn:asciiname":"Kandran",
    "gn:country_code":"NP",
    "gn:dem":2019,
    "gn:feature_class":"P",
    "gn:feature_code":"PPL",
    "gn:name":"K\u0101ndr\u0101\u1e45",
    "gn:population":0,
    "gn:timezone":"Asia/Kathmandu",
    "iso:country":"NP",
    "wof:name":"Kandran",
    "wof:placetype":"locality"
},
  "geometry": {"coordinates":[85.06858000000003,28.09751],"type":"Point"}
}