{
  "type": "Feature",
  "properties": {
    "gn:admin1_code":"CR",
    "gn:admin2_code":"5",
    "gn:admin3_code":"21",
    "gn:admin4_code":"210054",
    "gn:asciiname":"Tilbung",
    "gn:country_code":"NP",
    "gn:dem":966,
    "gn:feature_class":"P",
    "gn:feature_code":"PPLL",
    "gn:name":"Tilbung",
    "gn:population":0,
    "gn:timezone":"Asia/Kathmandu",
    "iso:country":"NP",
    "wof:name":"Tilbung",
    "wof:placetype":"locality"
},
  "geometry": {"coordinates":[86.11071,27.43462],"type":"Point"}
}