{
  "type": "Feature",
  "properties": {
    "gn:admin1_code":"ER",
    "gn:admin2_code":"7",
    "gn:admin3_code":"10.0",
    "gn:admin4_code":"100043.0",
    "gn:asciiname":"Majuwabesi",
    "gn:country_code":"NP",
    "gn:dem":342,
    "gn:feature_class":"P",
    "gn:feature_code":"PPLL",
    "gn:name":"Majuwabesi",
    "gn:population":0,
    "gn:timezone":"Asia/Kathmandu",
    "iso:country":"NP",
    "wof:name":"Majuwabesi",
    "wof:placetype":"locality"
},
  "geometry": {"coordinates":[87.12945999999999,27.41062],"type":"Point"}
}