{
  "type": "Feature",
  "properties": {
    "gn:admin1_code":"00",
    "gn:asciiname":"Bhanbari",
    "gn:country_code":"NP",
    "gn:dem":129,
    "gn:feature_class":"P",
    "gn:feature_code":"PPL",
    "gn:name":"Bh\u0101\u1e45b\u0101ri\u0307\u0304",
    "gn:population":0,
    "gn:timezone":"Asia/Kathmandu",
    "iso:country":"NP",
    "name:nep_x_preferred":[
        "Bh\u0101\u1e45b\u0101ri\u0307\u0304"
    ],
    "wof:name":"Bhanbari",
    "wof:placetype":"locality"
},
  "geometry": {"coordinates":[87.44611,26.6424],"type":"Point"}
}