{
  "type": "Feature",
  "properties": {
    "gn:admin1_code":"MR",
    "gn:admin2_code":"12",
    "gn:admin3_code":"53",
    "gn:admin4_code":"530047",
    "gn:asciiname":"Thangkrachin",
    "gn:country_code":"NP",
    "gn:dem":2872,
    "gn:feature_class":"P",
    "gn:feature_code":"PPLL",
    "gn:name":"Thangkrachin",
    "gn:population":0,
    "gn:timezone":"Asia/Kathmandu",
    "iso:country":"NP",
    "wof:name":"Thangkrachin",
    "wof:placetype":"locality"
},
  "geometry": {"coordinates":[82.75256,28.49384],"type":"Point"}
}