{
  "type": "Feature",
  "properties": {
    "gn:admin1_code":"ER",
    "gn:admin2_code":"13",
    "gn:admin3_code":"12",
    "gn:admin4_code":"120003",
    "gn:asciiname":"Lukuwa",
    "gn:country_code":"NP",
    "gn:dem":1548,
    "gn:feature_class":"P",
    "gn:feature_code":"PPLL",
    "gn:name":"Lukuwa",
    "gn:population":0,
    "gn:timezone":"Asia/Kathmandu",
    "iso:country":"NP",
    "wof:name":"Lukuwa",
    "wof:placetype":"locality"
},
  "geometry": {"coordinates":[86.30037,27.26769],"type":"Point"}
}