{
  "type": "Feature",
  "properties": {
    "gn:admin1_code":"ER",
    "gn:admin2_code":"13.0",
    "gn:admin3_code":"14.0",
    "gn:admin4_code":"140028.0",
    "gn:asciiname":"Mathillo Malbanse",
    "gn:country_code":"NP",
    "gn:dem":1539,
    "gn:feature_class":"P",
    "gn:feature_code":"PPLL",
    "gn:name":"Mathillo Malbanse",
    "gn:population":0,
    "gn:timezone":"Asia/Kathmandu",
    "iso:country":"NP",
    "wof:name":"Mathillo Malbanse",
    "wof:placetype":"locality"
},
  "geometry": {"coordinates":[86.68852,26.96237],"type":"Point"}
}