{
  "type": "Feature",
  "properties": {
    "gn:admin1_code":"MR",
    "gn:admin2_code":"12",
    "gn:admin3_code":"56.0",
    "gn:admin4_code":"560039.0",
    "gn:asciiname":"Turuntapur",
    "gn:country_code":"NP",
    "gn:dem":722,
    "gn:feature_class":"P",
    "gn:feature_code":"PPLL",
    "gn:name":"Turuntapur",
    "gn:population":0,
    "gn:timezone":"Asia/Kathmandu",
    "iso:country":"NP",
    "wof:name":"Turuntapur",
    "wof:placetype":"locality"
},
  "geometry": {"coordinates":[82.48779999999999,28.0653],"type":"Point"}
}