{
  "type": "Feature",
  "properties": {
    "gn:admin1_code":"00",
    "gn:asciiname":"Selan",
    "gn:country_code":"NP",
    "gn:dem":1466,
    "gn:feature_class":"P",
    "gn:feature_code":"PPL",
    "gn:name":"Sel\u0101\u1e45",
    "gn:population":0,
    "gn:timezone":"Asia/Kathmandu",
    "iso:country":"NP",
    "name:nep_x_preferred":[
        "Sel\u0101\u1e45"
    ],
    "wof:name":"Selan",
    "wof:placetype":"locality"
},
  "geometry": {"coordinates":[85.75024000000001,27.85114],"type":"Point"}
}