{
  "type": "Feature",
  "properties": {
    "gn:admin1_code":"CR",
    "gn:admin2_code":"11",
    "gn:admin3_code":"34",
    "gn:admin4_code":"340057.0",
    "gn:asciiname":"Gopibasti",
    "gn:country_code":"NP",
    "gn:dem":140,
    "gn:feature_class":"P",
    "gn:feature_code":"PPLL",
    "gn:name":"Gopibasti",
    "gn:population":0,
    "gn:timezone":"Asia/Kathmandu",
    "iso:country":"NP",
    "wof:name":"Gopibasti",
    "wof:placetype":"locality"
},
  "geometry": {"coordinates":[84.68295000000001,27.24607],"type":"Point"}
}