{
  "type": "Feature",
  "properties": {
    "gn:admin1_code":"00",
    "gn:asciiname":"Bhanjyang Kharka",
    "gn:country_code":"NP",
    "gn:dem":3257,
    "gn:feature_class":"P",
    "gn:feature_code":"PPL",
    "gn:name":"Bha\u00f1jy\u0101ng Kharka",
    "gn:population":0,
    "gn:timezone":"Asia/Kathmandu",
    "iso:country":"NP",
    "name:nep_x_preferred":[
        "Bha\u00f1jy\u0101ng Kharka"
    ],
    "wof:name":"Bhanjyang Kharka",
    "wof:placetype":"locality"
},
  "geometry": {"coordinates":[85.48186,27.96761],"type":"Point"}
}