{
  "type": "Feature",
  "properties": {
    "gn:admin1_code":"ER",
    "gn:admin2_code":"7",
    "gn:admin3_code":"9",
    "gn:admin4_code":"90027",
    "gn:asciiname":"Kaphalbote",
    "gn:country_code":"NP",
    "gn:dem":1319,
    "gn:feature_class":"P",
    "gn:feature_code":"PPLL",
    "gn:name":"Kaphalbote",
    "gn:population":0,
    "gn:timezone":"Asia/Kathmandu",
    "iso:country":"NP",
    "wof:name":"Kaphalbote",
    "wof:placetype":"locality"
},
  "geometry": {"coordinates":[87.38193000000003,27.30349],"type":"Point"}
}