{
  "type": "Feature",
  "properties": {
    "gn:admin1_code":"00",
    "gn:asciiname":"Ghumthan",
    "gn:country_code":"NP",
    "gn:dem":1884,
    "gn:feature_class":"P",
    "gn:feature_code":"PPL",
    "gn:name":"Ghumth\u0101\u1e45",
    "gn:population":0,
    "gn:timezone":"Asia/Kathmandu",
    "iso:country":"NP",
    "name:nep_x_preferred":[
        "Ghumth\u0101\u1e45"
    ],
    "wof:name":"Ghumthan",
    "wof:placetype":"locality"
},
  "geometry": {"coordinates":[85.80421,27.96475],"type":"Point"}
}