{
  "type": "Feature",
  "properties": {
    "gn:admin1_code":"CR",
    "gn:admin2_code":"1",
    "gn:admin3_code":"23",
    "gn:admin4_code":"230050.0",
    "gn:asciiname":"Nawalpur",
    "gn:country_code":"NP",
    "gn:dem":1714,
    "gn:feature_class":"P",
    "gn:feature_code":"PPLL",
    "gn:name":"Nawalpur",
    "gn:population":0,
    "gn:timezone":"Asia/Kathmandu",
    "iso:country":"NP",
    "wof:name":"Nawalpur",
    "wof:placetype":"locality"
},
  "geometry": {"coordinates":[85.63329,27.81797000000001],"type":"Point"}
}