{
  "type": "Feature",
  "properties": {
    "gn:admin1_code":"CR",
    "gn:admin2_code":"5",
    "gn:admin3_code":"20",
    "gn:admin4_code":"200013",
    "gn:asciiname":"Dandi",
    "gn:country_code":"NP",
    "gn:dem":416,
    "gn:feature_class":"P",
    "gn:feature_code":"PPLL",
    "gn:name":"Dandi",
    "gn:population":0,
    "gn:timezone":"Asia/Kathmandu",
    "iso:country":"NP",
    "name:ceb_x_preferred":[
        "Dandi"
    ],
    "name:deu_x_preferred":[
        "Dandi"
    ],
    "name:ita_x_preferred":[
        "Dandi"
    ],
    "name:por_x_preferred":[
        "Dandi"
    ],
    "name:swe_x_preferred":[
        "Dandi"
    ],
    "name:tam_x_preferred":[
        "\u0ba4\u0ba3\u0bcd\u0b9f\u0bbf"
    ],
    "wof:name":"Dandi",
    "wof:placetype":"locality"
},
  "geometry": {"coordinates":[85.87168,27.26206],"type":"Point"}
}