{
  "type": "Feature",
  "properties": {
    "gn:admin1_code":"FR",
    "gn:admin2_code":"9",
    "gn:admin3_code":"74",
    "gn:admin4_code":"740058",
    "gn:asciiname":"Silanga",
    "gn:country_code":"NP",
    "gn:dem":1482,
    "gn:feature_class":"P",
    "gn:feature_code":"PPLL",
    "gn:name":"Silanga",
    "gn:population":0,
    "gn:timezone":"Asia/Kathmandu",
    "iso:country":"NP",
    "wof:name":"Silanga",
    "wof:placetype":"locality"
},
  "geometry": {"coordinates":[80.568,29.4433],"type":"Point"}
}