{
  "type": "Feature",
  "properties": {
    "gn:admin1_code":"FR",
    "gn:admin2_code":"9",
    "gn:admin3_code":"74",
    "gn:admin4_code":"740058",
    "gn:asciiname":"Silanga",
    "gn:country_code":"NP",
    "gn:dem":1482,
    "gn:feature_class":"P",
    "gn:feature_code":"PPLL",
    "gn:name":"Silanga",
    "gn:population":0,
    "gn:timezone":"Asia/Kathmandu",
    "iso:country":"NP",
    "name:ceb_x_preferred":[
        "Silanga"
    ],
    "name:msa_x_preferred":[
        "Silanga"
    ],
    "name:nep_x_preferred":[
        "\u0938\u093f\u0932\u0902\u0917\u093e"
    ],
    "name:new_x_preferred":[
        "\u0938\u093f\u0932\u0919\u094d\u0917\u093e"
    ],
    "name:pol_x_preferred":[
        "Silanga"
    ],
    "wof:name":"Silanga",
    "wof:placetype":"locality"
},
  "geometry": {"coordinates":[80.568,29.4433],"type":"Point"}
}