{
  "type": "Feature",
  "properties": {
    "gn:admin1_code":"ER",
    "gn:admin2_code":"7",
    "gn:admin3_code":"10.0",
    "gn:admin4_code":"100058.0",
    "gn:asciiname":"Yangchhungpa",
    "gn:country_code":"NP",
    "gn:dem":2193,
    "gn:feature_class":"P",
    "gn:feature_code":"PPLL",
    "gn:name":"Yangchhungpa",
    "gn:population":0,
    "gn:timezone":"Asia/Kathmandu",
    "iso:country":"NP",
    "wof:name":"Yangchhungpa",
    "wof:placetype":"locality"
},
  "geometry": {"coordinates":[87.0091,27.27644],"type":"Point"}
}