{
  "type": "Feature",
  "properties": {
    "gn:admin1_code":"WR",
    "gn:admin2_code":"8",
    "gn:admin3_code":"47",
    "gn:admin4_code":"470017.0",
    "gn:asciiname":"Darlam",
    "gn:country_code":"NP",
    "gn:dem":999,
    "gn:feature_class":"P",
    "gn:feature_code":"PPLL",
    "gn:name":"Darlam",
    "gn:population":0,
    "gn:timezone":"Asia/Kathmandu",
    "iso:country":"NP",
    "wof:name":"Darlam",
    "wof:placetype":"locality"
},
  "geometry": {"coordinates":[83.59456,27.90289000000001],"type":"Point"}
}