{
  "type": "Feature",
  "properties": {
    "gn:admin1_code":"00",
    "gn:asciiname":"Kyanjin Gumba",
    "gn:country_code":"NP",
    "gn:dem":3912,
    "gn:feature_class":"P",
    "gn:feature_code":"PPL",
    "gn:name":"Ky\u0101\u1e45ji\u1e45 Gumb\u0101",
    "gn:population":0,
    "gn:timezone":"Asia/Kathmandu",
    "iso:country":"NP",
    "wof:name":"Kyanjin Gumba",
    "wof:placetype":"locality"
},
  "geometry": {"coordinates":[85.56896999999999,28.21268],"type":"Point"}
}