{
  "type": "Feature",
  "properties": {
    "gn:admin1_code":"WR",
    "gn:admin2_code":"3",
    "gn:admin3_code":"45.0",
    "gn:admin4_code":"450025.0",
    "gn:asciiname":"Naitul",
    "gn:country_code":"NP",
    "gn:dem":1914,
    "gn:feature_class":"P",
    "gn:feature_code":"PPLL",
    "gn:name":"Naitul",
    "gn:population":0,
    "gn:timezone":"Asia/Kathmandu",
    "iso:country":"NP",
    "wof:name":"Naitul",
    "wof:placetype":"locality"
},
  "geometry": {"coordinates":[83.28912,28.26101],"type":"Point"}
}