{
  "type": "Feature",
  "properties": {
    "gn:admin1_code":"WR",
    "gn:admin2_code":"8",
    "gn:admin3_code":"47",
    "gn:admin4_code":"470046.0",
    "gn:asciiname":"Kaphaldanda",
    "gn:country_code":"NP",
    "gn:dem":1029,
    "gn:feature_class":"P",
    "gn:feature_code":"PPLL",
    "gn:name":"Kaphaldanda",
    "gn:population":0,
    "gn:timezone":"Asia/Kathmandu",
    "iso:country":"NP",
    "wof:name":"Kaphaldanda",
    "wof:placetype":"locality"
},
  "geometry": {"coordinates":[83.92381999999998,27.77696],"type":"Point"}
}