{
  "type": "Feature",
  "properties": {
    "gn:admin1_code":"00",
    "gn:asciiname":"Sagutar",
    "gn:country_code":"NP",
    "gn:dem":1145,
    "gn:feature_class":"P",
    "gn:feature_code":"PPL",
    "gn:name":"S\u0101\u0303gu\u1e6d\u0101r",
    "gn:population":0,
    "gn:timezone":"Asia/Kathmandu",
    "iso:country":"NP",
    "name:und_x_variant":[
        "S\u0101\u0303gu\u1e6d\u0101r",
        "S\u0101ngu\u1e6d\u0101r"
    ],
    "wof:name":"Sagutar",
    "wof:placetype":"locality"
},
  "geometry": {"coordinates":[85.87411,27.52145],"type":"Point"}
}