{
  "type": "Feature",
  "properties": {
    "gn:admin1_code":"00",
    "gn:asciiname":"Janakpur",
    "gn:country_code":"NP",
    "gn:dem":179,
    "gn:feature_class":"P",
    "gn:feature_code":"PPL",
    "gn:name":"Janakpur",
    "gn:population":0,
    "gn:timezone":"Asia/Kathmandu",
    "iso:country":"NP",
    "name:nep_x_preferred":[
        "Janakpur"
    ],
    "wof:name":"Janakpur",
    "wof:placetype":"locality"
},
  "geometry": {"coordinates":[80.93361,28.73401],"type":"Point"}
}