{
  "type": "Feature",
  "properties": {
    "gn:admin1_code":"00",
    "gn:asciiname":"Janakpur",
    "gn:country_code":"NP",
    "gn:dem":179,
    "gn:feature_class":"P",
    "gn:feature_code":"PPL",
    "gn:name":"Janakpur",
    "gn:population":0,
    "gn:timezone":"Asia/Kathmandu",
    "iso:country":"NP",
    "name:fra_x_preferred":[
        "Janakpur"
    ],
    "name:hin_x_preferred":[
        "\u091c\u0928\u0915\u092a\u0941\u0930"
    ],
    "name:nep_x_preferred":[
        "Janakpur"
    ],
    "name:nep_x_variant":[
        "\u091c\u0928\u0915\u092a\u0941\u0930\u0927\u093e\u092e"
    ],
    "name:new_x_preferred":[
        "\u091c\u0928\u0915\u092a\u0941\u0930 \u0928\u0917\u0930\u092a\u093e\u0932\u093f\u0915\u093e"
    ],
    "name:nor_x_preferred":[
        "Janakpur"
    ],
    "name:pol_x_preferred":[
        "Janakpur"
    ],
    "name:swe_x_preferred":[
        "Janakpur"
    ],
    "wof:name":"Janakpur",
    "wof:placetype":"locality"
},
  "geometry": {"coordinates":[80.93361,28.73401],"type":"Point"}
}