{
  "type": "Feature",
  "properties": {
    "gn:admin1_code":"ER",
    "gn:admin2_code":"13",
    "gn:admin3_code":"13.0",
    "gn:admin4_code":"130025.0",
    "gn:asciiname":"Dalmi Bhanjyang",
    "gn:country_code":"NP",
    "gn:dem":1256,
    "gn:feature_class":"P",
    "gn:feature_code":"PPLL",
    "gn:name":"Dalmi Bhanjyang",
    "gn:population":0,
    "gn:timezone":"Asia/Kathmandu",
    "iso:country":"NP",
    "wof:name":"Dalmi Bhanjyang",
    "wof:placetype":"locality"
},
  "geometry": {"coordinates":[86.49395,27.14779],"type":"Point"}
}