{
  "type": "Feature",
  "properties": {
    "gn:admin1_code":"MR",
    "gn:admin2_code":"12",
    "gn:admin3_code":"54",
    "gn:admin4_code":"540007",
    "gn:asciiname":"Loribang",
    "gn:country_code":"NP",
    "gn:dem":983,
    "gn:feature_class":"P",
    "gn:feature_code":"PPLL",
    "gn:name":"Loribang",
    "gn:population":0,
    "gn:timezone":"Asia/Kathmandu",
    "iso:country":"NP",
    "wof:name":"Loribang",
    "wof:placetype":"locality"
},
  "geometry": {"coordinates":[82.40208,28.64263],"type":"Point"}
}