{
  "type": "Feature",
  "properties": {
    "gn:admin1_code":"WR",
    "gn:admin2_code":"4",
    "gn:admin3_code":"36.0",
    "gn:admin4_code":"360044.0",
    "gn:asciiname":"Kabre",
    "gn:country_code":"NP",
    "gn:dem":1431,
    "gn:feature_class":"P",
    "gn:feature_code":"PPLL",
    "gn:name":"Kabre",
    "gn:population":0,
    "gn:timezone":"Asia/Kathmandu",
    "iso:country":"NP",
    "wof:name":"Kabre",
    "wof:placetype":"locality"
},
  "geometry": {"coordinates":[84.65245999999998,28.15106],"type":"Point"}
}