{
  "type": "Feature",
  "properties": {
    "gn:admin1_code":"MR",
    "gn:admin2_code":"12",
    "gn:admin3_code":"53",
    "gn:admin4_code":"530027",
    "gn:asciiname":"Hile",
    "gn:country_code":"NP",
    "gn:dem":1135,
    "gn:feature_class":"P",
    "gn:feature_code":"PPLL",
    "gn:name":"Hile",
    "gn:population":0,
    "gn:timezone":"Asia/Kathmandu",
    "iso:country":"NP",
    "name:nep_x_preferred":[
        "\u0939\u093f\u0932\u0947 \u092c\u091c\u093e\u0930"
    ],
    "wof:name":"Hile",
    "wof:placetype":"locality"
},
  "geometry": {"coordinates":[82.6902,28.24629],"type":"Point"}
}