{
  "type": "Feature",
  "properties": {
    "gn:admin1_code":"MR",
    "gn:admin2_code":"12",
    "gn:admin3_code":"56.0",
    "gn:admin4_code":"560006.0",
    "gn:asciiname":"Kukur Bhukuwa",
    "gn:country_code":"NP",
    "gn:dem":588,
    "gn:feature_class":"P",
    "gn:feature_code":"PPLL",
    "gn:name":"Kukur Bhukuwa",
    "gn:population":0,
    "gn:timezone":"Asia/Kathmandu",
    "iso:country":"NP",
    "wof:name":"Kukur Bhukuwa",
    "wof:placetype":"locality"
},
  "geometry": {"coordinates":[82.40700000000002,27.99329],"type":"Point"}
}