{
  "type": "Feature",
  "properties": {
    "gn:admin1_code":"FR",
    "gn:admin2_code":"14",
    "gn:admin3_code":"69.0",
    "gn:admin4_code":"690019.0",
    "gn:asciiname":"Raksekhet",
    "gn:country_code":"NP",
    "gn:dem":1262,
    "gn:feature_class":"P",
    "gn:feature_code":"PPLL",
    "gn:name":"Raksekhet",
    "gn:population":0,
    "gn:timezone":"Asia/Kathmandu",
    "iso:country":"NP",
    "wof:name":"Raksekhet",
    "wof:placetype":"locality"
},
  "geometry": {"coordinates":[81.32914,29.1874],"type":"Point"}
}