{
  "type": "Feature",
  "properties": {
    "gn:admin1_code":"CR",
    "gn:admin2_code":"1",
    "gn:admin3_code":"30.0",
    "gn:admin4_code":"300002.0",
    "gn:asciiname":"Ristabote",
    "gn:country_code":"NP",
    "gn:dem":736,
    "gn:feature_class":"P",
    "gn:feature_code":"PPLL",
    "gn:name":"Ristabote",
    "gn:population":0,
    "gn:timezone":"Asia/Kathmandu",
    "iso:country":"NP",
    "wof:name":"Ristabote",
    "wof:placetype":"locality"
},
  "geometry": {"coordinates":[84.95059999999999,27.7624],"type":"Point"}
}