{
  "type": "Feature",
  "properties": {
    "gn:admin1_code":"FR",
    "gn:admin2_code":"14",
    "gn:admin3_code":"70.0",
    "gn:admin4_code":"700013.0",
    "gn:asciiname":"Antola",
    "gn:country_code":"NP",
    "gn:dem":885,
    "gn:feature_class":"P",
    "gn:feature_code":"PPLL",
    "gn:name":"Antola",
    "gn:population":0,
    "gn:timezone":"Asia/Kathmandu",
    "iso:country":"NP",
    "wof:name":"Antola",
    "wof:placetype":"locality"
},
  "geometry": {"coordinates":[80.97712,29.23368],"type":"Point"}
}