{
  "type": "Feature",
  "properties": {
    "gn:admin1_code":"CR",
    "gn:admin2_code":"1",
    "gn:admin3_code":"28",
    "gn:admin4_code":"280032",
    "gn:asciiname":"Budenphant",
    "gn:country_code":"NP",
    "gn:dem":746,
    "gn:feature_class":"P",
    "gn:feature_code":"PPLL",
    "gn:name":"Budenphant",
    "gn:population":0,
    "gn:timezone":"Asia/Kathmandu",
    "iso:country":"NP",
    "wof:name":"Budenphant",
    "wof:placetype":"locality"
},
  "geometry": {"coordinates":[85.30880999999999,27.91875],"type":"Point"}
}