{
  "type": "Feature",
  "properties": {
    "gn:admin1_code":"CR",
    "gn:admin2_code":"1",
    "gn:admin3_code":"23",
    "gn:admin4_code":"230073",
    "gn:asciiname":"Kotgaun",
    "gn:country_code":"NP",
    "gn:dem":1657,
    "gn:feature_class":"P",
    "gn:feature_code":"PPLL",
    "gn:name":"Kotgaun",
    "gn:population":0,
    "gn:timezone":"Asia/Kathmandu",
    "iso:country":"NP",
    "wof:name":"Kotgaun",
    "wof:placetype":"locality"
},
  "geometry": {"coordinates":[85.66185,27.9239],"type":"Point"}
}