{
  "type": "Feature",
  "properties": {
    "gn:admin1_code":"CR",
    "gn:admin2_code":"1",
    "gn:admin3_code":"23",
    "gn:admin4_code":"230073",
    "gn:asciiname":"Kotgaun",
    "gn:country_code":"NP",
    "gn:dem":1657,
    "gn:feature_class":"P",
    "gn:feature_code":"PPLL",
    "gn:name":"Kotgaun",
    "gn:population":0,
    "gn:timezone":"Asia/Kathmandu",
    "iso:country":"NP",
    "name:ceb_x_preferred":[
        "Kotgaun"
    ],
    "name:fra_x_preferred":[
        "Kotgaun"
    ],
    "name:mai_x_preferred":[
        "\u0915\u094b\u091f\u0917\u093e\u0909\u0901"
    ],
    "name:msa_x_preferred":[
        "Kotgaun"
    ],
    "name:nep_x_preferred":[
        "\u0915\u094b\u091f\u0917\u093e\u0909\u0901"
    ],
    "name:new_x_preferred":[
        "\u0915\u094b\u0924\u0917\u093e\u0909\u0902"
    ],
    "name:pol_x_preferred":[
        "Kotgaun"
    ],
    "wof:name":"Kotgaun",
    "wof:placetype":"locality"
},
  "geometry": {"coordinates":[85.66185,27.9239],"type":"Point"}
}