{
  "type": "Feature",
  "properties": {
    "gn:admin1_code":"FR",
    "gn:admin2_code":"9",
    "gn:admin3_code":"73.0",
    "gn:admin4_code":"730012.0",
    "gn:asciiname":"Adad",
    "gn:country_code":"NP",
    "gn:dem":1965,
    "gn:feature_class":"P",
    "gn:feature_code":"PPLL",
    "gn:name":"Adad",
    "gn:population":0,
    "gn:timezone":"Asia/Kathmandu",
    "iso:country":"NP",
    "name:afr_x_preferred":[
        "Adad"
    ],
    "name:ara_x_preferred":[
        "\u0623\u062f\u0627\u062f"
    ],
    "name:cat_x_preferred":[
        "Adad"
    ],
    "name:dan_x_preferred":[
        "Adad"
    ],
    "name:deu_x_preferred":[
        "Adad"
    ],
    "name:eus_x_preferred":[
        "Adad"
    ],
    "name:fas_x_preferred":[
        "\u0627\u062f\u062f"
    ],
    "name:fin_x_preferred":[
        "Adad"
    ],
    "name:fra_x_preferred":[
        "Adad"
    ],
    "name:heb_x_preferred":[
        "\u05d0\u05d3\u05d3"
    ],
    "name:hun_x_preferred":[
        "Adad"
    ],
    "name:ita_x_preferred":[
        "Adad"
    ],
    "name:kat_x_preferred":[
        "\u10d0\u10d3\u10d0\u10d3\u10d8"
    ],
    "name:kor_x_preferred":[
        "\uc544\ub2e4\ub4dc"
    ],
    "name:lit_x_preferred":[
        "Adadas"
    ],
    "name:mal_x_preferred":[
        "\u0d05\u0d21\u0d3e\u0d21\u0d4d"
    ],
    "name:nld_x_preferred":[
        "Adad"
    ],
    "name:nor_x_preferred":[
        "Adad"
    ],
    "name:pol_x_preferred":[
        "Adad"
    ],
    "name:ron_x_preferred":[
        "Adad"
    ],
    "name:rus_x_preferred":[
        "\u0410\u0434\u0430\u0434"
    ],
    "name:sco_x_preferred":[
        "Adad"
    ],
    "name:slk_x_preferred":[
        "Adad"
    ],
    "name:slv_x_preferred":[
        "Adad"
    ],
    "name:swe_x_preferred":[
        "Adad"
    ],
    "name:tur_x_preferred":[
        "Adad"
    ],
    "name:ukr_x_preferred":[
        "\u0410\u0434\u0430\u0434"
    ],
    "name:uzb_x_preferred":[
        "Adad"
    ],
    "name:zho_x_preferred":[
        "\u963f\u8fbe\u5fb7"
    ],
    "wof:name":"Adad",
    "wof:placetype":"locality"
},
  "geometry": {"coordinates":[80.47454,29.21926],"type":"Point"}
}