{
  "type": "Feature",
  "properties": {
    "gn:admin1_code":"ER",
    "gn:admin2_code":"13",
    "gn:admin3_code":"11",
    "gn:admin4_code":"110003",
    "gn:asciiname":"Temuche",
    "gn:country_code":"NP",
    "gn:dem":2727,
    "gn:feature_class":"P",
    "gn:feature_code":"PPLL",
    "gn:name":"Temuche",
    "gn:population":0,
    "gn:timezone":"Asia/Kathmandu",
    "iso:country":"NP",
    "wof:name":"Temuche",
    "wof:placetype":"locality"
},
  "geometry": {"coordinates":[86.60155,27.57217],"type":"Point"}
}