{
  "type": "Feature",
  "properties": {
    "gn:admin1_code":"MR",
    "gn:admin2_code":"12",
    "gn:admin3_code":"56.0",
    "gn:admin4_code":"560021.0",
    "gn:asciiname":"Murkuti",
    "gn:country_code":"NP",
    "gn:dem":1547,
    "gn:feature_class":"P",
    "gn:feature_code":"PPLL",
    "gn:name":"Murkuti",
    "gn:population":0,
    "gn:timezone":"Asia/Kathmandu",
    "iso:country":"NP",
    "wof:name":"Murkuti",
    "wof:placetype":"locality"
},
  "geometry": {"coordinates":[82.69948000000002,27.99949],"type":"Point"}
}