{
  "type": "Feature",
  "properties": {
    "gn:admin1_code":"WR",
    "gn:admin2_code":"4.0",
    "gn:admin3_code":"38.0",
    "gn:admin4_code":"380010.0",
    "gn:asciiname":"Lakaswanra",
    "gn:country_code":"NP",
    "gn:dem":305,
    "gn:feature_class":"P",
    "gn:feature_code":"PPLL",
    "gn:name":"Lakaswanra",
    "gn:population":0,
    "gn:timezone":"Asia/Kathmandu",
    "iso:country":"NP",
    "wof:name":"Lakaswanra",
    "wof:placetype":"locality"
},
  "geometry": {"coordinates":[84.27699,27.84036],"type":"Point"}
}