{
  "type": "Feature",
  "properties": {
    "gn:admin1_code":"WR",
    "gn:admin2_code":"4",
    "gn:admin3_code":"41",
    "gn:admin4_code":"410008",
    "gn:asciiname":"Amatsan Himal",
    "gn:country_code":"NP",
    "gn:dem":5752,
    "gn:feature_class":"P",
    "gn:feature_code":"PPLL",
    "gn:name":"Amatsan Himal",
    "gn:population":0,
    "gn:timezone":"Asia/Kathmandu",
    "iso:country":"NP",
    "wof:name":"Amatsan Himal",
    "wof:placetype":"locality"
},
  "geometry": {"coordinates":[84.14827,28.83478],"type":"Point"}
}