{
  "type": "Feature",
  "properties": {
    "gn:admin1_code":"WR",
    "gn:admin2_code":"4",
    "gn:admin3_code":"40.0",
    "gn:admin4_code":"400006.0",
    "gn:asciiname":"Ghaderi",
    "gn:country_code":"NP",
    "gn:dem":1127,
    "gn:feature_class":"P",
    "gn:feature_code":"PPLL",
    "gn:name":"Ghaderi",
    "gn:population":0,
    "gn:timezone":"Asia/Kathmandu",
    "iso:country":"NP",
    "wof:name":"Ghaderi",
    "wof:placetype":"locality"
},
  "geometry": {"coordinates":[83.88519000000002,28.22627],"type":"Point"}
}