{
  "type": "Feature",
  "properties": {
    "gn:admin1_code":"CR",
    "gn:admin2_code":"5",
    "gn:admin3_code":"21",
    "gn:admin4_code":"210052",
    "gn:asciiname":"Sunarpani",
    "gn:country_code":"NP",
    "gn:dem":1102,
    "gn:feature_class":"P",
    "gn:feature_code":"PPLL",
    "gn:name":"Sunarpani",
    "gn:population":0,
    "gn:timezone":"Asia/Kathmandu",
    "iso:country":"NP",
    "wof:name":"Sunarpani",
    "wof:placetype":"locality"
},
  "geometry": {"coordinates":[86.10819000000002,27.35743],"type":"Point"}
}