{
  "type": "Feature",
  "properties": {
    "gn:admin1_code":"00",
    "gn:asciiname":"Adheri",
    "gn:country_code":"NP",
    "gn:dem":1226,
    "gn:feature_class":"P",
    "gn:feature_code":"PPL",
    "gn:name":"\u00c3dheri\u0307\u0304",
    "gn:population":0,
    "gn:timezone":"Asia/Kathmandu",
    "iso:country":"NP",
    "name:nep_x_preferred":[
        "\u00c3dheri\u0307\u0304"
    ],
    "name:nep_x_variant":[
        "\u00c3dher\u012b"
    ],
    "wof:name":"Adheri",
    "wof:placetype":"locality"
},
  "geometry": {"coordinates":[86.34254,27.15259],"type":"Point"}
}