{
  "type": "Feature",
  "properties": {
    "gn:admin1_code":"WR",
    "gn:admin2_code":"8",
    "gn:admin3_code":"46.0",
    "gn:admin4_code":"460055.0",
    "gn:asciiname":"Chitipani",
    "gn:country_code":"NP",
    "gn:dem":1143,
    "gn:feature_class":"P",
    "gn:feature_code":"PPLL",
    "gn:name":"Chitipani",
    "gn:population":0,
    "gn:timezone":"Asia/Kathmandu",
    "iso:country":"NP",
    "wof:name":"Chitipani",
    "wof:placetype":"locality"
},
  "geometry": {"coordinates":[83.30781999999998,28.15809],"type":"Point"}
}