{
  "type": "Feature",
  "properties": {
    "gn:admin1_code":"ER",
    "gn:admin2_code":"13",
    "gn:admin3_code":"12",
    "gn:admin4_code":"120004",
    "gn:asciiname":"Saune",
    "gn:country_code":"NP",
    "gn:dem":2631,
    "gn:feature_class":"P",
    "gn:feature_code":"PPLL",
    "gn:name":"Saune",
    "gn:population":0,
    "gn:timezone":"Asia/Kathmandu",
    "iso:country":"NP",
    "wof:name":"Saune",
    "wof:placetype":"locality"
},
  "geometry": {"coordinates":[86.52633,27.37027],"type":"Point"}
}