{
  "type": "Feature",
  "properties": {
    "gn:admin1_code":"ER",
    "gn:admin2_code":"13",
    "gn:admin3_code":"12",
    "gn:admin4_code":"120004",
    "gn:asciiname":"Saune",
    "gn:country_code":"NP",
    "gn:dem":2631,
    "gn:feature_class":"P",
    "gn:feature_code":"PPLL",
    "gn:name":"Saune",
    "gn:population":0,
    "gn:timezone":"Asia/Kathmandu",
    "iso:country":"NP",
    "name:bih_x_preferred":[
        "\u0938\u093e\u0909\u0928\u0947"
    ],
    "name:ceb_x_preferred":[
        "Saune"
    ],
    "name:ita_x_preferred":[
        "Saune"
    ],
    "name:mai_x_preferred":[
        "\u0938\u093e\u0909\u0928\u0947"
    ],
    "name:msa_x_preferred":[
        "Saune"
    ],
    "name:nep_x_preferred":[
        "\u0938\u093e\u0909\u0928\u0947"
    ],
    "name:new_x_preferred":[
        "\u0938\u093e\u0909\u0928\u0947"
    ],
    "name:pol_x_preferred":[
        "Saune"
    ],
    "wof:name":"Saune",
    "wof:placetype":"locality"
},
  "geometry": {"coordinates":[86.52633,27.37027],"type":"Point"}
}