{
  "type": "Feature",
  "properties": {
    "gn:admin1_code":"MR",
    "gn:admin2_code":"6",
    "gn:admin3_code":"64.0",
    "gn:admin4_code":"640020.0",
    "gn:asciiname":"Bhakseda",
    "gn:country_code":"NP",
    "gn:dem":2285,
    "gn:feature_class":"P",
    "gn:feature_code":"PPLL",
    "gn:name":"Bhakseda",
    "gn:population":0,
    "gn:timezone":"Asia/Kathmandu",
    "iso:country":"NP",
    "wof:name":"Bhakseda",
    "wof:placetype":"locality"
},
  "geometry": {"coordinates":[81.75224,29.14348],"type":"Point"}
}