{
  "type": "Feature",
  "properties": {
    "gn:admin1_code":"FR",
    "gn:admin2_code":"9",
    "gn:admin3_code":"74",
    "gn:admin4_code":"740059",
    "gn:asciiname":"Toligada",
    "gn:country_code":"NP",
    "gn:dem":1472,
    "gn:feature_class":"P",
    "gn:feature_code":"PPLL",
    "gn:name":"Toligada",
    "gn:population":0,
    "gn:timezone":"Asia/Kathmandu",
    "iso:country":"NP",
    "wof:name":"Toligada",
    "wof:placetype":"locality"
},
  "geometry": {"coordinates":[80.45406,29.5894],"type":"Point"}
}