{
  "type": "Feature",
  "properties": {
    "gn:admin1_code":"WR",
    "gn:admin2_code":"8",
    "gn:admin3_code":"47",
    "gn:admin4_code":"470018",
    "gn:asciiname":"Malmul",
    "gn:country_code":"NP",
    "gn:dem":1047,
    "gn:feature_class":"P",
    "gn:feature_code":"PPLL",
    "gn:name":"Malmul",
    "gn:population":0,
    "gn:timezone":"Asia/Kathmandu",
    "iso:country":"NP",
    "wof:name":"Malmul",
    "wof:placetype":"locality"
},
  "geometry": {"coordinates":[83.46726,27.89221],"type":"Point"}
}