{
  "type": "Feature",
  "properties": {
    "gn:admin1_code":"MR",
    "gn:admin2_code":"12",
    "gn:admin3_code":"52",
    "gn:admin4_code":"520004",
    "gn:asciiname":"Wabang",
    "gn:country_code":"NP",
    "gn:dem":938,
    "gn:feature_class":"P",
    "gn:feature_code":"PPLL",
    "gn:name":"Wabang",
    "gn:population":0,
    "gn:timezone":"Asia/Kathmandu",
    "iso:country":"NP",
    "wof:name":"Wabang",
    "wof:placetype":"locality"
},
  "geometry": {"coordinates":[82.94851,27.9846],"type":"Point"}
}