{
  "type": "Feature",
  "properties": {
    "gn:admin1_code":"MR",
    "gn:admin2_code":"12",
    "gn:admin3_code":"55",
    "gn:admin4_code":"550025",
    "gn:asciiname":"Dumrigaun",
    "gn:country_code":"NP",
    "gn:dem":1039,
    "gn:feature_class":"P",
    "gn:feature_code":"PPLL",
    "gn:name":"Dumrigaun",
    "gn:population":0,
    "gn:timezone":"Asia/Kathmandu",
    "iso:country":"NP",
    "wof:name":"Dumrigaun",
    "wof:placetype":"locality"
},
  "geometry": {"coordinates":[82.23478,28.29471],"type":"Point"}
}