{
  "type": "Feature",
  "properties": {
    "gn:admin1_code":"WR",
    "gn:admin2_code":"8",
    "gn:admin3_code":"51.0",
    "gn:admin4_code":"510039.0",
    "gn:asciiname":"Kharsyangau",
    "gn:country_code":"NP",
    "gn:dem":1698,
    "gn:feature_class":"P",
    "gn:feature_code":"PPLL",
    "gn:name":"Kharsyangau",
    "gn:population":0,
    "gn:timezone":"Asia/Kathmandu",
    "iso:country":"NP",
    "wof:name":"Kharsyangau",
    "wof:placetype":"locality"
},
  "geometry": {"coordinates":[83.12401,27.89696],"type":"Point"}
}