{
  "type": "Feature",
  "properties": {
    "gn:admin1_code":"WR",
    "gn:admin2_code":"3",
    "gn:admin3_code":"45.0",
    "gn:admin4_code":"450043.0",
    "gn:asciiname":"Khaligara",
    "gn:country_code":"NP",
    "gn:dem":1339,
    "gn:feature_class":"P",
    "gn:feature_code":"PPLL",
    "gn:name":"Khaligara",
    "gn:population":0,
    "gn:timezone":"Asia/Kathmandu",
    "iso:country":"NP",
    "wof:name":"Khaligara",
    "wof:placetype":"locality"
},
  "geometry": {"coordinates":[83.50713,28.29134],"type":"Point"}
}