{
  "type": "Feature",
  "properties": {
    "gn:admin1_code":"WR",
    "gn:admin2_code":"4",
    "gn:admin3_code":"40.0",
    "gn:admin4_code":"400031.0",
    "gn:asciiname":"Kyauru",
    "gn:country_code":"NP",
    "gn:dem":1448,
    "gn:feature_class":"P",
    "gn:feature_code":"PPLL",
    "gn:name":"Kyauru",
    "gn:population":0,
    "gn:timezone":"Asia/Kathmandu",
    "iso:country":"NP",
    "wof:name":"Kyauru",
    "wof:placetype":"locality"
},
  "geometry": {"coordinates":[84.06958,28.33176],"type":"Point"}
}