{
  "type": "Feature",
  "properties": {
    "gn:admin1_code":"CR",
    "gn:admin2_code":"5",
    "gn:admin3_code":"20",
    "gn:admin4_code":"200026",
    "gn:asciiname":"Baseri",
    "gn:country_code":"NP",
    "gn:dem":950,
    "gn:feature_class":"P",
    "gn:feature_code":"PPLL",
    "gn:name":"Baseri",
    "gn:population":0,
    "gn:timezone":"Asia/Kathmandu",
    "iso:country":"NP",
    "name:ceb_x_preferred":[
        "Baseri"
    ],
    "name:msa_x_preferred":[
        "Baseri"
    ],
    "name:pol_x_preferred":[
        "Baseri"
    ],
    "wof:name":"Baseri",
    "wof:placetype":"locality"
},
  "geometry": {"coordinates":[85.73430999999999,27.29899],"type":"Point"}
}