{
  "type": "Feature",
  "properties": {
    "gn:admin1_code":"WR",
    "gn:admin2_code":"8",
    "gn:admin3_code":"49",
    "gn:admin4_code":"490001",
    "gn:asciiname":"Bangawa",
    "gn:country_code":"NP",
    "gn:dem":94,
    "gn:feature_class":"P",
    "gn:feature_code":"PPLL",
    "gn:name":"Bangawa",
    "gn:population":0,
    "gn:timezone":"Asia/Kathmandu",
    "iso:country":"NP",
    "wof:name":"Bangawa",
    "wof:placetype":"locality"
},
  "geometry": {"coordinates":[83.28856999999998,27.3816],"type":"Point"}
}