{
  "type": "Feature",
  "properties": {
    "gn:admin1_code":"CR",
    "gn:admin2_code":"1",
    "gn:admin3_code":"28",
    "gn:admin4_code":"280059",
    "gn:asciiname":"Aruchaur",
    "gn:country_code":"NP",
    "gn:dem":956,
    "gn:feature_class":"P",
    "gn:feature_code":"PPLL",
    "gn:name":"Aruchaur",
    "gn:population":0,
    "gn:timezone":"Asia/Kathmandu",
    "iso:country":"NP",
    "name:ceb_x_preferred":[
        "Aruchaur"
    ],
    "name:hin_x_preferred":[
        "\u0906\u0930\u0941\u091a\u094c\u0930"
    ],
    "name:mai_x_preferred":[
        "\u0906\u0930\u0941\u091a\u094c\u0930"
    ],
    "name:msa_x_preferred":[
        "Aruchaur"
    ],
    "name:nep_x_preferred":[
        "\u0906\u0930\u0941\u091a\u094c\u0930"
    ],
    "name:new_x_preferred":[
        "\u0906\u0930\u0941\u091a\u094c\u0930"
    ],
    "name:pol_x_preferred":[
        "Aruchaur"
    ],
    "name:urd_x_preferred":[
        "\u0622\u0631\u0648\u0686\u0648\u0631"
    ],
    "wof:name":"Aruchaur",
    "wof:placetype":"locality"
},
  "geometry": {"coordinates":[85.25971,27.85825],"type":"Point"}
}