{
  "type": "Feature",
  "properties": {
    "gn:admin1_code":"CR",
    "gn:admin2_code":"1",
    "gn:admin3_code":"28",
    "gn:admin4_code":"280033",
    "gn:asciiname":"Santar",
    "gn:country_code":"NP",
    "gn:dem":609,
    "gn:feature_class":"P",
    "gn:feature_code":"PPLL",
    "gn:name":"Santar",
    "gn:population":0,
    "gn:timezone":"Asia/Kathmandu",
    "iso:country":"NP",
    "wof:name":"Santar",
    "wof:placetype":"locality"
},
  "geometry": {"coordinates":[85.2157,27.91745],"type":"Point"}
}