{
  "type": "Feature",
  "properties": {
    "gn:admin1_code":"00",
    "gn:asciiname":"Pahritol",
    "gn:country_code":"NP",
    "gn:dem":193,
    "gn:feature_class":"P",
    "gn:feature_code":"PPL",
    "gn:name":"Pahritol",
    "gn:population":0,
    "gn:timezone":"Asia/Kathmandu",
    "iso:country":"NP",
    "wof:name":"Pahritol",
    "wof:placetype":"locality"
},
  "geometry": {"coordinates":[85.51732,27.18352],"type":"Point"}
}