{
  "type": "Feature",
  "properties": {
    "gn:admin1_code":"FR",
    "gn:admin2_code":"14",
    "gn:admin3_code":"69",
    "gn:admin4_code":"690004",
    "gn:asciiname":"Sandik",
    "gn:country_code":"NP",
    "gn:dem":1215,
    "gn:feature_class":"P",
    "gn:feature_code":"PPLL",
    "gn:name":"Sandik",
    "gn:population":0,
    "gn:timezone":"Asia/Kathmandu",
    "iso:country":"NP",
    "wof:name":"Sandik",
    "wof:placetype":"locality"
},
  "geometry": {"coordinates":[81.29843000000002,29.21402],"type":"Point"}
}