{
  "type": "Feature",
  "properties": {
    "gn:admin1_code":"ER",
    "gn:admin2_code":"7.0",
    "gn:admin3_code":"8.0",
    "gn:admin4_code":"80015.0",
    "gn:asciiname":"Tinkhopre",
    "gn:country_code":"NP",
    "gn:dem":1125,
    "gn:feature_class":"P",
    "gn:feature_code":"PPLL",
    "gn:name":"Tinkhopre",
    "gn:population":0,
    "gn:timezone":"Asia/Kathmandu",
    "iso:country":"NP",
    "wof:name":"Tinkhopre",
    "wof:placetype":"locality"
},
  "geometry": {"coordinates":[87.51484000000001,27.12182],"type":"Point"}
}