{
  "type": "Feature",
  "properties": {
    "gn:admin1_code":"CR",
    "gn:admin2_code":"5",
    "gn:admin3_code":"20",
    "gn:admin4_code":"200002",
    "gn:asciiname":"Bahundanda",
    "gn:country_code":"NP",
    "gn:dem":809,
    "gn:feature_class":"P",
    "gn:feature_code":"PPLL",
    "gn:name":"Bahundanda",
    "gn:population":0,
    "gn:timezone":"Asia/Kathmandu",
    "iso:country":"NP",
    "name:ara_x_preferred":[
        "\u0628\u0627\u0647\u0648\u0646\u062f\u0627\u0646\u062f\u0627"
    ],
    "name:ceb_x_preferred":[
        "Bahundanda"
    ],
    "name:deu_x_preferred":[
        "Bahundanda"
    ],
    "name:fra_x_preferred":[
        "Bahundanda"
    ],
    "name:mai_x_preferred":[
        "\u092c\u093e\u0939\u0941\u0928\u0921\u093e\u0901\u0921\u093e"
    ],
    "name:msa_x_preferred":[
        "Bahundanda"
    ],
    "name:nep_x_preferred":[
        "\u092c\u093e\u0939\u0941\u0928\u0921\u093e\u0901\u0921\u093e"
    ],
    "name:new_x_preferred":[
        "\u092c\u093e\u0939\u0941\u0928\u0921\u093e\u0902\u0921\u093e"
    ],
    "name:pol_x_preferred":[
        "Bahundanda"
    ],
    "wof:name":"Bahundanda",
    "wof:placetype":"locality"
},
  "geometry": {"coordinates":[86.26304,27.06235],"type":"Point"}
}