{
  "type": "Feature",
  "properties": {
    "gn:admin1_code":"CR",
    "gn:admin2_code":"5",
    "gn:admin3_code":"20",
    "gn:admin4_code":"200002",
    "gn:asciiname":"Bahundanda",
    "gn:country_code":"NP",
    "gn:dem":809,
    "gn:feature_class":"P",
    "gn:feature_code":"PPLL",
    "gn:name":"Bahundanda",
    "gn:population":0,
    "gn:timezone":"Asia/Kathmandu",
    "iso:country":"NP",
    "wof:name":"Bahundanda",
    "wof:placetype":"locality"
},
  "geometry": {"coordinates":[86.26304,27.06235],"type":"Point"}
}