{
  "type": "Feature",
  "properties": {
    "gn:admin1_code":"ER",
    "gn:admin2_code":"13",
    "gn:admin3_code":"11",
    "gn:admin4_code":"110029.0",
    "gn:asciiname":"Taibuk",
    "gn:country_code":"NP",
    "gn:dem":2779,
    "gn:feature_class":"P",
    "gn:feature_code":"PPLL",
    "gn:name":"Taibuk",
    "gn:population":0,
    "gn:timezone":"Asia/Kathmandu",
    "iso:country":"NP",
    "wof:name":"Taibuk",
    "wof:placetype":"locality"
},
  "geometry": {"coordinates":[86.6108,27.53099000000001],"type":"Point"}
}