{
  "type": "Feature",
  "properties": {
    "gn:admin1_code":"WR",
    "gn:admin2_code":"8",
    "gn:admin3_code":"49",
    "gn:admin4_code":"490061",
    "gn:asciiname":"Gauraiya",
    "gn:country_code":"NP",
    "gn:dem":131,
    "gn:feature_class":"P",
    "gn:feature_code":"PPLL",
    "gn:name":"Gauraiya",
    "gn:population":0,
    "gn:timezone":"Asia/Kathmandu",
    "iso:country":"NP",
    "wof:name":"Gauraiya",
    "wof:placetype":"locality"
},
  "geometry": {"coordinates":[83.39073,27.67366],"type":"Point"}
}