{
  "type": "Feature",
  "properties": {
    "gn:admin1_code":"FR",
    "gn:admin2_code":"9",
    "gn:admin3_code":"74",
    "gn:admin4_code":"740001",
    "gn:asciiname":"Janggaltada",
    "gn:country_code":"NP",
    "gn:dem":645,
    "gn:feature_class":"P",
    "gn:feature_code":"PPLL",
    "gn:name":"Janggaltada",
    "gn:population":0,
    "gn:timezone":"Asia/Kathmandu",
    "iso:country":"NP",
    "wof:name":"Janggaltada",
    "wof:placetype":"locality"
},
  "geometry": {"coordinates":[80.30237,29.46202000000001],"type":"Point"}
}