{
  "type": "Feature",
  "properties": {
    "gn:admin1_code":"FR",
    "gn:admin2_code":"14",
    "gn:admin3_code":"71.0",
    "gn:admin4_code":"710023.0",
    "gn:asciiname":"Baskota",
    "gn:country_code":"NP",
    "gn:dem":208,
    "gn:feature_class":"P",
    "gn:feature_code":"PPLL",
    "gn:name":"Baskota",
    "gn:population":0,
    "gn:timezone":"Asia/Kathmandu",
    "iso:country":"NP",
    "wof:name":"Baskota",
    "wof:placetype":"locality"
},
  "geometry": {"coordinates":[80.5718,28.83138],"type":"Point"}
}