{
  "type": "Feature",
  "properties": {
    "gn:admin1_code":"WR",
    "gn:admin2_code":"4",
    "gn:admin3_code":"40.0",
    "gn:admin4_code":"400003.0",
    "gn:asciiname":"Kasyari",
    "gn:country_code":"NP",
    "gn:dem":750,
    "gn:feature_class":"P",
    "gn:feature_code":"PPLL",
    "gn:name":"Kasyari",
    "gn:population":0,
    "gn:timezone":"Asia/Kathmandu",
    "iso:country":"NP",
    "wof:name":"Kasyari",
    "wof:placetype":"locality"
},
  "geometry": {"coordinates":[84.14863000000003,28.21614000000001],"type":"Point"}
}