{
  "type": "Feature",
  "properties": {
    "gn:admin1_code":"FR",
    "gn:admin2_code":"14.0",
    "gn:admin3_code":"68.0",
    "gn:admin4_code":"680045.0",
    "gn:asciiname":"Doba",
    "gn:country_code":"NP",
    "gn:dem":1081,
    "gn:feature_class":"P",
    "gn:feature_code":"PPLL",
    "gn:name":"Doba",
    "gn:population":0,
    "gn:timezone":"Asia/Kathmandu",
    "iso:country":"NP",
    "name:ben_x_preferred":[
        "\u09a6\u09cb\u09ac\u09be"
    ],
    "name:ceb_x_preferred":[
        "Doba"
    ],
    "name:ces_x_preferred":[
        "Doba"
    ],
    "name:deu_x_preferred":[
        "Doba"
    ],
    "name:ell_x_preferred":[
        "\u039d\u03c4\u03cc\u03bc\u03c0\u03b1"
    ],
    "name:epo_x_preferred":[
        "Doba"
    ],
    "name:fas_x_preferred":[
        "\u062f\u0648\u0628\u0627"
    ],
    "name:fra_x_preferred":[
        "Doba"
    ],
    "name:heb_x_preferred":[
        "\u05d3\u05d5\u05d1\u05d4"
    ],
    "name:hun_x_preferred":[
        "Doba"
    ],
    "name:ita_x_preferred":[
        "Doba"
    ],
    "name:nld_x_preferred":[
        "Doba"
    ],
    "name:pol_x_preferred":[
        "Doba"
    ],
    "name:por_x_preferred":[
        "Doba"
    ],
    "name:ron_x_preferred":[
        "Doba"
    ],
    "name:rue_x_preferred":[
        "\u0414\u043e\u0431\u0430"
    ],
    "name:rus_x_preferred":[
        "\u0414\u043e\u0431\u0430"
    ],
    "name:slk_x_preferred":[
        "Doba"
    ],
    "name:srp_x_preferred":[
        "\u0414\u043e\u0431\u0430"
    ],
    "name:swe_x_preferred":[
        "Doba"
    ],
    "name:tur_x_preferred":[
        "Doba"
    ],
    "name:ukr_x_preferred":[
        "\u0414\u043e\u0431\u0430"
    ],
    "wof:name":"Doba",
    "wof:placetype":"locality"
},
  "geometry": {"coordinates":[80.89431999999999,29.45785],"type":"Point"}
}