{
  "type": "Feature",
  "properties": {
    "gn:admin1_code":"CR",
    "gn:admin2_code":"11",
    "gn:admin3_code":"31",
    "gn:admin4_code":"310040.0",
    "gn:asciiname":"Bimire",
    "gn:country_code":"NP",
    "gn:dem":354,
    "gn:feature_class":"P",
    "gn:feature_code":"PPLL",
    "gn:name":"Bimire",
    "gn:population":0,
    "gn:timezone":"Asia/Kathmandu",
    "iso:country":"NP",
    "wof:name":"Bimire",
    "wof:placetype":"locality"
},
  "geometry": {"coordinates":[85.24798,27.34332],"type":"Point"}
}