{
  "type": "Feature",
  "properties": {
    "gn:admin1_code":"ER",
    "gn:admin2_code":"10.0",
    "gn:admin3_code":"1.0",
    "gn:admin4_code":"10045.0",
    "gn:asciiname":"Khahare",
    "gn:country_code":"NP",
    "gn:dem":826,
    "gn:feature_class":"P",
    "gn:feature_code":"PPLL",
    "gn:name":"Khahare",
    "gn:population":0,
    "gn:timezone":"Asia/Kathmandu",
    "iso:country":"NP",
    "wof:name":"Khahare",
    "wof:placetype":"locality"
},
  "geometry": {"coordinates":[87.72728000000002,27.29134],"type":"Point"}
}