{
  "type": "Feature",
  "properties": {
    "gn:admin1_code":"FR",
    "gn:admin2_code":"14",
    "gn:admin3_code":"70.0",
    "gn:admin4_code":"700007.0",
    "gn:asciiname":"Patihalna",
    "gn:country_code":"NP",
    "gn:dem":2017,
    "gn:feature_class":"P",
    "gn:feature_code":"PPLL",
    "gn:name":"Patihalna",
    "gn:population":0,
    "gn:timezone":"Asia/Kathmandu",
    "iso:country":"NP",
    "wof:name":"Patihalna",
    "wof:placetype":"locality"
},
  "geometry": {"coordinates":[80.92246,29.39516],"type":"Point"}
}