{
  "type": "Feature",
  "properties": {
    "gn:admin1_code":"WR",
    "gn:admin2_code":"4",
    "gn:admin3_code":"40.0",
    "gn:admin4_code":"400022.0",
    "gn:asciiname":"Simalpata",
    "gn:country_code":"NP",
    "gn:dem":1108,
    "gn:feature_class":"P",
    "gn:feature_code":"PPLL",
    "gn:name":"Simalpata",
    "gn:population":0,
    "gn:timezone":"Asia/Kathmandu",
    "iso:country":"NP",
    "wof:name":"Simalpata",
    "wof:placetype":"locality"
},
  "geometry": {"coordinates":[84.11091,28.19138],"type":"Point"}
}