{
  "type": "Feature",
  "properties": {
    "gn:admin1_code":"WR",
    "gn:admin2_code":"3",
    "gn:admin3_code":"43",
    "gn:admin4_code":"430031",
    "gn:asciiname":"Daduwa",
    "gn:country_code":"NP",
    "gn:dem":1558,
    "gn:feature_class":"P",
    "gn:feature_code":"PPLL",
    "gn:name":"Daduwa",
    "gn:population":0,
    "gn:timezone":"Asia/Kathmandu",
    "iso:country":"NP",
    "wof:name":"Daduwa",
    "wof:placetype":"locality"
},
  "geometry": {"coordinates":[83.49701,28.38716],"type":"Point"}
}