{
  "type": "Feature",
  "properties": {
    "gn:admin1_code":"WR",
    "gn:admin2_code":"4",
    "gn:admin3_code":"37",
    "gn:admin4_code":"370049",
    "gn:asciiname":"Khanalphat",
    "gn:country_code":"NP",
    "gn:dem":433,
    "gn:feature_class":"P",
    "gn:feature_code":"PPLL",
    "gn:name":"Khanalphat",
    "gn:population":0,
    "gn:timezone":"Asia/Kathmandu",
    "iso:country":"NP",
    "wof:name":"Khanalphat",
    "wof:placetype":"locality"
},
  "geometry": {"coordinates":[84.23430999999999,28.09534],"type":"Point"}
}