{
  "type": "Feature",
  "properties": {
    "gn:admin1_code":"MR",
    "gn:admin2_code":"12",
    "gn:admin3_code":"54",
    "gn:admin4_code":"540015",
    "gn:asciiname":"Bhani",
    "gn:country_code":"NP",
    "gn:dem":2654,
    "gn:feature_class":"P",
    "gn:feature_code":"PPLL",
    "gn:name":"Bhani",
    "gn:population":0,
    "gn:timezone":"Asia/Kathmandu",
    "iso:country":"NP",
    "wof:name":"Bhani",
    "wof:placetype":"locality"
},
  "geometry": {"coordinates":[82.77153,28.66078],"type":"Point"}
}