{
  "type": "Feature",
  "properties": {
    "gn:admin1_code":"CR",
    "gn:admin2_code":"11",
    "gn:admin3_code":"31",
    "gn:admin4_code":"310036",
    "gn:asciiname":"Sakhatar",
    "gn:country_code":"NP",
    "gn:dem":207,
    "gn:feature_class":"P",
    "gn:feature_code":"PPLL",
    "gn:name":"Sakhatar",
    "gn:population":0,
    "gn:timezone":"Asia/Kathmandu",
    "iso:country":"NP",
    "wof:name":"Sakhatar",
    "wof:placetype":"locality"
},
  "geometry": {"coordinates":[85.47308000000002,27.2197],"type":"Point"}
}