{
  "type": "Feature",
  "properties": {
    "gn:admin1_code":"MR",
    "gn:admin2_code":"2",
    "gn:admin3_code":"60.0",
    "gn:admin4_code":"600045.0",
    "gn:asciiname":"Selgaun",
    "gn:country_code":"NP",
    "gn:dem":938,
    "gn:feature_class":"P",
    "gn:feature_code":"PPLL",
    "gn:name":"Selgaun",
    "gn:population":0,
    "gn:timezone":"Asia/Kathmandu",
    "iso:country":"NP",
    "wof:name":"Selgaun",
    "wof:placetype":"locality"
},
  "geometry": {"coordinates":[81.45227,29.04087],"type":"Point"}
}