{
  "type": "Feature",
  "properties": {
    "gn:admin1_code":"WR",
    "gn:admin2_code":"4.0",
    "gn:admin3_code":"38.0",
    "gn:admin4_code":"380006.0",
    "gn:asciiname":"Birketar",
    "gn:country_code":"NP",
    "gn:dem":548,
    "gn:feature_class":"P",
    "gn:feature_code":"PPLL",
    "gn:name":"Birketar",
    "gn:population":0,
    "gn:timezone":"Asia/Kathmandu",
    "iso:country":"NP",
    "wof:name":"Birketar",
    "wof:placetype":"locality"
},
  "geometry": {"coordinates":[84.41889999999999,28.05444],"type":"Point"}
}