{
  "type": "Feature",
  "properties": {
    "gn:admin1_code":"MR",
    "gn:admin2_code":"12",
    "gn:admin3_code":"56.0",
    "gn:admin4_code":"560001.0",
    "gn:asciiname":"Patighar",
    "gn:country_code":"NP",
    "gn:dem":809,
    "gn:feature_class":"P",
    "gn:feature_code":"PPLL",
    "gn:name":"Patighar",
    "gn:population":0,
    "gn:timezone":"Asia/Kathmandu",
    "iso:country":"NP",
    "wof:name":"Patighar",
    "wof:placetype":"locality"
},
  "geometry": {"coordinates":[82.16956999999999,28.19929],"type":"Point"}
}