{
  "type": "Feature",
  "properties": {
    "gn:admin1_code":"WR",
    "gn:admin2_code":"4.0",
    "gn:admin3_code":"39.0",
    "gn:admin4_code":"390048.0",
    "gn:asciiname":"Murtichaur",
    "gn:country_code":"NP",
    "gn:dem":427,
    "gn:feature_class":"P",
    "gn:feature_code":"PPLL",
    "gn:name":"Murtichaur",
    "gn:population":0,
    "gn:timezone":"Asia/Kathmandu",
    "iso:country":"NP",
    "wof:name":"Murtichaur",
    "wof:placetype":"locality"
},
  "geometry": {"coordinates":[83.91476,27.88271],"type":"Point"}
}