{
  "type": "Feature",
  "properties": {
    "gn:admin1_code":"WR",
    "gn:admin2_code":"8",
    "gn:admin3_code":"46.0",
    "gn:admin4_code":"460019.0",
    "gn:asciiname":"Dewaldhara",
    "gn:country_code":"NP",
    "gn:dem":1542,
    "gn:feature_class":"P",
    "gn:feature_code":"PPLL",
    "gn:name":"Dewaldhara",
    "gn:population":0,
    "gn:timezone":"Asia/Kathmandu",
    "iso:country":"NP",
    "wof:name":"Dewaldhara",
    "wof:placetype":"locality"
},
  "geometry": {"coordinates":[83.38656,28.12815],"type":"Point"}
}