{
  "type": "Feature",
  "properties": {
    "gn:admin1_code":"00",
    "gn:asciiname":"Syuri",
    "gn:country_code":"NP",
    "gn:dem":1723,
    "gn:feature_class":"P",
    "gn:feature_code":"PPL",
    "gn:name":"Syuri\u0307\u0304",
    "gn:population":0,
    "gn:timezone":"Asia/Kathmandu",
    "iso:country":"NP",
    "name:ita_x_preferred":[
        "Shuri Kond\u014d"
    ],
    "name:nep_x_preferred":[
        "Syuri\u0307\u0304"
    ],
    "name:spa_x_preferred":[
        "Shuri Kondo"
    ],
    "name:und_x_variant":[
        "Siurigaon"
    ],
    "wof:name":"Syuri",
    "wof:placetype":"locality"
},
  "geometry": {"coordinates":[82.81294,28.35413],"type":"Point"}
}