{
  "type": "Feature",
  "properties": {
    "gn:admin1_code":"FR",
    "gn:admin2_code":"9",
    "gn:admin3_code":"74",
    "gn:admin4_code":"740010",
    "gn:asciiname":"Salani",
    "gn:country_code":"NP",
    "gn:dem":1300,
    "gn:feature_class":"P",
    "gn:feature_code":"PPLL",
    "gn:name":"Salani",
    "gn:population":0,
    "gn:timezone":"Asia/Kathmandu",
    "iso:country":"NP",
    "wof:name":"Salani",
    "wof:placetype":"locality"
},
  "geometry": {"coordinates":[80.39055,29.55078],"type":"Point"}
}