{
  "type": "Feature",
  "properties": {
    "gn:admin1_code":"MR",
    "gn:admin2_code":"2",
    "gn:admin3_code":"61.0",
    "gn:admin4_code":"610022.0",
    "gn:asciiname":"Ragda",
    "gn:country_code":"NP",
    "gn:dem":1778,
    "gn:feature_class":"P",
    "gn:feature_code":"PPLL",
    "gn:name":"Ragda",
    "gn:population":0,
    "gn:timezone":"Asia/Kathmandu",
    "iso:country":"NP",
    "wof:name":"Ragda",
    "wof:placetype":"locality"
},
  "geometry": {"coordinates":[82.41034999999999,28.85623],"type":"Point"}
}