{
  "type": "Feature",
  "properties": {
    "gn:admin1_code":"CR",
    "gn:admin2_code":"1",
    "gn:admin3_code":"23",
    "gn:admin4_code":"230049",
    "gn:asciiname":"Hutungrang Bhaunjyang",
    "gn:country_code":"NP",
    "gn:dem":2113,
    "gn:feature_class":"P",
    "gn:feature_code":"PPLL",
    "gn:name":"Hutungrang Bhaunjyang",
    "gn:population":0,
    "gn:timezone":"Asia/Kathmandu",
    "iso:country":"NP",
    "wof:name":"Hutungrang Bhaunjyang",
    "wof:placetype":"locality"
},
  "geometry": {"coordinates":[85.65380999999999,28.00288],"type":"Point"}
}