{
  "type": "Feature",
  "properties": {
    "gn:admin1_code":"FR",
    "gn:admin2_code":"14",
    "gn:admin3_code":"70.0",
    "gn:admin4_code":"700008.0",
    "gn:asciiname":"Ulje",
    "gn:country_code":"NP",
    "gn:dem":1049,
    "gn:feature_class":"P",
    "gn:feature_code":"PPLL",
    "gn:name":"Ulje",
    "gn:population":0,
    "gn:timezone":"Asia/Kathmandu",
    "iso:country":"NP",
    "name:deu_x_preferred":[
        "Ulje"
    ],
    "name:est_x_preferred":[
        "Ulje"
    ],
    "name:fra_x_preferred":[
        "Ulje"
    ],
    "name:hye_x_preferred":[
        "\u0548\u0582\u056c\u0575\u0565"
    ],
    "name:pol_x_preferred":[
        "Ulje"
    ],
    "name:spa_x_preferred":[
        "Ulje"
    ],
    "name:ukr_x_preferred":[
        "\u0423\u043b\u044c\u0454"
    ],
    "name:vol_x_preferred":[
        "Ulje"
    ],
    "wof:name":"Ulje",
    "wof:placetype":"locality"
},
  "geometry": {"coordinates":[80.61085,29.06241],"type":"Point"}
}