{
  "type": "Feature",
  "properties": {
    "gn:admin1_code":"MR",
    "gn:admin2_code":"12",
    "gn:admin3_code":"55",
    "gn:admin4_code":"550031",
    "gn:asciiname":"Tallo Ghareli",
    "gn:country_code":"NP",
    "gn:dem":1039,
    "gn:feature_class":"P",
    "gn:feature_code":"PPLL",
    "gn:name":"Tallo Ghareli",
    "gn:population":0,
    "gn:timezone":"Asia/Kathmandu",
    "iso:country":"NP",
    "wof:name":"Tallo Ghareli",
    "wof:placetype":"locality"
},
  "geometry": {"coordinates":[81.96818,28.42822],"type":"Point"}
}