{
  "type": "Feature",
  "properties": {
    "gn:admin1_code":"MR",
    "gn:admin2_code":"2.0",
    "gn:admin3_code":"58.0",
    "gn:admin4_code":"580004.0",
    "gn:asciiname":"Achhariya",
    "gn:country_code":"NP",
    "gn:dem":163,
    "gn:feature_class":"P",
    "gn:feature_code":"PPLL",
    "gn:name":"Achhariya",
    "gn:population":0,
    "gn:timezone":"Asia/Kathmandu",
    "iso:country":"NP",
    "wof:name":"Achhariya",
    "wof:placetype":"locality"
},
  "geometry": {"coordinates":[81.59135000000001,28.2523],"type":"Point"}
}