{
  "type": "Feature",
  "properties": {
    "gn:admin1_code":"MR",
    "gn:admin2_code":"12",
    "gn:admin3_code":"55",
    "gn:admin4_code":"550015",
    "gn:asciiname":"Bhanggarchaur",
    "gn:country_code":"NP",
    "gn:dem":1435,
    "gn:feature_class":"P",
    "gn:feature_code":"PPLL",
    "gn:name":"Bhanggarchaur",
    "gn:population":0,
    "gn:timezone":"Asia/Kathmandu",
    "iso:country":"NP",
    "wof:name":"Bhanggarchaur",
    "wof:placetype":"locality"
},
  "geometry": {"coordinates":[82.10384000000001,28.36949000000001],"type":"Point"}
}