{
  "type": "Feature",
  "properties": {
    "gn:admin1_code":"WR",
    "gn:admin2_code":"3",
    "gn:admin3_code":"44",
    "gn:admin4_code":"440054",
    "gn:asciiname":"Mahindanda",
    "gn:country_code":"NP",
    "gn:dem":1114,
    "gn:feature_class":"P",
    "gn:feature_code":"PPLL",
    "gn:name":"Mahindanda",
    "gn:population":0,
    "gn:timezone":"Asia/Kathmandu",
    "iso:country":"NP",
    "wof:name":"Mahindanda",
    "wof:placetype":"locality"
},
  "geometry": {"coordinates":[83.64952,28.02206],"type":"Point"}
}