{
  "type": "Feature",
  "properties": {
    "gn:admin1_code":"MR",
    "gn:admin2_code":"2",
    "gn:admin3_code":"61.0",
    "gn:admin4_code":"610003.0",
    "gn:asciiname":"Rauterahya",
    "gn:country_code":"NP",
    "gn:dem":1260,
    "gn:feature_class":"P",
    "gn:feature_code":"PPLL",
    "gn:name":"Rauterahya",
    "gn:population":0,
    "gn:timezone":"Asia/Kathmandu",
    "iso:country":"NP",
    "wof:name":"Rauterahya",
    "wof:placetype":"locality"
},
  "geometry": {"coordinates":[82.13036,28.67691],"type":"Point"}
}