{
  "type": "Feature",
  "properties": {
    "gn:admin1_code":"WR",
    "gn:admin2_code":"4.0",
    "gn:admin3_code":"39.0",
    "gn:admin4_code":"390060.0",
    "gn:asciiname":"Pokhari Danda",
    "gn:country_code":"NP",
    "gn:dem":857,
    "gn:feature_class":"P",
    "gn:feature_code":"PPLL",
    "gn:name":"Pokhari Danda",
    "gn:population":0,
    "gn:timezone":"Asia/Kathmandu",
    "iso:country":"NP",
    "wof:name":"Pokhari Danda",
    "wof:placetype":"locality"
},
  "geometry": {"coordinates":[83.81818,27.98854],"type":"Point"}
}