{
  "type": "Feature",
  "properties": {
    "gn:admin1_code":"WR",
    "gn:admin2_code":"3",
    "gn:admin3_code":"42",
    "gn:admin4_code":"420006.0",
    "gn:asciiname":"Jhong",
    "gn:country_code":"NP",
    "gn:dem":3566,
    "gn:feature_class":"P",
    "gn:feature_code":"PPLL",
    "gn:name":"Jhong",
    "gn:population":0,
    "gn:timezone":"Asia/Kathmandu",
    "iso:country":"NP",
    "name:ceb_x_preferred":[
        "Jhong"
    ],
    "name:deu_x_preferred":[
        "Jhong"
    ],
    "name:dty_x_preferred":[
        "\u091d\u094b\u0919"
    ],
    "name:fra_x_preferred":[
        "Jhong"
    ],
    "name:mai_x_preferred":[
        "\u091d\u094b\u0919"
    ],
    "name:msa_x_preferred":[
        "Jhong"
    ],
    "name:nep_x_preferred":[
        "\u091d\u094b\u0919"
    ],
    "name:new_x_preferred":[
        "\u091d\u094b\u0919"
    ],
    "name:nld_x_preferred":[
        "Jhong"
    ],
    "name:pol_x_preferred":[
        "Jhong"
    ],
    "name:por_x_preferred":[
        "Jhong"
    ],
    "wof:name":"Jhong",
    "wof:placetype":"locality"
},
  "geometry": {"coordinates":[83.85516,28.82777],"type":"Point"}
}