{
  "type": "Feature",
  "properties": {
    "gn:admin1_code":"ER",
    "gn:admin2_code":"7",
    "gn:admin3_code":"5",
    "gn:admin4_code":"50040",
    "gn:asciiname":"Sitamtol",
    "gn:country_code":"NP",
    "gn:dem":69,
    "gn:feature_class":"P",
    "gn:feature_code":"PPLL",
    "gn:name":"Sitamtol",
    "gn:population":0,
    "gn:timezone":"Asia/Kathmandu",
    "iso:country":"NP",
    "wof:name":"Sitamtol",
    "wof:placetype":"locality"
},
  "geometry": {"coordinates":[87.34501999999998,26.40233],"type":"Point"}
}