{
  "type": "Feature",
  "properties": {
    "gn:admin1_code":"FR",
    "gn:admin2_code":"9",
    "gn:admin3_code":"74",
    "gn:admin4_code":"740001",
    "gn:asciiname":"Chaudali",
    "gn:country_code":"NP",
    "gn:dem":1163,
    "gn:feature_class":"P",
    "gn:feature_code":"PPLL",
    "gn:name":"Chaudali",
    "gn:population":0,
    "gn:timezone":"Asia/Kathmandu",
    "iso:country":"NP",
    "wof:name":"Chaudali",
    "wof:placetype":"locality"
},
  "geometry": {"coordinates":[80.32094000000002,29.44012],"type":"Point"}
}