{
  "type": "Feature",
  "properties": {
    "gn:admin1_code":"CR",
    "gn:admin2_code":"1",
    "gn:admin3_code":"24.0",
    "gn:admin4_code":"240038.0",
    "gn:asciiname":"Bhataregaun",
    "gn:country_code":"NP",
    "gn:dem":1451,
    "gn:feature_class":"P",
    "gn:feature_code":"PPLL",
    "gn:name":"Bhataregaun",
    "gn:population":0,
    "gn:timezone":"Asia/Kathmandu",
    "iso:country":"NP",
    "wof:name":"Bhataregaun",
    "wof:placetype":"locality"
},
  "geometry": {"coordinates":[85.69377,27.53973],"type":"Point"}
}