{
  "type": "Feature",
  "properties": {
    "gn:admin1_code":"CR",
    "gn:admin2_code":"5",
    "gn:admin3_code":"21",
    "gn:admin4_code":"210022",
    "gn:asciiname":"Sagutar",
    "gn:country_code":"NP",
    "gn:dem":1012,
    "gn:feature_class":"P",
    "gn:feature_code":"PPLL",
    "gn:name":"Sagutar",
    "gn:population":0,
    "gn:timezone":"Asia/Kathmandu",
    "iso:country":"NP",
    "wof:name":"Sagutar",
    "wof:placetype":"locality"
},
  "geometry": {"coordinates":[85.8417,27.51377],"type":"Point"}
}