{
  "type": "Feature",
  "properties": {
    "gn:admin1_code":"ER",
    "gn:admin2_code":"13",
    "gn:admin3_code":"11",
    "gn:admin4_code":"110027",
    "gn:asciiname":"Ghurmise",
    "gn:country_code":"NP",
    "gn:dem":2460,
    "gn:feature_class":"P",
    "gn:feature_code":"PPLL",
    "gn:name":"Ghurmise",
    "gn:population":0,
    "gn:timezone":"Asia/Kathmandu",
    "iso:country":"NP",
    "wof:name":"Ghurmise",
    "wof:placetype":"locality"
},
  "geometry": {"coordinates":[86.64086,27.45016],"type":"Point"}
}