{
  "type": "Feature",
  "properties": {
    "gn:admin1_code":"MR",
    "gn:admin2_code":"2",
    "gn:admin3_code":"61.0",
    "gn:admin4_code":"610003.0",
    "gn:asciiname":"Kamigaun",
    "gn:country_code":"NP",
    "gn:dem":1305,
    "gn:feature_class":"P",
    "gn:feature_code":"PPLL",
    "gn:name":"Kamigaun",
    "gn:population":0,
    "gn:timezone":"Asia/Kathmandu",
    "iso:country":"NP",
    "wof:name":"Kamigaun",
    "wof:placetype":"locality"
},
  "geometry": {"coordinates":[82.13506,28.66917],"type":"Point"}
}