{
  "type": "Feature",
  "properties": {
    "gn:admin1_code":"CR",
    "gn:admin2_code":"5",
    "gn:admin3_code":"21",
    "gn:admin4_code":"210015",
    "gn:asciiname":"Okhreni",
    "gn:country_code":"NP",
    "gn:dem":1948,
    "gn:feature_class":"P",
    "gn:feature_code":"PPLL",
    "gn:name":"Okhreni",
    "gn:population":0,
    "gn:timezone":"Asia/Kathmandu",
    "iso:country":"NP",
    "wof:name":"Okhreni",
    "wof:placetype":"locality"
},
  "geometry": {"coordinates":[85.94525,27.5391],"type":"Point"}
}