{
  "type": "Feature",
  "properties": {
    "gn:admin1_code":"00",
    "gn:asciiname":"Byase",
    "gn:country_code":"NP",
    "gn:dem":1681,
    "gn:feature_class":"P",
    "gn:feature_code":"PPL",
    "gn:name":"By\u0101\u0303se",
    "gn:population":0,
    "gn:timezone":"Asia/Kathmandu",
    "iso:country":"NP",
    "name:nep_x_preferred":[
        "By\u0101nse"
    ],
    "name:und_x_variant":[
        "By\u0101\u0303se"
    ],
    "wof:name":"Byase",
    "wof:placetype":"locality"
},
  "geometry": {"coordinates":[85.82415999999998,27.78274],"type":"Point"}
}