{
  "type": "Feature",
  "properties": {
    "gn:admin1_code":"CR",
    "gn:admin2_code":"5",
    "gn:admin3_code":"19",
    "gn:admin4_code":"190081",
    "gn:asciiname":"Kismatpur",
    "gn:country_code":"NP",
    "gn:dem":117,
    "gn:feature_class":"P",
    "gn:feature_code":"PPLL",
    "gn:name":"Kismatpur",
    "gn:population":0,
    "gn:timezone":"Asia/Kathmandu",
    "iso:country":"NP",
    "wof:name":"Kismatpur",
    "wof:placetype":"locality"
},
  "geometry": {"coordinates":[85.46120999999999,27.07086],"type":"Point"}
}