{
  "type": "Feature",
  "properties": {
    "gn:admin1_code":"ER",
    "gn:admin2_code":"10.0",
    "gn:admin3_code":"1.0",
    "gn:admin4_code":"10032.0",
    "gn:asciiname":"Batase",
    "gn:country_code":"NP",
    "gn:dem":2183,
    "gn:feature_class":"P",
    "gn:feature_code":"PPLL",
    "gn:name":"Batase",
    "gn:population":0,
    "gn:timezone":"Asia/Kathmandu",
    "iso:country":"NP",
    "name:ceb_x_preferred":[
        "Batase"
    ],
    "name:pol_x_preferred":[
        "Batase"
    ],
    "wof:name":"Batase",
    "wof:placetype":"locality"
},
  "geometry": {"coordinates":[87.69095,27.35771],"type":"Point"}
}