{
  "type": "Feature",
  "properties": {
    "gn:admin1_code":"ER",
    "gn:admin2_code":"13",
    "gn:admin3_code":"15",
    "gn:admin4_code":"150042",
    "gn:asciiname":"Laksmipur",
    "gn:country_code":"NP",
    "gn:dem":74,
    "gn:feature_class":"P",
    "gn:feature_code":"PPLL",
    "gn:name":"Laksmipur",
    "gn:population":0,
    "gn:timezone":"Asia/Kathmandu",
    "iso:country":"NP",
    "wof:name":"Laksmipur",
    "wof:placetype":"locality"
},
  "geometry": {"coordinates":[86.87778,26.4617],"type":"Point"}
}