{
  "type": "Feature",
  "properties": {
    "gn:admin1_code":"WR",
    "gn:admin2_code":"8",
    "gn:admin3_code":"51.0",
    "gn:admin4_code":"510028.0",
    "gn:asciiname":"Ghaskhola Gaun",
    "gn:country_code":"NP",
    "gn:dem":1013,
    "gn:feature_class":"P",
    "gn:feature_code":"PPLL",
    "gn:name":"Ghaskhola Gaun",
    "gn:population":0,
    "gn:timezone":"Asia/Kathmandu",
    "iso:country":"NP",
    "wof:name":"Ghaskhola Gaun",
    "wof:placetype":"locality"
},
  "geometry": {"coordinates":[83.24294,27.89989000000001],"type":"Point"}
}