{
  "type": "Feature",
  "properties": {
    "gn:admin1_code":"WR",
    "gn:admin2_code":"8",
    "gn:admin3_code":"51.0",
    "gn:admin4_code":"510017.0",
    "gn:asciiname":"Bande",
    "gn:country_code":"NP",
    "gn:dem":1822,
    "gn:feature_class":"P",
    "gn:feature_code":"PPLL",
    "gn:name":"Bande",
    "gn:population":0,
    "gn:timezone":"Asia/Kathmandu",
    "iso:country":"NP",
    "wof:name":"Bande",
    "wof:placetype":"locality"
},
  "geometry": {"coordinates":[83.00905999999998,28.07593],"type":"Point"}
}