{
  "type": "Feature",
  "properties": {
    "gn:admin1_code":"ER",
    "gn:admin2_code":"7",
    "gn:admin3_code":"10.0",
    "gn:admin4_code":"100029.0",
    "gn:asciiname":"Phosretar",
    "gn:country_code":"NP",
    "gn:dem":655,
    "gn:feature_class":"P",
    "gn:feature_code":"PPLL",
    "gn:name":"Phosretar",
    "gn:population":0,
    "gn:timezone":"Asia/Kathmandu",
    "iso:country":"NP",
    "wof:name":"Phosretar",
    "wof:placetype":"locality"
},
  "geometry": {"coordinates":[87.22253000000001,27.11587],"type":"Point"}
}