{
  "type": "Feature",
  "properties": {
    "gn:admin1_code":"CR",
    "gn:admin2_code":"11",
    "gn:admin3_code":"35.0",
    "gn:admin4_code":"350027.0",
    "gn:asciiname":"Dadrahani",
    "gn:country_code":"NP",
    "gn:dem":152,
    "gn:feature_class":"P",
    "gn:feature_code":"PPLL",
    "gn:name":"Dadrahani",
    "gn:population":0,
    "gn:timezone":"Asia/Kathmandu",
    "iso:country":"NP",
    "wof:name":"Dadrahani",
    "wof:placetype":"locality"
},
  "geometry": {"coordinates":[84.20860999999999,27.59507],"type":"Point"}
}