{
  "type": "Feature",
  "properties": {
    "gn:admin1_code":"MR",
    "gn:admin2_code":"2",
    "gn:admin3_code":"60.0",
    "gn:admin4_code":"600017.0",
    "gn:asciiname":"Barun",
    "gn:country_code":"NP",
    "gn:dem":972,
    "gn:feature_class":"P",
    "gn:feature_code":"PPLL",
    "gn:name":"Barun",
    "gn:population":0,
    "gn:timezone":"Asia/Kathmandu",
    "iso:country":"NP",
    "wof:name":"Barun",
    "wof:placetype":"locality"
},
  "geometry": {"coordinates":[81.65867,28.76859],"type":"Point"}
}