{
  "type": "Feature",
  "properties": {
    "gn:admin1_code":"ER",
    "gn:admin2_code":"10",
    "gn:admin3_code":"4.0",
    "gn:admin4_code":"40048.0",
    "gn:asciiname":"Tallo Chapramari",
    "gn:country_code":"NP",
    "gn:dem":100,
    "gn:feature_class":"P",
    "gn:feature_code":"PPLL",
    "gn:name":"Tallo Chapramari",
    "gn:population":0,
    "gn:timezone":"Asia/Kathmandu",
    "iso:country":"NP",
    "wof:name":"Tallo Chapramari",
    "wof:placetype":"locality"
},
  "geometry": {"coordinates":[87.89667,26.57972],"type":"Point"}
}