{
  "type": "Feature",
  "properties": {
    "gn:admin1_code":"ER",
    "gn:admin2_code":"10",
    "gn:admin3_code":"3.0",
    "gn:admin4_code":"30015.0",
    "gn:asciiname":"Puwajung",
    "gn:country_code":"NP",
    "gn:dem":581,
    "gn:feature_class":"P",
    "gn:feature_code":"PPLL",
    "gn:name":"Puwajung",
    "gn:population":0,
    "gn:timezone":"Asia/Kathmandu",
    "iso:country":"NP",
    "wof:name":"Puwajung",
    "wof:placetype":"locality"
},
  "geometry": {"coordinates":[87.90671999999998,26.86809],"type":"Point"}
}