{
  "type": "Feature",
  "properties": {
    "gn:admin1_code":"WR",
    "gn:admin2_code":"8",
    "gn:admin3_code":"51.0",
    "gn:admin4_code":"510032.0",
    "gn:asciiname":"Pali",
    "gn:country_code":"NP",
    "gn:dem":1067,
    "gn:feature_class":"P",
    "gn:feature_code":"PPLL",
    "gn:name":"Pali",
    "gn:population":0,
    "gn:timezone":"Asia/Kathmandu",
    "iso:country":"NP",
    "name:bih_x_preferred":[
        "\u092a\u093e\u0932\u0940 \u0917\u093e\u0935\u093f\u0938"
    ],
    "name:hin_x_preferred":[
        "\u092a\u0932\u0940"
    ],
    "name:mai_x_preferred":[
        "\u092a\u093e\u0932\u0940 \u0917\u093e\u0935\u093f\u0938"
    ],
    "name:msa_x_preferred":[
        "Pali"
    ],
    "name:nep_x_preferred":[
        "\u092a\u093e\u0932\u0940 \u0917\u093e\u0935\u093f\u0938"
    ],
    "name:new_x_preferred":[
        "\u092a\u0932\u0940"
    ],
    "name:pol_x_preferred":[
        "Pali"
    ],
    "wof:name":"Pali",
    "wof:placetype":"locality"
},
  "geometry": {"coordinates":[83.21562,27.93213],"type":"Point"}
}