{
  "type": "Feature",
  "properties": {
    "gn:admin1_code":"ER",
    "gn:admin2_code":"10",
    "gn:admin3_code":"3.0",
    "gn:admin4_code":"30010.0",
    "gn:asciiname":"Nabugaun",
    "gn:country_code":"NP",
    "gn:dem":766,
    "gn:feature_class":"P",
    "gn:feature_code":"PPLL",
    "gn:name":"Nabugaun",
    "gn:population":0,
    "gn:timezone":"Asia/Kathmandu",
    "iso:country":"NP",
    "wof:name":"Nabugaun",
    "wof:placetype":"locality"
},
  "geometry": {"coordinates":[87.77899000000002,26.93173],"type":"Point"}
}