{
  "type": "Feature",
  "properties": {
    "gn:admin1_code":"CR",
    "gn:admin2_code":"1",
    "gn:admin3_code":"28",
    "gn:admin4_code":"280012",
    "gn:asciiname":"Tareli",
    "gn:country_code":"NP",
    "gn:dem":840,
    "gn:feature_class":"P",
    "gn:feature_code":"PPLL",
    "gn:name":"Tareli",
    "gn:population":0,
    "gn:timezone":"Asia/Kathmandu",
    "iso:country":"NP",
    "wof:name":"Tareli",
    "wof:placetype":"locality"
},
  "geometry": {"coordinates":[85.21453000000002,27.86658],"type":"Point"}
}