{
  "type": "Feature",
  "properties": {
    "gn:admin1_code":"MR",
    "gn:admin2_code":"12",
    "gn:admin3_code":"56.0",
    "gn:admin4_code":"560037.0",
    "gn:asciiname":"Tusarpani",
    "gn:country_code":"NP",
    "gn:dem":1396,
    "gn:feature_class":"P",
    "gn:feature_code":"PPLL",
    "gn:name":"Tusarpani",
    "gn:population":0,
    "gn:timezone":"Asia/Kathmandu",
    "iso:country":"NP",
    "wof:name":"Tusarpani",
    "wof:placetype":"locality"
},
  "geometry": {"coordinates":[82.60732,28.06249],"type":"Point"}
}