{
  "type": "Feature",
  "properties": {
    "gn:admin1_code":"CR",
    "gn:admin2_code":"11",
    "gn:admin3_code":"35.0",
    "gn:admin4_code":"350033.0",
    "gn:asciiname":"Parsauni",
    "gn:country_code":"NP",
    "gn:dem":202,
    "gn:feature_class":"P",
    "gn:feature_code":"PPLL",
    "gn:name":"Parsauni",
    "gn:population":0,
    "gn:timezone":"Asia/Kathmandu",
    "iso:country":"NP",
    "name:msa_x_preferred":[
        "Parsauni"
    ],
    "name:nep_x_preferred":[
        "\u092a\u0938\u094c\u0930\u0928\u0940"
    ],
    "name:new_x_preferred":[
        "\u092a\u0930\u094d\u0938\u094c\u0928\u0940"
    ],
    "name:pol_x_preferred":[
        "Parsauni"
    ],
    "wof:name":"Parsauni",
    "wof:placetype":"locality"
},
  "geometry": {"coordinates":[84.51005000000001,27.63078],"type":"Point"}
}