{
  "type": "Feature",
  "properties": {
    "gn:admin1_code":"ER",
    "gn:admin2_code":"7",
    "gn:admin3_code":"5",
    "gn:admin4_code":"50065",
    "gn:asciiname":"Kerabari",
    "gn:country_code":"NP",
    "gn:dem":1339,
    "gn:feature_class":"P",
    "gn:feature_code":"PPLL",
    "gn:name":"Kerabari",
    "gn:population":0,
    "gn:timezone":"Asia/Kathmandu",
    "iso:country":"NP",
    "wof:name":"Kerabari",
    "wof:placetype":"locality"
},
  "geometry": {"coordinates":[87.54959000000002,26.84119],"type":"Point"}
}