{
  "type": "Feature",
  "properties": {
    "gn:admin1_code":"MR",
    "gn:admin2_code":"6",
    "gn:admin3_code":"65",
    "gn:admin4_code":"650002",
    "gn:asciiname":"Loli",
    "gn:country_code":"NP",
    "gn:dem":2336,
    "gn:feature_class":"P",
    "gn:feature_code":"PPLL",
    "gn:name":"Loli",
    "gn:population":0,
    "gn:timezone":"Asia/Kathmandu",
    "iso:country":"NP",
    "name:ceb_x_preferred":[
        "Loli"
    ],
    "name:deu_x_preferred":[
        "Loli"
    ],
    "name:ind_x_preferred":[
        "Loli"
    ],
    "name:nor_x_preferred":[
        "Loli"
    ],
    "name:por_x_preferred":[
        "Loli"
    ],
    "name:swe_x_preferred":[
        "Loli"
    ],
    "name:vie_x_preferred":[
        "Loli"
    ],
    "wof:name":"Loli",
    "wof:placetype":"locality"
},
  "geometry": {"coordinates":[81.86405000000001,29.58872],"type":"Point"}
}