{
  "type": "Feature",
  "properties": {
    "gn:admin1_code":"CR",
    "gn:admin2_code":"11",
    "gn:admin3_code":"35.0",
    "gn:admin4_code":"350035.0",
    "gn:asciiname":"Kalikasthan",
    "gn:country_code":"NP",
    "gn:dem":279,
    "gn:feature_class":"P",
    "gn:feature_code":"PPLL",
    "gn:name":"Kalikasthan",
    "gn:population":0,
    "gn:timezone":"Asia/Kathmandu",
    "iso:country":"NP",
    "name:fra_x_preferred":[
        "Kalikasthan"
    ],
    "name:new_x_preferred":[
        "\u0915\u093e\u0932\u093f\u0915\u093e\u0938\u094d\u0925\u093e\u0928"
    ],
    "name:pol_x_preferred":[
        "Kalikasthan"
    ],
    "wof:name":"Kalikasthan",
    "wof:placetype":"locality"
},
  "geometry": {"coordinates":[84.56814,27.69757],"type":"Point"}
}