{
  "type": "Feature",
  "properties": {
    "gn:admin1_code":"WR",
    "gn:admin2_code":"4",
    "gn:admin3_code":"41",
    "gn:admin4_code":"410011",
    "gn:asciiname":"Mathillo Dharapanee",
    "gn:country_code":"NP",
    "gn:dem":1916,
    "gn:feature_class":"P",
    "gn:feature_code":"PPLL",
    "gn:name":"Mathillo Dharapanee",
    "gn:population":0,
    "gn:timezone":"Asia/Kathmandu",
    "iso:country":"NP",
    "wof:name":"Mathillo Dharapanee",
    "wof:placetype":"locality"
},
  "geometry": {"coordinates":[84.35595000000001,28.52612],"type":"Point"}
}