{
  "type": "Feature",
  "properties": {
    "gn:admin1_code":"CR",
    "gn:admin2_code":"11",
    "gn:admin3_code":"32",
    "gn:admin4_code":"320019",
    "gn:asciiname":"Tekantol",
    "gn:country_code":"NP",
    "gn:dem":139,
    "gn:feature_class":"P",
    "gn:feature_code":"PPLL",
    "gn:name":"Tekantol",
    "gn:population":0,
    "gn:timezone":"Asia/Kathmandu",
    "iso:country":"NP",
    "wof:name":"Tekantol",
    "wof:placetype":"locality"
},
  "geometry": {"coordinates":[85.36131,27.13082],"type":"Point"}
}