{
  "type": "Feature",
  "properties": {
    "gn:admin1_code":"CR",
    "gn:admin2_code":"11",
    "gn:admin3_code":"32",
    "gn:admin4_code":"320010",
    "gn:asciiname":"Namnagada",
    "gn:country_code":"NP",
    "gn:dem":82,
    "gn:feature_class":"P",
    "gn:feature_code":"PPLL",
    "gn:name":"Namnagada",
    "gn:population":0,
    "gn:timezone":"Asia/Kathmandu",
    "iso:country":"NP",
    "wof:name":"Namnagada",
    "wof:placetype":"locality"
},
  "geometry": {"coordinates":[85.23354,26.84123],"type":"Point"}
}