{
  "type": "Feature",
  "properties": {
    "gn:admin1_code":"FR",
    "gn:admin2_code":"14.0",
    "gn:admin3_code":"69.0",
    "gn:admin4_code":"690054.0",
    "gn:asciiname":"Bagdula",
    "gn:country_code":"NP",
    "gn:dem":1233,
    "gn:feature_class":"P",
    "gn:feature_code":"PPLL",
    "gn:name":"Bagdula",
    "gn:population":0,
    "gn:timezone":"Asia/Kathmandu",
    "iso:country":"NP",
    "wof:name":"Bagdula",
    "wof:placetype":"locality"
},
  "geometry": {"coordinates":[81.28319,29.12769],"type":"Point"}
}