{
  "type": "Feature",
  "properties": {
    "gn:admin1_code":"WR",
    "gn:admin2_code":"8",
    "gn:admin3_code":"47",
    "gn:admin4_code":"470060",
    "gn:asciiname":"Somadi",
    "gn:country_code":"NP",
    "gn:dem":1167,
    "gn:feature_class":"P",
    "gn:feature_code":"PPLL",
    "gn:name":"Somadi",
    "gn:population":0,
    "gn:timezone":"Asia/Kathmandu",
    "iso:country":"NP",
    "wof:name":"Somadi",
    "wof:placetype":"locality"
},
  "geometry": {"coordinates":[83.38735,27.90703],"type":"Point"}
}