{
  "type": "Feature",
  "properties": {
    "gn:admin1_code":"MR",
    "gn:admin2_code":"2.0",
    "gn:admin3_code":"59.0",
    "gn:admin4_code":"590044.0",
    "gn:asciiname":"Mathillo Rahakul",
    "gn:country_code":"NP",
    "gn:dem":1541,
    "gn:feature_class":"P",
    "gn:feature_code":"PPLL",
    "gn:name":"Mathillo Rahakul",
    "gn:population":0,
    "gn:timezone":"Asia/Kathmandu",
    "iso:country":"NP",
    "wof:name":"Mathillo Rahakul",
    "wof:placetype":"locality"
},
  "geometry": {"coordinates":[81.87698,28.61102],"type":"Point"}
}