{
  "type": "Feature",
  "properties": {
    "gn:admin1_code":"ER",
    "gn:admin2_code":"10",
    "gn:admin3_code":"3.0",
    "gn:admin4_code":"30004.0",
    "gn:asciiname":"Kusedanda",
    "gn:country_code":"NP",
    "gn:dem":1646,
    "gn:feature_class":"P",
    "gn:feature_code":"PPLL",
    "gn:name":"Kusedanda",
    "gn:population":0,
    "gn:timezone":"Asia/Kathmandu",
    "iso:country":"NP",
    "wof:name":"Kusedanda",
    "wof:placetype":"locality"
},
  "geometry": {"coordinates":[87.80855,27.01411],"type":"Point"}
}