{
  "type": "Feature",
  "properties": {
    "gn:admin1_code":"CR",
    "gn:admin2_code":"1",
    "gn:admin3_code":"30.0",
    "gn:admin4_code":"300040.0",
    "gn:asciiname":"Bhirswanra",
    "gn:country_code":"NP",
    "gn:dem":1014,
    "gn:feature_class":"P",
    "gn:feature_code":"PPLL",
    "gn:name":"Bhirswanra",
    "gn:population":0,
    "gn:timezone":"Asia/Kathmandu",
    "iso:country":"NP",
    "wof:name":"Bhirswanra",
    "wof:placetype":"locality"
},
  "geometry": {"coordinates":[84.90899999999998,28.02521],"type":"Point"}
}