{
  "type": "Feature",
  "properties": {
    "gn:admin1_code":"CR",
    "gn:admin2_code":"11",
    "gn:admin3_code":"31",
    "gn:admin4_code":"310005",
    "gn:asciiname":"Okhledanda",
    "gn:country_code":"NP",
    "gn:dem":840,
    "gn:feature_class":"P",
    "gn:feature_code":"PPLL",
    "gn:name":"Okhledanda",
    "gn:population":0,
    "gn:timezone":"Asia/Kathmandu",
    "iso:country":"NP",
    "wof:name":"Okhledanda",
    "wof:placetype":"locality"
},
  "geometry": {"coordinates":[85.37201,27.41346],"type":"Point"}
}