{
  "type": "Feature",
  "properties": {
    "gn:admin1_code":"MR",
    "gn:admin2_code":"2",
    "gn:admin3_code":"60.0",
    "gn:admin4_code":"600004.0",
    "gn:asciiname":"Ghiyatidu",
    "gn:country_code":"NP",
    "gn:dem":1324,
    "gn:feature_class":"P",
    "gn:feature_code":"PPLL",
    "gn:name":"Ghiyatidu",
    "gn:population":0,
    "gn:timezone":"Asia/Kathmandu",
    "iso:country":"NP",
    "wof:name":"Ghiyatidu",
    "wof:placetype":"locality"
},
  "geometry": {"coordinates":[81.61211,28.88356],"type":"Point"}
}