{
  "type": "Feature",
  "properties": {
    "gn:admin1_code":"ER",
    "gn:admin2_code":"13",
    "gn:admin3_code":"13",
    "gn:admin4_code":"130073",
    "gn:asciiname":"Mabugaira",
    "gn:country_code":"NP",
    "gn:dem":1197,
    "gn:feature_class":"P",
    "gn:feature_code":"PPLL",
    "gn:name":"Mabugaira",
    "gn:population":0,
    "gn:timezone":"Asia/Kathmandu",
    "iso:country":"NP",
    "wof:name":"Mabugaira",
    "wof:placetype":"locality"
},
  "geometry": {"coordinates":[86.80181999999998,27.14602],"type":"Point"}
}