{
  "type": "Feature",
  "properties": {
    "gn:admin1_code":"ER",
    "gn:admin2_code":"13",
    "gn:admin3_code":"13",
    "gn:admin4_code":"130047",
    "gn:asciiname":"Andheri",
    "gn:country_code":"NP",
    "gn:dem":1738,
    "gn:feature_class":"P",
    "gn:feature_code":"PPLL",
    "gn:name":"Andheri",
    "gn:population":0,
    "gn:timezone":"Asia/Kathmandu",
    "iso:country":"NP",
    "wof:name":"Andheri",
    "wof:placetype":"locality"
},
  "geometry": {"coordinates":[86.95614,27.06414],"type":"Point"}
}