{
  "type": "Feature",
  "properties": {
    "gn:admin1_code":"WR",
    "gn:admin2_code":"8",
    "gn:admin3_code":"46.0",
    "gn:admin4_code":"460079.0",
    "gn:asciiname":"Wami Taksar",
    "gn:country_code":"NP",
    "gn:dem":872,
    "gn:feature_class":"P",
    "gn:feature_code":"PPLL",
    "gn:name":"Wami Taksar",
    "gn:population":0,
    "gn:timezone":"Asia/Kathmandu",
    "iso:country":"NP",
    "name:ceb_x_preferred":[
        "Wamitaksar"
    ],
    "name:fra_x_preferred":[
        "Wamitaksar"
    ],
    "name:mai_x_preferred":[
        "\u0935\u093e\u092e\u0940\u091f\u0915\u094d\u0938\u093e\u0930"
    ],
    "name:msa_x_preferred":[
        "Wamitaksar"
    ],
    "name:nep_x_preferred":[
        "\u0935\u093e\u092e\u0940\u091f\u0915\u094d\u0938\u093e\u0930"
    ],
    "name:new_x_preferred":[
        "\u0935\u093e\u092e\u093f\u091f\u0915\u094d\u0938\u093e\u0930"
    ],
    "name:pol_x_preferred":[
        "Wamitaksar"
    ],
    "wof:name":"Wami Taksar",
    "wof:placetype":"locality"
},
  "geometry": {"coordinates":[83.28523,28.18447],"type":"Point"}
}