{
  "type": "Feature",
  "properties": {
    "gn:admin1_code":"FR",
    "gn:admin2_code":"9",
    "gn:admin3_code":"73.0",
    "gn:admin4_code":"730004.0",
    "gn:asciiname":"Chira",
    "gn:country_code":"NP",
    "gn:dem":1348,
    "gn:feature_class":"P",
    "gn:feature_code":"PPLL",
    "gn:name":"Chira",
    "gn:population":0,
    "gn:timezone":"Asia/Kathmandu",
    "iso:country":"NP",
    "wof:name":"Chira",
    "wof:placetype":"locality"
},
  "geometry": {"coordinates":[80.66331,29.24843],"type":"Point"}
}