{
  "type": "Feature",
  "properties": {
    "gn:admin1_code":"CR",
    "gn:admin2_code":"5",
    "gn:admin3_code":"17.0",
    "gn:admin4_code":"170039.0",
    "gn:asciiname":"Eklejamuna",
    "gn:country_code":"NP",
    "gn:dem":298,
    "gn:feature_class":"P",
    "gn:feature_code":"PPLL",
    "gn:name":"Eklejamuna",
    "gn:population":0,
    "gn:timezone":"Asia/Kathmandu",
    "iso:country":"NP",
    "wof:name":"Eklejamuna",
    "wof:placetype":"locality"
},
  "geometry": {"coordinates":[86.34093,26.90254],"type":"Point"}
}