{
  "type": "Feature",
  "properties": {
    "gn:admin1_code":"ER",
    "gn:admin2_code":"10.0",
    "gn:admin3_code":"1.0",
    "gn:admin4_code":"10036.0",
    "gn:asciiname":"Ghattepari",
    "gn:country_code":"NP",
    "gn:dem":1951,
    "gn:feature_class":"P",
    "gn:feature_code":"PPLL",
    "gn:name":"Ghattepari",
    "gn:population":0,
    "gn:timezone":"Asia/Kathmandu",
    "iso:country":"NP",
    "wof:name":"Ghattepari",
    "wof:placetype":"locality"
},
  "geometry": {"coordinates":[87.59209,27.40616],"type":"Point"}
}