{
  "type": "Feature",
  "properties": {
    "gn:admin1_code":"MR",
    "gn:admin2_code":"6",
    "gn:admin3_code":"63.0",
    "gn:admin4_code":"630023.0",
    "gn:asciiname":"Nainalmadu",
    "gn:country_code":"NP",
    "gn:dem":2617,
    "gn:feature_class":"P",
    "gn:feature_code":"PPLL",
    "gn:name":"Nainalmadu",
    "gn:population":0,
    "gn:timezone":"Asia/Kathmandu",
    "iso:country":"NP",
    "wof:name":"Nainalmadu",
    "wof:placetype":"locality"
},
  "geometry": {"coordinates":[81.99150999999998,29.32408],"type":"Point"}
}