{
  "type": "Feature",
  "properties": {
    "gn:admin1_code":"WR",
    "gn:admin2_code":"4.0",
    "gn:admin3_code":"39.0",
    "gn:admin4_code":"390024.0",
    "gn:asciiname":"Tallo Galyang  Bajar",
    "gn:country_code":"NP",
    "gn:dem":739,
    "gn:feature_class":"P",
    "gn:feature_code":"PPLL",
    "gn:name":"Tallo Galyang  Bajar",
    "gn:population":0,
    "gn:timezone":"Asia/Kathmandu",
    "iso:country":"NP",
    "wof:name":"Tallo Galyang Bajar",
    "wof:placetype":"locality"
},
  "geometry": {"coordinates":[83.67925,27.94637],"type":"Point"}
}