{
  "type": "Feature",
  "properties": {
    "gn:admin1_code":"WR",
    "gn:admin2_code":"3",
    "gn:admin3_code":"45.0",
    "gn:admin4_code":"450042.0",
    "gn:asciiname":"Theule",
    "gn:country_code":"NP",
    "gn:dem":1088,
    "gn:feature_class":"P",
    "gn:feature_code":"PPLL",
    "gn:name":"Theule",
    "gn:population":0,
    "gn:timezone":"Asia/Kathmandu",
    "iso:country":"NP",
    "wof:name":"Theule",
    "wof:placetype":"locality"
},
  "geometry": {"coordinates":[83.58539,28.16849],"type":"Point"}
}