{
  "type": "Feature",
  "properties": {
    "gn:admin1_code":"WR",
    "gn:admin2_code":"3",
    "gn:admin3_code":"45.0",
    "gn:admin4_code":"450018.0",
    "gn:asciiname":"Bhuwane",
    "gn:country_code":"NP",
    "gn:dem":2169,
    "gn:feature_class":"P",
    "gn:feature_code":"PPLL",
    "gn:name":"Bhuwane",
    "gn:population":0,
    "gn:timezone":"Asia/Kathmandu",
    "iso:country":"NP",
    "wof:name":"Bhuwane",
    "wof:placetype":"locality"
},
  "geometry": {"coordinates":[83.54191,28.21223],"type":"Point"}
}