{
  "type": "Feature",
  "properties": {
    "gn:admin1_code":"MR",
    "gn:admin2_code":"6",
    "gn:admin3_code":"63.0",
    "gn:admin4_code":"630026.0",
    "gn:asciiname":"Thingke",
    "gn:country_code":"NP",
    "gn:dem":2534,
    "gn:feature_class":"P",
    "gn:feature_code":"PPLL",
    "gn:name":"Thingke",
    "gn:population":0,
    "gn:timezone":"Asia/Kathmandu",
    "iso:country":"NP",
    "wof:name":"Thingke",
    "wof:placetype":"locality"
},
  "geometry": {"coordinates":[82.22804000000002,29.30039],"type":"Point"}
}