{
  "type": "Feature",
  "properties": {
    "gn:admin1_code":"CR",
    "gn:admin2_code":"1",
    "gn:admin3_code":"30.0",
    "gn:admin4_code":"300027.0",
    "gn:asciiname":"Chhurmrang",
    "gn:country_code":"NP",
    "gn:dem":1437,
    "gn:feature_class":"P",
    "gn:feature_code":"PPLL",
    "gn:name":"Chhurmrang",
    "gn:population":0,
    "gn:timezone":"Asia/Kathmandu",
    "iso:country":"NP",
    "wof:name":"Chhurmrang",
    "wof:placetype":"locality"
},
  "geometry": {"coordinates":[85.03864,28.14697],"type":"Point"}
}