{
  "type": "Feature",
  "properties": {
    "gn:admin1_code":"00",
    "gn:asciiname":"Dhung",
    "gn:country_code":"NP",
    "gn:dem":1604,
    "gn:feature_class":"P",
    "gn:feature_code":"PPL",
    "gn:name":"Dhung",
    "gn:population":0,
    "gn:timezone":"Asia/Kathmandu",
    "iso:country":"NP",
    "wof:name":"Dhung",
    "wof:placetype":"locality"
},
  "geometry": {"coordinates":[80.75100999999999,29.60693],"type":"Point"}
}