{
  "type": "Feature",
  "properties": {
    "gn:admin1_code":"CR",
    "gn:admin2_code":"1",
    "gn:admin3_code":"23",
    "gn:admin4_code":"230078",
    "gn:asciiname":"Dadapakhar",
    "gn:country_code":"NP",
    "gn:dem":1319,
    "gn:feature_class":"P",
    "gn:feature_code":"PPLL",
    "gn:name":"Dadapakhar",
    "gn:population":0,
    "gn:timezone":"Asia/Kathmandu",
    "iso:country":"NP",
    "wof:name":"Dadapakhar",
    "wof:placetype":"locality"
},
  "geometry": {"coordinates":[85.83435,27.72059],"type":"Point"}
}