{
  "type": "Feature",
  "properties": {
    "gn:admin1_code":"CR",
    "gn:admin2_code":"5",
    "gn:admin3_code":"22.0",
    "gn:admin4_code":"220044.0",
    "gn:asciiname":"Dobate",
    "gn:country_code":"NP",
    "gn:dem":1161,
    "gn:feature_class":"P",
    "gn:feature_code":"PPLL",
    "gn:name":"Dobate",
    "gn:population":0,
    "gn:timezone":"Asia/Kathmandu",
    "iso:country":"NP",
    "wof:name":"Dobate",
    "wof:placetype":"locality"
},
  "geometry": {"coordinates":[86.07386,27.58719],"type":"Point"}
}