{
  "type": "Feature",
  "properties": {
    "gn:admin1_code":"FR",
    "gn:admin2_code":"14",
    "gn:admin3_code":"71.0",
    "gn:admin4_code":"710006.0",
    "gn:asciiname":"Bahunpura",
    "gn:country_code":"NP",
    "gn:dem":187,
    "gn:feature_class":"P",
    "gn:feature_code":"PPLL",
    "gn:name":"Bahunpura",
    "gn:population":0,
    "gn:timezone":"Asia/Kathmandu",
    "iso:country":"NP",
    "wof:name":"Bahunpura",
    "wof:placetype":"locality"
},
  "geometry": {"coordinates":[81.12634,28.66166],"type":"Point"}
}