{
  "type": "Feature",
  "properties": {
    "gn:admin1_code":"MR",
    "gn:admin2_code":"12",
    "gn:admin3_code":"53",
    "gn:admin4_code":"530035",
    "gn:asciiname":"Kaphal Pokhari",
    "gn:country_code":"NP",
    "gn:dem":2005,
    "gn:feature_class":"P",
    "gn:feature_code":"PPLL",
    "gn:name":"Kaphal Pokhari",
    "gn:population":0,
    "gn:timezone":"Asia/Kathmandu",
    "iso:country":"NP",
    "wof:name":"Kaphal Pokhari",
    "wof:placetype":"locality"
},
  "geometry": {"coordinates":[82.52106999999999,28.52318],"type":"Point"}
}