{
  "type": "Feature",
  "properties": {
    "gn:admin1_code":"FR",
    "gn:admin2_code":"14",
    "gn:admin3_code":"70.0",
    "gn:admin4_code":"700052.0",
    "gn:asciiname":"Lampuchhre",
    "gn:country_code":"NP",
    "gn:dem":3054,
    "gn:feature_class":"P",
    "gn:feature_code":"PPLL",
    "gn:name":"Lampuchhre",
    "gn:population":0,
    "gn:timezone":"Asia/Kathmandu",
    "iso:country":"NP",
    "wof:name":"Lampuchhre",
    "wof:placetype":"locality"
},
  "geometry": {"coordinates":[81.12888000000002,29.3979],"type":"Point"}
}