{
  "type": "Feature",
  "properties": {
    "gn:admin1_code":"CR",
    "gn:admin2_code":"5",
    "gn:admin3_code":"19",
    "gn:admin4_code":"190016",
    "gn:asciiname":"Bhandsar",
    "gn:country_code":"NP",
    "gn:dem":85,
    "gn:feature_class":"P",
    "gn:feature_code":"PPLL",
    "gn:name":"Bhandsar",
    "gn:population":0,
    "gn:timezone":"Asia/Kathmandu",
    "iso:country":"NP",
    "wof:name":"Bhandsar",
    "wof:placetype":"locality"
},
  "geometry": {"coordinates":[85.52333,26.81894],"type":"Point"}
}