{
  "type": "Feature",
  "properties": {
    "gn:admin1_code":"WR",
    "gn:admin2_code":"4",
    "gn:admin3_code":"36.0",
    "gn:admin4_code":"360013.0",
    "gn:asciiname":"Nueladajjyen(Mailatasaching)Bhanjyang",
    "gn:country_code":"NP",
    "gn:dem":4867,
    "gn:feature_class":"P",
    "gn:feature_code":"PPLL",
    "gn:name":"Nueladajjyen(Mailatasaching)Bhanjyang",
    "gn:population":0,
    "gn:timezone":"Asia/Kathmandu",
    "iso:country":"NP",
    "wof:name":"Nueladajjyen(Mailatasaching)Bhanjyang",
    "wof:placetype":"locality"
},
  "geometry": {"coordinates":[85.18708000000002,28.61564000000001],"type":"Point"}
}