{
  "type": "Feature",
  "properties": {
    "gn:admin1_code":"FR",
    "gn:admin2_code":"14",
    "gn:admin3_code":"68",
    "gn:admin4_code":"680003",
    "gn:asciiname":"Kadachaud",
    "gn:country_code":"NP",
    "gn:dem":2461,
    "gn:feature_class":"P",
    "gn:feature_code":"PPLL",
    "gn:name":"Kadachaud",
    "gn:population":0,
    "gn:timezone":"Asia/Kathmandu",
    "iso:country":"NP",
    "wof:name":"Kadachaud",
    "wof:placetype":"locality"
},
  "geometry": {"coordinates":[80.93070999999998,29.56266],"type":"Point"}
}