{
  "type": "Feature",
  "properties": {
    "gn:admin1_code":"CR",
    "gn:admin2_code":"1",
    "gn:admin3_code":"28",
    "gn:admin4_code":"280022",
    "gn:asciiname":"Majh Gerkhu",
    "gn:country_code":"NP",
    "gn:dem":1254,
    "gn:feature_class":"P",
    "gn:feature_code":"PPLL",
    "gn:name":"Majh Gerkhu",
    "gn:population":0,
    "gn:timezone":"Asia/Kathmandu",
    "iso:country":"NP",
    "wof:name":"Majh Gerkhu",
    "wof:placetype":"locality"
},
  "geometry": {"coordinates":[85.20424,27.95505],"type":"Point"}
}