{
  "type": "Feature",
  "properties": {
    "gn:admin1_code":"CR",
    "gn:admin2_code":"1",
    "gn:admin3_code":"23",
    "gn:admin4_code":"230029.0",
    "gn:asciiname":"Tartong",
    "gn:country_code":"NP",
    "gn:dem":1892,
    "gn:feature_class":"P",
    "gn:feature_code":"PPLL",
    "gn:name":"Tartong",
    "gn:population":0,
    "gn:timezone":"Asia/Kathmandu",
    "iso:country":"NP",
    "wof:name":"Tartong",
    "wof:placetype":"locality"
},
  "geometry": {"coordinates":[85.52994,27.96271],"type":"Point"}
}