{
  "type": "Feature",
  "properties": {
    "gn:admin1_code":"ER",
    "gn:admin2_code":"10",
    "gn:admin3_code":"3.0",
    "gn:admin4_code":"30033.0",
    "gn:asciiname":"Dharmadwar",
    "gn:country_code":"NP",
    "gn:dem":1683,
    "gn:feature_class":"P",
    "gn:feature_code":"PPLL",
    "gn:name":"Dharmadwar",
    "gn:population":0,
    "gn:timezone":"Asia/Kathmandu",
    "iso:country":"NP",
    "wof:name":"Dharmadwar",
    "wof:placetype":"locality"
},
  "geometry": {"coordinates":[87.75634000000002,27.00658],"type":"Point"}
}