{
  "type": "Feature",
  "properties": {
    "gn:admin1_code":"WR",
    "gn:admin2_code":"3",
    "gn:admin3_code":"44",
    "gn:admin4_code":"440039",
    "gn:asciiname":"Dhanubase",
    "gn:country_code":"NP",
    "gn:dem":1012,
    "gn:feature_class":"P",
    "gn:feature_code":"PPLL",
    "gn:name":"Dhanubase",
    "gn:population":0,
    "gn:timezone":"Asia/Kathmandu",
    "iso:country":"NP",
    "name:msa_x_preferred":[
        "Dhanubase"
    ],
    "wof:name":"Dhanubase",
    "wof:placetype":"locality"
},
  "geometry": {"coordinates":[83.68771,28.09081],"type":"Point"}
}