{
  "type": "Feature",
  "properties": {
    "gn:admin1_code":"00",
    "gn:asciiname":"Temban",
    "gn:country_code":"NP",
    "gn:dem":871,
    "gn:feature_class":"P",
    "gn:feature_code":"PPL",
    "gn:name":"Temb\u0101\u1e45",
    "gn:population":0,
    "gn:timezone":"Asia/Kathmandu",
    "iso:country":"NP",
    "name:nep_x_preferred":[
        "Temb\u0101\u1e45"
    ],
    "wof:name":"Temban",
    "wof:placetype":"locality"
},
  "geometry": {"coordinates":[87.32089000000001,26.90868],"type":"Point"}
}