{
  "type": "Feature",
  "properties": {
    "gn:admin1_code":"MR",
    "gn:admin2_code":"2.0",
    "gn:admin3_code":"57.0",
    "gn:admin4_code":"570047.0",
    "gn:asciiname":"Lodhaigaun",
    "gn:country_code":"NP",
    "gn:dem":148,
    "gn:feature_class":"P",
    "gn:feature_code":"PPLL",
    "gn:name":"Lodhaigaun",
    "gn:population":0,
    "gn:timezone":"Asia/Kathmandu",
    "iso:country":"NP",
    "wof:name":"Lodhaigaun",
    "wof:placetype":"locality"
},
  "geometry": {"coordinates":[81.64558000000002,28.04132],"type":"Point"}
}