{
  "type": "Feature",
  "properties": {
    "gn:admin1_code":"MR",
    "gn:admin2_code":"12",
    "gn:admin3_code":"54",
    "gn:admin4_code":"540028",
    "gn:asciiname":"Badhandanda",
    "gn:country_code":"NP",
    "gn:dem":1432,
    "gn:feature_class":"P",
    "gn:feature_code":"PPLL",
    "gn:name":"Badhandanda",
    "gn:population":0,
    "gn:timezone":"Asia/Kathmandu",
    "iso:country":"NP",
    "wof:name":"Badhandanda",
    "wof:placetype":"locality"
},
  "geometry": {"coordinates":[82.31310999999999,28.61855],"type":"Point"}
}