{
  "type": "Feature",
  "properties": {
    "gn:admin1_code":"FR",
    "gn:admin2_code":"9",
    "gn:admin3_code":"75.0",
    "gn:admin4_code":"750032.0",
    "gn:asciiname":"Malli Sugarkhal",
    "gn:country_code":"NP",
    "gn:dem":1257,
    "gn:feature_class":"P",
    "gn:feature_code":"PPLL",
    "gn:name":"Malli Sugarkhal",
    "gn:population":0,
    "gn:timezone":"Asia/Kathmandu",
    "iso:country":"NP",
    "wof:name":"Malli Sugarkhal",
    "wof:placetype":"locality"
},
  "geometry": {"coordinates":[80.46309000000002,29.66547000000001],"type":"Point"}
}