{
  "type": "Feature",
  "properties": {
    "gn:admin1_code":"ER",
    "gn:admin2_code":"10",
    "gn:admin3_code":"4.0",
    "gn:admin4_code":"40020.0",
    "gn:asciiname":"Bimalegaun",
    "gn:country_code":"NP",
    "gn:dem":105,
    "gn:feature_class":"P",
    "gn:feature_code":"PPLL",
    "gn:name":"Bimalegaun",
    "gn:population":0,
    "gn:timezone":"Asia/Kathmandu",
    "iso:country":"NP",
    "wof:name":"Bimalegaun",
    "wof:placetype":"locality"
},
  "geometry": {"coordinates":[87.89936999999998,26.61624],"type":"Point"}
}