{
  "type": "Feature",
  "properties": {
    "gn:admin1_code":"CR",
    "gn:admin2_code":"1",
    "gn:admin3_code":"25",
    "gn:admin4_code":"250017",
    "gn:asciiname":"Gimdi",
    "gn:country_code":"NP",
    "gn:dem":682,
    "gn:feature_class":"P",
    "gn:feature_code":"PPLL",
    "gn:name":"Gimdi",
    "gn:population":0,
    "gn:timezone":"Asia/Kathmandu",
    "iso:country":"NP",
    "name:bih_x_preferred":[
        "\u0917\u093f\u092e\u094d\u0926\u0940"
    ],
    "name:ceb_x_preferred":[
        "Gimdi"
    ],
    "name:msa_x_preferred":[
        "Gimdi"
    ],
    "name:nep_x_preferred":[
        "\u0917\u093f\u092e\u094d\u0926\u0940"
    ],
    "name:new_x_preferred":[
        "\u0917\u093f\u092e\u094d\u0926\u0940"
    ],
    "name:pol_x_preferred":[
        "Gimdi"
    ],
    "wof:name":"Gimdi",
    "wof:placetype":"locality"
},
  "geometry": {"coordinates":[85.37331,27.42562],"type":"Point"}
}