{
  "type": "Feature",
  "properties": {
    "gn:admin1_code":"WR",
    "gn:admin2_code":"8",
    "gn:admin3_code":"47",
    "gn:admin4_code":"470046",
    "gn:asciiname":"Arya Bhanjyang",
    "gn:country_code":"NP",
    "gn:dem":1384,
    "gn:feature_class":"P",
    "gn:feature_code":"PPLL",
    "gn:name":"Arya Bhanjyang",
    "gn:population":0,
    "gn:timezone":"Asia/Kathmandu",
    "iso:country":"NP",
    "wof:name":"Arya Bhanjyang",
    "wof:placetype":"locality"
},
  "geometry": {"coordinates":[83.90196,27.76789],"type":"Point"}
}