{
  "type": "Feature",
  "properties": {
    "gn:admin1_code":"MR",
    "gn:admin2_code":"6",
    "gn:admin3_code":"63.0",
    "gn:admin4_code":"630001.0",
    "gn:asciiname":"Chema",
    "gn:country_code":"NP",
    "gn:dem":2675,
    "gn:feature_class":"P",
    "gn:feature_code":"PPLL",
    "gn:name":"Chema",
    "gn:population":0,
    "gn:timezone":"Asia/Kathmandu",
    "iso:country":"NP",
    "name:ceb_x_preferred":[
        "Chema"
    ],
    "name:por_x_preferred":[
        "Chema"
    ],
    "name:spa_x_preferred":[
        "Chema"
    ],
    "name:swe_x_preferred":[
        "Chema"
    ],
    "wof:name":"Chema",
    "wof:placetype":"locality"
},
  "geometry": {"coordinates":[81.99346,29.28151],"type":"Point"}
}