{
  "type": "Feature",
  "properties": {
    "gn:admin1_code":"MR",
    "gn:admin2_code":"6",
    "gn:admin3_code":"66.0",
    "gn:admin4_code":"660002.0",
    "gn:asciiname":"Talki",
    "gn:country_code":"NP",
    "gn:dem":2944,
    "gn:feature_class":"P",
    "gn:feature_code":"PPLL",
    "gn:name":"Talki",
    "gn:population":0,
    "gn:timezone":"Asia/Kathmandu",
    "iso:country":"NP",
    "wof:name":"Talki",
    "wof:placetype":"locality"
},
  "geometry": {"coordinates":[81.87828,29.96807],"type":"Point"}
}