{
  "type": "Feature",
  "properties": {
    "gn:admin1_code":"FR",
    "gn:admin2_code":"9",
    "gn:admin3_code":"75.0",
    "gn:admin4_code":"750031.0",
    "gn:asciiname":"Rangthal",
    "gn:country_code":"NP",
    "gn:dem":1842,
    "gn:feature_class":"P",
    "gn:feature_code":"PPLL",
    "gn:name":"Rangthal",
    "gn:population":0,
    "gn:timezone":"Asia/Kathmandu",
    "iso:country":"NP",
    "wof:name":"Rangthal",
    "wof:placetype":"locality"
},
  "geometry": {"coordinates":[80.71300000000002,29.98257000000001],"type":"Point"}
}