{
  "type": "Feature",
  "properties": {
    "gn:admin1_code":"WR",
    "gn:admin2_code":"4.0",
    "gn:admin3_code":"39.0",
    "gn:admin4_code":"390059.0",
    "gn:asciiname":"Lamachaur",
    "gn:country_code":"NP",
    "gn:dem":477,
    "gn:feature_class":"P",
    "gn:feature_code":"PPLL",
    "gn:name":"Lamachaur",
    "gn:population":0,
    "gn:timezone":"Asia/Kathmandu",
    "iso:country":"NP",
    "name:ceb_x_preferred":[
        "Lamachaur"
    ],
    "name:fra_x_preferred":[
        "Lamachaur"
    ],
    "name:mai_x_preferred":[
        "\u0932\u093e\u092e\u093e\u091a\u094c\u0930"
    ],
    "name:msa_x_preferred":[
        "Lamachaur"
    ],
    "name:nep_x_preferred":[
        "\u0932\u093e\u092e\u093e\u091a\u094c\u0930"
    ],
    "name:new_x_preferred":[
        "\u0932\u093e\u092e\u093e\u091a\u094c\u0930"
    ],
    "name:pol_x_preferred":[
        "Lamachaur"
    ],
    "name:urd_x_preferred":[
        "\u0644\u0627\u0645\u0627\u0686\u0648\u0631"
    ],
    "wof:name":"Lamachaur",
    "wof:placetype":"locality"
},
  "geometry": {"coordinates":[83.7063,27.92501],"type":"Point"}
}