{
  "type": "Feature",
  "properties": {
    "gn:admin1_code":"MR",
    "gn:admin2_code":"6",
    "gn:admin3_code":"62.0",
    "gn:admin4_code":"620022.0",
    "gn:asciiname":"Namyal",
    "gn:country_code":"NP",
    "gn:dem":4079,
    "gn:feature_class":"P",
    "gn:feature_code":"PPLL",
    "gn:name":"Namyal",
    "gn:population":0,
    "gn:timezone":"Asia/Kathmandu",
    "iso:country":"NP",
    "wof:name":"Namyal",
    "wof:placetype":"locality"
},
  "geometry": {"coordinates":[83.25417,29.41403],"type":"Point"}
}