{
  "type": "Feature",
  "properties": {
    "gn:admin1_code":"00",
    "gn:asciiname":"Girigau",
    "gn:country_code":"NP",
    "gn:dem":149,
    "gn:feature_class":"P",
    "gn:feature_code":"PPL",
    "gn:name":"Giri\u0307\u0304g\u0101\u0169",
    "gn:population":0,
    "gn:timezone":"Asia/Kathmandu",
    "iso:country":"NP",
    "name:nep_x_preferred":[
        "Giri\u0307\u0304g\u0101\u0169"
    ],
    "wof:name":"Girigau",
    "wof:placetype":"locality"
},
  "geometry": {"coordinates":[88.12749000000002,26.68211],"type":"Point"}
}