{
  "type": "Feature",
  "properties": {
    "gn:admin1_code":"FR",
    "gn:admin2_code":"14",
    "gn:admin3_code":"70.0",
    "gn:admin4_code":"700021.0",
    "gn:asciiname":"Jijoda",
    "gn:country_code":"NP",
    "gn:dem":1268,
    "gn:feature_class":"P",
    "gn:feature_code":"PPLL",
    "gn:name":"Jijoda",
    "gn:population":0,
    "gn:timezone":"Asia/Kathmandu",
    "iso:country":"NP",
    "wof:name":"Jijoda",
    "wof:placetype":"locality"
},
  "geometry": {"coordinates":[80.78668,29.26735],"type":"Point"}
}