{
  "type": "Feature",
  "properties": {
    "gn:admin1_code":"ER",
    "gn:admin2_code":"7",
    "gn:admin3_code":"10.0",
    "gn:admin4_code":"100036.0",
    "gn:asciiname":"Phaldanda",
    "gn:country_code":"NP",
    "gn:dem":1333,
    "gn:feature_class":"P",
    "gn:feature_code":"PPLL",
    "gn:name":"Phaldanda",
    "gn:population":0,
    "gn:timezone":"Asia/Kathmandu",
    "iso:country":"NP",
    "wof:name":"Phaldanda",
    "wof:placetype":"locality"
},
  "geometry": {"coordinates":[87.00251,27.16336],"type":"Point"}
}