{
  "type": "Feature",
  "properties": {
    "gn:admin1_code":"ER",
    "gn:admin2_code":"13",
    "gn:admin3_code":"13",
    "gn:admin4_code":"130075",
    "gn:asciiname":"Tomprang",
    "gn:country_code":"NP",
    "gn:dem":1459,
    "gn:feature_class":"P",
    "gn:feature_code":"PPLL",
    "gn:name":"Tomprang",
    "gn:population":0,
    "gn:timezone":"Asia/Kathmandu",
    "iso:country":"NP",
    "wof:name":"Tomprang",
    "wof:placetype":"locality"
},
  "geometry": {"coordinates":[86.95298000000003,26.94513],"type":"Point"}
}