{
  "type": "Feature",
  "properties": {
    "gn:admin1_code":"MR",
    "gn:admin2_code":"12",
    "gn:admin3_code":"53",
    "gn:admin4_code":"530019",
    "gn:asciiname":"Kotabang",
    "gn:country_code":"NP",
    "gn:dem":1515,
    "gn:feature_class":"P",
    "gn:feature_code":"PPLL",
    "gn:name":"Kotabang",
    "gn:population":0,
    "gn:timezone":"Asia/Kathmandu",
    "iso:country":"NP",
    "wof:name":"Kotabang",
    "wof:placetype":"locality"
},
  "geometry": {"coordinates":[82.55416,28.40223],"type":"Point"}
}