{
  "type": "Feature",
  "properties": {
    "gn:admin1_code":"CR",
    "gn:admin2_code":"5",
    "gn:admin3_code":"21",
    "gn:admin4_code":"210047",
    "gn:asciiname":"Thamgaun",
    "gn:country_code":"NP",
    "gn:dem":2160,
    "gn:feature_class":"P",
    "gn:feature_code":"PPLL",
    "gn:name":"Thamgaun",
    "gn:population":0,
    "gn:timezone":"Asia/Kathmandu",
    "iso:country":"NP",
    "wof:name":"Thamgaun",
    "wof:placetype":"locality"
},
  "geometry": {"coordinates":[86.24791999999999,27.58105],"type":"Point"}
}