{
  "type": "Feature",
  "properties": {
    "gn:admin1_code":"CR",
    "gn:admin2_code":"1",
    "gn:admin3_code":"23",
    "gn:admin4_code":"230011",
    "gn:asciiname":"Kaphale",
    "gn:country_code":"NP",
    "gn:dem":2046,
    "gn:feature_class":"P",
    "gn:feature_code":"PPLL",
    "gn:name":"Kaphale",
    "gn:population":0,
    "gn:timezone":"Asia/Kathmandu",
    "iso:country":"NP",
    "wof:name":"Kaphale",
    "wof:placetype":"locality"
},
  "geometry": {"coordinates":[85.66240999999999,27.89448],"type":"Point"}
}