{
  "type": "Feature",
  "properties": {
    "gn:admin1_code":"FR",
    "gn:admin2_code":"14.0",
    "gn:admin3_code":"67.0",
    "gn:admin4_code":"670005.0",
    "gn:asciiname":"Khaula",
    "gn:country_code":"NP",
    "gn:dem":2042,
    "gn:feature_class":"P",
    "gn:feature_code":"PPLL",
    "gn:name":"Khaula",
    "gn:population":0,
    "gn:timezone":"Asia/Kathmandu",
    "iso:country":"NP",
    "wof:name":"Khaula",
    "wof:placetype":"locality"
},
  "geometry": {"coordinates":[81.67307,29.65865],"type":"Point"}
}