{
  "type": "Feature",
  "properties": {
    "gn:admin1_code":"WR",
    "gn:admin2_code":"4.0",
    "gn:admin3_code":"39.0",
    "gn:admin4_code":"390050.0",
    "gn:asciiname":"Chanpswanra",
    "gn:country_code":"NP",
    "gn:dem":696,
    "gn:feature_class":"P",
    "gn:feature_code":"PPLL",
    "gn:name":"Chanpswanra",
    "gn:population":0,
    "gn:timezone":"Asia/Kathmandu",
    "iso:country":"NP",
    "wof:name":"Chanpswanra",
    "wof:placetype":"locality"
},
  "geometry": {"coordinates":[83.89879000000001,27.93778],"type":"Point"}
}