{
  "type": "Feature",
  "properties": {
    "gn:admin1_code":"FR",
    "gn:admin2_code":"14.0",
    "gn:admin3_code":"67.0",
    "gn:admin4_code":"670025.0",
    "gn:asciiname":"Lek Beksha",
    "gn:country_code":"NP",
    "gn:dem":1955,
    "gn:feature_class":"P",
    "gn:feature_code":"PPLL",
    "gn:name":"Lek Beksha",
    "gn:population":0,
    "gn:timezone":"Asia/Kathmandu",
    "iso:country":"NP",
    "wof:name":"Lek Beksha",
    "wof:placetype":"locality"
},
  "geometry": {"coordinates":[81.72879,29.59325],"type":"Point"}
}