{
  "type": "Feature",
  "properties": {
    "gn:admin1_code":"WR",
    "gn:admin2_code":"4.0",
    "gn:admin3_code":"39.0",
    "gn:admin4_code":"390054.0",
    "gn:asciiname":"Archalekholahgaun",
    "gn:country_code":"NP",
    "gn:dem":805,
    "gn:feature_class":"P",
    "gn:feature_code":"PPLL",
    "gn:name":"Archalekholahgaun",
    "gn:population":0,
    "gn:timezone":"Asia/Kathmandu",
    "iso:country":"NP",
    "wof:name":"Archalekholahgaun",
    "wof:placetype":"locality"
},
  "geometry": {"coordinates":[83.75399999999998,28.00242],"type":"Point"}
}