{
  "type": "Feature",
  "properties": {
    "gn:admin1_code":"WR",
    "gn:admin2_code":"4",
    "gn:admin3_code":"36.0",
    "gn:admin4_code":"360063.0",
    "gn:asciiname":"Keureni",
    "gn:country_code":"NP",
    "gn:dem":1011,
    "gn:feature_class":"P",
    "gn:feature_code":"PPLL",
    "gn:name":"Keureni",
    "gn:population":0,
    "gn:timezone":"Asia/Kathmandu",
    "iso:country":"NP",
    "wof:name":"Keureni",
    "wof:placetype":"locality"
},
  "geometry": {"coordinates":[84.66996999999998,28.03169],"type":"Point"}
}