{
  "type": "Feature",
  "properties": {
    "gn:admin1_code":"ER",
    "gn:admin2_code":"10",
    "gn:admin3_code":"3.0",
    "gn:admin4_code":"30031.0",
    "gn:asciiname":"Amlisegaun",
    "gn:country_code":"NP",
    "gn:dem":1380,
    "gn:feature_class":"P",
    "gn:feature_code":"PPLL",
    "gn:name":"Amlisegaun",
    "gn:population":0,
    "gn:timezone":"Asia/Kathmandu",
    "iso:country":"NP",
    "wof:name":"Amlisegaun",
    "wof:placetype":"locality"
},
  "geometry": {"coordinates":[88.01732,26.85803],"type":"Point"}
}