{
  "type": "Feature",
  "properties": {
    "gn:admin1_code":"ER",
    "gn:admin2_code":"13",
    "gn:admin3_code":"11",
    "gn:admin4_code":"110016",
    "gn:asciiname":"Amras",
    "gn:country_code":"NP",
    "gn:dem":1367,
    "gn:feature_class":"P",
    "gn:feature_code":"PPLL",
    "gn:name":"Amras",
    "gn:population":0,
    "gn:timezone":"Asia/Kathmandu",
    "iso:country":"NP",
    "name:bos_x_preferred":[
        "Amras"
    ],
    "name:cat_x_preferred":[
        "\u00c0mras"
    ],
    "name:eus_x_preferred":[
        "Amras"
    ],
    "name:ita_x_preferred":[
        "Amras"
    ],
    "name:jpn_x_preferred":[
        "\u30a2\u30e0\u30e9\u30b9"
    ],
    "name:nld_x_preferred":[
        "Amras"
    ],
    "name:pol_x_preferred":[
        "Lista Calaquendich#Amras"
    ],
    "name:por_x_preferred":[
        "Amras"
    ],
    "name:slv_x_preferred":[
        "Amras"
    ],
    "name:spa_x_preferred":[
        "Amras"
    ],
    "name:swe_x_preferred":[
        "Amras"
    ],
    "name:zho_x_preferred":[
        "\u5b89\u745e\u65af"
    ],
    "wof:name":"Amras",
    "wof:placetype":"locality"
},
  "geometry": {"coordinates":[86.68859999999999,27.48838],"type":"Point"}
}