{
  "type": "Feature",
  "properties": {
    "gn:admin1_code":"CR",
    "gn:admin2_code":"11",
    "gn:admin3_code":"31",
    "gn:admin4_code":"310008",
    "gn:asciiname":"Birta",
    "gn:country_code":"NP",
    "gn:dem":1208,
    "gn:feature_class":"P",
    "gn:feature_code":"PPLL",
    "gn:name":"Birta",
    "gn:population":0,
    "gn:timezone":"Asia/Kathmandu",
    "iso:country":"NP",
    "wof:name":"Birta",
    "wof:placetype":"locality"
},
  "geometry": {"coordinates":[85.1413,27.55017],"type":"Point"}
}