{
  "type": "Feature",
  "properties": {
    "gn:admin1_code":"MR",
    "gn:admin2_code":"12",
    "gn:admin3_code":"56.0",
    "gn:admin4_code":"560030.0",
    "gn:asciiname":"Galena",
    "gn:country_code":"NP",
    "gn:dem":1109,
    "gn:feature_class":"P",
    "gn:feature_code":"PPLL",
    "gn:name":"Galena",
    "gn:population":0,
    "gn:timezone":"Asia/Kathmandu",
    "iso:country":"NP",
    "name:afr_x_preferred":[
        "Galeniet"
    ],
    "name:ara_x_preferred":[
        "\u063a\u0627\u0644\u064a\u0646\u0627"
    ],
    "name:azb_x_preferred":[
        "\u0642\u0627\u0644\u06cc\u0646\u0627"
    ],
    "name:aze_x_preferred":[
        "Qalenit"
    ],
    "name:bel_x_preferred":[
        "\u0413\u0430\u043b\u0435\u043d\u0456\u0442"
    ],
    "name:bos_x_preferred":[
        "Galenit"
    ],
    "name:bul_x_preferred":[
        "\u0413\u0430\u043b\u0435\u043d\u0438\u0442"
    ],
    "name:cat_x_preferred":[
        "Galena"
    ],
    "name:ces_x_preferred":[
        "Galenit"
    ],
    "name:dan_x_preferred":[
        "Blyglans"
    ],
    "name:deu_x_preferred":[
        "Galenit"
    ],
    "name:ell_x_preferred":[
        "\u0393\u03b1\u03bb\u03b7\u03bd\u03af\u03c4\u03b7\u03c2"
    ],
    "name:epo_x_preferred":[
        "Galeno"
    ],
    "name:est_x_preferred":[
        "Galeniit"
    ],
    "name:eus_x_preferred":[
        "Galena"
    ],
    "name:fas_x_preferred":[
        "\u06af\u0627\u0644\u0646"
    ],
    "name:fin_x_preferred":[
        "Lyijyhohde"
    ],
    "name:fra_x_preferred":[
        "Gal\u00e8ne"
    ],
    "name:glg_x_preferred":[
        "Galena"
    ],
    "name:heb_x_preferred":[
        "\u05d2\u05dc\u05e0\u05d4"
    ],
    "name:hrv_x_preferred":[
        "Olovni sjajnik"
    ],
    "name:hun_x_preferred":[
        "Galenit"
    ],
    "name:ido_x_preferred":[
        "Galeno"
    ],
    "name:ina_x_preferred":[
        "Galena"
    ],
    "name:ind_x_preferred":[
        "Galena"
    ],
    "name:isl_x_preferred":[
        "Bl\u00fdglans"
    ],
    "name:ita_x_preferred":[
        "Galena"
    ],
    "name:jpn_x_preferred":[
        "\u65b9\u925b\u9271"
    ],
    "name:kaz_x_preferred":[
        "\u0413\u0430\u043b\u0435\u043d\u0438\u0442"
    ],
    "name:kir_x_preferred":[
        "\u0413\u0430\u043b\u0435\u043d\u0438\u0442"
    ],
    "name:kor_x_preferred":[
        "\ubc29\uc5f0\uc11d"
    ],
    "name:lit_x_preferred":[
        "Galenitas"
    ],
    "name:mon_x_preferred":[
        "\u0413\u0430\u043b\u0435\u043d\u0438\u0442"
    ],
    "name:nds_x_preferred":[
        "Galenit"
    ],
    "name:nld_x_preferred":[
        "Galeniet"
    ],
    "name:nno_x_preferred":[
        "Galenitt"
    ],
    "name:nor_x_preferred":[
        "Blyglans"
    ],
    "name:pol_x_preferred":[
        "Galena"
    ],
    "name:por_x_preferred":[
        "Galena"
    ],
    "name:ron_x_preferred":[
        "Galen\u0103"
    ],
    "name:rus_x_preferred":[
        "\u0413\u0430\u043b\u0435\u043d\u0438\u0442"
    ],
    "name:sco_x_preferred":[
        "Galena"
    ],
    "name:slk_x_preferred":[
        "Galenit"
    ],
    "name:slv_x_preferred":[
        "Galenit"
    ],
    "name:spa_x_preferred":[
        "Galena"
    ],
    "name:srp_x_preferred":[
        "\u0413\u0430\u043b\u0435\u043d\u0438\u0442"
    ],
    "name:swe_x_preferred":[
        "Blyglans"
    ],
    "name:tha_x_preferred":[
        "\u0e01\u0e32\u0e25\u0e35\u0e19\u0e32"
    ],
    "name:ukr_x_preferred":[
        "\u0413\u0430\u043b\u0435\u043d\u0456\u0442"
    ],
    "name:uzb_x_preferred":[
        "Galenit"
    ],
    "name:vie_x_preferred":[
        "Galen"
    ],
    "name:zho_x_preferred":[
        "\u65b9\u94c5\u77ff"
    ],
    "wof:name":"Galena",
    "wof:placetype":"locality"
},
  "geometry": {"coordinates":[82.50669000000001,28.12301],"type":"Point"}
}