{
  "type": "Feature",
  "properties": {
    "gn:admin1_code":"CR",
    "gn:admin2_code":"5",
    "gn:admin3_code":"17.0",
    "gn:admin4_code":"170016.0",
    "gn:asciiname":"Tallo Bengadawar",
    "gn:country_code":"NP",
    "gn:dem":179,
    "gn:feature_class":"P",
    "gn:feature_code":"PPLL",
    "gn:name":"Tallo Bengadawar",
    "gn:population":0,
    "gn:timezone":"Asia/Kathmandu",
    "iso:country":"NP",
    "wof:name":"Tallo Bengadawar",
    "wof:placetype":"locality"
},
  "geometry": {"coordinates":[85.92291,26.94046],"type":"Point"}
}