{
  "type": "Feature",
  "properties": {
    "iso:country":"NP",
    "name:ben_x_preferred":[
        "\u0997\u09c1\u09b2\u09cd\u09ae\u09c0 \u099c\u09c7\u09b2\u09be"
    ],
    "name:bpy_x_preferred":[
        "\u0997\u09c1\u09b2\u09cd\u09ae\u09c0"
    ],
    "name:dan_x_preferred":[
        "Gulmi District"
    ],
    "name:deu_x_preferred":[
        "Gulmi"
    ],
    "name:fin_x_preferred":[
        "Gulmin piirikunta"
    ],
    "name:fra_x_preferred":[
        "District de Gulmi"
    ],
    "name:guj_x_preferred":[
        "\u0a97\u0ac1\u0ab2\u0acd\u0aae\u0ac0 \u0a9c\u0abf\u0ab2\u0acd\u0ab2\u0acb"
    ],
    "name:hif_x_preferred":[
        "Gulmi"
    ],
    "name:hin_x_preferred":[
        "\u0917\u0941\u0932\u094d\u092e\u0940 \u091c\u093f\u0932\u093e"
    ],
    "name:ita_x_preferred":[
        "Distretto di Gulmi"
    ],
    "name:jpn_x_preferred":[
        "\u30b0\u30eb\u30df\u90e1"
    ],
    "name:nep_x_preferred":[
        "\u0917\u0941\u0932\u094d\u092e\u0940 \u091c\u093f\u0932\u094d\u0932\u093e"
    ],
    "name:new_x_preferred":[
        "\u0917\u0941\u0932\u094d\u092e\u0940 \u091c\u093f\u0932\u094d\u0932\u093e"
    ],
    "name:nld_x_preferred":[
        "Gulmi"
    ],
    "name:nor_x_preferred":[
        "Gulmi"
    ],
    "name:pnb_x_preferred":[
        "\u0636\u0644\u0639 \u06af\u0644\u0645\u06cc"
    ],
    "name:pol_x_preferred":[
        "Gulmi"
    ],
    "name:por_x_preferred":[
        "Gulmi"
    ],
    "name:rus_x_preferred":[
        "\u0413\u0443\u043b\u043c\u0438"
    ],
    "name:san_x_preferred":[
        "\u0917\u0941\u0932\u094d\u092e\u0940\u092e\u0923\u094d\u0921\u0932\u092e\u094d"
    ],
    "name:unk_x_variant":[
        "Gulm\u012b"
    ],
    "name:vie_x_preferred":[
        "Gulmi"
    ],
    "qs:gn_country":"NP",
    "qs:gn_fcode":"ADM3",
    "qs:gn_pop":307098,
    "qs:name":"Gulmi",
    "qs:name_adm0":"Nepal",
    "qs:name_adm1":"Pashchimanchal",
    "qs:photos":9,
    "qs:photos_1k":2,
    "qs:photos_9k":1,
    "qs:photos_9r":1,
    "qs:photos_all":9,
    "qs:photos_sr":1,
    "qs:placetype":"LocalAdmin",
    "qs:pop_sr":"10",
    "qs:woe_adm0":23424911,
    "wd:wordcount":505,
    "wof:name":"Gulmi",
    "wof:placetype":"localadmin",
    "wof:population":307098
},
  "geometry": {"coordinates":[83.33333,28.08333],"type":"Point"}
}