{
  "type": "Feature",
  "properties": {
    "gn:admin1_code":"CR",
    "gn:admin2_code":"5",
    "gn:admin3_code":"18",
    "gn:admin4_code":"180073",
    "gn:asciiname":"Bhoil",
    "gn:country_code":"NP",
    "gn:dem":104,
    "gn:feature_class":"P",
    "gn:feature_code":"PPLL",
    "gn:name":"Bhoil",
    "gn:population":0,
    "gn:timezone":"Asia/Kathmandu",
    "iso:country":"NP",
    "wof:name":"Bhoil",
    "wof:placetype":"locality"
},
  "geometry": {"coordinates":[85.8115,26.87026],"type":"Point"}
}