{
  "type": "Feature",
  "properties": {
    "gn:admin1_code":"FR",
    "gn:admin2_code":"14.0",
    "gn:admin3_code":"67.0",
    "gn:admin4_code":"670008.0",
    "gn:asciiname":"Jumlldanda",
    "gn:country_code":"NP",
    "gn:dem":2023,
    "gn:feature_class":"P",
    "gn:feature_code":"PPLL",
    "gn:name":"Jumlldanda",
    "gn:population":0,
    "gn:timezone":"Asia/Kathmandu",
    "iso:country":"NP",
    "wof:name":"Jumlldanda",
    "wof:placetype":"locality"
},
  "geometry": {"coordinates":[81.34680999999998,29.32117],"type":"Point"}
}