{
  "type": "Feature",
  "properties": {
    "gn:admin1_code":"MR",
    "gn:admin2_code":"2.0",
    "gn:admin3_code":"59.0",
    "gn:admin4_code":"590038.0",
    "gn:asciiname":"Bettara",
    "gn:country_code":"NP",
    "gn:dem":956,
    "gn:feature_class":"P",
    "gn:feature_code":"PPLL",
    "gn:name":"Bettara",
    "gn:population":0,
    "gn:timezone":"Asia/Kathmandu",
    "iso:country":"NP",
    "wof:name":"Bettara",
    "wof:placetype":"locality"
},
  "geometry": {"coordinates":[81.77703000000002,28.56232],"type":"Point"}
}