{
  "type": "Feature",
  "properties": {
    "gn:admin1_code":"00",
    "gn:asciiname":"Bedan",
    "gn:country_code":"NP",
    "gn:dem":1901,
    "gn:feature_class":"P",
    "gn:feature_code":"PPL",
    "gn:name":"Bed\u0101\u1e45",
    "gn:population":0,
    "gn:timezone":"Asia/Kathmandu",
    "iso:country":"NP",
    "name:nep_x_preferred":[
        "Bed\u0101\u1e45"
    ],
    "wof:name":"Bedan",
    "wof:placetype":"locality"
},
  "geometry": {"coordinates":[85.38061,28.27049],"type":"Point"}
}