{
  "type": "Feature",
  "properties": {
    "gn:admin1_code":"MR",
    "gn:admin2_code":"12",
    "gn:admin3_code":"53",
    "gn:admin4_code":"530021",
    "gn:asciiname":"Bhujel Takura",
    "gn:country_code":"NP",
    "gn:dem":1267,
    "gn:feature_class":"P",
    "gn:feature_code":"PPLL",
    "gn:name":"Bhujel Takura",
    "gn:population":0,
    "gn:timezone":"Asia/Kathmandu",
    "iso:country":"NP",
    "wof:name":"Bhujel Takura",
    "wof:placetype":"locality"
},
  "geometry": {"coordinates":[82.61539999999999,28.24082000000001],"type":"Point"}
}