{
  "type": "Feature",
  "properties": {
    "gn:admin1_code":"ER",
    "gn:admin2_code":"13",
    "gn:admin3_code":"12",
    "gn:admin4_code":"120039",
    "gn:asciiname":"Majhkharka",
    "gn:country_code":"NP",
    "gn:dem":2368,
    "gn:feature_class":"P",
    "gn:feature_code":"PPLL",
    "gn:name":"Majhkharka",
    "gn:population":0,
    "gn:timezone":"Asia/Kathmandu",
    "iso:country":"NP",
    "wof:name":"Majhkharka",
    "wof:placetype":"locality"
},
  "geometry": {"coordinates":[86.47569,27.39245],"type":"Point"}
}