{
  "type": "Feature",
  "properties": {
    "gn:admin1_code":"ER",
    "gn:admin2_code":"13",
    "gn:admin3_code":"12",
    "gn:admin4_code":"120033",
    "gn:asciiname":"Kamere",
    "gn:country_code":"NP",
    "gn:dem":1860,
    "gn:feature_class":"P",
    "gn:feature_code":"PPLL",
    "gn:name":"Kamere",
    "gn:population":0,
    "gn:timezone":"Asia/Kathmandu",
    "iso:country":"NP",
    "wof:name":"Kamere",
    "wof:placetype":"locality"
},
  "geometry": {"coordinates":[86.50676999999997,27.32767],"type":"Point"}
}