{
  "type": "Feature",
  "properties": {
    "gn:admin1_code":"ER",
    "gn:admin2_code":"10.0",
    "gn:admin3_code":"1.0",
    "gn:admin4_code":"10042.0",
    "gn:asciiname":"Kerabari",
    "gn:country_code":"NP",
    "gn:dem":1788,
    "gn:feature_class":"P",
    "gn:feature_code":"PPLL",
    "gn:name":"Kerabari",
    "gn:population":0,
    "gn:timezone":"Asia/Kathmandu",
    "iso:country":"NP",
    "wof:name":"Kerabari",
    "wof:placetype":"locality"
},
  "geometry": {"coordinates":[87.94117,27.37706],"type":"Point"}
}